{
  "type": "Feature",
  "properties": {
    "gn:admin1_code":"11",
    "gn:admin2_code":"2007",
    "gn:asciiname":"Shaykh Bahlol",
    "gn:country_code":"AF",
    "gn:dem":1364,
    "gn:feature_class":"P",
    "gn:feature_code":"PPL",
    "gn:name":"Shaykh Bahl\u014dl",
    "gn:population":0,
    "gn:timezone":"Asia/Kabul",
    "iso:country":"AF",
    "name:und_x_variant":[
        "Saykh Bahl\u014dl",
        "Shaykh Bahl\u014dl",
        "\u0634\u06cc\u062e \u0628\u0647\u0644\u0648\u0644",
        "Sheykh Bahl\u016bl"
    ],
    "wof:name":"Shaykh Bahlol",
    "wof:placetype":"locality"
},
  "geometry": {"coordinates":[61.98588,34.82327],"type":"Point"}
}