{
  "type": "Feature",
  "properties": {
    "gn:admin1_code":"05",
    "gn:admin2_code":"2806.0",
    "gn:asciiname":"Bile Mundyak",
    "gn:country_code":"AF",
    "gn:dem":2820,
    "gn:feature_class":"P",
    "gn:feature_code":"PPL",
    "gn:name":"Bil\u0113 Mundyak",
    "gn:population":0,
    "gn:timezone":"Asia/Kabul",
    "iso:country":"AF",
    "name:rus_x_preferred":[
        "Bil\u2019mund\u2019yak"
    ],
    "name:und_x_variant":[
        "Bel\u0113mundyak",
        "Belmundyak",
        "Bil\u0113 Mundyak",
        "\u0628\u0644 \u0645\u0646\u062f\u06cc\u06a9"
    ],
    "wof:name":"Bile Mundyak",
    "wof:placetype":"locality"
},
  "geometry": {"coordinates":[67.25469,34.32395],"type":"Point"}
}