{
  "type": "Feature",
  "properties": {
    "gn:admin1_code":"19",
    "gn:admin2_code":"2202",
    "gn:asciiname":"Haji Malang",
    "gn:country_code":"AF",
    "gn:dem":484,
    "gn:feature_class":"P",
    "gn:feature_code":"PPL",
    "gn:name":"\u1e28\u0101j\u012b Malang",
    "gn:population":0,
    "gn:timezone":"Asia/Kabul",
    "iso:country":"AF",
    "name:fas_x_preferred":[
        "\u062d\u0627\u062c\u06cc \u0645\u0644\u0646\u06af"
    ],
    "name:und_x_variant":[
        "H\u0331\u0101jimalang",
        "\u1e28\u0101j\u012b Malang"
    ],
    "wof:name":"Haji Malang",
    "wof:placetype":"locality"
},
  "geometry": {"coordinates":[61.90123000000001,31.17219],"type":"Point"}
}