{
  "type": "Feature",
  "properties": {
    "gn:admin1_code":"34",
    "gn:admin2_code":"1008.0",
    "gn:asciiname":"Shahid",
    "gn:country_code":"AF",
    "gn:dem":1252,
    "gn:feature_class":"P",
    "gn:feature_code":"PPL",
    "gn:name":"Shah\u012bd",
    "gn:population":0,
    "gn:timezone":"Asia/Kabul",
    "iso:country":"AF",
    "name:und_x_variant":[
        "\u0160ah\u012bd",
        "Shakhid",
        "Shah\u012bd",
        "\u0634\u0647\u06cc\u062f"
    ],
    "wof:name":"Shahid",
    "wof:placetype":"locality"
},
  "geometry": {"coordinates":[71.08561,34.98836],"type":"Point"}
}