{
  "type": "Feature",
  "properties": {
    "gn:admin1_code":"8",
    "gn:admin2_code":"604.0",
    "gn:asciiname":"Sang-e Surakh",
    "gn:country_code":"AF",
    "gn:dem":2857,
    "gn:feature_class":"P",
    "gn:feature_code":"PPL",
    "gn:name":"Sang-e S\u016br\u0101kh",
    "gn:population":0,
    "gn:timezone":"Asia/Kabul",
    "iso:country":"AF",
    "name:und_x_variant":[
        "Sang-e S\u016br\u0101kh",
        "\u0633\u0646\u06af \u0633\u0648\u0631\u0627\u062e"
    ],
    "wof:name":"Sang-e Surakh",
    "wof:placetype":"locality"
},
  "geometry": {"coordinates":[67.48761,33.95968],"type":"Point"}
}