{
  "type": "Feature",
  "properties": {
    "gn:admin1_code":"18",
    "gn:admin2_code":"807.0",
    "gn:asciiname":"Katah Khel",
    "gn:country_code":"AF",
    "gn:dem":1440,
    "gn:feature_class":"P",
    "gn:feature_code":"PPL",
    "gn:name":"Ka\u1e6fah Kh\u0113l",
    "gn:population":0,
    "gn:timezone":"Asia/Kabul",
    "iso:country":"AF",
    "wof:name":"Katah Khel",
    "wof:placetype":"locality"
},
  "geometry": {"coordinates":[70.27916,34.13944],"type":"Point"}
}