{
  "type": "Feature",
  "properties": {
    "gn:admin1_code":"41",
    "gn:admin2_code":"3407.0",
    "gn:asciiname":"Dunalagak",
    "gn:country_code":"AF",
    "gn:dem":2496,
    "gn:feature_class":"P",
    "gn:feature_code":"PPL",
    "gn:name":"Dun\u0101lagak",
    "gn:population":0,
    "gn:timezone":"Asia/Kabul",
    "iso:country":"AF",
    "name:und_x_variant":[
        "Don\u0101lagak",
        "Don\u0101lahgak",
        "Dun\u0101lagak",
        "\u062f\u0646\u0627\u0644\u06af\u06a9"
    ],
    "wof:name":"Dunalagak",
    "wof:placetype":"locality"
},
  "geometry": {"coordinates":[66.56983000000001,33.87311],"type":"Point"}
}