{
  "type": "Feature",
  "properties": {
    "gn:admin1_code":"06",
    "gn:admin2_code":"2110",
    "gn:asciiname":"Husayabad",
    "gn:country_code":"AF",
    "gn:dem":543,
    "gn:feature_class":"P",
    "gn:feature_code":"PPL",
    "gn:name":"\u1e28usay\u0101b\u0101d",
    "gn:population":0,
    "gn:timezone":"Asia/Kabul",
    "iso:country":"AF",
    "name:und_x_variant":[
        "H\u0331osay\u0101b\u0101\u1e0f",
        "\u1e28oseyn\u0101b\u0101d",
        "\u1e28usay\u0101b\u0101d",
        "\u062d\u0633\u06cc \u0622\u0628\u0627\u062f",
        "\u1e28\u014dsay \u0100b\u0101d",
        "\u062d\u0648\u0633\u06cc \u0622\u0628\u0627\u062f"
    ],
    "wof:name":"Husayabad",
    "wof:placetype":"locality"
},
  "geometry": {"coordinates":[61.38118000000001,32.08129],"type":"Point"}
}