{
  "type": "Feature",
  "properties": {
    "gn:admin1_code":"28",
    "gn:admin2_code":"2502",
    "gn:asciiname":"Sayyidzai",
    "gn:country_code":"AF",
    "gn:dem":1915,
    "gn:feature_class":"P",
    "gn:feature_code":"PPL",
    "gn:name":"Sayyidza\u012b",
    "gn:population":0,
    "gn:timezone":"Asia/Kabul",
    "iso:country":"AF",
    "name:und_x_variant":[
        "Seyidzay",
        "Saye\u1e0fz\u0101\u2018i",
        "Sayyidza\u012b",
        "\u0633\u06cc\u062f\u0632\u06cc",
        "Seyyed Z\u0101\u2019\u012b"
    ],
    "wof:name":"Sayyidzai",
    "wof:placetype":"locality"
},
  "geometry": {"coordinates":[67.52561,32.54936],"type":"Point"}
}