{
  "type": "Feature",
  "properties": {
    "gn:admin1_code":"30",
    "gn:admin2_code":"1610",
    "gn:asciiname":"Nighak",
    "gn:country_code":"AF",
    "gn:dem":1273,
    "gn:feature_class":"P",
    "gn:feature_code":"PPL",
    "gn:name":"Nighak",
    "gn:population":0,
    "gn:timezone":"Asia/Kabul",
    "iso:country":"AF",
    "name:und_x_variant":[
        "Nighak (1)",
        "Nighak",
        "\u0646\u063a\u06a9"
    ],
    "wof:name":"Nighak",
    "wof:placetype":"locality"
},
  "geometry": {"coordinates":[67.07785,36.04629],"type":"Point"}
}