{
  "type": "Feature",
  "properties": {
    "gn:admin1_code":"05",
    "gn:admin2_code":"2801",
    "gn:asciiname":"Darah-ye Gulistan",
    "gn:country_code":"AF",
    "gn:dem":3231,
    "gn:feature_class":"P",
    "gn:feature_code":"PPL",
    "gn:name":"Darah-ye Gulist\u0101n",
    "gn:population":0,
    "gn:timezone":"Asia/Kabul",
    "iso:country":"AF",
    "name:und_x_variant":[
        "\u1e0ea\u1e5fa-i-Gulest\u0101n",
        "Darayi-Gulistan",
        "Darah-ye Gulist\u0101n",
        "Darreh-ye Golest\u0101n",
        "\u062f\u0631\u0647 \u06cc \u06af\u0644\u0633\u062a\u0627\u0646",
        "Darah-ye Gulis\u1e6f\u0101n"
    ],
    "wof:name":"Darah-ye Gulistan",
    "wof:placetype":"locality"
},
  "geometry": {"coordinates":[67.69369,34.95717],"type":"Point"}
}