{
  "type": "Feature",
  "properties": {
    "gn:admin1_code":"8",
    "gn:admin2_code":"605.0",
    "gn:asciiname":"Nuraki",
    "gn:country_code":"AF",
    "gn:dem":2746,
    "gn:feature_class":"P",
    "gn:feature_code":"PPL",
    "gn:name":"N\u016brak\u012b",
    "gn:population":0,
    "gn:timezone":"Asia/Kabul",
    "iso:country":"AF",
    "name:und_x_variant":[
        "N\u016b\u1e5faki",
        "Nowrak\u012b",
        "N\u016brak\u012b",
        "\u0646\u0648\u0631\u06a9\u06cc"
    ],
    "wof:name":"Nuraki",
    "wof:placetype":"locality"
},
  "geometry": {"coordinates":[67.3116,33.58317],"type":"Point"}
}