{
  "type": "Feature",
  "properties": {
    "gn:admin1_code":"32",
    "gn:admin2_code":"1506",
    "gn:asciiname":"Junjushkah",
    "gn:country_code":"AF",
    "gn:dem":2586,
    "gn:feature_class":"P",
    "gn:feature_code":"PPL",
    "gn:name":"Junjushkah",
    "gn:population":0,
    "gn:timezone":"Asia/Kabul",
    "iso:country":"AF",
    "name:und_x_variant":[
        "Junju\u0161ka",
        "Junjushka",
        "Junjushkah",
        "\u062c\u0646\u062c\u0634\u06a9\u0647"
    ],
    "wof:name":"Junjushkah",
    "wof:placetype":"locality"
},
  "geometry": {"coordinates":[68.21735,35.84407],"type":"Point"}
}