{
  "type": "Feature",
  "properties": {
    "gn:admin1_code":"05",
    "gn:admin2_code":"2805.0",
    "gn:asciiname":"Chiji",
    "gn:country_code":"AF",
    "gn:dem":3129,
    "gn:feature_class":"P",
    "gn:feature_code":"PPL",
    "gn:name":"Chij\u012b",
    "gn:population":0,
    "gn:timezone":"Asia/Kabul",
    "iso:country":"AF",
    "name:und_x_variant":[
        "Chidzhi",
        "\u010ciji",
        "Ch\u012bj\u012b",
        "Chij\u012b",
        "\u0686\u062c\u06cc"
    ],
    "wof:name":"Chiji",
    "wof:placetype":"locality"
},
  "geometry": {"coordinates":[67.09111999999999,34.48149],"type":"Point"}
}