{
  "type": "Feature",
  "properties": {
    "gn:admin1_code":"18",
    "gn:admin2_code":"802.0",
    "gn:asciiname":"Jamal Kala",
    "gn:country_code":"AF",
    "gn:dem":671,
    "gn:feature_class":"P",
    "gn:feature_code":"PPL",
    "gn:name":"Jam\u0101l Kal\u0101",
    "gn:population":0,
    "gn:timezone":"Asia/Kabul",
    "iso:country":"AF",
    "name:fas_x_preferred":[
        "\u062c\u0645\u0627\u0644 \u0643\u0644\u0627"
    ],
    "name:rus_x_preferred":[
        "Dzhamal\u2019kala"
    ],
    "name:und_x_variant":[
        "Jam\u0101l Kal\u0101",
        "\u062c\u0645\u0627\u0644 \u06a9\u0644\u0627"
    ],
    "wof:name":"Jamal Kala",
    "wof:placetype":"locality"
},
  "geometry": {"coordinates":[70.30915,34.43185],"type":"Point"}
}