{
  "type": "Feature",
  "properties": {
    "gn:admin1_code":"34",
    "gn:admin2_code":"1010.0",
    "gn:asciiname":"Yas Cham",
    "gn:country_code":"AF",
    "gn:dem":1750,
    "gn:feature_class":"P",
    "gn:feature_code":"PPL",
    "gn:name":"Y\u0101s Cham",
    "gn:population":0,
    "gn:timezone":"Asia/Kabul",
    "iso:country":"AF",
    "wof:name":"Yas Cham",
    "wof:placetype":"locality"
},
  "geometry": {"coordinates":[70.89565,34.90332],"type":"Point"}
}