{
  "type": "Feature",
  "properties": {
    "gn:admin1_code":"6",
    "gn:admin2_code":"2107.0",
    "gn:asciiname":"Bulaq",
    "gn:country_code":"AF",
    "gn:dem":702,
    "gn:feature_class":"P",
    "gn:feature_code":"PPL",
    "gn:name":"B\u016bl\u0101q",
    "gn:population":0,
    "gn:timezone":"Asia/Kabul",
    "iso:country":"AF",
    "name:fas_x_preferred":[
        "B\u016bl\u0101q"
    ],
    "name:fas_x_variant":[
        "\u0628\u0648\u0644\u0627\u0642"
    ],
    "name:und_x_variant":[
        "\u0628\u0648\u0644\u0627\u0642",
        "Bol\u0101gh"
    ],
    "wof:name":"Bulaq",
    "wof:placetype":"locality"
},
  "geometry": {"coordinates":[61.55484000000001,32.6223],"type":"Point"}
}