{
  "type": "Feature",
  "properties": {
    "gn:admin1_code":"6",
    "gn:admin2_code":"2107.0",
    "gn:asciiname":"Bulaq",
    "gn:country_code":"AF",
    "gn:dem":702,
    "gn:feature_class":"P",
    "gn:feature_code":"PPL",
    "gn:name":"B\u016bl\u0101q",
    "gn:population":0,
    "gn:timezone":"Asia/Kabul",
    "iso:country":"AF",
    "name:ara_x_preferred":[
        "\u062d\u064a \u0628\u0648\u0644\u0627\u0642"
    ],
    "name:cat_x_preferred":[
        "Bulak"
    ],
    "name:deu_x_preferred":[
        "Bulaq"
    ],
    "name:fas_x_preferred":[
        "B\u016bl\u0101q"
    ],
    "name:fas_x_variant":[
        "\u0628\u0648\u0644\u0627\u0642"
    ],
    "name:fra_x_preferred":[
        "Boulaq"
    ],
    "name:gle_x_preferred":[
        "Bulaq"
    ],
    "name:ita_x_preferred":[
        "Bulaq"
    ],
    "name:kat_x_preferred":[
        "\u10d1\u10e3\u10da\u10d0\u10d9\u10d8"
    ],
    "name:pol_x_preferred":[
        "Bulak"
    ],
    "name:por_x_preferred":[
        "Bulaque"
    ],
    "name:rus_x_preferred":[
        "\u0411\u0443\u043b\u0430\u043a"
    ],
    "name:spa_x_preferred":[
        "Bulaq"
    ],
    "name:swe_x_preferred":[
        "Boulaq"
    ],
    "name:und_x_variant":[
        "Bol\u0101gh"
    ],
    "name:urd_x_preferred":[
        "\u0628\u0648\u0644\u0627\u0642"
    ],
    "wof:name":"Bulaq",
    "wof:placetype":"locality"
},
  "geometry": {"coordinates":[61.55484000000001,32.6223],"type":"Point"}
}