{
  "type": "Feature",
  "properties": {
    "gn:admin1_code":"2",
    "gn:admin2_code":"1901.0",
    "gn:asciiname":"Abzikhudai",
    "gn:country_code":"AF",
    "gn:dem":1078,
    "gn:feature_class":"P",
    "gn:feature_code":"PPL",
    "gn:name":"Abzikhudai",
    "gn:population":0,
    "gn:timezone":"Asia/Kabul",
    "iso:country":"AF",
    "name:und_x_variant":[
        "Abzi Khud\u0101",
        "Abzi Khu\u1e0f\u0101\u2019i",
        "\u0100bz\u012b Khud\u0101\u2019\u012b",
        "\u0622\u0628\u0632\u06cc \u062e\u062f\u0627\u0626\u06cc",
        "\u0100bz\u012b Khod\u0101\u2019\u012b"
    ],
    "wof:name":"Abzikhudai",
    "wof:placetype":"locality"
},
  "geometry": {"coordinates":[63.06804,34.8876],"type":"Point"}
}