{
  "type": "Feature",
  "properties": {
    "gn:admin1_code":"10",
    "gn:admin2_code":"2306",
    "gn:asciiname":"Shor Ab",
    "gn:country_code":"AF",
    "gn:dem":974,
    "gn:feature_class":"P",
    "gn:feature_code":"PPL",
    "gn:name":"Sh\u014dr \u0100b",
    "gn:population":0,
    "gn:timezone":"Asia/Kabul",
    "iso:country":"AF",
    "name:und_x_variant":[
        "\u0160or\u0101b",
        "Shorab",
        "Sh\u014dr \u0100b",
        "\u0634\u0648\u0631 \u0622\u0628",
        "Sh\u016br \u0100b",
        "Sh\u014dr\u0101b"
    ],
    "wof:name":"Shor Ab",
    "wof:placetype":"locality"
},
  "geometry": {"coordinates":[64.63547,32.09195],"type":"Point"}
}