{
  "type": "Feature",
  "properties": {
    "gn:admin1_code":"28",
    "gn:admin2_code":"2507",
    "gn:asciiname":"Loy-Shor",
    "gn:country_code":"AF",
    "gn:dem":1920,
    "gn:feature_class":"P",
    "gn:feature_code":"PPL",
    "gn:name":"Loy-Shor",
    "gn:population":0,
    "gn:timezone":"Asia/Kabul",
    "iso:country":"AF",
    "name:fas_x_preferred":[
        "\u0634\u0648\u0631\u0654 \u0643\u0644\u0627\u0646"
    ],
    "name:und_x_variant":[
        "S\u0304\u014dr",
        "L\u014dy S\u0304\u014d\u1e5f",
        "Lowy S\u0332h\u0332\u016br",
        "Loy-Shor",
        "S\u0332h\u0332\u016br",
        "L\u014dy S\u0332h\u0332\u014dr",
        "\u0644\u0648\u06cc \u069a\u0648\u0631",
        "L\u016by S\u0332h\u0332\u016br"
    ],
    "wof:name":"Loy-Shor",
    "wof:placetype":"locality"
},
  "geometry": {"coordinates":[67.11667,32.01555],"type":"Point"}
}