{
  "type": "Feature",
  "properties": {
    "gn:admin1_code":"23",
    "gn:admin2_code":"2414.0",
    "gn:asciiname":"Gazkol",
    "gn:country_code":"AF",
    "gn:dem":1613,
    "gn:feature_class":"P",
    "gn:feature_code":"PPL",
    "gn:name":"Gazk\u014dl",
    "gn:population":0,
    "gn:timezone":"Asia/Kabul",
    "iso:country":"AF",
    "name:rus_x_preferred":[
        "Gazkul\u2019"
    ],
    "name:und_x_variant":[
        "Gazk\u014dl",
        "\u06af\u0632\u06a9\u0648\u0644",
        "Gazk\u016bl"
    ],
    "wof:name":"Gazkol",
    "wof:placetype":"locality"
},
  "geometry": {"coordinates":[66.15640999999999,32.25429],"type":"Point"}
}