{
  "type": "Feature",
  "properties": {
    "gn:admin1_code":"41",
    "gn:admin2_code":"3409.0",
    "gn:asciiname":"Ladugak",
    "gn:country_code":"AF",
    "gn:dem":1833,
    "gn:feature_class":"P",
    "gn:feature_code":"PPL",
    "gn:name":"La\u1e0f\u016bgak",
    "gn:population":0,
    "gn:timezone":"Asia/Kabul",
    "iso:country":"AF",
    "name:und_x_variant":[
        "La\u1e0f\u016bgak",
        "\u0644\u0689\u0648\u06af\u06a9",
        "Lad\u016bgak"
    ],
    "wof:name":"Ladugak",
    "wof:placetype":"locality"
},
  "geometry": {"coordinates":[66.5448,33.65872],"type":"Point"}
}