{
  "type": "Feature",
  "properties": {
    "gn:admin1_code":"29",
    "gn:admin2_code":"2905",
    "gn:asciiname":"Sado Khan",
    "gn:country_code":"AF",
    "gn:dem":2117,
    "gn:feature_class":"P",
    "gn:feature_code":"PPL",
    "gn:name":"Sad\u014d Kh\u0101n",
    "gn:population":0,
    "gn:timezone":"Asia/Kabul",
    "iso:country":"AF",
    "name:fas_x_preferred":[
        "\u0633\u062f\u0648 \u062e\u0627\u0646"
    ],
    "name:und_x_variant":[
        "Sadukhan",
        "Sado Kh\u0101n",
        "Sad\u014d Kh\u0101n"
    ],
    "wof:name":"Sado Khan",
    "wof:placetype":"locality"
},
  "geometry": {"coordinates":[68.88641,32.10325],"type":"Point"}
}