{
  "type": "Feature",
  "properties": {
    "gn:admin1_code":"03",
    "gn:admin2_code":"1315",
    "gn:asciiname":"Zard Aspan",
    "gn:country_code":"AF",
    "gn:dem":1999,
    "gn:feature_class":"P",
    "gn:feature_code":"PPL",
    "gn:name":"Zard Asp\u0101n",
    "gn:population":0,
    "gn:timezone":"Asia/Kabul",
    "iso:country":"AF",
    "name:und_x_variant":[
        "Zard Asp\u0101n",
        "\u0632\u0631\u062f \u0627\u0633\u067e\u0627\u0646"
    ],
    "wof:name":"Zard Aspan",
    "wof:placetype":"locality"
},
  "geometry": {"coordinates":[69.26680999999999,35.87947],"type":"Point"}
}