{
  "type": "Feature",
  "properties": {
    "gn:admin1_code":"5",
    "gn:admin2_code":"2802.0",
    "gn:asciiname":"Dahan-e Qol",
    "gn:country_code":"AF",
    "gn:dem":2800,
    "gn:feature_class":"P",
    "gn:feature_code":"PPL",
    "gn:name":"Dahan-e Q\u014dl",
    "gn:population":0,
    "gn:timezone":"Asia/Kabul",
    "iso:country":"AF",
    "name:rus_x_preferred":[
        "Dakhani-Kul\u2019"
    ],
    "name:und_x_variant":[
        "\u1e0eahane Q\u014dl",
        "Dahan-e Qowl",
        "Dahan-e Q\u014dl",
        "\u062f\u0647\u0646 \u0642\u0648\u0644"
    ],
    "wof:name":"Dahan-e Qol",
    "wof:placetype":"locality"
},
  "geometry": {"coordinates":[68.19485999999999,34.85196],"type":"Point"}
}