{
  "type": "Feature",
  "properties": {
    "gn:admin1_code":"05",
    "gn:admin2_code":"2805",
    "gn:asciiname":"Sar-e Takhak",
    "gn:country_code":"AF",
    "gn:dem":2977,
    "gn:feature_class":"P",
    "gn:feature_code":"PPL",
    "gn:name":"Sar-e Takhak",
    "gn:population":0,
    "gn:timezone":"Asia/Kabul",
    "iso:country":"AF",
    "name:und_x_variant":[
        "Sari-Takhak",
        "Sar-e Takhak",
        "\u0633\u0631 \u062a\u062e\u06a9"
    ],
    "wof:name":"Sar-e Takhak",
    "wof:placetype":"locality"
},
  "geometry": {"coordinates":[66.90289,34.31126],"type":"Point"}
}