{
  "type": "Feature",
  "properties": {
    "gn:admin1_code":"27",
    "gn:admin2_code":"403.0",
    "gn:asciiname":"Kudulak",
    "gn:country_code":"AF",
    "gn:dem":3271,
    "gn:feature_class":"P",
    "gn:feature_code":"PPL",
    "gn:name":"Ku\u1e0fulak",
    "gn:population":0,
    "gn:timezone":"Asia/Kabul",
    "iso:country":"AF",
    "name:und_x_variant":[
        "Kodolak",
        "K\u014ddalak",
        "Ku\u1e0fulak",
        "\u06a9\u0689\u0644\u06a9"
    ],
    "wof:name":"Kudulak",
    "wof:placetype":"locality"
},
  "geometry": {"coordinates":[68.18809,34.54599],"type":"Point"}
}