{
  "type": "Feature",
  "properties": {
    "gn:admin1_code":"14",
    "gn:admin2_code":"201.0",
    "gn:asciiname":"Sorghal",
    "gn:country_code":"AF",
    "gn:dem":1493,
    "gn:feature_class":"P",
    "gn:feature_code":"PPL",
    "gn:name":"S\u014drghal",
    "gn:population":0,
    "gn:timezone":"Asia/Kabul",
    "iso:country":"AF",
    "name:rus_x_preferred":[
        "Sorgal\u2019"
    ],
    "name:und_x_variant":[
        "S\u014d\u1e5fghal",
        "S\u016brghal",
        "S\u014drghal",
        "\u0633\u0648\u0631\u063a\u0644"
    ],
    "wof:name":"Sorghal",
    "wof:placetype":"locality"
},
  "geometry": {"coordinates":[69.31844,35.04295],"type":"Point"}
}