{
  "type": "Feature",
  "properties": {
    "gn:admin1_code":"23",
    "gn:admin2_code":"2413",
    "gn:asciiname":"Piranay",
    "gn:country_code":"AF",
    "gn:dem":2232,
    "gn:feature_class":"P",
    "gn:feature_code":"PPL",
    "gn:name":"Piranay",
    "gn:population":0,
    "gn:timezone":"Asia/Kabul",
    "iso:country":"AF",
    "name:und_x_variant":[
        "\u067e\u0631\u0646\u06cc"
    ],
    "wof:name":"Piranay",
    "wof:placetype":"locality"
},
  "geometry": {"coordinates":[67.76969,31.38455],"type":"Point"}
}