{
  "type": "Feature",
  "properties": {
    "gn:admin1_code":"34",
    "gn:admin2_code":"1006.0",
    "gn:asciiname":"Alingal",
    "gn:country_code":"AF",
    "gn:dem":1342,
    "gn:feature_class":"P",
    "gn:feature_code":"PPL",
    "gn:name":"Al\u012bngal",
    "gn:population":0,
    "gn:timezone":"Asia/Kabul",
    "iso:country":"AF",
    "name:rus_x_preferred":[
        "Alingal\u2019"
    ],
    "name:und_x_variant":[
        "\u0627\u0644\u06cc\u0646\u06af\u0644",
        "Al\u012bngal"
    ],
    "wof:name":"Alingal",
    "wof:placetype":"locality"
},
  "geometry": {"coordinates":[71.3172,35.13971],"type":"Point"}
}