{
  "type": "Feature",
  "properties": {
    "gn:admin1_code":"01",
    "gn:admin2_code":"1101.0",
    "gn:asciiname":"Khanaqa",
    "gn:country_code":"AF",
    "gn:dem":1295,
    "gn:feature_class":"P",
    "gn:feature_code":"PPL",
    "gn:name":"Kh\u0101naq\u0101",
    "gn:population":0,
    "gn:timezone":"Asia/Kabul",
    "iso:country":"AF",
    "name:und_x_variant":[
        "Kh\u0101neq\u0101h",
        "Kh\u0101naq\u0101",
        "\u062e\u0627\u0646\u0642\u0627"
    ],
    "wof:name":"Khanaqa",
    "wof:placetype":"locality"
},
  "geometry": {"coordinates":[70.65215999999999,37.0577],"type":"Point"}
}