{
  "type": "Feature",
  "properties": {
    "gn:admin1_code":"01",
    "gn:admin2_code":"1112.0",
    "gn:asciiname":"Qishlaq-e Safed",
    "gn:country_code":"AF",
    "gn:dem":2424,
    "gn:feature_class":"P",
    "gn:feature_code":"PPL",
    "gn:name":"Qishl\u0101q-e Saf\u0113d",
    "gn:population":0,
    "gn:timezone":"Asia/Kabul",
    "iso:country":"AF",
    "name:und_x_variant":[
        "Qesl\u0101q-i-Saf\u0113\u1e0f",
        "Qeshl\u0101q-e Sef\u012bd",
        "Qishl\u0101q-e Safayd",
        "\u0642\u0634\u0644\u0627\u0642 \u0633\u0641\u06d0\u062f",
        "Qishl\u0101q-e Saf\u0113d"
    ],
    "wof:name":"Qishlaq-e Safed",
    "wof:placetype":"locality"
},
  "geometry": {"coordinates":[70.35613000000001,37.66653],"type":"Point"}
}