{
  "type": "Feature",
  "properties": {
    "gn:admin1_code":"5",
    "gn:admin2_code":"2806.0",
    "gn:asciiname":"Dahan-e Buzgirak",
    "gn:country_code":"AF",
    "gn:dem":2486,
    "gn:feature_class":"P",
    "gn:feature_code":"PPL",
    "gn:name":"Dahan-e Buzgirak",
    "gn:population":0,
    "gn:timezone":"Asia/Kabul",
    "iso:country":"AF",
    "name:und_x_variant":[
        "Dakhani-Buzgirak",
        "\u1e0eahane Buzgi\u1e5fak",
        "Dahan-e Bozg\u012brak",
        "Dahan-e Buzg\u012brak",
        "Dahan-e Buzgirak",
        "\u062f\u0647\u0646 \u0628\u0632\u06af\u0631\u06a9"
    ],
    "wof:name":"Dahan-e Buzgirak",
    "wof:placetype":"locality"
},
  "geometry": {"coordinates":[66.96074,34.1956],"type":"Point"}
}