{
  "type": "Feature",
  "properties": {
    "gn:admin1_code":"28",
    "gn:admin2_code":"2507",
    "gn:asciiname":"Shinkai",
    "gn:country_code":"AF",
    "gn:dem":2079,
    "gn:feature_class":"P",
    "gn:feature_code":"PPL",
    "gn:name":"Sh\u012bnka\u012b",
    "gn:population":0,
    "gn:timezone":"Asia/Kabul",
    "iso:country":"AF",
    "name:ita_x_preferred":[
        "Shinkai"
    ],
    "name:jpn_x_preferred":[
        "\u6df1\u6d77"
    ],
    "name:kor_x_preferred":[
        "\uc2ec\ud574"
    ],
    "name:pus_x_preferred":[
        "\u0634\u06cc\u0646\u06a9\u06cc"
    ],
    "name:und_x_variant":[
        "S\u0304enkay",
        "Sh\u012bnka\u012b",
        "\u0160inkay",
        "Sh\u012bnkay",
        "\u0634\u06cc\u0646\u06a9\u06cc"
    ],
    "name:zho_x_preferred":[
        "\u6df1\u6d77"
    ],
    "wof:name":"Shinkai",
    "wof:placetype":"locality"
},
  "geometry": {"coordinates":[67.38002,31.96964],"type":"Point"}
}