{
  "type": "Feature",
  "properties": {
    "gn:admin1_code":"27",
    "gn:admin2_code":"401.0",
    "gn:asciiname":"Ahangar",
    "gn:country_code":"AF",
    "gn:dem":2217,
    "gn:feature_class":"P",
    "gn:feature_code":"PPL",
    "gn:name":"\u0100hangar",
    "gn:population":0,
    "gn:timezone":"Asia/Kabul",
    "iso:country":"AF",
    "name:ara_x_preferred":[
        "\u0622\u0647\u0646\u063a\u0631"
    ],
    "name:fas_x_preferred":[
        "\u0622\u0647\u0646\u06af\u0631"
    ],
    "name:und_x_variant":[
        "Akhingar",
        "\u0100henga\u1e5f",
        "\u0100hangar"
    ],
    "name:urd_x_preferred":[
        "\u0622\u06c1\u0646\u06af\u0627\u0631"
    ],
    "wof:name":"Ahangar",
    "wof:placetype":"locality"
},
  "geometry": {"coordinates":[68.81667,34.42922],"type":"Point"}
}