{
  "type": "Feature",
  "properties": {
    "gn:admin1_code":"29",
    "gn:admin2_code":"2904.0",
    "gn:asciiname":"Abdakay",
    "gn:country_code":"AF",
    "gn:dem":2273,
    "gn:feature_class":"P",
    "gn:feature_code":"PPL",
    "gn:name":"Abdakay",
    "gn:population":0,
    "gn:timezone":"Asia/Kabul",
    "iso:country":"AF",
    "name:und_x_variant":[
        "\u0627\u0628\u062f\u06a9\u06cc",
        "Ab\u1e0fakay",
        "Abdakay"
    ],
    "wof:name":"Abdakay",
    "wof:placetype":"locality"
},
  "geometry": {"coordinates":[68.24485,32.23397],"type":"Point"}
}