{
  "type": "Feature",
  "properties": {
    "gn:admin1_code":"41",
    "gn:admin2_code":"3404",
    "gn:asciiname":"Gurdak",
    "gn:country_code":"AF",
    "gn:dem":1568,
    "gn:feature_class":"P",
    "gn:feature_code":"PPL",
    "gn:name":"Gurdak",
    "gn:population":0,
    "gn:timezone":"Asia/Kabul",
    "iso:country":"AF",
    "name:fas_x_preferred":[
        "\u06af\u0648\u0631\u062f\u0643"
    ],
    "name:rus_x_preferred":[
        "\u0413\u0443\u0440\u0434\u0430\u043a"
    ],
    "name:und_x_variant":[
        "Gu\u1e5f\u1e0fak",
        "Gurdak",
        "Gerdak",
        "\u06af\u0631\u062f\u06a9",
        "Gordak"
    ],
    "wof:name":"Gurdak",
    "wof:placetype":"locality"
},
  "geometry": {"coordinates":[65.494,33.32919],"type":"Point"}
}