{
  "type": "Feature",
  "properties": {
    "gn:admin1_code":"08",
    "gn:admin2_code":"604",
    "gn:asciiname":"Sarnah Qal'ah",
    "gn:country_code":"AF",
    "gn:dem":3247,
    "gn:feature_class":"P",
    "gn:feature_code":"PPL",
    "gn:name":"Sarnah Qal\u2018ah",
    "gn:population":0,
    "gn:timezone":"Asia/Kabul",
    "iso:country":"AF",
    "name:fas_x_preferred":[
        "\u0642\u0644\u0639\u0647\u0654 \u0633\u0631\u0646\u0647"
    ],
    "name:rus_x_preferred":[
        "\u0421\u0430\u0440\u043d\u0430\u043a\u0430\u043b\u0430"
    ],
    "name:und_x_variant":[
        "Sarnaqal\u2018eh",
        "Sarnakala",
        "Sa\u1e5fnaqal\u2018a",
        "Sarnahqal\u2018eh",
        "Sarnah Qal\u2018ah",
        "\u0633\u0631\u0646\u0647 \u0642\u0644\u0639\u0647"
    ],
    "wof:name":"Sarnah Qal'ah",
    "wof:placetype":"locality"
},
  "geometry": {"coordinates":[67.98983,33.65586],"type":"Point"}
}