{
  "type": "Feature",
  "properties": {
    "gn:admin1_code":"5",
    "gn:admin2_code":"2801.0",
    "gn:asciiname":"Qal'ah-ye 'Ali Beg",
    "gn:country_code":"AF",
    "gn:dem":3072,
    "gn:feature_class":"P",
    "gn:feature_code":"PPL",
    "gn:name":"Qal\u2018ah-ye \u2018Al\u012b B\u0113g",
    "gn:population":0,
    "gn:timezone":"Asia/Kabul",
    "iso:country":"AF",
    "name:und_x_variant":[
        "Qal\u2018a-i-Al\u012bb\u0113g",
        "Kalayi-Alibek",
        "Qal\u2018ah-ye \u2018Al\u012b Bayg",
        "Qal\u2018eh-ye \u2018Al\u012bbeyg",
        "Qal\u2018ah-ye \u2018Al\u012b B\u0113g",
        "\u0642\u0644\u0639\u0647 \u0639\u0644\u06cc \u0628\u06d0\u06af"
    ],
    "wof:name":"Qal'ah-ye 'Ali Beg",
    "wof:placetype":"locality"
},
  "geometry": {"coordinates":[67.6892,34.72675],"type":"Point"}
}