{
  "type": "Feature",
  "properties": {
    "gn:admin1_code":"18",
    "gn:admin2_code":"819",
    "gn:asciiname":"Kanday",
    "gn:country_code":"AF",
    "gn:dem":616,
    "gn:feature_class":"P",
    "gn:feature_code":"PPL",
    "gn:name":"Kan\u1e0fay",
    "gn:population":0,
    "gn:timezone":"Asia/Kabul",
    "iso:country":"AF",
    "name:fas_x_preferred":[
        "\u0643\u0646\u062f\u06cc"
    ],
    "name:und_x_variant":[
        "Kon\u012b",
        "Kanday",
        "Kunai",
        "Kan\u1e0fay",
        "\u06a9\u0646\u0689\u06cc"
    ],
    "wof:name":"Kanday",
    "wof:placetype":"locality"
},
  "geometry": {"coordinates":[70.6576,34.58750999999999],"type":"Point"}
}