{
  "type": "Feature",
  "properties": {
    "gn:admin1_code":"35",
    "gn:admin2_code":"903",
    "gn:asciiname":"Shaykhan",
    "gn:country_code":"AF",
    "gn:dem":1014,
    "gn:feature_class":"P",
    "gn:feature_code":"PPL",
    "gn:name":"Shaykh\u0101n",
    "gn:population":0,
    "gn:timezone":"Asia/Kabul",
    "iso:country":"AF",
    "name:und_x_variant":[
        "\u0160\u0113kh\u0101n",
        "Sheykhan",
        "Shaykh\u0101n",
        "\u0634\u06cc\u062e\u0627\u0646",
        "Sheykh\u0101n"
    ],
    "wof:name":"Shaykhan",
    "wof:placetype":"locality"
},
  "geometry": {"coordinates":[70.38544,34.76656],"type":"Point"}
}