{
  "type": "Feature",
  "properties": {
    "gn:admin1_code":"36",
    "gn:admin2_code":"701",
    "gn:asciiname":"Nowrakay",
    "gn:country_code":"AF",
    "gn:dem":2588,
    "gn:feature_class":"P",
    "gn:feature_code":"PPL",
    "gn:name":"Now\u1e5fakay",
    "gn:population":0,
    "gn:timezone":"Asia/Kabul",
    "iso:country":"AF",
    "name:fas_x_preferred":[
        "\u0646\u0648\u0631\u0643\u06cc"
    ],
    "name:und_x_variant":[
        "Nawrakay",
        "Naurakay",
        "Nowrakay",
        "Now\u1e5fakay",
        "\u0646\u0648\u0693\u06a9\u06cc"
    ],
    "wof:name":"Nowrakay",
    "wof:placetype":"locality"
},
  "geometry": {"coordinates":[69.20647,33.7003],"type":"Point"}
}