{
  "type": "Feature",
  "properties": {
    "gn:admin1_code":"30",
    "gn:admin2_code":"1609.0",
    "gn:asciiname":"Dahganah",
    "gn:country_code":"AF",
    "gn:dem":1208,
    "gn:feature_class":"P",
    "gn:feature_code":"PPL",
    "gn:name":"Dahg\u0101nah",
    "gn:population":0,
    "gn:timezone":"Asia/Kabul",
    "iso:country":"AF",
    "name:und_x_variant":[
        "Dahgana",
        "Dahganah",
        "Dahg\u0101nah",
        "\u062f\u0647 \u06af\u0627\u0646\u0647"
    ],
    "wof:name":"Dahganah",
    "wof:placetype":"locality"
},
  "geometry": {"coordinates":[67.12805,36.24015],"type":"Point"}
}