{
  "type": "Feature",
  "properties": {
    "gn:admin1_code":"23",
    "gn:admin2_code":"2411",
    "gn:asciiname":"Gharbi Bayanzai",
    "gn:country_code":"AF",
    "gn:dem":1321,
    "gn:feature_class":"P",
    "gn:feature_code":"PPL",
    "gn:name":"Gharb\u012b Bay\u0101nza\u012b",
    "gn:population":0,
    "gn:timezone":"Asia/Kabul",
    "iso:country":"AF",
    "name:und_x_variant":[
        "Garbibayanzay",
        "Gharb\u012b Bay\u0101nza\u012b",
        "Gharbi Bayanzay",
        "\u063a\u0631\u0628\u06cc \u0628\u06cc\u0627\u0646\u0632\u06cc"
    ],
    "wof:name":"Gharbi Bayanzai",
    "wof:placetype":"locality"
},
  "geometry": {"coordinates":[66.53129,31.05351],"type":"Point"}
}