{
  "type": "Feature",
  "properties": {
    "gn:admin1_code":"28",
    "gn:admin2_code":"2502.0",
    "gn:asciiname":"Kash",
    "gn:country_code":"AF",
    "gn:dem":2206,
    "gn:feature_class":"P",
    "gn:feature_code":"PPL",
    "gn:name":"K\u0101sh",
    "gn:population":0,
    "gn:timezone":"Asia/Kabul",
    "iso:country":"AF",
    "name:fas_x_preferred":[
        "\u0643\u0634"
    ],
    "name:und_x_variant":[
        "K\u0101\u0161",
        "K\u0101sh",
        "\u06a9\u0627\u0634",
        "Kash"
    ],
    "wof:name":"Kash",
    "wof:placetype":"locality"
},
  "geometry": {"coordinates":[67.17953,32.48356],"type":"Point"}
}