{
  "type": "Feature",
  "properties": {
    "gn:admin1_code":"05",
    "gn:admin2_code":"2806",
    "gn:asciiname":"Zer Qal'ah",
    "gn:country_code":"AF",
    "gn:dem":2482,
    "gn:feature_class":"P",
    "gn:feature_code":"PPL",
    "gn:name":"Z\u0113r Qal\u2018ah",
    "gn:population":0,
    "gn:timezone":"Asia/Kabul",
    "iso:country":"AF",
    "name:und_x_variant":[
        "Z\u0113\u1e5fqal\u2018a",
        "Zerkala",
        "Z\u012br Qal\u2018ah",
        "Z\u012brqal\u2018eh",
        "Z\u0113r Qal\u2018ah",
        "\u0632\u06d0\u0631 \u0642\u0644\u0639\u0647"
    ],
    "wof:name":"Zer Qal'ah",
    "wof:placetype":"locality"
},
  "geometry": {"coordinates":[66.94006,34.21285],"type":"Point"}
}