{
  "type": "Feature",
  "properties": {
    "gn:admin1_code":"11",
    "gn:admin2_code":"2002.0",
    "gn:asciiname":"Sar-e Hasan Khwajah",
    "gn:country_code":"AF",
    "gn:dem":981,
    "gn:feature_class":"P",
    "gn:feature_code":"PPL",
    "gn:name":"Sar-e \u1e28asan Khw\u0101jah",
    "gn:population":0,
    "gn:timezone":"Asia/Kabul",
    "iso:country":"AF",
    "name:fas_x_preferred":[
        "\u0633\u0631\u0654 \u062d\u0633\u0646 \u062e\u0648\u0627\u062c\u0647"
    ],
    "name:und_x_variant":[
        "Sa\u0163-e \u1e28asan Khv\u0101jeh",
        "Sa\u1e5f-i-\u1e28asan Khw\u0101ja",
        "Sa\u0163-i-Hasan Khw\u0101ja",
        "Sari-Khasankhodzha",
        "Sar-e \u1e28asan Khv\u0101jeh",
        "Sar-e \u1e28asan Khw\u0101jah",
        "\u0633\u0631 \u062d\u0633\u0646 \u062e\u0648\u0627\u062c\u0647"
    ],
    "wof:name":"Sar-e Hasan Khwajah",
    "wof:placetype":"locality"
},
  "geometry": {"coordinates":[62.39637,34.2768],"type":"Point"}
}