{
  "type": "Feature",
  "properties": {
    "gn:admin1_code":"36",
    "gn:admin2_code":"704",
    "gn:asciiname":"Haki Kelay",
    "gn:country_code":"AF",
    "gn:dem":2243,
    "gn:feature_class":"P",
    "gn:feature_code":"PPL",
    "gn:name":"H\u0101k\u012b K\u00ealay",
    "gn:population":0,
    "gn:timezone":"Asia/Kabul",
    "iso:country":"AF",
    "name:fas_x_preferred":[
        "\u0647\u0627\u06a9\u06cc \u06a9\u0644\u06cc"
    ],
    "name:und_x_variant":[
        "Khakikalay",
        "\u0647\u0627\u06a9\u06cc \u06a9\u0644\u06cc",
        "\u1e28aq\u012b K\u00ealay",
        "H\u0101ki Kalay",
        "H\u0101k\u012b K\u00ealay"
    ],
    "wof:name":"Haki Kelay",
    "wof:placetype":"locality"
},
  "geometry": {"coordinates":[69.36006,33.34613],"type":"Point"}
}