{
  "type": "Feature",
  "properties": {
    "gn:admin1_code":"37",
    "gn:admin2_code":"3211.0",
    "gn:asciiname":"Azhdano Kelay",
    "gn:country_code":"AF",
    "gn:dem":1223,
    "gn:feature_class":"P",
    "gn:feature_code":"PPL",
    "gn:name":"Az\u0332h\u0332\u1e0fan\u014d K\u00ealay",
    "gn:population":0,
    "gn:timezone":"Asia/Kabul",
    "iso:country":"AF",
    "name:fas_x_preferred":[
        "\u0642\u0631\u064a\u06c0 \u0627\u0698\u062f\u0646\u0648"
    ],
    "name:und_x_variant":[
        "Azdanu-Kala",
        "A\u017edano Kalay",
        "Az\u0332h\u0332\u1e0fan\u014d K\u00ealay",
        "Az\u0332h\u0332dano Kalay",
        "\u0627\u0696\u062f\u0646\u0648 \u06a9\u0644\u06cc"
    ],
    "wof:name":"Azhdano Kelay",
    "wof:placetype":"locality"
},
  "geometry": {"coordinates":[69.94962,33.27223],"type":"Point"}
}