{
  "type": "Feature",
  "properties": {
    "gn:admin1_code":"41",
    "gn:admin2_code":"3407.0",
    "gn:asciiname":"Dahan-e Ramo",
    "gn:country_code":"AF",
    "gn:dem":3061,
    "gn:feature_class":"P",
    "gn:feature_code":"PPL",
    "gn:name":"Dahan-e R\u0101m\u014d",
    "gn:population":0,
    "gn:timezone":"Asia/Kabul",
    "iso:country":"AF",
    "name:und_x_variant":[
        "\u1e0eahane \u1e5e\u0101ma",
        "Dahan-e R\u0101m\u014d",
        "Dahan-e R\u0101mah",
        "\u062f\u0647\u0646 \u0631\u0627\u0645\u0648"
    ],
    "wof:name":"Dahan-e Ramo",
    "wof:placetype":"locality"
},
  "geometry": {"coordinates":[66.71420999999999,33.93293],"type":"Point"}
}