{
  "type": "Feature",
  "properties": {
    "gn:admin1_code":"34",
    "gn:admin2_code":"1011.0",
    "gn:asciiname":"Shanko Kelay",
    "gn:country_code":"AF",
    "gn:dem":1643,
    "gn:feature_class":"P",
    "gn:feature_code":"PPL",
    "gn:name":"Shank\u014d K\u00ealay",
    "gn:population":0,
    "gn:timezone":"Asia/Kabul",
    "iso:country":"AF",
    "wof:name":"Shanko Kelay",
    "wof:placetype":"locality"
},
  "geometry": {"coordinates":[70.94941,34.80559],"type":"Point"}
}