{
  "type": "Feature",
  "properties": {
    "gn:admin1_code":"01",
    "gn:admin2_code":"1110.0",
    "gn:asciiname":"Dirch",
    "gn:country_code":"AF",
    "gn:dem":2604,
    "gn:feature_class":"P",
    "gn:feature_code":"PPL",
    "gn:name":"Dirch",
    "gn:population":0,
    "gn:timezone":"Asia/Kabul",
    "iso:country":"AF",
    "name:und_x_variant":[
        "\u1e0eerc",
        "Derch",
        "Dirch",
        "\u062f\u0631\u0686"
    ],
    "wof:name":"Dirch",
    "wof:placetype":"locality"
},
  "geometry": {"coordinates":[70.8832,38.1767],"type":"Point"}
}