{
  "type": "Feature",
  "properties": {
    "gn:admin1_code":"5",
    "gn:admin2_code":"2806.0",
    "gn:asciiname":"Khak-e Mulla",
    "gn:country_code":"AF",
    "gn:dem":3008,
    "gn:feature_class":"P",
    "gn:feature_code":"PPL",
    "gn:name":"Kh\u0101k-e Mull\u0101",
    "gn:population":0,
    "gn:timezone":"Asia/Kabul",
    "iso:country":"AF",
    "name:und_x_variant":[
        "Khaki-Mulla",
        "Kh\u0101ke Mull\u0101",
        "Kh\u0101k-e Mull\u0101",
        "\u062e\u0627\u06a9 \u0645\u0644\u0627"
    ],
    "wof:name":"Khak-e Mulla",
    "wof:placetype":"locality"
},
  "geometry": {"coordinates":[66.69184,34.16905999999999],"type":"Point"}
}