{
  "type": "Feature",
  "properties": {
    "gn:admin1_code":"08",
    "gn:admin2_code":"607",
    "gn:asciiname":"Khar Zar",
    "gn:country_code":"AF",
    "gn:dem":2873,
    "gn:feature_class":"P",
    "gn:feature_code":"PPL",
    "gn:name":"Kh\u0101r Z\u0101r",
    "gn:population":0,
    "gn:timezone":"Asia/Kabul",
    "iso:country":"AF",
    "name:fas_x_preferred":[
        "\u062e\u0627\u0631\u0632\u0627\u0631"
    ],
    "name:rus_x_preferred":[
        "\u0425\u0430\u0440\u0437\u0430\u0440"
    ],
    "name:und_x_variant":[
        "Kh\u0101\u1e5fz\u0101\u1e5f Gh\u016bja",
        "Kharzar",
        "Kh\u0101rz\u0101r",
        "Kh\u0101r Z\u0101r",
        "\u062e\u0627\u0631 \u0632\u0627\u0631"
    ],
    "name:urd_x_preferred":[
        "\u062e\u0627\u0631 \u0632\u0627\u0631"
    ],
    "wof:name":"Khar Zar",
    "wof:placetype":"locality"
},
  "geometry": {"coordinates":[67.66924,33.20232],"type":"Point"}
}