{
  "type": "Feature",
  "properties": {
    "gn:admin1_code":"02",
    "gn:admin2_code":"1902.0",
    "gn:asciiname":"Gandah Ab",
    "gn:country_code":"AF",
    "gn:dem":1398,
    "gn:feature_class":"P",
    "gn:feature_code":"PPL",
    "gn:name":"Gandah \u0100b",
    "gn:population":0,
    "gn:timezone":"Asia/Kabul",
    "iso:country":"AF",
    "name:und_x_variant":[
        "Ganda \u0100b",
        "Gandeh \u0100b",
        "Gandah \u0100b",
        "\u06af\u0646\u062f\u0647 \u0622\u0628"
    ],
    "wof:name":"Gandah Ab",
    "wof:placetype":"locality"
},
  "geometry": {"coordinates":[62.90444,34.79015],"type":"Point"}
}