{
  "type": "Feature",
  "properties": {
    "gn:admin1_code":"23",
    "gn:admin2_code":"2413",
    "gn:asciiname":"'Omar Kelay",
    "gn:country_code":"AF",
    "gn:dem":2010,
    "gn:feature_class":"P",
    "gn:feature_code":"PPL",
    "gn:name":"\u2018Omar K\u00ealay",
    "gn:population":0,
    "gn:timezone":"Asia/Kabul",
    "iso:country":"AF",
    "name:und_x_variant":[
        "Umarkalay",
        "\u2018Omar K\u00ealay",
        "\u2018Omar Kalay",
        "\u0639\u0645\u0631 \u06a9\u0644\u06cc"
    ],
    "wof:name":"'Omar Kelay",
    "wof:placetype":"locality"
},
  "geometry": {"coordinates":[67.17834999999999,31.47874],"type":"Point"}
}