{
  "type": "Feature",
  "properties": {
    "gn:admin1_code":"26",
    "gn:admin2_code":"1205.0",
    "gn:asciiname":"Bala Mokhow-ye",
    "gn:country_code":"AF",
    "gn:dem":2990,
    "gn:feature_class":"P",
    "gn:feature_code":"PPL",
    "gn:name":"B\u0101l\u0101 Mokhow-ye",
    "gn:population":0,
    "gn:timezone":"Asia/Kabul",
    "iso:country":"AF",
    "wof:name":"Bala Mokhow-ye",
    "wof:placetype":"locality"
},
  "geometry": {"coordinates":[69.95083000000001,36.15389],"type":"Point"}
}