{
  "type": "Feature",
  "properties": {
    "gn:admin1_code":"11",
    "gn:admin2_code":"2010.0",
    "gn:asciiname":"Kharabah-ye Gaw Siyah",
    "gn:country_code":"AF",
    "gn:dem":908,
    "gn:feature_class":"P",
    "gn:feature_code":"PPL",
    "gn:name":"Khar\u0101bah-ye G\u0101w Siy\u0101h",
    "gn:population":0,
    "gn:timezone":"Asia/Kabul",
    "iso:country":"AF",
    "name:und_x_variant":[
        "Kha\u1e5f\u0101ba-i-G\u0101w Sy\u0101h",
        "Khar\u0101beh-ye G\u0101v S\u012b\u0101h",
        "Khar\u0101bah-ye G\u0101w S\u012b\u0101h",
        "\u062e\u0631\u0627\u0628\u06c0 \u06af\u0627\u0648 \u0633\u06cc\u0627\u0647",
        "Khar\u0101bah-ye G\u0101w Siy\u0101h"
    ],
    "wof:name":"Kharabah-ye Gaw Siyah",
    "wof:placetype":"locality"
},
  "geometry": {"coordinates":[61.98002,34.2628],"type":"Point"}
}