{
  "type": "Feature",
  "properties": {
    "gn:admin1_code":"13",
    "gn:admin2_code":"113.0",
    "gn:asciiname":"Malik Agha Khel",
    "gn:country_code":"AF",
    "gn:dem":2206,
    "gn:feature_class":"P",
    "gn:feature_code":"PPL",
    "gn:name":"Malik \u0100gh\u0101 Kh\u0113l",
    "gn:population":0,
    "gn:timezone":"Asia/Kabul",
    "iso:country":"AF",
    "name:fas_x_preferred":[
        "\u0645\u0644\u06a9 \u0622\u063a\u0627 \u062e\u064a\u0644"
    ],
    "name:rus_x_preferred":[
        "Malikagakheyl\u2019"
    ],
    "name:und_x_variant":[
        "Malek-\u0101gh\u0101kh\u0113l",
        "Malik \u0100gh\u0101 Kh\u0113l",
        "Malek \u0100gh\u0101kheyl",
        "Malik-\u0100gh\u0101 Kh\u0113l",
        "\u0645\u0644\u06a9 \u0622\u063a\u0627 \u062e\u06d0\u0644"
    ],
    "wof:name":"Malik Agha Khel",
    "wof:placetype":"locality"
},
  "geometry": {"coordinates":[69.00700999999999,34.75664],"type":"Point"}
}