{
  "type": "Feature",
  "properties": {
    "gn:admin1_code":"10",
    "gn:admin2_code":"2304.0",
    "gn:asciiname":"Landay",
    "gn:country_code":"AF",
    "gn:dem":1017,
    "gn:feature_class":"P",
    "gn:feature_code":"PPL",
    "gn:name":"Lan\u1e0fay",
    "gn:population":0,
    "gn:timezone":"Asia/Kabul",
    "iso:country":"AF",
    "name:slv_x_preferred":[
        "Landaj"
    ],
    "name:und_x_variant":[
        "Lan\u1e0fay",
        "\u0644\u0646\u0689\u06cc"
    ],
    "wof:name":"Landay",
    "wof:placetype":"locality"
},
  "geometry": {"coordinates":[64.85605,32.30721],"type":"Point"}
}