{
  "type": "Feature",
  "properties": {
    "gn:admin1_code":"02",
    "gn:admin2_code":"1902",
    "gn:asciiname":"Qipchaq",
    "gn:country_code":"AF",
    "gn:dem":954,
    "gn:feature_class":"P",
    "gn:feature_code":"PPL",
    "gn:name":"Q\u012bpch\u0101q",
    "gn:population":0,
    "gn:timezone":"Asia/Kabul",
    "iso:country":"AF",
    "name:und_x_variant":[
        "Kipchak",
        "Qip\u010d\u0101q",
        "Q\u012bpch\u0101q",
        "\u0642\u067e\u064a\u0686\u0627\u0642"
    ],
    "wof:name":"Qipchaq",
    "wof:placetype":"locality"
},
  "geometry": {"coordinates":[63.02954,34.9113],"type":"Point"}
}