{
  "type": "Feature",
  "properties": {
    "gn:admin1_code":"40",
    "gn:admin2_code":"310.0",
    "gn:asciiname":"Akhtaj",
    "gn:country_code":"AF",
    "gn:dem":1479,
    "gn:feature_class":"P",
    "gn:feature_code":"PPL",
    "gn:name":"Akht\u0101j",
    "gn:population":0,
    "gn:timezone":"Asia/Kabul",
    "iso:country":"AF",
    "name:fas_x_preferred":[
        "\u0627\u0647\u062a\u0627\u062c"
    ],
    "name:und_x_variant":[
        "Akht\u0101j",
        "Akhtadzh",
        "Aqt\u0101\u0161",
        "Aht\u0101j",
        "\u0627\u062e\u062a\u0627\u062c",
        "Aqt\u0101sh",
        "\u0627\u0642\u062a\u0627\u0634"
    ],
    "wof:name":"Akhtaj",
    "wof:placetype":"locality"
},
  "geometry": {"coordinates":[69.25888,35.04109],"type":"Point"}
}