{
  "type": "Feature",
  "properties": {
    "gn:admin1_code":"8",
    "gn:admin2_code":"607.0",
    "gn:asciiname":"Dahan-e Butaw",
    "gn:country_code":"AF",
    "gn:dem":2652,
    "gn:feature_class":"P",
    "gn:feature_code":"PPL",
    "gn:name":"Dah\u0101n-e But\u0101w",
    "gn:population":0,
    "gn:timezone":"Asia/Kabul",
    "iso:country":"AF",
    "name:und_x_variant":[
        "\u1e0eahane But\u0101w",
        "Dakhani-Butau",
        "Dah\u0101n-e But\u0101w",
        "\u062f\u0647\u0627\u0646 \u0628\u062a\u0627\u0648",
        "Dah\u0101neh-ye But\u0101w"
    ],
    "wof:name":"Dahan-e Butaw",
    "wof:placetype":"locality"
},
  "geometry": {"coordinates":[67.43059000000001,32.97394],"type":"Point"}
}