{
  "type": "Feature",
  "properties": {
    "gn:admin1_code":"11",
    "gn:admin2_code":"2011",
    "gn:asciiname":"Zulmabad",
    "gn:country_code":"AF",
    "gn:dem":1274,
    "gn:feature_class":"P",
    "gn:feature_code":"PPL",
    "gn:name":"Z\u0327ulm\u0101b\u0101d",
    "gn:population":0,
    "gn:timezone":"Asia/Kabul",
    "iso:country":"AF",
    "name:rus_x_preferred":[
        "Zul\u2019mabad"
    ],
    "name:und_x_variant":[
        "Z\u0327ulm \u0100b\u0101\u1e0f",
        "Z\u0327olm \u0100b\u0101d",
        "Z\u0327ulm\u0101b\u0101d",
        "\u0638\u0644\u0645 \u0622\u0628\u0627\u062f"
    ],
    "wof:name":"Zulmabad",
    "wof:placetype":"locality"
},
  "geometry": {"coordinates":[62.14633000000001,33.5487],"type":"Point"}
}