{
  "type": "Feature",
  "properties": {
    "gn:admin1_code":"7",
    "gn:admin2_code":"1805.0",
    "gn:asciiname":"Qaryeh-e Sangin",
    "gn:cc2":"AF",
    "gn:country_code":"AF",
    "gn:dem":2115,
    "gn:feature_class":"P",
    "gn:feature_code":"PPL",
    "gn:name":"Qaryeh-e Sang\u012bn",
    "gn:population":0,
    "gn:timezone":"Asia/Kabul",
    "iso:country":"AF",
    "name:und_x_variant":[
        "Qarya-i-Sang\u012bn",
        "Qaryeh-e Sang\u012bn"
    ],
    "wof:name":"Qaryeh-e Sangin",
    "wof:placetype":"locality"
},
  "geometry": {"coordinates":[64.83528000000001,35.38528],"type":"Point"}
}