{
  "type": "Feature",
  "properties": {
    "gn:admin1_code":"10",
    "gn:admin2_code":"2302.0",
    "gn:asciiname":"Anizo Kelay",
    "gn:country_code":"AF",
    "gn:dem":811,
    "gn:feature_class":"P",
    "gn:feature_code":"PPL",
    "gn:name":"Aniz\u014d K\u00ealay",
    "gn:population":0,
    "gn:timezone":"Asia/Kabul",
    "iso:country":"AF",
    "name:fas_x_preferred":[
        "\u0642\u0631\u064a\u06c0 \u0627\u0646\u0632\u0648"
    ],
    "name:und_x_variant":[
        "Anzio Kalay",
        "Anizukulay",
        "Anizo Kalay",
        "Aniz\u014d K\u00ealay",
        "\u0627\u0646\u0632\u0648 \u06a9\u0644\u06cc",
        "Aniz\u0327\u016b Kalay"
    ],
    "wof:name":"Anizo Kelay",
    "wof:placetype":"locality"
},
  "geometry": {"coordinates":[64.49361,31.75978],"type":"Point"}
}