{
  "type": "Feature",
  "properties": {
    "gn:admin1_code":"08",
    "gn:admin2_code":"613",
    "gn:asciiname":"Khar Toghay",
    "gn:country_code":"AF",
    "gn:dem":2610,
    "gn:feature_class":"P",
    "gn:feature_code":"PPL",
    "gn:name":"Khar T\u014dghay",
    "gn:population":0,
    "gn:timezone":"Asia/Kabul",
    "iso:country":"AF",
    "name:fas_x_preferred":[
        "\u062e\u0631\u062a\u0648\u063a\u06cc"
    ],
    "name:und_x_variant":[
        "Khartogay",
        "Kha\u1e5ft\u014dghay",
        "Khar T\u014dghay",
        "Khartowghay",
        "\u062e\u0631 \u062a\u0648\u063a\u06cc"
    ],
    "wof:name":"Khar Toghay",
    "wof:placetype":"locality"
},
  "geometry": {"coordinates":[68.02557,33.3741],"type":"Point"}
}