{
  "type": "Feature",
  "properties": {
    "gn:admin1_code":"23",
    "gn:admin2_code":"2411",
    "gn:asciiname":"Yaro Kelay",
    "gn:country_code":"AF",
    "gn:dem":1325,
    "gn:feature_class":"P",
    "gn:feature_code":"PPL",
    "gn:name":"Y\u0101r\u014d K\u00ealay",
    "gn:population":0,
    "gn:timezone":"Asia/Kabul",
    "iso:country":"AF",
    "name:und_x_variant":[
        "Yarukalay",
        "Y\u0101r\u014d K\u00ealay",
        "Y\u0101ro Kalay",
        "\u06cc\u0627\u0631\u0648 \u06a9\u0644\u06cc"
    ],
    "wof:name":"Yaro Kelay",
    "wof:placetype":"locality"
},
  "geometry": {"coordinates":[66.55667,31.07453],"type":"Point"}
}