{
  "type": "Feature",
  "properties": {
    "gn:admin1_code":"02",
    "gn:admin2_code":"1904",
    "gn:asciiname":"Shorab",
    "gn:country_code":"AF",
    "gn:dem":803,
    "gn:feature_class":"P",
    "gn:feature_code":"PPL",
    "gn:name":"Sh\u014dr\u0101b",
    "gn:population":0,
    "gn:timezone":"Asia/Kabul",
    "iso:country":"AF",
    "name:und_x_variant":[
        "Sh\u014d\u1e5faw",
        "Sh\u014dr\u0101b",
        "\u0634\u0648\u0631\u0627\u0628",
        "Sh\u016br\u0101b"
    ],
    "wof:name":"Shorab",
    "wof:placetype":"locality"
},
  "geometry": {"coordinates":[63.88851999999999,35.09337],"type":"Point"}
}