{
  "type": "Feature",
  "properties": {
    "gn:admin1_code":"29",
    "gn:admin2_code":"2906.0",
    "gn:asciiname":"Mulla Muhammad Ibrahim Kelay",
    "gn:country_code":"AF",
    "gn:dem":2130,
    "gn:feature_class":"P",
    "gn:feature_code":"PPL",
    "gn:name":"Mull\u0101 Mu\u1e29ammad Ibr\u0101h\u012bm K\u00ealay",
    "gn:population":0,
    "gn:timezone":"Asia/Kabul",
    "iso:country":"AF",
    "name:fas_x_preferred":[
        "\u0642\u0631\u064a\u06c0 \u0645\u0644\u0627 \u0645\u062d\u0645\u062f \u0627\u0628\u0631\u0627\u0647\u064a\u0645"
    ],
    "name:und_x_variant":[
        "Mull\u0101 Mo\u1e29amma\u1e0f Eb\u1e5f\u0101h\u012bm Kalay",
        "Mulla-Mukhammed-Ibrakhimkalay",
        "\u0645\u0644\u0627 \u0645\u062d\u0645\u062f \u0627\u0628\u0631\u0627\u0647\u06cc\u0645 \u06a9\u0644\u06cc",
        "Moll\u0101 Mo\u1e29ammad Ebr\u0101h\u012bm Kalay",
        "Mull\u0101 Mu\u1e29ammad Ibr\u0101h\u012bm K\u00ealay"
    ],
    "wof:name":"Mulla Muhammad Ibrahim Kelay",
    "wof:placetype":"locality"
},
  "geometry": {"coordinates":[68.82673,32.33063],"type":"Point"}
}