{
  "type": "Feature",
  "properties": {
    "gn:admin1_code":"08",
    "gn:admin2_code":"604",
    "gn:asciiname":"Ramzi",
    "gn:country_code":"AF",
    "gn:dem":3171,
    "gn:feature_class":"P",
    "gn:feature_code":"PPL",
    "gn:name":"Ramz\u012b",
    "gn:population":0,
    "gn:timezone":"Asia/Kabul",
    "iso:country":"AF",
    "name:und_x_variant":[
        "Ramz\u012b",
        "\u0631\u0645\u0632\u06cc"
    ],
    "wof:name":"Ramzi",
    "wof:placetype":"locality"
},
  "geometry": {"coordinates":[67.55508,34.02374],"type":"Point"}
}