{
  "type": "Feature",
  "properties": {
    "gn:admin1_code":"40",
    "gn:admin2_code":"303",
    "gn:asciiname":"Samida",
    "gn:country_code":"AF",
    "gn:dem":2232,
    "gn:feature_class":"P",
    "gn:feature_code":"PPL",
    "gn:name":"S\u0101mid\u0101",
    "gn:population":0,
    "gn:timezone":"Asia/Kabul",
    "iso:country":"AF",
    "name:fas_x_preferred":[
        "\u0633\u0627\u0645\u062f\u0627\u0644"
    ],
    "name:und_x_variant":[
        "S\u0101me\u1e0f\u0101",
        "S\u0101med\u0101l",
        "S\u0101mid\u0101",
        "\u0633\u0627\u0645\u062f\u0627"
    ],
    "wof:name":"Samida",
    "wof:placetype":"locality"
},
  "geometry": {"coordinates":[69.15461999999999,35.24010999999999],"type":"Point"}
}