{
  "type": "Feature",
  "properties": {
    "gn:admin1_code":"18",
    "gn:admin2_code":"810.0",
    "gn:asciiname":"Seh Naw Khulah",
    "gn:country_code":"AF",
    "gn:dem":1870,
    "gn:feature_class":"P",
    "gn:feature_code":"PPL",
    "gn:name":"Seh N\u0101w Kh\u016blah",
    "gn:population":0,
    "gn:timezone":"Asia/Kabul",
    "iso:country":"AF",
    "name:fas_x_preferred":[
        "\u062f\u0647\u0627\u0646\u0654 \u0633\u0647 \u0634\u064a\u0644\u0647"
    ],
    "name:und_x_variant":[
        "Sikhnaukhula",
        "Sehnaw Kholeh",
        "Seh N\u0101w Kh\u016blah",
        "\u0633\u0647 \u0646\u0627\u0648 \u062e\u0648\u0644\u0647"
    ],
    "wof:name":"Seh Naw Khulah",
    "wof:placetype":"locality"
},
  "geometry": {"coordinates":[70.56633000000002,34.03165],"type":"Point"}
}