{
  "type": "Feature",
  "properties": {
    "gn:admin1_code":"05",
    "gn:admin2_code":"2804",
    "gn:asciiname":"Halwa Qol",
    "gn:country_code":"AF",
    "gn:dem":2979,
    "gn:feature_class":"P",
    "gn:feature_code":"PPL",
    "gn:name":"\u1e28alw\u0101 Q\u014dl",
    "gn:population":0,
    "gn:timezone":"Asia/Kabul",
    "iso:country":"AF",
    "name:fas_x_preferred":[
        "\u062d\u0644\u0648\u0627 \u0642\u0648\u0644"
    ],
    "name:rus_x_preferred":[
        "Khal\u2019vakul\u2019"
    ],
    "name:rus_x_variant":[
        "\u0425\u0430\u043b\u044c\u0432\u0430\u043a\u0443\u043b\u044c"
    ],
    "name:und_x_variant":[
        "\u1e28alw\u0101q\u014dl",
        "\u1e28alw\u0101qowl",
        "\u1e28alw\u0101 Q\u014dl",
        "\u1e28alv\u0101qowl"
    ],
    "wof:name":"Halwa Qol",
    "wof:placetype":"locality"
},
  "geometry": {"coordinates":[67.22279,34.645],"type":"Point"}
}