{
  "type": "Feature",
  "properties": {
    "gn:admin1_code":"13",
    "gn:admin2_code":"101.0",
    "gn:asciiname":"Ta'mirat",
    "gn:country_code":"AF",
    "gn:dem":1791,
    "gn:feature_class":"P",
    "gn:feature_code":"PPL",
    "gn:name":"Ta\u2018m\u012br\u0101t",
    "gn:population":0,
    "gn:timezone":"Asia/Kabul",
    "iso:country":"AF",
    "name:und_x_variant":[
        "Ta\u2018m\u012br\u0101t",
        "\u062a\u0639\u0645\u06cc\u0631\u0627\u062a"
    ],
    "wof:name":"Ta'mirat",
    "wof:placetype":"locality"
},
  "geometry": {"coordinates":[69.30385,34.55055],"type":"Point"}
}