{
  "type": "Feature",
  "properties": {
    "gn:admin1_code":"36",
    "gn:admin2_code":"710",
    "gn:asciiname":"Kerkin Khulah",
    "gn:country_code":"AF",
    "gn:dem":2255,
    "gn:feature_class":"P",
    "gn:feature_code":"PPL",
    "gn:name":"K\u00ea\u1e5fk\u012bn Kh\u016blah",
    "gn:population":0,
    "gn:timezone":"Asia/Kabul",
    "iso:country":"AF",
    "name:und_x_variant":[
        "Kerkinkhula",
        "K\u00ea\u1e5fk\u012bn Kh\u016blah",
        "Kerk\u012bn Kholeh",
        "\u06a9\u0631\u06a9\u06cc\u0646 \u062e\u0648\u0644\u0647"
    ],
    "wof:name":"Kerkin Khulah",
    "wof:placetype":"locality"
},
  "geometry": {"coordinates":[69.55722,33.81528],"type":"Point"}
}