{
  "type": "Feature",
  "properties": {
    "gn:admin1_code":"28",
    "gn:admin2_code":"2509",
    "gn:asciiname":"Gerdey Takhay",
    "gn:country_code":"AF",
    "gn:dem":2058,
    "gn:feature_class":"P",
    "gn:feature_code":"PPL",
    "gn:name":"Gerd\u00eay Takhay",
    "gn:population":0,
    "gn:timezone":"Asia/Kabul",
    "iso:country":"AF",
    "name:und_x_variant":[
        "Girdaytikhay",
        "G\u00eard\u00eay T\u00eakh\u00eay",
        "Ge\u1e5f\u1e0f\u0113y Tekhay",
        "Gerd\u00eay Takhay",
        "\u06af\u0631\u062f\u06cd \u062a\u062e\u06cd"
    ],
    "wof:name":"Gerdey Takhay",
    "wof:placetype":"locality"
},
  "geometry": {"coordinates":[67.57025,31.88431],"type":"Point"}
}