{
  "type": "Feature",
  "properties": {
    "gn:admin1_code":"27",
    "gn:admin2_code":"403.0",
    "gn:asciiname":"Dahan-e Garm Ab",
    "gn:country_code":"AF",
    "gn:dem":2713,
    "gn:feature_class":"P",
    "gn:feature_code":"PPL",
    "gn:name":"Dahan-e Garm \u0100b",
    "gn:population":0,
    "gn:timezone":"Asia/Kabul",
    "iso:country":"AF",
    "name:und_x_variant":[
        "Dakhani-Garmav",
        "Dahan-e Garm Ow",
        "\u1e0eahane Ga\u1e5fmaw",
        "Dahan-e Garm \u0100b",
        "Dahan-e Garm\u0101b",
        "\u062f\u0647\u0646 \u06af\u0631\u0645 \u0622\u0628"
    ],
    "wof:name":"Dahan-e Garm Ab",
    "wof:placetype":"locality"
},
  "geometry": {"coordinates":[68.12105,34.3176],"type":"Point"}
}