{
  "type": "Feature",
  "properties": {
    "gn:admin1_code":"23",
    "gn:admin2_code":"2401",
    "gn:asciiname":"Kuchnay Karezak",
    "gn:country_code":"AF",
    "gn:dem":979,
    "gn:feature_class":"P",
    "gn:feature_code":"PPL",
    "gn:name":"Kuchnay K\u0101r\u0113zak",
    "gn:population":0,
    "gn:timezone":"Asia/Kabul",
    "iso:country":"AF",
    "name:fas_x_preferred":[
        "\u0643\u0627\u0631\u064a\u0632\u06a9\u0654 \u062e\u0648\u0631\u062f"
    ],
    "name:und_x_variant":[
        "Ku\u010dnay K\u0101r\u0113\u017eak",
        "Kuchnay K\u0101r\u0113zak",
        "Kuchnay-Karezak",
        "\u06a9\u0686\u0646\u06cc \u06a9\u0627\u0631\u06d0\u0632\u06a9",
        "Kuchnay K\u0101r\u012bzak"
    ],
    "wof:name":"Kuchnay Karezak",
    "wof:placetype":"locality"
},
  "geometry": {"coordinates":[65.68621999999999,31.5549],"type":"Point"}
}