{
  "type": "Feature",
  "properties": {
    "gn:admin1_code":"41",
    "gn:admin2_code":"3408.0",
    "gn:asciiname":"Kakrak",
    "gn:country_code":"AF",
    "gn:dem":2815,
    "gn:feature_class":"P",
    "gn:feature_code":"PPL",
    "gn:name":"Kakrak",
    "gn:population":0,
    "gn:timezone":"Asia/Kabul",
    "iso:country":"AF",
    "name:ceb_x_preferred":[
        "Darah-ye Kakrak"
    ],
    "name:fas_x_preferred":[
        "\u06a9\u06a9\u0631\u06a9"
    ],
    "name:swe_x_preferred":[
        "Darah-ye Kakrak"
    ],
    "wof:name":"Kakrak",
    "wof:placetype":"locality"
},
  "geometry": {"coordinates":[66.20934,34.26667],"type":"Point"}
}