{
  "type": "Feature",
  "properties": {
    "gn:admin1_code":"10",
    "gn:admin2_code":"2302",
    "gn:asciiname":"Ghundey",
    "gn:country_code":"AF",
    "gn:dem":813,
    "gn:feature_class":"P",
    "gn:feature_code":"PPL",
    "gn:name":"Ghun\u1e0f\u00eay",
    "gn:population":0,
    "gn:timezone":"Asia/Kabul",
    "iso:country":"AF",
    "name:und_x_variant":[
        "Gunday",
        "Ghun\u1e0f\u00eay",
        "\u063a\u0646\u0689\u06cd",
        "Gh\u016bn\u1e0f\u0113y"
    ],
    "wof:name":"Ghundey",
    "wof:placetype":"locality"
},
  "geometry": {"coordinates":[64.51102,31.77345],"type":"Point"}
}