{
  "type": "Feature",
  "properties": {
    "gn:admin1_code":"23",
    "gn:admin2_code":"2402.0",
    "gn:asciiname":"Biaban Darah",
    "gn:country_code":"AF",
    "gn:dem":1032,
    "gn:feature_class":"P",
    "gn:feature_code":"PPL",
    "gn:name":"B\u012b\u0101b\u0101n Darah",
    "gn:population":0,
    "gn:timezone":"Asia/Kabul",
    "iso:country":"AF",
    "name:fas_x_preferred":[
        "\u0628\u064a\u0627\u0628\u0627\u0646 \u062f\u064e\u0631\u064e\u0647"
    ],
    "name:und_x_variant":[
        "By\u0101b\u0101n \u1e0ea\u1e5f\u1e5fah",
        "Biabandarra",
        "B\u012b\u0101b\u0101n Darah",
        "\u0628\u06cc\u0627\u0628\u0627\u0646 \u062f\u0631\u0647",
        "B\u012b\u0101b\u0101n Darreh"
    ],
    "wof:name":"Biaban Darah",
    "wof:placetype":"locality"
},
  "geometry": {"coordinates":[65.92394,31.44983],"type":"Point"}
}