{
  "type": "Feature",
  "properties": {
    "gn:admin1_code":"01",
    "gn:admin2_code":"1117.0",
    "gn:asciiname":"Dzashtak",
    "gn:country_code":"AF",
    "gn:dem":1476,
    "gn:feature_class":"P",
    "gn:feature_code":"PPL",
    "gn:name":"Dz\u0101shtak",
    "gn:population":0,
    "gn:timezone":"Asia/Kabul",
    "iso:country":"AF",
    "name:und_x_variant":[
        "J\u0101\u0161tak",
        "J\u0101shtak",
        "Dz\u0101shtak",
        "\u0681\u0627\u0634\u062a\u06a9"
    ],
    "wof:name":"Dzashtak",
    "wof:placetype":"locality"
},
  "geometry": {"coordinates":[71.13503,38.39622],"type":"Point"}
}