{
  "type": "Feature",
  "properties": {
    "gn:admin1_code":"06",
    "gn:admin2_code":"2104",
    "gn:asciiname":"Ghay Bist",
    "gn:country_code":"AF",
    "gn:dem":1772,
    "gn:feature_class":"P",
    "gn:feature_code":"PPL",
    "gn:name":"Gh\u0101y Bist",
    "gn:population":0,
    "gn:timezone":"Asia/Kabul",
    "iso:country":"AF",
    "name:und_x_variant":[
        "Gh\u0101y Bist",
        "\u063a\u0627\u06cc \u0628\u0633\u062a",
        "Gh\u0101y Best"
    ],
    "wof:name":"Ghay Bist",
    "wof:placetype":"locality"
},
  "geometry": {"coordinates":[63.88534,33.36704],"type":"Point"}
}