{
  "type": "Feature",
  "properties": {
    "gn:admin1_code":"28",
    "gn:admin2_code":"2510.0",
    "gn:asciiname":"Khadzhiruzi",
    "gn:country_code":"AF",
    "gn:dem":2666,
    "gn:feature_class":"P",
    "gn:feature_code":"PPL",
    "gn:name":"Khadzhiruzi",
    "gn:population":0,
    "gn:timezone":"Asia/Kabul",
    "iso:country":"AF",
    "name:und_x_variant":[
        "H\u0101ji \u1e5e\u016bzi",
        "\u1e28\u0101j\u012b R\u016bz\u012b",
        "\u062d\u0627\u062c\u06cc \u0631\u0648\u0632\u06cc",
        "\u1e28\u0101jj\u012b R\u016bz\u012b"
    ],
    "wof:name":"Khadzhiruzi",
    "wof:placetype":"locality"
},
  "geometry": {"coordinates":[67.09844,32.81985],"type":"Point"}
}