{
  "type": "Feature",
  "properties": {
    "gn:admin1_code":"23",
    "gn:admin2_code":"2413.0",
    "gn:asciiname":"Patikzai Chinah",
    "gn:country_code":"AF",
    "gn:dem":1621,
    "gn:feature_class":"P",
    "gn:feature_code":"PPL",
    "gn:name":"P\u0101tikza\u012b Ch\u012bnah",
    "gn:population":0,
    "gn:timezone":"Asia/Kabul",
    "iso:country":"AF",
    "name:fas_x_preferred":[
        "\u0686\u0634\u0645\u06c0 \u067e\u0627\u062a\u0643\u0632\u06cc"
    ],
    "name:pus_x_preferred":[
        "\u067e\u0627\u062a\u06a9\u0632\u06cc \u0686\u06cc\u0646\u0647"
    ],
    "name:und_x_variant":[
        "P\u0101tekzay \u010cina",
        "Patikzaychina",
        "P\u0101tikza\u012b Ch\u012bnah",
        "P\u0101tekz\u0101y Ch\u012bnah",
        "P\u0101tikz\u012b Ch\u012bnah"
    ],
    "wof:name":"Patikzai Chinah",
    "wof:placetype":"locality"
},
  "geometry": {"coordinates":[67.01628000000001,31.56799],"type":"Point"}
}