{
  "type": "Feature",
  "properties": {
    "gn:admin1_code":"40",
    "gn:admin2_code":"310.0",
    "gn:asciiname":"Kuyah Khel",
    "gn:country_code":"AF",
    "gn:dem":1503,
    "gn:feature_class":"P",
    "gn:feature_code":"PPL",
    "gn:name":"K\u016byah Kh\u0113l",
    "gn:population":0,
    "gn:timezone":"Asia/Kabul",
    "iso:country":"AF",
    "name:fas_x_preferred":[
        "\u0643\u0648\u064a\u0647 \u062e\u064a\u0644"
    ],
    "name:rus_x_preferred":[
        "Kuyakkheyl\u2019"
    ],
    "name:und_x_variant":[
        "K\u016byakh\u0113l",
        "K\u016byehkheyl",
        "K\u016byah Kh\u0113l",
        "\u06a9\u0648\u06cc\u0647 \u062e\u06d0\u0644"
    ],
    "wof:name":"Kuyah Khel",
    "wof:placetype":"locality"
},
  "geometry": {"coordinates":[69.25657,35.06345],"type":"Point"}
}