{
  "type": "Feature",
  "properties": {
    "gn:admin1_code":"10",
    "gn:admin2_code":"2304.0",
    "gn:asciiname":"Darakhel",
    "gn:country_code":"AF",
    "gn:dem":993,
    "gn:feature_class":"P",
    "gn:feature_code":"PPL",
    "gn:name":"D\u0101r\u0101kh\u0113l",
    "gn:population":0,
    "gn:timezone":"Asia/Kabul",
    "iso:country":"AF",
    "name:rus_x_preferred":[
        "Darakheyl\u2019"
    ],
    "name:und_x_variant":[
        "\u1e0e\u0101\u1e5f\u0101kh\u0113l",
        "D\u0101r\u0101kh\u0113l",
        "\u062f\u0627\u0631\u0627\u062e\u06d0\u0644",
        "D\u0101r\u0101kheyl"
    ],
    "wof:name":"Darakhel",
    "wof:placetype":"locality"
},
  "geometry": {"coordinates":[64.77269,32.3199],"type":"Point"}
}