{
  "type": "Feature",
  "properties": {
    "gn:admin1_code":"18",
    "gn:admin2_code":"802.0",
    "gn:asciiname":"Bandah-ye Bemaran",
    "gn:country_code":"AF",
    "gn:dem":619,
    "gn:feature_class":"P",
    "gn:feature_code":"PPL",
    "gn:name":"B\u0101n\u1e0fah-ye B\u0113m\u0101r\u0101n",
    "gn:population":0,
    "gn:timezone":"Asia/Kabul",
    "iso:country":"AF",
    "name:fas_x_preferred":[
        "\u0628\u0646\u062f\u06c0 \u0628\u064a\u0645\u0627\u0631\u0627\u0646"
    ],
    "name:und_x_variant":[
        "B\u0101nda-i-B\u0113m\u0101\u1e5f\u0101n",
        "Bandaii-Bemaran",
        "Bandeh-ye B\u012bm\u0101r\u0101n",
        "\u0628\u0646\u062f\u06c0 \u0628\u064a\u0645\u0627\u0631\u0627\u0646",
        "B\u0101n\u1e0fah-ye B\u0113m\u0101r\u0101n",
        "\u0628\u0627\u0646\u0689\u06c0 \u0628\u06d0\u0645\u0627\u0631\u0627\u0646"
    ],
    "wof:name":"Bandah-ye Bemaran",
    "wof:placetype":"locality"
},
  "geometry": {"coordinates":[70.34774,34.45895],"type":"Point"}
}