{
  "type": "Feature",
  "properties": {
    "gn:admin1_code":"41",
    "gn:admin2_code":"3406",
    "gn:asciiname":"Espi Zarak",
    "gn:country_code":"AF",
    "gn:dem":2956,
    "gn:feature_class":"P",
    "gn:feature_code":"PPL",
    "gn:name":"Esp\u012b Zarak",
    "gn:population":0,
    "gn:timezone":"Asia/Kabul",
    "iso:country":"AF",
    "name:und_x_variant":[
        "Esp\u012b Zarak",
        "\u0627\u0633\u067e\u06cc \u0632\u0631\u06a9",
        "Espizarak"
    ],
    "wof:name":"Espi Zarak",
    "wof:placetype":"locality"
},
  "geometry": {"coordinates":[65.95928000000001,33.81762],"type":"Point"}
}