{
  "type": "Feature",
  "properties": {
    "gn:admin1_code":"10",
    "gn:admin2_code":"2302.0",
    "gn:asciiname":"Haji Jamal Kelay",
    "gn:country_code":"AF",
    "gn:dem":805,
    "gn:feature_class":"P",
    "gn:feature_code":"PPL",
    "gn:name":"\u1e28\u0101j\u012b Jam\u0101l K\u00ealay",
    "gn:population":0,
    "gn:timezone":"Asia/Kabul",
    "iso:country":"AF",
    "name:fas_x_preferred":[
        "\u0642\u0631\u064a\u06c0 \u062d\u0627\u062c\u06cc \u062c\u0645\u0627\u0644"
    ],
    "name:rus_x_preferred":[
        "Khadzhidzhamal\u2019-Kalay"
    ],
    "name:und_x_variant":[
        "\u1e28\u0101jijam\u0101l Kalay",
        "\u1e28\u0101j\u012b Jam\u0101l K\u00ealay",
        "\u062d\u0627\u062c\u06cc \u062c\u0645\u0627\u0644 \u06a9\u0644\u06cc",
        "\u1e28\u0101jj\u012b Jam\u0101l Kalay"
    ],
    "wof:name":"Haji Jamal Kelay",
    "wof:placetype":"locality"
},
  "geometry": {"coordinates":[64.45947,31.74725],"type":"Point"}
}