{
  "type": "Feature",
  "properties": {
    "gn:admin1_code":"13",
    "gn:admin2_code":"110.0",
    "gn:asciiname":"Takar Kala",
    "gn:country_code":"AF",
    "gn:dem":1837,
    "gn:feature_class":"P",
    "gn:feature_code":"PPL",
    "gn:name":"Takar Kal\u0101",
    "gn:population":0,
    "gn:timezone":"Asia/Kabul",
    "iso:country":"AF",
    "name:und_x_variant":[
        "Takar Kal\u0101",
        "\u062a\u06a9\u0631 \u06a9\u0644\u0627"
    ],
    "wof:name":"Takar Kala",
    "wof:placetype":"locality"
},
  "geometry": {"coordinates":[69.3129,34.47109],"type":"Point"}
}