{
  "type": "Feature",
  "properties": {
    "gn:admin1_code":"7",
    "gn:admin2_code":"1802.0",
    "gn:asciiname":"Aq-e 'Abdul",
    "gn:country_code":"AF",
    "gn:dem":1945,
    "gn:feature_class":"P",
    "gn:feature_code":"PPL",
    "gn:name":"\u0100q-e \u2018Abdul",
    "gn:population":0,
    "gn:timezone":"Asia/Kabul",
    "iso:country":"AF",
    "name:und_x_variant":[
        "\u0100q-i-\u2018\u0100b\u1e0ful",
        "\u0100q-e \u2018Abdol",
        "\u0100q-e \u2018Abdul",
        "\u0622\u0642 \u0639\u0628\u062f\u0644"
    ],
    "wof:name":"Aq-e 'Abdul",
    "wof:placetype":"locality"
},
  "geometry": {"coordinates":[64.76527,35.6077],"type":"Point"}
}