{
  "type": "Feature",
  "properties": {
    "gn:admin1_code":"23",
    "gn:admin2_code":"2404",
    "gn:asciiname":"Mazra'ah",
    "gn:country_code":"AF",
    "gn:dem":1032,
    "gn:feature_class":"P",
    "gn:feature_code":"PPL",
    "gn:name":"Mazra\u2018ah",
    "gn:population":0,
    "gn:timezone":"Asia/Kabul",
    "iso:country":"AF",
    "name:und_x_variant":[
        "Maz\u1e5fah",
        "Mazarai",
        "Mazra\u2018eh",
        "Mazra\u2018ah",
        "\u0645\u0632\u0631\u0639\u0647",
        "Mazra"
    ],
    "wof:name":"Mazra'ah",
    "wof:placetype":"locality"
},
  "geometry": {"coordinates":[65.67435,31.66719],"type":"Point"}
}