{
  "type": "Feature",
  "properties": {
    "gn:admin1_code":"17",
    "gn:admin2_code":"505",
    "gn:asciiname":"Gozay",
    "gn:country_code":"AF",
    "gn:dem":2343,
    "gn:feature_class":"P",
    "gn:feature_code":"PPL",
    "gn:name":"G\u014dzay",
    "gn:population":0,
    "gn:timezone":"Asia/Kabul",
    "iso:country":"AF",
    "name:und_x_variant":[
        "G\u014dzay",
        "Gozay",
        "Gowzay",
        "\u06af\u0648\u0632\u06cc"
    ],
    "wof:name":"Gozay",
    "wof:placetype":"locality"
},
  "geometry": {"coordinates":[69.27158,34.10694],"type":"Point"}
}