{
  "type": "Feature",
  "properties": {
    "gn:admin1_code":"08",
    "gn:admin2_code":"613",
    "gn:asciiname":"Mir Hasan",
    "gn:country_code":"AF",
    "gn:dem":2088,
    "gn:feature_class":"P",
    "gn:feature_code":"PPL",
    "gn:name":"M\u012br \u1e28asan",
    "gn:population":0,
    "gn:timezone":"Asia/Kabul",
    "iso:country":"AF",
    "name:ceb_x_preferred":[
        "M\u012br \u1e28asan"
    ],
    "name:fas_x_preferred":[
        "\u0645\u064a\u0631 \u062d\u0633\u0646"
    ],
    "name:fas_x_variant":[
        "\u0645\u06cc\u0631\u062d\u0633\u0646"
    ],
    "name:swe_x_preferred":[
        "M\u012br \u1e28asan"
    ],
    "name:und_x_variant":[
        "Mir",
        "\u0645\u06cc\u0631 \u062d\u0633\u0646"
    ],
    "wof:name":"Mir Hasan",
    "wof:placetype":"locality"
},
  "geometry": {"coordinates":[68.07594,33.12632],"type":"Point"}
}