{
  "type": "Feature",
  "properties": {
    "gn:country":"AF",
    "gn:fcode":"PPLA2",
    "gn:population":9642,
    "iso:country":"AF",
    "name:ast_x_preferred":[
        "Darzi Ab"
    ],
    "name:ceb_x_preferred":[
        "Darz\u0101b"
    ],
    "name:eng_x_preferred":[
        "Darzab"
    ],
    "name:fas_x_preferred":[
        "\u062f\u0631\u0632\u0627\u0628"
    ],
    "name:nld_x_preferred":[
        "Darzab"
    ],
    "name:spa_x_preferred":[
        "Darzi \u0100b"
    ],
    "name:swe_x_preferred":[
        "Darz\u0101b"
    ],
    "name:swe_x_variant":[
        "Darzab"
    ],
    "name:und_x_variant":[
        "Durz\u0101b"
    ],
    "qs:name":"Darz\u0101b",
    "qs:photos_9r":0,
    "qs:photos_sr":0,
    "qs:pop_sr":"5",
    "wof:name":"Darz\u0101b",
    "wof:placetype":"locality",
    "wof:population":9642
},
  "geometry": {"coordinates":[65.37828,35.97744],"type":"Point"}
}