{
  "type": "Feature",
  "properties": {
    "gn:admin1_code":"01",
    "gn:admin2_code":"1119.0",
    "gn:asciiname":"Chashtezh",
    "gn:country_code":"AF",
    "gn:dem":2478,
    "gn:feature_class":"P",
    "gn:feature_code":"PPL",
    "gn:name":"Ch\u0101sht\u0113zh",
    "gn:population":0,
    "gn:timezone":"Asia/Kabul",
    "iso:country":"AF",
    "name:und_x_variant":[
        "\u010c\u0101\u0161t\u0113\u017e",
        "\u0686\u0627\u0634\u062a\u06cc\u0698",
        "Ch\u0101sht\u0113zh",
        "Ch\u0101shtayzh",
        "\u0686\u0627\u0634\u062a\u06d0\u0698"
    ],
    "wof:name":"Chashtezh",
    "wof:placetype":"locality"
},
  "geometry": {"coordinates":[70.64791,37.48699000000001],"type":"Point"}
}