{
  "type": "Feature",
  "properties": {
    "gn:admin1_code":"09",
    "gn:admin2_code":"2707",
    "gn:asciiname":"Karam Zar",
    "gn:country_code":"AF",
    "gn:dem":3004,
    "gn:feature_class":"P",
    "gn:feature_code":"PPL",
    "gn:name":"Karam Z\u0101r",
    "gn:population":0,
    "gn:timezone":"Asia/Kabul",
    "iso:country":"AF",
    "name:und_x_variant":[
        "Karamz\u0101r",
        "Karamzar",
        "Karam Z\u0101r",
        "\u06a9\u0631\u0645 \u0632\u0627\u0631"
    ],
    "wof:name":"Karam Zar",
    "wof:placetype":"locality"
},
  "geometry": {"coordinates":[66.34124,34.58682],"type":"Point"}
}