{
  "type": "Feature",
  "properties": {
    "gn:admin1_code":"18",
    "gn:admin2_code":"806",
    "gn:asciiname":"Lukhay",
    "gn:country_code":"AF",
    "gn:dem":853,
    "gn:feature_class":"P",
    "gn:feature_code":"PPL",
    "gn:name":"Lukhay",
    "gn:population":0,
    "gn:timezone":"Asia/Kabul",
    "iso:country":"AF",
    "name:und_x_variant":[
        "Lokhay",
        "Lukhay",
        "\u0644\u062e\u06cc"
    ],
    "wof:name":"Lukhay",
    "wof:placetype":"locality"
},
  "geometry": {"coordinates":[70.3523,34.31584],"type":"Point"}
}