{
  "type": "Feature",
  "properties": {
    "gn:admin1_code":"30",
    "gn:admin2_code":"1606",
    "gn:asciiname":"Deh Razi",
    "gn:country_code":"AF",
    "gn:dem":362,
    "gn:feature_class":"P",
    "gn:feature_code":"PPL",
    "gn:name":"Deh Raz\u012b",
    "gn:population":0,
    "gn:timezone":"Asia/Kabul",
    "iso:country":"AF",
    "name:fas_x_preferred":[
        "\u062f\u06c0 \u0631\u0627\u0636\u06cc"
    ],
    "name:rus_x_preferred":[
        "\u0414\u0435\u0440\u0430\u0437\u0438"
    ],
    "name:und_x_variant":[
        "Zaulakai",
        "Derazi",
        "Deh-e R\u0101\u1e95\u012b",
        "Deh Raz\u012b",
        "\u062f\u0647 \u0631\u0632\u06cc",
        "Zowlaka\u012b",
        "\u0632\u0648\u0644\u06a9\u06cc"
    ],
    "wof:name":"Deh Razi",
    "wof:placetype":"locality"
},
  "geometry": {"coordinates":[66.86718,36.71791],"type":"Point"}
}