{
  "type": "Feature",
  "properties": {
    "gn:admin1_code":"09",
    "gn:admin2_code":"2702",
    "gn:asciiname":"Palangan",
    "gn:country_code":"AF",
    "gn:dem":2457,
    "gn:feature_class":"P",
    "gn:feature_code":"PPL",
    "gn:name":"Palang\u0101n",
    "gn:population":0,
    "gn:timezone":"Asia/Kabul",
    "iso:country":"AF",
    "name:ceb_x_preferred":[
        "Palangan"
    ],
    "name:fas_x_preferred":[
        "\u067e\u0644\u0646\u06af\u0627\u0646"
    ],
    "name:nld_x_preferred":[
        "Palangan"
    ],
    "name:swe_x_preferred":[
        "Palangan"
    ],
    "name:und_x_variant":[
        "Palang\u0101n",
        "\u067e\u0644\u0646\u06af\u0627\u0646"
    ],
    "wof:name":"Palangan",
    "wof:placetype":"locality"
},
  "geometry": {"coordinates":[64.14412,34.05038],"type":"Point"}
}