{
  "type": "Feature",
  "properties": {
    "gn:admin1_code":"41",
    "gn:admin2_code":"3407.0",
    "gn:asciiname":"Dahan-e Israk",
    "gn:country_code":"AF",
    "gn:dem":2516,
    "gn:feature_class":"P",
    "gn:feature_code":"PPL",
    "gn:name":"Dah\u0101n-e Israk",
    "gn:population":0,
    "gn:timezone":"Asia/Kabul",
    "iso:country":"AF",
    "name:und_x_variant":[
        "Dah\u0101n-e Israk",
        "\u062f\u0647\u0627\u0646 \u0627\u0633\u0631\u06a9"
    ],
    "wof:name":"Dahan-e Israk",
    "wof:placetype":"locality"
},
  "geometry": {"coordinates":[67.27426,33.88049],"type":"Point"}
}