{
  "type": "Feature",
  "properties": {
    "gn:admin1_code":"36",
    "gn:admin2_code":"706",
    "gn:asciiname":"Uluswali Jani Khel-e Mangal",
    "gn:country_code":"AF",
    "gn:dem":1992,
    "gn:feature_class":"P",
    "gn:feature_code":"PPL",
    "gn:name":"Ulusw\u0101l\u012b J\u0101n\u012b Kh\u0113l-e Mangal",
    "gn:population":0,
    "gn:timezone":"Asia/Kabul",
    "iso:country":"AF",
    "name:rus_x_preferred":[
        "Ulusvali-Dzhanikheyli-Mangal\u2019"
    ],
    "name:und_x_variant":[
        "Dz\u0101n\u012b Kheyl",
        "Olusw\u0101l\u012b J\u0101nikh\u0113le Mangal",
        "J\u0101nikh\u0113l",
        "Juni Khel",
        "Janikhele Mangal",
        "Dz\u0101n\u012b Kh\u0113l Mangal",
        "J\u0101n\u012b Kheyl Mangal",
        "Ulusw\u0101l\u012b J\u0101n\u012b Kh\u0113l-e Mangal",
        "\u0627\u0644\u0633\u0648\u0627\u0644\u06cc \u062c\u0627\u0646\u06cc \u062e\u06d0\u0644 \u0645\u0646\u06af\u0644",
        "J\u0101n\u012b Kh\u0113l-e Mangal",
        "\u062c\u0627\u0646\u06cc \u062e\u06d0\u0644 \u0645\u0646\u06af\u0644"
    ],
    "wof:name":"Uluswali Jani Khel-e Mangal",
    "wof:placetype":"locality"
},
  "geometry": {"coordinates":[69.77729000000001,33.65641],"type":"Point"}
}