{
  "type": "Feature",
  "properties": {
    "gn:admin1_code":"42",
    "gn:admin2_code":"3301.0",
    "gn:asciiname":"Sar-e Tambanah",
    "gn:country_code":"AF",
    "gn:dem":2420,
    "gn:feature_class":"P",
    "gn:feature_code":"PPL",
    "gn:name":"Sar-e Tambanah",
    "gn:population":0,
    "gn:timezone":"Asia/Kabul",
    "iso:country":"AF",
    "name:fas_x_preferred":[
        "\u0633\u0631\u0654 \u062a\u0645\u0628\u0627\u0646\u0647"
    ],
    "name:und_x_variant":[
        "Sa\u1e5fe Tambana",
        "Sari-Tambana",
        "Sar-e Tamb\u0101neh",
        "Sar-e Tambanah",
        "\u0633\u0631 \u062a\u0645\u0628\u0646\u0647"
    ],
    "wof:name":"Sar-e Tambanah",
    "wof:placetype":"locality"
},
  "geometry": {"coordinates":[69.46204,35.30432000000001],"type":"Point"}
}