{
  "type": "Feature",
  "properties": {
    "gn:admin1_code":"28",
    "gn:admin2_code":"2509",
    "gn:asciiname":"Ghwazhe Baso Khel",
    "gn:country_code":"AF",
    "gn:dem":2390,
    "gn:feature_class":"P",
    "gn:feature_code":"PPL",
    "gn:name":"Ghwaz\u0332h\u0332\u0113 Bas\u014d Kh\u0113l",
    "gn:population":0,
    "gn:timezone":"Asia/Kabul",
    "iso:country":"AF",
    "name:rus_x_preferred":[
        "Gvazebasokheyl\u2019"
    ],
    "name:und_x_variant":[
        "Ghwaz\u0113 Bas\u014dkh\u0113l",
        "Ghwazh\u012b Bas\u014d Kh\u0113l",
        "Ghwazh\u012b Basowkheyl",
        "Ghwaz\u0332h\u0332\u0113 Bas\u014d Kh\u0113l",
        "\u063a\u0648\u0696\u06d0 \u0628\u0633\u0648 \u062e\u06d0\u0644"
    ],
    "wof:name":"Ghwazhe Baso Khel",
    "wof:placetype":"locality"
},
  "geometry": {"coordinates":[67.92036999999999,31.98447],"type":"Point"}
}