{
  "type": "Feature",
  "properties": {
    "gn:admin1_code":"27",
    "gn:admin2_code":"408",
    "gn:asciiname":"Qolak",
    "gn:country_code":"AF",
    "gn:dem":2669,
    "gn:feature_class":"P",
    "gn:feature_code":"PPL",
    "gn:name":"Q\u014dlak",
    "gn:population":0,
    "gn:timezone":"Asia/Kabul",
    "iso:country":"AF",
    "name:und_x_variant":[
        "Kulak",
        "Q\u014dlak",
        "Qowlak",
        "\u0642\u0648\u0644\u06a9"
    ],
    "wof:name":"Qolak",
    "wof:placetype":"locality"
},
  "geometry": {"coordinates":[68.61523000000001,34.35033],"type":"Point"}
}