{
  "type": "Feature",
  "properties": {
    "gn:admin1_code":"8",
    "gn:admin2_code":"602.0",
    "gn:asciiname":"Sayyidha-ye Balkhi",
    "gn:country_code":"AF",
    "gn:dem":2488,
    "gn:feature_class":"P",
    "gn:feature_code":"PPL",
    "gn:name":"Sayyidh\u0101-ye Balkh\u012b",
    "gn:population":0,
    "gn:timezone":"Asia/Kabul",
    "iso:country":"AF",
    "name:fas_x_preferred":[
        "\u0633\u064a\u062f\u0647\u0627\u06cc \u0628\u0644\u062e\u06cc"
    ],
    "name:rus_x_preferred":[
        "Saidkhayi-Bal\u2019khi"
    ],
    "name:und_x_variant":[
        "Say\u1e0fh\u0101-i-Balkhi",
        "Seyyedh\u0101-ye Balkh\u012b",
        "Sayyidh\u0101-ye Balkh\u012b",
        "\u0633\u06cc\u062f \u0647\u0627\u06cc \u0628\u0644\u062e\u06cc"
    ],
    "wof:name":"Sayyidha-ye Balkhi",
    "wof:placetype":"locality"
},
  "geometry": {"coordinates":[68.21104,33.52329],"type":"Point"}
}