{
  "type": "Feature",
  "properties": {
    "gn:admin1_code":"8",
    "gn:admin2_code":"608.0",
    "gn:asciiname":"Chambar-e Wali Muhammad",
    "gn:country_code":"AF",
    "gn:dem":2014,
    "gn:feature_class":"P",
    "gn:feature_code":"PPL",
    "gn:name":"Chambar-e Wal\u012b Mu\u1e29ammad",
    "gn:population":0,
    "gn:timezone":"Asia/Kabul",
    "iso:country":"AF",
    "name:und_x_variant":[
        "\u010cambare Wali Mohammad",
        "Chanbar-e Valey Mo\u1e29ammad",
        "Chambari-Vali-Mukhammed",
        "Chambar-e Wal\u012b Mu\u1e29ammad",
        "\u0686\u0645\u0628\u0631 \u0648\u0644\u06cc \u0645\u062d\u0645\u062f",
        "Chanbar-e Val\u012b Mo\u1e29ammad"
    ],
    "wof:name":"Chambar-e Wali Muhammad",
    "wof:placetype":"locality"
},
  "geometry": {"coordinates":[67.77592,32.84273],"type":"Point"}
}