{
  "type": "Feature",
  "properties": {
    "gn:admin1_code":"37",
    "gn:admin2_code":"3208",
    "gn:asciiname":"Sevikan",
    "gn:country_code":"AF",
    "gn:dem":1903,
    "gn:feature_class":"P",
    "gn:feature_code":"PPL",
    "gn:name":"Sevikan",
    "gn:population":0,
    "gn:timezone":"Asia/Kabul",
    "iso:country":"AF",
    "name:fas_x_preferred":[
        "\u0633\u0648\u06cc \u0643\u0627\u0646"
    ],
    "name:und_x_variant":[
        "Sewi K\u0101\u1e49",
        "S\u00eaw\u012b K\u0101\u1e49",
        "Sev\u012b K\u0101n",
        "\u0633\u0648\u06cc \u0643\u0627\u06bc"
    ],
    "wof:name":"Sevikan",
    "wof:placetype":"locality"
},
  "geometry": {"coordinates":[69.62443,33.4044],"type":"Point"}
}