{
  "type": "Feature",
  "properties": {
    "gn:admin1_code":"03",
    "gn:admin2_code":"1303",
    "gn:asciiname":"Qaburghah",
    "gn:country_code":"AF",
    "gn:dem":1390,
    "gn:feature_class":"P",
    "gn:feature_code":"PPL",
    "gn:name":"Qaburghah",
    "gn:population":0,
    "gn:timezone":"Asia/Kabul",
    "iso:country":"AF",
    "name:und_x_variant":[
        "Qaburgha",
        "Qaburghah",
        "\u0642\u0628\u0631\u063a\u0647"
    ],
    "wof:name":"Qaburghah",
    "wof:placetype":"locality"
},
  "geometry": {"coordinates":[68.40510999999999,35.88132],"type":"Point"}
}