{
  "type": "Feature",
  "properties": {
    "gn:admin1_code":"08",
    "gn:admin2_code":"613",
    "gn:asciiname":"Lar",
    "gn:country_code":"AF",
    "gn:dem":2311,
    "gn:feature_class":"P",
    "gn:feature_code":"PPL",
    "gn:name":"Lar",
    "gn:population":0,
    "gn:timezone":"Asia/Kabul",
    "iso:country":"AF",
    "name:fas_x_preferred":[
        "\u0644\u0627\u0631"
    ],
    "name:rus_x_preferred":[
        "\u041b\u0430\u0440"
    ],
    "name:und_x_variant":[
        "L\u0101r",
        "\u0644\u0631"
    ],
    "wof:name":"Lar",
    "wof:placetype":"locality"
},
  "geometry": {"coordinates":[67.87172,33.14873],"type":"Point"}
}