{
  "type": "Feature",
  "properties": {
    "gn:admin1_code":"05",
    "gn:admin2_code":"2805",
    "gn:asciiname":"Quduq",
    "gn:country_code":"AF",
    "gn:dem":3331,
    "gn:feature_class":"P",
    "gn:feature_code":"PPL",
    "gn:name":"Q\u016bd\u016bq",
    "gn:population":0,
    "gn:timezone":"Asia/Kabul",
    "iso:country":"AF",
    "name:und_x_variant":[
        "Q\u016b\u1e0f\u016bq",
        "Kuduk",
        "Q\u016bd\u016bq",
        "Qowdowq",
        "\u0642\u0648\u062f\u0648\u0642",
        "Qod\u016bq",
        "\u0642\u062f\u0648\u0642"
    ],
    "wof:name":"Quduq",
    "wof:placetype":"locality"
},
  "geometry": {"coordinates":[66.88786,34.45254],"type":"Point"}
}