{
  "type": "Feature",
  "properties": {
    "gn:admin1_code":"26",
    "gn:admin2_code":"1213.0",
    "gn:asciiname":"Chapir",
    "gn:country_code":"AF",
    "gn:dem":730,
    "gn:feature_class":"P",
    "gn:feature_code":"PPL",
    "gn:name":"Chapir",
    "gn:population":0,
    "gn:timezone":"Asia/Kabul",
    "iso:country":"AF",
    "name:fas_x_preferred":[
        "\u0686\u0627\u067e\u0627\u0631"
    ],
    "name:rus_x_preferred":[
        "\u0427\u0430\u043f\u0438\u0440"
    ],
    "name:und_x_variant":[
        "\u010caper",
        "Chaper",
        "Chapir",
        "Ch\u0101p\u0101r",
        "\u0686\u067e\u0631"
    ],
    "wof:name":"Chapir",
    "wof:placetype":"locality"
},
  "geometry": {"coordinates":[69.4187,36.83783],"type":"Point"}
}