{
  "type": "Feature",
  "properties": {
    "gn:admin1_code":"03",
    "gn:admin2_code":"1308",
    "gn:asciiname":"Do Abi",
    "gn:country_code":"AF",
    "gn:dem":1549,
    "gn:feature_class":"P",
    "gn:feature_code":"PPL",
    "gn:name":"Do \u0100b\u012b",
    "gn:population":0,
    "gn:timezone":"Asia/Kabul",
    "iso:country":"AF",
    "wof:name":"Do Abi",
    "wof:placetype":"locality"
},
  "geometry": {"coordinates":[69.53333000000001,36.01667],"type":"Point"}
}