{
  "type": "Feature",
  "properties": {
    "gn:admin1_code":"40",
    "gn:admin2_code":"303",
    "gn:asciiname":"Nowach-e Pa'in",
    "gn:country_code":"AF",
    "gn:dem":1964,
    "gn:feature_class":"P",
    "gn:feature_code":"PPL",
    "gn:name":"Nowach-e P\u0101\u2019\u012bn",
    "gn:population":0,
    "gn:timezone":"Asia/Kabul",
    "iso:country":"AF",
    "name:fas_x_preferred":[
        "\u0646\u0648\u0686\u0654 \u067e\u0627\u0626\u064a\u0646"
    ],
    "name:und_x_variant":[
        "Noach",
        "Navachi-Pain",
        "Nawa\u010de P\u0101\u2019\u012bn",
        "Navach-e P\u0101\u2019\u012bn",
        "Nowach-e P\u0101\u2019\u012bn",
        "\u0646\u0648\u0686 \u067e\u0627\u0626\u06cc\u0646"
    ],
    "wof:name":"Nowach-e Pa'in",
    "wof:placetype":"locality"
},
  "geometry": {"coordinates":[69.21373,35.21397],"type":"Point"}
}