{
  "type": "Feature",
  "properties": {
    "gn:admin1_code":"18",
    "gn:admin2_code":"822",
    "gn:asciiname":"Zarbachah",
    "gn:country_code":"AF",
    "gn:dem":653,
    "gn:feature_class":"P",
    "gn:feature_code":"PPL",
    "gn:name":"Zarbachah",
    "gn:population":0,
    "gn:timezone":"Asia/Kabul",
    "iso:country":"AF",
    "name:und_x_variant":[
        "Zarba\u010da",
        "Zarbachah",
        "\u0632\u0631\u0628\u0686\u0647",
        "Zarbacha"
    ],
    "wof:name":"Zarbachah",
    "wof:placetype":"locality"
},
  "geometry": {"coordinates":[70.68550999999999,34.21869],"type":"Point"}
}