{
  "type": "Feature",
  "properties": {
    "gn:admin1_code":"01",
    "gn:admin2_code":"1113.0",
    "gn:asciiname":"Shorak",
    "gn:country_code":"AF",
    "gn:dem":1473,
    "gn:feature_class":"P",
    "gn:feature_code":"PPL",
    "gn:name":"Sh\u014drak",
    "gn:population":0,
    "gn:timezone":"Asia/Kabul",
    "iso:country":"AF",
    "name:und_x_variant":[
        "S\u014d\u1e5fak",
        "Showrak",
        "Sh\u014drak",
        "\u0634\u0648\u0631\u06a9"
    ],
    "wof:name":"Shorak",
    "wof:placetype":"locality"
},
  "geometry": {"coordinates":[70.10433,37.32175],"type":"Point"}
}