{
  "type": "Feature",
  "properties": {
    "gn:admin1_code":"05",
    "gn:admin2_code":"2804.0",
    "gn:asciiname":"Namadak",
    "gn:country_code":"AF",
    "gn:dem":2768,
    "gn:feature_class":"P",
    "gn:feature_code":"PPL",
    "gn:name":"Namadak",
    "gn:population":0,
    "gn:timezone":"Asia/Kabul",
    "iso:country":"AF",
    "name:fas_x_preferred":[
        "\u0646\u0645\u062f\u0643"
    ],
    "name:rus_x_preferred":[
        "\u041d\u0430\u043c\u0430\u0434\u0430\u043a"
    ],
    "wof:name":"Namadak",
    "wof:placetype":"locality"
},
  "geometry": {"coordinates":[67.12583000000001,34.73],"type":"Point"}
}