{
  "type": "Feature",
  "properties": {
    "gn:admin1_code":"23",
    "gn:admin2_code":"2403",
    "gn:asciiname":"Khal Bilagh",
    "gn:country_code":"AF",
    "gn:dem":1780,
    "gn:feature_class":"P",
    "gn:feature_code":"PPL",
    "gn:name":"Kh\u0101l Bil\u0101gh",
    "gn:population":0,
    "gn:timezone":"Asia/Kabul",
    "iso:country":"AF",
    "name:rus_x_preferred":[
        "Khal\u2019bilag"
    ],
    "name:und_x_variant":[
        "Kh\u0101l Bil\u0101gh",
        "\u062e\u0627\u0644 \u0628\u0644\u0627\u063a",
        "Kh\u0101lbel\u0101gh"
    ],
    "wof:name":"Khal Bilagh",
    "wof:placetype":"locality"
},
  "geometry": {"coordinates":[65.9853,32.23037],"type":"Point"}
}