{
  "type": "Feature",
  "properties": {
    "gn:admin1_code":"5",
    "gn:admin2_code":"2804.0",
    "gn:asciiname":"Bum",
    "gn:country_code":"AF",
    "gn:dem":2648,
    "gn:feature_class":"P",
    "gn:feature_code":"PPL",
    "gn:name":"B\u016bm",
    "gn:population":0,
    "gn:timezone":"Asia/Kabul",
    "iso:country":"AF",
    "name:fas_x_preferred":[
        "\u0628\u0648\u0645"
    ],
    "name:rus_x_preferred":[
        "\u0411\u0443\u043c"
    ],
    "name:und_x_variant":[
        "B\u016bm",
        "\u0628\u0648\u0645"
    ],
    "wof:name":"Bum",
    "wof:placetype":"locality"
},
  "geometry": {"coordinates":[67.01560000000001,34.71698],"type":"Point"}
}