{
  "type": "Feature",
  "properties": {
    "gn:admin1_code":"34",
    "gn:admin2_code":"1009",
    "gn:asciiname":"Kuz Kordar",
    "gn:country_code":"AF",
    "gn:dem":1985,
    "gn:feature_class":"P",
    "gn:feature_code":"PPL",
    "gn:name":"K\u016bz K\u014drdar",
    "gn:population":0,
    "gn:timezone":"Asia/Kabul",
    "iso:country":"AF",
    "name:und_x_variant":[
        "Kuz-Kordar",
        "K\u016bz K\u014d\u1e5f\u1e0fa\u1e5f",
        "K\u016bz Kowrdar",
        "K\u016bz K\u014drdar",
        "\u06a9\u0648\u0632 \u06a9\u0648\u0631\u062f\u0631"
    ],
    "wof:name":"Kuz Kordar",
    "wof:placetype":"locality"
},
  "geometry": {"coordinates":[70.64269,34.99954],"type":"Point"}
}