{
  "type": "Feature",
  "properties": {
    "gn:admin1_code":"23",
    "gn:admin2_code":"2407.0",
    "gn:asciiname":"Karez-e Garmabak",
    "gn:country_code":"AF",
    "gn:dem":1111,
    "gn:feature_class":"P",
    "gn:feature_code":"PPL",
    "gn:name":"K\u0101r\u0113z-e Garm\u0101bak",
    "gn:population":0,
    "gn:timezone":"Asia/Kabul",
    "iso:country":"AF",
    "name:fas_x_preferred":[
        "\u0643\u0627\u0631\u064a\u0632 \u06af\u0631\u0645\u0627\u0628\u0643"
    ],
    "name:und_x_variant":[
        "Garm\u0101bak",
        "Karezio-Garmabak",
        "K\u0101\u1e5f\u0113ze Ga\u1e5fm\u0101bak",
        "K\u0101r\u0113z-e Garm \u0100bak",
        "\u06a9\u0627\u0631\u06d0\u0632 \u06af\u0631\u0645 \u0622\u0628\u06a9",
        "K\u0101r\u012bz Garm\u0101bak",
        "K\u0101r\u0113z-e Garm\u0101bak",
        "\u06a9\u0627\u0631\u06d0\u0632 \u06af\u0631\u0645\u0622\u0628\u06a9"
    ],
    "wof:name":"Karez-e Garmabak",
    "wof:placetype":"locality"
},
  "geometry": {"coordinates":[65.0625,31.79673],"type":"Point"}
}