{
  "type": "Feature",
  "properties": {
    "gn:admin1_code":"8",
    "gn:admin2_code":"607.0",
    "gn:asciiname":"Kundil Qash",
    "gn:country_code":"AF",
    "gn:dem":2404,
    "gn:feature_class":"P",
    "gn:feature_code":"PPL",
    "gn:name":"Kundil Q\u0101sh",
    "gn:population":0,
    "gn:timezone":"Asia/Kabul",
    "iso:country":"AF",
    "name:und_x_variant":[
        "Kundel Q\u0101\u0161",
        "Kundel Q\u0101sh",
        "Kundil Q\u0101sh",
        "\u06a9\u0646\u062f\u0644 \u0642\u0627\u0634"
    ],
    "wof:name":"Kundil Qash",
    "wof:placetype":"locality"
},
  "geometry": {"coordinates":[67.48939,33.13542],"type":"Point"}
}