{
  "type": "Feature",
  "properties": {
    "gn:admin1_code":"03",
    "gn:admin2_code":"1301",
    "gn:asciiname":"Kokan",
    "gn:country_code":"AF",
    "gn:dem":618,
    "gn:feature_class":"P",
    "gn:feature_code":"PPL",
    "gn:name":"K\u014dkan",
    "gn:population":0,
    "gn:timezone":"Asia/Kabul",
    "iso:country":"AF",
    "name:und_x_variant":[
        "K\u014dkan",
        "Kokan",
        "K\u016bkan",
        "\u06a9\u0648\u06a9\u0646"
    ],
    "wof:name":"Kokan",
    "wof:placetype":"locality"
},
  "geometry": {"coordinates":[68.6815,35.99375],"type":"Point"}
}