{
  "type": "Feature",
  "properties": {
    "gn:admin1_code":"02",
    "gn:admin2_code":"1906.0",
    "gn:asciiname":"Khwajah Yakhdan",
    "gn:country_code":"AF",
    "gn:dem":1913,
    "gn:feature_class":"P",
    "gn:feature_code":"PPL",
    "gn:name":"Khw\u0101jah Yakhd\u0101n",
    "gn:population":0,
    "gn:timezone":"Asia/Kabul",
    "iso:country":"AF",
    "name:und_x_variant":[
        "Khwaja Yakhd\u0101n",
        "Khw\u0101jah Yakhd\u0101n",
        "\u062e\u0648\u0627\u062c\u0647 \u06cc\u062e\u062f\u0627\u0646",
        "Khv\u0101jeh Yakhd\u0101n"
    ],
    "wof:name":"Khwajah Yakhdan",
    "wof:placetype":"locality"
},
  "geometry": {"coordinates":[64.00587,35.43557],"type":"Point"}
}