{
  "type": "Feature",
  "properties": {
    "gn:admin1_code":"37",
    "gn:admin2_code":"3203.0",
    "gn:asciiname":"Muni Kelay",
    "gn:country_code":"AF",
    "gn:dem":1246,
    "gn:feature_class":"P",
    "gn:feature_code":"PPL",
    "gn:name":"Mun\u012b K\u00ealay",
    "gn:population":0,
    "gn:timezone":"Asia/Kabul",
    "iso:country":"AF",
    "name:fas_x_preferred":[
        "\u0642\u0631\u064a\u06c0 \u0645\u0648\u0646\u06cc"
    ],
    "name:und_x_variant":[
        "Munikalay",
        "Mun\u012b K\u00ealay",
        "Mon\u012b Kalay",
        "\u0645\u0646\u06cc \u06a9\u0644\u06cc"
    ],
    "wof:name":"Muni Kelay",
    "wof:placetype":"locality"
},
  "geometry": {"coordinates":[69.87494000000001,33.26163],"type":"Point"}
}