{
  "type": "Feature",
  "properties": {
    "gn:admin1_code":"40",
    "gn:admin2_code":"309.0",
    "gn:asciiname":"Siyah Sang",
    "gn:country_code":"AF",
    "gn:dem":1945,
    "gn:feature_class":"P",
    "gn:feature_code":"PPL",
    "gn:name":"Siy\u0101h Sang",
    "gn:population":0,
    "gn:timezone":"Asia/Kabul",
    "iso:country":"AF",
    "name:fas_x_preferred":[
        "\u0633\u064a\u0627\u0647 \u0633\u0646\u06af"
    ],
    "name:und_x_variant":[
        "Siasang",
        "Sy\u0101sang",
        "Say\u0101sang",
        "S\u012b\u0101h Sang",
        "\u0633\u064a\u0627\u0647 \u0633\u0646\u06af",
        "Siy\u0101h Sang"
    ],
    "wof:name":"Siyah Sang",
    "wof:placetype":"locality"
},
  "geometry": {"coordinates":[69.47971,34.82575],"type":"Point"}
}