{
  "type": "Feature",
  "properties": {
    "gn:admin1_code":"23",
    "gn:admin2_code":"2413.0",
    "gn:asciiname":"Tan Karez",
    "gn:country_code":"AF",
    "gn:dem":1575,
    "gn:feature_class":"P",
    "gn:feature_code":"PPL",
    "gn:name":"T\u0101n K\u0101r\u0113z",
    "gn:population":0,
    "gn:timezone":"Asia/Kabul",
    "iso:country":"AF",
    "name:und_x_variant":[
        "Tankarez",
        "T\u0101n K\u0101\u1e5f\u0113z",
        "T\u0101n K\u0101r\u0113z",
        "T\u0101n K\u0101r\u012bz",
        "\u062a\u0627\u0646 \u06a9\u0627\u0631\u06d0\u0632"
    ],
    "wof:name":"Tan Karez",
    "wof:placetype":"locality"
},
  "geometry": {"coordinates":[66.9025,31.46333],"type":"Point"}
}