{
  "type": "Feature",
  "properties": {
    "gn:admin1_code":"37",
    "gn:admin2_code":"3204",
    "gn:asciiname":"Kheng Kelay",
    "gn:country_code":"AF",
    "gn:dem":2279,
    "gn:feature_class":"P",
    "gn:feature_code":"PPL",
    "gn:name":"Kh\u00eang K\u00ealay",
    "gn:population":0,
    "gn:timezone":"Asia/Kabul",
    "iso:country":"AF",
    "name:und_x_variant":[
        "Khengkalay",
        "\u062e\u0646\u06af \u06a9\u0644\u06cc",
        "Kh\u0113ng Kalay",
        "Kh\u00eang K\u00ealay"
    ],
    "wof:name":"Kheng Kelay",
    "wof:placetype":"locality"
},
  "geometry": {"coordinates":[69.44211,33.12284],"type":"Point"}
}