{
  "type": "Feature",
  "properties": {
    "gn:admin1_code":"41",
    "gn:admin2_code":"3402.0",
    "gn:asciiname":"Zin",
    "gn:country_code":"AF",
    "gn:dem":1313,
    "gn:feature_class":"P",
    "gn:feature_code":"PPL",
    "gn:name":"Z\u012bn",
    "gn:population":0,
    "gn:timezone":"Asia/Kabul",
    "iso:country":"AF",
    "name:und_x_variant":[
        "Z\u012bn",
        "\u0632\u06cc\u0646"
    ],
    "wof:name":"Zin",
    "wof:placetype":"locality"
},
  "geometry": {"coordinates":[66.09693,33.22245],"type":"Point"}
}