{
  "type": "Feature",
  "properties": {
    "gn:admin1_code":"23",
    "gn:admin2_code":"2413.0",
    "gn:asciiname":"Wal",
    "gn:country_code":"AF",
    "gn:dem":2060,
    "gn:feature_class":"P",
    "gn:feature_code":"PPL",
    "gn:name":"Wal",
    "gn:population":0,
    "gn:timezone":"Asia/Kabul",
    "iso:country":"AF",
    "name:als_x_preferred":[
        "Wal"
    ],
    "name:ceb_x_preferred":[
        "Wal"
    ],
    "name:deu_x_preferred":[
        "Wal"
    ],
    "name:ltz_x_preferred":[
        "Wal"
    ],
    "name:nld_x_preferred":[
        "Wal"
    ],
    "name:pol_x_preferred":[
        "Wal"
    ],
    "name:rus_x_preferred":[
        "Val\u2019"
    ],
    "name:und_x_variant":[
        "\u0648\u0644"
    ],
    "wof:name":"Wal",
    "wof:placetype":"locality"
},
  "geometry": {"coordinates":[67.34619000000001,31.32613],"type":"Point"}
}