{
  "type": "Feature",
  "properties": {
    "gn:admin1_code":"30",
    "gn:admin2_code":"1611.0",
    "gn:asciiname":"Shah Anjir",
    "gn:country_code":"AF",
    "gn:dem":1809,
    "gn:feature_class":"P",
    "gn:feature_code":"PPL",
    "gn:name":"Sh\u0101h Anj\u012br",
    "gn:population":0,
    "gn:timezone":"Asia/Kabul",
    "iso:country":"AF",
    "name:und_x_variant":[
        "Sh\u0101h Anj\u012br",
        "\u0634\u0627\u0647 \u0627\u0646\u062c\u06cc\u0631"
    ],
    "wof:name":"Shah Anjir",
    "wof:placetype":"locality"
},
  "geometry": {"coordinates":[67.22058,36.34359],"type":"Point"}
}