{
  "type": "Feature",
  "properties": {
    "gn:admin1_code":"23",
    "gn:admin2_code":"2416",
    "gn:asciiname":"Zihdanan",
    "gn:country_code":"AF",
    "gn:dem":947,
    "gn:feature_class":"P",
    "gn:feature_code":"PPL",
    "gn:name":"Zihd\u0101n\u0101n",
    "gn:population":0,
    "gn:timezone":"Asia/Kabul",
    "iso:country":"AF",
    "name:und_x_variant":[
        "Zikhdanan",
        "Zihd\u0101n\u0101n",
        "\u0632\u0647\u062f\u0627\u0646\u0627\u0646",
        "Zehd\u0101n\u0101n"
    ],
    "wof:name":"Zihdanan",
    "wof:placetype":"locality"
},
  "geometry": {"coordinates":[65.43803,31.56538],"type":"Point"}
}