{
  "type": "Feature",
  "properties": {
    "gn:admin1_code":"41",
    "gn:admin2_code":"3409.0",
    "gn:asciiname":"Imarak",
    "gn:country_code":"AF",
    "gn:dem":2846,
    "gn:feature_class":"P",
    "gn:feature_code":"PPL",
    "gn:name":"Imarak",
    "gn:population":0,
    "gn:timezone":"Asia/Kabul",
    "iso:country":"AF",
    "name:und_x_variant":[
        "\u0627\u0645\u0631\u06a9",
        "Ema\u1e5fak"
    ],
    "wof:name":"Imarak",
    "wof:placetype":"locality"
},
  "geometry": {"coordinates":[66.40988,33.91888],"type":"Point"}
}