{
  "type": "Feature",
  "properties": {
    "gn:admin1_code":"1",
    "gn:admin2_code":"1115.0",
    "gn:asciiname":"'Ali Mangu",
    "gn:country_code":"AF",
    "gn:dem":2031,
    "gn:feature_class":"P",
    "gn:feature_code":"PPL",
    "gn:name":"\u2018Al\u012b Mang\u016b",
    "gn:population":0,
    "gn:timezone":"Asia/Kabul",
    "iso:country":"AF",
    "name:und_x_variant":[
        "\u2018Al\u012b Mang\u016b",
        "\u0639\u0644\u06cc \u0645\u0646\u06af\u0648"
    ],
    "wof:name":"'Ali Mangu",
    "wof:placetype":"locality"
},
  "geometry": {"coordinates":[70.46128,36.97759],"type":"Point"}
}