{
  "type": "Feature",
  "properties": {
    "gn:admin1_code":"23",
    "gn:admin2_code":"2411",
    "gn:asciiname":"Spin Boldak",
    "gn:country_code":"AF",
    "gn:dem":1218,
    "gn:feature_class":"P",
    "gn:feature_code":"PPLA2",
    "gn:name":"Sp\u012bn B\u014dldak",
    "gn:population":0,
    "gn:timezone":"Asia/Kabul",
    "iso:country":"AF",
    "name:und_x_variant":[
        "Sp\u012bn Baldak",
        "Sp\u012bn B\u016bldak",
        "Sp\u012bn B\u014dldak",
        "\u0633\u067e\u06cc\u0646 \u0628\u0648\u0644\u062f\u06a9"
    ],
    "wof:name":"Spin Boldak",
    "wof:placetype":"locality"
},
  "geometry": {"coordinates":[66.40000999999999,31.00575],"type":"Point"}
}