{
  "type": "Feature",
  "properties": {
    "gn:admin1_code":"37",
    "gn:admin2_code":"3203",
    "gn:asciiname":"Lalmay",
    "gn:country_code":"AF",
    "gn:dem":1292,
    "gn:feature_class":"P",
    "gn:feature_code":"PPL",
    "gn:name":"Lalmay",
    "gn:population":0,
    "gn:timezone":"Asia/Kabul",
    "iso:country":"AF",
    "name:fas_x_preferred":[
        "\u0644\u0644\u0645\u06cc"
    ],
    "name:rus_x_preferred":[
        "Lal\u2019may"
    ],
    "wof:name":"Lalmay",
    "wof:placetype":"locality"
},
  "geometry": {"coordinates":[69.82191,33.26479],"type":"Point"}
}