{
  "type": "Feature",
  "properties": {
    "gn:admin1_code":"23",
    "gn:admin2_code":"2411",
    "gn:asciiname":"Popalzai",
    "gn:country_code":"AF",
    "gn:dem":1285,
    "gn:feature_class":"P",
    "gn:feature_code":"PPL",
    "gn:name":"P\u014dpalza\u012b",
    "gn:population":0,
    "gn:timezone":"Asia/Kabul",
    "iso:country":"AF",
    "name:deu_x_preferred":[
        "Popalzai"
    ],
    "name:fas_x_preferred":[
        "\u067e\u0648\u067e\u0644\u200c\u0632\u0627\u06cc\u06cc"
    ],
    "name:nld_x_preferred":[
        "Popalzai"
    ],
    "name:pol_x_preferred":[
        "Popalzai"
    ],
    "name:pus_x_preferred":[
        "\u067e\u0648\u067e\u0644\u0632\u064a"
    ],
    "name:rus_x_preferred":[
        "Popal\u2019zay"
    ],
    "name:swe_x_preferred":[
        "Popalzai-klanen"
    ],
    "name:und_x_variant":[
        "P\u014dpalza\u2019i",
        "P\u014dpalza\u012b",
        "\u067e\u0648\u067e\u0644\u0632\u06cc",
        "P\u016bpalzay",
        "Popal\u2019zay"
    ],
    "wof:name":"Popalzai",
    "wof:placetype":"locality"
},
  "geometry": {"coordinates":[66.47851,31.0745],"type":"Point"}
}