{
  "type": "Feature",
  "properties": {
    "gn:admin1_code":"01",
    "gn:admin2_code":"1112",
    "gn:asciiname":"Rah-e Darah",
    "gn:country_code":"AF",
    "gn:dem":2733,
    "gn:feature_class":"P",
    "gn:feature_code":"PPL",
    "gn:name":"R\u0101h-e Darah",
    "gn:population":0,
    "gn:timezone":"Asia/Kabul",
    "iso:country":"AF",
    "name:und_x_variant":[
        "\u1e5e\u0101y \u1e0ea\u1e5f\u1e5fah",
        "R\u0101y Darreh",
        "R\u0101h-e Darah",
        "\u0631\u0627\u0647 \u062f\u0631\u0647"
    ],
    "wof:name":"Rah-e Darah",
    "wof:placetype":"locality"
},
  "geometry": {"coordinates":[70.46831,37.70289],"type":"Point"}
}