{
  "type": "Feature",
  "properties": {
    "gn:admin1_code":"08",
    "gn:admin2_code":"604.0",
    "gn:asciiname":"Ghowch",
    "gn:country_code":"AF",
    "gn:dem":3036,
    "gn:feature_class":"P",
    "gn:feature_code":"PPL",
    "gn:name":"Ghowch",
    "gn:population":0,
    "gn:timezone":"Asia/Kabul",
    "iso:country":"AF",
    "name:und_x_variant":[
        "Ghaw\u010d",
        "Ghawch",
        "Ghowch",
        "\u063a\u0648\u0686"
    ],
    "wof:name":"Ghowch",
    "wof:placetype":"locality"
},
  "geometry": {"coordinates":[67.4992,34.02656],"type":"Point"}
}