{
  "type": "Feature",
  "properties": {
    "gn:admin1_code":"01",
    "gn:admin2_code":"1126.0",
    "gn:asciiname":"Sipak",
    "gn:country_code":"AF",
    "gn:dem":1410,
    "gn:feature_class":"P",
    "gn:feature_code":"PPL",
    "gn:name":"Sip\u0101k",
    "gn:population":0,
    "gn:timezone":"Asia/Kabul",
    "iso:country":"AF",
    "name:und_x_variant":[
        "Sip\u0101k",
        "\u0633\u067e\u0627\u06a9",
        "Sep\u0101k"
    ],
    "wof:name":"Sipak",
    "wof:placetype":"locality"
},
  "geometry": {"coordinates":[70.35066999999999,37.30258],"type":"Point"}
}