{
  "type": "Feature",
  "properties": {
    "gn:admin1_code":"11",
    "gn:admin2_code":"2006.0",
    "gn:asciiname":"Khalifah Rahmat",
    "gn:country_code":"AF",
    "gn:dem":1270,
    "gn:feature_class":"P",
    "gn:feature_code":"PPL",
    "gn:name":"Khal\u012bfah Ra\u1e29mat",
    "gn:population":0,
    "gn:timezone":"Asia/Kabul",
    "iso:country":"AF",
    "name:und_x_variant":[
        "Khalifarakhmat",
        "Khalifa \u1e5ea\u1e29mat",
        "Khal\u012bfah Ra\u1e29mat",
        "\u062e\u0644\u06cc\u0641\u0647 \u0631\u062d\u0645\u062a",
        "Khal\u012bfeh Ra\u1e29mat"
    ],
    "wof:name":"Khalifah Rahmat",
    "wof:placetype":"locality"
},
  "geometry": {"coordinates":[62.28744,34.78641],"type":"Point"}
}