{
  "type": "Feature",
  "properties": {
    "gn:admin1_code":"03",
    "gn:admin2_code":"1310.0",
    "gn:asciiname":"Shash Kal",
    "gn:country_code":"AF",
    "gn:dem":1174,
    "gn:feature_class":"P",
    "gn:feature_code":"PPL",
    "gn:name":"Shash Kal",
    "gn:population":0,
    "gn:timezone":"Asia/Kabul",
    "iso:country":"AF",
    "name:und_x_variant":[
        "\u0634\u0634 \u06a9\u0644"
    ],
    "wof:name":"Shash Kal",
    "wof:placetype":"locality"
},
  "geometry": {"coordinates":[69.14045,36.22405],"type":"Point"}
}