{
  "type": "Feature",
  "properties": {
    "gn:admin1_code":"1",
    "gn:admin2_code":"1113.0",
    "gn:asciiname":"Chowgani",
    "gn:country_code":"AF",
    "gn:dem":1992,
    "gn:feature_class":"P",
    "gn:feature_code":"PPL",
    "gn:name":"Chowg\u0101n\u012b",
    "gn:population":0,
    "gn:timezone":"Asia/Kabul",
    "iso:country":"AF",
    "name:und_x_variant":[
        "Cawg\u0101ni",
        "Chowg\u0101n\u012b",
        "\u0686\u0648\u06af\u0627\u0646\u06cc"
    ],
    "wof:name":"Chowgani",
    "wof:placetype":"locality"
},
  "geometry": {"coordinates":[70.13724999999999,37.41184000000001],"type":"Point"}
}