{
  "type": "Feature",
  "properties": {
    "gn:admin1_code":"13",
    "gn:admin2_code":"108.0",
    "gn:asciiname":"Qal'ah-ye Atam",
    "gn:country_code":"AF",
    "gn:dem":2246,
    "gn:feature_class":"P",
    "gn:feature_code":"PPL",
    "gn:name":"Qal\u2018ah-ye Atam",
    "gn:population":0,
    "gn:timezone":"Asia/Kabul",
    "iso:country":"AF",
    "name:und_x_variant":[
        "Kalaatam",
        "Qal\u2018a Atam",
        "Qal\u2018eh-ye Atam",
        "Qal\u2018ah-ye Atam",
        "\u0642\u0644\u0639\u0647 \u0627\u062a\u0645"
    ],
    "wof:name":"Qal'ah-ye Atam",
    "wof:placetype":"locality"
},
  "geometry": {"coordinates":[68.93675,34.55654000000001],"type":"Point"}
}