{
  "type": "Feature",
  "properties": {
    "gn:admin1_code":"14",
    "gn:admin2_code":"204.0",
    "gn:asciiname":"Koras",
    "gn:country_code":"AF",
    "gn:dem":2488,
    "gn:feature_class":"P",
    "gn:feature_code":"PPL",
    "gn:name":"K\u014dras",
    "gn:population":0,
    "gn:timezone":"Asia/Kabul",
    "iso:country":"AF",
    "name:rus_x_preferred":[
        "\u041a\u043e\u0440\u0430\u0441"
    ],
    "name:und_x_variant":[
        "K\u014d\u1e5fas",
        "Kowras",
        "K\u014dras",
        "\u06a9\u0648\u0631\u0633"
    ],
    "wof:name":"Koras",
    "wof:placetype":"locality"
},
  "geometry": {"coordinates":[69.66863000000001,35.11189],"type":"Point"}
}