{
  "type": "Feature",
  "properties": {
    "gn:admin1_code":"11",
    "gn:admin2_code":"2001.0",
    "gn:asciiname":"Yakah Khanah",
    "gn:country_code":"AF",
    "gn:dem":874,
    "gn:feature_class":"P",
    "gn:feature_code":"PPL",
    "gn:name":"Yakah Kh\u0101nah",
    "gn:population":0,
    "gn:timezone":"Asia/Kabul",
    "iso:country":"AF",
    "name:und_x_variant":[
        "Yaka Kh\u0101na",
        "Yekkeh Kh\u0101neh",
        "Yakah Kh\u0101nah",
        "\u06cc\u06a9\u0647 \u062e\u0627\u0646\u0647"
    ],
    "wof:name":"Yakah Khanah",
    "wof:placetype":"locality"
},
  "geometry": {"coordinates":[61.98319,34.36523],"type":"Point"}
}