{
  "type": "Feature",
  "properties": {
    "gn:admin1_code":"06",
    "gn:admin2_code":"2105",
    "gn:asciiname":"Suji-ye Gharbi",
    "gn:country_code":"AF",
    "gn:dem":759,
    "gn:feature_class":"P",
    "gn:feature_code":"PPL",
    "gn:name":"S\u016bj\u012b-ye Gharb\u012b",
    "gn:population":0,
    "gn:timezone":"Asia/Kabul",
    "iso:country":"AF",
    "name:und_x_variant":[
        "Sudzhi-Garbi",
        "S\u016bj\u012b Gha\u1e5fbi",
        "S\u016bj\u012b-ye Gharb\u012b",
        "\u0633\u0648\u062c\u06cc \u063a\u0631\u0628\u06cc"
    ],
    "wof:name":"Suji-ye Gharbi",
    "wof:placetype":"locality"
},
  "geometry": {"coordinates":[62.48976,32.67846],"type":"Point"}
}