{
  "type": "Feature",
  "properties": {
    "gn:admin1_code":"34",
    "gn:admin2_code":"1014.0",
    "gn:asciiname":"Shamkar",
    "gn:country_code":"AF",
    "gn:dem":725,
    "gn:feature_class":"P",
    "gn:feature_code":"PPL",
    "gn:name":"Sh\u0101mk\u0101r",
    "gn:population":0,
    "gn:timezone":"Asia/Kabul",
    "iso:country":"AF",
    "name:fas_x_preferred":[
        "\u0634\u0627\u0645\u0643\u0627\u0631"
    ],
    "name:und_x_variant":[
        "\u0160\u0101mk\u0101r",
        "Shamkar",
        "Sh\u0101mk\u0101r",
        "\u0634\u0627\u0645\u06a9\u0627\u0631"
    ],
    "wof:name":"Shamkar",
    "wof:placetype":"locality"
},
  "geometry": {"coordinates":[70.95484999999999,34.68886],"type":"Point"}
}