{
  "type": "Feature",
  "properties": {
    "gn:admin1_code":"23",
    "gn:admin2_code":"2415",
    "gn:asciiname":"`Alaqadari Nes",
    "gn:country_code":"AF",
    "gn:dem":1489,
    "gn:feature_class":"P",
    "gn:feature_code":"PPL",
    "gn:name":"`Al\u0101qad\u0101r\u012b N\u0113\u0161",
    "gn:population":0,
    "gn:timezone":"Asia/Kabul",
    "iso:country":"AF",
    "name:fas_x_preferred":[
        "\u0646\u064a\u0634"
    ],
    "name:pus_x_preferred":[
        "N\u012bsh"
    ],
    "name:und_x_variant":[
        "N\u0113\u0161",
        "\u2018Al\u0101qad\u0101r\u012b N\u0113\u0161",
        "\u2018Al\u0101qahd\u0101r\u012b Naysh",
        "\u0639\u0644\u0627\u0642\u0647 \u062f\u0627\u0631\u06cc \u0646\u06cc\u0634"
    ],
    "wof:name":"`Alaqadari Nes",
    "wof:placetype":"locality"
},
  "geometry": {"coordinates":[65.63706999999999,32.42688],"type":"Point"}
}