{
  "type": "Feature",
  "properties": {
    "gn:admin1_code":"29",
    "gn:admin2_code":"2911.0",
    "gn:asciiname":"Balay Kelay",
    "gn:country_code":"AF",
    "gn:dem":2400,
    "gn:feature_class":"P",
    "gn:feature_code":"PPL",
    "gn:name":"Balay K\u00ealay",
    "gn:population":0,
    "gn:timezone":"Asia/Kabul",
    "iso:country":"AF",
    "name:fas_x_preferred":[
        "\u0642\u0631\u064a\u06c0 \u0628\u0644\u06cc"
    ],
    "name:und_x_variant":[
        "Balaykalay",
        "Balay K\u00ealay",
        "Balay Kalay",
        "\u0628\u0644\u06cc \u06a9\u0644\u06cc"
    ],
    "wof:name":"Balay Kelay",
    "wof:placetype":"locality"
},
  "geometry": {"coordinates":[69.22914,33.06303],"type":"Point"}
}