{
  "type": "Feature",
  "properties": {
    "gn:admin1_code":"34",
    "gn:admin2_code":"1014",
    "gn:asciiname":"Hazar Naw",
    "gn:country_code":"AF",
    "gn:dem":1242,
    "gn:feature_class":"P",
    "gn:feature_code":"PPL",
    "gn:name":"Haz\u0101r N\u0101w",
    "gn:population":0,
    "gn:timezone":"Asia/Kabul",
    "iso:country":"AF",
    "name:fas_x_preferred":[
        "\u0647\u0632\u0627\u0631 \u0646\u0648"
    ],
    "name:und_x_variant":[
        "Khazarnav",
        "Haz\u0101\u1e5fn\u0101w",
        "Haz\u0101rn\u0101v",
        "Haz\u0101r Now",
        "\u0647\u0632\u0627\u0631 \u0646\u0648",
        "Haz\u0101r N\u0101w",
        "\u0647\u0632\u0627\u0631 \u0646\u0627\u0648"
    ],
    "wof:name":"Hazar Naw",
    "wof:placetype":"locality"
},
  "geometry": {"coordinates":[71.07077,34.63847],"type":"Point"}
}