{
  "type": "Feature",
  "properties": {
    "gn:admin1_code":"29",
    "gn:admin2_code":"2905",
    "gn:asciiname":"Khatak",
    "gn:country_code":"AF",
    "gn:dem":2034,
    "gn:feature_class":"P",
    "gn:feature_code":"PPL",
    "gn:name":"Kha\u1e6fak",
    "gn:population":0,
    "gn:timezone":"Asia/Kabul",
    "iso:country":"AF",
    "name:fas_x_preferred":[
        "\u062e\u062a\u0643"
    ],
    "name:und_x_variant":[
        "\u062e\u067c\u06a9",
        "Khatak",
        "Kha\u1e6fak"
    ],
    "wof:name":"Khatak",
    "wof:placetype":"locality"
},
  "geometry": {"coordinates":[68.79661,32.03865],"type":"Point"}
}