{
  "type": "Feature",
  "properties": {
    "gn:admin1_code":"27",
    "gn:admin2_code":"406.0",
    "gn:asciiname":"Afzal Khel",
    "gn:country_code":"AF",
    "gn:dem":2252,
    "gn:feature_class":"P",
    "gn:feature_code":"PPL",
    "gn:name":"Af\u1e95al Kh\u0113l",
    "gn:population":0,
    "gn:timezone":"Asia/Kabul",
    "iso:country":"AF",
    "name:rus_x_preferred":[
        "Afzal\u2019kheyl\u2019"
    ],
    "name:und_x_variant":[
        "Af\u1e0f\u1e95alkh\u0113l",
        "Af\u1e95al Kh\u0113l",
        "Af\u1e95alkheyl",
        "\u0627\u0641\u0636\u0644 \u062e\u06d0\u0644"
    ],
    "wof:name":"Afzal Khel",
    "wof:placetype":"locality"
},
  "geometry": {"coordinates":[68.50828,34.11311],"type":"Point"}
}