{
  "type": "Feature",
  "properties": {
    "gn:admin1_code":"18",
    "gn:admin2_code":"810.0",
    "gn:asciiname":"Kamkai Kelay",
    "gn:country_code":"AF",
    "gn:dem":1200,
    "gn:feature_class":"P",
    "gn:feature_code":"PPL",
    "gn:name":"Kamka\u012b K\u00ealay",
    "gn:population":0,
    "gn:timezone":"Asia/Kabul",
    "iso:country":"AF",
    "name:fas_x_preferred":[
        "\u0642\u0631\u064a\u06c0 \u062e\u0648\u0631\u062f"
    ],
    "name:und_x_variant":[
        "Kamlaykalay",
        "Kamkay Kalay",
        "Kamka\u012b K\u00ealay",
        "\u06a9\u0645\u06a9\u06cc \u06a9\u0644\u06cc"
    ],
    "wof:name":"Kamkai Kelay",
    "wof:placetype":"locality"
},
  "geometry": {"coordinates":[70.66656999999999,34.10004],"type":"Point"}
}