{
  "type": "Feature",
  "properties": {
    "gn:admin1_code":"30",
    "gn:admin2_code":"1606",
    "gn:asciiname":"Siyah Qanduq",
    "gn:country_code":"AF",
    "gn:dem":359,
    "gn:feature_class":"P",
    "gn:feature_code":"PPL",
    "gn:name":"Siy\u0101h Qanduq",
    "gn:population":0,
    "gn:timezone":"Asia/Kabul",
    "iso:country":"AF",
    "name:fas_x_preferred":[
        "\u0633\u064a\u0627\u0647 \u0642\u0646\u062f\u0648\u0642"
    ],
    "name:rus_x_preferred":[
        "\u0421\u0438\u0430\u0445\u043a\u0430\u043d\u0434\u0443\u043a"
    ],
    "name:und_x_variant":[
        "Siakhkanduk",
        "S\u012b\u0101h Qanduq",
        "\u0633\u06cc\u0627\u0647 \u0642\u0646\u062f\u0642",
        "Siy\u0101h Qanduq"
    ],
    "wof:name":"Siyah Qanduq",
    "wof:placetype":"locality"
},
  "geometry": {"coordinates":[66.91983,36.72518],"type":"Point"}
}