{
  "type": "Feature",
  "properties": {
    "gn:admin1_code":"11",
    "gn:admin2_code":"2004",
    "gn:asciiname":"Qal'ah-ye Dasht",
    "gn:country_code":"AF",
    "gn:dem":1205,
    "gn:feature_class":"P",
    "gn:feature_code":"PPL",
    "gn:name":"Qal\u2018ah-ye Dasht",
    "gn:population":0,
    "gn:timezone":"Asia/Kabul",
    "iso:country":"AF",
    "name:und_x_variant":[
        "Qal\u2018a-i-Da\u0161t",
        "Kalayi-Dasht",
        "Qal\u2018eh-ye Dasht",
        "Qal\u2018ah-ye Dasht",
        "\u0642\u0644\u0639\u06c0 \u062f\u0634\u062a"
    ],
    "wof:name":"Qal'ah-ye Dasht",
    "wof:placetype":"locality"
},
  "geometry": {"coordinates":[62.95099,34.24121],"type":"Point"}
}