{
  "type": "Feature",
  "properties": {
    "gn:admin1_code":"8",
    "gn:admin2_code":"614.0",
    "gn:asciiname":"Mulla Salim Kelay",
    "gn:country_code":"AF",
    "gn:dem":2099,
    "gn:feature_class":"P",
    "gn:feature_code":"PPL",
    "gn:name":"Mull\u0101 Sal\u012bm K\u00ealay",
    "gn:population":0,
    "gn:timezone":"Asia/Kabul",
    "iso:country":"AF",
    "name:fas_x_preferred":[
        "\u0642\u0631\u064a\u06c0 \u0645\u0644\u0627 \u0633\u0644\u064a\u0645"
    ],
    "name:und_x_variant":[
        "Mull\u0101 Sal\u012bm Kalay",
        "Mulla-Salim-Kalay",
        "Mull\u0101 Sal\u012bm K\u00ealay",
        "Moll\u0101 Sal\u012bm Kalay",
        "\u0645\u0644\u0627 \u0633\u0644\u064a\u0645 \u06a9\u0644\u06cc"
    ],
    "wof:name":"Mulla Salim Kelay",
    "wof:placetype":"locality"
},
  "geometry": {"coordinates":[68.48298,33.39209],"type":"Point"}
}