{
  "type": "Feature",
  "properties": {
    "gn:admin1_code":"7",
    "gn:admin2_code":"1811.0",
    "gn:asciiname":"Bai Khan",
    "gn:country_code":"AF",
    "gn:dem":260,
    "gn:feature_class":"P",
    "gn:feature_code":"PPL",
    "gn:name":"Bai Kh\u0101n",
    "gn:population":0,
    "gn:timezone":"Asia/Kabul",
    "iso:country":"AF",
    "wof:name":"Bai Khan",
    "wof:placetype":"locality"
},
  "geometry": {"coordinates":[65.38333,37.21667],"type":"Point"}
}