{
  "type": "Feature",
  "properties": {
    "gn:admin1_code":"11",
    "gn:admin2_code":"2016",
    "gn:asciiname":"Kham-e Sabz",
    "gn:country_code":"AF",
    "gn:dem":1142,
    "gn:feature_class":"P",
    "gn:feature_code":"PPL",
    "gn:name":"Kham-e Sabz",
    "gn:population":0,
    "gn:timezone":"Asia/Kabul",
    "iso:country":"AF",
    "name:und_x_variant":[
        "Kham-i-Sabz",
        "Kham-e Sabz",
        "\u062e\u0645 \u0633\u0628\u0632"
    ],
    "wof:name":"Kham-e Sabz",
    "wof:placetype":"locality"
},
  "geometry": {"coordinates":[62.58564000000001,34.82134],"type":"Point"}
}