{
  "type": "Feature",
  "properties": {
    "gn:admin1_code":"10",
    "gn:admin2_code":"2304",
    "gn:asciiname":"Gurjat",
    "gn:country_code":"AF",
    "gn:dem":1017,
    "gn:feature_class":"P",
    "gn:feature_code":"PPL",
    "gn:name":"Gurjat",
    "gn:population":0,
    "gn:timezone":"Asia/Kabul",
    "iso:country":"AF",
    "name:und_x_variant":[
        "Gurdzhak",
        "Gurjat",
        "\u06af\u0631\u062c\u062a",
        "Gu\u1e5fjat"
    ],
    "wof:name":"Gurjat",
    "wof:placetype":"locality"
},
  "geometry": {"coordinates":[64.71185,32.24975],"type":"Point"}
}