{
  "type": "Feature",
  "properties": {
    "gn:admin1_code":"09",
    "gn:admin2_code":"2705",
    "gn:asciiname":"Larghah",
    "gn:country_code":"AF",
    "gn:dem":2286,
    "gn:feature_class":"P",
    "gn:feature_code":"PPL",
    "gn:name":"L\u0101rghah",
    "gn:population":0,
    "gn:timezone":"Asia/Kabul",
    "iso:country":"AF",
    "name:und_x_variant":[
        "L\u0101\u1e5fgha",
        "Larga",
        "L\u0101rghah",
        "\u0644\u0627\u0631\u063a\u0647",
        "L\u0101rgheh"
    ],
    "wof:name":"Larghah",
    "wof:placetype":"locality"
},
  "geometry": {"coordinates":[64.14570000000001,33.5715],"type":"Point"}
}