{
  "type": "Feature",
  "properties": {
    "gn:admin1_code":"41",
    "gn:admin2_code":"3403.0",
    "gn:asciiname":"Surkh Joy",
    "gn:country_code":"AF",
    "gn:dem":2133,
    "gn:feature_class":"P",
    "gn:feature_code":"PPL",
    "gn:name":"Surkh J\u014dy",
    "gn:population":0,
    "gn:timezone":"Asia/Kabul",
    "iso:country":"AF",
    "name:und_x_variant":[
        "Surkhdzhoy",
        "Su\u1e5fkhj\u014dy",
        "Surkh J\u014dy",
        "Sorkhj\u016by",
        "\u0633\u0631\u062e \u062c\u0648\u06cc"
    ],
    "wof:name":"Surkh Joy",
    "wof:placetype":"locality"
},
  "geometry": {"coordinates":[66.29316,34.03536],"type":"Point"}
}