{
  "type": "Feature",
  "properties": {
    "gn:admin1_code":"5",
    "gn:admin2_code":"2802.0",
    "gn:asciiname":"Sokhtah",
    "gn:country_code":"AF",
    "gn:dem":2804,
    "gn:feature_class":"P",
    "gn:feature_code":"PPL",
    "gn:name":"S\u014dkhtah",
    "gn:population":0,
    "gn:timezone":"Asia/Kabul",
    "iso:country":"AF",
    "name:und_x_variant":[
        "Sokhta",
        "S\u014dkhta",
        "S\u014dkhtah",
        "S\u016bkhteh",
        "\u0633\u0648\u062e\u062a\u0647"
    ],
    "wof:name":"Sokhtah",
    "wof:placetype":"locality"
},
  "geometry": {"coordinates":[67.85977,34.9877],"type":"Point"}
}