{
  "type": "Feature",
  "properties": {
    "gn:admin1_code":"06",
    "gn:admin2_code":"2105",
    "gn:asciiname":"Dowlatabad",
    "gn:country_code":"AF",
    "gn:dem":816,
    "gn:feature_class":"P",
    "gn:feature_code":"PPL",
    "gn:name":"Dowlat\u0101b\u0101d",
    "gn:population":0,
    "gn:timezone":"Asia/Kabul",
    "iso:country":"AF",
    "name:aze_x_preferred":[
        "D\u00f6vl\u0259tabad"
    ],
    "name:ceb_x_preferred":[
        "Dowlatabad"
    ],
    "name:fas_x_preferred":[
        "\u062f\u0648\u0644\u062a\u200c\u0622\u0628\u0627\u062f"
    ],
    "name:swe_x_preferred":[
        "Dowlatabad"
    ],
    "name:und_x_variant":[
        "Daolatabad",
        "Doalatabad",
        "\u1e0eawlat\u0101b\u0101\u1e0f",
        "Daulat\u0101b\u0101d",
        "Daulatabad",
        "Dowlat\u0101b\u0101d",
        "\u062f\u0648\u0644\u062a \u0622\u0628\u0627\u062f",
        "Dowlat \u0100b\u0101d"
    ],
    "wof:name":"Dowlatabad",
    "wof:placetype":"locality"
},
  "geometry": {"coordinates":[62.67844,32.7935],"type":"Point"}
}