{
  "type": "Feature",
  "properties": {
    "gn:admin1_code":"03",
    "gn:admin2_code":"1312.0",
    "gn:asciiname":"Surkh-Paryaw",
    "gn:country_code":"AF",
    "gn:dem":2283,
    "gn:feature_class":"P",
    "gn:feature_code":"PPL",
    "gn:name":"Surkh-Pary\u0101w",
    "gn:population":0,
    "gn:timezone":"Asia/Kabul",
    "iso:country":"AF",
    "name:und_x_variant":[
        "Su\u1e5fkh-pa\u1e5fy\u0101w",
        "Sorkh Pary\u0101b",
        "Surkh-Pary\u0101w",
        "\u0633\u0631\u062e \u067e\u0631\u06cc\u0627\u0648"
    ],
    "wof:name":"Surkh-Paryaw",
    "wof:placetype":"locality"
},
  "geometry": {"coordinates":[69.40262,35.80723],"type":"Point"}
}