{
  "type": "Feature",
  "properties": {
    "gn:admin1_code":"18",
    "gn:admin2_code":"818.0",
    "gn:asciiname":"Kandahari",
    "gn:country_code":"AF",
    "gn:dem":540,
    "gn:feature_class":"P",
    "gn:feature_code":"PPL",
    "gn:name":"Kandah\u0101r\u012b",
    "gn:population":0,
    "gn:timezone":"Asia/Kabul",
    "iso:country":"AF",
    "name:fas_x_preferred":[
        "\u0643\u0646\u062f\u0647\u0627\u0631\u06cc"
    ],
    "name:und_x_variant":[
        "Kandakhari",
        "Kandah\u0101r\u012b"
    ],
    "wof:name":"Kandahari",
    "wof:placetype":"locality"
},
  "geometry": {"coordinates":[70.59384,34.41585],"type":"Point"}
}