{
  "type": "Feature",
  "properties": {
    "gn:admin1_code":"40",
    "gn:admin2_code":"306",
    "gn:asciiname":"Tangi Bala",
    "gn:country_code":"AF",
    "gn:dem":2637,
    "gn:feature_class":"P",
    "gn:feature_code":"PPL",
    "gn:name":"Tang\u012b B\u0101l\u0101",
    "gn:population":0,
    "gn:timezone":"Asia/Kabul",
    "iso:country":"AF",
    "name:und_x_variant":[
        "Tangi-Bala",
        "Tang",
        "Tang\u012b B\u0101l\u0101",
        "\u062a\u0646\u06af\u06cc \u0628\u0627\u0644\u0627"
    ],
    "wof:name":"Tangi Bala",
    "wof:placetype":"locality"
},
  "geometry": {"coordinates":[68.29589,34.90037],"type":"Point"}
}