{
  "type": "Feature",
  "properties": {
    "gn:admin1_code":"08",
    "gn:admin2_code":"604",
    "gn:asciiname":"Tukrang",
    "gn:country_code":"AF",
    "gn:dem":3134,
    "gn:feature_class":"P",
    "gn:feature_code":"PPL",
    "gn:name":"T\u016bkrang",
    "gn:population":0,
    "gn:timezone":"Asia/Kabul",
    "iso:country":"AF",
    "name:und_x_variant":[
        "T\u016bk\u1e5fang",
        "Tukrang",
        "Towkrang",
        "T\u016bkrang",
        "\u062a\u0648\u06a9\u0631\u0646\u06af"
    ],
    "wof:name":"Tukrang",
    "wof:placetype":"locality"
},
  "geometry": {"coordinates":[67.64497,34.10236],"type":"Point"}
}