{
  "type": "Feature",
  "properties": {
    "gn:admin1_code":"10",
    "gn:admin2_code":"2306",
    "gn:asciiname":"Qaryah-ye Darband",
    "gn:country_code":"AF",
    "gn:dem":1704,
    "gn:feature_class":"P",
    "gn:feature_code":"PPL",
    "gn:name":"Qaryah-ye Darband",
    "gn:population":0,
    "gn:timezone":"Asia/Kabul",
    "iso:country":"AF",
    "name:rus_x_preferred":[
        "Kar\u2019yayi-Darband"
    ],
    "name:und_x_variant":[
        "Qa\u1e5fya-i-\u1e0ea\u1e5fban\u1e0f",
        "Qaryah-ye Darband",
        "\u0642\u0631\u06cc\u0647 \u062f\u0631\u0628\u0646\u062f",
        "Qaryeh-ye Darband"
    ],
    "wof:name":"Qaryah-ye Darband",
    "wof:placetype":"locality"
},
  "geometry": {"coordinates":[64.19134,32.44730999999999],"type":"Point"}
}