{
  "type": "Feature",
  "properties": {
    "gn:admin1_code":"19",
    "gn:admin2_code":"2202.0",
    "gn:asciiname":"Mingal",
    "gn:country_code":"AF",
    "gn:dem":478,
    "gn:feature_class":"P",
    "gn:feature_code":"PPL",
    "gn:name":"M\u012bngal",
    "gn:population":0,
    "gn:timezone":"Asia/Kabul",
    "iso:country":"AF",
    "wof:name":"Mingal",
    "wof:placetype":"locality"
},
  "geometry": {"coordinates":[61.84591,31.18006],"type":"Point"}
}