{
  "type": "Feature",
  "properties": {
    "gn:admin1_code":"06",
    "gn:admin2_code":"2103",
    "gn:asciiname":"Ghoziney",
    "gn:country_code":"AF",
    "gn:dem":1310,
    "gn:feature_class":"P",
    "gn:feature_code":"PPL",
    "gn:name":"Gh\u014dzin\u00eay",
    "gn:population":0,
    "gn:timezone":"Asia/Kabul",
    "iso:country":"AF",
    "name:und_x_variant":[
        "Gh\u014dz\u012bney",
        "Gh\u014dzin\u00eay",
        "\u063a\u0648\u0632\u0646\u06cd",
        "Ghowz\u012bney"
    ],
    "wof:name":"Ghoziney",
    "wof:placetype":"locality"
},
  "geometry": {"coordinates":[63.61952,32.56045],"type":"Point"}
}