{
  "type": "Feature",
  "properties": {
    "gn:admin1_code":"18",
    "gn:admin2_code":"805.0",
    "gn:asciiname":"Qadir Khan Bandah",
    "gn:country_code":"AF",
    "gn:dem":1263,
    "gn:feature_class":"P",
    "gn:feature_code":"PPL",
    "gn:name":"Q\u0101dir Kh\u0101n B\u0101n\u1e0fah",
    "gn:population":0,
    "gn:timezone":"Asia/Kabul",
    "iso:country":"AF",
    "name:fas_x_preferred":[
        "\u0642\u0627\u062f\u0631\u062e\u0627\u0646 \u0628\u0627\u0646\u062f\u0647"
    ],
    "name:und_x_variant":[
        "Kadirkhanbanda",
        "Q\u0101derkh\u0101n B\u0101ndeh",
        "Q\u0101dir Kh\u0101n B\u0101n\u1e0fah",
        "\u0642\u0627\u062f\u0631 \u062e\u0627\u0646 \u0628\u0627\u0646\u0689\u0647",
        "Q\u0101dir Kh\u0113l B\u0101n\u1e0fah",
        "\u0642\u0627\u062f\u0631 \u062e\u06d0\u0644 \u0628\u0627\u0646\u0689\u0647"
    ],
    "wof:name":"Qadir Khan Bandah",
    "wof:placetype":"locality"
},
  "geometry": {"coordinates":[70.20255,34.24733],"type":"Point"}
}