{
  "type": "Feature",
  "properties": {
    "gn:admin1_code":"28",
    "gn:admin2_code":"2505",
    "gn:asciiname":"Korghan",
    "gn:country_code":"AF",
    "gn:dem":1676,
    "gn:feature_class":"P",
    "gn:feature_code":"PPL",
    "gn:name":"K\u014drgh\u0101n",
    "gn:population":0,
    "gn:timezone":"Asia/Kabul",
    "iso:country":"AF",
    "name:und_x_variant":[
        "Korgan",
        "K\u014d\u1e5fgh\u0101n",
        "K\u014drgh\u0101n",
        "\u06a9\u0648\u0631\u063a\u0627\u0646",
        "K\u016brgh\u0101n"
    ],
    "wof:name":"Korghan",
    "wof:placetype":"locality"
},
  "geometry": {"coordinates":[66.48376,32.32339],"type":"Point"}
}