{
  "type": "Feature",
  "properties": {
    "gn:admin1_code":"11",
    "gn:admin2_code":"2014",
    "gn:asciiname":"Qal'ah-ye Nurullah Khan",
    "gn:country_code":"AF",
    "gn:dem":1242,
    "gn:feature_class":"P",
    "gn:feature_code":"PPL",
    "gn:name":"Qal\u2018ah-ye N\u016brull\u0101h Kh\u0101n",
    "gn:population":0,
    "gn:timezone":"Asia/Kabul",
    "iso:country":"AF",
    "name:fas_x_preferred":[
        "\u0642\u0644\u063a\u0647\u0654 \u0646\u0648\u0631\u0627\u0644\u0644\u0647 \u062e\u0627\u0646"
    ],
    "name:und_x_variant":[
        "Qal\u2018a-i-N\u016b\u1e5full\u0101h Kh\u0101n",
        "Qal\u2018eh-ye N\u016brull\u0101h Kh\u0101n",
        "My\u0101n R\u014di",
        "Kalayi-Nurullakhan",
        "My\u0101n \u1e5e\u014d\u1e0fi",
        "Mian-Rudi",
        "Qal\u2018eh-ye N\u016broll\u0101h Kh\u0101n",
        "Qal\u2018ah-ye N\u016brull\u0101h Kh\u0101n",
        "\u0642\u0644\u0639\u06c0 \u0646\u0648\u0631\u0627\u0644\u0644\u0647 \u062e\u0627\u0646",
        "M\u012b\u0101n R\u014dd\u012b",
        "\u0645\u06cc\u0627\u0646 \u0631\u0648\u062f\u06cc",
        "\u0642\u0644\u063a\u0647\u0654 \u0646\u0648\u0631\u0627\u0644\u0644\u0647 \u062e\u0627\u0646"
    ],
    "wof:name":"Qal'ah-ye Nurullah Khan",
    "wof:placetype":"locality"
},
  "geometry": {"coordinates":[62.44626,33.4463],"type":"Point"}
}