{
  "type": "Feature",
  "properties": {
    "gn:admin1_code":"07",
    "gn:admin2_code":"1804",
    "gn:asciiname":"Khwajah Kinti",
    "gn:country_code":"AF",
    "gn:dem":1218,
    "gn:feature_class":"P",
    "gn:feature_code":"PPL",
    "gn:name":"Khw\u0101jah Kint\u012b",
    "gn:population":0,
    "gn:timezone":"Asia/Kabul",
    "iso:country":"AF",
    "name:und_x_variant":[
        "M\u012brz\u0101 Mo\u1e29ammad \u2018Omar",
        "Khw\u0101ja Kinti",
        "Khwajah Kan\u012bt\u012b",
        "Khv\u0101jeh Kent\u012b",
        "Khw\u0101jah Kint\u012b",
        "\u062e\u0648\u0627\u062c\u0647 \u06a9\u0646\u062a\u06cc"
    ],
    "wof:name":"Khwajah Kinti",
    "wof:placetype":"locality"
},
  "geometry": {"coordinates":[64.02445,35.59593],"type":"Point"}
}