{
  "type": "Feature",
  "properties": {
    "gn:admin1_code":"34",
    "gn:admin2_code":"1005",
    "gn:asciiname":"Tarashpin Khune",
    "gn:country_code":"AF",
    "gn:dem":1065,
    "gn:feature_class":"P",
    "gn:feature_code":"PPL",
    "gn:name":"Tarashpin Kh\u016bn\u0113",
    "gn:population":0,
    "gn:timezone":"Asia/Kabul",
    "iso:country":"AF",
    "name:fas_x_preferred":[
        "\u062a\u0631\u0634\u067e\u0646 \u062e\u0648\u0646\u06cc"
    ],
    "name:und_x_variant":[
        "Tarashpenkhune",
        "Tara\u0161pen Kh\u016bn\u0113",
        "Tarashpen Kh\u016bn\u0113",
        "Tarashpin Kh\u016bn\u0113",
        "\u062a\u0631\u0634\u067e\u0646 \u062e\u0648\u0646\u06d0"
    ],
    "wof:name":"Tarashpin Khune",
    "wof:placetype":"locality"
},
  "geometry": {"coordinates":[71.5098,35.18965],"type":"Point"}
}