{
  "type": "Feature",
  "properties": {
    "gn:admin1_code":"23",
    "gn:admin2_code":"2414.0",
    "gn:asciiname":"Shah Joy",
    "gn:country_code":"AF",
    "gn:dem":2017,
    "gn:feature_class":"P",
    "gn:feature_code":"PPL",
    "gn:name":"Sh\u0101h J\u014dy",
    "gn:population":0,
    "gn:timezone":"Asia/Kabul",
    "iso:country":"AF",
    "name:und_x_variant":[
        "Shakhdzhoy",
        "\u0160\u0101hjoy",
        "Sh\u0101h J\u014dy",
        "\u0634\u0627\u0647 \u062c\u0648\u06cc",
        "Sh\u0101hj\u016by"
    ],
    "wof:name":"Shah Joy",
    "wof:placetype":"locality"
},
  "geometry": {"coordinates":[66.41443000000001,32.32423],"type":"Point"}
}