{
  "type": "Feature",
  "properties": {
    "gn:admin1_code":"01",
    "gn:admin2_code":"1122.0",
    "gn:asciiname":"Pejuj",
    "gn:country_code":"AF",
    "gn:dem":1835,
    "gn:feature_class":"P",
    "gn:feature_code":"PPL",
    "gn:name":"P\u0113j\u016bj",
    "gn:population":0,
    "gn:timezone":"Asia/Kabul",
    "iso:country":"AF",
    "name:und_x_variant":[
        "P\u0113j\u016bj",
        "\u067e\u06d0\u062c\u0648\u062c"
    ],
    "wof:name":"Pejuj",
    "wof:placetype":"locality"
},
  "geometry": {"coordinates":[71.00572,37.03902],"type":"Point"}
}