{
  "type": "Feature",
  "properties": {
    "gn:admin1_code":"10",
    "gn:admin2_code":"2302.0",
    "gn:asciiname":"Sur Gul Khan Kelay",
    "gn:country_code":"AF",
    "gn:dem":805,
    "gn:feature_class":"P",
    "gn:feature_code":"PPL",
    "gn:name":"S\u016br Gul Kh\u0101n K\u00ealay",
    "gn:population":0,
    "gn:timezone":"Asia/Kabul",
    "iso:country":"AF",
    "name:fas_x_preferred":[
        "\u0642\u0631\u064a\u0647\u0654 \u0633\u0648\u0631 \u06af\u0644 \u062e\u0627\u0646"
    ],
    "name:rus_x_preferred":[
        "Surgul\u2019khankalay"
    ],
    "name:und_x_variant":[
        "S\u016b\u1e5fgulkh\u0101n Kalay",
        "S\u016br Gul Kh\u0101n K\u00ealay",
        "\u0634\u0648\u0631 \u06af\u0644 \u062e\u0627\u0646 \u06a9\u0644\u06cc",
        "S\u016br Gol Kh\u0101n Kalay"
    ],
    "wof:name":"Sur Gul Khan Kelay",
    "wof:placetype":"locality"
},
  "geometry": {"coordinates":[64.3736,31.71656],"type":"Point"}
}