{
  "type": "Feature",
  "properties": {
    "gn:admin1_code":"28",
    "gn:admin2_code":"2502.0",
    "gn:asciiname":"Baghgay",
    "gn:country_code":"AF",
    "gn:dem":2092,
    "gn:feature_class":"P",
    "gn:feature_code":"PPL",
    "gn:name":"B\u0101ghgay",
    "gn:population":0,
    "gn:timezone":"Asia/Kabul",
    "iso:country":"AF",
    "name:und_x_variant":[
        "Bahghay",
        "Baggay",
        "B\u0101ghgay",
        "\u0628\u0627\u063a\u06af\u06cc"
    ],
    "wof:name":"Baghgay",
    "wof:placetype":"locality"
},
  "geometry": {"coordinates":[67.61341999999999,32.55585],"type":"Point"}
}