{
  "type": "Feature",
  "properties": {
    "gn:admin1_code":"5",
    "gn:admin2_code":"2806.0",
    "gn:asciiname":"Surkh Top",
    "gn:country_code":"AF",
    "gn:dem":2755,
    "gn:feature_class":"P",
    "gn:feature_code":"PPL",
    "gn:name":"Surkh T\u014dp",
    "gn:population":0,
    "gn:timezone":"Asia/Kabul",
    "iso:country":"AF",
    "name:und_x_variant":[
        "Surkhtop",
        "Su\u1e5fkht\u014dp",
        "Surkht\u014dp",
        "Surkh T\u014dp",
        "\u0633\u0631\u062e \u062a\u0648\u067e"
    ],
    "wof:name":"Surkh Top",
    "wof:placetype":"locality"
},
  "geometry": {"coordinates":[66.53657,34.23148],"type":"Point"}
}