{
  "type": "Feature",
  "properties": {
    "gn:admin1_code":"26",
    "gn:admin2_code":"1209.0",
    "gn:asciiname":"Chinar Darah",
    "gn:country_code":"AF",
    "gn:dem":717,
    "gn:feature_class":"P",
    "gn:feature_code":"PPL",
    "gn:name":"Chin\u0101r Darah",
    "gn:population":0,
    "gn:timezone":"Asia/Kabul",
    "iso:country":"AF",
    "name:und_x_variant":[
        "Cen\u0101\u1e5f \u1e0ea\u1e5f\u1e5fah",
        "Chen\u0101r Darreh",
        "Chin\u0101r Darah",
        "\u0686\u0646\u0627\u0631 \u062f\u0631\u0647"
    ],
    "wof:name":"Chinar Darah",
    "wof:placetype":"locality"
},
  "geometry": {"coordinates":[69.90784000000001,37.57625],"type":"Point"}
}