{
  "type": "Feature",
  "properties": {
    "gn:admin1_code":"5",
    "gn:admin2_code":"2802.0",
    "gn:asciiname":"Sar-e Kondeh",
    "gn:cc2":"AF",
    "gn:country_code":"AF",
    "gn:dem":2741,
    "gn:feature_class":"P",
    "gn:feature_code":"PPL",
    "gn:name":"Sar-e Kondeh",
    "gn:population":0,
    "gn:timezone":"Asia/Kabul",
    "iso:country":"AF",
    "name:und_x_variant":[
        "Sare Kundi",
        "Sar-e Kondeh"
    ],
    "wof:name":"Sar-e Kondeh",
    "wof:placetype":"locality"
},
  "geometry": {"coordinates":[67.93083,35.11111],"type":"Point"}
}