{
  "type": "Feature",
  "properties": {
    "gn:admin1_code":"14",
    "gn:admin2_code":"207.0",
    "gn:asciiname":"Qal'ah-ye Now",
    "gn:country_code":"AF",
    "gn:dem":1551,
    "gn:feature_class":"P",
    "gn:feature_code":"PPL",
    "gn:name":"Qal\u2018ah-ye Now",
    "gn:population":0,
    "gn:timezone":"Asia/Kabul",
    "iso:country":"AF",
    "name:fas_x_preferred":[
        "\u0642\u0644\u0639\u0647 \u0646\u0648"
    ],
    "name:und_x_variant":[
        "Kalayi-Nau",
        "Qal\u2018a Naw",
        "Qal\u2018eh Now",
        "Qal\u2018ah-ye Now",
        "\u0642\u0644\u0639\u06c0 \u0646\u0648"
    ],
    "wof:name":"Qal'ah-ye Now",
    "wof:placetype":"locality"
},
  "geometry": {"coordinates":[69.35904000000001,35.08899],"type":"Point"}
}