{
  "type": "Feature",
  "properties": {
    "gn:admin1_code":"05",
    "gn:admin2_code":"2806",
    "gn:asciiname":"Sar-e Warzang",
    "gn:country_code":"AF",
    "gn:dem":2776,
    "gn:feature_class":"P",
    "gn:feature_code":"PPL",
    "gn:name":"Sar-e Warzang",
    "gn:population":0,
    "gn:timezone":"Asia/Kabul",
    "iso:country":"AF",
    "name:und_x_variant":[
        "Sari-Varzang",
        "Sar-e Warzang",
        "\u0633\u0631 \u0648\u0631\u0632\u0646\u06af"
    ],
    "wof:name":"Sar-e Warzang",
    "wof:placetype":"locality"
},
  "geometry": {"coordinates":[67.19943000000001,34.00753],"type":"Point"}
}