{
  "type": "Feature",
  "properties": {
    "gn:admin1_code":"28",
    "gn:admin2_code":"2511",
    "gn:asciiname":"Khano Kor",
    "gn:country_code":"AF",
    "gn:dem":2002,
    "gn:feature_class":"P",
    "gn:feature_code":"PPL",
    "gn:name":"Kh\u0101n\u014d K\u014dr",
    "gn:population":0,
    "gn:timezone":"Asia/Kabul",
    "iso:country":"AF",
    "name:und_x_variant":[
        "Kh\u0101no K\u014d\u1e5f",
        "Khanukor",
        "Kh\u0101n\u014d K\u014dr",
        "\u062e\u0627\u0646\u0648 \u06a9\u0648\u0631",
        "Kh\u0101no K\u016br"
    ],
    "wof:name":"Khano Kor",
    "wof:placetype":"locality"
},
  "geometry": {"coordinates":[67.52504999999999,32.2655],"type":"Point"}
}