{
  "type": "Feature",
  "properties": {
    "gn:admin1_code":"08",
    "gn:admin2_code":"613",
    "gn:asciiname":"Junubi Na Khel",
    "gn:country_code":"AF",
    "gn:dem":2057,
    "gn:feature_class":"P",
    "gn:feature_code":"PPL",
    "gn:name":"Jun\u016bb\u012b N\u0101 Kh\u0113l",
    "gn:population":0,
    "gn:timezone":"Asia/Kabul",
    "iso:country":"AF",
    "name:fas_x_preferred":[
        "\u0646\u0627\u062e\u064a\u0644\u0654\u0654 \u062c\u0646\u0648\u0628\u06cc"
    ],
    "name:rus_x_preferred":[
        "Dzhanubi-Nakheyl\u2019"
    ],
    "name:und_x_variant":[
        "Jan\u016bb\u012b N\u0101kheyl",
        "Jan\u016bbi N\u0101kh\u0113l",
        "N\u0101kheyl-e Jon\u016bb\u012b",
        "Jun\u016bb\u012b N\u0101 Kh\u0113l",
        "\u062c\u0646\u0648\u0628\u06cc \u0646\u0627 \u062e\u06d0\u0644",
        "\u0646\u0627\u062e\u064a\u0644\u0654\u0654 \u062c\u0646\u0648\u0628\u06cc"
    ],
    "wof:name":"Junubi Na Khel",
    "wof:placetype":"locality"
},
  "geometry": {"coordinates":[68.11436999999999,33.11476],"type":"Point"}
}