{
  "type": "Feature",
  "properties": {
    "gn:admin1_code":"27",
    "gn:admin2_code":"405.0",
    "gn:asciiname":"Kala",
    "gn:country_code":"AF",
    "gn:dem":2357,
    "gn:feature_class":"P",
    "gn:feature_code":"PPL",
    "gn:name":"Kal\u0101",
    "gn:population":0,
    "gn:timezone":"Asia/Kabul",
    "iso:country":"AF",
    "name:und_x_variant":[
        "Kal\u0101",
        "\u06a9\u0644\u0627"
    ],
    "wof:name":"Kala",
    "wof:placetype":"locality"
},
  "geometry": {"coordinates":[68.47335,34.23654000000001],"type":"Point"}
}