{
  "type": "Feature",
  "properties": {
    "gn:admin1_code":"30",
    "gn:admin2_code":"1607.0",
    "gn:asciiname":"Chahar Bulaq",
    "gn:country_code":"AF",
    "gn:dem":331,
    "gn:feature_class":"P",
    "gn:feature_code":"PPL",
    "gn:name":"Chah\u0101r B\u016bl\u0101q",
    "gn:population":0,
    "gn:timezone":"Asia/Kabul",
    "iso:country":"AF",
    "name:por_x_preferred":[
        "Char Bulak"
    ],
    "name:rus_x_preferred":[
        "\u0427\u0430\u0440\u0431\u0443\u043b\u0430\u043a"
    ],
    "name:und_x_variant":[
        "Charbulak",
        "Ch\u0101r B\u016blak",
        "Chah\u0101r B\u016bl\u0101q",
        "Char B\u016bl\u0101q",
        "Chah\u0101r B\u016blak",
        "Char Bol\u0101gh",
        "\u0686\u0647\u0627\u0631 \u0628\u0648\u0644\u0627\u0642",
        "\u0686\u0627\u0631 \u0628\u0648\u0644\u06a9"
    ],
    "wof:name":"Chahar Bulaq",
    "wof:placetype":"locality"
},
  "geometry": {"coordinates":[66.7051,36.76744],"type":"Point"}
}