{
  "type": "Feature",
  "properties": {
    "gn:admin1_code":"40",
    "gn:admin2_code":"304",
    "gn:asciiname":"Kajakan-e 'Ulya",
    "gn:country_code":"AF",
    "gn:dem":1717,
    "gn:feature_class":"P",
    "gn:feature_code":"PPL",
    "gn:name":"Kajak\u0101n-e \u2018Uly\u0101",
    "gn:population":0,
    "gn:timezone":"Asia/Kabul",
    "iso:country":"AF",
    "name:fas_x_preferred":[
        "\u0643\u062c\u0643\u0627\u0646\u0654 \u0639\u0644\u06cc\u0627"
    ],
    "name:und_x_variant":[
        "Kajak\u0101ne \u2018Ulya",
        "Kadzhakani-Ulia",
        "Kajak\u0101n-e \u2018Oly\u0101",
        "Kajak\u0101n-e \u2018Uly\u0101",
        "\u06a9\u062c\u06a9\u0627\u0646 \u0639\u0644\u06cc\u0627"
    ],
    "wof:name":"Kajakan-e 'Ulya",
    "wof:placetype":"locality"
},
  "geometry": {"coordinates":[69.08207,35.05654000000001],"type":"Point"}
}