{
  "type": "Feature",
  "properties": {
    "gn:admin1_code":"11",
    "gn:admin2_code":"2014",
    "gn:asciiname":"Shakh Kaman Pa'in",
    "gn:country_code":"AF",
    "gn:dem":1150,
    "gn:feature_class":"P",
    "gn:feature_code":"PPL",
    "gn:name":"Sh\u0101kh Kam\u0101n P\u0101\u2018\u012bn",
    "gn:population":0,
    "gn:timezone":"Asia/Kabul",
    "iso:country":"AF",
    "name:und_x_variant":[
        "S\u0304akh Kam\u0101n P\u0101\u2018\u012bn",
        "Shakh Kam\u0101n P\u0101\u2018\u012bn",
        "\u0634\u0627\u062e \u06a9\u0645\u0627\u0646 \u067e\u0627\u0626\u06cc\u0646",
        "Sh\u0101kh Kam\u0101n P\u0101\u2018\u012bn"
    ],
    "wof:name":"Shakh Kaman Pa'in",
    "wof:placetype":"locality"
},
  "geometry": {"coordinates":[61.9635,33.36067],"type":"Point"}
}