{
  "type": "Feature",
  "properties": {
    "gn:admin1_code":"42",
    "gn:admin2_code":"3304",
    "gn:asciiname":"Shaniz",
    "gn:country_code":"AF",
    "gn:dem":2552,
    "gn:feature_class":"P",
    "gn:feature_code":"PPL",
    "gn:name":"Sh\u0101n\u012bz",
    "gn:population":0,
    "gn:timezone":"Asia/Kabul",
    "iso:country":"AF",
    "name:und_x_variant":[
        "\u0160\u0101niz",
        "Sh\u0101n\u012bz",
        "\u0634\u0627\u0646\u06cc\u0632"
    ],
    "wof:name":"Shaniz",
    "wof:placetype":"locality"
},
  "geometry": {"coordinates":[69.97349,35.60624],"type":"Point"}
}