{
  "type": "Feature",
  "properties": {
    "gn:admin1_code":"27",
    "gn:admin2_code":"404",
    "gn:asciiname":"Olyad",
    "gn:country_code":"AF",
    "gn:dem":3158,
    "gn:feature_class":"P",
    "gn:feature_code":"PPL",
    "gn:name":"\u014cly\u0101d",
    "gn:population":0,
    "gn:timezone":"Asia/Kabul",
    "iso:country":"AF",
    "name:fas_x_preferred":[
        "\u0648\u0644\u064a\u0627\u062f"
    ],
    "name:rus_x_preferred":[
        "Ol\u2019yad"
    ],
    "name:rus_x_variant":[
        "\u041e\u043b\u044c\u044f\u0434"
    ],
    "name:und_x_variant":[
        "\u014cly\u0101\u1e0f",
        "\u014cly\u0101d",
        "\u016aly\u0101d",
        "\u0648\u0644\u064a\u0627\u062f",
        "\u0627\u0648\u0644\u064a\u0627\u062f"
    ],
    "wof:name":"Olyad",
    "wof:placetype":"locality"
},
  "geometry": {"coordinates":[67.31058,34.51019],"type":"Point"}
}