{
  "type": "Feature",
  "properties": {
    "gn:admin1_code":"03",
    "gn:admin2_code":"1308",
    "gn:asciiname":"Kajnaw",
    "gn:country_code":"AF",
    "gn:dem":1856,
    "gn:feature_class":"P",
    "gn:feature_code":"PPL",
    "gn:name":"Kajn\u0101w",
    "gn:population":0,
    "gn:timezone":"Asia/Kabul",
    "iso:country":"AF",
    "name:und_x_variant":[
        "Kajin\u0101w",
        "Kajn\u0101w",
        "Kajnow",
        "\u06a9\u062c\u0646\u0627\u0648"
    ],
    "wof:name":"Kajnaw",
    "wof:placetype":"locality"
},
  "geometry": {"coordinates":[69.66218000000001,35.9313],"type":"Point"}
}