{
  "type": "Feature",
  "properties": {
    "gn:admin1_code":"6",
    "gn:admin2_code":"2101.0",
    "gn:asciiname":"Farah Kot",
    "gn:country_code":"AF",
    "gn:dem":662,
    "gn:feature_class":"P",
    "gn:feature_code":"PPL",
    "gn:name":"Far\u0101h K\u014dt",
    "gn:population":0,
    "gn:timezone":"Asia/Kabul",
    "iso:country":"AF",
    "name:und_x_variant":[
        "Farakhkot",
        "Fa\u1e5f\u0101h K\u014dt",
        "Far\u0101h Kowt",
        "Far\u0101h K\u014dt",
        "\u0641\u0631\u0627\u0647 \u06a9\u0648\u062a"
    ],
    "wof:name":"Farah Kot",
    "wof:placetype":"locality"
},
  "geometry": {"coordinates":[62.11564,32.39467],"type":"Point"}
}