{
  "type": "Feature",
  "properties": {
    "gn:admin1_code":"18",
    "gn:admin2_code":"803",
    "gn:asciiname":"Duav",
    "gn:country_code":"AF",
    "gn:dem":1838,
    "gn:feature_class":"P",
    "gn:feature_code":"PPL",
    "gn:name":"Duav",
    "gn:population":0,
    "gn:timezone":"Asia/Kabul",
    "iso:country":"AF",
    "name:fas_x_preferred":[
        "\u062f\u0648 \u0622\u0628"
    ],
    "name:und_x_variant":[
        "\u1e0eoaw",
        "D\u014d\u0101b",
        "Do\u0101b",
        "D\u016b\u0101w",
        "\u062f\u0648\u0627\u0648"
    ],
    "wof:name":"Duav",
    "wof:placetype":"locality"
},
  "geometry": {"coordinates":[69.72048000000001,34.30084],"type":"Point"}
}