{
  "type": "Feature",
  "properties": {
    "gn:admin1_code":"36",
    "gn:admin2_code":"702",
    "gn:asciiname":"Guldad Khel",
    "gn:country_code":"AF",
    "gn:dem":2141,
    "gn:feature_class":"P",
    "gn:feature_code":"PPL",
    "gn:name":"Guld\u0101d Kh\u0113l",
    "gn:population":0,
    "gn:timezone":"Asia/Kabul",
    "iso:country":"AF",
    "name:rus_x_preferred":[
        "Gul\u2019dadkheyl\u2019"
    ],
    "name:und_x_variant":[
        "Gul\u1e0f\u0101\u1e0fkh\u0113l",
        "Gold\u0101d Kheyl",
        "Guld\u0101d Kh\u0113l",
        "\u06af\u0644\u062f\u0627\u062f \u062e\u06d0\u0644"
    ],
    "wof:name":"Guldad Khel",
    "wof:placetype":"locality"
},
  "geometry": {"coordinates":[68.976,33.43644],"type":"Point"}
}