{
  "type": "Feature",
  "properties": {
    "gn:admin1_code":"28",
    "gn:admin2_code":"2510",
    "gn:asciiname":"Kunagh",
    "gn:country_code":"AF",
    "gn:dem":2373,
    "gn:feature_class":"P",
    "gn:feature_code":"PPL",
    "gn:name":"K\u016bnagh",
    "gn:population":0,
    "gn:timezone":"Asia/Kabul",
    "iso:country":"AF",
    "name:und_x_variant":[
        "Kunag",
        "K\u016bnagh",
        "\u06a9\u0648\u0646\u063a"
    ],
    "wof:name":"Kunagh",
    "wof:placetype":"locality"
},
  "geometry": {"coordinates":[67.23975,32.93813],"type":"Point"}
}