{
  "type": "Feature",
  "properties": {
    "gn:admin1_code":"17",
    "gn:admin2_code":"507.0",
    "gn:asciiname":"Arzo Khel",
    "gn:country_code":"AF",
    "gn:dem":2469,
    "gn:feature_class":"P",
    "gn:feature_code":"PPL",
    "gn:name":"\u0100rz\u014d Kh\u0113l",
    "gn:population":0,
    "gn:timezone":"Asia/Kabul",
    "iso:country":"AF",
    "name:rus_x_preferred":[
        "Arzokheyl\u2019"
    ],
    "name:und_x_variant":[
        "\u0100\u1e5fz\u014dkh\u0113l",
        "\u0100rz\u016b Kheyl",
        "\u0100rz\u014d Kh\u0113l",
        "\u0100rez\u016b Kheyl",
        "\u0622\u0631\u0632\u0648 \u062e\u06d0\u0644"
    ],
    "wof:name":"Arzo Khel",
    "wof:placetype":"locality"
},
  "geometry": {"coordinates":[68.88839,33.69355],"type":"Point"}
}