{
  "type": "Feature",
  "properties": {
    "gn:admin1_code":"30",
    "gn:admin2_code":"1608",
    "gn:asciiname":"Qal'ah-ye Allah Nur",
    "gn:country_code":"AF",
    "gn:dem":352,
    "gn:feature_class":"P",
    "gn:feature_code":"PPL",
    "gn:name":"Qal\u2018ah-ye All\u0101h N\u016br",
    "gn:population":0,
    "gn:timezone":"Asia/Kabul",
    "iso:country":"AF",
    "name:fas_x_preferred":[
        "\u0642\u0644\u0639\u0647\u0654 \u0627\u0644\u0627\u0647 \u0646\u0648\u0631"
    ],
    "name:rus_x_preferred":[
        "\u041a\u0430\u043b\u0430\u0439\u0438-\u0410\u043b\u0430\u0445\u043d\u0443\u0440"
    ],
    "name:rus_x_variant":[
        "\u041a\u0430\u043b\u0430-\u0410\u043b\u0430\u043d\u0443\u0440"
    ],
    "name:und_x_variant":[
        "Qala-i-Allah N\u016br",
        "Kalayi-Alakhnur",
        "Qal\u2018eh-ye All\u0101h N\u016br",
        "Qal\u2018ah-ye All\u0101h N\u016br",
        "\u0642\u0644\u0639\u06c0 \u0627\u0644\u0644\u0640\u0647 \u0646\u0648\u0631",
        "Qal\u2018eh All\u0101h N\u016br",
        "Kala-Alanur"
    ],
    "wof:name":"Qal'ah-ye Allah Nur",
    "wof:placetype":"locality"
},
  "geometry": {"coordinates":[66.68448000000001,36.6883],"type":"Point"}
}