{
  "type": "Feature",
  "properties": {
    "gn:admin1_code":"23",
    "gn:admin2_code":"2402.0",
    "gn:asciiname":"Kuchnay Karez",
    "gn:country_code":"AF",
    "gn:dem":1157,
    "gn:feature_class":"P",
    "gn:feature_code":"PPL",
    "gn:name":"Kuchnay K\u0101r\u0113z",
    "gn:population":0,
    "gn:timezone":"Asia/Kabul",
    "iso:country":"AF",
    "name:und_x_variant":[
        "Kuchnay-Karez",
        "Ku\u010dnay K\u0101r\u0113z",
        "\u06a9\u0686\u0646\u06cc \u06a9\u0627\u0631\u06d0\u0632",
        "Kuchnay K\u0101r\u012bz",
        "Kuchnay K\u0101r\u0113z"
    ],
    "wof:name":"Kuchnay Karez",
    "wof:placetype":"locality"
},
  "geometry": {"coordinates":[66.05873000000001,31.72881],"type":"Point"}
}