{
  "type": "Feature",
  "properties": {
    "gn:admin1_code":"35",
    "gn:admin2_code":"903",
    "gn:asciiname":"Kelay",
    "gn:country_code":"AF",
    "gn:dem":981,
    "gn:feature_class":"P",
    "gn:feature_code":"PPL",
    "gn:name":"K\u00ealay",
    "gn:population":0,
    "gn:timezone":"Asia/Kabul",
    "iso:country":"AF",
    "name:und_x_variant":[
        "\u06a9\u0644\u06cc",
        "Kalay",
        "K\u00ealay"
    ],
    "wof:name":"Kelay",
    "wof:placetype":"locality"
},
  "geometry": {"coordinates":[70.36924999999999,34.76711],"type":"Point"}
}