{
  "type": "Feature",
  "properties": {
    "gn:admin1_code":"11",
    "gn:admin2_code":"2007.0",
    "gn:asciiname":"Buniad",
    "gn:country_code":"AF",
    "gn:dem":709,
    "gn:feature_class":"P",
    "gn:feature_code":"PPL",
    "gn:name":"Buniad",
    "gn:population":0,
    "gn:timezone":"Asia/Kabul",
    "iso:country":"AF",
    "name:und_x_variant":[
        "Buny\u0101d Kh\u0101n",
        "Banyad Khan",
        "Buniad",
        "Bony\u0101d Kh\u0101n",
        "Boniy\u0101d Kh\u0101n",
        "\u0628\u0646\u06cc\u0627\u062f \u062e\u0627\u0646"
    ],
    "wof:name":"Buniad",
    "wof:placetype":"locality"
},
  "geometry": {"coordinates":[61.09373000000001,34.87908],"type":"Point"}
}