{
  "type": "Feature",
  "properties": {
    "gn:admin1_code":"23",
    "gn:admin2_code":"2412",
    "gn:asciiname":"Shash Qalandar",
    "gn:country_code":"AF",
    "gn:dem":1326,
    "gn:feature_class":"P",
    "gn:feature_code":"PPL",
    "gn:name":"Shash Qalandar",
    "gn:population":0,
    "gn:timezone":"Asia/Kabul",
    "iso:country":"AF",
    "name:und_x_variant":[
        "\u0160a\u0161 Qalandar",
        "Shashkalandar",
        "Shash Qalandar",
        "\u0634\u0634 \u0642\u0644\u0646\u062f\u0631",
        "Shesh Qalandar"
    ],
    "wof:name":"Shash Qalandar",
    "wof:placetype":"locality"
},
  "geometry": {"coordinates":[66.51803000000001,31.64824],"type":"Point"}
}