{
  "type": "Feature",
  "properties": {
    "gn:admin1_code":"23",
    "gn:admin2_code":"2402.0",
    "gn:asciiname":"De 'Abdul Wahab Kalachah",
    "gn:country_code":"AF",
    "gn:dem":1029,
    "gn:feature_class":"P",
    "gn:feature_code":"PPL",
    "gn:name":"D\u00ea \u2018Abdul Wah\u0101b Kal\u0101chah",
    "gn:population":0,
    "gn:timezone":"Asia/Kabul",
    "iso:country":"AF",
    "name:und_x_variant":[
        "D\u00ea \u2018Abdul Wah\u0101b Kal\u0101chah",
        "\u062f \u0639\u0628\u062f\u0644 \u0648\u0647\u0627\u0628 \u06a9\u0644\u0627\u0686\u0647"
    ],
    "wof:name":"De 'Abdul Wahab Kalachah",
    "wof:placetype":"locality"
},
  "geometry": {"coordinates":[65.8614,31.59084],"type":"Point"}
}