{
  "type": "Feature",
  "properties": {
    "gn:admin1_code":"08",
    "gn:admin2_code":"602",
    "gn:asciiname":"Gudali Yaray",
    "gn:country_code":"AF",
    "gn:dem":2893,
    "gn:feature_class":"P",
    "gn:feature_code":"PPL",
    "gn:name":"Gu\u1e0fal\u012b Y\u0101ray",
    "gn:population":0,
    "gn:timezone":"Asia/Kabul",
    "iso:country":"AF",
    "name:fas_x_preferred":[
        "\u06af\u062f\u0644\u0626 \u064a\u0627\u0631\u06cc"
    ],
    "name:rus_x_preferred":[
        "\u0413\u0443\u0434\u0430\u043b\u0438\u044f\u0440\u0430\u0439"
    ],
    "name:und_x_variant":[
        "Gudaliyaray",
        "Godal\u012b Y\u0101ray",
        "Gu\u1e0fal\u012b Y\u0101ray",
        "\u06af\u0689\u0644\u06cc \u06cc\u0627\u0631\u06cc"
    ],
    "wof:name":"Gudali Yaray",
    "wof:placetype":"locality"
},
  "geometry": {"coordinates":[67.98821,33.5262],"type":"Point"}
}