{
  "type": "Feature",
  "properties": {
    "gn:admin1_code":"03",
    "gn:admin2_code":"1304.0",
    "gn:asciiname":"Chaharbagh",
    "gn:country_code":"AF",
    "gn:dem":911,
    "gn:feature_class":"P",
    "gn:feature_code":"PPL",
    "gn:name":"Chah\u0101rb\u0101gh",
    "gn:population":0,
    "gn:timezone":"Asia/Kabul",
    "iso:country":"AF",
    "name:ara_x_preferred":[
        "\u062a\u0634\u0647\u0627\u0631\u0628\u0627\u063a"
    ],
    "name:aze_x_preferred":[
        "\u00c7aharba\u011f"
    ],
    "name:fas_x_preferred":[
        "\u0686\u0647\u0627\u0631\u0628\u0627\u063a"
    ],
    "name:ita_x_preferred":[
        "Cheharbagh"
    ],
    "name:mlg_x_preferred":[
        "Chaharbagh"
    ],
    "name:msa_x_preferred":[
        "Chaharbagh"
    ],
    "name:rus_x_preferred":[
        "\u0427\u0435\u0445\u0430\u0440\u0431\u0430\u0433"
    ],
    "name:tur_x_preferred":[
        "\u00c7eharba\u011f"
    ],
    "name:und_x_variant":[
        "\u010cah\u0101rb\u0101gh",
        "Chakharbag",
        "Chah\u0101rb\u0101gh",
        "\u0686\u0647\u0627\u0631\u0628\u0627\u063a"
    ],
    "name:urd_x_preferred":[
        "\u0686\u06c1\u0627\u0631\u0628\u0627\u063a"
    ],
    "wof:name":"Chaharbagh",
    "wof:placetype":"locality"
},
  "geometry": {"coordinates":[68.57796,35.60023],"type":"Point"}
}