{
  "type": "Feature",
  "properties": {
    "gn:admin1_code":"03",
    "gn:admin2_code":"1304.0",
    "gn:asciiname":"Chaharbagh",
    "gn:country_code":"AF",
    "gn:dem":911,
    "gn:feature_class":"P",
    "gn:feature_code":"PPL",
    "gn:name":"Chah\u0101rb\u0101gh",
    "gn:population":0,
    "gn:timezone":"Asia/Kabul",
    "iso:country":"AF",
    "name:und_x_variant":[
        "\u010cah\u0101rb\u0101gh",
        "Chakharbag",
        "Chah\u0101rb\u0101gh",
        "\u0686\u0647\u0627\u0631\u0628\u0627\u063a"
    ],
    "wof:name":"Chaharbagh",
    "wof:placetype":"locality"
},
  "geometry": {"coordinates":[68.57796,35.60023],"type":"Point"}
}