{
  "type": "Feature",
  "properties": {
    "gn:admin1_code":"37",
    "gn:admin2_code":"3213",
    "gn:asciiname":"Zemitsah",
    "gn:country_code":"AF",
    "gn:dem":1928,
    "gn:feature_class":"P",
    "gn:feature_code":"PPL",
    "gn:name":"Z\u00eam\u012btsah",
    "gn:population":0,
    "gn:timezone":"Asia/Kabul",
    "iso:country":"AF",
    "name:fas_x_preferred":[
        "\u0632\u06cc\u0645\u0686\u0647"
    ],
    "name:und_x_variant":[
        "Zemicha",
        "Z\u011bmica",
        "Dzmitsah",
        "Z\u00eamitsah",
        "Z\u0113mitsah",
        "Z\u00eam\u012btsah",
        "\u0632\u0645\u06cc\u0685\u0647"
    ],
    "wof:name":"Zemitsah",
    "wof:placetype":"locality"
},
  "geometry": {"coordinates":[69.49783000000001,33.29659],"type":"Point"}
}