{
  "type": "Feature",
  "properties": {
    "gn:admin1_code":"40",
    "gn:admin2_code":"308",
    "gn:asciiname":"Deh-e Miskin",
    "gn:country_code":"AF",
    "gn:dem":1536,
    "gn:feature_class":"P",
    "gn:feature_code":"PPL",
    "gn:name":"Deh-e Misk\u012bn",
    "gn:population":0,
    "gn:timezone":"Asia/Kabul",
    "iso:country":"AF",
    "name:fas_x_preferred":[
        "\u062f\u0647\u0654 \u0645\u0633\u0643\u064a\u0646"
    ],
    "name:und_x_variant":[
        "Dekhi-Miskin",
        "Deh-e Mesk\u012bn",
        "\u062f\u0647 \u0645\u0633\u06a9\u06cc\u0646",
        "Deh-e Misk\u012bn"
    ],
    "wof:name":"Deh-e Miskin",
    "wof:placetype":"locality"
},
  "geometry": {"coordinates":[69.16834,34.95885999999999],"type":"Point"}
}