{
  "type": "Feature",
  "properties": {
    "gn:admin1_code":"18",
    "gn:admin2_code":"804.0",
    "gn:asciiname":"Gangah Khel",
    "gn:country_code":"AF",
    "gn:dem":1508,
    "gn:feature_class":"P",
    "gn:feature_code":"PPL",
    "gn:name":"Gangah Kh\u0113l",
    "gn:population":0,
    "gn:timezone":"Asia/Kabul",
    "iso:country":"AF",
    "name:fas_x_preferred":[
        "\u06af\u0646\u06af\u0647 \u062e\u064a\u0644"
    ],
    "name:rus_x_preferred":[
        "Gangakheyl\u2019"
    ],
    "name:und_x_variant":[
        "Gangakh\u0113l",
        "Gangakheyl",
        "Gangah Kh\u0113l",
        "\u06af\u0646\u06af\u0647 \u062e\u06d0\u0644"
    ],
    "wof:name":"Gangah Khel",
    "wof:placetype":"locality"
},
  "geometry": {"coordinates":[70.04349000000001,34.24239],"type":"Point"}
}