{
  "type": "Feature",
  "properties": {
    "gn:admin1_code":"03",
    "gn:admin2_code":"1312.0",
    "gn:asciiname":"Pul-e Muhammad-Salabeg",
    "gn:country_code":"AF",
    "gn:dem":1670,
    "gn:feature_class":"P",
    "gn:feature_code":"PPL",
    "gn:name":"Pul-e Mu\u1e29ammad-\u015eal\u0101b\u0113g",
    "gn:population":0,
    "gn:timezone":"Asia/Kabul",
    "iso:country":"AF",
    "name:und_x_variant":[
        "Pule Mohamma\u1e0f-sal\u0101b\u0113g",
        "Pol-e Mo\u1e29ammad \u015eal\u0101beyg",
        "Pul-e Mu\u1e29ammad-\u015eal\u0101b\u0113g",
        "\u067e\u0644 \u0645\u062d\u0645\u062f \u0635\u0644\u0627\u0628\u06d0\u06af"
    ],
    "wof:name":"Pul-e Muhammad-Salabeg",
    "wof:placetype":"locality"
},
  "geometry": {"coordinates":[69.35538000000001,35.66578],"type":"Point"}
}