{
  "type": "Feature",
  "properties": {
    "gn:admin1_code":"06",
    "gn:admin2_code":"2105",
    "gn:asciiname":"Kand-e Salih",
    "gn:country_code":"AF",
    "gn:dem":1045,
    "gn:feature_class":"P",
    "gn:feature_code":"PPL",
    "gn:name":"Kand-e \u015e\u0101li\u1e29",
    "gn:population":0,
    "gn:timezone":"Asia/Kabul",
    "iso:country":"AF",
    "name:und_x_variant":[
        "Kandi-Sala",
        "Kand-e \u015e\u0101le\u1e29",
        "Kand-e \u015e\u0101li\u1e29",
        "\u06a9\u0646\u062f \u0635\u0627\u0644\u062d"
    ],
    "wof:name":"Kand-e Salih",
    "wof:placetype":"locality"
},
  "geometry": {"coordinates":[63.13347,32.84025],"type":"Point"}
}