{
  "type": "Feature",
  "properties": {
    "gn:admin1_code":"08",
    "gn:admin2_code":"613",
    "gn:asciiname":"Nowe Gerdah",
    "gn:country_code":"AF",
    "gn:dem":2045,
    "gn:feature_class":"P",
    "gn:feature_code":"PPL",
    "gn:name":"Now\u0113 G\u00eardah",
    "gn:population":0,
    "gn:timezone":"Asia/Kabul",
    "iso:country":"AF",
    "name:fas_x_preferred":[
        "\u0646\u0648\u06cc \u06af\u064a\u0631\u062f\u0647"
    ],
    "name:und_x_variant":[
        "Nave-Gerda",
        "Naw\u0113 Ge\u1e5f\u1e0fa",
        "N\u00eaw\u00eay G\u0113rdah",
        "Naw\u0113 G\u0113rdah",
        "Now\u0113 G\u00eardah",
        "\u0646\u0648\u06cc \u06af\u0631\u062f\u0647"
    ],
    "wof:name":"Nowe Gerdah",
    "wof:placetype":"locality"
},
  "geometry": {"coordinates":[68.27095,33.22602],"type":"Point"}
}