{
  "type": "Feature",
  "properties": {
    "gn:admin1_code":"18",
    "gn:admin2_code":"820.0",
    "gn:asciiname":"Janjah Pur",
    "gn:country_code":"AF",
    "gn:dem":953,
    "gn:feature_class":"P",
    "gn:feature_code":"PPL",
    "gn:name":"Janjah P\u016br",
    "gn:population":0,
    "gn:timezone":"Asia/Kabul",
    "iso:country":"AF",
    "name:fas_x_preferred":[
        "\u062c\u0646\u062c\u067e\u0648\u0631"
    ],
    "name:und_x_variant":[
        "Dzhanzhapur",
        "Janjap\u016b\u1e5f",
        "Janjah P\u016br",
        "\u062c\u0646\u062c\u0647 \u067e\u0648\u0631"
    ],
    "wof:name":"Janjah Pur",
    "wof:placetype":"locality"
},
  "geometry": {"coordinates":[70.59161999999998,34.65923],"type":"Point"}
}