{
  "type": "Feature",
  "properties": {
    "gn:admin1_code":"35",
    "gn:admin2_code":"901.0",
    "gn:asciiname":"Mianpur",
    "gn:country_code":"AF",
    "gn:dem":777,
    "gn:feature_class":"P",
    "gn:feature_code":"PPL",
    "gn:name":"Mianpur",
    "gn:population":0,
    "gn:timezone":"Asia/Kabul",
    "iso:country":"AF",
    "name:und_x_variant":[
        "My\u0101np\u016b\u1e5f",
        "Mianpur",
        "M\u012b\u0101np\u016br",
        "\u0645\u06cc\u0627\u0646 \u067e\u0648\u0631"
    ],
    "wof:name":"Mianpur",
    "wof:placetype":"locality"
},
  "geometry": {"coordinates":[70.19523000000001,34.66886],"type":"Point"}
}