{
  "type": "Feature",
  "properties": {
    "gn:admin1_code":"27",
    "gn:admin2_code":"404",
    "gn:asciiname":"Now Joy",
    "gn:country_code":"AF",
    "gn:dem":2950,
    "gn:feature_class":"P",
    "gn:feature_code":"PPL",
    "gn:name":"Now J\u014dy",
    "gn:population":0,
    "gn:timezone":"Asia/Kabul",
    "iso:country":"AF",
    "name:fas_x_preferred":[
        "\u0646\u0648 \u062c\u0648\u06cc"
    ],
    "name:rus_x_preferred":[
        "\u041d\u0430\u0443\u0434\u0436\u043e\u0439"
    ],
    "name:und_x_variant":[
        "Naudzhoy",
        "Nawj\u014dy",
        "Now J\u014dy",
        "Nowj\u016by"
    ],
    "wof:name":"Now Joy",
    "wof:placetype":"locality"
},
  "geometry": {"coordinates":[67.47861,34.54864],"type":"Point"}
}