{
  "type": "Feature",
  "properties": {
    "gn:admin1_code":"02",
    "gn:admin2_code":"1903",
    "gn:asciiname":"Zay Hakima",
    "gn:country_code":"AF",
    "gn:dem":1582,
    "gn:feature_class":"P",
    "gn:feature_code":"PPL",
    "gn:name":"Z\u0101y \u1e28ak\u012bm\u0101",
    "gn:population":0,
    "gn:timezone":"Asia/Kabul",
    "iso:country":"AF",
    "name:und_x_variant":[
        "Zaykhakima",
        "Z\u0101y \u1e28ak\u012bm\u0101",
        "\u0632\u0627\u06cc \u062d\u06a9\u06cc\u0645\u0627"
    ],
    "wof:name":"Zay Hakima",
    "wof:placetype":"locality"
},
  "geometry": {"coordinates":[63.48838000000001,34.76997],"type":"Point"}
}