{
  "type": "Feature",
  "properties": {
    "gn:admin1_code":"1",
    "gn:admin2_code":"1123.0",
    "gn:asciiname":"Asyawani",
    "gn:country_code":"AF",
    "gn:dem":1610,
    "gn:feature_class":"P",
    "gn:feature_code":"PPL",
    "gn:name":"\u0100sy\u0101w\u0101n\u012b",
    "gn:population":0,
    "gn:timezone":"Asia/Kabul",
    "iso:country":"AF",
    "name:und_x_variant":[
        "\u0100sy\u0101w\u0101n\u012b",
        "\u0622\u0633\u06cc\u0627\u0648\u0627\u0646\u06cc",
        "Asy\u0101w\u0101ni"
    ],
    "wof:name":"Asyawani",
    "wof:placetype":"locality"
},
  "geometry": {"coordinates":[70.3026,36.56034],"type":"Point"}
}