{
  "type": "Feature",
  "properties": {
    "gn:admin1_code":"23",
    "gn:admin2_code":"2413",
    "gn:asciiname":"Mihraban Khel",
    "gn:country_code":"AF",
    "gn:dem":1700,
    "gn:feature_class":"P",
    "gn:feature_code":"PPL",
    "gn:name":"Mihrab\u0101n Kh\u0113l",
    "gn:population":0,
    "gn:timezone":"Asia/Kabul",
    "iso:country":"AF",
    "name:fas_x_preferred":[
        "\u0645\u0647\u0631\u0628\u0627\u0646 \u062e\u064a\u0644"
    ],
    "name:pus_x_preferred":[
        "\u0645\u0647\u0631\u0628\u0627\u0646 \u062e\u06d0\u0644"
    ],
    "name:rus_x_preferred":[
        "Mikhrabankheyl\u2019"
    ],
    "name:und_x_variant":[
        "Meh\u1e5fab\u0101nkh\u0113l",
        "Mihrab\u0101n Kh\u0113l",
        "Mehrab\u0101n Kheyl"
    ],
    "wof:name":"Mihraban Khel",
    "wof:placetype":"locality"
},
  "geometry": {"coordinates":[67.01876,31.53976],"type":"Point"}
}