{
  "type": "Feature",
  "properties": {
    "gn:admin1_code":"23",
    "gn:admin2_code":"2416.0",
    "gn:asciiname":"Haji Muhammad 'Iwaz",
    "gn:country_code":"AF",
    "gn:dem":935,
    "gn:feature_class":"P",
    "gn:feature_code":"PPL",
    "gn:name":"\u1e28\u0101j\u012b Mu\u1e29ammad \u2018Iwa\u1e95",
    "gn:population":0,
    "gn:timezone":"Asia/Kabul",
    "iso:country":"AF",
    "name:und_x_variant":[
        "Khadzhi-Mukhammedivaz",
        "\u1e28\u0101ji Mo\u1e29amma\u1e0f \u2018Ewa\u1e0f\u1e95",
        "\u2018Eva\u1e95",
        "\u2018Ewadz",
        "\u1e28\u0101j\u012b Mu\u1e29ammad \u2018Iwa\u1e95",
        "\u062d\u0627\u062c\u06cc \u0645\u062d\u0645\u062f \u0639\u0648\u0636",
        "\u1e28\u0101jj\u012b Mo\u1e29ammad \u2018Eva\u1e95"
    ],
    "wof:name":"Haji Muhammad 'Iwaz",
    "wof:placetype":"locality"
},
  "geometry": {"coordinates":[65.41847,31.53996],"type":"Point"}
}