{
  "type": "Feature",
  "properties": {
    "gn:admin1_code":"41",
    "gn:admin2_code":"3407.0",
    "gn:asciiname":"Barmanay",
    "gn:country_code":"AF",
    "gn:dem":2511,
    "gn:feature_class":"P",
    "gn:feature_code":"PPL",
    "gn:name":"Barmanay",
    "gn:population":0,
    "gn:timezone":"Asia/Kabul",
    "iso:country":"AF",
    "name:und_x_variant":[
        "\u0628\u0631\u0645\u0646\u06cc",
        "Ba\u1e5fmanay"
    ],
    "wof:name":"Barmanay",
    "wof:placetype":"locality"
},
  "geometry": {"coordinates":[67.10661,33.73982],"type":"Point"}
}