{
  "type": "Feature",
  "properties": {
    "gn:admin1_code":"28",
    "gn:admin2_code":"2503",
    "gn:asciiname":"Indzer",
    "gn:country_code":"AF",
    "gn:dem":1692,
    "gn:feature_class":"P",
    "gn:feature_code":"PPL",
    "gn:name":"Indz\u00ear",
    "gn:population":0,
    "gn:timezone":"Asia/Kabul",
    "iso:country":"AF",
    "name:fas_x_preferred":[
        "\u0627\u0646\u062c\u0631"
    ],
    "name:und_x_variant":[
        "Indzhar",
        "Indz\u00ear",
        "\u0627\u0646\u0681\u0631",
        "Enjar"
    ],
    "wof:name":"Indzer",
    "wof:placetype":"locality"
},
  "geometry": {"coordinates":[66.94197,32.43127],"type":"Point"}
}