{
  "type": "Feature",
  "properties": {
    "gn:admin1_code":"29",
    "gn:admin2_code":"2904",
    "gn:asciiname":"Toley Kelay",
    "gn:country_code":"AF",
    "gn:dem":2199,
    "gn:feature_class":"P",
    "gn:feature_code":"PPL",
    "gn:name":"\u1e6e\u014dl\u00eay K\u00ealay",
    "gn:population":0,
    "gn:timezone":"Asia/Kabul",
    "iso:country":"AF",
    "name:und_x_variant":[
        "T\u014dlay Kalay",
        "T\u014dl\u0259y Kalay",
        "\u067c\u0648\u0644\u06cd \u06a9\u0644\u06cc",
        "T\u016blay Kalay",
        "\u1e6e\u014dl\u00eay K\u00ealay"
    ],
    "wof:name":"Toley Kelay",
    "wof:placetype":"locality"
},
  "geometry": {"coordinates":[68.32164,32.36877],"type":"Point"}
}