{
  "type": "Feature",
  "properties": {
    "gn:admin1_code":"07",
    "gn:admin2_code":"1805",
    "gn:asciiname":"Quduqak",
    "gn:country_code":"AF",
    "gn:dem":2081,
    "gn:feature_class":"P",
    "gn:feature_code":"PPL",
    "gn:name":"Q\u016bd\u016bqak",
    "gn:population":0,
    "gn:timezone":"Asia/Kabul",
    "iso:country":"AF",
    "name:und_x_variant":[
        "Qu\u1e0f\u016bghak",
        "Q\u016bd\u016bqak",
        "\u0642\u0648\u062f\u0648\u0642\u06a9"
    ],
    "wof:name":"Quduqak",
    "wof:placetype":"locality"
},
  "geometry": {"coordinates":[64.79788000000001,35.3682],"type":"Point"}
}