{
  "type": "Feature",
  "properties": {
    "gn:admin1_code":"8",
    "gn:admin2_code":"607.0",
    "gn:asciiname":"Mashal",
    "gn:country_code":"AF",
    "gn:dem":2593,
    "gn:feature_class":"P",
    "gn:feature_code":"PPL",
    "gn:name":"M\u0101sh\u0101l",
    "gn:population":0,
    "gn:timezone":"Asia/Kabul",
    "iso:country":"AF",
    "name:heb_x_preferred":[
        "\u05de\u05e9\u05dc"
    ],
    "name:rus_x_preferred":[
        "\u041c\u0430\u0448\u0430\u043b"
    ],
    "name:und_x_variant":[
        "M\u0101\u0161\u0101l",
        "M\u0101sh\u0101l",
        "\u0645\u0627\u0634\u0627\u0644"
    ],
    "wof:name":"Mashal",
    "wof:placetype":"locality"
},
  "geometry": {"coordinates":[67.46288,33.17701],"type":"Point"}
}