{
  "type": "Feature",
  "properties": {
    "gn:admin1_code":"13",
    "gn:admin2_code":"112",
    "gn:asciiname":"Suhak-e Mulla Khel",
    "gn:country_code":"AF",
    "gn:dem":2037,
    "gn:feature_class":"P",
    "gn:feature_code":"PPL",
    "gn:name":"Su\u1e29\u0101k-e Mull\u0101 Kh\u0113l",
    "gn:population":0,
    "gn:timezone":"Asia/Kabul",
    "iso:country":"AF",
    "name:fas_x_preferred":[
        "\u0633\u062d\u0627\u0643\u0647 \u0645\u0644\u0627 \u062e\u064a\u0644"
    ],
    "name:rus_x_preferred":[
        "Sukhaki-Mullakheyl\u2019"
    ],
    "name:und_x_variant":[
        "So\u1e29\u0101ke Mol\u0101kh\u0113l",
        "Soh\u0101ke Mol\u0101kh\u0113l",
        "So\u1e29\u0101k-e Mull\u0101 Kh\u0113l",
        "So\u1e29\u0101keh Moll\u0101kheyl",
        "Su\u1e29\u0101k-e Mull\u0101 Kh\u0113l",
        "\u0633\u062d\u0627\u06a9 \u0645\u0644\u0627 \u062e\u06d0\u0644"
    ],
    "wof:name":"Suhak-e Mulla Khel",
    "wof:placetype":"locality"
},
  "geometry": {"coordinates":[69.60831999999999,34.37649],"type":"Point"}
}