{
  "type": "Feature",
  "properties": {
    "gn:admin1_code":"6",
    "gn:admin2_code":"2101.0",
    "gn:asciiname":"Showalga-ye Wasati",
    "gn:country_code":"AF",
    "gn:dem":698,
    "gn:feature_class":"P",
    "gn:feature_code":"PPL",
    "gn:name":"Show\u0101lg\u0101-ye Wasa\u0163\u012b",
    "gn:population":0,
    "gn:timezone":"Asia/Kabul",
    "iso:country":"AF",
    "name:rus_x_preferred":[
        "Shaval\u2019gakh-Vasati"
    ],
    "name:und_x_variant":[
        "\u0160ow\u0101lg\u0101 Was\u0101\u0163\u012b",
        "Sh\u0101h W\u0101lg\u0101 Was\u0101fi",
        "Show\u0101lg\u0101-ye Wasa\u0163\u012b",
        "\u0634\u0648\u0627\u0644\u06af\u0627 \u0648\u0633\u0637\u06cc"
    ],
    "wof:name":"Showalga-ye Wasati",
    "wof:placetype":"locality"
},
  "geometry": {"coordinates":[62.26283000000001,32.5084],"type":"Point"}
}