{
  "type": "Feature",
  "properties": {
    "gn:admin1_code":"35",
    "gn:admin2_code":"903",
    "gn:asciiname":"Radzhay",
    "gn:country_code":"AF",
    "gn:dem":871,
    "gn:feature_class":"P",
    "gn:feature_code":"PPL",
    "gn:name":"Radzhay",
    "gn:population":0,
    "gn:timezone":"Asia/Kabul",
    "iso:country":"AF",
    "name:und_x_variant":[
        "\u0631\u062c\u0627\u0626\u06cc",
        "Rajah\u2019\u012b",
        "Raj\u0101\u2019\u012b"
    ],
    "wof:name":"Radzhay",
    "wof:placetype":"locality"
},
  "geometry": {"coordinates":[70.32975999999999,34.79691],"type":"Point"}
}