{
  "type": "Feature",
  "properties": {
    "gn:admin1_code":"7",
    "gn:admin2_code":"1813.0",
    "gn:asciiname":"Shu Bakhtu",
    "gn:country_code":"AF",
    "gn:dem":750,
    "gn:feature_class":"P",
    "gn:feature_code":"PPL",
    "gn:name":"Sh\u016b B\u0101kht\u016b",
    "gn:population":0,
    "gn:timezone":"Asia/Kabul",
    "iso:country":"AF",
    "name:und_x_variant":[
        "S\u016b B\u0101kht\u016b",
        "Sh\u016b B\u0101kht\u016b",
        "\u0634\u0648 \u0628\u0627\u062e\u062a\u0648",
        "Sh\u016b Bakht\u016b",
        "\u0634\u0648 \u0628\u062e\u062a\u0648"
    ],
    "wof:name":"Shu Bakhtu",
    "wof:placetype":"locality"
},
  "geometry": {"coordinates":[64.90364,35.99944],"type":"Point"}
}