{
  "type": "Feature",
  "properties": {
    "gn:admin1_code":"10",
    "gn:admin2_code":"2307",
    "gn:asciiname":"Langar",
    "gn:country_code":"AF",
    "gn:dem":1173,
    "gn:feature_class":"P",
    "gn:feature_code":"PPL",
    "gn:name":"Langar",
    "gn:population":0,
    "gn:timezone":"Asia/Kabul",
    "iso:country":"AF",
    "name:und_x_variant":[
        "Langer",
        "Langar",
        "\u0644\u0646\u06af\u0631"
    ],
    "wof:name":"Langar",
    "wof:placetype":"locality"
},
  "geometry": {"coordinates":[63.86009,32.2579],"type":"Point"}
}