{
  "type": "Feature",
  "properties": {
    "gn:admin1_code":"29",
    "gn:admin2_code":"2912",
    "gn:asciiname":"Madiki Kuhnah",
    "gn:country_code":"AF",
    "gn:dem":2312,
    "gn:feature_class":"P",
    "gn:feature_code":"PPL",
    "gn:name":"Madik\u012b Kuhnah",
    "gn:population":0,
    "gn:timezone":"Asia/Kabul",
    "iso:country":"AF",
    "name:und_x_variant":[
        "Madiki-Kukhna",
        "Ma\u1e0fek\u012b Kuhna",
        "\u0645\u062f\u06a9\u06cc \u06a9\u0647\u0646\u0647",
        "Madek\u012b Kohneh",
        "Madik\u012b Kuhnah"
    ],
    "wof:name":"Madiki Kuhnah",
    "wof:placetype":"locality"
},
  "geometry": {"coordinates":[69.31681999999999,33.1525],"type":"Point"}
}