{
  "type": "Feature",
  "properties": {
    "gn:admin1_code":"05",
    "gn:admin2_code":"2805.0",
    "gn:asciiname":"Kaj Now",
    "gn:country_code":"AF",
    "gn:dem":2732,
    "gn:feature_class":"P",
    "gn:feature_code":"PPL",
    "gn:name":"Kaj Now",
    "gn:population":0,
    "gn:timezone":"Asia/Kabul",
    "iso:country":"AF",
    "name:und_x_variant":[
        "Kadzhnau",
        "Kaj Now",
        "Kajn\u0101w",
        "\u06a9\u062c \u0646\u0648"
    ],
    "wof:name":"Kaj Now",
    "wof:placetype":"locality"
},
  "geometry": {"coordinates":[67.03048000000001,34.34435],"type":"Point"}
}