{
  "type": "Feature",
  "properties": {
    "gn:admin1_code":"05",
    "gn:admin2_code":"2805",
    "gn:asciiname":"Wutipur",
    "gn:country_code":"AF",
    "gn:dem":3002,
    "gn:feature_class":"P",
    "gn:feature_code":"PPL",
    "gn:name":"Wu\u1e6fip\u016br",
    "gn:population":0,
    "gn:timezone":"Asia/Kabul",
    "iso:country":"AF",
    "name:und_x_variant":[
        "Vutipur",
        "Wo\u1e6f\u012bp\u016br",
        "Wot\u012bp\u016br",
        "Wu\u1e6fip\u016br",
        "\u0648\u067c\u067e\u0648\u0631"
    ],
    "wof:name":"Wutipur",
    "wof:placetype":"locality"
},
  "geometry": {"coordinates":[67.30703000000001,34.38851],"type":"Point"}
}