{
  "type": "Feature",
  "properties": {
    "gn:admin1_code":"32",
    "gn:admin2_code":"1506",
    "gn:asciiname":"Sar-e Ab Darah",
    "gn:country_code":"AF",
    "gn:dem":2111,
    "gn:feature_class":"P",
    "gn:feature_code":"PPL",
    "gn:name":"Sar-e \u0100b Darah",
    "gn:population":0,
    "gn:timezone":"Asia/Kabul",
    "iso:country":"AF",
    "name:und_x_variant":[
        "Sa\u1e5fe \u0100b\u1e0fa\u1e5fa",
        "Sar-e-\u0100b Darreh",
        "Sar-e \u0100b Darah",
        "\u0633\u0631 \u0622\u0628 \u062f\u0631\u0647"
    ],
    "wof:name":"Sar-e Ab Darah",
    "wof:placetype":"locality"
},
  "geometry": {"coordinates":[68.24779000000001,35.93847],"type":"Point"}
}