{
  "type": "Feature",
  "properties": {
    "gn:admin1_code":"40",
    "gn:admin2_code":"304",
    "gn:asciiname":"Mullai",
    "gn:country_code":"AF",
    "gn:dem":1666,
    "gn:feature_class":"P",
    "gn:feature_code":"PPL",
    "gn:name":"Mullai",
    "gn:population":0,
    "gn:timezone":"Asia/Kabul",
    "iso:country":"AF",
    "name:und_x_variant":[
        "Mol\u0101\u2019i",
        "Mullai",
        "Moll\u0101\u2019\u012b",
        "Mull\u0101\u2019\u012b",
        "\u0645\u0644\u0627\u0626\u06cc"
    ],
    "wof:name":"Mullai",
    "wof:placetype":"locality"
},
  "geometry": {"coordinates":[69.09225000000001,35.07366],"type":"Point"}
}