{
  "type": "Feature",
  "properties": {
    "gn:admin1_code":"8",
    "gn:admin2_code":"606.0",
    "gn:asciiname":"Dahan-e Awqash",
    "gn:country_code":"AF",
    "gn:dem":2889,
    "gn:feature_class":"P",
    "gn:feature_code":"PPL",
    "gn:name":"Dah\u0101n-e \u0100wq\u0101sh",
    "gn:population":0,
    "gn:timezone":"Asia/Kabul",
    "iso:country":"AF",
    "name:und_x_variant":[
        "Dahane Awq\u0101\u0161",
        "Dahan-e \u0100bq\u0101sh",
        "Dah\u0101n-e \u0100wq\u0101sh",
        "\u062f\u0647\u0627\u0646 \u0622\u0648\u0642\u0627\u0634"
    ],
    "wof:name":"Dahan-e Awqash",
    "wof:placetype":"locality"
},
  "geometry": {"coordinates":[67.32441,33.31496],"type":"Point"}
}