{
  "type": "Feature",
  "properties": {
    "gn:admin1_code":"40",
    "gn:admin2_code":"304",
    "gn:asciiname":"Toghzar",
    "gn:country_code":"AF",
    "gn:dem":2250,
    "gn:feature_class":"P",
    "gn:feature_code":"PPL",
    "gn:name":"T\u014dghz\u0101r",
    "gn:population":0,
    "gn:timezone":"Asia/Kabul",
    "iso:country":"AF",
    "name:und_x_variant":[
        "T\u014dghz\u0101r",
        "Togzar",
        "Towghz\u0101r",
        "\u062a\u0648\u063a\u0632\u0627\u0631"
    ],
    "wof:name":"Toghzar",
    "wof:placetype":"locality"
},
  "geometry": {"coordinates":[69.05977,35.13251],"type":"Point"}
}