{
  "type": "Feature",
  "properties": {
    "gn:admin1_code":"5",
    "gn:admin2_code":"2806.0",
    "gn:asciiname":"Shah Bayd",
    "gn:country_code":"AF",
    "gn:dem":2489,
    "gn:feature_class":"P",
    "gn:feature_code":"PPL",
    "gn:name":"Sh\u0101h Bayd",
    "gn:population":0,
    "gn:timezone":"Asia/Kabul",
    "iso:country":"AF",
    "name:und_x_variant":[
        "Shakhbed",
        "\u0160\u0101hb\u0113d",
        "Sh\u0101h Bayd",
        "Sh\u0101hb\u012bd",
        "\u0634\u0627\u0647 \u0628\u06cc\u062f"
    ],
    "wof:name":"Shah Bayd",
    "wof:placetype":"locality"
},
  "geometry": {"coordinates":[66.93250999999999,34.22116],"type":"Point"}
}