{
  "type": "Feature",
  "properties": {
    "gn:admin1_code":"41",
    "gn:admin2_code":"3402",
    "gn:asciiname":"Shiyir Nazar",
    "gn:country_code":"AF",
    "gn:dem":1511,
    "gn:feature_class":"P",
    "gn:feature_code":"PPL",
    "gn:name":"Shiyir Naz\u0327ar",
    "gn:population":0,
    "gn:timezone":"Asia/Kabul",
    "iso:country":"AF",
    "name:und_x_variant":[
        "Seye\u1e5f N\u0101\u1e95a\u1e5f",
        "Shiyir Naz\u0327ar",
        "\u0634\u06cc\u0631 \u0646\u0638\u0631",
        "Sheyer N\u0101z\u0327er"
    ],
    "wof:name":"Shiyir Nazar",
    "wof:placetype":"locality"
},
  "geometry": {"coordinates":[65.97905,33.24459],"type":"Point"}
}