{
  "type": "Feature",
  "properties": {
    "gn:admin1_code":"41",
    "gn:admin2_code":"3409.0",
    "gn:asciiname":"Dahanghi",
    "gn:country_code":"AF",
    "gn:dem":2235,
    "gn:feature_class":"P",
    "gn:feature_code":"PPL",
    "gn:name":"Dah\u0101ngh\u012b",
    "gn:population":0,
    "gn:timezone":"Asia/Kabul",
    "iso:country":"AF",
    "name:und_x_variant":[
        "Dah\u0101ngh\u012b",
        "\u062f\u0647\u0646\u063a\u06cc",
        "Dahangh\u012b"
    ],
    "wof:name":"Dahanghi",
    "wof:placetype":"locality"
},
  "geometry": {"coordinates":[66.47530999999999,33.78699],"type":"Point"}
}