{
  "type": "Feature",
  "properties": {
    "gn:admin1_code":"39",
    "gn:admin2_code":"2602",
    "gn:asciiname":"Morigak",
    "gn:country_code":"AF",
    "gn:dem":1875,
    "gn:feature_class":"P",
    "gn:feature_code":"PPL",
    "gn:name":"M\u014dr\u012bgak",
    "gn:population":0,
    "gn:timezone":"Asia/Kabul",
    "iso:country":"AF",
    "name:fas_x_preferred":[
        "\u0645\u0648\u0631\u06af\u0643"
    ],
    "name:und_x_variant":[
        "M\u014d\u1e5figak",
        "M\u014dr\u012bgak",
        "\u0645\u0648\u0631\u06af\u06a9",
        "M\u016brigak"
    ],
    "wof:name":"Morigak",
    "wof:placetype":"locality"
},
  "geometry": {"coordinates":[66.19524,32.60371],"type":"Point"}
}