{
  "type": "Feature",
  "properties": {
    "gn:admin1_code":"01",
    "gn:admin2_code":"1120.0",
    "gn:asciiname":"Garyon",
    "gn:country_code":"AF",
    "gn:dem":2321,
    "gn:feature_class":"P",
    "gn:feature_code":"PPL",
    "gn:name":"G\u0101ry\u014dn",
    "gn:population":0,
    "gn:timezone":"Asia/Kabul",
    "iso:country":"AF",
    "name:und_x_variant":[
        "G\u0101\u1e5fy\u014dn",
        "G\u0101ry\u016bn",
        "G\u0101r\u012b\u014dn",
        "\u06af\u0627\u0631\u06cc\u0648\u0646",
        "G\u0101ry\u014dn"
    ],
    "wof:name":"Garyon",
    "wof:placetype":"locality"
},
  "geometry": {"coordinates":[70.53437,38.00364],"type":"Point"}
}