{
  "type": "Feature",
  "properties": {
    "gn:admin1_code":"09",
    "gn:admin2_code":"2701",
    "gn:asciiname":"Dota'i",
    "gn:country_code":"AF",
    "gn:dem":2420,
    "gn:feature_class":"P",
    "gn:feature_code":"PPL",
    "gn:name":"D\u014dt\u0101\u2019\u012b",
    "gn:population":0,
    "gn:timezone":"Asia/Kabul",
    "iso:country":"AF",
    "name:und_x_variant":[
        "D\u014dt\u0101\u2019\u012b",
        "\u062f\u0648\u062a\u0627\u0626\u06cc",
        "\u1e0eot\u0101\u2019i"
    ],
    "wof:name":"Dota'i",
    "wof:placetype":"locality"
},
  "geometry": {"coordinates":[65.06048,34.39828],"type":"Point"}
}