{
  "type": "Feature",
  "properties": {
    "gn:admin1_code":"28",
    "gn:admin2_code":"2504",
    "gn:asciiname":"Witi",
    "gn:country_code":"AF",
    "gn:dem":2611,
    "gn:feature_class":"P",
    "gn:feature_code":"PPL",
    "gn:name":"Wit\u012b",
    "gn:population":0,
    "gn:timezone":"Asia/Kabul",
    "iso:country":"AF",
    "name:ita_x_preferred":[
        "Witi"
    ],
    "name:por_x_preferred":[
        "Witiness Quembo"
    ],
    "name:rus_x_preferred":[
        "\u0412\u0438\u0442\u0438"
    ],
    "name:und_x_variant":[
        "Viti",
        "Wit\u012b",
        "\u0648\u062a\u06cc",
        "Weti"
    ],
    "name:vie_x_preferred":[
        "Witi"
    ],
    "wof:name":"Witi",
    "wof:placetype":"locality"
},
  "geometry": {"coordinates":[66.46569000000001,32.58019],"type":"Point"}
}