{
  "type": "Feature",
  "properties": {
    "gn:admin1_code":"13",
    "gn:admin2_code":"108.0",
    "gn:asciiname":"Qal'ah-ye Sardar",
    "gn:country_code":"AF",
    "gn:dem":2012,
    "gn:feature_class":"P",
    "gn:feature_code":"PPL",
    "gn:name":"Qal\u2018ah-ye Sard\u0101r",
    "gn:population":0,
    "gn:timezone":"Asia/Kabul",
    "iso:country":"AF",
    "name:und_x_variant":[
        "Qal\u2018ah-ye Sard\u0101r",
        "\u0642\u0644\u0639\u0647 \u0633\u0631\u062f\u0627\u0631"
    ],
    "wof:name":"Qal'ah-ye Sardar",
    "wof:placetype":"locality"
},
  "geometry": {"coordinates":[69.00256,34.54181],"type":"Point"}
}