{
  "type": "Feature",
  "properties": {
    "gn:admin1_code":"11",
    "gn:admin2_code":"2005.0",
    "gn:asciiname":"Deh Surkh",
    "gn:country_code":"AF",
    "gn:dem":1274,
    "gn:feature_class":"P",
    "gn:feature_code":"PPL",
    "gn:name":"Deh Surkh",
    "gn:population":0,
    "gn:timezone":"Asia/Kabul",
    "iso:country":"AF",
    "name:und_x_variant":[
        "\u1e0eeh Surkh",
        "Dekheurkh",
        "Deh Surkh",
        "\u062f\u0647 \u0633\u0631\u062e",
        "Deh Sorkh"
    ],
    "wof:name":"Deh Surkh",
    "wof:placetype":"locality"
},
  "geometry": {"coordinates":[62.46272,34.48253],"type":"Point"}
}