{
  "type": "Feature",
  "properties": {
    "gn:admin1_code":"29",
    "gn:admin2_code":"2911",
    "gn:asciiname":"Raghay Kelay",
    "gn:country_code":"AF",
    "gn:dem":2434,
    "gn:feature_class":"P",
    "gn:feature_code":"PPL",
    "gn:name":"Raghay K\u00ealay",
    "gn:population":0,
    "gn:timezone":"Asia/Kabul",
    "iso:country":"AF",
    "name:fas_x_preferred":[
        "\u0642\u0631\u064a\u06c0 \u0631\u063a\u06cc"
    ],
    "name:und_x_variant":[
        "Ragaykalay",
        "\u1e5eaghay Kalay",
        "Raghay K\u00ealay",
        "\u0631\u063a\u06cc \u06a9\u0644\u06cc",
        "\u0642\u0631\u064a\u06c0 \u0631\u063a\u06cc"
    ],
    "wof:name":"Raghay Kelay",
    "wof:placetype":"locality"
},
  "geometry": {"coordinates":[69.23674,33.06441],"type":"Point"}
}