{
  "type": "Feature",
  "properties": {
    "gn:admin1_code":"09",
    "gn:admin2_code":"2707",
    "gn:asciiname":"Qizil",
    "gn:country_code":"AF",
    "gn:dem":2727,
    "gn:feature_class":"P",
    "gn:feature_code":"PPL",
    "gn:name":"Qizil",
    "gn:population":0,
    "gn:timezone":"Asia/Kabul",
    "iso:country":"AF",
    "name:und_x_variant":[
        "Kizil",
        "Qezel",
        "Kyzyl",
        "Qizil Qala",
        "Qizil",
        "Q\u012bz\u012bl",
        "\u0642\u0632\u0644"
    ],
    "name:uzb_x_preferred":[
        "Qizil"
    ],
    "wof:name":"Qizil",
    "wof:placetype":"locality"
},
  "geometry": {"coordinates":[66.02436,34.47138],"type":"Point"}
}