{
  "type": "Feature",
  "properties": {
    "gn:admin1_code":"35",
    "gn:admin2_code":"905.0",
    "gn:asciiname":"Hasanzai",
    "gn:country_code":"AF",
    "gn:dem":919,
    "gn:feature_class":"P",
    "gn:feature_code":"PPL",
    "gn:name":"\u1e28asanza\u012b",
    "gn:population":0,
    "gn:timezone":"Asia/Kabul",
    "iso:country":"AF",
    "name:und_x_variant":[
        "Khasanzai",
        "\u1e28asanza\u2018i",
        "\u1e28asanza\u012b",
        "\u062d\u0633\u0646 \u0632\u06cc"
    ],
    "wof:name":"Hasanzai",
    "wof:placetype":"locality"
},
  "geometry": {"coordinates":[70.13039999999999,34.73116],"type":"Point"}
}