{
  "type": "Feature",
  "properties": {
    "gn:admin1_code":"37",
    "gn:admin2_code":"3211.0",
    "gn:asciiname":"Charkhay Kelay",
    "gn:country_code":"AF",
    "gn:dem":1364,
    "gn:feature_class":"P",
    "gn:feature_code":"PPL",
    "gn:name":"Charkhay K\u00ealay",
    "gn:population":0,
    "gn:timezone":"Asia/Kabul",
    "iso:country":"AF",
    "name:fas_x_preferred":[
        "\u0642\u0631\u06cc\u0647\u0654 \u0686\u0631\u062e\u06cc"
    ],
    "name:fas_x_variant":[
        "\u0686\u0631\u062e\u06cc \u0643\u0644\u06cc"
    ],
    "name:und_x_variant":[
        "\u010carkhay Kalay",
        "Charkhaikalay",
        "Charkhay K\u00ealay",
        "Charkhay Kalay"
    ],
    "wof:name":"Charkhay Kelay",
    "wof:placetype":"locality"
},
  "geometry": {"coordinates":[69.9969,33.15139],"type":"Point"}
}