{
  "type": "Feature",
  "properties": {
    "gn:admin1_code":"33",
    "gn:admin2_code":"3105",
    "gn:asciiname":"Mahi Khorha",
    "gn:country_code":"AF",
    "gn:dem":902,
    "gn:feature_class":"P",
    "gn:feature_code":"PPL",
    "gn:name":"M\u0101h\u012b Kh\u014drh\u0101",
    "gn:population":0,
    "gn:timezone":"Asia/Kabul",
    "iso:country":"AF",
    "name:und_x_variant":[
        "M\u0101h\u012b Khvorh\u0101",
        "M\u0101h\u012b Kh\u014drh\u0101",
        "\u0645\u0627\u0647\u06cc \u062e\u0648\u0631\u0647\u0627"
    ],
    "wof:name":"Mahi Khorha",
    "wof:placetype":"locality"
},
  "geometry": {"coordinates":[66.22635,36.09077],"type":"Point"}
}