{
  "type": "Feature",
  "properties": {
    "gn:admin1_code":"29",
    "gn:admin2_code":"2909.0",
    "gn:asciiname":"Khuram",
    "gn:country_code":"AF",
    "gn:dem":2127,
    "gn:feature_class":"P",
    "gn:feature_code":"PPL",
    "gn:name":"Khuram",
    "gn:population":0,
    "gn:timezone":"Asia/Kabul",
    "iso:country":"AF",
    "name:und_x_variant":[
        "Kho\u1e5fam",
        "Khorram",
        "Khuram",
        "\u062e\u0631\u0645"
    ],
    "wof:name":"Khuram",
    "wof:placetype":"locality"
},
  "geometry": {"coordinates":[69.26453000000001,32.90878],"type":"Point"}
}