{
  "type": "Feature",
  "properties": {
    "gn:admin1_code":"29",
    "gn:admin2_code":"2910.0",
    "gn:asciiname":"Toghah",
    "gn:country_code":"AF",
    "gn:dem":2097,
    "gn:feature_class":"P",
    "gn:feature_code":"PPL",
    "gn:name":"T\u014dghah",
    "gn:population":0,
    "gn:timezone":"Asia/Kabul",
    "iso:country":"AF",
    "name:und_x_variant":[
        "T\u014dgha",
        "Taga",
        "Towghah",
        "T\u014dghah",
        "\u062a\u0648\u063a\u0647"
    ],
    "wof:name":"Toghah",
    "wof:placetype":"locality"
},
  "geometry": {"coordinates":[69.37551999999999,32.9669],"type":"Point"}
}