{
  "type": "Feature",
  "properties": {
    "gn:admin1_code":"23",
    "gn:admin2_code":"2413.0",
    "gn:asciiname":"Churmay",
    "gn:country_code":"AF",
    "gn:dem":1690,
    "gn:feature_class":"P",
    "gn:feature_code":"PPL",
    "gn:name":"Churmay",
    "gn:population":0,
    "gn:timezone":"Asia/Kabul",
    "iso:country":"AF",
    "name:fas_x_preferred":[
        "\u0686\u0648\u0631\u0645\u06cc"
    ],
    "name:pus_x_preferred":[
        "\u0686\u0631\u0645\u06cc"
    ],
    "name:und_x_variant":[
        "\u010curmay",
        "Churmay"
    ],
    "wof:name":"Churmay",
    "wof:placetype":"locality"
},
  "geometry": {"coordinates":[67.1403,31.58976],"type":"Point"}
}