{
  "type": "Feature",
  "properties": {
    "gn:admin1_code":"06",
    "gn:admin2_code":"2111",
    "gn:asciiname":"Masaw",
    "gn:country_code":"AF",
    "gn:dem":667,
    "gn:feature_class":"P",
    "gn:feature_code":"PPL",
    "gn:name":"Mas\u0101w",
    "gn:population":0,
    "gn:timezone":"Asia/Kabul",
    "iso:country":"AF",
    "name:und_x_variant":[
        "Masow",
        "Masao",
        "Mas\u0101w",
        "\u0645\u0633\u0627\u0648",
        "Masau"
    ],
    "wof:name":"Masaw",
    "wof:placetype":"locality"
},
  "geometry": {"coordinates":[62.03612,32.48164000000001],"type":"Point"}
}