{
  "type": "Feature",
  "properties": {
    "gn:admin1_code":"09",
    "gn:admin2_code":"2705",
    "gn:asciiname":"Ghuchi",
    "gn:country_code":"AF",
    "gn:dem":2553,
    "gn:feature_class":"P",
    "gn:feature_code":"PPL",
    "gn:name":"Ghuch\u012b",
    "gn:population":0,
    "gn:timezone":"Asia/Kabul",
    "iso:country":"AF",
    "name:und_x_variant":[
        "Guchi",
        "Gho\u010di",
        "Ghuch\u012b",
        "\u063a\u0686\u06cc",
        "Ghoch\u012b"
    ],
    "wof:name":"Ghuchi",
    "wof:placetype":"locality"
},
  "geometry": {"coordinates":[64.59770999999999,33.64961],"type":"Point"}
}