{
  "type": "Feature",
  "properties": {
    "gn:admin1_code":"26",
    "gn:admin2_code":"1201",
    "gn:asciiname":"Ilftow",
    "gn:country_code":"AF",
    "gn:dem":889,
    "gn:feature_class":"P",
    "gn:feature_code":"PPL",
    "gn:name":"Ilftow",
    "gn:population":0,
    "gn:timezone":"Asia/Kabul",
    "iso:country":"AF",
    "name:und_x_variant":[
        "Elftaw",
        "\u0627\u0644\u0641\u062a\u0648"
    ],
    "wof:name":"Ilftow",
    "wof:placetype":"locality"
},
  "geometry": {"coordinates":[69.7607,36.80538],"type":"Point"}
}