{
  "type": "Feature",
  "properties": {
    "gn:admin1_code":"33",
    "gn:admin2_code":"3103",
    "gn:asciiname":"Jarofzar",
    "gn:country_code":"AF",
    "gn:dem":2235,
    "gn:feature_class":"P",
    "gn:feature_code":"PPL",
    "gn:name":"J\u0101r\u014dfz\u0101r",
    "gn:population":0,
    "gn:timezone":"Asia/Kabul",
    "iso:country":"AF",
    "name:und_x_variant":[
        "J\u0101\u1e5f\u014dfz\u0101\u1e5f",
        "J\u0101\u1e5fowfz\u0101\u1e5f",
        "J\u0101r\u014dfz\u0101r",
        "\u062c\u0627\u0631\u0648\u0641\u0632\u0627\u0631"
    ],
    "wof:name":"Jarofzar",
    "wof:placetype":"locality"
},
  "geometry": {"coordinates":[66.22816,35.05037],"type":"Point"}
}