{
  "type": "Feature",
  "properties": {
    "gn:admin1_code":"10",
    "gn:admin2_code":"2307",
    "gn:asciiname":"Lundak",
    "gn:country_code":"AF",
    "gn:dem":1235,
    "gn:feature_class":"P",
    "gn:feature_code":"PPL",
    "gn:name":"Lun\u1e0fak",
    "gn:population":0,
    "gn:timezone":"Asia/Kabul",
    "iso:country":"AF",
    "name:und_x_variant":[
        "Lun\u1e0fak",
        "\u0644\u0646\u0689\u06a9",
        "Lundak"
    ],
    "wof:name":"Lundak",
    "wof:placetype":"locality"
},
  "geometry": {"coordinates":[64.2919,32.27885],"type":"Point"}
}