{
  "type": "Feature",
  "properties": {
    "gn:admin1_code":"34",
    "gn:admin2_code":"1002.0",
    "gn:asciiname":"Sangam",
    "gn:country_code":"AF",
    "gn:dem":978,
    "gn:feature_class":"P",
    "gn:feature_code":"PPL",
    "gn:name":"S\u0101ng\u0101m",
    "gn:population":0,
    "gn:timezone":"Asia/Kabul",
    "iso:country":"AF",
    "name:fas_x_preferred":[
        "\u0633\u0646\u06af\u0645"
    ],
    "name:und_x_variant":[
        "S\u0101ng\u0101m",
        "\u0633\u0627\u0646\u06af\u0627\u0645",
        "Sangam"
    ],
    "wof:name":"Sangam",
    "wof:placetype":"locality"
},
  "geometry": {"coordinates":[71.19651999999998,34.87337],"type":"Point"}
}