{
  "type": "Feature",
  "properties": {
    "gn:admin1_code":"26",
    "gn:admin2_code":"1214",
    "gn:asciiname":"Dasht-e Qal'ah",
    "gn:country_code":"AF",
    "gn:dem":449,
    "gn:feature_class":"P",
    "gn:feature_code":"PPLA2",
    "gn:name":"Dasht-e Qal\u2018ah",
    "gn:population":0,
    "gn:timezone":"Asia/Kabul",
    "iso:country":"AF",
    "name:und_x_variant":[
        "Shahr-e Dasht-e Qal\u2018eh",
        "Dashti-Kala",
        "\u1e0eas\u0304t-i-Qal\u2019a",
        "\u1e0eas\u0304te Qal\u2018a",
        "Dasht Qala",
        "Dasht-e Qal\u2018eh",
        "Dasht-e Qal\u2018ah",
        "\u062f\u0634\u062a \u0642\u0644\u0639\u0647"
    ],
    "wof:name":"Dasht-e Qal'ah",
    "wof:placetype":"locality"
},
  "geometry": {"coordinates":[69.4435,37.1539],"type":"Point"}
}