{
  "type": "Feature",
  "properties": {
    "gn:admin1_code":"06",
    "gn:admin2_code":"2101",
    "gn:asciiname":"Shorabad",
    "gn:country_code":"AF",
    "gn:dem":651,
    "gn:feature_class":"P",
    "gn:feature_code":"PPL",
    "gn:name":"Sh\u014dr\u0101b\u0101d",
    "gn:population":0,
    "gn:timezone":"Asia/Kabul",
    "iso:country":"AF",
    "name:und_x_variant":[
        "\u0160or\u0101b\u0101d",
        "Sh\u014drab\u0101d",
        "Shorabad",
        "Sh\u016brab\u0101d",
        "Sh\u014dr\u0101b\u0101d",
        "\u0634\u0648\u0631 \u0622\u0628\u0627\u062f"
    ],
    "wof:name":"Shorabad",
    "wof:placetype":"locality"
},
  "geometry": {"coordinates":[62.07182,32.33827],"type":"Point"}
}