{
  "type": "Feature",
  "properties": {
    "gn:admin1_code":"23",
    "gn:admin2_code":"2402",
    "gn:asciiname":"Pay Jakan Kelay",
    "gn:country_code":"AF",
    "gn:dem":1203,
    "gn:feature_class":"P",
    "gn:feature_code":"PPL",
    "gn:name":"P\u0101y Jak\u0101n K\u00ealay",
    "gn:population":0,
    "gn:timezone":"Asia/Kabul",
    "iso:country":"AF",
    "name:und_x_variant":[
        "Paydzhakankalay",
        "\u067e\u0627\u06cc \u062c\u0627\u06cc \u06a9\u0644\u06cc",
        "P\u0101y Jak\u0101n Kalay",
        "P\u0101y J\u0101n K\u00ealay",
        "P\u0101y Jak\u0101n K\u00ealay",
        "\u067e\u0627\u06cc \u062c\u06a9\u0627\u0646 \u06a9\u0644\u06cc"
    ],
    "wof:name":"Pay Jakan Kelay",
    "wof:placetype":"locality"
},
  "geometry": {"coordinates":[66.11497,31.73714],"type":"Point"}
}