{
  "type": "Feature",
  "properties": {
    "gn:admin1_code":"26",
    "gn:admin2_code":"1205",
    "gn:asciiname":"Yangay",
    "gn:country_code":"AF",
    "gn:dem":2637,
    "gn:feature_class":"P",
    "gn:feature_code":"PPL",
    "gn:name":"Yangay",
    "gn:population":0,
    "gn:timezone":"Asia/Kabul",
    "iso:country":"AF",
    "name:und_x_variant":[
        "Yang\u012b",
        "Yangay",
        "\u06cc\u0646\u06af\u06cc"
    ],
    "wof:name":"Yangay",
    "wof:placetype":"locality"
},
  "geometry": {"coordinates":[70.02670999999999,36.01074000000001],"type":"Point"}
}