{
  "type": "Feature",
  "properties": {
    "gn:admin1_code":"18",
    "gn:admin2_code":"819.0",
    "gn:asciiname":"Shatlaw",
    "gn:country_code":"AF",
    "gn:dem":613,
    "gn:feature_class":"P",
    "gn:feature_code":"PPL",
    "gn:name":"Shatl\u0101w",
    "gn:population":0,
    "gn:timezone":"Asia/Kabul",
    "iso:country":"AF",
    "name:und_x_variant":[
        "\u0160atl\u0101w",
        "Shatlau",
        "S\u0332h\u0332atl\u0101w",
        "Shatl\u0101w",
        "\u0634\u062a\u0644\u0627\u0648",
        "Satl\u0101w",
        "\u0633\u062a\u0644\u0627\u0648"
    ],
    "wof:name":"Shatlaw",
    "wof:placetype":"locality"
},
  "geometry": {"coordinates":[70.64761999999997,34.58975],"type":"Point"}
}