{
  "type": "Feature",
  "properties": {
    "gn:admin1_code":"39",
    "gn:admin2_code":"2603",
    "gn:asciiname":"Kundilan",
    "gn:country_code":"AF",
    "gn:dem":2715,
    "gn:feature_class":"P",
    "gn:feature_code":"PPL",
    "gn:name":"Kundil\u0101n",
    "gn:population":0,
    "gn:timezone":"Asia/Kabul",
    "iso:country":"AF",
    "name:und_x_variant":[
        "Kun\u1e0fel\u0101n",
        "Kondel\u0101n",
        "Kundil\u0101n",
        "\u06a9\u0646\u062f\u0644\u0627\u0646"
    ],
    "wof:name":"Kundilan",
    "wof:placetype":"locality"
},
  "geometry": {"coordinates":[66.82811,33.01008],"type":"Point"}
}