{
  "type": "Feature",
  "properties": {
    "gn:admin1_code":"23",
    "gn:admin2_code":"2403.0",
    "gn:asciiname":"Dadgey",
    "gn:country_code":"AF",
    "gn:dem":1262,
    "gn:feature_class":"P",
    "gn:feature_code":"PPL",
    "gn:name":"Dadg\u00eay",
    "gn:population":0,
    "gn:timezone":"Asia/Kabul",
    "iso:country":"AF",
    "name:und_x_variant":[
        "Dadgay",
        "\u062f\u062f\u06af\u06cd",
        "Dadgey",
        "Dadg\u00eay"
    ],
    "wof:name":"Dadgey",
    "wof:placetype":"locality"
},
  "geometry": {"coordinates":[66.13353000000001,31.87011],"type":"Point"}
}