{
  "type": "Feature",
  "properties": {
    "gn:admin1_code":"05",
    "gn:admin2_code":"2805",
    "gn:asciiname":"Duqad",
    "gn:country_code":"AF",
    "gn:dem":3222,
    "gn:feature_class":"P",
    "gn:feature_code":"PPL",
    "gn:name":"Duqad",
    "gn:population":0,
    "gn:timezone":"Asia/Kabul",
    "iso:country":"AF",
    "name:fas_x_preferred":[
        "\u062f\u0648 \u0642\u062f"
    ],
    "name:rus_x_preferred":[
        "\u0414\u0443\u043a\u0430\u0434"
    ],
    "name:und_x_variant":[
        "Dukad",
        "D\u014d Qad",
        "Doqad",
        "Duqad",
        "\u062f\u0642\u062f"
    ],
    "wof:name":"Duqad",
    "wof:placetype":"locality"
},
  "geometry": {"coordinates":[67.1022,34.54465],"type":"Point"}
}