{
  "type": "Feature",
  "properties": {
    "gn:admin1_code":"23",
    "gn:admin2_code":"2402.0",
    "gn:asciiname":"Gari Kelay",
    "gn:country_code":"AF",
    "gn:dem":1138,
    "gn:feature_class":"P",
    "gn:feature_code":"PPL",
    "gn:name":"Ga\u1e5f\u012b K\u00ealay",
    "gn:population":0,
    "gn:timezone":"Asia/Kabul",
    "iso:country":"AF",
    "name:fas_x_preferred":[
        "\u0642\u0631\u064a\u06c0 \u06af\u0631\u06cc"
    ],
    "name:und_x_variant":[
        "Garkalay",
        "\u06af\u0693\u06cc \u06a9\u0644\u06cc",
        "Gar\u012b Kalay",
        "Ga\u1e5f\u012b K\u00ealay"
    ],
    "wof:name":"Gari Kelay",
    "wof:placetype":"locality"
},
  "geometry": {"coordinates":[66.00596999999999,31.7421],"type":"Point"}
}