{
  "type": "Feature",
  "properties": {
    "gn:admin1_code":"17",
    "gn:admin2_code":"506.0",
    "gn:asciiname":"Dadi Khel",
    "gn:country_code":"AF",
    "gn:dem":2458,
    "gn:feature_class":"P",
    "gn:feature_code":"PPL",
    "gn:name":"D\u0101d\u012b Kh\u0113l",
    "gn:population":0,
    "gn:timezone":"Asia/Kabul",
    "iso:country":"AF",
    "name:fas_x_preferred":[
        "\u062f\u0627\u062f\u06cc \u062e\u064a\u0644"
    ],
    "name:rus_x_preferred":[
        "Dadikheyl\u2019"
    ],
    "name:und_x_variant":[
        "\u1e0e\u0101\u1e0fikh\u0113l",
        "D\u0101d\u012b Kh\u0113l",
        "D\u0101dikheyl",
        "\u062f\u0627\u062f\u06cc \u062e\u064a\u0644",
        "\u062f\u0627\u062f\u06cc \u062e\u06d0\u0644"
    ],
    "wof:name":"Dadi Khel",
    "wof:placetype":"locality"
},
  "geometry": {"coordinates":[69.73558,34.12069],"type":"Point"}
}