{
  "type": "Feature",
  "properties": {
    "gn:admin1_code":"41",
    "gn:admin2_code":"3406",
    "gn:asciiname":"Zarni",
    "gn:country_code":"AF",
    "gn:dem":1412,
    "gn:feature_class":"P",
    "gn:feature_code":"PPL",
    "gn:name":"Zarn\u012b",
    "gn:population":0,
    "gn:timezone":"Asia/Kabul",
    "iso:country":"AF",
    "name:und_x_variant":[
        "Zarn\u012b",
        "\u0632\u0631\u0646\u06cc",
        "Za\u1e5fni"
    ],
    "wof:name":"Zarni",
    "wof:placetype":"locality"
},
  "geometry": {"coordinates":[65.7056,33.45652],"type":"Point"}
}