{
  "type": "Feature",
  "properties": {
    "gn:admin1_code":"18",
    "gn:admin2_code":"810.0",
    "gn:asciiname":"Girdi",
    "gn:country_code":"AF",
    "gn:dem":1124,
    "gn:feature_class":"P",
    "gn:feature_code":"PPL",
    "gn:name":"Gird\u012b",
    "gn:population":0,
    "gn:timezone":"Asia/Kabul",
    "iso:country":"AF",
    "name:und_x_variant":[
        "Gerdi",
        "Gird\u012b",
        "\u06af\u0631\u062f\u06cc"
    ],
    "wof:name":"Girdi",
    "wof:placetype":"locality"
},
  "geometry": {"coordinates":[70.66676,34.10866],"type":"Point"}
}