{
  "type": "Feature",
  "properties": {
    "gn:admin1_code":"26",
    "gn:admin2_code":"1210.0",
    "gn:asciiname":"Moghulan",
    "gn:country_code":"AF",
    "gn:dem":769,
    "gn:feature_class":"P",
    "gn:feature_code":"PPL",
    "gn:name":"Moghul\u0101n",
    "gn:population":0,
    "gn:timezone":"Asia/Kabul",
    "iso:country":"AF",
    "name:und_x_variant":[
        "Mughul\u0101n (2)",
        "Moghol\u0101n (2)",
        "Moghul\u0101n",
        "\u0645\u063a\u0644\u0627\u0646"
    ],
    "wof:name":"Moghulan",
    "wof:placetype":"locality"
},
  "geometry": {"coordinates":[69.73340999999999,37.38992],"type":"Point"}
}