{
  "type": "Feature",
  "properties": {
    "gn:admin1_code":"3",
    "gn:admin2_code":"1303.0",
    "gn:asciiname":"Band-e Sabzak",
    "gn:country_code":"AF",
    "gn:dem":2267,
    "gn:feature_class":"P",
    "gn:feature_code":"PPL",
    "gn:name":"Band-e Sabzak",
    "gn:population":0,
    "gn:timezone":"Asia/Kabul",
    "iso:country":"AF",
    "name:und_x_variant":[
        "\u0628\u0646\u062f \u0633\u0628\u0632\u06a9"
    ],
    "wof:name":"Band-e Sabzak",
    "wof:placetype":"locality"
},
  "geometry": {"coordinates":[68.45014,35.69935],"type":"Point"}
}