{
  "type": "Feature",
  "properties": {
    "gn:admin1_code":"05",
    "gn:admin2_code":"2804",
    "gn:asciiname":"Kalak",
    "gn:country_code":"AF",
    "gn:dem":2294,
    "gn:feature_class":"P",
    "gn:feature_code":"PPL",
    "gn:name":"Kalak",
    "gn:population":0,
    "gn:timezone":"Asia/Kabul",
    "iso:country":"AF",
    "name:ceb_x_preferred":[
        "Kalak"
    ],
    "name:swe_x_preferred":[
        "Kalak"
    ],
    "name:und_x_variant":[
        "\u06a9\u0644\u06a9"
    ],
    "wof:name":"Kalak",
    "wof:placetype":"locality"
},
  "geometry": {"coordinates":[66.50846,34.9611],"type":"Point"}
}