{
  "type": "Feature",
  "properties": {
    "gn:admin1_code":"18",
    "gn:admin2_code":"809.0",
    "gn:asciiname":"Roghani",
    "gn:country_code":"AF",
    "gn:dem":860,
    "gn:feature_class":"P",
    "gn:feature_code":"PPL",
    "gn:name":"R\u014dghan\u012b",
    "gn:population":0,
    "gn:timezone":"Asia/Kabul",
    "iso:country":"AF",
    "name:und_x_variant":[
        "R\u014dghani",
        "Rogani",
        "Rowghan\u012b",
        "R\u014dghan\u012b",
        "\u0631\u0648\u063a\u0646\u06cc"
    ],
    "wof:name":"Roghani",
    "wof:placetype":"locality"
},
  "geometry": {"coordinates":[70.53369000000001,34.2353],"type":"Point"}
}