{
  "type": "Feature",
  "properties": {
    "gn:admin1_code":"8",
    "gn:admin2_code":"609.0",
    "gn:asciiname":"Mastan Kala",
    "gn:country_code":"AF",
    "gn:dem":1938,
    "gn:feature_class":"P",
    "gn:feature_code":"PPL",
    "gn:name":"Mast\u0101n Kal\u0101",
    "gn:population":0,
    "gn:timezone":"Asia/Kabul",
    "iso:country":"AF",
    "name:und_x_variant":[
        "Mast\u0101n Kal\u0101",
        "\u0645\u0633\u062a\u0627\u0646 \u06a9\u0644\u0627"
    ],
    "wof:name":"Mastan Kala",
    "wof:placetype":"locality"
},
  "geometry": {"coordinates":[67.73019000000001,32.68169],"type":"Point"}
}