{
  "type": "Feature",
  "properties": {
    "gn:admin1_code":"11",
    "gn:admin2_code":"2006",
    "gn:asciiname":"Nur Zai",
    "gn:country_code":"AF",
    "gn:dem":796,
    "gn:feature_class":"P",
    "gn:feature_code":"PPL",
    "gn:name":"N\u016br Za\u012b",
    "gn:population":0,
    "gn:timezone":"Asia/Kabul",
    "iso:country":"AF",
    "name:und_x_variant":[
        "Nurzai",
        "N\u016br Za\u012b",
        "\u0646\u0648\u0631 \u0632\u06cc",
        "N\u016brz\u0101\u2019i"
    ],
    "wof:name":"Nur Zai",
    "wof:placetype":"locality"
},
  "geometry": {"coordinates":[62.31519,35.08267],"type":"Point"}
}