{
  "type": "Feature",
  "properties": {
    "gn:admin1_code":"06",
    "gn:admin2_code":"2101",
    "gn:asciiname":"Khoshdil Khan Karez",
    "gn:country_code":"AF",
    "gn:dem":777,
    "gn:feature_class":"P",
    "gn:feature_code":"PPL",
    "gn:name":"Kh\u014dshdil Kh\u0101n K\u0101r\u0113z",
    "gn:population":0,
    "gn:timezone":"Asia/Kabul",
    "iso:country":"AF",
    "name:fas_x_preferred":[
        "\u062e\u0648\u0634\u062f\u0644 \u062e\u0627\u0646 \u0643\u0627\u0631\u064a\u0632"
    ],
    "name:rus_x_preferred":[
        "Khushdil\u2019khankarez"
    ],
    "name:und_x_variant":[
        "Khoshdel Kh\u0101n K\u0101r\u012bz",
        "Khu\u0161delkh\u0101n K\u0101r\u0113z",
        "Khus\u0304\u1e0felkh\u0101n K\u0101r\u012bz",
        "Khvoshdel Kh\u0101n K\u0101r\u012bz",
        "Kh\u014dshdil Kh\u0101n K\u0101r\u0113z",
        "\u062e\u0648\u0634\u062f\u0644 \u062e\u0627\u0646 \u06a9\u0627\u0631\u06d0\u0632"
    ],
    "wof:name":"Khoshdil Khan Karez",
    "wof:placetype":"locality"
},
  "geometry": {"coordinates":[62.46078000000001,32.29179],"type":"Point"}
}