{
  "type": "Feature",
  "properties": {
    "gn:admin1_code":"08",
    "gn:admin2_code":"609",
    "gn:asciiname":"Tadzh",
    "gn:country_code":"AF",
    "gn:dem":1986,
    "gn:feature_class":"P",
    "gn:feature_code":"PPL",
    "gn:name":"Tadzh",
    "gn:population":0,
    "gn:timezone":"Asia/Kabul",
    "iso:country":"AF",
    "name:und_x_variant":[
        "T\u0101j",
        "\u062a\u0627\u062c"
    ],
    "wof:name":"Tadzh",
    "wof:placetype":"locality"
},
  "geometry": {"coordinates":[67.76675999999999,32.62765],"type":"Point"}
}