{
  "type": "Feature",
  "properties": {
    "gn:admin1_code":"13",
    "gn:admin2_code":"107.0",
    "gn:asciiname":"Qal'ah-ye Dasht",
    "gn:country_code":"AF",
    "gn:dem":1905,
    "gn:feature_class":"P",
    "gn:feature_code":"PPL",
    "gn:name":"Qal\u2018ah-ye Dasht",
    "gn:population":0,
    "gn:timezone":"Asia/Kabul",
    "iso:country":"AF",
    "name:und_x_variant":[
        "Kaladasht",
        "Qal\u2018a Da\u0161t",
        "Qal\u2018eh-ye Dasht",
        "\u0642\u0644\u0639\u06c0 \u062f\u0634\u062a",
        "Qal\u2018ah-ye Dasht"
    ],
    "wof:name":"Qal'ah-ye Dasht",
    "wof:placetype":"locality"
},
  "geometry": {"coordinates":[69.06740000000001,34.61457],"type":"Point"}
}