{
  "type": "Feature",
  "properties": {
    "gn:admin1_code":"11",
    "gn:admin2_code":"2014",
    "gn:asciiname":"Qal'ah-ye Mirza Aslam",
    "gn:country_code":"AF",
    "gn:dem":1141,
    "gn:feature_class":"P",
    "gn:feature_code":"PPL",
    "gn:name":"Qal\u2018ah-ye M\u012brz\u0101 Aslam",
    "gn:population":0,
    "gn:timezone":"Asia/Kabul",
    "iso:country":"AF",
    "name:fas_x_preferred":[
        "\u0642\u0644\u063a\u0647\u0654 \u0645\u064a\u0631\u0632\u0627 \u0627\u0633\u0644\u0645"
    ],
    "name:und_x_variant":[
        "Qal\u2018a-i-M\u012b\u1e5fz\u0101 Aslam",
        "Kalayi-Mirza-Aslam",
        "Qal\u2018eh-ye M\u012brz\u0101 Aslam",
        "Qal\u2018ah-ye M\u012brz\u0101 Aslam",
        "\u0642\u0644\u0639\u06c0 \u0645\u06cc\u0631\u0632\u0627 \u0627\u0633\u0644\u0645"
    ],
    "wof:name":"Qal'ah-ye Mirza Aslam",
    "wof:placetype":"locality"
},
  "geometry": {"coordinates":[62.30268,33.38911],"type":"Point"}
}