{
  "type": "Feature",
  "properties": {
    "gn:admin1_code":"06",
    "gn:admin2_code":"2103",
    "gn:asciiname":"Pay Tangi",
    "gn:country_code":"AF",
    "gn:dem":1109,
    "gn:feature_class":"P",
    "gn:feature_code":"PPL",
    "gn:name":"P\u0101y Tang\u012b",
    "gn:population":0,
    "gn:timezone":"Asia/Kabul",
    "iso:country":"AF",
    "name:und_x_variant":[
        "Paytangay",
        "P\u0101y Tang\u012b",
        "\u067e\u0627\u06cc \u062a\u0646\u06af\u06cc",
        "P\u0101ytangay"
    ],
    "wof:name":"Pay Tangi",
    "wof:placetype":"locality"
},
  "geometry": {"coordinates":[63.30971,32.9908],"type":"Point"}
}