{
  "type": "Feature",
  "properties": {
    "gn:admin1_code":"09",
    "gn:admin2_code":"2706",
    "gn:asciiname":"Siyah Sangak",
    "gn:country_code":"AF",
    "gn:dem":2719,
    "gn:feature_class":"P",
    "gn:feature_code":"PPL",
    "gn:name":"Siy\u0101h Sangak",
    "gn:population":0,
    "gn:timezone":"Asia/Kabul",
    "iso:country":"AF",
    "name:rus_x_preferred":[
        "S\u2019yasangak"
    ],
    "name:und_x_variant":[
        "Sy\u0101sangak",
        "S\u012b\u0101h Sangak",
        "\u0633\u06cc\u0627\u0647 \u0633\u0646\u06af\u06a9",
        "Siy\u0101h Sangak"
    ],
    "wof:name":"Siyah Sangak",
    "wof:placetype":"locality"
},
  "geometry": {"coordinates":[64.89921,33.59411],"type":"Point"}
}