{
  "type": "Feature",
  "properties": {
    "gn:admin1_code":"26",
    "gn:admin2_code":"1201.0",
    "gn:asciiname":"Chashmah-ye Sher",
    "gn:country_code":"AF",
    "gn:dem":756,
    "gn:feature_class":"P",
    "gn:feature_code":"PPL",
    "gn:name":"Chashmah-ye Sh\u0113r",
    "gn:population":0,
    "gn:timezone":"Asia/Kabul",
    "iso:country":"AF",
    "name:fas_x_preferred":[
        "\u0686\u0634\u0645\u06c0 \u0634\u064a\u0631"
    ],
    "name:rus_x_preferred":[
        "\u0427\u0430\u0448\u043c\u0430\u0439\u0438-\u0428\u0435\u0440"
    ],
    "name:und_x_variant":[
        "\u010ca\u0161ma-i-\u0160\u0113r",
        "Chashmayi-Sher",
        "Cheshmeh-ye Sh\u012br",
        "Chashmah-ye Shayr",
        "\u0686\u0634\u0645\u06c0 \u0634\u06cc\u0631",
        "Chashmah-ye Sh\u0113r"
    ],
    "wof:name":"Chashmah-ye Sher",
    "wof:placetype":"locality"
},
  "geometry": {"coordinates":[69.45741,36.71627],"type":"Point"}
}