{
  "type": "Feature",
  "properties": {
    "gn:admin1_code":"01",
    "gn:admin2_code":"1115",
    "gn:asciiname":"Khaksari",
    "gn:country_code":"AF",
    "gn:dem":1615,
    "gn:feature_class":"P",
    "gn:feature_code":"PPL",
    "gn:name":"Kh\u0101ks\u0101r\u012b",
    "gn:population":0,
    "gn:timezone":"Asia/Kabul",
    "iso:country":"AF",
    "name:und_x_variant":[
        "Kh\u0101ks\u0101r\u012b",
        "\u062e\u0627\u06a9\u0633\u0627\u0631\u06cc",
        "Kh\u0101ksa\u1e5fi"
    ],
    "wof:name":"Khaksari",
    "wof:placetype":"locality"
},
  "geometry": {"coordinates":[70.36448,37.0818],"type":"Point"}
}