{
  "type": "Feature",
  "properties": {
    "gn:admin1_code":"27",
    "gn:admin2_code":"404.0",
    "gn:asciiname":"Jol-e 'Ala Nazar",
    "gn:country_code":"AF",
    "gn:dem":2813,
    "gn:feature_class":"P",
    "gn:feature_code":"PPL",
    "gn:name":"J\u014dl-e \u2018Al\u0101 Naz\u0327ar",
    "gn:population":0,
    "gn:timezone":"Asia/Kabul",
    "iso:country":"AF",
    "name:und_x_variant":[
        "Dzholi-Alanazar",
        "J\u014dle Al\u0101na\u1e95a\u1e5f",
        "J\u016bl-e Al\u0101naz\u0327ar",
        "J\u014dl-e \u2018Al\u00e1 Naz\u0327ar",
        "J\u014dl-e \u2018Al\u0101 Naz\u0327ar",
        "\u062c\u0648\u0644 \u0639\u0644\u0627 \u0646\u0638\u0631"
    ],
    "wof:name":"Jol-e 'Ala Nazar",
    "wof:placetype":"locality"
},
  "geometry": {"coordinates":[67.39322,34.48486],"type":"Point"}
}