{
  "type": "Feature",
  "properties": {
    "gn:admin1_code":"33",
    "gn:admin2_code":"3104.0",
    "gn:asciiname":"Alakah",
    "gn:country_code":"AF",
    "gn:dem":1928,
    "gn:feature_class":"P",
    "gn:feature_code":"PPL",
    "gn:name":"Alakah",
    "gn:population":0,
    "gn:timezone":"Asia/Kabul",
    "iso:country":"AF",
    "name:und_x_variant":[
        "Bedak",
        "Alaka",
        "Deh Allakah",
        "Deh Alakah",
        "Deh All\u0101ka",
        "Alakeh",
        "Alakah",
        "\u0627\u0644\u06a9\u0647"
    ],
    "wof:name":"Alakah",
    "wof:placetype":"locality"
},
  "geometry": {"coordinates":[66.74391,35.63531],"type":"Point"}
}