{
  "type": "Feature",
  "properties": {
    "gn:admin1_code":"29",
    "gn:admin2_code":"2909.0",
    "gn:asciiname":"De Pash Khunah",
    "gn:country_code":"AF",
    "gn:dem":2293,
    "gn:feature_class":"P",
    "gn:feature_code":"PPL",
    "gn:name":"D\u00ea Pas\u0332h\u0332 Kh\u016bnah",
    "gn:population":0,
    "gn:timezone":"Asia/Kabul",
    "iso:country":"AF",
    "name:und_x_variant":[
        "Pashkhune",
        "De Pa\u0161 Khon\u0113",
        "D\u00ea Pas\u0332h\u0332 Kh\u016bn\u0113",
        "De Pash Khon\u0113",
        "D\u00ea Pas\u0332h\u0332 Khun\u0113",
        "D\u00ea Pas\u0332h\u0332 Kh\u016bnah",
        "\u062f \u067e\u069a \u062e\u0648\u0646\u0647"
    ],
    "wof:name":"De Pash Khunah",
    "wof:placetype":"locality"
},
  "geometry": {"coordinates":[69.30311,32.57515],"type":"Point"}
}