{
  "type": "Feature",
  "properties": {
    "gn:admin1_code":"8",
    "gn:admin2_code":"604.0",
    "gn:asciiname":"Alday",
    "gn:country_code":"AF",
    "gn:dem":3143,
    "gn:feature_class":"P",
    "gn:feature_code":"PPL",
    "gn:name":"Alday",
    "gn:population":0,
    "gn:timezone":"Asia/Kabul",
    "iso:country":"AF",
    "name:rus_x_preferred":[
        "\u0410\u043b\u044c\u0434\u0430\u0439"
    ],
    "name:und_x_variant":[
        "Al\u2019day",
        "Alday",
        "\u0627\u0644\u062f\u06cc"
    ],
    "wof:name":"Alday",
    "wof:placetype":"locality"
},
  "geometry": {"coordinates":[67.7428,33.73112],"type":"Point"}
}