{
  "type": "Feature",
  "properties": {
    "gn:admin1_code":"13",
    "gn:admin2_code":"105",
    "gn:asciiname":"Jarchi",
    "gn:country_code":"AF",
    "gn:dem":1518,
    "gn:feature_class":"P",
    "gn:feature_code":"PPL",
    "gn:name":"J\u0101rch\u012b",
    "gn:population":0,
    "gn:timezone":"Asia/Kabul",
    "iso:country":"AF",
    "name:aze_x_preferred":[
        "Car\u00e7\u0131"
    ],
    "name:und_x_variant":[
        "Dzharchi",
        "J\u0101r\u010di",
        "J\u0101rch\u012b",
        "\u062c\u0627\u0631\u0686\u06cc"
    ],
    "wof:name":"Jarchi",
    "wof:placetype":"locality"
},
  "geometry": {"coordinates":[69.20059000000001,34.87978],"type":"Point"}
}