{
  "type": "Feature",
  "properties": {
    "gn:admin1_code":"13",
    "gn:admin2_code":"106.0",
    "gn:asciiname":"Qal'ah-ye Salar",
    "gn:country_code":"AF",
    "gn:dem":1719,
    "gn:feature_class":"P",
    "gn:feature_code":"PPL",
    "gn:name":"Qal\u2018ah-ye S\u0101l\u0101r",
    "gn:population":0,
    "gn:timezone":"Asia/Kabul",
    "iso:country":"AF",
    "name:und_x_variant":[
        "Kalayi-Salar",
        "Qal\u0101-i-S\u0101l\u0101\u1e5f",
        "Qal\u2018eh-ye S\u0101l\u0101r",
        "\u0642\u0644\u0639\u06c0 \u0633\u0627\u0644\u0627\u0631",
        "Qal\u2018ah-ye S\u0101l\u0101r"
    ],
    "wof:name":"Qal'ah-ye Salar",
    "wof:placetype":"locality"
},
  "geometry": {"coordinates":[69.09673000000001,34.81394],"type":"Point"}
}