{
  "type": "Feature",
  "properties": {
    "gn:admin1_code":"8",
    "gn:admin2_code":"607.0",
    "gn:asciiname":"Maysah",
    "gn:country_code":"AF",
    "gn:dem":2816,
    "gn:feature_class":"P",
    "gn:feature_code":"PPL",
    "gn:name":"Maysah",
    "gn:population":0,
    "gn:timezone":"Asia/Kabul",
    "iso:country":"AF",
    "name:und_x_variant":[
        "Maysa",
        "Maysah",
        "\u0645\u06cc\u0633\u0647"
    ],
    "wof:name":"Maysah",
    "wof:placetype":"locality"
},
  "geometry": {"coordinates":[67.2839,33.10736],"type":"Point"}
}