{
  "type": "Feature",
  "properties": {
    "gn:admin1_code":"09",
    "gn:admin2_code":"2701",
    "gn:asciiname":"Sokhtah-ye 'Ulya",
    "gn:country_code":"AF",
    "gn:dem":2506,
    "gn:feature_class":"P",
    "gn:feature_code":"PPL",
    "gn:name":"S\u014dkhtah-ye \u2018Uly\u0101",
    "gn:population":0,
    "gn:timezone":"Asia/Kabul",
    "iso:country":"AF",
    "name:und_x_variant":[
        "Sokhtayi-Ulia",
        "S\u014dkhta-i-\u2018Uly\u0101",
        "S\u016bkhteh-ye \u2018Oly\u0101",
        "S\u014dkhtah-ye \u2018Uly\u0101",
        "\u0633\u0648\u062e\u062a\u06c0 \u0639\u0644\u06cc\u0627"
    ],
    "wof:name":"Sokhtah-ye 'Ulya",
    "wof:placetype":"locality"
},
  "geometry": {"coordinates":[64.92511999999999,34.38505],"type":"Point"}
}