{
  "type": "Feature",
  "properties": {
    "gn:admin1_code":"26",
    "gn:admin2_code":"1205",
    "gn:asciiname":"Qal'achah",
    "gn:country_code":"AF",
    "gn:dem":2281,
    "gn:feature_class":"P",
    "gn:feature_code":"PPL",
    "gn:name":"Qal\u2018achah",
    "gn:population":0,
    "gn:timezone":"Asia/Kabul",
    "iso:country":"AF",
    "name:und_x_variant":[
        "Qal\u2018acha",
        "Qal\u2018ehcheh",
        "Qal\u2018achah",
        "\u0642\u0644\u0639\u0686\u0647"
    ],
    "wof:name":"Qal'achah",
    "wof:placetype":"locality"
},
  "geometry": {"coordinates":[70.24330999999999,36.11809],"type":"Point"}
}