{
  "type": "Feature",
  "properties": {
    "gn:admin1_code":"09",
    "gn:admin2_code":"2707",
    "gn:asciiname":"Sang Zard",
    "gn:country_code":"AF",
    "gn:dem":2591,
    "gn:feature_class":"P",
    "gn:feature_code":"PPL",
    "gn:name":"Sang Zard",
    "gn:population":0,
    "gn:timezone":"Asia/Kabul",
    "iso:country":"AF",
    "name:und_x_variant":[
        "Sang-i-Zard",
        "Sangzard",
        "Sang-e Zard",
        "Sang Zard",
        "\u0633\u0646\u06af \u0632\u0631\u062f"
    ],
    "wof:name":"Sang Zard",
    "wof:placetype":"locality"
},
  "geometry": {"coordinates":[66.04373000000001,34.58436],"type":"Point"}
}