{
  "type": "Feature",
  "properties": {
    "gn:admin1_code":"37",
    "gn:admin2_code":"3201.0",
    "gn:asciiname":"Khargay",
    "gn:country_code":"AF",
    "gn:dem":1076,
    "gn:feature_class":"P",
    "gn:feature_code":"PPL",
    "gn:name":"Khargay",
    "gn:population":0,
    "gn:timezone":"Asia/Kabul",
    "iso:country":"AF",
    "name:und_x_variant":[
        "Kha\u1e5fgay",
        "\u062e\u0631\u06af\u06cc"
    ],
    "wof:name":"Khargay",
    "wof:placetype":"locality"
},
  "geometry": {"coordinates":[70.05880999999999,33.32268],"type":"Point"}
}