{
  "type": "Feature",
  "properties": {
    "gn:admin1_code":"33",
    "gn:admin2_code":"3106",
    "gn:asciiname":"Sayad",
    "gn:country_code":"AF",
    "gn:dem":946,
    "gn:feature_class":"P",
    "gn:feature_code":"PPLA2",
    "gn:name":"\u015eay\u0101d",
    "gn:population":0,
    "gn:timezone":"Asia/Kabul",
    "iso:country":"AF",
    "name:ceb_x_preferred":[
        "Sayad"
    ],
    "name:fra_x_preferred":[
        "Sayad"
    ],
    "name:swe_x_preferred":[
        "Sayad"
    ],
    "name:und_x_variant":[
        "Saiyid",
        "Saiad",
        "Seyyed",
        "\u015eay\u0101d",
        "\u0635\u06cc\u0627\u062f"
    ],
    "wof:name":"Sayad",
    "wof:placetype":"locality"
},
  "geometry": {"coordinates":[65.8297,36.13529000000001],"type":"Point"}
}