{
  "type": "Feature",
  "properties": {
    "gn:admin1_code":"01",
    "gn:admin2_code":"1121",
    "gn:asciiname":"Zangirya",
    "gn:country_code":"AF",
    "gn:dem":1131,
    "gn:feature_class":"P",
    "gn:feature_code":"PPL",
    "gn:name":"Zangiry\u0101",
    "gn:population":0,
    "gn:timezone":"Asia/Kabul",
    "iso:country":"AF",
    "name:und_x_variant":[
        "Zangr\u012b\u0101",
        "Zangriya",
        "\u0632\u0646\u06af\u0631\u06cc\u0627",
        "Zangery\u0101",
        "Zangir\u012b\u0101",
        "Zangiry\u0101"
    ],
    "wof:name":"Zangirya",
    "wof:placetype":"locality"
},
  "geometry": {"coordinates":[70.60939,38.31327],"type":"Point"}
}