{
  "type": "Feature",
  "properties": {
    "gn:admin1_code":"06",
    "gn:admin2_code":"2104",
    "gn:asciiname":"Walimah",
    "gn:country_code":"AF",
    "gn:dem":2248,
    "gn:feature_class":"P",
    "gn:feature_code":"PPL",
    "gn:name":"Wal\u012bmah",
    "gn:population":0,
    "gn:timezone":"Asia/Kabul",
    "iso:country":"AF",
    "name:und_x_variant":[
        "B\u014dlma",
        "Valm",
        "Walma",
        "Wulma",
        "Walima",
        "Bowlameh",
        "Wal\u012bmah",
        "\u0648\u0644\u06cc\u0645\u0647",
        "Val\u012bmeh",
        "B\u014dlmah",
        "\u0628\u0648\u0644\u0645\u0647"
    ],
    "wof:name":"Walimah",
    "wof:placetype":"locality"
},
  "geometry": {"coordinates":[63.85638,33.42799],"type":"Point"}
}