{
  "type": "Feature",
  "properties": {
    "gn:admin1_code":"33",
    "gn:admin2_code":"3101",
    "gn:asciiname":"Nowakai",
    "gn:country_code":"AF",
    "gn:dem":541,
    "gn:feature_class":"P",
    "gn:feature_code":"PPL",
    "gn:name":"Nowaka\u012b",
    "gn:population":0,
    "gn:timezone":"Asia/Kabul",
    "iso:country":"AF",
    "name:und_x_variant":[
        "Nowaka\u012b",
        "\u0646\u0648\u06a9\u06cc",
        "Nawakai"
    ],
    "wof:name":"Nowakai",
    "wof:placetype":"locality"
},
  "geometry": {"coordinates":[65.94049,36.32644000000001],"type":"Point"}
}