{
  "type": "Feature",
  "properties": {
    "gn:admin1_code":"8",
    "gn:admin2_code":"608.0",
    "gn:asciiname":"Asghar Khel-e Shamali",
    "gn:country_code":"AF",
    "gn:dem":1993,
    "gn:feature_class":"P",
    "gn:feature_code":"PPL",
    "gn:name":"A\u015fghar Kh\u0113l-e Sham\u0101l\u012b",
    "gn:population":0,
    "gn:timezone":"Asia/Kabul",
    "iso:country":"AF",
    "name:und_x_variant":[
        "Asgarkheyli-Dzhanubi",
        "Asgharkh\u0113le \u0160am\u0101li",
        "A\u015fghar Kheyl-e Shom\u0101l\u012b",
        "A\u015fghar Kh\u0113l-e Sham\u0101l\u012b",
        "\u0627\u0635\u063a\u0631 \u062e\u06d0\u0644 \u0634\u0645\u0627\u0644\u06cc"
    ],
    "wof:name":"Asghar Khel-e Shamali",
    "wof:placetype":"locality"
},
  "geometry": {"coordinates":[67.79769,32.81793],"type":"Point"}
}