{
  "type": "Feature",
  "properties": {
    "gn:admin1_code":"18",
    "gn:admin2_code":"804",
    "gn:asciiname":"Pishdare",
    "gn:country_code":"AF",
    "gn:dem":1460,
    "gn:feature_class":"P",
    "gn:feature_code":"PPL",
    "gn:name":"Pis\u0332h\u0332dar\u0113",
    "gn:population":0,
    "gn:timezone":"Asia/Kabul",
    "iso:country":"AF",
    "name:fas_x_preferred":[
        "\u062f\u0631\u06c0 \u067e\u064a\u0634"
    ],
    "name:und_x_variant":[
        "Peshdare",
        "Pishdare",
        "Pe\u0161dar\u0113",
        "Peshdar\u0113",
        "P\u012bsh Darreh",
        "Pis\u0332h\u0332dar\u0113",
        "\u067e\u069a\u062f\u0631\u06d0",
        "Paysh Dar\u012b",
        "\u067e\u06cc\u0634 \u062f\u0631\u06cc"
    ],
    "wof:name":"Pishdare",
    "wof:placetype":"locality"
},
  "geometry": {"coordinates":[69.9344,34.2733],"type":"Point"}
}