{
  "type": "Feature",
  "properties": {
    "gn:admin1_code":"38",
    "gn:admin2_code":"3004.0",
    "gn:asciiname":"Shaladur",
    "gn:country_code":"AF",
    "gn:dem":2735,
    "gn:feature_class":"P",
    "gn:feature_code":"PPL",
    "gn:name":"Shaladur",
    "gn:population":0,
    "gn:timezone":"Asia/Kabul",
    "iso:country":"AF",
    "name:und_x_variant":[
        "Sala\u1e0fu\u1e5f",
        "\u0634\u0644\u062f\u0631",
        "Shaladur"
    ],
    "wof:name":"Shaladur",
    "wof:placetype":"locality"
},
  "geometry": {"coordinates":[70.15804,35.38695999999999],"type":"Point"}
}