{
  "type": "Feature",
  "properties": {
    "gn:admin1_code":"07",
    "gn:admin2_code":"1811.0",
    "gn:asciiname":"Qanli Chahar Bagh",
    "gn:country_code":"AF",
    "gn:dem":281,
    "gn:feature_class":"P",
    "gn:feature_code":"PPL",
    "gn:name":"Qanl\u012b Chah\u0101r B\u0101gh",
    "gn:population":0,
    "gn:timezone":"Asia/Kabul",
    "iso:country":"AF",
    "name:und_x_variant":[
        "Qanl\u012b Chah\u0101r B\u0101gh",
        "\u0642\u0646\u0644\u06cc \u0686\u0647\u0627\u0631 \u0628\u0627\u063a",
        "Qanly Ch\u0101r B\u0101gh"
    ],
    "wof:name":"Qanli Chahar Bagh",
    "wof:placetype":"locality"
},
  "geometry": {"coordinates":[65.23916,37.01813],"type":"Point"}
}