{
  "type": "Feature",
  "properties": {
    "gn:admin1_code":"06",
    "gn:admin2_code":"2111",
    "gn:asciiname":"Dukin",
    "gn:country_code":"AF",
    "gn:dem":677,
    "gn:feature_class":"P",
    "gn:feature_code":"PPL",
    "gn:name":"Dukin",
    "gn:population":0,
    "gn:timezone":"Asia/Kabul",
    "iso:country":"AF",
    "name:und_x_variant":[
        "D\u016bk\u012bn",
        "\u1e0e\u016bk\u012bn",
        "\u0689\u0648\u06a9\u06cc\u0646",
        "\u062f\u0648\u06a9\u06cc\u0646"
    ],
    "wof:name":"Dukin",
    "wof:placetype":"locality"
},
  "geometry": {"coordinates":[62.13145,32.51351],"type":"Point"}
}