{
  "type": "Feature",
  "properties": {
    "gn:admin1_code":"11",
    "gn:admin2_code":"2011.0",
    "gn:asciiname":"'Alijan",
    "gn:country_code":"AF",
    "gn:dem":1977,
    "gn:feature_class":"P",
    "gn:feature_code":"PPL",
    "gn:name":"\u2018Al\u012bj\u0101n",
    "gn:population":0,
    "gn:timezone":"Asia/Kabul",
    "iso:country":"AF",
    "name:und_x_variant":[
        "\u2018Al\u012bj\u0101n",
        "\u0639\u0644\u06cc\u062c\u0627\u0646",
        "\u2018Al\u012b Kh\u0101n",
        "\u0639\u0644\u06cc \u062e\u0627\u0646"
    ],
    "wof:name":"'Alijan",
    "wof:placetype":"locality"
},
  "geometry": {"coordinates":[62.75581,33.82921],"type":"Point"}
}