{
  "type": "Feature",
  "properties": {
    "gn:admin1_code":"23",
    "gn:admin2_code":"2402.0",
    "gn:asciiname":"Sandi Band",
    "gn:country_code":"AF",
    "gn:dem":1044,
    "gn:feature_class":"P",
    "gn:feature_code":"PPL",
    "gn:name":"Sand\u012b Band",
    "gn:population":0,
    "gn:timezone":"Asia/Kabul",
    "iso:country":"AF",
    "name:fas_x_preferred":[
        "\u0628\u0646\u062f\u0654 \u0633\u0646\u062f\u06cc"
    ],
    "name:und_x_variant":[
        "Sandiband",
        "Sand\u012b Band",
        "\u0633\u0646\u062f\u06cc \u0628\u0646\u062f",
        "San\u1e0fi Ban\u1e0f"
    ],
    "wof:name":"Sandi Band",
    "wof:placetype":"locality"
},
  "geometry": {"coordinates":[65.90971999999999,31.57893],"type":"Point"}
}