{
  "type": "Feature",
  "properties": {
    "gn:admin1_code":"5",
    "gn:admin2_code":"2805.0",
    "gn:asciiname":"Narqalah",
    "gn:country_code":"AF",
    "gn:dem":2755,
    "gn:feature_class":"P",
    "gn:feature_code":"PPL",
    "gn:name":"Narqalah",
    "gn:population":0,
    "gn:timezone":"Asia/Kabul",
    "iso:country":"AF",
    "name:und_x_variant":[
        "Narkala",
        "Narqal\u0101",
        "Narqalah",
        "\u0646\u0631\u0641\u0644\u0647"
    ],
    "wof:name":"Narqalah",
    "wof:placetype":"locality"
},
  "geometry": {"coordinates":[66.65594,34.30537],"type":"Point"}
}