{
  "type": "Feature",
  "properties": {
    "gn:admin1_code":"11",
    "gn:admin2_code":"2015.0",
    "gn:asciiname":"Chisht-e Sharif",
    "gn:country_code":"AF",
    "gn:dem":1572,
    "gn:feature_class":"P",
    "gn:feature_code":"PPLA2",
    "gn:name":"Chisht-e Shar\u012bf",
    "gn:population":0,
    "gn:timezone":"Asia/Kabul",
    "iso:country":"AF",
    "name:und_x_variant":[
        "Chesht-e Shar\u012bf",
        "Khv\u0101jeh Chesht",
        "Ces\u0304te S\u0304a\u1e5f\u012bf",
        "Khwaja Chist",
        "Chest-e Sharif",
        "Qaryeh-ye Chest-e Shar\u012bf",
        "Chisht-e Shar\u012bf",
        "\u0686\u0634\u062a \u0634\u0631\u06cc\u0641",
        "Chusht-e Shar\u012bf"
    ],
    "wof:name":"Chisht-e Sharif",
    "wof:placetype":"locality"
},
  "geometry": {"coordinates":[63.73966,34.34731],"type":"Point"}
}