{
  "type": "Feature",
  "properties": {
    "gn:admin1_code":"41",
    "gn:admin2_code":"3403.0",
    "gn:asciiname":"Shilandrabad",
    "gn:country_code":"AF",
    "gn:dem":2664,
    "gn:feature_class":"P",
    "gn:feature_code":"PPL",
    "gn:name":"Shil\u0101ndr\u0101b\u0101d",
    "gn:population":0,
    "gn:timezone":"Asia/Kabul",
    "iso:country":"AF",
    "name:und_x_variant":[
        "Sil\u0101n\u1e0f\u1e5f\u0101b\u0101\u1e0f",
        "Shil\u0101ndr\u0101b\u0101d",
        "\u0634\u0644\u0627\u0646\u062f\u0631 \u0622\u0628\u0627\u062f",
        "Sh\u012bl\u0101n\u1e0f\u1e5f\u0101b\u0101d"
    ],
    "wof:name":"Shilandrabad",
    "wof:placetype":"locality"
},
  "geometry": {"coordinates":[66.20355000000001,33.95341],"type":"Point"}
}