{
  "type": "Feature",
  "properties": {
    "gn:admin1_code":"09",
    "gn:admin2_code":"2707",
    "gn:asciiname":"Khuk Kushtah-ye Taynah",
    "gn:country_code":"AF",
    "gn:dem":3217,
    "gn:feature_class":"P",
    "gn:feature_code":"PPL",
    "gn:name":"Kh\u016bk Kushtah-ye T\u0101ynah",
    "gn:population":0,
    "gn:timezone":"Asia/Kabul",
    "iso:country":"AF",
    "name:und_x_variant":[
        "Kh\u016bk-e Koshteh",
        "Kh\u016bkku\u0161ta-i-T\u0101yna",
        "Kh\u016bg-e Koshteh",
        "Kh\u016bk Koshtah-ye T\u0101ynah",
        "Khukkushtayi-Tayna",
        "Kh\u016bkkus\u0304ta-i-B\u0101lana",
        "Kh\u016bk Koshtah-ye Balanah",
        "Kh\u016bk Kushtah-ye T\u0101ynah",
        "Kh\u016bkkoshteh-ye T\u0101ynah",
        "\u062c\u0648\u06a9 \u06a9\u0634\u062a\u0647 \u062a\u0627\u06cc\u0646\u0647"
    ],
    "wof:name":"Khuk Kushtah-ye Taynah",
    "wof:placetype":"locality"
},
  "geometry": {"coordinates":[66.68325,34.60937],"type":"Point"}
}