{
  "type": "Feature",
  "properties": {
    "gn:admin1_code":"33",
    "gn:admin2_code":"3104.0",
    "gn:asciiname":"Toghay-e Pa'in",
    "gn:country_code":"AF",
    "gn:dem":1532,
    "gn:feature_class":"P",
    "gn:feature_code":"PPL",
    "gn:name":"T\u014dghay-e P\u0101\u2019\u012bn",
    "gn:population":0,
    "gn:timezone":"Asia/Kabul",
    "iso:country":"AF",
    "name:und_x_variant":[
        "T\u014dghaye P\u0101y\u0101n",
        "Towghay-ye P\u0101y\u0101n",
        "T\u014dghay-e P\u0101\u2019\u012bn",
        "\u062a\u0648\u063a\u06cc \u067e\u0627\u0626\u06cc\u0646"
    ],
    "wof:name":"Toghay-e Pa'in",
    "wof:placetype":"locality"
},
  "geometry": {"coordinates":[66.55129000000001,35.49831],"type":"Point"}
}