{
  "type": "Feature",
  "properties": {
    "gn:admin1_code":"17",
    "gn:admin2_code":"504.0",
    "gn:asciiname":"Ghuzar Khel",
    "gn:country_code":"AF",
    "gn:dem":2661,
    "gn:feature_class":"P",
    "gn:feature_code":"PPL",
    "gn:name":"Ghuzar Kh\u0113l",
    "gn:population":0,
    "gn:timezone":"Asia/Kabul",
    "iso:country":"AF",
    "name:fas_x_preferred":[
        "\u063a\u0632\u0631 \u062e\u064a\u0644"
    ],
    "name:rus_x_preferred":[
        "Guzarkheyl\u2019"
    ],
    "name:und_x_variant":[
        "Ghoza\u1e5fkh\u0113l",
        "Ghozar Kh\u0113l",
        "Ghozar Kheyl",
        "Ghuzar Kh\u0113l",
        "\u063a\u0632\u0631 \u062e\u06d0\u0644"
    ],
    "wof:name":"Ghuzar Khel",
    "wof:placetype":"locality"
},
  "geometry": {"coordinates":[69.34496,33.9688],"type":"Point"}
}