{
  "type": "Feature",
  "properties": {
    "gn:admin1_code":"3",
    "gn:admin2_code":"1311.0",
    "gn:asciiname":"Chachah",
    "gn:country_code":"AF",
    "gn:dem":651,
    "gn:feature_class":"P",
    "gn:feature_code":"PPL",
    "gn:name":"Ch\u0101chah",
    "gn:population":0,
    "gn:timezone":"Asia/Kabul",
    "iso:country":"AF",
    "name:rus_x_preferred":[
        "\u0427\u0430\u0447\u0430"
    ],
    "name:und_x_variant":[
        "\u010c\u0101\u010da",
        "Ts\u0101ch\u0101",
        "Chacha",
        "Ch\u0101chah",
        "\u0686\u0627\u0686\u0647"
    ],
    "wof:name":"Chachah",
    "wof:placetype":"locality"
},
  "geometry": {"coordinates":[68.87836999999999,36.2292],"type":"Point"}
}