{
  "type": "Feature",
  "properties": {
    "gn:admin1_code":"41",
    "gn:admin2_code":"3409.0",
    "gn:asciiname":"Amij",
    "gn:country_code":"AF",
    "gn:dem":2643,
    "gn:feature_class":"P",
    "gn:feature_code":"PPL",
    "gn:name":"\u0100mij",
    "gn:population":0,
    "gn:timezone":"Asia/Kabul",
    "iso:country":"AF",
    "name:und_x_variant":[
        "\u0100mowj",
        "\u0100moj",
        "Amich-e Sad Kh\u0101neh",
        "\u0100mej",
        "Am\u012bch-e \u015ead Kh\u0101neh",
        "\u0100mij",
        "\u0622\u0645\u062c"
    ],
    "wof:name":"Amij",
    "wof:placetype":"locality"
},
  "geometry": {"coordinates":[66.33109,33.66921],"type":"Point"}
}