{
  "type": "Feature",
  "properties": {
    "gn:admin1_code":"2",
    "gn:admin2_code":"1901.0",
    "gn:asciiname":"Baghak",
    "gn:country_code":"AF",
    "gn:dem":943,
    "gn:feature_class":"P",
    "gn:feature_code":"PPL",
    "gn:name":"B\u0101ghak",
    "gn:population":0,
    "gn:timezone":"Asia/Kabul",
    "iso:country":"AF",
    "name:ceb_x_preferred":[
        "Baghak"
    ],
    "name:fas_x_preferred":[
        "\u0628\u0627\u063a\u06a9"
    ],
    "name:swe_x_preferred":[
        "Baghak"
    ],
    "name:und_x_variant":[
        "Bagak",
        "B\u0101ghak",
        "\u0628\u0627\u063a\u06a9"
    ],
    "wof:name":"Baghak",
    "wof:placetype":"locality"
},
  "geometry": {"coordinates":[63.13802,34.97223],"type":"Point"}
}