{
  "type": "Feature",
  "properties": {
    "gn:admin1_code":"01",
    "gn:admin2_code":"1120.0",
    "gn:asciiname":"Khirch",
    "gn:country_code":"AF",
    "gn:dem":1703,
    "gn:feature_class":"P",
    "gn:feature_code":"PPL",
    "gn:name":"Khirch",
    "gn:population":0,
    "gn:timezone":"Asia/Kabul",
    "iso:country":"AF",
    "name:und_x_variant":[
        "Khe\u1e5fc",
        "Kherch",
        "Khirch",
        "\u062e\u0631\u0686"
    ],
    "wof:name":"Khirch",
    "wof:placetype":"locality"
},
  "geometry": {"coordinates":[70.462,38.05416],"type":"Point"}
}