{
  "type": "Feature",
  "properties": {
    "gn:admin1_code":"41",
    "gn:admin2_code":"3408.0",
    "gn:asciiname":"Dahan-e Roghani",
    "gn:country_code":"AF",
    "gn:dem":2770,
    "gn:feature_class":"P",
    "gn:feature_code":"PPL",
    "gn:name":"Dahan-e R\u014dghan\u012b",
    "gn:population":0,
    "gn:timezone":"Asia/Kabul",
    "iso:country":"AF",
    "name:und_x_variant":[
        "\u1e0eahan-\u1e5f\u014dghani",
        "Dakhanrogani",
        "Dahan-e R\u014dghan\u012b",
        "\u062f\u0647\u0646 \u0631\u0648\u063a\u0646\u06cc",
        "Dahan Rowghan\u012b"
    ],
    "wof:name":"Dahan-e Roghani",
    "wof:placetype":"locality"
},
  "geometry": {"coordinates":[65.83294000000001,34.312],"type":"Point"}
}