{
  "type": "Feature",
  "properties": {
    "gn:admin1_code":"09",
    "gn:admin2_code":"2701",
    "gn:asciiname":"Wini",
    "gn:country_code":"AF",
    "gn:dem":2104,
    "gn:feature_class":"P",
    "gn:feature_code":"PPL",
    "gn:name":"Wini",
    "gn:population":0,
    "gn:timezone":"Asia/Kabul",
    "iso:country":"AF",
    "name:und_x_variant":[
        "W\u012bn\u012b",
        "\u0648\u06cc\u0646\u06cc",
        "Wini"
    ],
    "wof:name":"Wini",
    "wof:placetype":"locality"
},
  "geometry": {"coordinates":[65.64355999999999,35.14398],"type":"Point"}
}