{
  "type": "Feature",
  "properties": {
    "gn:admin1_code":"18",
    "gn:admin2_code":"804.0",
    "gn:asciiname":"Samal Khel",
    "gn:country_code":"AF",
    "gn:dem":1600,
    "gn:feature_class":"P",
    "gn:feature_code":"PPL",
    "gn:name":"Samal Kh\u0113l",
    "gn:population":0,
    "gn:timezone":"Asia/Kabul",
    "iso:country":"AF",
    "name:fas_x_preferred":[
        "\u0633\u0644\u0627\u0645 \u062e\u064a\u0644"
    ],
    "name:rus_x_preferred":[
        "Samal\u2019kheyl\u2019"
    ],
    "name:und_x_variant":[
        "Sal\u0101mkh\u0113l",
        "Samal Kh\u0113l",
        "Sal\u0101mkheyl",
        "\u0633\u0645\u0644 \u062e\u06d0\u0644"
    ],
    "wof:name":"Samal Khel",
    "wof:placetype":"locality"
},
  "geometry": {"coordinates":[69.9781,34.24528],"type":"Point"}
}