{
  "type": "Feature",
  "properties": {
    "gn:admin1_code":"05",
    "gn:admin2_code":"2804",
    "gn:asciiname":"Sulaych",
    "gn:country_code":"AF",
    "gn:dem":2165,
    "gn:feature_class":"P",
    "gn:feature_code":"PPL",
    "gn:name":"Sulaych",
    "gn:population":0,
    "gn:timezone":"Asia/Kabul",
    "iso:country":"AF",
    "name:und_x_variant":[
        "S\u016bl\u012bc",
        "Solej",
        "Sulij",
        "Sol\u0113c",
        "Solech",
        "Sulaych",
        "\u0633\u0644\u06cc\u0686"
    ],
    "wof:name":"Sulaych",
    "wof:placetype":"locality"
},
  "geometry": {"coordinates":[66.43575,35.05112],"type":"Point"}
}