{
  "type": "Feature",
  "properties": {
    "gn:admin1_code":"24",
    "gn:admin2_code":"1403",
    "gn:asciiname":"Yanghariq",
    "gn:country_code":"AF",
    "gn:dem":353,
    "gn:feature_class":"P",
    "gn:feature_code":"PPL",
    "gn:name":"Yangh\u0101riq",
    "gn:population":0,
    "gn:timezone":"Asia/Kabul",
    "iso:country":"AF",
    "name:rus_x_preferred":[
        "\u042f\u043d\u0433\u0430\u0440\u044b\u043a"
    ],
    "name:und_x_variant":[
        "Yangaryk",
        "Yangh\u0101req",
        "Yangh\u0101riq",
        "\u06cc\u0646\u063a\u0627\u0631\u0642"
    ],
    "wof:name":"Yanghariq",
    "wof:placetype":"locality"
},
  "geometry": {"coordinates":[68.62451999999999,36.90382],"type":"Point"}
}