{
  "type": "Feature",
  "properties": {
    "gn:admin1_code":"11",
    "gn:admin2_code":"2014.0",
    "gn:asciiname":"Deh-e Afghan",
    "gn:country_code":"AF",
    "gn:dem":1110,
    "gn:feature_class":"P",
    "gn:feature_code":"PPL",
    "gn:name":"Deh-e Afgh\u0101n",
    "gn:population":0,
    "gn:timezone":"Asia/Kabul",
    "iso:country":"AF",
    "name:fas_x_preferred":[
        "\u0642\u0631\u064a\u06c0 \u0627\u0641\u063a\u0627\u0646"
    ],
    "name:und_x_variant":[
        "Dekhi-Afgan",
        "Deh-e Afgh\u0101n",
        "\u062f\u0647 \u0627\u0641\u063a\u0627\u0646",
        "\u0642\u0631\u064a\u06c0 \u0627\u0641\u063a\u0627\u0646"
    ],
    "wof:name":"Deh-e Afghan",
    "wof:placetype":"locality"
},
  "geometry": {"coordinates":[62.29707,33.32471],"type":"Point"}
}