{
  "type": "Feature",
  "properties": {
    "gn:admin1_code":"8",
    "gn:admin2_code":"604.0",
    "gn:asciiname":"Sinjid",
    "gn:country_code":"AF",
    "gn:dem":2755,
    "gn:feature_class":"P",
    "gn:feature_code":"PPL",
    "gn:name":"Sinj\u012bd",
    "gn:population":0,
    "gn:timezone":"Asia/Kabul",
    "iso:country":"AF",
    "name:und_x_variant":[
        "Senj\u012b\u1e0f",
        "Senjed",
        "Sinj\u012bd",
        "\u0633\u0646\u062c\u06cc\u062f"
    ],
    "wof:name":"Sinjid",
    "wof:placetype":"locality"
},
  "geometry": {"coordinates":[67.44837,33.97025],"type":"Point"}
}