{
  "type": "Feature",
  "properties": {
    "gn:admin1_code":"28",
    "gn:admin2_code":"2508",
    "gn:asciiname":"Shamawun",
    "gn:country_code":"AF",
    "gn:dem":2228,
    "gn:feature_class":"P",
    "gn:feature_code":"PPL",
    "gn:name":"Sham\u0101w\u016bn",
    "gn:population":0,
    "gn:timezone":"Asia/Kabul",
    "iso:country":"AF",
    "name:und_x_variant":[
        "S\u0304am\u0101w\u016bn",
        "Shamavun",
        "Sham\u0101w\u016bn"
    ],
    "wof:name":"Shamawun",
    "wof:placetype":"locality"
},
  "geometry": {"coordinates":[67.52673,31.73492],"type":"Point"}
}