{
  "type": "Feature",
  "properties": {
    "gn:admin1_code":"10",
    "gn:admin2_code":"2302.0",
    "gn:asciiname":"Junubi Nurzai",
    "gn:country_code":"AF",
    "gn:dem":825,
    "gn:feature_class":"P",
    "gn:feature_code":"PPL",
    "gn:name":"Jun\u016bb\u012b Nurza\u012b",
    "gn:population":0,
    "gn:timezone":"Asia/Kabul",
    "iso:country":"AF",
    "name:und_x_variant":[
        "Dzhanubi-Nurzai",
        "Jan\u016bbi Nu\u1e5fza\u2019i",
        "Jun\u016bb\u012b Nurza\u012b",
        "\u062c\u0646\u0648\u0628\u06cc \u0646\u0631\u0632\u06cc",
        "Jon\u016bb\u012b N\u016brza\u2019i"
    ],
    "wof:name":"Junubi Nurzai",
    "wof:placetype":"locality"
},
  "geometry": {"coordinates":[64.59708000000001,31.79839],"type":"Point"}
}