{
  "type": "Feature",
  "properties": {
    "gn:admin1_code":"07",
    "gn:admin2_code":"1809",
    "gn:asciiname":"Quraish",
    "gn:country_code":"AF",
    "gn:dem":416,
    "gn:feature_class":"P",
    "gn:feature_code":"PPL",
    "gn:name":"Qura\u012bsh",
    "gn:population":0,
    "gn:timezone":"Asia/Kabul",
    "iso:country":"AF",
    "name:und_x_variant":[
        "Qura\u012bsh",
        "\u0642\u0631\u06cc\u0634",
        "Qoraish"
    ],
    "wof:name":"Quraish",
    "wof:placetype":"locality"
},
  "geometry": {"coordinates":[64.92733,36.42859],"type":"Point"}
}