{
  "type": "Feature",
  "properties": {
    "gn:admin1_code":"02",
    "gn:admin2_code":"1906",
    "gn:asciiname":"Sahib Zadah",
    "gn:country_code":"AF",
    "gn:dem":609,
    "gn:feature_class":"P",
    "gn:feature_code":"PPL",
    "gn:name":"\u015e\u0101\u1e29ib Z\u0101dah",
    "gn:population":0,
    "gn:timezone":"Asia/Kabul",
    "iso:country":"AF",
    "name:und_x_variant":[
        "Sa\u1e96eb Z\u0101da",
        "\u015e\u0101\u1e29ebz\u0101deh",
        "\u015e\u0101\u1e29ib Z\u0101dah",
        "\u0635\u0627\u062d\u0628 \u0632\u0627\u062f\u0647"
    ],
    "wof:name":"Sahib Zadah",
    "wof:placetype":"locality"
},
  "geometry": {"coordinates":[63.52695,35.25415],"type":"Point"}
}