{
  "type": "Feature",
  "properties": {
    "gn:admin1_code":"41",
    "gn:admin2_code":"3406",
    "gn:asciiname":"Rashk",
    "gn:country_code":"AF",
    "gn:dem":1325,
    "gn:feature_class":"P",
    "gn:feature_code":"PPL",
    "gn:name":"\u1e5eashk",
    "gn:population":0,
    "gn:timezone":"Asia/Kabul",
    "iso:country":"AF",
    "name:und_x_variant":[
        "Ra\u0161k",
        "\u1e5eashk",
        "\u0693\u0634\u06a9",
        "Rashk"
    ],
    "wof:name":"Rashk",
    "wof:placetype":"locality"
},
  "geometry": {"coordinates":[65.73428,33.34968],"type":"Point"}
}