{
  "type": "Feature",
  "properties": {
    "gn:admin1_code":"35",
    "gn:admin2_code":"905.0",
    "gn:asciiname":"Sar-e Bala Khanah",
    "gn:country_code":"AF",
    "gn:dem":1694,
    "gn:feature_class":"P",
    "gn:feature_code":"PPL",
    "gn:name":"Sar-e B\u0101l\u0101 Kh\u0101nah",
    "gn:population":0,
    "gn:timezone":"Asia/Kabul",
    "iso:country":"AF",
    "name:fas_x_preferred":[
        "\u0633\u0631\u0628\u0627\u0644\u0627\u062e\u0627\u0646\u0647"
    ],
    "name:und_x_variant":[
        "Sa\u1e5fb\u0101l\u0101kh\u0101na",
        "Sarbalakhana",
        "Sar B\u0101l\u0101 Kh\u0101nah",
        "Sarb\u0101l\u0101kh\u0101neh",
        "Sar-e B\u0101l\u0101 Kh\u0101nah",
        "\u0633\u0631 \u0628\u0627\u0644\u0627 \u062e\u0627\u0646\u0647"
    ],
    "wof:name":"Sar-e Bala Khanah",
    "wof:placetype":"locality"
},
  "geometry": {"coordinates":[69.97166999999999,34.72859],"type":"Point"}
}