{
  "type": "Feature",
  "properties": {
    "gn:admin1_code":"03",
    "gn:admin2_code":"1308.0",
    "gn:asciiname":"Ab-e Barik",
    "gn:country_code":"AF",
    "gn:dem":2247,
    "gn:feature_class":"P",
    "gn:feature_code":"PPL",
    "gn:name":"\u0100b-e B\u0101r\u012bk",
    "gn:population":0,
    "gn:timezone":"Asia/Kabul",
    "iso:country":"AF",
    "wof:name":"Ab-e Barik",
    "wof:placetype":"locality"
},
  "geometry": {"coordinates":[69.72833,35.87110999999999],"type":"Point"}
}