{
  "type": "Feature",
  "properties": {
    "gn:admin1_code":"08",
    "gn:admin2_code":"604",
    "gn:asciiname":"Khak-e Folad",
    "gn:country_code":"AF",
    "gn:dem":3207,
    "gn:feature_class":"P",
    "gn:feature_code":"PPL",
    "gn:name":"Kh\u0101k-e F\u014dl\u0101d",
    "gn:population":0,
    "gn:timezone":"Asia/Kabul",
    "iso:country":"AF",
    "name:und_x_variant":[
        "Kh\u0101ke F\u014dl\u0101\u1e0f",
        "Kh\u0101k-e F\u016bl\u0101d",
        "Kh\u0101k-e F\u014dl\u0101d",
        "\u062e\u0627\u06a9 \u0641\u0648\u0644\u0627\u062f"
    ],
    "wof:name":"Khak-e Folad",
    "wof:placetype":"locality"
},
  "geometry": {"coordinates":[67.39686,33.80421],"type":"Point"}
}