{
  "type": "Feature",
  "properties": {
    "gn:admin1_code":"02",
    "gn:admin2_code":"1904",
    "gn:asciiname":"Nawer",
    "gn:country_code":"AF",
    "gn:dem":2282,
    "gn:feature_class":"P",
    "gn:feature_code":"PPL",
    "gn:name":"N\u0101w\u00ear",
    "gn:population":0,
    "gn:timezone":"Asia/Kabul",
    "iso:country":"AF",
    "name:und_x_variant":[
        "N\u0101w\u0113\u1e5f",
        "N\u0101w\u00ear",
        "\u0646\u0627\u0648\u0631",
        "N\u0101war"
    ],
    "wof:name":"Nawer",
    "wof:placetype":"locality"
},
  "geometry": {"coordinates":[64.98024000000001,34.9693],"type":"Point"}
}