{
  "type": "Feature",
  "properties": {
    "gn:admin1_code":"13",
    "gn:admin2_code":"107.0",
    "gn:asciiname":"Aghil-e Khwajah",
    "gn:country_code":"AF",
    "gn:dem":1919,
    "gn:feature_class":"P",
    "gn:feature_code":"PPL",
    "gn:name":"\u0100ghil-e Khw\u0101jah",
    "gn:population":0,
    "gn:timezone":"Asia/Kabul",
    "iso:country":"AF",
    "name:und_x_variant":[
        "Agali-Khodzha",
        "Aghale Khw\u0101ja",
        "Aghel-e Khv\u0101jeh",
        "\u0100ghil-e Khw\u0101jah",
        "\u0627\u063a\u0644 \u062e\u0648\u0627\u062c\u0647",
        "\u0100ghel-e Khw\u0101jah"
    ],
    "wof:name":"Aghil-e Khwajah",
    "wof:placetype":"locality"
},
  "geometry": {"coordinates":[69.05800000000001,34.68443],"type":"Point"}
}