{
  "type": "Feature",
  "properties": {
    "gn:admin1_code":"8",
    "gn:admin2_code":"614.0",
    "gn:asciiname":"Qal'ah-ye 'Ali",
    "gn:country_code":"AF",
    "gn:dem":2096,
    "gn:feature_class":"P",
    "gn:feature_code":"PPL",
    "gn:name":"Qal\u2018ah-ye \u2018Al\u012b",
    "gn:population":0,
    "gn:timezone":"Asia/Kabul",
    "iso:country":"AF",
    "name:und_x_variant":[
        "Kalaali",
        "Qal\u2018a \u2018Ali",
        "Qal\u2018a-i-\u2018Ali",
        "Qal\u2018ah-ye \u2018Al\u012b",
        "Qal\u2018eh-ye \u2018Al\u012b",
        "\u0642\u0644\u0639\u0647 \u0639\u0644\u06cc"
    ],
    "wof:name":"Qal'ah-ye 'Ali",
    "wof:placetype":"locality"
},
  "geometry": {"coordinates":[68.40501,33.39601],"type":"Point"}
}