{
  "type": "Feature",
  "properties": {
    "gn:admin1_code":"18",
    "gn:admin2_code":"820.0",
    "gn:asciiname":"Surich",
    "gn:country_code":"AF",
    "gn:dem":714,
    "gn:feature_class":"P",
    "gn:feature_code":"PPL",
    "gn:name":"S\u016brich",
    "gn:population":0,
    "gn:timezone":"Asia/Kabul",
    "iso:country":"AF",
    "name:und_x_variant":[
        "S\u016bre\u010d",
        "S\u016b\u1e5fech",
        "S\u016brich",
        "\u0633\u0648\u0631\u0686"
    ],
    "wof:name":"Surich",
    "wof:placetype":"locality"
},
  "geometry": {"coordinates":[70.60880999999998,34.61333],"type":"Point"}
}