{
  "type": "Feature",
  "properties": {
    "gn:admin1_code":"28",
    "gn:admin2_code":"2506",
    "gn:asciiname":"Khishk",
    "gn:country_code":"AF",
    "gn:dem":1574,
    "gn:feature_class":"P",
    "gn:feature_code":"PPL",
    "gn:name":"Kh\u012bshk",
    "gn:population":0,
    "gn:timezone":"Asia/Kabul",
    "iso:country":"AF",
    "name:fas_x_preferred":[
        "\u062e\u064a\u0634\u0643"
    ],
    "name:und_x_variant":[
        "Kh\u012bs\u0304k",
        "Kh\u012bshk",
        "\u062e\u06cc\u0634\u06a9"
    ],
    "wof:name":"Khishk",
    "wof:placetype":"locality"
},
  "geometry": {"coordinates":[66.72923,32.05821],"type":"Point"}
}