{
  "type": "Feature",
  "properties": {
    "gn:admin1_code":"7",
    "gn:admin2_code":"1804.0",
    "gn:asciiname":"Chashmah-ye Yanbulaq",
    "gn:country_code":"AF",
    "gn:dem":680,
    "gn:feature_class":"P",
    "gn:feature_code":"PPL",
    "gn:name":"Chashmah-ye Y\u0101nb\u016bl\u0101q",
    "gn:population":0,
    "gn:timezone":"Asia/Kabul",
    "iso:country":"AF",
    "name:und_x_variant":[
        "Y\u0101n B\u016blak",
        "Chashma Y\u0101n Bul\u0101k",
        "Y\u0101n Bul\u0101k Chashma",
        "Chashmeh-ye Y\u0101nbol\u0101q",
        "Cas\u0304ma-i-Yanbul\u0101q",
        "Chashmah-ye Y\u0101nb\u016bl\u0101q"
    ],
    "wof:name":"Chashmah-ye Yanbulaq",
    "wof:placetype":"locality"
},
  "geometry": {"coordinates":[63.93842,35.8297],"type":"Point"}
}