{
  "type": "Feature",
  "properties": {
    "gn:admin1_code":"23",
    "gn:admin2_code":"2413.0",
    "gn:asciiname":"Ghundey",
    "gn:country_code":"AF",
    "gn:dem":1714,
    "gn:feature_class":"P",
    "gn:feature_code":"PPL",
    "gn:name":"Ghun\u1e0f\u00eay",
    "gn:population":0,
    "gn:timezone":"Asia/Kabul",
    "iso:country":"AF",
    "name:fas_x_preferred":[
        "\u063a\u0648\u0646\u062f\u06cc"
    ],
    "name:pus_x_preferred":[
        "\u063a\u0646\u0689\u06cd"
    ],
    "name:und_x_variant":[
        "Gunday",
        "Ghun\u1e0f\u00eay",
        "\u063a\u0646\u0689\u06cd",
        "Gh\u016bn\u1e0fey"
    ],
    "wof:name":"Ghundey",
    "wof:placetype":"locality"
},
  "geometry": {"coordinates":[67.22815,31.65783],"type":"Point"}
}