{
  "type": "Feature",
  "properties": {
    "gn:admin1_code":"32",
    "gn:admin2_code":"1504",
    "gn:asciiname":"Mulla Nazar",
    "gn:country_code":"AF",
    "gn:dem":1275,
    "gn:feature_class":"P",
    "gn:feature_code":"PPL",
    "gn:name":"Mulla Nazar",
    "gn:population":0,
    "gn:timezone":"Asia/Kabul",
    "iso:country":"AF",
    "name:und_x_variant":[
        "Moll\u0101 Naz\u0327ar"
    ],
    "wof:name":"Mulla Nazar",
    "wof:placetype":"locality"
},
  "geometry": {"coordinates":[67.15000000000001,36.03333],"type":"Point"}
}