{
  "type": "Feature",
  "properties": {
    "gn:admin1_code":"10",
    "gn:admin2_code":"2307",
    "gn:asciiname":"Qaryah-ye Mandzarakah",
    "gn:country_code":"AF",
    "gn:dem":1104,
    "gn:feature_class":"P",
    "gn:feature_code":"PPL",
    "gn:name":"Qaryah-ye Mandzarakah",
    "gn:population":0,
    "gn:timezone":"Asia/Kabul",
    "iso:country":"AF",
    "name:rus_x_preferred":[
        "Kar\u2019yayi-Mandzha"
    ],
    "name:und_x_variant":[
        "Qaryeh-ye Manjaraka",
        "Qa\u1e5fya-i-Manja\u1e5faka",
        "Qaryah-ye Mandzarakah",
        "\u0642\u0631\u06cc\u0647 \u0645\u0646\u0681\u0631\u06a9\u0647",
        "Qaryeh-ye Mandzarakah"
    ],
    "wof:name":"Qaryah-ye Mandzarakah",
    "wof:placetype":"locality"
},
  "geometry": {"coordinates":[64.31045999999999,32.20125],"type":"Point"}
}