{
  "type": "Feature",
  "properties": {
    "gn:admin1_code":"27",
    "gn:admin2_code":"404",
    "gn:asciiname":"Darah-ye Qafzar",
    "gn:country_code":"AF",
    "gn:dem":3087,
    "gn:feature_class":"P",
    "gn:feature_code":"PPL",
    "gn:name":"Darah-ye Qafz\u0101r",
    "gn:population":0,
    "gn:timezone":"Asia/Kabul",
    "iso:country":"AF",
    "name:und_x_variant":[
        "Darrahe Qafz\u0101r",
        "Darrakafzar",
        "\u1e0ea\u1e5f\u1e5fah Qafz\u0101\u1e5f",
        "Darah-ye Qafz\u0101r",
        "Darreh-ye Qafz\u0101r",
        "\u062f\u0631\u0647 \u0642\u0641\u0632\u0627\u0631"
    ],
    "wof:name":"Darah-ye Qafzar",
    "wof:placetype":"locality"
},
  "geometry": {"coordinates":[67.77916999999999,34.49806],"type":"Point"}
}