{
  "type": "Feature",
  "properties": {
    "gn:admin1_code":"33",
    "gn:admin2_code":"3107",
    "gn:asciiname":"Rishkan",
    "gn:country_code":"AF",
    "gn:dem":1245,
    "gn:feature_class":"P",
    "gn:feature_code":"PPL",
    "gn:name":"Rishk\u0101n",
    "gn:population":0,
    "gn:timezone":"Asia/Kabul",
    "iso:country":"AF",
    "name:und_x_variant":[
        "\u1e5ees\u0304k\u0101n",
        "Reshk\u0101n",
        "Rishk\u0101n",
        "\u0631\u0634\u06a9\u0627\u0646"
    ],
    "wof:name":"Rishkan",
    "wof:placetype":"locality"
},
  "geometry": {"coordinates":[66.60736999999999,35.93584],"type":"Point"}
}