{
  "type": "Feature",
  "properties": {
    "gn:admin1_code":"07",
    "gn:admin2_code":"1803",
    "gn:asciiname":"Jilgildah",
    "gn:country_code":"AF",
    "gn:dem":858,
    "gn:feature_class":"P",
    "gn:feature_code":"PPL",
    "gn:name":"Jilgildah",
    "gn:population":0,
    "gn:timezone":"Asia/Kabul",
    "iso:country":"AF",
    "name:und_x_variant":[
        "Jelgel\u1e0fa",
        "Jilgildah",
        "\u062c\u0644\u06af\u0644\u062f\u0647",
        "Jelgeldah"
    ],
    "wof:name":"Jilgildah",
    "wof:placetype":"locality"
},
  "geometry": {"coordinates":[64.51888000000001,35.83467],"type":"Point"}
}