{
  "type": "Feature",
  "properties": {
    "gn:admin1_code":"24",
    "gn:admin2_code":"1406.0",
    "gn:asciiname":"'Arab Quduk",
    "gn:country_code":"AF",
    "gn:dem":850,
    "gn:feature_class":"P",
    "gn:feature_code":"PPL",
    "gn:name":"\u2018Arab Qud\u016bk",
    "gn:population":0,
    "gn:timezone":"Asia/Kabul",
    "iso:country":"AF",
    "name:fas_x_preferred":[
        "\u0639\u0631\u0628 \u0642\u062f\u0648\u0643"
    ],
    "name:rus_x_preferred":[
        "\u0410\u0440\u0430\u0431\u043a\u0443\u0434\u0443\u043a"
    ],
    "name:und_x_variant":[
        "Arabkuduk",
        "\u2018Arab Qod\u016bk",
        "\u2018Arab Qud\u016bk",
        "\u0639\u0631\u0628 \u0642\u062f\u0648\u06a9"
    ],
    "wof:name":"'Arab Quduk",
    "wof:placetype":"locality"
},
  "geometry": {"coordinates":[69.12420999999999,36.53056],"type":"Point"}
}