{
  "type": "Feature",
  "properties": {
    "gn:admin1_code":"06",
    "gn:admin2_code":"2104",
    "gn:asciiname":"Taj Koh",
    "gn:country_code":"AF",
    "gn:dem":1650,
    "gn:feature_class":"P",
    "gn:feature_code":"PPL",
    "gn:name":"T\u0101j K\u014dh",
    "gn:population":0,
    "gn:timezone":"Asia/Kabul",
    "iso:country":"AF",
    "name:und_x_variant":[
        "T\u0101j K\u014dh",
        "\u062a\u0627\u062c \u06a9\u0648\u0647",
        "T\u0101j K\u016bh"
    ],
    "wof:name":"Taj Koh",
    "wof:placetype":"locality"
},
  "geometry": {"coordinates":[63.75899,32.84892],"type":"Point"}
}