{
  "type": "Feature",
  "properties": {
    "gn:admin1_code":"10",
    "gn:admin2_code":"2303.0",
    "gn:asciiname":"Qaryah-ye Malik Shah",
    "gn:country_code":"AF",
    "gn:dem":1441,
    "gn:feature_class":"P",
    "gn:feature_code":"PPL",
    "gn:name":"Qaryah-ye Malik Sh\u0101h",
    "gn:population":0,
    "gn:timezone":"Asia/Kabul",
    "iso:country":"AF",
    "name:rus_x_preferred":[
        "Kar\u2019yayi-Malikshakh"
    ],
    "name:und_x_variant":[
        "Qarya-i-Malek \u0160\u0101h",
        "Qaryah-ye Malik Sh\u0101h",
        "\u0642\u0631\u06cc\u0647 \u0645\u0644\u06a9 \u0634\u0627\u0647",
        "Qaryeh-ye-Malek Sh\u0101h"
    ],
    "wof:name":"Qaryah-ye Malik Shah",
    "wof:placetype":"locality"
},
  "geometry": {"coordinates":[64.86327,32.6699],"type":"Point"}
}