{
  "type": "Feature",
  "properties": {
    "gn:admin1_code":"28",
    "gn:admin2_code":"2504",
    "gn:asciiname":"Sarak",
    "gn:country_code":"AF",
    "gn:dem":2060,
    "gn:feature_class":"P",
    "gn:feature_code":"PPL",
    "gn:name":"Sarak",
    "gn:population":0,
    "gn:timezone":"Asia/Kabul",
    "iso:country":"AF",
    "name:fas_x_preferred":[
        "\u0633\u0631\u0643"
    ],
    "name:hin_x_preferred":[
        "\u0938\u0930\u093e\u0915"
    ],
    "name:und_x_variant":[
        "\u0633\u0693\u06a9"
    ],
    "wof:name":"Sarak",
    "wof:placetype":"locality"
},
  "geometry": {"coordinates":[66.75915999999999,32.57944000000001],"type":"Point"}
}