{
  "type": "Feature",
  "properties": {
    "gn:admin1_code":"07",
    "gn:admin2_code":"1806",
    "gn:asciiname":"Kowlian",
    "gn:country_code":"AF",
    "gn:dem":1447,
    "gn:feature_class":"P",
    "gn:feature_code":"PPL",
    "gn:name":"Kowl\u012b\u0101n",
    "gn:population":0,
    "gn:timezone":"Asia/Kabul",
    "iso:country":"AF",
    "name:rus_x_preferred":[
        "\u041a\u0430\u0443\u043b\u0438\u0430\u043d"
    ],
    "name:und_x_variant":[
        "Kawly\u0101n",
        "K\u0101ol\u012b\u0101n",
        "Kowl\u012b\u0101n",
        "\u06a9\u0648\u0644\u06cc\u0627\u0646"
    ],
    "wof:name":"Kowlian",
    "wof:placetype":"locality"
},
  "geometry": {"coordinates":[65.4038,35.88298],"type":"Point"}
}