{
  "type": "Feature",
  "properties": {
    "gn:admin1_code":"08",
    "gn:admin2_code":"604",
    "gn:asciiname":"Ir Bulaq",
    "gn:country_code":"AF",
    "gn:dem":3298,
    "gn:feature_class":"P",
    "gn:feature_code":"PPL",
    "gn:name":"\u012ar B\u016bl\u0101q",
    "gn:population":0,
    "gn:timezone":"Asia/Kabul",
    "iso:country":"AF",
    "name:und_x_variant":[
        "Irbulak",
        "\u012arbol\u0101gh",
        "\u012ar B\u016bl\u0101q",
        "\u0627\u06cc\u0631 \u0628\u0648\u0644\u0627\u0642"
    ],
    "wof:name":"Ir Bulaq",
    "wof:placetype":"locality"
},
  "geometry": {"coordinates":[67.73018,34.10794],"type":"Point"}
}