{
  "type": "Feature",
  "properties": {
    "gn:admin1_code":"24",
    "gn:admin2_code":"1405.0",
    "gn:asciiname":"Qarah Qishlaq",
    "gn:country_code":"AF",
    "gn:dem":409,
    "gn:feature_class":"P",
    "gn:feature_code":"PPL",
    "gn:name":"Qarah Qishl\u0101q",
    "gn:population":0,
    "gn:timezone":"Asia/Kabul",
    "iso:country":"AF",
    "name:rus_x_preferred":[
        "\u041a\u0430\u0440\u0430\u043a\u044b\u0448\u043b\u0430\u043a"
    ],
    "name:und_x_variant":[
        "Karakyshlak",
        "Qara Qe\u0161l\u0101q",
        "Qareh Qeshl\u0101q",
        "Qarah Qishl\u0101q",
        "\u0642\u0631\u0647 \u0642\u0634\u0644\u0627\u0642"
    ],
    "wof:name":"Qarah Qishlaq",
    "wof:placetype":"locality"
},
  "geometry": {"coordinates":[68.89288000000001,36.65705],"type":"Point"}
}