{
  "type": "Feature",
  "properties": {
    "gn:admin1_code":"19",
    "gn:admin2_code":"2203",
    "gn:asciiname":"Nawab Khanah-ye Sabz Gazi",
    "gn:country_code":"AF",
    "gn:dem":498,
    "gn:feature_class":"P",
    "gn:feature_code":"PPL",
    "gn:name":"Naw\u0101b Kh\u0101nah-ye Sabz Gaz\u012b",
    "gn:population":0,
    "gn:timezone":"Asia/Kabul",
    "iso:country":"AF",
    "name:und_x_variant":[
        "Sabz Gaz\u012b",
        "Naw\u0101b Kh\u0101nah-ye Sabz Gaz\u012b",
        "Nav\u0101bkh\u0101n-e Sabz Gaz\u012b"
    ],
    "wof:name":"Nawab Khanah-ye Sabz Gazi",
    "wof:placetype":"locality"
},
  "geometry": {"coordinates":[61.82333000000001,30.70833],"type":"Point"}
}