{
  "type": "Feature",
  "properties": {
    "gn:admin1_code":"29",
    "gn:admin2_code":"2905",
    "gn:asciiname":"Sanzali Kili",
    "gn:country_code":"AF",
    "gn:dem":1649,
    "gn:feature_class":"P",
    "gn:feature_code":"PPL",
    "gn:name":"Sanzali Kili",
    "gn:population":0,
    "gn:timezone":"Asia/Kabul",
    "iso:country":"AF",
    "name:und_x_variant":[
        "Sanzali Kalay",
        "Sandz\u00eal\u012b K\u00ealay",
        "Sanzali Kili"
    ],
    "wof:name":"Sanzali Kili",
    "wof:placetype":"locality"
},
  "geometry": {"coordinates":[69.05139,31.68389],"type":"Point"}
}