{
  "type": "Feature",
  "properties": {
    "gn:admin1_code":"23",
    "gn:admin2_code":"2401",
    "gn:asciiname":"Gundigan",
    "gn:country_code":"AF",
    "gn:dem":1006,
    "gn:feature_class":"P",
    "gn:feature_code":"PPL",
    "gn:name":"Gundig\u0101n",
    "gn:population":0,
    "gn:timezone":"Asia/Kabul",
    "iso:country":"AF",
    "name:fas_x_preferred":[
        "\u06af\u0646\u062f\u064a\u06af\u0627\u0646"
    ],
    "name:und_x_variant":[
        "Gun\u1e0fig\u0101n",
        "Gundigan",
        "Gond\u012bg\u0101n",
        "Gundig\u0101n",
        "\u06af\u0646\u062f\u06af\u0627\u0646"
    ],
    "wof:name":"Gundigan",
    "wof:placetype":"locality"
},
  "geometry": {"coordinates":[65.64393000000001,31.62056],"type":"Point"}
}