{
  "type": "Feature",
  "properties": {
    "gn:admin1_code":"07",
    "gn:admin2_code":"1804",
    "gn:asciiname":"Gul Quduq",
    "gn:country_code":"AF",
    "gn:dem":1169,
    "gn:feature_class":"P",
    "gn:feature_code":"PPL",
    "gn:name":"Gul Qud\u016bq",
    "gn:population":0,
    "gn:timezone":"Asia/Kabul",
    "iso:country":"AF",
    "name:fas_x_preferred":[
        "Q\u014dl Qudoq"
    ],
    "name:fas_x_variant":[
        "\u0642\u0648\u0644 \u0642\u062f\u0642"
    ],
    "name:und_x_variant":[
        "Gul Qud\u016bq",
        "\u06af\u0644 \u0642\u062f\u0648\u0642",
        "Gul Qu\u1e0f\u016bg"
    ],
    "wof:name":"Gul Quduq",
    "wof:placetype":"locality"
},
  "geometry": {"coordinates":[64.40897,35.7812],"type":"Point"}
}