{
  "type": "Feature",
  "properties": {
    "gn:admin1_code":"06",
    "gn:admin2_code":"2111",
    "gn:asciiname":"Ganj Gin",
    "gn:country_code":"AF",
    "gn:dem":671,
    "gn:feature_class":"P",
    "gn:feature_code":"PPL",
    "gn:name":"Ganj G\u012bn",
    "gn:population":0,
    "gn:timezone":"Asia/Kabul",
    "iso:country":"AF",
    "name:und_x_variant":[
        "Ganjg\u012bn",
        "Gaj Kan",
        "Gajkin",
        "Gandzhgin",
        "Ganjk\u012bn",
        "\u06af\u0646\u062c\u0643\u064a\u0646",
        "Ganj G\u012bn",
        "\u06af\u0646\u062c \u06af\u06cc\u0646",
        "Konj G\u012bn"
    ],
    "wof:name":"Ganj Gin",
    "wof:placetype":"locality"
},
  "geometry": {"coordinates":[62.11565,32.46997],"type":"Point"}
}