{
  "type": "Feature",
  "properties": {
    "gn:admin1_code":"33",
    "gn:admin2_code":"3101.0",
    "gn:asciiname":"Bughawi",
    "gn:country_code":"AF",
    "gn:dem":757,
    "gn:feature_class":"P",
    "gn:feature_code":"PPL",
    "gn:name":"Bugh\u0101w\u012b",
    "gn:population":0,
    "gn:timezone":"Asia/Kabul",
    "iso:country":"AF",
    "name:und_x_variant":[
        "Boghai",
        "Bogh\u0101wi",
        "Bogh\u0101v\u012b",
        "Bugh\u0101w\u012b",
        "\u0628\u063a\u0627\u0648\u06cc"
    ],
    "wof:name":"Bughawi",
    "wof:placetype":"locality"
},
  "geometry": {"coordinates":[66.09295,36.16843],"type":"Point"}
}