{
  "type": "Feature",
  "properties": {
    "gn:admin1_code":"01",
    "gn:admin2_code":"1101.0",
    "gn:asciiname":"Aywri Darah",
    "gn:country_code":"AF",
    "gn:dem":2153,
    "gn:feature_class":"P",
    "gn:feature_code":"PPL",
    "gn:name":"Aywr\u012b Darah",
    "gn:population":0,
    "gn:timezone":"Asia/Kabul",
    "iso:country":"AF",
    "name:und_x_variant":[
        "\u0112w\u1e5f\u012b Darrah",
        "\u0627\u06d0\u0648\u0631\u06cc \u062f\u0631\u0647",
        "\u0112w\u1e5f\u012b Darreh",
        "\u0112wr\u012b Darah",
        "Aywr\u012b Darah"
    ],
    "wof:name":"Aywri Darah",
    "wof:placetype":"locality"
},
  "geometry": {"coordinates":[70.60041,37.25184],"type":"Point"}
}