{
  "type": "Feature",
  "properties": {
    "gn:admin1_code":"23",
    "gn:admin2_code":"2412",
    "gn:asciiname":"Spinah Garah",
    "gn:country_code":"AF",
    "gn:dem":1441,
    "gn:feature_class":"P",
    "gn:feature_code":"PPL",
    "gn:name":"Sp\u012bnah G\u0101\u1e5fah",
    "gn:population":0,
    "gn:timezone":"Asia/Kabul",
    "iso:country":"AF",
    "name:und_x_variant":[
        "Spinagara",
        "Sp\u012bna G\u0101\u1e5fa",
        "Sp\u012bnah G\u0101\u1e5fah",
        "\u0633\u067e\u06cc\u0646\u0647 \u06af\u0627\u0693\u0647",
        "Sp\u012bnah Ga\u1e5fah"
    ],
    "wof:name":"Spinah Garah",
    "wof:placetype":"locality"
},
  "geometry": {"coordinates":[66.73484999999999,31.69322],"type":"Point"}
}