{
  "type": "Feature",
  "properties": {
    "gn:admin1_code":"01",
    "gn:admin2_code":"1121",
    "gn:asciiname":"Ubaghn",
    "gn:country_code":"AF",
    "gn:dem":1061,
    "gn:feature_class":"P",
    "gn:feature_code":"PPL",
    "gn:name":"\u016abaghn",
    "gn:population":0,
    "gn:timezone":"Asia/Kabul",
    "iso:country":"AF",
    "name:und_x_variant":[
        "\u016abaghn",
        "\u0627\u0648\u0628\u063a\u0646"
    ],
    "wof:name":"Ubaghn",
    "wof:placetype":"locality"
},
  "geometry": {"coordinates":[70.49258,38.11692],"type":"Point"}
}