{
  "type": "Feature",
  "properties": {
    "gn:admin1_code":"07",
    "gn:admin2_code":"1805",
    "gn:asciiname":"Talab Jar",
    "gn:country_code":"AF",
    "gn:dem":1811,
    "gn:feature_class":"P",
    "gn:feature_code":"PPL",
    "gn:name":"\u0162alab Jar",
    "gn:population":0,
    "gn:timezone":"Asia/Kabul",
    "iso:country":"AF",
    "name:und_x_variant":[
        "\u0162alab Jar",
        "\u0637\u0644\u0628 \u062c\u0631"
    ],
    "wof:name":"Talab Jar",
    "wof:placetype":"locality"
},
  "geometry": {"coordinates":[64.65886,35.35703],"type":"Point"}
}