{
  "type": "Feature",
  "properties": {
    "gn:admin1_code":"01",
    "gn:admin2_code":"1128.0",
    "gn:asciiname":"Pas-e Khir",
    "gn:country_code":"AF",
    "gn:dem":1705,
    "gn:feature_class":"P",
    "gn:feature_code":"PPL",
    "gn:name":"Pas-e Khir",
    "gn:population":0,
    "gn:timezone":"Asia/Kabul",
    "iso:country":"AF",
    "name:und_x_variant":[
        "Pas-i-Khe\u1e5f",
        "Pas-e Khe\u1e5f",
        "Pas-e Khir",
        "\u067e\u0633 \u062e\u0631"
    ],
    "wof:name":"Pas-e Khir",
    "wof:placetype":"locality"
},
  "geometry": {"coordinates":[70.27798,37.57169],"type":"Point"}
}