{
  "type": "Feature",
  "properties": {
    "gn:admin1_code":"33",
    "gn:admin2_code":"3104.0",
    "gn:asciiname":"Kuh-e Dag",
    "gn:country_code":"AF",
    "gn:dem":1519,
    "gn:feature_class":"P",
    "gn:feature_code":"PPL",
    "gn:name":"K\u016bh-e Dag",
    "gn:population":0,
    "gn:timezone":"Asia/Kabul",
    "iso:country":"AF",
    "name:und_x_variant":[
        "Kohe \u1e0eag",
        "K\u016bh-e Dag"
    ],
    "wof:name":"Kuh-e Dag",
    "wof:placetype":"locality"
},
  "geometry": {"coordinates":[66.61556,35.495],"type":"Point"}
}