{
  "type": "Feature",
  "properties": {
    "gn:admin1_code":"05",
    "gn:admin2_code":"2802",
    "gn:asciiname":"Kampiri",
    "gn:country_code":"AF",
    "gn:dem":2881,
    "gn:feature_class":"P",
    "gn:feature_code":"PPL",
    "gn:name":"Kampir\u012b",
    "gn:population":0,
    "gn:timezone":"Asia/Kabul",
    "iso:country":"AF",
    "name:und_x_variant":[
        "Kamperey",
        "Kamp\u012br\u012b",
        "Kampir\u012b",
        "\u06a9\u0645\u067e\u0631\u06cc"
    ],
    "wof:name":"Kampiri",
    "wof:placetype":"locality"
},
  "geometry": {"coordinates":[68.00883,34.68562],"type":"Point"}
}