{
  "type": "Feature",
  "properties": {
    "gn:admin1_code":"05",
    "gn:admin2_code":"2805",
    "gn:asciiname":"Shibar",
    "gn:country_code":"AF",
    "gn:dem":2864,
    "gn:feature_class":"P",
    "gn:feature_code":"PPL",
    "gn:name":"Sh\u012bbar",
    "gn:population":0,
    "gn:timezone":"Asia/Kabul",
    "iso:country":"AF",
    "name:und_x_variant":[
        "\u0160ibar",
        "Shibar",
        "Sh\u012bbar",
        "\u0634\u06cc\u0628\u0631"
    ],
    "wof:name":"Shibar",
    "wof:placetype":"locality"
},
  "geometry": {"coordinates":[66.71709,34.38071],"type":"Point"}
}