{
  "type": "Feature",
  "properties": {
    "gn:admin1_code":"23",
    "gn:admin2_code":"2413.0",
    "gn:asciiname":"Gawidah Chinah",
    "gn:country_code":"AF",
    "gn:dem":1843,
    "gn:feature_class":"P",
    "gn:feature_code":"PPL",
    "gn:name":"G\u0101widah Ch\u012bnah",
    "gn:population":0,
    "gn:timezone":"Asia/Kabul",
    "iso:country":"AF",
    "name:fas_x_preferred":[
        "\u0686\u0634\u0645\u06c0 \u06af\u0627\u0648\u062f\u0647"
    ],
    "name:und_x_variant":[
        "G\u0101weda \u010cina",
        "Gavidachina",
        "G\u0101widah Ch\u012bnah",
        "\u06af\u0627\u0648\u062f\u0647 \u0686\u06cc\u0646\u0647",
        "G\u0101wedh Ch\u012bnah",
        "\u0686\u0634\u0645\u06c0 \u06af\u0627\u0648\u062f\u0647"
    ],
    "wof:name":"Gawidah Chinah",
    "wof:placetype":"locality"
},
  "geometry": {"coordinates":[67.04271,31.52681],"type":"Point"}
}