{
  "type": "Feature",
  "properties": {
    "gn:admin1_code":"08",
    "gn:admin2_code":"609",
    "gn:asciiname":"Vakhabkala",
    "gn:country_code":"AF",
    "gn:dem":1955,
    "gn:feature_class":"P",
    "gn:feature_code":"PPL",
    "gn:name":"Vakhabkala",
    "gn:population":0,
    "gn:timezone":"Asia/Kabul",
    "iso:country":"AF",
    "name:und_x_variant":[
        "Wah\u0101b Kal\u0101",
        "\u0648\u0647\u0627\u0628 \u06a9\u0644\u0627",
        "Vakhabkala"
    ],
    "wof:name":"Vakhabkala",
    "wof:placetype":"locality"
},
  "geometry": {"coordinates":[67.75516999999999,32.66621],"type":"Point"}
}