{
  "type": "Feature",
  "properties": {
    "gn:admin1_code":"24",
    "gn:admin2_code":"1404.0",
    "gn:asciiname":"Qosh Tapah",
    "gn:country_code":"AF",
    "gn:dem":370,
    "gn:feature_class":"P",
    "gn:feature_code":"PPL",
    "gn:name":"Q\u014dsh Tapah",
    "gn:population":0,
    "gn:timezone":"Asia/Kabul",
    "iso:country":"AF",
    "name:rus_x_preferred":[
        "\u041a\u043e\u0448\u0442\u0430\u043f\u0430"
    ],
    "name:und_x_variant":[
        "Qo\u0161 Tapa",
        "Koshtapa",
        "Q\u016bsh Tappeh",
        "Q\u014dsh Tapah",
        "\u0642\u0648\u0634 \u062a\u067e\u0647"
    ],
    "wof:name":"Qosh Tapah",
    "wof:placetype":"locality"
},
  "geometry": {"coordinates":[68.65897,36.78163],"type":"Point"}
}