{
  "type": "Feature",
  "properties": {
    "gn:admin1_code":"03",
    "gn:admin2_code":"1308",
    "gn:asciiname":"Wech",
    "gn:country_code":"AF",
    "gn:dem":2016,
    "gn:feature_class":"P",
    "gn:feature_code":"PPL",
    "gn:name":"W\u00each",
    "gn:population":0,
    "gn:timezone":"Asia/Kabul",
    "iso:country":"AF",
    "name:und_x_variant":[
        "Wu\u010d",
        "Wuch",
        "W\u00each",
        "\u0648\u0686"
    ],
    "wof:name":"Wech",
    "wof:placetype":"locality"
},
  "geometry": {"coordinates":[69.44714999999999,35.98523],"type":"Point"}
}