{
  "type": "Feature",
  "properties": {
    "gn:admin1_code":"03",
    "gn:admin2_code":"1304.0",
    "gn:asciiname":"Lukhtoghay",
    "gn:country_code":"AF",
    "gn:dem":949,
    "gn:feature_class":"P",
    "gn:feature_code":"PPL",
    "gn:name":"Lukht\u014dghay",
    "gn:population":0,
    "gn:timezone":"Asia/Kabul",
    "iso:country":"AF",
    "name:und_x_variant":[
        "Lukhtogay",
        "Lukht\u014dghay",
        "Lukhtowghay",
        "\u0644\u062e\u062a\u0648\u063a\u06cc"
    ],
    "wof:name":"Lukhtoghay",
    "wof:placetype":"locality"
},
  "geometry": {"coordinates":[68.51132,35.60805],"type":"Point"}
}