{
  "type": "Feature",
  "properties": {
    "gn:admin1_code":"14",
    "gn:admin2_code":"206.0",
    "gn:asciiname":"Janah Gul",
    "gn:country_code":"AF",
    "gn:dem":2025,
    "gn:feature_class":"P",
    "gn:feature_code":"PPL",
    "gn:name":"J\u0101nah Gul",
    "gn:population":0,
    "gn:timezone":"Asia/Kabul",
    "iso:country":"AF",
    "name:fas_x_preferred":[
        "\u062c\u0627\u0646\u06af\u0644"
    ],
    "name:rus_x_preferred":[
        "Dzhangal\u2019"
    ],
    "name:und_x_variant":[
        "J\u0101nagal",
        "J\u0101nah Gul",
        "\u062c\u0627\u0646\u0647 \u06af\u0644"
    ],
    "wof:name":"Janah Gul",
    "wof:placetype":"locality"
},
  "geometry": {"coordinates":[69.78059,34.89079],"type":"Point"}
}