{
  "type": "Feature",
  "properties": {
    "gn:admin1_code":"14",
    "gn:admin2_code":"207.0",
    "gn:asciiname":"Qalandar Khel",
    "gn:country_code":"AF",
    "gn:dem":1551,
    "gn:feature_class":"P",
    "gn:feature_code":"PPL",
    "gn:name":"Qalandar Kh\u0113l",
    "gn:population":0,
    "gn:timezone":"Asia/Kabul",
    "iso:country":"AF",
    "name:fas_x_preferred":[
        "\u0642\u0644\u0646\u062f\u0631 \u062e\u064a\u0644"
    ],
    "name:rus_x_preferred":[
        "Kalandarkheyl\u2019"
    ],
    "name:und_x_variant":[
        "Qalan\u1e0fa\u1e5fkh\u0113l",
        "Qalandarkheyl",
        "Qalandar Kh\u0113l",
        "\u0642\u0644\u0646\u062f\u0631 \u062e\u06d0\u0644"
    ],
    "wof:name":"Qalandar Khel",
    "wof:placetype":"locality"
},
  "geometry": {"coordinates":[69.35003,35.09847],"type":"Point"}
}