{
  "type": "Feature",
  "properties": {
    "gn:admin1_code":"19",
    "gn:admin2_code":"2205",
    "gn:asciiname":"Qal'ah Gay",
    "gn:country_code":"AF",
    "gn:dem":845,
    "gn:feature_class":"P",
    "gn:feature_code":"PPL",
    "gn:name":"Qal\u2018ah Gay",
    "gn:population":0,
    "gn:timezone":"Asia/Kabul",
    "iso:country":"AF",
    "name:und_x_variant":[
        "Qal\u2018eh G\u012b",
        "Qal\u2018ag\u012b",
        "Qal\u2018ah Gay",
        "\u0642\u0644\u0639\u0647 \u06af\u06cc"
    ],
    "wof:name":"Qal'ah Gay",
    "wof:placetype":"locality"
},
  "geometry": {"coordinates":[63.52611,32.17039],"type":"Point"}
}