{
  "type": "Feature",
  "properties": {
    "gn:admin1_code":"29",
    "gn:admin2_code":"2906",
    "gn:asciiname":"Dinay Khel",
    "gn:country_code":"AF",
    "gn:dem":2435,
    "gn:feature_class":"P",
    "gn:feature_code":"PPL",
    "gn:name":"D\u012bnay Kh\u0113l",
    "gn:population":0,
    "gn:timezone":"Asia/Kabul",
    "iso:country":"AF",
    "name:fas_x_preferred":[
        "D\u012bnay Kh\u0113l"
    ],
    "name:fas_x_variant":[
        "\u062f\u06cc\u0646\u06cc \u062e\u06cc\u0644"
    ],
    "name:rus_x_preferred":[
        "Dinaykheyl\u2019"
    ],
    "name:und_x_variant":[
        "\u1e0einaykh\u0113l"
    ],
    "wof:name":"Dinay Khel",
    "wof:placetype":"locality"
},
  "geometry": {"coordinates":[68.82111999999999,32.76059],"type":"Point"}
}