{
  "type": "Feature",
  "properties": {
    "gn:admin1_code":"13",
    "gn:admin2_code":"102",
    "gn:asciiname":"Khwajah Chisht",
    "gn:country_code":"AF",
    "gn:dem":1746,
    "gn:feature_class":"P",
    "gn:feature_code":"PPL",
    "gn:name":"Khw\u0101jah Chisht",
    "gn:population":0,
    "gn:timezone":"Asia/Kabul",
    "iso:country":"AF",
    "name:und_x_variant":[
        "Khw\u0101ja-\u010de\u0161t",
        "Khodzhachisht",
        "Khw\u0101jah Chisht",
        "Khv\u0101jeh Chesht",
        "Khw\u0101jah-Chisht",
        "\u062e\u0648\u0627\u062c\u0647 \u0686\u0634\u062a"
    ],
    "wof:name":"Khwajah Chisht",
    "wof:placetype":"locality"
},
  "geometry": {"coordinates":[69.23940999999999,34.64592],"type":"Point"}
}