{
  "type": "Feature",
  "properties": {
    "gn:admin1_code":"27",
    "gn:admin2_code":"404.0",
    "gn:asciiname":"Khalil Murdah",
    "gn:country_code":"AF",
    "gn:dem":3141,
    "gn:feature_class":"P",
    "gn:feature_code":"PPL",
    "gn:name":"Khal\u012bl Murdah",
    "gn:population":0,
    "gn:timezone":"Asia/Kabul",
    "iso:country":"AF",
    "name:rus_x_preferred":[
        "Khalil\u2019murda"
    ],
    "name:und_x_variant":[
        "Khal\u012blmu\u1e5f\u1e0fa",
        "Khal\u012blmordeh",
        "Khal\u012bl Murdah",
        "\u062e\u0644\u06cc\u0644 \u0645\u0631\u062f\u0647"
    ],
    "wof:name":"Khalil Murdah",
    "wof:placetype":"locality"
},
  "geometry": {"coordinates":[68.03201999999999,34.35001],"type":"Point"}
}