{
  "type": "Feature",
  "properties": {
    "gn:admin1_code":"09",
    "gn:admin2_code":"2701",
    "gn:asciiname":"Yowmuki",
    "gn:country_code":"AF",
    "gn:dem":2695,
    "gn:feature_class":"P",
    "gn:feature_code":"PPL",
    "gn:name":"Yowm\u016bk\u012b",
    "gn:population":0,
    "gn:timezone":"Asia/Kabul",
    "iso:country":"AF",
    "name:und_x_variant":[
        "Yowm\u016bk\u012b",
        "\u06cc\u0648\u0645\u0648\u06a9\u06cc",
        "Yawm\u016bki"
    ],
    "wof:name":"Yowmuki",
    "wof:placetype":"locality"
},
  "geometry": {"coordinates":[65.02114,34.71842],"type":"Point"}
}