{
  "type": "Feature",
  "properties": {
    "gn:admin1_code":"03",
    "gn:admin2_code":"1307",
    "gn:asciiname":"Shah Kush",
    "gn:country_code":"AF",
    "gn:dem":1358,
    "gn:feature_class":"P",
    "gn:feature_code":"PPL",
    "gn:name":"Sh\u0101h Kush",
    "gn:population":0,
    "gn:timezone":"Asia/Kabul",
    "iso:country":"AF",
    "name:und_x_variant":[
        "\u0160\u0101kus",
        "Shakush",
        "Sh\u0101h Kush",
        "\u0634\u0627\u0647 \u06a9\u0634"
    ],
    "wof:name":"Shah Kush",
    "wof:placetype":"locality"
},
  "geometry": {"coordinates":[69.11244000000001,35.62233],"type":"Point"}
}