{
  "type": "Feature",
  "properties": {
    "gn:admin1_code":"11",
    "gn:admin2_code":"2012.0",
    "gn:asciiname":"Sunjitak",
    "gn:country_code":"AF",
    "gn:dem":1614,
    "gn:feature_class":"P",
    "gn:feature_code":"PPL",
    "gn:name":"Sunjitak",
    "gn:population":0,
    "gn:timezone":"Asia/Kabul",
    "iso:country":"AF",
    "name:und_x_variant":[
        "\u0633\u0646\u062c\u062a\u06a9",
        "Sunjetak",
        "Sinj\u012btak",
        "\u0633\u0646\u062c\u06cc\u062a\u06a9"
    ],
    "wof:name":"Sunjitak",
    "wof:placetype":"locality"
},
  "geometry": {"coordinates":[63.35487,34.33724],"type":"Point"}
}