{
  "type": "Feature",
  "properties": {
    "gn:admin1_code":"09",
    "gn:admin2_code":"2706",
    "gn:asciiname":"Naychah",
    "gn:country_code":"AF",
    "gn:dem":2458,
    "gn:feature_class":"P",
    "gn:feature_code":"PPL",
    "gn:name":"N\u0101ychah",
    "gn:population":0,
    "gn:timezone":"Asia/Kabul",
    "iso:country":"AF",
    "name:und_x_variant":[
        "Naycha",
        "Nay\u010da",
        "N\u0101ychah",
        "\u0646\u0627\u06cc\u0686\u0647",
        "Neycheh"
    ],
    "wof:name":"Naychah",
    "wof:placetype":"locality"
},
  "geometry": {"coordinates":[64.84003,33.68764],"type":"Point"}
}