{
  "type": "Feature",
  "properties": {
    "gn:admin1_code":"39",
    "gn:admin2_code":"2601",
    "gn:asciiname":"Yak Lingah",
    "gn:country_code":"AF",
    "gn:dem":1254,
    "gn:feature_class":"P",
    "gn:feature_code":"PPL",
    "gn:name":"Yak Lingah",
    "gn:population":0,
    "gn:timezone":"Asia/Kabul",
    "iso:country":"AF",
    "name:fas_x_preferred":[
        "\u064a\u0643\u0644\u0646\u06af\u0647"
    ],
    "name:und_x_variant":[
        "Yaklinga",
        "Yaklenga",
        "Yak Lingah",
        "\u06cc\u06a9 \u0644\u0646\u06af\u0647",
        "Yaklengah"
    ],
    "wof:name":"Yak Lingah",
    "wof:placetype":"locality"
},
  "geometry": {"coordinates":[65.77500000000001,32.59014000000001],"type":"Point"}
}