{
  "type": "Feature",
  "properties": {
    "gn:admin1_code":"01",
    "gn:admin2_code":"1101.0",
    "gn:asciiname":"Deblo",
    "gn:country_code":"AF",
    "gn:dem":2250,
    "gn:feature_class":"P",
    "gn:feature_code":"PPL",
    "gn:name":"D\u0113bl\u014d",
    "gn:population":0,
    "gn:timezone":"Asia/Kabul",
    "iso:country":"AF",
    "name:und_x_variant":[
        "\u062f\u06d0\u0628\u0644\u0648",
        "\u1e0e\u0113bl\u014d",
        "D\u0113bl\u014d"
    ],
    "wof:name":"Deblo",
    "wof:placetype":"locality"
},
  "geometry": {"coordinates":[70.58745999999999,37.30249],"type":"Point"}
}