{
  "type": "Feature",
  "properties": {
    "gn:admin1_code":"36",
    "gn:admin2_code":"701.0",
    "gn:asciiname":"Talbi Khel",
    "gn:country_code":"AF",
    "gn:dem":2396,
    "gn:feature_class":"P",
    "gn:feature_code":"PPL",
    "gn:name":"Talb\u012b Kh\u0113l",
    "gn:population":0,
    "gn:timezone":"Asia/Kabul",
    "iso:country":"AF",
    "name:fas_x_preferred":[
        "\u062a\u0644\u0628\u06cc \u062e\u064a\u0644"
    ],
    "name:rus_x_preferred":[
        "Tal\u2019bikheyl\u2019"
    ],
    "name:und_x_variant":[
        "Talbikh\u0113l",
        "Talb\u012b Kheyl",
        "Talb\u012b Kh\u0113l",
        "\u062a\u0644\u0628\u06cc \u062e\u06d0\u0644"
    ],
    "wof:name":"Talbi Khel",
    "wof:placetype":"locality"
},
  "geometry": {"coordinates":[69.30741999999999,33.65541],"type":"Point"}
}