{
  "type": "Feature",
  "properties": {
    "gn:admin1_code":"26",
    "gn:admin2_code":"1215",
    "gn:asciiname":"Hazarah Chiwah",
    "gn:country_code":"AF",
    "gn:dem":1154,
    "gn:feature_class":"P",
    "gn:feature_code":"PPL",
    "gn:name":"Haz\u0101rah Ch\u012bwah",
    "gn:population":0,
    "gn:timezone":"Asia/Kabul",
    "iso:country":"AF",
    "name:rus_x_preferred":[
        "\u0425\u0430\u0437\u0430\u0440\u0430\u0447\u0438\u0432\u0430"
    ],
    "name:und_x_variant":[
        "Haz\u0101ra \u010c\u012bwa",
        "Haz\u0101ra Ch\u012bwa",
        "Khazarachiva",
        "Hez\u0101reh Ch\u012bwah",
        "Haz\u0101rah Ch\u012bwah",
        "\u0647\u0632\u0627\u0631\u0647 \u0686\u06cc\u0648\u0647"
    ],
    "wof:name":"Hazarah Chiwah",
    "wof:placetype":"locality"
},
  "geometry": {"coordinates":[69.55530999999999,36.8583],"type":"Point"}
}