{
  "type": "Feature",
  "properties": {
    "gn:admin1_code":"01",
    "gn:admin2_code":"1108",
    "gn:asciiname":"Park",
    "gn:country_code":"AF",
    "gn:dem":2518,
    "gn:feature_class":"P",
    "gn:feature_code":"PPL",
    "gn:name":"P\u0101rk",
    "gn:population":0,
    "gn:timezone":"Asia/Kabul",
    "iso:country":"AF",
    "name:und_x_variant":[
        "P\u0101rk"
    ],
    "wof:name":"Park",
    "wof:placetype":"locality"
},
  "geometry": {"coordinates":[70.91667,37.03333],"type":"Point"}
}