{
  "type": "Feature",
  "properties": {
    "gn:admin1_code":"08",
    "gn:admin2_code":"618",
    "gn:asciiname":"Qol-e Shorah",
    "gn:country_code":"AF",
    "gn:dem":2619,
    "gn:feature_class":"P",
    "gn:feature_code":"PPL",
    "gn:name":"Q\u014dl-e Sh\u014drah",
    "gn:population":0,
    "gn:timezone":"Asia/Kabul",
    "iso:country":"AF",
    "name:fas_x_preferred":[
        "\u0642\u0648\u0644\u0654\u0654 \u0634\u0648\u0631\u0647"
    ],
    "name:und_x_variant":[
        "Kuli-Shora",
        "Qole \u0160ora",
        "Q\u014dl-e Sh\u014drah",
        "Qowl-e Sh\u016breh",
        "\u0642\u0648\u0644 \u0634\u0648\u0631\u0647"
    ],
    "wof:name":"Qol-e Shorah",
    "wof:placetype":"locality"
},
  "geometry": {"coordinates":[68.13343,33.4807],"type":"Point"}
}