{
  "type": "Feature",
  "properties": {
    "gn:admin1_code":"01",
    "gn:admin2_code":"1104",
    "gn:asciiname":"Miyan Deh",
    "gn:country_code":"AF",
    "gn:dem":2813,
    "gn:feature_class":"P",
    "gn:feature_code":"PPL",
    "gn:name":"Miy\u0101n Deh",
    "gn:population":0,
    "gn:timezone":"Asia/Kabul",
    "iso:country":"AF",
    "name:und_x_variant":[
        "My\u0101n\u1e0feh",
        "M\u012by\u0101n Deh",
        "Miandekh",
        "\u0645\u06cc\u0627\u0646 \u062f\u0647",
        "M\u012b\u0101n Deh",
        "Miy\u0101n Deh"
    ],
    "wof:name":"Miyan Deh",
    "wof:placetype":"locality"
},
  "geometry": {"coordinates":[70.85624,35.85392],"type":"Point"}
}