{
  "type": "Feature",
  "properties": {
    "gn:admin1_code":"27",
    "gn:admin2_code":"408.0",
    "gn:asciiname":"Tashligh",
    "gn:country_code":"AF",
    "gn:dem":2350,
    "gn:feature_class":"P",
    "gn:feature_code":"PPL",
    "gn:name":"T\u0101shligh",
    "gn:population":0,
    "gn:timezone":"Asia/Kabul",
    "iso:country":"AF",
    "name:und_x_variant":[
        "Tashlig",
        "T\u0101\u0161legh",
        "T\u0101shlaq \u2018Omar Kh\u0113l",
        "T\u0101shlegh",
        "T\u0101shligh",
        "\u062a\u0627\u0634\u0644\u063a"
    ],
    "wof:name":"Tashligh",
    "wof:placetype":"locality"
},
  "geometry": {"coordinates":[68.69889000000001,34.35019],"type":"Point"}
}