{
  "type": "Feature",
  "properties": {
    "gn:admin1_code":"07",
    "gn:admin2_code":"1805",
    "gn:asciiname":"Qishlaq-e Chahatah",
    "gn:country_code":"AF",
    "gn:dem":2331,
    "gn:feature_class":"P",
    "gn:feature_code":"PPL",
    "gn:name":"Qishl\u0101q-e Ch\u0101h\u0101tah",
    "gn:population":0,
    "gn:timezone":"Asia/Kabul",
    "iso:country":"AF",
    "name:und_x_variant":[
        "Qos\u0304 C\u0101h\u0101ta",
        "Qeshl\u0101q-e Ch\u0101h\u0101tah",
        "Qs C\u0101h\u0101ta",
        "Qosh Ch\u0101h\u0101tah",
        "Qishl\u0101q-e Ch\u0101h\u0101tah",
        "\u0642\u0634\u0644\u0627\u0642 \u0686\u0627\u0647\u0627\u062a\u0647"
    ],
    "wof:name":"Qishlaq-e Chahatah",
    "wof:placetype":"locality"
},
  "geometry": {"coordinates":[64.95153000000001,35.27122],"type":"Point"}
}