{
  "type": "Feature",
  "properties": {
    "gn:admin1_code":"11",
    "gn:admin2_code":"2004.0",
    "gn:asciiname":"Tah Kham-e Muhammad Nur Khan",
    "gn:country_code":"AF",
    "gn:dem":1175,
    "gn:feature_class":"P",
    "gn:feature_code":"PPL",
    "gn:name":"Tah Kham-e Mu\u1e29ammad N\u016br Kh\u0101n",
    "gn:population":0,
    "gn:timezone":"Asia/Kabul",
    "iso:country":"AF",
    "name:und_x_variant":[
        "Takhami-Mukhammednurkhan",
        "Tah Kham-i-Mo\u1e29amma\u1e0f N\u016b\u1e5f Kh\u0101n",
        "Tah Kham-e Mo\u1e29ammad N\u016br Kh\u0101n",
        "Tah Kham-e Mu\u1e29ammad N\u016br Kh\u0101n",
        "\u062a\u0647 \u062e\u0645 \u0645\u062d\u0645\u062f \u0646\u0648\u0631 \u062e\u0627\u0646"
    ],
    "wof:name":"Tah Kham-e Muhammad Nur Khan",
    "wof:placetype":"locality"
},
  "geometry": {"coordinates":[62.94034,34.24371],"type":"Point"}
}