{
  "type": "Feature",
  "properties": {
    "gn:admin1_code":"09",
    "gn:admin2_code":"2709",
    "gn:asciiname":"Mian Ghalak",
    "gn:country_code":"AF",
    "gn:dem":2613,
    "gn:feature_class":"P",
    "gn:feature_code":"PPL",
    "gn:name":"M\u012b\u0101n Gh\u0101lak",
    "gn:population":0,
    "gn:timezone":"Asia/Kabul",
    "iso:country":"AF",
    "name:und_x_variant":[
        "My\u0101ngh\u0101lak",
        "M\u012b\u0101n Gh\u0101lak",
        "\u0645\u06cc\u0627\u0646 \u063a\u0627\u0644\u06a9"
    ],
    "wof:name":"Mian Ghalak",
    "wof:placetype":"locality"
},
  "geometry": {"coordinates":[65.65311,34.64012],"type":"Point"}
}