{
  "type": "Feature",
  "properties": {
    "gn:admin1_code":"08",
    "gn:admin2_code":"604",
    "gn:asciiname":"Gardan-e Bakhara",
    "gn:country_code":"AF",
    "gn:dem":3207,
    "gn:feature_class":"P",
    "gn:feature_code":"PPL",
    "gn:name":"Gardan-e Bakh\u0101r\u0101",
    "gn:population":0,
    "gn:timezone":"Asia/Kabul",
    "iso:country":"AF",
    "name:fas_x_preferred":[
        "\u06af\u0631\u062f\u0646\u0654 \u0628\u062e\u0627\u0631\u0627"
    ],
    "name:rus_x_preferred":[
        "\u0413\u0430\u0440\u0434\u0430\u043d\u0438-\u0411\u0430\u0445\u0430\u0440\u0430"
    ],
    "name:und_x_variant":[
        "Gardani-Bakhara",
        "Gardan-e Bakh\u0101r\u0101",
        "\u06af\u0631\u062f\u0646 \u0628\u062e\u0627\u0631\u0627"
    ],
    "wof:name":"Gardan-e Bakhara",
    "wof:placetype":"locality"
},
  "geometry": {"coordinates":[67.70773,33.51569],"type":"Point"}
}