{
  "type": "Feature",
  "properties": {
    "gn:admin1_code":"01",
    "gn:admin2_code":"1106",
    "gn:asciiname":"Warut",
    "gn:country_code":"AF",
    "gn:dem":2725,
    "gn:feature_class":"P",
    "gn:feature_code":"PPL",
    "gn:name":"Warut",
    "gn:population":0,
    "gn:timezone":"Asia/Kabul",
    "iso:country":"AF",
    "name:und_x_variant":[
        "Orgoon",
        "Y\u016brgand",
        "V\u0101r\u016bp",
        "Urg\u016bn",
        "Warut",
        "Warup",
        "\u016ar\u016bp",
        "\u0627\u0648\u0631\u0648\u067e"
    ],
    "wof:name":"Warut",
    "wof:placetype":"locality"
},
  "geometry": {"coordinates":[71.98849,36.77544],"type":"Point"}
}