{
  "type": "Feature",
  "properties": {
    "gn:admin1_code":"29",
    "gn:admin2_code":"2915.0",
    "gn:asciiname":"Kudali",
    "gn:country_code":"AF",
    "gn:dem":2119,
    "gn:feature_class":"P",
    "gn:feature_code":"PPL",
    "gn:name":"Ku\u1e0fal\u012b",
    "gn:population":0,
    "gn:timezone":"Asia/Kabul",
    "iso:country":"AF",
    "name:und_x_variant":[
        "\u06a9\u0689\u0644\u06cc",
        "Kodali",
        "Ku\u1e0fal\u012b",
        "K\u014d\u1e0fal\u012b"
    ],
    "wof:name":"Kudali",
    "wof:placetype":"locality"
},
  "geometry": {"coordinates":[68.86329000000001,33.26473],"type":"Point"}
}