{
  "type": "Feature",
  "properties": {
    "gn:admin1_code":"09",
    "gn:admin2_code":"2706",
    "gn:asciiname":"Joy-e Purdil",
    "gn:country_code":"AF",
    "gn:dem":2266,
    "gn:feature_class":"P",
    "gn:feature_code":"PPL",
    "gn:name":"J\u014dy-e Purdil",
    "gn:population":0,
    "gn:timezone":"Asia/Kabul",
    "iso:country":"AF",
    "name:fas_x_preferred":[
        "\u062c\u0648\u0626 \u067e\u0648\u0631\u062f\u0644"
    ],
    "name:rus_x_preferred":[
        "\u0414\u0436\u043e\u0439\u0438-\u041f\u0443\u0440\u0434\u0438\u043b\u044c"
    ],
    "name:und_x_variant":[
        "J\u016by-ye Pordel",
        "J\u014dye Pu\u1e5f\u1e0fel",
        "Dzhoyi-Purdil\u2019",
        "J\u014dy-e Purdil",
        "\u062c\u0648\u06cc \u067e\u0631\u062f\u0644",
        "J\u016by-e Pordel"
    ],
    "wof:name":"Joy-e Purdil",
    "wof:placetype":"locality"
},
  "geometry": {"coordinates":[65.02439,33.41349],"type":"Point"}
}