{
  "type": "Feature",
  "properties": {
    "gn:admin1_code":"09",
    "gn:admin2_code":"2707",
    "gn:asciiname":"Now Nishan",
    "gn:country_code":"AF",
    "gn:dem":3141,
    "gn:feature_class":"P",
    "gn:feature_code":"PPL",
    "gn:name":"Now Nish\u0101n",
    "gn:population":0,
    "gn:timezone":"Asia/Kabul",
    "iso:country":"AF",
    "name:und_x_variant":[
        "Naunishan",
        "Nawne\u0161\u0101n",
        "Nownesh\u0101n",
        "Now Nish\u0101n",
        "\u0646\u0648 \u0646\u0634\u0627\u0646"
    ],
    "wof:name":"Now Nishan",
    "wof:placetype":"locality"
},
  "geometry": {"coordinates":[66.52969,34.43381],"type":"Point"}
}