{
  "type": "Feature",
  "properties": {
    "gn:admin1_code":"28",
    "gn:admin2_code":"2506.0",
    "gn:asciiname":"Miltanay",
    "gn:country_code":"AF",
    "gn:dem":1491,
    "gn:feature_class":"P",
    "gn:feature_code":"PPL",
    "gn:name":"Miltanay",
    "gn:population":0,
    "gn:timezone":"Asia/Kabul",
    "iso:country":"AF",
    "name:rus_x_preferred":[
        "Mil\u2019tanay"
    ],
    "name:und_x_variant":[
        "\u0645\u0644\u062a\u0646\u06cc",
        "Meltanay",
        "Miltanay"
    ],
    "wof:name":"Miltanay",
    "wof:placetype":"locality"
},
  "geometry": {"coordinates":[66.71483000000001,31.91956],"type":"Point"}
}