{
  "type": "Feature",
  "properties": {
    "gn:admin1_code":"38",
    "gn:admin2_code":"3006.0",
    "gn:asciiname":"Boni",
    "gn:country_code":"AF",
    "gn:dem":2190,
    "gn:feature_class":"P",
    "gn:feature_code":"PPL",
    "gn:name":"Boni",
    "gn:population":0,
    "gn:timezone":"Asia/Kabul",
    "iso:country":"AF",
    "name:ceb_x_preferred":[
        "Boni"
    ],
    "name:deu_x_preferred":[
        "Boni"
    ],
    "name:fas_x_preferred":[
        "\u0628\u0648\u0646\u06cc"
    ],
    "name:fra_x_preferred":[
        "Boni"
    ],
    "name:ita_x_preferred":[
        "Boni"
    ],
    "name:nld_x_preferred":[
        "Boni"
    ],
    "name:pol_x_preferred":[
        "Boni"
    ],
    "name:por_x_preferred":[
        "Boni"
    ],
    "name:rus_x_preferred":[
        "\u0411\u043e\u043d\u0438"
    ],
    "name:srp_x_preferred":[
        "\u0411\u043e\u043d\u0438"
    ],
    "name:swe_x_preferred":[
        "Boni"
    ],
    "name:und_x_variant":[
        "B\u014dni",
        "\u0628\u0648\u0646\u06cc",
        "Bown\u012b",
        "B\u014dn\u012b"
    ],
    "wof:name":"Boni",
    "wof:placetype":"locality"
},
  "geometry": {"coordinates":[70.8385,35.19357],"type":"Point"}
}