{
  "type": "Feature",
  "properties": {
    "gn:admin1_code":"38",
    "gn:admin2_code":"3006.0",
    "gn:asciiname":"Boni",
    "gn:country_code":"AF",
    "gn:dem":2190,
    "gn:feature_class":"P",
    "gn:feature_code":"PPL",
    "gn:name":"Boni",
    "gn:population":0,
    "gn:timezone":"Asia/Kabul",
    "iso:country":"AF",
    "name:und_x_variant":[
        "B\u014dni",
        "\u0628\u0648\u0646\u06cc",
        "Bown\u012b",
        "B\u014dn\u012b"
    ],
    "wof:name":"Boni",
    "wof:placetype":"locality"
},
  "geometry": {"coordinates":[70.8385,35.19357],"type":"Point"}
}