{
  "type": "Feature",
  "properties": {
    "gn:admin1_code":"11",
    "gn:admin2_code":"2013",
    "gn:asciiname":"Kilkak",
    "gn:country_code":"AF",
    "gn:dem":2369,
    "gn:feature_class":"P",
    "gn:feature_code":"PPL",
    "gn:name":"Kilkak",
    "gn:population":0,
    "gn:timezone":"Asia/Kabul",
    "iso:country":"AF",
    "name:rus_x_preferred":[
        "Kil\u2019kak"
    ],
    "name:und_x_variant":[
        "\u06a9\u0644\u06a9\u06a9",
        "Kelkak"
    ],
    "wof:name":"Kilkak",
    "wof:placetype":"locality"
},
  "geometry": {"coordinates":[63.29506,33.80857],"type":"Point"}
}