{
  "type": "Feature",
  "properties": {
    "gn:admin1_code":"29",
    "gn:admin2_code":"2904",
    "gn:asciiname":"Hayat Khel",
    "gn:country_code":"AF",
    "gn:dem":2260,
    "gn:feature_class":"P",
    "gn:feature_code":"PPL",
    "gn:name":"\u1e28ay\u0101t Kh\u0113l",
    "gn:population":0,
    "gn:timezone":"Asia/Kabul",
    "iso:country":"AF",
    "name:rus_x_preferred":[
        "Khayatkheyl\u2019"
    ],
    "name:und_x_variant":[
        "H\u0331ay\u0101t Kh\u0113l",
        "\u062d\u06cc\u0627\u062a \u062e\u06cc\u0644",
        "\u1e28ay\u0101t Kheyl",
        "\u1e28ay\u0101t Kh\u0113l"
    ],
    "wof:name":"Hayat Khel",
    "wof:placetype":"locality"
},
  "geometry": {"coordinates":[68.3334,32.19612],"type":"Point"}
}