{
  "type": "Feature",
  "properties": {
    "gn:admin1_code":"13",
    "gn:admin2_code":"107",
    "gn:asciiname":"Qal'ah-ye Yonus",
    "gn:country_code":"AF",
    "gn:dem":2329,
    "gn:feature_class":"P",
    "gn:feature_code":"PPL",
    "gn:name":"Qal\u2018ah-ye Y\u014dnus",
    "gn:population":0,
    "gn:timezone":"Asia/Kabul",
    "iso:country":"AF",
    "name:und_x_variant":[
        "Qal\u2018a-i-Y\u014dnus",
        "Qal\u2018eh-ye Y\u014dnus",
        "Qal\u2018a Y\u014dnus",
        "Kalayunus",
        "Qal\u2018ah-ye Y\u014dnus",
        "Qal\u2018eh-ye Y\u016bnos",
        "\u0642\u0644\u0639\u0647 \u06cc\u0648\u0646\u0633"
    ],
    "wof:name":"Qal'ah-ye Yonus",
    "wof:placetype":"locality"
},
  "geometry": {"coordinates":[68.98298,34.70441],"type":"Point"}
}