{
  "type": "Feature",
  "properties": {
    "gn:admin1_code":"28",
    "gn:admin2_code":"2506.0",
    "gn:asciiname":"Pul-e Sowz",
    "gn:country_code":"AF",
    "gn:dem":1282,
    "gn:feature_class":"P",
    "gn:feature_code":"PPL",
    "gn:name":"Pul-e Sowz",
    "gn:population":0,
    "gn:timezone":"Asia/Kabul",
    "iso:country":"AF",
    "name:und_x_variant":[
        "Pul\u2019sauz",
        "Pul Sawz",
        "\u067e\u0644 \u0633\u0648\u0632",
        "Sabz",
        "Pol-e Sabz",
        "\u0633\u0628\u0632",
        "Pul-e Sawz",
        "Pul-e Sowz"
    ],
    "wof:name":"Pul-e Sowz",
    "wof:placetype":"locality"
},
  "geometry": {"coordinates":[66.3661,31.79894],"type":"Point"}
}