{
  "type": "Feature",
  "properties": {
    "gn:admin1_code":"01",
    "gn:admin2_code":"1112.0",
    "gn:asciiname":"Rubat-e Seh Ab",
    "gn:country_code":"AF",
    "gn:dem":2580,
    "gn:feature_class":"P",
    "gn:feature_code":"PPL",
    "gn:name":"Rub\u0101\u0163-e Seh \u0100b",
    "gn:population":0,
    "gn:timezone":"Asia/Kabul",
    "iso:country":"AF",
    "name:und_x_variant":[
        "Rab\u0101\u0163-i-Seh Ab",
        "\u0631\u0628\u0627\u0637 \u0633\u0647 \u0622\u0628",
        "Rob\u0101\u0163-e Seh \u0100b",
        "Rab\u0101\u0163-e Seh \u0100b",
        "Rub\u0101\u0163-e Seh \u0100b"
    ],
    "wof:name":"Rubat-e Seh Ab",
    "wof:placetype":"locality"
},
  "geometry": {"coordinates":[70.63287,37.58947],"type":"Point"}
}