{
  "type": "Feature",
  "properties": {
    "gn:admin1_code":"36",
    "gn:admin2_code":"711.0",
    "gn:asciiname":"Chownay",
    "gn:country_code":"AF",
    "gn:dem":2161,
    "gn:feature_class":"P",
    "gn:feature_code":"PPL",
    "gn:name":"Chow\u1e49ay",
    "gn:population":0,
    "gn:timezone":"Asia/Kabul",
    "iso:country":"AF",
    "name:und_x_variant":[
        "\u010cawnay",
        "Chaw\u1e49ay",
        "Chow\u1e49\u00eay",
        "Chow\u1e49ay",
        "\u0686\u0648\u06bc\u06cc"
    ],
    "wof:name":"Chownay",
    "wof:placetype":"locality"
},
  "geometry": {"coordinates":[69.70969000000001,33.93621],"type":"Point"}
}