{
  "type": "Feature",
  "properties": {
    "gn:admin1_code":"30",
    "gn:admin2_code":"1609",
    "gn:asciiname":"Diwan",
    "gn:country_code":"AF",
    "gn:dem":884,
    "gn:feature_class":"P",
    "gn:feature_code":"PPL",
    "gn:name":"D\u012bw\u0101n",
    "gn:population":0,
    "gn:timezone":"Asia/Kabul",
    "iso:country":"AF",
    "name:und_x_variant":[
        "D\u012bwan",
        "D\u012bv\u0101n",
        "D\u012bw\u0101n",
        "\u062f\u06cc\u0648\u0627\u0646"
    ],
    "wof:name":"Diwan",
    "wof:placetype":"locality"
},
  "geometry": {"coordinates":[66.83412,36.14471],"type":"Point"}
}