{
  "type": "Feature",
  "properties": {
    "gn:admin1_code":"30",
    "gn:admin2_code":"1609",
    "gn:asciiname":"Diwan",
    "gn:country_code":"AF",
    "gn:dem":884,
    "gn:feature_class":"P",
    "gn:feature_code":"PPL",
    "gn:name":"D\u012bw\u0101n",
    "gn:population":0,
    "gn:timezone":"Asia/Kabul",
    "iso:country":"AF",
    "name:ara_x_preferred":[
        "\u062f\u064a\u0648\u0627\u0646"
    ],
    "name:cat_x_preferred":[
        "Diwan"
    ],
    "name:ceb_x_preferred":[
        "Diwan"
    ],
    "name:ckb_x_preferred":[
        "\u062f\u06cc\u0648\u0627\u0646"
    ],
    "name:deu_x_preferred":[
        "Diwan"
    ],
    "name:fas_x_preferred":[
        "\u062f\u06cc\u0648\u0627\u0646"
    ],
    "name:fra_x_preferred":[
        "Diwan"
    ],
    "name:ita_x_preferred":[
        "Diwan"
    ],
    "name:nld_x_preferred":[
        "Diwan"
    ],
    "name:pol_x_preferred":[
        "Dywan"
    ],
    "name:por_x_preferred":[
        "Div\u00e3"
    ],
    "name:swe_x_preferred":[
        "Diwan"
    ],
    "name:und_x_variant":[
        "D\u012bwan",
        "D\u012bv\u0101n",
        "D\u012bw\u0101n"
    ],
    "name:urd_x_preferred":[
        "\u062f\u06cc\u0648\u0627\u0646"
    ],
    "wof:name":"Diwan",
    "wof:placetype":"locality"
},
  "geometry": {"coordinates":[66.83412,36.14471],"type":"Point"}
}