{
  "type": "Feature",
  "properties": {
    "gn:admin1_code":"24",
    "gn:admin2_code":"1407.0",
    "gn:asciiname":"Khwajah Gardab",
    "gn:country_code":"AF",
    "gn:dem":414,
    "gn:feature_class":"P",
    "gn:feature_code":"PPL",
    "gn:name":"Khw\u0101jah Gard\u0101b",
    "gn:population":0,
    "gn:timezone":"Asia/Kabul",
    "iso:country":"AF",
    "name:und_x_variant":[
        "Khw\u0101jah Gard\u0101b",
        "\u062e\u0648\u0627\u062c\u0647 \u06af\u0631\u062f\u0627\u0628",
        "Khv\u0101jeh Gard\u0101b"
    ],
    "wof:name":"Khwajah Gardab",
    "wof:placetype":"locality"
},
  "geometry": {"coordinates":[69.28378000000001,37.0972],"type":"Point"}
}