{
  "type": "Feature",
  "properties": {
    "gn:admin1_code":"8",
    "gn:admin2_code":"607.0",
    "gn:asciiname":"Sang Shindah",
    "gn:country_code":"AF",
    "gn:dem":2760,
    "gn:feature_class":"P",
    "gn:feature_code":"PPL",
    "gn:name":"Sang Shindah",
    "gn:population":0,
    "gn:timezone":"Asia/Kabul",
    "iso:country":"AF",
    "name:fas_x_preferred":[
        "\u0633\u0646\u06af \u0634\u064a\u0646\u062f\u0647"
    ],
    "name:rus_x_preferred":[
        "\u0421\u0430\u043d\u0433\u0448\u0438\u043d\u0434\u0430"
    ],
    "name:und_x_variant":[
        "Sange S\u0101n\u1e0fe",
        "Sang \u0160en\u1e0fa",
        "Sangshinda",
        "Sang Sh\u012bndah",
        "Sang Shindah",
        "\u0633\u0646\u06af \u0634\u0646\u062f\u0647"
    ],
    "wof:name":"Sang Shindah",
    "wof:placetype":"locality"
},
  "geometry": {"coordinates":[67.50985,33.03328],"type":"Point"}
}