{
  "type": "Feature",
  "properties": {
    "gn:admin1_code":"36",
    "gn:admin2_code":"701.0",
    "gn:asciiname":"Ghundey Kelay",
    "gn:country_code":"AF",
    "gn:dem":2315,
    "gn:feature_class":"P",
    "gn:feature_code":"PPL",
    "gn:name":"Ghun\u1e0f\u00eay K\u00ealay",
    "gn:population":0,
    "gn:timezone":"Asia/Kabul",
    "iso:country":"AF",
    "name:fas_x_preferred":[
        "\u063a\u0631\u0654 \u0643\u0644\u06cc"
    ],
    "name:und_x_variant":[
        "Garkalay",
        "Gha\u1e5f Kalay",
        "Ghar-e Kalay",
        "Ghun\u1e0f\u00eay K\u00ealay",
        "\u063a\u0646\u0689\u06cd \u06a9\u0644\u06cc"
    ],
    "wof:name":"Ghundey Kelay",
    "wof:placetype":"locality"
},
  "geometry": {"coordinates":[69.23438,33.57168],"type":"Point"}
}