{
  "type": "Feature",
  "properties": {
    "gn:gn_country":"AF",
    "gn:gn_fcode":"PPL",
    "gn:gn_pop":6979,
    "gn:population":6979,
    "iso:country":"AF",
    "name:unk_x_variant":[
        "Tirpul"
    ],
    "qs_pg:aaroncc":"AF",
    "qs_pg:gn_country":"AF",
    "qs_pg:gn_fcode":"PPL",
    "qs_pg:gn_pop":6979,
    "qs_pg:name":"T\u012br Pul",
    "qs_pg:photos_9r":0,
    "qs_pg:photos_sr":0,
    "qs_pg:pop_sr":5,
    "qs_pg:qs_pg_placetype":"locality",
    "wof:name":"T\u012br Pul",
    "wof:placetype":"locality",
    "wof:population":6979
},
  "geometry": {"coordinates":[61.26895,34.59431],"type":"Point"}
}