{
  "type": "Feature",
  "properties": {
    "gn:admin1_code":"08",
    "gn:admin2_code":"605",
    "gn:asciiname":"Qalandar Khel",
    "gn:country_code":"AF",
    "gn:dem":2546,
    "gn:feature_class":"P",
    "gn:feature_code":"PPL",
    "gn:name":"Qalandar Kh\u0113l",
    "gn:population":0,
    "gn:timezone":"Asia/Kabul",
    "iso:country":"AF",
    "name:und_x_variant":[
        "Qalan\u1e0fa\u1e5fkh\u0113l",
        "Qalandar Kheyl",
        "Qalandar Kh\u0113l",
        "\u0642\u0644\u0646\u062f\u0631 \u062e\u06d0\u0644"
    ],
    "wof:name":"Qalandar Khel",
    "wof:placetype":"locality"
},
  "geometry": {"coordinates":[67.15278000000001,33.48694],"type":"Point"}
}