{
  "type": "Feature",
  "properties": {
    "gn:admin1_code":"08",
    "gn:admin2_code":"614",
    "gn:asciiname":"Sahib Khan",
    "gn:country_code":"AF",
    "gn:dem":2071,
    "gn:feature_class":"P",
    "gn:feature_code":"PPL",
    "gn:name":"\u015e\u0101\u1e29ib Kh\u0101n",
    "gn:population":0,
    "gn:timezone":"Asia/Kabul",
    "iso:country":"AF",
    "name:fas_x_preferred":[
        "\u0635\u0627\u062d\u0628 \u062e\u0627\u0646"
    ],
    "name:und_x_variant":[
        "Qaryah-ye \u015e\u0101heb Kh\u0101n",
        "Sakhibkhan",
        "\u015e\u0101\u1e29eb Kh\u0101n",
        "\u0635\u0627\u062d\u0628 \u062e\u0627\u0646",
        "\u015e\u0101\u1e29ib Kh\u0101n"
    ],
    "wof:name":"Sahib Khan",
    "wof:placetype":"locality"
},
  "geometry": {"coordinates":[68.41299000000001,33.31525999999999],"type":"Point"}
}