{
  "type": "Feature",
  "properties": {
    "gn:admin1_code":"35",
    "gn:admin2_code":"902.0",
    "gn:asciiname":"Spin Juma'at",
    "gn:country_code":"AF",
    "gn:dem":628,
    "gn:feature_class":"P",
    "gn:feature_code":"PPL",
    "gn:name":"Sp\u012bn Jum\u0101\u2019at",
    "gn:population":0,
    "gn:timezone":"Asia/Kabul",
    "iso:country":"AF",
    "wof:name":"Spin Juma'at",
    "wof:placetype":"locality"
},
  "geometry": {"coordinates":[70.35481,34.51854],"type":"Point"}
}