{
  "type": "Feature",
  "properties": {
    "gn:admin1_code":"24",
    "gn:admin2_code":"1406.0",
    "gn:asciiname":"Myahli",
    "gn:country_code":"AF",
    "gn:dem":927,
    "gn:feature_class":"P",
    "gn:feature_code":"PPL",
    "gn:name":"Myahl\u012b",
    "gn:population":0,
    "gn:timezone":"Asia/Kabul",
    "iso:country":"AF",
    "name:fas_x_preferred":[
        "\u0645\u064a\u0644\u06cc"
    ],
    "name:rus_x_preferred":[
        "\u041c\u0438\u0430\u043b\u0438"
    ],
    "name:und_x_variant":[
        "Miali",
        "Myal\u012b",
        "Myahl\u012b",
        "\u0645\u06cc\u0647 \u0644\u06cc"
    ],
    "wof:name":"Myahli",
    "wof:placetype":"locality"
},
  "geometry": {"coordinates":[69.14874,36.57451],"type":"Point"}
}