{
  "type": "Feature",
  "properties": {
    "gn:admin1_code":"32",
    "gn:admin2_code":"1504.0",
    "gn:asciiname":"Galahwan Say",
    "gn:country_code":"AF",
    "gn:dem":1727,
    "gn:feature_class":"P",
    "gn:feature_code":"PPL",
    "gn:name":"Galahw\u0101n S\u0101y",
    "gn:population":0,
    "gn:timezone":"Asia/Kabul",
    "iso:country":"AF",
    "name:und_x_variant":[
        "Galahw\u0101n S\u0101y",
        "\u06af\u0644\u0647 \u0648\u0627\u0646 \u0633\u0627\u06cc"
    ],
    "wof:name":"Galahwan Say",
    "wof:placetype":"locality"
},
  "geometry": {"coordinates":[67.32949000000001,36.00849],"type":"Point"}
}