{
  "type": "Feature",
  "properties": {
    "gn:admin1_code":"9",
    "gn:admin2_code":"2702.0",
    "gn:asciiname":"Dahan-Duta'i",
    "gn:country_code":"AF",
    "gn:dem":2243,
    "gn:feature_class":"P",
    "gn:feature_code":"PPL",
    "gn:name":"Dah\u0101n-Dut\u0101\u2019\u012b",
    "gn:population":0,
    "gn:timezone":"Asia/Kabul",
    "iso:country":"AF",
    "name:und_x_variant":[
        "Dakhandutai",
        "Dahan Dot\u0101\u2019\u012b",
        "Dah\u0101n-Dut\u0101\u2019\u012b",
        "\u062f\u0647\u0627\u0646 \u062f\u0648\u062a\u0627\u0626\u06cc"
    ],
    "wof:name":"Dahan-Duta'i",
    "wof:placetype":"locality"
},
  "geometry": {"coordinates":[64.61759000000001,34.31610999999999],"type":"Point"}
}