{
  "type": "Feature",
  "properties": {
    "gn:admin1_code":"06",
    "gn:admin2_code":"2101.0",
    "gn:asciiname":"Showalga Janubi",
    "gn:country_code":"AF",
    "gn:dem":698,
    "gn:feature_class":"P",
    "gn:feature_code":"PPL",
    "gn:name":"Show\u0101lg\u0101 Jan\u016bb\u012b",
    "gn:population":0,
    "gn:timezone":"Asia/Kabul",
    "iso:country":"AF",
    "name:rus_x_preferred":[
        "Shaval\u2019gakh-Dzhanubi"
    ],
    "name:und_x_variant":[
        "\u0160ow\u0101lg\u0101 Jan\u016bb\u012b",
        "Sh\u0101h W\u0101lg\u0101 Jan\u016bbi",
        "Sh\u0101h W\u0101lg\u0101 Jon\u016bb\u012b",
        "Show\u0101lg\u0101 Jan\u016bb\u012b",
        "\u0634\u0648\u0627\u0644\u06af\u0627 \u062c\u0646\u0648\u0628\u06cc"
    ],
    "wof:name":"Showalga Janubi",
    "wof:placetype":"locality"
},
  "geometry": {"coordinates":[62.27244,32.50829],"type":"Point"}
}