{
  "type": "Feature",
  "properties": {
    "gn:admin1_code":"30",
    "gn:admin2_code":"1609.0",
    "gn:asciiname":"Alakah Jar",
    "gn:country_code":"AF",
    "gn:dem":520,
    "gn:feature_class":"P",
    "gn:feature_code":"PPL",
    "gn:name":"Alakah Jar",
    "gn:population":0,
    "gn:timezone":"Asia/Kabul",
    "iso:country":"AF",
    "name:und_x_variant":[
        "\u0627\u0644\u06a9\u0647 \u062c\u0631",
        "Alakajar"
    ],
    "wof:name":"Alakah Jar",
    "wof:placetype":"locality"
},
  "geometry": {"coordinates":[66.91268000000001,36.48721],"type":"Point"}
}