{
  "type": "Feature",
  "properties": {
    "gn:admin1_code":"05",
    "gn:admin2_code":"2806",
    "gn:asciiname":"Shiniah",
    "gn:country_code":"AF",
    "gn:dem":2328,
    "gn:feature_class":"P",
    "gn:feature_code":"PPL",
    "gn:name":"Sh\u012bn\u012bah",
    "gn:population":0,
    "gn:timezone":"Asia/Kabul",
    "iso:country":"AF",
    "name:und_x_variant":[
        "\u0160\u012bneya",
        "Sh\u012bneyah",
        "Sh\u012bn\u012bah",
        "\u0634\u06cc\u0646\u06cc\u0647"
    ],
    "wof:name":"Shiniah",
    "wof:placetype":"locality"
},
  "geometry": {"coordinates":[67.12966999999999,33.98771],"type":"Point"}
}