{
  "type": "Feature",
  "properties": {
    "gn:admin1_code":"35",
    "gn:admin2_code":"902.0",
    "gn:asciiname":"Qal'ah-ye Qazi",
    "gn:country_code":"AF",
    "gn:dem":614,
    "gn:feature_class":"P",
    "gn:feature_code":"PPL",
    "gn:name":"Qal\u2018ah-ye Q\u0101\u1e95\u012b",
    "gn:population":0,
    "gn:timezone":"Asia/Kabul",
    "iso:country":"AF",
    "name:und_x_variant":[
        "Qal\u2018ah-ye Q\u0101\u1e95\u012b",
        "\u0642\u0644\u0639\u06c0 \u0642\u0627\u0636\u06cc"
    ],
    "wof:name":"Qal'ah-ye Qazi",
    "wof:placetype":"locality"
},
  "geometry": {"coordinates":[70.29489000000001,34.52118],"type":"Point"}
}