{
  "type": "Feature",
  "properties": {
    "gn:admin1_code":"13",
    "gn:admin2_code":"112",
    "gn:asciiname":"Mir Ghundey",
    "gn:country_code":"AF",
    "gn:dem":1324,
    "gn:feature_class":"P",
    "gn:feature_code":"PPL",
    "gn:name":"M\u012br Ghun\u1e0f\u00eay",
    "gn:population":0,
    "gn:timezone":"Asia/Kabul",
    "iso:country":"AF",
    "name:fas_x_preferred":[
        "\u0643\u0648\u0647\u0654 \u0645\u064a\u0631"
    ],
    "name:und_x_variant":[
        "Mirgar",
        "\u0645\u06cc\u0631 \u063a\u0646\u0689\u06cd",
        "Mi\u1e5f Gha\u1e5f",
        "M\u012br Ghun\u1e0f\u00eay"
    ],
    "wof:name":"Mir Ghundey",
    "wof:placetype":"locality"
},
  "geometry": {"coordinates":[69.77175,34.47966],"type":"Point"}
}