{
  "type": "Feature",
  "properties": {
    "gn:admin1_code":"37",
    "gn:admin2_code":"3211.0",
    "gn:asciiname":"Towdah Chinah",
    "gn:country_code":"AF",
    "gn:dem":1379,
    "gn:feature_class":"P",
    "gn:feature_code":"PPL",
    "gn:name":"Towdah Ch\u012bnah",
    "gn:population":0,
    "gn:timezone":"Asia/Kabul",
    "iso:country":"AF",
    "name:und_x_variant":[
        "Towdah Ch\u012bnah",
        "\u062a\u0648\u062f\u0647 \u0686\u06cc\u0646\u0647"
    ],
    "wof:name":"Towdah Chinah",
    "wof:placetype":"locality"
},
  "geometry": {"coordinates":[70.00239999999999,33.23948],"type":"Point"}
}