{
  "type": "Feature",
  "properties": {
    "gn:admin1_code":"02",
    "gn:admin2_code":"1902",
    "gn:asciiname":"Pahlawan",
    "gn:country_code":"AF",
    "gn:dem":856,
    "gn:feature_class":"P",
    "gn:feature_code":"PPL",
    "gn:name":"Pahlaw\u0101n",
    "gn:population":0,
    "gn:timezone":"Asia/Kabul",
    "iso:country":"AF",
    "name:nld_x_preferred":[
        "Pahlawan"
    ],
    "name:und_x_variant":[
        "Pakhlavan",
        "Pahlaw\u0101n",
        "\u067e\u0647\u0644\u0648\u0627\u0646",
        "Pahlav\u0101n"
    ],
    "wof:name":"Pahlawan",
    "wof:placetype":"locality"
},
  "geometry": {"coordinates":[63.04298000000001,34.97681],"type":"Point"}
}