{
  "type": "Feature",
  "properties": {
    "gn:admin1_code":"23",
    "gn:admin2_code":"2413",
    "gn:asciiname":"De Klake Shelah",
    "gn:country_code":"AF",
    "gn:dem":1942,
    "gn:feature_class":"P",
    "gn:feature_code":"PPL",
    "gn:name":"D\u00ea Klak\u0113 Sh\u0113lah",
    "gn:population":0,
    "gn:timezone":"Asia/Kabul",
    "iso:country":"AF",
    "name:und_x_variant":[
        "Kilakeshela",
        "Kelak\u012b Sh\u012blah",
        "Klak\u0113 S\u0304ela",
        "De Kelak\u0113 Sh\u0113lah",
        "\u1e0ee Kelak\u0113 S\u0304\u0113la",
        "D\u00ea Klak\u0113 Sh\u0113lah",
        "De Kelakey Sheylah",
        "D\u00ea Klak\u0113 Shaylah",
        "\u062f \u06a9\u0644\u06a9\u06d0 \u0634\u06d0\u0644\u0647"
    ],
    "wof:name":"De Klake Shelah",
    "wof:placetype":"locality"
},
  "geometry": {"coordinates":[67.11105999999999,31.25215],"type":"Point"}
}