{
  "type": "Feature",
  "properties": {
    "gn:admin1_code":"40",
    "gn:admin2_code":"308.0",
    "gn:asciiname":"Qal'ah-ye Pa'in",
    "gn:country_code":"AF",
    "gn:dem":1498,
    "gn:feature_class":"P",
    "gn:feature_code":"PPL",
    "gn:name":"Qal\u2018ah-ye P\u0101\u2019\u012bn",
    "gn:population":0,
    "gn:timezone":"Asia/Kabul",
    "iso:country":"AF",
    "name:fas_x_preferred":[
        "\u0642\u0644\u0639\u06c0 \u067e\u0627\u0626\u064a\u0646"
    ],
    "name:und_x_variant":[
        "Kala-Pain",
        "Qal\u2018a P\u0101\u2018\u012bn",
        "Qal\u2018eh-ye P\u0101\u2018\u012bn",
        "\u0642\u0644\u0639\u06c0 \u067e\u0627\u0626\u064a\u0646",
        "\u0642\u0644\u0639\u06c0 \u067e\u0627\u0626\u06cc\u0646",
        "Qal\u2018ah-ye P\u0101\u2019\u012bn"
    ],
    "wof:name":"Qal'ah-ye Pa'in",
    "wof:placetype":"locality"
},
  "geometry": {"coordinates":[69.21925,34.95763],"type":"Point"}
}