{
  "type": "Feature",
  "properties": {
    "gn:admin1_code":"23",
    "gn:admin2_code":"2404",
    "gn:asciiname":"Jilawur",
    "gn:country_code":"AF",
    "gn:dem":1025,
    "gn:feature_class":"P",
    "gn:feature_code":"PPL",
    "gn:name":"Jil\u0101wur",
    "gn:population":0,
    "gn:timezone":"Asia/Kabul",
    "iso:country":"AF",
    "name:und_x_variant":[
        "Dzhilavur",
        "Jel\u0101wur",
        "Jil\u0101wur",
        "\u062c\u0644\u0627\u0648\u0631"
    ],
    "wof:name":"Jilawur",
    "wof:placetype":"locality"
},
  "geometry": {"coordinates":[65.64459000000001,31.70518],"type":"Point"}
}