{
  "type": "Feature",
  "properties": {
    "gn:admin1_code":"38",
    "gn:admin2_code":"3007.0",
    "gn:asciiname":"Dahan-e Piar",
    "gn:country_code":"AF",
    "gn:dem":1588,
    "gn:feature_class":"P",
    "gn:feature_code":"PPL",
    "gn:name":"Dah\u0101n-e P\u012b\u0101r",
    "gn:population":0,
    "gn:timezone":"Asia/Kabul",
    "iso:country":"AF",
    "name:rus_x_preferred":[
        "Dakhani-P\u2019yar"
    ],
    "name:und_x_variant":[
        "\u1e0eahane Py\u0101",
        "Dahan-e Py\u0101r",
        "Dah\u0101n-e P\u012b\u0101r",
        "\u062f\u0647\u0627\u0646 \u067e\u06cc\u0627\u0631",
        "Dah\u0101nah-ye P\u012b\u0101r",
        "\u062f\u0647\u0627\u0646\u06c0 \u067e\u06cc\u0627\u0631"
    ],
    "wof:name":"Dahan-e Piar",
    "wof:placetype":"locality"
},
  "geometry": {"coordinates":[70.30266999999999,35.15044],"type":"Point"}
}