{
  "type": "Feature",
  "properties": {
    "gn:admin1_code":"41",
    "gn:admin2_code":"3408.0",
    "gn:asciiname":"Katah Darakht",
    "gn:country_code":"AF",
    "gn:dem":2640,
    "gn:feature_class":"P",
    "gn:feature_code":"PPL",
    "gn:name":"Ka\u1e6fah Darakht",
    "gn:population":0,
    "gn:timezone":"Asia/Kabul",
    "iso:country":"AF",
    "name:und_x_variant":[
        "Kata\u1e0fa\u1e5fakht",
        "Katadarakht",
        "Ka\u1e6fah Darakht",
        "\u06a9\u067c\u0647 \u062f\u0631\u062e\u062a",
        "Ka\u1e6fahderakht"
    ],
    "wof:name":"Katah Darakht",
    "wof:placetype":"locality"
},
  "geometry": {"coordinates":[65.92879000000001,34.17035],"type":"Point"}
}