{
  "type": "Feature",
  "properties": {
    "gn:admin1_code":"32",
    "gn:admin2_code":"1503",
    "gn:asciiname":"Marak",
    "gn:country_code":"AF",
    "gn:dem":1995,
    "gn:feature_class":"P",
    "gn:feature_code":"PPL",
    "gn:name":"Marak",
    "gn:population":0,
    "gn:timezone":"Asia/Kabul",
    "iso:country":"AF",
    "name:deu_x_preferred":[
        "Marak"
    ],
    "name:nld_x_preferred":[
        "Marak"
    ],
    "name:und_x_variant":[
        "\u0645\u0631\u06a9",
        "Ma\u1e5fak"
    ],
    "wof:name":"Marak",
    "wof:placetype":"locality"
},
  "geometry": {"coordinates":[67.33001999999999,35.68705],"type":"Point"}
}