{
  "type": "Feature",
  "properties": {
    "gn:admin1_code":"31",
    "gn:admin2_code":"1701.0",
    "gn:asciiname":"Charamgar Khanah",
    "gn:country_code":"AF",
    "gn:dem":356,
    "gn:feature_class":"P",
    "gn:feature_code":"PPL",
    "gn:name":"Charamgar Kh\u0101nah",
    "gn:population":0,
    "gn:timezone":"Asia/Kabul",
    "iso:country":"AF",
    "name:und_x_variant":[
        "Charamgar Kh\u0101nah",
        "\u0686\u0631\u0645\u06af\u0631 \u062e\u0627\u0646\u0647"
    ],
    "wof:name":"Charamgar Khanah",
    "wof:placetype":"locality"
},
  "geometry": {"coordinates":[65.75402,36.68155],"type":"Point"}
}