{
  "type": "Feature",
  "properties": {
    "gn:admin1_code":"29",
    "gn:admin2_code":"2909.0",
    "gn:asciiname":"'Azam Kelay",
    "gn:country_code":"AF",
    "gn:dem":1938,
    "gn:feature_class":"P",
    "gn:feature_code":"PPL",
    "gn:name":"\u2018Az\u0327am K\u00ealay",
    "gn:population":0,
    "gn:timezone":"Asia/Kabul",
    "iso:country":"AF",
    "name:und_x_variant":[
        "Azamkalay",
        "\u2018Az\u0327am K\u00ealay",
        "\u2018Az\u0327am Kalay"
    ],
    "wof:name":"'Azam Kelay",
    "wof:placetype":"locality"
},
  "geometry": {"coordinates":[69.27528000000001,32.79583],"type":"Point"}
}