{
  "type": "Feature",
  "properties": {
    "gn:admin1_code":"05",
    "gn:admin2_code":"2807",
    "gn:asciiname":"Gaw Paridah",
    "gn:country_code":"AF",
    "gn:dem":2370,
    "gn:feature_class":"P",
    "gn:feature_code":"PPL",
    "gn:name":"G\u0101w Par\u012bdah",
    "gn:population":0,
    "gn:timezone":"Asia/Kabul",
    "iso:country":"AF",
    "name:und_x_variant":[
        "G\u0101wpa\u1e5fi\u1e0fa",
        "G\u0101vpar\u012bdeh",
        "G\u0101w Par\u012bdah",
        "\u06af\u0627\u0648 \u067e\u0631\u06cc\u062f\u0647"
    ],
    "wof:name":"Gaw Paridah",
    "wof:placetype":"locality"
},
  "geometry": {"coordinates":[67.48626,35.1879],"type":"Point"}
}