{
  "type": "Feature",
  "properties": {
    "gn:admin1_code":"5",
    "gn:admin2_code":"2806.0",
    "gn:asciiname":"Chah",
    "gn:country_code":"AF",
    "gn:dem":2558,
    "gn:feature_class":"P",
    "gn:feature_code":"PPL",
    "gn:name":"Ch\u0101h",
    "gn:population":0,
    "gn:timezone":"Asia/Kabul",
    "iso:country":"AF",
    "name:und_x_variant":[
        "\u010c\u0101h",
        "Chakh",
        "Ch\u0101h",
        "\u0686\u0627\u0647"
    ],
    "wof:name":"Chah",
    "wof:placetype":"locality"
},
  "geometry": {"coordinates":[67.20321,34.24334],"type":"Point"}
}