{
  "type": "Feature",
  "properties": {
    "gn:admin1_code":"3",
    "gn:admin2_code":"1304.0",
    "gn:asciiname":"Dahan-e Turmosh",
    "gn:country_code":"AF",
    "gn:dem":1121,
    "gn:feature_class":"P",
    "gn:feature_code":"PPL",
    "gn:name":"Dah\u0101n-e Turm\u014dsh",
    "gn:population":0,
    "gn:timezone":"Asia/Kabul",
    "iso:country":"AF",
    "name:und_x_variant":[
        "\u1e0eahane Tu\u1e5fm\u014ds",
        "Dahan-e Turm\u016bsh",
        "Dah\u0101n-e Turm\u014dsh",
        "\u062f\u0647\u0627\u0646 \u062a\u0631\u0645\u0648\u0634"
    ],
    "wof:name":"Dahan-e Turmosh",
    "wof:placetype":"locality"
},
  "geometry": {"coordinates":[68.33035,35.49898],"type":"Point"}
}