{
  "type": "Feature",
  "properties": {
    "gn:admin1_code":"31",
    "gn:admin2_code":"1701.0",
    "gn:asciiname":"Chahar Shanbah",
    "gn:country_code":"AF",
    "gn:dem":336,
    "gn:feature_class":"P",
    "gn:feature_code":"PPL",
    "gn:name":"Chah\u0101r Shanbah",
    "gn:population":0,
    "gn:timezone":"Asia/Kabul",
    "iso:country":"AF",
    "name:und_x_variant":[
        "Ch\u0101har Shanba",
        "Chah\u0101r Shanbeh",
        "Chah\u0101r Shanbah",
        "\u0686\u0647\u0627\u0631 \u0634\u0646\u0628\u0647"
    ],
    "wof:name":"Chahar Shanbah",
    "wof:placetype":"locality"
},
  "geometry": {"coordinates":[65.83979000000001,36.73187],"type":"Point"}
}