{
  "type": "Feature",
  "properties": {
    "gn:admin1_code":"01",
    "gn:admin2_code":"1119",
    "gn:asciiname":"Tor Chu",
    "gn:country_code":"AF",
    "gn:dem":2647,
    "gn:feature_class":"P",
    "gn:feature_code":"PPL",
    "gn:name":"T\u014dr Ch\u016b",
    "gn:population":0,
    "gn:timezone":"Asia/Kabul",
    "iso:country":"AF",
    "name:und_x_variant":[
        "T\u014d\u1e5f C\u016b",
        "\u062a\u0648\u0631 \u0686\u0648",
        "T\u016br Ch\u016b",
        "T\u014dr Ch\u016b"
    ],
    "wof:name":"Tor Chu",
    "wof:placetype":"locality"
},
  "geometry": {"coordinates":[70.70255999999998,37.36368],"type":"Point"}
}