{
  "type": "Feature",
  "properties": {
    "gn:admin1_code":"13",
    "gn:admin2_code":"111.0",
    "gn:asciiname":"'Aynak",
    "gn:country_code":"AF",
    "gn:dem":2102,
    "gn:feature_class":"P",
    "gn:feature_code":"PPL",
    "gn:name":"\u2018Aynak",
    "gn:population":0,
    "gn:timezone":"Asia/Kabul",
    "iso:country":"AF",
    "name:und_x_variant":[
        "Aynak",
        "\u2018Aynak",
        "\u0639\u06cc\u0646\u06a9",
        "Taghar",
        "\u062a\u063a\u0631"
    ],
    "wof:name":"'Aynak",
    "wof:placetype":"locality"
},
  "geometry": {"coordinates":[69.37139999999999,34.40036],"type":"Point"}
}