{
  "type": "Feature",
  "properties": {
    "gn:admin1_code":"01",
    "gn:admin2_code":"1120",
    "gn:asciiname":"Nowabad Imj",
    "gn:country_code":"AF",
    "gn:dem":1548,
    "gn:feature_class":"P",
    "gn:feature_code":"PPL",
    "gn:name":"Now\u0101b\u0101d \u012amj",
    "gn:population":0,
    "gn:timezone":"Asia/Kabul",
    "iso:country":"AF",
    "name:und_x_variant":[
        "Naw\u0101b\u0101\u1e0fe Im\u012b",
        "Naw \u0100b\u0101\u1e0f \u012amj",
        "Now\u0101b\u0101d-e \u012am\u012b",
        "Now\u0101b\u0101d-e \u012ash",
        "Now\u0101b\u0101d \u012amj",
        "\u0646\u0648 \u0622\u0628\u0627\u062f \u0627\u06cc\u0645\u062c"
    ],
    "wof:name":"Nowabad Imj",
    "wof:placetype":"locality"
},
  "geometry": {"coordinates":[70.50221999999999,38.00688],"type":"Point"}
}