{
  "type": "Feature",
  "properties": {
    "gn:admin1_code":"33",
    "gn:admin2_code":"3103.0",
    "gn:asciiname":"Wutjay",
    "gn:country_code":"AF",
    "gn:dem":1682,
    "gn:feature_class":"P",
    "gn:feature_code":"PPL",
    "gn:name":"Wutj\u0101y",
    "gn:population":0,
    "gn:timezone":"Asia/Kabul",
    "iso:country":"AF",
    "name:und_x_variant":[
        "Wutj\u0101y",
        "\u0648\u062a\u062c\u0627\u06cc"
    ],
    "wof:name":"Wutjay",
    "wof:placetype":"locality"
},
  "geometry": {"coordinates":[66.06061,35.69362],"type":"Point"}
}