{
  "type": "Feature",
  "properties": {
    "gn:admin1_code":"01",
    "gn:admin2_code":"1105.0",
    "gn:asciiname":"Uspu",
    "gn:country_code":"AF",
    "gn:dem":2992,
    "gn:feature_class":"P",
    "gn:feature_code":"PPL",
    "gn:name":"\u016asp\u016b",
    "gn:population":0,
    "gn:timezone":"Asia/Kabul",
    "iso:country":"AF",
    "name:und_x_variant":[
        "\u016asp\u016b",
        "\u0627\u0648\u0633\u067e\u0648"
    ],
    "wof:name":"Uspu",
    "wof:placetype":"locality"
},
  "geometry": {"coordinates":[71.4423,36.59051],"type":"Point"}
}