{
  "type": "Feature",
  "properties": {
    "gn:admin1_code":"8",
    "gn:admin2_code":"604.0",
    "gn:asciiname":"Binisang",
    "gn:country_code":"AF",
    "gn:dem":3111,
    "gn:feature_class":"P",
    "gn:feature_code":"PPL",
    "gn:name":"B\u012bn\u012bsang",
    "gn:population":0,
    "gn:timezone":"Asia/Kabul",
    "iso:country":"AF",
    "name:fas_x_preferred":[
        "\u0628\u0646\u06cc \u0633\u0646\u06af"
    ],
    "name:fas_x_variant":[
        "\u0628\u06cc\u0646\u06cc\u200c\u0633\u0646\u06af"
    ],
    "name:rus_x_preferred":[
        "\u0411\u0438\u043d\u0438\u0441\u0430\u043d\u0433"
    ],
    "name:und_x_variant":[
        "B\u012bn\u012b Sang",
        "\u0628\u06cc\u0646\u06cc \u0633\u0646\u06af"
    ],
    "wof:name":"Binisang",
    "wof:placetype":"locality"
},
  "geometry": {"coordinates":[67.55575,33.77422],"type":"Point"}
}