{
  "type": "Feature",
  "properties": {
    "gn:admin1_code":"11",
    "gn:admin2_code":"2004",
    "gn:asciiname":"Safedan",
    "gn:country_code":"AF",
    "gn:dem":1092,
    "gn:feature_class":"P",
    "gn:feature_code":"PPL",
    "gn:name":"Saf\u0113d\u0101n",
    "gn:population":0,
    "gn:timezone":"Asia/Kabul",
    "iso:country":"AF",
    "name:und_x_variant":[
        "Saf\u0113\u1e0f\u0101n",
        "Sef\u012bd\u0101n",
        "Safayd\u0101n",
        "\u0633\u0641\u06d0\u062f\u0627\u0646",
        "Saf\u0113d\u0101n"
    ],
    "wof:name":"Safedan",
    "wof:placetype":"locality"
},
  "geometry": {"coordinates":[62.6525,34.22688],"type":"Point"}
}