{
  "type": "Feature",
  "properties": {
    "gn:admin1_code":"34",
    "gn:admin2_code":"1005.0",
    "gn:asciiname":"Badir Mashal",
    "gn:country_code":"AF",
    "gn:dem":1892,
    "gn:feature_class":"P",
    "gn:feature_code":"PPL",
    "gn:name":"B\u0101dir Mash\u0101l",
    "gn:population":0,
    "gn:timezone":"Asia/Kabul",
    "iso:country":"AF",
    "name:fas_x_preferred":[
        "\u0642\u0627\u062f\u0631 \u0645\u0634\u0627\u0644"
    ],
    "name:rus_x_preferred":[
        "Badermashal\u2019"
    ],
    "name:und_x_variant":[
        "B\u0101derma\u0161\u0101l",
        "B\u0101der Mash\u0101l",
        "B\u0101dermash\u0101l",
        "B\u0101dir Mash\u0101l",
        "\u0628\u0627\u062f\u0631 \u0645\u0634\u0627\u0644"
    ],
    "wof:name":"Badir Mashal",
    "wof:placetype":"locality"
},
  "geometry": {"coordinates":[71.54086,35.16025],"type":"Point"}
}