{
  "type": "Feature",
  "properties": {
    "gn:admin1_code":"28",
    "gn:admin2_code":"2502",
    "gn:asciiname":"Surkay Tangay",
    "gn:country_code":"AF",
    "gn:dem":2042,
    "gn:feature_class":"P",
    "gn:feature_code":"PPL",
    "gn:name":"S\u016brkay Tangay",
    "gn:population":0,
    "gn:timezone":"Asia/Kabul",
    "iso:country":"AF",
    "name:fas_x_preferred":[
        "\u062a\u0646\u06af\u0626 \u0633\u0631\u0643\u06cc"
    ],
    "name:und_x_variant":[
        "S\u016brkay Tanga\u012b",
        "\u0633\u0648\u0631\u06a9\u06cc \u062a\u0646\u06af\u06cc",
        "Surkay Tangay",
        "S\u016brkay Tangay"
    ],
    "wof:name":"Surkay Tangay",
    "wof:placetype":"locality"
},
  "geometry": {"coordinates":[67.33189,32.22195],"type":"Point"}
}