{
  "type": "Feature",
  "properties": {
    "gn:admin1_code":"09",
    "gn:admin2_code":"2707",
    "gn:asciiname":"Geru",
    "gn:country_code":"AF",
    "gn:dem":2862,
    "gn:feature_class":"P",
    "gn:feature_code":"PPL",
    "gn:name":"Geru",
    "gn:population":0,
    "gn:timezone":"Asia/Kabul",
    "iso:country":"AF",
    "name:und_x_variant":[
        "Giru",
        "G\u012br\u014d",
        "Geru",
        "\u06af\u06cc\u0631\u0648"
    ],
    "wof:name":"Geru",
    "wof:placetype":"locality"
},
  "geometry": {"coordinates":[66.35216,34.73619],"type":"Point"}
}