{
  "type": "Feature",
  "properties": {
    "gn:admin1_code":"33",
    "gn:admin2_code":"3104",
    "gn:asciiname":"Gowlah",
    "gn:country_code":"AF",
    "gn:dem":1833,
    "gn:feature_class":"P",
    "gn:feature_code":"PPL",
    "gn:name":"Gowlah",
    "gn:population":0,
    "gn:timezone":"Asia/Kabul",
    "iso:country":"AF",
    "name:und_x_variant":[
        "G\u014dla",
        "Gowla",
        "Gowlah"
    ],
    "wof:name":"Gowlah",
    "wof:placetype":"locality"
},
  "geometry": {"coordinates":[67.00076999999999,35.66518],"type":"Point"}
}