{
  "type": "Feature",
  "properties": {
    "gn:admin1_code":"8",
    "gn:admin2_code":"614.0",
    "gn:asciiname":"Akhundzadah",
    "gn:country_code":"AF",
    "gn:dem":2097,
    "gn:feature_class":"P",
    "gn:feature_code":"PPL",
    "gn:name":"\u0100kh\u016bndz\u0101dah",
    "gn:population":0,
    "gn:timezone":"Asia/Kabul",
    "iso:country":"AF",
    "name:fas_x_preferred":[
        "\u0627\u062e\u0648\u0646\u062f\u0632\u0627\u062f\u0647"
    ],
    "name:und_x_variant":[
        "Akhundzada",
        "Akhun\u1e0fz\u0101\u1e0fah",
        "\u0100kh\u016bndz\u0101dah",
        "Akhvondz\u0101deh",
        "\u0622\u062e\u0648\u0646\u062f\u0632\u0627\u062f\u0647"
    ],
    "wof:name":"Akhundzadah",
    "wof:placetype":"locality"
},
  "geometry": {"coordinates":[68.27687,33.30065],"type":"Point"}
}