{
  "type": "Feature",
  "properties": {
    "gn:admin1_code":"34",
    "gn:admin2_code":"1002.0",
    "gn:asciiname":"Zhrando Korunah",
    "gn:country_code":"AF",
    "gn:dem":1212,
    "gn:feature_class":"P",
    "gn:feature_code":"PPL",
    "gn:name":"Zhrand\u014d K\u014dr\u016bnah",
    "gn:population":0,
    "gn:timezone":"Asia/Kabul",
    "iso:country":"AF",
    "name:fas_x_preferred":[
        "\u0698\u0631\u0646\u062f\u0648 \u0643\u0648\u0631\u0648\u0646\u0647"
    ],
    "name:und_x_variant":[
        "Zrandokoruna",
        "\u017drando Kor\u016bna",
        "Zhrando Kowr\u016bnah",
        "Zhrand\u014d K\u014dr\u016bnah",
        "\u0698\u0631\u0646\u062f\u0648 \u06a9\u0648\u0631\u0648\u0646\u0647"
    ],
    "wof:name":"Zhrando Korunah",
    "wof:placetype":"locality"
},
  "geometry": {"coordinates":[71.2281,34.847],"type":"Point"}
}