{
  "type": "Feature",
  "properties": {
    "gn:admin1_code":"23",
    "gn:admin2_code":"2405",
    "gn:asciiname":"Du Khanah",
    "gn:country_code":"AF",
    "gn:dem":1310,
    "gn:feature_class":"P",
    "gn:feature_code":"PPL",
    "gn:name":"D\u016b Kh\u0101nah",
    "gn:population":0,
    "gn:timezone":"Asia/Kabul",
    "iso:country":"AF",
    "name:und_x_variant":[
        "Dukhana",
        "\u1e0eokh\u0101na",
        "D\u016b Kh\u0101nah",
        "\u062f\u0648 \u062e\u0627\u0646\u0647",
        "Dokh\u0101neh"
    ],
    "wof:name":"Du Khanah",
    "wof:placetype":"locality"
},
  "geometry": {"coordinates":[65.3839,31.87436],"type":"Point"}
}