{
  "type": "Feature",
  "properties": {
    "gn:admin1_code":"11",
    "gn:admin2_code":"2003.0",
    "gn:asciiname":"Asyachah",
    "gn:country_code":"AF",
    "gn:dem":988,
    "gn:feature_class":"P",
    "gn:feature_code":"PPL",
    "gn:name":"\u0100sy\u0101chah",
    "gn:population":0,
    "gn:timezone":"Asia/Kabul",
    "iso:country":"AF",
    "name:fas_x_preferred":[
        "\u0622\u0633\u064a\u0627\u0686\u0647"
    ],
    "name:und_x_variant":[
        "Asiacha",
        "Asy\u0101chah",
        "\u0100sy\u0101\u010dah",
        "\u0100sy\u0101cheh",
        "\u0100sy\u0101chah",
        "\u0622\u0633\u06cc\u0627\u0686\u0647",
        "\u0622\u0633\u064a\u0627\u0686\u0647"
    ],
    "wof:name":"Asyachah",
    "wof:placetype":"locality"
},
  "geometry": {"coordinates":[62.44217,34.25606],"type":"Point"}
}