{
  "type": "Feature",
  "properties": {
    "gn:admin1_code":"02",
    "gn:admin2_code":"1906",
    "gn:asciiname":"Haji Aqa Muhammad Khan",
    "gn:country_code":"AF",
    "gn:dem":501,
    "gn:feature_class":"P",
    "gn:feature_code":"PPL",
    "gn:name":"\u1e28\u0101j\u012b \u0100q\u0101 Mu\u1e29ammad Kh\u0101n",
    "gn:population":0,
    "gn:timezone":"Asia/Kabul",
    "iso:country":"AF",
    "name:und_x_variant":[
        "H\u0331\u0101ji Aq\u0101 Mohamma\u1e0f Kh\u0101n",
        "\u1e28\u0101j\u012b \u0100q\u0101 Mu\u1e29ammad Kh\u0101n",
        "\u062d\u0627\u062c\u06cc \u0622\u0642\u0627 \u0645\u062d\u0645\u062f \u062e\u0627\u0646",
        "\u1e28\u0101jj\u012b \u0100q\u0101 Mo\u1e29ammad Kh\u0101n"
    ],
    "wof:name":"Haji Aqa Muhammad Khan",
    "wof:placetype":"locality"
},
  "geometry": {"coordinates":[63.37125,35.51382],"type":"Point"}
}