{
  "type": "Feature",
  "properties": {
    "gn:admin1_code":"29",
    "gn:admin2_code":"2903",
    "gn:asciiname":"Landay Karez",
    "gn:country_code":"AF",
    "gn:dem":2062,
    "gn:feature_class":"P",
    "gn:feature_code":"PPL",
    "gn:name":"Lan\u1e0fay K\u0101r\u0113z",
    "gn:population":0,
    "gn:timezone":"Asia/Kabul",
    "iso:country":"AF",
    "name:und_x_variant":[
        "Londay K\u0101r\u012bz",
        "Landay K\u0101\u1e5f\u0113z",
        "\u0644\u0646\u0689\u06cc \u06a9\u0627\u0693\u06d0\u0632",
        "Lan\u1e0fay K\u0101r\u012bz",
        "Lan\u1e0fay K\u0101r\u0113z"
    ],
    "wof:name":"Landay Karez",
    "wof:placetype":"locality"
},
  "geometry": {"coordinates":[68.36389,32.55585],"type":"Point"}
}