{
  "type": "Feature",
  "properties": {
    "gn:admin1_code":"02",
    "gn:admin2_code":"1904",
    "gn:asciiname":"Zaluk",
    "gn:country_code":"AF",
    "gn:dem":1510,
    "gn:feature_class":"P",
    "gn:feature_code":"PPL",
    "gn:name":"Zal\u016bk",
    "gn:population":0,
    "gn:timezone":"Asia/Kabul",
    "iso:country":"AF",
    "name:und_x_variant":[
        "Zal\u016bk",
        "\u0632\u0644\u0648\u06a9"
    ],
    "wof:name":"Zaluk",
    "wof:placetype":"locality"
},
  "geometry": {"coordinates":[64.16464999999999,35.02938],"type":"Point"}
}