{
  "type": "Feature",
  "properties": {
    "gn:admin1_code":"24",
    "gn:admin2_code":"1401",
    "gn:asciiname":"Shorah Khak-e Pa'in",
    "gn:country_code":"AF",
    "gn:dem":396,
    "gn:feature_class":"P",
    "gn:feature_code":"PPL",
    "gn:name":"Sh\u014drah Kh\u0101k-e P\u0101\u2019\u012bn",
    "gn:population":0,
    "gn:timezone":"Asia/Kabul",
    "iso:country":"AF",
    "name:fas_x_preferred":[
        "\u0634\u0648\u0631\u0647 \u062e\u0627\u06a9\u0654 \u067e\u0627\u0626\u064a\u0646"
    ],
    "name:rus_x_preferred":[
        "\u0428\u043e\u0440\u0445\u0430\u043a\u0438-\u041f\u0430\u0438\u043d"
    ],
    "name:und_x_variant":[
        "Shorkhaki-Pain",
        "Sh\u016bra Kh\u0101k-e P\u0101\u2019\u012bn",
        "\u0160ora Kh\u0101k-i-P\u0101 in",
        "Sh\u016breh Kh\u0101k-e P\u0101\u2019\u012bn",
        "Sh\u014drah Kh\u0101k-e P\u0101\u2019\u012bn",
        "\u0634\u0648\u0631\u0647 \u062e\u0627\u06a9 \u067e\u0627\u0626\u06cc\u0646"
    ],
    "wof:name":"Shorah Khak-e Pa'in",
    "wof:placetype":"locality"
},
  "geometry": {"coordinates":[68.85812,36.69063],"type":"Point"}
}