{
  "type": "Feature",
  "properties": {
    "gn:admin1_code":"34",
    "gn:admin2_code":"1010.0",
    "gn:asciiname":"Tantil",
    "gn:country_code":"AF",
    "gn:dem":995,
    "gn:feature_class":"P",
    "gn:feature_code":"PPL",
    "gn:name":"\u1e6ean\u1e6f\u012bl",
    "gn:population":0,
    "gn:timezone":"Asia/Kabul",
    "iso:country":"AF",
    "name:fas_x_preferred":[
        "\u062a\u0646\u062a\u064a\u0644"
    ],
    "name:rus_x_preferred":[
        "Tantil\u2019"
    ],
    "name:und_x_variant":[
        "Tant\u012bl",
        "\u1e6ean\u1e6f\u012bl",
        "\u067c\u0646\u067c\u06cc\u0644"
    ],
    "wof:name":"Tantil",
    "wof:placetype":"locality"
},
  "geometry": {"coordinates":[70.94126,34.95378],"type":"Point"}
}