{
  "type": "Feature",
  "properties": {
    "gn:admin1_code":"24",
    "gn:admin2_code":"1406",
    "gn:asciiname":"Deh-e Kalan",
    "gn:country_code":"AF",
    "gn:dem":487,
    "gn:feature_class":"P",
    "gn:feature_code":"PPL",
    "gn:name":"Deh-e Kal\u0101n",
    "gn:population":0,
    "gn:timezone":"Asia/Kabul",
    "iso:country":"AF",
    "name:fas_x_preferred":[
        "\u062f\u06c0 \u0643\u0644\u0627\u0646"
    ],
    "name:rus_x_preferred":[
        "\u0414\u0435\u0445\u0438-\u041a\u0430\u043b\u0430\u043d"
    ],
    "name:und_x_variant":[
        "\u1e0eeh-i-Kal\u0101n",
        "Dekhi-Kalan",
        "Deh-e Kal\u0101n",
        "\u062f\u0647 \u06a9\u0644\u0627\u0646"
    ],
    "wof:name":"Deh-e Kalan",
    "wof:placetype":"locality"
},
  "geometry": {"coordinates":[69.00864,36.61908],"type":"Point"}
}