{
  "type": "Feature",
  "properties": {
    "gn:admin1_code":"29",
    "gn:admin2_code":"2909",
    "gn:asciiname":"Shkin",
    "gn:country_code":"AF",
    "gn:dem":2209,
    "gn:feature_class":"P",
    "gn:feature_code":"PPL",
    "gn:name":"Shk\u012bn",
    "gn:population":0,
    "gn:timezone":"Asia/Kabul",
    "iso:country":"AF",
    "name:und_x_variant":[
        "\u0160k\u012bn",
        "Shkin",
        "Sh\u0101ken",
        "Shakin",
        "Shk\u012bn",
        "\u0634\u06a9\u06cc\u0646"
    ],
    "wof:name":"Shkin",
    "wof:placetype":"locality"
},
  "geometry": {"coordinates":[69.26491999999999,32.52606],"type":"Point"}
}