{
  "type": "Feature",
  "properties": {
    "gn:admin1_code":"13",
    "gn:admin2_code":"105.0",
    "gn:asciiname":"Aghilak",
    "gn:country_code":"AF",
    "gn:dem":1832,
    "gn:feature_class":"P",
    "gn:feature_code":"PPL",
    "gn:name":"\u0100ghilak",
    "gn:population":0,
    "gn:timezone":"Asia/Kabul",
    "iso:country":"AF",
    "name:fas_x_preferred":[
        "\u0627\u063a\u06cc\u0644\u06a9"
    ],
    "name:und_x_variant":[
        "Agelak",
        "\u0100ghaylak",
        "Agh\u0113lak",
        "\u0100ghelak",
        "\u0622\u063a\u0644\u06a9",
        "\u0100ghilak"
    ],
    "wof:name":"Aghilak",
    "wof:placetype":"locality"
},
  "geometry": {"coordinates":[69.09836,34.8931],"type":"Point"}
}