{
  "type": "Feature",
  "properties": {
    "gn:admin1_code":"08",
    "gn:admin2_code":"614",
    "gn:asciiname":"Nuri Kala",
    "gn:country_code":"AF",
    "gn:dem":2095,
    "gn:feature_class":"P",
    "gn:feature_code":"PPL",
    "gn:name":"N\u016br\u012b Kal\u0101",
    "gn:population":0,
    "gn:timezone":"Asia/Kabul",
    "iso:country":"AF",
    "name:und_x_variant":[
        "Nurikala",
        "N\u016br\u012b Kal\u0101",
        "\u0646\u0648\u0631\u06cc \u06a9\u0644\u0627"
    ],
    "wof:name":"Nuri Kala",
    "wof:placetype":"locality"
},
  "geometry": {"coordinates":[68.54916,33.24405],"type":"Point"}
}