{
  "type": "Feature",
  "properties": {
    "gn:admin1_code":"40",
    "gn:admin2_code":"301.0",
    "gn:asciiname":"Qal'ah-ye Lalah Mir Khan",
    "gn:country_code":"AF",
    "gn:dem":1542,
    "gn:feature_class":"P",
    "gn:feature_code":"PPL",
    "gn:name":"Qal\u2018ah-ye L\u0101lah M\u012br Kh\u0101n",
    "gn:population":0,
    "gn:timezone":"Asia/Kabul",
    "iso:country":"AF",
    "name:fas_x_preferred":[
        "\u0642\u0644\u0639\u06c0 \u0644\u0627\u0644\u0647 \u0645\u064a\u0631 \u062e\u0627\u0646"
    ],
    "name:und_x_variant":[
        "Kalayi-Lalamirkhan",
        "Qal\u2018a-i-L\u0101lam\u012b\u1e5fkh\u0101n",
        "Qal\u2018ah-ye L\u0101l\u0101 M\u012br Kh\u0101n",
        "Qal\u2018eh-ye L\u0101lam\u012brkh\u0101n",
        "Qal\u2018ah-ye L\u0101lah M\u012br Kh\u0101n",
        "\u0642\u0644\u0639\u06c0 \u0644\u0627\u0644\u0647 \u0645\u06cc\u0631 \u062e\u0627\u0646"
    ],
    "wof:name":"Qal'ah-ye Lalah Mir Khan",
    "wof:placetype":"locality"
},
  "geometry": {"coordinates":[69.16786999999999,34.99472],"type":"Point"}
}