{
  "type": "Feature",
  "properties": {
    "gn:admin1_code":"01",
    "gn:admin2_code":"1113.0",
    "gn:asciiname":"Sayyidan",
    "gn:country_code":"AF",
    "gn:dem":1250,
    "gn:feature_class":"P",
    "gn:feature_code":"PPL",
    "gn:name":"Sayyid\u0101n",
    "gn:population":0,
    "gn:timezone":"Asia/Kabul",
    "iso:country":"AF",
    "name:und_x_variant":[
        "Saye\u1e0f\u0101n",
        "Seyyed\u0101n",
        "Sayyid\u0101n",
        "\u0633\u06cc\u062f\u0627\u0646"
    ],
    "wof:name":"Sayyidan",
    "wof:placetype":"locality"
},
  "geometry": {"coordinates":[70.0919,37.44378],"type":"Point"}
}