{
  "type": "Feature",
  "properties": {
    "gn:admin1_code":"27",
    "gn:admin2_code":"403.0",
    "gn:asciiname":"Chap Qol",
    "gn:country_code":"AF",
    "gn:dem":3324,
    "gn:feature_class":"P",
    "gn:feature_code":"PPL",
    "gn:name":"Chap Q\u014dl",
    "gn:population":0,
    "gn:timezone":"Asia/Kabul",
    "iso:country":"AF",
    "name:rus_x_preferred":[
        "Chapkul\u2019"
    ],
    "name:und_x_variant":[
        "\u010capqol",
        "Chapqowl",
        "Chap Q\u014dl",
        "\u0686\u067e \u0642\u0648\u0644"
    ],
    "wof:name":"Chap Qol",
    "wof:placetype":"locality"
},
  "geometry": {"coordinates":[68.15985000000001,34.62859],"type":"Point"}
}