{
  "type": "Feature",
  "properties": {
    "gn:admin1_code":"35",
    "gn:admin2_code":"905",
    "gn:asciiname":"Sabrabad",
    "gn:country_code":"AF",
    "gn:dem":977,
    "gn:feature_class":"P",
    "gn:feature_code":"PPL",
    "gn:name":"\u015eabr\u0101b\u0101d",
    "gn:population":0,
    "gn:timezone":"Asia/Kabul",
    "iso:country":"AF",
    "name:und_x_variant":[
        "Sab\u1e5f\u0101b\u0101\u1e0f",
        "\u015eabr\u0101b\u0101d",
        "\u0635\u0628\u0631 \u0622\u0628\u0627\u062f"
    ],
    "wof:name":"Sabrabad",
    "wof:placetype":"locality"
},
  "geometry": {"coordinates":[70.11033,34.74204],"type":"Point"}
}