{
  "type": "Feature",
  "properties": {
    "gn:admin1_code":"28",
    "gn:admin2_code":"2501",
    "gn:asciiname":"Nowkhez",
    "gn:country_code":"AF",
    "gn:dem":1599,
    "gn:feature_class":"P",
    "gn:feature_code":"PPL",
    "gn:name":"Nowkh\u0113z",
    "gn:population":0,
    "gn:timezone":"Asia/Kabul",
    "iso:country":"AF",
    "name:fas_x_preferred":[
        "\u0646\u0648\u062e\u064a\u0632"
    ],
    "name:und_x_variant":[
        "Nawkh\u0113z",
        "Naukhez",
        "Nowkh\u0113z",
        "\u0646\u0648\u062e\u06d0\u0632",
        "Nowkh\u012bz"
    ],
    "wof:name":"Nowkhez",
    "wof:placetype":"locality"
},
  "geometry": {"coordinates":[66.79862,32.09076],"type":"Point"}
}