{
  "type": "Feature",
  "properties": {
    "gn:admin1_code":"13",
    "gn:admin2_code":"102",
    "gn:asciiname":"Yakah Darakht",
    "gn:country_code":"AF",
    "gn:dem":1861,
    "gn:feature_class":"P",
    "gn:feature_code":"PPL",
    "gn:name":"Yakah Darakht",
    "gn:population":0,
    "gn:timezone":"Asia/Kabul",
    "iso:country":"AF",
    "name:fas_x_preferred":[
        "\u064a\u0643\u062f\u0631\u062e\u062a"
    ],
    "name:und_x_variant":[
        "Yakadarakht",
        "\u064a\u0643\u062f\u0631\u062e\u062a",
        "Yakah Darakht",
        "\u06cc\u06a9\u0647 \u062f\u0631\u062e\u062a"
    ],
    "name:urd_x_preferred":[
        "\u06cc\u06a9\u06c1 \u062f\u0631\u062e\u062a"
    ],
    "wof:name":"Yakah Darakht",
    "wof:placetype":"locality"
},
  "geometry": {"coordinates":[69.34941999999999,34.63207],"type":"Point"}
}