{
  "type": "Feature",
  "properties": {
    "gn:admin1_code":"05",
    "gn:admin2_code":"2805.0",
    "gn:asciiname":"Khushkab-e 'Ulya",
    "gn:country_code":"AF",
    "gn:dem":3172,
    "gn:feature_class":"P",
    "gn:feature_code":"PPL",
    "gn:name":"Khushk\u0101b-e \u2018Uly\u0101",
    "gn:population":0,
    "gn:timezone":"Asia/Kabul",
    "iso:country":"AF",
    "name:und_x_variant":[
        "Khu\u0161k\u0101be \u2018Uly\u0101",
        "Khushkabi-Ulia",
        "Khoshk\u0101b-e \u2018Oly\u0101",
        "Khushk\u0101b-e \u2018Oly\u0101",
        "Khushk\u0101b-e \u2018Uly\u0101",
        "\u062e\u0634\u06a9 \u0622\u0628 \u0639\u0644\u064a\u0627"
    ],
    "wof:name":"Khushkab-e 'Ulya",
    "wof:placetype":"locality"
},
  "geometry": {"coordinates":[67.22346999999999,34.40501],"type":"Point"}
}