{
  "type": "Feature",
  "properties": {
    "gn:admin1_code":"23",
    "gn:admin2_code":"2404",
    "gn:asciiname":"Kogak",
    "gn:country_code":"AF",
    "gn:dem":1004,
    "gn:feature_class":"P",
    "gn:feature_code":"PPL",
    "gn:name":"K\u014dgak",
    "gn:population":0,
    "gn:timezone":"Asia/Kabul",
    "iso:country":"AF",
    "name:fas_x_preferred":[
        "\u0643\u0648\u0647\u0643"
    ],
    "name:und_x_variant":[
        "G\u016bgak",
        "Kohoc",
        "K\u014dgak",
        "K\u014dhak",
        "Kogak",
        "K\u016bhak",
        "\u06a9\u0648\u06af\u06a9",
        "\u0643\u0648\u0647\u0643",
        "\u06a9\u0648\u0647\u06a9"
    ],
    "wof:name":"Kogak",
    "wof:placetype":"locality"
},
  "geometry": {"coordinates":[65.61299,31.64914000000001],"type":"Point"}
}