{
  "type": "Feature",
  "properties": {
    "gn:admin1_code":"9",
    "gn:admin2_code":"2710.0",
    "gn:asciiname":"Shikhliyak",
    "gn:country_code":"AF",
    "gn:dem":2361,
    "gn:feature_class":"P",
    "gn:feature_code":"PPL",
    "gn:name":"Shikhliyak",
    "gn:population":0,
    "gn:timezone":"Asia/Kabul",
    "iso:country":"AF",
    "name:und_x_variant":[
        "\u0160ekhleyak",
        "Sheykhliyak",
        "Sheykhleyak",
        "Shikhliyak",
        "\u0634\u062e\u0644\u06cc\u06a9"
    ],
    "wof:name":"Shikhliyak",
    "wof:placetype":"locality"
},
  "geometry": {"coordinates":[64.67553000000001,34.30205],"type":"Point"}
}