{
  "type": "Feature",
  "properties": {
    "gn:admin1_code":"23",
    "gn:admin2_code":"2413.0",
    "gn:asciiname":"Chinah",
    "gn:country_code":"AF",
    "gn:dem":1682,
    "gn:feature_class":"P",
    "gn:feature_code":"PPL",
    "gn:name":"Ch\u012bnah",
    "gn:population":0,
    "gn:timezone":"Asia/Kabul",
    "iso:country":"AF",
    "name:pus_x_preferred":[
        "\u0686\u06cc\u0646\u0647"
    ],
    "name:und_x_variant":[
        "Ch\u012bneh",
        "China",
        "\u010cina",
        "Ch\u012bnah"
    ],
    "wof:name":"Chinah",
    "wof:placetype":"locality"
},
  "geometry": {"coordinates":[67.06573,31.57242],"type":"Point"}
}