{
  "type": "Feature",
  "properties": {
    "gn:admin1_code":"41",
    "gn:admin2_code":"3405",
    "gn:asciiname":"Joynu",
    "gn:country_code":"AF",
    "gn:dem":2013,
    "gn:feature_class":"P",
    "gn:feature_code":"PPL",
    "gn:name":"J\u014dyn\u016b",
    "gn:population":0,
    "gn:timezone":"Asia/Kabul",
    "iso:country":"AF",
    "name:und_x_variant":[
        "J\u014dynu",
        "J\u014dyn\u016b",
        "\u062c\u0648\u06cc\u0646\u0648",
        "J\u016bynow"
    ],
    "wof:name":"Joynu",
    "wof:placetype":"locality"
},
  "geometry": {"coordinates":[65.73024000000001,33.88087],"type":"Point"}
}