{
  "type": "Feature",
  "properties": {
    "gn:admin1_code":"08",
    "gn:admin2_code":"617",
    "gn:asciiname":"Zarif Khel",
    "gn:country_code":"AF",
    "gn:dem":2543,
    "gn:feature_class":"P",
    "gn:feature_code":"PPL",
    "gn:name":"Z\u0327ar\u012bf Kh\u0113l",
    "gn:population":0,
    "gn:timezone":"Asia/Kabul",
    "iso:country":"AF",
    "name:fas_x_preferred":[
        "\u0638\u0631\u064a\u0641 \u062e\u064a\u0644"
    ],
    "name:rus_x_preferred":[
        "Zarifkheyl\u2019"
    ],
    "name:und_x_variant":[
        "\u1e94a\u1e5f\u012bfkh\u0113l",
        "Z\u0327ar\u012bf Kh\u0113l",
        "Z\u0327ar\u012bf Kheyl",
        "\u0638\u0631\u064a\u0641 \u062e\u06d0\u0644"
    ],
    "wof:name":"Zarif Khel",
    "wof:placetype":"locality"
},
  "geometry": {"coordinates":[68.22094,33.71151],"type":"Point"}
}