{
  "type": "Feature",
  "properties": {
    "gn:admin1_code":"27",
    "gn:admin2_code":"404",
    "gn:asciiname":"Khar Qol",
    "gn:country_code":"AF",
    "gn:dem":3218,
    "gn:feature_class":"P",
    "gn:feature_code":"PPL",
    "gn:name":"Khar Q\u014dl",
    "gn:population":0,
    "gn:timezone":"Asia/Kabul",
    "iso:country":"AF",
    "name:rus_x_preferred":[
        "Kharkul\u2019"
    ],
    "name:und_x_variant":[
        "Kha\u1e5fq\u014dl",
        "Kharqowl",
        "Khar Q\u014dl",
        "\u062e\u0631 \u0642\u0648\u0644"
    ],
    "wof:name":"Khar Qol",
    "wof:placetype":"locality"
},
  "geometry": {"coordinates":[67.51579,34.16423],"type":"Point"}
}