{
  "type": "Feature",
  "properties": {
    "gn:admin1_code":"27",
    "gn:admin2_code":"402.0",
    "gn:asciiname":"Darah",
    "gn:country_code":"AF",
    "gn:dem":2537,
    "gn:feature_class":"P",
    "gn:feature_code":"PPL",
    "gn:name":"Darah",
    "gn:population":0,
    "gn:timezone":"Asia/Kabul",
    "iso:country":"AF",
    "name:ceb_x_preferred":[
        "Darah"
    ],
    "name:swe_x_preferred":[
        "Darah"
    ],
    "name:und_x_variant":[
        "\u1e0ea\u1e5fa",
        "Dara",
        "Darreh",
        "\u062f\u0631\u0647"
    ],
    "wof:name":"Darah",
    "wof:placetype":"locality"
},
  "geometry": {"coordinates":[68.75161999999999,34.48513],"type":"Point"}
}