{
  "type": "Feature",
  "properties": {
    "gn:admin1_code":"28",
    "gn:admin2_code":"2505",
    "gn:asciiname":"Jankah",
    "gn:country_code":"AF",
    "gn:dem":1776,
    "gn:feature_class":"P",
    "gn:feature_code":"PPL",
    "gn:name":"J\u0101nkah",
    "gn:population":0,
    "gn:timezone":"Asia/Kabul",
    "iso:country":"AF",
    "name:und_x_variant":[
        "Dzhanka",
        "J\u0101nka",
        "J\u0101nkah",
        "\u062c\u0627\u0646\u06a9\u0647"
    ],
    "wof:name":"Jankah",
    "wof:placetype":"locality"
},
  "geometry": {"coordinates":[66.53113,32.33072],"type":"Point"}
}