{
  "type": "Feature",
  "properties": {
    "gn:admin1_code":"05",
    "gn:admin2_code":"2806",
    "gn:asciiname":"Deh-e Menah",
    "gn:country_code":"AF",
    "gn:dem":2975,
    "gn:feature_class":"P",
    "gn:feature_code":"PPL",
    "gn:name":"Deh-e M\u0113nah",
    "gn:population":0,
    "gn:timezone":"Asia/Kabul",
    "iso:country":"AF",
    "name:und_x_variant":[
        "Dekhi-Mena",
        "\u1e0eehe M\u0113na",
        "Deh-e M\u0113nah",
        "Deh-e M\u012b\u0101nah",
        "\u062f\u0647 \u0645\u06d0\u0646\u0647"
    ],
    "wof:name":"Deh-e Menah",
    "wof:placetype":"locality"
},
  "geometry": {"coordinates":[66.83579,34.13876],"type":"Point"}
}