{
  "type": "Feature",
  "properties": {
    "gn:admin1_code":"8",
    "gn:admin2_code":"609.0",
    "gn:asciiname":"Qaryah-ye Sahib Zadah",
    "gn:country_code":"AF",
    "gn:dem":1951,
    "gn:feature_class":"P",
    "gn:feature_code":"PPL",
    "gn:name":"Qaryah-ye \u015e\u0101\u1e29ib Z\u0101dah",
    "gn:population":0,
    "gn:timezone":"Asia/Kabul",
    "iso:country":"AF",
    "name:rus_x_preferred":[
        "Kar\u2019yayi-Sakhibzada"
    ],
    "name:und_x_variant":[
        "Qa\u1e5fya-i-S\u0101hebz\u0101\u1e0fah",
        "Qaryah-ye \u015e\u0101\u1e29ib Z\u0101dah",
        "\u0642\u0631\u06cc\u06c0 \u0635\u0627\u062d\u0628 \u0632\u0627\u062f\u0647",
        "Qaryeh-ye \u015e\u0101\u1e29ebz\u0101deh"
    ],
    "wof:name":"Qaryah-ye Sahib Zadah",
    "wof:placetype":"locality"
},
  "geometry": {"coordinates":[67.73739999999999,32.70954],"type":"Point"}
}