{
  "type": "Feature",
  "properties": {
    "gn:admin1_code":"01",
    "gn:admin2_code":"1128.0",
    "gn:asciiname":"Mazayk Dasht",
    "gn:country_code":"AF",
    "gn:dem":2877,
    "gn:feature_class":"P",
    "gn:feature_code":"PPL",
    "gn:name":"Mazayk Dasht",
    "gn:population":0,
    "gn:timezone":"Asia/Kabul",
    "iso:country":"AF",
    "name:und_x_variant":[
        "Maz\u0113k Da\u0161t",
        "Maz\u0113k Dasht",
        "Mazayk Dasht",
        "\u0645\u0632\u06cc\u06a9 \u062f\u0634\u062a"
    ],
    "wof:name":"Mazayk Dasht",
    "wof:placetype":"locality"
},
  "geometry": {"coordinates":[70.3426,37.47337],"type":"Point"}
}