{
  "type": "Feature",
  "properties": {
    "gn:admin1_code":"3",
    "gn:admin2_code":"1303.0",
    "gn:asciiname":"Charmab",
    "gn:country_code":"AF",
    "gn:dem":866,
    "gn:feature_class":"P",
    "gn:feature_code":"PPL",
    "gn:name":"Charm\u0101b",
    "gn:population":0,
    "gn:timezone":"Asia/Kabul",
    "iso:country":"AF",
    "name:und_x_variant":[
        "\u010carm\u0101b",
        "Charmab",
        "Charm\u0101b",
        "\u0686\u0631\u0645\u0627\u0628"
    ],
    "wof:name":"Charmab",
    "wof:placetype":"locality"
},
  "geometry": {"coordinates":[68.58844999999999,35.81373],"type":"Point"}
}