{
  "type": "Feature",
  "properties": {
    "gn:admin1_code":"09",
    "gn:admin2_code":"2706",
    "gn:asciiname":"Khak-e Basir",
    "gn:country_code":"AF",
    "gn:dem":2143,
    "gn:feature_class":"P",
    "gn:feature_code":"PPL",
    "gn:name":"Kh\u0101k-e Ba\u015f\u012br",
    "gn:population":0,
    "gn:timezone":"Asia/Kabul",
    "iso:country":"AF",
    "name:fas_x_preferred":[
        "\u062e\u0627\u06a9\u0654 \u0628\u0635\u064a\u0631"
    ],
    "name:rus_x_preferred":[
        "\u0425\u0430\u043a\u0438-\u0411\u0430\u0441\u0438\u0440"
    ],
    "name:und_x_variant":[
        "Khaki-Basir",
        "Kh\u0101k-e Ba\u015f\u012br",
        "\u062e\u0627\u06a9 \u0628\u0635\u06cc\u0631",
        "Kh\u0101k-e B\u0101\u015f\u012br"
    ],
    "wof:name":"Khak-e Basir",
    "wof:placetype":"locality"
},
  "geometry": {"coordinates":[65.09921999999999,33.38531],"type":"Point"}
}