{
  "type": "Feature",
  "properties": {
    "gn:admin1_code":"23",
    "gn:admin2_code":"2416.0",
    "gn:asciiname":"Aniza'i",
    "gn:country_code":"AF",
    "gn:dem":934,
    "gn:feature_class":"P",
    "gn:feature_code":"PPL",
    "gn:name":"Aniza\u2019\u012b",
    "gn:population":0,
    "gn:timezone":"Asia/Kabul",
    "iso:country":"AF",
    "name:und_x_variant":[
        "Anizai",
        "Aniza\u012b",
        "\u0627\u0646\u0632\u06cc",
        "Aniza\u2019i",
        "Aniza\u2019\u012b",
        "\u0627\u0646\u0632\u0626\u06cc"
    ],
    "wof:name":"Aniza'i",
    "wof:placetype":"locality"
},
  "geometry": {"coordinates":[65.38427,31.53931],"type":"Point"}
}