{
  "type": "Feature",
  "properties": {
    "gn:admin1_code":"06",
    "gn:admin2_code":"2102",
    "gn:asciiname":"Saynabad",
    "gn:country_code":"AF",
    "gn:dem":744,
    "gn:feature_class":"P",
    "gn:feature_code":"PPL",
    "gn:name":"Sayn\u0101b\u0101d",
    "gn:population":0,
    "gn:timezone":"Asia/Kabul",
    "iso:country":"AF",
    "name:und_x_variant":[
        "Sayn\u0101b\u0101d",
        "\u0633\u06cc\u0646\u0627\u0628\u0627\u062f"
    ],
    "wof:name":"Saynabad",
    "wof:placetype":"locality"
},
  "geometry": {"coordinates":[63.08015,32.20397],"type":"Point"}
}