{
  "type": "Feature",
  "properties": {
    "gn:admin1_code":"27",
    "gn:admin2_code":"404",
    "gn:asciiname":"Tala Qol",
    "gn:country_code":"AF",
    "gn:dem":3064,
    "gn:feature_class":"P",
    "gn:feature_code":"PPL",
    "gn:name":"T\u0101l\u0101 Q\u014dl",
    "gn:population":0,
    "gn:timezone":"Asia/Kabul",
    "iso:country":"AF",
    "name:rus_x_preferred":[
        "Talakul\u2019"
    ],
    "name:und_x_variant":[
        "T\u0101l\u0101q\u014dl",
        "T\u0101l\u0101 Q\u014dl",
        "T\u0101l\u0101qowl",
        "\u062a\u0627\u0644\u0627 \u0642\u0648\u0644"
    ],
    "wof:name":"Tala Qol",
    "wof:placetype":"locality"
},
  "geometry": {"coordinates":[67.88381,34.51188],"type":"Point"}
}