{
  "type": "Feature",
  "properties": {
    "gn:admin1_code":"32",
    "gn:admin2_code":"1503",
    "gn:asciiname":"Zayduri",
    "gn:country_code":"AF",
    "gn:dem":2097,
    "gn:feature_class":"P",
    "gn:feature_code":"PPL",
    "gn:name":"Zaydur\u012b",
    "gn:population":0,
    "gn:timezone":"Asia/Kabul",
    "iso:country":"AF",
    "name:und_x_variant":[
        "Zaydur\u012b",
        "\u0632\u06cc\u062f\u0648\u0631\u06cc",
        "Zay\u1e0fo\u1e5fi"
    ],
    "wof:name":"Zayduri",
    "wof:placetype":"locality"
},
  "geometry": {"coordinates":[67.47041999999999,35.8633],"type":"Point"}
}