{
  "type": "Feature",
  "properties": {
    "gn:admin1_code":"33",
    "gn:admin2_code":"3102",
    "gn:asciiname":"Larak-e Ayshan",
    "gn:country_code":"AF",
    "gn:dem":1066,
    "gn:feature_class":"P",
    "gn:feature_code":"PPL",
    "gn:name":"Larak-e Aysh\u0101n",
    "gn:population":0,
    "gn:timezone":"Asia/Kabul",
    "iso:country":"AF",
    "name:und_x_variant":[
        "Larak-i-Aysh\u0101n",
        "Larak-e Aysh\u0101n",
        "\u0644\u0631\u06a9 \u0627\u06cc\u0634\u0627\u0646"
    ],
    "wof:name":"Larak-e Ayshan",
    "wof:placetype":"locality"
},
  "geometry": {"coordinates":[66.45968000000001,36.02752],"type":"Point"}
}