{
  "type": "Feature",
  "properties": {
    "gn:admin1_code":"5",
    "gn:admin2_code":"2806.0",
    "gn:asciiname":"Dahan-e Ahingaran",
    "gn:country_code":"AF",
    "gn:dem":2551,
    "gn:feature_class":"P",
    "gn:feature_code":"PPL",
    "gn:name":"Dahan-e \u0100hingar\u0101n",
    "gn:population":0,
    "gn:timezone":"Asia/Kabul",
    "iso:country":"AF",
    "name:und_x_variant":[
        "Dakhani-Akhingaran",
        "\u1e0eahane \u0100henga\u1e5f\u0101n",
        "Dahan-e \u0100hangar\u0101n",
        "Dahan-e \u0100hingar\u0101n",
        "\u062f\u0647\u0646 \u0622\u0647\u0646\u06af\u0631\u0627\u0646"
    ],
    "wof:name":"Dahan-e Ahingaran",
    "wof:placetype":"locality"
},
  "geometry": {"coordinates":[66.58501,34.19839],"type":"Point"}
}