{
  "type": "Feature",
  "properties": {
    "gn:admin1_code":"39",
    "gn:admin2_code":"2601.0",
    "gn:asciiname":"Chinarak",
    "gn:country_code":"AF",
    "gn:dem":1646,
    "gn:feature_class":"P",
    "gn:feature_code":"PPL",
    "gn:name":"Chin\u0101rak",
    "gn:population":0,
    "gn:timezone":"Asia/Kabul",
    "iso:country":"AF",
    "name:fas_x_preferred":[
        "\u0686\u0646\u0627\u0631\u0643"
    ],
    "name:und_x_variant":[
        "\u010cen\u0101rak",
        "Chin\u0101rak",
        "\u0686\u0646\u0627\u0631\u06a9",
        "Chen\u0101rak"
    ],
    "wof:name":"Chinarak",
    "wof:placetype":"locality"
},
  "geometry": {"coordinates":[65.82901,32.7979],"type":"Point"}
}