{
  "type": "Feature",
  "properties": {
    "gn:admin1_code":"08",
    "gn:admin2_code":"607",
    "gn:asciiname":"Jijgah",
    "gn:country_code":"AF",
    "gn:dem":2322,
    "gn:feature_class":"P",
    "gn:feature_code":"PPL",
    "gn:name":"J\u012bjgah",
    "gn:population":0,
    "gn:timezone":"Asia/Kabul",
    "iso:country":"AF",
    "name:und_x_variant":[
        "Dzhidzhga",
        "J\u012bjga",
        "J\u012bjgah",
        "\u062c\u06cc\u062c\u06af\u0647"
    ],
    "wof:name":"Jijgah",
    "wof:placetype":"locality"
},
  "geometry": {"coordinates":[67.29548,32.97656],"type":"Point"}
}