{
  "type": "Feature",
  "properties": {
    "gn:admin1_code":"11",
    "gn:admin2_code":"2011.0",
    "gn:asciiname":"Chahak",
    "gn:country_code":"AF",
    "gn:dem":1315,
    "gn:feature_class":"P",
    "gn:feature_code":"PPL",
    "gn:name":"Ch\u0101hak",
    "gn:population":0,
    "gn:timezone":"Asia/Kabul",
    "iso:country":"AF",
    "name:ceb_x_preferred":[
        "Chahak"
    ],
    "name:fas_x_preferred":[
        "\u0686\u0627\u0647\u0643"
    ],
    "name:fas_x_variant":[
        "\u0686\u0627\u0647\u06a9"
    ],
    "name:swe_x_preferred":[
        "Chahak"
    ],
    "name:und_x_variant":[
        "\u010c\u0101hak",
        "Ch\u0101hak"
    ],
    "wof:name":"Chahak",
    "wof:placetype":"locality"
},
  "geometry": {"coordinates":[62.39232,33.48423],"type":"Point"}
}