{
  "type": "Feature",
  "properties": {
    "gn:admin1_code":"11",
    "gn:admin2_code":"2009",
    "gn:asciiname":"Faruq Agha",
    "gn:country_code":"AF",
    "gn:dem":936,
    "gn:feature_class":"P",
    "gn:feature_code":"PPL",
    "gn:name":"F\u0101r\u016bq \u0100gh\u0101",
    "gn:population":0,
    "gn:timezone":"Asia/Kabul",
    "iso:country":"AF",
    "name:und_x_variant":[
        "F\u0101r\u016bq \u0100gh\u0101",
        "\u0641\u0627\u0631\u0648\u0642 \u0622\u063a\u0627",
        "F\u0101r\u016bq \u0100q\u0101"
    ],
    "wof:name":"Faruq Agha",
    "wof:placetype":"locality"
},
  "geometry": {"coordinates":[61.01389,34.26853],"type":"Point"}
}