{
  "type": "Feature",
  "properties": {
    "gn:admin1_code":"28",
    "gn:admin2_code":"2502.0",
    "gn:asciiname":"Chachob",
    "gn:country_code":"AF",
    "gn:dem":2077,
    "gn:feature_class":"P",
    "gn:feature_code":"PPL",
    "gn:name":"Chach\u014db",
    "gn:population":0,
    "gn:timezone":"Asia/Kabul",
    "iso:country":"AF",
    "name:und_x_variant":[
        "\u010ca\u010dob",
        "Chachob",
        "Chach\u014db",
        "\u0686\u0686\u0648\u0628",
        "Chach\u016bb"
    ],
    "wof:name":"Chachob",
    "wof:placetype":"locality"
},
  "geometry": {"coordinates":[67.19750000000001,32.46853],"type":"Point"}
}