{
  "type": "Feature",
  "properties": {
    "gn:admin1_code":"18",
    "gn:admin2_code":"808",
    "gn:asciiname":"Shabay",
    "gn:country_code":"AF",
    "gn:dem":1428,
    "gn:feature_class":"P",
    "gn:feature_code":"PPL",
    "gn:name":"Sh\u0101bay",
    "gn:population":0,
    "gn:timezone":"Asia/Kabul",
    "iso:country":"AF",
    "name:und_x_variant":[
        "\u0160\u0101bay",
        "Shabay",
        "S\u0304\u0101bi",
        "Sh\u0101bay",
        "Sh\u0101b\u012b",
        "\u0634\u0627\u0628\u06cc"
    ],
    "wof:name":"Shabay",
    "wof:placetype":"locality"
},
  "geometry": {"coordinates":[70.38749,34.10563],"type":"Point"}
}