{
  "type": "Feature",
  "properties": {
    "gn:admin1_code":"37",
    "gn:admin2_code":"3203",
    "gn:asciiname":"Khandakay",
    "gn:country_code":"AF",
    "gn:dem":1694,
    "gn:feature_class":"P",
    "gn:feature_code":"PPL",
    "gn:name":"Khan\u1e0fakay",
    "gn:population":0,
    "gn:timezone":"Asia/Kabul",
    "iso:country":"AF",
    "name:fas_x_preferred":[
        "\u062e\u0646\u062f\u0643\u06cc"
    ],
    "name:und_x_variant":[
        "Khandaka\u012b",
        "Khan\u1e0fakay",
        "\u062e\u0646\u0689\u0643\u06cc"
    ],
    "wof:name":"Khandakay",
    "wof:placetype":"locality"
},
  "geometry": {"coordinates":[69.6936,33.22217],"type":"Point"}
}