{
  "type": "Feature",
  "properties": {
    "gn:admin1_code":"05",
    "gn:admin2_code":"2806.0",
    "gn:asciiname":"Jowzar",
    "gn:country_code":"AF",
    "gn:dem":3204,
    "gn:feature_class":"P",
    "gn:feature_code":"PPL",
    "gn:name":"Jowz\u0101r",
    "gn:population":0,
    "gn:timezone":"Asia/Kabul",
    "iso:country":"AF",
    "name:fas_x_preferred":[
        "\u062c\u0648\u0632\u0627\u0631"
    ],
    "name:und_x_variant":[
        "Dzhauzar",
        "Jowz\u0101r",
        "Jawz\u0101r",
        "\u062c\u0648\u0632\u0627\u0631"
    ],
    "wof:name":"Jowzar",
    "wof:placetype":"locality"
},
  "geometry": {"coordinates":[67.18975,34.32966],"type":"Point"}
}