{
  "type": "Feature",
  "properties": {
    "gn:admin1_code":"41",
    "gn:admin2_code":"3401",
    "gn:asciiname":"Pay Kotal",
    "gn:country_code":"AF",
    "gn:dem":2130,
    "gn:feature_class":"P",
    "gn:feature_code":"PPL",
    "gn:name":"P\u0101y K\u014dtal",
    "gn:population":0,
    "gn:timezone":"Asia/Kabul",
    "iso:country":"AF",
    "name:und_x_variant":[
        "P\u0101y K\u014dtal",
        "P\u0101y Kowtal",
        "\u067e\u0627\u06cc \u06a9\u0648\u062a\u0644"
    ],
    "wof:name":"Pay Kotal",
    "wof:placetype":"locality"
},
  "geometry": {"coordinates":[66.12562,33.66118],"type":"Point"}
}