{
  "type": "Feature",
  "properties": {
    "gn:admin1_code":"28",
    "gn:admin2_code":"2509",
    "gn:asciiname":"Sine Kelay",
    "gn:country_code":"AF",
    "gn:dem":2337,
    "gn:feature_class":"P",
    "gn:feature_code":"PPL",
    "gn:name":"S\u012bn\u0113 K\u00ealay",
    "gn:population":0,
    "gn:timezone":"Asia/Kabul",
    "iso:country":"AF",
    "name:und_x_variant":[
        "S\u012bn\u0113 Kalay",
        "S\u012bn\u0113 K\u00ealay",
        "\u0633\u06cc\u0646\u06d0 \u06a9\u0644\u06cc",
        "S\u012bn\u012b Kalay"
    ],
    "wof:name":"Sine Kelay",
    "wof:placetype":"locality"
},
  "geometry": {"coordinates":[67.81650999999999,32.02889],"type":"Point"}
}