{
  "type": "Feature",
  "properties": {
    "gn:admin1_code":"13",
    "gn:admin2_code":"101.0",
    "gn:asciiname":"Qal'achah-ye Sahib Zadahha",
    "gn:country_code":"AF",
    "gn:dem":1795,
    "gn:feature_class":"P",
    "gn:feature_code":"PPL",
    "gn:name":"Qal\u2018achah-ye \u015e\u0101\u1e29ib Z\u0101dahh\u0101",
    "gn:population":0,
    "gn:timezone":"Asia/Kabul",
    "iso:country":"AF",
    "name:fas_x_preferred":[
        "\u0642\u0644\u0639\u0647\u0686\u06c0 \u0635\u0627\u062d\u0628 \u0632\u0627\u062f\u0647"
    ],
    "name:und_x_variant":[
        "Kalachayn-Sakhibzada",
        "Qal\u2018acha-i-\u015e\u0101\u1e29ebz\u0101da",
        "Qal\u2019a\u010da-i-\u015e\u0101hebz\u0101da",
        "Qal\u2018ahchah-ye \u015e\u0101\u1e29ibz\u0101dah",
        "Qal\u2018ehcheh-ye \u015e\u0101\u1e29ebz\u0101deh",
        "Qal\u2018achah-ye \u015e\u0101\u1e29ib Z\u0101dah",
        "\u0642\u0644\u0639\u0686\u0647 \u0635\u0627\u062d\u0628 \u0632\u0627\u062f\u0647",
        "Qal\u2018achah-ye \u015e\u0101\u1e29ib Z\u0101dahh\u0101",
        "\u0642\u0644\u0639\u0686\u0647 \u0635\u0627\u062d\u0628 \u0632\u0627\u062f\u0647 \u0647\u0627"
    ],
    "wof:name":"Qal'achah-ye Sahib Zadahha",
    "wof:placetype":"locality"
},
  "geometry": {"coordinates":[69.21333,34.49333],"type":"Point"}
}