{
  "type": "Feature",
  "properties": {
    "gn:admin1_code":"5",
    "gn:admin2_code":"2805.0",
    "gn:asciiname":"Baraki",
    "gn:country_code":"AF",
    "gn:dem":2761,
    "gn:feature_class":"P",
    "gn:feature_code":"PPL",
    "gn:name":"Barak\u012b",
    "gn:population":0,
    "gn:timezone":"Asia/Kabul",
    "iso:country":"AF",
    "name:und_x_variant":[
        "Barahk\u012b",
        "Barak\u012b",
        "\u0628\u0631\u06a9\u06cc"
    ],
    "wof:name":"Baraki",
    "wof:placetype":"locality"
},
  "geometry": {"coordinates":[67.05287,34.34719],"type":"Point"}
}