{
  "type": "Feature",
  "properties": {
    "gn:admin1_code":"28",
    "gn:admin2_code":"2511",
    "gn:asciiname":"Latak",
    "gn:country_code":"AF",
    "gn:dem":2026,
    "gn:feature_class":"P",
    "gn:feature_code":"PPL",
    "gn:name":"La\u1e6fak",
    "gn:population":0,
    "gn:timezone":"Asia/Kabul",
    "iso:country":"AF",
    "name:ceb_x_preferred":[
        "Latak"
    ],
    "name:swe_x_preferred":[
        "Latak"
    ],
    "name:und_x_variant":[
        "Latik",
        "La\u1e6fak",
        "Latek",
        "\u0644\u067c\u06a9"
    ],
    "wof:name":"Latak",
    "wof:placetype":"locality"
},
  "geometry": {"coordinates":[67.50927,31.98797],"type":"Point"}
}