{
  "type": "Feature",
  "properties": {
    "gn:admin1_code":"06",
    "gn:admin2_code":"2103",
    "gn:asciiname":"Maidan-e Jabha",
    "gn:country_code":"AF",
    "gn:dem":1506,
    "gn:feature_class":"P",
    "gn:feature_code":"PPL",
    "gn:name":"Ma\u012bd\u0101n-e Jabh\u0101",
    "gn:population":0,
    "gn:timezone":"Asia/Kabul",
    "iso:country":"AF",
    "name:und_x_variant":[
        "May\u1e0f\u0101n Jabha",
        "Ma\u012bd\u0101n-e Jabh\u0101",
        "\u0645\u06cc\u062f\u0627\u0646 \u062c\u0628\u0647\u0627",
        "Meyd\u0101n Jabhah"
    ],
    "wof:name":"Maidan-e Jabha",
    "wof:placetype":"locality"
},
  "geometry": {"coordinates":[63.70234,32.65915],"type":"Point"}
}