{
  "type": "Feature",
  "properties": {
    "gn:admin1_code":"23",
    "gn:admin2_code":"2403.0",
    "gn:asciiname":"Chakaw",
    "gn:country_code":"AF",
    "gn:dem":1370,
    "gn:feature_class":"P",
    "gn:feature_code":"PPL",
    "gn:name":"Chak\u0101w",
    "gn:population":0,
    "gn:timezone":"Asia/Kabul",
    "iso:country":"AF",
    "name:fas_x_preferred":[
        "\u0686\u0643\u0627\u0628"
    ],
    "name:und_x_variant":[
        "\u010cak\u0101w",
        "Chak\u0101w",
        "Chakav",
        "\u0686\u06a9\u0627\u0648",
        "Chak\u0101b"
    ],
    "wof:name":"Chakaw",
    "wof:placetype":"locality"
},
  "geometry": {"coordinates":[65.68184000000001,31.93223],"type":"Point"}
}