{
  "type": "Feature",
  "properties": {
    "gn:admin1_code":"26",
    "gn:admin2_code":"1204",
    "gn:asciiname":"Pil Kha",
    "gn:country_code":"AF",
    "gn:dem":1495,
    "gn:feature_class":"P",
    "gn:feature_code":"PPL",
    "gn:name":"P\u012bl Kh\u0101",
    "gn:population":0,
    "gn:timezone":"Asia/Kabul",
    "iso:country":"AF",
    "name:und_x_variant":[
        "P\u012bl Kh\u0101",
        "\u067e\u06cc\u0644 \u062e\u0627"
    ],
    "wof:name":"Pil Kha",
    "wof:placetype":"locality"
},
  "geometry": {"coordinates":[69.44991,36.49131],"type":"Point"}
}