{
  "type": "Feature",
  "properties": {
    "gn:admin1_code":"32",
    "gn:admin2_code":"1503",
    "gn:asciiname":"Dawud",
    "gn:country_code":"AF",
    "gn:dem":2464,
    "gn:feature_class":"P",
    "gn:feature_code":"PPL",
    "gn:name":"D\u0101w\u016bd",
    "gn:population":0,
    "gn:timezone":"Asia/Kabul",
    "iso:country":"AF",
    "name:deu_x_preferred":[
        "Dawud"
    ],
    "name:ita_x_preferred":[
        "Dawud"
    ],
    "name:und_x_variant":[
        "D\u0101w\u016bd",
        "\u062f\u0627\u0648\u0648\u062f",
        "\u1e0e\u0101\u2019\u016b\u1e0f"
    ],
    "wof:name":"Dawud",
    "wof:placetype":"locality"
},
  "geometry": {"coordinates":[67.40748000000001,35.68769],"type":"Point"}
}