{
  "type": "Feature",
  "properties": {
    "gn:admin1_code":"8",
    "gn:admin2_code":"606.0",
    "gn:asciiname":"Baraki",
    "gn:country_code":"AF",
    "gn:dem":2717,
    "gn:feature_class":"P",
    "gn:feature_code":"PPL",
    "gn:name":"Barak\u012b",
    "gn:population":0,
    "gn:timezone":"Asia/Kabul",
    "iso:country":"AF",
    "name:ceb_x_preferred":[
        "Baraki"
    ],
    "name:deu_x_preferred":[
        "Baraki"
    ],
    "name:fra_x_preferred":[
        "Baraki"
    ],
    "name:msa_x_preferred":[
        "Baraki"
    ],
    "name:pol_x_preferred":[
        "Baraki"
    ],
    "name:ron_x_preferred":[
        "Baraki"
    ],
    "name:rus_x_preferred":[
        "\u0411\u0430\u0440\u0430\u043a\u0438"
    ],
    "name:swe_x_preferred":[
        "Baraki"
    ],
    "name:ukr_x_preferred":[
        "\u0411\u0430\u0440\u0430\u043a\u0456"
    ],
    "name:und_x_variant":[
        "Barak\u012b",
        "\u0628\u0631\u06a9\u06cc",
        "Ba\u1e5faki"
    ],
    "name:wol_x_preferred":[
        "Baraki"
    ],
    "wof:name":"Baraki",
    "wof:placetype":"locality"
},
  "geometry": {"coordinates":[67.37733,33.28417],"type":"Point"}
}