{
  "type": "Feature",
  "properties": {
    "gn:admin1_code":"23",
    "gn:admin2_code":"2407.0",
    "gn:asciiname":"Darwazah",
    "gn:country_code":"AF",
    "gn:dem":864,
    "gn:feature_class":"P",
    "gn:feature_code":"PPL",
    "gn:name":"Darw\u0101zah",
    "gn:population":0,
    "gn:timezone":"Asia/Kabul",
    "iso:country":"AF",
    "name:und_x_variant":[
        "Darviza",
        "\u1e0ea\u1e5fweza",
        "Darw\u0101zah",
        "\u062f\u0631\u0648\u0627\u0632\u0647",
        "Darv\u0101zeh"
    ],
    "wof:name":"Darwazah",
    "wof:placetype":"locality"
},
  "geometry": {"coordinates":[64.99293,31.54576],"type":"Point"}
}