{
  "type": "Feature",
  "properties": {
    "gn:admin1_code":"18",
    "gn:admin2_code":"810.0",
    "gn:asciiname":"Kurogh Menah",
    "gn:country_code":"AF",
    "gn:dem":2435,
    "gn:feature_class":"P",
    "gn:feature_code":"PPL",
    "gn:name":"Kur\u014dgh M\u0113nah",
    "gn:population":0,
    "gn:timezone":"Asia/Kabul",
    "iso:country":"AF",
    "name:und_x_variant":[
        "Ko\u1e5f\u014dgh M\u0113na",
        "Kurogmena",
        "Kur\u014dgh M\u0113nah",
        "Kor\u016bgh M\u0113nah",
        "\u06a9\u0631\u0648\u063a \u0645\u06d0\u0646\u0647"
    ],
    "wof:name":"Kurogh Menah",
    "wof:placetype":"locality"
},
  "geometry": {"coordinates":[70.71285999999998,33.98602],"type":"Point"}
}