{
  "type": "Feature",
  "properties": {
    "gn:admin1_code":"13",
    "gn:admin2_code":"103.0",
    "gn:asciiname":"Guzar",
    "gn:country_code":"AF",
    "gn:dem":1724,
    "gn:feature_class":"P",
    "gn:feature_code":"PPL",
    "gn:name":"Guzar",
    "gn:population":0,
    "gn:timezone":"Asia/Kabul",
    "iso:country":"AF",
    "name:und_x_variant":[
        "Goz\u0304ar",
        "Gozar",
        "Guzar",
        "\u06af\u0632\u0631"
    ],
    "wof:name":"Guzar",
    "wof:placetype":"locality"
},
  "geometry": {"coordinates":[69.10804,34.71184],"type":"Point"}
}