{
  "type": "Feature",
  "properties": {
    "gn:admin1_code":"36",
    "gn:admin2_code":"710",
    "gn:asciiname":"'Usman Khel",
    "gn:country_code":"AF",
    "gn:dem":2581,
    "gn:feature_class":"P",
    "gn:feature_code":"PPL",
    "gn:name":"\u2018Us\u0304m\u0101n Kh\u0113l",
    "gn:population":0,
    "gn:timezone":"Asia/Kabul",
    "iso:country":"AF",
    "name:fas_x_preferred":[
        "\u0639\u062b\u0645\u0627\u0646 \u062e\u064a\u0644"
    ],
    "name:rus_x_preferred":[
        "Ushmankheyl\u2019"
    ],
    "name:und_x_variant":[
        "\u2019Us\u0304m\u0101nkh\u0113l",
        "Os\u0304m\u0101n Kheyl",
        "\u2018Us\u0304m\u0101n Kh\u0113l",
        "\u0639\u062b\u0645\u0627\u0646\u062e\u06d0\u0644"
    ],
    "wof:name":"'Usman Khel",
    "wof:placetype":"locality"
},
  "geometry": {"coordinates":[69.43245,33.65459],"type":"Point"}
}