{
  "type": "Feature",
  "properties": {
    "gn:admin1_code":"11",
    "gn:admin2_code":"2013",
    "gn:asciiname":"Qaryah-ye Shelah-ye Masjid",
    "gn:country_code":"AF",
    "gn:dem":2275,
    "gn:feature_class":"P",
    "gn:feature_code":"PPL",
    "gn:name":"Qaryah-ye Sh\u0113lah-ye Masjid",
    "gn:population":0,
    "gn:timezone":"Asia/Kabul",
    "iso:country":"AF",
    "name:und_x_variant":[
        "Kor\u2019yashelayi-Masdzhid",
        "Qarya \u0160\u0113la-i-Masjed",
        "Qarya-i-\u0160\u0113la-i-Masjed",
        "Qaryah-ye Shaylah-ye Masjid",
        "\u0642\u0631\u06cc\u06c0 \u0634\u06d0\u0644\u0647 \u0645\u0633\u062c\u062f",
        "Qaryeh Sh\u0113lah-e Masjed",
        "Qaryah-ye Sh\u0113lah-ye Masjid"
    ],
    "wof:name":"Qaryah-ye Shelah-ye Masjid",
    "wof:placetype":"locality"
},
  "geometry": {"coordinates":[63.11600000000001,33.76923],"type":"Point"}
}