{
  "type": "Feature",
  "properties": {
    "gn:admin1_code":"01",
    "gn:admin2_code":"1110.0",
    "gn:asciiname":"Wurashan",
    "gn:country_code":"AF",
    "gn:dem":2303,
    "gn:feature_class":"P",
    "gn:feature_code":"PPL",
    "gn:name":"Wur\u0101sh\u0101n",
    "gn:population":0,
    "gn:timezone":"Asia/Kabul",
    "iso:country":"AF",
    "name:und_x_variant":[
        "Wo\u1e5f\u0101s\u0101n",
        "Wur\u0101sh\u0101n",
        "\u0648\u0631\u0627\u0634\u0627\u0646"
    ],
    "wof:name":"Wurashan",
    "wof:placetype":"locality"
},
  "geometry": {"coordinates":[70.80879,38.37196],"type":"Point"}
}