{
  "type": "Feature",
  "properties": {
    "gn:admin1_code":"07",
    "gn:admin2_code":"1804",
    "gn:asciiname":"Muhammad Khwajah",
    "gn:country_code":"AF",
    "gn:dem":1196,
    "gn:feature_class":"P",
    "gn:feature_code":"PPL",
    "gn:name":"Mu\u1e29ammad Khw\u0101jah",
    "gn:population":0,
    "gn:timezone":"Asia/Kabul",
    "iso:country":"AF",
    "name:fas_x_preferred":[
        "Mu\u1e29ammad Khw\u0101jah"
    ],
    "name:fas_x_variant":[
        "\u0645\u062d\u0645\u062f \u062e\u0648\u0627\u062c\u0647"
    ],
    "name:und_x_variant":[
        "Mo\u1e96amma\u1e0f Khw\u0101ja",
        "Mo\u1e29ammad Khv\u0101jeh"
    ],
    "wof:name":"Muhammad Khwajah",
    "wof:placetype":"locality"
},
  "geometry": {"coordinates":[64.25662,35.67048],"type":"Point"}
}