{
  "type": "Feature",
  "properties": {
    "gn:admin1_code":"26",
    "gn:admin2_code":"1209.0",
    "gn:asciiname":"Ghani Darah",
    "gn:country_code":"AF",
    "gn:dem":1215,
    "gn:feature_class":"P",
    "gn:feature_code":"PPL",
    "gn:name":"Gh\u0101n\u012b Darah",
    "gn:population":0,
    "gn:timezone":"Asia/Kabul",
    "iso:country":"AF",
    "name:und_x_variant":[
        "Gh\u0101ni Darrah",
        "Gh\u0101n\u012b Darreh",
        "Gh\u0101n\u012b Darah",
        "\u063a\u0627\u0646\u06cc \u062f\u0631\u0647"
    ],
    "wof:name":"Ghani Darah",
    "wof:placetype":"locality"
},
  "geometry": {"coordinates":[69.76819,37.48126],"type":"Point"}
}