{
  "type": "Feature",
  "properties": {
    "gn:admin1_code":"31",
    "gn:admin2_code":"1701.0",
    "gn:asciiname":"Darah-ye Akhtah",
    "gn:country_code":"AF",
    "gn:dem":525,
    "gn:feature_class":"P",
    "gn:feature_code":"PPL",
    "gn:name":"Darah-ye Akhtah",
    "gn:population":0,
    "gn:timezone":"Asia/Kabul",
    "iso:country":"AF",
    "name:und_x_variant":[
        "Dara-i-Akhta",
        "Darreh-ye Akhteh",
        "Darah-ye Akhtah",
        "\u062f\u0631\u06c0 \u0627\u062e\u062a\u0647"
    ],
    "wof:name":"Darah-ye Akhtah",
    "wof:placetype":"locality"
},
  "geometry": {"coordinates":[66.04536999999999,36.53731],"type":"Point"}
}