{
  "type": "Feature",
  "properties": {
    "gn:admin1_code":"11",
    "gn:admin2_code":"2010",
    "gn:asciiname":"Qal'ah-ye Jamal",
    "gn:country_code":"AF",
    "gn:dem":836,
    "gn:feature_class":"P",
    "gn:feature_code":"PPL",
    "gn:name":"Qal\u2018ah-ye Jam\u0101l",
    "gn:population":0,
    "gn:timezone":"Asia/Kabul",
    "iso:country":"AF",
    "name:und_x_variant":[
        "Qal\u2018a-i-Jam\u0101l",
        "Qal\u2018eh-ye Jam\u0101l",
        "Qal\u2018ah-ye Jam\u0101l",
        "\u0642\u0644\u0639\u06c0 \u062c\u0645\u0627\u0644"
    ],
    "wof:name":"Qal'ah-ye Jamal",
    "wof:placetype":"locality"
},
  "geometry": {"coordinates":[61.76424,34.37349],"type":"Point"}
}