{
  "type": "Feature",
  "properties": {
    "gn:admin1_code":"10",
    "gn:admin2_code":"2305.0",
    "gn:asciiname":"Surnay",
    "gn:country_code":"AF",
    "gn:dem":1864,
    "gn:feature_class":"P",
    "gn:feature_code":"PPL",
    "gn:name":"S\u016brnay",
    "gn:population":0,
    "gn:timezone":"Asia/Kabul",
    "iso:country":"AF",
    "name:und_x_variant":[
        "Surni",
        "S\u016b\u1e5fnay",
        "S\u016brnay",
        "\u0633\u0648\u0631\u0646\u06cc",
        "Sow\u1e5fnay"
    ],
    "wof:name":"Surnay",
    "wof:placetype":"locality"
},
  "geometry": {"coordinates":[65.17256,32.76105],"type":"Point"}
}