{
  "type": "Feature",
  "properties": {
    "gn:admin1_code":"28",
    "gn:admin2_code":"2507.0",
    "gn:asciiname":"Patu Khel Kelay",
    "gn:country_code":"AF",
    "gn:dem":1804,
    "gn:feature_class":"P",
    "gn:feature_code":"PPL",
    "gn:name":"Pat\u016b Kh\u0113l K\u00ealay",
    "gn:population":0,
    "gn:timezone":"Asia/Kabul",
    "iso:country":"AF",
    "name:und_x_variant":[
        "Palukheyl\u2019kalay",
        "Pat\u016bkh\u0113l Kalay",
        "Pat\u016b Kh\u0113l K\u00ealay",
        "\u067e\u062a\u0648 \u062e\u06d0\u0644 \u06a9\u0644\u06cc",
        "Pat\u016bkheyl Kalay"
    ],
    "wof:name":"Patu Khel Kelay",
    "wof:placetype":"locality"
},
  "geometry": {"coordinates":[66.97684,31.93122],"type":"Point"}
}