{
  "type": "Feature",
  "properties": {
    "gn:admin1_code":"26",
    "gn:admin2_code":"1211.0",
    "gn:asciiname":"Musa Zai",
    "gn:country_code":"AF",
    "gn:dem":426,
    "gn:feature_class":"P",
    "gn:feature_code":"PPL",
    "gn:name":"M\u016bs\u00e1 Za\u012b",
    "gn:population":0,
    "gn:timezone":"Asia/Kabul",
    "iso:country":"AF",
    "name:und_x_variant":[
        "M\u016bs\u00e1 Za\u012b",
        "\u0645\u0648\u0633\u0649 \u0632\u06cc",
        "M\u016bs\u00e1 Zay"
    ],
    "wof:name":"Musa Zai",
    "wof:placetype":"locality"
},
  "geometry": {"coordinates":[69.42271,37.36085],"type":"Point"}
}