{
  "type": "Feature",
  "properties": {
    "gn:admin1_code":"02",
    "gn:admin2_code":"1906",
    "gn:asciiname":"Shahzadah",
    "gn:country_code":"AF",
    "gn:dem":625,
    "gn:feature_class":"P",
    "gn:feature_code":"PPL",
    "gn:name":"Shahz\u0101dah",
    "gn:population":0,
    "gn:timezone":"Asia/Kabul",
    "iso:country":"AF",
    "name:und_x_variant":[
        "S\u0304ahz\u0101\u1e0fa",
        "Shahz\u0101dah",
        "\u0634\u0647\u0632\u0627\u062f\u0647",
        "Sh\u0101hz\u0101deh"
    ],
    "wof:name":"Shahzadah",
    "wof:placetype":"locality"
},
  "geometry": {"coordinates":[63.415,35.41052],"type":"Point"}
}