{
  "type": "Feature",
  "properties": {
    "gn:admin1_code":"10",
    "gn:admin2_code":"2306",
    "gn:asciiname":"Karez-e Afghan",
    "gn:country_code":"AF",
    "gn:dem":1210,
    "gn:feature_class":"P",
    "gn:feature_code":"PPL",
    "gn:name":"K\u0101r\u0113z-e Afgh\u0101n",
    "gn:population":0,
    "gn:timezone":"Asia/Kabul",
    "iso:country":"AF",
    "name:und_x_variant":[
        "K\u0101\u1e5f\u0113ze Afgh\u0101n",
        "Karezi-Afgan",
        "K\u0101r\u0113z-e Afgh\u0101n",
        "\u06a9\u0627\u0631\u06d0\u0632 \u0627\u0641\u063a\u0627\u0646",
        "K\u0101r\u012bz-e Afgh\u0101n"
    ],
    "wof:name":"Karez-e Afghan",
    "wof:placetype":"locality"
},
  "geometry": {"coordinates":[64.48875,32.39122],"type":"Point"}
}