{
  "type": "Feature",
  "properties": {
    "gn:admin1_code":"11",
    "gn:admin2_code":"2006",
    "gn:asciiname":"Fayzabad",
    "gn:country_code":"AF",
    "gn:dem":1041,
    "gn:feature_class":"P",
    "gn:feature_code":"PPL",
    "gn:name":"Fayzabad",
    "gn:population":0,
    "gn:timezone":"Asia/Kabul",
    "iso:country":"AF",
    "name:und_x_variant":[
        "Fay\u1e0f\u1e95 \u0100b\u0101\u1e0f",
        "Fayzabad",
        "Fay\u1e95\u0101b\u0101d",
        "\u0641\u06cc\u0636 \u0622\u0628\u0627\u062f",
        "Fey\u1e95\u0101b\u0101d",
        "Fay\u1e95 \u0100b\u0101d",
        "Fa\u012b\u1e95\u0101b\u0101d"
    ],
    "wof:name":"Fayzabad",
    "wof:placetype":"locality"
},
  "geometry": {"coordinates":[62.09047,34.90728],"type":"Point"}
}