{
  "type": "Feature",
  "properties": {
    "gn:admin1_code":"39",
    "gn:admin2_code":"2603",
    "gn:asciiname":"Feroza",
    "gn:country_code":"AF",
    "gn:dem":2355,
    "gn:feature_class":"P",
    "gn:feature_code":"PPL",
    "gn:name":"F\u0113\u1e5f\u014dza",
    "gn:population":0,
    "gn:timezone":"Asia/Kabul",
    "iso:country":"AF",
    "name:und_x_variant":[
        "F\u012br\u016bzeh",
        "F\u0113\u1e5f\u014dz Kalay",
        "F\u0113\u1e5f\u014dza",
        "F\u012br\u016bz Kalay",
        "F\u012br\u016bz",
        "F\u0113r\u014dz K\u00ealay",
        "\u0641\u06d0\u0631\u0648\u0632 \u06a9\u0644\u06cc",
        "\u0641\u064a\u0631\u0648\u0632"
    ],
    "wof:name":"Feroza",
    "wof:placetype":"locality"
},
  "geometry": {"coordinates":[66.5754,32.82128],"type":"Point"}
}