{
  "type": "Feature",
  "properties": {
    "gn:admin1_code":"09",
    "gn:admin2_code":"2706",
    "gn:asciiname":"Karez",
    "gn:country_code":"AF",
    "gn:dem":2301,
    "gn:feature_class":"P",
    "gn:feature_code":"PPL",
    "gn:name":"K\u0101r\u0113z",
    "gn:population":0,
    "gn:timezone":"Asia/Kabul",
    "iso:country":"AF",
    "name:fas_x_preferred":[
        "\u0643\u0627\u0631\u064a\u0632"
    ],
    "name:und_x_variant":[
        "K\u0101\u1e5f\u0113z",
        "K\u0101r\u0113z",
        "\u06a9\u0627\u0631\u06d0\u0632",
        "K\u0101r\u012bz"
    ],
    "wof:name":"Karez",
    "wof:placetype":"locality"
},
  "geometry": {"coordinates":[65.00083000000001,33.40229],"type":"Point"}
}