{
  "type": "Feature",
  "properties": {
    "gn:admin1_code":"11",
    "gn:admin2_code":"2007.0",
    "gn:asciiname":"Aqa Muhammad Khan",
    "gn:country_code":"AF",
    "gn:dem":760,
    "gn:feature_class":"P",
    "gn:feature_code":"PPL",
    "gn:name":"\u0100q\u0101 Mu\u1e29ammad Kh\u0101n",
    "gn:population":0,
    "gn:timezone":"Asia/Kabul",
    "iso:country":"AF",
    "name:und_x_variant":[
        "\u0100q\u0101 Mo\u1e29ammad Kh\u0101n",
        "\u0622\u0642\u0627 \u0645\u062d\u0645\u062f \u062e\u0627\u0646",
        "\u0100gh\u0101 Mo\u1e29ammad Kh\u0101n",
        "\u0100q\u0101 Mu\u1e29ammad Kh\u0101n"
    ],
    "wof:name":"Aqa Muhammad Khan",
    "wof:placetype":"locality"
},
  "geometry": {"coordinates":[61.31508,35.2651],"type":"Point"}
}