{
  "type": "Feature",
  "properties": {
    "gn:admin1_code":"27",
    "gn:admin2_code":"406.0",
    "gn:asciiname":"Nashkak",
    "gn:country_code":"AF",
    "gn:dem":2426,
    "gn:feature_class":"P",
    "gn:feature_code":"PPL",
    "gn:name":"N\u0101shkak",
    "gn:population":0,
    "gn:timezone":"Asia/Kabul",
    "iso:country":"AF",
    "name:und_x_variant":[
        "N\u0101\u0161kak",
        "Nashkak",
        "N\u0101shkak",
        "\u0646\u0627\u0634\u06a9\u06a9"
    ],
    "wof:name":"Nashkak",
    "wof:placetype":"locality"
},
  "geometry": {"coordinates":[68.47112,34.08770999999999],"type":"Point"}
}