{
  "type": "Feature",
  "properties": {
    "gn:admin1_code":"23",
    "gn:admin2_code":"2413",
    "gn:asciiname":"Hafan",
    "gn:country_code":"AF",
    "gn:dem":2143,
    "gn:feature_class":"P",
    "gn:feature_code":"PPL",
    "gn:name":"Haf\u0101n",
    "gn:population":0,
    "gn:timezone":"Asia/Kabul",
    "iso:country":"AF",
    "name:und_x_variant":[
        "Khafan",
        "Haf\u0101n",
        "\u0647\u0641\u0627\u0646"
    ],
    "wof:name":"Hafan",
    "wof:placetype":"locality"
},
  "geometry": {"coordinates":[67.51579,31.25441],"type":"Point"}
}