{
  "type": "Feature",
  "properties": {
    "gn:admin1_code":"8",
    "gn:admin2_code":"607.0",
    "gn:asciiname":"Pidgah",
    "gn:country_code":"AF",
    "gn:dem":2517,
    "gn:feature_class":"P",
    "gn:feature_code":"PPL",
    "gn:name":"P\u012bdgah",
    "gn:population":0,
    "gn:timezone":"Asia/Kabul",
    "iso:country":"AF",
    "name:und_x_variant":[
        "P\u012b\u1e0fga",
        "P\u012b\u1e0fgah",
        "P\u012bdgah",
        "\u067e\u06cc\u062f\u06af\u0647"
    ],
    "wof:name":"Pidgah",
    "wof:placetype":"locality"
},
  "geometry": {"coordinates":[67.32894,33.07107],"type":"Point"}
}