{
  "type": "Feature",
  "properties": {
    "gn:admin1_code":"27",
    "gn:admin2_code":"404",
    "gn:asciiname":"Gardan Buridah",
    "gn:country_code":"AF",
    "gn:dem":2711,
    "gn:feature_class":"P",
    "gn:feature_code":"PPL",
    "gn:name":"Gardan Buridah",
    "gn:population":0,
    "gn:timezone":"Asia/Kabul",
    "iso:country":"AF",
    "name:und_x_variant":[
        "Gardanburida",
        "Ga\u1e5f\u1e0fanbo\u1e5fi\u1e0fa",
        "Gardan Bor\u012bdah",
        "Gardanbor\u012bdeh",
        "Gardan Buridah",
        "\u06af\u0631\u062f\u0646 \u0628\u0631\u062f\u0647"
    ],
    "wof:name":"Gardan Buridah",
    "wof:placetype":"locality"
},
  "geometry": {"coordinates":[67.86058,34.42849],"type":"Point"}
}