{
  "type": "Feature",
  "properties": {
    "gn:admin1_code":"11",
    "gn:admin2_code":"2002.0",
    "gn:asciiname":"Safed-e Rawan",
    "gn:country_code":"AF",
    "gn:dem":951,
    "gn:feature_class":"P",
    "gn:feature_code":"PPL",
    "gn:name":"Saf\u0113d-e Raw\u0101n",
    "gn:population":0,
    "gn:timezone":"Asia/Kabul",
    "iso:country":"AF",
    "name:fas_x_preferred":[
        "\u0633\u0641\u064a\u062f\u0654 \u0631\u0648\u0627\u0646"
    ],
    "name:und_x_variant":[
        "Safedi-Ravan",
        "S\u0101wa",
        "Saf\u0113\u1e0f-i-\u1e5eaw\u0101n",
        "Sava",
        "Sef\u012bd-e Rav\u0101n",
        "Safayd-e Raw\u0101n",
        "\u0633\u0641\u06d0\u062f \u0631\u0648\u0627\u0646",
        "S\u0101wah",
        "\u0633\u0627\u0648\u0647",
        "Saf\u0113d-e Raw\u0101n"
    ],
    "wof:name":"Safed-e Rawan",
    "wof:placetype":"locality"
},
  "geometry": {"coordinates":[62.28813,34.2834],"type":"Point"}
}