{
  "type": "Feature",
  "properties": {
    "gn:admin1_code":"08",
    "gn:admin2_code":"609",
    "gn:asciiname":"Latek Kelay",
    "gn:country_code":"AF",
    "gn:dem":2382,
    "gn:feature_class":"P",
    "gn:feature_code":"PPL",
    "gn:name":"La\u1e6f\u0113k K\u00ealay",
    "gn:population":0,
    "gn:timezone":"Asia/Kabul",
    "iso:country":"AF",
    "name:und_x_variant":[
        "La\u1e6f\u0113k K\u00ealay",
        "\u0644\u067c\u06d0\u06a9 \u06a9\u0644\u06cc",
        "Lat\u0113k Kalay"
    ],
    "wof:name":"Latek Kelay",
    "wof:placetype":"locality"
},
  "geometry": {"coordinates":[67.47668,32.87357],"type":"Point"}
}