{
  "type": "Feature",
  "properties": {
    "gn:admin1_code":"11",
    "gn:admin2_code":"2012",
    "gn:asciiname":"Washa",
    "gn:country_code":"AF",
    "gn:dem":1707,
    "gn:feature_class":"P",
    "gn:feature_code":"PPL",
    "gn:name":"Washa",
    "gn:population":0,
    "gn:timezone":"Asia/Kabul",
    "iso:country":"AF",
    "name:und_x_variant":[
        "W\u0101\u0161a",
        "Washa",
        "W\u0101shah",
        "\u0648\u0627\u0634\u0647"
    ],
    "wof:name":"Washa",
    "wof:placetype":"locality"
},
  "geometry": {"coordinates":[63.41744,34.33431],"type":"Point"}
}