{
  "type": "Feature",
  "properties": {
    "gn:admin1_code":"33",
    "gn:admin2_code":"3104",
    "gn:asciiname":"Kawburdah",
    "gn:country_code":"AF",
    "gn:dem":2502,
    "gn:feature_class":"P",
    "gn:feature_code":"PPL",
    "gn:name":"K\u0101wburdah",
    "gn:population":0,
    "gn:timezone":"Asia/Kabul",
    "iso:country":"AF",
    "name:und_x_variant":[
        "K\u0101wbu\u1e5f\u1e0fa",
        "K\u0101wbu\u1e5f\u1e0fah",
        "K\u0101wburdah",
        "\u06a9\u0627\u0648\u0628\u0631\u062f\u0647"
    ],
    "wof:name":"Kawburdah",
    "wof:placetype":"locality"
},
  "geometry": {"coordinates":[66.49844,35.5347],"type":"Point"}
}