{
  "type": "Feature",
  "properties": {
    "gn:admin1_code":"01",
    "gn:admin2_code":"1128.0",
    "gn:asciiname":"Elk",
    "gn:country_code":"AF",
    "gn:dem":2356,
    "gn:feature_class":"P",
    "gn:feature_code":"PPL",
    "gn:name":"\u0112lk",
    "gn:population":0,
    "gn:timezone":"Asia/Kabul",
    "iso:country":"AF",
    "name:und_x_variant":[
        "\u0112lk",
        "\u0627\u06cc\u0644\u06a9",
        "\u0112lk (2)"
    ],
    "wof:name":"Elk",
    "wof:placetype":"locality"
},
  "geometry": {"coordinates":[70.48854,37.53978],"type":"Point"}
}