{
  "type": "Feature",
  "properties": {
    "gn:admin1_code":"23",
    "gn:admin2_code":"2408",
    "gn:asciiname":"Kanozai",
    "gn:country_code":"AF",
    "gn:dem":891,
    "gn:feature_class":"P",
    "gn:feature_code":"PPL",
    "gn:name":"Kanozai",
    "gn:population":0,
    "gn:timezone":"Asia/Kabul",
    "iso:country":"AF",
    "name:und_x_variant":[
        "K\u0101nowzay",
        "Kanozai",
        "K\u0101\u1e49\u014dza\u2019i",
        "K\u0101\u1e49\u014dza\u012b",
        "\u06a9\u0627\u06bc\u0648\u0632\u06cc",
        "K\u0101nowza\u2019\u012b"
    ],
    "wof:name":"Kanozai",
    "wof:placetype":"locality"
},
  "geometry": {"coordinates":[65.23235,31.46596],"type":"Point"}
}