{
  "type": "Feature",
  "properties": {
    "gn:admin1_code":"05",
    "gn:admin2_code":"2804",
    "gn:asciiname":"Katah Bayd",
    "gn:country_code":"AF",
    "gn:dem":2562,
    "gn:feature_class":"P",
    "gn:feature_code":"PPL",
    "gn:name":"Katah Bayd",
    "gn:population":0,
    "gn:timezone":"Asia/Kabul",
    "iso:country":"AF",
    "name:und_x_variant":[
        "Katab\u0113\u1e0f",
        "Ka\u1e6fah B\u012bd",
        "Katah Bayd",
        "\u06a9\u062a\u0647 \u0628\u06cc\u062f"
    ],
    "wof:name":"Katah Bayd",
    "wof:placetype":"locality"
},
  "geometry": {"coordinates":[66.45293000000001,35.09714],"type":"Point"}
}