{
  "type": "Feature",
  "properties": {
    "gn:admin1_code":"31",
    "gn:admin2_code":"1701",
    "gn:asciiname":"Rig",
    "gn:country_code":"AF",
    "gn:dem":376,
    "gn:feature_class":"P",
    "gn:feature_code":"PPL",
    "gn:name":"R\u012bg",
    "gn:population":0,
    "gn:timezone":"Asia/Kabul",
    "iso:country":"AF",
    "name:ceb_x_preferred":[
        "Rig"
    ],
    "name:deu_x_preferred":[
        "Rig"
    ],
    "name:fas_x_preferred":[
        "\u0631\u06cc\u06af"
    ],
    "name:swe_x_preferred":[
        "Rig"
    ],
    "wof:name":"Rig",
    "wof:placetype":"locality"
},
  "geometry": {"coordinates":[65.66667,36.66667],"type":"Point"}
}