{
  "type": "Feature",
  "properties": {
    "gn:admin1_code":"05",
    "gn:admin2_code":"2801",
    "gn:asciiname":"Nashar",
    "gn:country_code":"AF",
    "gn:dem":2887,
    "gn:feature_class":"P",
    "gn:feature_code":"PPL",
    "gn:name":"Nashar",
    "gn:population":0,
    "gn:timezone":"Asia/Kabul",
    "iso:country":"AF",
    "name:und_x_variant":[
        "Na\u0161ar",
        "Nashar",
        "\u0646\u0634\u0631"
    ],
    "wof:name":"Nashar",
    "wof:placetype":"locality"
},
  "geometry": {"coordinates":[67.63557,34.83269],"type":"Point"}
}