{
  "type": "Feature",
  "properties": {
    "gn:admin1_code":"23",
    "gn:admin2_code":"2412",
    "gn:asciiname":"Shaykhzay",
    "gn:country_code":"AF",
    "gn:dem":1203,
    "gn:feature_class":"P",
    "gn:feature_code":"PPL",
    "gn:name":"Shaykhzay",
    "gn:population":0,
    "gn:timezone":"Asia/Kabul",
    "iso:country":"AF",
    "name:und_x_variant":[
        "S\u0304\u0113knzay",
        "Sh\u0113knzay",
        "\u0160\u0113khzay",
        "Sh\u0113khza\u012b",
        "\u0634\u06d0\u062e\u0632\u06cc",
        "Sheykhzay",
        "Shaykhzay",
        "\u0634\u06cc\u062e\u0632\u06cc"
    ],
    "wof:name":"Shaykhzay",
    "wof:placetype":"locality"
},
  "geometry": {"coordinates":[66.24212,31.57581],"type":"Point"}
}