{
  "type": "Feature",
  "properties": {
    "gn:admin1_code":"40",
    "gn:admin2_code":"307.0",
    "gn:asciiname":"Dahan-e Lukhak",
    "gn:country_code":"AF",
    "gn:dem":2416,
    "gn:feature_class":"P",
    "gn:feature_code":"PPL",
    "gn:name":"Dahan-e Lukhak",
    "gn:population":0,
    "gn:timezone":"Asia/Kabul",
    "iso:country":"AF",
    "name:und_x_variant":[
        "Dikhani-Lukhak",
        "Dahan-e Lokhak",
        "Dahan-e Lukhak",
        "\u062f\u0647\u0646 \u0644\u062e\u06a9"
    ],
    "wof:name":"Dahan-e Lukhak",
    "wof:placetype":"locality"
},
  "geometry": {"coordinates":[68.74705,34.83747],"type":"Point"}
}