{
  "type": "Feature",
  "properties": {
    "gn:admin1_code":"41",
    "gn:admin2_code":"3408.0",
    "gn:asciiname":"Sar Bastah",
    "gn:country_code":"AF",
    "gn:dem":2808,
    "gn:feature_class":"P",
    "gn:feature_code":"PPL",
    "gn:name":"Sar Bastah",
    "gn:population":0,
    "gn:timezone":"Asia/Kabul",
    "iso:country":"AF",
    "name:und_x_variant":[
        "Sarbasta",
        "Sa\u1e5fbasta",
        "Sar Bastah",
        "Sarbasteh",
        "\u0633\u0631 \u0628\u0633\u062a\u0647"
    ],
    "wof:name":"Sar Bastah",
    "wof:placetype":"locality"
},
  "geometry": {"coordinates":[66.05190999999999,34.25588],"type":"Point"}
}