{
  "type": "Feature",
  "properties": {
    "gn:admin1_code":"27",
    "gn:admin2_code":"404.0",
    "gn:asciiname":"Zard Sang",
    "gn:country_code":"AF",
    "gn:dem":3016,
    "gn:feature_class":"P",
    "gn:feature_code":"PPL",
    "gn:name":"Zard Sang",
    "gn:population":0,
    "gn:timezone":"Asia/Kabul",
    "iso:country":"AF",
    "name:und_x_variant":[
        "\u0632\u0631\u062f \u0633\u0646\u06af"
    ],
    "wof:name":"Zard Sang",
    "wof:placetype":"locality"
},
  "geometry": {"coordinates":[67.99973,34.29716],"type":"Point"}
}