{
  "type": "Feature",
  "properties": {
    "gn:admin1_code":"01",
    "gn:admin2_code":"1113",
    "gn:asciiname":"Qasab",
    "gn:country_code":"AF",
    "gn:dem":1762,
    "gn:feature_class":"P",
    "gn:feature_code":"PPL",
    "gn:name":"Qa\u015f\u0101b",
    "gn:population":0,
    "gn:timezone":"Asia/Kabul",
    "iso:country":"AF",
    "name:und_x_variant":[
        "Qas\u0101b",
        "Qa\u015f\u015f\u0101b",
        "Qa\u015f\u0101b",
        "\u0642\u0635\u0627\u0628"
    ],
    "wof:name":"Qasab",
    "wof:placetype":"locality"
},
  "geometry": {"coordinates":[70.20017,37.40955],"type":"Point"}
}