{
  "type": "Feature",
  "properties": {
    "gn:admin1_code":"41",
    "gn:admin2_code":"3403.0",
    "gn:asciiname":"Darah Bafir",
    "gn:country_code":"AF",
    "gn:dem":2564,
    "gn:feature_class":"P",
    "gn:feature_code":"PPL",
    "gn:name":"Darah B\u0101f\u012br",
    "gn:population":0,
    "gn:timezone":"Asia/Kabul",
    "iso:country":"AF",
    "name:und_x_variant":[
        "Darya B\u0101f\u012b\u1e5f",
        "Darrabafir",
        "Darah B\u0101f\u012br",
        "Darrah B\u0101f\u012br",
        "\u062f\u0631\u0647 \u0628\u0627\u0641\u064a\u0631"
    ],
    "wof:name":"Darah Bafir",
    "wof:placetype":"locality"
},
  "geometry": {"coordinates":[66.1399,34.00243],"type":"Point"}
}