{
  "type": "Feature",
  "properties": {
    "gn:admin1_code":"14",
    "gn:admin2_code":"204.0",
    "gn:asciiname":"Dzholayan",
    "gn:country_code":"AF",
    "gn:dem":2240,
    "gn:feature_class":"P",
    "gn:feature_code":"PPL",
    "gn:name":"Dzholayan",
    "gn:population":0,
    "gn:timezone":"Asia/Kabul",
    "iso:country":"AF",
    "name:rus_x_preferred":[
        "\u0414\u0436\u043e\u043b\u0430\u044f\u043d"
    ],
    "name:und_x_variant":[
        "J\u014dl\u0101y\u0101n",
        "Dzholayan",
        "Jowl\u0101y\u0101n",
        "\u062c\u0648\u0644\u0627\u06cc\u0627\u0646"
    ],
    "wof:name":"Dzholayan",
    "wof:placetype":"locality"
},
  "geometry": {"coordinates":[69.7064,35.01979],"type":"Point"}
}