{
  "type": "Feature",
  "properties": {
    "gn:admin1_code":"30",
    "gn:admin2_code":"1614",
    "gn:asciiname":"Turkmania",
    "gn:country_code":"AF",
    "gn:dem":374,
    "gn:feature_class":"P",
    "gn:feature_code":"PPL",
    "gn:name":"Turkman\u012b\u0101",
    "gn:population":0,
    "gn:timezone":"Asia/Kabul",
    "iso:country":"AF",
    "name:fas_x_preferred":[
        "\u062a\u0631\u0643\u0645\u0646\u0647\u0627"
    ],
    "name:rus_x_preferred":[
        "\u0422\u0443\u0440\u043a\u043c\u0430\u043d\u0438\u044f"
    ],
    "name:und_x_variant":[
        "Torkman\u012bah",
        "Torkman\u012ba",
        "Turkmaniya",
        "Torkmanh\u0101",
        "Turkman\u012b\u0101",
        "\u062a\u0631\u06a9\u0645\u0646\u06cc\u0627"
    ],
    "wof:name":"Turkmania",
    "wof:placetype":"locality"
},
  "geometry": {"coordinates":[67.71423,36.77919],"type":"Point"}
}