{
  "type": "Feature",
  "properties": {
    "gn:admin1_code":"36",
    "gn:admin2_code":"702",
    "gn:asciiname":"Makawah",
    "gn:country_code":"AF",
    "gn:dem":2154,
    "gn:feature_class":"P",
    "gn:feature_code":"PPL",
    "gn:name":"Mak\u0101wah",
    "gn:population":0,
    "gn:timezone":"Asia/Kabul",
    "iso:country":"AF",
    "name:und_x_variant":[
        "Mak\u0101veh",
        "Mak\u0101wa",
        "Makava",
        "Mak\u0101wah",
        "\u0645\u06a9\u0627\u0648\u0647"
    ],
    "wof:name":"Makawah",
    "wof:placetype":"locality"
},
  "geometry": {"coordinates":[68.94348000000001,33.47646],"type":"Point"}
}