{
  "type": "Feature",
  "properties": {
    "gn:admin1_code":"8",
    "gn:admin2_code":"607.0",
    "gn:asciiname":"Alaghzar",
    "gn:country_code":"AF",
    "gn:dem":2371,
    "gn:feature_class":"P",
    "gn:feature_code":"PPL",
    "gn:name":"Alaghz\u0101r",
    "gn:population":0,
    "gn:timezone":"Asia/Kabul",
    "iso:country":"AF",
    "name:und_x_variant":[
        "Alagzar",
        "Alaghz\u0101r",
        "\u0627\u0644\u063a\u0632\u0627\u0631",
        "Alaghz\u0101\u1e5f"
    ],
    "wof:name":"Alaghzar",
    "wof:placetype":"locality"
},
  "geometry": {"coordinates":[67.53756,32.93641],"type":"Point"}
}