{
  "type": "Feature",
  "properties": {
    "gn:admin1_code":"13",
    "gn:admin2_code":"112.0",
    "gn:asciiname":"Ahangaran",
    "gn:country_code":"AF",
    "gn:dem":1012,
    "gn:feature_class":"P",
    "gn:feature_code":"PPL",
    "gn:name":"\u0100hangar\u0101n",
    "gn:population":0,
    "gn:timezone":"Asia/Kabul",
    "iso:country":"AF",
    "name:fas_x_preferred":[
        "\u0622\u0647\u0646\u06af\u0631\u0627\u0646"
    ],
    "name:und_x_variant":[
        "\u0100hangar\u0101n"
    ],
    "name:urd_x_preferred":[
        "\u0622\u06c1\u0646\u06af\u0627\u0631\u0627\u0646"
    ],
    "wof:name":"Ahangaran",
    "wof:placetype":"locality"
},
  "geometry": {"coordinates":[69.74061,34.61292],"type":"Point"}
}