{
  "type": "Feature",
  "properties": {
    "gn:admin1_code":"40",
    "gn:admin2_code":"305",
    "gn:asciiname":"Wazghar",
    "gn:country_code":"AF",
    "gn:dem":2223,
    "gn:feature_class":"P",
    "gn:feature_code":"PPL",
    "gn:name":"W\u0101zghar",
    "gn:population":0,
    "gn:timezone":"Asia/Kabul",
    "iso:country":"AF",
    "name:und_x_variant":[
        "Vazgar",
        "W\u0101zghar",
        "\u0648\u0627\u0632\u063a\u0631"
    ],
    "wof:name":"Wazghar",
    "wof:placetype":"locality"
},
  "geometry": {"coordinates":[68.8622,35.05449],"type":"Point"}
}