{
  "type": "Feature",
  "properties": {
    "gn:admin1_code":"13",
    "gn:admin2_code":"104",
    "gn:asciiname":"Quchi",
    "gn:country_code":"AF",
    "gn:dem":1646,
    "gn:feature_class":"P",
    "gn:feature_code":"PPL",
    "gn:name":"Q\u016bch\u012b",
    "gn:population":0,
    "gn:timezone":"Asia/Kabul",
    "iso:country":"AF",
    "name:und_x_variant":[
        "Kuchi",
        "Q\u016b\u010di",
        "Q\u016bch\u012b",
        "\u0642\u0648\u0686\u06cc"
    ],
    "wof:name":"Quchi",
    "wof:placetype":"locality"
},
  "geometry": {"coordinates":[69.12300999999999,34.77479],"type":"Point"}
}