{
  "type": "Feature",
  "properties": {
    "gn:admin1_code":"23",
    "gn:admin2_code":"2412.0",
    "gn:asciiname":"Sur Ghbargay",
    "gn:country_code":"AF",
    "gn:dem":1562,
    "gn:feature_class":"P",
    "gn:feature_code":"PPL",
    "gn:name":"S\u016br Ghbargay",
    "gn:population":0,
    "gn:timezone":"Asia/Kabul",
    "iso:country":"AF",
    "name:und_x_variant":[
        "Surgbargay",
        "S\u016br Ghbargay",
        "S\u016b\u1e5f Ghba\u1e5fgay",
        "\u0633\u0648\u0631 \u063a\u0628\u0631\u06af\u06cc"
    ],
    "wof:name":"Sur Ghbargay",
    "wof:placetype":"locality"
},
  "geometry": {"coordinates":[66.67283,31.28947],"type":"Point"}
}