{
  "type": "Feature",
  "properties": {
    "gn:admin1_code":"07",
    "gn:admin2_code":"1810",
    "gn:asciiname":"Qipchaq",
    "gn:country_code":"AF",
    "gn:dem":317,
    "gn:feature_class":"P",
    "gn:feature_code":"PPL",
    "gn:name":"Qipchaq",
    "gn:population":0,
    "gn:timezone":"Asia/Kabul",
    "iso:country":"AF",
    "name:und_x_variant":[
        "Kupch\u0101k",
        "Qipchaq",
        "\u0642\u067e\u0686\u0642",
        "Qepch\u0101q"
    ],
    "wof:name":"Qipchaq",
    "wof:placetype":"locality"
},
  "geometry": {"coordinates":[65.11717,36.887],"type":"Point"}
}