{
  "type": "Feature",
  "properties": {
    "gn:admin1_code":"34",
    "gn:admin2_code":"1007.0",
    "gn:asciiname":"Dag",
    "gn:country_code":"AF",
    "gn:dem":862,
    "gn:feature_class":"P",
    "gn:feature_code":"PPL",
    "gn:name":"Dag",
    "gn:population":0,
    "gn:timezone":"Asia/Kabul",
    "iso:country":"AF",
    "name:ceb_x_preferred":[
        "Dag"
    ],
    "name:dan_x_preferred":[
        "Dag"
    ],
    "name:fas_x_preferred":[
        "\u062f\u0627\u06af"
    ],
    "name:fra_x_preferred":[
        "Dag"
    ],
    "name:hun_x_preferred":[
        "DAG"
    ],
    "name:isl_x_preferred":[
        "Dag"
    ],
    "name:lat_x_preferred":[
        "Dag"
    ],
    "name:nld_x_preferred":[
        "Dag"
    ],
    "name:nor_x_preferred":[
        "Dag"
    ],
    "name:pol_x_preferred":[
        "Dag"
    ],
    "name:rus_x_preferred":[
        "\u0414\u0430\u0433"
    ],
    "name:slk_x_preferred":[
        "Dag"
    ],
    "name:srp_x_preferred":[
        "\u0414\u0430\u0433"
    ],
    "name:swe_x_preferred":[
        "Dag"
    ],
    "name:und_x_variant":[
        "D\u0101g",
        "\u1e0e\u0101g",
        "\u0689\u0627\u06af"
    ],
    "wof:name":"Dag",
    "wof:placetype":"locality"
},
  "geometry": {"coordinates":[71.24861999999997,34.95426],"type":"Point"}
}