{
  "type": "Feature",
  "properties": {
    "gn:admin1_code":"09",
    "gn:admin2_code":"2706",
    "gn:asciiname":"Sherghalji",
    "gn:country_code":"AF",
    "gn:dem":2026,
    "gn:feature_class":"P",
    "gn:feature_code":"PPL",
    "gn:name":"Sh\u0113rghalj\u012b",
    "gn:population":0,
    "gn:timezone":"Asia/Kabul",
    "iso:country":"AF",
    "name:fas_x_preferred":[
        "\u0634\u064a\u0631 \u063a\u0644\u062c\u06cc"
    ],
    "name:rus_x_preferred":[
        "\u0428\u0435\u0440\u0433\u0430\u043b\u044c\u0434\u0436\u0438"
    ],
    "name:und_x_variant":[
        "\u0160\u0113rghalji",
        "Shergal\u2019dzhi",
        "Shayrghalj\u012b",
        "\u0634\u06cc\u0631\u063a\u0644\u062c\u06cc",
        "Sh\u012brghalj\u012b",
        "Sh\u0113rghalj\u012b"
    ],
    "wof:name":"Sherghalji",
    "wof:placetype":"locality"
},
  "geometry": {"coordinates":[65.20981,33.44864],"type":"Point"}
}