{
  "type": "Feature",
  "properties": {
    "gn:admin1_code":"30",
    "gn:admin2_code":"1603",
    "gn:asciiname":"Gholyak",
    "gn:country_code":"AF",
    "gn:dem":2239,
    "gn:feature_class":"P",
    "gn:feature_code":"PPL",
    "gn:name":"Gh\u014dlyak",
    "gn:population":0,
    "gn:timezone":"Asia/Kabul",
    "iso:country":"AF",
    "name:und_x_variant":[
        "Gh\u014dlyak",
        "Ghowlyak",
        "\u063a\u0648\u0644\u06cc\u06a9"
    ],
    "wof:name":"Gholyak",
    "wof:placetype":"locality"
},
  "geometry": {"coordinates":[66.6845,35.80454],"type":"Point"}
}