{
  "type": "Feature",
  "properties": {
    "gn:admin1_code":"35",
    "gn:admin2_code":"903.0",
    "gn:asciiname":"Wuluswali 'Alingar",
    "gn:country_code":"AF",
    "gn:dem":937,
    "gn:feature_class":"P",
    "gn:feature_code":"PPLA2",
    "gn:name":"Wulusw\u0101l\u012b \u2018Al\u012bng\u0101r",
    "gn:population":0,
    "gn:timezone":"Asia/Kabul",
    "iso:country":"AF",
    "name:und_x_variant":[
        "Ulusvali-Alingar",
        "Olusw\u0101li Al\u012bng\u0101\u1e5f",
        "\u2018Al\u012bng\u0101r",
        "Wulusw\u0101l\u012b \u2018Al\u012bng\u0101r",
        "\u0648\u0644\u0633\u0648\u0627\u0644\u06cc \u0639\u0644\u06cc\u0646\u06af\u0627\u0631"
    ],
    "wof:name":"Wuluswali 'Alingar",
    "wof:placetype":"locality"
},
  "geometry": {"coordinates":[70.3593,34.83529],"type":"Point"}
}