{
  "type": "Feature",
  "properties": {
    "gn:admin1_code":"8",
    "gn:admin2_code":"604.0",
    "gn:asciiname":"Daygwar Shandah",
    "gn:country_code":"AF",
    "gn:dem":3093,
    "gn:feature_class":"P",
    "gn:feature_code":"PPL",
    "gn:name":"Daygw\u0101r Sh\u0101ndah",
    "gn:population":0,
    "gn:timezone":"Asia/Kabul",
    "iso:country":"AF",
    "name:und_x_variant":[
        "Degvarshanda",
        "D\u0113gw\u0101r\u0161\u0101nda",
        "D\u012bgv\u0101rsh\u0101ndeh",
        "Daygw\u0101r Sh\u0101ndah",
        "\u062f\u06cc\u06af\u0648\u0627\u0631 \u0634\u0627\u0646\u062f\u0647"
    ],
    "wof:name":"Daygwar Shandah",
    "wof:placetype":"locality"
},
  "geometry": {"coordinates":[67.62659000000001,34.09631],"type":"Point"}
}