{
  "type": "Feature",
  "properties": {
    "gn:admin1_code":"35",
    "gn:admin2_code":"903.0",
    "gn:asciiname":"Tigalam",
    "gn:country_code":"AF",
    "gn:dem":885,
    "gn:feature_class":"P",
    "gn:feature_code":"PPL",
    "gn:name":"\u1e6eigal\u0101m",
    "gn:population":0,
    "gn:timezone":"Asia/Kabul",
    "iso:country":"AF",
    "name:und_x_variant":[
        "\u067c\u06af\u0644\u0627\u0645",
        "Tigal\u0101m",
        "\u1e6eigal\u0101m"
    ],
    "wof:name":"Tigalam",
    "wof:placetype":"locality"
},
  "geometry": {"coordinates":[70.33835000000001,34.78867],"type":"Point"}
}