{
  "type": "Feature",
  "properties": {
    "gn:admin1_code":"08",
    "gn:admin2_code":"615",
    "gn:asciiname":"Sado Kala",
    "gn:country_code":"AF",
    "gn:dem":2099,
    "gn:feature_class":"P",
    "gn:feature_code":"PPL",
    "gn:name":"\u015ead\u014d Kal\u0101",
    "gn:population":0,
    "gn:timezone":"Asia/Kabul",
    "iso:country":"AF",
    "name:und_x_variant":[
        "Sa\u1e0fo Kai\u0101",
        "Sadukala",
        "\u015ea\u1e0fo Kal\u0101",
        "\u015ead\u014d Kal\u0101",
        "\u0635\u062f\u0648 \u06a9\u0644\u0627"
    ],
    "wof:name":"Sado Kala",
    "wof:placetype":"locality"
},
  "geometry": {"coordinates":[68.56728000000001,33.39968],"type":"Point"}
}