{
  "type": "Feature",
  "properties": {
    "gn:admin1_code":"28",
    "gn:admin2_code":"2507",
    "gn:asciiname":"Show Khel",
    "gn:country_code":"AF",
    "gn:dem":2030,
    "gn:feature_class":"P",
    "gn:feature_code":"PPL",
    "gn:name":"Show Kh\u0113l",
    "gn:population":0,
    "gn:timezone":"Asia/Kabul",
    "iso:country":"AF",
    "name:fas_x_preferred":[
        "\u0634\u0648 \u062e\u064a\u0644"
    ],
    "name:rus_x_preferred":[
        "Shaukheyl\u2019"
    ],
    "name:und_x_variant":[
        "\u0160awkhel",
        "Show Kh\u0113l",
        "\u0634\u0648 \u062e\u06d0\u0644",
        "Shaw Kheyl",
        "Shaukheyl\u2019"
    ],
    "wof:name":"Show Khel",
    "wof:placetype":"locality"
},
  "geometry": {"coordinates":[67.38375000000001,31.99789],"type":"Point"}
}