{
  "type": "Feature",
  "properties": {
    "gn:admin1_code":"09",
    "gn:admin2_code":"2707",
    "gn:asciiname":"Naw-e Jalal",
    "gn:country_code":"AF",
    "gn:dem":2863,
    "gn:feature_class":"P",
    "gn:feature_code":"PPL",
    "gn:name":"N\u0101w-e Jal\u0101l",
    "gn:population":0,
    "gn:timezone":"Asia/Kabul",
    "iso:country":"AF",
    "name:und_x_variant":[
        "Navi-Dzhalal\u2019",
        "N\u0101w-e Jal\u0101l",
        "\u0646\u0627\u0648 \u062c\u0644\u0627\u0644"
    ],
    "wof:name":"Naw-e Jalal",
    "wof:placetype":"locality"
},
  "geometry": {"coordinates":[66.34444000000001,34.47451],"type":"Point"}
}