{
  "type": "Feature",
  "properties": {
    "gn:admin1_code":"7",
    "gn:admin2_code":"1812.0",
    "gn:asciiname":"Akhtachi",
    "gn:country_code":"AF",
    "gn:dem":315,
    "gn:feature_class":"P",
    "gn:feature_code":"PPL",
    "gn:name":"Akhtach\u012b",
    "gn:population":0,
    "gn:timezone":"Asia/Kabul",
    "iso:country":"AF",
    "name:und_x_variant":[
        "Akhtach\u012b",
        "\u0627\u062e\u062a\u0686\u06cc",
        "Akhtachi"
    ],
    "wof:name":"Akhtachi",
    "wof:placetype":"locality"
},
  "geometry": {"coordinates":[65.13561999999999,36.90645],"type":"Point"}
}