{
  "type": "Feature",
  "properties": {
    "gn:admin1_code":"18",
    "gn:admin2_code":"804.0",
    "gn:asciiname":"Suri Khel",
    "gn:country_code":"AF",
    "gn:dem":1409,
    "gn:feature_class":"P",
    "gn:feature_code":"PPL",
    "gn:name":"S\u016br\u012b Kh\u0113l",
    "gn:population":0,
    "gn:timezone":"Asia/Kabul",
    "iso:country":"AF",
    "name:fas_x_preferred":[
        "\u0633\u0648\u0631\u06cc \u062e\u064a\u0644"
    ],
    "name:rus_x_preferred":[
        "Surikheyl\u2019"
    ],
    "name:und_x_variant":[
        "S\u016b\u1e5fikh\u0113l",
        "S\u016brikheyl",
        "S\u016br\u012b Kh\u0113l",
        "\u0633\u0648\u0631\u06cc \u062e\u06d0\u0644"
    ],
    "wof:name":"Suri Khel",
    "wof:placetype":"locality"
},
  "geometry": {"coordinates":[69.91065,34.30512],"type":"Point"}
}