{
  "type": "Feature",
  "properties": {
    "gn:admin1_code":"8",
    "gn:admin2_code":"606.0",
    "gn:asciiname":"Siyah Shighlan",
    "gn:country_code":"AF",
    "gn:dem":2646,
    "gn:feature_class":"P",
    "gn:feature_code":"PPL",
    "gn:name":"Siy\u0101h Shighl\u0101n",
    "gn:population":0,
    "gn:timezone":"Asia/Kabul",
    "iso:country":"AF",
    "name:und_x_variant":[
        "Sy\u0101\u0161eghlan",
        "S\u012b\u0101sheghlan",
        "S\u012b\u0101h Shighl\u0101n",
        "\u0633\u06cc\u0627\u0647 \u0634\u063a\u0644\u0627\u0646",
        "Siy\u0101h Shighl\u0101n"
    ],
    "wof:name":"Siyah Shighlan",
    "wof:placetype":"locality"
},
  "geometry": {"coordinates":[67.49445,33.3242],"type":"Point"}
}