{
  "type": "Feature",
  "properties": {
    "gn:admin1_code":"10",
    "gn:admin2_code":"2305",
    "gn:asciiname":"Sar Jinjay",
    "gn:country_code":"AF",
    "gn:dem":1668,
    "gn:feature_class":"P",
    "gn:feature_code":"PPL",
    "gn:name":"Sar Jinjay",
    "gn:population":0,
    "gn:timezone":"Asia/Kabul",
    "iso:country":"AF",
    "name:fas_x_preferred":[
        "\u0633\u0631\u0654 \u062c\u0646\u062c\u06cc"
    ],
    "name:rus_x_preferred":[
        "\u0421\u0430\u0440\u0434\u0436\u0438\u043d\u0434\u0436\u0430\u0439"
    ],
    "name:und_x_variant":[
        "Sardzhindzhay",
        "Sar Jinjay",
        "\u0633\u0631 \u062c\u0646\u062c\u06cc",
        "Sar Jenjay"
    ],
    "wof:name":"Sar Jinjay",
    "wof:placetype":"locality"
},
  "geometry": {"coordinates":[65.07643,33.03526],"type":"Point"}
}