{
  "type": "Feature",
  "properties": {
    "gn:admin1_code":"29",
    "gn:admin2_code":"2909.0",
    "gn:asciiname":"Aman Kot",
    "gn:country_code":"AF",
    "gn:dem":2123,
    "gn:feature_class":"P",
    "gn:feature_code":"PPL",
    "gn:name":"Am\u0101n K\u014d\u1e6f",
    "gn:population":0,
    "gn:timezone":"Asia/Kabul",
    "iso:country":"AF",
    "name:und_x_variant":[
        "Am\u0101n K\u014dt",
        "Amankot",
        "Am\u0101n Kowt",
        "Am\u0101n K\u014d\u1e6f",
        "\u0627\u0645\u0627\u0646 \u06a9\u0648\u067c"
    ],
    "wof:name":"Aman Kot",
    "wof:placetype":"locality"
},
  "geometry": {"coordinates":[69.25671,32.90821],"type":"Point"}
}