{
  "type": "Feature",
  "properties": {
    "gn:admin1_code":"8",
    "gn:admin2_code":"604.0",
    "gn:asciiname":"Burguch",
    "gn:country_code":"AF",
    "gn:dem":3382,
    "gn:feature_class":"P",
    "gn:feature_code":"PPL",
    "gn:name":"B\u016brg\u016bch",
    "gn:population":0,
    "gn:timezone":"Asia/Kabul",
    "iso:country":"AF",
    "name:rus_x_preferred":[
        "\u0411\u0443\u0440\u0433\u0443\u0447"
    ],
    "name:und_x_variant":[
        "B\u016brg\u016bch",
        "B\u016brg\u016b\u010d",
        "Bowrgowch",
        "\u0628\u0648\u0631\u06af\u0648\u0686"
    ],
    "wof:name":"Burguch",
    "wof:placetype":"locality"
},
  "geometry": {"coordinates":[67.62606,33.47902],"type":"Point"}
}