{
  "type": "Feature",
  "properties": {
    "gn:admin1_code":"39",
    "gn:admin2_code":"2602",
    "gn:asciiname":"Sar Kala-ye Shamali",
    "gn:country_code":"AF",
    "gn:dem":1848,
    "gn:feature_class":"P",
    "gn:feature_code":"PPL",
    "gn:name":"Sar Kal\u0101-ye Sham\u0101l\u012b",
    "gn:population":0,
    "gn:timezone":"Asia/Kabul",
    "iso:country":"AF",
    "name:fas_x_preferred":[
        "\u0654\u0642\u0644\u0639\u0647\u0654 \u0633\u0631"
    ],
    "name:und_x_variant":[
        "\u0160am\u0101li",
        "\u0160am\u0101li Kal\u0101",
        "Sarkala-Shamali",
        "Sar Kal\u0101-ye Sham\u0101l\u012b",
        "\u0633\u0631 \u06a9\u0644\u0627 \u0634\u0645\u0627\u0644\u06cc",
        "Sar Kal\u0101"
    ],
    "wof:name":"Sar Kala-ye Shamali",
    "wof:placetype":"locality"
},
  "geometry": {"coordinates":[66.23456999999999,32.64199],"type":"Point"}
}