{
  "type": "Feature",
  "properties": {
    "gn:admin1_code":"09",
    "gn:admin2_code":"2705",
    "gn:asciiname":"Pilari",
    "gn:country_code":"AF",
    "gn:dem":2303,
    "gn:feature_class":"P",
    "gn:feature_code":"PPL",
    "gn:name":"Pilar\u012b",
    "gn:population":0,
    "gn:timezone":"Asia/Kabul",
    "iso:country":"AF",
    "name:und_x_variant":[
        "Pilar\u012b",
        "\u067e\u0644\u0631\u06cc",
        "Pelar\u012b"
    ],
    "wof:name":"Pilari",
    "wof:placetype":"locality"
},
  "geometry": {"coordinates":[64.07784000000001,33.60655],"type":"Point"}
}