{
  "type": "Feature",
  "properties": {
    "gn:admin1_code":"33",
    "gn:admin2_code":"3101.0",
    "gn:asciiname":"Gungur",
    "gn:country_code":"AF",
    "gn:dem":735,
    "gn:feature_class":"P",
    "gn:feature_code":"PPL",
    "gn:name":"Gungur",
    "gn:population":0,
    "gn:timezone":"Asia/Kabul",
    "iso:country":"AF",
    "name:und_x_variant":[
        "\u06af\u0646\u06af\u0631",
        "Gongor"
    ],
    "wof:name":"Gungur",
    "wof:placetype":"locality"
},
  "geometry": {"coordinates":[66.24504,36.37702],"type":"Point"}
}