{
  "type": "Feature",
  "properties": {
    "gn:admin1_code":"10",
    "gn:admin2_code":"2305.0",
    "gn:asciiname":"Malang",
    "gn:country_code":"AF",
    "gn:dem":1292,
    "gn:feature_class":"P",
    "gn:feature_code":"PPL",
    "gn:name":"Malang",
    "gn:population":0,
    "gn:timezone":"Asia/Kabul",
    "iso:country":"AF",
    "name:und_x_variant":[
        "\u0645\u0644\u0646\u06af"
    ],
    "wof:name":"Malang",
    "wof:placetype":"locality"
},
  "geometry": {"coordinates":[64.84708000000001,32.85848],"type":"Point"}
}