{
  "type": "Feature",
  "properties": {
    "gn:admin1_code":"8",
    "gn:admin2_code":"618.0",
    "gn:asciiname":"Shaykhi Gudale",
    "gn:country_code":"AF",
    "gn:dem":2437,
    "gn:feature_class":"P",
    "gn:feature_code":"PPL",
    "gn:name":"Shaykh\u012b Gu\u1e0fal\u0113",
    "gn:population":0,
    "gn:timezone":"Asia/Kabul",
    "iso:country":"AF",
    "name:fas_x_preferred":[
        "\u0634\u064a\u062e\u06cc \u06af\u062f\u0644\u06cc"
    ],
    "name:und_x_variant":[
        "\u0160\u0113khi Godal\u0113",
        "Sheykhigudale",
        "Sh\u0113kh\u012b G\u014ddal\u012b",
        "Sheykh\u012b Godal\u0113",
        "Shaykh\u012b Gu\u1e0fal\u0113",
        "\u0634\u064a\u062e\u06cc \u06af\u0689\u0644\u06d0"
    ],
    "wof:name":"Shaykhi Gudale",
    "wof:placetype":"locality"
},
  "geometry": {"coordinates":[68.12598,33.35229],"type":"Point"}
}