{
  "type": "Feature",
  "properties": {
    "gn:admin1_code":"23",
    "gn:admin2_code":"2407.0",
    "gn:asciiname":"Badizo Kelay",
    "gn:country_code":"AF",
    "gn:dem":851,
    "gn:feature_class":"P",
    "gn:feature_code":"PPL",
    "gn:name":"B\u0101diz\u014d K\u00ealay",
    "gn:population":0,
    "gn:timezone":"Asia/Kabul",
    "iso:country":"AF",
    "name:und_x_variant":[
        "Badizukalay",
        "B\u0101diz\u014d K\u00ealay",
        "\u0628\u0627\u062f\u0632\u0648 \u06a9\u0644\u06cc",
        "B\u0101\u1e0fezo Kalay"
    ],
    "wof:name":"Badizo Kelay",
    "wof:placetype":"locality"
},
  "geometry": {"coordinates":[64.96813,31.53514],"type":"Point"}
}