{
  "type": "Feature",
  "properties": {
    "gn:admin1_code":"5",
    "gn:admin2_code":"2802.0",
    "gn:asciiname":"Surkhak Bilandi",
    "gn:country_code":"AF",
    "gn:dem":2273,
    "gn:feature_class":"P",
    "gn:feature_code":"PPL",
    "gn:name":"Surkhak Biland\u012b",
    "gn:population":0,
    "gn:timezone":"Asia/Kabul",
    "iso:country":"AF",
    "name:und_x_variant":[
        "Su\u1e5fkhak-belan\u1e0fi",
        "Surkhakbilandi",
        "Surkhak-e Biland\u012b",
        "Sorkhak Boland\u012b",
        "Surkhak Biland\u012b",
        "\u0633\u0631\u062e\u06a9 \u0628\u0644\u0646\u062f\u06cc"
    ],
    "wof:name":"Surkhak Bilandi",
    "wof:placetype":"locality"
},
  "geometry": {"coordinates":[67.98307,34.9959],"type":"Point"}
}