{
  "type": "Feature",
  "properties": {
    "gn:admin1_code":"18",
    "gn:admin2_code":"806",
    "gn:asciiname":"Terelay",
    "gn:country_code":"AF",
    "gn:dem":777,
    "gn:feature_class":"P",
    "gn:feature_code":"PPL",
    "gn:name":"T\u00ear\u0113lay",
    "gn:population":0,
    "gn:timezone":"Asia/Kabul",
    "iso:country":"AF",
    "name:fas_x_preferred":[
        "\u062a\u06cc\u0631\u06cc\u0644\u06cc"
    ],
    "name:und_x_variant":[
        "T\u0113\u1e5f\u0113lay",
        "T\u00ear\u0113lay",
        "\u062a\u0631\u06d0 \u0644\u06cc",
        "Terelay"
    ],
    "wof:name":"Terelay",
    "wof:placetype":"locality"
},
  "geometry": {"coordinates":[70.4211,34.32013],"type":"Point"}
}