{
  "type": "Feature",
  "properties": {
    "gn:admin1_code":"02",
    "gn:admin2_code":"1904",
    "gn:asciiname":"Tanorah",
    "gn:country_code":"AF",
    "gn:dem":1675,
    "gn:feature_class":"P",
    "gn:feature_code":"PPL",
    "gn:name":"Tan\u014drah",
    "gn:population":0,
    "gn:timezone":"Asia/Kabul",
    "iso:country":"AF",
    "name:und_x_variant":[
        "Tan\u014d\u1e5fa",
        "Tan\u016breh",
        "Tan\u014drah",
        "\u062a\u0646\u0648\u0631\u0647"
    ],
    "wof:name":"Tanorah",
    "wof:placetype":"locality"
},
  "geometry": {"coordinates":[64.37052,35.09350999999999],"type":"Point"}
}