{
  "type": "Feature",
  "properties": {
    "gn:admin1_code":"33",
    "gn:admin2_code":"3102.0",
    "gn:asciiname":"Guzar-e Bala",
    "gn:country_code":"AF",
    "gn:dem":1246,
    "gn:feature_class":"P",
    "gn:feature_code":"PPL",
    "gn:name":"Guz\u0304ar-e B\u0101l\u0101",
    "gn:population":0,
    "gn:timezone":"Asia/Kabul",
    "iso:country":"AF",
    "name:und_x_variant":[
        "Guz\u0304ar-e B\u0101l\u0101",
        "\u06af\u0630\u0631 \u0628\u0627\u0644\u0627"
    ],
    "wof:name":"Guzar-e Bala",
    "wof:placetype":"locality"
},
  "geometry": {"coordinates":[66.35104,35.93262],"type":"Point"}
}