{
  "type": "Feature",
  "properties": {
    "gn:admin1_code":"05",
    "gn:admin2_code":"2806",
    "gn:asciiname":"Siyah Qol",
    "gn:country_code":"AF",
    "gn:dem":2775,
    "gn:feature_class":"P",
    "gn:feature_code":"PPL",
    "gn:name":"Siy\u0101h Q\u014dl",
    "gn:population":0,
    "gn:timezone":"Asia/Kabul",
    "iso:country":"AF",
    "name:rus_x_preferred":[
        "Siakhkul\u2019"
    ],
    "name:und_x_variant":[
        "Sy\u0101hq\u014dl",
        "S\u012b\u0101h Q\u014dl",
        "S\u012b\u0101hqowl",
        "Siy\u0101h Q\u014dl",
        "\u0633\u06cc\u0627\u0647 \u0642\u0648\u0644"
    ],
    "wof:name":"Siyah Qol",
    "wof:placetype":"locality"
},
  "geometry": {"coordinates":[66.91988000000001,34.01824000000001],"type":"Point"}
}