{
  "type": "Feature",
  "properties": {
    "gn:admin1_code":"10",
    "gn:admin2_code":"2302.0",
    "gn:asciiname":"Khalifah Anwar Kor",
    "gn:country_code":"AF",
    "gn:dem":793,
    "gn:feature_class":"P",
    "gn:feature_code":"PPL",
    "gn:name":"Khal\u012bfah Anwar K\u014dr",
    "gn:population":0,
    "gn:timezone":"Asia/Kabul",
    "iso:country":"AF",
    "name:fas_x_preferred":[
        "\u062e\u0644\u064a\u0641\u0647 \u0627\u0646\u0648\u0631 \u0643\u0648\u0631"
    ],
    "name:und_x_variant":[
        "Khalifa Anwa\u1e5f K\u014d\u1e5f",
        "Khalifa-Anvar-Kor",
        "Khal\u012bfah Anwar K\u014dr",
        "\u062e\u0644\u0641\u0647 \u0627\u0646\u0648\u0631 \u06a9\u0648\u0631",
        "Khal\u012bfeh Anvar Kowr"
    ],
    "wof:name":"Khalifah Anwar Kor",
    "wof:placetype":"locality"
},
  "geometry": {"coordinates":[64.39388000000001,31.69753],"type":"Point"}
}