{
  "type": "Feature",
  "properties": {
    "gn:admin1_code":"11",
    "gn:admin2_code":"2013",
    "gn:asciiname":"Takht-e Shah",
    "gn:country_code":"AF",
    "gn:dem":2429,
    "gn:feature_class":"P",
    "gn:feature_code":"PPL",
    "gn:name":"Takht-e Sh\u0101h",
    "gn:population":0,
    "gn:timezone":"Asia/Kabul",
    "iso:country":"AF",
    "name:und_x_variant":[
        "Takhte \u0160\u0101h",
        "T\u0101t\u1e5f\u0101n",
        "Takhti-Shakh",
        "Takht-e Sh\u0101h",
        "\u062b\u062e\u062a \u0634\u0627\u0647",
        "T\u0101tr\u0101n",
        "\u062a\u0627\u062a\u0631\u0627\u0646"
    ],
    "wof:name":"Takht-e Shah",
    "wof:placetype":"locality"
},
  "geometry": {"coordinates":[63.25706,33.74261],"type":"Point"}
}