{
  "type": "Feature",
  "properties": {
    "gn:admin1_code":"30",
    "gn:admin2_code":"1614",
    "gn:asciiname":"Qachir",
    "gn:country_code":"AF",
    "gn:dem":412,
    "gn:feature_class":"P",
    "gn:feature_code":"PPL",
    "gn:name":"Qachir",
    "gn:population":0,
    "gn:timezone":"Asia/Kabul",
    "iso:country":"AF",
    "name:rus_x_preferred":[
        "\u041a\u0430\u0447\u0438\u0440"
    ],
    "name:und_x_variant":[
        "Kachir",
        "Qacher",
        "Qachir",
        "\u0642\u0686\u0631"
    ],
    "wof:name":"Qachir",
    "wof:placetype":"locality"
},
  "geometry": {"coordinates":[67.68963000000001,36.72792000000001],"type":"Point"}
}