{
  "type": "Feature",
  "properties": {
    "gn:admin1_code":"41",
    "gn:admin2_code":"3403.0",
    "gn:asciiname":"Tajikan",
    "gn:country_code":"AF",
    "gn:dem":2363,
    "gn:feature_class":"P",
    "gn:feature_code":"PPL",
    "gn:name":"T\u0101jik\u0101n",
    "gn:population":0,
    "gn:timezone":"Asia/Kabul",
    "iso:country":"AF",
    "name:und_x_variant":[
        "T\u0101jik\u0101n",
        "\u062a\u0627\u062c\u06a9\u0627\u0646",
        "Tajek\u0101n"
    ],
    "wof:name":"Tajikan",
    "wof:placetype":"locality"
},
  "geometry": {"coordinates":[66.1978,33.8927],"type":"Point"}
}