{
  "type": "Feature",
  "properties": {
    "gn:admin1_code":"07",
    "gn:admin2_code":"1802",
    "gn:asciiname":"Katah Qal'ah",
    "gn:country_code":"AF",
    "gn:dem":918,
    "gn:feature_class":"P",
    "gn:feature_code":"PPL",
    "gn:name":"Katah Qal\u2018ah",
    "gn:population":0,
    "gn:timezone":"Asia/Kabul",
    "iso:country":"AF",
    "name:und_x_variant":[
        "Kateh Qal\u2018eh",
        "Kata Kala",
        "Kata Qala",
        "Kata Qal\u2018eh",
        "Ka\u1e6fah Qal\u2018eh",
        "Katah Qal\u2018ah",
        "\u06a9\u062a\u0647 \u0642\u0644\u0639\u0647"
    ],
    "wof:name":"Katah Qal'ah",
    "wof:placetype":"locality"
},
  "geometry": {"coordinates":[65.02705,35.91133],"type":"Point"}
}