{
  "type": "Feature",
  "properties": {
    "gn:admin1_code":"02",
    "gn:admin2_code":"1904",
    "gn:asciiname":"Zardabah",
    "gn:country_code":"AF",
    "gn:dem":1633,
    "gn:feature_class":"P",
    "gn:feature_code":"PPL",
    "gn:name":"Zard\u0101bah",
    "gn:population":0,
    "gn:timezone":"Asia/Kabul",
    "iso:country":"AF",
    "name:und_x_variant":[
        "Zardaba",
        "Za\u1e5f\u1e0f\u0101ba",
        "Zard\u0101bah",
        "\u0632\u0631\u062f\u0627\u0628\u0647",
        "Zard\u0101beh"
    ],
    "wof:name":"Zardabah",
    "wof:placetype":"locality"
},
  "geometry": {"coordinates":[63.88501,34.81118],"type":"Point"}
}