{
  "type": "Feature",
  "properties": {
    "gn:admin1_code":"27",
    "gn:admin2_code":"403.0",
    "gn:asciiname":"Altar Ghanagak",
    "gn:country_code":"AF",
    "gn:dem":3288,
    "gn:feature_class":"P",
    "gn:feature_code":"PPL",
    "gn:name":"Altar Ghanagak",
    "gn:population":0,
    "gn:timezone":"Asia/Kabul",
    "iso:country":"AF",
    "name:rus_x_preferred":[
        "Al\u2019targanagak"
    ],
    "name:und_x_variant":[
        "Alta\u1e5fghanagak",
        "Altarghanehgak",
        "Altargh\u0101nahgak",
        "Altar Ghanagak",
        "\u0627\u0644\u062a\u0631 \u063a\u0646\u06af\u06a9"
    ],
    "wof:name":"Altar Ghanagak",
    "wof:placetype":"locality"
},
  "geometry": {"coordinates":[68.322,34.5313],"type":"Point"}
}