{
  "type": "Feature",
  "properties": {
    "gn:admin1_code":"23",
    "gn:admin2_code":"2407",
    "gn:asciiname":"Khik",
    "gn:country_code":"AF",
    "gn:dem":1026,
    "gn:feature_class":"P",
    "gn:feature_code":"PPL",
    "gn:name":"Kh\u012bk",
    "gn:population":0,
    "gn:timezone":"Asia/Kabul",
    "iso:country":"AF",
    "name:und_x_variant":[
        "Kh\u012bk",
        "\u062e\u06cc\u06a9"
    ],
    "wof:name":"Khik",
    "wof:placetype":"locality"
},
  "geometry": {"coordinates":[65.10325,31.73286],"type":"Point"}
}