{
  "type": "Feature",
  "properties": {
    "gn:admin1_code":"05",
    "gn:admin2_code":"2801",
    "gn:asciiname":"Khawal",
    "gn:country_code":"AF",
    "gn:dem":2607,
    "gn:feature_class":"P",
    "gn:feature_code":"PPL",
    "gn:name":"Khaw\u0101l",
    "gn:population":0,
    "gn:timezone":"Asia/Kabul",
    "iso:country":"AF",
    "name:rus_x_preferred":[
        "Khaval\u2019"
    ],
    "name:und_x_variant":[
        "Khav\u0101l",
        "Khaw\u0101l",
        "\u062e\u0648\u0627\u0644"
    ],
    "wof:name":"Khawal",
    "wof:placetype":"locality"
},
  "geometry": {"coordinates":[67.84563,34.78025],"type":"Point"}
}