{
  "type": "Feature",
  "properties": {
    "gn:admin1_code":"5",
    "gn:admin2_code":"2805.0",
    "gn:asciiname":"Biland Bulaq",
    "gn:country_code":"AF",
    "gn:dem":3105,
    "gn:feature_class":"P",
    "gn:feature_code":"PPL",
    "gn:name":"Biland B\u016bl\u0101q",
    "gn:population":0,
    "gn:timezone":"Asia/Kabul",
    "iso:country":"AF",
    "name:und_x_variant":[
        "Belan\u1e0fbol\u0101q",
        "Bilandbulak",
        "Buland Bul\u0101gh",
        "Biland B\u016bl\u0101q",
        "\u0628\u0644\u0646\u062f \u0628\u0648\u0644\u0627\u063a"
    ],
    "wof:name":"Biland Bulaq",
    "wof:placetype":"locality"
},
  "geometry": {"coordinates":[66.55705,34.26851],"type":"Point"}
}