{
  "type": "Feature",
  "properties": {
    "gn:admin1_code":"27",
    "gn:admin2_code":"404.0",
    "gn:asciiname":"Jowpalal",
    "gn:country_code":"AF",
    "gn:dem":3563,
    "gn:feature_class":"P",
    "gn:feature_code":"PPL",
    "gn:name":"Jowpal\u0101l",
    "gn:population":0,
    "gn:timezone":"Asia/Kabul",
    "iso:country":"AF",
    "name:und_x_variant":[
        "Jowpal\u0101l",
        "Jawpal\u0101l",
        "\u062c\u0648\u067e\u0644\u0627\u0644"
    ],
    "wof:name":"Jowpalal",
    "wof:placetype":"locality"
},
  "geometry": {"coordinates":[67.73266,34.60775],"type":"Point"}
}