{
  "type": "Feature",
  "properties": {
    "gn:admin1_code":"8",
    "gn:admin2_code":"606.0",
    "gn:asciiname":"Qal'ah-ye Nawerquzi",
    "gn:country_code":"AF",
    "gn:dem":2888,
    "gn:feature_class":"P",
    "gn:feature_code":"PPL",
    "gn:name":"Qal\u2018ah-ye N\u0101w\u00earq\u016bz\u012b",
    "gn:population":0,
    "gn:timezone":"Asia/Kabul",
    "iso:country":"AF",
    "name:und_x_variant":[
        "Qal\u2018ah-ye N\u0101w\u00earq\u016bz\u012b",
        "\u0642\u0644\u0639\u06c0 \u0646\u0627\u0648\u0631\u0642\u0648\u0632\u06cc",
        "Qal\u0101y N\u0101we\u1e5fq\u016bzi"
    ],
    "wof:name":"Qal'ah-ye Nawerquzi",
    "wof:placetype":"locality"
},
  "geometry": {"coordinates":[67.34605000000001,33.42886],"type":"Point"}
}