{
  "type": "Feature",
  "properties": {
    "gn:admin1_code":"32",
    "gn:admin2_code":"1505",
    "gn:asciiname":"Shorqul",
    "gn:country_code":"AF",
    "gn:dem":2851,
    "gn:feature_class":"P",
    "gn:feature_code":"PPL",
    "gn:name":"Sh\u014drqul",
    "gn:population":0,
    "gn:timezone":"Asia/Kabul",
    "iso:country":"AF",
    "name:und_x_variant":[
        "Sh\u014drqul",
        "S\u014d\u1e5fqul",
        "Sh\u016br Qowl",
        "\u0634\u0648\u0631\u0642\u0644"
    ],
    "wof:name":"Shorqul",
    "wof:placetype":"locality"
},
  "geometry": {"coordinates":[67.94644,35.54909],"type":"Point"}
}