{
  "type": "Feature",
  "properties": {
    "gn:admin1_code":"19",
    "gn:admin2_code":"2202.0",
    "gn:asciiname":"Sayyid Ibrahim Shah",
    "gn:country_code":"AF",
    "gn:dem":483,
    "gn:feature_class":"P",
    "gn:feature_code":"PPL",
    "gn:name":"Sayyid Ibr\u0101h\u012bm Sh\u0101h",
    "gn:population":0,
    "gn:timezone":"Asia/Kabul",
    "iso:country":"AF",
    "name:und_x_variant":[
        "Sayyid Ibr\u0101h\u012bm Sh\u0101h",
        "Seyyed Ebr\u0101h\u012bm Sh\u0101h"
    ],
    "wof:name":"Sayyid Ibrahim Shah",
    "wof:placetype":"locality"
},
  "geometry": {"coordinates":[61.88944,31.10944000000001],"type":"Point"}
}