{
  "type": "Feature",
  "properties": {
    "gn:admin1_code":"8",
    "gn:admin2_code":"617.0",
    "gn:asciiname":"Chahar Qal'ah",
    "gn:country_code":"AF",
    "gn:dem":2793,
    "gn:feature_class":"P",
    "gn:feature_code":"PPL",
    "gn:name":"Chah\u0101r Qal\u2018ah",
    "gn:population":0,
    "gn:timezone":"Asia/Kabul",
    "iso:country":"AF",
    "name:fas_x_preferred":[
        "\u0686\u0627\u0631 \u0642\u0644\u0639\u0647"
    ],
    "name:und_x_variant":[
        "\u010c\u0101rqal\u2018a",
        "Charkala",
        "Chah\u0101r Qal\u2018ah",
        "Ch\u0101r Qal\u2018eh",
        "\u0686\u0647\u0627\u0631 \u0642\u0644\u0639\u0647"
    ],
    "wof:name":"Chahar Qal'ah",
    "wof:placetype":"locality"
},
  "geometry": {"coordinates":[68.14282,33.76545],"type":"Point"}
}