{
  "type": "Feature",
  "properties": {
    "gn:admin1_code":"01",
    "gn:admin2_code":"1113",
    "gn:asciiname":"Paytow",
    "gn:country_code":"AF",
    "gn:dem":1685,
    "gn:feature_class":"P",
    "gn:feature_code":"PPL",
    "gn:name":"Paytow",
    "gn:population":0,
    "gn:timezone":"Asia/Kabul",
    "iso:country":"AF",
    "name:und_x_variant":[
        "P\u012bt\u0101v",
        "P\u0113t\u0101w",
        "P\u0113t\u0101v",
        "Paytow",
        "\u067e\u06cc\u062a\u0648"
    ],
    "wof:name":"Paytow",
    "wof:placetype":"locality"
},
  "geometry": {"coordinates":[70.16490999999999,37.30618],"type":"Point"}
}