{
  "type": "Feature",
  "properties": {
    "gn:admin1_code":"6",
    "gn:admin2_code":"2104.0",
    "gn:asciiname":"Astanah",
    "gn:country_code":"AF",
    "gn:dem":1680,
    "gn:feature_class":"P",
    "gn:feature_code":"PPL",
    "gn:name":"Ast\u0101nah",
    "gn:population":0,
    "gn:timezone":"Asia/Kabul",
    "iso:country":"AF",
    "name:und_x_variant":[
        "Astana",
        "Ast\u0101na",
        "Ast\u0101nah",
        "\u0627\u0633\u062a\u0627\u0646\u0647",
        "\u0100st\u0101neh"
    ],
    "wof:name":"Astanah",
    "wof:placetype":"locality"
},
  "geometry": {"coordinates":[63.27455,33.48683],"type":"Point"}
}