{
  "type": "Feature",
  "properties": {
    "gn:admin1_code":"28",
    "gn:admin2_code":"2501",
    "gn:asciiname":"Qanat-e Barakzai",
    "gn:country_code":"AF",
    "gn:dem":1830,
    "gn:feature_class":"P",
    "gn:feature_code":"PPL",
    "gn:name":"Qan\u0101t-e B\u0101rakza\u012b",
    "gn:population":0,
    "gn:timezone":"Asia/Kabul",
    "iso:country":"AF",
    "name:fas_x_preferred":[
        "\u0642\u0646\u0627\u062a\u0654 \u0628\u0631\u0643\u0632\u06cc"
    ],
    "name:und_x_variant":[
        "Kanati-Barakzay",
        "Qan\u0101t-e B\u0101rakza\u012b",
        "\u0642\u0646\u0627\u062a \u0628\u0627\u0631\u06a9\u0632\u06cc",
        "Qan\u0101t-e Barakzay"
    ],
    "wof:name":"Qanat-e Barakzai",
    "wof:placetype":"locality"
},
  "geometry": {"coordinates":[67.22904,32.22056],"type":"Point"}
}