{
  "type": "Feature",
  "properties": {
    "gn:admin1_code":"34",
    "gn:admin2_code":"1002.0",
    "gn:asciiname":"Belah Wan",
    "gn:country_code":"AF",
    "gn:dem":1226,
    "gn:feature_class":"P",
    "gn:feature_code":"PPL",
    "gn:name":"B\u0113lah W\u0101n",
    "gn:population":0,
    "gn:timezone":"Asia/Kabul",
    "iso:country":"AF",
    "name:fas_x_preferred":[
        "\u0628\u064a\u0644\u0648\u0627\u0646"
    ],
    "name:und_x_variant":[
        "Belavan",
        "B\u0113law\u0101n",
        "B\u0113lah W\u0101n",
        "\u0628\u06d0\u0644\u0647 \u0648\u0627\u0646"
    ],
    "wof:name":"Belah Wan",
    "wof:placetype":"locality"
},
  "geometry": {"coordinates":[71.23595,34.87454],"type":"Point"}
}