{
  "type": "Feature",
  "properties": {
    "gn:admin1_code":"8",
    "gn:admin2_code":"607.0",
    "gn:asciiname":"Chihil Baghtuy Uqi",
    "gn:country_code":"AF",
    "gn:dem":3192,
    "gn:feature_class":"P",
    "gn:feature_code":"PPL",
    "gn:name":"Chihil B\u0101ght\u016by \u016aq\u012b",
    "gn:population":0,
    "gn:timezone":"Asia/Kabul",
    "iso:country":"AF",
    "name:und_x_variant":[
        "Cehelb\u0101ght\u016by \u016aqi",
        "Chehel B\u0101ght\u016by \u016aqi",
        "Chihil B\u0101ght\u016by \u016aq\u012b",
        "\u0686\u0647\u0644 \u0628\u0627\u063a\u062a\u0648\u06cc \u0627\u0648\u0642\u06cc"
    ],
    "wof:name":"Chihil Baghtuy Uqi",
    "wof:placetype":"locality"
},
  "geometry": {"coordinates":[67.24681,33.14973],"type":"Point"}
}