{
  "type": "Feature",
  "properties": {
    "gn:admin1_code":"23",
    "gn:admin2_code":"2411.0",
    "gn:asciiname":"Ghows Muhammad",
    "gn:country_code":"AF",
    "gn:dem":1222,
    "gn:feature_class":"P",
    "gn:feature_code":"PPL",
    "gn:name":"Ghows\u0304 Mu\u1e29ammad",
    "gn:population":0,
    "gn:timezone":"Asia/Kabul",
    "iso:country":"AF",
    "name:und_x_variant":[
        "Gaushmukhammed",
        "Ghaws\u0304 Mu\u1e29ammad",
        "\u063a\u0648\u062b \u0645\u062d\u0645\u062f",
        "Ghawsmo\u1e29ammad",
        "Ghows\u0304 Mu\u1e29ammad"
    ],
    "wof:name":"Ghows Muhammad",
    "wof:placetype":"locality"
},
  "geometry": {"coordinates":[66.39107,31.04292],"type":"Point"}
}