{
  "type": "Feature",
  "properties": {
    "gn:admin1_code":"26",
    "gn:admin2_code":"1204",
    "gn:asciiname":"Khanaqah",
    "gn:country_code":"AF",
    "gn:dem":1378,
    "gn:feature_class":"P",
    "gn:feature_code":"PPLA2",
    "gn:name":"Kh\u0101naq\u0101h",
    "gn:population":0,
    "gn:timezone":"Asia/Kabul",
    "iso:country":"AF",
    "name:fas_x_preferred":[
        "\u062e\u0627\u0646\u0647\u0642\u0627\u0647"
    ],
    "name:rus_x_preferred":[
        "\u0425\u0430\u043d\u0430\u043a\u0430"
    ],
    "name:und_x_variant":[
        "Khanaka",
        "Kh\u0101naq\u0101",
        "Kh\u0101neq\u0101",
        "Kh\u0101neg\u0101",
        "Kh\u0101nehq\u0101h",
        "Kh\u0101naq\u0101h",
        "\u062e\u0627\u0646\u0642\u0627\u0647"
    ],
    "wof:name":"Khanaqah",
    "wof:placetype":"locality"
},
  "geometry": {"coordinates":[69.53695,36.62587],"type":"Point"}
}