{
  "type": "Feature",
  "properties": {
    "gn:admin1_code":"08",
    "gn:admin2_code":"607",
    "gn:asciiname":"Qal'ah-ye Wakil",
    "gn:country_code":"AF",
    "gn:dem":2606,
    "gn:feature_class":"P",
    "gn:feature_code":"PPL",
    "gn:name":"Qal\u2018ah-ye Wak\u012bl",
    "gn:population":0,
    "gn:timezone":"Asia/Kabul",
    "iso:country":"AF",
    "name:fas_x_preferred":[
        "\u0642\u0644\u0639\u0647\u0654 \u0648\u0643\u064a\u0644"
    ],
    "name:rus_x_preferred":[
        "\u041a\u0430\u043b\u0430\u0439\u0438-\u0412\u0430\u043a\u0438\u043b\u044c"
    ],
    "name:und_x_variant":[
        "Kalayi-Vakil\u2019",
        "Qal\u2018a-i-Wak\u012bl",
        "Qal\u2018eh-ye Vak\u012bl",
        "Qal\u2018ah-ye Wak\u012bl",
        "\u0642\u0644\u0639\u06c0 \u0648\u06a9\u06cc\u0644",
        "\u0642\u0644\u0639\u0647\u0654 \u0648\u0643\u064a\u0644"
    ],
    "wof:name":"Qal'ah-ye Wakil",
    "wof:placetype":"locality"
},
  "geometry": {"coordinates":[67.60204,33.01701],"type":"Point"}
}