{
  "type": "Feature",
  "properties": {
    "gn:admin1_code":"40",
    "gn:admin2_code":"304",
    "gn:asciiname":"Malang",
    "gn:country_code":"AF",
    "gn:dem":2699,
    "gn:feature_class":"P",
    "gn:feature_code":"PPL",
    "gn:name":"Malang",
    "gn:population":0,
    "gn:timezone":"Asia/Kabul",
    "iso:country":"AF",
    "name:und_x_variant":[
        "\u0645\u0644\u0646\u06af"
    ],
    "wof:name":"Malang",
    "wof:placetype":"locality"
},
  "geometry": {"coordinates":[69.03948000000001,35.16558],"type":"Point"}
}