{
  "type": "Feature",
  "properties": {
    "gn:admin1_code":"40",
    "gn:admin2_code":"304",
    "gn:asciiname":"Malang",
    "gn:country_code":"AF",
    "gn:dem":2699,
    "gn:feature_class":"P",
    "gn:feature_code":"PPL",
    "gn:name":"Malang",
    "gn:population":0,
    "gn:timezone":"Asia/Kabul",
    "iso:country":"AF",
    "name:afr_x_preferred":[
        "Malang"
    ],
    "name:ara_x_preferred":[
        "\u0645\u0627\u0644\u0627\u0646\u063a"
    ],
    "name:azb_x_preferred":[
        "\u0645\u0627\u0644\u0627\u0646\u06af"
    ],
    "name:bul_x_preferred":[
        "\u041c\u0430\u043b\u0430\u043d\u0433"
    ],
    "name:ceb_x_preferred":[
        "Malang"
    ],
    "name:ces_x_preferred":[
        "Malang"
    ],
    "name:che_x_preferred":[
        "\u041c\u0430\u043b\u0430\u043d\u0433"
    ],
    "name:deu_x_preferred":[
        "Malang"
    ],
    "name:epo_x_preferred":[
        "Malang"
    ],
    "name:fas_x_preferred":[
        "\u0645\u0627\u0644\u0646\u06af"
    ],
    "name:fin_x_preferred":[
        "Malang"
    ],
    "name:fra_x_preferred":[
        "Malang"
    ],
    "name:gor_x_preferred":[
        "Kota Malang"
    ],
    "name:hun_x_preferred":[
        "Malang"
    ],
    "name:hye_x_preferred":[
        "\u0544\u0561\u056c\u0561\u0576\u0563"
    ],
    "name:ind_x_preferred":[
        "Kota Malang"
    ],
    "name:ita_x_preferred":[
        "Malang"
    ],
    "name:jav_x_preferred":[
        "Kutha Malang"
    ],
    "name:jpn_x_preferred":[
        "\u30de\u30e9\u30f3"
    ],
    "name:kat_x_preferred":[
        "\u10db\u10d0\u10da\u10d0\u10dc\u10d2\u10d8"
    ],
    "name:lit_x_preferred":[
        "Malangas"
    ],
    "name:mal_x_preferred":[
        "\u0d2e\u0d46\u0d32\u0d19\u0d4d\u0d19\u0d4d"
    ],
    "name:mlg_x_preferred":[
        "Kota Malang"
    ],
    "name:msa_x_preferred":[
        "Malang"
    ],
    "name:nld_x_preferred":[
        "Malang"
    ],
    "name:nno_x_preferred":[
        "Malang"
    ],
    "name:nor_x_preferred":[
        "Malang"
    ],
    "name:pol_x_preferred":[
        "Malang"
    ],
    "name:por_x_preferred":[
        "Malang"
    ],
    "name:ron_x_preferred":[
        "Malang"
    ],
    "name:rus_x_preferred":[
        "\u041c\u0430\u043b\u0430\u043d\u0433"
    ],
    "name:spa_x_preferred":[
        "Malang"
    ],
    "name:sqi_x_preferred":[
        "Malang"
    ],
    "name:sun_x_preferred":[
        "Kota Malang"
    ],
    "name:swe_x_preferred":[
        "Malang"
    ],
    "name:tam_x_preferred":[
        "\u0bae\u0bb2\u0bbe\u0b99\u0bcd"
    ],
    "name:tur_x_preferred":[
        "Malang"
    ],
    "name:ukr_x_preferred":[
        "\u041c\u0430\u043b\u0430\u043d\u0433"
    ],
    "name:und_x_variant":[
        "\u0645\u0644\u0646\u06af"
    ],
    "name:urd_x_preferred":[
        "\u0645\u0627\u0644\u0627\u0646\u06af"
    ],
    "name:vie_x_preferred":[
        "Malang"
    ],
    "name:war_x_preferred":[
        "Malang"
    ],
    "wof:name":"Malang",
    "wof:placetype":"locality"
},
  "geometry": {"coordinates":[69.03948000000001,35.16558],"type":"Point"}
}