{
  "type": "Feature",
  "properties": {
    "gn:admin1_code":"11",
    "gn:admin2_code":"2003.0",
    "gn:asciiname":"Kalatah",
    "gn:country_code":"AF",
    "gn:dem":905,
    "gn:feature_class":"P",
    "gn:feature_code":"PPL",
    "gn:name":"Kal\u0101tah",
    "gn:population":0,
    "gn:timezone":"Asia/Kabul",
    "iso:country":"AF",
    "name:und_x_variant":[
        "Kalata",
        "Kal\u0101tah",
        "\u06a9\u0644\u0627\u062a\u0647",
        "Kal\u0101teh"
    ],
    "wof:name":"Kalatah",
    "wof:placetype":"locality"
},
  "geometry": {"coordinates":[62.05983000000001,34.28592],"type":"Point"}
}