{
  "type": "Feature",
  "properties": {
    "gn:admin1_code":"11",
    "gn:admin2_code":"2003.0",
    "gn:asciiname":"Bedam",
    "gn:country_code":"AF",
    "gn:dem":1149,
    "gn:feature_class":"P",
    "gn:feature_code":"PPL",
    "gn:name":"Bedam",
    "gn:population":0,
    "gn:timezone":"Asia/Kabul",
    "iso:country":"AF",
    "name:und_x_variant":[
        "Bed\u0101\u2019\u012b",
        "Bid\u0101\u2019\u012b",
        "\u0628\u062f\u0627\u0626\u06cc"
    ],
    "wof:name":"Bedam",
    "wof:placetype":"locality"
},
  "geometry": {"coordinates":[62.35966,34.14771],"type":"Point"}
}