{
  "type": "Feature",
  "properties": {
    "gn:admin1_code":"5",
    "gn:admin2_code":"2804.0",
    "gn:asciiname":"Chihil Burj",
    "gn:country_code":"AF",
    "gn:dem":2377,
    "gn:feature_class":"P",
    "gn:feature_code":"PPL",
    "gn:name":"Chihil Burj",
    "gn:population":0,
    "gn:timezone":"Asia/Kabul",
    "iso:country":"AF",
    "name:rus_x_preferred":[
        "Chekhil\u2019burdzh"
    ],
    "name:und_x_variant":[
        "\u010cehelburi",
        "Chihil Burj",
        "Chehelborj",
        "Chehel Burj",
        "\u0686\u0647\u0644 \u0628\u0631\u062c"
    ],
    "wof:name":"Chihil Burj",
    "wof:placetype":"locality"
},
  "geometry": {"coordinates":[66.61754999999999,34.91805],"type":"Point"}
}