{
  "type": "Feature",
  "properties": {
    "gn:admin1_code":"11",
    "gn:admin2_code":"2013",
    "gn:asciiname":"Shing-e Mabayn",
    "gn:country_code":"AF",
    "gn:dem":2372,
    "gn:feature_class":"P",
    "gn:feature_code":"PPL",
    "gn:name":"Shing-e M\u0101bayn",
    "gn:population":0,
    "gn:timezone":"Asia/Kabul",
    "iso:country":"AF",
    "name:und_x_variant":[
        "\u0160enge M\u0101bayn",
        "Shingi-Mabayn",
        "Sheng-e M\u0101beyn",
        "Shing-e M\u0101bayn",
        "\u0634\u0646\u06af \u0645\u0627\u0628\u06cc\u0646",
        "Shing-e M\u0101bay\u0101n",
        "\u0634\u0646\u06af \u0645\u0627\u0628\u06cc\u0627\u0646"
    ],
    "wof:name":"Shing-e Mabayn",
    "wof:placetype":"locality"
},
  "geometry": {"coordinates":[63.37664,33.99923],"type":"Point"}
}