{
  "type": "Feature",
  "properties": {
    "gn:admin1_code":"33",
    "gn:admin2_code":"3103",
    "gn:asciiname":"Jahi",
    "gn:country_code":"AF",
    "gn:dem":2633,
    "gn:feature_class":"P",
    "gn:feature_code":"PPL",
    "gn:name":"Jah\u012b",
    "gn:population":0,
    "gn:timezone":"Asia/Kabul",
    "iso:country":"AF",
    "name:fas_x_preferred":[
        "\u062c\u0647\u06cc"
    ],
    "name:jpn_x_preferred":[
        "\u30b8\u30e3\u30d2\u30fc"
    ],
    "name:und_x_variant":[
        "Jah\u012b",
        "Jahi"
    ],
    "wof:name":"Jahi",
    "wof:placetype":"locality"
},
  "geometry": {"coordinates":[65.96265,35.29913],"type":"Point"}
}