{
  "type": "Feature",
  "properties": {
    "gn:admin1_code":"28",
    "gn:admin2_code":"2501",
    "gn:asciiname":"Mushmani",
    "gn:country_code":"AF",
    "gn:dem":1848,
    "gn:feature_class":"P",
    "gn:feature_code":"PPL",
    "gn:name":"M\u016bshm\u0101n\u012b",
    "gn:population":0,
    "gn:timezone":"Asia/Kabul",
    "iso:country":"AF",
    "name:und_x_variant":[
        "M\u016b\u0161m\u0101ni",
        "M\u016bshm\u0101n\u012b",
        "\u0645\u0648\u0634\u0645\u0627\u0646\u06cc"
    ],
    "wof:name":"Mushmani",
    "wof:placetype":"locality"
},
  "geometry": {"coordinates":[67.24883,32.2412],"type":"Point"}
}