{
  "type": "Feature",
  "properties": {
    "gn:admin1_code":"5",
    "gn:admin2_code":"2805.0",
    "gn:asciiname":"Dahan-e Ab Darah",
    "gn:country_code":"AF",
    "gn:dem":2764,
    "gn:feature_class":"P",
    "gn:feature_code":"PPL",
    "gn:name":"Dahan-e \u0100b Darah",
    "gn:population":0,
    "gn:timezone":"Asia/Kabul",
    "iso:country":"AF",
    "name:und_x_variant":[
        "Dakhani-Avdara",
        "Dahan-e \u0100wdarreh",
        "\u1e0eahane \u0100w\u1e0fa\u1e5fa",
        "Dahan-e \u0100bdarreh",
        "Dahan-e \u0100w Darah",
        "Dahan-e \u0100b Darah",
        "\u062f\u0647\u0646 \u0622\u0628 \u062f\u0631\u0647"
    ],
    "wof:name":"Dahan-e Ab Darah",
    "wof:placetype":"locality"
},
  "geometry": {"coordinates":[66.99585,34.38942],"type":"Point"}
}