{
  "type": "Feature",
  "properties": {
    "gn:admin1_code":"08",
    "gn:admin2_code":"604",
    "gn:asciiname":"Tukrik",
    "gn:country_code":"AF",
    "gn:dem":3344,
    "gn:feature_class":"P",
    "gn:feature_code":"PPL",
    "gn:name":"T\u016bkr\u012bk",
    "gn:population":0,
    "gn:timezone":"Asia/Kabul",
    "iso:country":"AF",
    "name:und_x_variant":[
        "T\u016bkr\u012bk",
        "\u062a\u0648\u06a9\u0631\u064a\u06a9",
        "Tukrik"
    ],
    "wof:name":"Tukrik",
    "wof:placetype":"locality"
},
  "geometry": {"coordinates":[68.01651,33.79802],"type":"Point"}
}