{
  "type": "Feature",
  "properties": {
    "gn:admin1_code":"17",
    "gn:admin2_code":"503.0",
    "gn:asciiname":"Ziya ud Din",
    "gn:country_code":"AF",
    "gn:dem":1952,
    "gn:feature_class":"P",
    "gn:feature_code":"PPL",
    "gn:name":"\u1e94iy\u0101 ud D\u012bn",
    "gn:population":0,
    "gn:timezone":"Asia/Kabul",
    "iso:country":"AF",
    "name:und_x_variant":[
        "Ziavuddin",
        "\u1e0e\u1e95y\u0101wu\u1e0f\u1e0f\u012bn",
        "\u1e94iy\u0101 u\u1e0f D\u012bn",
        "Dzy\u0101b od D\u012bn",
        "\u1e94iy\u0101 ud D\u012bn",
        "\u0636\u064a\u0627 \u0627\u0644\u062f\u064a\u0646"
    ],
    "wof:name":"Ziya ud Din",
    "wof:placetype":"locality"
},
  "geometry": {"coordinates":[68.94344,33.92375999999999],"type":"Point"}
}