{
  "type": "Feature",
  "properties": {
    "gn:admin1_code":"3",
    "gn:admin2_code":"1303.0",
    "gn:asciiname":"Tsinzai",
    "gn:country_code":"AF",
    "gn:dem":593,
    "gn:feature_class":"P",
    "gn:feature_code":"PPL",
    "gn:name":"Ts\u012bnza\u012b",
    "gn:population":0,
    "gn:timezone":"Asia/Kabul",
    "iso:country":"AF",
    "name:und_x_variant":[
        "Chinzai",
        "C\u012bnza\u2019i",
        "Ch\u012bnzay",
        "Ts\u012bnza\u012b",
        "\u0685\u06cc\u0646\u0632\u06cc"
    ],
    "wof:name":"Tsinzai",
    "wof:placetype":"locality"
},
  "geometry": {"coordinates":[68.58354,35.98927],"type":"Point"}
}