{
  "type": "Feature",
  "properties": {
    "gn:admin1_code":"08",
    "gn:admin2_code":"610",
    "gn:asciiname":"Wuli Khel",
    "gn:country_code":"AF",
    "gn:dem":2044,
    "gn:feature_class":"P",
    "gn:feature_code":"PPL",
    "gn:name":"Wul\u012b Kh\u0113l",
    "gn:population":0,
    "gn:timezone":"Asia/Kabul",
    "iso:country":"AF",
    "name:und_x_variant":[
        "Vulikheyl\u2019",
        "Wolikh\u0113l",
        "Wul\u012b Kh\u0113l",
        "\u0648\u0644\u06cc \u062e\u06d0\u0644",
        "Wol\u012b Kheyl"
    ],
    "wof:name":"Wuli Khel",
    "wof:placetype":"locality"
},
  "geometry": {"coordinates":[67.97044,32.30494],"type":"Point"}
}