{
  "type": "Feature",
  "properties": {
    "gn:admin1_code":"10",
    "gn:admin2_code":"2305",
    "gn:asciiname":"Kalan Joy",
    "gn:country_code":"AF",
    "gn:dem":1651,
    "gn:feature_class":"P",
    "gn:feature_code":"PPL",
    "gn:name":"Kal\u0101n J\u014dy",
    "gn:population":0,
    "gn:timezone":"Asia/Kabul",
    "iso:country":"AF",
    "name:fas_x_preferred":[
        "\u0643\u0644\u0627\u0646 \u062c\u0648\u06cc"
    ],
    "name:rus_x_preferred":[
        "\u041a\u0430\u043b\u0430\u043d\u0434\u0436\u043e\u0439"
    ],
    "name:und_x_variant":[
        "Kal\u0101n J\u014dy",
        "Kalandzhoy",
        "\u06a9\u0644\u0627\u0646 \u062c\u0648\u06cc",
        "Kal\u0101nj\u016by"
    ],
    "wof:name":"Kalan Joy",
    "wof:placetype":"locality"
},
  "geometry": {"coordinates":[65.12702,33.17636],"type":"Point"}
}