{
  "type": "Feature",
  "properties": {
    "gn:admin1_code":"09",
    "gn:admin2_code":"2706",
    "gn:asciiname":"Ghoweh",
    "gn:country_code":"AF",
    "gn:dem":2374,
    "gn:feature_class":"P",
    "gn:feature_code":"PPL",
    "gn:name":"Ghow\u00eah",
    "gn:population":0,
    "gn:timezone":"Asia/Kabul",
    "iso:country":"AF",
    "name:und_x_variant":[
        "Ghow\u00eah",
        "\u063a\u0648\u0647",
        "Ghawe"
    ],
    "wof:name":"Ghoweh",
    "wof:placetype":"locality"
},
  "geometry": {"coordinates":[65.39899,33.6392],"type":"Point"}
}