{
  "type": "Feature",
  "properties": {
    "gn:admin1_code":"29",
    "gn:admin2_code":"2905.0",
    "gn:asciiname":"Akhtar Dad",
    "gn:country_code":"AF",
    "gn:dem":2270,
    "gn:feature_class":"P",
    "gn:feature_code":"PPL",
    "gn:name":"Akhtar D\u0101d",
    "gn:population":0,
    "gn:timezone":"Asia/Kabul",
    "iso:country":"AF",
    "name:fas_x_preferred":[
        "\u0627\u062e\u062a\u0631\u062f\u0627\u062f"
    ],
    "name:und_x_variant":[
        "Akhtardad",
        "Akhtar D\u0101d"
    ],
    "wof:name":"Akhtar Dad",
    "wof:placetype":"locality"
},
  "geometry": {"coordinates":[68.59824999999999,32.16701],"type":"Point"}
}