{
  "type": "Feature",
  "properties": {
    "gn:admin1_code":"34",
    "gn:admin2_code":"1013",
    "gn:asciiname":"Gaziabad",
    "gn:country_code":"AF",
    "gn:dem":1289,
    "gn:feature_class":"P",
    "gn:feature_code":"PPL",
    "gn:name":"Gaziabad",
    "gn:population":0,
    "gn:timezone":"Asia/Kabul",
    "iso:country":"AF",
    "name:und_x_variant":[
        "Gh\u0101z\u012b\u0101b\u0101d",
        "\u063a\u0627\u0632\u06cc \u0622\u0628\u0627\u062f"
    ],
    "wof:name":"Gaziabad",
    "wof:placetype":"locality"
},
  "geometry": {"coordinates":[70.76405,34.71581],"type":"Point"}
}