{
  "type": "Feature",
  "properties": {
    "gn:admin1_code":"35",
    "gn:admin2_code":"904.0",
    "gn:asciiname":"Angus",
    "gn:country_code":"AF",
    "gn:dem":2218,
    "gn:feature_class":"P",
    "gn:feature_code":"PPL",
    "gn:name":"Ang\u016bs",
    "gn:population":0,
    "gn:timezone":"Asia/Kabul",
    "iso:country":"AF",
    "name:und_x_variant":[
        "Ang\u016bs",
        "\u0627\u0646\u06af\u0648\u0633"
    ],
    "wof:name":"Angus",
    "wof:placetype":"locality"
},
  "geometry": {"coordinates":[70.14129,35.0135],"type":"Point"}
}