{
  "type": "Feature",
  "properties": {
    "gn:admin1_code":"39",
    "gn:admin2_code":"2603",
    "gn:asciiname":"Kaji Khar Bayd",
    "gn:country_code":"AF",
    "gn:dem":2153,
    "gn:feature_class":"P",
    "gn:feature_code":"PPL",
    "gn:name":"Kaj\u012b Khar Bayd",
    "gn:population":0,
    "gn:timezone":"Asia/Kabul",
    "iso:country":"AF",
    "name:und_x_variant":[
        "Kaj\u012b Kha\u1e5fb\u0113\u1e0f",
        "Kaj\u012b Khar Bayd",
        "\u06a9\u062c\u06cc \u062e\u0631 \u0628\u06cc\u062f",
        "K\u0101j\u012b Kharb\u012bd"
    ],
    "wof:name":"Kaji Khar Bayd",
    "wof:placetype":"locality"
},
  "geometry": {"coordinates":[66.72843,33.03888],"type":"Point"}
}