{
  "type": "Feature",
  "properties": {
    "gn:admin1_code":"27",
    "gn:admin2_code":"408.0",
    "gn:asciiname":"Barah Kushtah",
    "gn:country_code":"AF",
    "gn:dem":2639,
    "gn:feature_class":"P",
    "gn:feature_code":"PPL",
    "gn:name":"Barah Kushtah",
    "gn:population":0,
    "gn:timezone":"Asia/Kabul",
    "iso:country":"AF",
    "name:und_x_variant":[
        "Baraku\u0161ta",
        "Barakoshteh",
        "Barah K\u00eashtah",
        "Barakushta",
        "B\u0101rehkoshteh",
        "Barah Kushtah",
        "\u0628\u0631\u0647 \u06a9\u0634\u062a\u0647"
    ],
    "wof:name":"Barah Kushtah",
    "wof:placetype":"locality"
},
  "geometry": {"coordinates":[68.68533000000001,34.30096],"type":"Point"}
}