{
  "type": "Feature",
  "properties": {
    "gn:admin1_code":"11",
    "gn:admin2_code":"2005",
    "gn:asciiname":"Sakhiri-ye 'Ulya",
    "gn:country_code":"AF",
    "gn:dem":1629,
    "gn:feature_class":"P",
    "gn:feature_code":"PPL",
    "gn:name":"S\u0101khir\u012b-ye \u2018Uly\u0101",
    "gn:population":0,
    "gn:timezone":"Asia/Kabul",
    "iso:country":"AF",
    "name:und_x_variant":[
        "S\u0101khe\u1e5fi \u2018Uly\u0101",
        "S\u0101khir\u012b-ye \u2018Uly\u0101",
        "\u0633\u0627\u062e\u0631\u06cc \u0639\u0644\u06cc\u0627",
        "S\u0101kher\u012b \u2018Oly\u0101",
        "Baydak",
        "\u0628\u06cc\u062f\u06a9"
    ],
    "wof:name":"Sakhiri-ye 'Ulya",
    "wof:placetype":"locality"
},
  "geometry": {"coordinates":[62.62074000000001,34.56553],"type":"Point"}
}