{
  "type": "Feature",
  "properties": {
    "gn:admin1_code":"01",
    "gn:admin2_code":"1128.0",
    "gn:asciiname":"Kham-e Elchah",
    "gn:country_code":"AF",
    "gn:dem":1954,
    "gn:feature_class":"P",
    "gn:feature_code":"PPL",
    "gn:name":"Kham-e \u0112lchah",
    "gn:population":0,
    "gn:timezone":"Asia/Kabul",
    "iso:country":"AF",
    "name:und_x_variant":[
        "Kham-i-\u0112l\u010da",
        "Kham-e \u0112lchah",
        "\u062e\u0645 \u0627\u06d0\u0644\u0686\u0647"
    ],
    "wof:name":"Kham-e Elchah",
    "wof:placetype":"locality"
},
  "geometry": {"coordinates":[70.42231,37.52546],"type":"Point"}
}