{
  "type": "Feature",
  "properties": {
    "gn:admin1_code":"26",
    "gn:admin2_code":"1209.0",
    "gn:asciiname":"Rabat-e Gardan",
    "gn:country_code":"AF",
    "gn:dem":1966,
    "gn:feature_class":"P",
    "gn:feature_code":"PPL",
    "gn:name":"Rab\u0101\u0163-e Gardan",
    "gn:population":0,
    "gn:timezone":"Asia/Kabul",
    "iso:country":"AF",
    "name:und_x_variant":[
        "\u1e5eab\u0101\u1e6f-i-Ga\u1e5f\u1e0fan",
        "Rob\u0101\u0163-e Gardan",
        "Rab\u0101\u0163-e Gardan",
        "\u0631\u0628\u0627\u0637 \u06af\u0631\u062f\u0646"
    ],
    "wof:name":"Rabat-e Gardan",
    "wof:placetype":"locality"
},
  "geometry": {"coordinates":[69.98668000000001,37.37131],"type":"Point"}
}