{
  "type": "Feature",
  "properties": {
    "gn:admin1_code":"8",
    "gn:admin2_code":"607.0",
    "gn:asciiname":"Bini Barik",
    "gn:country_code":"AF",
    "gn:dem":2438,
    "gn:feature_class":"P",
    "gn:feature_code":"PPL",
    "gn:name":"B\u012bn\u012b B\u0101r\u012bk",
    "gn:population":0,
    "gn:timezone":"Asia/Kabul",
    "iso:country":"AF",
    "name:und_x_variant":[
        "B\u012bn\u012b B\u0101r\u012bk",
        "\u0628\u06cc\u0646\u06cc \u0628\u0627\u0631\u06cc\u06a9",
        "Binib\u0101r\u012bk"
    ],
    "wof:name":"Bini Barik",
    "wof:placetype":"locality"
},
  "geometry": {"coordinates":[67.39398,32.96987],"type":"Point"}
}