{
  "type": "Feature",
  "properties": {
    "gn:admin1_code":"02",
    "gn:admin2_code":"1903",
    "gn:asciiname":"Kalbia",
    "gn:country_code":"AF",
    "gn:dem":1758,
    "gn:feature_class":"P",
    "gn:feature_code":"PPL",
    "gn:name":"Kalb\u012b\u0101",
    "gn:population":0,
    "gn:timezone":"Asia/Kabul",
    "iso:country":"AF",
    "name:rus_x_preferred":[
        "Kal\u2019bia"
    ],
    "name:und_x_variant":[
        "Kalby\u0101",
        "Kalb\u012b\u0101",
        "\u06a9\u0644\u0628\u06cc\u0627"
    ],
    "wof:name":"Kalbia",
    "wof:placetype":"locality"
},
  "geometry": {"coordinates":[63.74881,34.79337],"type":"Point"}
}