{
  "type": "Feature",
  "properties": {
    "gn:admin1_code":"8",
    "gn:admin2_code":"605.0",
    "gn:asciiname":"Qandahari",
    "gn:country_code":"AF",
    "gn:dem":2907,
    "gn:feature_class":"P",
    "gn:feature_code":"PPL",
    "gn:name":"Qandah\u0101r\u012b",
    "gn:population":0,
    "gn:timezone":"Asia/Kabul",
    "iso:country":"AF",
    "name:fas_x_preferred":[
        "\u0642\u0646\u062f\u0647\u0627\u0631\u06cc"
    ],
    "name:und_x_variant":[
        "Qandah\u0101r\u012b",
        "\u0642\u0646\u062f\u0647\u0627\u0631\u06cc"
    ],
    "wof:name":"Qandahari",
    "wof:placetype":"locality"
},
  "geometry": {"coordinates":[67.29024,33.52582],"type":"Point"}
}