{
  "type": "Feature",
  "properties": {
    "gn:admin1_code":"11",
    "gn:admin2_code":"2014",
    "gn:asciiname":"Sang Bar",
    "gn:country_code":"AF",
    "gn:dem":840,
    "gn:feature_class":"P",
    "gn:feature_code":"PPL",
    "gn:name":"Sang Bar",
    "gn:population":0,
    "gn:timezone":"Asia/Kabul",
    "iso:country":"AF",
    "name:fas_x_preferred":[
        "\u0633\u0646\u06af \u0628\u0631"
    ],
    "name:und_x_variant":[
        "Sangbur",
        "Sang Bar",
        "Sangbor"
    ],
    "wof:name":"Sang Bar",
    "wof:placetype":"locality"
},
  "geometry": {"coordinates":[61.62633,32.87742],"type":"Point"}
}