{
  "type": "Feature",
  "properties": {
    "gn:admin1_code":"23",
    "gn:admin2_code":"2411.0",
    "gn:asciiname":"Pitaw Kelay",
    "gn:country_code":"AF",
    "gn:dem":1221,
    "gn:feature_class":"P",
    "gn:feature_code":"PPL",
    "gn:name":"Pit\u0101w K\u00ealay",
    "gn:population":0,
    "gn:timezone":"Asia/Kabul",
    "iso:country":"AF",
    "name:fas_x_preferred":[
        "\u0642\u0631\u06cc\u06c0 \u067e\u06cc\u062a\u0627\u0628"
    ],
    "name:und_x_variant":[
        "Petach-Kalay",
        "P\u0113t\u0101w Kalay",
        "Pit\u0101w K\u00ealay",
        "\u067e\u062a\u0627\u0648 \u06a9\u0644\u06cc",
        "P\u012bt\u0101b Kalay"
    ],
    "wof:name":"Pitaw Kelay",
    "wof:placetype":"locality"
},
  "geometry": {"coordinates":[66.34295999999999,31.18022],"type":"Point"}
}