{
  "type": "Feature",
  "properties": {
    "gn:admin1_code":"17",
    "gn:admin2_code":"503.0",
    "gn:asciiname":"Zaqum Khel",
    "gn:country_code":"AF",
    "gn:dem":1946,
    "gn:feature_class":"P",
    "gn:feature_code":"PPL",
    "gn:name":"Z\u0304aq\u016bm Kh\u0113l",
    "gn:population":0,
    "gn:timezone":"Asia/Kabul",
    "iso:country":"AF",
    "name:rus_x_preferred":[
        "Zakumkheyl\u2019"
    ],
    "name:und_x_variant":[
        "Z\u0304aq\u016bm Kh\u0113l",
        "Zaq\u016bmkh\u0113l",
        "\u0632\u0642\u0648\u0645 \u062e\u06d0\u0644"
    ],
    "wof:name":"Zaqum Khel",
    "wof:placetype":"locality"
},
  "geometry": {"coordinates":[68.91183000000001,33.95934],"type":"Point"}
}