{
  "type": "Feature",
  "properties": {
    "gn:admin1_code":"09",
    "gn:admin2_code":"2701",
    "gn:asciiname":"Ilyatah",
    "gn:country_code":"AF",
    "gn:dem":2388,
    "gn:feature_class":"P",
    "gn:feature_code":"PPL",
    "gn:name":"Ilyatah",
    "gn:population":0,
    "gn:timezone":"Asia/Kabul",
    "iso:country":"AF",
    "name:und_x_variant":[
        "Elyata",
        "Ilyatah",
        "\u0627\u0644\u06cc\u062a\u0647",
        "Elyatah"
    ],
    "wof:name":"Ilyatah",
    "wof:placetype":"locality"
},
  "geometry": {"coordinates":[65.4713,34.84883],"type":"Point"}
}