{
  "type": "Feature",
  "properties": {
    "gn:admin1_code":"13",
    "gn:admin2_code":"114",
    "gn:asciiname":"Gumbazah",
    "gn:country_code":"AF",
    "gn:dem":1843,
    "gn:feature_class":"P",
    "gn:feature_code":"PPL",
    "gn:name":"Gumbazah",
    "gn:population":0,
    "gn:timezone":"Asia/Kabul",
    "iso:country":"AF",
    "name:und_x_variant":[
        "Gumbaza",
        "Gumbazah",
        "Gombazah",
        "\u06af\u0645\u0628\u0632\u0647"
    ],
    "wof:name":"Gumbazah",
    "wof:placetype":"locality"
},
  "geometry": {"coordinates":[69.23354,34.36921],"type":"Point"}
}