{
  "type": "Feature",
  "properties": {
    "gn:admin1_code":"05",
    "gn:admin2_code":"2806",
    "gn:asciiname":"Istarab",
    "gn:country_code":"AF",
    "gn:dem":2684,
    "gn:feature_class":"P",
    "gn:feature_code":"PPL",
    "gn:name":"Istar\u0101b",
    "gn:population":0,
    "gn:timezone":"Asia/Kabul",
    "iso:country":"AF",
    "name:und_x_variant":[
        "Estar\u0101b",
        "Istar\u0101b",
        "\u0627\u0633\u062a\u0631\u0627\u0628"
    ],
    "wof:name":"Istarab",
    "wof:placetype":"locality"
},
  "geometry": {"coordinates":[67.07562,34.03254],"type":"Point"}
}