{
  "type": "Feature",
  "properties": {
    "gn:admin1_code":"11",
    "gn:admin2_code":"2006.0",
    "gn:asciiname":"Muqur",
    "gn:country_code":"AF",
    "gn:dem":758,
    "gn:feature_class":"P",
    "gn:feature_code":"PPL",
    "gn:name":"Muqur",
    "gn:population":0,
    "gn:timezone":"Asia/Kabul",
    "iso:country":"AF",
    "name:pnb_x_preferred":[
        "\u0636\u0644\u0639 \u0645\u0648\u0642\u0631"
    ],
    "name:und_x_variant":[
        "Mukur",
        "Muqu\u1e5f",
        "Muqur",
        "\u0645\u0642\u0631",
        "Moqor"
    ],
    "wof:name":"Muqur",
    "wof:placetype":"locality"
},
  "geometry": {"coordinates":[62.15857,35.13538],"type":"Point"}
}