{
  "type": "Feature",
  "properties": {
    "gn:admin1_code":"14",
    "gn:admin2_code":"205",
    "gn:asciiname":"Lowrowan",
    "gn:country_code":"AF",
    "gn:dem":2318,
    "gn:feature_class":"P",
    "gn:feature_code":"PPL",
    "gn:name":"Low\u1e5fow\u0101n",
    "gn:population":0,
    "gn:timezone":"Asia/Kabul",
    "iso:country":"AF",
    "name:fas_x_preferred":[
        "\u0644\u0648\u0631\u0648\u0646"
    ],
    "name:und_x_variant":[
        "Lauravan",
        "Lawraw\u0101n",
        "Lawrawan",
        "Low\u1e5fow\u0101n",
        "\u0644\u0648\u0631\u0648\u0627\u0646"
    ],
    "wof:name":"Lowrowan",
    "wof:placetype":"locality"
},
  "geometry": {"coordinates":[69.82859999999999,34.82727],"type":"Point"}
}