{
  "type": "Feature",
  "properties": {
    "gn:admin1_code":"35",
    "gn:admin2_code":"904",
    "gn:asciiname":"Obarah",
    "gn:country_code":"AF",
    "gn:dem":2436,
    "gn:feature_class":"P",
    "gn:feature_code":"PPL",
    "gn:name":"\u014cbarah",
    "gn:population":0,
    "gn:timezone":"Asia/Kabul",
    "iso:country":"AF",
    "name:rus_x_preferred":[
        "\u041e\u0431\u0430\u0440\u0430"
    ],
    "name:und_x_variant":[
        "\u014cba\u1e5fa",
        "Obara",
        "Owbarah",
        "\u014cbarah",
        "\u0627\u0648\u0628\u0631\u0647"
    ],
    "wof:name":"Obarah",
    "wof:placetype":"locality"
},
  "geometry": {"coordinates":[69.92274999999999,35.03759],"type":"Point"}
}