{
  "type": "Feature",
  "properties": {
    "gn:admin1_code":"32",
    "gn:admin2_code":"1504",
    "gn:asciiname":"Zai Ghulaq",
    "gn:country_code":"AF",
    "gn:dem":1198,
    "gn:feature_class":"P",
    "gn:feature_code":"PPL",
    "gn:name":"Za\u012b Ghulaq",
    "gn:population":0,
    "gn:timezone":"Asia/Kabul",
    "iso:country":"AF",
    "name:und_x_variant":[
        "Zai Gholaq",
        "Za\u012b Ghulaq",
        "\u0632\u06cc \u063a\u0644\u0642"
    ],
    "wof:name":"Zai Ghulaq",
    "wof:placetype":"locality"
},
  "geometry": {"coordinates":[67.09789000000001,36.04879],"type":"Point"}
}