{
  "type": "Feature",
  "properties": {
    "gn:admin1_code":"8",
    "gn:admin2_code":"608.0",
    "gn:asciiname":"'Izat Kala",
    "gn:country_code":"AF",
    "gn:dem":1981,
    "gn:feature_class":"P",
    "gn:feature_code":"PPL",
    "gn:name":"\u2018Izat Kal\u0101",
    "gn:population":0,
    "gn:timezone":"Asia/Kabul",
    "iso:country":"AF",
    "name:und_x_variant":[
        "Izzatkala",
        "\u2018Ezzat Kal\u0101",
        "\u2018Izat Kal\u0101",
        "\u0639\u0632\u062a \u06a9\u0644\u0627"
    ],
    "wof:name":"'Izat Kala",
    "wof:placetype":"locality"
},
  "geometry": {"coordinates":[67.80258000000001,32.78723],"type":"Point"}
}