{
  "type": "Feature",
  "properties": {
    "gn:admin1_code":"05",
    "gn:admin2_code":"2805",
    "gn:asciiname":"Gumaw",
    "gn:country_code":"AF",
    "gn:dem":2866,
    "gn:feature_class":"P",
    "gn:feature_code":"PPL",
    "gn:name":"Gum\u0101w",
    "gn:population":0,
    "gn:timezone":"Asia/Kabul",
    "iso:country":"AF",
    "name:und_x_variant":[
        "Gumau",
        "Gom\u0101w",
        "Gom\u0101b",
        "Gum\u0101w",
        "\u06af\u0645\u0622\u0648"
    ],
    "wof:name":"Gumaw",
    "wof:placetype":"locality"
},
  "geometry": {"coordinates":[66.82642,34.32697],"type":"Point"}
}