{
  "type": "Feature",
  "properties": {
    "gn:admin1_code":"8",
    "gn:admin2_code":"602.0",
    "gn:asciiname":"Deh-e Nurullah",
    "gn:country_code":"AF",
    "gn:dem":2504,
    "gn:feature_class":"P",
    "gn:feature_code":"PPL",
    "gn:name":"Deh-e N\u016brull\u0101h",
    "gn:population":0,
    "gn:timezone":"Asia/Kabul",
    "iso:country":"AF",
    "name:fas_x_preferred":[
        "\u062f\u0647\u0654 \u0646\u0648\u0631 \u0627\u0644\u0644\u0647"
    ],
    "name:und_x_variant":[
        "Dekhi-Nurulla",
        "\u1e0eehe N\u016b\u1e5full\u0101h",
        "Deh-e N\u016broll\u0101h",
        "Deh-e N\u016brull\u0101h",
        "\u062f\u0647 \u0646\u0648\u0631 \u0627\u0644\u0644\u0640\u0647"
    ],
    "wof:name":"Deh-e Nurullah",
    "wof:placetype":"locality"
},
  "geometry": {"coordinates":[68.20285,33.52309],"type":"Point"}
}