{
  "type": "Feature",
  "properties": {
    "gn:admin1_code":"9",
    "gn:admin2_code":"2710.0",
    "gn:asciiname":"Dahan-e Bibian",
    "gn:country_code":"AF",
    "gn:dem":2143,
    "gn:feature_class":"P",
    "gn:feature_code":"PPL",
    "gn:name":"Dahan-e B\u012bb\u012b\u0101n",
    "gn:population":0,
    "gn:timezone":"Asia/Kabul",
    "iso:country":"AF",
    "name:und_x_variant":[
        "Dakhani-Bibian",
        "Dahan-e B\u012bb\u012b\u0101n",
        "\u062f\u0647\u0646 \u0628\u06cc\u0628\u06cc\u0627\u0646",
        "Dahanah-ye B\u012bb\u012b \u0100n",
        "\u062f\u0647\u0646\u06c0 \u0628\u06cc \u0628\u06cc \u0622\u0646"
    ],
    "wof:name":"Dahan-e Bibian",
    "wof:placetype":"locality"
},
  "geometry": {"coordinates":[64.88372,34.45408],"type":"Point"}
}