{
  "type": "Feature",
  "properties": {
    "gn:admin1_code":"26",
    "gn:admin2_code":"1214.0",
    "gn:asciiname":"Sasik Kol",
    "gn:country_code":"AF",
    "gn:dem":436,
    "gn:feature_class":"P",
    "gn:feature_code":"PPL",
    "gn:name":"S\u0101sik K\u014dl",
    "gn:population":0,
    "gn:timezone":"Asia/Kabul",
    "iso:country":"AF",
    "name:und_x_variant":[
        "S\u0101sik K\u014dl",
        "\u0633\u0627\u0633\u06a9 \u06a9\u0648\u0644",
        "S\u0101sik Kol"
    ],
    "wof:name":"Sasik Kol",
    "wof:placetype":"locality"
},
  "geometry": {"coordinates":[69.44606,37.19712],"type":"Point"}
}