{
  "type": "Feature",
  "properties": {
    "gn:admin1_code":"27",
    "gn:admin2_code":"405.0",
    "gn:asciiname":"Chito",
    "gn:country_code":"AF",
    "gn:dem":2420,
    "gn:feature_class":"P",
    "gn:feature_code":"PPL",
    "gn:name":"Chi\u0163\u014d",
    "gn:population":0,
    "gn:timezone":"Asia/Kabul",
    "iso:country":"AF",
    "name:und_x_variant":[
        "\u010cito",
        "Chitu",
        "Ch\u012b\u0163o",
        "Chayt\u014d",
        "Chi\u0163\u014d",
        "\u0686\u0637\u0648"
    ],
    "wof:name":"Chito",
    "wof:placetype":"locality"
},
  "geometry": {"coordinates":[68.37223,34.22476],"type":"Point"}
}