{
  "type": "Feature",
  "properties": {
    "gn:admin1_code":"41",
    "gn:admin2_code":"3405",
    "gn:asciiname":"Pul Band",
    "gn:country_code":"AF",
    "gn:dem":2207,
    "gn:feature_class":"P",
    "gn:feature_code":"PPL",
    "gn:name":"Pul Band",
    "gn:population":0,
    "gn:timezone":"Asia/Kabul",
    "iso:country":"AF",
    "name:und_x_variant":[
        "Pulban\u1e0f",
        "Pul Band",
        "\u067e\u0644 \u0628\u0646\u062f",
        "Pol Band"
    ],
    "wof:name":"Pul Band",
    "wof:placetype":"locality"
},
  "geometry": {"coordinates":[65.80991,33.96802],"type":"Point"}
}