{
  "type": "Feature",
  "properties": {
    "gn:admin1_code":"27",
    "gn:admin2_code":"406",
    "gn:asciiname":"Shab Ash Khan",
    "gn:country_code":"AF",
    "gn:dem":2389,
    "gn:feature_class":"P",
    "gn:feature_code":"PPL",
    "gn:name":"Shab \u0100sh Kh\u0101n",
    "gn:population":0,
    "gn:timezone":"Asia/Kabul",
    "iso:country":"AF",
    "name:und_x_variant":[
        "\u0160ab\u0101\u0161kh\u0101n",
        "Shabashkhan",
        "Shab\u0101shkh\u0101n",
        "Shab B\u0101sh Kh\u0101n",
        "Shab \u0100sh Kh\u0101n",
        "\u0634\u0628 \u0622\u0634 \u062e\u0627\u0646"
    ],
    "wof:name":"Shab Ash Khan",
    "wof:placetype":"locality"
},
  "geometry": {"coordinates":[68.45881999999999,34.0648],"type":"Point"}
}