{
  "type": "Feature",
  "properties": {
    "gn:admin1_code":"08",
    "gn:admin2_code":"606",
    "gn:asciiname":"Qaryah-ye Wali",
    "gn:country_code":"AF",
    "gn:dem":2869,
    "gn:feature_class":"P",
    "gn:feature_code":"PPL",
    "gn:name":"Qaryah-ye Wal\u012b",
    "gn:population":0,
    "gn:timezone":"Asia/Kabul",
    "iso:country":"AF",
    "name:und_x_variant":[
        "Qaryeh-ye Wali",
        "Qa\u1e5fya-i-Wali",
        "Qaryeh-ye Val\u012b",
        "Qaryah-ye Wal\u012b",
        "\u0642\u0631\u06cc\u06c0 \u0648\u0644\u06cc"
    ],
    "wof:name":"Qaryah-ye Wali",
    "wof:placetype":"locality"
},
  "geometry": {"coordinates":[67.04301,33.26998],"type":"Point"}
}