{
  "type": "Feature",
  "properties": {
    "gn:admin1_code":"3",
    "gn:admin2_code":"1303.0",
    "gn:asciiname":"Nakil'",
    "gn:country_code":"AF",
    "gn:dem":619,
    "gn:feature_class":"P",
    "gn:feature_code":"PPL",
    "gn:name":"Nakil\u2019",
    "gn:population":0,
    "gn:timezone":"Asia/Kabul",
    "iso:country":"AF",
    "name:rus_x_preferred":[
        "Nakil\u2019"
    ],
    "wof:name":"Nakil'",
    "wof:placetype":"locality"
},
  "geometry": {"coordinates":[68.575,35.95556],"type":"Point"}
}