{
  "type": "Feature",
  "properties": {
    "gn:admin1_code":"33",
    "gn:admin2_code":"3105",
    "gn:asciiname":"Qishlaq Habib Khan",
    "gn:country_code":"AF",
    "gn:dem":878,
    "gn:feature_class":"P",
    "gn:feature_code":"PPL",
    "gn:name":"Qishl\u0101q \u1e28ab\u012bb Kh\u0101n",
    "gn:population":0,
    "gn:timezone":"Asia/Kabul",
    "iso:country":"AF",
    "name:und_x_variant":[
        "Qishl\u0101q Habib Kh\u0101n",
        "Qeshl\u0101q \u1e28ab\u012bb Kh\u0101n",
        "Qishl\u0101q \u1e28ab\u012bb Kh\u0101n",
        "\u0642\u0634\u0644\u0627\u0642 \u062d\u0628\u06cc\u0628 \u062e\u0627\u0646"
    ],
    "wof:name":"Qishlaq Habib Khan",
    "wof:placetype":"locality"
},
  "geometry": {"coordinates":[66.21512,36.08916],"type":"Point"}
}