{
  "type": "Feature",
  "properties": {
    "gn:admin1_code":"8",
    "gn:admin2_code":"607.0",
    "gn:asciiname":"Qash-e Hajat",
    "gn:country_code":"AF",
    "gn:dem":2507,
    "gn:feature_class":"P",
    "gn:feature_code":"PPL",
    "gn:name":"Q\u0101sh-e \u1e28\u0101j\u0101t",
    "gn:population":0,
    "gn:timezone":"Asia/Kabul",
    "iso:country":"AF",
    "name:fas_x_preferred":[
        "\u0642\u0627\u0634\u0654 \u062d\u0627\u062c\u0627\u0631"
    ],
    "name:und_x_variant":[
        "Q\u0101\u0161yajat",
        "Q\u0101\u0161e H\u0101j\u0101r",
        "Q\u0101sh-e \u1e28\u0101j\u0101r",
        "Q\u0101sh-e \u1e28\u0101j\u0101t",
        "\u0642\u0627\u0634 \u062d\u0627\u062c\u0627\u062a",
        "Qashyajat",
        "\u0642\u0634\u06cc\u062c\u062a"
    ],
    "wof:name":"Qash-e Hajat",
    "wof:placetype":"locality"
},
  "geometry": {"coordinates":[67.49563000000001,33.18562],"type":"Point"}
}