{
  "type": "Feature",
  "properties": {
    "gn:admin1_code":"8",
    "gn:admin2_code":"607.0",
    "gn:asciiname":"Jalah",
    "gn:country_code":"AF",
    "gn:dem":2472,
    "gn:feature_class":"P",
    "gn:feature_code":"PPL",
    "gn:name":"J\u0101lah",
    "gn:population":0,
    "gn:timezone":"Asia/Kabul",
    "iso:country":"AF",
    "name:und_x_variant":[
        "J\u0101la",
        "J\u0101lah",
        "\u062c\u0627\u0644\u0647"
    ],
    "wof:name":"Jalah",
    "wof:placetype":"locality"
},
  "geometry": {"coordinates":[67.36384,33.08834],"type":"Point"}
}