{
  "type": "Feature",
  "properties": {
    "gn:admin1_code":"33",
    "gn:admin2_code":"3105",
    "gn:asciiname":"Sowaji",
    "gn:country_code":"AF",
    "gn:dem":935,
    "gn:feature_class":"P",
    "gn:feature_code":"PPL",
    "gn:name":"Sowaj\u012b",
    "gn:population":0,
    "gn:timezone":"Asia/Kabul",
    "iso:country":"AF",
    "name:und_x_variant":[
        "Sowaj\u012b",
        "\u0633\u0648\u062c\u06cc",
        "Sawaji"
    ],
    "wof:name":"Sowaji",
    "wof:placetype":"locality"
},
  "geometry": {"coordinates":[66.22564,36.03955],"type":"Point"}
}