{
  "type": "Feature",
  "properties": {
    "gn:admin1_code":"06",
    "gn:admin2_code":"2104",
    "gn:asciiname":"Qaryah-ye Deh",
    "gn:country_code":"AF",
    "gn:dem":1196,
    "gn:feature_class":"P",
    "gn:feature_code":"PPL",
    "gn:name":"Qaryah-ye Deh",
    "gn:population":0,
    "gn:timezone":"Asia/Kabul",
    "iso:country":"AF",
    "name:und_x_variant":[
        "Qa\u1e5fya-i-\u1e0eeh",
        "Qaryah-ye Deh",
        "\u0642\u0631\u06cc\u06c0 \u062f\u0647",
        "Qaryeh-ye Deh"
    ],
    "wof:name":"Qaryah-ye Deh",
    "wof:placetype":"locality"
},
  "geometry": {"coordinates":[63.54252,33.16588],"type":"Point"}
}