{
  "type": "Feature",
  "properties": {
    "gn:admin1_code":"23",
    "gn:admin2_code":"2412",
    "gn:asciiname":"Muhammadah",
    "gn:country_code":"AF",
    "gn:dem":1395,
    "gn:feature_class":"P",
    "gn:feature_code":"PPL",
    "gn:name":"Mu\u1e29ammadah",
    "gn:population":0,
    "gn:timezone":"Asia/Kabul",
    "iso:country":"AF",
    "name:und_x_variant":[
        "Mukhammeda",
        "Mo\u1e29ammadah",
        "Mu\u1e29ammadah",
        "\u0645\u062d\u0645\u062f\u0647"
    ],
    "wof:name":"Muhammadah",
    "wof:placetype":"locality"
},
  "geometry": {"coordinates":[66.69117,31.4659],"type":"Point"}
}