{
  "type": "Feature",
  "properties": {
    "gn:admin1_code":"29",
    "gn:admin2_code":"2909.0",
    "gn:asciiname":"Pindzikha Junubi",
    "gn:country_code":"AF",
    "gn:dem":2281,
    "gn:feature_class":"P",
    "gn:feature_code":"PPL",
    "gn:name":"Pindzikh\u0101 Jun\u016bb\u012b",
    "gn:population":0,
    "gn:timezone":"Asia/Kabul",
    "iso:country":"AF",
    "name:und_x_variant":[
        "Pindzhikha-Dzhanubi",
        "Penjikh\u0101 Jan\u016bbi",
        "Pendz\u012bkh\u0101h-e Jon\u016bb\u012b",
        "Pindz\u012bkh\u0101 Jun\u016bb\u012b",
        "Pindzikh\u0101 Jun\u016bb\u012b",
        "\u067e\u0646\u0681\u062e\u0627 \u062c\u0646\u0648\u0628\u06cc",
        "Panjkh\u0101 Jun\u016bb\u012b",
        "\u067e\u0646\u062c\u062e\u0627 \u062c\u0646\u0648\u0628\u06cc"
    ],
    "wof:name":"Pindzikha Junubi",
    "wof:placetype":"locality"
},
  "geometry": {"coordinates":[69.15373000000001,32.76725],"type":"Point"}
}