{
  "type": "Feature",
  "properties": {
    "gn:admin1_code":"03",
    "gn:admin2_code":"1301",
    "gn:asciiname":"Shamarq",
    "gn:country_code":"AF",
    "gn:dem":668,
    "gn:feature_class":"P",
    "gn:feature_code":"PPL",
    "gn:name":"Shamarq",
    "gn:population":0,
    "gn:timezone":"Asia/Kabul",
    "iso:country":"AF",
    "name:und_x_variant":[
        "\u0160amarq",
        "Shamark",
        "Shamarq",
        "\u0634\u0645\u0631\u0642"
    ],
    "wof:name":"Shamarq",
    "wof:placetype":"locality"
},
  "geometry": {"coordinates":[68.75436999999999,35.89388],"type":"Point"}
}