{
  "type": "Feature",
  "properties": {
    "gn:admin1_code":"09",
    "gn:admin2_code":"2710",
    "gn:asciiname":"Galah Asya",
    "gn:country_code":"AF",
    "gn:dem":2809,
    "gn:feature_class":"P",
    "gn:feature_code":"PPL",
    "gn:name":"Galah \u0100sy\u0101",
    "gn:population":0,
    "gn:timezone":"Asia/Kabul",
    "iso:country":"AF",
    "name:und_x_variant":[
        "Gala \u0100sy\u0101",
        "Galaasia",
        "Galleh \u0100s\u012b\u0101",
        "Galah \u0100sy\u0101",
        "\u06af\u0644\u0647 \u0622\u0633\u06cc\u0627"
    ],
    "wof:name":"Galah Asya",
    "wof:placetype":"locality"
},
  "geometry": {"coordinates":[64.88120000000001,34.27219],"type":"Point"}
}