{
  "type": "Feature",
  "properties": {
    "gn:admin1_code":"01",
    "gn:admin2_code":"1119.0",
    "gn:asciiname":"Dowlat Rubat",
    "gn:country_code":"AF",
    "gn:dem":2626,
    "gn:feature_class":"P",
    "gn:feature_code":"PPL",
    "gn:name":"Dowlat Rub\u0101\u0163",
    "gn:population":0,
    "gn:timezone":"Asia/Kabul",
    "iso:country":"AF",
    "name:und_x_variant":[
        "\u1e0eawlat Rab\u0101\u0163",
        "\u062f\u0648\u0644\u062a \u0631\u0628\u0627\u0637",
        "Dowlat Rob\u0101\u0163",
        "Dowlat Rab\u0101\u0163",
        "Dowlat Rub\u0101\u0163"
    ],
    "wof:name":"Dowlat Rubat",
    "wof:placetype":"locality"
},
  "geometry": {"coordinates":[70.61225,37.49971],"type":"Point"}
}