{
  "type": "Feature",
  "properties": {
    "gn:admin1_code":"06",
    "gn:admin2_code":"2103",
    "gn:asciiname":"Nawah-ye Ayran",
    "gn:country_code":"AF",
    "gn:dem":1259,
    "gn:feature_class":"P",
    "gn:feature_code":"PPL",
    "gn:name":"N\u0101wah-ye Ayr\u0101n",
    "gn:population":0,
    "gn:timezone":"Asia/Kabul",
    "iso:country":"AF",
    "name:und_x_variant":[
        "N\u0101wa-i- E\u1e5f\u0101n",
        "N\u0101wah-ye Ayr\u0101n",
        "\u0646\u0627\u0648\u06c0 \u0627\u06cc\u0631\u0627\u0646",
        "N\u0101veh-ye \u012ar\u0101n"
    ],
    "wof:name":"Nawah-ye Ayran",
    "wof:placetype":"locality"
},
  "geometry": {"coordinates":[63.73316,32.45132],"type":"Point"}
}