{
  "type": "Feature",
  "properties": {
    "gn:admin1_code":"23",
    "gn:admin2_code":"2407",
    "gn:asciiname":"Dolah",
    "gn:country_code":"AF",
    "gn:dem":819,
    "gn:feature_class":"P",
    "gn:feature_code":"PPL",
    "gn:name":"\u1e0e\u014dlah",
    "gn:population":0,
    "gn:timezone":"Asia/Kabul",
    "iso:country":"AF",
    "name:und_x_variant":[
        "Dola",
        "D\u014dla",
        "\u1e0e\u014dlah",
        "\u0689\u0648\u0644\u0647",
        "Dowlah"
    ],
    "wof:name":"Dolah",
    "wof:placetype":"locality"
},
  "geometry": {"coordinates":[64.78964000000001,31.6047],"type":"Point"}
}