{
  "type": "Feature",
  "properties": {
    "gn:admin1_code":"2",
    "gn:admin2_code":"1903.0",
    "gn:asciiname":"Darah-ye Bum",
    "gn:country_code":"AF",
    "gn:dem":795,
    "gn:feature_class":"P",
    "gn:feature_code":"PPL",
    "gn:name":"Darah-ye B\u016bm",
    "gn:population":0,
    "gn:timezone":"Asia/Kabul",
    "iso:country":"AF",
    "name:und_x_variant":[
        "Boomdarra",
        "M\u012b\u0101nah B\u016bm",
        "\u1e0ea\u1e5fae B\u016bm",
        "\u1e0ea\u1e5f\u1e5fah-i-B\u016bm",
        "M\u012b\u0101na B\u0101m",
        "Darreh-ye B\u016bm",
        "Darah-ye B\u016bm",
        "\u062f\u0631\u06c0 \u0628\u0648\u0645"
    ],
    "wof:name":"Darah-ye Bum",
    "wof:placetype":"locality"
},
  "geometry": {"coordinates":[63.46874,35.13514],"type":"Point"}
}