{
  "type": "Feature",
  "properties": {
    "gn:admin1_code":"09",
    "gn:admin2_code":"2710",
    "gn:asciiname":"Zanu",
    "gn:country_code":"AF",
    "gn:dem":2503,
    "gn:feature_class":"P",
    "gn:feature_code":"PPL",
    "gn:name":"Zanu",
    "gn:population":0,
    "gn:timezone":"Asia/Kabul",
    "iso:country":"AF",
    "name:und_x_variant":[
        "Z\u0101n\u016b",
        "Zanu",
        "\u0632\u0627\u0646\u0648"
    ],
    "wof:name":"Zanu",
    "wof:placetype":"locality"
},
  "geometry": {"coordinates":[64.7291,33.86131],"type":"Point"}
}