{
  "type": "Feature",
  "properties": {
    "gn:admin1_code":"7",
    "gn:admin2_code":"1801.0",
    "gn:asciiname":"Khwajah Paytagh",
    "gn:country_code":"AF",
    "gn:dem":848,
    "gn:feature_class":"P",
    "gn:feature_code":"PPL",
    "gn:name":"Khw\u0101jah Payt\u0101gh",
    "gn:population":0,
    "gn:timezone":"Asia/Kabul",
    "iso:country":"AF",
    "name:und_x_variant":[
        "Khw\u0101ja Payt\u0101gh",
        "Khv\u0101jeh Payt\u0101gh",
        "Khw\u0101jah Payt\u0101gh",
        "\u062e\u0648\u0627\u062c\u0647 \u067e\u06cc\u062a\u0627\u063a",
        "Khw\u0101jah Payt\u0101q",
        "\u062e\u0648\u0627\u062c\u0647 \u067e\u06cc\u062a\u0627\u0642"
    ],
    "wof:name":"Khwajah Paytagh",
    "wof:placetype":"locality"
},
  "geometry": {"coordinates":[64.7761,35.93589],"type":"Point"}
}