{
  "type": "Feature",
  "properties": {
    "gn:admin1_code":"41",
    "gn:admin2_code":"3401.0",
    "gn:asciiname":"Pay Nili",
    "gn:country_code":"AF",
    "gn:dem":1877,
    "gn:feature_class":"P",
    "gn:feature_code":"PPL",
    "gn:name":"P\u0101y N\u012bl\u012b",
    "gn:population":0,
    "gn:timezone":"Asia/Kabul",
    "iso:country":"AF",
    "name:und_x_variant":[
        "P\u0101y N\u012bl\u012b",
        "\u067e\u0627\u06cc \u0646\u06cc\u0644\u06cc"
    ],
    "wof:name":"Pay Nili",
    "wof:placetype":"locality"
},
  "geometry": {"coordinates":[66.17774,33.69224000000001],"type":"Point"}
}