{
  "type": "Feature",
  "properties": {
    "gn:admin1_code":"30",
    "gn:admin2_code":"1608",
    "gn:asciiname":"Joy Shor",
    "gn:country_code":"AF",
    "gn:dem":326,
    "gn:feature_class":"P",
    "gn:feature_code":"PPL",
    "gn:name":"J\u014dy Sh\u014dr",
    "gn:population":0,
    "gn:timezone":"Asia/Kabul",
    "iso:country":"AF",
    "name:und_x_variant":[
        "J\u016by Sh\u016br",
        "J\u014dy Sh\u014dr",
        "\u062c\u0648\u0647 \u0634\u0648\u0631",
        "\u062c\u0648\u06cc \u0634\u0648\u0631"
    ],
    "wof:name":"Joy Shor",
    "wof:placetype":"locality"
},
  "geometry": {"coordinates":[66.54923000000001,36.71423],"type":"Point"}
}