{
  "type": "Feature",
  "properties": {
    "gn:admin1_code":"28",
    "gn:admin2_code":"2502.0",
    "gn:asciiname":"'Amah Kelay",
    "gn:country_code":"AF",
    "gn:dem":1859,
    "gn:feature_class":"P",
    "gn:feature_code":"PPL",
    "gn:name":"\u2018Amah K\u00ealay",
    "gn:population":0,
    "gn:timezone":"Asia/Kabul",
    "iso:country":"AF",
    "name:fas_x_preferred":[
        "\u0642\u0631\u064a\u06c0 \u0639\u0645\u0647"
    ],
    "name:und_x_variant":[
        "\u2018Ama Kalay",
        "\u2018Amah K\u00ealay",
        "\u0639\u0645\u0647 \u06a9\u0644\u06cc",
        "\u2018Ammah Kalay"
    ],
    "wof:name":"'Amah Kelay",
    "wof:placetype":"locality"
},
  "geometry": {"coordinates":[67.28565999999999,32.44802],"type":"Point"}
}