{
  "type": "Feature",
  "properties": {
    "gn:admin1_code":"14",
    "gn:admin2_code":"204.0",
    "gn:asciiname":"Chashmah-ye Roshan",
    "gn:country_code":"AF",
    "gn:dem":1904,
    "gn:feature_class":"P",
    "gn:feature_code":"PPL",
    "gn:name":"Chashmah-ye R\u014dsh\u0101n",
    "gn:population":0,
    "gn:timezone":"Asia/Kabul",
    "iso:country":"AF",
    "name:fas_x_preferred":[
        "\u0686\u0627\u06c0 \u0631\u0648\u0634\u0646"
    ],
    "name:rus_x_preferred":[
        "\u0427\u0430\u0448\u043c\u0430\u0440\u043e\u0448\u0430\u043d"
    ],
    "name:und_x_variant":[
        "Chashmaroshan",
        "\u010c\u0101he Ro\u0161\u0101n",
        "\u010cah Ro\u0161\u0101n",
        "Ch\u0101h-e Rowshan",
        "Chashmah-ye R\u014dsh\u0101n",
        "\u0686\u0634\u0645\u06c0 \u0631\u0648\u0634\u0627\u0646"
    ],
    "wof:name":"Chashmah-ye Roshan",
    "wof:placetype":"locality"
},
  "geometry": {"coordinates":[69.63025999999999,35.03832],"type":"Point"}
}