{
  "type": "Feature",
  "properties": {
    "gn:admin1_code":"41",
    "gn:admin2_code":"3406",
    "gn:asciiname":"Malmonjak",
    "gn:country_code":"AF",
    "gn:dem":1738,
    "gn:feature_class":"P",
    "gn:feature_code":"PPL",
    "gn:name":"M\u0101lm\u014dnjak",
    "gn:population":0,
    "gn:timezone":"Asia/Kabul",
    "iso:country":"AF",
    "name:und_x_variant":[
        "M\u0101lm\u016bnjak",
        "M\u0101lm\u014dnjak",
        "\u0645\u0627\u0644\u0645\u0648\u0646\u062c\u06a9"
    ],
    "wof:name":"Malmonjak",
    "wof:placetype":"locality"
},
  "geometry": {"coordinates":[65.73761999999999,33.49692],"type":"Point"}
}