{
  "type": "Feature",
  "properties": {
    "gn:admin1_code":"01",
    "gn:admin2_code":"1110",
    "gn:asciiname":"Durman",
    "gn:country_code":"AF",
    "gn:dem":2320,
    "gn:feature_class":"P",
    "gn:feature_code":"PPL",
    "gn:name":"D\u016brman",
    "gn:population":0,
    "gn:timezone":"Asia/Kabul",
    "iso:country":"AF",
    "name:ben_x_preferred":[
        "\u09a6\u09c1\u09b0\u09ae\u09be\u09a8"
    ],
    "name:por_x_preferred":[
        "Durman"
    ],
    "name:und_x_variant":[
        "\u062f\u0648\u0631\u0645\u0646",
        "D\u016brm\u0101n",
        "D\u016brman"
    ],
    "wof:name":"Durman",
    "wof:placetype":"locality"
},
  "geometry": {"coordinates":[70.80807,38.25842],"type":"Point"}
}