{
  "type": "Feature",
  "properties": {
    "gn:admin1_code":"39",
    "gn:admin2_code":"2604",
    "gn:asciiname":"Durji",
    "gn:country_code":"AF",
    "gn:dem":1510,
    "gn:feature_class":"P",
    "gn:feature_code":"PPL",
    "gn:name":"Durj\u012b",
    "gn:population":0,
    "gn:timezone":"Asia/Kabul",
    "iso:country":"AF",
    "name:und_x_variant":[
        "Durdzhi",
        "Durj\u012b",
        "\u062f\u0631\u062c\u06cc",
        "Du\u1e5fji"
    ],
    "wof:name":"Durji",
    "wof:placetype":"locality"
},
  "geometry": {"coordinates":[65.31338000000001,32.85185],"type":"Point"}
}