{
  "type": "Feature",
  "properties": {
    "gn:admin1_code":"28",
    "gn:admin2_code":"2504",
    "gn:asciiname":"Shamali Karez",
    "gn:country_code":"AF",
    "gn:dem":2142,
    "gn:feature_class":"P",
    "gn:feature_code":"PPL",
    "gn:name":"Sham\u0101l\u012b K\u0101r\u0113z",
    "gn:population":0,
    "gn:timezone":"Asia/Kabul",
    "iso:country":"AF",
    "name:fas_x_preferred":[
        "\u0634\u0645\u0627\u0644\u06cc \u0643\u0627\u0631\u064a\u0632"
    ],
    "name:und_x_variant":[
        "\u0160am\u0101li K\u0101r\u0113z",
        "Shamali-Karez",
        "Sham\u0101l\u012b K\u0101r\u0113z",
        "\u0634\u0645\u0627\u0644\u06cc \u06a9\u0627\u0631\u06d0\u0632",
        "Sham\u0101l\u012b K\u0101r\u012bz"
    ],
    "wof:name":"Shamali Karez",
    "wof:placetype":"locality"
},
  "geometry": {"coordinates":[66.61022,32.52245],"type":"Point"}
}