{
  "type": "Feature",
  "properties": {
    "gn:admin1_code":"10",
    "gn:admin2_code":"2307",
    "gn:asciiname":"Karwangah",
    "gn:country_code":"AF",
    "gn:dem":972,
    "gn:feature_class":"P",
    "gn:feature_code":"PPL",
    "gn:name":"K\u0101rw\u0101ng\u0101h",
    "gn:population":0,
    "gn:timezone":"Asia/Kabul",
    "iso:country":"AF",
    "name:und_x_variant":[
        "K\u0101rv\u0101ng\u0101h",
        "Karvangakh",
        "K\u0101rw\u0101ng\u0101h",
        "\u06a9\u0627\u0631\u0648\u0627\u0646\u06af\u0627\u0647",
        "K\u0101\u1e5fw\u0101ng\u0101h"
    ],
    "wof:name":"Karwangah",
    "wof:placetype":"locality"
},
  "geometry": {"coordinates":[64.05305,32.0094],"type":"Point"}
}