{
  "type": "Feature",
  "properties": {
    "gn:admin1_code":"09",
    "gn:admin2_code":"2705",
    "gn:asciiname":"Isfowr",
    "gn:country_code":"AF",
    "gn:dem":2292,
    "gn:feature_class":"P",
    "gn:feature_code":"PPL",
    "gn:name":"Isfowr",
    "gn:population":0,
    "gn:timezone":"Asia/Kabul",
    "iso:country":"AF",
    "name:und_x_variant":[
        "Isfaur",
        "Isfowr",
        "\u0627\u0633\u0641\u0648\u0631",
        "Esfawr"
    ],
    "wof:name":"Isfowr",
    "wof:placetype":"locality"
},
  "geometry": {"coordinates":[64.19400999999999,33.33249],"type":"Point"}
}