{
  "type": "Feature",
  "properties": {
    "gn:admin1_code":"13",
    "gn:admin2_code":"106.0",
    "gn:asciiname":"Asya-ye Gudi",
    "gn:country_code":"AF",
    "gn:dem":1701,
    "gn:feature_class":"P",
    "gn:feature_code":"PPL",
    "gn:name":"\u0100sy\u0101-ye Gud\u012b",
    "gn:population":0,
    "gn:timezone":"Asia/Kabul",
    "iso:country":"AF",
    "name:fas_x_preferred":[
        "\u0622\u0633\u064a\u0627\u0628\u0654 \u06af\u0648\u062f\u06cc"
    ],
    "name:und_x_variant":[
        "Asiayi-Gudi",
        "\u0100sy\u0101-i-Go\u1e0fi",
        "\u0100sy\u0101-ye Gud\u012b",
        "\u0100s\u012b\u0101b-e Gowd\u012b",
        "\u0622\u0633\u06cc\u0627\u06cc \u06af\u062f\u06cc",
        "\u0100s\u012b\u0101-ye Gud\u012b",
        "\u0622\u0633\u06cc\u0627 \u06af\u062f\u06cc"
    ],
    "wof:name":"Asya-ye Gudi",
    "wof:placetype":"locality"
},
  "geometry": {"coordinates":[69.10096,34.8373],"type":"Point"}
}