{
  "type": "Feature",
  "properties": {
    "gn:admin1_code":"27",
    "gn:admin2_code":"406.0",
    "gn:asciiname":"Nokar Khel",
    "gn:country_code":"AF",
    "gn:dem":2424,
    "gn:feature_class":"P",
    "gn:feature_code":"PPL",
    "gn:name":"N\u014dkar Kh\u0113l",
    "gn:population":0,
    "gn:timezone":"Asia/Kabul",
    "iso:country":"AF",
    "name:rus_x_preferred":[
        "Nokarkheyl\u2019"
    ],
    "name:und_x_variant":[
        "N\u014dka\u1e5fkh\u0113l",
        "N\u014dkar Kh\u0113l",
        "Nowkarkheyl",
        "\u0646\u0648\u06a9\u0631 \u062e\u06d0\u0644"
    ],
    "wof:name":"Nokar Khel",
    "wof:placetype":"locality"
},
  "geometry": {"coordinates":[68.44055,34.05179],"type":"Point"}
}