{
  "type": "Feature",
  "properties": {
    "gn:admin1_code":"11",
    "gn:admin2_code":"2010.0",
    "gn:asciiname":"Izghilak",
    "gn:country_code":"AF",
    "gn:dem":1126,
    "gn:feature_class":"P",
    "gn:feature_code":"PPL",
    "gn:name":"Izgh\u012blak",
    "gn:population":0,
    "gn:timezone":"Asia/Kabul",
    "iso:country":"AF",
    "name:und_x_variant":[
        "Izgh\u012blak",
        "\u0627\u0632\u063a\u06cc\u0644\u06a9",
        "Ezgh\u012blah",
        "\u0627\u0632\u063a\u06cc\u0644\u0647"
    ],
    "wof:name":"Izghilak",
    "wof:placetype":"locality"
},
  "geometry": {"coordinates":[61.99332,34.53834000000001],"type":"Point"}
}