{
  "type": "Feature",
  "properties": {
    "gn:admin1_code":"11",
    "gn:admin2_code":"2007",
    "gn:asciiname":"Shayda'i",
    "gn:country_code":"AF",
    "gn:dem":899,
    "gn:feature_class":"P",
    "gn:feature_code":"PPL",
    "gn:name":"Shayd\u0101\u2019\u012b",
    "gn:population":0,
    "gn:timezone":"Asia/Kabul",
    "iso:country":"AF",
    "name:und_x_variant":[
        "Sayda\u2019\u012b",
        "Sheyd\u0101\u2019\u012b",
        "Shayd\u0101\u2019\u012b",
        "\u0634\u0649\u062f\u0627\u0639\u0649",
        "\u0634\u0649\u062f\u0627\u0626\u0649"
    ],
    "wof:name":"Shayda'i",
    "wof:placetype":"locality"
},
  "geometry": {"coordinates":[61.43578,35.26130999999999],"type":"Point"}
}