{
  "type": "Feature",
  "properties": {
    "gn:admin1_code":"08",
    "gn:admin2_code":"610",
    "gn:asciiname":"Khwajah Khel",
    "gn:country_code":"AF",
    "gn:dem":1993,
    "gn:feature_class":"P",
    "gn:feature_code":"PPL",
    "gn:name":"Khw\u0101jah Kh\u0113l",
    "gn:population":0,
    "gn:timezone":"Asia/Kabul",
    "iso:country":"AF",
    "name:rus_x_preferred":[
        "Khodzhakheyl\u2019"
    ],
    "name:und_x_variant":[
        "Khw\u0101jakh\u0113l",
        "Khw\u0101jah Kh\u0113l",
        "\u062e\u0648\u0627\u062c\u0647 \u062e\u06d0\u0644",
        "Khv\u0101jeh Kheyl"
    ],
    "wof:name":"Khwajah Khel",
    "wof:placetype":"locality"
},
  "geometry": {"coordinates":[67.8562,32.32623],"type":"Point"}
}