{
  "type": "Feature",
  "properties": {
    "gn:admin1_code":"28",
    "gn:admin2_code":"2509",
    "gn:asciiname":"Hoteko Kelay",
    "gn:country_code":"AF",
    "gn:dem":2328,
    "gn:feature_class":"P",
    "gn:feature_code":"PPL",
    "gn:name":"H\u014dt\u00eak\u014d K\u00ealay",
    "gn:population":0,
    "gn:timezone":"Asia/Kabul",
    "iso:country":"AF",
    "name:und_x_variant":[
        "Khotikukalay",
        "H\u014dteko Kalay",
        "H\u014dt\u00eak\u014d K\u00ealay",
        "\u0647\u0648\u062a\u06a9\u0648 \u06a9\u0644\u06cc",
        "H\u016bteko Kalay"
    ],
    "wof:name":"Hoteko Kelay",
    "wof:placetype":"locality"
},
  "geometry": {"coordinates":[67.95014,32.07307],"type":"Point"}
}