{
  "type": "Feature",
  "properties": {
    "gn:admin1_code":"10",
    "gn:admin2_code":"2307",
    "gn:asciiname":"Washer",
    "gn:country_code":"AF",
    "gn:dem":1175,
    "gn:feature_class":"P",
    "gn:feature_code":"PPLA2",
    "gn:name":"W\u0101sh\u0113r",
    "gn:population":0,
    "gn:timezone":"Asia/Kabul",
    "iso:country":"AF",
    "name:deu_x_preferred":[
        "Washer"
    ],
    "name:und_x_variant":[
        "W\u0101s\u0113\u1e5f",
        "Wash\u0101r",
        "V\u0101sh\u012br",
        "W\u0101shayr",
        "\u0648\u0627\u0634\u06cc\u0631",
        "W\u0101sh\u0113r"
    ],
    "wof:name":"Washer",
    "wof:placetype":"locality"
},
  "geometry": {"coordinates":[63.85553,32.25122],"type":"Point"}
}