{
  "type": "Feature",
  "properties": {
    "gn:admin1_code":"40",
    "gn:admin2_code":"306.0",
    "gn:asciiname":"Dahan-e Jangalak",
    "gn:country_code":"AF",
    "gn:dem":2194,
    "gn:feature_class":"P",
    "gn:feature_code":"PPL",
    "gn:name":"Dahan-e Jangalak",
    "gn:population":0,
    "gn:timezone":"Asia/Kabul",
    "iso:country":"AF",
    "name:und_x_variant":[
        "Dakhani-Dzhangalak",
        "Dahan-e Jangalak",
        "\u062f\u0647\u0646 \u062c\u0646\u06af\u0644\u06a9"
    ],
    "wof:name":"Dahan-e Jangalak",
    "wof:placetype":"locality"
},
  "geometry": {"coordinates":[68.55643000000001,34.94262],"type":"Point"}
}