{
  "type": "Feature",
  "properties": {
    "gn:admin1_code":"09",
    "gn:admin2_code":"2705",
    "gn:asciiname":"Kilgu'i Bayan",
    "gn:country_code":"AF",
    "gn:dem":2230,
    "gn:feature_class":"P",
    "gn:feature_code":"PPL",
    "gn:name":"Kilg\u016b\u2018\u012b B\u0101yan",
    "gn:population":0,
    "gn:timezone":"Asia/Kabul",
    "iso:country":"AF",
    "name:rus_x_preferred":[
        "Kil\u2019guibayan"
    ],
    "name:und_x_variant":[
        "Kilg\u016b\u2018\u012b B\u0101yan",
        "\u06a9\u0644\u06af\u0648\u0639\u06cc \u0628\u0627\u06cc\u0646",
        "Kelg\u016b\u2019\u012b Bay\u0101n"
    ],
    "wof:name":"Kilgu'i Bayan",
    "wof:placetype":"locality"
},
  "geometry": {"coordinates":[64.46468,33.75303],"type":"Point"}
}