{
  "type": "Feature",
  "properties": {
    "gn:admin1_code":"41",
    "gn:admin2_code":"3403.0",
    "gn:asciiname":"Dahan-e Nawchah",
    "gn:country_code":"AF",
    "gn:dem":2516,
    "gn:feature_class":"P",
    "gn:feature_code":"PPL",
    "gn:name":"Dahan-e N\u0101wchah",
    "gn:population":0,
    "gn:timezone":"Asia/Kabul",
    "iso:country":"AF",
    "name:und_x_variant":[
        "Dahane Naw\u010da",
        "Dakhani-Naucha",
        "Dahan-e N\u0101wchah",
        "Dahan-e Nowch\u0101h",
        "\u062f\u0647\u0646 \u0646\u0627\u0648\u0686\u0647"
    ],
    "wof:name":"Dahan-e Nawchah",
    "wof:placetype":"locality"
},
  "geometry": {"coordinates":[66.40337,34.17112],"type":"Point"}
}