{
  "type": "Feature",
  "properties": {
    "gn:admin1_code":"01",
    "gn:admin2_code":"1112.0",
    "gn:asciiname":"Khambel",
    "gn:country_code":"AF",
    "gn:dem":2572,
    "gn:feature_class":"P",
    "gn:feature_code":"PPL",
    "gn:name":"Khamb\u0113l",
    "gn:population":0,
    "gn:timezone":"Asia/Kabul",
    "iso:country":"AF",
    "name:und_x_variant":[
        "Khamb\u0113l",
        "\u062e\u0645\u0628\u06d0\u0644"
    ],
    "wof:name":"Khambel",
    "wof:placetype":"locality"
},
  "geometry": {"coordinates":[70.55529,37.66615],"type":"Point"}
}