{
  "type": "Feature",
  "properties": {
    "gn:admin1_code":"27",
    "gn:admin2_code":"403.0",
    "gn:asciiname":"Dasht-e Lukhak",
    "gn:country_code":"AF",
    "gn:dem":3041,
    "gn:feature_class":"P",
    "gn:feature_code":"PPL",
    "gn:name":"Dasht-e Lukhak",
    "gn:population":0,
    "gn:timezone":"Asia/Kabul",
    "iso:country":"AF",
    "name:und_x_variant":[
        "Da\u0161te Lokhak",
        "Dashti-Lukhak",
        "Dasht-e Lokhak",
        "Dasht-e L\u014dkhak",
        "Dasht-e Lukhak",
        "\u062f\u0634\u062a \u0644\u062e\u06a9"
    ],
    "wof:name":"Dasht-e Lukhak",
    "wof:placetype":"locality"
},
  "geometry": {"coordinates":[68.07573000000001,34.50698],"type":"Point"}
}