{
  "type": "Feature",
  "properties": {
    "gn:admin1_code":"09",
    "gn:admin2_code":"2705",
    "gn:asciiname":"Pushwarah",
    "gn:country_code":"AF",
    "gn:dem":2640,
    "gn:feature_class":"P",
    "gn:feature_code":"PPL",
    "gn:name":"Pushwarah",
    "gn:population":0,
    "gn:timezone":"Asia/Kabul",
    "iso:country":"AF",
    "name:fas_x_preferred":[
        "\u067e\u0648\u0634\u0648\u0627\u0631\u0647"
    ],
    "name:und_x_variant":[
        "Pashwarah",
        "P\u016bshw\u0101rah",
        "Pushvara",
        "Pu\u0161wara",
        "Pushwarah",
        "\u067e\u0634\u0648\u0631\u0647",
        "P\u016bshv\u0101reh"
    ],
    "wof:name":"Pushwarah",
    "wof:placetype":"locality"
},
  "geometry": {"coordinates":[64.56185000000001,33.35082],"type":"Point"}
}