{
  "type": "Feature",
  "properties": {
    "gn:admin1_code":"9",
    "gn:admin2_code":"2703.0",
    "gn:asciiname":"Dahan-e Gildan",
    "gn:country_code":"AF",
    "gn:dem":2285,
    "gn:feature_class":"P",
    "gn:feature_code":"PPL",
    "gn:name":"Dah\u0101n-e Gild\u0101n",
    "gn:population":0,
    "gn:timezone":"Asia/Kabul",
    "iso:country":"AF",
    "name:und_x_variant":[
        "Dah\u0101n-e Gild\u0101n",
        "\u062f\u0647\u0627\u0646 \u06af\u0644\u062f\u0627\u0646",
        "Dahan-e Geld\u0101n"
    ],
    "wof:name":"Dahan-e Gildan",
    "wof:placetype":"locality"
},
  "geometry": {"coordinates":[63.90246,33.9914],"type":"Point"}
}