{
  "type": "Feature",
  "properties": {
    "gn:admin1_code":"7",
    "gn:admin2_code":"1804.0",
    "gn:asciiname":"Boyla",
    "gn:country_code":"AF",
    "gn:dem":1400,
    "gn:feature_class":"P",
    "gn:feature_code":"PPL",
    "gn:name":"B\u014dyl\u0101",
    "gn:population":0,
    "gn:timezone":"Asia/Kabul",
    "iso:country":"AF",
    "name:fas_x_preferred":[
        "B\u014dyl\u0101"
    ],
    "name:fas_x_variant":[
        "\u0628\u0648\u06cc\u0644\u0627"
    ],
    "name:und_x_variant":[
        "B\u014dyl\u0101",
        "Bowyl\u0101",
        "\u0628\u0648\u06cc\u0644\u0627"
    ],
    "wof:name":"Boyla",
    "wof:placetype":"locality"
},
  "geometry": {"coordinates":[64.41558000000001,35.73239],"type":"Point"}
}