{
  "type": "Feature",
  "properties": {
    "gn:admin1_code":"11",
    "gn:admin2_code":"2014",
    "gn:asciiname":"Karez-e Karkoh",
    "gn:country_code":"AF",
    "gn:dem":1161,
    "gn:feature_class":"P",
    "gn:feature_code":"PPL",
    "gn:name":"K\u0101r\u0113z-e Kark\u014dh",
    "gn:population":0,
    "gn:timezone":"Asia/Kabul",
    "iso:country":"AF",
    "name:und_x_variant":[
        "K\u0101\u1e5f\u0113ze Ka\u1e5fkoh",
        "K\u0101r\u012bz-e Karkoh",
        "K\u0101r\u0113z-e Kark\u014dh",
        "\u06a9\u0627\u0631\u06d0\u0632 \u06a9\u0631\u06a9\u0648\u0647"
    ],
    "wof:name":"Karez-e Karkoh",
    "wof:placetype":"locality"
},
  "geometry": {"coordinates":[61.86411,33.04815],"type":"Point"}
}