{
  "type": "Feature",
  "properties": {
    "gn:admin1_code":"01",
    "gn:admin2_code":"1101.0",
    "gn:asciiname":"Deh-Zindan",
    "gn:country_code":"AF",
    "gn:dem":1200,
    "gn:feature_class":"P",
    "gn:feature_code":"PPL",
    "gn:name":"Deh-Zind\u0101n",
    "gn:population":0,
    "gn:timezone":"Asia/Kabul",
    "iso:country":"AF",
    "name:und_x_variant":[
        "Deh-Zind\u0101n",
        "\u062f\u0647 \u0632\u0646\u062f\u0627\u0646",
        "Deh Zend\u0101n (1)"
    ],
    "wof:name":"Deh-Zindan",
    "wof:placetype":"locality"
},
  "geometry": {"coordinates":[70.47609,37.2255],"type":"Point"}
}