{
  "type": "Feature",
  "properties": {
    "gn:admin1_code":"28",
    "gn:admin2_code":"2509.0",
    "gn:asciiname":"Sin Bayn",
    "gn:country_code":"AF",
    "gn:dem":1906,
    "gn:feature_class":"P",
    "gn:feature_code":"PPL",
    "gn:name":"S\u012bn Bayn",
    "gn:population":0,
    "gn:timezone":"Asia/Kabul",
    "iso:country":"AF",
    "name:und_x_variant":[
        "S\u012bn Bayn",
        "\u0633\u06cc\u0646 \u0628\u06cc\u0646"
    ],
    "wof:name":"Sin Bayn",
    "wof:placetype":"locality"
},
  "geometry": {"coordinates":[67.45161999999999,31.60997],"type":"Point"}
}