{
  "type": "Feature",
  "properties": {
    "gn:admin1_code":"11",
    "gn:admin2_code":"2006",
    "gn:asciiname":"Qurban",
    "gn:country_code":"AF",
    "gn:dem":1379,
    "gn:feature_class":"P",
    "gn:feature_code":"PPL",
    "gn:name":"Qurb\u0101n",
    "gn:population":0,
    "gn:timezone":"Asia/Kabul",
    "iso:country":"AF",
    "name:und_x_variant":[
        "Kurban",
        "Qu\u1e5fb\u0101n",
        "Qurb\u0101n",
        "\u0642\u0631\u0628\u0627\u0646",
        "Qorb\u0101n"
    ],
    "wof:name":"Qurban",
    "wof:placetype":"locality"
},
  "geometry": {"coordinates":[62.25402,34.74327],"type":"Point"}
}