{
  "type": "Feature",
  "properties": {
    "gn:admin1_code":"01",
    "gn:admin2_code":"1112.0",
    "gn:asciiname":"Bashidew",
    "gn:country_code":"AF",
    "gn:dem":2418,
    "gn:feature_class":"P",
    "gn:feature_code":"PPL",
    "gn:name":"B\u0101shid\u0113w",
    "gn:population":0,
    "gn:timezone":"Asia/Kabul",
    "iso:country":"AF",
    "name:und_x_variant":[
        "\u0628\u0627\u0634\u062f\u06d0\u0648",
        "B\u0101si\u1e0f\u0113w",
        "B\u0101shid\u0113w"
    ],
    "wof:name":"Bashidew",
    "wof:placetype":"locality"
},
  "geometry": {"coordinates":[70.56865000000001,37.54101],"type":"Point"}
}