{
  "type": "Feature",
  "properties": {
    "gn:admin1_code":"40",
    "gn:admin2_code":"302.0",
    "gn:asciiname":"Khwajah Khel",
    "gn:country_code":"AF",
    "gn:dem":1563,
    "gn:feature_class":"P",
    "gn:feature_code":"PPL",
    "gn:name":"Khw\u0101jah Kh\u0113l",
    "gn:population":0,
    "gn:timezone":"Asia/Kabul",
    "iso:country":"AF",
    "name:fas_x_preferred":[
        "\u062e\u0648\u0627\u062c\u0647 \u062e\u064a\u0644"
    ],
    "name:rus_x_preferred":[
        "Khadzhakheyl\u2019"
    ],
    "name:und_x_variant":[
        "Khw\u0101jakh\u0113l",
        "Khv\u0101jehkheyl",
        "Khw\u0101jah Kh\u0113l",
        "\u062e\u0648\u0627\u062c\u0647 \u062e\u06d0\u0644"
    ],
    "wof:name":"Khwajah Khel",
    "wof:placetype":"locality"
},
  "geometry": {"coordinates":[69.27161,35.11722],"type":"Point"}
}