{
  "type": "Feature",
  "properties": {
    "gn:admin1_code":"28",
    "gn:admin2_code":"2510.0",
    "gn:asciiname":"Dahan-e Gulzar",
    "gn:country_code":"AF",
    "gn:dem":1932,
    "gn:feature_class":"P",
    "gn:feature_code":"PPL",
    "gn:name":"Dah\u0101n-e Gulz\u0101r",
    "gn:population":0,
    "gn:timezone":"Asia/Kabul",
    "iso:country":"AF",
    "name:rus_x_preferred":[
        "Dakhani-Gul\u2019zar"
    ],
    "name:und_x_variant":[
        "\u1e0eahane Gulz\u0101\u1e5f",
        "Dah\u0101n-e Gulz\u0101r",
        "\u062f\u0647\u0627\u0646 \u06af\u0644\u0632\u0627\u0631",
        "Dah\u0101neh-ye Golz\u0101r"
    ],
    "wof:name":"Dahan-e Gulzar",
    "wof:placetype":"locality"
},
  "geometry": {"coordinates":[67.31631,32.86998],"type":"Point"}
}