{
  "type": "Feature",
  "properties": {
    "gn:admin1_code":"31",
    "gn:admin2_code":"1702.0",
    "gn:asciiname":"Chob Bash-e Kalan",
    "gn:country_code":"AF",
    "gn:dem":318,
    "gn:feature_class":"P",
    "gn:feature_code":"PPL",
    "gn:name":"Ch\u014db Bash-e Kal\u0101n",
    "gn:population":0,
    "gn:timezone":"Asia/Kabul",
    "iso:country":"AF",
    "name:und_x_variant":[
        "Chapash",
        "Chob Bash-i-Kal\u0101n",
        "Ch\u016bb B\u0101sh-e Kal\u0101n",
        "Ch\u014db Bash-e Kal\u0101n",
        "\u0686\u0648\u0628 \u0628\u0634 \u06a9\u0644\u0627\u0646"
    ],
    "wof:name":"Chob Bash-e Kalan",
    "wof:placetype":"locality"
},
  "geometry": {"coordinates":[65.8077,36.79981],"type":"Point"}
}