{
  "type": "Feature",
  "properties": {
    "gn:admin1_code":"17",
    "gn:admin2_code":"507",
    "gn:asciiname":"Khwajah Angur",
    "gn:country_code":"AF",
    "gn:dem":2684,
    "gn:feature_class":"P",
    "gn:feature_code":"PPL",
    "gn:name":"Khw\u0101jah Ang\u016br",
    "gn:population":0,
    "gn:timezone":"Asia/Kabul",
    "iso:country":"AF",
    "name:und_x_variant":[
        "Khw\u0101jaang\u016b\u1e5f",
        "Khodzhaangur",
        "Khv\u0101jeh Ang\u016br",
        "Khw\u0101jah Ang\u016br",
        "\u062e\u0648\u0627\u062c\u0647 \u0627\u0646\u06af\u0648\u0631"
    ],
    "wof:name":"Khwajah Angur",
    "wof:placetype":"locality"
},
  "geometry": {"coordinates":[69.03489,33.69847],"type":"Point"}
}