{
  "type": "Feature",
  "properties": {
    "gn:admin1_code":"28",
    "gn:admin2_code":"2501.0",
    "gn:asciiname":"Zurmatiyan",
    "gn:country_code":"AF",
    "gn:dem":1599,
    "gn:feature_class":"P",
    "gn:feature_code":"PPL",
    "gn:name":"Zurmatiy\u0101n",
    "gn:population":0,
    "gn:timezone":"Asia/Kabul",
    "iso:country":"AF",
    "name:fas_x_preferred":[
        "\u0632\u0631\u0645\u062a\u064a\u0627\u0646"
    ],
    "name:und_x_variant":[
        "Zu\u1e5fmaty\u0101n",
        "Zurmatiy\u0101n",
        "\u0632\u0631\u0645\u062a\u06cc\u0627\u0646",
        "Zormat\u012b\u0101n"
    ],
    "wof:name":"Zurmatiyan",
    "wof:placetype":"locality"
},
  "geometry": {"coordinates":[66.83526999999999,32.13812],"type":"Point"}
}