{
  "type": "Feature",
  "properties": {
    "gn:admin1_code":"36",
    "gn:admin2_code":"702",
    "gn:asciiname":"Shilgad",
    "gn:country_code":"AF",
    "gn:dem":2225,
    "gn:feature_class":"P",
    "gn:feature_code":"PPL",
    "gn:name":"Shilgad",
    "gn:population":0,
    "gn:timezone":"Asia/Kabul",
    "iso:country":"AF",
    "name:fas_x_preferred":[
        "\u0634\u0644\u06af\u062f"
    ],
    "name:rus_x_preferred":[
        "Shil\u2019gad"
    ],
    "name:und_x_variant":[
        "\u0160elgad",
        "Shelgad",
        "Shilgad",
        "\u0634\u0644 \u06af\u062f"
    ],
    "wof:name":"Shilgad",
    "wof:placetype":"locality"
},
  "geometry": {"coordinates":[69.04948,33.5575],"type":"Point"}
}