{
  "type": "Feature",
  "properties": {
    "gn:admin1_code":"28",
    "gn:admin2_code":"2501",
    "gn:asciiname":"Kajbaz",
    "gn:country_code":"AF",
    "gn:dem":1523,
    "gn:feature_class":"P",
    "gn:feature_code":"PPL",
    "gn:name":"Kajb\u0101z",
    "gn:population":0,
    "gn:timezone":"Asia/Kabul",
    "iso:country":"AF",
    "name:fas_x_preferred":[
        "\u0643\u062c \u0628\u0627\u0632"
    ],
    "name:und_x_variant":[
        "Kadzhbaz",
        "Kajb\u0101z",
        "\u06a9\u062c\u0628\u0627\u0632",
        "\u0643\u062c \u0628\u0627\u0632"
    ],
    "wof:name":"Kajbaz",
    "wof:placetype":"locality"
},
  "geometry": {"coordinates":[66.86454999999999,32.05045],"type":"Point"}
}