{
  "type": "Feature",
  "properties": {
    "gn:admin1_code":"41",
    "gn:admin2_code":"3404",
    "gn:asciiname":"Gharme Pay",
    "gn:country_code":"AF",
    "gn:dem":1607,
    "gn:feature_class":"P",
    "gn:feature_code":"PPL",
    "gn:name":"Gharm\u0113 P\u0101y",
    "gn:population":0,
    "gn:timezone":"Asia/Kabul",
    "iso:country":"AF",
    "name:fas_x_preferred":[
        "\u063a\u0631\u0645\u0647 \u067e\u0627\u06cc"
    ],
    "name:rus_x_preferred":[
        "\u041f\u043e\u0442\u044c\u044f\u043d"
    ],
    "name:rus_x_variant":[
        "\u0413\u0430\u0440\u043c\u0435\u043f\u0430\u0439"
    ],
    "name:und_x_variant":[
        "P\u014dty\u0101n",
        "Pot\u2019yan",
        "Garmepay",
        "Gharmeh P\u0101y",
        "Gharm\u0113 P\u0101y",
        "\u063a\u0631\u0645\u06d0 \u067e\u0627\u06cc",
        "P\u014dtiy\u0101n",
        "\u067e\u0648\u062a\u06cc\u0627\u0646"
    ],
    "wof:name":"Gharme Pay",
    "wof:placetype":"locality"
},
  "geometry": {"coordinates":[65.42872,33.14448],"type":"Point"}
}