{
  "type": "Feature",
  "properties": {
    "gn:admin1_code":"17",
    "gn:admin2_code":"501",
    "gn:asciiname":"Shash Qal'ah",
    "gn:country_code":"AF",
    "gn:dem":1893,
    "gn:feature_class":"P",
    "gn:feature_code":"PPL",
    "gn:name":"Shash Qal\u2018ah",
    "gn:population":0,
    "gn:timezone":"Asia/Kabul",
    "iso:country":"AF",
    "name:und_x_variant":[
        "Shashkala",
        "\u0160a\u0161qal\u2019a",
        "Shashqal\u2019a",
        "Shesh Qal\u2018eh",
        "Shash Qal\u2018ah",
        "\u0634\u0634 \u0642\u0644\u0639\u0647"
    ],
    "wof:name":"Shash Qal'ah",
    "wof:placetype":"locality"
},
  "geometry": {"coordinates":[69.02266999999999,34.03064000000001],"type":"Point"}
}