{
  "type": "Feature",
  "properties": {
    "gn:admin1_code":"29",
    "gn:admin2_code":"2906.0",
    "gn:asciiname":"Mir Salam Khunah",
    "gn:country_code":"AF",
    "gn:dem":2315,
    "gn:feature_class":"P",
    "gn:feature_code":"PPL",
    "gn:name":"M\u012br Sal\u0101m Kh\u016bnah",
    "gn:population":0,
    "gn:timezone":"Asia/Kabul",
    "iso:country":"AF",
    "name:fas_x_preferred":[
        "M\u012br Sal\u0101m Kh\u016bnah"
    ],
    "name:fas_x_variant":[
        "\u0645\u06cc\u0631\u0633\u0644\u0627\u0645 \u062e\u0648\u0646\u06cc"
    ],
    "name:und_x_variant":[
        "Mirsalamkhune",
        "M\u012b\u1e5fsal\u0101m Kh\u016bn\u0113"
    ],
    "wof:name":"Mir Salam Khunah",
    "wof:placetype":"locality"
},
  "geometry": {"coordinates":[68.81111999999999,32.69842],"type":"Point"}
}