{
  "type": "Feature",
  "properties": {
    "gn:admin1_code":"32",
    "gn:admin2_code":"1506",
    "gn:asciiname":"Zowara",
    "gn:country_code":"AF",
    "gn:dem":2483,
    "gn:feature_class":"P",
    "gn:feature_code":"PPL",
    "gn:name":"Zow\u0101r\u0101",
    "gn:population":0,
    "gn:timezone":"Asia/Kabul",
    "iso:country":"AF",
    "name:und_x_variant":[
        "Zow\u0101r\u0101",
        "\u0632\u0648\u0627\u0631\u0627",
        "Zaw\u0101r\u0101"
    ],
    "wof:name":"Zowara",
    "wof:placetype":"locality"
},
  "geometry": {"coordinates":[68.30410999999999,35.89823],"type":"Point"}
}