{
  "type": "Feature",
  "properties": {
    "gn:admin1_code":"01",
    "gn:admin2_code":"1106",
    "gn:asciiname":"Qal'ah-ye Ust",
    "gn:country_code":"AF",
    "gn:dem":2921,
    "gn:feature_class":"P",
    "gn:feature_code":"PPL",
    "gn:name":"Qal\u2018ah-ye \u016ast",
    "gn:population":0,
    "gn:timezone":"Asia/Kabul",
    "iso:country":"AF",
    "name:rus_x_preferred":[
        "\u041a\u0430\u043b\u0430\u0439\u0438-\u0423\u0441\u0442"
    ],
    "name:und_x_variant":[
        "Qal\u2018a-i-\u016ast",
        "Kala Wust",
        "Qal\u2018eh-ye Vost",
        "Qala Wust",
        "Qala Yost",
        "\u016ast",
        "Qal\u2018ah-ye \u016ast",
        "\u0642\u0644\u0639\u0647 \u0648\u0633\u062a"
    ],
    "wof:name":"Qal'ah-ye Ust",
    "wof:placetype":"locality"
},
  "geometry": {"coordinates":[72.84657,36.97198],"type":"Point"}
}