{
  "type": "Feature",
  "properties": {
    "gn:admin1_code":"18",
    "gn:admin2_code":"819.0",
    "gn:asciiname":"Sarband",
    "gn:country_code":"AF",
    "gn:dem":649,
    "gn:feature_class":"P",
    "gn:feature_code":"PPL",
    "gn:name":"Sarband",
    "gn:population":0,
    "gn:timezone":"Asia/Kabul",
    "iso:country":"AF",
    "name:deu_x_preferred":[
        "Ensemble Sarband"
    ],
    "name:nor_x_preferred":[
        "Ensemble Sarband"
    ],
    "name:tur_x_preferred":[
        "Sarband"
    ],
    "name:und_x_variant":[
        "\u0633\u0631\u0628\u0646\u062f"
    ],
    "wof:name":"Sarband",
    "wof:placetype":"locality"
},
  "geometry": {"coordinates":[70.73079,34.59658],"type":"Point"}
}