{
  "type": "Feature",
  "properties": {
    "gn:admin1_code":"28",
    "gn:admin2_code":"2506.0",
    "gn:asciiname":"Lashtay",
    "gn:country_code":"AF",
    "gn:dem":1393,
    "gn:feature_class":"P",
    "gn:feature_code":"PPL",
    "gn:name":"Lashtay",
    "gn:population":0,
    "gn:timezone":"Asia/Kabul",
    "iso:country":"AF",
    "name:und_x_variant":[
        "Lastay",
        "La\u0161tay",
        "\u0644\u0634\u062a\u06cc",
        "Lashtay"
    ],
    "wof:name":"Lashtay",
    "wof:placetype":"locality"
},
  "geometry": {"coordinates":[66.57341,31.91968],"type":"Point"}
}