{
  "type": "Feature",
  "properties": {
    "gn:admin1_code":"26",
    "gn:admin2_code":"1202",
    "gn:asciiname":"Khosh Bakht",
    "gn:country_code":"AF",
    "gn:dem":1143,
    "gn:feature_class":"P",
    "gn:feature_code":"PPL",
    "gn:name":"Kh\u014dsh Bakht",
    "gn:population":0,
    "gn:timezone":"Asia/Kabul",
    "iso:country":"AF",
    "name:und_x_variant":[
        "Khu\u0161 Bakht",
        "Khush Bakht",
        "Khvoshbakht",
        "Kh\u014dsh Bakht",
        "\u062e\u0648\u0634 \u0628\u062e\u062a"
    ],
    "wof:name":"Khosh Bakht",
    "wof:placetype":"locality"
},
  "geometry": {"coordinates":[69.34003,36.48535],"type":"Point"}
}