{
  "type": "Feature",
  "properties": {
    "gn:admin1_code":"2",
    "gn:admin2_code":"1904.0",
    "gn:asciiname":"Dahan-e Ab-e Gharmah",
    "gn:country_code":"AF",
    "gn:dem":1440,
    "gn:feature_class":"P",
    "gn:feature_code":"PPL",
    "gn:name":"Dah\u0101n-e \u0100b-e Gharmah",
    "gn:population":0,
    "gn:timezone":"Asia/Kabul",
    "iso:country":"AF",
    "name:und_x_variant":[
        "\u1e0e\u0101hane \u0100be Gha\u1e5fma",
        "Dahan-e \u0100b-e Gharmah",
        "Dah\u0101n-e \u0100b-e Gharmah",
        "\u062f\u0647\u0627\u0646 \u0622\u0628 \u063a\u0631\u0645\u0647"
    ],
    "wof:name":"Dahan-e Ab-e Gharmah",
    "wof:placetype":"locality"
},
  "geometry": {"coordinates":[64.0986,35.27198],"type":"Point"}
}