{
  "type": "Feature",
  "properties": {
    "gn:admin1_code":"14",
    "gn:admin2_code":"202.0",
    "gn:asciiname":"Nasir Khan Khel",
    "gn:country_code":"AF",
    "gn:dem":1584,
    "gn:feature_class":"P",
    "gn:feature_code":"PPL",
    "gn:name":"N\u0101\u015fir Kh\u0101n Kh\u0113l",
    "gn:population":0,
    "gn:timezone":"Asia/Kabul",
    "iso:country":"AF",
    "name:fas_x_preferred":[
        "\u0646\u0627\u0635\u0631 \u062e\u0627\u0646 \u062e\u064a\u0644"
    ],
    "name:rus_x_preferred":[
        "Nasirkhankheyl\u2019"
    ],
    "name:und_x_variant":[
        "N\u0101\u015fe\u1e5fkh\u0101nkh\u0113l",
        "N\u0101\u015fer Kh\u0101n Kheyl",
        "N\u0101\u015fir Kh\u0101n Kh\u0113l",
        "\u0646\u0627\u0635\u0631 \u062e\u0627\u0646 \u062e\u06d0\u0644"
    ],
    "wof:name":"Nasir Khan Khel",
    "wof:placetype":"locality"
},
  "geometry": {"coordinates":[69.31560999999999,35.12452],"type":"Point"}
}