{
  "type": "Feature",
  "properties": {
    "gn:admin1_code":"03",
    "gn:admin2_code":"1303",
    "gn:asciiname":"Larkhowi",
    "gn:country_code":"AF",
    "gn:dem":656,
    "gn:feature_class":"P",
    "gn:feature_code":"PPL",
    "gn:name":"Larkhow\u012b",
    "gn:population":0,
    "gn:timezone":"Asia/Kabul",
    "iso:country":"AF",
    "name:und_x_variant":[
        "Larkhavi",
        "Larkhaw\u012b",
        "Larkhow\u012b",
        "\u0644\u0631\u062e\u0648\u06cc"
    ],
    "wof:name":"Larkhowi",
    "wof:placetype":"locality"
},
  "geometry": {"coordinates":[68.60468,35.90452],"type":"Point"}
}