{
  "type": "Feature",
  "properties": {
    "gn:admin1_code":"17",
    "gn:admin2_code":"501.0",
    "gn:asciiname":"Harun Khel",
    "gn:country_code":"AF",
    "gn:dem":1879,
    "gn:feature_class":"P",
    "gn:feature_code":"PPL",
    "gn:name":"H\u0101r\u016bn Kh\u0113l",
    "gn:population":0,
    "gn:timezone":"Asia/Kabul",
    "iso:country":"AF",
    "name:rus_x_preferred":[
        "Kharunkheyl\u2019"
    ],
    "name:und_x_variant":[
        "H\u0101r\u016bn Kh\u0113l Muhajir\u012bn",
        "H\u0101r\u016bnkh\u0113l",
        "H\u0101r\u016bn Kh\u0113l",
        "\u0647\u0627\u062f\u0648\u0646 \u062e\u06d0\u0644"
    ],
    "wof:name":"Harun Khel",
    "wof:placetype":"locality"
},
  "geometry": {"coordinates":[69.05589999999999,34.09891],"type":"Point"}
}