{
  "type": "Feature",
  "properties": {
    "gn:admin1_code":"18",
    "gn:admin2_code":"818.0",
    "gn:asciiname":"Arbapan",
    "gn:country_code":"AF",
    "gn:dem":544,
    "gn:feature_class":"P",
    "gn:feature_code":"PPL",
    "gn:name":"Arb\u0101p\u0101n",
    "gn:population":0,
    "gn:timezone":"Asia/Kabul",
    "iso:country":"AF",
    "name:fas_x_preferred":[
        "\u0627\u0631\u0628\u0627\u067e\u0627\u0646"
    ],
    "name:und_x_variant":[
        "Arbalan",
        "Arb\u0101p\u0101n",
        "\u0622\u0631\u0628\u0627\u067e\u0627\u0646"
    ],
    "wof:name":"Arbapan",
    "wof:placetype":"locality"
},
  "geometry": {"coordinates":[70.58896999999997,34.43948],"type":"Point"}
}