{
  "type": "Feature",
  "properties": {
    "gn:admin1_code":"32",
    "gn:admin2_code":"1501.0",
    "gn:asciiname":"Khwajah Sang Bur",
    "gn:country_code":"AF",
    "gn:dem":1691,
    "gn:feature_class":"P",
    "gn:feature_code":"PPL",
    "gn:name":"Khw\u0101jah Sang Bur",
    "gn:population":0,
    "gn:timezone":"Asia/Kabul",
    "iso:country":"AF",
    "name:und_x_variant":[
        "Khw\u0101ja Sang Bu\u1e5f",
        "Khv\u0101jeh Sang Bor",
        "Khw\u0101jah Sang Bur",
        "\u062e\u0648\u0627\u062c\u0647 \u0633\u0646\u06af \u0628\u0631"
    ],
    "wof:name":"Khwajah Sang Bur",
    "wof:placetype":"locality"
},
  "geometry": {"coordinates":[68.0772,36.31761],"type":"Point"}
}