{
  "type": "Feature",
  "properties": {
    "gn:admin1_code":"23",
    "gn:admin2_code":"2412",
    "gn:asciiname":"Tozhnah",
    "gn:country_code":"AF",
    "gn:dem":1687,
    "gn:feature_class":"P",
    "gn:feature_code":"PPL",
    "gn:name":"T\u014dzhnah",
    "gn:population":0,
    "gn:timezone":"Asia/Kabul",
    "iso:country":"AF",
    "name:rus_x_preferred":[
        "\u0422\u043e\u0437\u043d\u0430"
    ],
    "name:und_x_variant":[
        "To\u017ena",
        "Tozna",
        "T\u014dzhnah",
        "T\u016bzhnah",
        "\u062a\u0648\u0698\u0646\u0647"
    ],
    "wof:name":"Tozhnah",
    "wof:placetype":"locality"
},
  "geometry": {"coordinates":[66.80436999999999,31.24776],"type":"Point"}
}