{
  "type": "Feature",
  "properties": {
    "gn:admin1_code":"6",
    "gn:admin2_code":"2105.0",
    "gn:asciiname":"Azow",
    "gn:country_code":"AF",
    "gn:dem":1293,
    "gn:feature_class":"P",
    "gn:feature_code":"PPL",
    "gn:name":"Azow",
    "gn:population":0,
    "gn:timezone":"Asia/Kabul",
    "iso:country":"AF",
    "name:und_x_variant":[
        "\u0627\u0632\u0648",
        "Qaryeh-ye Az\u0101b"
    ],
    "wof:name":"Azow",
    "wof:placetype":"locality"
},
  "geometry": {"coordinates":[62.97926,33.07354],"type":"Point"}
}