{
  "type": "Feature",
  "properties": {
    "gn:admin1_code":"13",
    "gn:admin2_code":"112",
    "gn:asciiname":"Gogamundah",
    "gn:country_code":"AF",
    "gn:dem":1128,
    "gn:feature_class":"P",
    "gn:feature_code":"PPL",
    "gn:name":"G\u014dg\u0101mundah",
    "gn:population":0,
    "gn:timezone":"Asia/Kabul",
    "iso:country":"AF",
    "name:und_x_variant":[
        "Kukamend",
        "Gowg\u0101mand\u012b",
        "Gogamunda",
        "G\u014dg\u0101mun\u1e0fa",
        "Gogamandai",
        "Gogam\u0101ndah",
        "Gowg\u0101mondah",
        "G\u014dg\u0101mundah",
        "G\u014dg\u0101mundah K\u00ealay",
        "\u06af\u0648\u06af\u0627\u0645\u0646\u062f\u0647 \u06a9\u0644\u06cc",
        "\u06af\u0648\u06af\u0627\u0645\u0646\u062f\u0647"
    ],
    "wof:name":"Gogamundah",
    "wof:placetype":"locality"
},
  "geometry": {"coordinates":[69.59585,34.57897],"type":"Point"}
}