{
  "type": "Feature",
  "properties": {
    "gn:admin1_code":"42",
    "gn:admin2_code":"3302.0",
    "gn:asciiname":"Bab 'Ali",
    "gn:country_code":"AF",
    "gn:dem":2318,
    "gn:feature_class":"P",
    "gn:feature_code":"PPL",
    "gn:name":"B\u0101b \u2018Al\u012b",
    "gn:population":0,
    "gn:timezone":"Asia/Kabul",
    "iso:country":"AF",
    "name:rus_x_preferred":[
        "\u0411\u0430\u0431\u0430\u043b\u0438"
    ],
    "name:und_x_variant":[
        "Babali",
        "B\u0101b \u2018Al\u012b",
        "\u0628\u0627\u0628 \u0639\u0644\u06cc"
    ],
    "wof:name":"Bab 'Ali",
    "wof:placetype":"locality"
},
  "geometry": {"coordinates":[69.68085000000001,35.26943],"type":"Point"}
}