{
  "type": "Feature",
  "properties": {
    "gn:admin1_code":"08",
    "gn:admin2_code":"604",
    "gn:asciiname":"Now Qal'ah",
    "gn:country_code":"AF",
    "gn:dem":3060,
    "gn:feature_class":"P",
    "gn:feature_code":"PPL",
    "gn:name":"Now Qal\u2018ah",
    "gn:population":0,
    "gn:timezone":"Asia/Kabul",
    "iso:country":"AF",
    "name:fas_x_preferred":[
        "\u0642\u0644\u0639\u0647\u0654 \u0646\u0648"
    ],
    "name:rus_x_preferred":[
        "\u041d\u0430\u0443\u043a\u0430\u043b\u0430"
    ],
    "name:und_x_variant":[
        "Now Qal\u0101",
        "Nawqal\u0101",
        "Naukala",
        "Nowqal\u2018eh",
        "Now Qal\u2018ah",
        "\u0646\u0648 \u0642\u0644\u0639\u0647"
    ],
    "wof:name":"Now Qal'ah",
    "wof:placetype":"locality"
},
  "geometry": {"coordinates":[67.53893000000001,33.76552],"type":"Point"}
}