{
  "type": "Feature",
  "properties": {
    "gn:admin1_code":"18",
    "gn:admin2_code":"815",
    "gn:asciiname":"Nur Khan Kelay",
    "gn:country_code":"AF",
    "gn:dem":1147,
    "gn:feature_class":"P",
    "gn:feature_code":"PPL",
    "gn:name":"N\u016br Kh\u0101n K\u00ealay",
    "gn:population":0,
    "gn:timezone":"Asia/Kabul",
    "iso:country":"AF",
    "name:fas_x_preferred":[
        "\u0642\u0631\u064a\u06c0 \u0646\u0648\u0631 \u062e\u0627\u0646"
    ],
    "name:und_x_variant":[
        "Nurkhankalay",
        "N\u016br Kh\u0101n K\u00ealay",
        "N\u016b\u1e5fkh\u0101n Kalay",
        "\u0646\u0648\u0631 \u062e\u0627\u0646 \u06a9\u0644\u06cc"
    ],
    "wof:name":"Nur Khan Kelay",
    "wof:placetype":"locality"
},
  "geometry": {"coordinates":[71.03943000000002,34.39911],"type":"Point"}
}