{
  "type": "Feature",
  "properties": {
    "gn:admin1_code":"34",
    "gn:admin2_code":"1012.0",
    "gn:asciiname":"Bargor",
    "gn:country_code":"AF",
    "gn:dem":1335,
    "gn:feature_class":"P",
    "gn:feature_code":"PPL",
    "gn:name":"Barg\u014dr",
    "gn:population":0,
    "gn:timezone":"Asia/Kabul",
    "iso:country":"AF",
    "name:und_x_variant":[
        "Ba\u1e5fg\u014dr",
        "Bargor",
        "Ba\u1e5fg\u016br",
        "Barg\u014dr",
        "\u0628\u0631\u06af\u0648\u0631"
    ],
    "wof:name":"Bargor",
    "wof:placetype":"locality"
},
  "geometry": {"coordinates":[70.85488000000002,34.7702],"type":"Point"}
}