{
  "type": "Feature",
  "properties": {
    "gn:admin1_code":"01",
    "gn:admin2_code":"1106",
    "gn:asciiname":"Qazi Deh",
    "gn:country_code":"AF",
    "gn:dem":2603,
    "gn:feature_class":"P",
    "gn:feature_code":"PPL",
    "gn:name":"Q\u0101\u1e95\u012b Deh",
    "gn:population":0,
    "gn:timezone":"Asia/Kabul",
    "iso:country":"AF",
    "name:und_x_variant":[
        "Q\u0101dz\u012b \u1e0eeh",
        "Q\u0101z\u012b Deh (1)",
        "Q\u0101\u1e95\u012b Deh",
        "\u0642\u0627\u0636\u0649 \u062f\u0647"
    ],
    "wof:name":"Qazi Deh",
    "wof:placetype":"locality"
},
  "geometry": {"coordinates":[71.76646,36.67086],"type":"Point"}
}