{
  "type": "Feature",
  "properties": {
    "gn:admin1_code":"8",
    "gn:admin2_code":"615.0",
    "gn:asciiname":"Qal'ah-ye 'Alam",
    "gn:country_code":"AF",
    "gn:dem":2114,
    "gn:feature_class":"P",
    "gn:feature_code":"PPL",
    "gn:name":"Qal\u2018ah-ye \u2018\u0100lam",
    "gn:population":0,
    "gn:timezone":"Asia/Kabul",
    "iso:country":"AF",
    "name:und_x_variant":[
        "Qal\u2018a-i \u2018\u0100lam",
        "Qal\u2018ah-ye \u2018Alam",
        "Qal\u2018eh-ye \u2018\u0100lam",
        "Qal\u2018ah-ye \u2018\u0100lam",
        "\u0642\u0644\u0639\u06c0 \u0639\u0627\u0644\u0645"
    ],
    "wof:name":"Qal'ah-ye 'Alam",
    "wof:placetype":"locality"
},
  "geometry": {"coordinates":[68.51668000000001,33.45593],"type":"Point"}
}