{
  "type": "Feature",
  "properties": {
    "gn:admin1_code":"01",
    "gn:admin2_code":"1115.0",
    "gn:asciiname":"Katah Qishlaq",
    "gn:country_code":"AF",
    "gn:dem":1702,
    "gn:feature_class":"P",
    "gn:feature_code":"PPL",
    "gn:name":"Katah Qishl\u0101q",
    "gn:population":0,
    "gn:timezone":"Asia/Kabul",
    "iso:country":"AF",
    "name:und_x_variant":[
        "Kata Qe\u0161l\u0101q",
        "Katah Qeshl\u0101q",
        "Katah Qishl\u0101q",
        "\u06a9\u062a\u0647 \u0642\u0634\u0644\u0627\u0642"
    ],
    "wof:name":"Katah Qishlaq",
    "wof:placetype":"locality"
},
  "geometry": {"coordinates":[70.32417,37.09845],"type":"Point"}
}