{
  "type": "Feature",
  "properties": {
    "gn:admin1_code":"08",
    "gn:admin2_code":"604",
    "gn:asciiname":"Shiniah",
    "gn:country_code":"AF",
    "gn:dem":2894,
    "gn:feature_class":"P",
    "gn:feature_code":"PPL",
    "gn:name":"Sh\u012bn\u012bah",
    "gn:population":0,
    "gn:timezone":"Asia/Kabul",
    "iso:country":"AF",
    "name:rus_x_preferred":[
        "Shin\u2019ya"
    ],
    "name:und_x_variant":[
        "\u0160\u012bnya",
        "Sh\u012bnyeh",
        "Shinyah",
        "Sh\u012bn\u012bah",
        "\u0634\u06cc\u0646\u06cc\u0647"
    ],
    "wof:name":"Shiniah",
    "wof:placetype":"locality"
},
  "geometry": {"coordinates":[67.50693000000001,34.04190999999999],"type":"Point"}
}