{
  "type": "Feature",
  "properties": {
    "gn:admin1_code":"01",
    "gn:admin2_code":"1109",
    "gn:asciiname":"Wistachi",
    "gn:country_code":"AF",
    "gn:dem":2855,
    "gn:feature_class":"P",
    "gn:feature_code":"PPL",
    "gn:name":"W\u012bst\u0101ch\u012b",
    "gn:population":0,
    "gn:timezone":"Asia/Kabul",
    "iso:country":"AF",
    "name:und_x_variant":[
        "W\u012bst\u0101ci",
        "\u0648\u06cc\u0633\u062a\u0627\u0686\u06cc",
        "W\u012bst\u0101ch\u012b"
    ],
    "wof:name":"Wistachi",
    "wof:placetype":"locality"
},
  "geometry": {"coordinates":[71.40955,37.38122],"type":"Point"}
}