{
  "type": "Feature",
  "properties": {
    "gn:admin1_code":"05",
    "gn:admin2_code":"2801",
    "gn:asciiname":"Surkh Joy",
    "gn:country_code":"AF",
    "gn:dem":2971,
    "gn:feature_class":"P",
    "gn:feature_code":"PPL",
    "gn:name":"Surkh J\u014dy",
    "gn:population":0,
    "gn:timezone":"Asia/Kabul",
    "iso:country":"AF",
    "name:und_x_variant":[
        "Su\u1e5fkhj\u014dy",
        "Surkhdzhoy",
        "Sorkh J\u014dy",
        "Sorkhj\u016by",
        "Surkh J\u014dy",
        "\u0633\u0631\u062e \u062c\u0648\u06cc"
    ],
    "wof:name":"Surkh Joy",
    "wof:placetype":"locality"
},
  "geometry": {"coordinates":[67.70323,34.74554000000001],"type":"Point"}
}