{
  "type": "Feature",
  "properties": {
    "gn:admin1_code":"06",
    "gn:admin2_code":"2104",
    "gn:asciiname":"Qaryah-ye Gaym Bagh",
    "gn:country_code":"AF",
    "gn:dem":1174,
    "gn:feature_class":"P",
    "gn:feature_code":"PPL",
    "gn:name":"Qaryah-ye Gaym B\u0101gh",
    "gn:population":0,
    "gn:timezone":"Asia/Kabul",
    "iso:country":"AF",
    "name:und_x_variant":[
        "Qa\u1e5fya-i-G\u0113mb\u0101gh",
        "Qaryah-ye Gaym B\u0101gh",
        "\u0642\u0631\u06cc\u06c0 \u06af\u06cc\u0645 \u0628\u0627\u063a",
        "Qaryeh-ye G\u0113mb\u0101gh"
    ],
    "wof:name":"Qaryah-ye Gaym Bagh",
    "wof:placetype":"locality"
},
  "geometry": {"coordinates":[63.50455,33.15746],"type":"Point"}
}