{
  "type": "Feature",
  "properties": {
    "gn:admin1_code":"10",
    "gn:admin2_code":"2303",
    "gn:asciiname":"Mazar-e 'Ulya",
    "gn:country_code":"AF",
    "gn:dem":1077,
    "gn:feature_class":"P",
    "gn:feature_code":"PPL",
    "gn:name":"Maz\u0101r-e \u2018Uly\u0101",
    "gn:population":0,
    "gn:timezone":"Asia/Kabul",
    "iso:country":"AF",
    "name:und_x_variant":[
        "Maz\u0101\u1e5fe \u2018Ulya",
        "Mazari-Ulia",
        "Mazar",
        "Maz\u0101r-e \u2018Uly\u0101",
        "\u0645\u0632\u0627\u0631 \u0639\u0644\u06cc\u0627",
        "Maz\u0101r-e \u2018Oly\u0101"
    ],
    "wof:name":"Mazar-e 'Ulya",
    "wof:placetype":"locality"
},
  "geometry": {"coordinates":[65.12998,32.44425],"type":"Point"}
}