{
  "type": "Feature",
  "properties": {
    "gn:admin1_code":"29",
    "gn:admin2_code":"2908.0",
    "gn:asciiname":"Izah'i",
    "gn:country_code":"AF",
    "gn:dem":2406,
    "gn:feature_class":"P",
    "gn:feature_code":"PPL",
    "gn:name":"Izah\u2019\u012b",
    "gn:population":0,
    "gn:timezone":"Asia/Kabul",
    "iso:country":"AF",
    "name:und_x_variant":[
        "Eza\u2019i",
        "Izai",
        "Iza\u2019i",
        "Izahay\u012b",
        "Izah\u2019\u012b",
        "\u0627\u0632\u0647 \u0626\u06cc"
    ],
    "wof:name":"Izah'i",
    "wof:placetype":"locality"
},
  "geometry": {"coordinates":[69.08901,32.78174],"type":"Point"}
}