{
  "type": "Feature",
  "properties": {
    "gn:admin1_code":"27",
    "gn:admin2_code":"402.0",
    "gn:asciiname":"Dahan-e Dar-e Boghah",
    "gn:country_code":"AF",
    "gn:dem":2531,
    "gn:feature_class":"P",
    "gn:feature_code":"PPL",
    "gn:name":"Dahan-e Dar-e B\u014dghah",
    "gn:population":0,
    "gn:timezone":"Asia/Kabul",
    "iso:country":"AF",
    "name:und_x_variant":[
        "Dakhani-Dari-Boga",
        "\u1e0eahane \u1e0ea\u1e5fe B\u014dgha",
        "Dahan-e Darah-ye B\u014dghah",
        "Dahan-e Dar-e B\u016bghah",
        "Dahan-e Dar-e B\u014dghah",
        "\u062f\u0647\u0646 \u062f\u0632 \u0628\u0648\u063a\u0647"
    ],
    "wof:name":"Dahan-e Dar-e Boghah",
    "wof:placetype":"locality"
},
  "geometry": {"coordinates":[68.52318000000001,34.44102],"type":"Point"}
}