{
  "type": "Feature",
  "properties": {
    "gn:admin1_code":"8",
    "gn:admin2_code":"614.0",
    "gn:asciiname":"Chor",
    "gn:country_code":"AF",
    "gn:dem":2088,
    "gn:feature_class":"P",
    "gn:feature_code":"PPL",
    "gn:name":"Chor",
    "gn:population":0,
    "gn:timezone":"Asia/Kabul",
    "iso:country":"AF",
    "name:fas_x_preferred":[
        "\u0686\u0648\u0631"
    ],
    "name:und_x_variant":[
        "\u010cor",
        "Chor",
        "Ch\u014dr",
        "Ch\u016b\u1e5f",
        "Ch\u014d\u1e5f",
        "\u0686\u0648\u0693"
    ],
    "wof:name":"Chor",
    "wof:placetype":"locality"
},
  "geometry": {"coordinates":[68.42164,33.35889],"type":"Point"}
}