{
  "type": "Feature",
  "properties": {
    "gn:admin1_code":"11",
    "gn:admin2_code":"2002.0",
    "gn:asciiname":"Qal'ah-ye Mukhtar",
    "gn:country_code":"AF",
    "gn:dem":972,
    "gn:feature_class":"P",
    "gn:feature_code":"PPL",
    "gn:name":"Qal\u2018ah-ye Mukht\u0101r",
    "gn:population":0,
    "gn:timezone":"Asia/Kabul",
    "iso:country":"AF",
    "name:und_x_variant":[
        "Kalayi-Mukhtar",
        "Qal\u2018eh-ye Mukht\u0101r",
        "Qal\u2018a-i-Mukht\u0101\u1e5f",
        "Qal\u2018eh-ye Mokht\u0101r",
        "Qal\u2018ah-ye Mukht\u0101r",
        "\u0642\u0644\u0639\u06c0 \u0645\u062e\u062a\u0627\u0631"
    ],
    "wof:name":"Qal'ah-ye Mukhtar",
    "wof:placetype":"locality"
},
  "geometry": {"coordinates":[62.31997,34.32997],"type":"Point"}
}