{
  "type": "Feature",
  "properties": {
    "gn:admin1_code":"35",
    "gn:admin2_code":"902.0",
    "gn:asciiname":"Perozabad",
    "gn:country_code":"AF",
    "gn:dem":609,
    "gn:feature_class":"P",
    "gn:feature_code":"PPL",
    "gn:name":"Perozabad",
    "gn:population":0,
    "gn:timezone":"Asia/Kabul",
    "iso:country":"AF",
    "name:und_x_variant":[
        "P\u0113\u1e5f\u014dz\u0101b\u0101\u1e0f",
        "P\u012br\u016bz\u0101b\u0101d",
        "P\u0113r\u014dz\u0101b\u0101d",
        "\u067e\u06d0\u0631\u0648\u0632 \u0622\u0628\u0627\u062f",
        "Fayr\u014dz\u0101b\u0101d",
        "\u0641\u06cc\u0631\u0648\u0632 \u0622\u0628\u0627\u062f"
    ],
    "wof:name":"Perozabad",
    "wof:placetype":"locality"
},
  "geometry": {"coordinates":[70.29489000000001,34.5046],"type":"Point"}
}