{
  "type": "Feature",
  "properties": {
    "gn:admin1_code":"24",
    "gn:admin2_code":"1401",
    "gn:asciiname":"Za Khel",
    "gn:country_code":"AF",
    "gn:dem":399,
    "gn:feature_class":"P",
    "gn:feature_code":"PPL",
    "gn:name":"Z\u0101 Kh\u0113l",
    "gn:population":0,
    "gn:timezone":"Asia/Kabul",
    "iso:country":"AF",
    "name:fas_x_preferred":[
        "\u0632\u0647 \u062e\u064a\u0644"
    ],
    "name:rus_x_preferred":[
        "\u0417\u0430\u0445\u0435\u0439\u043b\u044c"
    ],
    "name:und_x_variant":[
        "Za Kheyl",
        "Z\u0101 Kh\u0113l",
        "Zakheyl\u2019",
        "Zah Kheyl",
        "\u0632\u0627 \u062e\u06d0\u0644"
    ],
    "wof:name":"Za Khel",
    "wof:placetype":"locality"
},
  "geometry": {"coordinates":[68.84598000000001,36.70357],"type":"Point"}
}