{
  "type": "Feature",
  "properties": {
    "gn:admin1_code":"13",
    "gn:admin2_code":"112.0",
    "gn:asciiname":"Zandeh Kelay",
    "gn:country_code":"AF",
    "gn:dem":2123,
    "gn:feature_class":"P",
    "gn:feature_code":"PPL",
    "gn:name":"Z\u0101nd\u00eah K\u00ealay",
    "gn:population":0,
    "gn:timezone":"Asia/Kabul",
    "iso:country":"AF",
    "name:fas_x_preferred":[
        "\u0642\u0631\u064a\u06c0 \u0632\u0627\u0646\u062f\u0647"
    ],
    "name:und_x_variant":[
        "Zandekhkalay",
        "Z\u0101ndah K\u00ealay",
        "Z\u0101ndeh Kalay",
        "Z\u0101nd\u00eah K\u00ealay",
        "\u0632\u0627\u0646\u062f\u0647 \u06a9\u0644\u06cc"
    ],
    "wof:name":"Zandeh Kelay",
    "wof:placetype":"locality"
},
  "geometry": {"coordinates":[69.57701999999999,34.35221],"type":"Point"}
}