{
  "type": "Feature",
  "properties": {
    "gn:admin1_code":"28",
    "gn:admin2_code":"2504",
    "gn:asciiname":"Mulla Shadi Kelay",
    "gn:country_code":"AF",
    "gn:dem":1835,
    "gn:feature_class":"P",
    "gn:feature_code":"PPL",
    "gn:name":"Mull\u0101 Sh\u0101d\u012b K\u00ealay",
    "gn:population":0,
    "gn:timezone":"Asia/Kabul",
    "iso:country":"AF",
    "name:fas_x_preferred":[
        "\u0645\u0644\u0627 \u0634\u0627\u062f\u06cc \u0643\u0644\u06cc"
    ],
    "name:und_x_variant":[
        "Mull\u0101 \u0160\u0101di Kalay",
        "Mulla-Shadi-Kalay",
        "Mull\u0101 Sh\u0101d\u012b K\u00ealay",
        "\u0645\u0644\u0627 \u0634\u0627\u062f\u06cc \u06a9\u0644\u06cc",
        "Moll\u0101 Sh\u0101d\u012b Kalay"
    ],
    "wof:name":"Mulla Shadi Kelay",
    "wof:placetype":"locality"
},
  "geometry": {"coordinates":[66.73446,32.54522],"type":"Point"}
}