{
  "type": "Feature",
  "properties": {
    "gn:admin1_code":"28",
    "gn:admin2_code":"2507.0",
    "gn:asciiname":"Tushili",
    "gn:country_code":"AF",
    "gn:dem":2080,
    "gn:feature_class":"P",
    "gn:feature_code":"PPL",
    "gn:name":"T\u016bshil\u012b",
    "gn:population":0,
    "gn:timezone":"Asia/Kabul",
    "iso:country":"AF",
    "name:und_x_variant":[
        "T\u016b\u0161eli",
        "T\u016bshil\u012b",
        "\u062a\u0648\u0634\u0644\u06cc",
        "Towshel\u012b"
    ],
    "wof:name":"Tushili",
    "wof:placetype":"locality"
},
  "geometry": {"coordinates":[67.12430999999999,31.98716],"type":"Point"}
}