{
  "type": "Feature",
  "properties": {
    "gn:admin1_code":"27",
    "gn:admin2_code":"403.0",
    "gn:asciiname":"Kamar",
    "gn:country_code":"AF",
    "gn:dem":3021,
    "gn:feature_class":"P",
    "gn:feature_code":"PPL",
    "gn:name":"Kamar",
    "gn:population":0,
    "gn:timezone":"Asia/Kabul",
    "iso:country":"AF",
    "name:ceb_x_preferred":[
        "Kamar"
    ],
    "name:deu_x_preferred":[
        "Kamar"
    ],
    "name:ita_x_preferred":[
        "Kamar"
    ],
    "name:swe_x_preferred":[
        "Kamar"
    ],
    "name:und_x_variant":[
        "\u06a9\u0645\u0631"
    ],
    "name:uzb_x_preferred":[
        "Kamar"
    ],
    "wof:name":"Kamar",
    "wof:placetype":"locality"
},
  "geometry": {"coordinates":[68.03369000000001,34.514],"type":"Point"}
}