{
  "type": "Feature",
  "properties": {
    "gn:admin1_code":"06",
    "gn:admin2_code":"2104",
    "gn:asciiname":"Shelah-ye Sangak Siyah",
    "gn:country_code":"AF",
    "gn:dem":1166,
    "gn:feature_class":"P",
    "gn:feature_code":"PPL",
    "gn:name":"Sh\u0113lah-ye Sangak Siy\u0101h",
    "gn:population":0,
    "gn:timezone":"Asia/Kabul",
    "iso:country":"AF",
    "name:und_x_variant":[
        "\u0160\u0113la-i-Sangak Sy\u0101h",
        "Shelayi-Sangaksiakh",
        "Shaylah-ye Sangak S\u012b\u0101h",
        "\u0634\u06cc\u0644\u06c0 \u0633\u0646\u06af\u06a9 \u0633\u06cc\u0627\u0647",
        "Sh\u0113lah-e Sangak S\u012b\u0101h",
        "Sh\u0113lah-ye Sangak Siy\u0101h"
    ],
    "wof:name":"Shelah-ye Sangak Siyah",
    "wof:placetype":"locality"
},
  "geometry": {"coordinates":[63.4457,33.13811],"type":"Point"}
}