{
  "type": "Feature",
  "properties": {
    "gn:admin1_code":"23",
    "gn:admin2_code":"2413.0",
    "gn:asciiname":"Sulaimanzai",
    "gn:country_code":"AF",
    "gn:dem":1803,
    "gn:feature_class":"P",
    "gn:feature_code":"PPL",
    "gn:name":"Sula\u012bm\u0101nza\u012b",
    "gn:population":0,
    "gn:timezone":"Asia/Kabul",
    "iso:country":"AF",
    "name:und_x_variant":[
        "Sl\u0113m\u0101nzay",
        "Sula\u012bm\u0101nza\u012b",
        "Soleym\u0101nzay",
        "\u0633\u0644\u06cc\u0645\u0627\u0646\u0632\u06cc"
    ],
    "wof:name":"Sulaimanzai",
    "wof:placetype":"locality"
},
  "geometry": {"coordinates":[67.01165,31.47005],"type":"Point"}
}