{
  "type": "Feature",
  "properties": {
    "gn:admin1_code":"30",
    "gn:admin2_code":"1607",
    "gn:asciiname":"Wahanah Nowroz",
    "gn:country_code":"AF",
    "gn:dem":337,
    "gn:feature_class":"P",
    "gn:feature_code":"PPL",
    "gn:name":"Wahanah Nowr\u014dz",
    "gn:population":0,
    "gn:timezone":"Asia/Kabul",
    "iso:country":"AF",
    "name:fas_x_preferred":[
        "\u0648\u0647\u0646\u0647 \u0646\u0648 \u0631\u0648\u0632"
    ],
    "name:rus_x_preferred":[
        "\u0412\u0430\u0445\u0430\u043d\u0430-\u041d\u0430\u0443\u0440\u043e\u0437"
    ],
    "name:und_x_variant":[
        "Wahana Naurowz",
        "Vakhana-Nauroz",
        "Wahanah Nowr\u016bz",
        "Wahanah Nowr\u014dz",
        "\u0648\u0647\u0646\u0647 \u0646\u0648\u0631\u0648\u0632"
    ],
    "wof:name":"Wahanah Nowroz",
    "wof:placetype":"locality"
},
  "geometry": {"coordinates":[66.773,36.77421],"type":"Point"}
}