{
  "type": "Feature",
  "properties": {
    "gn:admin1_code":"10",
    "gn:admin2_code":"2305",
    "gn:asciiname":"Siyah Chow",
    "gn:country_code":"AF",
    "gn:dem":1781,
    "gn:feature_class":"P",
    "gn:feature_code":"PPL",
    "gn:name":"Siy\u0101h Chow",
    "gn:population":0,
    "gn:timezone":"Asia/Kabul",
    "iso:country":"AF",
    "name:fas_x_preferred":[
        "\u0633\u064a\u0627\u0647 \u0686\u0648\u0628"
    ],
    "name:rus_x_preferred":[
        "\u0421\u0438\u0430\u0445\u0447\u0430\u0443"
    ],
    "name:und_x_variant":[
        "Siakhchau",
        "Sy\u0101h\u010daw",
        "S\u012b\u0101hch\u016bb",
        "S\u012b\u0101hchow",
        "\u0633\u06cc\u0627\u0647 \u0686\u0648",
        "S\u012b\u0101hchaw",
        "Siy\u0101h Chow"
    ],
    "wof:name":"Siyah Chow",
    "wof:placetype":"locality"
},
  "geometry": {"coordinates":[65.02800999999999,33.13327],"type":"Point"}
}