{
  "type": "Feature",
  "properties": {
    "gn:admin1_code":"11",
    "gn:admin2_code":"2007",
    "gn:asciiname":"Seh Ab",
    "gn:country_code":"AF",
    "gn:dem":1314,
    "gn:feature_class":"P",
    "gn:feature_code":"PPL",
    "gn:name":"Seh \u0100b",
    "gn:population":0,
    "gn:timezone":"Asia/Kabul",
    "iso:country":"AF",
    "name:und_x_variant":[
        "Seh \u0100b",
        "\u0633\u0647 \u0622\u0628"
    ],
    "wof:name":"Seh Ab",
    "wof:placetype":"locality"
},
  "geometry": {"coordinates":[61.80583000000001,34.73755999999999],"type":"Point"}
}