{
  "type": "Feature",
  "properties": {
    "gn:admin1_code":"10",
    "gn:admin2_code":"2303.0",
    "gn:asciiname":"Bulukchow",
    "gn:country_code":"AF",
    "gn:dem":1032,
    "gn:feature_class":"P",
    "gn:feature_code":"PPL",
    "gn:name":"Bul\u016bkchow",
    "gn:population":0,
    "gn:timezone":"Asia/Kabul",
    "iso:country":"AF",
    "name:und_x_variant":[
        "Balukchau",
        "Bol\u016bk\u010daw",
        "Bul\u016bkchow",
        "\u0628\u0644\u0648\u06a9\u0686\u0648",
        "Bol\u016bkchaw"
    ],
    "wof:name":"Bulukchow",
    "wof:placetype":"locality"
},
  "geometry": {"coordinates":[65.20878,32.37911],"type":"Point"}
}