{
  "type": "Feature",
  "properties": {
    "gn:admin1_code":"01",
    "gn:admin2_code":"1104",
    "gn:asciiname":"Razir",
    "gn:country_code":"AF",
    "gn:dem":2569,
    "gn:feature_class":"P",
    "gn:feature_code":"PPL",
    "gn:name":"R\u0101zir",
    "gn:population":0,
    "gn:timezone":"Asia/Kabul",
    "iso:country":"AF",
    "name:und_x_variant":[
        "R\u0101zir",
        "\u0631\u0627\u0632\u0631",
        "R\u0101zer"
    ],
    "wof:name":"Razir",
    "wof:placetype":"locality"
},
  "geometry": {"coordinates":[70.72592,36.00887],"type":"Point"}
}