{
  "type": "Feature",
  "properties": {
    "gn:admin1_code":"5",
    "gn:admin2_code":"2805.0",
    "gn:asciiname":"Dah Mardah",
    "gn:country_code":"AF",
    "gn:dem":2796,
    "gn:feature_class":"P",
    "gn:feature_code":"PPL",
    "gn:name":"Dah Mardah",
    "gn:population":0,
    "gn:timezone":"Asia/Kabul",
    "iso:country":"AF",
    "name:und_x_variant":[
        "Dakhmarda",
        "\u1e0eahma\u1e5f\u1e0fa",
        "Dahmardah",
        "Dah Murdah",
        "\u062f\u0647 \u0645\u0631\u062f\u0647",
        "Dah Mardah"
    ],
    "wof:name":"Dah Mardah",
    "wof:placetype":"locality"
},
  "geometry": {"coordinates":[66.68611,34.37808],"type":"Point"}
}