{
  "type": "Feature",
  "properties": {
    "gn:admin1_code":"27",
    "gn:admin2_code":"404",
    "gn:asciiname":"Mir Hazar",
    "gn:country_code":"AF",
    "gn:dem":2815,
    "gn:feature_class":"P",
    "gn:feature_code":"PPL",
    "gn:name":"M\u012br Haz\u0101r",
    "gn:population":0,
    "gn:timezone":"Asia/Kabul",
    "iso:country":"AF",
    "wof:name":"Mir Hazar",
    "wof:placetype":"locality"
},
  "geometry": {"coordinates":[68.00109,34.23243],"type":"Point"}
}