{
  "type": "Feature",
  "properties": {
    "gn:admin1_code":"27",
    "gn:admin2_code":"404.0",
    "gn:asciiname":"Iskah",
    "gn:country_code":"AF",
    "gn:dem":2816,
    "gn:feature_class":"P",
    "gn:feature_code":"PPL",
    "gn:name":"\u012askah",
    "gn:population":0,
    "gn:timezone":"Asia/Kabul",
    "iso:country":"AF",
    "name:und_x_variant":[
        "\u012aska",
        "Iska",
        "Iskah",
        "Estg\u0101h",
        "\u012askah",
        "\u0627\u06cc\u0633\u06a9\u0647"
    ],
    "wof:name":"Iskah",
    "wof:placetype":"locality"
},
  "geometry": {"coordinates":[67.97091,34.46366],"type":"Point"}
}