{
  "type": "Feature",
  "properties": {
    "gn:admin1_code":"13",
    "gn:admin2_code":"115",
    "gn:asciiname":"Salah Khel",
    "gn:country_code":"AF",
    "gn:dem":2028,
    "gn:feature_class":"P",
    "gn:feature_code":"PPL",
    "gn:name":"\u015eal\u0101\u1e29 Kh\u0113l",
    "gn:population":0,
    "gn:timezone":"Asia/Kabul",
    "iso:country":"AF",
    "name:fas_x_preferred":[
        "\u0635\u0644\u0627\u062d \u062e\u064a\u0644"
    ],
    "name:und_x_variant":[
        "Salakheyl",
        "\u015eal\u0101\u1e29 Kh\u0113l",
        "\u015eal\u0101\u1e29kheyl",
        "\u0635\u0644\u0627\u062d \u062e\u06d0\u0644"
    ],
    "wof:name":"Salah Khel",
    "wof:placetype":"locality"
},
  "geometry": {"coordinates":[69.04604999999999,34.79916],"type":"Point"}
}