{
  "type": "Feature",
  "properties": {
    "gn:admin1_code":"41",
    "gn:admin2_code":"3409",
    "gn:asciiname":"Khisrow",
    "gn:country_code":"AF",
    "gn:dem":2194,
    "gn:feature_class":"P",
    "gn:feature_code":"PPL",
    "gn:name":"Khisrow",
    "gn:population":0,
    "gn:timezone":"Asia/Kabul",
    "iso:country":"AF",
    "name:und_x_variant":[
        "Khes\u1e5faw",
        "Khosrow",
        "Khisrow",
        "\u062e\u0633\u0631\u0648"
    ],
    "wof:name":"Khisrow",
    "wof:placetype":"locality"
},
  "geometry": {"coordinates":[66.56395999999999,33.70232],"type":"Point"}
}