{
  "type": "Feature",
  "properties": {
    "gn:admin1_code":"36",
    "gn:admin2_code":"702.0",
    "gn:asciiname":"Dirgay",
    "gn:country_code":"AF",
    "gn:dem":2140,
    "gn:feature_class":"P",
    "gn:feature_code":"PPL",
    "gn:name":"Dirgay",
    "gn:population":0,
    "gn:timezone":"Asia/Kabul",
    "iso:country":"AF",
    "name:und_x_variant":[
        "Dargay",
        "\u1e0eergay",
        "D\u00eargay",
        "Dirgay",
        "\u062f\u0631\u06af\u06cc"
    ],
    "wof:name":"Dirgay",
    "wof:placetype":"locality"
},
  "geometry": {"coordinates":[68.98017,33.44518],"type":"Point"}
}