{
  "type": "Feature",
  "properties": {
    "gn:admin1_code":"41",
    "gn:admin2_code":"3407",
    "gn:asciiname":"Mashak",
    "gn:country_code":"AF",
    "gn:dem":2347,
    "gn:feature_class":"P",
    "gn:feature_code":"PPL",
    "gn:name":"M\u0101shak",
    "gn:population":0,
    "gn:timezone":"Asia/Kabul",
    "iso:country":"AF",
    "name:deu_x_preferred":[
        "Mashak"
    ],
    "name:und_x_variant":[
        "M\u0101\u0161ak",
        "M\u0101shak",
        "\u0645\u0627\u0634\u06a9"
    ],
    "wof:name":"Mashak",
    "wof:placetype":"locality"
},
  "geometry": {"coordinates":[66.94183000000001,33.83872],"type":"Point"}
}