{
  "type": "Feature",
  "properties": {
    "gn:admin1_code":"23",
    "gn:admin2_code":"2413.0",
    "gn:asciiname":"Zilargak",
    "gn:country_code":"AF",
    "gn:dem":1817,
    "gn:feature_class":"P",
    "gn:feature_code":"PPL",
    "gn:name":"Zilargak",
    "gn:population":0,
    "gn:timezone":"Asia/Kabul",
    "iso:country":"AF",
    "name:fas_x_preferred":[
        "\u0632\u0644\u0631\u06af\u0643"
    ],
    "name:pus_x_preferred":[
        "\u0632\u0644\u0631\u06af\u06a9"
    ],
    "name:und_x_variant":[
        "\u0632\u0644\u0631\u06af\u06a9",
        "Zelargak"
    ],
    "wof:name":"Zilargak",
    "wof:placetype":"locality"
},
  "geometry": {"coordinates":[67.22277,31.57586],"type":"Point"}
}