{
  "type": "Feature",
  "properties": {
    "gn:admin1_code":"30",
    "gn:admin2_code":"1606",
    "gn:asciiname":"Ghulam Jan",
    "gn:country_code":"AF",
    "gn:dem":337,
    "gn:feature_class":"P",
    "gn:feature_code":"PPL",
    "gn:name":"Ghul\u0101m J\u0101n",
    "gn:population":0,
    "gn:timezone":"Asia/Kabul",
    "iso:country":"AF",
    "name:fas_x_preferred":[
        "\u063a\u0644\u0627\u0645 \u062c\u0627\u0646"
    ],
    "name:rus_x_preferred":[
        "\u0413\u0443\u043b\u044f\u043c\u0434\u0436\u0430\u043d"
    ],
    "name:und_x_variant":[
        "Tazhna",
        "Gulyamdzhan",
        "Ghul\u0101m J\u0101n",
        "Ghol\u0101mj\u0101n",
        "Tazhnah",
        "\u062a\u0698\u0646\u0647"
    ],
    "wof:name":"Ghulam Jan",
    "wof:placetype":"locality"
},
  "geometry": {"coordinates":[66.88974,36.79855],"type":"Point"}
}