{
  "type": "Feature",
  "properties": {
    "gn:admin1_code":"26",
    "gn:admin2_code":"1201",
    "gn:asciiname":"Mali",
    "gn:country_code":"AF",
    "gn:dem":1205,
    "gn:feature_class":"P",
    "gn:feature_code":"PPL",
    "gn:name":"Mal\u012b",
    "gn:population":0,
    "gn:timezone":"Asia/Kabul",
    "iso:country":"AF",
    "name:rus_x_preferred":[
        "\u041c\u0430\u043b\u0438"
    ],
    "name:und_x_variant":[
        "Mal\u012b",
        "\u0645\u0644\u06cc"
    ],
    "wof:name":"Mali",
    "wof:placetype":"locality"
},
  "geometry": {"coordinates":[69.58099,36.83374],"type":"Point"}
}