{
  "type": "Feature",
  "properties": {
    "gn:admin1_code":"28",
    "gn:admin2_code":"2509.0",
    "gn:asciiname":"Wech Kelay",
    "gn:country_code":"AF",
    "gn:dem":2073,
    "gn:feature_class":"P",
    "gn:feature_code":"PPL",
    "gn:name":"W\u00each K\u00ealay",
    "gn:population":0,
    "gn:timezone":"Asia/Kabul",
    "iso:country":"AF",
    "name:und_x_variant":[
        "Vechkalay",
        "W\u011b\u010dkalay",
        "W\u00each K\u00ealay",
        "W\u012bchkalay",
        "\u0648\u0686 \u06a9\u0644\u06cc"
    ],
    "wof:name":"Wech Kelay",
    "wof:placetype":"locality"
},
  "geometry": {"coordinates":[67.57366999999999,31.80555],"type":"Point"}
}