{
  "type": "Feature",
  "properties": {
    "gn:admin1_code":"09",
    "gn:admin2_code":"2706",
    "gn:asciiname":"Qishlaq-e Haji Gul",
    "gn:country_code":"AF",
    "gn:dem":2221,
    "gn:feature_class":"P",
    "gn:feature_code":"PPL",
    "gn:name":"Qishl\u0101q-e \u1e28\u0101j\u012b Gul",
    "gn:population":0,
    "gn:timezone":"Asia/Kabul",
    "iso:country":"AF",
    "name:fas_x_preferred":[
        "\u0642\u0634\u0644\u0627\u0642\u0654 \u062d\u0627\u062c\u06cc \u06af\u0644"
    ],
    "name:und_x_variant":[
        "Qe\u0161l\u0101qe H\u0101jigul",
        "Qishl\u0101q-e \u1e28\u0101j\u012b Gul",
        "\u0642\u0634\u0644\u0627\u0642 \u062d\u0627\u062c\u06cc\u06af\u0644",
        "Qeshl\u0101q-e \u1e28\u0101jj\u012bgol"
    ],
    "wof:name":"Qishlaq-e Haji Gul",
    "wof:placetype":"locality"
},
  "geometry": {"coordinates":[64.99361999999999,33.33356],"type":"Point"}
}