{
  "type": "Feature",
  "properties": {
    "gn:admin1_code":"29",
    "gn:admin2_code":"2909.0",
    "gn:asciiname":"Nizam Khel",
    "gn:country_code":"AF",
    "gn:dem":1813,
    "gn:feature_class":"P",
    "gn:feature_code":"PPL",
    "gn:name":"Niz\u0327\u0101m Kh\u0113l",
    "gn:population":0,
    "gn:timezone":"Asia/Kabul",
    "iso:country":"AF",
    "name:und_x_variant":[
        "Ne\u1e95\u0101mkh\u0113l",
        "Nizamkheyl\u2019",
        "Nez\u0327\u0101m Khey",
        "Niz\u0327\u0101m Kh\u0113l",
        "Nez\u0327\u0101m Kheyl"
    ],
    "wof:name":"Nizam Khel",
    "wof:placetype":"locality"
},
  "geometry": {"coordinates":[69.40916999999999,32.83111],"type":"Point"}
}