{
  "type": "Feature",
  "properties": {
    "gn:admin1_code":"17",
    "gn:admin2_code":"501.0",
    "gn:asciiname":"Darwesh",
    "gn:country_code":"AF",
    "gn:dem":1953,
    "gn:feature_class":"P",
    "gn:feature_code":"PPL",
    "gn:name":"Darw\u0113sh",
    "gn:population":0,
    "gn:timezone":"Asia/Kabul",
    "iso:country":"AF",
    "name:fas_x_preferred":[
        "\u062f\u0631\u0648\u064a\u0634"
    ],
    "name:und_x_variant":[
        "Darw\u0113\u0161",
        "Darvesh",
        "Darw\u0113sh",
        "Darv\u012bsh",
        "\u062f\u0631\u0648\u06d0\u0634"
    ],
    "wof:name":"Darwesh",
    "wof:placetype":"locality"
},
  "geometry": {"coordinates":[69.04975,33.96379],"type":"Point"}
}