{
  "type": "Feature",
  "properties": {
    "gn:admin1_code":"11",
    "gn:admin2_code":"2001",
    "gn:asciiname":"Shali Patrah",
    "gn:country_code":"AF",
    "gn:dem":909,
    "gn:feature_class":"P",
    "gn:feature_code":"PPL",
    "gn:name":"Sh\u0101l\u012b Patrah",
    "gn:population":0,
    "gn:timezone":"Asia/Kabul",
    "iso:country":"AF",
    "name:fas_x_preferred":[
        "\u0634\u0644\u06cc \u067e\u062a\u0631\u0647"
    ],
    "name:und_x_variant":[
        "\u0160\u0101li Patra",
        "Shalipatra",
        "Shal\u012b Patreh",
        "Sh\u0101l\u012b Patrah",
        "\u0634\u0627\u0644\u06cc \u067e\u062a\u0631\u0647"
    ],
    "wof:name":"Shali Patrah",
    "wof:placetype":"locality"
},
  "geometry": {"coordinates":[62.09936,34.3872],"type":"Point"}
}