{
  "type": "Feature",
  "properties": {
    "gn:admin1_code":"37",
    "gn:admin2_code":"3208.0",
    "gn:asciiname":"Arghu",
    "gn:country_code":"AF",
    "gn:dem":1670,
    "gn:feature_class":"P",
    "gn:feature_code":"PPL",
    "gn:name":"Argh\u016b",
    "gn:population":0,
    "gn:timezone":"Asia/Kabul",
    "iso:country":"AF",
    "name:fas_x_preferred":[
        "\u0627\u0631\u063a\u0648"
    ],
    "name:und_x_variant":[
        "Argu",
        "Argh\u016b",
        "A\u1e5fghu"
    ],
    "wof:name":"Arghu",
    "wof:placetype":"locality"
},
  "geometry": {"coordinates":[69.75626,33.41818],"type":"Point"}
}