{
  "type": "Feature",
  "properties": {
    "gn:admin1_code":"23",
    "gn:admin2_code":"2413.0",
    "gn:asciiname":"Mali Kelay",
    "gn:country_code":"AF",
    "gn:dem":1923,
    "gn:feature_class":"P",
    "gn:feature_code":"PPL",
    "gn:name":"Mal\u012b K\u00ealay",
    "gn:population":0,
    "gn:timezone":"Asia/Kabul",
    "iso:country":"AF",
    "name:fas_x_preferred":[
        "\u0642\u0631\u064a\u06c0 \u0645\u0644\u06cc"
    ],
    "name:pus_x_preferred":[
        "\u0645\u0644\u06cc \u06a9\u0644\u06cc"
    ],
    "name:und_x_variant":[
        "Mal\u012b K\u00ealay",
        "Mali Kalay"
    ],
    "wof:name":"Mali Kelay",
    "wof:placetype":"locality"
},
  "geometry": {"coordinates":[67.13455999999999,31.67525],"type":"Point"}
}