{
  "type": "Feature",
  "properties": {
    "gn:admin1_code":"09",
    "gn:admin2_code":"2703",
    "gn:asciiname":"Zawar",
    "gn:country_code":"AF",
    "gn:dem":2096,
    "gn:feature_class":"P",
    "gn:feature_code":"PPL",
    "gn:name":"Z\u0101w\u0101r",
    "gn:population":0,
    "gn:timezone":"Asia/Kabul",
    "iso:country":"AF",
    "name:hin_x_preferred":[
        "\u091c\u093e\u0935\u0930"
    ],
    "name:und_x_variant":[
        "Z\u0101w\u0101r",
        "\u0632\u0627\u0648\u0627\u0631"
    ],
    "wof:name":"Zawar",
    "wof:placetype":"locality"
},
  "geometry": {"coordinates":[63.94067,34.16098],"type":"Point"}
}