{
  "type": "Feature",
  "properties": {
    "gn:admin1_code":"27",
    "gn:admin2_code":"406.0",
    "gn:asciiname":"Khanak Khel",
    "gn:country_code":"AF",
    "gn:dem":2420,
    "gn:feature_class":"P",
    "gn:feature_code":"PPL",
    "gn:name":"Kh\u0101nak Kh\u0113l",
    "gn:population":0,
    "gn:timezone":"Asia/Kabul",
    "iso:country":"AF",
    "name:rus_x_preferred":[
        "Khanakkheyl\u2019"
    ],
    "name:und_x_variant":[
        "Kh\u0101nakkh\u0113l",
        "Kh\u0101nakkheyl",
        "Kh\u0101nak Kh\u0113l",
        "\u062e\u0627\u0646\u06a9 \u062e\u06d0\u0644"
    ],
    "wof:name":"Khanak Khel",
    "wof:placetype":"locality"
},
  "geometry": {"coordinates":[68.44551,34.05434],"type":"Point"}
}