{
  "type": "Feature",
  "properties": {
    "gn:admin1_code":"35",
    "gn:admin2_code":"903.0",
    "gn:asciiname":"Sangrak",
    "gn:country_code":"AF",
    "gn:dem":1795,
    "gn:feature_class":"P",
    "gn:feature_code":"PPL",
    "gn:name":"Sangr\u0101k",
    "gn:population":0,
    "gn:timezone":"Asia/Kabul",
    "iso:country":"AF",
    "name:fas_x_preferred":[
        "\u0633\u0646\u06af\u0631\u06a9"
    ],
    "name:und_x_variant":[
        "Sangr\u0101k",
        "\u0633\u0646\u06af\u0631\u0627\u06a9"
    ],
    "wof:name":"Sangrak",
    "wof:placetype":"locality"
},
  "geometry": {"coordinates":[70.51446999999997,34.84044],"type":"Point"}
}