{
  "type": "Feature",
  "properties": {
    "gn:admin1_code":"18",
    "gn:admin2_code":"805.0",
    "gn:asciiname":"Bar Kelay",
    "gn:country_code":"AF",
    "gn:dem":1178,
    "gn:feature_class":"P",
    "gn:feature_code":"PPL",
    "gn:name":"Bar K\u00ealay",
    "gn:population":0,
    "gn:timezone":"Asia/Kabul",
    "iso:country":"AF",
    "name:fas_x_preferred":[
        "\u0628\u0631 \u0643\u0644\u06cc"
    ],
    "name:und_x_variant":[
        "Bar-Kalay",
        "Ba\u1e5f Kalay",
        "Bar K\u00ealay",
        "\u0628\u0631 \u06a9\u0644\u06cc"
    ],
    "wof:name":"Bar Kelay",
    "wof:placetype":"locality"
},
  "geometry": {"coordinates":[70.09114,34.28139],"type":"Point"}
}