{
  "type": "Feature",
  "properties": {
    "gn:admin1_code":"06",
    "gn:admin2_code":"2101",
    "gn:asciiname":"Tujg",
    "gn:country_code":"AF",
    "gn:dem":589,
    "gn:feature_class":"P",
    "gn:feature_code":"PPL",
    "gn:name":"Tujg",
    "gn:population":0,
    "gn:timezone":"Asia/Kabul",
    "iso:country":"AF",
    "name:ceb_x_preferred":[
        "Tujg"
    ],
    "name:fas_x_preferred":[
        "\u062a\u062c\u06af"
    ],
    "name:fas_x_variant":[
        "\u062a\u0648\u062c"
    ],
    "name:swe_x_preferred":[
        "Tujg"
    ],
    "name:und_x_variant":[
        "Tojak",
        "Tujg",
        "Tojg",
        "\u062a\u062c\u06af"
    ],
    "wof:name":"Tujg",
    "wof:placetype":"locality"
},
  "geometry": {"coordinates":[61.80729,32.06941],"type":"Point"}
}