{
  "type": "Feature",
  "properties": {
    "gn:admin1_code":"10",
    "gn:admin2_code":"2305.0",
    "gn:asciiname":"Anar Joy",
    "gn:country_code":"AF",
    "gn:dem":1590,
    "gn:feature_class":"P",
    "gn:feature_code":"PPL",
    "gn:name":"An\u0101r J\u014dy",
    "gn:population":0,
    "gn:timezone":"Asia/Kabul",
    "iso:country":"AF",
    "name:rus_x_preferred":[
        "\u0410\u043d\u0430\u0440\u0434\u0436\u043e\u0439"
    ],
    "name:und_x_variant":[
        "An\u0101\u1e5fj\u014dy",
        "Anardzhoy",
        "An\u0101r J\u014dy",
        "\u0627\u0646\u0627\u0631 \u062c\u0648\u06cc",
        "An\u0101rj\u016by"
    ],
    "wof:name":"Anar Joy",
    "wof:placetype":"locality"
},
  "geometry": {"coordinates":[65.09958,33.12514],"type":"Point"}
}