{
  "type": "Feature",
  "properties": {
    "gn:admin1_code":"08",
    "gn:admin2_code":"604",
    "gn:asciiname":"Jowqol",
    "gn:country_code":"AF",
    "gn:dem":3210,
    "gn:feature_class":"P",
    "gn:feature_code":"PPL",
    "gn:name":"Jowq\u014dl",
    "gn:population":0,
    "gn:timezone":"Asia/Kabul",
    "iso:country":"AF",
    "name:und_x_variant":[
        "Jawq\u014dl",
        "Jawqowl",
        "Jowq\u014dl",
        "\u062c\u0648\u0642\u0648\u0644"
    ],
    "wof:name":"Jowqol",
    "wof:placetype":"locality"
},
  "geometry": {"coordinates":[67.33915999999999,33.94515],"type":"Point"}
}