{
  "type": "Feature",
  "properties": {
    "gn:admin1_code":"27",
    "gn:admin2_code":"404.0",
    "gn:asciiname":"Beremak",
    "gn:country_code":"AF",
    "gn:dem":2733,
    "gn:feature_class":"P",
    "gn:feature_code":"PPL",
    "gn:name":"B\u0113r\u0113mak",
    "gn:population":0,
    "gn:timezone":"Asia/Kabul",
    "iso:country":"AF",
    "name:und_x_variant":[
        "B\u0113r\u0113mak",
        "\u0628\u06cc\u0631\u06cc\u0645\u06a9",
        "Bayraymak"
    ],
    "wof:name":"Beremak",
    "wof:placetype":"locality"
},
  "geometry": {"coordinates":[67.47077,34.21601],"type":"Point"}
}