{
  "type": "Feature",
  "properties": {
    "gn:admin1_code":"5",
    "gn:admin2_code":"2801.0",
    "gn:asciiname":"Kundahha",
    "gn:country_code":"AF",
    "gn:dem":2872,
    "gn:feature_class":"P",
    "gn:feature_code":"PPL",
    "gn:name":"Kundahh\u0101",
    "gn:population":0,
    "gn:timezone":"Asia/Kabul",
    "iso:country":"AF",
    "name:und_x_variant":[
        "Kun\u1e0fah\u0101",
        "Kundakha",
        "Kundahh\u0101",
        "Kondehh\u0101",
        "\u06a9\u0646\u062f\u0647 \u0647\u0627"
    ],
    "wof:name":"Kundahha",
    "wof:placetype":"locality"
},
  "geometry": {"coordinates":[67.84605999999999,34.72623],"type":"Point"}
}