{
  "type": "Feature",
  "properties": {
    "gn:admin1_code":"39",
    "gn:admin2_code":"2603",
    "gn:asciiname":"Tale Maidan",
    "gn:country_code":"AF",
    "gn:dem":3173,
    "gn:feature_class":"P",
    "gn:feature_code":"PPL",
    "gn:name":"T\u0101l\u0113 Ma\u012bd\u0101n",
    "gn:population":0,
    "gn:timezone":"Asia/Kabul",
    "iso:country":"AF",
    "name:fas_x_preferred":[
        "\u062a\u0627\u0644\u06cc \u0645\u064a\u062f\u0627\u0646"
    ],
    "name:und_x_variant":[
        "Telemaydan",
        "T\u0101l\u0113 Ma\u012bd\u0101n",
        "\u062a\u0627\u0644\u06d0 \u0645\u06cc\u062f\u0627\u0646",
        "T\u0101l\u0113 Mayd\u0101n"
    ],
    "wof:name":"Tale Maidan",
    "wof:placetype":"locality"
},
  "geometry": {"coordinates":[66.87705,32.89932],"type":"Point"}
}