{
  "type": "Feature",
  "properties": {
    "gn:admin1_code":"11",
    "gn:admin2_code":"2015",
    "gn:asciiname":"Zow",
    "gn:country_code":"AF",
    "gn:dem":1789,
    "gn:feature_class":"P",
    "gn:feature_code":"PPL",
    "gn:name":"Zow",
    "gn:population":0,
    "gn:timezone":"Asia/Kabul",
    "iso:country":"AF",
    "name:und_x_variant":[
        "\u0632\u0648",
        "Zow",
        "Zaw"
    ],
    "wof:name":"Zow",
    "wof:placetype":"locality"
},
  "geometry": {"coordinates":[63.53791999999999,34.31799],"type":"Point"}
}