{
  "type": "Feature",
  "properties": {
    "gn:admin1_code":"32",
    "gn:admin2_code":"1501.0",
    "gn:asciiname":"Zindey Kot",
    "gn:country_code":"AF",
    "gn:dem":983,
    "gn:feature_class":"P",
    "gn:feature_code":"PPL",
    "gn:name":"Zin\u1e0f\u00eay K\u014d\u1e6f",
    "gn:population":0,
    "gn:timezone":"Asia/Kabul",
    "iso:country":"AF",
    "name:und_x_variant":[
        "Zend\u0101y K\u014dt",
        "Zend\u0101y K\u016bt",
        "Zin\u1e0f\u00eay K\u014d\u1e6f",
        "\u0632\u0646\u0689\u06cd \u06a9\u0648\u067c",
        "Dzand\u012b K\u014d\u1e6f",
        "\u0681\u0646\u062f\u06cc \u06a9\u0648\u067c"
    ],
    "wof:name":"Zindey Kot",
    "wof:placetype":"locality"
},
  "geometry": {"coordinates":[68.014,36.2568],"type":"Point"}
}