{
  "type": "Feature",
  "properties": {
    "gn:admin1_code":"05",
    "gn:admin2_code":"2803",
    "gn:asciiname":"Duab-e Maykh-e Zarin",
    "gn:country_code":"AF",
    "gn:dem":1462,
    "gn:feature_class":"P",
    "gn:feature_code":"PPL",
    "gn:name":"D\u016b\u0101b-e Maykh-e Zar\u012bn",
    "gn:population":0,
    "gn:timezone":"Asia/Kabul",
    "iso:country":"AF",
    "name:und_x_variant":[
        "Mehiari",
        "\u1e0eo\u0101be M\u0113khe Za\u1e5f\u012bn",
        "Do\u0101b Mekh-i-Zar\u012bn",
        "Doab-i-Mekhzari",
        "Doabb-i-Mehzari",
        "Do \u0100b-e M\u012bkh-e Zarr\u012bn",
        "D\u014d\u0101b-e Maykh-e Zar\u012bn",
        "\u062f\u0648\u0627\u0628 \u0645\u06cc\u062e \u0632\u0631\u06cc\u0646",
        "D\u016b\u0101b-e Maykh-e Zar\u012bn"
    ],
    "wof:name":"Duab-e Maykh-e Zarin",
    "wof:placetype":"locality"
},
  "geometry": {"coordinates":[67.99257,35.26212],"type":"Point"}
}