{
  "type": "Feature",
  "properties": {
    "gn:admin1_code":"8",
    "gn:admin2_code":"604.0",
    "gn:asciiname":"Sang-e Almas",
    "gn:country_code":"AF",
    "gn:dem":2876,
    "gn:feature_class":"P",
    "gn:feature_code":"PPL",
    "gn:name":"Sang-e Alm\u0101s",
    "gn:population":0,
    "gn:timezone":"Asia/Kabul",
    "iso:country":"AF",
    "name:und_x_variant":[
        "Sang-e Alm\u0101s",
        "\u0633\u0646\u06af \u0627\u0644\u0645\u0627\u0633"
    ],
    "wof:name":"Sang-e Almas",
    "wof:placetype":"locality"
},
  "geometry": {"coordinates":[67.42524,33.69452],"type":"Point"}
}