{
  "type": "Feature",
  "properties": {
    "gn:admin1_code":"10",
    "gn:admin2_code":"2302",
    "gn:asciiname":"Katmutian",
    "gn:country_code":"AF",
    "gn:dem":846,
    "gn:feature_class":"P",
    "gn:feature_code":"PPL",
    "gn:name":"Ka\u1e6fmut\u012b\u0101n",
    "gn:population":0,
    "gn:timezone":"Asia/Kabul",
    "iso:country":"AF",
    "name:rus_x_preferred":[
        "Katmut\u2019yan"
    ],
    "name:und_x_variant":[
        "Ka\u1e6fmutiy\u0101n",
        "\u06a9\u067c\u0645\u062a\u06cc\u0627\u0646",
        "Katmuty\u0101n",
        "Ka\u1e6fmut\u012b\u0101n"
    ],
    "wof:name":"Katmutian",
    "wof:placetype":"locality"
},
  "geometry": {"coordinates":[64.70578,31.88587],"type":"Point"}
}