{
  "type": "Feature",
  "properties": {
    "gn:admin1_code":"23",
    "gn:admin2_code":"2413",
    "gn:asciiname":"Kalagey",
    "gn:country_code":"AF",
    "gn:dem":2020,
    "gn:feature_class":"P",
    "gn:feature_code":"PPL",
    "gn:name":"Kal\u0101g\u00eay",
    "gn:population":0,
    "gn:timezone":"Asia/Kabul",
    "iso:country":"AF",
    "name:rus_x_preferred":[
        "\u041a\u0430\u043b\u0430\u0433\u0430\u0439"
    ],
    "name:und_x_variant":[
        "Kalagay",
        "Kal\u0101g\u00eay",
        "Kal\u0101gey",
        "\u06a9\u0644\u0627\u06af\u06cd"
    ],
    "wof:name":"Kalagey",
    "wof:placetype":"locality"
},
  "geometry": {"coordinates":[67.1841,31.23705],"type":"Point"}
}