{
  "type": "Feature",
  "properties": {
    "gn:admin1_code":"8",
    "gn:admin2_code":"606.0",
    "gn:asciiname":"Deh-e Zowar",
    "gn:country_code":"AF",
    "gn:dem":2715,
    "gn:feature_class":"P",
    "gn:feature_code":"PPL",
    "gn:name":"Deh-e Zow\u0101r",
    "gn:population":0,
    "gn:timezone":"Asia/Kabul",
    "iso:country":"AF",
    "name:und_x_variant":[
        "Deh-e Zow\u0101r",
        "\u062f\u0647 \u0632\u0648\u0627\u0631",
        "Deh-e Zaw\u0101\u1e5f"
    ],
    "wof:name":"Deh-e Zowar",
    "wof:placetype":"locality"
},
  "geometry": {"coordinates":[67.35746,33.36774],"type":"Point"}
}