{
  "type": "Feature",
  "properties": {
    "gn:admin1_code":"01",
    "gn:admin2_code":"1110",
    "gn:asciiname":"Hujm-e Bala",
    "gn:country_code":"AF",
    "gn:dem":1597,
    "gn:feature_class":"P",
    "gn:feature_code":"PPL",
    "gn:name":"\u1e28ujm-e B\u0101l\u0101",
    "gn:population":0,
    "gn:timezone":"Asia/Kabul",
    "iso:country":"AF",
    "name:und_x_variant":[
        "Ujum",
        "H\u0331ujm-i-B\u0101l\u0101",
        "\u062d\u062c\u0645 \u0628\u0627\u0644\u0627",
        "\u1e28ojm-e B\u0101l\u0101",
        "\u1e28ujm-e B\u0101l\u0101"
    ],
    "wof:name":"Hujm-e Bala",
    "wof:placetype":"locality"
},
  "geometry": {"coordinates":[70.86506,38.34866],"type":"Point"}
}