{
  "type": "Feature",
  "properties": {
    "gn:admin1_code":"08",
    "gn:admin2_code":"615",
    "gn:asciiname":"Rozi Kala",
    "gn:country_code":"AF",
    "gn:dem":2099,
    "gn:feature_class":"P",
    "gn:feature_code":"PPL",
    "gn:name":"R\u014dz\u012b Kal\u0101",
    "gn:population":0,
    "gn:timezone":"Asia/Kabul",
    "iso:country":"AF",
    "name:und_x_variant":[
        "\u1e5e\u014dzi Kal\u0101",
        "Rozikala",
        "R\u016bz\u012b Kal\u0101",
        "R\u014dz\u012b Kal\u0101",
        "\u0631\u0648\u0632\u06cc \u06a9\u0644\u0627"
    ],
    "wof:name":"Rozi Kala",
    "wof:placetype":"locality"
},
  "geometry": {"coordinates":[68.56879000000001,33.40855],"type":"Point"}
}