{
  "type": "Feature",
  "properties": {
    "gn:admin1_code":"41",
    "gn:admin2_code":"3409.0",
    "gn:asciiname":"Tudak",
    "gn:country_code":"AF",
    "gn:dem":2399,
    "gn:feature_class":"P",
    "gn:feature_code":"PPL",
    "gn:name":"T\u016bdak",
    "gn:population":0,
    "gn:timezone":"Asia/Kabul",
    "iso:country":"AF",
    "name:und_x_variant":[
        "T\u016b\u1e0fak",
        "Tow\u1e0fak",
        "T\u016bdak",
        "\u062a\u0648\u062f\u06a9"
    ],
    "wof:name":"Tudak",
    "wof:placetype":"locality"
},
  "geometry": {"coordinates":[66.26889,33.76787],"type":"Point"}
}