{
  "type": "Feature",
  "properties": {
    "gn:admin1_code":"17",
    "gn:admin2_code":"502",
    "gn:asciiname":"Qal'ah-ye Qumandan",
    "gn:country_code":"AF",
    "gn:dem":2121,
    "gn:feature_class":"P",
    "gn:feature_code":"PPL",
    "gn:name":"Qal\u2018ah-ye Qum\u0101nd\u0101n",
    "gn:population":0,
    "gn:timezone":"Asia/Kabul",
    "iso:country":"AF",
    "name:und_x_variant":[
        "Qal\u2018a-i-Qom\u0101n\u1e0f\u0101n",
        "Kalakamandan",
        "Qal\u2018a Qom\u0101n\u1e0f\u0101n",
        "Qal\u2018ah-ye Q\u016bm\u0101nd\u0101n",
        "Qal\u2018eh-ye Qom\u0101nd\u0101n",
        "Qal\u2018ah-ye Qum\u0101nd\u0101n",
        "\u0642\u0644\u0639\u0647 \u0642\u0645\u0627\u0646\u062f\u0627\u0646"
    ],
    "wof:name":"Qal'ah-ye Qumandan",
    "wof:placetype":"locality"
},
  "geometry": {"coordinates":[68.93191999999999,33.77937],"type":"Point"}
}