{
  "type": "Feature",
  "properties": {
    "gn:admin1_code":"08",
    "gn:admin2_code":"607",
    "gn:asciiname":"Gardan",
    "gn:country_code":"AF",
    "gn:dem":2484,
    "gn:feature_class":"P",
    "gn:feature_code":"PPL",
    "gn:name":"Gardan",
    "gn:population":0,
    "gn:timezone":"Asia/Kabul",
    "iso:country":"AF",
    "name:fas_x_preferred":[
        "\u06af\u0631\u062f\u0627\u0646"
    ],
    "name:und_x_variant":[
        "\u06af\u0631\u062f\u0646"
    ],
    "wof:name":"Gardan",
    "wof:placetype":"locality"
},
  "geometry": {"coordinates":[67.56451,32.98661],"type":"Point"}
}