{
  "type": "Feature",
  "properties": {
    "gn:admin1_code":"41",
    "gn:admin2_code":"3408",
    "gn:asciiname":"Jowzai",
    "gn:country_code":"AF",
    "gn:dem":2950,
    "gn:feature_class":"P",
    "gn:feature_code":"PPL",
    "gn:name":"Jowza\u012b",
    "gn:population":0,
    "gn:timezone":"Asia/Kabul",
    "iso:country":"AF",
    "name:und_x_variant":[
        "Dzhauzi",
        "Jowza\u012b",
        "\u062c\u0648\u0632\u06cc",
        "Jawz\u012b"
    ],
    "wof:name":"Jowzai",
    "wof:placetype":"locality"
},
  "geometry": {"coordinates":[65.96533000000001,34.24886],"type":"Point"}
}