{
  "type": "Feature",
  "properties": {
    "gn:admin1_code":"18",
    "gn:admin2_code":"818.0",
    "gn:asciiname":"Landah Boch",
    "gn:country_code":"AF",
    "gn:dem":535,
    "gn:feature_class":"P",
    "gn:feature_code":"PPL",
    "gn:name":"Lan\u1e0fah B\u014dch",
    "gn:population":0,
    "gn:timezone":"Asia/Kabul",
    "iso:country":"AF",
    "name:fas_x_preferred":[
        "\u0644\u0646\u062f\u0647 \u0628\u0648\u0686"
    ],
    "name:und_x_variant":[
        "Landaboch",
        "Landa B\u014dch",
        "Landa Bo\u010d",
        "Landah B\u014dch",
        "Landah Bowch",
        "Lan\u1e0fah B\u014dch",
        "\u0644\u0646\u0689\u0647 \u0628\u0648\u0686"
    ],
    "wof:name":"Landah Boch",
    "wof:placetype":"locality"
},
  "geometry": {"coordinates":[70.60802,34.43765],"type":"Point"}
}