{
  "type": "Feature",
  "properties": {
    "gn:admin1_code":"5",
    "gn:admin2_code":"2806.0",
    "gn:asciiname":"Allah Kolik",
    "gn:country_code":"AF",
    "gn:dem":2664,
    "gn:feature_class":"P",
    "gn:feature_code":"PPL",
    "gn:name":"All\u0101h K\u014dlik",
    "gn:population":0,
    "gn:timezone":"Asia/Kabul",
    "iso:country":"AF",
    "name:und_x_variant":[
        "Alakolik",
        "Alak\u014dlek",
        "Alahkowlek",
        "All\u0101h K\u014dlik",
        "\u0627\u0644\u0644\u0640\u0647 \u06a9\u0648\u0644\u06a9"
    ],
    "wof:name":"Allah Kolik",
    "wof:placetype":"locality"
},
  "geometry": {"coordinates":[66.84815999999999,34.19948],"type":"Point"}
}