{
  "type": "Feature",
  "properties": {
    "gn:admin1_code":"37",
    "gn:admin2_code":"3209.0",
    "gn:asciiname":"Mamad Kala",
    "gn:country_code":"AF",
    "gn:dem":1123,
    "gn:feature_class":"P",
    "gn:feature_code":"PPL",
    "gn:name":"M\u0101mad Kal\u0101",
    "gn:population":0,
    "gn:timezone":"Asia/Kabul",
    "iso:country":"AF",
    "name:fas_x_preferred":[
        "\u0642\u0644\u0639\u0647\u0654 \u0645\u0627\u0645\u062f"
    ],
    "name:und_x_variant":[
        "Mamadkala",
        "Mo\u1e29ammad Kal\u0101",
        "M\u0101mad Kal\u0101",
        "\u0645\u0627\u0645\u062f \u06a9\u0644\u0627"
    ],
    "wof:name":"Mamad Kala",
    "wof:placetype":"locality"
},
  "geometry": {"coordinates":[70.01933000000001,33.47425],"type":"Point"}
}