{
  "type": "Feature",
  "properties": {
    "gn:admin1_code":"08",
    "gn:admin2_code":"606",
    "gn:asciiname":"Sar Dzangal",
    "gn:country_code":"AF",
    "gn:dem":3235,
    "gn:feature_class":"P",
    "gn:feature_code":"PPL",
    "gn:name":"Sar Dzangal",
    "gn:population":0,
    "gn:timezone":"Asia/Kabul",
    "iso:country":"AF",
    "name:und_x_variant":[
        "\u0633\u0631 \u0681\u0646\u06af\u0644",
        "Sar Jangal"
    ],
    "wof:name":"Sar Dzangal",
    "wof:placetype":"locality"
},
  "geometry": {"coordinates":[67.43129,33.55259],"type":"Point"}
}