{
  "type": "Feature",
  "properties": {
    "gn:admin1_code":"29",
    "gn:admin2_code":"2914",
    "gn:asciiname":"Madu Kach",
    "gn:country_code":"AF",
    "gn:dem":2294,
    "gn:feature_class":"P",
    "gn:feature_code":"PPL",
    "gn:name":"Mad\u016b Kach",
    "gn:population":0,
    "gn:timezone":"Asia/Kabul",
    "iso:country":"AF",
    "name:und_x_variant":[
        "Madukai",
        "Madu Ka\u010d",
        "\u0645\u062f\u0648 \u06a9\u0686",
        "Madu Kach",
        "Mad\u016b Kach"
    ],
    "wof:name":"Madu Kach",
    "wof:placetype":"locality"
},
  "geometry": {"coordinates":[68.92805,33.08936],"type":"Point"}
}