{
  "type": "Feature",
  "properties": {
    "gn:admin1_code":"29",
    "gn:admin2_code":"2901",
    "gn:asciiname":"Khadzhiamir",
    "gn:country_code":"AF",
    "gn:dem":2130,
    "gn:feature_class":"P",
    "gn:feature_code":"PPL",
    "gn:name":"Khadzhiamir",
    "gn:population":0,
    "gn:timezone":"Asia/Kabul",
    "iso:country":"AF",
    "name:und_x_variant":[
        "\u1e28\u0101ji Am\u012b\u1e5f",
        "Khadzhiamir",
        "\u062d\u0627\u062c\u06cc \u0627\u0645\u06cc\u0631",
        "\u1e28\u0101jj\u012b Am\u012br",
        "\u1e28\u0101j\u012b Am\u012br"
    ],
    "wof:name":"Khadzhiamir",
    "wof:placetype":"locality"
},
  "geometry": {"coordinates":[68.76848000000001,33.19560999999999],"type":"Point"}
}