{
  "type": "Feature",
  "properties": {
    "gn:admin1_code":"08",
    "gn:admin2_code":"606",
    "gn:asciiname":"Olama",
    "gn:country_code":"AF",
    "gn:dem":2939,
    "gn:feature_class":"P",
    "gn:feature_code":"PPL",
    "gn:name":"\u014clam\u0101",
    "gn:population":0,
    "gn:timezone":"Asia/Kabul",
    "iso:country":"AF",
    "name:fas_x_preferred":[
        "\u0648\u0644\u0645\u0627"
    ],
    "name:und_x_variant":[
        "\u014clam\u0101",
        "\u0627\u0648\u0644\u0645\u0627",
        "\u016alam\u0101"
    ],
    "wof:name":"Olama",
    "wof:placetype":"locality"
},
  "geometry": {"coordinates":[66.91584,32.98108],"type":"Point"}
}