{
  "type": "Feature",
  "properties": {
    "gn:admin1_code":"05",
    "gn:admin2_code":"2805",
    "gn:asciiname":"Now Bala-ye Saray",
    "gn:country_code":"AF",
    "gn:dem":2802,
    "gn:feature_class":"P",
    "gn:feature_code":"PPL",
    "gn:name":"Now B\u0101l\u0101-ye Sar\u0101y",
    "gn:population":0,
    "gn:timezone":"Asia/Kabul",
    "iso:country":"AF",
    "name:und_x_variant":[
        "Naubalayi-Saray",
        "Nawb\u0101l\u0101-i-Sa\u1e5f\u0101y",
        "Now B\u0101l\u0101-ye Sar\u0101y",
        "\u0646\u0648 \u0628\u0627\u0644\u0627\u06cc \u0633\u0631\u0627\u06cc"
    ],
    "wof:name":"Now Bala-ye Saray",
    "wof:placetype":"locality"
},
  "geometry": {"coordinates":[66.71956999999999,34.36625],"type":"Point"}
}