{
  "type": "Feature",
  "properties": {
    "gn:admin1_code":"23",
    "gn:admin2_code":"2416.0",
    "gn:asciiname":"Sharo",
    "gn:country_code":"AF",
    "gn:dem":937,
    "gn:feature_class":"P",
    "gn:feature_code":"PPL",
    "gn:name":"Sharo",
    "gn:population":0,
    "gn:timezone":"Asia/Kabul",
    "iso:country":"AF",
    "wof:name":"Sharo",
    "wof:placetype":"locality"
},
  "geometry": {"coordinates":[65.36111,31.54694000000001],"type":"Point"}
}