{
  "type": "Feature",
  "properties": {
    "gn:admin1_code":"37",
    "gn:admin2_code":"3203.0",
    "gn:asciiname":"Khan Qul Kala",
    "gn:country_code":"AF",
    "gn:dem":1240,
    "gn:feature_class":"P",
    "gn:feature_code":"PPL",
    "gn:name":"Kh\u0101n Qul Kal\u0101",
    "gn:population":0,
    "gn:timezone":"Asia/Kabul",
    "iso:country":"AF",
    "name:fas_x_preferred":[
        "\u0642\u0644\u0639\u06c0 \u062e\u0627\u0646 \u0642\u0644"
    ],
    "name:rus_x_preferred":[
        "Khankul\u2019kala"
    ],
    "name:und_x_variant":[
        "Kh\u0101n Gul Kal\u0101",
        "Kh\u0101nqul Kal\u0101",
        "Kh\u0101n Qul Kal\u0101",
        "\u062e\u0627\u0646 \u0642\u0644 \u06a9\u0644\u0627"
    ],
    "wof:name":"Khan Qul Kala",
    "wof:placetype":"locality"
},
  "geometry": {"coordinates":[69.85996999999999,33.27907],"type":"Point"}
}