{
  "type": "Feature",
  "properties": {
    "gn:admin1_code":"39",
    "gn:admin2_code":"2604",
    "gn:asciiname":"Landi Chinar",
    "gn:country_code":"AF",
    "gn:dem":1735,
    "gn:feature_class":"P",
    "gn:feature_code":"PPL",
    "gn:name":"Lan\u1e0f\u012b Chin\u0101r",
    "gn:population":0,
    "gn:timezone":"Asia/Kabul",
    "iso:country":"AF",
    "name:und_x_variant":[
        "Landichinar",
        "Landi \u010cen\u0101r",
        "Lan\u1e0f\u012b Chin\u0101r",
        "\u0644\u0646\u0689\u06cc \u0686\u0646\u0627\u0631",
        "Landi Chen\u0101r"
    ],
    "wof:name":"Landi Chinar",
    "wof:placetype":"locality"
},
  "geometry": {"coordinates":[65.22471,32.68271],"type":"Point"}
}