{
  "type": "Feature",
  "properties": {
    "gn:admin1_code":"28",
    "gn:admin2_code":"2504.0",
    "gn:asciiname":"Haji Gahi Kelay",
    "gn:country_code":"AF",
    "gn:dem":1655,
    "gn:feature_class":"P",
    "gn:feature_code":"PPL",
    "gn:name":"\u1e28\u0101j\u012b G\u0101h\u012b K\u00ealay",
    "gn:population":0,
    "gn:timezone":"Asia/Kabul",
    "iso:country":"AF",
    "name:und_x_variant":[
        "Khadzhigakhi-Kalay",
        "\u1e28\u0101jig\u0101hi Kalay",
        "\u1e28\u0101j\u012b G\u0101h\u012b K\u00ealay",
        "\u062d\u0627\u062c\u06cc \u06af\u0627\u0647\u06cc \u06a9\u0644\u06cc",
        "\u1e28\u0101jj\u012bg\u0101h\u012b Kalay"
    ],
    "wof:name":"Haji Gahi Kelay",
    "wof:placetype":"locality"
},
  "geometry": {"coordinates":[66.67256,32.4587],"type":"Point"}
}