{
  "type": "Feature",
  "properties": {
    "gn:admin1_code":"23",
    "gn:admin2_code":"2411.0",
    "gn:asciiname":"Nazar Muhammad Kelay",
    "gn:country_code":"AF",
    "gn:dem":1149,
    "gn:feature_class":"P",
    "gn:feature_code":"PPL",
    "gn:name":"Naz\u0327ar Mu\u1e29ammad K\u00ealay",
    "gn:population":0,
    "gn:timezone":"Asia/Kabul",
    "iso:country":"AF",
    "name:rus_x_preferred":[
        "\u041d\u0430\u0437\u0430\u0440\u043c\u0443\u0445\u0430\u043c\u043c\u0435\u0434-\u041a\u0430\u043b\u0430\u0439"
    ],
    "name:und_x_variant":[
        "Nazarmukhammed-Kalay",
        "Na\u1e95a\u1e5fmo\u1e29amme\u1e0f Kalay",
        "Naz\u0327armo\u1e29ammad Kalay",
        "Naz\u0327ar Mu\u1e29ammad K\u00ealay",
        "\u0646\u0638\u0631 \u0645\u062d\u0645\u062f \u06a9\u0644\u06cc"
    ],
    "wof:name":"Nazar Muhammad Kelay",
    "wof:placetype":"locality"
},
  "geometry": {"coordinates":[66.27835,30.9596],"type":"Point"}
}