{
  "type": "Feature",
  "properties": {
    "gn:admin1_code":"01",
    "gn:admin2_code":"1114",
    "gn:asciiname":"Kulan",
    "gn:country_code":"AF",
    "gn:dem":2504,
    "gn:feature_class":"P",
    "gn:feature_code":"PPL",
    "gn:name":"K\u016bl\u0101n",
    "gn:population":0,
    "gn:timezone":"Asia/Kabul",
    "iso:country":"AF",
    "name:und_x_variant":[
        "Arganj Khwa",
        "K\u016bl\u0101n",
        "\u06a9\u0648\u0644\u0627\u0646"
    ],
    "wof:name":"Kulan",
    "wof:placetype":"locality"
},
  "geometry": {"coordinates":[70.77324,37.2262],"type":"Point"}
}