{
  "type": "Feature",
  "properties": {
    "gn:admin1_code":"32",
    "gn:admin2_code":"1505.0",
    "gn:asciiname":"Guzarak",
    "gn:country_code":"AF",
    "gn:dem":2574,
    "gn:feature_class":"P",
    "gn:feature_code":"PPL",
    "gn:name":"Guz\u0304arak",
    "gn:population":0,
    "gn:timezone":"Asia/Kabul",
    "iso:country":"AF",
    "name:und_x_variant":[
        "Guz\u0304arak",
        "\u06af\u0630\u0631\u06a9",
        "Gozarak"
    ],
    "wof:name":"Guzarak",
    "wof:placetype":"locality"
},
  "geometry": {"coordinates":[67.57831999999999,35.64559000000001],"type":"Point"}
}