{
  "type": "Feature",
  "properties": {
    "gn:admin1_code":"10",
    "gn:admin2_code":"2311.0",
    "gn:asciiname":"Faqir Muhammad Khan Kelay",
    "gn:country_code":"AF",
    "gn:dem":713,
    "gn:feature_class":"P",
    "gn:feature_code":"PPL",
    "gn:name":"Faq\u012br Mu\u1e29ammad Kh\u0101n K\u00ealay",
    "gn:population":0,
    "gn:timezone":"Asia/Kabul",
    "iso:country":"AF",
    "name:und_x_variant":[
        "Faq\u012br Mu\u1e29ammad Kh\u0101n K\u00ealay",
        "\u0641\u0642\u06cc\u0631 \u0645\u062d\u0645\u062f \u062e\u0627\u0646 \u06a9\u0644\u06cc",
        "Faq\u012br Mo\u1e29ammad Kh\u0101n Kalay"
    ],
    "wof:name":"Faqir Muhammad Khan Kelay",
    "wof:placetype":"locality"
},
  "geometry": {"coordinates":[64.17438,31.14022000000001],"type":"Point"}
}