{
  "type": "Feature",
  "properties": {
    "gn:admin1_code":"28",
    "gn:admin2_code":"2506",
    "gn:asciiname":"Haji Fateh Khan Kelay",
    "gn:country_code":"AF",
    "gn:dem":1357,
    "gn:feature_class":"P",
    "gn:feature_code":"PPL",
    "gn:name":"\u1e28\u0101j\u012b F\u0101te\u1e29 Kh\u0101n K\u00ealay",
    "gn:population":0,
    "gn:timezone":"Asia/Kabul",
    "iso:country":"AF",
    "name:und_x_variant":[
        "\u1e28\u0101ji F\u0101te\u1e29kh\u0101n Kalay",
        "Khadzhi-Fatekhkhankalay",
        "\u062d\u0627\u062c\u06cc \u0641\u0627\u062a\u062d \u062e\u0627\u0646 \u06a9\u0644\u06cc",
        "\u1e28\u0101jj\u012b F\u0101te\u1e29kh\u0101n Kalay",
        "\u1e28\u0101j\u012b F\u0101te\u1e29 Kh\u0101n K\u00ealay"
    ],
    "wof:name":"Haji Fateh Khan Kelay",
    "wof:placetype":"locality"
},
  "geometry": {"coordinates":[66.42255,31.87574],"type":"Point"}
}