{
  "type": "Feature",
  "properties": {
    "gn:admin1_code":"03",
    "gn:admin2_code":"1314",
    "gn:asciiname":"Mir Khel",
    "gn:country_code":"AF",
    "gn:dem":1572,
    "gn:feature_class":"P",
    "gn:feature_code":"PPL",
    "gn:name":"M\u012br Kh\u0113l",
    "gn:population":0,
    "gn:timezone":"Asia/Kabul",
    "iso:country":"AF",
    "name:und_x_variant":[
        "M\u012br Kh\u0113l",
        "M\u012br Kheyl",
        "\u0645\u06cc\u0631 \u062e\u06d0\u0644"
    ],
    "wof:name":"Mir Khel",
    "wof:placetype":"locality"
},
  "geometry": {"coordinates":[69.56255999999999,36.20768],"type":"Point"}
}