{
  "type": "Feature",
  "properties": {
    "gn:admin1_code":"05",
    "gn:admin2_code":"2804",
    "gn:asciiname":"Sadbarg",
    "gn:country_code":"AF",
    "gn:dem":3118,
    "gn:feature_class":"P",
    "gn:feature_code":"PPL",
    "gn:name":"\u015eadbarg",
    "gn:population":0,
    "gn:timezone":"Asia/Kabul",
    "iso:country":"AF",
    "name:und_x_variant":[
        "\u015eadbarg",
        "\u0635\u062f\u0628\u0631\u06af"
    ],
    "wof:name":"Sadbarg",
    "wof:placetype":"locality"
},
  "geometry": {"coordinates":[66.73308,34.52309],"type":"Point"}
}