{
  "type": "Feature",
  "properties": {
    "gn:admin1_code":"30",
    "gn:admin2_code":"1608",
    "gn:asciiname":"'Omar Qul Bay",
    "gn:country_code":"AF",
    "gn:dem":1211,
    "gn:feature_class":"P",
    "gn:feature_code":"PPL",
    "gn:name":"\u2018Omar Qul B\u0101y",
    "gn:population":0,
    "gn:timezone":"Asia/Kabul",
    "iso:country":"AF",
    "name:fas_x_preferred":[
        "\u0639\u0645\u0631 \u0642\u0648\u0644 \u0628\u06cc"
    ],
    "name:rus_x_preferred":[
        "\u0423\u043c\u0430\u0440\u043a\u0443\u043b\u044c\u0431\u0430\u0439"
    ],
    "name:und_x_variant":[
        "Umarkul\u2019bay",
        "Umar Qul Bai",
        "\u2018Omar Qol Be\u012b",
        "\u2018Omar Qol Bey",
        "Umar Qul B\u0101y",
        "\u0639\u0645\u0631 \u0642\u0644 \u0628\u0627\u06cc",
        "\u2018Omar Qul B\u0101y"
    ],
    "wof:name":"'Omar Qul Bay",
    "wof:placetype":"locality"
},
  "geometry": {"coordinates":[66.63489,36.53905],"type":"Point"}
}