{
  "type": "Feature",
  "properties": {
    "gn:admin1_code":"39",
    "gn:admin2_code":"2602",
    "gn:asciiname":"Surkay Nawah",
    "gn:country_code":"AF",
    "gn:dem":1783,
    "gn:feature_class":"P",
    "gn:feature_code":"PPL",
    "gn:name":"S\u016brkay N\u0101wah",
    "gn:population":0,
    "gn:timezone":"Asia/Kabul",
    "iso:country":"AF",
    "name:und_x_variant":[
        "Se\u1e5fkay N\u0101wa",
        "S\u016b\u1e5fkay N\u0101wa",
        "Serkay N\u0101veh",
        "S\u016brkay N\u0101wah",
        "\u0633\u0648\u0631\u06a9\u06cc \u0646\u0627\u0648\u0647"
    ],
    "wof:name":"Surkay Nawah",
    "wof:placetype":"locality"
},
  "geometry": {"coordinates":[66.30136,33.19183],"type":"Point"}
}