{
  "type": "Feature",
  "properties": {
    "gn:admin1_code":"24",
    "gn:admin2_code":"1404",
    "gn:asciiname":"Mama Khel",
    "gn:country_code":"AF",
    "gn:dem":383,
    "gn:feature_class":"P",
    "gn:feature_code":"PPL",
    "gn:name":"M\u0101m\u0101 Kh\u0113l",
    "gn:population":0,
    "gn:timezone":"Asia/Kabul",
    "iso:country":"AF",
    "name:fas_x_preferred":[
        "\u0645\u0627\u0645\u0627 \u062e\u064a\u0644"
    ],
    "name:fas_x_variant":[
        "\u0645\u0627\u0645\u0627 \u062e\u06cc\u0644"
    ],
    "name:rus_x_preferred":[
        "\u041c\u0430\u043c\u0430\u0445\u0435\u0439\u043b\u044c"
    ],
    "name:und_x_variant":[
        "M\u0101m\u0101 Kh\u0113l",
        "Mamakheyl\u2019",
        "M\u0101m\u0101 Kheyl",
        "\u0645\u0627\u0645\u0627 \u062e\u06d0\u0644"
    ],
    "name:urd_x_preferred":[
        "\u0645\u0627\u0645\u0627 \u062e\u06cc\u0644"
    ],
    "wof:name":"Mama Khel",
    "wof:placetype":"locality"
},
  "geometry": {"coordinates":[68.70635,36.73208],"type":"Point"}
}