{
  "type": "Feature",
  "properties": {
    "gn:admin1_code":"36",
    "gn:admin2_code":"710.0",
    "gn:asciiname":"Guldin Kala",
    "gn:country_code":"AF",
    "gn:dem":2486,
    "gn:feature_class":"P",
    "gn:feature_code":"PPL",
    "gn:name":"Guld\u012bn Kal\u0101",
    "gn:population":0,
    "gn:timezone":"Asia/Kabul",
    "iso:country":"AF",
    "name:fas_x_preferred":[
        "\u06af\u0644\u062f\u064a\u0646 \u0643\u0644\u0627"
    ],
    "name:rus_x_preferred":[
        "Gul\u2019dinkala"
    ],
    "name:und_x_variant":[
        "Gul\u1e0f\u012bn Kal\u0101",
        "Gold\u012bn Kal\u0101",
        "Guld\u012bn Kal\u0101",
        "\u06af\u0644\u062f\u06cc\u0646 \u06a9\u0644\u0627"
    ],
    "wof:name":"Guldin Kala",
    "wof:placetype":"locality"
},
  "geometry": {"coordinates":[69.38159,33.69457],"type":"Point"}
}