{
  "type": "Feature",
  "properties": {
    "gn:admin1_code":"09",
    "gn:admin2_code":"2705",
    "gn:asciiname":"Nahr-e Khushk",
    "gn:country_code":"AF",
    "gn:dem":2391,
    "gn:feature_class":"P",
    "gn:feature_code":"PPL",
    "gn:name":"Nahr-e Khushk",
    "gn:population":0,
    "gn:timezone":"Asia/Kabul",
    "iso:country":"AF",
    "name:und_x_variant":[
        "Nakhri-Khushk",
        "Nahre Khu\u0161k",
        "Nahr-e Khushk",
        "\u0646\u0647\u0631 \u062e\u0634\u06a9",
        "Nahr-e Khoshk"
    ],
    "wof:name":"Nahr-e Khushk",
    "wof:placetype":"locality"
},
  "geometry": {"coordinates":[64.42551999999999,33.24368],"type":"Point"}
}