{
  "type": "Feature",
  "properties": {
    "gn:admin1_code":"05",
    "gn:admin2_code":"2801",
    "gn:asciiname":"Lah Dow",
    "gn:country_code":"AF",
    "gn:dem":3074,
    "gn:feature_class":"P",
    "gn:feature_code":"PPL",
    "gn:name":"Lah Dow",
    "gn:population":0,
    "gn:timezone":"Asia/Kabul",
    "iso:country":"AF",
    "name:und_x_variant":[
        "Lad\u016b",
        "Ladu",
        "La\u1e0f\u016b",
        "\u0644\u0689\u0648"
    ],
    "wof:name":"Lah Dow",
    "wof:placetype":"locality"
},
  "geometry": {"coordinates":[67.58331,34.75695],"type":"Point"}
}