{
  "type": "Feature",
  "properties": {
    "gn:admin1_code":"10",
    "gn:admin2_code":"2305",
    "gn:asciiname":"Sar Shelmin",
    "gn:country_code":"AF",
    "gn:dem":1753,
    "gn:feature_class":"P",
    "gn:feature_code":"PPL",
    "gn:name":"Sar Sh\u00ealm\u012bn",
    "gn:population":0,
    "gn:timezone":"Asia/Kabul",
    "iso:country":"AF",
    "name:fas_x_preferred":[
        "\u0633\u0631\u0654 \u0634\u064a\u0644\u0645\u064a\u0646"
    ],
    "name:rus_x_preferred":[
        "\u0421\u0430\u0440\u0448\u0438\u0440\u043c\u0438\u043d"
    ],
    "name:und_x_variant":[
        "Sarshirmin",
        "Sar \u0160\u011blm\u012bn",
        "Sar Sh\u0113lm\u012bn",
        "Sar Sh\u00ealm\u012bn",
        "\u0633\u0631 \u0634\u0644\u0645\u06cc\u0646",
        "Sar Shalm\u012bn"
    ],
    "wof:name":"Sar Shelmin",
    "wof:placetype":"locality"
},
  "geometry": {"coordinates":[65.06296,33.00398],"type":"Point"}
}