{
  "type": "Feature",
  "properties": {
    "gn:admin1_code":"18",
    "gn:admin2_code":"808",
    "gn:asciiname":"Sharkay",
    "gn:country_code":"AF",
    "gn:dem":1671,
    "gn:feature_class":"P",
    "gn:feature_code":"PPL",
    "gn:name":"Sharkay",
    "gn:population":0,
    "gn:timezone":"Asia/Kabul",
    "iso:country":"AF",
    "name:fas_x_preferred":[
        "\u0634\u0631\u0643\u06cc"
    ],
    "name:und_x_variant":[
        "\u0160\u0101rkay",
        "S\u0332h\u0332\u0101rkay",
        "\u069a\u0627\u0631\u06a9\u06cc",
        "Sharkay"
    ],
    "wof:name":"Sharkay",
    "wof:placetype":"locality"
},
  "geometry": {"coordinates":[70.35268000000001,34.08049],"type":"Point"}
}