{
  "type": "Feature",
  "properties": {
    "gn:admin1_code":"18",
    "gn:admin2_code":"807.0",
    "gn:asciiname":"Sabr-e 'Ulya",
    "gn:country_code":"AF",
    "gn:dem":1217,
    "gn:feature_class":"P",
    "gn:feature_code":"PPL",
    "gn:name":"\u015eabr-e \u2018Uly\u0101",
    "gn:population":0,
    "gn:timezone":"Asia/Kabul",
    "iso:country":"AF",
    "name:fas_x_preferred":[
        "\u0633\u0628\u0631\u0654 \u0639\u0644\u06cc\u0627"
    ],
    "name:und_x_variant":[
        "Shabr-e \u2018Oly\u0101",
        "Sabri-Ulia",
        "Sab\u1e5fe \u2018Uly\u0101",
        "Sabr-e \u2018Oly\u0101",
        "\u015eabr-e \u2018Uly\u0101",
        "\u0635\u0628\u0631 \u0639\u0644\u06cc\u0627",
        "\u015eabr\u012b \u2018Uly\u0101",
        "\u0635\u0628\u0631\u06cc \u0639\u0644\u06cc\u0627"
    ],
    "wof:name":"Sabr-e 'Ulya",
    "wof:placetype":"locality"
},
  "geometry": {"coordinates":[70.28653,34.21155],"type":"Point"}
}