{
  "type": "Feature",
  "properties": {
    "gn:admin1_code":"23",
    "gn:admin2_code":"2403.0",
    "gn:asciiname":"Nurzi",
    "gn:country_code":"AF",
    "gn:dem":1368,
    "gn:feature_class":"P",
    "gn:feature_code":"PPL",
    "gn:name":"N\u016brz\u012b",
    "gn:population":0,
    "gn:timezone":"Asia/Kabul",
    "iso:country":"AF",
    "name:und_x_variant":[
        "\u0646\u0648\u0631\u0632\u06cc",
        "N\u016brz\u012b",
        "N\u016brza\u012b"
    ],
    "wof:name":"Nurzi",
    "wof:placetype":"locality"
},
  "geometry": {"coordinates":[66.25385,31.94258],"type":"Point"}
}