{
  "type": "Feature",
  "properties": {
    "gn:admin1_code":"09",
    "gn:admin2_code":"2705",
    "gn:asciiname":"Nawah-ye Gharak",
    "gn:country_code":"AF",
    "gn:dem":2588,
    "gn:feature_class":"P",
    "gn:feature_code":"PPL",
    "gn:name":"N\u0101wah-ye Gh\u0101rak",
    "gn:population":0,
    "gn:timezone":"Asia/Kabul",
    "iso:country":"AF",
    "name:fas_x_preferred":[
        "\u0648\u0627\u062f\u0626 \u063a\u0627\u0631\u0643"
    ],
    "name:und_x_variant":[
        "N\u0101wa-i-Gh\u0101\u1e5fak",
        "N\u0101w-i-Gh\u0101\u1e5fak",
        "N\u0101v-e Gh\u0101rak",
        "Navayi-Garak",
        "N\u0101wah-ye Gh\u0101rak",
        "\u0646\u0627\u0648\u06c0 \u063a\u0627\u0631\u06a9",
        "N\u0101wah-e Gh\u0101rak"
    ],
    "wof:name":"Nawah-ye Gharak",
    "wof:placetype":"locality"
},
  "geometry": {"coordinates":[64.71061999999999,33.428],"type":"Point"}
}