{
  "type": "Feature",
  "properties": {
    "gn:admin1_code":"13",
    "gn:admin2_code":"112",
    "gn:asciiname":"Dzandah",
    "gn:country_code":"AF",
    "gn:dem":2535,
    "gn:feature_class":"P",
    "gn:feature_code":"PPL",
    "gn:name":"Dz\u0101ndah",
    "gn:population":0,
    "gn:timezone":"Asia/Kabul",
    "iso:country":"AF",
    "name:und_x_variant":[
        "Dzhanda",
        "J\u0101n\u1e0fa",
        "Jan\u1e0fah",
        "Dz\u0101ndah",
        "\u0681\u0627\u0646\u062f\u0647",
        "J\u0101ndah",
        "\u062c\u0627\u0646\u062f\u0647"
    ],
    "wof:name":"Dzandah",
    "wof:placetype":"locality"
},
  "geometry": {"coordinates":[69.57418,34.30191],"type":"Point"}
}