{
  "type": "Feature",
  "properties": {
    "gn:admin1_code":"11",
    "gn:admin2_code":"2007",
    "gn:asciiname":"Karez-e Sakharia",
    "gn:country_code":"AF",
    "gn:dem":1040,
    "gn:feature_class":"P",
    "gn:feature_code":"PPL",
    "gn:name":"K\u0101r\u0113z-e S\u0101khar\u012b\u0101",
    "gn:population":0,
    "gn:timezone":"Asia/Kabul",
    "iso:country":"AF",
    "name:und_x_variant":[
        "K\u0101\u1e5f\u0113z-i-S\u0101kha\u1e5fy\u0101",
        "K\u0101r\u0113z-e S\u0101khar\u012b\u0101",
        "\u06a9\u0627\u0631\u06d0\u0632 \u0633\u0627\u062e\u0631\u06cc\u0627",
        "K\u0101r\u012bz-e S\u0101khary\u0101"
    ],
    "wof:name":"Karez-e Sakharia",
    "wof:placetype":"locality"
},
  "geometry": {"coordinates":[61.78672,34.88608],"type":"Point"}
}