{
  "type": "Feature",
  "properties": {
    "gn:admin1_code":"27",
    "gn:admin2_code":"405",
    "gn:asciiname":"So Sang",
    "gn:country_code":"AF",
    "gn:dem":3276,
    "gn:feature_class":"P",
    "gn:feature_code":"PPL",
    "gn:name":"S\u014d Sang",
    "gn:population":0,
    "gn:timezone":"Asia/Kabul",
    "iso:country":"AF",
    "name:und_x_variant":[
        "Sosang",
        "S\u014dsang",
        "S\u016bsang",
        "S\u014d Sang",
        "\u0633\u0648 \u0633\u0646\u06af"
    ],
    "wof:name":"So Sang",
    "wof:placetype":"locality"
},
  "geometry": {"coordinates":[68.31178,34.42672],"type":"Point"}
}