{
  "type": "Feature",
  "properties": {
    "gn:admin1_code":"07",
    "gn:admin2_code":"1810.0",
    "gn:asciiname":"Qaram Qol",
    "gn:country_code":"AF",
    "gn:dem":334,
    "gn:feature_class":"P",
    "gn:feature_code":"PPLA2",
    "gn:name":"Qaram Q\u014dl",
    "gn:population":0,
    "gn:timezone":"Asia/Kabul",
    "iso:country":"AF",
    "name:und_x_variant":[
        "Qaramqol",
        "Qaramq\u016bl",
        "Qaram Q\u014dl",
        "\u0642\u0631\u0645 \u0642\u0648\u0644"
    ],
    "wof:name":"Qaram Qol",
    "wof:placetype":"locality"
},
  "geometry": {"coordinates":[65.04299,36.83006],"type":"Point"}
}