{
  "type": "Feature",
  "properties": {
    "gn:admin1_code":"27",
    "gn:admin2_code":"406",
    "gn:asciiname":"'Imrat Khel",
    "gn:country_code":"AF",
    "gn:dem":2298,
    "gn:feature_class":"P",
    "gn:feature_code":"PPL",
    "gn:name":"\u2018Imr\u0101t Kh\u0113l",
    "gn:population":0,
    "gn:timezone":"Asia/Kabul",
    "iso:country":"AF",
    "name:rus_x_preferred":[
        "Imratkheyl\u2019"
    ],
    "name:und_x_variant":[
        "\u2018Em\u1e5f\u0101tkh\u0113l",
        "\u2018Em\u0101rat Kh\u0113l",
        "\u2018Emr\u0101t Kh\u0113l",
        "\u2018Emr\u0101tkheyl",
        "\u2018Imr\u0101t Kh\u0113l",
        "\u0639\u0645\u0631\u0627\u062a \u062e\u06d0\u0644"
    ],
    "wof:name":"'Imrat Khel",
    "wof:placetype":"locality"
},
  "geometry": {"coordinates":[68.50972,34.17067],"type":"Point"}
}