{
  "type": "Feature",
  "properties": {
    "gn:admin1_code":"36",
    "gn:admin2_code":"702",
    "gn:asciiname":"Mangal Khel",
    "gn:country_code":"AF",
    "gn:dem":2282,
    "gn:feature_class":"P",
    "gn:feature_code":"PPL",
    "gn:name":"Mangal Kh\u0113l",
    "gn:population":0,
    "gn:timezone":"Asia/Kabul",
    "iso:country":"AF",
    "name:fas_x_preferred":[
        "\u0645\u0646\u06af\u0644 \u062e\u064a\u0644"
    ],
    "name:rus_x_preferred":[
        "Mangal\u2019kheyl\u2019"
    ],
    "name:und_x_variant":[
        "Mangalkh\u0113l",
        "Mangal Kheyl",
        "Mangal Kh\u0113l",
        "\u0645\u0646\u06af\u0644 \u062e\u06d0\u0644",
        "Mangal Kal\u0101",
        "\u0645\u0646\u06af\u0644 \u06a9\u0644\u0627"
    ],
    "wof:name":"Mangal Khel",
    "wof:placetype":"locality"
},
  "geometry": {"coordinates":[69.17310999999999,33.47391],"type":"Point"}
}