{
  "type": "Feature",
  "properties": {
    "gn:admin1_code":"27",
    "gn:admin2_code":"404.0",
    "gn:asciiname":"Mekh Korah",
    "gn:country_code":"AF",
    "gn:dem":3014,
    "gn:feature_class":"P",
    "gn:feature_code":"PPL",
    "gn:name":"M\u0113kh K\u014drah",
    "gn:population":0,
    "gn:timezone":"Asia/Kabul",
    "iso:country":"AF",
    "name:und_x_variant":[
        "Mekhkora",
        "M\u0113khk\u014d\u1e5fa",
        "Maykh K\u016brah",
        "M\u012bkhk\u016breh",
        "M\u0113kh K\u014drah",
        "\u0645\u06d0\u062e \u06a9\u0648\u0631\u0647"
    ],
    "wof:name":"Mekh Korah",
    "wof:placetype":"locality"
},
  "geometry": {"coordinates":[67.74124999999999,34.47183],"type":"Point"}
}