{
  "type": "Feature",
  "properties": {
    "gn:admin1_code":"27",
    "gn:admin2_code":"409",
    "gn:asciiname":"Kala Minar",
    "gn:country_code":"AF",
    "gn:dem":2376,
    "gn:feature_class":"P",
    "gn:feature_code":"PPL",
    "gn:name":"Kal\u0101 Min\u0101r",
    "gn:population":0,
    "gn:timezone":"Asia/Kabul",
    "iso:country":"AF",
    "name:fas_x_preferred":[
        "\u0643\u0644\u0647 \u0645\u0646\u0627\u0631"
    ],
    "name:und_x_variant":[
        "Kala-min\u0101\u1e5f",
        "Kalaminar",
        "Kal\u0101 Min\u0101r",
        "Kalah Men\u0101r",
        "\u06a9\u0644\u0627 \u0645\u0646\u0627\u0631"
    ],
    "wof:name":"Kala Minar",
    "wof:placetype":"locality"
},
  "geometry": {"coordinates":[68.38618000000001,33.74719],"type":"Point"}
}