{
  "type": "Feature",
  "properties": {
    "gn:admin1_code":"18",
    "gn:admin2_code":"810.0",
    "gn:asciiname":"Chinah",
    "gn:country_code":"AF",
    "gn:dem":1557,
    "gn:feature_class":"P",
    "gn:feature_code":"PPL",
    "gn:name":"Ch\u012bnah",
    "gn:population":0,
    "gn:timezone":"Asia/Kabul",
    "iso:country":"AF",
    "name:fas_x_preferred":[
        "\u0686\u064a\u0646\u0647"
    ],
    "name:und_x_variant":[
        "\u010cina",
        "Chinah",
        "Ch\u012bnah",
        "\u0686\u06cc\u0646\u0647",
        "China"
    ],
    "wof:name":"Chinah",
    "wof:placetype":"locality"
},
  "geometry": {"coordinates":[70.60771,34.05619],"type":"Point"}
}