{
  "type": "Feature",
  "properties": {
    "gn:admin1_code":"40",
    "gn:admin2_code":"309",
    "gn:asciiname":"Pitaw",
    "gn:country_code":"AF",
    "gn:dem":2128,
    "gn:feature_class":"P",
    "gn:feature_code":"PPL",
    "gn:name":"Pit\u0101w",
    "gn:population":0,
    "gn:timezone":"Asia/Kabul",
    "iso:country":"AF",
    "name:fas_x_preferred":[
        "\u067e\u06cc\u062a\u0627\u0648"
    ],
    "name:und_x_variant":[
        "P\u0113t\u0101v",
        "Petau",
        "P\u012bt\u0101v",
        "P\u0113t\u0101w",
        "\u067e\u06cc\u062a\u0627\u0648",
        "Pit\u0101w",
        "\u067e\u062a\u0627\u0648"
    ],
    "wof:name":"Pitaw",
    "wof:placetype":"locality"
},
  "geometry": {"coordinates":[69.46928,34.7346],"type":"Point"}
}