{
  "type": "Feature",
  "properties": {
    "gn:admin1_code":"01",
    "gn:admin2_code":"1107.0",
    "gn:asciiname":"Sar Shakh",
    "gn:country_code":"AF",
    "gn:dem":2471,
    "gn:feature_class":"P",
    "gn:feature_code":"PPL",
    "gn:name":"Sar Sh\u0101kh",
    "gn:population":0,
    "gn:timezone":"Asia/Kabul",
    "iso:country":"AF",
    "name:und_x_variant":[
        "Sar Sh\u0101kh",
        "\u0633\u0631 \u0634\u0627\u062e"
    ],
    "wof:name":"Sar Shakh",
    "wof:placetype":"locality"
},
  "geometry": {"coordinates":[71.51611,36.88145],"type":"Point"}
}