{
  "type": "Feature",
  "properties": {
    "gn:admin1_code":"7",
    "gn:admin2_code":"1802.0",
    "gn:asciiname":"Chahar Tut",
    "gn:country_code":"AF",
    "gn:dem":1092,
    "gn:feature_class":"P",
    "gn:feature_code":"PPL",
    "gn:name":"Chah\u0101r T\u016bt",
    "gn:population":0,
    "gn:timezone":"Asia/Kabul",
    "iso:country":"AF",
    "name:und_x_variant":[
        "Chah\u0101rtu",
        "Ch\u0101r T\u016bt",
        "Chah\u0101r T\u016bt",
        "\u0686\u0647\u0627\u0631 \u062a\u0648\u062a"
    ],
    "wof:name":"Chahar Tut",
    "wof:placetype":"locality"
},
  "geometry": {"coordinates":[64.87329,35.80918],"type":"Point"}
}