{
  "type": "Feature",
  "properties": {
    "gn:admin1_code":"27",
    "gn:admin2_code":"404",
    "gn:asciiname":"Kowshak",
    "gn:country_code":"AF",
    "gn:dem":3067,
    "gn:feature_class":"P",
    "gn:feature_code":"PPL",
    "gn:name":"Kowshak",
    "gn:population":0,
    "gn:timezone":"Asia/Kabul",
    "iso:country":"AF",
    "name:und_x_variant":[
        "Kaw\u0161ak",
        "Kavshak",
        "Kaushak",
        "Kowshak",
        "Kawshak",
        "\u06a9\u0648\u0634\u06a9"
    ],
    "wof:name":"Kowshak",
    "wof:placetype":"locality"
},
  "geometry": {"coordinates":[67.89952,34.27417],"type":"Point"}
}