{
  "type": "Feature",
  "properties": {
    "gn:admin1_code":"23",
    "gn:admin2_code":"2411.0",
    "gn:asciiname":"Khadzhi-Balo-Gumbad",
    "gn:country_code":"AF",
    "gn:dem":1247,
    "gn:feature_class":"P",
    "gn:feature_code":"PPL",
    "gn:name":"Khadzhi-Balo-Gumbad",
    "gn:population":0,
    "gn:timezone":"Asia/Kabul",
    "iso:country":"AF",
    "name:rus_x_preferred":[
        "\u0425\u0430\u0434\u0436\u0438-\u0411\u0430\u043b\u043e-\u0413\u0443\u043c\u0431\u0430\u0434"
    ],
    "name:und_x_variant":[
        "Khadzh\u012b Bal\u014d Gumbad",
        "\u062e\u062f\u0698\u06cc \u0628\u0644\u0648 \u06af\u0645\u0628\u062f"
    ],
    "wof:name":"Khadzhi-Balo-Gumbad",
    "wof:placetype":"locality"
},
  "geometry": {"coordinates":[66.41611,30.96306],"type":"Point"}
}