{
  "type": "Feature",
  "properties": {
    "gn:admin1_code":"23",
    "gn:admin2_code":"2404.0",
    "gn:asciiname":"Shatore",
    "gn:country_code":"AF",
    "gn:dem":1056,
    "gn:feature_class":"P",
    "gn:feature_code":"PPL",
    "gn:name":"Shatore",
    "gn:population":0,
    "gn:timezone":"Asia/Kabul",
    "iso:country":"AF",
    "name:fas_x_preferred":[
        "\u0634\u0627\u062a\u0648\u0631\u06cc"
    ],
    "name:und_x_variant":[
        "\u0160\u0101tor\u0113",
        "Sh\u0101t\u014dr\u0113",
        "Shatore",
        "\u0634\u0627\u062a\u0648\u0631\u06d0",
        "Sh\u0101t\u016br\u012b"
    ],
    "wof:name":"Shatore",
    "wof:placetype":"locality"
},
  "geometry": {"coordinates":[65.73947,31.77605],"type":"Point"}
}