{
  "type": "Feature",
  "properties": {
    "gn:admin1_code":"33",
    "gn:admin2_code":"3103.0",
    "gn:asciiname":"Chay Mir",
    "gn:country_code":"AF",
    "gn:dem":2548,
    "gn:feature_class":"P",
    "gn:feature_code":"PPL",
    "gn:name":"Chay M\u012br",
    "gn:population":0,
    "gn:timezone":"Asia/Kabul",
    "iso:country":"AF",
    "name:und_x_variant":[
        "Caym\u012b\u1e5f",
        "Chay M\u012br",
        "\u0686\u06cc \u0645\u06cc\u0631"
    ],
    "wof:name":"Chay Mir",
    "wof:placetype":"locality"
},
  "geometry": {"coordinates":[65.76488000000001,35.64314],"type":"Point"}
}