{
  "type": "Feature",
  "properties": {
    "gn:admin1_code":"07",
    "gn:admin2_code":"1805",
    "gn:asciiname":"Korkori",
    "gn:country_code":"AF",
    "gn:dem":1787,
    "gn:feature_class":"P",
    "gn:feature_code":"PPL",
    "gn:name":"K\u014drk\u014dr\u012b",
    "gn:population":0,
    "gn:timezone":"Asia/Kabul",
    "iso:country":"AF",
    "name:und_x_variant":[
        "K\u014d\u1e5fk\u014d\u1e5fi",
        "K\u016brk\u016br\u012b",
        "K\u014drk\u014dr\u012b",
        "\u06a9\u0648\u0631\u06a9\u0648\u0631\u06cc",
        "K\u014dk\u014dr\u012b"
    ],
    "wof:name":"Korkori",
    "wof:placetype":"locality"
},
  "geometry": {"coordinates":[64.54635999999999,35.32379],"type":"Point"}
}