{
  "type": "Feature",
  "properties": {
    "gn:admin1_code":"18",
    "gn:admin2_code":"803.0",
    "gn:asciiname":"Ghazi Kelay",
    "gn:country_code":"AF",
    "gn:dem":1781,
    "gn:feature_class":"P",
    "gn:feature_code":"PPL",
    "gn:name":"Gh\u0101z\u012b K\u00ealay",
    "gn:population":0,
    "gn:timezone":"Asia/Kabul",
    "iso:country":"AF",
    "name:fas_x_preferred":[
        "\u0642\u0631\u064a\u06c0 \u063a\u0627\u0632\u06cc"
    ],
    "name:und_x_variant":[
        "Gazikalay",
        "Gh\u0101zi Kalay",
        "Gh\u0101z\u012b K\u00ealay",
        "\u063a\u0627\u0632\u06cc \u06a9\u0644\u06cc"
    ],
    "wof:name":"Ghazi Kelay",
    "wof:placetype":"locality"
},
  "geometry": {"coordinates":[69.86837,34.25176],"type":"Point"}
}