{
  "type": "Feature",
  "properties": {
    "gn:admin1_code":"5",
    "gn:admin2_code":"2806.0",
    "gn:asciiname":"Sar-e Qol",
    "gn:country_code":"AF",
    "gn:dem":3002,
    "gn:feature_class":"P",
    "gn:feature_code":"PPL",
    "gn:name":"Sar-e Q\u014dl",
    "gn:population":0,
    "gn:timezone":"Asia/Kabul",
    "iso:country":"AF",
    "name:und_x_variant":[
        "Sa\u1e5fe Q\u014dl",
        "Sari-Kul\u2019",
        "Sar-e Q\u014dl",
        "\u0633\u0631 \u0642\u0648\u0644"
    ],
    "wof:name":"Sar-e Qol",
    "wof:placetype":"locality"
},
  "geometry": {"coordinates":[66.60319,34.15036],"type":"Point"}
}