{
  "type": "Feature",
  "properties": {
    "gn:admin1_code":"09",
    "gn:admin2_code":"2706",
    "gn:asciiname":"Khushkak",
    "gn:country_code":"AF",
    "gn:dem":2936,
    "gn:feature_class":"P",
    "gn:feature_code":"PPL",
    "gn:name":"Khushkak",
    "gn:population":0,
    "gn:timezone":"Asia/Kabul",
    "iso:country":"AF",
    "name:und_x_variant":[
        "Khu\u0161kak",
        "Khushkak",
        "\u062e\u0634\u06a9\u06a9",
        "Khoshkak"
    ],
    "wof:name":"Khushkak",
    "wof:placetype":"locality"
},
  "geometry": {"coordinates":[65.2573,33.93214],"type":"Point"}
}