{
  "type": "Feature",
  "properties": {
    "gn:admin1_code":"23",
    "gn:admin2_code":"2403",
    "gn:asciiname":"Payo Kelay",
    "gn:country_code":"AF",
    "gn:dem":1093,
    "gn:feature_class":"P",
    "gn:feature_code":"PPL",
    "gn:name":"P\u0101y\u014d K\u00ealay",
    "gn:population":0,
    "gn:timezone":"Asia/Kabul",
    "iso:country":"AF",
    "name:fas_x_preferred":[
        "\u0642\u0631\u064a\u06c0 \u067e\u0627\u06cc"
    ],
    "name:und_x_variant":[
        "Payukalay",
        "P\u0101y\u014d K\u00ealay",
        "\u067e\u0627\u06cc\u0648 \u06a9\u0644\u06cc",
        "P\u0101yo Kalay"
    ],
    "wof:name":"Payo Kelay",
    "wof:placetype":"locality"
},
  "geometry": {"coordinates":[65.7752,31.81274],"type":"Point"}
}