{
  "type": "Feature",
  "properties": {
    "gn:admin1_code":"05",
    "gn:admin2_code":"2804",
    "gn:asciiname":"Sulaimani",
    "gn:country_code":"AF",
    "gn:dem":3225,
    "gn:feature_class":"P",
    "gn:feature_code":"PPL",
    "gn:name":"Sula\u012bm\u0101n\u012b",
    "gn:population":0,
    "gn:timezone":"Asia/Kabul",
    "iso:country":"AF",
    "name:fas_x_preferred":[
        "\u0633\u0644\u064a\u0645\u0627\u0646\u06cc"
    ],
    "name:rus_x_preferred":[
        "\u0421\u0438\u043b\u0435\u043c\u0430\u043d\u0438"
    ],
    "name:und_x_variant":[
        "Sel\u0113m\u0101ni",
        "Silemani",
        "Sula\u012bm\u0101n\u012b",
        "Soleym\u0101n\u012b"
    ],
    "wof:name":"Sulaimani",
    "wof:placetype":"locality"
},
  "geometry": {"coordinates":[67.06068,34.62849],"type":"Point"}
}