{
  "type": "Feature",
  "properties": {
    "gn:admin1_code":"23",
    "gn:admin2_code":"2406.0",
    "gn:asciiname":"Bahram",
    "gn:country_code":"AF",
    "gn:dem":1216,
    "gn:feature_class":"P",
    "gn:feature_code":"PPL",
    "gn:name":"Bahr\u0101m",
    "gn:population":0,
    "gn:timezone":"Asia/Kabul",
    "iso:country":"AF",
    "name:ara_x_preferred":[
        "\u0628\u0647\u0631\u0627\u0645"
    ],
    "name:aze_x_preferred":[
        "B\u0259hram"
    ],
    "name:cat_x_preferred":[
        "Bahram"
    ],
    "name:dan_x_preferred":[
        "Bahram"
    ],
    "name:deu_x_preferred":[
        "Bahram"
    ],
    "name:ell_x_preferred":[
        "\u0392\u03b1\u03c1\u03ac\u03bc\u03b7\u03c2"
    ],
    "name:fas_x_preferred":[
        "\u0628\u0647\u0631\u0627\u0645"
    ],
    "name:ita_x_preferred":[
        "Bahram"
    ],
    "name:jpn_x_preferred":[
        "\u30d0\u30cf\u30e9\u30fc\u30e0"
    ],
    "name:kor_x_preferred":[
        "\ubc14\ud750\ub78c"
    ],
    "name:mzn_x_preferred":[
        "\u0628\u0647\u0631\u0627\u0645"
    ],
    "name:por_x_preferred":[
        "Vararanes"
    ],
    "name:rus_x_preferred":[
        "\u0411\u0430\u0445\u0440\u0430\u043c"
    ],
    "name:tgk_x_preferred":[
        "\u0411\u0430\u04b3\u0440\u043e\u043c"
    ],
    "name:ukr_x_preferred":[
        "\u0411\u0430\u0445\u0440\u0430\u043c"
    ],
    "name:und_x_variant":[
        "Bakhram",
        "Bahr\u0101m"
    ],
    "wof:name":"Bahram",
    "wof:placetype":"locality"
},
  "geometry": {"coordinates":[65.17049,32.08772],"type":"Point"}
}