{
  "type": "Feature",
  "properties": {
    "gn:admin1_code":"17",
    "gn:admin2_code":"505.0",
    "gn:asciiname":"Qal'ah-ye Shaykhak",
    "gn:country_code":"AF",
    "gn:dem":1863,
    "gn:feature_class":"P",
    "gn:feature_code":"PPL",
    "gn:name":"Qal\u2018ah-ye Shaykhak",
    "gn:population":0,
    "gn:timezone":"Asia/Kabul",
    "iso:country":"AF",
    "name:und_x_variant":[
        "Kalasheykhak",
        "Qal\u2019eh \u0160\u0113khak",
        "Qal\u2019eh-ye \u0160h\u0113khak",
        "Qal\u2018eh-ye Sheykhak",
        "Qal\u2018ah-ye Shaykhak",
        "\u0642\u0644\u0639\u0647 \u0634\u06cc\u062e\u06a9"
    ],
    "wof:name":"Qal'ah-ye Shaykhak",
    "wof:placetype":"locality"
},
  "geometry": {"coordinates":[69.07715,34.17417],"type":"Point"}
}