{
  "type": "Feature",
  "properties": {
    "gn:admin1_code":"8",
    "gn:admin2_code":"613.0",
    "gn:asciiname":"Alakhshan",
    "gn:country_code":"AF",
    "gn:dem":2934,
    "gn:feature_class":"P",
    "gn:feature_code":"PPL",
    "gn:name":"Alakhsh\u0101n",
    "gn:population":0,
    "gn:timezone":"Asia/Kabul",
    "iso:country":"AF",
    "name:fas_x_preferred":[
        "\u0639\u0644\u062e\u0634\u0627\u0646"
    ],
    "name:rus_x_preferred":[
        "\u0410\u043b\u0430\u0445\u0448\u0430\u043d"
    ],
    "name:und_x_variant":[
        "Alakh\u0161\u0101n",
        "\u2018Alakhsh\u0101n",
        "Alakhsh\u0101n",
        "\u0627\u0644\u062e\u0634\u0627\u0646"
    ],
    "wof:name":"Alakhshan",
    "wof:placetype":"locality"
},
  "geometry": {"coordinates":[67.86797,33.30975],"type":"Point"}
}