{
  "type": "Feature",
  "properties": {
    "gn:admin1_code":"23",
    "gn:admin2_code":"2416.0",
    "gn:asciiname":"'Abd ur Razaq",
    "gn:country_code":"AF",
    "gn:dem":925,
    "gn:feature_class":"P",
    "gn:feature_code":"PPL",
    "gn:name":"\u2018Abd ur Raz\u0101q",
    "gn:population":0,
    "gn:timezone":"Asia/Kabul",
    "iso:country":"AF",
    "name:und_x_variant":[
        "\u2018Ab\u1e0fu\u1e5f\u1e5faz\u0101q",
        "Abdurrazak",
        "\u2018Abd ol Razz\u0101q",
        "\u2018Abd ur Raz\u0101q",
        "\u0639\u0628\u062f \u0627\u0644\u0631\u0632\u0627\u0642",
        "\u2018Abd or Razz\u0101q"
    ],
    "wof:name":"'Abd ur Razaq",
    "wof:placetype":"locality"
},
  "geometry": {"coordinates":[65.37716,31.514],"type":"Point"}
}