{
  "type": "Feature",
  "properties": {
    "gn:admin1_code":"36",
    "gn:admin2_code":"702",
    "gn:asciiname":"Sahak",
    "gn:country_code":"AF",
    "gn:dem":2183,
    "gn:feature_class":"P",
    "gn:feature_code":"PPL",
    "gn:name":"Sah\u0101k",
    "gn:population":0,
    "gn:timezone":"Asia/Kabul",
    "iso:country":"AF",
    "name:und_x_variant":[
        "Sakhak",
        "Sah\u0101k",
        "\u0633\u0647\u0627\u06a9"
    ],
    "wof:name":"Sahak",
    "wof:placetype":"locality"
},
  "geometry": {"coordinates":[69.04848,33.5302],"type":"Point"}
}