{
  "type": "Feature",
  "properties": {
    "gn:admin1_code":"30",
    "gn:admin2_code":"1607",
    "gn:asciiname":"Mahajirin",
    "gn:country_code":"AF",
    "gn:dem":328,
    "gn:feature_class":"P",
    "gn:feature_code":"PPL",
    "gn:name":"Mah\u0101jir\u012bn",
    "gn:population":0,
    "gn:timezone":"Asia/Kabul",
    "iso:country":"AF",
    "name:fas_x_preferred":[
        "\u0645\u0647\u0627\u062c\u0631\u06cc\u0646"
    ],
    "name:rus_x_preferred":[
        "\u041c\u0430\u0445\u0430\u0434\u0436\u0438\u0440\u0438\u043d"
    ],
    "name:und_x_variant":[
        "Mahajir\u012bn",
        "Makhadzhirin",
        "Moh\u0101jer\u012bn",
        "Mah\u0101jir\u012bn"
    ],
    "wof:name":"Mahajirin",
    "wof:placetype":"locality"
},
  "geometry": {"coordinates":[66.68798000000001,36.79141],"type":"Point"}
}