{
  "type": "Feature",
  "properties": {
    "gn:admin1_code":"42",
    "gn:admin2_code":"3307.0",
    "gn:asciiname":"Baran Khel",
    "gn:country_code":"AF",
    "gn:dem":1955,
    "gn:feature_class":"P",
    "gn:feature_code":"PPL",
    "gn:name":"B\u0101r\u0101n Kh\u0113l",
    "gn:population":0,
    "gn:timezone":"Asia/Kabul",
    "iso:country":"AF",
    "name:fas_x_preferred":[
        "\u0628\u0627\u0631\u0627\u0646 \u062e\u064a\u0644"
    ],
    "name:rus_x_preferred":[
        "Barankheyl\u2019"
    ],
    "name:und_x_variant":[
        "B\u0101\u1e5f\u0101nkh\u0113l",
        "B\u0101r\u0101nkheyl",
        "\u0628\u0627\u0631\u0627\u0646 \u062e\u064a\u0644",
        "B\u0101r\u0101n Kh\u0113l",
        "\u0628\u0627\u0631\u0627\u0646 \u062e\u06d0\u0644"
    ],
    "wof:name":"Baran Khel",
    "wof:placetype":"locality"
},
  "geometry": {"coordinates":[69.4573,35.2566],"type":"Point"}
}