{
  "type": "Feature",
  "properties": {
    "gn:admin1_code":"28",
    "gn:admin2_code":"2510.0",
    "gn:asciiname":"Haji Mulla Ya'qub Kala",
    "gn:country_code":"AF",
    "gn:dem":1959,
    "gn:feature_class":"P",
    "gn:feature_code":"PPL",
    "gn:name":"\u1e28\u0101j\u012b Mull\u0101 Ya\u2018q\u016bb Kal\u0101",
    "gn:population":0,
    "gn:timezone":"Asia/Kabul",
    "iso:country":"AF",
    "name:und_x_variant":[
        "Khadzhimulla-Yakub-Kala",
        "H\u0101ji Mull\u0101 Ya\u2018q\u016bb Kal\u0101",
        "\u1e28\u0101j\u012b Mull\u0101 Ya\u2018q\u016bb Kal\u0101",
        "\u062d\u0627\u062c\u06cc \u0645\u0644\u0627 \u06cc\u0639\u0642\u0648\u0628 \u06a9\u0644\u0627",
        "\u1e28\u0101jj\u012b Moll\u0101 Ya\u2018q\u016bb Kal\u0101"
    ],
    "wof:name":"Haji Mulla Ya'qub Kala",
    "wof:placetype":"locality"
},
  "geometry": {"coordinates":[67.30429000000001,32.92631],"type":"Point"}
}