{
  "type": "Feature",
  "properties": {
    "gn:admin1_code":"5",
    "gn:admin2_code":"2806.0",
    "gn:asciiname":"Qal'ah-ye Gushi",
    "gn:country_code":"AF",
    "gn:dem":2563,
    "gn:feature_class":"P",
    "gn:feature_code":"PPL",
    "gn:name":"Qal\u2018ah-ye G\u016bsh\u012b",
    "gn:population":0,
    "gn:timezone":"Asia/Kabul",
    "iso:country":"AF",
    "name:und_x_variant":[
        "Qal\u0101-i-G\u016b\u0161i",
        "Kalayi-Gushi",
        "Qal\u2018ah-yeG\u014dsh\u012b",
        "Qal\u0101-ye G\u016bsh\u012b",
        "Qal\u2018ah-ye G\u016bsh\u012b",
        "\u0642\u0644\u0639\u0647 \u06af\u0648\u0634"
    ],
    "wof:name":"Qal'ah-ye Gushi",
    "wof:placetype":"locality"
},
  "geometry": {"coordinates":[66.85439000000001,34.26243],"type":"Point"}
}