{
  "type": "Feature",
  "properties": {
    "gn:admin1_code":"30",
    "gn:admin2_code":"1603.0",
    "gn:asciiname":"Chuqurak",
    "gn:country_code":"AF",
    "gn:dem":1901,
    "gn:feature_class":"P",
    "gn:feature_code":"PPL",
    "gn:name":"Chuqurak",
    "gn:population":0,
    "gn:timezone":"Asia/Kabul",
    "iso:country":"AF",
    "name:und_x_variant":[
        "Coqo\u1e5fak",
        "Choqorak",
        "\u0686\u0642\u0631\u06a9",
        "Chuqurak"
    ],
    "wof:name":"Chuqurak",
    "wof:placetype":"locality"
},
  "geometry": {"coordinates":[66.80585000000001,35.9065],"type":"Point"}
}