{
  "type": "Feature",
  "properties": {
    "gn:admin1_code":"9",
    "gn:admin2_code":"2705.0",
    "gn:asciiname":"Arpatu",
    "gn:country_code":"AF",
    "gn:dem":2685,
    "gn:feature_class":"P",
    "gn:feature_code":"PPL",
    "gn:name":"Arpat\u016b",
    "gn:population":0,
    "gn:timezone":"Asia/Kabul",
    "iso:country":"AF",
    "name:und_x_variant":[
        "Arpat\u016b",
        "\u0627\u0631\u067e\u062a\u0648"
    ],
    "wof:name":"Arpatu",
    "wof:placetype":"locality"
},
  "geometry": {"coordinates":[64.55615,33.30336],"type":"Point"}
}