{
  "type": "Feature",
  "properties": {
    "gn:admin1_code":"11",
    "gn:admin2_code":"2003.0",
    "gn:asciiname":"Rabat-e Sahib Zadah",
    "gn:country_code":"AF",
    "gn:dem":960,
    "gn:feature_class":"P",
    "gn:feature_code":"PPL",
    "gn:name":"Rab\u0101\u0163-e \u015e\u0101\u1e29ib Z\u0101dah",
    "gn:population":0,
    "gn:timezone":"Asia/Kabul",
    "iso:country":"AF",
    "name:fas_x_preferred":[
        "\u0631\u0628\u0627\u0637\u0654 \u0635\u0627\u062d\u0628\u0632\u0627\u062f\u0647"
    ],
    "name:und_x_variant":[
        "Rabati-Sakhibzada",
        "\u1e5eab\u0101\u1e6f-i-\u015e\u0101\u1e29eb Z\u0101\u1e0fah",
        "Rab\u0101\u0163-e \u015e\u0101\u1e29ib Z\u0101dah",
        "\u0631\u0628\u0627\u0637 \u0635\u0627\u062d\u0628 \u0632\u0627\u062f\u0647",
        "Rob\u0101\u0163-e \u015e\u0101\u1e29ebz\u0101deh"
    ],
    "wof:name":"Rabat-e Sahib Zadah",
    "wof:placetype":"locality"
},
  "geometry": {"coordinates":[62.21361,34.23175],"type":"Point"}
}