{
  "type": "Feature",
  "properties": {
    "gn:admin1_code":"14",
    "gn:admin2_code":"205.0",
    "gn:asciiname":"Mano Khel",
    "gn:country_code":"AF",
    "gn:dem":1357,
    "gn:feature_class":"P",
    "gn:feature_code":"PPL",
    "gn:name":"M\u0101\u1e49\u014d Kh\u0113l",
    "gn:population":0,
    "gn:timezone":"Asia/Kabul",
    "iso:country":"AF",
    "name:fas_x_preferred":[
        "\u0645\u0627\u0646\u0627 \u062e\u064a\u0644"
    ],
    "name:rus_x_preferred":[
        "Manokheyl\u2019"
    ],
    "name:und_x_variant":[
        "M\u0101\u1e49\u014dkh\u0113l",
        "M\u0101n\u014d Kh\u0113l",
        "M\u0101n\u0101kheyl",
        "M\u0101\u1e49\u014d Kh\u0113l",
        "\u0645\u0627\u06bc\u0648 \u062e\u06d0\u0644"
    ],
    "wof:name":"Mano Khel",
    "wof:placetype":"locality"
},
  "geometry": {"coordinates":[69.66274,34.87658],"type":"Point"}
}