{
  "type": "Feature",
  "properties": {
    "gn:admin1_code":"27",
    "gn:admin2_code":"404",
    "gn:asciiname":"Tubia",
    "gn:country_code":"AF",
    "gn:dem":3046,
    "gn:feature_class":"P",
    "gn:feature_code":"PPL",
    "gn:name":"T\u016bb\u012b\u0101",
    "gn:population":0,
    "gn:timezone":"Asia/Kabul",
    "iso:country":"AF",
    "name:rus_x_preferred":[
        "Tub\u2019ya"
    ],
    "name:und_x_variant":[
        "T\u016bby\u0101",
        "T\u016bb\u012b\u0101",
        "\u062a\u0648\u0628\u06cc\u0627"
    ],
    "wof:name":"Tubia",
    "wof:placetype":"locality"
},
  "geometry": {"coordinates":[67.81551,34.23883],"type":"Point"}
}