{
  "type": "Feature",
  "properties": {
    "gn:admin1_code":"02",
    "gn:admin2_code":"1904",
    "gn:asciiname":"Zighand Jow",
    "gn:country_code":"AF",
    "gn:dem":1964,
    "gn:feature_class":"P",
    "gn:feature_code":"PPL",
    "gn:name":"Zighand Jow",
    "gn:population":0,
    "gn:timezone":"Asia/Kabul",
    "iso:country":"AF",
    "name:und_x_variant":[
        "\u0632\u063a\u0646\u062f \u062c\u0648",
        "Zighand Jow",
        "Zeghan\u1e0fjaw"
    ],
    "wof:name":"Zighand Jow",
    "wof:placetype":"locality"
},
  "geometry": {"coordinates":[64.66089000000001,35.11137],"type":"Point"}
}