{
  "type": "Feature",
  "properties": {
    "gn:admin1_code":"36",
    "gn:admin2_code":"704.0",
    "gn:asciiname":"Bagh-e Kahol",
    "gn:country_code":"AF",
    "gn:dem":1997,
    "gn:feature_class":"P",
    "gn:feature_code":"PPL",
    "gn:name":"Bagh-e Kah\u014dl",
    "gn:population":0,
    "gn:timezone":"Asia/Kabul",
    "iso:country":"AF",
    "name:fas_x_preferred":[
        "\u0628\u0627\u063a \u0643\u0647\u0648\u0644"
    ],
    "name:rus_x_preferred":[
        "Bagkakhol\u2019"
    ],
    "name:und_x_variant":[
        "Bagh-e Kah\u014dl",
        "Bagh Kah\u014dl",
        "B\u0101gh Kah\u014dl",
        "B\u0101gh-e Kah\u016bl",
        "\u0628\u063a \u06a9\u0647\u0648\u0644"
    ],
    "wof:name":"Bagh-e Kahol",
    "wof:placetype":"locality"
},
  "geometry": {"coordinates":[69.46539,33.41381],"type":"Point"}
}