{
  "type": "Feature",
  "properties": {
    "gn:admin1_code":"3",
    "gn:admin2_code":"1308.0",
    "gn:asciiname":"Chaman",
    "gn:country_code":"AF",
    "gn:dem":1633,
    "gn:feature_class":"P",
    "gn:feature_code":"PPL",
    "gn:name":"Chaman",
    "gn:population":0,
    "gn:timezone":"Asia/Kabul",
    "iso:country":"AF",
    "name:ben_x_preferred":[
        "\u099a\u09ae\u09a8"
    ],
    "name:deu_x_preferred":[
        "Chaman"
    ],
    "name:fas_x_preferred":[
        "\u0686\u0645\u0646"
    ],
    "name:fra_x_preferred":[
        "Chaman"
    ],
    "name:hin_x_preferred":[
        "\u091a\u092e\u0928"
    ],
    "name:ita_x_preferred":[
        "Chaman"
    ],
    "name:jpn_x_preferred":[
        "\u30c1\u30e3\u30de\u30f3"
    ],
    "name:lit_x_preferred":[
        "\u010camanas"
    ],
    "name:msa_x_preferred":[
        "Chaman"
    ],
    "name:nep_x_preferred":[
        "\u091a\u092e\u0928"
    ],
    "name:pnb_x_preferred":[
        "\u0686\u0645\u0646"
    ],
    "name:pol_x_preferred":[
        "\u0106aman"
    ],
    "name:por_x_preferred":[
        "Chaman"
    ],
    "name:pus_x_preferred":[
        "\u0686\u0645\u0646"
    ],
    "name:rus_x_preferred":[
        "\u0427\u0430\u043c\u0430\u043d"
    ],
    "name:snd_x_preferred":[
        "\u0686\u0645\u0646"
    ],
    "name:spa_x_preferred":[
        "Chaman"
    ],
    "name:swe_x_preferred":[
        "Chaman"
    ],
    "name:tur_x_preferred":[
        "\u00c7aman"
    ],
    "name:ukr_x_preferred":[
        "\u0427\u0430\u043c\u0430\u043d"
    ],
    "name:und_x_variant":[
        "\u010caman",
        "Chaman",
        "\u0686\u0645\u0646"
    ],
    "name:urd_x_preferred":[
        "\u0686\u0645\u0646"
    ],
    "name:vie_x_preferred":[
        "Chaman"
    ],
    "wof:name":"Chaman",
    "wof:placetype":"locality"
},
  "geometry": {"coordinates":[69.61591,35.99575],"type":"Point"}
}