{
  "type": "Feature",
  "properties": {
    "gn:admin1_code":"09",
    "gn:admin2_code":"2701",
    "gn:asciiname":"Rakhnah",
    "gn:country_code":"AF",
    "gn:dem":2228,
    "gn:feature_class":"P",
    "gn:feature_code":"PPL",
    "gn:name":"Rakhnah",
    "gn:population":0,
    "gn:timezone":"Asia/Kabul",
    "iso:country":"AF",
    "name:und_x_variant":[
        "\u1e5eakhana",
        "\u1e5eakhna",
        "Rakhneh",
        "Rakhnah",
        "\u0631\u062e\u0646\u0647"
    ],
    "wof:name":"Rakhnah",
    "wof:placetype":"locality"
},
  "geometry": {"coordinates":[64.54173,34.66539],"type":"Point"}
}