{
  "type": "Feature",
  "properties": {
    "gn:admin1_code":"9",
    "gn:admin2_code":"2707.0",
    "gn:asciiname":"Sar-e Gharak",
    "gn:country_code":"AF",
    "gn:dem":3055,
    "gn:feature_class":"P",
    "gn:feature_code":"PPL",
    "gn:name":"Sar-e Gharak",
    "gn:population":0,
    "gn:timezone":"Asia/Kabul",
    "iso:country":"AF",
    "name:und_x_variant":[
        "Sari-Garak",
        "Sar-e Gh\u0101rak",
        "Sar-e Gharak",
        "\u0633\u0631 \u063a\u0631\u06a9"
    ],
    "wof:name":"Sar-e Gharak",
    "wof:placetype":"locality"
},
  "geometry": {"coordinates":[66.39601,34.59779],"type":"Point"}
}