{
  "type": "Feature",
  "properties": {
    "gn:admin1_code":"8",
    "gn:admin2_code":"604.0",
    "gn:asciiname":"Ambulaq",
    "gn:country_code":"AF",
    "gn:dem":3069,
    "gn:feature_class":"P",
    "gn:feature_code":"PPL",
    "gn:name":"Amb\u016bl\u0101q",
    "gn:population":0,
    "gn:timezone":"Asia/Kabul",
    "iso:country":"AF",
    "name:und_x_variant":[
        "Ambulak",
        "Ambol\u0101gh",
        "Amb\u016bl\u0101q",
        "\u0627\u0645\u0628\u0648\u0644\u0627\u0642"
    ],
    "wof:name":"Ambulaq",
    "wof:placetype":"locality"
},
  "geometry": {"coordinates":[67.4372,34.11268],"type":"Point"}
}