{
  "type": "Feature",
  "properties": {
    "gn:admin1_code":"01",
    "gn:admin2_code":"1120",
    "gn:asciiname":"Qal'ah-ye Kuf",
    "gn:country_code":"AF",
    "gn:dem":1383,
    "gn:feature_class":"P",
    "gn:feature_code":"PPLA2",
    "gn:name":"Qal\u2018ah-ye K\u016bf",
    "gn:population":0,
    "gn:timezone":"Asia/Kabul",
    "iso:country":"AF",
    "name:und_x_variant":[
        "Qala-i-Kof",
        "Qal\u2019a-i-K\u016bf",
        "Qala-i-Kot",
        "Kala Kuf",
        "Qal\u2018eh-ye K\u016bf",
        "Qal\u2018ah-ye K\u016bf",
        "\u0642\u0644\u0639\u06c0 \u06a9\u0648\u0641"
    ],
    "wof:name":"Qal'ah-ye Kuf",
    "wof:placetype":"locality"
},
  "geometry": {"coordinates":[70.47298000000001,38.04119],"type":"Point"}
}