{
  "type": "Feature",
  "properties": {
    "gn:admin1_code":"36",
    "gn:admin2_code":"705.0",
    "gn:asciiname":"Sur Sang",
    "gn:country_code":"AF",
    "gn:dem":2413,
    "gn:feature_class":"P",
    "gn:feature_code":"PPL",
    "gn:name":"S\u016br Sang",
    "gn:population":0,
    "gn:timezone":"Asia/Kabul",
    "iso:country":"AF",
    "name:fas_x_preferred":[
        "\u0633\u0648\u0631 \u0633\u0646\u06af"
    ],
    "name:und_x_variant":[
        "Sursang",
        "S\u016b\u1e5f Sang",
        "S\u016br Sang",
        "Sowr Sang"
    ],
    "wof:name":"Sur Sang",
    "wof:placetype":"locality"
},
  "geometry": {"coordinates":[69.3275,33.6675],"type":"Point"}
}