{
  "type": "Feature",
  "properties": {
    "gn:admin1_code":"13",
    "gn:admin2_code":"110.0",
    "gn:asciiname":"Qaryah-ye Gul Butah",
    "gn:country_code":"AF",
    "gn:dem":1792,
    "gn:feature_class":"P",
    "gn:feature_code":"PPL",
    "gn:name":"Qaryah-ye Gul Butah",
    "gn:population":0,
    "gn:timezone":"Asia/Kabul",
    "iso:country":"AF",
    "name:und_x_variant":[
        "\u0642\u0631\u06cc\u0647 \u06af\u0644 \u0628\u062a\u0647",
        "Gul Butah"
    ],
    "wof:name":"Qaryah-ye Gul Butah",
    "wof:placetype":"locality"
},
  "geometry": {"coordinates":[69.23359000000001,34.47453],"type":"Point"}
}