{
  "type": "Feature",
  "properties": {
    "gn:admin1_code":"28",
    "gn:admin2_code":"2507.0",
    "gn:asciiname":"Karo Khel",
    "gn:country_code":"AF",
    "gn:dem":2193,
    "gn:feature_class":"P",
    "gn:feature_code":"PPL",
    "gn:name":"Kar\u014d Kh\u0113l",
    "gn:population":0,
    "gn:timezone":"Asia/Kabul",
    "iso:country":"AF",
    "name:fas_x_preferred":[
        "\u0643\u0631\u0648 \u062e\u064a\u0644"
    ],
    "name:rus_x_preferred":[
        "Karukheyl\u2019"
    ],
    "name:und_x_variant":[
        "Ka\u1e5fo Kh\u0113l",
        "Kar\u014d Kh\u0113l",
        "\u06a9\u0631\u0648 \u062e\u06d0\u0644",
        "Karo Kheyl"
    ],
    "wof:name":"Karo Khel",
    "wof:placetype":"locality"
},
  "geometry": {"coordinates":[67.11941999999999,31.9689],"type":"Point"}
}