{
  "type": "Feature",
  "properties": {
    "gn:admin1_code":"5",
    "gn:admin2_code":"2806.0",
    "gn:asciiname":"Katah Khak",
    "gn:country_code":"AF",
    "gn:dem":2480,
    "gn:feature_class":"P",
    "gn:feature_code":"PPL",
    "gn:name":"Katah Kh\u0101k",
    "gn:population":0,
    "gn:timezone":"Asia/Kabul",
    "iso:country":"AF",
    "name:und_x_variant":[
        "Katakh\u0101k",
        "Katakhak",
        "Katah Kh\u0101k",
        "Katahkh\u0101k",
        "\u06a9\u062a\u0647 \u062e\u0627\u06a9"
    ],
    "wof:name":"Katah Khak",
    "wof:placetype":"locality"
},
  "geometry": {"coordinates":[66.93594,34.21543],"type":"Point"}
}