{
  "type": "Feature",
  "properties": {
    "gn:admin1_code":"23",
    "gn:admin2_code":"2401.0",
    "gn:asciiname":"Amin Kalachah",
    "gn:country_code":"AF",
    "gn:dem":1000,
    "gn:feature_class":"P",
    "gn:feature_code":"PPL",
    "gn:name":"Am\u012bn Kal\u0101chah",
    "gn:population":0,
    "gn:timezone":"Asia/Kabul",
    "iso:country":"AF",
    "name:und_x_variant":[
        "Am\u012bn Kal\u0101cheh",
        "Am\u012bn Kal\u0101\u010da",
        "Amin Kal\u0101cha",
        "Am\u012bn Kal\u0101chah",
        "\u0627\u0645\u06cc\u0646 \u06a9\u0644\u0627\u0686\u0647"
    ],
    "wof:name":"Amin Kalachah",
    "wof:placetype":"locality"
},
  "geometry": {"coordinates":[65.75747,31.59824],"type":"Point"}
}