{
  "type": "Feature",
  "properties": {
    "gn:admin1_code":"29",
    "gn:admin2_code":"2903.0",
    "gn:asciiname":"'Abd ur Rahman Chambar",
    "gn:country_code":"AF",
    "gn:dem":1992,
    "gn:feature_class":"P",
    "gn:feature_code":"PPL",
    "gn:name":"\u2018Abd ur Ra\u1e29m\u0101n Chambar",
    "gn:population":0,
    "gn:timezone":"Asia/Kabul",
    "iso:country":"AF",
    "name:und_x_variant":[
        "Abdurrakhman-Chambar",
        "Ab\u1e0fu\u1e5f \u1e5eahm\u0101n Camba\u1e5f",
        "\u0639\u0628\u062f\u0627\u0644\u0631\u062d\u0645\u0627\u0646 \u0686\u0645\u0628\u0631",
        "\u2018Abd or Ra\u1e29m\u0101n Chambar",
        "\u2018Abd ur Ra\u1e29m\u0101n Chambar"
    ],
    "wof:name":"'Abd ur Rahman Chambar",
    "wof:placetype":"locality"
},
  "geometry": {"coordinates":[68.11816999999999,32.68783],"type":"Point"}
}