{
  "type": "Feature",
  "properties": {
    "gn:admin1_code":"05",
    "gn:admin2_code":"2806",
    "gn:asciiname":"Nowbala-ye 'Ulyatak",
    "gn:country_code":"AF",
    "gn:dem":2794,
    "gn:feature_class":"P",
    "gn:feature_code":"PPL",
    "gn:name":"Nowb\u0101l\u0101-ye \u2018Uly\u0101tak",
    "gn:population":0,
    "gn:timezone":"Asia/Kabul",
    "iso:country":"AF",
    "name:und_x_variant":[
        "Naubalayi-Uliatak",
        "Nawb\u0101l\u0101-i-\u2018Uly\u0101tak",
        "Nowb\u0101l\u0101-ye \u2018Oly\u0101tak",
        "Nowb\u0101l\u0101-ye \u2018Uly\u0101tak",
        "\u0646\u0648\u0628\u0627\u0644\u0627 \u0639\u0644\u06cc\u0627\u062a\u06a9"
    ],
    "wof:name":"Nowbala-ye 'Ulyatak",
    "wof:placetype":"locality"
},
  "geometry": {"coordinates":[66.82956999999999,34.25147],"type":"Point"}
}