{
  "type": "Feature",
  "properties": {
    "gn:admin1_code":"39",
    "gn:admin2_code":"2605",
    "gn:asciiname":"Kelay",
    "gn:country_code":"AF",
    "gn:dem":1140,
    "gn:feature_class":"P",
    "gn:feature_code":"PPL",
    "gn:name":"K\u00ealay",
    "gn:population":0,
    "gn:timezone":"Asia/Kabul",
    "iso:country":"AF",
    "name:und_x_variant":[
        "K\u00ealay",
        "\u06a9\u0644\u06cc",
        "Kalay"
    ],
    "wof:name":"Kelay",
    "wof:placetype":"locality"
},
  "geometry": {"coordinates":[65.32601,32.57963],"type":"Point"}
}