{
  "type": "Feature",
  "properties": {
    "gn:admin1_code":"34",
    "gn:admin2_code":"1005.0",
    "gn:asciiname":"Shah Mirak",
    "gn:country_code":"AF",
    "gn:dem":1312,
    "gn:feature_class":"P",
    "gn:feature_code":"PPL",
    "gn:name":"Sh\u0101h M\u012brak",
    "gn:population":0,
    "gn:timezone":"Asia/Kabul",
    "iso:country":"AF",
    "wof:name":"Shah Mirak",
    "wof:placetype":"locality"
},
  "geometry": {"coordinates":[71.54111999999998,35.25132],"type":"Point"}
}