{
  "type": "Feature",
  "properties": {
    "gn:admin1_code":"10",
    "gn:admin2_code":"2306",
    "gn:asciiname":"Mian Akhtak",
    "gn:country_code":"AF",
    "gn:dem":1524,
    "gn:feature_class":"P",
    "gn:feature_code":"PPL",
    "gn:name":"M\u012b\u0101n Akhtak",
    "gn:population":0,
    "gn:timezone":"Asia/Kabul",
    "iso:country":"AF",
    "name:und_x_variant":[
        "My\u0101n \u0100khtak",
        "Mian-Akhtak",
        "M\u012b\u0101n Akhtak",
        "\u0645\u06cc\u0627\u0646 \u0627\u062e\u062a\u06a9"
    ],
    "wof:name":"Mian Akhtak",
    "wof:placetype":"locality"
},
  "geometry": {"coordinates":[64.74518,32.93543],"type":"Point"}
}