{
  "type": "Feature",
  "properties": {
    "gn:admin1_code":"27",
    "gn:admin2_code":"405",
    "gn:asciiname":"Uzbaki",
    "gn:country_code":"AF",
    "gn:dem":2582,
    "gn:feature_class":"P",
    "gn:feature_code":"PPL",
    "gn:name":"Uzbak\u012b",
    "gn:population":0,
    "gn:timezone":"Asia/Kabul",
    "iso:country":"AF",
    "name:und_x_variant":[
        "Uzbak\u012b",
        "Ozbak\u012b",
        "\u0627\u0632\u0628\u06a9\u06cc"
    ],
    "wof:name":"Uzbaki",
    "wof:placetype":"locality"
},
  "geometry": {"coordinates":[68.21359,34.09173],"type":"Point"}
}