{
  "type": "Feature",
  "properties": {
    "gn:admin1_code":"08",
    "gn:admin2_code":"607.0",
    "gn:asciiname":"Badrazar",
    "gn:country_code":"AF",
    "gn:dem":2878,
    "gn:feature_class":"P",
    "gn:feature_code":"PPL",
    "gn:name":"Badr\u0101z\u0101r",
    "gn:population":0,
    "gn:timezone":"Asia/Kabul",
    "iso:country":"AF",
    "name:und_x_variant":[
        "Badr\u0101z\u0101r",
        "\u0628\u062f\u0631\u0627\u0632\u0627\u0631"
    ],
    "wof:name":"Badrazar",
    "wof:placetype":"locality"
},
  "geometry": {"coordinates":[67.35365999999999,33.21543],"type":"Point"}
}