{
  "type": "Feature",
  "properties": {
    "gn:admin1_code":"06",
    "gn:admin2_code":"2108",
    "gn:asciiname":"Karez-e Nowabad",
    "gn:country_code":"AF",
    "gn:dem":603,
    "gn:feature_class":"P",
    "gn:feature_code":"PPL",
    "gn:name":"K\u0101r\u0113z-e Now\u0101b\u0101d",
    "gn:population":0,
    "gn:timezone":"Asia/Kabul",
    "iso:country":"AF",
    "name:und_x_variant":[
        "K\u0101\u1e5f\u0113ze Naw\u0101b\u0101\u1e0f",
        "K\u0101r\u012bz-e Now\u0101b\u0101d",
        "K\u0101r\u0113z-e Now\u0101b\u0101d",
        "\u06a9\u0627\u0631\u06d0\u0632 \u0646\u0648 \u0622\u0628\u0627\u062f"
    ],
    "wof:name":"Karez-e Nowabad",
    "wof:placetype":"locality"
},
  "geometry": {"coordinates":[61.41058,32.28100999999999],"type":"Point"}
}