{
  "type": "Feature",
  "properties": {
    "gn:admin1_code":"28",
    "gn:admin2_code":"2504",
    "gn:asciiname":"Qol-e Gumbad",
    "gn:country_code":"AF",
    "gn:dem":2491,
    "gn:feature_class":"P",
    "gn:feature_code":"PPL",
    "gn:name":"Q\u014dl-e Gumbad",
    "gn:population":0,
    "gn:timezone":"Asia/Kabul",
    "iso:country":"AF",
    "name:fas_x_preferred":[
        "\u0642\u0648\u0644\u0654 \u06af\u0646\u0628\u062f"
    ],
    "name:und_x_variant":[
        "Kuli-Gumbad",
        "Q\u014dle Gumba\u1e0f",
        "Q\u014dl-e Gumbad",
        "\u0642\u0648\u0644 \u06af\u0645\u0628\u062f",
        "Qowl-e Gonbad"
    ],
    "wof:name":"Qol-e Gumbad",
    "wof:placetype":"locality"
},
  "geometry": {"coordinates":[66.75837,32.70858],"type":"Point"}
}