{
  "type": "Feature",
  "properties": {
    "gn:admin1_code":"41",
    "gn:admin2_code":"3402.0",
    "gn:asciiname":"Kamarak",
    "gn:country_code":"AF",
    "gn:dem":1318,
    "gn:feature_class":"P",
    "gn:feature_code":"PPL",
    "gn:name":"Kamarak",
    "gn:population":0,
    "gn:timezone":"Asia/Kabul",
    "iso:country":"AF",
    "name:ceb_x_preferred":[
        "Kamarak"
    ],
    "name:swe_x_preferred":[
        "Kamarak"
    ],
    "name:und_x_variant":[
        "\u06a9\u0645\u0631\u06a9",
        "Kama\u1e5fak"
    ],
    "wof:name":"Kamarak",
    "wof:placetype":"locality"
},
  "geometry": {"coordinates":[66.17798000000001,33.37155],"type":"Point"}
}