{
  "type": "Feature",
  "properties": {
    "gn:admin1_code":"11",
    "gn:admin2_code":"2007.0",
    "gn:asciiname":"'Abdullah Khan",
    "gn:country_code":"AF",
    "gn:dem":887,
    "gn:feature_class":"P",
    "gn:feature_code":"PPL",
    "gn:name":"\u2018Abdull\u0101h Kh\u0101n",
    "gn:population":0,
    "gn:timezone":"Asia/Kabul",
    "iso:country":"AF",
    "name:und_x_variant":[
        "Abdull\u0101h Kh\u0101n",
        "\u2018Abdull\u0101h Kh\u0101n",
        "\u0639\u0628\u062f\u0627\u0644\u0644\u0640\u0647 \u062e\u0627\u0646",
        "\u2018Abdoll\u0101h Kh\u0101n"
    ],
    "wof:name":"'Abdullah Khan",
    "wof:placetype":"locality"
},
  "geometry": {"coordinates":[61.68544,34.98434],"type":"Point"}
}