{
  "type": "Feature",
  "properties": {
    "gn:admin1_code":"07",
    "gn:admin2_code":"1802",
    "gn:asciiname":"Ming Darakht",
    "gn:country_code":"AF",
    "gn:dem":521,
    "gn:feature_class":"P",
    "gn:feature_code":"PPL",
    "gn:name":"Ming Darakht",
    "gn:population":0,
    "gn:timezone":"Asia/Kabul",
    "iso:country":"AF",
    "name:und_x_variant":[
        "Meng Darakht",
        "Minj Darakht",
        "Ming Darakht",
        "\u0645\u0646\u06af \u062f\u0631\u062e\u062a",
        "Meng Derakht"
    ],
    "wof:name":"Ming Darakht",
    "wof:placetype":"locality"
},
  "geometry": {"coordinates":[64.61031,36.15125],"type":"Point"}
}