{
  "type": "Feature",
  "properties": {
    "gn:admin1_code":"07",
    "gn:admin2_code":"1808",
    "gn:asciiname":"Simlik",
    "gn:country_code":"AF",
    "gn:dem":752,
    "gn:feature_class":"P",
    "gn:feature_code":"PPL",
    "gn:name":"Siml\u012bk",
    "gn:population":0,
    "gn:timezone":"Asia/Kabul",
    "iso:country":"AF",
    "name:und_x_variant":[
        "Semlik (1)",
        "Semlik",
        "Siml\u012bk",
        "\u0633\u0645\u0644\u06cc\u06a9"
    ],
    "wof:name":"Simlik",
    "wof:placetype":"locality"
},
  "geometry": {"coordinates":[65.05176,36.1186],"type":"Point"}
}