{
  "type": "Feature",
  "properties": {
    "gn:admin1_code":"02",
    "gn:admin2_code":"1904",
    "gn:asciiname":"Regi",
    "gn:country_code":"AF",
    "gn:dem":1244,
    "gn:feature_class":"P",
    "gn:feature_code":"PPL",
    "gn:name":"Regi",
    "gn:population":0,
    "gn:timezone":"Asia/Kabul",
    "iso:country":"AF",
    "name:cat_x_preferred":[
        "Reg\u00ed"
    ],
    "name:dan_x_preferred":[
        "Regi"
    ],
    "name:nld_x_preferred":[
        "Regi"
    ],
    "name:und_x_variant":[
        "R\u0113gay",
        "\u1e5e\u0113gi",
        "R\u012bg\u012b",
        "R\u0113g\u012b",
        "\u0631\u06d0\u06af\u06cc"
    ],
    "wof:name":"Regi",
    "wof:placetype":"locality"
},
  "geometry": {"coordinates":[63.81875,34.86814],"type":"Point"}
}