{
  "type": "Feature",
  "properties": {
    "gn:admin1_code":"01",
    "gn:admin2_code":"1116.0",
    "gn:asciiname":"Dogh Ghalat-e Darayim",
    "gn:country_code":"AF",
    "gn:dem":1766,
    "gn:feature_class":"P",
    "gn:feature_code":"PPL",
    "gn:name":"D\u014dgh Ghala\u0163-e Dar\u0101yim",
    "gn:population":0,
    "gn:timezone":"Asia/Kabul",
    "iso:country":"AF",
    "name:und_x_variant":[
        "\u1e0e\u014dgh",
        "D\u016bgh",
        "D\u014dgh Ghala\u0163-e Dar\u0101yim",
        "\u062f\u0648\u063a \u063a\u0644\u0637 \u062f\u0631\u0627\u06cc\u0645"
    ],
    "wof:name":"Dogh Ghalat-e Darayim",
    "wof:placetype":"locality"
},
  "geometry": {"coordinates":[70.36006,36.94871],"type":"Point"}
}