{
  "type": "Feature",
  "properties": {
    "gn:admin1_code":"23",
    "gn:admin2_code":"2412",
    "gn:asciiname":"Fayz Muhammad Kelay",
    "gn:country_code":"AF",
    "gn:dem":1191,
    "gn:feature_class":"P",
    "gn:feature_code":"PPL",
    "gn:name":"Fay\u1e95 Mu\u1e29ammad K\u00ealay",
    "gn:population":0,
    "gn:timezone":"Asia/Kabul",
    "iso:country":"AF",
    "name:und_x_variant":[
        "P\u012br Muhammad",
        "Fay\u1e0f\u1e95 Mo\u1e29amma\u1e0f Kalay",
        "Pir Muchamed",
        "Faizmukhammed-Kalay",
        "Fa\u012b\u1e95 Mu\u1e29ammad K\u00ealay",
        "\u0641\u06cc\u0636 \u0645\u062d\u0645\u062f \u06a9\u0644\u06cc",
        "Fey\u1e95 Mo\u1e29ammad Kal\u012b",
        "Fay\u1e95 Mu\u1e29ammad K\u00ealay"
    ],
    "wof:name":"Fayz Muhammad Kelay",
    "wof:placetype":"locality"
},
  "geometry": {"coordinates":[66.32428,31.56268],"type":"Point"}
}