{
  "type": "Feature",
  "properties": {
    "gn:admin1_code":"14",
    "gn:admin2_code":"204.0",
    "gn:asciiname":"Paryat",
    "gn:country_code":"AF",
    "gn:dem":1743,
    "gn:feature_class":"P",
    "gn:feature_code":"PPL",
    "gn:name":"P\u0101ryat",
    "gn:population":0,
    "gn:timezone":"Asia/Kabul",
    "iso:country":"AF",
    "name:fas_x_preferred":[
        "\u067e\u0627\u0631\u064a\u062a"
    ],
    "name:rus_x_preferred":[
        "Par\u2019yat"
    ],
    "name:und_x_variant":[
        "P\u0101rayat",
        "P\u0101ryat",
        "\u067e\u0627\u0631\u06cc\u062a"
    ],
    "wof:name":"Paryat",
    "wof:placetype":"locality"
},
  "geometry": {"coordinates":[69.61282,34.99785],"type":"Point"}
}