{
  "type": "Feature",
  "properties": {
    "gn:admin1_code":"09",
    "gn:admin2_code":"2701",
    "gn:asciiname":"Sadman",
    "gn:country_code":"AF",
    "gn:dem":2130,
    "gn:feature_class":"P",
    "gn:feature_code":"PPL",
    "gn:name":"\u015eadman",
    "gn:population":0,
    "gn:timezone":"Asia/Kabul",
    "iso:country":"AF",
    "name:und_x_variant":[
        "Sa\u1e0fman",
        "Sh\u0101dm\u0101n",
        "\u015eadman",
        "\u0635\u062f\u0645\u0646"
    ],
    "wof:name":"Sadman",
    "wof:placetype":"locality"
},
  "geometry": {"coordinates":[65.24815,34.87332],"type":"Point"}
}