{
  "type": "Feature",
  "properties": {
    "gn:admin1_code":"8",
    "gn:admin2_code":"614.0",
    "gn:asciiname":"Chanbar-e Yar Muhammad",
    "gn:country_code":"AF",
    "gn:dem":2095,
    "gn:feature_class":"P",
    "gn:feature_code":"PPL",
    "gn:name":"Chanbar-e Y\u0101r Mu\u1e29ammad",
    "gn:population":0,
    "gn:timezone":"Asia/Kabul",
    "iso:country":"AF",
    "name:und_x_variant":[
        "\u010cambare Y\u0101rmohammad",
        "Chambari-Yarmukhammed",
        "Chambar-e Y\u0101r Mu\u1e29ammad",
        "Chanbar-e Y\u0101r Mo\u1e29ammad",
        "Chanbar-e Y\u0101r Mu\u1e29ammad",
        "\u0686\u0646\u0628\u0631 \u064a\u0627\u0631 \u0645\u062d\u0645\u062f"
    ],
    "wof:name":"Chanbar-e Yar Muhammad",
    "wof:placetype":"locality"
},
  "geometry": {"coordinates":[68.38189,33.38214],"type":"Point"}
}