{
  "type": "Feature",
  "properties": {
    "gn:admin1_code":"5",
    "gn:admin2_code":"2806.0",
    "gn:asciiname":"Regak",
    "gn:country_code":"AF",
    "gn:dem":2679,
    "gn:feature_class":"P",
    "gn:feature_code":"PPL",
    "gn:name":"R\u0113gak",
    "gn:population":0,
    "gn:timezone":"Asia/Kabul",
    "iso:country":"AF",
    "name:und_x_variant":[
        "\u1e5e\u0113gak",
        "Regak",
        "R\u0113gak",
        "\u0631\u06d0\u06af\u06a9"
    ],
    "wof:name":"Regak",
    "wof:placetype":"locality"
},
  "geometry": {"coordinates":[66.62505999999999,34.04994],"type":"Point"}
}