{
  "type": "Feature",
  "properties": {
    "gn:admin1_code":"30",
    "gn:admin2_code":"1610.0",
    "gn:asciiname":"Chashmah",
    "gn:country_code":"AF",
    "gn:dem":842,
    "gn:feature_class":"P",
    "gn:feature_code":"PPL",
    "gn:name":"Chashmah",
    "gn:population":0,
    "gn:timezone":"Asia/Kabul",
    "iso:country":"AF",
    "name:und_x_variant":[
        "Chashma",
        "Cheshmeh",
        "Chashmah",
        "\u0686\u0634\u0645\u0647"
    ],
    "wof:name":"Chashmah",
    "wof:placetype":"locality"
},
  "geometry": {"coordinates":[66.85845999999999,36.09225],"type":"Point"}
}