{
  "type": "Feature",
  "properties": {
    "gn:admin1_code":"26",
    "gn:admin2_code":"1202.0",
    "gn:asciiname":"Naqil",
    "gn:country_code":"AF",
    "gn:dem":615,
    "gn:feature_class":"P",
    "gn:feature_code":"PPL",
    "gn:name":"N\u0101qil",
    "gn:population":0,
    "gn:timezone":"Asia/Kabul",
    "iso:country":"AF",
    "name:rus_x_preferred":[
        "\u041d\u0430\u043a\u0438\u043b\u044c"
    ],
    "name:und_x_variant":[
        "Nakil\u2019",
        "N\u0101qel",
        "N\u0101qil",
        "\u0646\u0627\u0642\u0644"
    ],
    "wof:name":"Naqil",
    "wof:placetype":"locality"
},
  "geometry": {"coordinates":[69.29271999999999,36.73762],"type":"Point"}
}