{
  "type": "Feature",
  "properties": {
    "gn:admin1_code":"5",
    "gn:admin2_code":"2805.0",
    "gn:asciiname":"Allah Koh",
    "gn:country_code":"AF",
    "gn:dem":2983,
    "gn:feature_class":"P",
    "gn:feature_code":"PPL",
    "gn:name":"All\u0101h K\u014dh",
    "gn:population":0,
    "gn:timezone":"Asia/Kabul",
    "iso:country":"AF",
    "name:und_x_variant":[
        "Alakoh",
        "Alakokh",
        "Alak\u016bh",
        "Alah K\u014dh",
        "Alahk\u016bh",
        "All\u0101h K\u014dh",
        "\u0627\u0644\u0644\u0640\u0647 \u06a9\u0648\u0647"
    ],
    "wof:name":"Allah Koh",
    "wof:placetype":"locality"
},
  "geometry": {"coordinates":[66.86256,34.29408],"type":"Point"}
}