{
  "type": "Feature",
  "properties": {
    "gn:admin1_code":"33",
    "gn:admin2_code":"3103.0",
    "gn:asciiname":"Baydistan",
    "gn:country_code":"AF",
    "gn:dem":1443,
    "gn:feature_class":"P",
    "gn:feature_code":"PPL",
    "gn:name":"Bayd\u012bst\u0101n",
    "gn:population":0,
    "gn:timezone":"Asia/Kabul",
    "iso:country":"AF",
    "name:und_x_variant":[
        "Bedist\u0101n",
        "B\u012bdest\u0101n",
        "Bayd\u012bst\u0101n",
        "\u0628\u06cc\u062f\u06cc\u0633\u062a\u0627\u0646"
    ],
    "wof:name":"Baydistan",
    "wof:placetype":"locality"
},
  "geometry": {"coordinates":[65.90854,35.83951],"type":"Point"}
}