{
  "type": "Feature",
  "properties": {
    "gn:admin1_code":"3",
    "gn:admin2_code":"1304.0",
    "gn:asciiname":"'Alam 'Ali",
    "gn:country_code":"AF",
    "gn:dem":978,
    "gn:feature_class":"P",
    "gn:feature_code":"PPL",
    "gn:name":"\u2018Alam \u2018Al\u012b",
    "gn:population":0,
    "gn:timezone":"Asia/Kabul",
    "iso:country":"AF",
    "name:und_x_variant":[
        "\u2018Alam\u2018ali",
        "\u2018Alam \u2018Al\u012b",
        "\u0639\u0644\u0645 \u0639\u0644\u06cc"
    ],
    "wof:name":"'Alam 'Ali",
    "wof:placetype":"locality"
},
  "geometry": {"coordinates":[68.46106999999999,35.57816],"type":"Point"}
}