{
  "type": "Feature",
  "properties": {
    "gn:admin1_code":"23",
    "gn:admin2_code":"2412.0",
    "gn:asciiname":"Tughay Qubod Kelay",
    "gn:country_code":"AF",
    "gn:dem":1401,
    "gn:feature_class":"P",
    "gn:feature_code":"PPL",
    "gn:name":"T\u016bghay Qub\u014dd K\u00ealay",
    "gn:population":0,
    "gn:timezone":"Asia/Kabul",
    "iso:country":"AF",
    "name:und_x_variant":[
        "Qob\u014dd Kalay",
        "T\u016bghay Qob\u014dd Kalay",
        "Tugaykubod-Kalay",
        "T\u016bghay Qob\u016bd Kalay",
        "T\u016bghay",
        "T\u016bghay Qub\u014dd K\u00ealay",
        "\u062a\u0648\u063a\u06cc \u0642\u0628\u0648\u062f \u06a9\u0644\u06cc"
    ],
    "wof:name":"Tughay Qubod Kelay",
    "wof:placetype":"locality"
},
  "geometry": {"coordinates":[66.73841,31.46181],"type":"Point"}
}