{
  "type": "Feature",
  "properties": {
    "gn:admin1_code":"5",
    "gn:admin2_code":"2802.0",
    "gn:asciiname":"Amrutak",
    "gn:country_code":"AF",
    "gn:dem":2796,
    "gn:feature_class":"P",
    "gn:feature_code":"PPL",
    "gn:name":"Amr\u016btak",
    "gn:population":0,
    "gn:timezone":"Asia/Kabul",
    "iso:country":"AF",
    "name:und_x_variant":[
        "Am\u1e5f\u016btak",
        "Amrutak",
        "Amrowtak",
        "Amr\u014dtak",
        "Amr\u016btak",
        "\u0627\u0645\u0631\u0648\u062a\u06a9"
    ],
    "wof:name":"Amrutak",
    "wof:placetype":"locality"
},
  "geometry": {"coordinates":[68.03230000000001,34.95978],"type":"Point"}
}