{
  "type": "Feature",
  "properties": {
    "gn:admin1_code":"30",
    "gn:admin2_code":"1610",
    "gn:asciiname":"Mulla Ghulam",
    "gn:country_code":"AF",
    "gn:dem":1873,
    "gn:feature_class":"P",
    "gn:feature_code":"PPL",
    "gn:name":"Mull\u0101 Ghul\u0101m",
    "gn:population":0,
    "gn:timezone":"Asia/Kabul",
    "iso:country":"AF",
    "name:und_x_variant":[
        "Mol\u0101ghol\u0101m",
        "Moll\u0101 Ghol\u0101m",
        "Mull\u0101 Ghul\u0101m",
        "\u0645\u0644\u0627 \u063a\u0644\u0627\u0645"
    ],
    "wof:name":"Mulla Ghulam",
    "wof:placetype":"locality"
},
  "geometry": {"coordinates":[67.07249,35.95286],"type":"Point"}
}