{
  "type": "Feature",
  "properties": {
    "gn:admin1_code":"03",
    "gn:admin2_code":"1308",
    "gn:asciiname":"Dehgak-e Khawush",
    "gn:country_code":"AF",
    "gn:dem":2384,
    "gn:feature_class":"P",
    "gn:feature_code":"PPL",
    "gn:name":"Dehgak-e Kh\u0101wush",
    "gn:population":0,
    "gn:timezone":"Asia/Kabul",
    "iso:country":"AF",
    "name:und_x_variant":[
        "\u1e0eehake Kh\u0101wus",
        "Dehaka",
        "Kh\u0101wush",
        "Dehgak-e Kh\u0101wush",
        "\u062f\u0647 \u06af\u06a9 \u062e\u0627\u0648\u0634"
    ],
    "wof:name":"Dehgak-e Khawush",
    "wof:placetype":"locality"
},
  "geometry": {"coordinates":[69.57652,35.7885],"type":"Point"}
}