{
  "type": "Feature",
  "properties": {
    "gn:admin1_code":"09",
    "gn:admin2_code":"2707",
    "gn:asciiname":"Shakh Now",
    "gn:country_code":"AF",
    "gn:dem":3037,
    "gn:feature_class":"P",
    "gn:feature_code":"PPL",
    "gn:name":"Sh\u0101kh Now",
    "gn:population":0,
    "gn:timezone":"Asia/Kabul",
    "iso:country":"AF",
    "name:und_x_variant":[
        "\u0160akhnaw",
        "Shakhnau",
        "Shakh Now",
        "Sh\u0101khnow",
        "\u0634\u0627\u062e \u0646\u0648",
        "Sh\u0101kh Now"
    ],
    "wof:name":"Shakh Now",
    "wof:placetype":"locality"
},
  "geometry": {"coordinates":[66.31215999999999,34.58962],"type":"Point"}
}