{
  "type": "Feature",
  "properties": {
    "gn:admin1_code":"34",
    "gn:admin2_code":"1014.0",
    "gn:asciiname":"Shaykhano Kelay",
    "gn:country_code":"AF",
    "gn:dem":719,
    "gn:feature_class":"P",
    "gn:feature_code":"PPL",
    "gn:name":"Shaykh\u0101n\u014d K\u00ealay",
    "gn:population":0,
    "gn:timezone":"Asia/Kabul",
    "iso:country":"AF",
    "name:und_x_variant":[
        "\u0160\u0113kh\u0101no Kalay",
        "Sheykhanukalay",
        "Sheykh\u0101no Kalay",
        "Shaykh\u0101n\u014d K\u00ealay",
        "\u0634\u06cc\u062e\u0627\u0646\u0648 \u06a9\u0644\u06cc"
    ],
    "wof:name":"Shaykhano Kelay",
    "wof:placetype":"locality"
},
  "geometry": {"coordinates":[70.91143000000002,34.65349000000001],"type":"Point"}
}