{
  "type": "Feature",
  "properties": {
    "gn:admin1_code":"32",
    "gn:admin2_code":"1503",
    "gn:asciiname":"Khowal-e Chaharmaghz",
    "gn:country_code":"AF",
    "gn:dem":1417,
    "gn:feature_class":"P",
    "gn:feature_code":"PPL",
    "gn:name":"Khow\u0101l-e Chah\u0101rmaghz",
    "gn:population":0,
    "gn:timezone":"Asia/Kabul",
    "iso:country":"AF",
    "name:und_x_variant":[
        "Khaw\u0101le Cah\u0101\u1e5fmaghz",
        "Khav\u0101leh Chah\u0101r Maghz",
        "Khow\u0101l-e Chah\u0101rmaghz",
        "\u062e\u0648\u0627\u0644 \u0686\u0647\u0627\u0631\u0645\u063a\u0632"
    ],
    "wof:name":"Khowal-e Chaharmaghz",
    "wof:placetype":"locality"
},
  "geometry": {"coordinates":[67.28354,35.85740999999999],"type":"Point"}
}