{
  "type": "Feature",
  "properties": {
    "gn:admin1_code":"29",
    "gn:admin2_code":"2909.0",
    "gn:asciiname":"Madi Khel",
    "gn:country_code":"AF",
    "gn:dem":1827,
    "gn:feature_class":"P",
    "gn:feature_code":"PPL",
    "gn:name":"M\u0101d\u012b Kh\u0113l",
    "gn:population":0,
    "gn:timezone":"Asia/Kabul",
    "iso:country":"AF",
    "name:rus_x_preferred":[
        "Madikheyl\u2019"
    ],
    "name:und_x_variant":[
        "M\u0101\u1e0fikh\u0113l",
        "M\u0101d\u012bkheyl",
        "M\u0101d\u012b Kh\u0113l",
        "\u0645\u0627\u062f\u06cc \u062e\u06d0\u0644"
    ],
    "wof:name":"Madi Khel",
    "wof:placetype":"locality"
},
  "geometry": {"coordinates":[69.36117,32.86105],"type":"Point"}
}