{
  "type": "Feature",
  "properties": {
    "gn:admin1_code":"32",
    "gn:admin2_code":"1503",
    "gn:asciiname":"Deh-e Ahmad Beg",
    "gn:country_code":"AF",
    "gn:dem":2345,
    "gn:feature_class":"P",
    "gn:feature_code":"PPL",
    "gn:name":"Deh-e A\u1e29mad B\u0113g",
    "gn:population":0,
    "gn:timezone":"Asia/Kabul",
    "iso:country":"AF",
    "name:und_x_variant":[
        "\u1e0eehe A\u1e96ma\u1e0fb\u0113g",
        "Deh-e A\u1e29madbeyg",
        "Deh-e A\u1e29mad B\u0113g",
        "\u062f\u0647 \u0627\u062d\u0645\u062f \u0628\u06d0\u06af"
    ],
    "wof:name":"Deh-e Ahmad Beg",
    "wof:placetype":"locality"
},
  "geometry": {"coordinates":[67.22669,35.53046],"type":"Point"}
}