{
  "type": "Feature",
  "properties": {
    "gn:admin1_code":"32",
    "gn:admin2_code":"1505.0",
    "gn:asciiname":"Aymaq",
    "gn:country_code":"AF",
    "gn:dem":2423,
    "gn:feature_class":"P",
    "gn:feature_code":"PPL",
    "gn:name":"Aym\u0101q",
    "gn:population":0,
    "gn:timezone":"Asia/Kabul",
    "iso:country":"AF",
    "name:und_x_variant":[
        "Aym\u0101q",
        "\u0627\u06cc\u0645\u0627\u0642"
    ],
    "wof:name":"Aymaq",
    "wof:placetype":"locality"
},
  "geometry": {"coordinates":[67.61468000000001,35.5834],"type":"Point"}
}