{
  "type": "Feature",
  "properties": {
    "gn:admin1_code":"31",
    "gn:admin2_code":"1708.0",
    "gn:asciiname":"Timurak Now Warid",
    "gn:country_code":"AF",
    "gn:dem":316,
    "gn:feature_class":"P",
    "gn:feature_code":"PPL",
    "gn:name":"Timurak Now W\u0101rid",
    "gn:population":0,
    "gn:timezone":"Asia/Kabul",
    "iso:country":"AF",
    "name:und_x_variant":[
        "Temorak Nauwarid",
        "Temorak Nav\u0101r\u012bd",
        "Taym\u014drak Now W\u0101rid",
        "\u062a\u06cc\u0645\u0648\u0631\u06a9 \u0646\u0648 \u0648\u0627\u0631\u062f",
        "Timurak Now W\u0101rid",
        "\u062a\u0645\u0631\u06a9 \u0646\u0648 \u0648\u0627\u0631\u062f"
    ],
    "wof:name":"Timurak Now Warid",
    "wof:placetype":"locality"
},
  "geometry": {"coordinates":[66.54037,36.79386],"type":"Point"}
}