{
  "type": "Feature",
  "properties": {
    "gn:admin1_code":"28",
    "gn:admin2_code":"2508.0",
    "gn:asciiname":"Shiglon Ghundey",
    "gn:country_code":"AF",
    "gn:dem":1939,
    "gn:feature_class":"P",
    "gn:feature_code":"PPL",
    "gn:name":"Shigl\u014dn Ghun\u1e0f\u00eay",
    "gn:population":0,
    "gn:timezone":"Asia/Kabul",
    "iso:country":"AF",
    "name:fas_x_preferred":[
        "\u0634\u06af\u0644\u0648\u0646 \u063a\u0648\u0646\u062f\u06cc"
    ],
    "name:und_x_variant":[
        "\u0160eglon Ghundey",
        "Shiglongunday",
        "Shigl\u014dn Ghun\u1e0f\u00eay",
        "\u0634\u06af\u0644\u0648\u0646 \u063a\u0646\u0689\u06cd",
        "Sheglown Gh\u016bn\u1e0fey"
    ],
    "wof:name":"Shiglon Ghundey",
    "wof:placetype":"locality"
},
  "geometry": {"coordinates":[67.47462,31.69034000000001],"type":"Point"}
}