{
  "type": "Feature",
  "properties": {
    "gn:admin1_code":"02",
    "gn:admin2_code":"1904",
    "gn:asciiname":"Shibij",
    "gn:country_code":"AF",
    "gn:dem":2262,
    "gn:feature_class":"P",
    "gn:feature_code":"PPL",
    "gn:name":"Shib\u012bj",
    "gn:population":0,
    "gn:timezone":"Asia/Kabul",
    "iso:country":"AF",
    "name:und_x_variant":[
        "Sh\u012bb\u012bj",
        "S\u0304ibij",
        "Sew\u0113j",
        "Shib\u012bj",
        "\u0634\u0628\u06cc\u062c",
        "S\u016bj",
        "Siwayj",
        "\u0633\u0648\u06cc\u062c"
    ],
    "wof:name":"Shibij",
    "wof:placetype":"locality"
},
  "geometry": {"coordinates":[64.9804,34.98183],"type":"Point"}
}