{
  "type": "Feature",
  "properties": {
    "gn:admin1_code":"27",
    "gn:admin2_code":"406",
    "gn:asciiname":"Shali",
    "gn:country_code":"AF",
    "gn:dem":2528,
    "gn:feature_class":"P",
    "gn:feature_code":"PPL",
    "gn:name":"Sh\u0101l\u012b",
    "gn:population":0,
    "gn:timezone":"Asia/Kabul",
    "iso:country":"AF",
    "name:bel_x_preferred":[
        "\u0428\u0430\u043b\u0456"
    ],
    "name:ceb_x_preferred":[
        "Shali"
    ],
    "name:rus_x_preferred":[
        "\u0428\u0430\u043b\u0438"
    ],
    "name:swe_x_preferred":[
        "Shali"
    ],
    "name:tgl_x_preferred":[
        "Shali"
    ],
    "name:tur_x_preferred":[
        "\u015eali"
    ],
    "name:ukr_x_preferred":[
        "\u0428\u0430\u043b\u0456"
    ],
    "name:und_x_variant":[
        "\u0160\u0101li",
        "Sh\u0101l\u012b",
        "\u0634\u0627\u0644\u06cc"
    ],
    "wof:name":"Shali",
    "wof:placetype":"locality"
},
  "geometry": {"coordinates":[68.40961,34.02853],"type":"Point"}
}