{
  "type": "Feature",
  "properties": {
    "gn:admin1_code":"10",
    "gn:admin2_code":"2307",
    "gn:asciiname":"Shonakay",
    "gn:country_code":"AF",
    "gn:dem":1015,
    "gn:feature_class":"P",
    "gn:feature_code":"PPL",
    "gn:name":"Sh\u014dnakay",
    "gn:population":0,
    "gn:timezone":"Asia/Kabul",
    "iso:country":"AF",
    "name:und_x_variant":[
        "\u0160onakay",
        "Shonakay",
        "Sh\u014dnakay",
        "\u0634\u0648\u0646\u06a9\u06cc",
        "Shownakay"
    ],
    "wof:name":"Shonakay",
    "wof:placetype":"locality"
},
  "geometry": {"coordinates":[64.03783,32.04796],"type":"Point"}
}