{
  "type": "Feature",
  "properties": {
    "gn:admin1_code":"05",
    "gn:admin2_code":"2806",
    "gn:asciiname":"Naspatan",
    "gn:country_code":"AF",
    "gn:dem":2781,
    "gn:feature_class":"P",
    "gn:feature_code":"PPL",
    "gn:name":"Naspat\u0101n",
    "gn:population":0,
    "gn:timezone":"Asia/Kabul",
    "iso:country":"AF",
    "name:und_x_variant":[
        "Naspat\u0101n",
        "\u0646\u0633\u067e\u062a\u0627\u0646"
    ],
    "wof:name":"Naspatan",
    "wof:placetype":"locality"
},
  "geometry": {"coordinates":[67.09699000000001,34.03069],"type":"Point"}
}