{
  "type": "Feature",
  "properties": {
    "gn:admin1_code":"03",
    "gn:admin2_code":"1302.0",
    "gn:asciiname":"Lowkani",
    "gn:country_code":"AF",
    "gn:dem":2133,
    "gn:feature_class":"P",
    "gn:feature_code":"PPL",
    "gn:name":"Lowk\u0101n\u012b",
    "gn:population":0,
    "gn:timezone":"Asia/Kabul",
    "iso:country":"AF",
    "name:und_x_variant":[
        "Lowk\u0101n\u012b",
        "\u0644\u0648\u06a9\u0627\u0646\u06cc"
    ],
    "wof:name":"Lowkani",
    "wof:placetype":"locality"
},
  "geometry": {"coordinates":[69.52736,35.61806],"type":"Point"}
}