{
  "type": "Feature",
  "properties": {
    "gn:admin1_code":"36",
    "gn:admin2_code":"707.0",
    "gn:asciiname":"Dandah",
    "gn:country_code":"AF",
    "gn:dem":1589,
    "gn:feature_class":"P",
    "gn:feature_code":"PPL",
    "gn:name":"\u1e0ean\u1e0fah",
    "gn:population":0,
    "gn:timezone":"Asia/Kabul",
    "iso:country":"AF",
    "name:und_x_variant":[
        "M\u0101lo Kili",
        "\u1e0ean\u1e0fah",
        "Dandah",
        "\u0689\u0646\u0689\u0647",
        "Danda"
    ],
    "wof:name":"Dandah",
    "wof:placetype":"locality"
},
  "geometry": {"coordinates":[69.92731999999999,33.80848],"type":"Point"}
}