{
  "type": "Feature",
  "properties": {
    "gn:admin1_code":"13",
    "gn:admin2_code":"110",
    "gn:asciiname":"Karez-e Akhundan",
    "gn:country_code":"AF",
    "gn:dem":1866,
    "gn:feature_class":"P",
    "gn:feature_code":"PPL",
    "gn:name":"K\u0101r\u0113z-e \u0100kh\u016bnd\u0101n",
    "gn:population":0,
    "gn:timezone":"Asia/Kabul",
    "iso:country":"AF",
    "name:und_x_variant":[
        "Karez-Akhundan",
        "K\u0101r\u012bz \u0100khun\u1e0f\u0101n",
        "K\u0101r\u012bz-e \u0100khund\u0101n",
        "K\u0101\u1e5feze \u0100khun\u1e0f\u0101n",
        "K\u0101rayz-e \u0100kh\u016bnd\u0101n",
        "K\u0101r\u012bz-e \u0100khvond\u0101n",
        "K\u0101r\u0113z-e \u0100kh\u016bnd\u0101n",
        "\u06a9\u0627\u0631\u06d0\u0632 \u0622\u062e\u0648\u0646\u062f\u0627\u0646"
    ],
    "wof:name":"Karez-e Akhundan",
    "wof:placetype":"locality"
},
  "geometry": {"coordinates":[69.29599,34.456],"type":"Point"}
}