{
  "type": "Feature",
  "properties": {
    "gn:admin1_code":"28",
    "gn:admin2_code":"2502.0",
    "gn:asciiname":"Khal Korunah",
    "gn:country_code":"AF",
    "gn:dem":1836,
    "gn:feature_class":"P",
    "gn:feature_code":"PPL",
    "gn:name":"Kh\u0101l K\u014dr\u016bnah",
    "gn:population":0,
    "gn:timezone":"Asia/Kabul",
    "iso:country":"AF",
    "name:fas_x_preferred":[
        "\u062e\u0627\u0646\u0647\u0627\u06cc \u062e\u0627\u0644"
    ],
    "name:und_x_variant":[
        "Kh\u0101l K\u014d\u1e5f\u016bna",
        "Kh\u0101l K\u014dr\u016bnah",
        "\u062e\u0627\u0644 \u06a9\u0648\u0631\u0648\u0646\u0647",
        "Kh\u0101l Kowr\u016bnah"
    ],
    "wof:name":"Khal Korunah",
    "wof:placetype":"locality"
},
  "geometry": {"coordinates":[67.33711,32.35041],"type":"Point"}
}