{
  "type": "Feature",
  "properties": {
    "gn:admin1_code":"01",
    "gn:admin2_code":"1112.0",
    "gn:asciiname":"Pakman",
    "gn:country_code":"AF",
    "gn:dem":1840,
    "gn:feature_class":"P",
    "gn:feature_code":"PPL",
    "gn:name":"P\u0101km\u0101n",
    "gn:population":0,
    "gn:timezone":"Asia/Kabul",
    "iso:country":"AF",
    "name:und_x_variant":[
        "P\u0101km\u0101n",
        "\u067e\u0627\u06a9\u0645\u0627\u0646"
    ],
    "wof:name":"Pakman",
    "wof:placetype":"locality"
},
  "geometry": {"coordinates":[70.42353,37.60546],"type":"Point"}
}