{
  "type": "Feature",
  "properties": {
    "gn:admin1_code":"30",
    "gn:admin2_code":"1604.0",
    "gn:asciiname":"Tashguzar",
    "gn:country_code":"AF",
    "gn:dem":292,
    "gn:feature_class":"P",
    "gn:feature_code":"PPL",
    "gn:name":"Tashguzar",
    "gn:population":0,
    "gn:timezone":"Asia/Kabul",
    "iso:country":"AF",
    "name:und_x_variant":[
        "Tash Goz\u0304ar",
        "\u062a\u0627\u0634 \u06af\u0630\u0631",
        "Tash Guz\u0304ar"
    ],
    "wof:name":"Tashguzar",
    "wof:placetype":"locality"
},
  "geometry": {"coordinates":[67.22083000000001,37.19611],"type":"Point"}
}