{
  "type": "Feature",
  "properties": {
    "gn:admin1_code":"09",
    "gn:admin2_code":"2706",
    "gn:asciiname":"Sokhtah",
    "gn:country_code":"AF",
    "gn:dem":2526,
    "gn:feature_class":"P",
    "gn:feature_code":"PPL",
    "gn:name":"S\u014dkhtah",
    "gn:population":0,
    "gn:timezone":"Asia/Kabul",
    "iso:country":"AF",
    "name:und_x_variant":[
        "S\u014dkhta",
        "Sokhta",
        "S\u014dkhtah",
        "\u0633\u0648\u062e\u062a\u0647",
        "S\u016bkhteh"
    ],
    "wof:name":"Sokhtah",
    "wof:placetype":"locality"
},
  "geometry": {"coordinates":[64.91914,33.49598],"type":"Point"}
}