{
  "type": "Feature",
  "properties": {
    "gn:admin1_code":"26",
    "gn:admin2_code":"1206.0",
    "gn:asciiname":"Atah",
    "gn:country_code":"AF",
    "gn:dem":1495,
    "gn:feature_class":"P",
    "gn:feature_code":"PPL",
    "gn:name":"\u0100tah",
    "gn:population":0,
    "gn:timezone":"Asia/Kabul",
    "iso:country":"AF",
    "name:und_x_variant":[
        "\u0100tah",
        "\u0622\u062a\u0647",
        "\u2018A\u0163\u0101"
    ],
    "wof:name":"Atah",
    "wof:placetype":"locality"
},
  "geometry": {"coordinates":[69.90325,36.44694000000001],"type":"Point"}
}