{
  "type": "Feature",
  "properties": {
    "gn:admin1_code":"39",
    "gn:admin2_code":"2601",
    "gn:asciiname":"Shah Mansur",
    "gn:country_code":"AF",
    "gn:dem":1344,
    "gn:feature_class":"P",
    "gn:feature_code":"PPL",
    "gn:name":"Sh\u0101h Man\u015f\u016br",
    "gn:population":0,
    "gn:timezone":"Asia/Kabul",
    "iso:country":"AF",
    "name:fas_x_preferred":[
        "\u0634\u0627\u0647 \u0645\u0646\u0635\u0648\u0631"
    ],
    "name:und_x_variant":[
        "\u0160\u0101hman\u015f\u016br",
        "Shakhmansur",
        "Sh\u0101h Man\u015f\u016br",
        "\u0633\u0627\u0647 \u0645\u0646\u0635\u0648\u0631"
    ],
    "wof:name":"Shah Mansur",
    "wof:placetype":"locality"
},
  "geometry": {"coordinates":[65.90335,32.65563],"type":"Point"}
}