{
  "type": "Feature",
  "properties": {
    "gn:admin1_code":"26",
    "gn:admin2_code":"1209.0",
    "gn:asciiname":"Warna Khan Chashmah",
    "gn:country_code":"AF",
    "gn:dem":1468,
    "gn:feature_class":"P",
    "gn:feature_code":"PPL",
    "gn:name":"Warn\u0101 Kh\u0101n Chashmah",
    "gn:population":0,
    "gn:timezone":"Asia/Kabul",
    "iso:country":"AF",
    "name:und_x_variant":[
        "Wa\u1e5fn\u0101 Kh\u0101n Casma",
        "Warn\u0101 Kh\u0101n Cheshmeh",
        "Warn\u0101 Kh\u0101n Chashmah",
        "\u0648\u0631\u0646\u0627 \u062e\u0627\u0646 \u0686\u0634\u0645\u0647"
    ],
    "wof:name":"Warna Khan Chashmah",
    "wof:placetype":"locality"
},
  "geometry": {"coordinates":[69.88258,37.36594],"type":"Point"}
}