{
  "type": "Feature",
  "properties": {
    "gn:admin1_code":"40",
    "gn:admin2_code":"302.0",
    "gn:asciiname":"Anarak",
    "gn:country_code":"AF",
    "gn:dem":1786,
    "gn:feature_class":"P",
    "gn:feature_code":"PPL",
    "gn:name":"An\u0101rak",
    "gn:population":0,
    "gn:timezone":"Asia/Kabul",
    "iso:country":"AF",
    "name:fas_x_preferred":[
        "\u0627\u0646\u0627\u0631\u0643"
    ],
    "name:und_x_variant":[
        "An\u0101rak",
        "\u0627\u0646\u0627\u0631\u06a9"
    ],
    "wof:name":"Anarak",
    "wof:placetype":"locality"
},
  "geometry": {"coordinates":[69.17764,35.11153],"type":"Point"}
}