{
  "type": "Feature",
  "properties": {
    "gn:admin1_code":"17",
    "gn:admin2_code":"505.0",
    "gn:asciiname":"Qal'ah-ye Dalil",
    "gn:country_code":"AF",
    "gn:dem":1857,
    "gn:feature_class":"P",
    "gn:feature_code":"PPL",
    "gn:name":"Qal\u2018ah-ye Dal\u012bl",
    "gn:population":0,
    "gn:timezone":"Asia/Kabul",
    "iso:country":"AF",
    "name:rus_x_preferred":[
        "Kaladalil\u2019"
    ],
    "name:und_x_variant":[
        "Qal\u2018eh \u1e0eal\u012bl",
        "Qal\u2018eh-ye Dal\u012bl",
        "Qal\u2018ah-ye Dal\u012bl",
        "\u0642\u0644\u0639\u0647 \u062f\u0644\u06cc\u0644"
    ],
    "wof:name":"Qal'ah-ye Dalil",
    "wof:placetype":"locality"
},
  "geometry": {"coordinates":[69.12690000000001,34.2912],"type":"Point"}
}