{
  "type": "Feature",
  "properties": {
    "gn:admin1_code":"14",
    "gn:admin2_code":"205.0",
    "gn:asciiname":"Adin Khel",
    "gn:country_code":"AF",
    "gn:dem":1366,
    "gn:feature_class":"P",
    "gn:feature_code":"PPL",
    "gn:name":"Ad\u012bn Kh\u0113l",
    "gn:population":0,
    "gn:timezone":"Asia/Kabul",
    "iso:country":"AF",
    "name:fas_x_preferred":[
        "\u0627\u062f\u064a\u0646 \u062e\u064a\u0644"
    ],
    "name:rus_x_preferred":[
        "Adinkheyl\u2019"
    ],
    "name:und_x_variant":[
        "A\u1e0f\u012bn Kh\u0113l",
        "Ad\u012bnkheyl",
        "Ad\u012bn Kh\u0113l",
        "\u0627\u062f\u06cc\u0646 \u062e\u06d0\u0644"
    ],
    "wof:name":"Adin Khel",
    "wof:placetype":"locality"
},
  "geometry": {"coordinates":[69.63462,34.89676],"type":"Point"}
}