{
  "type": "Feature",
  "properties": {
    "gn:admin1_code":"06",
    "gn:admin2_code":"2111",
    "gn:asciiname":"Qaryah-ye Kababi-ye Bala",
    "gn:country_code":"AF",
    "gn:dem":663,
    "gn:feature_class":"P",
    "gn:feature_code":"PPL",
    "gn:name":"Qaryah-ye Kab\u0101b\u012b-ye B\u0101l\u0101",
    "gn:population":0,
    "gn:timezone":"Asia/Kabul",
    "iso:country":"AF",
    "name:rus_x_preferred":[
        "Kar\u2019yani-Kababi-Bala"
    ],
    "name:und_x_variant":[
        "Qaryeh-ye Kab\u0101b\u012b B\u0101l\u0101",
        "Qaryeh-ye Kab\u0101b\u012b",
        "Qa\u1e5fya-i-Kab\u0101b\u012b B\u0101l\u0101",
        "Qaryeh-ye Kab\u0101b\u012b-ye B\u0101l\u0101",
        "Qaryah-ye Kab\u0101b\u012b-ye B\u0101l\u0101",
        "\u0642\u0631\u06cc\u0647 \u06a9\u0628\u0627\u0628\u06cc \u0628\u0627\u0644\u0627"
    ],
    "wof:name":"Qaryah-ye Kababi-ye Bala",
    "wof:placetype":"locality"
},
  "geometry": {"coordinates":[62.04529,32.44891],"type":"Point"}
}