{
  "type": "Feature",
  "properties": {
    "gn:admin1_code":"23",
    "gn:admin2_code":"2413",
    "gn:asciiname":"Newi Karez",
    "gn:country_code":"AF",
    "gn:dem":2173,
    "gn:feature_class":"P",
    "gn:feature_code":"PPL",
    "gn:name":"N\u00eaw\u012b K\u0101r\u0113z",
    "gn:population":0,
    "gn:timezone":"Asia/Kabul",
    "iso:country":"AF",
    "name:und_x_variant":[
        "Navay-Karez",
        "Naway K\u0101\u1e5f\u0113z",
        "Nevay K\u0101r\u012bz",
        "N\u00eaw\u012b K\u0101r\u0113z",
        "\u0646\u0648\u06cc \u06a9\u0627\u0631\u06d0\u0632"
    ],
    "wof:name":"Newi Karez",
    "wof:placetype":"locality"
},
  "geometry": {"coordinates":[67.63476999999999,31.28718],"type":"Point"}
}