{
  "type": "Feature",
  "properties": {
    "gn:admin1_code":"08",
    "gn:admin2_code":"613",
    "gn:asciiname":"Zareh Kala",
    "gn:country_code":"AF",
    "gn:dem":2180,
    "gn:feature_class":"P",
    "gn:feature_code":"PPL",
    "gn:name":"Z\u0101\u1e5f\u00eah Kal\u0101",
    "gn:population":0,
    "gn:timezone":"Asia/Kabul",
    "iso:country":"AF",
    "name:fas_x_preferred":[
        "\u0632\u0627\u0631\u0647 \u0643\u0644\u0627"
    ],
    "name:rus_x_preferred":[
        "\u0417\u0430\u0440\u0430-\u041a\u0430\u043b\u0430"
    ],
    "name:und_x_variant":[
        "Zara-Kala",
        "Z\u0101\u1e5fa Kal\u0101",
        "Z\u0101rah Kal\u0101",
        "Z\u0101\u1e5f\u00eah Kal\u0101",
        "\u0632\u0627\u0693\u0647 \u06a9\u0644\u0627"
    ],
    "wof:name":"Zareh Kala",
    "wof:placetype":"locality"
},
  "geometry": {"coordinates":[67.97936,33.12721],"type":"Point"}
}