{
  "type": "Feature",
  "properties": {
    "gn:admin1_code":"27",
    "gn:admin2_code":"404",
    "gn:asciiname":"Now Qal'ah",
    "gn:country_code":"AF",
    "gn:dem":3193,
    "gn:feature_class":"P",
    "gn:feature_code":"PPL",
    "gn:name":"Now Qal\u2018ah",
    "gn:population":0,
    "gn:timezone":"Asia/Kabul",
    "iso:country":"AF",
    "name:und_x_variant":[
        "Naukala",
        "Nawqal\u2018a",
        "N\u0101w Qal\u2018ah",
        "Nowqal\u2018eh",
        "Now Qal\u2018ah",
        "\u0646\u0648 \u0642\u0644\u0639\u0647"
    ],
    "wof:name":"Now Qal'ah",
    "wof:placetype":"locality"
},
  "geometry": {"coordinates":[67.59222,34.48683],"type":"Point"}
}