{
  "type": "Feature",
  "properties": {
    "gn:admin1_code":"8",
    "gn:admin2_code":"614.0",
    "gn:asciiname":"Sher Kala",
    "gn:country_code":"AF",
    "gn:dem":2095,
    "gn:feature_class":"P",
    "gn:feature_code":"PPL",
    "gn:name":"Sh\u0113r Kal\u0101",
    "gn:population":0,
    "gn:timezone":"Asia/Kabul",
    "iso:country":"AF",
    "name:fas_x_preferred":[
        "\u0642\u0644\u0639\u0647\u0654 \u0634\u064a\u0631"
    ],
    "name:und_x_variant":[
        "\u0160\u0113r Kal\u0101",
        "Sherkala",
        "Sh\u0113r Kal\u0101",
        "Sh\u012br Kal\u0101",
        "\u0634\u064a\u0631 \u06a9\u0644\u0627"
    ],
    "wof:name":"Sher Kala",
    "wof:placetype":"locality"
},
  "geometry": {"coordinates":[68.45106,33.3809],"type":"Point"}
}