{
  "type": "Feature",
  "properties": {
    "gn:admin1_code":"23",
    "gn:admin2_code":"2413",
    "gn:asciiname":"Khalu",
    "gn:country_code":"AF",
    "gn:dem":1968,
    "gn:feature_class":"P",
    "gn:feature_code":"PPL",
    "gn:name":"Khal\u016b",
    "gn:population":0,
    "gn:timezone":"Asia/Kabul",
    "iso:country":"AF",
    "name:und_x_variant":[
        "Khal\u016b",
        "Khalu",
        "\u062e\u0644\u0648"
    ],
    "wof:name":"Khalu",
    "wof:placetype":"locality"
},
  "geometry": {"coordinates":[67.30833,31.45222],"type":"Point"}
}