{
  "type": "Feature",
  "properties": {
    "iso:country":"AF",
    "name:ast_x_preferred":[
        "Nahrin"
    ],
    "name:ast_x_variant":[
        "Nahr\u00edn"
    ],
    "name:ceb_x_preferred":[
        "Nahr\u012bn"
    ],
    "name:eng_x_preferred":[
        "Nahrin"
    ],
    "name:fas_x_preferred":[
        "\u0646\u0647\u0631\u06cc\u0646"
    ],
    "name:nld_x_preferred":[
        "Nahrin"
    ],
    "name:rus_x_preferred":[
        "\u041d\u0430\u0445\u0440\u0438\u043d"
    ],
    "name:spa_x_preferred":[
        "Nahr\u012bn"
    ],
    "name:swe_x_preferred":[
        "Nahr\u012bn"
    ],
    "name:unk_x_variant":[
        "Nar\u012bn"
    ],
    "qs:gn_country":"AF",
    "qs:gn_fcode":"PPLA2",
    "qs:gn_pop":22363,
    "qs:name":"Nahr\u012bn",
    "qs:name_adm0":"Afghanistan",
    "qs:name_adm1":"Baghlan",
    "qs:photos":0,
    "qs:photos_1k":0,
    "qs:photos_9k":0,
    "qs:photos_9r":0,
    "qs:photos_all":0,
    "qs:photos_sr":0,
    "qs:placetype":"Town",
    "qs:pop_sr":"7",
    "qs:woe_adm0":23424739,
    "wd:wordcount":35,
    "wof:name":"Nahr\u012bn",
    "wof:placetype":"locality",
    "wof:population":22363
},
  "geometry": {"coordinates":[69.13343,36.0649],"type":"Point"}
}