{
  "type": "Feature",
  "properties": {
    "gn:admin1_code":"23",
    "gn:admin2_code":"2412.0",
    "gn:asciiname":"Putak",
    "gn:country_code":"AF",
    "gn:dem":1539,
    "gn:feature_class":"P",
    "gn:feature_code":"PPL",
    "gn:name":"Pu\u1e6fak",
    "gn:population":0,
    "gn:timezone":"Asia/Kabul",
    "iso:country":"AF",
    "name:und_x_variant":[
        "Pu\u1e6fak",
        "Potak",
        "\u067e\u062a\u06a9",
        "\u067e\u067c\u06a9"
    ],
    "wof:name":"Putak",
    "wof:placetype":"locality"
},
  "geometry": {"coordinates":[66.88356999999999,31.48368],"type":"Point"}
}