{
  "type": "Feature",
  "properties": {
    "gn:admin1_code":"11",
    "gn:admin2_code":"2005",
    "gn:asciiname":"Deh Moghul",
    "gn:country_code":"AF",
    "gn:dem":1280,
    "gn:feature_class":"P",
    "gn:feature_code":"PPL",
    "gn:name":"Deh Moghul",
    "gn:population":0,
    "gn:timezone":"Asia/Kabul",
    "iso:country":"AF",
    "name:rus_x_preferred":[
        "Dekhmugul\u2019"
    ],
    "name:und_x_variant":[
        "Deh Mogh\u016bl",
        "\u1e0eeh Mughul",
        "Deh Moghul",
        "\u062f\u0647 \u0645\u063a\u0644",
        "Deh Moghol"
    ],
    "wof:name":"Deh Moghul",
    "wof:placetype":"locality"
},
  "geometry": {"coordinates":[62.37727,34.48967],"type":"Point"}
}