{
  "type": "Feature",
  "properties": {
    "gn:admin1_code":"01",
    "gn:admin2_code":"1102.0",
    "gn:asciiname":"Nowchi",
    "gn:country_code":"AF",
    "gn:dem":1096,
    "gn:feature_class":"P",
    "gn:feature_code":"PPL",
    "gn:name":"Nowch\u012b",
    "gn:population":0,
    "gn:timezone":"Asia/Kabul",
    "iso:country":"AF",
    "name:und_x_variant":[
        "Naw\u010di",
        "Nawch\u012b",
        "Nowch\u012b",
        "\u0646\u0648\u0686\u06cc"
    ],
    "wof:name":"Nowchi",
    "wof:placetype":"locality"
},
  "geometry": {"coordinates":[70.13023000000001,36.90806],"type":"Point"}
}