{
  "type": "Feature",
  "properties": {
    "gn:admin1_code":"40",
    "gn:admin2_code":"301.0",
    "gn:asciiname":"Sarkah Chah",
    "gn:country_code":"AF",
    "gn:dem":2161,
    "gn:feature_class":"P",
    "gn:feature_code":"PPL",
    "gn:name":"Sarkah Ch\u0101h",
    "gn:population":0,
    "gn:timezone":"Asia/Kabul",
    "iso:country":"AF",
    "name:fas_x_preferred":[
        "\u0633\u0631\u0643\u0647 \u0686\u0627\u0647"
    ],
    "name:und_x_variant":[
        "Sarkachakh",
        "Sarka\u010d\u0101h",
        "Sar Kahchah",
        "Sarkach\u0101h",
        "Sarkah Ch\u0101h",
        "\u0633\u0631\u06a9\u0647 \u0686\u0627\u0647"
    ],
    "wof:name":"Sarkah Chah",
    "wof:placetype":"locality"
},
  "geometry": {"coordinates":[69.10945,34.9962],"type":"Point"}
}