{
  "type": "Feature",
  "properties": {
    "gn:admin1_code":"34",
    "gn:admin2_code":"1004.0",
    "gn:asciiname":"Dangam",
    "gn:country_code":"AF",
    "gn:dem":1250,
    "gn:feature_class":"P",
    "gn:feature_code":"PPLA2",
    "gn:name":"D\u0101ng\u0101m",
    "gn:population":0,
    "gn:timezone":"Asia/Kabul",
    "iso:country":"AF",
    "name:fas_x_preferred":[
        "\u062f\u0627\u0646\u06af\u0627\u0645"
    ],
    "name:und_x_variant":[
        "D\u0101ng\u0101m",
        "\u1e0e\u0101ng\u0101m",
        "\u0689\u0627\u0646\u06af\u0627\u0645"
    ],
    "wof:name":"Dangam",
    "wof:placetype":"locality"
},
  "geometry": {"coordinates":[71.41934999999999,34.99249],"type":"Point"}
}