{
  "type": "Feature",
  "properties": {
    "gn:admin1_code":"09",
    "gn:admin2_code":"2705",
    "gn:asciiname":"Miskarha",
    "gn:country_code":"AF",
    "gn:dem":2160,
    "gn:feature_class":"P",
    "gn:feature_code":"PPL",
    "gn:name":"Miskarh\u0101",
    "gn:population":0,
    "gn:timezone":"Asia/Kabul",
    "iso:country":"AF",
    "name:und_x_variant":[
        "Miskarkha",
        "Miskarh\u0101",
        "\u0645\u0633\u06a9\u0631\u0647\u0627",
        "Meskarh\u0101"
    ],
    "wof:name":"Miskarha",
    "wof:placetype":"locality"
},
  "geometry": {"coordinates":[64.42484,33.52823],"type":"Point"}
}