{
  "type": "Feature",
  "properties": {
    "gn:admin1_code":"11",
    "gn:admin2_code":"2014",
    "gn:asciiname":"Masian",
    "gn:country_code":"AF",
    "gn:dem":1002,
    "gn:feature_class":"P",
    "gn:feature_code":"PPL",
    "gn:name":"M\u0101s\u012b\u0101n",
    "gn:population":0,
    "gn:timezone":"Asia/Kabul",
    "iso:country":"AF",
    "name:fas_x_preferred":[
        "\u0645\u0627\u0633\u06cc\u0627\u0646"
    ],
    "name:rus_x_preferred":[
        "Mas\u2019yan"
    ],
    "name:und_x_variant":[
        "\u0645\u0627\u0633\u06cc\u0627\u0646",
        "M\u0101sy\u0101n",
        "M\u0101s\u012b\u0101n"
    ],
    "wof:name":"Masian",
    "wof:placetype":"locality"
},
  "geometry": {"coordinates":[62.16566,33.14872],"type":"Point"}
}