{
  "type": "Feature",
  "properties": {
    "gn:admin1_code":"23",
    "gn:admin2_code":"2412",
    "gn:asciiname":"Mardan Khel",
    "gn:country_code":"AF",
    "gn:dem":1571,
    "gn:feature_class":"P",
    "gn:feature_code":"PPL",
    "gn:name":"Mard\u0101n Kh\u0113l",
    "gn:population":0,
    "gn:timezone":"Asia/Kabul",
    "iso:country":"AF",
    "name:und_x_variant":[
        "Mardankheyl\u2019",
        "Ma\u1e5f\u1e0f\u0101nkh\u0113l",
        "Mard\u0101n Kh\u0113l",
        "\u0645\u0631\u062f\u0627\u0646 \u062e\u06d0\u0644",
        "Mard\u0101n Kheyl"
    ],
    "wof:name":"Mardan Khel",
    "wof:placetype":"locality"
},
  "geometry": {"coordinates":[66.88160999999999,31.6623],"type":"Point"}
}