{
  "type": "Feature",
  "properties": {
    "gn:admin1_code":"3",
    "gn:admin2_code":"1309.0",
    "gn:asciiname":"Dasht-e Qazi",
    "gn:country_code":"AF",
    "gn:dem":1057,
    "gn:feature_class":"P",
    "gn:feature_code":"PPL",
    "gn:name":"Dasht-e Q\u0101\u1e95\u012b",
    "gn:population":0,
    "gn:timezone":"Asia/Kabul",
    "iso:country":"AF",
    "name:ceb_x_preferred":[
        "Dasht-e Q\u0101\u1e95\u012b"
    ],
    "name:fas_x_preferred":[
        "\u062f\u0634\u062a \u0642\u0627\u0636\u06cc"
    ],
    "name:swe_x_preferred":[
        "Dasht-e Q\u0101\u1e95\u012b"
    ],
    "name:und_x_variant":[
        "Dast Q\u0101\u1e0fzi",
        "Dasht-e Q\u0101\u1e95\u012b",
        "\u062f\u0634\u062a \u0642\u0627\u0636\u06cc"
    ],
    "wof:name":"Dasht-e Qazi",
    "wof:placetype":"locality"
},
  "geometry": {"coordinates":[69.09217,36.06355],"type":"Point"}
}