{
  "type": "Feature",
  "properties": {
    "gn:admin1_code":"27",
    "gn:admin2_code":"404",
    "gn:asciiname":"Surkhak",
    "gn:country_code":"AF",
    "gn:dem":3200,
    "gn:feature_class":"P",
    "gn:feature_code":"PPL",
    "gn:name":"Surkhak",
    "gn:population":0,
    "gn:timezone":"Asia/Kabul",
    "iso:country":"AF",
    "name:rus_x_preferred":[
        "\u0421\u0443\u0440\u043a\u0430\u043a"
    ],
    "name:und_x_variant":[
        "Surkak",
        "Su\u1e5fkhak",
        "Surkhak",
        "Sorkhak",
        "\u0633\u0631\u062e\u06a9"
    ],
    "wof:name":"Surkhak",
    "wof:placetype":"locality"
},
  "geometry": {"coordinates":[67.48501999999999,34.59729],"type":"Point"}
}