{
  "type": "Feature",
  "properties": {
    "gn:admin1_code":"07",
    "gn:admin2_code":"1804",
    "gn:asciiname":"Telak",
    "gn:country_code":"AF",
    "gn:dem":1168,
    "gn:feature_class":"P",
    "gn:feature_code":"PPL",
    "gn:name":"T\u0113lak",
    "gn:population":0,
    "gn:timezone":"Asia/Kabul",
    "iso:country":"AF",
    "name:und_x_variant":[
        "T\u0113lak",
        "T\u012blak",
        "\u062a\u06d0\u0644\u06a9"
    ],
    "wof:name":"Telak",
    "wof:placetype":"locality"
},
  "geometry": {"coordinates":[64.08914,35.60227000000001],"type":"Point"}
}