{
  "type": "Feature",
  "properties": {
    "gn:admin1_code":"8",
    "gn:admin2_code":"609.0",
    "gn:asciiname":"Awparan",
    "gn:country_code":"AF",
    "gn:dem":2422,
    "gn:feature_class":"P",
    "gn:feature_code":"PPL",
    "gn:name":"\u0100wpar\u0101n",
    "gn:population":0,
    "gn:timezone":"Asia/Kabul",
    "iso:country":"AF",
    "name:und_x_variant":[
        "Auparan",
        "\u0100wpar\u0101n",
        "\u0622\u0648\u067e\u0631\u0627\u0646",
        "Awpar\u0101n"
    ],
    "wof:name":"Awparan",
    "wof:placetype":"locality"
},
  "geometry": {"coordinates":[67.44763,32.82741],"type":"Point"}
}