{
  "type": "Feature",
  "properties": {
    "gn:admin1_code":"02",
    "gn:admin2_code":"1903",
    "gn:asciiname":"Jowaliq",
    "gn:country_code":"AF",
    "gn:dem":1679,
    "gn:feature_class":"P",
    "gn:feature_code":"PPL",
    "gn:name":"Jow\u0101liq",
    "gn:population":0,
    "gn:timezone":"Asia/Kabul",
    "iso:country":"AF",
    "name:und_x_variant":[
        "Dzhavalek",
        "Jow\u0101liq",
        "\u062c\u0648\u0627\u0644\u0642",
        "Jaw\u0101leq"
    ],
    "wof:name":"Jowaliq",
    "wof:placetype":"locality"
},
  "geometry": {"coordinates":[63.36771,34.70536],"type":"Point"}
}