{
  "type": "Feature",
  "properties": {
    "gn:admin1_code":"24",
    "gn:admin2_code":"1403.0",
    "gn:asciiname":"Baghichah",
    "gn:country_code":"AF",
    "gn:dem":313,
    "gn:feature_class":"P",
    "gn:feature_code":"PPL",
    "gn:name":"B\u0101gh\u012bchah",
    "gn:population":0,
    "gn:timezone":"Asia/Kabul",
    "iso:country":"AF",
    "name:und_x_variant":[
        "B\u0101gh\u012bca",
        "Bagh-e Cheh",
        "B\u0101gh\u012bchah",
        "\u0628\u0627\u063a\u06cc\u0686\u0647"
    ],
    "wof:name":"Baghichah",
    "wof:placetype":"locality"
},
  "geometry": {"coordinates":[68.13554000000001,36.95083],"type":"Point"}
}