{
  "type": "Feature",
  "properties": {
    "gn:admin1_code":"08",
    "gn:admin2_code":"604",
    "gn:asciiname":"Dewalak",
    "gn:country_code":"AF",
    "gn:dem":3445,
    "gn:feature_class":"P",
    "gn:feature_code":"PPL",
    "gn:name":"D\u0113w\u0101lak",
    "gn:population":0,
    "gn:timezone":"Asia/Kabul",
    "iso:country":"AF",
    "name:und_x_variant":[
        "\u1e0e\u0113wlak",
        "Devlak",
        "D\u012bvlak",
        "Dayw\u0101lak",
        "\u062f\u06cc\u0648\u0627\u0644\u06a9",
        "D\u0113w\u0101lak"
    ],
    "wof:name":"Dewalak",
    "wof:placetype":"locality"
},
  "geometry": {"coordinates":[67.64503000000001,34.19286],"type":"Point"}
}