{
  "type": "Feature",
  "properties": {
    "gn:admin1_code":"9",
    "gn:admin2_code":"2707.0",
    "gn:asciiname":"Chahar Qash",
    "gn:country_code":"AF",
    "gn:dem":3316,
    "gn:feature_class":"P",
    "gn:feature_code":"PPL",
    "gn:name":"Chah\u0101r Q\u0101sh",
    "gn:population":0,
    "gn:timezone":"Asia/Kabul",
    "iso:country":"AF",
    "name:und_x_variant":[
        "\u010cah\u0101rq\u0101\u0161",
        "Chakharkash",
        "Chah\u0101r Q\u0101sh",
        "Chah\u0101rq\u0101sh",
        "\u0686\u0647\u0627\u0631 \u0642\u0627\u0634"
    ],
    "wof:name":"Chahar Qash",
    "wof:placetype":"locality"
},
  "geometry": {"coordinates":[66.26764,34.42232],"type":"Point"}
}