{
  "type": "Feature",
  "properties": {
    "gn:admin1_code":"01",
    "gn:admin2_code":"1127",
    "gn:asciiname":"Sar Sabil",
    "gn:country_code":"AF",
    "gn:dem":1926,
    "gn:feature_class":"P",
    "gn:feature_code":"PPL",
    "gn:name":"Sar Sab\u012bl",
    "gn:population":0,
    "gn:timezone":"Asia/Kabul",
    "iso:country":"AF",
    "name:und_x_variant":[
        "Sa\u1e5fsab\u012bl",
        "Sar Sab\u012bl",
        "\u0633\u0631 \u0633\u0628\u064a\u0644"
    ],
    "wof:name":"Sar Sabil",
    "wof:placetype":"locality"
},
  "geometry": {"coordinates":[70.77369,36.48835],"type":"Point"}
}