{
  "type": "Feature",
  "properties": {
    "gn:admin1_code":"9",
    "gn:admin2_code":"2706.0",
    "gn:asciiname":"Dahan-e Kakari",
    "gn:country_code":"AF",
    "gn:dem":2447,
    "gn:feature_class":"P",
    "gn:feature_code":"PPL",
    "gn:name":"Dah\u0101n-e K\u0101kar\u012b",
    "gn:population":0,
    "gn:timezone":"Asia/Kabul",
    "iso:country":"AF",
    "name:und_x_variant":[
        "Dakhani-Kakari",
        "Dah\u0101n-e K\u0101kar\u012b",
        "\u062f\u0647\u0627\u0646 \u06a9\u0627\u06a9\u0631\u06cc",
        "Dahan-e K\u0101kar\u012b"
    ],
    "wof:name":"Dahan-e Kakari",
    "wof:placetype":"locality"
},
  "geometry": {"coordinates":[64.77977,33.61612],"type":"Point"}
}