{
  "type": "Feature",
  "properties": {
    "gn:admin1_code":"23",
    "gn:admin2_code":"2411.0",
    "gn:asciiname":"Dadozai",
    "gn:country_code":"AF",
    "gn:dem":1314,
    "gn:feature_class":"P",
    "gn:feature_code":"PPL",
    "gn:name":"D\u0101d\u014dza\u012b",
    "gn:population":0,
    "gn:timezone":"Asia/Kabul",
    "iso:country":"AF",
    "name:und_x_variant":[
        "\u1e0e\u0101\u1e0f\u014dzay",
        "D\u0101d\u014dza\u012b",
        "D\u0101dowzay",
        "\u062f\u0627\u062f\u0648\u0632\u06cc"
    ],
    "wof:name":"Dadozai",
    "wof:placetype":"locality"
},
  "geometry": {"coordinates":[66.51359000000001,31.08628],"type":"Point"}
}