{
  "type": "Feature",
  "properties": {
    "gn:admin1_code":"01",
    "gn:admin2_code":"1120.0",
    "gn:asciiname":"Labgard",
    "gn:country_code":"AF",
    "gn:dem":1277,
    "gn:feature_class":"P",
    "gn:feature_code":"PPL",
    "gn:name":"Labgard",
    "gn:population":0,
    "gn:timezone":"Asia/Kabul",
    "iso:country":"AF",
    "name:und_x_variant":[
        "\u0644\u0628\u06af\u0631\u062f"
    ],
    "wof:name":"Labgard",
    "wof:placetype":"locality"
},
  "geometry": {"coordinates":[70.34708000000001,38.0087],"type":"Point"}
}