{
  "type": "Feature",
  "properties": {
    "gn:admin1_code":"11",
    "gn:admin2_code":"2003",
    "gn:asciiname":"Murghow",
    "gn:country_code":"AF",
    "gn:dem":951,
    "gn:feature_class":"P",
    "gn:feature_code":"PPL",
    "gn:name":"Murghow",
    "gn:population":0,
    "gn:timezone":"Asia/Kabul",
    "iso:country":"AF",
    "name:fas_x_preferred":[
        "\u0645\u0631\u063a\u0627\u0628"
    ],
    "name:und_x_variant":[
        "Murgau",
        "Mu\u1e5fghaw",
        "Murghow",
        "\u0645\u0631\u063a\u0648",
        "Morgh\u0101b"
    ],
    "wof:name":"Murghow",
    "wof:placetype":"locality"
},
  "geometry": {"coordinates":[62.1799,34.22922],"type":"Point"}
}