{
  "type": "Feature",
  "properties": {
    "gn:admin1_code":"27",
    "gn:admin2_code":"409",
    "gn:asciiname":"Khwajagan",
    "gn:country_code":"AF",
    "gn:dem":2538,
    "gn:feature_class":"P",
    "gn:feature_code":"PPL",
    "gn:name":"Khw\u0101jag\u0101n",
    "gn:population":0,
    "gn:timezone":"Asia/Kabul",
    "iso:country":"AF",
    "name:fas_x_preferred":[
        "\u062e\u0648\u0627\u062c\u06af\u0627\u0646"
    ],
    "name:und_x_variant":[
        "Khw\u0101jag\u0101n",
        "Khodzhagan",
        "Khw\u0101jahg\u0101n",
        "Khv\u0101jeg\u0101n",
        "\u062e\u0648\u0627\u062c\u06af\u0627\u0646"
    ],
    "wof:name":"Khwajagan",
    "wof:placetype":"locality"
},
  "geometry": {"coordinates":[68.30698000000001,33.7923],"type":"Point"}
}