{
  "type": "Feature",
  "properties": {
    "gn:admin1_code":"18",
    "gn:asciiname":"Torkham",
    "gn:country_code":"AF",
    "gn:dem":1133,
    "gn:feature_class":"P",
    "gn:feature_code":"PPL",
    "gn:name":"Torkham",
    "gn:population":0,
    "gn:timezone":"Asia/Kabul",
    "iso:country":"AF",
    "wof:name":"Torkham",
    "wof:placetype":"locality"
},
  "geometry": {"coordinates":[71.08471999999998,34.11472],"type":"Point"}
}