{
  "type": "Feature",
  "properties": {
    "gn:admin1_code":"18",
    "gn:asciiname":"Torkham",
    "gn:country_code":"AF",
    "gn:dem":1133,
    "gn:feature_class":"P",
    "gn:feature_code":"PPL",
    "gn:name":"Torkham",
    "gn:population":0,
    "gn:timezone":"Asia/Kabul",
    "iso:country":"AF",
    "name:deu_x_preferred":[
        "Torcham"
    ],
    "name:fas_x_preferred":[
        "\u062a\u0648\u0631\u062e\u0645"
    ],
    "name:fra_x_preferred":[
        "Torkham"
    ],
    "name:hin_x_preferred":[
        "\u0924\u094b\u0930\u0916\u093c\u092e"
    ],
    "name:jpn_x_preferred":[
        "\u30c8\u30fc\u30eb\u30cf\u30e0"
    ],
    "name:pus_x_preferred":[
        "\u062a\u0648\u0631\u062e\u0645"
    ],
    "wof:name":"Torkham",
    "wof:placetype":"locality"
},
  "geometry": {"coordinates":[71.08471999999998,34.11472],"type":"Point"}
}