{
  "type": "Feature",
  "properties": {
    "gn:admin1_code":"39",
    "gn:admin2_code":"2605",
    "gn:asciiname":"Jowdar",
    "gn:country_code":"AF",
    "gn:dem":1026,
    "gn:feature_class":"P",
    "gn:feature_code":"PPL",
    "gn:name":"Jowdar",
    "gn:population":0,
    "gn:timezone":"Asia/Kabul",
    "iso:country":"AF",
    "name:und_x_variant":[
        "Dzhaudar",
        "Jowdar",
        "\u062c\u0648\u062f\u0631",
        "Jaw\u1e0fa\u1e5f"
    ],
    "wof:name":"Jowdar",
    "wof:placetype":"locality"
},
  "geometry": {"coordinates":[65.35364,32.49802],"type":"Point"}
}