{
  "type": "Feature",
  "properties": {
    "gn:admin1_code":"09",
    "gn:admin2_code":"2704",
    "gn:asciiname":"Pushtah-ye Mu'min",
    "gn:country_code":"AF",
    "gn:dem":2055,
    "gn:feature_class":"P",
    "gn:feature_code":"PPL",
    "gn:name":"Pushtah-ye M\u016b\u2019min",
    "gn:population":0,
    "gn:timezone":"Asia/Kabul",
    "iso:country":"AF",
    "name:und_x_variant":[
        "Pus\u0304ta-i-Mu\u2019men",
        "Pushtah-ye M\u016b\u2019min",
        "\u067e\u0634\u062a\u06c0 \u0645\u0624\u0645\u0646",
        "Poshteh-ye Mo\u2019men"
    ],
    "wof:name":"Pushtah-ye Mu'min",
    "wof:placetype":"locality"
},
  "geometry": {"coordinates":[63.8811,33.6472],"type":"Point"}
}