{
  "type": "Feature",
  "properties": {
    "gn:admin1_code":"27",
    "gn:admin2_code":"407",
    "gn:asciiname":"Perong",
    "gn:country_code":"AF",
    "gn:dem":2554,
    "gn:feature_class":"P",
    "gn:feature_code":"PPL",
    "gn:name":"P\u0113r\u014dng",
    "gn:population":0,
    "gn:timezone":"Asia/Kabul",
    "iso:country":"AF",
    "name:und_x_variant":[
        "P\u0113\u1e5f\u014dng",
        "P\u0113r\u016bng",
        "P\u0113rowng",
        "P\u0113r\u014dng",
        "\u067e\u06d0\u0631\u0648\u0646\u06af"
    ],
    "wof:name":"Perong",
    "wof:placetype":"locality"
},
  "geometry": {"coordinates":[68.59331999999999,34.01191],"type":"Point"}
}