{
  "type": "Feature",
  "properties": {
    "gn:admin1_code":"18",
    "gn:admin2_code":"816.0",
    "gn:asciiname":"Siyahban",
    "gn:country_code":"AF",
    "gn:dem":487,
    "gn:feature_class":"P",
    "gn:feature_code":"PPL",
    "gn:name":"Siy\u0101hb\u0101n",
    "gn:population":0,
    "gn:timezone":"Asia/Kabul",
    "iso:country":"AF",
    "name:fas_x_preferred":[
        "\u0633\u064a\u0627\u0647\u0628\u0627\u0646"
    ],
    "name:und_x_variant":[
        "Sarband",
        "Siakhban",
        "Sarban\u1e0f",
        "Sy\u0101hb\u0101n",
        "Sar Band",
        "S\u012b\u0101hb\u0101n",
        "Siy\u0101hb\u0101n"
    ],
    "wof:name":"Siyahban",
    "wof:placetype":"locality"
},
  "geometry": {"coordinates":[70.74916,34.36549],"type":"Point"}
}