{
  "type": "Feature",
  "properties": {
    "gn:admin1_code":"27",
    "gn:admin2_code":"404",
    "gn:asciiname":"Shabarak-e Bala",
    "gn:country_code":"AF",
    "gn:dem":3048,
    "gn:feature_class":"P",
    "gn:feature_code":"PPL",
    "gn:name":"Shabarak-e B\u0101l\u0101",
    "gn:population":0,
    "gn:timezone":"Asia/Kabul",
    "iso:country":"AF",
    "name:rus_x_preferred":[
        "\u0428\u0430\u0431\u0430\u0440\u0430\u043a\u0438-\u0411\u0430\u043b\u0430"
    ],
    "name:und_x_variant":[
        "\u0160abarake B\u0101l\u0101",
        "Shabaraki-Bala",
        "Shabarak-e B\u0101l\u0101",
        "\u0634\u0628\u0631\u06a9 \u0628\u0627\u0644\u0627"
    ],
    "wof:name":"Shabarak-e Bala",
    "wof:placetype":"locality"
},
  "geometry": {"coordinates":[67.38698000000001,34.55849],"type":"Point"}
}