{
  "type": "Feature",
  "properties": {
    "gn:admin1_code":"33",
    "gn:admin2_code":"3103",
    "gn:asciiname":"Pushtah",
    "gn:country_code":"AF",
    "gn:dem":2527,
    "gn:feature_class":"P",
    "gn:feature_code":"PPL",
    "gn:name":"Pushtah",
    "gn:population":0,
    "gn:timezone":"Asia/Kabul",
    "iso:country":"AF",
    "name:und_x_variant":[
        "Pus\u0304ta",
        "Poshteh",
        "Pushtah",
        "\u067e\u0634\u062a\u0647"
    ],
    "wof:name":"Pushtah",
    "wof:placetype":"locality"
},
  "geometry": {"coordinates":[66.16381,35.2857],"type":"Point"}
}