{
  "type": "Feature",
  "properties": {
    "gn:admin1_code":"30",
    "gn:admin2_code":"1607",
    "gn:asciiname":"Sabzi Kar",
    "gn:country_code":"AF",
    "gn:dem":330,
    "gn:feature_class":"P",
    "gn:feature_code":"PPL",
    "gn:name":"Sabz\u012b K\u0101r",
    "gn:population":0,
    "gn:timezone":"Asia/Kabul",
    "iso:country":"AF",
    "name:fas_x_preferred":[
        "\u0633\u0628\u0632\u06cc \u0643\u0631"
    ],
    "name:rus_x_preferred":[
        "\u0421\u0430\u0431\u0437\u0438\u043a\u0430\u0440"
    ],
    "name:und_x_variant":[
        "Sabzikar",
        "Sabz\u012b Kar",
        "Sabz\u012b K\u0101r",
        "\u0633\u0628\u0632\u06cc \u06a9\u0627\u0631"
    ],
    "wof:name":"Sabzi Kar",
    "wof:placetype":"locality"
},
  "geometry": {"coordinates":[66.69383000000001,36.77318],"type":"Point"}
}