{
  "type": "Feature",
  "properties": {
    "gn:admin1_code":"40",
    "gn:admin2_code":"305",
    "gn:asciiname":"Miyandeh",
    "gn:country_code":"AF",
    "gn:dem":2010,
    "gn:feature_class":"P",
    "gn:feature_code":"PPL",
    "gn:name":"Miy\u0101ndeh",
    "gn:population":0,
    "gn:timezone":"Asia/Kabul",
    "iso:country":"AF",
    "name:und_x_variant":[
        "My\u0101n\u1e0feh",
        "Mpandekh",
        "M\u012b\u0101ndeh",
        "M\u012b\u0101ndah",
        "Miy\u0101ndeh",
        "\u0645\u06cc\u0627\u0646\u062f\u0647"
    ],
    "wof:name":"Miyandeh",
    "wof:placetype":"locality"
},
  "geometry": {"coordinates":[68.88420000000001,34.97113],"type":"Point"}
}