{
  "type": "Feature",
  "properties": {
    "gn:admin1_code":"9",
    "gn:admin2_code":"2702.0",
    "gn:asciiname":"Tawah Ghal",
    "gn:country_code":"AF",
    "gn:dem":2465,
    "gn:feature_class":"P",
    "gn:feature_code":"PPL",
    "gn:name":"T\u0101wah Gh\u0101l",
    "gn:population":0,
    "gn:timezone":"Asia/Kabul",
    "iso:country":"AF",
    "name:rus_x_preferred":[
        "Tavagal\u2019"
    ],
    "name:und_x_variant":[
        "T\u0101wagh\u0101l",
        "T\u0101wah Gh\u0101l",
        "\u062a\u0627\u0648\u0647 \u063a\u0627\u0644",
        "T\u0101behgh\u0101l"
    ],
    "wof:name":"Tawah Ghal",
    "wof:placetype":"locality"
},
  "geometry": {"coordinates":[64.17909,34.21262],"type":"Point"}
}