{
  "type": "Feature",
  "properties": {
    "gn:admin1_code":"8",
    "gn:admin2_code":"604.0",
    "gn:asciiname":"Dahan-e Sobah",
    "gn:country_code":"AF",
    "gn:dem":2882,
    "gn:feature_class":"P",
    "gn:feature_code":"PPL",
    "gn:name":"Dahan-e \u015e\u014dbah",
    "gn:population":0,
    "gn:timezone":"Asia/Kabul",
    "iso:country":"AF",
    "name:und_x_variant":[
        "\u1e0eahane \u015e\u014dba",
        "Dakhani-Soba",
        "Dahan-e \u015e\u014dbah",
        "Dahan-e \u015eowbah",
        "\u062f\u0647\u0646 \u0635\u0648\u0628\u0647"
    ],
    "wof:name":"Dahan-e Sobah",
    "wof:placetype":"locality"
},
  "geometry": {"coordinates":[68.13131,33.93698],"type":"Point"}
}