{
  "type": "Feature",
  "properties": {
    "gn:admin1_code":"23",
    "gn:admin2_code":"2412",
    "gn:asciiname":"Qanat-e Haji Bor",
    "gn:country_code":"AF",
    "gn:dem":1217,
    "gn:feature_class":"P",
    "gn:feature_code":"PPL",
    "gn:name":"Qan\u0101t-e \u1e28\u0101j\u012b B\u014dr",
    "gn:population":0,
    "gn:timezone":"Asia/Kabul",
    "iso:country":"AF",
    "name:und_x_variant":[
        "Kanate-Khadzhi-Bur",
        "Qan\u0101te \u1e28\u0101ji B\u014d\u1e5f",
        "\u0642\u0646\u0627\u062a \u062d\u0627\u062c\u06cc \u0628\u0648\u0631",
        "Qan\u0101t-e \u1e28\u0101jj\u012b B\u016br",
        "Qan\u0101t-e \u1e28\u0101j\u012b B\u014dr"
    ],
    "wof:name":"Qanat-e Haji Bor",
    "wof:placetype":"locality"
},
  "geometry": {"coordinates":[66.22620000000001,31.67244],"type":"Point"}
}