{
  "type": "Feature",
  "properties": {
    "gn:admin1_code":"40",
    "gn:admin2_code":"306.0",
    "gn:asciiname":"Tangi Lali",
    "gn:country_code":"AF",
    "gn:dem":2086,
    "gn:feature_class":"P",
    "gn:feature_code":"PPL",
    "gn:name":"Tang\u012b L\u0101l\u012b",
    "gn:population":0,
    "gn:timezone":"Asia/Kabul",
    "iso:country":"AF",
    "name:und_x_variant":[
        "Tang\u012b L\u0101li",
        "Tangilami",
        "Tang\u012b L\u0101le",
        "Tang\u012b L\u0101l\u012b",
        "\u062a\u0646\u06af\u06cc \u0644\u0627\u0644\u06cc"
    ],
    "wof:name":"Tangi Lali",
    "wof:placetype":"locality"
},
  "geometry": {"coordinates":[68.60396999999999,34.97203],"type":"Point"}
}