{
  "type": "Feature",
  "properties": {
    "gn:admin1_code":"18",
    "gn:admin2_code":"814.0",
    "gn:asciiname":"Sherabad",
    "gn:country_code":"AF",
    "gn:dem":426,
    "gn:feature_class":"P",
    "gn:feature_code":"PPL",
    "gn:name":"Sh\u0113r\u0101b\u0101d",
    "gn:population":0,
    "gn:timezone":"Asia/Kabul",
    "iso:country":"AF",
    "name:und_x_variant":[
        "\u0160\u0113r\u0101b\u0101d",
        "Sh\u0113r\u0101b\u0101d",
        "Sher\u0101b\u0101d",
        "Shayr\u0101b\u0101d",
        "\u0634\u06cc\u0631 \u0622\u0628\u0627\u062f"
    ],
    "wof:name":"Sherabad",
    "wof:placetype":"locality"
},
  "geometry": {"coordinates":[71.02762,34.23313],"type":"Point"}
}