{
  "type": "Feature",
  "properties": {
    "gn:admin1_code":"14",
    "gn:admin2_code":"203",
    "gn:asciiname":"Qal'ah-ye 'Ata Khan",
    "gn:country_code":"AF",
    "gn:dem":1682,
    "gn:feature_class":"P",
    "gn:feature_code":"PPL",
    "gn:name":"Qal\u2018ah-ye \u2018A\u0163\u0101 Kh\u0101n",
    "gn:population":0,
    "gn:timezone":"Asia/Kabul",
    "iso:country":"AF",
    "name:fas_x_preferred":[
        "\u0642\u0644\u0639\u0647\u0654 \u0627\u062a\u0627\u062e\u0646"
    ],
    "name:und_x_variant":[
        "Kalayi-Atakhan",
        "Qal\u2018a \u2018At\u0101kh\u0101n",
        "Qal\u2018eh-ye At\u0101khan",
        "Qal\u2018ah-ye \u2018A\u0163\u0101 Kh\u0101n",
        "\u0642\u0644\u0639\u06c0 \u0639\u0637\u0627 \u062e\u0627\u0646"
    ],
    "wof:name":"Qal'ah-ye 'Ata Khan",
    "wof:placetype":"locality"
},
  "geometry": {"coordinates":[69.39875000000001,35.09738],"type":"Point"}
}