{
  "type": "Feature",
  "properties": {
    "gn:admin1_code":"09",
    "gn:admin2_code":"2706.0",
    "gn:asciiname":"Bazan",
    "gn:country_code":"AF",
    "gn:dem":1939,
    "gn:feature_class":"P",
    "gn:feature_code":"PPL",
    "gn:name":"B\u0101z\u0101n",
    "gn:population":0,
    "gn:timezone":"Asia/Kabul",
    "iso:country":"AF",
    "name:ceb_x_preferred":[
        "Bazan"
    ],
    "name:ita_x_preferred":[
        "Bazan"
    ],
    "name:rus_x_preferred":[
        "\u0411\u0430\u0437\u0430\u043d"
    ],
    "name:slv_x_preferred":[
        "Bazan"
    ],
    "name:swe_x_preferred":[
        "Bazan"
    ],
    "name:und_x_variant":[
        "B\u0101z\u0101n",
        "\u0628\u0627\u0632\u0627\u0646"
    ],
    "wof:name":"Bazan",
    "wof:placetype":"locality"
},
  "geometry": {"coordinates":[65.22753,33.47241],"type":"Point"}
}