{
  "type": "Feature",
  "properties": {
    "gn:admin1_code":"39",
    "gn:admin2_code":"2604.0",
    "gn:asciiname":"Band-e Toghay",
    "gn:country_code":"AF",
    "gn:dem":1129,
    "gn:feature_class":"P",
    "gn:feature_code":"PPL",
    "gn:name":"Band-e T\u014dghay",
    "gn:population":0,
    "gn:timezone":"Asia/Kabul",
    "iso:country":"AF",
    "name:fas_x_preferred":[
        "\u0628\u0646\u062f\u0654 \u062a\u0648\u063a\u06cc"
    ],
    "name:und_x_variant":[
        "Band-e T\u014dghay",
        "\u0628\u0646\u062f \u062a\u0648\u063a\u06cc",
        "Band-e Toghay",
        "Band-e T\u016bghay",
        "Ban\u1e0fe T\u014dghay",
        "Bandi-Togay"
    ],
    "wof:name":"Band-e Toghay",
    "wof:placetype":"locality"
},
  "geometry": {"coordinates":[65.5018,32.96391],"type":"Point"}
}