{
  "type": "Feature",
  "properties": {
    "gn:admin1_code":"09",
    "gn:admin2_code":"2705",
    "gn:asciiname":"Deh-e Tay",
    "gn:country_code":"AF",
    "gn:dem":2428,
    "gn:feature_class":"P",
    "gn:feature_code":"PPL",
    "gn:name":"Deh-e T\u0101y",
    "gn:population":0,
    "gn:timezone":"Asia/Kabul",
    "iso:country":"AF",
    "name:und_x_variant":[
        "Deh Tay",
        "Dekhi-Tay",
        "Dehtai",
        "Deh-e T\u0101y",
        "\u062f\u06c0 \u062a\u0627\u06cc"
    ],
    "wof:name":"Deh-e Tay",
    "wof:placetype":"locality"
},
  "geometry": {"coordinates":[64.37597,33.58058],"type":"Point"}
}