{
  "type": "Feature",
  "properties": {
    "gn:admin1_code":"03",
    "gn:admin2_code":"1311",
    "gn:asciiname":"Girdab",
    "gn:country_code":"AF",
    "gn:dem":504,
    "gn:feature_class":"P",
    "gn:feature_code":"PPL",
    "gn:name":"Gird\u0101b",
    "gn:population":0,
    "gn:timezone":"Asia/Kabul",
    "iso:country":"AF",
    "name:rus_x_preferred":[
        "\u0413\u0438\u0440\u0434\u0430\u0431"
    ],
    "name:und_x_variant":[
        "Gerd\u0101b",
        "Gird\u0101b",
        "\u06af\u0631\u062f\u0627\u0628"
    ],
    "wof:name":"Girdab",
    "wof:placetype":"locality"
},
  "geometry": {"coordinates":[68.84023000000001,36.3377],"type":"Point"}
}