{
  "type": "Feature",
  "properties": {
    "gn:admin1_code":"08",
    "gn:admin2_code":"614",
    "gn:asciiname":"Khumri",
    "gn:country_code":"AF",
    "gn:dem":2079,
    "gn:feature_class":"P",
    "gn:feature_code":"PPL",
    "gn:name":"Khumr\u012b",
    "gn:population":0,
    "gn:timezone":"Asia/Kabul",
    "iso:country":"AF",
    "name:und_x_variant":[
        "Khum\u1e5fi",
        "Khomr\u012b",
        "Khumr\u012b",
        "\u062e\u0645\u0631\u06cc"
    ],
    "wof:name":"Khumri",
    "wof:placetype":"locality"
},
  "geometry": {"coordinates":[68.5852,33.31238],"type":"Point"}
}