{
  "type": "Feature",
  "properties": {
    "gn:admin1_code":"05",
    "gn:admin2_code":"2806",
    "gn:asciiname":"'Uliyad Qol-e Tak",
    "gn:country_code":"AF",
    "gn:dem":2788,
    "gn:feature_class":"P",
    "gn:feature_code":"PPL",
    "gn:name":"\u2018Uliy\u0101d Q\u014dl-e Tak",
    "gn:population":0,
    "gn:timezone":"Asia/Kabul",
    "iso:country":"AF",
    "name:rus_x_preferred":[
        "Uliadkul\u2019tak"
    ],
    "name:und_x_variant":[
        "\u2018Oley\u0101\u1e0fq\u014dl-tak",
        "\u2018Ol\u012b\u0101dqowl Tak",
        "\u2018Oley\u0101dqowl Tak",
        "\u2018Uliy\u0101d Q\u014dl-e Tak",
        "\u0639\u0644\u06cc\u0627\u062f \u0642\u0648\u0644 \u062a\u06a9"
    ],
    "wof:name":"'Uliyad Qol-e Tak",
    "wof:placetype":"locality"
},
  "geometry": {"coordinates":[67.31126999999999,34.11218],"type":"Point"}
}