{
  "type": "Feature",
  "properties": {
    "gn:admin1_code":"23",
    "gn:admin2_code":"2408",
    "gn:asciiname":"Mushan",
    "gn:country_code":"AF",
    "gn:dem":895,
    "gn:feature_class":"P",
    "gn:feature_code":"PPL",
    "gn:name":"M\u016bsh\u0101n",
    "gn:population":0,
    "gn:timezone":"Asia/Kabul",
    "iso:country":"AF",
    "name:und_x_variant":[
        "M\u016b\u0161\u0101n",
        "M\u016bsh\u0101n",
        "\u0645\u0648\u0634\u0627\u0646"
    ],
    "wof:name":"Mushan",
    "wof:placetype":"locality"
},
  "geometry": {"coordinates":[65.26116999999999,31.46553],"type":"Point"}
}