{
  "type": "Feature",
  "properties": {
    "gn:admin1_code":"8",
    "gn:admin2_code":"608.0",
    "gn:asciiname":"Rabo Khel",
    "gn:country_code":"AF",
    "gn:dem":1990,
    "gn:feature_class":"P",
    "gn:feature_code":"PPL",
    "gn:name":"R\u0101b\u014d Kh\u0113l",
    "gn:population":0,
    "gn:timezone":"Asia/Kabul",
    "iso:country":"AF",
    "name:rus_x_preferred":[
        "Rabokheyl\u2019"
    ],
    "name:und_x_variant":[
        "\u1e5e\u0101b\u014dkh\u0113l",
        "R\u0101bow Kheyl",
        "R\u0101b\u014d Kh\u0113l",
        "\u0631\u0627\u0628\u0648 \u062e\u06d0\u0644"
    ],
    "wof:name":"Rabo Khel",
    "wof:placetype":"locality"
},
  "geometry": {"coordinates":[67.80529,32.81449],"type":"Point"}
}