{
  "type": "Feature",
  "properties": {
    "gn:admin1_code":"23",
    "gn:admin2_code":"2404.0",
    "gn:asciiname":"Kherisak",
    "gn:country_code":"AF",
    "gn:dem":1001,
    "gn:feature_class":"P",
    "gn:feature_code":"PPL",
    "gn:name":"Kh\u00ea\u1e5fisak",
    "gn:population":0,
    "gn:timezone":"Asia/Kabul",
    "iso:country":"AF",
    "name:fas_x_preferred":[
        "\u062e\u0631\u0633\u0643"
    ],
    "name:und_x_variant":[
        "Kh\u011bresak",
        "Kherisak",
        "Kh\u00ea\u1e5fisak",
        "\u062e\u0693\u0633\u06a9",
        "Khersak"
    ],
    "wof:name":"Kherisak",
    "wof:placetype":"locality"
},
  "geometry": {"coordinates":[65.62751999999999,31.65224000000001],"type":"Point"}
}