{
  "type": "Feature",
  "properties": {
    "gn:admin1_code":"01",
    "gn:admin2_code":"1114.0",
    "gn:asciiname":"Kamar-e Saiqan",
    "gn:country_code":"AF",
    "gn:dem":2832,
    "gn:feature_class":"P",
    "gn:feature_code":"PPL",
    "gn:name":"Kamar-e \u015ea\u012bq\u0101n",
    "gn:population":0,
    "gn:timezone":"Asia/Kabul",
    "iso:country":"AF",
    "name:und_x_variant":[
        "Kamar-i-Sayq\u0101n",
        "\u06a9\u0645\u0631 \u0635\u0627\u06cc\u0642\u0627\u0646",
        "Kamar-e Seyq\u0101n",
        "Kamar-e \u015ea\u012bq\u0101n"
    ],
    "wof:name":"Kamar-e Saiqan",
    "wof:placetype":"locality"
},
  "geometry": {"coordinates":[70.86776999999999,37.39798],"type":"Point"}
}