{
  "type": "Feature",
  "properties": {
    "gn:admin1_code":"10",
    "gn:admin2_code":"2302",
    "gn:asciiname":"Jamal Kor",
    "gn:country_code":"AF",
    "gn:dem":799,
    "gn:feature_class":"P",
    "gn:feature_code":"PPL",
    "gn:name":"Jam\u0101l K\u014dr",
    "gn:population":0,
    "gn:timezone":"Asia/Kabul",
    "iso:country":"AF",
    "name:fas_x_preferred":[
        "\u062c\u0645\u0627\u0644 \u0643\u0648\u0631"
    ],
    "name:rus_x_preferred":[
        "Dzhamal\u2019kor"
    ],
    "name:und_x_variant":[
        "Jam\u0101l K\u014d\u1e5f",
        "Jam\u0101l",
        "Jam\u0101l K\u014d",
        "Jam\u0101l K\u014dr",
        "\u062c\u0645\u0627\u0644 \u06a9\u0648\u0631",
        "Jam\u0101l Kowr"
    ],
    "wof:name":"Jamal Kor",
    "wof:placetype":"locality"
},
  "geometry": {"coordinates":[64.44969,31.72455],"type":"Point"}
}