{
  "type": "Feature",
  "properties": {
    "gn:admin1_code":"08",
    "gn:admin2_code":"606",
    "gn:asciiname":"Panma",
    "gn:country_code":"AF",
    "gn:dem":2769,
    "gn:feature_class":"P",
    "gn:feature_code":"PPL",
    "gn:name":"Panm\u0101",
    "gn:population":0,
    "gn:timezone":"Asia/Kabul",
    "iso:country":"AF",
    "name:und_x_variant":[
        "Panm\u0101",
        "\u067e\u0646\u0645\u0627"
    ],
    "wof:name":"Panma",
    "wof:placetype":"locality"
},
  "geometry": {"coordinates":[67.28471,33.33048],"type":"Point"}
}