{
  "type": "Feature",
  "properties": {
    "gn:admin1_code":"05",
    "gn:admin2_code":"2806.0",
    "gn:asciiname":"Bahram",
    "gn:country_code":"AF",
    "gn:dem":2798,
    "gn:feature_class":"P",
    "gn:feature_code":"PPL",
    "gn:name":"Bahr\u0101m",
    "gn:population":0,
    "gn:timezone":"Asia/Kabul",
    "iso:country":"AF",
    "name:und_x_variant":[
        "Bakhram",
        "Bahr\u0101m",
        "\u0628\u0647\u0631\u0627\u0645"
    ],
    "wof:name":"Bahram",
    "wof:placetype":"locality"
},
  "geometry": {"coordinates":[67.29869000000001,34.07182],"type":"Point"}
}