{
  "type": "Feature",
  "properties": {
    "gn:admin1_code":"09",
    "gn:admin2_code":"2710",
    "gn:asciiname":"Ghal-Mulla",
    "gn:country_code":"AF",
    "gn:dem":2526,
    "gn:feature_class":"P",
    "gn:feature_code":"PPL",
    "gn:name":"Gh\u0101l-Mull\u0101",
    "gn:population":0,
    "gn:timezone":"Asia/Kabul",
    "iso:country":"AF",
    "name:und_x_variant":[
        "Gh\u0101l-Mull\u0101",
        "Gh\u0101l Moll\u0101",
        "\u063a\u0627\u0644 \u0645\u0644\u0627"
    ],
    "wof:name":"Ghal-Mulla",
    "wof:placetype":"locality"
},
  "geometry": {"coordinates":[64.71359,34.30685],"type":"Point"}
}