{
  "type": "Feature",
  "properties": {
    "gn:admin1_code":"23",
    "gn:admin2_code":"2405",
    "gn:asciiname":"Zarak",
    "gn:country_code":"AF",
    "gn:dem":1155,
    "gn:feature_class":"P",
    "gn:feature_code":"PPL",
    "gn:name":"Zarak",
    "gn:population":0,
    "gn:timezone":"Asia/Kabul",
    "iso:country":"AF",
    "name:fas_x_preferred":[
        "\u0632\u0631\u0643"
    ],
    "name:ita_x_preferred":[
        "Zarak Khan"
    ],
    "name:nld_x_preferred":[
        "Zarak"
    ],
    "name:und_x_variant":[
        "\u0632\u0631\u06a9",
        "Zarak",
        "Za\u1e5fak"
    ],
    "wof:name":"Zarak",
    "wof:placetype":"locality"
},
  "geometry": {"coordinates":[65.26205,31.78988],"type":"Point"}
}