{
  "type": "Feature",
  "properties": {
    "gn:admin1_code":"35",
    "gn:admin2_code":"902.0",
    "gn:asciiname":"Qasimabad",
    "gn:country_code":"AF",
    "gn:dem":626,
    "gn:feature_class":"P",
    "gn:feature_code":"PPL",
    "gn:name":"Q\u0101sim\u0101b\u0101d",
    "gn:population":0,
    "gn:timezone":"Asia/Kabul",
    "iso:country":"AF",
    "name:und_x_variant":[
        "Kasimabad",
        "Q\u0101sem \u0100b\u0101d",
        "Q\u0101sim\u0101b\u0101d",
        "\u0642\u0627\u0633\u0645 \u0622\u0628\u0627\u062f"
    ],
    "wof:name":"Qasimabad",
    "wof:placetype":"locality"
},
  "geometry": {"coordinates":[70.24422,34.51327],"type":"Point"}
}