{
  "type": "Feature",
  "properties": {
    "gn:admin1_code":"26",
    "gn:admin2_code":"1209.0",
    "gn:asciiname":"Khasar",
    "gn:country_code":"AF",
    "gn:dem":822,
    "gn:feature_class":"P",
    "gn:feature_code":"PPL",
    "gn:name":"Kh\u0101s\u0101\u1e5f",
    "gn:population":0,
    "gn:timezone":"Asia/Kabul",
    "iso:country":"AF",
    "wof:name":"Khasar",
    "wof:placetype":"locality"
},
  "geometry": {"coordinates":[69.82444,37.50278],"type":"Point"}
}