{
  "type": "Feature",
  "properties": {
    "gn:admin1_code":"30",
    "gn:admin2_code":"1610",
    "gn:asciiname":"Yakawulang",
    "gn:country_code":"AF",
    "gn:dem":1557,
    "gn:feature_class":"P",
    "gn:feature_code":"PPL",
    "gn:name":"Yak\u0101wulang",
    "gn:population":0,
    "gn:timezone":"Asia/Kabul",
    "iso:country":"AF",
    "name:und_x_variant":[
        "Yakawolang",
        "Yak\u0101wulang",
        "\u06cc\u06a9\u0627\u0648\u0644\u0646\u06af"
    ],
    "wof:name":"Yakawulang",
    "wof:placetype":"locality"
},
  "geometry": {"coordinates":[67.03222,36.00943],"type":"Point"}
}