{
  "type": "Feature",
  "properties": {
    "gn:admin1_code":"13",
    "gn:admin2_code":"114.0",
    "gn:asciiname":"Gul Darah",
    "gn:country_code":"AF",
    "gn:dem":1959,
    "gn:feature_class":"P",
    "gn:feature_code":"PPL",
    "gn:name":"Gul Darah",
    "gn:population":0,
    "gn:timezone":"Asia/Kabul",
    "iso:country":"AF",
    "name:und_x_variant":[
        "\u06af\u0644 \u062f\u0631\u0647"
    ],
    "wof:name":"Gul Darah",
    "wof:placetype":"locality"
},
  "geometry": {"coordinates":[69.25679000000001,34.39157],"type":"Point"}
}