{
  "type": "Feature",
  "properties": {
    "gn:admin1_code":"08",
    "gn:admin2_code":"609",
    "gn:asciiname":"Jabar Kala",
    "gn:country_code":"AF",
    "gn:dem":2081,
    "gn:feature_class":"P",
    "gn:feature_code":"PPL",
    "gn:name":"Jab\u0101r Kal\u0101",
    "gn:population":0,
    "gn:timezone":"Asia/Kabul",
    "iso:country":"AF",
    "name:und_x_variant":[
        "Dzhabbarkala",
        "Jab\u0101\u1e5f Kal\u0101",
        "Jab\u0101r Kal\u0101",
        "\u062c\u0628\u0627\u0631 \u06a9\u0644\u0627",
        "Jabb\u0101r Kal\u0101"
    ],
    "wof:name":"Jabar Kala",
    "wof:placetype":"locality"
},
  "geometry": {"coordinates":[67.76945000000001,32.50558],"type":"Point"}
}