{
  "type": "Feature",
  "properties": {
    "gn:admin1_code":"13",
    "gn:admin2_code":"101.0",
    "gn:asciiname":"Qal'ah-ye 'Aynullah",
    "gn:country_code":"AF",
    "gn:dem":1824,
    "gn:feature_class":"P",
    "gn:feature_code":"PPL",
    "gn:name":"Qal\u2018ah-ye \u2018Aynull\u0101h",
    "gn:population":0,
    "gn:timezone":"Asia/Kabul",
    "iso:country":"AF",
    "name:und_x_variant":[
        "Kalayi-Aynulla",
        "Qal\u2018ah-ye \u2018Aynull\u0101h",
        "\u0642\u0644\u0639\u0647 \u0639\u06cc\u0646 \u0627\u0644\u0644\u0647"
    ],
    "wof:name":"Qal'ah-ye 'Aynullah",
    "wof:placetype":"locality"
},
  "geometry": {"coordinates":[69.11168000000001,34.48482],"type":"Point"}
}