{
  "type": "Feature",
  "properties": {
    "gn:admin1_code":"29",
    "gn:admin2_code":"2910",
    "gn:asciiname":"Wusim Gharah",
    "gn:country_code":"AF",
    "gn:dem":2246,
    "gn:feature_class":"P",
    "gn:feature_code":"PPL",
    "gn:name":"Wus\u012bm Gh\u0101\u1e5fah",
    "gn:population":0,
    "gn:timezone":"Asia/Kabul",
    "iso:country":"AF",
    "name:und_x_variant":[
        "Vusimgara",
        "Wos\u012bm Gh\u0101ra",
        "Wus\u012bm Gh\u0101\u1e5fah",
        "Wus\u012bm Gh\u0101rah",
        "\u0648\u0633\u06cc\u0645 \u063a\u0627\u0631\u0647"
    ],
    "wof:name":"Wusim Gharah",
    "wof:placetype":"locality"
},
  "geometry": {"coordinates":[69.36691999999999,32.99878],"type":"Point"}
}