{
  "type": "Feature",
  "properties": {
    "gn:admin1_code":"10",
    "gn:admin2_code":"2306",
    "gn:asciiname":"Gurdah-ye 'Ulya",
    "gn:country_code":"AF",
    "gn:dem":1807,
    "gn:feature_class":"P",
    "gn:feature_code":"PPL",
    "gn:name":"Gurdah-ye \u2018Uly\u0101",
    "gn:population":0,
    "gn:timezone":"Asia/Kabul",
    "iso:country":"AF",
    "name:und_x_variant":[
        "Gurdakhi-Ulia",
        "Gu\u1e5f\u1e0fahe \u2018Uly\u0101",
        "Gurdah-ye \u2018Uly\u0101",
        "\u06af\u0631\u062f\u0647 \u0639\u0644\u06cc\u0627",
        "Gurdah-e \u2018Oly\u0101"
    ],
    "wof:name":"Gurdah-ye 'Ulya",
    "wof:placetype":"locality"
},
  "geometry": {"coordinates":[64.17796,32.50594],"type":"Point"}
}