{
  "type": "Feature",
  "properties": {
    "gn:admin1_code":"02",
    "gn:admin2_code":"1903",
    "gn:asciiname":"Qaybeli",
    "gn:country_code":"AF",
    "gn:dem":1133,
    "gn:feature_class":"P",
    "gn:feature_code":"PPL",
    "gn:name":"Qayb\u0113l\u012b",
    "gn:population":0,
    "gn:timezone":"Asia/Kabul",
    "iso:country":"AF",
    "name:und_x_variant":[
        "Kaybeli",
        "Qayb\u0113l\u012b",
        "\u0642\u06cc\u06d0\u0644\u06cc",
        "Qaybah",
        "\u0642\u06cc\u0628\u0647"
    ],
    "wof:name":"Qaybeli",
    "wof:placetype":"locality"
},
  "geometry": {"coordinates":[63.39054,34.89831],"type":"Point"}
}