{
  "type": "Feature",
  "properties": {
    "gn:admin1_code":"19",
    "gn:admin2_code":"2205.0",
    "gn:asciiname":"Basrang",
    "gn:country_code":"AF",
    "gn:dem":665,
    "gn:feature_class":"P",
    "gn:feature_code":"PPL",
    "gn:name":"Basrang",
    "gn:population":0,
    "gn:timezone":"Asia/Kabul",
    "iso:country":"AF",
    "name:fas_x_preferred":[
        "\u0628\u0633 \u0631\u0646\u06af"
    ],
    "name:und_x_variant":[
        "Bas\u1e5fang"
    ],
    "wof:name":"Basrang",
    "wof:placetype":"locality"
},
  "geometry": {"coordinates":[62.78556999999999,31.81958],"type":"Point"}
}