{
  "type": "Feature",
  "properties": {
    "gn:admin1_code":"01",
    "gn:admin2_code":"1111.0",
    "gn:asciiname":"Du Dargah",
    "gn:country_code":"AF",
    "gn:dem":1863,
    "gn:feature_class":"P",
    "gn:feature_code":"PPL",
    "gn:name":"D\u016b Dargah",
    "gn:population":0,
    "gn:timezone":"Asia/Kabul",
    "iso:country":"AF",
    "name:und_x_variant":[
        "\u1e0eu \u1e0ea\u1e5fgah",
        "Do Dargah",
        "D\u016b Dargah",
        "\u062f\u0648 \u062f\u0631\u06af\u0647"
    ],
    "wof:name":"Du Dargah",
    "wof:placetype":"locality"
},
  "geometry": {"coordinates":[70.2779,37.85809],"type":"Point"}
}