{
  "type": "Feature",
  "properties": {
    "gn:admin1_code":"09",
    "gn:admin2_code":"2706",
    "gn:asciiname":"Lorah",
    "gn:country_code":"AF",
    "gn:dem":2628,
    "gn:feature_class":"P",
    "gn:feature_code":"PPL",
    "gn:name":"L\u014drah",
    "gn:population":0,
    "gn:timezone":"Asia/Kabul",
    "iso:country":"AF",
    "name:und_x_variant":[
        "Lora",
        "L\u014d\u1e5fa",
        "L\u014drah",
        "\u0644\u0648\u0631\u0647",
        "Lowrah"
    ],
    "wof:name":"Lorah",
    "wof:placetype":"locality"
},
  "geometry": {"coordinates":[64.86696999999999,33.59693],"type":"Point"}
}