{
  "type": "Feature",
  "properties": {
    "gn:admin1_code":"36",
    "gn:admin2_code":"711.0",
    "gn:asciiname":"Nowabad",
    "gn:country_code":"AF",
    "gn:dem":2444,
    "gn:feature_class":"P",
    "gn:feature_code":"PPL",
    "gn:name":"Now\u0101b\u0101d",
    "gn:population":0,
    "gn:timezone":"Asia/Kabul",
    "iso:country":"AF",
    "name:und_x_variant":[
        "Navabad",
        "Naw\u0101b\u0101d",
        "Now\u0101b\u0101d",
        "\u0646\u0648 \u0622\u0628\u0627\u062f"
    ],
    "wof:name":"Nowabad",
    "wof:placetype":"locality"
},
  "geometry": {"coordinates":[69.8326,33.97567],"type":"Point"}
}