{
  "type": "Feature",
  "properties": {
    "gn:admin1_code":"18",
    "gn:admin2_code":"810.0",
    "gn:asciiname":"Shnah Kandah",
    "gn:country_code":"AF",
    "gn:dem":1112,
    "gn:feature_class":"P",
    "gn:feature_code":"PPL",
    "gn:name":"Shnah Kandah",
    "gn:population":0,
    "gn:timezone":"Asia/Kabul",
    "iso:country":"AF",
    "name:fas_x_preferred":[
        "\u062e\u0646\u062f\u0642\u0654 \u0634\u0646\u0647"
    ],
    "name:und_x_variant":[
        "\u0160na Kanda",
        "Shna Kanda",
        "Shnakanda",
        "Shnah Kandah",
        "\u0634\u0646\u0647 \u06a9\u0646\u062f\u0647"
    ],
    "wof:name":"Shnah Kandah",
    "wof:placetype":"locality"
},
  "geometry": {"coordinates":[70.59914000000001,34.08642],"type":"Point"}
}