{
  "type": "Feature",
  "properties": {
    "gn:admin1_code":"10",
    "gn:admin2_code":"2302.0",
    "gn:asciiname":"Haji Tor Khan Kelay",
    "gn:country_code":"AF",
    "gn:dem":820,
    "gn:feature_class":"P",
    "gn:feature_code":"PPL",
    "gn:name":"\u1e28\u0101j\u012b T\u014dr Kh\u0101n K\u00ealay",
    "gn:population":0,
    "gn:timezone":"Asia/Kabul",
    "iso:country":"AF",
    "name:und_x_variant":[
        "Take He\u1e5f\u0101tih\u0101",
        "Taki-Khiratikha",
        "\u1e28\u0101jit\u014d\u1e5fkh\u0101n Kalay",
        "Khadzhitorkhan-Kalay",
        "Tak-e Her\u0101tih\u0101 Kalay",
        "\u1e28\u0101j\u012b T\u014dr Kh\u0101n K\u00ealay",
        "\u062d\u0627\u062c\u06cc \u062a\u0648\u0631 \u062e\u0627\u0646 \u06a9\u0644\u06cc",
        "\u1e28\u0101jj\u012bt\u016brkh\u0101n Kalay",
        "\u1e6eak-e Hir\u0101t\u012b H\u0101",
        "\u067c\u06a9 \u0647\u0631\u0627\u062a\u06cc \u0647\u0627"
    ],
    "wof:name":"Haji Tor Khan Kelay",
    "wof:placetype":"locality"
},
  "geometry": {"coordinates":[64.56421,31.70931],"type":"Point"}
}