{
  "type": "Feature",
  "properties": {
    "gn:admin1_code":"32",
    "gn:admin2_code":"1504",
    "gn:asciiname":"Qarah Jangal",
    "gn:country_code":"AF",
    "gn:dem":1586,
    "gn:feature_class":"P",
    "gn:feature_code":"PPL",
    "gn:name":"Qarah Jangal",
    "gn:population":0,
    "gn:timezone":"Asia/Kabul",
    "iso:country":"AF",
    "name:ara_x_preferred":[
        "\u0642\u0631\u0647 \u062c\u0646\u063a\u0644"
    ],
    "name:ceb_x_preferred":[
        "Qarah Jangal"
    ],
    "name:fas_x_preferred":[
        "\u0642\u0631\u0647 \u062c\u0646\u06af\u0644"
    ],
    "name:swe_x_preferred":[
        "Qarah Jangal"
    ],
    "name:und_x_variant":[
        "Qa\u1e5fajangal",
        "Qareh Jangal"
    ],
    "wof:name":"Qarah Jangal",
    "wof:placetype":"locality"
},
  "geometry": {"coordinates":[67.16145999999999,35.99287],"type":"Point"}
}