{
  "type": "Feature",
  "properties": {
    "gn:admin1_code":"18",
    "gn:admin2_code":"805",
    "gn:asciiname":"Surmay",
    "gn:country_code":"AF",
    "gn:dem":1237,
    "gn:feature_class":"P",
    "gn:feature_code":"PPL",
    "gn:name":"Surmay",
    "gn:population":0,
    "gn:timezone":"Asia/Kabul",
    "iso:country":"AF",
    "name:fas_x_preferred":[
        "\u0633\u0648\u0631\u0645\u06cc"
    ],
    "name:und_x_variant":[
        "Su\u1e5fmay",
        "Surma\u012b",
        "Surmay",
        "\u0633\u0631\u0645\u06cc"
    ],
    "wof:name":"Surmay",
    "wof:placetype":"locality"
},
  "geometry": {"coordinates":[70.20925,34.23935],"type":"Point"}
}