{
  "type": "Feature",
  "properties": {
    "gn:admin1_code":"40",
    "gn:admin2_code":"308.0",
    "gn:asciiname":"Shabi Khel",
    "gn:country_code":"AF",
    "gn:dem":1496,
    "gn:feature_class":"P",
    "gn:feature_code":"PPL",
    "gn:name":"Sh\u0101b\u012b Kh\u0113l",
    "gn:population":0,
    "gn:timezone":"Asia/Kabul",
    "iso:country":"AF",
    "name:fas_x_preferred":[
        "\u0634\u0627\u0628\u06cc \u062e\u064a\u0644"
    ],
    "name:rus_x_preferred":[
        "Shibikheyl\u2019"
    ],
    "name:und_x_variant":[
        "\u0160\u0101bikh\u0113l",
        "Sh\u0101b\u012bkh\u0113l",
        "Sh\u0101b\u012bkheyl",
        "\u0634\u0627\u0628\u06cc \u062e\u064a\u0644",
        "\u0634\u0627\u0628\u06cc \u062e\u06d0\u0644",
        "Sh\u0101b\u012b Kh\u0113l"
    ],
    "wof:name":"Shabi Khel",
    "wof:placetype":"locality"
},
  "geometry": {"coordinates":[69.21485,34.97559],"type":"Point"}
}