{
  "type": "Feature",
  "properties": {
    "gn:admin1_code":"09",
    "gn:admin2_code":"2707",
    "gn:asciiname":"Kharzari Sangtu",
    "gn:country_code":"AF",
    "gn:dem":3374,
    "gn:feature_class":"P",
    "gn:feature_code":"PPL",
    "gn:name":"Kh\u0101rzar\u012b Sangt\u016b",
    "gn:population":0,
    "gn:timezone":"Asia/Kabul",
    "iso:country":"AF",
    "name:und_x_variant":[
        "Kh\u0101\u1e5fza\u1e5fi Sangtu",
        "Kharzarisangtu",
        "Kh\u0101rz\u0101r\u012b Sangt\u016b",
        "Kh\u0101rz\u0101r-e Sangtu",
        "Kh\u0101rzar\u012b Sangt\u016b",
        "\u062e\u0627\u0631\u0632\u0631\u06cc \u0633\u0646\u06af\u062a\u0648"
    ],
    "wof:name":"Kharzari Sangtu",
    "wof:placetype":"locality"
},
  "geometry": {"coordinates":[66.48993,34.40796],"type":"Point"}
}