{
  "type": "Feature",
  "properties": {
    "gn:admin1_code":"09",
    "gn:admin2_code":"2705",
    "gn:asciiname":"Pasi Shahr",
    "gn:country_code":"AF",
    "gn:dem":2171,
    "gn:feature_class":"P",
    "gn:feature_code":"PPL",
    "gn:name":"Pas\u012b Shahr",
    "gn:population":0,
    "gn:timezone":"Asia/Kabul",
    "iso:country":"AF",
    "name:und_x_variant":[
        "Pasishakhr",
        "Pas\u012b Shahr",
        "Pasi-\u0161ahr",
        "\u067e\u0633\u06cc \u0634\u0647\u0631",
        "Pas-e Shahr"
    ],
    "wof:name":"Pasi Shahr",
    "wof:placetype":"locality"
},
  "geometry": {"coordinates":[64.37735000000001,33.51111],"type":"Point"}
}