{
  "type": "Feature",
  "properties": {
    "gn:admin1_code":"41",
    "gn:admin2_code":"3408.0",
    "gn:asciiname":"Dahan-e Qut Quti",
    "gn:country_code":"AF",
    "gn:dem":2500,
    "gn:feature_class":"P",
    "gn:feature_code":"PPL",
    "gn:name":"Dahan-e Qut Qut\u012b",
    "gn:population":0,
    "gn:timezone":"Asia/Kabul",
    "iso:country":"AF",
    "name:und_x_variant":[
        "\u1e0eahane Qutqoti",
        "Dakhani-Kutkuti",
        "Dahan-e Qut Qot\u012b",
        "Dahan-e Qotqot\u012b",
        "Dahan-e Qut Qut\u012b",
        "\u062f\u0647\u0646 \u0642\u062a \u0642\u062a\u06cc"
    ],
    "wof:name":"Dahan-e Qut Quti",
    "wof:placetype":"locality"
},
  "geometry": {"coordinates":[66.10316999999999,34.22416],"type":"Point"}
}