{
  "type": "Feature",
  "properties": {
    "gn:admin1_code":"35",
    "gn:admin2_code":"901.0",
    "gn:asciiname":"Shakarman",
    "gn:country_code":"AF",
    "gn:dem":913,
    "gn:feature_class":"P",
    "gn:feature_code":"PPL",
    "gn:name":"Shakarm\u0101n",
    "gn:population":0,
    "gn:timezone":"Asia/Kabul",
    "iso:country":"AF",
    "name:und_x_variant":[
        "\u0160akarm\u0101n",
        "Shakarman",
        "Shakarm\u0101n",
        "\u0634\u06a9\u0631\u0645\u0627\u0646"
    ],
    "wof:name":"Shakarman",
    "wof:placetype":"locality"
},
  "geometry": {"coordinates":[70.14957,34.72178],"type":"Point"}
}