{
  "type": "Feature",
  "properties": {
    "gn:admin1_code":"8",
    "gn:admin2_code":"608.0",
    "gn:asciiname":"Gado Khel",
    "gn:country_code":"AF",
    "gn:dem":1984,
    "gn:feature_class":"P",
    "gn:feature_code":"PPL",
    "gn:name":"Gad\u014d Kh\u0113l",
    "gn:population":0,
    "gn:timezone":"Asia/Kabul",
    "iso:country":"AF",
    "name:rus_x_preferred":[
        "Gadokheyl\u2019"
    ],
    "name:und_x_variant":[
        "Ga\u1e0f\u014dkh\u0113l",
        "Gadow Kheyl",
        "Gad\u014d Kh\u0113l",
        "\u06af\u062f\u0648 \u062e\u06d0\u0644"
    ],
    "wof:name":"Gado Khel",
    "wof:placetype":"locality"
},
  "geometry": {"coordinates":[67.76734,32.80195],"type":"Point"}
}