{
  "type": "Feature",
  "properties": {
    "gn:admin1_code":"06",
    "gn:admin2_code":"2108",
    "gn:asciiname":"Nawbur",
    "gn:country_code":"AF",
    "gn:dem":602,
    "gn:feature_class":"P",
    "gn:feature_code":"PPL",
    "gn:name":"Nawbur",
    "gn:population":0,
    "gn:timezone":"Asia/Kabul",
    "iso:country":"AF",
    "name:fas_x_preferred":[
        "\u0646\u0648\u0628\u0631"
    ],
    "name:und_x_variant":[
        "Naubur",
        "Nawbu\u1e5f",
        "Nowbor",
        "\u0646\u0648\u0628\u0631"
    ],
    "wof:name":"Nawbur",
    "wof:placetype":"locality"
},
  "geometry": {"coordinates":[61.63639000000001,32.25191],"type":"Point"}
}