{
  "type": "Feature",
  "properties": {
    "gn:admin1_code":"28",
    "gn:admin2_code":"2501",
    "gn:asciiname":"Lairu",
    "gn:country_code":"AF",
    "gn:dem":1604,
    "gn:feature_class":"P",
    "gn:feature_code":"PPL",
    "gn:name":"La\u012br\u016b",
    "gn:population":0,
    "gn:timezone":"Asia/Kabul",
    "iso:country":"AF",
    "name:und_x_variant":[
        "La\u012br\u016b",
        "\u0644\u06cc\u0631\u0648",
        "Layru"
    ],
    "wof:name":"Lairu",
    "wof:placetype":"locality"
},
  "geometry": {"coordinates":[66.986,32.15225],"type":"Point"}
}