{
  "type": "Feature",
  "properties": {
    "gn:admin1_code":"27",
    "gn:admin2_code":"409.0",
    "gn:asciiname":"Mushungay",
    "gn:country_code":"AF",
    "gn:dem":2553,
    "gn:feature_class":"P",
    "gn:feature_code":"PPL",
    "gn:name":"Mushungay",
    "gn:population":0,
    "gn:timezone":"Asia/Kabul",
    "iso:country":"AF",
    "name:fas_x_preferred":[
        "\u0645\u0634\u0648\u0646\u06af\u06cc"
    ],
    "name:und_x_variant":[
        "Mo\u0161ungay",
        "Mosh\u016bngay",
        "\u0645\u0634\u0648\u0646\u06af\u06cc",
        "\u0645\u0634\u0646\u06af\u06cc"
    ],
    "wof:name":"Mushungay",
    "wof:placetype":"locality"
},
  "geometry": {"coordinates":[68.29835,33.71927],"type":"Point"}
}