{
  "type": "Feature",
  "properties": {
    "gn:admin1_code":"08",
    "gn:admin2_code":"616",
    "gn:asciiname":"Mullayan",
    "gn:country_code":"AF",
    "gn:dem":2731,
    "gn:feature_class":"P",
    "gn:feature_code":"PPL",
    "gn:name":"Mull\u0101y\u0101n",
    "gn:population":0,
    "gn:timezone":"Asia/Kabul",
    "iso:country":"AF",
    "name:und_x_variant":[
        "Mull\u0101y\u0101n",
        "Moll\u0101y\u0101n",
        "\u0645\u0644\u0627\u06cc\u0627\u0646",
        "Mull\u0101iy\u0101n"
    ],
    "wof:name":"Mullayan",
    "wof:placetype":"locality"
},
  "geometry": {"coordinates":[68.67453,33.66148],"type":"Point"}
}