{
  "type": "Feature",
  "properties": {
    "gn:admin1_code":"5",
    "gn:admin2_code":"2807.0",
    "gn:asciiname":"Darah-ye Bachah",
    "gn:country_code":"AF",
    "gn:dem":3113,
    "gn:feature_class":"P",
    "gn:feature_code":"PPL",
    "gn:name":"Darah-ye Bachah",
    "gn:population":0,
    "gn:timezone":"Asia/Kabul",
    "iso:country":"AF",
    "name:und_x_variant":[
        "\u1e0ea\u1e5f\u1e5fahe Baca",
        "Darreh-ye Bacheh",
        "Darah-ye Bachah",
        "\u062f\u0631\u06c0 \u0628\u0686\u0647"
    ],
    "wof:name":"Darah-ye Bachah",
    "wof:placetype":"locality"
},
  "geometry": {"coordinates":[67.43326999999999,35.05377],"type":"Point"}
}