{
  "type": "Feature",
  "properties": {
    "gn:admin1_code":"23",
    "gn:admin2_code":"2407",
    "gn:asciiname":"Sarwar Karez",
    "gn:country_code":"AF",
    "gn:dem":906,
    "gn:feature_class":"P",
    "gn:feature_code":"PPL",
    "gn:name":"Sarwar K\u0101r\u0113z",
    "gn:population":0,
    "gn:timezone":"Asia/Kabul",
    "iso:country":"AF",
    "name:fas_x_preferred":[
        "\u0633\u0631\u0648\u0631 \u0643\u0627\u0631\u064a\u0632"
    ],
    "name:und_x_variant":[
        "Sa\u1e5fwa\u1e5f K\u0101\u1e5f\u0113z",
        "Sarvarkarez",
        "Sarwar K\u0101r\u0113z",
        "\u0633\u0631\u0648\u0631 \u06a9\u0627\u0631\u06d0\u0632",
        "Sarwar K\u0101r\u012bz"
    ],
    "wof:name":"Sarwar Karez",
    "wof:placetype":"locality"
},
  "geometry": {"coordinates":[65.0592,31.57781],"type":"Point"}
}