{
  "type": "Feature",
  "properties": {
    "gn:admin1_code":"09",
    "gn:admin2_code":"2706",
    "gn:asciiname":"Du Sang-e Khushk",
    "gn:country_code":"AF",
    "gn:dem":2865,
    "gn:feature_class":"P",
    "gn:feature_code":"PPL",
    "gn:name":"D\u016b Sang-e Khushk",
    "gn:population":0,
    "gn:timezone":"Asia/Kabul",
    "iso:country":"AF",
    "name:und_x_variant":[
        "Dosange Khu\u0161k",
        "Dusangi-Khushk",
        "D\u016b Sang-e Khushk",
        "\u062f\u0648 \u0633\u0646\u06af \u062e\u0634\u06a9",
        "Dosang-e Khoshk"
    ],
    "wof:name":"Du Sang-e Khushk",
    "wof:placetype":"locality"
},
  "geometry": {"coordinates":[64.95195,33.65033],"type":"Point"}
}