{
  "type": "Feature",
  "properties": {
    "gn:admin1_code":"35",
    "gn:admin2_code":"903.0",
    "gn:asciiname":"Parwah'i",
    "gn:country_code":"AF",
    "gn:dem":962,
    "gn:feature_class":"P",
    "gn:feature_code":"PPL",
    "gn:name":"Parwah\u2019\u012b",
    "gn:population":0,
    "gn:timezone":"Asia/Kabul",
    "iso:country":"AF",
    "name:und_x_variant":[
        "Parvai",
        "P\u0101rwa\u2019i",
        "Parwah\u2019\u012b",
        "\u067e\u0631\u0648\u0647 \u0626\u06cc"
    ],
    "wof:name":"Parwah'i",
    "wof:placetype":"locality"
},
  "geometry": {"coordinates":[70.37439999999999,34.87108],"type":"Point"}
}