{
  "type": "Feature",
  "properties": {
    "gn:admin1_code":"08",
    "gn:admin2_code":"614",
    "gn:asciiname":"La'liwal",
    "gn:country_code":"AF",
    "gn:dem":2074,
    "gn:feature_class":"P",
    "gn:feature_code":"PPL",
    "gn:name":"La\u2018l\u012bw\u0101l",
    "gn:population":0,
    "gn:timezone":"Asia/Kabul",
    "iso:country":"AF",
    "name:rus_x_preferred":[
        "Lalival\u2019"
    ],
    "name:und_x_variant":[
        "La\u2018liw\u0101l",
        "La\u2018l\u012bv\u0101l",
        "La\u2018l\u012bw\u0101l",
        "\u0644\u0639\u0644\u06cc\u0648\u0627\u0644"
    ],
    "wof:name":"La'liwal",
    "wof:placetype":"locality"
},
  "geometry": {"coordinates":[68.50279,33.32008],"type":"Point"}
}