{
  "type": "Feature",
  "properties": {
    "gn:admin1_code":"23",
    "gn:admin2_code":"2413",
    "gn:asciiname":"Torwam",
    "gn:country_code":"AF",
    "gn:dem":1881,
    "gn:feature_class":"P",
    "gn:feature_code":"PPL",
    "gn:name":"T\u014drw\u0101m",
    "gn:population":0,
    "gn:timezone":"Asia/Kabul",
    "iso:country":"AF",
    "name:pus_x_preferred":[
        "\u062a\u0648\u0631\u0648\u0627\u0645"
    ],
    "name:und_x_variant":[
        "T\u014d\u1e5fw\u0101m",
        "Torvam",
        "T\u014drw\u0101m",
        "\u062a\u0648\u0631\u0648\u0627\u0645",
        "T\u016brw\u0101m"
    ],
    "wof:name":"Torwam",
    "wof:placetype":"locality"
},
  "geometry": {"coordinates":[67.24656999999999,31.56904],"type":"Point"}
}