{
  "type": "Feature",
  "properties": {
    "gn:admin1_code":"37",
    "gn:admin2_code":"3203.0",
    "gn:asciiname":"Walam Kelay",
    "gn:country_code":"AF",
    "gn:dem":1280,
    "gn:feature_class":"P",
    "gn:feature_code":"PPL",
    "gn:name":"Walam K\u00ealay",
    "gn:population":0,
    "gn:timezone":"Asia/Kabul",
    "iso:country":"AF",
    "name:fas_x_preferred":[
        "\u0642\u0631\u064a\u06c0 \u0648\u0644\u0645"
    ],
    "name:und_x_variant":[
        "Valamkalay",
        "Walam K\u00ealay",
        "Walam Kalay",
        "\u0648\u0644\u0645 \u06a9\u0644\u06cc"
    ],
    "wof:name":"Walam Kelay",
    "wof:placetype":"locality"
},
  "geometry": {"coordinates":[69.83169000000001,33.26045999999999],"type":"Point"}
}