{
  "type": "Feature",
  "properties": {
    "gn:admin1_code":"32",
    "gn:admin2_code":"1504",
    "gn:asciiname":"Pay Tawah",
    "gn:country_code":"AF",
    "gn:dem":1415,
    "gn:feature_class":"P",
    "gn:feature_code":"PPL",
    "gn:name":"P\u0101y T\u0101wah",
    "gn:population":0,
    "gn:timezone":"Asia/Kabul",
    "iso:country":"AF",
    "name:und_x_variant":[
        "Pai T\u0101wa",
        "Pai T\u0101wa (3)",
        "P\u0101y T\u0101veh",
        "P\u0101y T\u0101wah",
        "\u067e\u0627\u06cc \u062a\u0627\u0648\u0647"
    ],
    "wof:name":"Pay Tawah",
    "wof:placetype":"locality"
},
  "geometry": {"coordinates":[67.26285,36.05747],"type":"Point"}
}