{
  "type": "Feature",
  "properties": {
    "gn:admin1_code":"27",
    "gn:admin2_code":"407",
    "gn:asciiname":"Kharyan",
    "gn:country_code":"AF",
    "gn:dem":2091,
    "gn:feature_class":"P",
    "gn:feature_code":"PPL",
    "gn:name":"Khary\u0101n",
    "gn:population":0,
    "gn:timezone":"Asia/Kabul",
    "iso:country":"AF",
    "name:rus_x_preferred":[
        "Khar\u2019yan"
    ],
    "name:und_x_variant":[
        "Khery\u0101n",
        "Khary\u0101n",
        "\u062e\u0631\u06cc\u0627\u0646"
    ],
    "wof:name":"Kharyan",
    "wof:placetype":"locality"
},
  "geometry": {"coordinates":[68.73484000000001,34.12417],"type":"Point"}
}