{
  "type": "Feature",
  "properties": {
    "gn:admin1_code":"28",
    "gn:admin2_code":"2509",
    "gn:asciiname":"Garyo Kelay",
    "gn:country_code":"AF",
    "gn:dem":2314,
    "gn:feature_class":"P",
    "gn:feature_code":"PPL",
    "gn:name":"G\u0101\u1e5fy\u014d K\u00ealay",
    "gn:population":0,
    "gn:timezone":"Asia/Kabul",
    "iso:country":"AF",
    "name:rus_x_preferred":[
        "Gar\u2019yukalay"
    ],
    "name:und_x_variant":[
        "\u06af\u0627\u0693\u06cc\u0648 \u06a9\u0644\u06cc",
        "G\u0101ryo Kalay",
        "G\u0101\u1e5fy\u014d K\u00ealay"
    ],
    "wof:name":"Garyo Kelay",
    "wof:placetype":"locality"
},
  "geometry": {"coordinates":[68.00964999999999,32.04299],"type":"Point"}
}