{
  "type": "Feature",
  "properties": {
    "gn:admin1_code":"08",
    "gn:admin2_code":"601",
    "gn:asciiname":"Qarah Baghi",
    "gn:country_code":"AF",
    "gn:dem":2111,
    "gn:feature_class":"P",
    "gn:feature_code":"PPL",
    "gn:name":"Qarah B\u0101gh\u012b",
    "gn:population":0,
    "gn:timezone":"Asia/Kabul",
    "iso:country":"AF",
    "name:fas_x_preferred":[
        "\u0642\u0631\u0647 \u0628\u0627\u063a\u06cc"
    ],
    "name:und_x_variant":[
        "Karabagi",
        "Qa\u1e5fab\u0101ghi",
        "Qarah B\u0101gh\u012b",
        "Qareh B\u0101gh\u012b"
    ],
    "wof:name":"Qarah Baghi",
    "wof:placetype":"locality"
},
  "geometry": {"coordinates":[68.41908000000001,33.42521],"type":"Point"}
}