{
  "type": "Feature",
  "properties": {
    "gn:admin1_code":"38",
    "gn:admin2_code":"3008.0",
    "gn:asciiname":"Tirwat",
    "gn:country_code":"AF",
    "gn:dem":1746,
    "gn:feature_class":"P",
    "gn:feature_code":"PPL",
    "gn:name":"Tirwat",
    "gn:population":0,
    "gn:timezone":"Asia/Kabul",
    "iso:country":"AF",
    "name:und_x_variant":[
        "Tirvat",
        "Tarwat",
        "Te\u1e5fwat",
        "Tirwat",
        "\u062a\u0631\u0648\u062a"
    ],
    "wof:name":"Tirwat",
    "wof:placetype":"locality"
},
  "geometry": {"coordinates":[70.49172,35.00422],"type":"Point"}
}