{
  "type": "Feature",
  "properties": {
    "gn:admin1_code":"34",
    "gn:admin2_code":"1009.0",
    "gn:asciiname":"Awarah",
    "gn:country_code":"AF",
    "gn:dem":1942,
    "gn:feature_class":"P",
    "gn:feature_code":"PPL",
    "gn:name":"Aw\u0101rah",
    "gn:population":0,
    "gn:timezone":"Asia/Kabul",
    "iso:country":"AF",
    "name:und_x_variant":[
        "Avara",
        "Aw\u0101\u1e5fa",
        "Aw\u0101rah",
        "\u0627\u0648\u0627\u0631\u0647"
    ],
    "wof:name":"Awarah",
    "wof:placetype":"locality"
},
  "geometry": {"coordinates":[70.75920000000001,34.87254],"type":"Point"}
}