{
  "type": "Feature",
  "properties": {
    "gn:admin1_code":"41",
    "gn:admin2_code":"3404",
    "gn:asciiname":"Mazar",
    "gn:country_code":"AF",
    "gn:dem":2271,
    "gn:feature_class":"P",
    "gn:feature_code":"PPL",
    "gn:name":"Maz\u0101r",
    "gn:population":0,
    "gn:timezone":"Asia/Kabul",
    "iso:country":"AF",
    "name:ceb_x_preferred":[
        "Mazar"
    ],
    "name:deu_x_preferred":[
        "Mazar"
    ],
    "name:fas_x_preferred":[
        "\u0645\u0632\u0627\u0631"
    ],
    "name:fra_x_preferred":[
        "Mazar"
    ],
    "name:heb_x_preferred":[
        "\u05de\u05d6\u05e8"
    ],
    "name:rus_x_preferred":[
        "\u041c\u0430\u0437\u0430\u0440"
    ],
    "name:swe_x_preferred":[
        "Mazar"
    ],
    "name:und_x_variant":[
        "Maz\u0101r",
        "\u0645\u0632\u0627\u0631"
    ],
    "wof:name":"Mazar",
    "wof:placetype":"locality"
},
  "geometry": {"coordinates":[65.27842,33.35877],"type":"Point"}
}