{
  "type": "Feature",
  "properties": {
    "gn:admin1_code":"1",
    "gn:admin2_code":"1108.0",
    "gn:asciiname":"Baharak",
    "gn:country_code":"AF",
    "gn:dem":1552,
    "gn:feature_class":"P",
    "gn:feature_code":"PPLA2",
    "gn:name":"Bah\u0101rak",
    "gn:population":0,
    "gn:timezone":"Asia/Kabul",
    "iso:country":"AF",
    "name:ben_x_preferred":[
        "\u09ac\u09be\u09b9\u09be\u09b0\u0995"
    ],
    "name:fas_x_preferred":[
        "\u0628\u0647\u0627\u0631\u06a9"
    ],
    "name:pol_x_preferred":[
        "Baharak"
    ],
    "name:por_x_preferred":[
        "Baharak"
    ],
    "name:und_x_variant":[
        "Bekharek",
        "Barak",
        "Becharek",
        "Bah\u0101rak",
        "Bakharak",
        "Bah\u0101rest\u0101n",
        "Bagorak",
        "Bah\u0101rist\u0101n"
    ],
    "wof:name":"Baharak",
    "wof:placetype":"locality"
},
  "geometry": {"coordinates":[70.90664,37.00254],"type":"Point"}
}