{
  "type": "Feature",
  "properties": {
    "gn:admin1_code":"29",
    "gn:admin2_code":"2902.0",
    "gn:asciiname":"Khayr Kot",
    "gn:country_code":"AF",
    "gn:dem":2126,
    "gn:feature_class":"P",
    "gn:feature_code":"PPLA2",
    "gn:name":"Khayr K\u014d\u1e6f",
    "gn:population":0,
    "gn:timezone":"Asia/Kabul",
    "iso:country":"AF",
    "name:fas_x_preferred":[
        "Khayr K\u014d\u1e6f"
    ],
    "name:fas_x_variant":[
        "\u062e\u06cc\u0631 \u06a9\u0648\u067c"
    ],
    "name:und_x_variant":[
        "Khayrkot",
        "Kheyr K\u016bt",
        "\u062e\u06cc\u0631 \u06a9\u0648\u062a"
    ],
    "wof:name":"Khayr Kot",
    "wof:placetype":"locality"
},
  "geometry": {"coordinates":[68.44971,32.85355],"type":"Point"}
}