{
  "type": "Feature",
  "properties": {
    "gn:admin1_code":"03",
    "gn:admin2_code":"1303",
    "gn:asciiname":"Qal'ah-ye Murad",
    "gn:country_code":"AF",
    "gn:dem":2029,
    "gn:feature_class":"P",
    "gn:feature_code":"PPL",
    "gn:name":"Qal\u2018ah-ye Mur\u0101d",
    "gn:population":0,
    "gn:timezone":"Asia/Kabul",
    "iso:country":"AF",
    "name:und_x_variant":[
        "Qal\u2018a-i-Mo\u1e5f\u0101\u1e0f",
        "Qal\u2018eh-ye Mor\u0101d",
        "Qal\u2018ah-ye Mur\u0101d",
        "\u0642\u0644\u0639\u06c0 \u0645\u0631\u0627\u062f"
    ],
    "wof:name":"Qal'ah-ye Murad",
    "wof:placetype":"locality"
},
  "geometry": {"coordinates":[68.2847,35.72396],"type":"Point"}
}