{
  "type": "Feature",
  "properties": {
    "gn:admin1_code":"41",
    "gn:admin2_code":"3408.0",
    "gn:asciiname":"Safed Sang",
    "gn:country_code":"AF",
    "gn:dem":2399,
    "gn:feature_class":"P",
    "gn:feature_code":"PPL",
    "gn:name":"Saf\u0113d Sang",
    "gn:population":0,
    "gn:timezone":"Asia/Kabul",
    "iso:country":"AF",
    "name:und_x_variant":[
        "Sef\u0113\u1e0fsang",
        "Safedsang",
        "Safayd Sang",
        "Sef\u012bdsang",
        "Saf\u0113d Sang",
        "\u0633\u0641\u064a\u062f \u0633\u0646\u06af"
    ],
    "wof:name":"Safed Sang",
    "wof:placetype":"locality"
},
  "geometry": {"coordinates":[66.16273000000001,34.22121],"type":"Point"}
}