{
  "type": "Feature",
  "properties": {
    "gn:admin1_code":"08",
    "gn:admin2_code":"618",
    "gn:asciiname":"Shaykh Muhammad Kala",
    "gn:country_code":"AF",
    "gn:dem":2235,
    "gn:feature_class":"P",
    "gn:feature_code":"PPL",
    "gn:name":"Shaykh Mu\u1e29ammad Kal\u0101",
    "gn:population":0,
    "gn:timezone":"Asia/Kabul",
    "iso:country":"AF",
    "name:fas_x_preferred":[
        "\u0642\u0644\u0639\u0647\u0654 \u0634\u064a\u062e \u0645\u062d\u0645\u062f"
    ],
    "name:und_x_variant":[
        "\u0160aykhmohammed Kal\u0101",
        "Sheykhmukhammed-Kala",
        "\u0160aykhmohammad Kal\u0101",
        "S\u0304aykhmo\u1e29\u1e0f Kal\u0101",
        "Sh\u0113kh Mu\u1e29ammad Kal\u0101",
        "Sheykh Mo\u1e29ammad Kal\u0101",
        "Shaykh Mu\u1e29ammad Kal\u0101",
        "\u0634\u064a\u062e \u0645\u062d\u0645\u062f \u06a9\u0644\u0627"
    ],
    "wof:name":"Shaykh Muhammad Kala",
    "wof:placetype":"locality"
},
  "geometry": {"coordinates":[68.29576,33.4069],"type":"Point"}
}