{
  "type": "Feature",
  "properties": {
    "gn:admin1_code":"07",
    "gn:admin2_code":"1804",
    "gn:asciiname":"Gham Chin",
    "gn:country_code":"AF",
    "gn:dem":991,
    "gn:feature_class":"P",
    "gn:feature_code":"PPL",
    "gn:name":"Gham Ch\u012bn",
    "gn:population":0,
    "gn:timezone":"Asia/Kabul",
    "iso:country":"AF",
    "name:und_x_variant":[
        "Ghamcin",
        "Gham Ch\u012bn",
        "\u063a\u0645 \u0686\u06cc\u0646"
    ],
    "wof:name":"Gham Chin",
    "wof:placetype":"locality"
},
  "geometry": {"coordinates":[64.06441,35.66985],"type":"Point"}
}