{
  "type": "Feature",
  "properties": {
    "gn:admin1_code":"23",
    "gn:admin2_code":"2407.0",
    "gn:asciiname":"Khaugani",
    "gn:country_code":"AF",
    "gn:dem":901,
    "gn:feature_class":"P",
    "gn:feature_code":"PPL",
    "gn:name":"Khaugani",
    "gn:population":0,
    "gn:timezone":"Asia/Kabul",
    "iso:country":"AF",
    "name:rus_x_preferred":[
        "Khug\u2019ini"
    ],
    "name:und_x_variant":[
        "Kh\u016bgy\u0101\u1e49i",
        "Khaugani",
        "Khowg\u0101n\u012b",
        "\u062e\u0648\u06af\u0627\u0646\u06cc",
        "Khawg\u0101ni",
        "Kh\u016bg\u012b\u0101n\u012b",
        "\u062e\u0648\u06af\u06cc\u0627\u06bc\u06cc"
    ],
    "wof:name":"Khaugani",
    "wof:placetype":"locality"
},
  "geometry": {"coordinates":[64.92246999999999,31.64459],"type":"Point"}
}