{
  "type": "Feature",
  "properties": {
    "gn:admin1_code":"13",
    "gn:admin2_code":"105.0",
    "gn:asciiname":"Qal'ah-ye Saman",
    "gn:country_code":"AF",
    "gn:dem":1501,
    "gn:feature_class":"P",
    "gn:feature_code":"PPL",
    "gn:name":"Qal\u2018ah-ye S\u0101m\u0101n",
    "gn:population":0,
    "gn:timezone":"Asia/Kabul",
    "iso:country":"AF",
    "name:und_x_variant":[
        "Kalasaman",
        "Qal\u2018a S\u0101m\u0101n",
        "Qal\u2018eh-ye S\u0101m\u0101n",
        "\u0642\u0644\u0639\u06c0 \u0633\u0627\u0645\u0627\u0646",
        "Qal\u2018ah-ye S\u0101m\u0101n"
    ],
    "wof:name":"Qal'ah-ye Saman",
    "wof:placetype":"locality"
},
  "geometry": {"coordinates":[69.22013000000001,34.8677],"type":"Point"}
}