{
  "type": "Feature",
  "properties": {
    "gn:admin1_code":"35",
    "gn:admin2_code":"903.0",
    "gn:asciiname":"Daman",
    "gn:country_code":"AF",
    "gn:dem":799,
    "gn:feature_class":"P",
    "gn:feature_code":"PPL",
    "gn:name":"D\u0101m\u0101n",
    "gn:population":0,
    "gn:timezone":"Asia/Kabul",
    "iso:country":"AF",
    "name:ara_x_preferred":[
        "\u062f\u0627\u0645\u0627\u0646"
    ],
    "name:ben_x_preferred":[
        "\u09a6\u09ae\u09a8"
    ],
    "name:bpy_x_preferred":[
        "\u09a6\u09ae\u09a8"
    ],
    "name:cat_x_preferred":[
        "Daman"
    ],
    "name:ceb_x_preferred":[
        "Daman"
    ],
    "name:deu_x_preferred":[
        "Daman"
    ],
    "name:ell_x_preferred":[
        "\u039d\u03c4\u03b1\u03bc\u03ac\u03bd"
    ],
    "name:fra_x_preferred":[
        "Daman"
    ],
    "name:heb_x_preferred":[
        "\u05d3\u05d0\u05de\u05d0\u05df"
    ],
    "name:nld_x_preferred":[
        "Daman"
    ],
    "name:sat_x_preferred":[
        "\u1c70\u1c5f\u1c62\u1c5a\u1c71"
    ],
    "name:slk_x_preferred":[
        "Daman"
    ],
    "name:swe_x_preferred":[
        "Daman"
    ],
    "name:tur_x_preferred":[
        "Daman"
    ],
    "name:und_x_variant":[
        "\u062f\u0627\u0645\u0627\u0646",
        "\u1e0e\u0101m\u0101n",
        "D\u0101m\u0101n"
    ],
    "wof:name":"Daman",
    "wof:placetype":"locality"
},
  "geometry": {"coordinates":[70.28278,34.71972],"type":"Point"}
}