{
  "type": "Feature",
  "properties": {
    "gn:admin1_code":"35",
    "gn:admin2_code":"903.0",
    "gn:asciiname":"Daman",
    "gn:country_code":"AF",
    "gn:dem":799,
    "gn:feature_class":"P",
    "gn:feature_code":"PPL",
    "gn:name":"D\u0101m\u0101n",
    "gn:population":0,
    "gn:timezone":"Asia/Kabul",
    "iso:country":"AF",
    "name:und_x_variant":[
        "\u062f\u0627\u0645\u0627\u0646",
        "\u1e0e\u0101m\u0101n",
        "D\u0101m\u0101n"
    ],
    "wof:name":"Daman",
    "wof:placetype":"locality"
},
  "geometry": {"coordinates":[70.28278,34.71972],"type":"Point"}
}