{
  "type": "Feature",
  "properties": {
    "gn:admin1_code":"28",
    "gn:admin2_code":"2509.0",
    "gn:asciiname":"Hajji Bowyen",
    "gn:cc2":"AF",
    "gn:country_code":"AF",
    "gn:dem":2258,
    "gn:feature_class":"P",
    "gn:feature_code":"PPL",
    "gn:name":"\u1e28\u0101jj\u012b Bowyen",
    "gn:population":0,
    "gn:timezone":"Asia/Kabul",
    "iso:country":"AF",
    "name:und_x_variant":[
        "H\u0101ji Bayan",
        "\u1e28\u0101jj\u012b Bowyen"
    ],
    "wof:name":"Hajji Bowyen",
    "wof:placetype":"locality"
},
  "geometry": {"coordinates":[67.99972,31.98333],"type":"Point"}
}