{
  "type": "Feature",
  "properties": {
    "gn:admin1_code":"30",
    "gn:admin2_code":"1612",
    "gn:asciiname":"Kul Timar",
    "gn:country_code":"AF",
    "gn:dem":346,
    "gn:feature_class":"P",
    "gn:feature_code":"PPL",
    "gn:name":"Kul Timar",
    "gn:population":0,
    "gn:timezone":"Asia/Kabul",
    "iso:country":"AF",
    "name:fas_x_preferred":[
        "\u06a9\u0648\u0644 \u062a\u0645\u0631"
    ],
    "name:rus_x_preferred":[
        "\u041a\u0443\u043b\u044c\u0442\u0438\u043c\u0430\u0440"
    ],
    "name:und_x_variant":[
        "Kul\u2019timar",
        "Kul Temar",
        "Kul Timar",
        "\u06a9\u0644 \u062a\u0645\u0631"
    ],
    "wof:name":"Kul Timar",
    "wof:placetype":"locality"
},
  "geometry": {"coordinates":[66.99173,36.75074],"type":"Point"}
}