{
  "type": "Feature",
  "properties": {
    "gn:admin1_code":"08",
    "gn:admin2_code":"604",
    "gn:asciiname":"Zard Talah",
    "gn:country_code":"AF",
    "gn:dem":2888,
    "gn:feature_class":"P",
    "gn:feature_code":"PPL",
    "gn:name":"Zard Talah",
    "gn:population":0,
    "gn:timezone":"Asia/Kabul",
    "iso:country":"AF",
    "name:rus_x_preferred":[
        "\u0417\u0430\u0440\u0434\u0442\u0430\u043b\u0430"
    ],
    "name:und_x_variant":[
        "Zardtala",
        "Za\u1e5f\u1e0ftala",
        "Zard Talah",
        "\u0632\u0631\u062f \u062a\u0644\u0647"
    ],
    "wof:name":"Zard Talah",
    "wof:placetype":"locality"
},
  "geometry": {"coordinates":[67.52559000000001,33.95587],"type":"Point"}
}