{
  "type": "Feature",
  "properties": {
    "gn:admin1_code":"27",
    "gn:admin2_code":"404.0",
    "gn:asciiname":"Qafzar",
    "gn:country_code":"AF",
    "gn:dem":3053,
    "gn:feature_class":"P",
    "gn:feature_code":"PPL",
    "gn:name":"Qafz\u0101r",
    "gn:population":0,
    "gn:timezone":"Asia/Kabul",
    "iso:country":"AF",
    "name:und_x_variant":[
        "Kafzar",
        "Qafz\u0101r",
        "\u0642\u0641\u0632\u0627\u0631"
    ],
    "wof:name":"Qafzar",
    "wof:placetype":"locality"
},
  "geometry": {"coordinates":[67.83774,34.53659],"type":"Point"}
}