{
  "type": "Feature",
  "properties": {
    "gn:admin1_code":"10",
    "gn:admin2_code":"2303.0",
    "gn:asciiname":"Kaka Khel",
    "gn:country_code":"AF",
    "gn:dem":986,
    "gn:feature_class":"P",
    "gn:feature_code":"PPL",
    "gn:name":"K\u0101k\u0101 Kh\u0113l",
    "gn:population":0,
    "gn:timezone":"Asia/Kabul",
    "iso:country":"AF",
    "name:fas_x_preferred":[
        "\u06a9\u0627\u06a9\u0627\u062e\u06cc\u0644"
    ],
    "name:fra_x_preferred":[
        "Kaka Khel"
    ],
    "name:rus_x_preferred":[
        "Kakakheyl\u2019"
    ],
    "name:und_x_variant":[
        "K\u0101k\u0101 Kh\u0113l",
        "\u06a9\u0627\u06a9\u0627 \u062e\u06d0\u0644",
        "K\u0101k\u0101 Kheyl"
    ],
    "name:urd_x_preferred":[
        "\u06a9\u0627\u06a9\u0627\u062e\u06cc\u0644"
    ],
    "wof:name":"Kaka Khel",
    "wof:placetype":"locality"
},
  "geometry": {"coordinates":[65.07856,32.35502],"type":"Point"}
}