{
  "type": "Feature",
  "properties": {
    "gn:admin1_code":"01",
    "gn:admin2_code":"1102",
    "gn:asciiname":"Khwajah Bagh",
    "gn:country_code":"AF",
    "gn:dem":1714,
    "gn:feature_class":"P",
    "gn:feature_code":"PPL",
    "gn:name":"Khw\u0101jah B\u0101gh",
    "gn:population":0,
    "gn:timezone":"Asia/Kabul",
    "iso:country":"AF",
    "name:und_x_variant":[
        "Kh\u014djab\u0101gh",
        "Khv\u0101jeh B\u0101gh",
        "Khw\u0101jah B\u0101gh",
        "\u062e\u0648\u0627\u062c\u0647 \u0628\u0627\u063a"
    ],
    "wof:name":"Khwajah Bagh",
    "wof:placetype":"locality"
},
  "geometry": {"coordinates":[70.16239,36.63204],"type":"Point"}
}