{
  "type": "Feature",
  "properties": {
    "gn:admin1_code":"9",
    "gn:admin2_code":"2707.0",
    "gn:asciiname":"Besarak-e Sufla",
    "gn:country_code":"AF",
    "gn:dem":2989,
    "gn:feature_class":"P",
    "gn:feature_code":"PPL",
    "gn:name":"B\u0113sarak-e Sufl\u00e1",
    "gn:population":0,
    "gn:timezone":"Asia/Kabul",
    "iso:country":"AF",
    "name:und_x_variant":[
        "B\u0113sa\u1e5fake Sufl\u0101",
        "Besaraki-Sufla",
        "Baysarak-e Sufl\u00e1",
        "B\u012b Sarak-e Sofl\u00e1",
        "B\u0113sarak-e Sufl\u00e1",
        "\u0628\u06cc\u0633\u0631\u06a9 \u0633\u0641\u0644\u0649"
    ],
    "wof:name":"Besarak-e Sufla",
    "wof:placetype":"locality"
},
  "geometry": {"coordinates":[66.14062,34.44008],"type":"Point"}
}