{
  "type": "Feature",
  "properties": {
    "gn:admin1_code":"27",
    "gn:admin2_code":"406",
    "gn:asciiname":"Faqiray",
    "gn:country_code":"AF",
    "gn:dem":2237,
    "gn:feature_class":"P",
    "gn:feature_code":"PPL",
    "gn:name":"Faq\u012bray",
    "gn:population":0,
    "gn:timezone":"Asia/Kabul",
    "iso:country":"AF",
    "name:und_x_variant":[
        "Faqi\u1e5fay",
        "Fakiray",
        "Faq\u012br\u012b",
        "Faq\u012bray",
        "\u0641\u0642\u06cc\u0631\u06cc"
    ],
    "wof:name":"Faqiray",
    "wof:placetype":"locality"
},
  "geometry": {"coordinates":[68.53764,34.09075],"type":"Point"}
}