{
  "type": "Feature",
  "properties": {
    "gn:admin1_code":"01",
    "gn:admin2_code":"1101.0",
    "gn:asciiname":"Angarah-ye Kalan",
    "gn:country_code":"AF",
    "gn:dem":2089,
    "gn:feature_class":"P",
    "gn:feature_code":"PPL",
    "gn:name":"Ang\u0101rah-ye Kal\u0101n",
    "gn:population":0,
    "gn:timezone":"Asia/Kabul",
    "iso:country":"AF",
    "name:und_x_variant":[
        "Ang\u0101\u1e5fa-i-Kalan",
        "\u0627\u0646\u06af\u0627\u0631\u0647 \u06a9\u0644\u0627\u0646",
        "Ang\u0101rah-e Kalan",
        "Ang\u0101rah-ye Kal\u0101n"
    ],
    "wof:name":"Angarah-ye Kalan",
    "wof:placetype":"locality"
},
  "geometry": {"coordinates":[70.56229,37.28748],"type":"Point"}
}