{
  "type": "Feature",
  "properties": {
    "gn:admin1_code":"23",
    "gn:admin2_code":"2413.0",
    "gn:asciiname":"Dangar",
    "gn:country_code":"AF",
    "gn:dem":1793,
    "gn:feature_class":"P",
    "gn:feature_code":"PPL",
    "gn:name":"\u1e0eangar",
    "gn:population":0,
    "gn:timezone":"Asia/Kabul",
    "iso:country":"AF",
    "name:fas_x_preferred":[
        "\u062f\u0646\u06af\u0631"
    ],
    "name:pus_x_preferred":[
        "\u0689\u0646\u06af\u0631"
    ],
    "name:und_x_variant":[
        "K\u0101\u1e5f\u0113z",
        "\u1e0eangar",
        "\u0689\u0646\u06af\u0631",
        "Danga\u1e5f",
        "K\u0101r\u0113z",
        "\u06a9\u0627\u0631\u06d0\u0632"
    ],
    "wof:name":"Dangar",
    "wof:placetype":"locality"
},
  "geometry": {"coordinates":[67.17219,31.57219000000001],"type":"Point"}
}