{
  "type": "Feature",
  "properties": {
    "gn:admin1_code":"9",
    "gn:admin2_code":"2702.0",
    "gn:asciiname":"Dahan-e Ghok",
    "gn:country_code":"AF",
    "gn:dem":1778,
    "gn:feature_class":"P",
    "gn:feature_code":"PPL",
    "gn:name":"Dahan-e Gh\u014dk",
    "gn:population":0,
    "gn:timezone":"Asia/Kabul",
    "iso:country":"AF",
    "name:und_x_variant":[
        "Dakhani-Gok",
        "\u1e0eahane Gh\u014dk",
        "Dahan-e Ghowk",
        "Dahan-e Gh\u016bk",
        "Dahan-e Gh\u014dk",
        "\u062f\u0647\u0646 \u063a\u0648\u06a9",
        "Dahanah-ye Ghowak",
        "\u062f\u0647\u0646\u0647 \u063a\u0648\u06a9"
    ],
    "wof:name":"Dahan-e Ghok",
    "wof:placetype":"locality"
},
  "geometry": {"coordinates":[64.36629000000001,34.38091],"type":"Point"}
}