{
  "type": "Feature",
  "properties": {
    "gn:admin1_code":"41",
    "gn:admin2_code":"3407.0",
    "gn:asciiname":"Darah",
    "gn:country_code":"AF",
    "gn:dem":2757,
    "gn:feature_class":"P",
    "gn:feature_code":"PPL",
    "gn:name":"Darah",
    "gn:population":0,
    "gn:timezone":"Asia/Kabul",
    "iso:country":"AF",
    "name:ceb_x_preferred":[
        "Darah"
    ],
    "name:swe_x_preferred":[
        "Darah"
    ],
    "name:und_x_variant":[
        "Da\u1e5fa",
        "Darah",
        "\u1e0earah",
        "\u062f\u0631\u0647"
    ],
    "wof:name":"Darah",
    "wof:placetype":"locality"
},
  "geometry": {"coordinates":[66.7431,33.92865],"type":"Point"}
}