{
  "type": "Feature",
  "properties": {
    "gn:admin1_code":"1",
    "gn:admin2_code":"1108.0",
    "gn:asciiname":"Baharestan",
    "gn:cc2":"AF",
    "gn:country_code":"AF",
    "gn:dem":1443,
    "gn:feature_class":"P",
    "gn:feature_code":"PPL",
    "gn:name":"Bah\u0101rest\u0101n",
    "gn:population":0,
    "gn:timezone":"Asia/Kabul",
    "iso:country":"AF",
    "name:ben_x_preferred":[
        "\u09ac\u09be\u09b9\u09be\u09b0\u09c7\u09b8\u09cd\u09a4\u09be\u09a8"
    ],
    "name:fas_x_preferred":[
        "Bah\u0101rest\u0101n"
    ],
    "name:por_x_preferred":[
        "Baharestan"
    ],
    "name:pus_x_preferred":[
        "Bah\u0101rak"
    ],
    "name:und_x_variant":[
        "Barak",
        "Bagorak",
        "Bah\u0101rak",
        "Bakharak"
    ],
    "wof:name":"Baharestan",
    "wof:placetype":"locality"
},
  "geometry": {"coordinates":[70.88333,36.98333],"type":"Point"}
}