{
  "type": "Feature",
  "properties": {
    "gn:admin1_code":"35",
    "gn:admin2_code":"904",
    "gn:asciiname":"Zvane",
    "gn:country_code":"AF",
    "gn:dem":2142,
    "gn:feature_class":"P",
    "gn:feature_code":"PPL",
    "gn:name":"Zvane",
    "gn:population":0,
    "gn:timezone":"Asia/Kabul",
    "iso:country":"AF",
    "name:und_x_variant":[
        "\u017dw\u0101n\u0113",
        "Zvane",
        "Zhw\u0101n\u0113",
        "Zhw\u0101\u1e49\u0113",
        "\u0698\u0648\u0627\u06bc\u06d0"
    ],
    "wof:name":"Zvane",
    "wof:placetype":"locality"
},
  "geometry": {"coordinates":[70.14086999999999,35.00594],"type":"Point"}
}