{
  "type": "Feature",
  "properties": {
    "gn:admin1_code":"09",
    "gn:admin2_code":"2705",
    "gn:asciiname":"Kham-e Zard",
    "gn:country_code":"AF",
    "gn:dem":2149,
    "gn:feature_class":"P",
    "gn:feature_code":"PPL",
    "gn:name":"Kham-e Zard",
    "gn:population":0,
    "gn:timezone":"Asia/Kabul",
    "iso:country":"AF",
    "name:und_x_variant":[
        "Khami-Zard",
        "Kham-e Zard",
        "\u062e\u0645 \u0632\u0631\u062f"
    ],
    "wof:name":"Kham-e Zard",
    "wof:placetype":"locality"
},
  "geometry": {"coordinates":[64.40174,33.52106],"type":"Point"}
}