{
  "type": "Feature",
  "properties": {
    "gn:admin1_code":"34",
    "gn:admin2_code":"1011.0",
    "gn:asciiname":"Bar Narang",
    "gn:country_code":"AF",
    "gn:dem":778,
    "gn:feature_class":"P",
    "gn:feature_code":"PPL",
    "gn:name":"Bar Narang",
    "gn:population":0,
    "gn:timezone":"Asia/Kabul",
    "iso:country":"AF",
    "name:fas_x_preferred":[
        "\u0628\u0631 \u0646\u0631\u0646\u06af"
    ],
    "name:und_x_variant":[
        "Ba\u1e5f Na\u1e5fang"
    ],
    "wof:name":"Bar Narang",
    "wof:placetype":"locality"
},
  "geometry": {"coordinates":[71.06874999999999,34.76405],"type":"Point"}
}