{
  "type": "Feature",
  "properties": {
    "gn:admin1_code":"31",
    "gn:admin2_code":"1701",
    "gn:asciiname":"Qarah Bo'in",
    "gn:country_code":"AF",
    "gn:dem":369,
    "gn:feature_class":"P",
    "gn:feature_code":"PPL",
    "gn:name":"Qarah B\u014d\u2019\u012bn",
    "gn:population":0,
    "gn:timezone":"Asia/Kabul",
    "iso:country":"AF",
    "name:und_x_variant":[
        "Qara Boyen",
        "Qareh Boyen",
        "Qarah B\u014d\u2019\u012bn",
        "\u0642\u0631\u0647 \u0628\u0648\u0626\u06cc\u0646"
    ],
    "wof:name":"Qarah Bo'in",
    "wof:placetype":"locality"
},
  "geometry": {"coordinates":[65.83289000000001,36.62593],"type":"Point"}
}