{
  "type": "Feature",
  "properties": {
    "gn:admin1_code":"06",
    "gn:admin2_code":"2106",
    "gn:asciiname":"Karez-e Tapah",
    "gn:country_code":"AF",
    "gn:dem":946,
    "gn:feature_class":"P",
    "gn:feature_code":"PPL",
    "gn:name":"K\u0101r\u0113z-e Tapah",
    "gn:population":0,
    "gn:timezone":"Asia/Kabul",
    "iso:country":"AF",
    "name:und_x_variant":[
        "K\u0101r\u012bz-e Tapa",
        "K\u0101r\u0113ze Tapa",
        "K\u0101r\u012bz-e Tappeh",
        "K\u0101r\u0113z-e Tapah",
        "\u06a9\u0627\u0631\u06d0\u0632 \u062a\u067e\u0647"
    ],
    "wof:name":"Karez-e Tapah",
    "wof:placetype":"locality"
},
  "geometry": {"coordinates":[61.87908,32.90842],"type":"Point"}
}