{
  "type": "Feature",
  "properties": {
    "gn:admin1_code":"10",
    "gn:admin2_code":"2302",
    "gn:asciiname":"Kakaran",
    "gn:country_code":"AF",
    "gn:dem":835,
    "gn:feature_class":"P",
    "gn:feature_code":"PPL",
    "gn:name":"Kakaran",
    "gn:population":0,
    "gn:timezone":"Asia/Kabul",
    "iso:country":"AF",
    "name:fas_x_preferred":[
        "\u06a9\u06a9\u0631\u0627\u0646"
    ],
    "name:msa_x_preferred":[
        "Kakaran"
    ],
    "name:und_x_variant":[
        "K\u0101ka\u1e5f\u0101n",
        "\u06a9\u0627\u06a9\u0693\u0627\u0646",
        "K\u0101kar\u0101n"
    ],
    "wof:name":"Kakaran",
    "wof:placetype":"locality"
},
  "geometry": {"coordinates":[64.64440999999999,31.84721],"type":"Point"}
}