{
  "type": "Feature",
  "properties": {
    "gn:admin1_code":"05",
    "gn:admin2_code":"2801",
    "gn:asciiname":"Dashtak",
    "gn:country_code":"AF",
    "gn:dem":2842,
    "gn:feature_class":"P",
    "gn:feature_code":"PPL",
    "gn:name":"Dashtak",
    "gn:population":0,
    "gn:timezone":"Asia/Kabul",
    "iso:country":"AF",
    "name:ceb_x_preferred":[
        "Dashtak"
    ],
    "name:swe_x_preferred":[
        "Dashtak"
    ],
    "name:und_x_variant":[
        "Da\u0161tak",
        "Dashtak",
        "\u062f\u0634\u062a\u06a9"
    ],
    "wof:name":"Dashtak",
    "wof:placetype":"locality"
},
  "geometry": {"coordinates":[67.81849,34.75598],"type":"Point"}
}