{
  "type": "Feature",
  "properties": {
    "gn:admin1_code":"41",
    "gn:admin2_code":"3409.0",
    "gn:asciiname":"Bakhbi",
    "gn:country_code":"AF",
    "gn:dem":2189,
    "gn:feature_class":"P",
    "gn:feature_code":"PPL",
    "gn:name":"B\u0101khb\u012b",
    "gn:population":0,
    "gn:timezone":"Asia/Kabul",
    "iso:country":"AF",
    "name:und_x_variant":[
        "B\u0101khb\u012b",
        "\u0628\u0627\u062e\u0628\u06cc",
        "B\u0101khbi"
    ],
    "wof:name":"Bakhbi",
    "wof:placetype":"locality"
},
  "geometry": {"coordinates":[66.6742,33.74952],"type":"Point"}
}