{
  "type": "Feature",
  "properties": {
    "gn:admin1_code":"26",
    "gn:admin2_code":"1204",
    "gn:asciiname":"Yakah Tut",
    "gn:country_code":"AF",
    "gn:dem":1542,
    "gn:feature_class":"P",
    "gn:feature_code":"PPL",
    "gn:name":"Yakah T\u016bt",
    "gn:population":0,
    "gn:timezone":"Asia/Kabul",
    "iso:country":"AF",
    "name:rus_x_preferred":[
        "\u042f\u043a\u043a\u0430\u0442\u0443\u0442"
    ],
    "name:und_x_variant":[
        "Yaka T\u016bt",
        "Yakkeh T\u016bt",
        "Yakkatut",
        "Yekkeh T\u016bt",
        "Yakah T\u016bt",
        "\u06cc\u06a9\u0647 \u062a\u0648\u062a"
    ],
    "wof:name":"Yakah Tut",
    "wof:placetype":"locality"
},
  "geometry": {"coordinates":[69.54600000000001,36.58047],"type":"Point"}
}