{
  "type": "Feature",
  "properties": {
    "gn:admin1_code":"26",
    "gn:admin2_code":"1201.0",
    "gn:asciiname":"Dahan-e Shorab",
    "gn:country_code":"AF",
    "gn:dem":817,
    "gn:feature_class":"P",
    "gn:feature_code":"PPL",
    "gn:name":"Dah\u0101n-e Sh\u014dr\u0101b",
    "gn:population":0,
    "gn:timezone":"Asia/Kabul",
    "iso:country":"AF",
    "name:fas_x_preferred":[
        "\u062f\u0647\u0646\u06c0 \u0634\u0648\u0631\u0627\u0628"
    ],
    "name:rus_x_preferred":[
        "\u0414\u0430\u0445\u0430\u043d\u0438-\u0428\u043e\u0440\u0430\u0431"
    ],
    "name:und_x_variant":[
        "Dakhani-Shorab",
        "Dahan-e Sh\u016br\u0101b",
        "Dahan-i-\u0160or\u0101b",
        "Dahaneh-ye Sh\u016br\u0101b",
        "Dah\u0101n-e Sh\u014dr\u0101b",
        "\u062f\u0647\u0627\u0646 \u0634\u0648\u0631\u0627\u0628"
    ],
    "wof:name":"Dahan-e Shorab",
    "wof:placetype":"locality"
},
  "geometry": {"coordinates":[69.55365,36.71913],"type":"Point"}
}