{
  "type": "Feature",
  "properties": {
    "gn:admin1_code":"34",
    "gn:admin2_code":"1010.0",
    "gn:asciiname":"Landay Gal",
    "gn:country_code":"AF",
    "gn:dem":1661,
    "gn:feature_class":"P",
    "gn:feature_code":"PPL",
    "gn:name":"Lan\u1e0fay Gal",
    "gn:population":0,
    "gn:timezone":"Asia/Kabul",
    "iso:country":"AF",
    "name:fas_x_preferred":[
        "\u0644\u0646\u062f\u06af\u0644"
    ],
    "name:rus_x_preferred":[
        "Landigal\u2019"
    ],
    "name:und_x_variant":[
        "Lan\u1e0f\u012b Gal",
        "Lan\u1e0fay Gal",
        "\u0644\u0646\u0689\u06cc \u06af\u0644"
    ],
    "wof:name":"Landay Gal",
    "wof:placetype":"locality"
},
  "geometry": {"coordinates":[70.91710999999999,34.86947],"type":"Point"}
}