{
  "type": "Feature",
  "properties": {
    "gn:admin1_code":"09",
    "gn:admin2_code":"2710",
    "gn:asciiname":"Shah Joy",
    "gn:country_code":"AF",
    "gn:dem":2489,
    "gn:feature_class":"P",
    "gn:feature_code":"PPL",
    "gn:name":"Sh\u0101h J\u014dy",
    "gn:population":0,
    "gn:timezone":"Asia/Kabul",
    "iso:country":"AF",
    "name:und_x_variant":[
        "\u0160\u0101hjoy",
        "Shakhdzhoy",
        "Sh\u0101hj\u016by",
        "Sh\u0101h J\u014dy",
        "\u0634\u0627\u0647 \u062c\u0648\u06cc"
    ],
    "wof:name":"Shah Joy",
    "wof:placetype":"locality"
},
  "geometry": {"coordinates":[64.64180999999999,34.00854],"type":"Point"}
}