{
  "type": "Feature",
  "properties": {
    "gn:admin1_code":"27",
    "gn:admin2_code":"404",
    "gn:asciiname":"Degtor",
    "gn:country_code":"AF",
    "gn:dem":2933,
    "gn:feature_class":"P",
    "gn:feature_code":"PPL",
    "gn:name":"D\u0113gt\u014dr",
    "gn:population":0,
    "gn:timezone":"Asia/Kabul",
    "iso:country":"AF",
    "name:und_x_variant":[
        "\u1e0e\u0113gt\u014d\u1e5f",
        "Degtor",
        "D\u012bgtowr",
        "Daygt\u014dr",
        "D\u0113gt\u014dr",
        "\u062f\u06d0\u06af\u062a\u0648\u0631"
    ],
    "wof:name":"Degtor",
    "wof:placetype":"locality"
},
  "geometry": {"coordinates":[67.32614000000001,34.4619],"type":"Point"}
}