{
  "type": "Feature",
  "properties": {
    "gn:admin1_code":"27",
    "gn:admin2_code":"408.0",
    "gn:asciiname":"Deh-e Muslim",
    "gn:country_code":"AF",
    "gn:dem":2259,
    "gn:feature_class":"P",
    "gn:feature_code":"PPL",
    "gn:name":"Deh-e Muslim",
    "gn:population":0,
    "gn:timezone":"Asia/Kabul",
    "iso:country":"AF",
    "name:und_x_variant":[
        "Hin\u1e0fu",
        "Dekhi-Muslim",
        "Khindu",
        "\u1e0eehe Muslem",
        "Deh-e Muslim",
        "Deh-e Moslem",
        "\u062f\u0647 \u0645\u0633\u0644\u0645"
    ],
    "wof:name":"Deh-e Muslim",
    "wof:placetype":"locality"
},
  "geometry": {"coordinates":[68.80214000000001,34.3392],"type":"Point"}
}