{
  "type": "Feature",
  "properties": {
    "gn:admin1_code":"5",
    "gn:admin2_code":"2806.0",
    "gn:asciiname":"Zardak Beranah",
    "gn:country_code":"AF",
    "gn:dem":2565,
    "gn:feature_class":"P",
    "gn:feature_code":"PPL",
    "gn:name":"Zardak B\u0113r\u0101nah",
    "gn:population":0,
    "gn:timezone":"Asia/Kabul",
    "iso:country":"AF",
    "name:und_x_variant":[
        "Za\u1e5f\u1e0fak-b\u0113\u1e5f\u0101na",
        "Zardakberana",
        "Zardak B\u0113r\u0101nah",
        "\u0632\u0631\u062f\u06a9 \u0628\u06d0\u0631\u0627\u0646\u0647"
    ],
    "wof:name":"Zardak Beranah",
    "wof:placetype":"locality"
},
  "geometry": {"coordinates":[66.60603,34.05858],"type":"Point"}
}