{
  "type": "Feature",
  "properties": {
    "gn:admin1_code":"01",
    "gn:admin2_code":"1110.0",
    "gn:asciiname":"Kay",
    "gn:country_code":"AF",
    "gn:dem":2543,
    "gn:feature_class":"P",
    "gn:feature_code":"PPL",
    "gn:name":"Kay",
    "gn:population":0,
    "gn:timezone":"Asia/Kabul",
    "iso:country":"AF",
    "name:ita_x_preferred":[
        "Kay"
    ],
    "name:und_x_variant":[
        "\u06a9\u06cc"
    ],
    "wof:name":"Kay",
    "wof:placetype":"locality"
},
  "geometry": {"coordinates":[70.88868000000002,38.1762],"type":"Point"}
}