{
  "type": "Feature",
  "properties": {
    "gn:admin1_code":"27",
    "gn:admin2_code":"407",
    "gn:asciiname":"Muhabat Khel",
    "gn:country_code":"AF",
    "gn:dem":2371,
    "gn:feature_class":"P",
    "gn:feature_code":"PPL",
    "gn:name":"Mu\u1e29abat Kh\u0113l",
    "gn:population":0,
    "gn:timezone":"Asia/Kabul",
    "iso:country":"AF",
    "name:rus_x_preferred":[
        "Mukhabbatkheyl\u2019"
    ],
    "name:und_x_variant":[
        "Mo\u1e29abbatkh\u0113l",
        "Mu\u1e29abat Kh\u0113l",
        "Mo\u1e29abbat Kheyl",
        "\u0645\u062d\u0628\u062a \u062e\u06d0\u0644"
    ],
    "wof:name":"Muhabat Khel",
    "wof:placetype":"locality"
},
  "geometry": {"coordinates":[68.63302,33.98114],"type":"Point"}
}