{
  "type": "Feature",
  "properties": {
    "gn:admin1_code":"10",
    "gn:admin2_code":"2304",
    "gn:asciiname":"Kuchnay Regay",
    "gn:country_code":"AF",
    "gn:dem":943,
    "gn:feature_class":"P",
    "gn:feature_code":"PPL",
    "gn:name":"Kuchnay R\u0113gay",
    "gn:population":0,
    "gn:timezone":"Asia/Kabul",
    "iso:country":"AF",
    "name:und_x_variant":[
        "Kugnay-Regay",
        "Ku\u010dnay R\u0113gay",
        "Kuchnay Raygay",
        "\u06a9\u0686\u0646\u06cc \u0631\u06cc\u06af\u06cc",
        "Kuchnay R\u0113gay"
    ],
    "wof:name":"Kuchnay Regay",
    "wof:placetype":"locality"
},
  "geometry": {"coordinates":[64.80419000000001,32.21657],"type":"Point"}
}