{
  "type": "Feature",
  "properties": {
    "gn:admin1_code":"37",
    "gn:admin2_code":"3201.0",
    "gn:asciiname":"Zandah Khel",
    "gn:country_code":"AF",
    "gn:dem":1056,
    "gn:feature_class":"P",
    "gn:feature_code":"PPL",
    "gn:name":"Zan\u1e0fah Kh\u0113l",
    "gn:population":0,
    "gn:timezone":"Asia/Kabul",
    "iso:country":"AF",
    "name:fas_x_preferred":[
        "\u0632\u0646\u062f\u0647 \u062e\u064a\u0644"
    ],
    "name:rus_x_preferred":[
        "Zandakheyl\u2019"
    ],
    "name:und_x_variant":[
        "Zandakh\u0113l",
        "Zan\u1e0fah Kh\u0113l",
        "Zendeh Kheyl",
        "\u0632\u0646\u0689\u0647 \u062e\u06d0\u0644"
    ],
    "wof:name":"Zandah Khel",
    "wof:placetype":"locality"
},
  "geometry": {"coordinates":[70.08861,33.33361],"type":"Point"}
}