{
  "type": "Feature",
  "properties": {
    "gn:admin1_code":"37",
    "gn:admin2_code":"3202",
    "gn:asciiname":"Indzer Payalah",
    "gn:country_code":"AF",
    "gn:dem":1529,
    "gn:feature_class":"P",
    "gn:feature_code":"PPL",
    "gn:name":"Indz\u00ear Payalah",
    "gn:population":0,
    "gn:timezone":"Asia/Kabul",
    "iso:country":"AF",
    "name:und_x_variant":[
        "Enje Payalah",
        "Enj\u011br Payala",
        "Endzherpaala",
        "Enje Payala",
        "Indz\u00ear Payalah",
        "Enj\u0113\u1e5f Payalah",
        "\u0627\u0646\u0681\u0631 \u067e\u06cc\u0644\u0647"
    ],
    "wof:name":"Indzer Payalah",
    "wof:placetype":"locality"
},
  "geometry": {"coordinates":[70.04066999999999,33.6341],"type":"Point"}
}