{
  "type": "Feature",
  "properties": {
    "gn:admin1_code":"18",
    "gn:admin2_code":"802.0",
    "gn:asciiname":"Dand",
    "gn:country_code":"AF",
    "gn:dem":683,
    "gn:feature_class":"P",
    "gn:feature_code":"PPL",
    "gn:name":"Dand",
    "gn:population":0,
    "gn:timezone":"Asia/Kabul",
    "iso:country":"AF",
    "name:fas_x_preferred":[
        "\u062f\u0646\u062f"
    ],
    "name:und_x_variant":[
        "\u062f\u0646\u062f",
        "\u1e0ean\u1e0f",
        "\u0689\u0646\u0689",
        "Dand"
    ],
    "wof:name":"Dand",
    "wof:placetype":"locality"
},
  "geometry": {"coordinates":[70.31115,34.41191],"type":"Point"}
}