{
  "type": "Feature",
  "properties": {
    "gn:admin1_code":"05",
    "gn:admin2_code":"2806",
    "gn:asciiname":"Shaykhu",
    "gn:country_code":"AF",
    "gn:dem":2577,
    "gn:feature_class":"P",
    "gn:feature_code":"PPL",
    "gn:name":"Shaykh\u016b",
    "gn:population":0,
    "gn:timezone":"Asia/Kabul",
    "iso:country":"AF",
    "name:und_x_variant":[
        "\u0160aykhu",
        "Shaykh\u016b",
        "Sheykhu",
        "\u0634\u06cc\u062e\u0648"
    ],
    "wof:name":"Shaykhu",
    "wof:placetype":"locality"
},
  "geometry": {"coordinates":[66.84501,34.25892],"type":"Point"}
}