{
  "type": "Feature",
  "properties": {
    "gn:admin1_code":"33",
    "gn:admin2_code":"3104",
    "gn:asciiname":"Siyah Tal",
    "gn:country_code":"AF",
    "gn:dem":2724,
    "gn:feature_class":"P",
    "gn:feature_code":"PPL",
    "gn:name":"Siy\u0101h Tal",
    "gn:population":0,
    "gn:timezone":"Asia/Kabul",
    "iso:country":"AF",
    "name:und_x_variant":[
        "Sy\u0101tal",
        "S\u012b\u0101h Tal",
        "\u0633\u06cc\u0627\u0647 \u062a\u0644",
        "Siy\u0101h Tal"
    ],
    "wof:name":"Siyah Tal",
    "wof:placetype":"locality"
},
  "geometry": {"coordinates":[66.58587,35.65382],"type":"Point"}
}