{
  "type": "Feature",
  "properties": {
    "gn:admin1_code":"34",
    "gn:admin2_code":"1009",
    "gn:asciiname":"Wudolo",
    "gn:country_code":"AF",
    "gn:dem":1339,
    "gn:feature_class":"P",
    "gn:feature_code":"PPL",
    "gn:name":"Wud\u014dl\u014d",
    "gn:population":0,
    "gn:timezone":"Asia/Kabul",
    "iso:country":"AF",
    "name:und_x_variant":[
        "Vudolu",
        "Wo\u1e0f\u014dlo",
        "Wo\u1e0fowlo",
        "Wud\u014dl\u014d",
        "\u0648\u062f\u0648\u0644\u0648"
    ],
    "wof:name":"Wudolo",
    "wof:placetype":"locality"
},
  "geometry": {"coordinates":[70.73581999999998,34.99258],"type":"Point"}
}