{
  "type": "Feature",
  "properties": {
    "gn:admin1_code":"17",
    "gn:admin2_code":"503.0",
    "gn:asciiname":"Ahmadak",
    "gn:country_code":"AF",
    "gn:dem":1953,
    "gn:feature_class":"P",
    "gn:feature_code":"PPL",
    "gn:name":"A\u1e29madak",
    "gn:population":0,
    "gn:timezone":"Asia/Kabul",
    "iso:country":"AF",
    "name:und_x_variant":[
        "Akhmedak",
        "A\u1e29madak",
        "\u0627\u062d\u0645\u062f\u06a9"
    ],
    "wof:name":"Ahmadak",
    "wof:placetype":"locality"
},
  "geometry": {"coordinates":[68.89376999999999,33.94746],"type":"Point"}
}