{
  "type": "Feature",
  "properties": {
    "gn:admin1_code":"28",
    "gn:admin2_code":"2508.0",
    "gn:asciiname":"Chagai",
    "gn:country_code":"AF",
    "gn:dem":2057,
    "gn:feature_class":"P",
    "gn:feature_code":"PPL",
    "gn:name":"Ch\u0101ga\u012b",
    "gn:population":0,
    "gn:timezone":"Asia/Kabul",
    "iso:country":"AF",
    "name:cat_x_preferred":[
        "Chagai"
    ],
    "name:snd_x_preferred":[
        "\u0686\u0627\u063a\u064a"
    ],
    "name:und_x_variant":[
        "C\u0101gay",
        "Ch\u0101ga\u012b",
        "Ch\u0101gay",
        "\u0686\u0627\u06af\u06cc"
    ],
    "wof:name":"Chagai",
    "wof:placetype":"locality"
},
  "geometry": {"coordinates":[67.51472,31.75972],"type":"Point"}
}