{
  "type": "Feature",
  "properties": {
    "gn:admin1_code":"07",
    "gn:admin2_code":"1804",
    "gn:asciiname":"Kalishli",
    "gn:country_code":"AF",
    "gn:dem":1930,
    "gn:feature_class":"P",
    "gn:feature_code":"PPL",
    "gn:name":"Kal\u012bshl\u012b",
    "gn:population":0,
    "gn:timezone":"Asia/Kabul",
    "iso:country":"AF",
    "name:und_x_variant":[
        "Kal\u012bs\u0304li",
        "Kal\u012bshl\u012b",
        "\u06a9\u0644\u064a\u0634\u0644\u06cc"
    ],
    "wof:name":"Kalishli",
    "wof:placetype":"locality"
},
  "geometry": {"coordinates":[64.58412,35.61467000000001],"type":"Point"}
}