{
  "type": "Feature",
  "properties": {
    "gn:admin1_code":"41",
    "gn:admin2_code":"3408.0",
    "gn:asciiname":"Sar-e Top",
    "gn:country_code":"AF",
    "gn:dem":3024,
    "gn:feature_class":"P",
    "gn:feature_code":"PPL",
    "gn:name":"Sar-e T\u014dp",
    "gn:population":0,
    "gn:timezone":"Asia/Kabul",
    "iso:country":"AF",
    "name:und_x_variant":[
        "Sari-Top",
        "Sa\u1e5fe T\u014dp",
        "Sar-e T\u016bp",
        "Sar-e T\u014dp",
        "\u0633\u0631 \u062a\u0648\u067e"
    ],
    "wof:name":"Sar-e Top",
    "wof:placetype":"locality"
},
  "geometry": {"coordinates":[66.13076,34.34085],"type":"Point"}
}