{
  "type": "Feature",
  "properties": {
    "gn:admin1_code":"10",
    "gn:admin2_code":"2302",
    "gn:asciiname":"Nahr-e Saraj Pa'in Kala",
    "gn:country_code":"AF",
    "gn:dem":810,
    "gn:feature_class":"P",
    "gn:feature_code":"PPL",
    "gn:name":"Nahr-e Sar\u0101j P\u0101\u2019\u012bn Kal\u0101",
    "gn:population":0,
    "gn:timezone":"Asia/Kabul",
    "iso:country":"AF",
    "name:und_x_variant":[
        "Nakhri-Saradzhpayan-Kala",
        "Nah\u1e5fe Sa\u1e5f\u0101j P\u0101y\u0101n Kal\u0101",
        "Nahr-e Sar\u0101j P\u0101\u2019\u012bn Kal\u0101",
        "\u0646\u0647\u0631 \u0633\u0631\u0627\u062c \u067e\u0627\u0626\u06cc\u0646 \u06a9\u0644\u0627",
        "Nahr-e Ser\u0101j P\u0101y\u0101n Kal\u0101"
    ],
    "wof:name":"Nahr-e Saraj Pa'in Kala",
    "wof:placetype":"locality"
},
  "geometry": {"coordinates":[64.51416999999999,31.69201],"type":"Point"}
}