{
  "type": "Feature",
  "properties": {
    "gn:admin1_code":"28",
    "gn:admin2_code":"2510",
    "gn:asciiname":"Tabut",
    "gn:country_code":"AF",
    "gn:dem":2271,
    "gn:feature_class":"P",
    "gn:feature_code":"PPL",
    "gn:name":"T\u0101b\u016bt",
    "gn:population":0,
    "gn:timezone":"Asia/Kabul",
    "iso:country":"AF",
    "name:und_x_variant":[
        "T\u0101b\u016bt",
        "\u062a\u0627\u0628\u0648\u062a"
    ],
    "wof:name":"Tabut",
    "wof:placetype":"locality"
},
  "geometry": {"coordinates":[67.16826999999999,32.93865],"type":"Point"}
}