{
  "type": "Feature",
  "properties": {
    "gn:admin1_code":"8",
    "gn:admin2_code":"614.0",
    "gn:asciiname":"Madak Khel",
    "gn:country_code":"AF",
    "gn:dem":2079,
    "gn:feature_class":"P",
    "gn:feature_code":"PPL",
    "gn:name":"Madak Kh\u0113l",
    "gn:population":0,
    "gn:timezone":"Asia/Kabul",
    "iso:country":"AF",
    "name:fas_x_preferred":[
        "\u0645\u062f\u0643 \u062e\u064a\u0644"
    ],
    "name:rus_x_preferred":[
        "Madakkheyl\u2019"
    ],
    "name:und_x_variant":[
        "Ma\u1e0fakkh\u0113l",
        "Madak Kh\u0113l",
        "Madak Kheyl",
        "\u0645\u062f\u06a9 \u062e\u06d0\u0644"
    ],
    "wof:name":"Madak Khel",
    "wof:placetype":"locality"
},
  "geometry": {"coordinates":[68.35364,33.34206],"type":"Point"}
}