{
  "type": "Feature",
  "properties": {
    "gn:admin1_code":"39",
    "gn:admin2_code":"2604.0",
    "gn:asciiname":"Baghakhi",
    "gn:country_code":"AF",
    "gn:dem":1377,
    "gn:feature_class":"P",
    "gn:feature_code":"PPL",
    "gn:name":"B\u0101ghakh\u012b",
    "gn:population":0,
    "gn:timezone":"Asia/Kabul",
    "iso:country":"AF",
    "name:rus_x_preferred":[
        "\u0411\u0430\u0433\u0430\u0445\u0438"
    ],
    "name:und_x_variant":[
        "Bagakhi",
        "B\u0101ghakh\u012b",
        "\u0628\u0627\u063a\u062e\u06cc"
    ],
    "wof:name":"Baghakhi",
    "wof:placetype":"locality"
},
  "geometry": {"coordinates":[65.45947,33.05548],"type":"Point"}
}