{
  "type": "Feature",
  "properties": {
    "gn:admin1_code":"05",
    "gn:admin2_code":"2806",
    "gn:asciiname":"Zangi",
    "gn:country_code":"AF",
    "gn:dem":3092,
    "gn:feature_class":"P",
    "gn:feature_code":"PPL",
    "gn:name":"Zang\u012b",
    "gn:population":0,
    "gn:timezone":"Asia/Kabul",
    "iso:country":"AF",
    "name:ceb_x_preferred":[
        "Zangi"
    ],
    "name:kat_x_preferred":[
        "\u10d6\u10d0\u10dc\u10d2\u10d8"
    ],
    "name:swe_x_preferred":[
        "Zangi"
    ],
    "name:und_x_variant":[
        "Zang\u012b",
        "Zangi",
        "\u0632\u0646\u06af\u06cc"
    ],
    "wof:name":"Zangi",
    "wof:placetype":"locality"
},
  "geometry": {"coordinates":[66.79046,34.17312],"type":"Point"}
}