{
  "type": "Feature",
  "properties": {
    "gn:admin1_code":"13",
    "gn:admin2_code":"101.0",
    "gn:asciiname":"Qaryah-ye 'Umaryah",
    "gn:country_code":"AF",
    "gn:dem":1789,
    "gn:feature_class":"P",
    "gn:feature_code":"PPL",
    "gn:name":"Qaryah-ye \u2018Umaryah",
    "gn:population":0,
    "gn:timezone":"Asia/Kabul",
    "iso:country":"AF",
    "name:fas_x_preferred":[
        "\u062a\u062e\u0631\u06cc"
    ],
    "name:und_x_variant":[
        "Qaryah-ye \u2018Omaryah",
        "Takhiri",
        "Qaryah-ye \u2018Umaryah",
        "\u0642\u0631\u064a\u0647 \u0639\u0645\u0631\u064a\u0647"
    ],
    "wof:name":"Qaryah-ye 'Umaryah",
    "wof:placetype":"locality"
},
  "geometry": {"coordinates":[69.17528,34.55944],"type":"Point"}
}