{
  "type": "Feature",
  "properties": {
    "gn:admin1_code":"23",
    "gn:admin2_code":"2404",
    "gn:asciiname":"Nagahan",
    "gn:country_code":"AF",
    "gn:dem":994,
    "gn:feature_class":"P",
    "gn:feature_code":"PPL",
    "gn:name":"N\u0101gah\u0101n",
    "gn:population":0,
    "gn:timezone":"Asia/Kabul",
    "iso:country":"AF",
    "name:und_x_variant":[
        "Nagakhan",
        "Nagahon",
        "N\u0101gah\u0101n",
        "\u0646\u0627\u06af\u0647\u0627\u0646"
    ],
    "wof:name":"Nagahan",
    "wof:placetype":"locality"
},
  "geometry": {"coordinates":[65.58599,31.647],"type":"Point"}
}