{
  "type": "Feature",
  "properties": {
    "gn:admin1_code":"03",
    "gn:admin2_code":"1308.0",
    "gn:asciiname":"Deh Ishan",
    "gn:country_code":"AF",
    "gn:dem":1630,
    "gn:feature_class":"P",
    "gn:feature_code":"PPL",
    "gn:name":"Deh Ish\u0101n",
    "gn:population":0,
    "gn:timezone":"Asia/Kabul",
    "iso:country":"AF",
    "name:und_x_variant":[
        "\u1e0eeh-es\u0101n",
        "Deh-e Sh\u0101n",
        "Deh Ish\u0101n",
        "\u062f\u0647 \u0627\u0634\u0627\u0646"
    ],
    "wof:name":"Deh Ishan",
    "wof:placetype":"locality"
},
  "geometry": {"coordinates":[69.63398000000001,36.01801],"type":"Point"}
}