{
  "type": "Feature",
  "properties": {
    "gn:admin1_code":"05",
    "gn:admin2_code":"2805.0",
    "gn:asciiname":"Katah Qal'ah",
    "gn:country_code":"AF",
    "gn:dem":2830,
    "gn:feature_class":"P",
    "gn:feature_code":"PPL",
    "gn:name":"Ka\u1e6fah Qal\u2018ah",
    "gn:population":0,
    "gn:timezone":"Asia/Kabul",
    "iso:country":"AF",
    "name:und_x_variant":[
        "Katakala",
        "Kataqal\u2018a",
        "Katahqal\u2018eh",
        "Katah Qal\u2018ah",
        "Ka\u1e6fah Qal\u2018ah",
        "\u06a9\u067c\u0647 \u0642\u0644\u0639\u0647"
    ],
    "wof:name":"Katah Qal'ah",
    "wof:placetype":"locality"
},
  "geometry": {"coordinates":[67.05577,34.44151],"type":"Point"}
}