{
  "type": "Feature",
  "properties": {
    "gn:admin1_code":"01",
    "gn:admin2_code":"1127",
    "gn:asciiname":"Gowhar",
    "gn:country_code":"AF",
    "gn:dem":1999,
    "gn:feature_class":"P",
    "gn:feature_code":"PPL",
    "gn:name":"Gowhar",
    "gn:population":0,
    "gn:timezone":"Asia/Kabul",
    "iso:country":"AF",
    "name:und_x_variant":[
        "\u06af\u0648\u0647\u0631",
        "Gawhar",
        "G\u0101whar"
    ],
    "wof:name":"Gowhar",
    "wof:placetype":"locality"
},
  "geometry": {"coordinates":[70.76258,36.42076],"type":"Point"}
}