{
  "type": "Feature",
  "properties": {
    "gn:admin1_code":"30",
    "gn:admin2_code":"1608",
    "gn:asciiname":"Uruzgani",
    "gn:country_code":"AF",
    "gn:dem":389,
    "gn:feature_class":"P",
    "gn:feature_code":"PPL",
    "gn:name":"Uruzg\u0101n\u012b",
    "gn:population":0,
    "gn:timezone":"Asia/Kabul",
    "iso:country":"AF",
    "name:fas_x_preferred":[
        "\u0627\u0648\u0631\u0632\u06af\u0646\u06cc"
    ],
    "name:rus_x_preferred":[
        "\u0423\u0440\u0437\u0433\u0430\u043d\u0438"
    ],
    "name:und_x_variant":[
        "Urzgani",
        "Urzgan\u012b",
        "\u0627\u0631\u0632\u06af\u0627\u0646\u06cc",
        "Uruzg\u0101n\u012b"
    ],
    "wof:name":"Uruzgani",
    "wof:placetype":"locality"
},
  "geometry": {"coordinates":[66.74064,36.66967],"type":"Point"}
}