{
  "type": "Feature",
  "properties": {
    "gn:admin1_code":"32",
    "gn:admin2_code":"1504.0",
    "gn:asciiname":"Ajriqsay",
    "gn:country_code":"AF",
    "gn:dem":1837,
    "gn:feature_class":"P",
    "gn:feature_code":"PPL",
    "gn:name":"Ajriqs\u0101y",
    "gn:population":0,
    "gn:timezone":"Asia/Kabul",
    "iso:country":"AF",
    "name:und_x_variant":[
        "Ajriqs\u0101y",
        "\u0627\u062c\u0631\u0642\u0633\u0627\u06cc",
        "Aj\u1e5feqs\u0101y"
    ],
    "wof:name":"Ajriqsay",
    "wof:placetype":"locality"
},
  "geometry": {"coordinates":[67.4323,35.95211],"type":"Point"}
}