{
  "type": "Feature",
  "properties": {
    "gn:admin1_code":"41",
    "gn:admin2_code":"3403.0",
    "gn:asciiname":"Sang-e Surakh",
    "gn:country_code":"AF",
    "gn:dem":2581,
    "gn:feature_class":"P",
    "gn:feature_code":"PPL",
    "gn:name":"Sang-e S\u016br\u0101kh",
    "gn:population":0,
    "gn:timezone":"Asia/Kabul",
    "iso:country":"AF",
    "name:ara_x_preferred":[
        "\u0633\u0646\u063a \u0633\u0648\u0631\u0627\u062e"
    ],
    "name:ceb_x_preferred":[
        "Sang-e S\u016br\u0101kh"
    ],
    "name:fas_x_preferred":[
        "\u0633\u0646\u06af \u0633\u0648\u0631\u0627\u062e"
    ],
    "name:swe_x_preferred":[
        "Sang-e S\u016br\u0101kh"
    ],
    "name:und_x_variant":[
        "Sangi-Surakh"
    ],
    "wof:name":"Sang-e Surakh",
    "wof:placetype":"locality"
},
  "geometry": {"coordinates":[66.3104,34.24995999999999],"type":"Point"}
}