{
  "type": "Feature",
  "properties": {
    "gn:admin1_code":"05",
    "gn:admin2_code":"2805.0",
    "gn:asciiname":"Ghujurak",
    "gn:country_code":"AF",
    "gn:dem":2912,
    "gn:feature_class":"P",
    "gn:feature_code":"PPL",
    "gn:name":"Ghuj\u016brak",
    "gn:population":0,
    "gn:timezone":"Asia/Kabul",
    "iso:country":"AF",
    "name:und_x_variant":[
        "Gudzhurak",
        "Ghoj\u016b\u1e5fak",
        "Ghoj\u016brak",
        "Ghojowrak",
        "Ghuj\u016brak",
        "\u063a\u062c\u0648\u0631\u06a9"
    ],
    "wof:name":"Ghujurak",
    "wof:placetype":"locality"
},
  "geometry": {"coordinates":[67.04529000000001,34.46478],"type":"Point"}
}