{
  "type": "Feature",
  "properties": {
    "gn:admin1_code":"41",
    "gn:admin2_code":"3402",
    "gn:asciiname":"Mullayan",
    "gn:country_code":"AF",
    "gn:dem":1974,
    "gn:feature_class":"P",
    "gn:feature_code":"PPL",
    "gn:name":"Mull\u0101y\u0101n",
    "gn:population":0,
    "gn:timezone":"Asia/Kabul",
    "iso:country":"AF",
    "name:und_x_variant":[
        "Mull\u0101y\u0101n",
        "\u0645\u0644\u0627\u06cc\u0627\u0646",
        "Moll\u0101y\u0101n"
    ],
    "wof:name":"Mullayan",
    "wof:placetype":"locality"
},
  "geometry": {"coordinates":[65.95981999999999,33.57080999999999],"type":"Point"}
}