{
  "type": "Feature",
  "properties": {
    "gn:admin1_code":"01",
    "gn:admin2_code":"1125",
    "gn:asciiname":"Tarang",
    "gn:country_code":"AF",
    "gn:dem":1760,
    "gn:feature_class":"P",
    "gn:feature_code":"PPL",
    "gn:name":"Tarang",
    "gn:population":0,
    "gn:timezone":"Asia/Kabul",
    "iso:country":"AF",
    "name:hin_x_preferred":[
        "\u0924\u0930\u0902\u0917"
    ],
    "name:und_x_variant":[
        "Deh-e Tarang",
        "\u062a\u0631\u0646\u06af",
        "Tarang"
    ],
    "wof:name":"Tarang",
    "wof:placetype":"locality"
},
  "geometry": {"coordinates":[71.05299000000002,36.92058],"type":"Point"}
}