{
  "type": "Feature",
  "properties": {
    "gn:admin1_code":"41",
    "gn:admin2_code":"3403.0",
    "gn:asciiname":"Dahan-e Now Bandak",
    "gn:country_code":"AF",
    "gn:dem":2038,
    "gn:feature_class":"P",
    "gn:feature_code":"PPL",
    "gn:name":"Dah\u0101n-e Now Bandak",
    "gn:population":0,
    "gn:timezone":"Asia/Kabul",
    "iso:country":"AF",
    "name:und_x_variant":[
        "D\u0101ne Nawban\u1e0fak",
        "Dah\u0101n-e Now Bandak",
        "\u062f\u0647\u0627\u0646 \u0646\u0648 \u0628\u0646\u062f\u06a9",
        "D\u0101ne Now Bandak"
    ],
    "wof:name":"Dahan-e Now Bandak",
    "wof:placetype":"locality"
},
  "geometry": {"coordinates":[66.30328,33.97317],"type":"Point"}
}