{
  "type": "Feature",
  "properties": {
    "gn:admin1_code":"09",
    "gn:admin2_code":"2706",
    "gn:asciiname":"Khamin",
    "gn:country_code":"AF",
    "gn:dem":2832,
    "gn:feature_class":"P",
    "gn:feature_code":"PPL",
    "gn:name":"Kham\u012bn",
    "gn:population":0,
    "gn:timezone":"Asia/Kabul",
    "iso:country":"AF",
    "name:und_x_variant":[
        "Kham\u012bn",
        "\u062e\u0645\u06cc\u0646"
    ],
    "wof:name":"Khamin",
    "wof:placetype":"locality"
},
  "geometry": {"coordinates":[65.01609000000001,33.67389],"type":"Point"}
}