{
  "type": "Feature",
  "properties": {
    "gn:admin1_code":"28",
    "gn:admin2_code":"2511.0",
    "gn:asciiname":"Ghulam Sadiq Kala",
    "gn:country_code":"AF",
    "gn:dem":1976,
    "gn:feature_class":"P",
    "gn:feature_code":"PPL",
    "gn:name":"Ghul\u0101m \u015ead\u012bq Kal\u0101",
    "gn:population":0,
    "gn:timezone":"Asia/Kabul",
    "iso:country":"AF",
    "name:und_x_variant":[
        "Gulyam-Sidik-Kala",
        "Ghul\u0101m Se\u1e0f\u1e0f\u012bq Kal\u0101",
        "Ghol\u0101m \u015eedd\u012bq Kal\u0101",
        "Ghul\u0101m \u015ead\u012bq Kal\u0101",
        "\u063a\u0644\u0627\u0645 \u0635\u062f\u06cc\u0642 \u06a9\u0644\u0627"
    ],
    "wof:name":"Ghulam Sadiq Kala",
    "wof:placetype":"locality"
},
  "geometry": {"coordinates":[67.60805999999999,32.31528],"type":"Point"}
}