{
  "type": "Feature",
  "properties": {
    "gn:admin1_code":"09",
    "gn:admin2_code":"2706",
    "gn:asciiname":"Maidan-e Mal",
    "gn:country_code":"AF",
    "gn:dem":1723,
    "gn:feature_class":"P",
    "gn:feature_code":"PPL",
    "gn:name":"Ma\u012bd\u0101n-e M\u0101l",
    "gn:population":0,
    "gn:timezone":"Asia/Kabul",
    "iso:country":"AF",
    "name:und_x_variant":[
        "Ma\u012bd\u0101n-e M\u0101l",
        "\u0645\u06cc\u062f\u0627\u0646 \u0645\u0627\u0644",
        "Meyd\u0101n-e M\u0101l"
    ],
    "wof:name":"Maidan-e Mal",
    "wof:placetype":"locality"
},
  "geometry": {"coordinates":[65.5312,33.65737],"type":"Point"}
}