{
  "type": "Feature",
  "properties": {
    "gn:admin1_code":"39",
    "gn:admin2_code":"2601.0",
    "gn:asciiname":"Daraz Joy-e Junubi",
    "gn:country_code":"AF",
    "gn:dem":1437,
    "gn:feature_class":"P",
    "gn:feature_code":"PPL",
    "gn:name":"Dar\u0101z J\u014dy-e Jun\u016bb\u012b",
    "gn:population":0,
    "gn:timezone":"Asia/Kabul",
    "iso:country":"AF",
    "name:fas_x_preferred":[
        "\u062f\u0631\u0627\u0632 \u062c\u0648\u06cc\u0654 \u062c\u0646\u0648\u0628\u06cc"
    ],
    "name:und_x_variant":[
        "\u1e0ea\u1e5f\u0101zj\u0101y Jan\u016bbi",
        "\u1e0ea\u1e5f\u0101zj\u0101y Jon\u016bbi",
        "Darazdzhoyi-Dzhanubi",
        "Dar\u0101z J\u014dy-e Jun\u016bb\u012b",
        "\u062f\u0631\u0627\u0632 \u062c\u0648\u06cc \u062c\u0646\u0648\u0628\u06cc",
        "Der\u0101zj\u0101y Jon\u016bb\u012b"
    ],
    "wof:name":"Daraz Joy-e Junubi",
    "wof:placetype":"locality"
},
  "geometry": {"coordinates":[65.94801,32.5912],"type":"Point"}
}