{
  "type": "Feature",
  "properties": {
    "gn:admin1_code":"09",
    "gn:admin2_code":"2706",
    "gn:asciiname":"Jay-e Moghul",
    "gn:country_code":"AF",
    "gn:dem":2431,
    "gn:feature_class":"P",
    "gn:feature_code":"PPL",
    "gn:name":"J\u0101y-e Moghul",
    "gn:population":0,
    "gn:timezone":"Asia/Kabul",
    "iso:country":"AF",
    "name:rus_x_preferred":[
        "Dzhoyi-Mugul\u2019"
    ],
    "name:und_x_variant":[
        "J\u0101y-e Moghul",
        "\u062c\u0627\u06cc \u0645\u063a\u0644",
        "J\u0101-ye Mogh\u016bl"
    ],
    "wof:name":"Jay-e Moghul",
    "wof:placetype":"locality"
},
  "geometry": {"coordinates":[64.81504,33.68104],"type":"Point"}
}