{
  "type": "Feature",
  "properties": {
    "gn:admin1_code":"23",
    "gn:admin2_code":"2413",
    "gn:asciiname":"Khogam Fort",
    "gn:country_code":"AF",
    "gn:dem":1761,
    "gn:feature_class":"P",
    "gn:feature_code":"PPL",
    "gn:name":"Khogam Fort",
    "gn:population":0,
    "gn:timezone":"Asia/Kabul",
    "iso:country":"AF",
    "name:fas_x_preferred":[
        "\u062e\u0648\u06af\u064a\u0627\u0646\u06cc"
    ],
    "name:pus_x_preferred":[
        "\u062e\u0648\u06af\u06cc\u0627\u06bc\u06cc"
    ],
    "name:und_x_variant":[
        "Chogani",
        "Khog\u0101ni",
        "Khowg\u012b\u0101\u1e49ay",
        "Kh\u016bgay\u0101n\u012b",
        "Kh\u016bgy\u0101\u1e49ay",
        "Khogam Fort",
        "Kh\u016bg\u012b\u0101\u1e49ay",
        "Kh\u016bgy\u0101na\u012b"
    ],
    "wof:name":"Khogam Fort",
    "wof:placetype":"locality"
},
  "geometry": {"coordinates":[67.17778,31.64782],"type":"Point"}
}