{
  "type": "Feature",
  "properties": {
    "gn:admin1_code":"08",
    "gn:admin2_code":"604",
    "gn:asciiname":"Qarghah-ye Pa'in",
    "gn:country_code":"AF",
    "gn:dem":3159,
    "gn:feature_class":"P",
    "gn:feature_code":"PPL",
    "gn:name":"Qarghah-ye P\u0101\u2019\u012bn",
    "gn:population":0,
    "gn:timezone":"Asia/Kabul",
    "iso:country":"AF",
    "name:fas_x_preferred":[
        "\u0642\u0631\u063a\u06c0 \u067e\u0627\u0626\u064a\u0646"
    ],
    "name:rus_x_preferred":[
        "\u041a\u0430\u0440\u0433\u0430\u0439\u0438-\u041f\u0430\u0438\u043d"
    ],
    "name:und_x_variant":[
        "Kargayi-Pain",
        "Qa\u1e5fgha-i-P\u0101\u2019\u012bn",
        "Qarghah-e P\u0101\u2019\u012bn",
        "Qarghah-ye P\u0101\u2019\u012bn",
        "\u0642\u0631\u063a\u06c0 \u067e\u0627\u0626\u06cc\u0646"
    ],
    "wof:name":"Qarghah-ye Pa'in",
    "wof:placetype":"locality"
},
  "geometry": {"coordinates":[67.85159,33.91683],"type":"Point"}
}