{
  "type": "Feature",
  "properties": {
    "gn:admin1_code":"23",
    "gn:admin2_code":"2403",
    "gn:asciiname":"Mian",
    "gn:country_code":"AF",
    "gn:dem":1480,
    "gn:feature_class":"P",
    "gn:feature_code":"PPL",
    "gn:name":"Mian",
    "gn:population":0,
    "gn:timezone":"Asia/Kabul",
    "iso:country":"AF",
    "name:ceb_x_preferred":[
        "Mian"
    ],
    "name:deu_x_preferred":[
        "Mian"
    ],
    "name:fas_x_preferred":[
        "\u0645\u064a\u0627\u0646"
    ],
    "name:fra_x_preferred":[
        "Mian"
    ],
    "name:und_x_variant":[
        "M\u012b\u0101n",
        "Mian",
        "\u0645\u06cc\u0627\u0646"
    ],
    "wof:name":"Mian",
    "wof:placetype":"locality"
},
  "geometry": {"coordinates":[65.85096999999999,32.13717],"type":"Point"}
}