{
  "type": "Feature",
  "properties": {
    "gn:admin1_code":"8",
    "gn:admin2_code":"615.0",
    "gn:asciiname":"Adah",
    "gn:country_code":"AF",
    "gn:dem":2459,
    "gn:feature_class":"P",
    "gn:feature_code":"PPL",
    "gn:name":"A\u1e0fah",
    "gn:population":0,
    "gn:timezone":"Asia/Kabul",
    "iso:country":"AF",
    "name:und_x_variant":[
        "A\u1e0fah",
        "\u0627\u0689\u0647",
        "Ada"
    ],
    "wof:name":"Adah",
    "wof:placetype":"locality"
},
  "geometry": {"coordinates":[68.75634000000001,33.5707],"type":"Point"}
}