{
  "type": "Feature",
  "properties": {
    "gn:admin1_code":"19",
    "gn:admin2_code":"2201.0",
    "gn:asciiname":"Muhammad 'Alam",
    "gn:country_code":"AF",
    "gn:dem":488,
    "gn:feature_class":"P",
    "gn:feature_code":"PPL",
    "gn:name":"Mu\u1e29ammad \u2018Alam",
    "gn:population":0,
    "gn:timezone":"Asia/Kabul",
    "iso:country":"AF",
    "name:und_x_variant":[
        "Mo\u1e96\u1e0f \u2018Alam",
        "Mu\u1e29ammad \u2018Alam"
    ],
    "wof:name":"Muhammad 'Alam",
    "wof:placetype":"locality"
},
  "geometry": {"coordinates":[61.84486,30.93399],"type":"Point"}
}