{
  "type": "Feature",
  "properties": {
    "gn:admin1_code":"36",
    "gn:admin2_code":"704",
    "gn:asciiname":"Howas Khel",
    "gn:country_code":"AF",
    "gn:dem":1940,
    "gn:feature_class":"P",
    "gn:feature_code":"PPL",
    "gn:name":"Howas Kh\u0113l",
    "gn:population":0,
    "gn:timezone":"Asia/Kabul",
    "iso:country":"AF",
    "name:fas_x_preferred":[
        "\u0647\u0648\u0633 \u062e\u064a\u0644"
    ],
    "name:rus_x_preferred":[
        "Khavaskhel\u2019"
    ],
    "name:und_x_variant":[
        "Hawaskh\u0113l",
        "Hawas Kh\u0113l",
        "Havas Kheyl",
        "Howas Kh\u0113l",
        "\u0647\u0648\u0633 \u062e\u06d0\u0644"
    ],
    "wof:name":"Howas Khel",
    "wof:placetype":"locality"
},
  "geometry": {"coordinates":[69.46550000000001,33.40414000000001],"type":"Point"}
}