{
  "type": "Feature",
  "properties": {
    "gn:admin1_code":"27",
    "gn:admin2_code":"403.0",
    "gn:asciiname":"Qol-e Chakar",
    "gn:country_code":"AF",
    "gn:dem":2862,
    "gn:feature_class":"P",
    "gn:feature_code":"PPL",
    "gn:name":"Q\u014dl-e Chakar",
    "gn:population":0,
    "gn:timezone":"Asia/Kabul",
    "iso:country":"AF",
    "name:und_x_variant":[
        "Kuli-Chakar",
        "Qole \u010cakar",
        "Qowl-e Chakar",
        "Q\u014dl-e Chakar",
        "\u0642\u0648\u0644 \u0686\u06a9\u0631"
    ],
    "wof:name":"Qol-e Chakar",
    "wof:placetype":"locality"
},
  "geometry": {"coordinates":[68.12654000000001,34.34309],"type":"Point"}
}