{
  "type": "Feature",
  "properties": {
    "gn:admin1_code":"29",
    "gn:admin2_code":"2908.0",
    "gn:asciiname":"Marzak",
    "gn:country_code":"AF",
    "gn:dem":2474,
    "gn:feature_class":"P",
    "gn:feature_code":"PPL",
    "gn:name":"Marzak",
    "gn:population":0,
    "gn:timezone":"Asia/Kabul",
    "iso:country":"AF",
    "name:fas_x_preferred":[
        "\u0645\u0631\u0632\u06a9"
    ],
    "wof:name":"Marzak",
    "wof:placetype":"locality"
},
  "geometry": {"coordinates":[69.06641999999999,32.8386],"type":"Point"}
}