{
  "type": "Feature",
  "properties": {
    "gn:admin1_code":"23",
    "gn:admin2_code":"2412.0",
    "gn:asciiname":"Terwakey",
    "gn:country_code":"AF",
    "gn:dem":1199,
    "gn:feature_class":"P",
    "gn:feature_code":"PPL",
    "gn:name":"T\u00earwak\u00eay",
    "gn:population":0,
    "gn:timezone":"Asia/Kabul",
    "iso:country":"AF",
    "name:und_x_variant":[
        "Tervakay",
        "T\u00earwak\u00eay",
        "\u062a\u0631\u0648\u06a9\u06cd",
        "Terwakey"
    ],
    "wof:name":"Terwakey",
    "wof:placetype":"locality"
},
  "geometry": {"coordinates":[66.34855,31.49717],"type":"Point"}
}