{
  "type": "Feature",
  "properties": {
    "gn:admin1_code":"05",
    "gn:admin2_code":"2806.0",
    "gn:asciiname":"Sar-e Manghoz",
    "gn:country_code":"AF",
    "gn:dem":3170,
    "gn:feature_class":"P",
    "gn:feature_code":"PPL",
    "gn:name":"Sar-e M\u0101ngh\u014dz\u0304",
    "gn:population":0,
    "gn:timezone":"Asia/Kabul",
    "iso:country":"AF",
    "name:und_x_variant":[
        "Sa\u1e5fe M\u0101ngh\u014dz\u0304",
        "Sari-Mangoz",
        "Sar-e M\u0101ngh\u016b\u1e95",
        "Sar-e M\u0101ngh\u016bz",
        "Sar-e M\u0101ngh\u014dz\u0304",
        "\u0633\u0631 \u0645\u0627\u0646\u063a\u0648\u0630"
    ],
    "wof:name":"Sar-e Manghoz",
    "wof:placetype":"locality"
},
  "geometry": {"coordinates":[67.11700999999999,34.29972],"type":"Point"}
}