{
  "type": "Feature",
  "properties": {
    "gn:admin1_code":"31",
    "gn:admin2_code":"1710",
    "gn:asciiname":"Khanaqah",
    "gn:country_code":"AF",
    "gn:dem":299,
    "gn:feature_class":"P",
    "gn:feature_code":"PPLA2",
    "gn:name":"Kh\u0101naq\u0101h",
    "gn:population":0,
    "gn:timezone":"Asia/Kabul",
    "iso:country":"AF",
    "name:und_x_variant":[
        "Kh\u0101neq\u0101h",
        "Kh\u0101naka",
        "Kh\u0101nanq\u0101",
        "Kh\u0101naq\u0101",
        "Kh\u0101naq\u0101h",
        "\u062e\u0627\u0646\u0642\u0647",
        "\u062e\u0627\u0646\u0642\u0627\u0647"
    ],
    "wof:name":"Khanaqah",
    "wof:placetype":"locality"
},
  "geometry": {"coordinates":[66.16656,36.86279],"type":"Point"}
}