{
  "type": "Feature",
  "properties": {
    "gn:admin1_code":"09",
    "gn:admin2_code":"2707",
    "gn:asciiname":"Kamran",
    "gn:country_code":"AF",
    "gn:dem":2741,
    "gn:feature_class":"P",
    "gn:feature_code":"PPL",
    "gn:name":"K\u0101mr\u0101n",
    "gn:population":0,
    "gn:timezone":"Asia/Kabul",
    "iso:country":"AF",
    "name:aze_x_preferred":[
        "Kamran"
    ],
    "name:deu_x_preferred":[
        "Kamran"
    ],
    "name:fas_x_preferred":[
        "\u06a9\u0627\u0645\u0631\u0627\u0646"
    ],
    "name:rus_x_preferred":[
        "\u041a\u0430\u043c\u0440\u0430\u043d"
    ],
    "name:swe_x_preferred":[
        "Kamran"
    ],
    "name:und_x_variant":[
        "K\u0101mr\u0101n"
    ],
    "wof:name":"Kamran",
    "wof:placetype":"locality"
},
  "geometry": {"coordinates":[66.30248,34.64283],"type":"Point"}
}