{
  "type": "Feature",
  "properties": {
    "gn:admin1_code":"13",
    "gn:admin2_code":"107.0",
    "gn:asciiname":"Khwajah Wujud",
    "gn:country_code":"AF",
    "gn:dem":1870,
    "gn:feature_class":"P",
    "gn:feature_code":"PPL",
    "gn:name":"Khw\u0101jah Wuj\u016bd",
    "gn:population":0,
    "gn:timezone":"Asia/Kabul",
    "iso:country":"AF",
    "name:und_x_variant":[
        "Khodzha-Vudzhud",
        "Khw\u0101ja-woj\u016bd",
        "Khw\u0101jah Woj\u016bd",
        "Khv\u0101jeh Voj\u016bd",
        "Khw\u0101jah-Wuj\u016bd",
        "\u062e\u0648\u0627\u062c\u0647 \u0648\u062c\u0648\u062f",
        "Khw\u0101jah Wuj\u016bd"
    ],
    "wof:name":"Khwajah Wujud",
    "wof:placetype":"locality"
},
  "geometry": {"coordinates":[69.06555,34.66309],"type":"Point"}
}