{
  "type": "Feature",
  "properties": {
    "gn:admin1_code":"06",
    "gn:admin2_code":"2103",
    "gn:asciiname":"Rabat",
    "gn:country_code":"AF",
    "gn:dem":1869,
    "gn:feature_class":"P",
    "gn:feature_code":"PPL",
    "gn:name":"Rab\u0101\u0163",
    "gn:population":0,
    "gn:timezone":"Asia/Kabul",
    "iso:country":"AF",
    "name:und_x_variant":[
        "Rab\u0101\u0163",
        "\u0631\u0628\u0627\u0637",
        "Roba\u0163"
    ],
    "wof:name":"Rabat",
    "wof:placetype":"locality"
},
  "geometry": {"coordinates":[63.80544,32.75628],"type":"Point"}
}