{
  "type": "Feature",
  "properties": {
    "gn:admin1_code":"5",
    "gn:admin2_code":"2804.0",
    "gn:asciiname":"Sachak",
    "gn:country_code":"AF",
    "gn:dem":2541,
    "gn:feature_class":"P",
    "gn:feature_code":"PPL",
    "gn:name":"Sachak",
    "gn:population":0,
    "gn:timezone":"Asia/Kabul",
    "iso:country":"AF",
    "name:und_x_variant":[
        "Sa\u010dak",
        "Sachak",
        "\u0634\u0686\u06a9"
    ],
    "wof:name":"Sachak",
    "wof:placetype":"locality"
},
  "geometry": {"coordinates":[66.63568000000001,34.84481],"type":"Point"}
}