{
  "type": "Feature",
  "properties": {
    "gn:admin1_code":"03",
    "gn:admin2_code":"1308",
    "gn:asciiname":"Kizar",
    "gn:country_code":"AF",
    "gn:dem":2020,
    "gn:feature_class":"P",
    "gn:feature_code":"PPL",
    "gn:name":"Kiz\u0304ar",
    "gn:population":0,
    "gn:timezone":"Asia/Kabul",
    "iso:country":"AF",
    "name:und_x_variant":[
        "Kiz\u0304ar",
        "\u06a9\u0630\u0631",
        "Kez\u0101r"
    ],
    "wof:name":"Kizar",
    "wof:placetype":"locality"
},
  "geometry": {"coordinates":[69.68970999999999,35.89359],"type":"Point"}
}