{
  "type": "Feature",
  "properties": {
    "gn:admin1_code":"39",
    "gn:admin2_code":"2601",
    "gn:asciiname":"Deh Jowz-e Hasanzai",
    "gn:country_code":"AF",
    "gn:dem":1391,
    "gn:feature_class":"P",
    "gn:feature_code":"PPL",
    "gn:name":"Deh Jowz-e \u1e28asanza\u012b",
    "gn:population":0,
    "gn:timezone":"Asia/Kabul",
    "iso:country":"AF",
    "name:fas_x_preferred":[
        "\u062f\u0647 \u062c\u0648\u0632\u0654 \u062d\u0633\u0646\u0632\u06cc"
    ],
    "name:und_x_variant":[
        "Dekhdzhauzi-Khasanzi",
        "\u1e0eehjawze \u1e28asanzi",
        "Deh Jowz-e \u1e28asanza\u012b",
        "\u062f\u0647 \u062c\u0648\u0632 \u062d\u0633\u0646\u0632\u06cc",
        "Dehjawz-e \u1e28asanzay"
    ],
    "wof:name":"Deh Jowz-e Hasanzai",
    "wof:placetype":"locality"
},
  "geometry": {"coordinates":[65.89695,32.69642],"type":"Point"}
}