{
  "type": "Feature",
  "properties": {
    "gn:admin1_code":"34",
    "gn:admin2_code":"1009.0",
    "gn:asciiname":"Kandar",
    "gn:country_code":"AF",
    "gn:dem":1876,
    "gn:feature_class":"P",
    "gn:feature_code":"PPL",
    "gn:name":"Kandar",
    "gn:population":0,
    "gn:timezone":"Asia/Kabul",
    "iso:country":"AF",
    "name:fas_x_preferred":[
        "\u0643\u0627\u0646\u062f\u0631"
    ],
    "name:und_x_variant":[
        "K\u0101ndar",
        "K\u0101n\u1e0fa\u1e5f",
        "\u06a9\u0627\u0646\u0689\u0693",
        "K\u0101n\u1e0far",
        "\u06a9\u0627\u0646\u0689\u0631"
    ],
    "wof:name":"Kandar",
    "wof:placetype":"locality"
},
  "geometry": {"coordinates":[70.76345999999999,34.88302],"type":"Point"}
}