{
  "type": "Feature",
  "properties": {
    "gn:admin1_code":"11",
    "gn:admin2_code":"2008",
    "gn:asciiname":"Waliabad",
    "gn:country_code":"AF",
    "gn:dem":791,
    "gn:feature_class":"P",
    "gn:feature_code":"PPL",
    "gn:name":"Wal\u012b\u0101b\u0101d",
    "gn:population":0,
    "gn:timezone":"Asia/Kabul",
    "iso:country":"AF",
    "name:und_x_variant":[
        "Val\u012b\u0101b\u0101d",
        "Wal\u012b\u0101b\u0101d"
    ],
    "wof:name":"Waliabad",
    "wof:placetype":"locality"
},
  "geometry": {"coordinates":[60.91486,34.50464],"type":"Point"}
}