{
  "type": "Feature",
  "properties": {
    "gn:admin1_code":"03",
    "gn:admin2_code":"1305",
    "gn:asciiname":"Dowlat Beg",
    "gn:country_code":"AF",
    "gn:dem":1302,
    "gn:feature_class":"P",
    "gn:feature_code":"PPL",
    "gn:name":"Dowlat B\u0113g",
    "gn:population":0,
    "gn:timezone":"Asia/Kabul",
    "iso:country":"AF",
    "name:und_x_variant":[
        "\u1e0eawlatb\u0113g",
        "Dowlatb\u0113g",
        "Dowlatbeyg",
        "Dowlat B\u0113g",
        "\u062f\u0648\u0644\u062a \u0628\u06d0\u06af"
    ],
    "wof:name":"Dowlat Beg",
    "wof:placetype":"locality"
},
  "geometry": {"coordinates":[68.14856,35.35402],"type":"Point"}
}