{
  "type": "Feature",
  "properties": {
    "gn:admin1_code":"26",
    "gn:admin2_code":"1213.0",
    "gn:asciiname":"Ab Sarinah",
    "gn:country_code":"AF",
    "gn:dem":679,
    "gn:feature_class":"P",
    "gn:feature_code":"PPL",
    "gn:name":"\u0100b Sar\u012bnah",
    "gn:population":0,
    "gn:timezone":"Asia/Kabul",
    "iso:country":"AF",
    "name:fas_x_preferred":[
        "\u0622\u0628 \u0633\u0631\u064a\u0646\u0647"
    ],
    "name:rus_x_preferred":[
        "\u0410\u0431\u0441\u0430\u0440\u0438\u043d\u0430"
    ],
    "name:und_x_variant":[
        "\u0100b Sa\u1e5f\u012bna",
        "Absarina",
        "\u0100b Sar\u012bneh",
        "\u0100b Sar\u012bnah",
        "\u0622\u0628 \u0633\u0631\u06cc\u0646\u0647"
    ],
    "wof:name":"Ab Sarinah",
    "wof:placetype":"locality"
},
  "geometry": {"coordinates":[69.37297,36.7868],"type":"Point"}
}