{
  "type": "Feature",
  "properties": {
    "gn:admin1_code":"07",
    "gn:admin2_code":"1803",
    "gn:asciiname":"Nughayli Bala",
    "gn:country_code":"AF",
    "gn:dem":915,
    "gn:feature_class":"P",
    "gn:feature_code":"PPL",
    "gn:name":"N\u016bghayl\u012b B\u0101l\u0101",
    "gn:population":0,
    "gn:timezone":"Asia/Kabul",
    "iso:country":"AF",
    "name:und_x_variant":[
        "N\u016bghayl\u012b B\u0101l\u0101",
        "\u0646\u0648\u063a\u064a\u0644\u06cc \u0628\u0627\u0644\u0627"
    ],
    "wof:name":"Nughayli Bala",
    "wof:placetype":"locality"
},
  "geometry": {"coordinates":[64.56469,35.81035],"type":"Point"}
}