{
  "type": "Feature",
  "properties": {
    "gn:admin1_code":"08",
    "gn:admin2_code":"601",
    "gn:asciiname":"Qal'ah-ye Mulla-ye Lang",
    "gn:country_code":"AF",
    "gn:dem":2333,
    "gn:feature_class":"P",
    "gn:feature_code":"PPL",
    "gn:name":"Qal\u2018ah-ye Mull\u0101-ye Lang",
    "gn:population":0,
    "gn:timezone":"Asia/Kabul",
    "iso:country":"AF",
    "name:fas_x_preferred":[
        "\u0642\u0644\u0639\u0647\u0654 \u0645\u0644\u0627\u06cc \u0644\u0646\u06af"
    ],
    "name:und_x_variant":[
        "Kalamullayi-Lang",
        "Qal\u2018a-i-Mull\u0101-i-Lang",
        "Qal\u2018eh-ye Moll\u0101-ye Lang",
        "Qal\u2018a Mull\u0101-i-Lang",
        "Qal\u2018ah Mull\u0101-ye Lang",
        "Qal\u2018eh Moll\u0101-ye Lang",
        "Qal\u2018ah-ye Mull\u0101-ye Lang",
        "\u0642\u0644\u0639\u0647 \u0645\u0644\u0627 \u0644\u0646\u06af"
    ],
    "wof:name":"Qal'ah-ye Mulla-ye Lang",
    "wof:placetype":"locality"
},
  "geometry": {"coordinates":[68.45585,33.61702],"type":"Point"}
}