{
  "type": "Feature",
  "properties": {
    "gn:admin1_code":"8",
    "gn:admin2_code":"605.0",
    "gn:asciiname":"Dahan-e Qol",
    "gn:country_code":"AF",
    "gn:dem":2809,
    "gn:feature_class":"P",
    "gn:feature_code":"PPL",
    "gn:name":"Dah\u0101n-e Q\u014dl",
    "gn:population":0,
    "gn:timezone":"Asia/Kabul",
    "iso:country":"AF",
    "name:und_x_variant":[
        "\u1e0eahane Q\u014dl",
        "Dahane Qolleh",
        "Dahan-e Qowl",
        "Dah\u0101n-e Q\u014dl",
        "\u062f\u0647\u0627\u0646 \u0642\u0648\u0644"
    ],
    "wof:name":"Dahan-e Qol",
    "wof:placetype":"locality"
},
  "geometry": {"coordinates":[67.37145,33.66559],"type":"Point"}
}