{
  "type": "Feature",
  "properties": {
    "gn:admin1_code":"40",
    "gn:admin2_code":"309.0",
    "gn:asciiname":"Khushk Qol",
    "gn:country_code":"AF",
    "gn:dem":2123,
    "gn:feature_class":"P",
    "gn:feature_code":"PPL",
    "gn:name":"Khushk Q\u014dl",
    "gn:population":0,
    "gn:timezone":"Asia/Kabul",
    "iso:country":"AF",
    "name:fas_x_preferred":[
        "\u062e\u0634\u06a9 \u0642\u0648\u0644"
    ],
    "name:rus_x_preferred":[
        "Khushkkul\u2019"
    ],
    "name:und_x_variant":[
        "Khushk Q\u014dl",
        "Khu\u0161kqol",
        "Khoshk Q\u014dl",
        "Khoshk Qowl"
    ],
    "wof:name":"Khushk Qol",
    "wof:placetype":"locality"
},
  "geometry": {"coordinates":[69.46434000000001,34.70147],"type":"Point"}
}