{
  "type": "Feature",
  "properties": {
    "gn:admin1_code":"39",
    "gn:admin2_code":"2603",
    "gn:asciiname":"Wardak Kot",
    "gn:country_code":"AF",
    "gn:dem":1941,
    "gn:feature_class":"P",
    "gn:feature_code":"PPL",
    "gn:name":"Wardak K\u014d\u1e6f",
    "gn:population":0,
    "gn:timezone":"Asia/Kabul",
    "iso:country":"AF",
    "name:fas_x_preferred":[
        "\u0648\u0631\u062f\u06af \u0643\u0648\u062a"
    ],
    "name:und_x_variant":[
        "Wa\u1e5f\u1e0fag K\u014dt",
        "Vardagkot",
        "Wardak K\u014d\u1e6f",
        "\u0648\u0631\u062f\u06a9 \u06a9\u0648\u067c",
        "Wardag Kowt"
    ],
    "wof:name":"Wardak Kot",
    "wof:placetype":"locality"
},
  "geometry": {"coordinates":[66.56679,32.91463],"type":"Point"}
}