{
  "type": "Feature",
  "properties": {
    "gn:admin1_code":"40",
    "gn:admin2_code":"306",
    "gn:asciiname":"Sarjow",
    "gn:country_code":"AF",
    "gn:dem":3199,
    "gn:feature_class":"P",
    "gn:feature_code":"PPL",
    "gn:name":"Sarjow",
    "gn:population":0,
    "gn:timezone":"Asia/Kabul",
    "iso:country":"AF",
    "name:und_x_variant":[
        "Sardzhau",
        "Sarjaw",
        "Sarjow",
        "\u0633\u0631\u062c\u0648"
    ],
    "wof:name":"Sarjow",
    "wof:placetype":"locality"
},
  "geometry": {"coordinates":[68.37891999999999,34.8692],"type":"Point"}
}