{
  "type": "Feature",
  "properties": {
    "gn:admin1_code":"33",
    "gn:admin2_code":"3101.0",
    "gn:asciiname":"Apardi",
    "gn:country_code":"AF",
    "gn:dem":620,
    "gn:feature_class":"P",
    "gn:feature_code":"PPL",
    "gn:name":"Apard\u012b",
    "gn:population":0,
    "gn:timezone":"Asia/Kabul",
    "iso:country":"AF",
    "name:und_x_variant":[
        "Aprad\u012b",
        "\u0627\u067e\u0631\u062f\u06cc",
        "Apardi",
        "Apard\u012b",
        "Qaryah-ye Apard\u012b",
        "\u0642\u0631\u064a\u0647 \u0627\u067e\u0631\u062f\u06cc"
    ],
    "wof:name":"Apardi",
    "wof:placetype":"locality"
},
  "geometry": {"coordinates":[65.94261,36.24252],"type":"Point"}
}