{
  "type": "Feature",
  "properties": {
    "gn:admin1_code":"13",
    "gn:admin2_code":"101.0",
    "gn:asciiname":"Qaryah-ye Mya Sahib",
    "gn:country_code":"AF",
    "gn:dem":1812,
    "gn:feature_class":"P",
    "gn:feature_code":"PPL",
    "gn:name":"Qaryah-ye My\u0101 \u015e\u0101\u1e29ib",
    "gn:population":0,
    "gn:timezone":"Asia/Kabul",
    "iso:country":"AF",
    "name:und_x_variant":[
        "Qaryah-ye My\u0101 \u015e\u0101\u1e29ib",
        "\u0642\u0631\u06cc\u0647 \u0645\u06cc\u0627 \u0635\u0627\u062d\u0628"
    ],
    "wof:name":"Qaryah-ye Mya Sahib",
    "wof:placetype":"locality"
},
  "geometry": {"coordinates":[69.18686,34.49534],"type":"Point"}
}