{
  "type": "Feature",
  "properties": {
    "gn:admin1_code":"11",
    "gn:admin2_code":"2013",
    "gn:asciiname":"Diyar Aghah",
    "gn:country_code":"AF",
    "gn:dem":2019,
    "gn:feature_class":"P",
    "gn:feature_code":"PPL",
    "gn:name":"Diy\u0101r \u0100ghah",
    "gn:population":0,
    "gn:timezone":"Asia/Kabul",
    "iso:country":"AF",
    "name:und_x_variant":[
        "\u1e0ey\u0101\u1e5f\u0101gha",
        "D\u012b\u0101r\u0101ghah",
        "Diy\u0101r \u0100ghah",
        "\u062f\u06cc\u0627\u0631 \u0622\u063a\u0647"
    ],
    "wof:name":"Diyar Aghah",
    "wof:placetype":"locality"
},
  "geometry": {"coordinates":[63.53285,33.89147],"type":"Point"}
}