{
  "type": "Feature",
  "properties": {
    "gn:admin1_code":"01",
    "gn:admin2_code":"1120.0",
    "gn:asciiname":"Parkhich",
    "gn:country_code":"AF",
    "gn:dem":2078,
    "gn:feature_class":"P",
    "gn:feature_code":"PPL",
    "gn:name":"Parkh\u012bch",
    "gn:population":0,
    "gn:timezone":"Asia/Kabul",
    "iso:country":"AF",
    "name:und_x_variant":[
        "Pa\u1e5fkh\u012bc",
        "\u067e\u0631\u062e\u06cc\u0686",
        "Pa\u1e5fkh\u012bch",
        "Parkh\u012bch"
    ],
    "wof:name":"Parkhich",
    "wof:placetype":"locality"
},
  "geometry": {"coordinates":[70.66634000000001,37.92452],"type":"Point"}
}