{
  "type": "Feature",
  "properties": {
    "gn:admin1_code":"37",
    "gn:admin2_code":"3206.0",
    "gn:asciiname":"Sahibuddin Kelay",
    "gn:country_code":"AF",
    "gn:dem":1322,
    "gn:feature_class":"P",
    "gn:feature_code":"PPL",
    "gn:name":"\u015e\u0101\u1e29ibudd\u012bn K\u00ealay",
    "gn:population":0,
    "gn:timezone":"Asia/Kabul",
    "iso:country":"AF",
    "name:fas_x_preferred":[
        "\u0642\u0631\u064a\u06c0 \u0635\u0627\u062d\u0628 \u0627\u0644\u062f\u064a\u0646"
    ],
    "name:und_x_variant":[
        "Sakhibuddin-Kalay",
        "\u015e\u0101\u1e29ebu\u1e0f\u1e0f\u012bn Kalay",
        "\u015e\u0101\u1e29ib ud D\u012bn K\u00ealay",
        "\u015e\u0101\u1e29eb od D\u012bn Kalay",
        "\u015e\u0101\u1e29ibudd\u012bn K\u00ealay",
        "\u0635\u0627\u062d\u0628\u0627\u0644\u062f\u06cc\u0646 \u06a9\u0644\u06cc"
    ],
    "wof:name":"Sahibuddin Kelay",
    "wof:placetype":"locality"
},
  "geometry": {"coordinates":[69.76241,33.31485],"type":"Point"}
}