{
  "type": "Feature",
  "properties": {
    "gn:admin1_code":"13",
    "gn:admin2_code":"107.0",
    "gn:asciiname":"Luku",
    "gn:country_code":"AF",
    "gn:dem":1993,
    "gn:feature_class":"P",
    "gn:feature_code":"PPL",
    "gn:name":"Luku",
    "gn:population":0,
    "gn:timezone":"Asia/Kabul",
    "iso:country":"AF",
    "name:fas_x_preferred":[
        "\u0644\u0648\u0643\u0648"
    ],
    "name:und_x_variant":[
        "L\u016bk\u016b",
        "\u0644\u0648\u06a9\u0648"
    ],
    "wof:name":"Luku",
    "wof:placetype":"locality"
},
  "geometry": {"coordinates":[69.03773000000001,34.70157],"type":"Point"}
}