{
  "type": "Feature",
  "properties": {
    "gn:admin1_code":"11",
    "gn:admin2_code":"2009",
    "gn:asciiname":"Stownu",
    "gn:country_code":"AF",
    "gn:dem":789,
    "gn:feature_class":"P",
    "gn:feature_code":"PPL",
    "gn:name":"Stown\u016b",
    "gn:population":0,
    "gn:timezone":"Asia/Kabul",
    "iso:country":"AF",
    "name:und_x_variant":[
        "Stavn\u016b",
        "Stawn\u016b",
        "Stown\u016b",
        "\u0633\u062a\u0648\u0646\u0648",
        "Stavnow"
    ],
    "wof:name":"Stownu",
    "wof:placetype":"locality"
},
  "geometry": {"coordinates":[61.47864000000001,34.37937],"type":"Point"}
}