{
  "type": "Feature",
  "properties": {
    "gn:admin1_code":"27",
    "gn:admin2_code":"403.0",
    "gn:asciiname":"Dost Dar",
    "gn:country_code":"AF",
    "gn:dem":2899,
    "gn:feature_class":"P",
    "gn:feature_code":"PPL",
    "gn:name":"D\u014dst D\u0101r",
    "gn:population":0,
    "gn:timezone":"Asia/Kabul",
    "iso:country":"AF",
    "name:und_x_variant":[
        "Dostdar",
        "\u1e0e\u014dst\u1e0f\u0101\u1e5f",
        "D\u014dst D\u0101r",
        "D\u016bstd\u0101r",
        "\u062f\u0648\u0633\u062a \u062f\u0627\u0631"
    ],
    "wof:name":"Dost Dar",
    "wof:placetype":"locality"
},
  "geometry": {"coordinates":[68.13864000000001,34.49828],"type":"Point"}
}