{
  "type": "Feature",
  "properties": {
    "gn:admin1_code":"09",
    "gn:admin2_code":"2709",
    "gn:asciiname":"Khushnow",
    "gn:country_code":"AF",
    "gn:dem":2768,
    "gn:feature_class":"P",
    "gn:feature_code":"PPL",
    "gn:name":"Khushnow",
    "gn:population":0,
    "gn:timezone":"Asia/Kabul",
    "iso:country":"AF",
    "name:und_x_variant":[
        "Khus\u0304naw",
        "Khvosh N\u0101v",
        "Khushnow",
        "\u062e\u0634\u0646\u0648"
    ],
    "wof:name":"Khushnow",
    "wof:placetype":"locality"
},
  "geometry": {"coordinates":[65.72192,34.66911],"type":"Point"}
}