{
  "type": "Feature",
  "properties": {
    "gn:admin1_code":"13",
    "gn:admin2_code":"108.0",
    "gn:asciiname":"Jelgah",
    "gn:country_code":"AF",
    "gn:dem":2352,
    "gn:feature_class":"P",
    "gn:feature_code":"PPL",
    "gn:name":"J\u00ealgah",
    "gn:population":0,
    "gn:timezone":"Asia/Kabul",
    "iso:country":"AF",
    "name:rus_x_preferred":[
        "Dzhul\u2019ga"
    ],
    "name:und_x_variant":[
        "Julga",
        "Jilgah",
        "Jolgeh",
        "J\u00ealgah",
        "\u062c\u0644\u06af\u0647"
    ],
    "wof:name":"Jelgah",
    "wof:placetype":"locality"
},
  "geometry": {"coordinates":[68.91961999999999,34.56035],"type":"Point"}
}