{
  "type": "Feature",
  "properties": {
    "gn:admin1_code":"29",
    "gn:admin2_code":"2911.0",
    "gn:asciiname":"Zarmah",
    "gn:country_code":"AF",
    "gn:dem":2391,
    "gn:feature_class":"P",
    "gn:feature_code":"PPL",
    "gn:name":"Zarmah",
    "gn:population":0,
    "gn:timezone":"Asia/Kabul",
    "iso:country":"AF",
    "wof:name":"Zarmah",
    "wof:placetype":"locality"
},
  "geometry": {"coordinates":[69.08171999999999,32.86399],"type":"Point"}
}