{
  "type": "Feature",
  "properties": {
    "gn:admin1_code":"09",
    "gn:admin2_code":"2703",
    "gn:asciiname":"Surunah",
    "gn:country_code":"AF",
    "gn:dem":2528,
    "gn:feature_class":"P",
    "gn:feature_code":"PPL",
    "gn:name":"S\u016br\u016bnah",
    "gn:population":0,
    "gn:timezone":"Asia/Kabul",
    "iso:country":"AF",
    "name:und_x_variant":[
        "S\u016b\u1e5f\u016bna",
        "S\u016br\u016bnah",
        "\u0633\u0648\u0631\u0648\u0646\u0647"
    ],
    "wof:name":"Surunah",
    "wof:placetype":"locality"
},
  "geometry": {"coordinates":[63.66023000000001,33.74279],"type":"Point"}
}