{
  "type": "Feature",
  "properties": {
    "gn:admin1_code":"33",
    "gn:admin2_code":"3103",
    "gn:asciiname":"Kulor",
    "gn:country_code":"AF",
    "gn:dem":2296,
    "gn:feature_class":"P",
    "gn:feature_code":"PPL",
    "gn:name":"Kul\u014dr",
    "gn:population":0,
    "gn:timezone":"Asia/Kabul",
    "iso:country":"AF",
    "name:ceb_x_preferred":[
        "K\u016blor"
    ],
    "name:fas_x_preferred":[
        "\u06a9\u0648\u0644\u0631"
    ],
    "name:swe_x_preferred":[
        "K\u016blor"
    ],
    "name:und_x_variant":[
        "Kol\u014d\u1e5f",
        "Kolowr",
        "Kul\u014dr",
        "\u06a9\u0644\u0648\u0631"
    ],
    "wof:name":"Kulor",
    "wof:placetype":"locality"
},
  "geometry": {"coordinates":[66.24472,35.05859],"type":"Point"}
}