{
  "type": "Feature",
  "properties": {
    "gn:admin1_code":"5",
    "gn:admin2_code":"2807.0",
    "gn:asciiname":"Bayani",
    "gn:country_code":"AF",
    "gn:dem":1936,
    "gn:feature_class":"P",
    "gn:feature_code":"PPL",
    "gn:name":"Bay\u0101n\u012b",
    "gn:population":0,
    "gn:timezone":"Asia/Kabul",
    "iso:country":"AF",
    "name:deu_x_preferred":[
        "Bayani"
    ],
    "name:fra_x_preferred":[
        "Bayani"
    ],
    "name:tgl_x_preferred":[
        "Bayani"
    ],
    "name:und_x_variant":[
        "Bay\u0101n\u012b",
        "\u0628\u06cc\u0627\u0646\u06cc",
        "Ba\u012b\u0101n\u012b"
    ],
    "wof:name":"Bayani",
    "wof:placetype":"locality"
},
  "geometry": {"coordinates":[67.78426,35.19527],"type":"Point"}
}