{
  "type": "Feature",
  "properties": {
    "gn:admin1_code":"10",
    "gn:admin2_code":"2310",
    "gn:asciiname":"Khwajah 'Ali 'Ulya",
    "gn:country_code":"AF",
    "gn:dem":593,
    "gn:feature_class":"P",
    "gn:feature_code":"PPL",
    "gn:name":"Khw\u0101jah \u2018Al\u012b \u2018Uly\u0101",
    "gn:population":0,
    "gn:timezone":"Asia/Kabul",
    "iso:country":"AF",
    "name:und_x_variant":[
        "Khwaja \u2018Al\u012b \u2018Uly\u0101",
        "Khv\u0101jeh \u2018Al\u012b-e B\u0101l\u0101",
        "Khw\u0101ja Ali",
        "Khw\u0101jah \u2018Al\u012b \u2018Uly\u0101",
        "\u062e\u0648\u0627\u062c\u0647 \u0639\u0644\u06cc \u0639\u0644\u06cc\u0627",
        "Khv\u0101jeh \u2018Al\u012b \u2018Oly\u0101"
    ],
    "wof:name":"Khwajah 'Ali 'Ulya",
    "wof:placetype":"locality"
},
  "geometry": {"coordinates":[63.22221,30.33153],"type":"Point"}
}