{
  "type": "Feature",
  "properties": {
    "gn:admin1_code":"09",
    "gn:admin2_code":"2710",
    "gn:asciiname":"Qishlaq Haji 'Abdullah",
    "gn:country_code":"AF",
    "gn:dem":2551,
    "gn:feature_class":"P",
    "gn:feature_code":"PPL",
    "gn:name":"Qishl\u0101q \u1e28\u0101j\u012b \u2018Abdull\u0101h",
    "gn:population":0,
    "gn:timezone":"Asia/Kabul",
    "iso:country":"AF",
    "name:und_x_variant":[
        "Qos\u0304 H\u0331\u0101ji \u2019Ab\u1e0full\u0101h",
        "Qs H\u0101ji Ab\u1e0full\u0101h",
        "Qishl\u0101q \u1e28\u0101j\u012b \u2018Abdull\u0101h",
        "\u0642\u0634\u0644\u0627\u0642 \u062d\u0627\u062c\u06cc \u0639\u0628\u062f\u0627\u0644\u0644\u0640\u0647",
        "Qosh \u1e28\u0101jj\u012b \u2018Abdoll\u0101h"
    ],
    "wof:name":"Qishlaq Haji 'Abdullah",
    "wof:placetype":"locality"
},
  "geometry": {"coordinates":[65.48783,34.17923],"type":"Point"}
}