{
  "type": "Feature",
  "properties": {
    "gn:admin1_code":"18",
    "gn:admin2_code":"809.0",
    "gn:asciiname":"Sur Dag",
    "gn:country_code":"AF",
    "gn:dem":621,
    "gn:feature_class":"P",
    "gn:feature_code":"PPL",
    "gn:name":"S\u016br \u1e0e\u0101g",
    "gn:population":0,
    "gn:timezone":"Asia/Kabul",
    "iso:country":"AF",
    "wof:name":"Sur Dag",
    "wof:placetype":"locality"
},
  "geometry": {"coordinates":[70.6568,34.27804],"type":"Point"}
}