{
  "type": "Feature",
  "properties": {
    "gn:admin1_code":"42",
    "gn:admin2_code":"3303",
    "gn:asciiname":"Dehgak",
    "gn:country_code":"AF",
    "gn:dem":2211,
    "gn:feature_class":"P",
    "gn:feature_code":"PPL",
    "gn:name":"Dehgak",
    "gn:population":0,
    "gn:timezone":"Asia/Kabul",
    "iso:country":"AF",
    "name:fas_x_preferred":[
        "\u062f\u06af\u0643"
    ],
    "name:rus_x_preferred":[
        "\u0414\u0438\u0433\u0430\u043a"
    ],
    "name:und_x_variant":[
        "Digak",
        "Degak",
        "Dehgak",
        "\u062f\u0647 \u06af\u06a9"
    ],
    "wof:name":"Dehgak",
    "wof:placetype":"locality"
},
  "geometry": {"coordinates":[69.77606,35.46329],"type":"Point"}
}