{
  "type": "Feature",
  "properties": {
    "gn:admin1_code":"10",
    "gn:admin2_code":"2305",
    "gn:asciiname":"Lwar Qiblatu",
    "gn:country_code":"AF",
    "gn:dem":1839,
    "gn:feature_class":"P",
    "gn:feature_code":"PPL",
    "gn:name":"Lwa\u1e5f Qiblat\u016b",
    "gn:population":0,
    "gn:timezone":"Asia/Kabul",
    "iso:country":"AF",
    "name:rus_x_preferred":[
        "L\u2019varkiblatu"
    ],
    "name:und_x_variant":[
        "Lwar Qiblat\u016b",
        "Lwa\u1e5f Qiblat\u016b",
        "\u0644\u0648\u0693 \u0642\u0628\u0644\u062a\u0648",
        "Lwa\u1e5f Qeblat\u016b"
    ],
    "wof:name":"Lwar Qiblatu",
    "wof:placetype":"locality"
},
  "geometry": {"coordinates":[64.98850999999999,32.93349],"type":"Point"}
}