{
  "type": "Feature",
  "properties": {
    "gn:admin1_code":"02",
    "gn:admin2_code":"1904.0",
    "gn:asciiname":"Yakhak",
    "gn:country_code":"AF",
    "gn:dem":1728,
    "gn:feature_class":"P",
    "gn:feature_code":"PPL",
    "gn:name":"Yakhak",
    "gn:population":0,
    "gn:timezone":"Asia/Kabul",
    "iso:country":"AF",
    "name:und_x_variant":[
        "\u06cc\u062e\u06a9"
    ],
    "wof:name":"Yakhak",
    "wof:placetype":"locality"
},
  "geometry": {"coordinates":[64.07460999999999,34.8892],"type":"Point"}
}