{
  "type": "Feature",
  "properties": {
    "gn:admin1_code":"18",
    "gn:admin2_code":"810.0",
    "gn:asciiname":"Damgal",
    "gn:country_code":"AF",
    "gn:dem":1489,
    "gn:feature_class":"P",
    "gn:feature_code":"PPL",
    "gn:name":"Damgal",
    "gn:population":0,
    "gn:timezone":"Asia/Kabul",
    "iso:country":"AF",
    "name:rus_x_preferred":[
        "Damgal\u2019"
    ],
    "name:und_x_variant":[
        "\u062f\u0645\u06af\u0644"
    ],
    "wof:name":"Damgal",
    "wof:placetype":"locality"
},
  "geometry": {"coordinates":[70.69974000000001,34.04473],"type":"Point"}
}