{
  "type": "Feature",
  "properties": {
    "gn:admin1_code":"23",
    "gn:admin2_code":"2403",
    "gn:asciiname":"Gumbad",
    "gn:country_code":"AF",
    "gn:dem":1531,
    "gn:feature_class":"P",
    "gn:feature_code":"PPL",
    "gn:name":"Gumbad",
    "gn:population":0,
    "gn:timezone":"Asia/Kabul",
    "iso:country":"AF",
    "name:ceb_x_preferred":[
        "Gumbad"
    ],
    "name:fas_x_preferred":[
        "\u06af\u0646\u0628\u062f"
    ],
    "name:swe_x_preferred":[
        "Gumbad"
    ],
    "name:und_x_variant":[
        "Gumba\u1e0f",
        "Gumbad",
        "\u06af\u0645\u0628\u062f",
        "Gonbad"
    ],
    "wof:name":"Gumbad",
    "wof:placetype":"locality"
},
  "geometry": {"coordinates":[65.88882,32.18425999999999],"type":"Point"}
}