{
  "type": "Feature",
  "properties": {
    "gn:admin1_code":"13",
    "gn:admin2_code":"112.0",
    "gn:asciiname":"Manu Kelay",
    "gn:country_code":"AF",
    "gn:dem":1319,
    "gn:feature_class":"P",
    "gn:feature_code":"PPL",
    "gn:name":"M\u0101\u1e49\u016b K\u00ealay",
    "gn:population":0,
    "gn:timezone":"Asia/Kabul",
    "iso:country":"AF",
    "name:und_x_variant":[
        "M\u0101\u1e49\u016b K\u00ealay",
        "\u0645\u0627\u06bc\u0648 \u06a9\u0644\u06cc"
    ],
    "wof:name":"Manu Kelay",
    "wof:placetype":"locality"
},
  "geometry": {"coordinates":[69.58136999999999,34.58714000000001],"type":"Point"}
}