{
  "type": "Feature",
  "properties": {
    "gn:admin1_code":"05",
    "gn:admin2_code":"2806",
    "gn:asciiname":"Kharmah Sang",
    "gn:country_code":"AF",
    "gn:dem":2536,
    "gn:feature_class":"P",
    "gn:feature_code":"PPL",
    "gn:name":"Kharmah Sang",
    "gn:population":0,
    "gn:timezone":"Asia/Kabul",
    "iso:country":"AF",
    "name:und_x_variant":[
        "Kharmasang",
        "Kha\u1e5fmasang",
        "Kharmehsang",
        "Kharmah Sang",
        "\u062e\u0631\u0645\u0647 \u0633\u0646\u06af"
    ],
    "wof:name":"Kharmah Sang",
    "wof:placetype":"locality"
},
  "geometry": {"coordinates":[67.2111,34.0151],"type":"Point"}
}