{
  "type": "Feature",
  "properties": {
    "gn:admin1_code":"10",
    "gn:admin2_code":"2303.0",
    "gn:asciiname":"Besham",
    "gn:country_code":"AF",
    "gn:dem":1018,
    "gn:feature_class":"P",
    "gn:feature_code":"PPL",
    "gn:name":"B\u0113sh\u0101m",
    "gn:population":0,
    "gn:timezone":"Asia/Kabul",
    "iso:country":"AF",
    "name:fas_x_preferred":[
        "\u0628\u0634\u0627\u0645"
    ],
    "name:ita_x_preferred":[
        "Besham"
    ],
    "name:und_x_variant":[
        "B\u0113\u0161\u0101m",
        "Bensham",
        "Besham",
        "B\u0113sh\u0101m",
        "\u0628\u06d0\u0634\u0627\u0645",
        "B\u012bsh\u0101m"
    ],
    "name:urd_x_preferred":[
        "\u0628\u0634\u0627\u0645"
    ],
    "name:vie_x_preferred":[
        "Besham"
    ],
    "wof:name":"Besham",
    "wof:placetype":"locality"
},
  "geometry": {"coordinates":[64.93753000000001,32.30479],"type":"Point"}
}