{
  "type": "Feature",
  "properties": {
    "gn:admin1_code":"05",
    "gn:admin2_code":"2806",
    "gn:asciiname":"Riwkak",
    "gn:country_code":"AF",
    "gn:dem":3070,
    "gn:feature_class":"P",
    "gn:feature_code":"PPL",
    "gn:name":"Riwkak",
    "gn:population":0,
    "gn:timezone":"Asia/Kabul",
    "iso:country":"AF",
    "name:und_x_variant":[
        "Rivkak",
        "R\u012bwkak",
        "Riwkak",
        "\u0631\u0648\u06a9\u06a9"
    ],
    "wof:name":"Riwkak",
    "wof:placetype":"locality"
},
  "geometry": {"coordinates":[67.13481999999999,34.03537],"type":"Point"}
}