{
  "type": "Feature",
  "properties": {
    "gn:admin1_code":"29",
    "gn:admin2_code":"2913",
    "gn:asciiname":"Marzek",
    "gn:country_code":"AF",
    "gn:dem":2620,
    "gn:feature_class":"P",
    "gn:feature_code":"PPL",
    "gn:name":"M\u0101rz\u00eak",
    "gn:population":0,
    "gn:timezone":"Asia/Kabul",
    "iso:country":"AF",
    "name:und_x_variant":[
        "M\u0101\u1e5fzek",
        "M\u0101rz\u00eak",
        "\u0645\u0627\u0631\u0632\u06a9"
    ],
    "wof:name":"Marzek",
    "wof:placetype":"locality"
},
  "geometry": {"coordinates":[69.27176999999999,33.20731],"type":"Point"}
}