{
  "type": "Feature",
  "properties": {
    "gn:admin1_code":"10",
    "gn:admin2_code":"2308.0",
    "gn:asciiname":"Balotsan",
    "gn:country_code":"AF",
    "gn:dem":807,
    "gn:feature_class":"P",
    "gn:feature_code":"PPL",
    "gn:name":"Bal\u014dts\u0101n",
    "gn:population":0,
    "gn:timezone":"Asia/Kabul",
    "iso:country":"AF",
    "name:fas_x_preferred":[
        "\u0628\u0644\u0648\u0686\u0627\u0646"
    ],
    "name:und_x_variant":[
        "Bal\u016bc\u0101n",
        "Bal\u014dc\u0101n",
        "Baluchan",
        "Balochan",
        "Bal\u016bch\u0101n",
        "Bal\u014dts\u0101n",
        "\u0628\u0644\u0648\u0685\u0627\u0646",
        "Bal\u016bts\u0101n",
        "\u0628\u0644\u0648\u0686\u0627\u0646"
    ],
    "wof:name":"Balotsan",
    "wof:placetype":"locality"
},
  "geometry": {"coordinates":[64.23520000000001,31.67956],"type":"Point"}
}