{
  "type": "Feature",
  "properties": {
    "gn:admin1_code":"08",
    "gn:admin2_code":"604.0",
    "gn:asciiname":"Argbiru",
    "gn:country_code":"AF",
    "gn:dem":2942,
    "gn:feature_class":"P",
    "gn:feature_code":"PPL",
    "gn:name":"Argbir\u016b",
    "gn:population":0,
    "gn:timezone":"Asia/Kabul",
    "iso:country":"AF",
    "name:und_x_variant":[
        "Argbir\u016b",
        "\u0627\u0631\u06af\u0628\u0631\u0648"
    ],
    "wof:name":"Argbiru",
    "wof:placetype":"locality"
},
  "geometry": {"coordinates":[67.54921999999999,33.95403],"type":"Point"}
}