{
  "type": "Feature",
  "properties": {
    "gn:admin1_code":"39",
    "gn:admin2_code":"2602",
    "gn:asciiname":"Raz Muhammad Khan",
    "gn:country_code":"AF",
    "gn:dem":1705,
    "gn:feature_class":"P",
    "gn:feature_code":"PPL",
    "gn:name":"R\u0101z Mu\u1e29ammad Kh\u0101n",
    "gn:population":0,
    "gn:timezone":"Asia/Kabul",
    "iso:country":"AF",
    "name:und_x_variant":[
        "Razmukhammedkhan",
        "\u1e5e\u0101zmohamma\u1e0fkh\u0101n",
        "\u0100\u0161iza\u2019i",
        "R\u0101z Mu\u1e29ammad Kh\u0101n",
        "\u0631\u0627\u0632 \u0645\u062d\u0645\u062f \u062e\u0627\u0646",
        "R\u0101z Mo\u1e29ammad Kh\u0101n",
        "\u0100shiza\u012b",
        "\u0622\u0634\u0632\u06cc"
    ],
    "wof:name":"Raz Muhammad Khan",
    "wof:placetype":"locality"
},
  "geometry": {"coordinates":[66.08126999999999,32.86416],"type":"Point"}
}