{
  "type": "Feature",
  "properties": {
    "gn:admin1_code":"18",
    "gn:admin2_code":"805",
    "gn:asciiname":"Khozah Khel",
    "gn:country_code":"AF",
    "gn:dem":1388,
    "gn:feature_class":"P",
    "gn:feature_code":"PPL",
    "gn:name":"Kh\u014dzah Kh\u0113l",
    "gn:population":0,
    "gn:timezone":"Asia/Kabul",
    "iso:country":"AF",
    "name:fas_x_preferred":[
        "\u062e\u0632\u0647 \u062e\u064a\u0644"
    ],
    "name:rus_x_preferred":[
        "Khuzakheyl\u2019"
    ],
    "name:und_x_variant":[
        "Khozakh\u0113l",
        "Khozakheyl",
        "Kh\u014dzah Kh\u0113l",
        "\u062e\u0648\u0632\u0647 \u062e\u06d0\u0644"
    ],
    "wof:name":"Khozah Khel",
    "wof:placetype":"locality"
},
  "geometry": {"coordinates":[70.18856,34.19459000000001],"type":"Point"}
}