{
  "type": "Feature",
  "properties": {
    "gn:admin1_code":"01",
    "gn:admin2_code":"1126.0",
    "gn:asciiname":"Darah-ye Rast",
    "gn:country_code":"AF",
    "gn:dem":1183,
    "gn:feature_class":"P",
    "gn:feature_code":"PPL",
    "gn:name":"Darah-ye R\u0101st",
    "gn:population":0,
    "gn:timezone":"Asia/Kabul",
    "iso:country":"AF",
    "name:und_x_variant":[
        "Darrah-i-\u1e5e\u0101st",
        "Darreh-ye R\u0101st",
        "Darah-ye R\u0101st",
        "\u062f\u0631\u06c0 \u0631\u0627\u0633\u062a"
    ],
    "wof:name":"Darah-ye Rast",
    "wof:placetype":"locality"
},
  "geometry": {"coordinates":[70.33264,37.24026],"type":"Point"}
}