{
  "type": "Feature",
  "properties": {
    "gn:admin1_code":"10",
    "gn:admin2_code":"2306",
    "gn:asciiname":"Qaryah-ye Barang",
    "gn:country_code":"AF",
    "gn:dem":1104,
    "gn:feature_class":"P",
    "gn:feature_code":"PPL",
    "gn:name":"Qaryah-ye Barang",
    "gn:population":0,
    "gn:timezone":"Asia/Kabul",
    "iso:country":"AF",
    "name:rus_x_preferred":[
        "Kar\u2019yayi-Barang"
    ],
    "name:und_x_variant":[
        "Qa\u1e5fya-i-Ba\u1e5fa\u1e49g",
        "Qaryah-ye Barang",
        "\u0642\u0631\u06cc\u0647 \u0628\u0631\u0646\u06af",
        "Qaryeh-ye Barang"
    ],
    "wof:name":"Qaryah-ye Barang",
    "wof:placetype":"locality"
},
  "geometry": {"coordinates":[64.49507,32.24405],"type":"Point"}
}