{
  "type": "Feature",
  "properties": {
    "gn:admin1_code":"3",
    "gn:admin2_code":"1307.0",
    "gn:asciiname":"Chaylah",
    "gn:country_code":"AF",
    "gn:dem":2491,
    "gn:feature_class":"P",
    "gn:feature_code":"PPL",
    "gn:name":"Chaylah",
    "gn:population":0,
    "gn:timezone":"Asia/Kabul",
    "iso:country":"AF",
    "name:und_x_variant":[
        "\u010cayla",
        "Chayla",
        "Chaylah",
        "\u0686\u06cc\u0644\u0647"
    ],
    "wof:name":"Chaylah",
    "wof:placetype":"locality"
},
  "geometry": {"coordinates":[69.05382,35.79338],"type":"Point"}
}