{
  "type": "Feature",
  "properties": {
    "gn:admin1_code":"17",
    "gn:admin2_code":"507",
    "gn:asciiname":"Gudale Kelay",
    "gn:country_code":"AF",
    "gn:dem":2443,
    "gn:feature_class":"P",
    "gn:feature_code":"PPL",
    "gn:name":"Gu\u1e0fal\u0113 K\u00ealay",
    "gn:population":0,
    "gn:timezone":"Asia/Kabul",
    "iso:country":"AF",
    "name:und_x_variant":[
        "Gudalekalay",
        "G\u016b\u1e0fal\u0113 K\u00ealay",
        "Godal\u0113 Kalay",
        "Gu\u1e0fal\u0113 K\u00ealay",
        "\u06af\u0689\u0644\u06d0 \u06a9\u0644\u06cc"
    ],
    "wof:name":"Gudale Kelay",
    "wof:placetype":"locality"
},
  "geometry": {"coordinates":[68.86065000000001,33.71423],"type":"Point"}
}