{
  "type": "Feature",
  "properties": {
    "gn:admin1_code":"30",
    "gn:admin2_code":"1610.0",
    "gn:asciiname":"Bikhak",
    "gn:country_code":"AF",
    "gn:dem":1721,
    "gn:feature_class":"P",
    "gn:feature_code":"PPL",
    "gn:name":"Bikhak",
    "gn:population":0,
    "gn:timezone":"Asia/Kabul",
    "iso:country":"AF",
    "name:und_x_variant":[
        "\u0628\u062e\u06a9"
    ],
    "wof:name":"Bikhak",
    "wof:placetype":"locality"
},
  "geometry": {"coordinates":[66.99852,36.02715999999999],"type":"Point"}
}