{
  "type": "Feature",
  "properties": {
    "gn:admin1_code":"18",
    "gn:admin2_code":"807.0",
    "gn:asciiname":"Mirza Bagh",
    "gn:country_code":"AF",
    "gn:dem":1511,
    "gn:feature_class":"P",
    "gn:feature_code":"PPL",
    "gn:name":"M\u012brz\u0101 B\u0101gh",
    "gn:population":0,
    "gn:timezone":"Asia/Kabul",
    "iso:country":"AF",
    "wof:name":"Mirza Bagh",
    "wof:placetype":"locality"
},
  "geometry": {"coordinates":[70.23903,34.13948],"type":"Point"}
}