{
  "type": "Feature",
  "properties": {
    "gn:admin1_code":"23",
    "gn:admin2_code":"2412.0",
    "gn:asciiname":"Lwar Babey",
    "gn:country_code":"AF",
    "gn:dem":1595,
    "gn:feature_class":"P",
    "gn:feature_code":"PPL",
    "gn:name":"Lw\u0101\u1e5f B\u0101b\u00eay",
    "gn:population":0,
    "gn:timezone":"Asia/Kabul",
    "iso:country":"AF",
    "name:rus_x_preferred":[
        "L\u2019varbabay"
    ],
    "name:und_x_variant":[
        "Lw\u0101\u1e5f B\u0101b\u00eay",
        "Lw\u0101\u1e5f B\u0101bey",
        "\u0644\u0648\u0627\u0693 \u0628\u0627\u0628\u06cd"
    ],
    "wof:name":"Lwar Babey",
    "wof:placetype":"locality"
},
  "geometry": {"coordinates":[66.84447,31.47825],"type":"Point"}
}