{
  "type": "Feature",
  "properties": {
    "gn:admin1_code":"23",
    "gn:admin2_code":"2403",
    "gn:asciiname":"Khak-e Shirin",
    "gn:country_code":"AF",
    "gn:dem":1349,
    "gn:feature_class":"P",
    "gn:feature_code":"PPL",
    "gn:name":"Kh\u0101k-e Sh\u012br\u012bn",
    "gn:population":0,
    "gn:timezone":"Asia/Kabul",
    "iso:country":"AF",
    "name:und_x_variant":[
        "Khaki-Shirin",
        "Kh\u0101ke \u0160ir\u012bn",
        "Kh\u0101k-e Shir\u012bn",
        "\u062e\u0627\u06a9 \u0634\u0631\u06cc\u0646",
        "Kh\u0101k-e Sh\u012br\u012bn",
        "\u062e\u0627\u06a9 \u0634\u064a\u0631\u06cc\u0646"
    ],
    "wof:name":"Khak-e Shirin",
    "wof:placetype":"locality"
},
  "geometry": {"coordinates":[66.1613,32.10982],"type":"Point"}
}