{
  "type": "Feature",
  "properties": {
    "gn:admin1_code":"06",
    "gn:admin2_code":"2105",
    "gn:asciiname":"Shurkh Khara",
    "gn:country_code":"AF",
    "gn:dem":1084,
    "gn:feature_class":"P",
    "gn:feature_code":"PPL",
    "gn:name":"Sh\u016brkh Kh\u0101r\u0101",
    "gn:population":0,
    "gn:timezone":"Asia/Kabul",
    "iso:country":"AF",
    "name:und_x_variant":[
        "Sk\u016brkh Kh\u0101r\u0101",
        "Surkhkhara",
        "S\u016b\u1e5fkh Kh\u0101\u1e5f\u0101",
        "Sorkh Kh\u0101r\u0101",
        "Sh\u016brkh Kh\u0101r\u0101",
        "\u0634\u0648\u0631\u062e \u062e\u0627\u0631\u0627"
    ],
    "wof:name":"Shurkh Khara",
    "wof:placetype":"locality"
},
  "geometry": {"coordinates":[62.92103,32.97652],"type":"Point"}
}