{
  "type": "Feature",
  "properties": {
    "gn:admin1_code":"13",
    "gn:admin2_code":"112.0",
    "gn:asciiname":"Indzeri Kelay",
    "gn:country_code":"AF",
    "gn:dem":1715,
    "gn:feature_class":"P",
    "gn:feature_code":"PPL",
    "gn:name":"Indz\u00ear\u012b K\u00ealay",
    "gn:population":0,
    "gn:timezone":"Asia/Kabul",
    "iso:country":"AF",
    "name:und_x_variant":[
        "Indz\u00ear\u012b K\u00ealay",
        "\u0627\u0646\u0681\u0631\u06cc \u06a9\u0644\u06cc"
    ],
    "wof:name":"Indzeri Kelay",
    "wof:placetype":"locality"
},
  "geometry": {"coordinates":[69.59168000000001,34.5201],"type":"Point"}
}