{
  "type": "Feature",
  "properties": {
    "gn:admin1_code":"06",
    "gn:admin2_code":"2104",
    "gn:asciiname":"Qaryah-ye Mulla Satar",
    "gn:country_code":"AF",
    "gn:dem":1228,
    "gn:feature_class":"P",
    "gn:feature_code":"PPL",
    "gn:name":"Qaryah-ye Mull\u0101 Sat\u0101r",
    "gn:population":0,
    "gn:timezone":"Asia/Kabul",
    "iso:country":"AF",
    "name:und_x_variant":[
        "Qa\u1e5fya-i-Mull\u0101 Satt\u0101\u1e5f",
        "Qaryah-ye Mull\u0101 Sat\u0101r",
        "\u0642\u0631\u06cc\u06c0 \u0645\u0644\u0627 \u0633\u062a\u0627\u0631",
        "Qaryeh-ye Moll\u0101 Satt\u0101r"
    ],
    "wof:name":"Qaryah-ye Mulla Satar",
    "wof:placetype":"locality"
},
  "geometry": {"coordinates":[63.52085,33.12161],"type":"Point"}
}