{
  "type": "Feature",
  "properties": {
    "gn:admin1_code":"01",
    "gn:admin2_code":"1110",
    "gn:asciiname":"Minah Du",
    "gn:country_code":"AF",
    "gn:dem":2324,
    "gn:feature_class":"P",
    "gn:feature_code":"PPL",
    "gn:name":"M\u012bnah D\u016b",
    "gn:population":0,
    "gn:timezone":"Asia/Kabul",
    "iso:country":"AF",
    "name:und_x_variant":[
        "M\u012bna \u1e0eu",
        "\u0645\u06cc\u0646\u0647 \u062f\u0648",
        "M\u012bn\u0101 Do",
        "M\u012bnah D\u016b"
    ],
    "wof:name":"Minah Du",
    "wof:placetype":"locality"
},
  "geometry": {"coordinates":[70.81872,38.30758],"type":"Point"}
}