{
  "type": "Feature",
  "properties": {
    "gn:admin1_code":"37",
    "gn:admin2_code":"3213.0",
    "gn:asciiname":"Haram Kotah",
    "gn:country_code":"AF",
    "gn:dem":1707,
    "gn:feature_class":"P",
    "gn:feature_code":"PPL",
    "gn:name":"\u1e28ar\u0101m K\u014d\u1e6fah",
    "gn:population":0,
    "gn:timezone":"Asia/Kabul",
    "iso:country":"AF",
    "name:fas_x_preferred":[
        "\u062d\u0631\u0627\u0645 \u0643\u0648\u062a\u0647"
    ],
    "name:und_x_variant":[
        "Kharamkota",
        "\u1e28a\u1e5f\u0101m K\u014dta",
        "\u1e28ar\u0101m K\u014d\u1e6fah",
        "\u1e28ar\u0101m Kowtah",
        "\u062d\u0631\u0627\u0645 \u0643\u0648\u062a\u0647",
        "\u062d\u0631\u0627\u0645 \u0643\u0648\u067c\u0647"
    ],
    "wof:name":"Haram Kotah",
    "wof:placetype":"locality"
},
  "geometry": {"coordinates":[69.54156,33.33898],"type":"Point"}
}