{
  "type": "Feature",
  "properties": {
    "gn:admin1_code":"31",
    "gn:admin2_code":"1711",
    "gn:asciiname":"Sher Bayq",
    "gn:country_code":"AF",
    "gn:dem":964,
    "gn:feature_class":"P",
    "gn:feature_code":"PPL",
    "gn:name":"Sh\u0113r Bayq",
    "gn:population":0,
    "gn:timezone":"Asia/Kabul",
    "iso:country":"AF",
    "name:und_x_variant":[
        "Qaryeh-ye Sh\u012br Beyk",
        "Sher Beg Bacha",
        "Shayr Bayq",
        "Sh\u012br Beyg Bachcheh",
        "Sh\u012br Beyg",
        "\u0634\u06cc\u0631 \u0628\u06cc\u0642",
        "Sh\u0113r Bayq"
    ],
    "wof:name":"Sher Bayq",
    "wof:placetype":"locality"
},
  "geometry": {"coordinates":[65.37289,36.06215],"type":"Point"}
}