{
  "type": "Feature",
  "properties": {
    "gn:admin1_code":"8",
    "gn:admin2_code":"613.0",
    "gn:asciiname":"Kot Khanah",
    "gn:country_code":"AF",
    "gn:dem":2604,
    "gn:feature_class":"P",
    "gn:feature_code":"PPL",
    "gn:name":"K\u014d\u1e6f Kh\u0101nah",
    "gn:population":0,
    "gn:timezone":"Asia/Kabul",
    "iso:country":"AF",
    "name:fas_x_preferred":[
        "\u0643\u0648\u062a\u062e\u0627\u0646\u0647"
    ],
    "name:rus_x_preferred":[
        "\u041a\u043e\u0442\u0445\u0430\u043d\u0430"
    ],
    "name:und_x_variant":[
        "K\u014dtkh\u0101na",
        "Kotkhana",
        "Koth\u0101na",
        "Ko\u1e6fh\u0101nah",
        "Kowtkh\u0101neh",
        "K\u014d\u1e6f Kh\u0101nah",
        "\u06a9\u0648\u067c \u062e\u0627\u0646\u0647"
    ],
    "wof:name":"Kot Khanah",
    "wof:placetype":"locality"
},
  "geometry": {"coordinates":[67.74778000000001,33.17433],"type":"Point"}
}