{
  "type": "Feature",
  "properties": {
    "gn:admin1_code":"13",
    "gn:admin2_code":"114",
    "gn:asciiname":"Mayan Khel",
    "gn:country_code":"AF",
    "gn:dem":1821,
    "gn:feature_class":"P",
    "gn:feature_code":"PPL",
    "gn:name":"Mayan Kh\u0113l",
    "gn:population":0,
    "gn:timezone":"Asia/Kabul",
    "iso:country":"AF",
    "name:rus_x_preferred":[
        "Mayankheyl\u2019"
    ],
    "name:und_x_variant":[
        "Mayan Kheyl",
        "Mayan Kh\u0113l",
        "Mayankh\u0113l",
        "Mu\u2018ayyan Kh\u0113l",
        "\u0645\u064a\u0646 \u062e\u06d0\u0644"
    ],
    "wof:name":"Mayan Khel",
    "wof:placetype":"locality"
},
  "geometry": {"coordinates":[69.22425,34.38841],"type":"Point"}
}