{
  "type": "Feature",
  "properties": {
    "gn:admin1_code":"27",
    "gn:admin2_code":"404.0",
    "gn:asciiname":"Qal'ah-ye Khalak",
    "gn:country_code":"AF",
    "gn:dem":3012,
    "gn:feature_class":"P",
    "gn:feature_code":"PPL",
    "gn:name":"Qal\u2018ah-ye Kh\u0101lak",
    "gn:population":0,
    "gn:timezone":"Asia/Kabul",
    "iso:country":"AF",
    "name:und_x_variant":[
        "Kalakhalak",
        "Qal\u2018a-i-Khalak",
        "Qal\u2018a Khalak",
        "Qal\u2018ah-ye Kh\u0101lak",
        "Qal\u2018eh-ye Kh\u0101lak",
        "\u0642\u0644\u0639\u06c0 \u062e\u0627\u0644\u06a9"
    ],
    "wof:name":"Qal'ah-ye Khalak",
    "wof:placetype":"locality"
},
  "geometry": {"coordinates":[67.96675999999999,34.32593],"type":"Point"}
}