{
  "type": "Feature",
  "properties": {
    "gn:admin1_code":"27",
    "gn:admin2_code":"404.0",
    "gn:asciiname":"Chahar Burjah",
    "gn:country_code":"AF",
    "gn:dem":2948,
    "gn:feature_class":"P",
    "gn:feature_code":"PPL",
    "gn:name":"Chah\u0101r Burjah",
    "gn:population":0,
    "gn:timezone":"Asia/Kabul",
    "iso:country":"AF",
    "name:und_x_variant":[
        "\u010cah\u0101rburja",
        "Chakharburdzha",
        "Chah\u0101r Burjah",
        "Chah\u0101rborjeh",
        "\u0686\u0647\u0627\u0631 \u0628\u0631\u062c\u0647"
    ],
    "wof:name":"Chahar Burjah",
    "wof:placetype":"locality"
},
  "geometry": {"coordinates":[67.90468,34.3355],"type":"Point"}
}