{
  "type": "Feature",
  "properties": {
    "gn:admin1_code":"23",
    "gn:admin2_code":"2405.0",
    "gn:asciiname":"Bizhandoke",
    "gn:country_code":"AF",
    "gn:dem":1802,
    "gn:feature_class":"P",
    "gn:feature_code":"PPL",
    "gn:name":"Bizhand\u014dk\u0113",
    "gn:population":0,
    "gn:timezone":"Asia/Kabul",
    "iso:country":"AF",
    "name:fas_x_preferred":[
        "\u0628\u0698\u0646 \u062f\u0648\u06a9\u06cc"
    ],
    "name:und_x_variant":[
        "Be\u017eandok\u0113",
        "Bezandoke",
        "Bizhand\u014dk\u0113",
        "\u0628\u0698\u0646\u062f\u0648\u06a9\u06d0",
        "Bezhan\u1e0f\u016bk\u0113"
    ],
    "wof:name":"Bizhandoke",
    "wof:placetype":"locality"
},
  "geometry": {"coordinates":[65.66129000000001,32.16212],"type":"Point"}
}