{
  "type": "Feature",
  "properties": {
    "gn:admin1_code":"14",
    "gn:admin2_code":"206.0",
    "gn:asciiname":"Kastar Khel",
    "gn:country_code":"AF",
    "gn:dem":2638,
    "gn:feature_class":"P",
    "gn:feature_code":"PPL",
    "gn:name":"Kastar Kh\u0113l",
    "gn:population":0,
    "gn:timezone":"Asia/Kabul",
    "iso:country":"AF",
    "name:fas_x_preferred":[
        "\u0643\u0633\u062a\u0631 \u062e\u064a\u0644"
    ],
    "name:rus_x_preferred":[
        "Kastarkheyl\u2019"
    ],
    "name:und_x_variant":[
        "Kasta\u1e5fkh\u0113l",
        "Kastarkheyl",
        "Kastar Kh\u0113l",
        "\u06a9\u0633\u062a\u0631 \u062e\u06d0\u0644"
    ],
    "wof:name":"Kastar Khel",
    "wof:placetype":"locality"
},
  "geometry": {"coordinates":[69.85420000000001,34.90554],"type":"Point"}
}