{
  "type": "Feature",
  "properties": {
    "gn:admin1_code":"8",
    "gn:admin2_code":"606.0",
    "gn:asciiname":"Khushk Karez",
    "gn:country_code":"AF",
    "gn:dem":2989,
    "gn:feature_class":"P",
    "gn:feature_code":"PPL",
    "gn:name":"Khushk K\u0101r\u0113z",
    "gn:population":0,
    "gn:timezone":"Asia/Kabul",
    "iso:country":"AF",
    "name:und_x_variant":[
        "Khu\u0161k K\u0101r\u0113z",
        "Khoshk K\u0101r\u012bz",
        "Khushk K\u0101r\u0113z",
        "\u062e\u0634\u06a9 \u06a9\u0627\u0631\u06d0\u0632"
    ],
    "wof:name":"Khushk Karez",
    "wof:placetype":"locality"
},
  "geometry": {"coordinates":[67.45551999999999,33.40708],"type":"Point"}
}