{
  "type": "Feature",
  "properties": {
    "gn:admin1_code":"03",
    "gn:admin2_code":"1302.0",
    "gn:asciiname":"Dushawan",
    "gn:country_code":"AF",
    "gn:dem":1787,
    "gn:feature_class":"P",
    "gn:feature_code":"PPL",
    "gn:name":"Dushaw\u0101n",
    "gn:population":0,
    "gn:timezone":"Asia/Kabul",
    "iso:country":"AF",
    "name:und_x_variant":[
        "\u1e0eosaw\u0101n",
        "Doshav\u0101n",
        "Dushaw\u0101n",
        "\u062f\u0634\u0648\u0627\u0646"
    ],
    "wof:name":"Dushawan",
    "wof:placetype":"locality"
},
  "geometry": {"coordinates":[69.4064,35.64082],"type":"Point"}
}