{
  "type": "Feature",
  "properties": {
    "gn:admin1_code":"26",
    "gn:admin2_code":"1201",
    "gn:asciiname":"Shamar",
    "gn:country_code":"AF",
    "gn:dem":1307,
    "gn:feature_class":"P",
    "gn:feature_code":"PPL",
    "gn:name":"Shamar",
    "gn:population":0,
    "gn:timezone":"Asia/Kabul",
    "iso:country":"AF",
    "name:und_x_variant":[
        "Sama\u1e5f",
        "Shamar",
        "\u0634\u0645\u0631"
    ],
    "wof:name":"Shamar",
    "wof:placetype":"locality"
},
  "geometry": {"coordinates":[69.69440999999999,36.71715],"type":"Point"}
}