{
  "type": "Feature",
  "properties": {
    "gn:admin1_code":"29",
    "gn:admin2_code":"2909.0",
    "gn:asciiname":"Tazi Khel Kot",
    "gn:country_code":"AF",
    "gn:dem":2171,
    "gn:feature_class":"P",
    "gn:feature_code":"PPL",
    "gn:name":"T\u0101z\u012b Kh\u0113l K\u014d\u1e6f",
    "gn:population":0,
    "gn:timezone":"Asia/Kabul",
    "iso:country":"AF",
    "name:rus_x_preferred":[
        "Tazikheyl\u2019kot"
    ],
    "name:und_x_variant":[
        "Tazikheyl\u2019kot",
        "T\u0101zikh\u0113l K\u014dt",
        "T\u0101z\u012bkheyl Kow\u1e6f",
        "T\u0101z\u012b Kh\u0113l K\u014d\u1e6f",
        "\u062a\u0627\u0632\u06cc \u062e\u06d0\u0644 \u06a9\u0648\u067c"
    ],
    "wof:name":"Tazi Khel Kot",
    "wof:placetype":"locality"
},
  "geometry": {"coordinates":[69.24566,32.54224],"type":"Point"}
}