{
  "type": "Feature",
  "properties": {
    "gn:admin1_code":"8",
    "gn:admin2_code":"606.0",
    "gn:asciiname":"Olghu",
    "gn:country_code":"AF",
    "gn:dem":3045,
    "gn:feature_class":"P",
    "gn:feature_code":"PPL",
    "gn:name":"\u014clgh\u016b",
    "gn:population":0,
    "gn:timezone":"Asia/Kabul",
    "iso:country":"AF",
    "name:und_x_variant":[
        "\u014clghu",
        "Owlghu",
        "\u014clgh\u016b",
        "\u0627\u0648\u0644\u063a\u0648"
    ],
    "wof:name":"Olghu",
    "wof:placetype":"locality"
},
  "geometry": {"coordinates":[67.43304000000001,33.36979],"type":"Point"}
}