{
  "type": "Feature",
  "properties": {
    "gn:admin1_code":"28",
    "gn:admin2_code":"2503.0",
    "gn:asciiname":"'Alaqadari Arghandab",
    "gn:country_code":"AF",
    "gn:dem":1726,
    "gn:feature_class":"P",
    "gn:feature_code":"PPL",
    "gn:name":"\u2018Al\u0101qad\u0101r\u012b Arghand\u0101b",
    "gn:population":0,
    "gn:timezone":"Asia/Kabul",
    "iso:country":"AF",
    "name:und_x_variant":[
        "Arghand\u0101b",
        "\u2018Al\u0101qa\u1e0f\u0101\u1e5fi A\u1e5fghan\u1e0f\u0101b",
        "Alakadari-Argandab",
        "\u2018Al\u0101qad\u0101r\u012b Arghand\u0101b",
        "\u0639\u0644\u0627\u0642\u062f\u0627\u0631\u06cc \u0627\u0631\u063a\u0646\u062f\u0627\u0628",
        "\u2018Al\u0101qehd\u0101r\u012b Arghand\u0101b",
        "\u0627\u0631\u063a\u0646\u062f\u0627\u0628"
    ],
    "wof:name":"'Alaqadari Arghandab",
    "wof:placetype":"locality"
},
  "geometry": {"coordinates":[67.03713,32.55547],"type":"Point"}
}