{
  "type": "Feature",
  "properties": {
    "gn:admin1_code":"06",
    "gn:admin2_code":"2104",
    "gn:asciiname":"Qaryah-ye Kharistan",
    "gn:country_code":"AF",
    "gn:dem":1430,
    "gn:feature_class":"P",
    "gn:feature_code":"PPL",
    "gn:name":"Qaryah-ye Kh\u0101rist\u0101n",
    "gn:population":0,
    "gn:timezone":"Asia/Kabul",
    "iso:country":"AF",
    "name:rus_x_preferred":[
        "Kar\u2019yayi-Kharistan"
    ],
    "name:und_x_variant":[
        "Qa\u1e5fya-i-Kh\u0101\u1e5fest\u0101n",
        "Qaryah-ye Kh\u0101rist\u0101n",
        "\u0642\u0631\u06cc\u06c0 \u062e\u0627\u0631\u0633\u062a\u0627\u0646",
        "Qaryeh-ye Kh\u0101rest\u0101n"
    ],
    "wof:name":"Qaryah-ye Kharistan",
    "wof:placetype":"locality"
},
  "geometry": {"coordinates":[63.34371,33.25909],"type":"Point"}
}