{
  "type": "Feature",
  "properties": {
    "gn:admin1_code":"07",
    "gn:admin2_code":"1803",
    "gn:asciiname":"Khudaimat",
    "gn:country_code":"AF",
    "gn:dem":802,
    "gn:feature_class":"P",
    "gn:feature_code":"PPL",
    "gn:name":"Khud\u0101\u012bmat",
    "gn:population":0,
    "gn:timezone":"Asia/Kabul",
    "iso:country":"AF",
    "name:und_x_variant":[
        "Khu\u1e0f\u0101ymat",
        "Khud\u0101\u012bmat",
        "\u062e\u062f\u0627\u06cc\u0645\u062a",
        "Khod\u0101ymat"
    ],
    "wof:name":"Khudaimat",
    "wof:placetype":"locality"
},
  "geometry": {"coordinates":[64.55423,35.86854],"type":"Point"}
}