{
  "type": "Feature",
  "properties": {
    "gn:admin1_code":"14",
    "gn:admin2_code":"201.0",
    "gn:asciiname":"Koratas",
    "gn:country_code":"AF",
    "gn:dem":1501,
    "gn:feature_class":"P",
    "gn:feature_code":"PPL",
    "gn:name":"Koratas",
    "gn:population":0,
    "gn:timezone":"Asia/Kabul",
    "iso:country":"AF",
    "name:fas_x_preferred":[
        "\u0643\u0648\u0631\u0637\u0627\u0633"
    ],
    "name:und_x_variant":[
        "K\u014d\u1e5fa\u0163\u0101s",
        "K\u016bra\u0163\u0101s",
        "K\u014dra\u0163\u0101s",
        "\u06a9\u0648\u0631\u0637\u0627\u0633"
    ],
    "wof:name":"Koratas",
    "wof:placetype":"locality"
},
  "geometry": {"coordinates":[69.36906,35.04077],"type":"Point"}
}