{
  "type": "Feature",
  "properties": {
    "gn:admin1_code":"11",
    "gn:admin2_code":"2014",
    "gn:asciiname":"Ghowdal",
    "gn:country_code":"AF",
    "gn:dem":1015,
    "gn:feature_class":"P",
    "gn:feature_code":"PPL",
    "gn:name":"Ghowd\u0101l",
    "gn:population":0,
    "gn:timezone":"Asia/Kabul",
    "iso:country":"AF",
    "name:rus_x_preferred":[
        "Gaudal\u2019"
    ],
    "name:und_x_variant":[
        "Ghawd\u0101l",
        "Ghowd\u0101l",
        "\u063a\u0648\u062f\u0627\u0644"
    ],
    "wof:name":"Ghowdal",
    "wof:placetype":"locality"
},
  "geometry": {"coordinates":[62.17976,33.18766],"type":"Point"}
}