{
  "type": "Feature",
  "properties": {
    "gn:admin1_code":"5",
    "gn:admin2_code":"2806.0",
    "gn:asciiname":"Charq",
    "gn:country_code":"AF",
    "gn:dem":2474,
    "gn:feature_class":"P",
    "gn:feature_code":"PPL",
    "gn:name":"Charq",
    "gn:population":0,
    "gn:timezone":"Asia/Kabul",
    "iso:country":"AF",
    "name:und_x_variant":[
        "\u010carq",
        "Charg",
        "Charq",
        "\u0686\u0631\u0642"
    ],
    "wof:name":"Charq",
    "wof:placetype":"locality"
},
  "geometry": {"coordinates":[67.17971999999999,34.0892],"type":"Point"}
}