{
  "type": "Feature",
  "properties": {
    "gn:admin1_code":"26",
    "gn:admin2_code":"1204.0",
    "gn:asciiname":"Chashmah-ye Gawan",
    "gn:country_code":"AF",
    "gn:dem":978,
    "gn:feature_class":"P",
    "gn:feature_code":"PPL",
    "gn:name":"Chashmah-ye G\u0101w\u0101n",
    "gn:population":0,
    "gn:timezone":"Asia/Kabul",
    "iso:country":"AF",
    "name:rus_x_preferred":[
        "\u0427\u0430\u0448\u043c\u0430\u0439\u0438-\u0413\u0430\u0432\u0430\u043d"
    ],
    "name:und_x_variant":[
        "Cheshmeh-ye G\u0101w\u0101n",
        "Chashmayi-Gavan",
        "\u010ca\u0161ma-i-G\u0101w\u0101n",
        "Cheshmeh-ye G\u0101v\u0101n",
        "Chashmah-ye G\u0101w\u0101n",
        "\u0686\u0634\u0645\u06c0 \u06af\u0627\u0648\u0627\u0646"
    ],
    "wof:name":"Chashmah-ye Gawan",
    "wof:placetype":"locality"
},
  "geometry": {"coordinates":[69.52248,36.50234],"type":"Point"}
}