{
  "type": "Feature",
  "properties": {
    "gn:admin1_code":"14",
    "gn:admin2_code":"205.0",
    "gn:asciiname":"Sanjar Khel",
    "gn:country_code":"AF",
    "gn:dem":1465,
    "gn:feature_class":"P",
    "gn:feature_code":"PPL",
    "gn:name":"Sanjar Kh\u0113l",
    "gn:population":0,
    "gn:timezone":"Asia/Kabul",
    "iso:country":"AF",
    "name:fas_x_preferred":[
        "\u0633\u0646\u064a\u0631 \u062e\u064a\u0644"
    ],
    "name:rus_x_preferred":[
        "Sandzharkheyl\u2019"
    ],
    "name:und_x_variant":[
        "Saniarkh\u0113l",
        "Sanja\u1e5fkh\u0113l",
        "Saniarkheyl",
        "Sanjar Kh\u0113l",
        "\u0633\u0646\u062c\u0631 \u062e\u06d0\u0644"
    ],
    "wof:name":"Sanjar Khel",
    "wof:placetype":"locality"
},
  "geometry": {"coordinates":[69.71208,34.8452],"type":"Point"}
}