{
  "type": "Feature",
  "properties": {
    "gn:admin1_code":"14",
    "gn:admin2_code":"205.0",
    "gn:asciiname":"Loy Juma'at",
    "gn:country_code":"AF",
    "gn:dem":1435,
    "gn:feature_class":"P",
    "gn:feature_code":"PPL",
    "gn:name":"L\u014dy J\u016bm\u0101\u2019at",
    "gn:population":0,
    "gn:timezone":"Asia/Kabul",
    "iso:country":"AF",
    "name:fas_x_preferred":[
        "\u062c\u0645\u0627\u062a\u0654 \u0643\u0644\u0627\u0646"
    ],
    "name:und_x_variant":[
        "Loi-Dzhuma",
        "Loy Jum\u0101t",
        "L\u014dy J\u014dm\u0101t",
        "L\u016by Jum\u0101t",
        "L\u014dy J\u016bm\u0101\u2019at",
        "\u0644\u0648\u06cc \u062c\u0648\u0645\u0627\u062a"
    ],
    "wof:name":"Loy Juma'at",
    "wof:placetype":"locality"
},
  "geometry": {"coordinates":[69.70314,34.84095],"type":"Point"}
}