{
  "type": "Feature",
  "properties": {
    "gn:admin1_code":"18",
    "gn:admin2_code":"805.0",
    "gn:asciiname":"Asman Bandah",
    "gn:country_code":"AF",
    "gn:dem":1983,
    "gn:feature_class":"P",
    "gn:feature_code":"PPL",
    "gn:name":"\u0100sm\u0101n B\u0101n\u1e0fah",
    "gn:population":0,
    "gn:timezone":"Asia/Kabul",
    "iso:country":"AF",
    "name:fas_x_preferred":[
        "\u0622\u0633\u0645\u0627\u0646 \u0628\u0627\u0646\u062f\u0647"
    ],
    "name:und_x_variant":[
        "Asmanibanda",
        "\u0100sm\u0101n B\u0101ndeh",
        "\u0100sm\u0101n B\u0101n\u1e0fah",
        "\u0622\u0633\u0645\u0627\u0646 \u0628\u0627\u0646\u0689\u0647"
    ],
    "wof:name":"Asman Bandah",
    "wof:placetype":"locality"
},
  "geometry": {"coordinates":[70.09184,34.16282],"type":"Point"}
}