{
  "type": "Feature",
  "properties": {
    "gn:admin1_code":"18",
    "gn:admin2_code":"802.0",
    "gn:asciiname":"Baluts Kelay",
    "gn:country_code":"AF",
    "gn:dem":834,
    "gn:feature_class":"P",
    "gn:feature_code":"PPL",
    "gn:name":"Bal\u016bts K\u00ealay",
    "gn:population":0,
    "gn:timezone":"Asia/Kabul",
    "iso:country":"AF",
    "name:und_x_variant":[
        "Baluchkalay",
        "Bal\u016bc Kalay",
        "Bal\u016bch Kalay",
        "Bal\u016bts K\u00ealay",
        "\u0628\u0644\u0648\u0685 \u06a9\u0644\u06cc",
        "Bal\u016bch K\u00ealay",
        "\u0628\u0644\u0648\u0686 \u06a9\u0644\u06cc"
    ],
    "wof:name":"Baluts Kelay",
    "wof:placetype":"locality"
},
  "geometry": {"coordinates":[70.17511999999999,34.38926],"type":"Point"}
}