{
  "type": "Feature",
  "properties": {
    "gn:admin1_code":"27",
    "gn:admin2_code":"402.0",
    "gn:asciiname":"Dukanha-ye Sar Chashmah",
    "gn:country_code":"AF",
    "gn:dem":2554,
    "gn:feature_class":"P",
    "gn:feature_code":"PPL",
    "gn:name":"Duk\u0101nh\u0101-ye Sar Chashmah",
    "gn:population":0,
    "gn:timezone":"Asia/Kabul",
    "iso:country":"AF",
    "name:und_x_variant":[
        "Dukankhayi-Sarchashma",
        "Dok\u0101nh\u0101-i-Sar\u010da\u0161m\u0101",
        "Dok\u0101nh\u0101-i-Sarchashma",
        "Dok\u0101nh\u0101-ye-Sarcheshmeh",
        "Dok\u0101nh\u0101-ye Sar Chashmah",
        "Duk\u0101nh\u0101-ye Sar Chashmah",
        "\u062f\u06a9\u0627\u0646\u0647\u0627 \u0633\u0631 \u0686\u0634\u0645\u0647"
    ],
    "wof:name":"Dukanha-ye Sar Chashmah",
    "wof:placetype":"locality"
},
  "geometry": {"coordinates":[68.52032,34.43513],"type":"Point"}
}