{
  "type": "Feature",
  "properties": {
    "gn:admin1_code":"28",
    "gn:admin2_code":"2506.0",
    "gn:asciiname":"Karez-e Mazar",
    "gn:country_code":"AF",
    "gn:dem":1256,
    "gn:feature_class":"P",
    "gn:feature_code":"PPL",
    "gn:name":"K\u0101r\u0113z-e Maz\u0101r",
    "gn:population":0,
    "gn:timezone":"Asia/Kabul",
    "iso:country":"AF",
    "name:und_x_variant":[
        "K\u0101\u1e5f\u0113ze Maz\u0101\u1e5f",
        "Karezi-Mazor",
        "\u06a9\u0627\u0631\u06d0\u0632 \u0645\u0632\u0627\u0631",
        "K\u0101r\u012bz-e Maz\u0101r",
        "K\u0101r\u0113z-e Maz\u0101r"
    ],
    "wof:name":"Karez-e Mazar",
    "wof:placetype":"locality"
},
  "geometry": {"coordinates":[66.3128,31.79827],"type":"Point"}
}