{
  "type": "Feature",
  "properties": {
    "gn:admin1_code":"27",
    "gn:admin2_code":"407",
    "gn:asciiname":"Takyah",
    "gn:country_code":"AF",
    "gn:dem":2257,
    "gn:feature_class":"P",
    "gn:feature_code":"PPL",
    "gn:name":"Takyah",
    "gn:population":0,
    "gn:timezone":"Asia/Kabul",
    "iso:country":"AF",
    "name:rus_x_preferred":[
        "Tak\u2019ya"
    ],
    "name:und_x_variant":[
        "Takya",
        "Takyah",
        "Takyey",
        "\u062a\u06a9\u064a\u0647"
    ],
    "wof:name":"Takyah",
    "wof:placetype":"locality"
},
  "geometry": {"coordinates":[68.68004999999999,33.91708],"type":"Point"}
}