{
  "type": "Feature",
  "properties": {
    "gn:admin1_code":"09",
    "gn:admin2_code":"2704",
    "gn:asciiname":"Padak",
    "gn:country_code":"AF",
    "gn:dem":1621,
    "gn:feature_class":"P",
    "gn:feature_code":"PPL",
    "gn:name":"Pad\u0101k",
    "gn:population":0,
    "gn:timezone":"Asia/Kabul",
    "iso:country":"AF",
    "name:und_x_variant":[
        "Pad\u0101k",
        "\u067e\u062f\u0627\u06a9"
    ],
    "wof:name":"Padak",
    "wof:placetype":"locality"
},
  "geometry": {"coordinates":[63.31643,33.47647],"type":"Point"}
}