{
  "type": "Feature",
  "properties": {
    "gn:admin1_code":"40",
    "gn:admin2_code":"304.0",
    "gn:asciiname":"Daraz Gird",
    "gn:country_code":"AF",
    "gn:dem":1838,
    "gn:feature_class":"P",
    "gn:feature_code":"PPL",
    "gn:name":"Dar\u0101z Gird",
    "gn:population":0,
    "gn:timezone":"Asia/Kabul",
    "iso:country":"AF",
    "name:und_x_variant":[
        "Darazgird",
        "Dar\u0101z Gerd",
        "Dar\u0101z Gird",
        "\u062f\u0631\u0627\u0632 \u06af\u0631\u062f"
    ],
    "wof:name":"Daraz Gird",
    "wof:placetype":"locality"
},
  "geometry": {"coordinates":[68.89983000000001,35.00846],"type":"Point"}
}