{
  "type": "Feature",
  "properties": {
    "gn:admin1_code":"36",
    "gn:admin2_code":"709",
    "gn:asciiname":"Wam Hasan Khel",
    "gn:country_code":"AF",
    "gn:dem":1909,
    "gn:feature_class":"P",
    "gn:feature_code":"PPL",
    "gn:name":"W\u0101m \u1e28asan Kh\u0113l",
    "gn:population":0,
    "gn:timezone":"Asia/Kabul",
    "iso:country":"AF",
    "name:rus_x_preferred":[
        "Vamkhasankheyl\u2019"
    ],
    "name:und_x_variant":[
        "W\u0101m \u1e28asankh\u0113l",
        "W\u0101m \u1e28asan Kh\u0113l",
        "W\u0101m \u1e28asan Kheyl",
        "\u0648\u0627\u0645 \u062d\u0633\u0646 \u062e\u06d0\u0644"
    ],
    "wof:name":"Wam Hasan Khel",
    "wof:placetype":"locality"
},
  "geometry": {"coordinates":[69.657,33.81393],"type":"Point"}
}