{
  "type": "Feature",
  "properties": {
    "gn:admin1_code":"35",
    "gn:admin2_code":"902.0",
    "gn:asciiname":"Qal'ah-ye Haji 'Omar Khan",
    "gn:country_code":"AF",
    "gn:dem":613,
    "gn:feature_class":"P",
    "gn:feature_code":"PPL",
    "gn:name":"Qal\u2018ah-ye \u1e28\u0101j\u012b \u2018Omar Kh\u0101n",
    "gn:population":0,
    "gn:timezone":"Asia/Kabul",
    "iso:country":"AF",
    "name:und_x_variant":[
        "Qal\u2018ah-ye \u1e28\u0101j\u012b \u2018Omar Kh\u0101n",
        "\u0642\u0644\u0639\u06c0 \u062d\u0627\u062c\u06cc \u0639\u0645\u0631 \u062e\u0627\u0646"
    ],
    "wof:name":"Qal'ah-ye Haji 'Omar Khan",
    "wof:placetype":"locality"
},
  "geometry": {"coordinates":[70.2915,34.51946],"type":"Point"}
}