{
  "type": "Feature",
  "properties": {
    "gn:admin1_code":"19",
    "gn:admin2_code":"2205",
    "gn:asciiname":"Deh Mazang",
    "gn:country_code":"AF",
    "gn:dem":717,
    "gn:feature_class":"P",
    "gn:feature_code":"PPL",
    "gn:name":"Deh Mazang",
    "gn:population":0,
    "gn:timezone":"Asia/Kabul",
    "iso:country":"AF",
    "name:fas_x_preferred":[
        "\u062f\u0647 \u0645\u0632\u0646\u06af"
    ],
    "name:und_x_variant":[
        "Dehmazong",
        "Deh Mazang",
        "\u062f\u0647 \u0645\u0632\u0646\u06af"
    ],
    "wof:name":"Deh Mazang",
    "wof:placetype":"locality"
},
  "geometry": {"coordinates":[63.13361999999999,31.9635],"type":"Point"}
}