{
  "type": "Feature",
  "properties": {
    "gn:admin1_code":"30",
    "gn:admin2_code":"1606.0",
    "gn:asciiname":"Chahar Sang",
    "gn:country_code":"AF",
    "gn:dem":359,
    "gn:feature_class":"P",
    "gn:feature_code":"PPL",
    "gn:name":"Chah\u0101r Sang",
    "gn:population":0,
    "gn:timezone":"Asia/Kabul",
    "iso:country":"AF",
    "name:fas_x_preferred":[
        "\u0686\u0647\u0627\u0631 \u0633\u0646\u06af"
    ],
    "name:rus_x_preferred":[
        "\u0427\u0430\u0440\u0441\u0430\u043d\u0433"
    ],
    "name:und_x_variant":[
        "Ch\u0101r Sang",
        "Charsang",
        "Chah\u0101r Sang"
    ],
    "wof:name":"Chahar Sang",
    "wof:placetype":"locality"
},
  "geometry": {"coordinates":[66.83408,36.70585],"type":"Point"}
}