{
  "type": "Feature",
  "properties": {
    "gn:admin1_code":"41",
    "gn:admin2_code":"3407.0",
    "gn:asciiname":"War-e Burkot",
    "gn:country_code":"AF",
    "gn:dem":2648,
    "gn:feature_class":"P",
    "gn:feature_code":"PPL",
    "gn:name":"W\u0101r-e Burk\u014dt",
    "gn:population":0,
    "gn:timezone":"Asia/Kabul",
    "iso:country":"AF",
    "name:und_x_variant":[
        "W\u0101\u1e5fe Bu\u1e5fk\u014dt",
        "W\u0101ray Burk\u014dt",
        "W\u0101re Burkow\u1e6f",
        "W\u0101r-e Burk\u014dt",
        "\u0648\u0627\u0631 \u0628\u0631\u06a9\u0648\u062a"
    ],
    "wof:name":"War-e Burkot",
    "wof:placetype":"locality"
},
  "geometry": {"coordinates":[66.58929999999999,33.93321],"type":"Point"}
}