{
  "type": "Feature",
  "properties": {
    "gn:admin1_code":"10",
    "gn:admin2_code":"2312.0",
    "gn:asciiname":"Mazak",
    "gn:country_code":"AF",
    "gn:dem":888,
    "gn:feature_class":"P",
    "gn:feature_code":"PPL",
    "gn:name":"Mazak",
    "gn:population":0,
    "gn:timezone":"Asia/Kabul",
    "iso:country":"AF",
    "name:deu_x_preferred":[
        "Mazak"
    ],
    "name:fra_x_preferred":[
        "Mazak"
    ],
    "name:und_x_variant":[
        "\u0645\u0632\u06a9"
    ],
    "wof:name":"Mazak",
    "wof:placetype":"locality"
},
  "geometry": {"coordinates":[64.87074,32.10419],"type":"Point"}
}