{
  "type": "Feature",
  "properties": {
    "gn:admin1_code":"27",
    "gn:admin2_code":"404",
    "gn:asciiname":"Toghay-e Mushi",
    "gn:country_code":"AF",
    "gn:dem":2555,
    "gn:feature_class":"P",
    "gn:feature_code":"PPL",
    "gn:name":"T\u014dghay-e M\u016bsh\u012b",
    "gn:population":0,
    "gn:timezone":"Asia/Kabul",
    "iso:country":"AF",
    "name:und_x_variant":[
        "Tugayi Mushi",
        "Toghaye M\u016b\u0161i",
        "Toghay-e M\u016bsh\u012b",
        "T\u014dghay-e M\u016bsh\u012b",
        "\u062a\u0648\u063a\u06cc \u0645\u0648\u0634\u06cc"
    ],
    "wof:name":"Toghay-e Mushi",
    "wof:placetype":"locality"
},
  "geometry": {"coordinates":[67.46207,34.37055],"type":"Point"}
}