{
  "type": "Feature",
  "properties": {
    "gn:admin1_code":"09",
    "gn:admin2_code":"2707",
    "gn:asciiname":"Sar-e Khagak",
    "gn:country_code":"AF",
    "gn:dem":2999,
    "gn:feature_class":"P",
    "gn:feature_code":"PPL",
    "gn:name":"Sar-e Kh\u0101gak",
    "gn:population":0,
    "gn:timezone":"Asia/Kabul",
    "iso:country":"AF",
    "name:und_x_variant":[
        "Sari-Khagak",
        "Sar-e Kh\u0101gak",
        "\u0633\u0631 \u062e\u0627\u06af\u06a9"
    ],
    "wof:name":"Sar-e Khagak",
    "wof:placetype":"locality"
},
  "geometry": {"coordinates":[66.18233000000001,34.55654000000001],"type":"Point"}
}