{
  "type": "Feature",
  "properties": {
    "gn:admin1_code":"11",
    "gn:admin2_code":"2007.0",
    "gn:asciiname":"Chahar Del",
    "gn:country_code":"AF",
    "gn:dem":893,
    "gn:feature_class":"P",
    "gn:feature_code":"PPL",
    "gn:name":"Chah\u0101r Del",
    "gn:population":0,
    "gn:timezone":"Asia/Kabul",
    "iso:country":"AF",
    "name:und_x_variant":[
        "Caha\u1e5f \u1e0eel",
        "Chah\u0101r Del",
        "\u0686\u0647\u0627\u0631 \u062f\u0644",
        "Chah\u0101r Dil"
    ],
    "wof:name":"Chahar Del",
    "wof:placetype":"locality"
},
  "geometry": {"coordinates":[61.22086,35.19518],"type":"Point"}
}