{
  "type": "Feature",
  "properties": {
    "gn:admin1_code":"11",
    "gn:admin2_code":"2016",
    "gn:asciiname":"Ghuri",
    "gn:country_code":"AF",
    "gn:dem":1155,
    "gn:feature_class":"P",
    "gn:feature_code":"PPL",
    "gn:name":"Gh\u016br\u012b",
    "gn:population":0,
    "gn:timezone":"Asia/Kabul",
    "iso:country":"AF",
    "name:fas_x_preferred":[
        "\u063a\u0648\u0631\u06cc"
    ],
    "name:msa_x_preferred":[
        "Ghuri"
    ],
    "name:und_x_variant":[
        "Gh\u016br\u012b",
        "Ghu\u1e5fi"
    ],
    "wof:name":"Ghuri",
    "wof:placetype":"locality"
},
  "geometry": {"coordinates":[62.59582,34.81572],"type":"Point"}
}