{
  "type": "Feature",
  "properties": {
    "gn:admin1_code":"30",
    "gn:admin2_code":"1607.0",
    "gn:asciiname":"Zigzig",
    "gn:country_code":"AF",
    "gn:dem":327,
    "gn:feature_class":"P",
    "gn:feature_code":"PPL",
    "gn:name":"Zigzig",
    "gn:population":0,
    "gn:timezone":"Asia/Kabul",
    "iso:country":"AF",
    "name:fas_x_preferred":[
        "\u0632\u064a\u06af\u0632\u064a\u06af"
    ],
    "name:rus_x_preferred":[
        "\u0417\u0438\u0433\u0437\u0438\u0433"
    ],
    "name:und_x_variant":[
        "Z\u012bgz\u012bg",
        "\u0632\u06af\u0632\u06af"
    ],
    "wof:name":"Zigzig",
    "wof:placetype":"locality"
},
  "geometry": {"coordinates":[66.61496,36.73985],"type":"Point"}
}