{
  "type": "Feature",
  "properties": {
    "iso:country":"AF",
    "name:rus_x_preferred":[
        "\u041a\u0443\u0448\u043a"
    ],
    "name:unk_x_variant":[
        "Kus\u0304k"
    ],
    "qs:gn_country":"AF",
    "qs:gn_fcode":"PPL",
    "qs:gn_pop":16952,
    "qs:name":"Kusk",
    "qs:name_adm0":"Afghanistan",
    "qs:name_adm1":"Herat",
    "qs:photos":0,
    "qs:photos_1k":0,
    "qs:photos_9k":0,
    "qs:photos_9r":0,
    "qs:photos_all":0,
    "qs:photos_sr":0,
    "qs:placetype":"Town",
    "qs:pop_sr":"6",
    "qs:woe_adm0":23424739,
    "wof:name":"Kusk",
    "wof:placetype":"locality",
    "wof:population":16952
},
  "geometry": {"coordinates":[61.95221,33.29565],"type":"Point"}
}