{
  "type": "Feature",
  "properties": {
    "gn:admin1_code":"32",
    "gn:admin2_code":"1505",
    "gn:asciiname":"Duab",
    "gn:country_code":"AF",
    "gn:dem":2238,
    "gn:feature_class":"P",
    "gn:feature_code":"PPLA2",
    "gn:name":"D\u016b\u0101b",
    "gn:population":0,
    "gn:timezone":"Asia/Kabul",
    "iso:country":"AF",
    "name:und_x_variant":[
        "T\u0101t\u0101\u1e5f",
        "Dow \u0100b-e Sh\u0101h Pasand",
        "Do\u0101b-i-Sh\u0101hpasand",
        "Do \u0100b",
        "D\u016b\u0101b",
        "\u062f\u0648\u0627\u0628",
        "T\u0101t\u0101r",
        "\u062a\u0627\u062a\u0627\u0631"
    ],
    "wof:name":"Duab",
    "wof:placetype":"locality"
},
  "geometry": {"coordinates":[67.82191,35.56277],"type":"Point"}
}