{
  "type": "Feature",
  "properties": {
    "gn:admin1_code":"27",
    "gn:admin2_code":"405",
    "gn:asciiname":"Tara",
    "gn:country_code":"AF",
    "gn:dem":2708,
    "gn:feature_class":"P",
    "gn:feature_code":"PPL",
    "gn:name":"Tar\u0101",
    "gn:population":0,
    "gn:timezone":"Asia/Kabul",
    "iso:country":"AF",
    "name:bel_x_preferred":[
        "\u0422\u0430\u0440\u0430"
    ],
    "name:bos_x_preferred":[
        "Tara"
    ],
    "name:bul_x_preferred":[
        "\u0422\u0430\u0440\u0430"
    ],
    "name:cat_x_preferred":[
        "Tara"
    ],
    "name:ceb_x_preferred":[
        "Tara"
    ],
    "name:ces_x_preferred":[
        "Tara"
    ],
    "name:dan_x_preferred":[
        "Tara"
    ],
    "name:deu_x_preferred":[
        "Tara"
    ],
    "name:epo_x_preferred":[
        "Tara"
    ],
    "name:est_x_preferred":[
        "Tara"
    ],
    "name:fas_x_preferred":[
        "\u062a\u0627\u0631\u0627"
    ],
    "name:fin_x_preferred":[
        "Tara"
    ],
    "name:fra_x_preferred":[
        "Tara"
    ],
    "name:heb_x_preferred":[
        "\u05d8\u05d0\u05e8\u05d4"
    ],
    "name:hin_x_preferred":[
        "\u0924\u093e\u0930\u093e"
    ],
    "name:hrv_x_preferred":[
        "Tara"
    ],
    "name:hsb_x_preferred":[
        "Tara"
    ],
    "name:hun_x_preferred":[
        "Tara"
    ],
    "name:ind_x_preferred":[
        "Tara"
    ],
    "name:isl_x_preferred":[
        "Tara"
    ],
    "name:ita_x_preferred":[
        "Tara"
    ],
    "name:jpn_x_preferred":[
        "\u30bf\u30e9"
    ],
    "name:lat_x_preferred":[
        "Tara"
    ],
    "name:lit_x_preferred":[
        "Tara"
    ],
    "name:new_x_preferred":[
        "\u0924\u0930\u093e"
    ],
    "name:nld_x_preferred":[
        "Tara"
    ],
    "name:nno_x_preferred":[
        "Tara"
    ],
    "name:nor_x_preferred":[
        "Tara"
    ],
    "name:pol_x_preferred":[
        "Tara"
    ],
    "name:por_x_preferred":[
        "Tara"
    ],
    "name:rus_x_preferred":[
        "\u0422\u0430\u0440\u0430"
    ],
    "name:slk_x_preferred":[
        "Tara"
    ],
    "name:slv_x_preferred":[
        "Tara"
    ],
    "name:spa_x_preferred":[
        "Tara"
    ],
    "name:srp_x_preferred":[
        "\u0422\u0430\u0440\u0430"
    ],
    "name:swe_x_preferred":[
        "Tara"
    ],
    "name:ukr_x_preferred":[
        "\u0422\u0430\u0440\u0430"
    ],
    "name:und_x_variant":[
        "Tar\u0101",
        "\u062a\u0631\u0627"
    ],
    "wof:name":"Tara",
    "wof:placetype":"locality"
},
  "geometry": {"coordinates":[68.40269000000001,34.26904],"type":"Point"}
}