{
  "type": "Feature",
  "properties": {
    "gn:admin1_code":"09",
    "gn:admin2_code":"2706",
    "gn:asciiname":"Olamqul",
    "gn:country_code":"AF",
    "gn:dem":2602,
    "gn:feature_class":"P",
    "gn:feature_code":"PPL",
    "gn:name":"Olamq\u016bl",
    "gn:population":0,
    "gn:timezone":"Asia/Kabul",
    "iso:country":"AF",
    "name:rus_x_preferred":[
        "Ulamkul\u2019"
    ],
    "name:und_x_variant":[
        "Olamq\u016bl",
        "\u0627\u0644\u0645\u0642\u0648\u0644",
        "Olamqol"
    ],
    "wof:name":"Olamqul",
    "wof:placetype":"locality"
},
  "geometry": {"coordinates":[64.72728000000001,33.73995],"type":"Point"}
}