{
  "type": "Feature",
  "properties": {
    "gn:admin1_code":"18",
    "gn:admin2_code":"802.0",
    "gn:asciiname":"Hazratan",
    "gn:country_code":"AF",
    "gn:dem":607,
    "gn:feature_class":"P",
    "gn:feature_code":"PPL",
    "gn:name":"\u1e28a\u1e95rat\u0101n",
    "gn:population":0,
    "gn:timezone":"Asia/Kabul",
    "iso:country":"AF",
    "name:und_x_variant":[
        "Khazratan",
        "\u1e28a\u1e0f\u1e95\u1e5fat\u0101n",
        "\u1e28a\u1e95rat\u0101n",
        "\u062d\u0636\u0631\u062a\u0627\u0646"
    ],
    "wof:name":"Hazratan",
    "wof:placetype":"locality"
},
  "geometry": {"coordinates":[70.38799,34.41784000000001],"type":"Point"}
}