{
  "type": "Feature",
  "properties": {
    "gn:admin1_code":"06",
    "gn:admin2_code":"2104",
    "gn:asciiname":"Kut",
    "gn:country_code":"AF",
    "gn:dem":1783,
    "gn:feature_class":"P",
    "gn:feature_code":"PPL",
    "gn:name":"K\u016bt",
    "gn:population":0,
    "gn:timezone":"Asia/Kabul",
    "iso:country":"AF",
    "name:und_x_variant":[
        "K\u016bt",
        "Kut",
        "\u06a9\u0648\u062a",
        "Kowt"
    ],
    "wof:name":"Kut",
    "wof:placetype":"locality"
},
  "geometry": {"coordinates":[64.11216,33.25076],"type":"Point"}
}