{
  "type": "Feature",
  "properties": {
    "gn:admin1_code":"24",
    "gn:admin2_code":"1403",
    "gn:asciiname":"Tarbuz Guzar",
    "gn:country_code":"AF",
    "gn:dem":341,
    "gn:feature_class":"P",
    "gn:feature_code":"PPL",
    "gn:name":"Tarb\u016bz Guz\u0304ar",
    "gn:population":0,
    "gn:timezone":"Asia/Kabul",
    "iso:country":"AF",
    "name:rus_x_preferred":[
        "\u0422\u0430\u0440\u0431\u0443\u0437\u0433\u0443\u0437\u0430\u0440"
    ],
    "name:und_x_variant":[
        "Tarbuzguzar",
        "Ta\u1e5fb\u016bz Guz\u0304a\u1e5f",
        "Tarboz Goz\u0304ar",
        "Tarb\u016bz Guz\u0304ar",
        "\u062a\u0631\u0628\u0648\u0632 \u06af\u0630\u0631"
    ],
    "wof:name":"Tarbuz Guzar",
    "wof:placetype":"locality"
},
  "geometry": {"coordinates":[68.52065,36.96543],"type":"Point"}
}