{
  "type": "Feature",
  "properties": {
    "gn:admin1_code":"41",
    "gn:admin2_code":"3408.0",
    "gn:asciiname":"Dahan-e Sang Shandah",
    "gn:country_code":"AF",
    "gn:dem":2390,
    "gn:feature_class":"P",
    "gn:feature_code":"PPL",
    "gn:name":"Dahan-e Sang Sh\u0101ndah",
    "gn:population":0,
    "gn:timezone":"Asia/Kabul",
    "iso:country":"AF",
    "name:und_x_variant":[
        "Dahan-e Sangsh\u0101nda",
        "Dahane Sang\u0161\u0101nda",
        "Dakhani-Sangshanda",
        "Dahan-e Sang Sh\u0101ndah",
        "Dahan-e Sangsh\u0101ndeh",
        "\u062f\u0647\u0646 \u0633\u0646\u06af \u0634\u0627\u0646\u062f\u0647"
    ],
    "wof:name":"Dahan-e Sang Shandah",
    "wof:placetype":"locality"
},
  "geometry": {"coordinates":[66.16694,34.21666],"type":"Point"}
}