{
  "type": "Feature",
  "properties": {
    "gn:admin1_code":"33",
    "gn:admin2_code":"3102.0",
    "gn:asciiname":"'Arab Bay",
    "gn:country_code":"AF",
    "gn:dem":1035,
    "gn:feature_class":"P",
    "gn:feature_code":"PPL",
    "gn:name":"\u2018Arab B\u0101y",
    "gn:population":0,
    "gn:timezone":"Asia/Kabul",
    "iso:country":"AF",
    "name:und_x_variant":[
        "Arab Bai",
        "\u2018Arab B\u0101y"
    ],
    "wof:name":"'Arab Bay",
    "wof:placetype":"locality"
},
  "geometry": {"coordinates":[66.40971999999999,36.05639],"type":"Point"}
}