{
  "type": "Feature",
  "properties": {
    "gn:admin1_code":"26",
    "gn:admin2_code":"1201",
    "gn:asciiname":"Shor Chah",
    "gn:country_code":"AF",
    "gn:dem":1257,
    "gn:feature_class":"P",
    "gn:feature_code":"PPL",
    "gn:name":"Sh\u014dr Ch\u0101h",
    "gn:population":0,
    "gn:timezone":"Asia/Kabul",
    "iso:country":"AF",
    "name:rus_x_preferred":[
        "\u0428\u043e\u0440\u0447\u0430"
    ],
    "name:und_x_variant":[
        "Shorcha",
        "Sh\u016br Cha",
        "Sh\u016brcheh",
        "\u0160or \u010ca",
        "Sh\u016br Ch\u0101h",
        "Sh\u014dr Ch\u0101h",
        "\u0634\u0648\u0631 \u0686\u0627\u0647"
    ],
    "wof:name":"Shor Chah",
    "wof:placetype":"locality"
},
  "geometry": {"coordinates":[69.47633,36.61771],"type":"Point"}
}