{
  "type": "Feature",
  "properties": {
    "gn:admin1_code":"10",
    "gn:admin2_code":"2307",
    "gn:asciiname":"Khayraday",
    "gn:country_code":"AF",
    "gn:dem":1141,
    "gn:feature_class":"P",
    "gn:feature_code":"PPL",
    "gn:name":"Khayraday",
    "gn:population":0,
    "gn:timezone":"Asia/Kabul",
    "iso:country":"AF",
    "name:und_x_variant":[
        "\u062e\u06cc\u0631\u062f\u06cc"
    ],
    "wof:name":"Khayraday",
    "wof:placetype":"locality"
},
  "geometry": {"coordinates":[64.24684999999999,32.19819],"type":"Point"}
}