{
  "type": "Feature",
  "properties": {
    "gn:admin1_code":"41",
    "gn:admin2_code":"3409",
    "gn:asciiname":"Shahlij",
    "gn:country_code":"AF",
    "gn:dem":1857,
    "gn:feature_class":"P",
    "gn:feature_code":"PPL",
    "gn:name":"Sh\u0101hlij",
    "gn:population":0,
    "gn:timezone":"Asia/Kabul",
    "iso:country":"AF",
    "name:und_x_variant":[
        "\u0160\u0101hlej",
        "Sh\u0101h Lej",
        "Sh\u0101hlij",
        "\u0634\u0627\u0647\u0644\u062c"
    ],
    "wof:name":"Shahlij",
    "wof:placetype":"locality"
},
  "geometry": {"coordinates":[66.26106999999999,33.6445],"type":"Point"}
}