{
  "type": "Feature",
  "properties": {
    "gn:admin1_code":"28",
    "gn:admin2_code":"2501.0",
    "gn:asciiname":"Nowab Khan Kelay",
    "gn:country_code":"AF",
    "gn:dem":1636,
    "gn:feature_class":"P",
    "gn:feature_code":"PPL",
    "gn:name":"Now\u0101b Kh\u0101n K\u00ealay",
    "gn:population":0,
    "gn:timezone":"Asia/Kabul",
    "iso:country":"AF",
    "name:fas_x_preferred":[
        "\u0646\u0648\u0627\u0628 \u062e\u0627\u0646 \u0643\u0644\u06cc"
    ],
    "name:fas_x_variant":[
        "\u0642\u0631\u064a\u06c0 \u0646\u0648\u0627\u0628 \u062e\u0627\u0646"
    ],
    "name:und_x_variant":[
        "Naw\u0101bkh\u0101n Kalay",
        "Now\u0101b Kh\u0101n K\u00ealay",
        "\u0646\u0648\u0627\u0628 \u062e\u0627\u0646 \u06a9\u0644\u06cc",
        "Nav\u0101b Kh\u0101n Kalay"
    ],
    "wof:name":"Nowab Khan Kelay",
    "wof:placetype":"locality"
},
  "geometry": {"coordinates":[67.00041,32.10065],"type":"Point"}
}