{
  "type": "Feature",
  "properties": {
    "gn:admin1_code":"07",
    "gn:admin2_code":"1810",
    "gn:asciiname":"Tuquz Darak",
    "gn:country_code":"AF",
    "gn:dem":321,
    "gn:feature_class":"P",
    "gn:feature_code":"PPL",
    "gn:name":"Tuquz Darak",
    "gn:population":0,
    "gn:timezone":"Asia/Kabul",
    "iso:country":"AF",
    "name:und_x_variant":[
        "\u062a\u0642\u0632 \u062f\u0631\u06a9",
        "Toqoz Darak",
        "Tuquz Darak"
    ],
    "wof:name":"Tuquz Darak",
    "wof:placetype":"locality"
},
  "geometry": {"coordinates":[65.09071,36.88549],"type":"Point"}
}