{
  "type": "Feature",
  "properties": {
    "gn:admin1_code":"09",
    "gn:admin2_code":"2701",
    "gn:asciiname":"Qal'ah-ye Kuhnah",
    "gn:country_code":"AF",
    "gn:dem":2376,
    "gn:feature_class":"P",
    "gn:feature_code":"PPL",
    "gn:name":"Qal\u2018ah-ye Kuhnah",
    "gn:population":0,
    "gn:timezone":"Asia/Kabul",
    "iso:country":"AF",
    "name:und_x_variant":[
        "Qal\u2018a-Kuhna",
        "Qal\u2018eh Kohneh",
        "Qal\u2018ah-ye Kuhnah",
        "\u0642\u0644\u0639\u0647 \u06a9\u0647\u0646\u0647"
    ],
    "wof:name":"Qal'ah-ye Kuhnah",
    "wof:placetype":"locality"
},
  "geometry": {"coordinates":[65.43449,34.4736],"type":"Point"}
}