{
  "type": "Feature",
  "properties": {
    "gn:admin1_code":"23",
    "gn:admin2_code":"2413.0",
    "gn:asciiname":"Kshetah Wulgay",
    "gn:country_code":"AF",
    "gn:dem":2083,
    "gn:feature_class":"P",
    "gn:feature_code":"PPL",
    "gn:name":"Ks\u0332h\u0332\u00eatah Wulgay",
    "gn:population":0,
    "gn:timezone":"Asia/Kabul",
    "iso:country":"AF",
    "name:fas_x_preferred":[
        "\u0643\u0634\u062a\u0647 \u0648\u0644\u06af\u06cc"
    ],
    "name:rus_x_preferred":[
        "Kshatavul\u2019gay"
    ],
    "name:und_x_variant":[
        "K\u0161ata Wulgay",
        "Ks\u0332h\u0332\u00eatah Wulgay",
        "\u06a9\u069a\u062a\u0647 \u0648\u0644\u06af\u06cc",
        "Kshatah Wulgay"
    ],
    "wof:name":"Kshetah Wulgay",
    "wof:placetype":"locality"
},
  "geometry": {"coordinates":[67.38231999999999,31.55905],"type":"Point"}
}