{
  "type": "Feature",
  "properties": {
    "gn:admin1_code":"30",
    "gn:admin2_code":"1608.0",
    "gn:asciiname":"Burmah",
    "gn:country_code":"AF",
    "gn:dem":656,
    "gn:feature_class":"P",
    "gn:feature_code":"PPL",
    "gn:name":"Burmah",
    "gn:population":0,
    "gn:timezone":"Asia/Kabul",
    "iso:country":"AF",
    "name:und_x_variant":[
        "Borma",
        "Bormah",
        "Burmah",
        "\u0628\u0631\u0645\u0647"
    ],
    "wof:name":"Burmah",
    "wof:placetype":"locality"
},
  "geometry": {"coordinates":[66.30829,36.41994],"type":"Point"}
}