{
  "type": "Feature",
  "properties": {
    "gn:admin1_code":"6",
    "gn:admin2_code":"2105.0",
    "gn:asciiname":"Bar Azow",
    "gn:country_code":"AF",
    "gn:dem":1302,
    "gn:feature_class":"P",
    "gn:feature_code":"PPL",
    "gn:name":"Bar Azow",
    "gn:population":0,
    "gn:timezone":"Asia/Kabul",
    "iso:country":"AF",
    "name:und_x_variant":[
        "Barz\u012br\u012b",
        "Bar-Azau",
        "Bar\u0101z\u012b",
        "Ba\u1e5f Asaw",
        "Ba\u1e5f Azaw",
        "Bar \u0100zow",
        "Bar Azow",
        "\u0628\u0631 \u0627\u0632\u0648",
        "Bar \u0100z\u0101b"
    ],
    "wof:name":"Bar Azow",
    "wof:placetype":"locality"
},
  "geometry": {"coordinates":[63.12539,33.05556],"type":"Point"}
}