{
  "type": "Feature",
  "properties": {
    "gn:admin1_code":"13",
    "gn:admin2_code":"110.0",
    "gn:asciiname":"Alu Khel",
    "gn:country_code":"AF",
    "gn:dem":1784,
    "gn:feature_class":"P",
    "gn:feature_code":"PPL",
    "gn:name":"Al\u016b Kh\u0113l",
    "gn:population":0,
    "gn:timezone":"Asia/Kabul",
    "iso:country":"AF",
    "name:fas_x_preferred":[
        "\u0622\u0644\u0648 \u062e\u064a\u0644"
    ],
    "name:rus_x_preferred":[
        "Alukheyl\u2019"
    ],
    "name:und_x_variant":[
        "Al\u016b Kh\u0113l",
        "\u0100l\u016b Kh\u0113l",
        "\u0100l\u016bkheyl",
        "\u0627\u0644\u0648 \u062e\u06d0\u0644"
    ],
    "wof:name":"Alu Khel",
    "wof:placetype":"locality"
},
  "geometry": {"coordinates":[69.27523000000001,34.52967],"type":"Point"}
}