{
  "type": "Feature",
  "properties": {
    "gn:admin1_code":"11",
    "gn:admin2_code":"2013",
    "gn:asciiname":"Joy-e Khukab",
    "gn:country_code":"AF",
    "gn:dem":2100,
    "gn:feature_class":"P",
    "gn:feature_code":"PPL",
    "gn:name":"J\u014dy-e Kh\u016bk\u0101b",
    "gn:population":0,
    "gn:timezone":"Asia/Kabul",
    "iso:country":"AF",
    "name:und_x_variant":[
        "Dzhoyi-Khukab",
        "J\u014dy-e Kh\u016bk\u0101b",
        "\u062c\u0648\u06cc \u062e\u0648\u06a9\u0627\u0628",
        "J\u016by-e Kh\u016bk\u0101b"
    ],
    "wof:name":"Joy-e Khukab",
    "wof:placetype":"locality"
},
  "geometry": {"coordinates":[63.09811,33.70107],"type":"Point"}
}