{
  "type": "Feature",
  "properties": {
    "gn:admin1_code":"8",
    "gn:admin2_code":"607.0",
    "gn:asciiname":"Miyanadang",
    "gn:country_code":"AF",
    "gn:dem":2389,
    "gn:feature_class":"P",
    "gn:feature_code":"PPL",
    "gn:name":"Miy\u0101na\u1e0fang",
    "gn:population":0,
    "gn:timezone":"Asia/Kabul",
    "iso:country":"AF",
    "name:und_x_variant":[
        "My\u0101nadang",
        "Mianadang",
        "M\u012b\u0101na\u1e0fang",
        "\u0645\u06cc\u0627\u0646\u0689\u0646\u06af",
        "M\u012b\u0101neh\u1e0fang",
        "Miy\u0101na\u1e0fang"
    ],
    "wof:name":"Miyanadang",
    "wof:placetype":"locality"
},
  "geometry": {"coordinates":[67.53729,32.95345],"type":"Point"}
}