{
  "type": "Feature",
  "properties": {
    "gn:admin1_code":"01",
    "gn:admin2_code":"1101.0",
    "gn:asciiname":"Sar-e Qol",
    "gn:country_code":"AF",
    "gn:dem":2227,
    "gn:feature_class":"P",
    "gn:feature_code":"PPL",
    "gn:name":"Sar-e Q\u014dl",
    "gn:population":0,
    "gn:timezone":"Asia/Kabul",
    "iso:country":"AF",
    "name:und_x_variant":[
        "Sar-i-Q\u014dl",
        "\u0633\u0631 \u0642\u0648\u0644",
        "Sar-e Q\u016bl",
        "Sar-e Q\u014dl",
        "Sa\u1e5f-i-Q\u0101l",
        "Sar-e Q\u0101l"
    ],
    "wof:name":"Sar-e Qol",
    "wof:placetype":"locality"
},
  "geometry": {"coordinates":[70.64851999999998,37.22523],"type":"Point"}
}