{
  "type": "Feature",
  "properties": {
    "gn:admin1_code":"28",
    "gn:admin2_code":"2507",
    "gn:asciiname":"Izh Kelay",
    "gn:country_code":"AF",
    "gn:dem":2261,
    "gn:feature_class":"P",
    "gn:feature_code":"PPL",
    "gn:name":"Izh K\u00ealay",
    "gn:population":0,
    "gn:timezone":"Asia/Kabul",
    "iso:country":"AF",
    "name:fas_x_preferred":[
        "\u0642\u0631\u064a\u06c0 \u0627\u0698"
    ],
    "name:und_x_variant":[
        "Izkalay",
        "E\u017e Kalay",
        "Ezh Kalay",
        "Izh K\u00ealay",
        "\u0627\u0698 \u06a9\u0644\u06cc"
    ],
    "wof:name":"Izh Kelay",
    "wof:placetype":"locality"
},
  "geometry": {"coordinates":[67.33893,32.14537],"type":"Point"}
}