{
  "type": "Feature",
  "properties": {
    "gn:admin1_code":"37",
    "gn:admin2_code":"3204",
    "gn:asciiname":"Kande Kelay",
    "gn:country_code":"AF",
    "gn:dem":2182,
    "gn:feature_class":"P",
    "gn:feature_code":"PPL",
    "gn:name":"Kand\u0113 K\u00ealay",
    "gn:population":0,
    "gn:timezone":"Asia/Kabul",
    "iso:country":"AF",
    "name:fas_x_preferred":[
        "\u0643\u0646\u062f\u06cc \u0643\u0644\u06cc"
    ],
    "name:und_x_variant":[
        "Kandekalay",
        "Kan\u1e0f\u0113 Kalay",
        "Kand\u0113 K\u00ealay",
        "Kandey Kalay",
        "\u0643\u0646\u062f\u06d0 \u0643\u0644\u06cc"
    ],
    "wof:name":"Kande Kelay",
    "wof:placetype":"locality"
},
  "geometry": {"coordinates":[69.55543,33.13175],"type":"Point"}
}