{
  "type": "Feature",
  "properties": {
    "gn:admin1_code":"27",
    "gn:admin2_code":"404.0",
    "gn:asciiname":"Dordang",
    "gn:country_code":"AF",
    "gn:dem":2929,
    "gn:feature_class":"P",
    "gn:feature_code":"PPL",
    "gn:name":"D\u014drdang",
    "gn:population":0,
    "gn:timezone":"Asia/Kabul",
    "iso:country":"AF",
    "name:und_x_variant":[
        "\u1e0e\u014d\u1e5f\u1e0fang",
        "D\u014drdang",
        "Dowrdang",
        "\u062f\u0648\u0631\u062f\u0646\u06af"
    ],
    "wof:name":"Dordang",
    "wof:placetype":"locality"
},
  "geometry": {"coordinates":[67.84666,34.38693],"type":"Point"}
}