{
  "type": "Feature",
  "properties": {
    "gn:admin1_code":"02",
    "gn:admin2_code":"1901",
    "gn:asciiname":"Najak",
    "gn:country_code":"AF",
    "gn:dem":1076,
    "gn:feature_class":"P",
    "gn:feature_code":"PPL",
    "gn:name":"Najak",
    "gn:population":0,
    "gn:timezone":"Asia/Kabul",
    "iso:country":"AF",
    "name:und_x_variant":[
        "Nadzhak",
        "Najak",
        "\u0646\u062c\u06a9"
    ],
    "wof:name":"Najak",
    "wof:placetype":"locality"
},
  "geometry": {"coordinates":[63.07174000000001,34.88175],"type":"Point"}
}