{
  "type": "Feature",
  "properties": {
    "gn:admin1_code":"28",
    "gn:admin2_code":"2504.0",
    "gn:asciiname":"'Abdullah Kelay",
    "gn:country_code":"AF",
    "gn:dem":2166,
    "gn:feature_class":"P",
    "gn:feature_code":"PPL",
    "gn:name":"\u2018Abdull\u0101h K\u00ealay",
    "gn:population":0,
    "gn:timezone":"Asia/Kabul",
    "iso:country":"AF",
    "name:fas_x_preferred":[
        "\u0639\u0628\u062f\u0627\u0644\u0644\u0647 \u0643\u0644\u06cc"
    ],
    "name:und_x_variant":[
        "\u2018Ab\u1e0full\u0101h Kalay",
        "Abdullakalay",
        "\u2018Abdull\u0101h K\u00ealay",
        "\u0639\u0628\u062f\u0627\u0644\u0644\u0640\u0647 \u06a9\u0644\u06cc",
        "\u2018Abdoll\u0101h Kalay"
    ],
    "wof:name":"'Abdullah Kelay",
    "wof:placetype":"locality"
},
  "geometry": {"coordinates":[66.71510000000001,32.62688],"type":"Point"}
}