{
  "type": "Feature",
  "properties": {
    "gn:admin1_code":"05",
    "gn:admin2_code":"2807",
    "gn:asciiname":"Pusht-e Waz",
    "gn:country_code":"AF",
    "gn:dem":2922,
    "gn:feature_class":"P",
    "gn:feature_code":"PPL",
    "gn:name":"Pusht-e W\u0101z",
    "gn:population":0,
    "gn:timezone":"Asia/Kabul",
    "iso:country":"AF",
    "name:und_x_variant":[
        "Pus\u0304te W\u0101z",
        "Posht-e W\u0101z",
        "Pusht-e W\u0101z",
        "\u067e\u0634\u062a \u0648\u0627\u0632"
    ],
    "wof:name":"Pusht-e Waz",
    "wof:placetype":"locality"
},
  "geometry": {"coordinates":[67.46273000000001,35.26215],"type":"Point"}
}