{
  "type": "Feature",
  "properties": {
    "gn:admin1_code":"37",
    "gn:admin2_code":"3203.0",
    "gn:asciiname":"'Id Akbar Kelay",
    "gn:country_code":"AF",
    "gn:dem":1260,
    "gn:feature_class":"P",
    "gn:feature_code":"PPL",
    "gn:name":"\u2018\u012ad Akbar K\u00ealay",
    "gn:population":0,
    "gn:timezone":"Asia/Kabul",
    "iso:country":"AF",
    "name:fas_x_preferred":[
        "\u0642\u0631\u064a\u06c0 \u0639\u064a\u062f \u0627\u0643\u0628\u0631"
    ],
    "name:und_x_variant":[
        "Indakbarkalay",
        "\u2018\u012ad Akbar K\u00ealay",
        "\u012ad Akbar Kalay",
        "\u0639\u06cc\u062f \u0627\u06a9\u0628\u0631 \u06a9\u0644\u06cc"
    ],
    "wof:name":"'Id Akbar Kelay",
    "wof:placetype":"locality"
},
  "geometry": {"coordinates":[69.84251999999999,33.27577],"type":"Point"}
}