{
  "type": "Feature",
  "properties": {
    "gn:admin1_code":"23",
    "gn:admin2_code":"2403",
    "gn:asciiname":"Kuchnay Karez",
    "gn:country_code":"AF",
    "gn:dem":1301,
    "gn:feature_class":"P",
    "gn:feature_code":"PPL",
    "gn:name":"Kuchnay K\u0101r\u0113z",
    "gn:population":0,
    "gn:timezone":"Asia/Kabul",
    "iso:country":"AF",
    "name:fas_x_preferred":[
        "\u0643\u0627\u0631\u064a\u0632\u0654 \u062e\u0648\u0631\u062f"
    ],
    "name:und_x_variant":[
        "Kuchnay-Karez",
        "Ku\u010dnay K\u0101r\u0113z",
        "Kuchnay K\u0101r\u0113z",
        "\u06a9\u0686\u0646\u06cc \u06a9\u0627\u0631\u06d0\u0632",
        "Kuchnay K\u0101r\u012bz"
    ],
    "wof:name":"Kuchnay Karez",
    "wof:placetype":"locality"
},
  "geometry": {"coordinates":[65.94559,32.03077],"type":"Point"}
}