{
  "type": "Feature",
  "properties": {
    "gn:admin1_code":"08",
    "gn:admin2_code":"607",
    "gn:asciiname":"Wakil Khel",
    "gn:country_code":"AF",
    "gn:dem":3044,
    "gn:feature_class":"P",
    "gn:feature_code":"PPL",
    "gn:name":"Wak\u012bl Kh\u0113l",
    "gn:population":0,
    "gn:timezone":"Asia/Kabul",
    "iso:country":"AF",
    "name:fas_x_preferred":[
        "\u0648\u0643\u064a\u0644 \u062e\u064a\u0644"
    ],
    "name:rus_x_preferred":[
        "\u0412\u0430\u043a\u0438\u043b\u044c\u0445\u0435\u0439\u043b\u044c"
    ],
    "name:und_x_variant":[
        "Wak\u012bl Kh\u0113l",
        "Vakil\u2019kheyl\u2019",
        "Wak\u012blkheyl",
        "Vak\u012blkheyl",
        "\u0648\u06a9\u06cc\u0644 \u062e\u06d0\u0644"
    ],
    "wof:name":"Wakil Khel",
    "wof:placetype":"locality"
},
  "geometry": {"coordinates":[67.66266999999999,33.2602],"type":"Point"}
}