{
  "type": "Feature",
  "properties": {
    "gn:admin1_code":"6",
    "gn:admin2_code":"2103.0",
    "gn:asciiname":"Chinagi",
    "gn:country_code":"AF",
    "gn:dem":888,
    "gn:feature_class":"P",
    "gn:feature_code":"PPL",
    "gn:name":"Chinag\u012b",
    "gn:population":0,
    "gn:timezone":"Asia/Kabul",
    "iso:country":"AF",
    "name:und_x_variant":[
        "\u010cenagi",
        "Chenag\u012b",
        "Chinag\u012b",
        "\u0686\u0646\u06af\u06cc"
    ],
    "wof:name":"Chinagi",
    "wof:placetype":"locality"
},
  "geometry": {"coordinates":[63.62777,32.23662],"type":"Point"}
}