{
  "type": "Feature",
  "properties": {
    "gn:admin1_code":"41",
    "gn:admin2_code":"3406.0",
    "gn:asciiname":"Chinarak",
    "gn:country_code":"AF",
    "gn:dem":2213,
    "gn:feature_class":"P",
    "gn:feature_code":"PPL",
    "gn:name":"Chin\u0101rak",
    "gn:population":0,
    "gn:timezone":"Asia/Kabul",
    "iso:country":"AF",
    "name:und_x_variant":[
        "Cen\u0101\u1e5fak",
        "Chin\u0101rak",
        "\u0686\u0646\u0627\u0631\u06a9",
        "Chen\u0101rak"
    ],
    "wof:name":"Chinarak",
    "wof:placetype":"locality"
},
  "geometry": {"coordinates":[65.62578000000001,33.65154],"type":"Point"}
}