{
  "type": "Feature",
  "properties": {
    "gn:admin1_code":"34",
    "gn:admin2_code":"1014.0",
    "gn:asciiname":"Chanchan",
    "gn:country_code":"AF",
    "gn:dem":704,
    "gn:feature_class":"P",
    "gn:feature_code":"PPL",
    "gn:name":"Cha\u1e49cha\u1e49",
    "gn:population":0,
    "gn:timezone":"Asia/Kabul",
    "iso:country":"AF",
    "name:fas_x_preferred":[
        "\u0686\u0646\u0686\u0646"
    ],
    "name:und_x_variant":[
        "\u010can\u010dan",
        "Cha\u1e49cha\u1e49",
        "\u0686\u06bc\u0686\u06bc",
        "Chanchan"
    ],
    "wof:name":"Chanchan",
    "wof:placetype":"locality"
},
  "geometry": {"coordinates":[70.83351,34.60521],"type":"Point"}
}