{
  "type": "Feature",
  "properties": {
    "gn:admin1_code":"01",
    "gn:admin2_code":"1119.0",
    "gn:asciiname":"Pasniyas",
    "gn:country_code":"AF",
    "gn:dem":2729,
    "gn:feature_class":"P",
    "gn:feature_code":"PPL",
    "gn:name":"Pasniyas",
    "gn:population":0,
    "gn:timezone":"Asia/Kabul",
    "iso:country":"AF",
    "name:und_x_variant":[
        "Pasnyas",
        "\u067e\u0633\u0646\u06cc\u0633",
        "Pasniyas"
    ],
    "wof:name":"Pasniyas",
    "wof:placetype":"locality"
},
  "geometry": {"coordinates":[70.64703,37.36894],"type":"Point"}
}