{
  "type": "Feature",
  "properties": {
    "gn:admin1_code":"30",
    "gn:admin2_code":"1608.0",
    "gn:asciiname":"Asya-ye Firqah",
    "gn:country_code":"AF",
    "gn:dem":345,
    "gn:feature_class":"P",
    "gn:feature_code":"PPL",
    "gn:name":"\u0100sy\u0101-ye Firqah",
    "gn:population":0,
    "gn:timezone":"Asia/Kabul",
    "iso:country":"AF",
    "name:fas_x_preferred":[
        "\u0622\u0633\u064a\u0627\u06cc \u0641\u064a\u0631\u0642\u0647"
    ],
    "name:rus_x_preferred":[
        "\u0410\u0441\u0438\u0430\u0439\u0438-\u0424\u0438\u0440\u043a\u0430"
    ],
    "name:und_x_variant":[
        "Asyay-i-Firqa",
        "Asiayi-Firka",
        "\u0100s\u012b\u0101-ye F\u012brqah",
        "\u0100sy\u0101-ye F\u012brqah",
        "\u0100sy\u0101-ye Firqah",
        "\u0622\u0633\u064a\u0627\u06cc \u0641\u0631\u0642\u0647"
    ],
    "wof:name":"Asya-ye Firqah",
    "wof:placetype":"locality"
},
  "geometry": {"coordinates":[66.65523,36.69771],"type":"Point"}
}