{
  "type": "Feature",
  "properties": {
    "gn:admin1_code":"37",
    "gn:admin2_code":"3207.0",
    "gn:asciiname":"Dabgay",
    "gn:country_code":"AF",
    "gn:dem":938,
    "gn:feature_class":"P",
    "gn:feature_code":"PPL",
    "gn:name":"Dabgay",
    "gn:population":0,
    "gn:timezone":"Asia/Kabul",
    "iso:country":"AF",
    "name:und_x_variant":[
        "\u062f\u0628\u06af\u06cc",
        "K\u014d\u1e6fga\u012b",
        "Kotkai",
        "\u0643\u062a\u0643\u06cc"
    ],
    "wof:name":"Dabgay",
    "wof:placetype":"locality"
},
  "geometry": {"coordinates":[70.19684000000001,33.30331],"type":"Point"}
}