{
  "type": "Feature",
  "properties": {
    "gn:admin1_code":"34",
    "gn:admin2_code":"1015.0",
    "gn:asciiname":"Mamunda",
    "gn:country_code":"AF",
    "gn:dem":1811,
    "gn:feature_class":"P",
    "gn:feature_code":"PPL",
    "gn:name":"M\u0101mund\u0101",
    "gn:population":0,
    "gn:timezone":"Asia/Kabul",
    "iso:country":"AF",
    "name:fas_x_preferred":[
        "\u0645\u0627\u0645\u0646\u062f\u0627"
    ],
    "name:und_x_variant":[
        "M\u0101mund\u0101",
        "M\u0101mun\u1e0f\u0101"
    ],
    "wof:name":"Mamunda",
    "wof:placetype":"locality"
},
  "geometry": {"coordinates":[71.09805,34.70048],"type":"Point"}
}