{
  "type": "Feature",
  "properties": {
    "gn:admin1_code":"10",
    "gn:admin2_code":"2312.0",
    "gn:asciiname":"Gulabad",
    "gn:country_code":"AF",
    "gn:dem":1015,
    "gn:feature_class":"P",
    "gn:feature_code":"PPL",
    "gn:name":"Gul\u0101b\u0101d",
    "gn:population":0,
    "gn:timezone":"Asia/Kabul",
    "iso:country":"AF",
    "name:und_x_variant":[
        "Gul\u0101b\u0101\u1e0f",
        "Gul\u0101b\u0101d",
        "\u06af\u0644 \u0622\u0628\u0627\u062f",
        "Gol\u0101b\u0101d"
    ],
    "wof:name":"Gulabad",
    "wof:placetype":"locality"
},
  "geometry": {"coordinates":[65.04075999999999,32.11635],"type":"Point"}
}