{
  "type": "Feature",
  "properties": {
    "gn:admin1_code":"10",
    "gn:admin2_code":"2312.0",
    "gn:asciiname":"Gulabad",
    "gn:country_code":"AF",
    "gn:dem":1015,
    "gn:feature_class":"P",
    "gn:feature_code":"PPL",
    "gn:name":"Gul\u0101b\u0101d",
    "gn:population":0,
    "gn:timezone":"Asia/Kabul",
    "iso:country":"AF",
    "name:azb_x_preferred":[
        "\u06af\u0648\u0644\u200c\u0622\u0628\u0627\u062f"
    ],
    "name:fas_x_preferred":[
        "\u06af\u0644\u200c\u0622\u0628\u0627\u062f"
    ],
    "name:kik_x_preferred":[
        "Gulobod"
    ],
    "name:rus_x_preferred":[
        "\u0413\u044e\u043b\u0430\u0431\u0430\u0434"
    ],
    "name:tur_x_preferred":[
        "G\u00fclabad"
    ],
    "name:und_x_variant":[
        "Gul\u0101b\u0101\u1e0f",
        "Gul\u0101b\u0101d",
        "\u06af\u0644 \u0622\u0628\u0627\u062f",
        "Gol\u0101b\u0101d"
    ],
    "name:urd_x_preferred":[
        "\u06af\u0648\u0644 \u0622\u0628\u0627\u062f"
    ],
    "name:uzb_x_preferred":[
        "Gulobod"
    ],
    "wof:name":"Gulabad",
    "wof:placetype":"locality"
},
  "geometry": {"coordinates":[65.04075999999999,32.11635],"type":"Point"}
}