{
  "type": "Feature",
  "properties": {
    "gn:admin1_code":"03",
    "gn:admin2_code":"1303.0",
    "gn:asciiname":"Kharoti",
    "gn:country_code":"AF",
    "gn:dem":628,
    "gn:feature_class":"P",
    "gn:feature_code":"PPL",
    "gn:name":"Kharoti",
    "gn:population":0,
    "gn:timezone":"Asia/Kabul",
    "iso:country":"AF",
    "name:und_x_variant":[
        "Kha\u1e5f\u014dti",
        "Kharoti",
        "Kha\u1e5fowti",
        "Khar\u014d\u1e6f\u012b",
        "\u062e\u0631\u0648\u067c\u06cc"
    ],
    "wof:name":"Kharoti",
    "wof:placetype":"locality"
},
  "geometry": {"coordinates":[68.58513000000001,35.93841],"type":"Point"}
}