{
  "type": "Feature",
  "properties": {
    "gn:admin1_code":"07",
    "gn:admin2_code":"1809",
    "gn:asciiname":"Taktah-ye Dolatabad",
    "gn:country_code":"AF",
    "gn:dem":397,
    "gn:feature_class":"P",
    "gn:feature_code":"PPL",
    "gn:name":"Taktah-ye D\u014dlat\u0101b\u0101d",
    "gn:population":0,
    "gn:timezone":"Asia/Kabul",
    "iso:country":"AF",
    "name:und_x_variant":[
        "Takta-Ye-Daulat\u0101b\u0101d",
        "Takta-i-Daulat\u0101b\u0101d",
        "Taktah-ye D\u014dlat\u0101b\u0101d",
        "\u062a\u062e\u062a\u06c0 \u062f\u0648\u0644\u062a \u0622\u0628\u0627\u062f",
        "Takhteh-ye Dowlat\u0101b\u0101d"
    ],
    "wof:name":"Taktah-ye Dolatabad",
    "wof:placetype":"locality"
},
  "geometry": {"coordinates":[64.91364,36.49153],"type":"Point"}
}