{
  "type": "Feature",
  "properties": {
    "gn:admin1_code":"41",
    "gn:admin2_code":"3409.0",
    "gn:asciiname":"Tagab",
    "gn:country_code":"AF",
    "gn:dem":2326,
    "gn:feature_class":"P",
    "gn:feature_code":"PPL",
    "gn:name":"Tag\u0101b",
    "gn:population":0,
    "gn:timezone":"Asia/Kabul",
    "iso:country":"AF",
    "name:ceb_x_preferred":[
        "Tagab"
    ],
    "name:deu_x_preferred":[
        "Tagab"
    ],
    "name:pnb_x_preferred":[
        "\u0636\u0644\u0639 \u062a\u06af\u0627\u0628"
    ],
    "name:swe_x_preferred":[
        "Tagab"
    ],
    "name:und_x_variant":[
        "Tag\u0101b",
        "\u062a\u06af\u0627\u0628"
    ],
    "wof:name":"Tagab",
    "wof:placetype":"locality"
},
  "geometry": {"coordinates":[66.39169,33.88493],"type":"Point"}
}