{
  "type": "Feature",
  "properties": {
    "gn:admin1_code":"29",
    "gn:admin2_code":"2901.0",
    "gn:asciiname":"Dzadran",
    "gn:country_code":"AF",
    "gn:dem":2136,
    "gn:feature_class":"P",
    "gn:feature_code":"PPL",
    "gn:name":"Dzadr\u0101n",
    "gn:population":0,
    "gn:timezone":"Asia/Kabul",
    "iso:country":"AF",
    "name:und_x_variant":[
        "Dzhadran",
        "\u0681\u062f\u0631\u0627\u06bc",
        "Jadr\u0101n",
        "Dzadr\u0101\u1e49",
        "Dzadr\u0101n",
        "\u0681\u062f\u0631\u0627\u0646"
    ],
    "wof:name":"Dzadran",
    "wof:placetype":"locality"
},
  "geometry": {"coordinates":[68.80289,33.20111],"type":"Point"}
}