{
  "type": "Feature",
  "properties": {
    "gn:admin1_code":"13",
    "gn:admin2_code":"108.0",
    "gn:asciiname":"Qazi Khel",
    "gn:country_code":"AF",
    "gn:dem":2177,
    "gn:feature_class":"P",
    "gn:feature_code":"PPL",
    "gn:name":"Q\u0101\u1e95\u012b Kh\u0113l",
    "gn:population":0,
    "gn:timezone":"Asia/Kabul",
    "iso:country":"AF",
    "name:rus_x_preferred":[
        "Kazikheyl\u2019"
    ],
    "name:und_x_variant":[
        "Q\u0101\u1e0f\u1e95ikh\u0113l",
        "Q\u0101\u1e95\u012bkheyl",
        "Q\u0101\u1e95\u012b Kh\u0113l",
        "\u0642\u0627\u0636\u06cc \u062e\u06d0\u0644"
    ],
    "wof:name":"Qazi Khel",
    "wof:placetype":"locality"
},
  "geometry": {"coordinates":[68.96032,34.56339000000001],"type":"Point"}
}