{
  "type": "Feature",
  "properties": {
    "gn:admin1_code":"23",
    "gn:admin2_code":"2412",
    "gn:asciiname":"Koghey",
    "gn:country_code":"AF",
    "gn:dem":1229,
    "gn:feature_class":"P",
    "gn:feature_code":"PPL",
    "gn:name":"K\u014dgh\u00eay",
    "gn:population":0,
    "gn:timezone":"Asia/Kabul",
    "iso:country":"AF",
    "name:und_x_variant":[
        "Towgh\u012b",
        "Kowgh\u012b",
        "K\u014dghey",
        "K\u014dghay",
        "Kogay",
        "K\u014dgh\u00eay",
        "\u06a9\u0648\u063a\u06cd",
        "Kowghay"
    ],
    "wof:name":"Koghey",
    "wof:placetype":"locality"
},
  "geometry": {"coordinates":[66.29661,31.43903],"type":"Point"}
}