{
  "type": "Feature",
  "properties": {
    "gn:admin1_code":"08",
    "gn:admin2_code":"611",
    "gn:asciiname":"Manur Kala",
    "gn:country_code":"AF",
    "gn:dem":2021,
    "gn:feature_class":"P",
    "gn:feature_code":"PPL",
    "gn:name":"Man\u016br Kal\u0101",
    "gn:population":0,
    "gn:timezone":"Asia/Kabul",
    "iso:country":"AF",
    "name:und_x_variant":[
        "\u0645\u0646\u0648\u0631 \u06a9\u0644\u0627",
        "Man\u016br Kal\u0101"
    ],
    "wof:name":"Manur Kala",
    "wof:placetype":"locality"
},
  "geometry": {"coordinates":[68.08991999999999,32.82201],"type":"Point"}
}