{
  "type": "Feature",
  "properties": {
    "gn:admin1_code":"27",
    "gn:admin2_code":"403.0",
    "gn:asciiname":"Naray",
    "gn:cc2":"AF",
    "gn:country_code":"AF",
    "gn:dem":3366,
    "gn:feature_class":"P",
    "gn:feature_code":"PPL",
    "gn:name":"Naray",
    "gn:population":0,
    "gn:timezone":"Asia/Kabul",
    "iso:country":"AF",
    "name:und_x_variant":[
        "\u0646\u0631\u06cc"
    ],
    "wof:name":"Naray",
    "wof:placetype":"locality"
},
  "geometry": {"coordinates":[68.25833,34.43917],"type":"Point"}
}