{
  "type": "Feature",
  "properties": {
    "gn:admin1_code":"27",
    "gn:admin2_code":"405.0",
    "gn:asciiname":"Ghow Charak",
    "gn:country_code":"AF",
    "gn:dem":2834,
    "gn:feature_class":"P",
    "gn:feature_code":"PPL",
    "gn:name":"Ghow Ch\u0101rak",
    "gn:population":0,
    "gn:timezone":"Asia/Kabul",
    "iso:country":"AF",
    "name:und_x_variant":[
        "Gavcharak",
        "Ghaw\u010d\u0101rak",
        "Gh\u014d Ch\u0101rak",
        "Gh\u0101bch\u0101rak",
        "Ghow Ch\u0101rak",
        "\u063a\u0648 \u0686\u0627\u0631\u06a9"
    ],
    "wof:name":"Ghow Charak",
    "wof:placetype":"locality"
},
  "geometry": {"coordinates":[68.2825,34.34389],"type":"Point"}
}