{
  "type": "Feature",
  "properties": {
    "gn:admin1_code":"42",
    "gn:admin2_code":"3306.0",
    "gn:asciiname":"Kankoh",
    "gn:country_code":"AF",
    "gn:dem":2136,
    "gn:feature_class":"P",
    "gn:feature_code":"PPL",
    "gn:name":"Kank\u014dh",
    "gn:population":0,
    "gn:timezone":"Asia/Kabul",
    "iso:country":"AF",
    "name:fas_x_preferred":[
        "\u0643\u0646\u0643\u0648\u0647"
    ],
    "name:und_x_variant":[
        "Kankokh",
        "Kankoh",
        "Kank\u016bh",
        "Kank\u014dh",
        "\u06a9\u0646\u06a9\u0648\u0647"
    ],
    "wof:name":"Kankoh",
    "wof:placetype":"locality"
},
  "geometry": {"coordinates":[69.45000999999999,35.22155],"type":"Point"}
}