{
  "type": "Feature",
  "properties": {
    "gn:admin1_code":"23",
    "gn:admin2_code":"2408.0",
    "gn:asciiname":"Bala Deh-e 'Ulya",
    "gn:country_code":"AF",
    "gn:dem":965,
    "gn:feature_class":"P",
    "gn:feature_code":"PPL",
    "gn:name":"B\u0101l\u0101 Deh-e \u2018Uly\u0101",
    "gn:population":0,
    "gn:timezone":"Asia/Kabul",
    "iso:country":"AF",
    "name:fas_x_preferred":[
        "\u0628\u0627\u0644\u0627 \u062f\u0647\u0654\u0654 \u0639\u0644\u064a\u0627"
    ],
    "name:und_x_variant":[
        "Bala-Dekhi-Ulia",
        "B\u0101l\u0101 \u1e0eehe \u2018Uly\u0101",
        "B\u0101l\u0101 Deh-e \u2018Uly\u0101",
        "\u0628\u0627\u0644\u0627 \u062f\u0647 \u0639\u0644\u06cc\u0627",
        "B\u0101l\u0101 Deh-e \u2018Oly\u0101"
    ],
    "wof:name":"Bala Deh-e 'Ulya",
    "wof:placetype":"locality"
},
  "geometry": {"coordinates":[65.59957,31.53833],"type":"Point"}
}