{
  "type": "Feature",
  "properties": {
    "gn:admin1_code":"27",
    "gn:admin2_code":"404.0",
    "gn:asciiname":"Baba Khan",
    "gn:country_code":"AF",
    "gn:dem":2703,
    "gn:feature_class":"P",
    "gn:feature_code":"PPL",
    "gn:name":"B\u0101b\u0101 Kh\u0101n",
    "gn:population":0,
    "gn:timezone":"Asia/Kabul",
    "iso:country":"AF",
    "name:und_x_variant":[
        "Babakhan",
        "B\u0101bah Kh\u0101n",
        "B\u0101b\u0101 Kh\u0101n",
        "B\u0101b\u0101kh\u0101n",
        "\u0628\u0627\u0628\u0627 \u062e\u0627\u0646"
    ],
    "wof:name":"Baba Khan",
    "wof:placetype":"locality"
},
  "geometry": {"coordinates":[67.82661,34.42665],"type":"Point"}
}