{
  "type": "Feature",
  "properties": {
    "gn:admin1_code":"05",
    "gn:admin2_code":"2806.0",
    "gn:asciiname":"Qaryah-ye Qarateray",
    "gn:country_code":"AF",
    "gn:dem":3338,
    "gn:feature_class":"P",
    "gn:feature_code":"PPL",
    "gn:name":"Qaryah-ye Qarater\u0101y",
    "gn:population":0,
    "gn:timezone":"Asia/Kabul",
    "iso:country":"AF",
    "wof:name":"Qaryah-ye Qarateray",
    "wof:placetype":"locality"
},
  "geometry": {"coordinates":[67.35469000000001,34.31111],"type":"Point"}
}