{
  "type": "Feature",
  "properties": {
    "gn:admin1_code":"08",
    "gn:admin2_code":"606",
    "gn:asciiname":"Olang",
    "gn:country_code":"AF",
    "gn:dem":3092,
    "gn:feature_class":"P",
    "gn:feature_code":"PPL",
    "gn:name":"\u014clang",
    "gn:population":0,
    "gn:timezone":"Asia/Kabul",
    "iso:country":"AF",
    "name:und_x_variant":[
        "\u016alang",
        "Owlang",
        "\u014clang",
        "\u0627\u0648\u0644\u0646\u06af"
    ],
    "wof:name":"Olang",
    "wof:placetype":"locality"
},
  "geometry": {"coordinates":[67.14553000000001,33.15304],"type":"Point"}
}