{
  "type": "Feature",
  "properties": {
    "gn:admin1_code":"10",
    "gn:admin2_code":"2305",
    "gn:asciiname":"Ta Chinah",
    "gn:country_code":"AF",
    "gn:dem":1746,
    "gn:feature_class":"P",
    "gn:feature_code":"PPL",
    "gn:name":"T\u0101 Ch\u012bnah",
    "gn:population":0,
    "gn:timezone":"Asia/Kabul",
    "iso:country":"AF",
    "name:fas_x_preferred":[
        "\u0686\u0634\u0645\u06c0 \u062a\u0627"
    ],
    "name:rus_x_preferred":[
        "\u0422\u0430\u0447\u0438\u043d\u0430"
    ],
    "name:und_x_variant":[
        "Tachina",
        "T\u0101 \u010cina",
        "T\u0101 Ch\u012bnah",
        "\u062a\u0627 \u0686\u06cc\u0646\u0647"
    ],
    "wof:name":"Ta Chinah",
    "wof:placetype":"locality"
},
  "geometry": {"coordinates":[65.0346,33.13177],"type":"Point"}
}