{
  "type": "Feature",
  "properties": {
    "gn:admin1_code":"28",
    "gn:admin2_code":"2509",
    "gn:asciiname":"Skhwandar",
    "gn:country_code":"AF",
    "gn:dem":2090,
    "gn:feature_class":"P",
    "gn:feature_code":"PPL",
    "gn:name":"Skhwandar",
    "gn:population":0,
    "gn:timezone":"Asia/Kabul",
    "iso:country":"AF",
    "name:und_x_variant":[
        "Skhvandar",
        "Skhwandar",
        "\u0633\u062e\u0648\u0646\u062f\u0631"
    ],
    "wof:name":"Skhwandar",
    "wof:placetype":"locality"
},
  "geometry": {"coordinates":[67.77938,31.8783],"type":"Point"}
}