{
  "type": "Feature",
  "properties": {
    "gn:admin1_code":"18",
    "gn:admin2_code":"810.0",
    "gn:asciiname":"Bahram Khel",
    "gn:country_code":"AF",
    "gn:dem":1095,
    "gn:feature_class":"P",
    "gn:feature_code":"PPL",
    "gn:name":"Bahr\u0101m Kh\u0113l",
    "gn:population":0,
    "gn:timezone":"Asia/Kabul",
    "iso:country":"AF",
    "name:fas_x_preferred":[
        "\u0628\u0647\u0631\u0627\u0645 \u062e\u064a\u0644"
    ],
    "name:rus_x_preferred":[
        "Bakhramkheyl\u2019"
    ],
    "name:und_x_variant":[
        "Bah\u1e5f\u0101mkh\u0113l",
        "Bahr\u0101mkheyl",
        "Bahr\u0101m Kh\u0113l",
        "\u0628\u0647\u0631\u0627\u0645 \u062e\u06d0\u0644"
    ],
    "wof:name":"Bahram Khel",
    "wof:placetype":"locality"
},
  "geometry": {"coordinates":[70.67610999999999,34.1171],"type":"Point"}
}