{
  "type": "Feature",
  "properties": {
    "gn:admin1_code":"32",
    "gn:admin2_code":"1505",
    "gn:asciiname":"Khwajah Za'id",
    "gn:country_code":"AF",
    "gn:dem":2519,
    "gn:feature_class":"P",
    "gn:feature_code":"PPL",
    "gn:name":"Khw\u0101jah Z\u0101\u2019\u012bd",
    "gn:population":0,
    "gn:timezone":"Asia/Kabul",
    "iso:country":"AF",
    "name:und_x_variant":[
        "Khw\u0101jaz\u0101\u2019\u012b\u1e0f",
        "Khw\u0101ja-Z\u0101he\u1e0f",
        "Khv\u0101jeh Z\u0101\u2019\u012b",
        "Khw\u0101jah Z\u0304\u0101yed",
        "Khw\u0101ja Zai",
        "Khv\u0101jeh Z\u0101hed",
        "Khw\u0101jah Z\u0101\u2019\u012bd",
        "\u062e\u0648\u0627\u062c\u0647 \u0632\u0627\u0626\u06cc\u062f"
    ],
    "wof:name":"Khwajah Za'id",
    "wof:placetype":"locality"
},
  "geometry": {"coordinates":[67.73260000000001,35.60290999999999],"type":"Point"}
}