{
  "type": "Feature",
  "properties": {
    "gn:admin1_code":"27",
    "gn:admin2_code":"403",
    "gn:asciiname":"Sakowlah",
    "gn:country_code":"AF",
    "gn:dem":2694,
    "gn:feature_class":"P",
    "gn:feature_code":"PPL",
    "gn:name":"Sakowlah",
    "gn:population":0,
    "gn:timezone":"Asia/Kabul",
    "iso:country":"AF",
    "name:und_x_variant":[
        "Sakaula",
        "Sakawla",
        "Sak\u014dlah",
        "Sakawalah",
        "Sakowlah",
        "\u0633\u06a9\u0648\u0644\u0647"
    ],
    "wof:name":"Sakowlah",
    "wof:placetype":"locality"
},
  "geometry": {"coordinates":[68.13417,34.31798],"type":"Point"}
}