{
  "type": "Feature",
  "properties": {
    "gn:admin1_code":"17",
    "gn:admin2_code":"505.0",
    "gn:asciiname":"Dag Kala",
    "gn:country_code":"AF",
    "gn:dem":1969,
    "gn:feature_class":"P",
    "gn:feature_code":"PPL",
    "gn:name":"\u1e0e\u0101g Kal\u0101",
    "gn:population":0,
    "gn:timezone":"Asia/Kabul",
    "iso:country":"AF",
    "name:und_x_variant":[
        "Dagkala",
        "\u1e0e\u0101g Kal\u0101",
        "D\u0101g Kal\u0101",
        "\u0689\u0627\u06af \u06a9\u0644\u0627"
    ],
    "wof:name":"Dag Kala",
    "wof:placetype":"locality"
},
  "geometry": {"coordinates":[69.07458000000001,34.28614],"type":"Point"}
}