{
  "type": "Feature",
  "properties": {
    "gn:admin1_code":"02",
    "gn:admin2_code":"1903",
    "gn:asciiname":"Lowandan Langar",
    "gn:country_code":"AF",
    "gn:dem":1196,
    "gn:feature_class":"P",
    "gn:feature_code":"PPL",
    "gn:name":"Lowand\u0101n Langar",
    "gn:population":0,
    "gn:timezone":"Asia/Kabul",
    "iso:country":"AF",
    "name:und_x_variant":[
        "Lavandanlangar",
        "Lawan\u1e0f\u0101n Langa\u1e5f",
        "Lavand\u0101n Langar",
        "Lowand\u0101n Langar",
        "\u0644\u0648\u0646\u062f\u0627\u0646 \u0644\u0646\u06af\u0631"
    ],
    "wof:name":"Lowandan Langar",
    "wof:placetype":"locality"
},
  "geometry": {"coordinates":[63.43365,34.87761],"type":"Point"}
}