{
  "type": "Feature",
  "properties": {
    "gn:admin1_code":"41",
    "gn:admin2_code":"3406",
    "gn:asciiname":"Sar-e Tayghan",
    "gn:country_code":"AF",
    "gn:dem":1423,
    "gn:feature_class":"P",
    "gn:feature_code":"PPLA2",
    "gn:name":"Sar-e Taygh\u0101n",
    "gn:population":0,
    "gn:timezone":"Asia/Kabul",
    "iso:country":"AF",
    "name:und_x_variant":[
        "Sar-e Taygh\u0101n",
        "\u0633\u0631 \u062a\u06cc\u063a\u0627\u0646",
        "Sa\u1e5f T\u0113gh\u0101n"
    ],
    "wof:name":"Sar-e Tayghan",
    "wof:placetype":"locality"
},
  "geometry": {"coordinates":[65.67631999999999,33.50998],"type":"Point"}
}