{
  "type": "Feature",
  "properties": {
    "gn:admin1_code":"13",
    "gn:admin2_code":"106",
    "gn:asciiname":"Sang Lakh",
    "gn:country_code":"AF",
    "gn:dem":1720,
    "gn:feature_class":"P",
    "gn:feature_code":"PPL",
    "gn:name":"Sang L\u0101kh",
    "gn:population":0,
    "gn:timezone":"Asia/Kabul",
    "iso:country":"AF",
    "name:fas_x_preferred":[
        "\u0633\u0646\u06af\u0644\u0627\u062e"
    ],
    "name:und_x_variant":[
        "Sanglakh",
        "Sang L\u0101kh",
        "\u0633\u0646\u06af \u0644\u0627\u062e"
    ],
    "wof:name":"Sang Lakh",
    "wof:placetype":"locality"
},
  "geometry": {"coordinates":[69.09896999999999,34.82806],"type":"Point"}
}