{
  "type": "Feature",
  "properties": {
    "gn:admin1_code":"27",
    "gn:admin2_code":"404",
    "gn:asciiname":"Khushk Qol",
    "gn:country_code":"AF",
    "gn:dem":2995,
    "gn:feature_class":"P",
    "gn:feature_code":"PPL",
    "gn:name":"Khushk Q\u014dl",
    "gn:population":0,
    "gn:timezone":"Asia/Kabul",
    "iso:country":"AF",
    "name:rus_x_preferred":[
        "Khushkkul\u2019"
    ],
    "name:rus_x_variant":[
        "\u0425\u0443\u0448\u043a\u043a\u0443\u043b\u044c"
    ],
    "name:und_x_variant":[
        "Khu\u0161kqol",
        "Khushk Q\u014dl",
        "Khoshkqowl",
        "\u062e\u0634\u06a9 \u0642\u0648\u0644"
    ],
    "wof:name":"Khushk Qol",
    "wof:placetype":"locality"
},
  "geometry": {"coordinates":[67.39291999999999,34.58141],"type":"Point"}
}