{
  "type": "Feature",
  "properties": {
    "gn:admin1_code":"18",
    "gn:admin2_code":"804",
    "gn:asciiname":"Showe",
    "gn:country_code":"AF",
    "gn:dem":1213,
    "gn:feature_class":"P",
    "gn:feature_code":"PPL",
    "gn:name":"Show\u0113",
    "gn:population":0,
    "gn:timezone":"Asia/Kabul",
    "iso:country":"AF",
    "name:fas_x_preferred":[
        "\u0634\u0648\u06cc"
    ],
    "name:und_x_variant":[
        "Shave",
        "\u0160aw\u0113",
        "Shaw\u0113",
        "Show\u0113",
        "\u0634\u0648\u06d0"
    ],
    "wof:name":"Showe",
    "wof:placetype":"locality"
},
  "geometry": {"coordinates":[70.03137,34.31001],"type":"Point"}
}