{
  "type": "Feature",
  "properties": {
    "gn:admin1_code":"27",
    "gn:admin2_code":"402.0",
    "gn:asciiname":"Kotah-ye Habibullah",
    "gn:country_code":"AF",
    "gn:dem":2573,
    "gn:feature_class":"P",
    "gn:feature_code":"PPL",
    "gn:name":"K\u014dtah-ye \u1e28ab\u012bbull\u0101h",
    "gn:population":0,
    "gn:timezone":"Asia/Kabul",
    "iso:country":"AF",
    "wof:name":"Kotah-ye Habibullah",
    "wof:placetype":"locality"
},
  "geometry": {"coordinates":[68.51518,34.44922],"type":"Point"}
}