{
  "type": "Feature",
  "properties": {
    "gn:admin1_code":"29",
    "gn:admin2_code":"2909.0",
    "gn:asciiname":"Sharif Khel",
    "gn:country_code":"AF",
    "gn:dem":1925,
    "gn:feature_class":"P",
    "gn:feature_code":"PPL",
    "gn:name":"Shar\u012bf Kh\u0113l",
    "gn:population":0,
    "gn:timezone":"Asia/Kabul",
    "iso:country":"AF",
    "name:und_x_variant":[
        "Sharifkheyl\u2019",
        "\u0160ar\u012bfkh\u0113l",
        "Sar\u012bf Kheyl",
        "Shar\u012bf Kh\u0113l"
    ],
    "wof:name":"Sharif Khel",
    "wof:placetype":"locality"
},
  "geometry": {"coordinates":[69.34234000000001,32.79074],"type":"Point"}
}