{
  "type": "Feature",
  "properties": {
    "gn:admin1_code":"03",
    "gn:admin2_code":"1301",
    "gn:asciiname":"Shahabuddin",
    "gn:country_code":"AF",
    "gn:dem":580,
    "gn:feature_class":"P",
    "gn:feature_code":"PPL",
    "gn:name":"Shah\u0101budd\u012bn",
    "gn:population":0,
    "gn:timezone":"Asia/Kabul",
    "iso:country":"AF",
    "name:fas_x_preferred":[
        "\u0634\u0647\u0627\u0628 \u0627\u0644\u062f\u064a\u0646"
    ],
    "name:rus_x_preferred":[
        "\u0428\u0430\u0445\u0430\u0431\u0443\u0434\u0434\u0438\u043d"
    ],
    "name:und_x_variant":[
        "Mi\u0101n S\u0101hib",
        "\u0160ah\u0101buddin",
        "Shah\u0101bodd\u012bn",
        "Shakhabuddin",
        "Shah\u0101b od D\u012bn",
        "Shah\u0101budd\u012bn",
        "\u0634\u0647\u0627\u0628 \u0627\u0644\u062f\u06cc\u0646"
    ],
    "wof:name":"Shahabuddin",
    "wof:placetype":"locality"
},
  "geometry": {"coordinates":[68.6454,36.03534000000001],"type":"Point"}
}