{
  "type": "Feature",
  "properties": {
    "gn:admin1_code":"10",
    "gn:admin2_code":"2307",
    "gn:asciiname":"Landay Karez",
    "gn:country_code":"AF",
    "gn:dem":1174,
    "gn:feature_class":"P",
    "gn:feature_code":"PPL",
    "gn:name":"Lan\u1e0fay K\u0101r\u0113z",
    "gn:population":0,
    "gn:timezone":"Asia/Kabul",
    "iso:country":"AF",
    "name:und_x_variant":[
        "Landaykarez",
        "Landay K\u0101\u1e5f\u0113z",
        "Lan\u1e0fay K\u0101r\u0113z",
        "\u0644\u0646\u0689\u06cc \u06a9\u0627\u0631\u06d0\u0632",
        "Landay K\u0101r\u012bz"
    ],
    "wof:name":"Landay Karez",
    "wof:placetype":"locality"
},
  "geometry": {"coordinates":[64.04203000000001,32.13644],"type":"Point"}
}