{
  "type": "Feature",
  "properties": {
    "gn:admin1_code":"07",
    "gn:admin2_code":"1808",
    "gn:asciiname":"Khwajah Anjir",
    "gn:country_code":"AF",
    "gn:dem":990,
    "gn:feature_class":"P",
    "gn:feature_code":"PPL",
    "gn:name":"Khw\u0101jah Anj\u012br",
    "gn:population":0,
    "gn:timezone":"Asia/Kabul",
    "iso:country":"AF",
    "name:und_x_variant":[
        "Khw\u0101ja Anj\u012br",
        "Khv\u0101jeh Anj\u012br",
        "Khw\u0101jah Anj\u012br",
        "\u062e\u0648\u0627\u062c\u0647 \u0627\u0646\u062c\u06cc\u0631"
    ],
    "wof:name":"Khwajah Anjir",
    "wof:placetype":"locality"
},
  "geometry": {"coordinates":[65.03404,36.17898],"type":"Point"}
}