{
  "type": "Feature",
  "properties": {
    "gn:admin1_code":"37",
    "gn:admin2_code":"3202.0",
    "gn:asciiname":"Taghari",
    "gn:country_code":"AF",
    "gn:dem":1463,
    "gn:feature_class":"P",
    "gn:feature_code":"PPL",
    "gn:name":"Taghar\u012b",
    "gn:population":0,
    "gn:timezone":"Asia/Kabul",
    "iso:country":"AF",
    "name:und_x_variant":[
        "Loghori",
        "Tagari",
        "Taghar\u012b",
        "Taghari",
        "\u062a\u063a\u0631\u06cc"
    ],
    "wof:name":"Taghari",
    "wof:placetype":"locality"
},
  "geometry": {"coordinates":[70.08112,33.60995],"type":"Point"}
}