{
  "type": "Feature",
  "properties": {
    "gn:admin1_code":"8",
    "gn:admin2_code":"614.0",
    "gn:asciiname":"Miyani",
    "gn:country_code":"AF",
    "gn:dem":2102,
    "gn:feature_class":"P",
    "gn:feature_code":"PPL",
    "gn:name":"Miy\u0101n\u012b",
    "gn:population":0,
    "gn:timezone":"Asia/Kabul",
    "iso:country":"AF",
    "name:fas_x_preferred":[
        "\u0645\u064a\u0627\u0646\u06cc"
    ],
    "name:und_x_variant":[
        "My\u0101ni",
        "Miani",
        "My\u0101n\u012b",
        "M\u012b\u0101n\u012b",
        "Miy\u0101n\u012b"
    ],
    "wof:name":"Miyani",
    "wof:placetype":"locality"
},
  "geometry": {"coordinates":[68.42889,33.39625],"type":"Point"}
}