{
  "type": "Feature",
  "properties": {
    "gn:admin1_code":"09",
    "gn:admin2_code":"2705",
    "gn:asciiname":"Khwajah Ziarat",
    "gn:country_code":"AF",
    "gn:dem":2290,
    "gn:feature_class":"P",
    "gn:feature_code":"PPL",
    "gn:name":"Khw\u0101jah Z\u012b\u0101rat",
    "gn:population":0,
    "gn:timezone":"Asia/Kabul",
    "iso:country":"AF",
    "name:und_x_variant":[
        "Khodzhaziarat",
        "Khw\u0101ja Zy\u0101\u1e5fat",
        "Khw\u0101jah Z\u012b\u0101rat",
        "\u062e\u0648\u0627\u062c\u0647 \u0632\u06cc\u0627\u0631\u062a",
        "Khv\u0101jeh Z\u012b\u0101rat"
    ],
    "wof:name":"Khwajah Ziarat",
    "wof:placetype":"locality"
},
  "geometry": {"coordinates":[64.30608000000001,33.35576],"type":"Point"}
}