{
  "type": "Feature",
  "properties": {
    "gn:admin1_code":"39",
    "gn:admin2_code":"2602",
    "gn:asciiname":"Kham",
    "gn:country_code":"AF",
    "gn:dem":2053,
    "gn:feature_class":"P",
    "gn:feature_code":"PPL",
    "gn:name":"Kh\u0101m",
    "gn:population":0,
    "gn:timezone":"Asia/Kabul",
    "iso:country":"AF",
    "name:und_x_variant":[
        "Kh\u0101m",
        "\u062e\u0627\u0645"
    ],
    "wof:name":"Kham",
    "wof:placetype":"locality"
},
  "geometry": {"coordinates":[66.39609,33.24471],"type":"Point"}
}