{
  "type": "Feature",
  "properties": {
    "gn:admin1_code":"27",
    "gn:admin2_code":"404.0",
    "gn:asciiname":"Diyari",
    "gn:country_code":"AF",
    "gn:dem":2869,
    "gn:feature_class":"P",
    "gn:feature_code":"PPL",
    "gn:name":"Diy\u0101r\u012b",
    "gn:population":0,
    "gn:timezone":"Asia/Kabul",
    "iso:country":"AF",
    "name:und_x_variant":[
        "Diari",
        "D\u012b\u0101r\u012b",
        "\u062f\u064a\u0627\u0631\u06cc",
        "Diy\u0101r\u012b"
    ],
    "wof:name":"Diyari",
    "wof:placetype":"locality"
},
  "geometry": {"coordinates":[67.40805999999999,34.4964],"type":"Point"}
}