{
  "type": "Feature",
  "properties": {
    "gn:admin1_code":"14",
    "gn:admin2_code":"201.0",
    "gn:asciiname":"Shahbaz Khel",
    "gn:country_code":"AF",
    "gn:dem":1474,
    "gn:feature_class":"P",
    "gn:feature_code":"PPL",
    "gn:name":"Sh\u0101hb\u0101z Kh\u0113l",
    "gn:population":0,
    "gn:timezone":"Asia/Kabul",
    "iso:country":"AF",
    "name:fas_x_preferred":[
        "\u0634\u0647\u0628\u0627\u0632 \u062e\u064a\u0644"
    ],
    "name:fas_x_variant":[
        "\u0634\u0647\u0628\u0627\u0632 \u062e\u06cc\u0644"
    ],
    "name:rus_x_preferred":[
        "Shakhbazkheyl\u2019"
    ],
    "name:und_x_variant":[
        "\u0160ahb\u0101zkh\u0113l",
        "Shahb\u0101zkheyl",
        "Sh\u0101hb\u0101z Kh\u0113l",
        "\u0634\u0627\u0647\u0628\u0627\u0632 \u062e\u06d0\u0644"
    ],
    "wof:name":"Shahbaz Khel",
    "wof:placetype":"locality"
},
  "geometry": {"coordinates":[69.30993000000001,35.02242],"type":"Point"}
}