{
  "type": "Feature",
  "properties": {
    "gn:admin1_code":"11",
    "gn:admin2_code":"2015",
    "gn:asciiname":"Spizow",
    "gn:country_code":"AF",
    "gn:dem":1974,
    "gn:feature_class":"P",
    "gn:feature_code":"PPL",
    "gn:name":"Sp\u012bzow",
    "gn:population":0,
    "gn:timezone":"Asia/Kabul",
    "iso:country":"AF",
    "name:und_x_variant":[
        "Spizau",
        "Spizaw",
        "Sp\u012bzow",
        "\u0633\u067e\u06cc\u0632\u0648",
        "Sp\u012bdzaw"
    ],
    "wof:name":"Spizow",
    "wof:placetype":"locality"
},
  "geometry": {"coordinates":[64.05585000000001,34.46096],"type":"Point"}
}