{
  "type": "Feature",
  "properties": {
    "gn:admin1_code":"24",
    "gn:admin2_code":"1404.0",
    "gn:asciiname":"Basoz",
    "gn:country_code":"AF",
    "gn:dem":369,
    "gn:feature_class":"P",
    "gn:feature_code":"PPL",
    "gn:name":"B\u0101s\u014dz",
    "gn:population":0,
    "gn:timezone":"Asia/Kabul",
    "iso:country":"AF",
    "name:rus_x_preferred":[
        "\u0411\u0430\u0441\u043e\u0437"
    ],
    "name:und_x_variant":[
        "B\u0101s\u014dz",
        "B\u0101s\u016bz",
        "\u0628\u0627\u0633\u0648\u0632"
    ],
    "wof:name":"Basoz",
    "wof:placetype":"locality"
},
  "geometry": {"coordinates":[68.72269,36.76637],"type":"Point"}
}