{
  "type": "Feature",
  "properties": {
    "gn:admin1_code":"30",
    "gn:admin2_code":"1612.0",
    "gn:asciiname":"Qal'ah-ye 'Abbas Khan",
    "gn:country_code":"AF",
    "gn:dem":355,
    "gn:feature_class":"P",
    "gn:feature_code":"PPL",
    "gn:name":"Qal\u2018ah-ye \u2018Abb\u0101s Kh\u0101n",
    "gn:population":0,
    "gn:timezone":"Asia/Kabul",
    "iso:country":"AF",
    "name:fas_x_preferred":[
        "\u0642\u0644\u0639\u0647\u0654 \u0639\u0628\u0627\u0633 \u062e\u0627\u0646"
    ],
    "name:rus_x_preferred":[
        "\u041a\u0430\u043b\u0430\u0439\u0438-\u0410\u0431\u0431\u0430\u0441\u0445\u0430\u043d"
    ],
    "name:und_x_variant":[
        "Qala-i-Abb\u0101s Kh\u0101n",
        "Kalayi-Abbaskhan",
        "Qal\u2018ah-ye \u2018Abb\u0101s Kh\u0101n"
    ],
    "wof:name":"Qal'ah-ye 'Abbas Khan",
    "wof:placetype":"locality"
},
  "geometry": {"coordinates":[67.00194,36.7225],"type":"Point"}
}