{
  "type": "Feature",
  "properties": {
    "gn:admin1_code":"27",
    "gn:admin2_code":"404",
    "gn:asciiname":"Shaykh Qal'ah",
    "gn:country_code":"AF",
    "gn:dem":2771,
    "gn:feature_class":"P",
    "gn:feature_code":"PPL",
    "gn:name":"Shaykh Qal\u2018ah",
    "gn:population":0,
    "gn:timezone":"Asia/Kabul",
    "iso:country":"AF",
    "name:und_x_variant":[
        "\u0160\u0113khqal\u2018a",
        "Shekhkala",
        "Sheykhqal\u2018eh",
        "Shaykh Qal\u2018ah",
        "\u0634\u06cc\u062e \u0642\u0644\u0639\u0647"
    ],
    "wof:name":"Shaykh Qal'ah",
    "wof:placetype":"locality"
},
  "geometry": {"coordinates":[68.03301,34.27191],"type":"Point"}
}