{
  "type": "Feature",
  "properties": {
    "gn:admin1_code":"14",
    "gn:admin2_code":"204",
    "gn:asciiname":"Zulm Khel",
    "gn:country_code":"AF",
    "gn:dem":2061,
    "gn:feature_class":"P",
    "gn:feature_code":"PPL",
    "gn:name":"Z\u0327ulm Kh\u0113l",
    "gn:population":0,
    "gn:timezone":"Asia/Kabul",
    "iso:country":"AF",
    "name:fas_x_preferred":[
        "\u0638\u0644\u0645 \u062e\u064a\u0644"
    ],
    "name:rus_x_preferred":[
        "\u0417\u0443\u043b\u044c\u043c\u0445\u0435\u0439\u043b\u044c"
    ],
    "name:und_x_variant":[
        "Zul\u2019mkheyl\u2019",
        "\u1e94ulmkh\u0113l",
        "Z\u0327olmkheyl",
        "Z\u0327ulm Kh\u0113l",
        "\u0638\u0644\u0645 \u062e\u06d0\u0644"
    ],
    "wof:name":"Zulm Khel",
    "wof:placetype":"locality"
},
  "geometry": {"coordinates":[69.59683000000001,35.06237],"type":"Point"}
}