{
  "type": "Feature",
  "properties": {
    "gn:admin1_code":"40",
    "gn:admin2_code":"307.0",
    "gn:asciiname":"Qonaq",
    "gn:country_code":"AF",
    "gn:dem":2260,
    "gn:feature_class":"P",
    "gn:feature_code":"PPL",
    "gn:name":"Q\u014dn\u0101q",
    "gn:population":0,
    "gn:timezone":"Asia/Kabul",
    "iso:country":"AF",
    "name:und_x_variant":[
        "Konak",
        "Q\u014dn\u0101q",
        "Q\u016bn\u0101q",
        "\u0642\u0648\u0646\u0627\u0642"
    ],
    "wof:name":"Qonaq",
    "wof:placetype":"locality"
},
  "geometry": {"coordinates":[68.61758,34.81365],"type":"Point"}
}