{
  "type": "Feature",
  "properties": {
    "gn:admin1_code":"33",
    "gn:admin2_code":"3104",
    "gn:asciiname":"Sar-e Pul",
    "gn:country_code":"AF",
    "gn:dem":1372,
    "gn:feature_class":"P",
    "gn:feature_code":"PPL",
    "gn:name":"Sar-e Pul",
    "gn:population":0,
    "gn:timezone":"Asia/Kabul",
    "iso:country":"AF",
    "name:und_x_variant":[
        "Qaryeh-ye Sar-e Pol",
        "Sa\u1e5fe Pul",
        "Sar-i-Pul",
        "Sar-e Pol",
        "Sar-e Pul",
        "\u0633\u0631 \u067e\u0644"
    ],
    "wof:name":"Sar-e Pul",
    "wof:placetype":"locality"
},
  "geometry": {"coordinates":[66.71831,35.5352],"type":"Point"}
}