{
  "type": "Feature",
  "properties": {
    "gn:admin1_code":"26",
    "gn:admin2_code":"1205",
    "gn:asciiname":"Deh-e Jangalok",
    "gn:country_code":"AF",
    "gn:dem":2205,
    "gn:feature_class":"P",
    "gn:feature_code":"PPL",
    "gn:name":"Deh-e Jangal\u014dk",
    "gn:population":0,
    "gn:timezone":"Asia/Kabul",
    "iso:country":"AF",
    "name:und_x_variant":[
        "Deh-e Jangal\u014dk",
        "Deh Jangal\u014dk",
        "Deh-e Jangalowk",
        "\u062f\u0647 \u062c\u0646\u06af\u0644\u0648\u06a9"
    ],
    "wof:name":"Deh-e Jangalok",
    "wof:placetype":"locality"
},
  "geometry": {"coordinates":[70.01295,36.08213],"type":"Point"}
}