{
  "type": "Feature",
  "properties": {
    "gn:admin1_code":"37",
    "gn:admin2_code":"3210",
    "gn:asciiname":"Pilan Khel",
    "gn:country_code":"AF",
    "gn:dem":1220,
    "gn:feature_class":"P",
    "gn:feature_code":"PPL",
    "gn:name":"Pil\u0101n Kh\u0113l",
    "gn:population":0,
    "gn:timezone":"Asia/Kabul",
    "iso:country":"AF",
    "name:und_x_variant":[
        "Pelankhel",
        "Pel\u0101nkh\u0113l",
        "P\u00eal\u0101n Kh\u0113l",
        "Pel\u0101n Kheyl",
        "Pil\u0101n Kh\u0113l",
        "\u067e\u0644\u0627\u0646 \u062e\u06d0\u0644"
    ],
    "wof:name":"Pilan Khel",
    "wof:placetype":"locality"
},
  "geometry": {"coordinates":[70.02972,33.53304],"type":"Point"}
}