{
  "type": "Feature",
  "properties": {
    "gn:admin1_code":"28",
    "gn:admin2_code":"2510.0",
    "gn:asciiname":"Darah",
    "gn:country_code":"AF",
    "gn:dem":1959,
    "gn:feature_class":"P",
    "gn:feature_code":"PPL",
    "gn:name":"Darah",
    "gn:population":0,
    "gn:timezone":"Asia/Kabul",
    "iso:country":"AF",
    "name:ceb_x_preferred":[
        "Darah"
    ],
    "name:swe_x_preferred":[
        "Darah"
    ],
    "name:und_x_variant":[
        "\u1e0e\u0101\u1e5fa",
        "\u062f\u0631\u0647",
        "D\u0101rah"
    ],
    "wof:name":"Darah",
    "wof:placetype":"locality"
},
  "geometry": {"coordinates":[67.31452,32.91674],"type":"Point"}
}