{
  "type": "Feature",
  "properties": {
    "gn:admin1_code":"11",
    "gn:admin2_code":"2014",
    "gn:asciiname":"Kudul",
    "gn:country_code":"AF",
    "gn:dem":1112,
    "gn:feature_class":"P",
    "gn:feature_code":"PPL",
    "gn:name":"Kud\u016bl",
    "gn:population":0,
    "gn:timezone":"Asia/Kabul",
    "iso:country":"AF",
    "name:und_x_variant":[
        "Kud\u016bl",
        "\u06a9\u062f\u0648\u0644",
        "Kod\u016bl"
    ],
    "wof:name":"Kudul",
    "wof:placetype":"locality"
},
  "geometry": {"coordinates":[61.93481,33.28039],"type":"Point"}
}