{
  "type": "Feature",
  "properties": {
    "gn:admin1_code":"09",
    "gn:admin2_code":"2707",
    "gn:asciiname":"Garm Ab-e Sufla",
    "gn:country_code":"AF",
    "gn:dem":2753,
    "gn:feature_class":"P",
    "gn:feature_code":"PPL",
    "gn:name":"Garm \u0100b-e Sufl\u00e1",
    "gn:population":0,
    "gn:timezone":"Asia/Kabul",
    "iso:country":"AF",
    "name:und_x_variant":[
        "Garm \u0100v",
        "Garm\u0101o",
        "Garmabi-Sufla",
        "Garm\u0101be Sufl\u0101",
        "Garm \u0100b-e Sofl\u00e1",
        "Garm \u0100b-e Sufl\u00e1",
        "\u06af\u0631\u0645 \u0622\u0628 \u0633\u0641\u0644\u0649"
    ],
    "wof:name":"Garm Ab-e Sufla",
    "wof:placetype":"locality"
},
  "geometry": {"coordinates":[65.94670000000001,34.45245],"type":"Point"}
}