{
  "type": "Feature",
  "properties": {
    "gn:admin1_code":"13",
    "gn:admin2_code":"111.0",
    "gn:asciiname":"Taghar-e 'Ulya",
    "gn:country_code":"AF",
    "gn:dem":2365,
    "gn:feature_class":"P",
    "gn:feature_code":"PPL",
    "gn:name":"Taghar-e \u2018Uly\u0101",
    "gn:population":0,
    "gn:timezone":"Asia/Kabul",
    "iso:country":"AF",
    "name:und_x_variant":[
        "Tagari-Ulia",
        "Tagha\u1e5fe \u2018Uly\u0101",
        "Taghar-e \u2018Oly\u0101",
        "Taghar-e \u2018Uly\u0101",
        "\u062a\u063a\u0631 \u0639\u0644\u06cc\u0627"
    ],
    "wof:name":"Taghar-e 'Ulya",
    "wof:placetype":"locality"
},
  "geometry": {"coordinates":[69.42653,34.3187],"type":"Point"}
}