{
  "type": "Feature",
  "properties": {
    "gn:admin1_code":"06",
    "gn:admin2_code":"2109",
    "gn:asciiname":"Deh-e Kohkan",
    "gn:country_code":"AF",
    "gn:dem":488,
    "gn:feature_class":"P",
    "gn:feature_code":"PPL",
    "gn:name":"Deh-e K\u014dhk\u0101n",
    "gn:population":0,
    "gn:timezone":"Asia/Kabul",
    "iso:country":"AF",
    "name:und_x_variant":[
        "\u1e0eehe Kohk\u0101n",
        "Deh Kohk\u0101n",
        "Deh-e K\u014dhk\u0101n",
        "\u062f\u0647 \u06a9\u0648\u0647\u06a9\u0627\u0646",
        "Deh-e K\u016bhkan"
    ],
    "wof:name":"Deh-e Kohkan",
    "wof:placetype":"locality"
},
  "geometry": {"coordinates":[61.50925,31.55219],"type":"Point"}
}