{
  "type": "Feature",
  "properties": {
    "gn:admin1_code":"01",
    "gn:admin2_code":"1112.0",
    "gn:asciiname":"Degah",
    "gn:country_code":"AF",
    "gn:dem":2810,
    "gn:feature_class":"P",
    "gn:feature_code":"PPL",
    "gn:name":"D\u0113gah",
    "gn:population":0,
    "gn:timezone":"Asia/Kabul",
    "iso:country":"AF",
    "name:und_x_variant":[
        "\u1e0e\u0113ga",
        "\u062f\u06d0\u06af\u0647",
        "\u1e0e\u0113gah",
        "D\u0113gah"
    ],
    "wof:name":"Degah",
    "wof:placetype":"locality"
},
  "geometry": {"coordinates":[70.51661,37.72401],"type":"Point"}
}