{
  "type": "Feature",
  "properties": {
    "gn:admin1_code":"41",
    "gn:admin2_code":"3406",
    "gn:asciiname":"Zartala",
    "gn:country_code":"AF",
    "gn:dem":2934,
    "gn:feature_class":"P",
    "gn:feature_code":"PPL",
    "gn:name":"Zartal\u0101",
    "gn:population":0,
    "gn:timezone":"Asia/Kabul",
    "iso:country":"AF",
    "name:und_x_variant":[
        "Za\u1e5ftala",
        "Zartal\u0101",
        "\u0632\u0631\u062a\u0644\u0627",
        "Zartalah"
    ],
    "wof:name":"Zartala",
    "wof:placetype":"locality"
},
  "geometry": {"coordinates":[65.92015000000001,33.79218],"type":"Point"}
}