{
  "type": "Feature",
  "properties": {
    "gn:admin1_code":"3",
    "gn:admin2_code":"1303.0",
    "gn:asciiname":"Baklaw",
    "gn:country_code":"AF",
    "gn:dem":874,
    "gn:feature_class":"P",
    "gn:feature_code":"PPL",
    "gn:name":"Bakl\u0101w",
    "gn:population":0,
    "gn:timezone":"Asia/Kabul",
    "iso:country":"AF",
    "name:und_x_variant":[
        "Bakl\u0101w",
        "\u0628\u06a9\u0644\u0627\u0648"
    ],
    "wof:name":"Baklaw",
    "wof:placetype":"locality"
},
  "geometry": {"coordinates":[68.47945,35.93389000000001],"type":"Point"}
}