{
  "type": "Feature",
  "properties": {
    "gn:admin1_code":"28",
    "gn:admin2_code":"2511.0",
    "gn:asciiname":"Qal'ah-ye Sa'dullah",
    "gn:country_code":"AF",
    "gn:dem":2006,
    "gn:feature_class":"P",
    "gn:feature_code":"PPL",
    "gn:name":"Qal\u2018ah-ye Sa\u2018dull\u0101h",
    "gn:population":0,
    "gn:timezone":"Asia/Kabul",
    "iso:country":"AF",
    "name:und_x_variant":[
        "Kalayi-Sadulla",
        "Qal\u2019a-i-Sa\u2019\u1e0full\u0101h",
        "Qal\u2018ah-ye Sa\u2018dull\u0101h",
        "Qal\u2018eh-ye Sa\u2018doll\u0101h",
        "\u0642\u0644\u0639\u0647 \u0633\u0639\u062f\u0627\u0644\u0644\u0640\u0647"
    ],
    "wof:name":"Qal'ah-ye Sa'dullah",
    "wof:placetype":"locality"
},
  "geometry": {"coordinates":[67.51971,31.99905],"type":"Point"}
}