{
  "type": "Feature",
  "properties": {
    "gn:admin1_code":"10",
    "gn:admin2_code":"2303.0",
    "gn:asciiname":"Shah Malay",
    "gn:country_code":"AF",
    "gn:dem":935,
    "gn:feature_class":"P",
    "gn:feature_code":"PPL",
    "gn:name":"Sh\u0101h Malay",
    "gn:population":0,
    "gn:timezone":"Asia/Kabul",
    "iso:country":"AF",
    "name:und_x_variant":[
        "\u0160\u0101h Malay",
        "Shakh-Malay",
        "Sh\u0101h Malay",
        "\u0634\u0627\u0647 \u0645\u0644\u06cc"
    ],
    "wof:name":"Shah Malay",
    "wof:placetype":"locality"
},
  "geometry": {"coordinates":[65.01947,32.27200999999999],"type":"Point"}
}