{
  "type": "Feature",
  "properties": {
    "gn:admin1_code":"09",
    "gn:admin2_code":"2707",
    "gn:asciiname":"Saqawah",
    "gn:country_code":"AF",
    "gn:dem":2947,
    "gn:feature_class":"P",
    "gn:feature_code":"PPL",
    "gn:name":"Saq\u0101wah",
    "gn:population":0,
    "gn:timezone":"Asia/Kabul",
    "iso:country":"AF",
    "name:und_x_variant":[
        "Sakava",
        "Saq\u0101wa",
        "Saq\u0101wah",
        "\u0633\u0642\u0627\u0648\u0647"
    ],
    "wof:name":"Saqawah",
    "wof:placetype":"locality"
},
  "geometry": {"coordinates":[66.30019,34.47058],"type":"Point"}
}