{
  "type": "Feature",
  "properties": {
    "gn:admin1_code":"33",
    "gn:admin2_code":"3105",
    "gn:asciiname":"Siltar",
    "gn:country_code":"AF",
    "gn:dem":909,
    "gn:feature_class":"P",
    "gn:feature_code":"PPL",
    "gn:name":"Siltar",
    "gn:population":0,
    "gn:timezone":"Asia/Kabul",
    "iso:country":"AF",
    "name:und_x_variant":[
        "\u0633\u0644\u062a\u0631",
        "Seltar"
    ],
    "wof:name":"Siltar",
    "wof:placetype":"locality"
},
  "geometry": {"coordinates":[66.21892,36.0578],"type":"Point"}
}