{
  "type": "Feature",
  "properties": {
    "gn:admin1_code":"9",
    "gn:admin2_code":"2710.0",
    "gn:asciiname":"Chihilgazi",
    "gn:country_code":"AF",
    "gn:dem":2654,
    "gn:feature_class":"P",
    "gn:feature_code":"PPL",
    "gn:name":"Chihilgaz\u012b",
    "gn:population":0,
    "gn:timezone":"Asia/Kabul",
    "iso:country":"AF",
    "name:rus_x_preferred":[
        "Chikhil\u2019gazi"
    ],
    "name:und_x_variant":[
        "\u010cehelgazi",
        "Chehelgaz\u012b",
        "Chihilgaz\u012b",
        "\u0686\u0647\u0644\u06af\u0632\u06cc"
    ],
    "wof:name":"Chihilgazi",
    "wof:placetype":"locality"
},
  "geometry": {"coordinates":[64.85484,34.00385],"type":"Point"}
}