{
  "type": "Feature",
  "properties": {
    "gn:admin1_code":"23",
    "gn:admin2_code":"2413",
    "gn:asciiname":"Zhawirkan",
    "gn:country_code":"AF",
    "gn:dem":1770,
    "gn:feature_class":"P",
    "gn:feature_code":"PPL",
    "gn:name":"Zhawirk\u0101n",
    "gn:population":0,
    "gn:timezone":"Asia/Kabul",
    "iso:country":"AF",
    "name:fas_x_preferred":[
        "\u0632\u0648\u0631\u0643\u0627\u0646"
    ],
    "name:pus_x_preferred":[
        "\u0698\u0648\u0631\u06a9\u0627\u0646"
    ],
    "name:und_x_variant":[
        "Zhavirkan",
        "Zhawirk\u0101n",
        "Zawe\u1e5fk\u0101n"
    ],
    "wof:name":"Zhawirkan",
    "wof:placetype":"locality"
},
  "geometry": {"coordinates":[67.08356999999999,31.55474],"type":"Point"}
}