{
  "type": "Feature",
  "properties": {
    "gn:admin1_code":"23",
    "gn:admin2_code":"2401",
    "gn:asciiname":"Rurabat",
    "gn:country_code":"AF",
    "gn:dem":976,
    "gn:feature_class":"P",
    "gn:feature_code":"PPL",
    "gn:name":"Rurabat",
    "gn:population":0,
    "gn:timezone":"Asia/Kabul",
    "iso:country":"AF",
    "name:fas_x_preferred":[
        "\u0631\u0648\u062d \u0622\u0628\u0627\u062f"
    ],
    "name:und_x_variant":[
        "Ruhab\u0101b\u0101d",
        "Ruhb\u0101b\u0101d",
        "Rurabat",
        "\u1e5e\u016b\u1e5fab\u0101t",
        "R\u016b\u1e29\u0101b\u0101d",
        "R\u016brab\u0101\u0163",
        "\u0631\u0648\u0631\u0628\u0627\u0637",
        "\u0631\u0648\u062d \u0622\u0628\u0627\u062f"
    ],
    "wof:name":"Rurabat",
    "wof:placetype":"locality"
},
  "geometry": {"coordinates":[65.69436,31.46216],"type":"Point"}
}