{
  "type": "Feature",
  "properties": {
    "gn:admin1_code":"36",
    "gn:admin2_code":"711.0",
    "gn:asciiname":"Bar Bilawut",
    "gn:country_code":"AF",
    "gn:dem":2509,
    "gn:feature_class":"P",
    "gn:feature_code":"PPL",
    "gn:name":"Bar Bilaw\u016bt",
    "gn:population":0,
    "gn:timezone":"Asia/Kabul",
    "iso:country":"AF",
    "name:und_x_variant":[
        "P\u012br\u0101no Kili",
        "Bar-Bilavut",
        "Bar B\u00ealaw\u016bt",
        "Ba\u1e5f Belaw\u016bt",
        "Bar Bilaw\u016bt",
        "\u0628\u0631\u0628\u0644\u0648\u0648\u062a",
        "Bar B\u012blahw\u016bt",
        "\u0628\u0631\u0628\u06cc\u0644\u0647 \u0648\u0648\u062a"
    ],
    "wof:name":"Bar Bilawut",
    "wof:placetype":"locality"
},
  "geometry": {"coordinates":[69.80595,33.99467],"type":"Point"}
}