{
  "type": "Feature",
  "properties": {
    "gn:admin1_code":"05",
    "gn:admin2_code":"2804",
    "gn:asciiname":"Wulangak",
    "gn:country_code":"AF",
    "gn:dem":3212,
    "gn:feature_class":"P",
    "gn:feature_code":"PPL",
    "gn:name":"Wulangak",
    "gn:population":0,
    "gn:timezone":"Asia/Kabul",
    "iso:country":"AF",
    "name:rus_x_preferred":[
        "\u0412\u0443\u043b\u0430\u043d\u0433\u0430\u043a"
    ],
    "name:und_x_variant":[
        "Vulangak",
        "\u014clangak",
        "Wolangak",
        "Wulangak",
        "\u0648\u0644\u0646\u06af\u06a9"
    ],
    "wof:name":"Wulangak",
    "wof:placetype":"locality"
},
  "geometry": {"coordinates":[67.06549,34.6384],"type":"Point"}
}