{
  "type": "Feature",
  "properties": {
    "gn:admin1_code":"7",
    "gn:admin2_code":"1808.0",
    "gn:asciiname":"Jalayir",
    "gn:country_code":"AF",
    "gn:dem":426,
    "gn:feature_class":"P",
    "gn:feature_code":"PPL",
    "gn:name":"Jalayir",
    "gn:population":0,
    "gn:timezone":"Asia/Kabul",
    "iso:country":"AF",
    "name:und_x_variant":[
        "\u062c\u0644\u06cc\u0631",
        "Jalaier (2)"
    ],
    "wof:name":"Jalayir",
    "wof:placetype":"locality"
},
  "geometry": {"coordinates":[64.76783,36.36327],"type":"Point"}
}