{
  "type": "Feature",
  "properties": {
    "gn:admin1_code":"18",
    "gn:admin2_code":"810.0",
    "gn:asciiname":"Zhay Kelay",
    "gn:country_code":"AF",
    "gn:dem":1612,
    "gn:feature_class":"P",
    "gn:feature_code":"PPL",
    "gn:name":"Zhay K\u00ealay",
    "gn:population":0,
    "gn:timezone":"Asia/Kabul",
    "iso:country":"AF",
    "name:fas_x_preferred":[
        "\u0642\u0631\u064a\u06c0 \u0698\u06cc"
    ],
    "name:und_x_variant":[
        "\u017day Kalay",
        "Zaykalay",
        "Zhay Khalay",
        "Zhay K\u00ealay",
        "\u0698\u06cc \u06a9\u0644\u06cc"
    ],
    "wof:name":"Zhay Kelay",
    "wof:placetype":"locality"
},
  "geometry": {"coordinates":[70.71030999999998,34.0356],"type":"Point"}
}