{
  "type": "Feature",
  "properties": {
    "gn:admin1_code":"23",
    "gn:admin2_code":"2410",
    "gn:asciiname":"Shaykhan",
    "gn:country_code":"AF",
    "gn:dem":1010,
    "gn:feature_class":"P",
    "gn:feature_code":"PPL",
    "gn:name":"Shaykh\u0101n",
    "gn:population":0,
    "gn:timezone":"Asia/Kabul",
    "iso:country":"AF",
    "name:und_x_variant":[
        "S\u0304ekh\u0101n",
        "Sh\u0113kh\u0101n",
        "Sheykh\u0101n",
        "Shaykh Kh\u0101n",
        "\u0634\u06cc\u062e \u062e\u0627\u0646",
        "Shaykh\u0101n",
        "\u0634\u06cc\u062e\u0627\u0646"
    ],
    "wof:name":"Shaykhan",
    "wof:placetype":"locality"
},
  "geometry": {"coordinates":[66.15142,30.14603],"type":"Point"}
}