{
  "type": "Feature",
  "properties": {
    "gn:admin1_code":"2",
    "gn:admin2_code":"1904.0",
    "gn:asciiname":"Buzghalak",
    "gn:country_code":"AF",
    "gn:dem":1628,
    "gn:feature_class":"P",
    "gn:feature_code":"PPL",
    "gn:name":"Buzgh\u0101lak",
    "gn:population":0,
    "gn:timezone":"Asia/Kabul",
    "iso:country":"AF",
    "name:und_x_variant":[
        "Buzgh\u0101lak",
        "\u0628\u0632\u063a\u0627\u0644\u06a9"
    ],
    "wof:name":"Buzghalak",
    "wof:placetype":"locality"
},
  "geometry": {"coordinates":[64.03659,34.90409],"type":"Point"}
}