{
  "type": "Feature",
  "properties": {
    "gn:admin1_code":"29",
    "gn:admin2_code":"2905",
    "gn:asciiname":"Jawul Khel",
    "gn:country_code":"AF",
    "gn:dem":1959,
    "gn:feature_class":"P",
    "gn:feature_code":"PPL",
    "gn:name":"J\u0101wul Kh\u0113l",
    "gn:population":0,
    "gn:timezone":"Asia/Kabul",
    "iso:country":"AF",
    "name:rus_x_preferred":[
        "Dzhavul\u2019kheyl\u2019"
    ],
    "name:und_x_variant":[
        "J\u0101wol Kh\u0113l",
        "J\u0101wul Kh\u0113l",
        "J\u0101wol Kheyl",
        "\u062c\u0627\u0648\u0644 \u062e\u06d0\u0644"
    ],
    "wof:name":"Jawul Khel",
    "wof:placetype":"locality"
},
  "geometry": {"coordinates":[68.83166999999999,31.98806],"type":"Point"}
}