{
  "type": "Feature",
  "properties": {
    "gn:admin1_code":"18",
    "gn:admin2_code":"808",
    "gn:asciiname":"Papin",
    "gn:country_code":"AF",
    "gn:dem":1346,
    "gn:feature_class":"P",
    "gn:feature_code":"PPL",
    "gn:name":"P\u0101p\u012bn",
    "gn:population":0,
    "gn:timezone":"Asia/Kabul",
    "iso:country":"AF",
    "name:fas_x_preferred":[
        "\u067e\u0627\u067e\u064a\u0646"
    ],
    "name:und_x_variant":[
        "P\u0101p\u012bn",
        "\u067e\u0627\u067e\u06cc\u0646"
    ],
    "wof:name":"Papin",
    "wof:placetype":"locality"
},
  "geometry": {"coordinates":[70.4062,34.11202],"type":"Point"}
}