{
  "type": "Feature",
  "properties": {
    "gn:admin1_code":"29",
    "gn:admin2_code":"2919",
    "gn:asciiname":"Mist",
    "gn:country_code":"AF",
    "gn:dem":2187,
    "gn:feature_class":"P",
    "gn:feature_code":"PPL",
    "gn:name":"Mist",
    "gn:population":0,
    "gn:timezone":"Asia/Kabul",
    "iso:country":"AF",
    "name:afr_x_preferred":[
        "Mis"
    ],
    "name:ara_x_preferred":[
        "\u0633\u062f\u064a\u0645"
    ],
    "name:bcl_x_preferred":[
        "Ambon"
    ],
    "name:bih_x_preferred":[
        "\u0915\u0941\u0939\u0947\u0938\u093e"
    ],
    "name:cat_x_preferred":[
        "Boirina"
    ],
    "name:dan_x_preferred":[
        "Dis"
    ],
    "name:ell_x_preferred":[
        "\u03a5\u03b3\u03c1\u03ac \u03b1\u03c7\u03bb\u03cd\u03c2"
    ],
    "name:epo_x_preferred":[
        "Brumo"
    ],
    "name:fas_x_preferred":[
        "\u062a\u0646\u06a9\u200c\u0645\u0647"
    ],
    "name:fin_x_preferred":[
        "Utu"
    ],
    "name:fra_x_preferred":[
        "Brume"
    ],
    "name:fry_x_preferred":[
        "Dize"
    ],
    "name:hat_x_preferred":[
        "Labrim"
    ],
    "name:hin_x_preferred":[
        "\u0915\u0941\u0939\u093e\u0938\u093e"
    ],
    "name:isl_x_preferred":[
        "Mistur"
    ],
    "name:ita_x_preferred":[
        "Foschia"
    ],
    "name:kaz_x_preferred":[
        "\u041c\u04b1\u043d\u0430\u0440"
    ],
    "name:lav_x_preferred":[
        "D\u016bmaka"
    ],
    "name:lim_x_preferred":[
        "Nevel"
    ],
    "name:lit_x_preferred":[
        "Migla"
    ],
    "name:mal_x_preferred":[
        "\u0d15\u0d4b\u0d1f\u0d2e\u0d1e\u0d4d\u0d1e\u0d4d"
    ],
    "name:msa_x_preferred":[
        "Kabus"
    ],
    "name:nep_x_preferred":[
        "\u0939\u0941\u0938\u094d\u0938\u0941"
    ],
    "name:nld_x_preferred":[
        "Nevel"
    ],
    "name:nno_x_preferred":[
        "Dis"
    ],
    "name:nor_x_preferred":[
        "Dis"
    ],
    "name:pan_x_preferred":[
        "\u0a27\u0a41\u0a70\u0a26"
    ],
    "name:pol_x_preferred":[
        "Zamglenie"
    ],
    "name:por_x_preferred":[
        "Neblina"
    ],
    "name:rus_x_preferred":[
        "\u0414\u044b\u043c\u043a\u0430"
    ],
    "name:sah_x_preferred":[
        "\u041a\u04af\u0434\u044d\u043d"
    ],
    "name:sna_x_preferred":[
        "Mhute"
    ],
    "name:spa_x_preferred":[
        "Neblina"
    ],
    "name:sun_x_preferred":[
        "Halimun"
    ],
    "name:swe_x_preferred":[
        "Dis"
    ],
    "name:tur_x_preferred":[
        "Pus"
    ],
    "name:ukr_x_preferred":[
        "\u0421\u0435\u0440\u043f\u0430\u043d\u043e\u043a"
    ],
    "name:und_x_variant":[
        "\u0645\u0633\u062a",
        "Mest",
        "Mist"
    ],
    "wof:name":"Mist",
    "wof:placetype":"locality"
},
  "geometry": {"coordinates":[68.55943000000001,32.96386],"type":"Point"}
}