{
  "type": "Feature",
  "properties": {
    "gn:admin1_code":"29",
    "gn:admin2_code":"2919",
    "gn:asciiname":"Mist",
    "gn:country_code":"AF",
    "gn:dem":2187,
    "gn:feature_class":"P",
    "gn:feature_code":"PPL",
    "gn:name":"Mist",
    "gn:population":0,
    "gn:timezone":"Asia/Kabul",
    "iso:country":"AF",
    "name:und_x_variant":[
        "\u0645\u0633\u062a",
        "Mest",
        "Mist"
    ],
    "wof:name":"Mist",
    "wof:placetype":"locality"
},
  "geometry": {"coordinates":[68.55943000000001,32.96386],"type":"Point"}
}