{
  "type": "Feature",
  "properties": {
    "gn:admin1_code":"6",
    "gn:admin2_code":"2108.0",
    "gn:asciiname":"Galah Gumbaz",
    "gn:country_code":"AF",
    "gn:dem":650,
    "gn:feature_class":"P",
    "gn:feature_code":"PPL",
    "gn:name":"Galah Gumbaz",
    "gn:population":0,
    "gn:timezone":"Asia/Kabul",
    "iso:country":"AF",
    "name:und_x_variant":[
        "Gala Gumbaz",
        "Galah Gumbaz",
        "\u06af\u0644\u0647 \u06af\u0645\u0628\u0632",
        "Galeh Gombad"
    ],
    "wof:name":"Galah Gumbaz",
    "wof:placetype":"locality"
},
  "geometry": {"coordinates":[61.55261,32.4413],"type":"Point"}
}