{
  "type": "Feature",
  "properties": {
    "gn:admin1_code":"30",
    "gn:admin2_code":"1607.0",
    "gn:asciiname":"Akhir Rangah",
    "gn:country_code":"AF",
    "gn:dem":318,
    "gn:feature_class":"P",
    "gn:feature_code":"PPL",
    "gn:name":"Akh\u012br Rangah",
    "gn:population":0,
    "gn:timezone":"Asia/Kabul",
    "iso:country":"AF",
    "name:rus_x_preferred":[
        "\u0410\u0445\u0438\u0440\u0440\u0430\u043d\u0430\u0433\u0430"
    ],
    "name:und_x_variant":[
        "Akhirranaga",
        "\u0627\u062e\u064a\u0631 \u0631\u0646\u06af\u0647",
        "Akh\u012br Rangah"
    ],
    "wof:name":"Akhir Rangah",
    "wof:placetype":"locality"
},
  "geometry": {"coordinates":[66.66048000000001,36.87214],"type":"Point"}
}