{
  "type": "Feature",
  "properties": {
    "gn:admin1_code":"09",
    "gn:admin2_code":"2706",
    "gn:asciiname":"Murchah",
    "gn:country_code":"AF",
    "gn:dem":2420,
    "gn:feature_class":"P",
    "gn:feature_code":"PPL",
    "gn:name":"Murchah",
    "gn:population":0,
    "gn:timezone":"Asia/Kabul",
    "iso:country":"AF",
    "name:fas_x_preferred":[
        "\u0645\u0648\u0631\u0686\u0647"
    ],
    "name:rus_x_preferred":[
        "\u041c\u0443\u0440\u0447\u0430"
    ],
    "name:und_x_variant":[
        "Mur\u010da",
        "Murcha",
        "Murchah",
        "\u0645\u0631\u0686\u0647",
        "M\u016brcheh"
    ],
    "wof:name":"Murchah",
    "wof:placetype":"locality"
},
  "geometry": {"coordinates":[65.15560000000001,33.38624],"type":"Point"}
}