{
  "type": "Feature",
  "properties": {
    "gn:admin1_code":"32",
    "gn:admin2_code":"1501.0",
    "gn:asciiname":"Mangtash",
    "gn:country_code":"AF",
    "gn:dem":916,
    "gn:feature_class":"P",
    "gn:feature_code":"PPL",
    "gn:name":"Mangt\u0101sh",
    "gn:population":0,
    "gn:timezone":"Asia/Kabul",
    "iso:country":"AF",
    "name:und_x_variant":[
        "Mangt\u0101sh",
        "\u0645\u0646\u06af\u062a\u0627\u0634",
        "Mangtash"
    ],
    "wof:name":"Mangtash",
    "wof:placetype":"locality"
},
  "geometry": {"coordinates":[67.96522,36.30372],"type":"Point"}
}