{
  "type": "Feature",
  "properties": {
    "gn:admin1_code":"8",
    "gn:admin2_code":"604.0",
    "gn:asciiname":"Qishlaqha",
    "gn:country_code":"AF",
    "gn:dem":2772,
    "gn:feature_class":"P",
    "gn:feature_code":"PPL",
    "gn:name":"Qishl\u0101qh\u0101",
    "gn:population":0,
    "gn:timezone":"Asia/Kabul",
    "iso:country":"AF",
    "name:und_x_variant":[
        "Qe\u0161l\u0101qh\u0101",
        "Qeshl\u0101qh\u0101",
        "Qishl\u0101qh\u0101",
        "\u0642\u0634\u0644\u0627\u0642\u0647\u0627"
    ],
    "wof:name":"Qishlaqha",
    "wof:placetype":"locality"
},
  "geometry": {"coordinates":[68.01949999999999,34.09637],"type":"Point"}
}