{
  "type": "Feature",
  "properties": {
    "gn:admin1_code":"08",
    "gn:admin2_code":"618",
    "gn:asciiname":"Sarwan",
    "gn:country_code":"AF",
    "gn:dem":2359,
    "gn:feature_class":"P",
    "gn:feature_code":"PPL",
    "gn:name":"S\u0101rw\u0101n",
    "gn:population":0,
    "gn:timezone":"Asia/Kabul",
    "iso:country":"AF",
    "name:fas_x_preferred":[
        "\u0633\u0627\u0631\u0648\u0627\u0646"
    ],
    "name:und_x_variant":[
        "Sarvan",
        "S\u0101\u1e5fw\u0101n",
        "S\u0101rw\u0101n",
        "S\u0101rv\u0101n"
    ],
    "wof:name":"Sarwan",
    "wof:placetype":"locality"
},
  "geometry": {"coordinates":[68.22269,33.45865999999999],"type":"Point"}
}