{
  "type": "Feature",
  "properties": {
    "gn:admin1_code":"42",
    "gn:admin2_code":"3301.0",
    "gn:asciiname":"Gowinj",
    "gn:country_code":"AF",
    "gn:dem":2668,
    "gn:feature_class":"P",
    "gn:feature_code":"PPL",
    "gn:name":"Gowinj",
    "gn:population":0,
    "gn:timezone":"Asia/Kabul",
    "iso:country":"AF",
    "name:und_x_variant":[
        "Gavindzh",
        "Gawenj",
        "Gowinj",
        "\u06af\u0648\u0646\u062c"
    ],
    "wof:name":"Gowinj",
    "wof:placetype":"locality"
},
  "geometry": {"coordinates":[69.47458,35.36881],"type":"Point"}
}