{
  "type": "Feature",
  "properties": {
    "gn:admin1_code":"8",
    "gn:admin2_code":"604.0",
    "gn:asciiname":"Gardan-e Kamarak",
    "gn:country_code":"AF",
    "gn:dem":3301,
    "gn:feature_class":"P",
    "gn:feature_code":"PPL",
    "gn:name":"Gardan-e Kamarak",
    "gn:population":0,
    "gn:timezone":"Asia/Kabul",
    "iso:country":"AF",
    "name:und_x_variant":[
        "Gardani-Kamarak",
        "Gardan-e Kamarak",
        "\u06af\u0631\u062f\u0646 \u06a9\u0645\u0631\u06a9"
    ],
    "wof:name":"Gardan-e Kamarak",
    "wof:placetype":"locality"
},
  "geometry": {"coordinates":[67.54613000000001,34.15234],"type":"Point"}
}