{
  "type": "Feature",
  "properties": {
    "gn:admin1_code":"10",
    "gn:admin2_code":"2311",
    "gn:asciiname":"Haji Ni'matullah Kelay",
    "gn:country_code":"AF",
    "gn:dem":707,
    "gn:feature_class":"P",
    "gn:feature_code":"PPL",
    "gn:name":"\u1e28\u0101j\u012b Ni\u2018matull\u0101h K\u00ealay",
    "gn:population":0,
    "gn:timezone":"Asia/Kabul",
    "iso:country":"AF",
    "name:und_x_variant":[
        "H\u0331aji Ne\u2018matull\u0101h Kalay",
        "\u1e28\u0101j\u012b Ni\u2018matull\u0101h K\u00ealay",
        "\u062d\u0627\u062c\u06cc \u0646\u0639\u0645\u062a\u0627\u0644\u0644\u0647 \u06a9\u0644\u06cc",
        "\u1e28\u0101jj\u012b Ne\u2018matoll\u0101h Kalay"
    ],
    "wof:name":"Haji Ni'matullah Kelay",
    "wof:placetype":"locality"
},
  "geometry": {"coordinates":[64.16576999999999,31.07978],"type":"Point"}
}