{
  "type": "Feature",
  "properties": {
    "gn:admin1_code":"29",
    "gn:admin2_code":"2906.0",
    "gn:asciiname":"Baghgi",
    "gn:country_code":"AF",
    "gn:dem":2283,
    "gn:feature_class":"P",
    "gn:feature_code":"PPL",
    "gn:name":"B\u0101ghg\u012b",
    "gn:population":0,
    "gn:timezone":"Asia/Kabul",
    "iso:country":"AF",
    "name:fas_x_preferred":[
        "B\u0101ghg\u012b"
    ],
    "name:fas_x_variant":[
        "\u0628\u0627\u063a\u06af\u06cc"
    ],
    "name:und_x_variant":[
        "\u0628\u0627\u063a\u06af\u06cc"
    ],
    "wof:name":"Baghgi",
    "wof:placetype":"locality"
},
  "geometry": {"coordinates":[68.76375,32.59473],"type":"Point"}
}