{
  "type": "Feature",
  "properties": {
    "gn:admin1_code":"27",
    "gn:admin2_code":"404.0",
    "gn:asciiname":"Obeh Chorah",
    "gn:country_code":"AF",
    "gn:dem":3222,
    "gn:feature_class":"P",
    "gn:feature_code":"PPL",
    "gn:name":"\u014cb\u00eah Ch\u014drah",
    "gn:population":0,
    "gn:timezone":"Asia/Kabul",
    "iso:country":"AF",
    "name:und_x_variant":[
        "Obeh\u010dora",
        "Obachora",
        "\u014cbah Ch\u014drah",
        "Obehchowreh",
        "\u014cb\u00eah Ch\u014drah",
        "\u0627\u0648\u0628\u0647 \u0686\u0648\u0631\u0647"
    ],
    "wof:name":"Obeh Chorah",
    "wof:placetype":"locality"
},
  "geometry": {"coordinates":[67.90785,34.53432],"type":"Point"}
}