{
  "type": "Feature",
  "properties": {
    "gn:admin1_code":"09",
    "gn:admin2_code":"2703",
    "gn:asciiname":"Kuhnah",
    "gn:country_code":"AF",
    "gn:dem":2493,
    "gn:feature_class":"P",
    "gn:feature_code":"PPL",
    "gn:name":"Kuhnah",
    "gn:population":0,
    "gn:timezone":"Asia/Kabul",
    "iso:country":"AF",
    "name:und_x_variant":[
        "Kuhna",
        "Kuhnah",
        "\u06a9\u0647\u0646\u0647",
        "Kohneh"
    ],
    "wof:name":"Kuhnah",
    "wof:placetype":"locality"
},
  "geometry": {"coordinates":[63.95861,34.02563],"type":"Point"}
}