{
  "type": "Feature",
  "properties": {
    "gn:admin1_code":"07",
    "gn:admin2_code":"1808.0",
    "gn:asciiname":"Gaw Kush",
    "gn:country_code":"AF",
    "gn:dem":892,
    "gn:feature_class":"P",
    "gn:feature_code":"PPL",
    "gn:name":"G\u0101w Kush",
    "gn:population":0,
    "gn:timezone":"Asia/Kabul",
    "iso:country":"AF",
    "name:und_x_variant":[
        "G\u0101w Kush",
        "G\u0101v Kush",
        "\u06af\u0627\u0648 \u06a9\u0634"
    ],
    "wof:name":"Gaw Kush",
    "wof:placetype":"locality"
},
  "geometry": {"coordinates":[65.12090000000001,36.18968],"type":"Point"}
}