{
  "type": "Feature",
  "properties": {
    "gn:admin1_code":"6",
    "gn:admin2_code":"2103.0",
    "gn:asciiname":"Saydal",
    "gn:country_code":"AF",
    "gn:dem":1224,
    "gn:feature_class":"P",
    "gn:feature_code":"PPL",
    "gn:name":"Sayd\u0101l",
    "gn:population":0,
    "gn:timezone":"Asia/Kabul",
    "iso:country":"AF",
    "wof:name":"Saydal",
    "wof:placetype":"locality"
},
  "geometry": {"coordinates":[63.57666999999999,32.51389],"type":"Point"}
}