{
  "type": "Feature",
  "properties": {
    "gn:admin1_code":"40",
    "gn:admin2_code":"307.0",
    "gn:asciiname":"Qarah-ye Fazil",
    "gn:country_code":"AF",
    "gn:dem":2301,
    "gn:feature_class":"P",
    "gn:feature_code":"PPL",
    "gn:name":"Qarah-ye F\u0101\u1e95il",
    "gn:population":0,
    "gn:timezone":"Asia/Kabul",
    "iso:country":"AF",
    "name:rus_x_preferred":[
        "Kar\u2019yafazil\u2019"
    ],
    "name:und_x_variant":[
        "Qarya-i-F\u0101dzel",
        "Qa\u1e5fya F\u0101\u1e0f\u1e95el",
        "Qaryeh-ye-F\u0101\u1e95el",
        "Qarah-ye F\u0101\u1e95el",
        "Qarah-ye F\u0101\u1e95il",
        "\u0642\u0631\u0647 \u0641\u0627\u0636\u0644"
    ],
    "wof:name":"Qarah-ye Fazil",
    "wof:placetype":"locality"
},
  "geometry": {"coordinates":[68.66034999999999,34.79552],"type":"Point"}
}