{
  "type": "Feature",
  "properties": {
    "gn:admin1_code":"34",
    "gn:admin2_code":"1006",
    "gn:asciiname":"Sidmashal",
    "gn:country_code":"AF",
    "gn:dem":1992,
    "gn:feature_class":"P",
    "gn:feature_code":"PPL",
    "gn:name":"Sidmashal",
    "gn:population":0,
    "gn:timezone":"Asia/Kabul",
    "iso:country":"AF",
    "name:fas_x_preferred":[
        "\u0633\u062f \u0645\u0634\u0644"
    ],
    "name:rus_x_preferred":[
        "Sidmashal\u2019"
    ],
    "name:und_x_variant":[
        "Sedma\u0161al",
        "Sedmashal",
        "Sidmashal",
        "Sidmashal\u2019"
    ],
    "wof:name":"Sidmashal",
    "wof:placetype":"locality"
},
  "geometry": {"coordinates":[71.3413,35.30845],"type":"Point"}
}