{
  "type": "Feature",
  "properties": {
    "gn:admin1_code":"11",
    "gn:admin2_code":"2012",
    "gn:asciiname":"Yakhak",
    "gn:country_code":"AF",
    "gn:dem":2580,
    "gn:feature_class":"P",
    "gn:feature_code":"PPL",
    "gn:name":"Yakhak",
    "gn:population":0,
    "gn:timezone":"Asia/Kabul",
    "iso:country":"AF",
    "name:ceb_x_preferred":[
        "Yakhak"
    ],
    "name:swe_x_preferred":[
        "Yakhak"
    ],
    "wof:name":"Yakhak",
    "wof:placetype":"locality"
},
  "geometry": {"coordinates":[63.25,34.61667],"type":"Point"}
}