{
  "type": "Feature",
  "properties": {
    "gn:admin1_code":"36",
    "gn:admin2_code":"706",
    "gn:asciiname":"Lmar Khel",
    "gn:country_code":"AF",
    "gn:dem":1922,
    "gn:feature_class":"P",
    "gn:feature_code":"PPL",
    "gn:name":"Lmar Kh\u0113l",
    "gn:population":0,
    "gn:timezone":"Asia/Kabul",
    "iso:country":"AF",
    "name:rus_x_preferred":[
        "L\u2019markheyl\u2019"
    ],
    "name:und_x_variant":[
        "Lma\u1e5fkh\u0113l",
        "Lmar Kh\u0113l",
        "Lmar Kheyl",
        "\u0644\u0645\u0631 \u062e\u064a\u0644"
    ],
    "wof:name":"Lmar Khel",
    "wof:placetype":"locality"
},
  "geometry": {"coordinates":[69.74694000000001,33.69110999999999],"type":"Point"}
}