{
  "type": "Feature",
  "properties": {
    "gn:admin1_code":"10",
    "gn:admin2_code":"2302.0",
    "gn:asciiname":"Sangchal",
    "gn:country_code":"AF",
    "gn:dem":832,
    "gn:feature_class":"P",
    "gn:feature_code":"PPL",
    "gn:name":"Sangch\u0101l",
    "gn:population":0,
    "gn:timezone":"Asia/Kabul",
    "iso:country":"AF",
    "name:rus_x_preferred":[
        "Sangchal\u2019"
    ],
    "name:und_x_variant":[
        "Sang\u010d\u0101l",
        "Sangch\u0101l",
        "\u0633\u0646\u06af\u0686\u0627\u0644"
    ],
    "wof:name":"Sangchal",
    "wof:placetype":"locality"
},
  "geometry": {"coordinates":[64.63226999999999,31.8406],"type":"Point"}
}