{
  "type": "Feature",
  "properties": {
    "gn:admin1_code":"19",
    "gn:admin2_code":"2202",
    "gn:asciiname":"Deh-e Now",
    "gn:cc2":"AF",
    "gn:country_code":"AF",
    "gn:dem":476,
    "gn:feature_class":"P",
    "gn:feature_code":"PPL",
    "gn:name":"Deh-e Now",
    "gn:population":0,
    "gn:timezone":"Asia/Kabul",
    "iso:country":"AF",
    "name:und_x_variant":[
        "\u1e0eehe Naw",
        "Deh-e Now"
    ],
    "wof:name":"Deh-e Now",
    "wof:placetype":"locality"
},
  "geometry": {"coordinates":[61.79278000000001,31.31361],"type":"Point"}
}