{
  "type": "Feature",
  "properties": {
    "gn:country":"AF",
    "gn:fcode":"MT",
    "gn:population":1563,
    "iso:country":"AF",
    "name:fas_x_preferred":[
        "\u0644\u0644\u0628\u0644\u0627\u0644"
    ],
    "name:rus_x_preferred":[
        "Gora Lal\u2019bilal\u2019"
    ],
    "name:und_x_variant":[
        "L\u0101l Bil\u0101l"
    ],
    "qs:name":"Lal Bil\u0101l",
    "qs:photos_9r":0,
    "qs:photos_sr":0,
    "qs:pop_sr":"3",
    "wof:name":"Lal Bil\u0101l",
    "wof:placetype":"locality",
    "wof:population":1563
},
  "geometry": {"coordinates":[65.55716,31.79336],"type":"Point"}
}