{
  "type": "Feature",
  "properties": {
    "gn:admin1_code":"9",
    "gn:admin2_code":"2710.0",
    "gn:asciiname":"Dahan-e Zanu",
    "gn:country_code":"AF",
    "gn:dem":2371,
    "gn:feature_class":"P",
    "gn:feature_code":"PPL",
    "gn:name":"Dah\u0101n-e Z\u0101n\u016b",
    "gn:population":0,
    "gn:timezone":"Asia/Kabul",
    "iso:country":"AF",
    "name:und_x_variant":[
        "\u1e0eehane Z\u0101nu",
        "Dakhani-Zanu",
        "Dah\u0101n-e Z\u0101n\u016b",
        "\u062f\u0647\u0627\u0646 \u0632\u0627\u0646\u0648",
        "Dahan-e Z\u0101n\u016b"
    ],
    "wof:name":"Dahan-e Zanu",
    "wof:placetype":"locality"
},
  "geometry": {"coordinates":[64.69518000000001,33.89972],"type":"Point"}
}