{
  "type": "Feature",
  "properties": {
    "gn:admin1_code":"05",
    "gn:admin2_code":"2806",
    "gn:asciiname":"Zard Qol",
    "gn:country_code":"AF",
    "gn:dem":2806,
    "gn:feature_class":"P",
    "gn:feature_code":"PPL",
    "gn:name":"Zard Q\u014dl",
    "gn:population":0,
    "gn:timezone":"Asia/Kabul",
    "iso:country":"AF",
    "name:rus_x_preferred":[
        "Zardkul\u2019"
    ],
    "name:und_x_variant":[
        "Za\u1e5f\u1e0fq\u014dl",
        "Zard Q\u014dlak",
        "Zardqowl",
        "Zard Q\u014dl",
        "\u0632\u0631\u062f \u0642\u0648\u0644"
    ],
    "wof:name":"Zard Qol",
    "wof:placetype":"locality"
},
  "geometry": {"coordinates":[66.95142,34.03169],"type":"Point"}
}