{
  "type": "Feature",
  "properties": {
    "gn:admin1_code":"19",
    "gn:admin2_code":"2202",
    "gn:asciiname":"Sher Malang",
    "gn:country_code":"AF",
    "gn:dem":482,
    "gn:feature_class":"P",
    "gn:feature_code":"PPL",
    "gn:name":"Sh\u0113r Malang",
    "gn:population":0,
    "gn:timezone":"Asia/Kabul",
    "iso:country":"AF",
    "name:fas_x_preferred":[
        "\u0634\u06cc\u0631 \u0645\u0644\u0646\u06af"
    ],
    "name:und_x_variant":[
        "\u0160\u0113rmalang",
        "Sh\u012br Matang",
        "Sh\u0113r Malang"
    ],
    "wof:name":"Sher Malang",
    "wof:placetype":"locality"
},
  "geometry": {"coordinates":[61.8806,31.13367],"type":"Point"}
}