{
  "type": "Feature",
  "properties": {
    "gn:admin1_code":"40",
    "gn:admin2_code":"302.0",
    "gn:asciiname":"Qal'ah-ye Surkh",
    "gn:country_code":"AF",
    "gn:dem":1596,
    "gn:feature_class":"P",
    "gn:feature_code":"PPL",
    "gn:name":"Qal\u2018ah-ye Surkh",
    "gn:population":0,
    "gn:timezone":"Asia/Kabul",
    "iso:country":"AF",
    "name:fas_x_preferred":[
        "\u0642\u0644\u0639\u0647 \u0633\u0631\u062e"
    ],
    "name:und_x_variant":[
        "Qal\u2018a Su\u1e5fkh",
        "Qal\u2018eh Sorkh",
        "Qal\u2018ah-ye Surkh",
        "\u0642\u0644\u0639\u06c0 \u0633\u0631\u062e"
    ],
    "wof:name":"Qal'ah-ye Surkh",
    "wof:placetype":"locality"
},
  "geometry": {"coordinates":[69.22435,35.10131],"type":"Point"}
}