{
  "type": "Feature",
  "properties": {
    "gn:admin1_code":"36",
    "gn:admin2_code":"710",
    "gn:asciiname":"Khano Khel",
    "gn:country_code":"AF",
    "gn:dem":2618,
    "gn:feature_class":"P",
    "gn:feature_code":"PPL",
    "gn:name":"Kh\u0101n\u014d Kh\u0113l",
    "gn:population":0,
    "gn:timezone":"Asia/Kabul",
    "iso:country":"AF",
    "name:fas_x_preferred":[
        "\u062e\u0627\u0646\u0648 \u062e\u064a\u0644"
    ],
    "name:rus_x_preferred":[
        "Khanikheyl\u2019"
    ],
    "name:und_x_variant":[
        "Kh\u0101n\u014d Kh\u0113l",
        "Kh\u0101now Kheyl",
        "\u062e\u0627\u0646\u0648 \u062e\u06d0\u0644"
    ],
    "wof:name":"Khano Khel",
    "wof:placetype":"locality"
},
  "geometry": {"coordinates":[69.468,33.67195],"type":"Point"}
}