{
  "type": "Feature",
  "properties": {
    "gn:admin1_code":"3",
    "gn:admin2_code":"1305.0",
    "gn:asciiname":"Aluchah",
    "gn:country_code":"AF",
    "gn:dem":2212,
    "gn:feature_class":"P",
    "gn:feature_code":"PPL",
    "gn:name":"\u0100l\u016bchah",
    "gn:population":0,
    "gn:timezone":"Asia/Kabul",
    "iso:country":"AF",
    "name:und_x_variant":[
        "\u0100l\u016b\u010da",
        "\u0100l\u016bch\u0101h",
        "\u0100l\u016bcheh",
        "\u0100l\u016bchah",
        "\u0622\u0644\u0648\u0686\u0647"
    ],
    "wof:name":"Aluchah",
    "wof:placetype":"locality"
},
  "geometry": {"coordinates":[68.14064999999999,35.21629],"type":"Point"}
}