{
  "type": "Feature",
  "properties": {
    "gn:admin1_code":"36",
    "gn:admin2_code":"710.0",
    "gn:asciiname":"Ashpan",
    "gn:country_code":"AF",
    "gn:dem":2595,
    "gn:feature_class":"P",
    "gn:feature_code":"PPL",
    "gn:name":"Ashp\u0101n",
    "gn:population":0,
    "gn:timezone":"Asia/Kabul",
    "iso:country":"AF",
    "name:und_x_variant":[
        "A\u0161p\u0101n",
        "Ashpan",
        "Ashp\u0101n",
        "\u0627\u0634\u067e\u0627\u0646"
    ],
    "wof:name":"Ashpan",
    "wof:placetype":"locality"
},
  "geometry": {"coordinates":[69.49705,33.74242],"type":"Point"}
}