{
  "type": "Feature",
  "properties": {
    "gn:admin1_code":"6",
    "gn:admin2_code":"2111.0",
    "gn:asciiname":"Ab Sulakh",
    "gn:country_code":"AF",
    "gn:dem":669,
    "gn:feature_class":"P",
    "gn:feature_code":"PPL",
    "gn:name":"\u0100b S\u016bl\u0101kh",
    "gn:population":0,
    "gn:timezone":"Asia/Kabul",
    "iso:country":"AF",
    "name:und_x_variant":[
        "Avsulakh",
        "Aw S\u016bl\u0101kh",
        "\u0100b S\u016bl\u0101kh",
        "\u0622\u0628 \u0633\u0648\u0644\u0627\u062e"
    ],
    "wof:name":"Ab Sulakh",
    "wof:placetype":"locality"
},
  "geometry": {"coordinates":[62.06141,32.50512],"type":"Point"}
}