{
  "type": "Feature",
  "properties": {
    "gn:admin1_code":"40",
    "gn:admin2_code":"309",
    "gn:asciiname":"Lar Mandikol",
    "gn:country_code":"AF",
    "gn:dem":1483,
    "gn:feature_class":"P",
    "gn:feature_code":"PPL",
    "gn:name":"Lar Man\u1e0f\u012bk\u014dl",
    "gn:population":0,
    "gn:timezone":"Asia/Kabul",
    "iso:country":"AF",
    "name:fas_x_preferred":[
        "\u0645\u0646\u062f\u06cc \u0643\u0648\u0644\u0654 \u0628\u0627\u0644\u0627"
    ],
    "name:rus_x_preferred":[
        "Lar-Mandikul\u2019"
    ],
    "name:und_x_variant":[
        "La\u1e5f Mandik\u014dl",
        "Lar Ma\u1e49\u1e0f\u012bkowl",
        "Lar Ma\u1e49\u1e0f\u012bk\u014dl",
        "Lar Man\u1e0f\u012bk\u014dl",
        "\u0644\u0631 \u0645\u0646\u0689\u06cc\u06a9\u0648\u0644"
    ],
    "wof:name":"Lar Mandikol",
    "wof:placetype":"locality"
},
  "geometry": {"coordinates":[69.53716999999999,34.70528],"type":"Point"}
}