{
  "type": "Feature",
  "properties": {
    "gn:admin1_code":"09",
    "gn:admin2_code":"2709",
    "gn:asciiname":"Tablak",
    "gn:country_code":"AF",
    "gn:dem":2674,
    "gn:feature_class":"P",
    "gn:feature_code":"PPL",
    "gn:name":"Tablak",
    "gn:population":0,
    "gn:timezone":"Asia/Kabul",
    "iso:country":"AF",
    "name:und_x_variant":[
        "\u062a\u0628\u0644\u06a9"
    ],
    "wof:name":"Tablak",
    "wof:placetype":"locality"
},
  "geometry": {"coordinates":[65.90706,34.68824],"type":"Point"}
}