{
  "type": "Feature",
  "properties": {
    "gn:admin1_code":"28",
    "gn:admin2_code":"2503",
    "gn:asciiname":"Sar Wulah",
    "gn:country_code":"AF",
    "gn:dem":1995,
    "gn:feature_class":"P",
    "gn:feature_code":"PPL",
    "gn:name":"Sar Wulah",
    "gn:population":0,
    "gn:timezone":"Asia/Kabul",
    "iso:country":"AF",
    "name:fas_x_preferred":[
        "\u0633\u0631 \u0648\u0648\u0644\u0647"
    ],
    "name:und_x_variant":[
        "Sa\u1e5f Wola",
        "Sarvula",
        "Sar Wulah",
        "\u0633\u0631 \u0648\u0644\u0647",
        "Sar Wolah"
    ],
    "wof:name":"Sar Wulah",
    "wof:placetype":"locality"
},
  "geometry": {"coordinates":[67.06456999999999,32.46257],"type":"Point"}
}