{
  "type": "Feature",
  "properties": {
    "gn:admin1_code":"35",
    "gn:admin2_code":"901.0",
    "gn:asciiname":"Baz Khel",
    "gn:country_code":"AF",
    "gn:dem":799,
    "gn:feature_class":"P",
    "gn:feature_code":"PPL",
    "gn:name":"B\u0101z Kh\u0113l",
    "gn:population":0,
    "gn:timezone":"Asia/Kabul",
    "iso:country":"AF",
    "name:rus_x_preferred":[
        "Bazkheyl\u2019"
    ],
    "name:und_x_variant":[
        "B\u0101z Kh\u0113l",
        "Bazkheyl",
        "\u0628\u0627\u0632 \u062e\u06d0\u0644"
    ],
    "wof:name":"Baz Khel",
    "wof:placetype":"locality"
},
  "geometry": {"coordinates":[70.18501999999999,34.67728],"type":"Point"}
}