{
  "type": "Feature",
  "properties": {
    "gn:admin1_code":"36",
    "gn:admin2_code":"706",
    "gn:asciiname":"Seway Kot",
    "gn:country_code":"AF",
    "gn:dem":2003,
    "gn:feature_class":"P",
    "gn:feature_code":"PPL",
    "gn:name":"S\u00eaway K\u014d\u1e6f",
    "gn:population":0,
    "gn:timezone":"Asia/Kabul",
    "iso:country":"AF",
    "name:und_x_variant":[
        "Sivaykot",
        "Seway K\u014dt",
        "S\u00eaway K\u014d\u1e6f",
        "Sevay Kowt",
        "\u0633\u0648\u06cc \u06a9\u0648\u067c"
    ],
    "wof:name":"Seway Kot",
    "wof:placetype":"locality"
},
  "geometry": {"coordinates":[69.80868000000001,33.67212],"type":"Point"}
}