{
  "type": "Feature",
  "properties": {
    "gn:admin1_code":"35",
    "gn:admin2_code":"901.0",
    "gn:asciiname":"Qal'ah-ye Khan",
    "gn:country_code":"AF",
    "gn:dem":746,
    "gn:feature_class":"P",
    "gn:feature_code":"PPL",
    "gn:name":"Qal\u2018ah-ye Kh\u0101n",
    "gn:population":0,
    "gn:timezone":"Asia/Kabul",
    "iso:country":"AF",
    "name:und_x_variant":[
        "Kalakhan",
        "Qal\u2018a Kh\u0101n",
        "Qal\u2018eh-ye Kh\u0101n",
        "Qal\u2018ah-ye Kh\u0101n",
        "\u0642\u0644\u0639\u06c0 \u062e\u0627\u0646"
    ],
    "wof:name":"Qal'ah-ye Khan",
    "wof:placetype":"locality"
},
  "geometry": {"coordinates":[70.24171,34.68337],"type":"Point"}
}