{
  "type": "Feature",
  "properties": {
    "gn:admin1_code":"32",
    "gn:admin2_code":"1504.0",
    "gn:asciiname":"Chamkoli",
    "gn:country_code":"AF",
    "gn:dem":1770,
    "gn:feature_class":"P",
    "gn:feature_code":"PPL",
    "gn:name":"Chamkol\u012b",
    "gn:population":0,
    "gn:timezone":"Asia/Kabul",
    "iso:country":"AF",
    "name:und_x_variant":[
        "Chamkol\u012b",
        "\u0686\u0645\u06a9\u0644\u06cc"
    ],
    "wof:name":"Chamkoli",
    "wof:placetype":"locality"
},
  "geometry": {"coordinates":[67.40442,36.02799],"type":"Point"}
}