{
  "type": "Feature",
  "properties": {
    "gn:admin1_code":"08",
    "gn:admin2_code":"604",
    "gn:asciiname":"Sun Bulaq",
    "gn:country_code":"AF",
    "gn:dem":2961,
    "gn:feature_class":"P",
    "gn:feature_code":"PPL",
    "gn:name":"S\u016bn B\u016bl\u0101q",
    "gn:population":0,
    "gn:timezone":"Asia/Kabul",
    "iso:country":"AF",
    "name:und_x_variant":[
        "Sunbulak",
        "S\u016bnb\u014dl\u0101gh",
        "S\u016bn B\u016bl\u0101q",
        "\u0633\u0648\u0646 \u0628\u0648\u0644\u0627\u0642"
    ],
    "wof:name":"Sun Bulaq",
    "wof:placetype":"locality"
},
  "geometry": {"coordinates":[67.34205,34.05177],"type":"Point"}
}