{
  "type": "Feature",
  "properties": {
    "gn:admin1_code":"17",
    "gn:admin2_code":"506",
    "gn:asciiname":"Kharowti",
    "gn:country_code":"AF",
    "gn:dem":2464,
    "gn:feature_class":"P",
    "gn:feature_code":"PPL",
    "gn:name":"Kharowti",
    "gn:population":0,
    "gn:timezone":"Asia/Kabul",
    "iso:country":"AF",
    "name:fas_x_preferred":[
        "\u062e\u0631\u0648\u062a\u06cc"
    ],
    "name:und_x_variant":[
        "Kha\u1e5f\u014dti",
        "Khar\u014dti",
        "Kharoti",
        "Khar\u014d\u1e6f\u012b",
        "Kharowti",
        "\u062e\u0631\u0648\u067c\u06cc"
    ],
    "wof:name":"Kharowti",
    "wof:placetype":"locality"
},
  "geometry": {"coordinates":[69.60021999999999,34.16505],"type":"Point"}
}