{
  "type": "Feature",
  "properties": {
    "gn:admin1_code":"01",
    "gn:admin2_code":"1126.0",
    "gn:asciiname":"Khugistanak",
    "gn:country_code":"AF",
    "gn:dem":1609,
    "gn:feature_class":"P",
    "gn:feature_code":"PPL",
    "gn:name":"Kh\u016bgist\u0101nak",
    "gn:population":0,
    "gn:timezone":"Asia/Kabul",
    "iso:country":"AF",
    "name:und_x_variant":[
        "\u062e\u0648\u06af\u0633\u062a\u0627\u0646\u06a9",
        "Kh\u016bgest\u0101nak",
        "Kh\u016bgist\u0101nak"
    ],
    "wof:name":"Khugistanak",
    "wof:placetype":"locality"
},
  "geometry": {"coordinates":[70.50791,37.25481],"type":"Point"}
}