{
  "type": "Feature",
  "properties": {
    "gn:admin1_code":"34",
    "gn:admin2_code":"1013.0",
    "gn:asciiname":"Mama Khel",
    "gn:country_code":"AF",
    "gn:dem":820,
    "gn:feature_class":"P",
    "gn:feature_code":"PPL",
    "gn:name":"M\u0101m\u0101 Kh\u0113l",
    "gn:population":0,
    "gn:timezone":"Asia/Kabul",
    "iso:country":"AF",
    "name:fas_x_preferred":[
        "\u0645\u0627\u0645\u0627 \u062e\u064a\u0644"
    ],
    "name:rus_x_preferred":[
        "Mamakheyl\u2019"
    ],
    "name:und_x_variant":[
        "M\u0101m\u0101 Kh\u0113l",
        "M\u0101m\u0101kheyl",
        "\u0645\u0627\u0645\u0627 \u062e\u06d0\u0644"
    ],
    "wof:name":"Mama Khel",
    "wof:placetype":"locality"
},
  "geometry": {"coordinates":[70.70636999999998,34.6454],"type":"Point"}
}