{
  "type": "Feature",
  "properties": {
    "gn:admin1_code":"08",
    "gn:admin2_code":"607",
    "gn:asciiname":"Khanah-ye 'Abdul Mehtar",
    "gn:country_code":"AF",
    "gn:dem":2830,
    "gn:feature_class":"P",
    "gn:feature_code":"PPL",
    "gn:name":"Kh\u0101nah-ye \u2018Abdul Mehtar",
    "gn:population":0,
    "gn:timezone":"Asia/Kabul",
    "iso:country":"AF",
    "name:fas_x_preferred":[
        "\u062e\u0627\u0646\u06c0 \u0639\u0628\u062f \u0627\u0644\u0645\u0647\u062a\u0631"
    ],
    "name:rus_x_preferred":[
        "\u0425\u0430\u043d\u0430\u0439\u0438-\u0410\u0431\u0434\u0443\u043b\u044c\u043c\u0438\u0445\u0442\u0430\u0440"
    ],
    "name:und_x_variant":[
        "Kh\u0101na-i-\u2018Ab\u1e0ful Mehta\u1e5f",
        "Khanayi-Abdul\u2019mikhtar",
        "Kh\u0101neh-ye \u2018Abdul Mehtar",
        "Kh\u0101neh-ye \u2018Abd ol Mehtar",
        "Kh\u0101nah-ye \u2018Abdul Mehtar",
        "\u062e\u0627\u0646\u06c0 \u0639\u0628\u062f\u0627\u0644 \u0645\u0647\u062a\u0631"
    ],
    "wof:name":"Khanah-ye 'Abdul Mehtar",
    "wof:placetype":"locality"
},
  "geometry": {"coordinates":[67.50743,33.00884],"type":"Point"}
}