{
  "type": "Feature",
  "properties": {
    "gn:admin1_code":"01",
    "gn:admin2_code":"1116",
    "gn:asciiname":"Khwajah-ye Bagh",
    "gn:country_code":"AF",
    "gn:dem":2180,
    "gn:feature_class":"P",
    "gn:feature_code":"PPL",
    "gn:name":"Khw\u0101jah-ye B\u0101gh",
    "gn:population":0,
    "gn:timezone":"Asia/Kabul",
    "iso:country":"AF",
    "name:und_x_variant":[
        "Khw\u0101ja-i-B\u0101gh",
        "Khv\u0101jeh-ye B\u0101gh",
        "Khw\u0101jah-ye B\u0101gh",
        "\u062e\u0648\u0627\u062c\u06c0 \u0628\u0627\u063a"
    ],
    "wof:name":"Khwajah-ye Bagh",
    "wof:placetype":"locality"
},
  "geometry": {"coordinates":[70.48454,36.9117],"type":"Point"}
}