{
  "type": "Feature",
  "properties": {
    "gn:admin1_code":"18",
    "gn:admin2_code":"805",
    "gn:asciiname":"Kuz Bangashayr",
    "gn:country_code":"AF",
    "gn:dem":1547,
    "gn:feature_class":"P",
    "gn:feature_code":"PPL",
    "gn:name":"K\u016bz Bangashayr",
    "gn:population":0,
    "gn:timezone":"Asia/Kabul",
    "iso:country":"AF",
    "name:fas_x_preferred":[
        "\u0643\u0648\u0632 \u0628\u0646\u06af\u0634\u064a\u0631"
    ],
    "name:und_x_variant":[
        "Kuzbangasher",
        "Kuz Bangash\u0113r",
        "K\u016bz Banga\u0161\u0113r",
        "K\u016bz Bengas\u0304\u0113\u1e5f",
        "K\u016bz Bengash\u012br",
        "K\u016bz Bangashayr",
        "\u06a9\u0648\u0632 \u0628\u0646\u06af\u0634\u06cc\u0631"
    ],
    "wof:name":"Kuz Bangashayr",
    "wof:placetype":"locality"
},
  "geometry": {"coordinates":[70.10514000000001,34.4156],"type":"Point"}
}