{
  "type": "Feature",
  "properties": {
    "gn:admin1_code":"08",
    "gn:admin2_code":"610",
    "gn:asciiname":"Sar Deh",
    "gn:country_code":"AF",
    "gn:dem":1968,
    "gn:feature_class":"P",
    "gn:feature_code":"PPL",
    "gn:name":"Sar Deh",
    "gn:population":0,
    "gn:timezone":"Asia/Kabul",
    "iso:country":"AF",
    "name:und_x_variant":[
        "Sardekh",
        "Sar Deh",
        "\u0633\u0631 \u062f\u0647"
    ],
    "wof:name":"Sar Deh",
    "wof:placetype":"locality"
},
  "geometry": {"coordinates":[67.67309,32.26749],"type":"Point"}
}