{
  "type": "Feature",
  "properties": {
    "gn:admin1_code":"26",
    "gn:admin2_code":"1201",
    "gn:asciiname":"Gavi",
    "gn:country_code":"AF",
    "gn:dem":689,
    "gn:feature_class":"P",
    "gn:feature_code":"PPL",
    "gn:name":"Gavi",
    "gn:population":0,
    "gn:timezone":"Asia/Kabul",
    "iso:country":"AF",
    "name:ceb_x_preferred":[
        "Gavi"
    ],
    "name:ces_x_preferred":[
        "Gavi"
    ],
    "name:deu_x_preferred":[
        "Gavi"
    ],
    "name:fas_x_preferred":[
        "\u06af\u0627\u0648\u06cc"
    ],
    "name:fra_x_preferred":[
        "Gavi"
    ],
    "name:ita_x_preferred":[
        "Gavi"
    ],
    "name:nld_x_preferred":[
        "Gavi"
    ],
    "name:rus_x_preferred":[
        "\u0413\u0430\u0432\u0438"
    ],
    "name:swe_x_preferred":[
        "Gavi"
    ],
    "name:und_x_variant":[
        "G\u0101wi",
        "Gavi",
        "G\u0101v\u012b",
        "G\u0101w\u012b",
        "\u06af\u0627\u0648\u06cc"
    ],
    "wof:name":"Gavi",
    "wof:placetype":"locality"
},
  "geometry": {"coordinates":[69.36403,36.73226],"type":"Point"}
}