{
  "type": "Feature",
  "properties": {
    "gn:admin1_code":"27",
    "gn:admin2_code":"403.0",
    "gn:asciiname":"Ghowch Qol",
    "gn:country_code":"AF",
    "gn:dem":3132,
    "gn:feature_class":"P",
    "gn:feature_code":"PPL",
    "gn:name":"Ghowch Q\u014dl",
    "gn:population":0,
    "gn:timezone":"Asia/Kabul",
    "iso:country":"AF",
    "name:rus_x_preferred":[
        "Gauchkul\u2019"
    ],
    "name:und_x_variant":[
        "Ghaw\u010dqol",
        "Ghawchqowl",
        "Gh\u014dch Q\u014dl",
        "Ghowch Q\u014dl",
        "\u063a\u0648\u0686 \u0642\u0648\u0644"
    ],
    "wof:name":"Ghowch Qol",
    "wof:placetype":"locality"
},
  "geometry": {"coordinates":[68.10159,34.51683],"type":"Point"}
}