{
  "type": "Feature",
  "properties": {
    "gn:admin1_code":"41",
    "gn:admin2_code":"3403.0",
    "gn:asciiname":"Akhtam",
    "gn:country_code":"AF",
    "gn:dem":2796,
    "gn:feature_class":"P",
    "gn:feature_code":"PPL",
    "gn:name":"Akhtam",
    "gn:population":0,
    "gn:timezone":"Asia/Kabul",
    "iso:country":"AF",
    "name:und_x_variant":[
        "\u0627\u062e\u062a\u0645"
    ],
    "wof:name":"Akhtam",
    "wof:placetype":"locality"
},
  "geometry": {"coordinates":[66.36043000000001,33.91135999999999],"type":"Point"}
}