{
  "type": "Feature",
  "properties": {
    "gn:admin1_code":"27",
    "gn:admin2_code":"404.0",
    "gn:asciiname":"Aw Darah",
    "gn:country_code":"AF",
    "gn:dem":3254,
    "gn:feature_class":"P",
    "gn:feature_code":"PPL",
    "gn:name":"\u0100w Darah",
    "gn:population":0,
    "gn:timezone":"Asia/Kabul",
    "iso:country":"AF",
    "name:und_x_variant":[
        "Aw\u1e0fa\u1e5fa",
        "Avdara",
        "\u0100w Darah",
        "\u0100bdarreh",
        "\u0622\u0648 \u062f\u0631\u0647"
    ],
    "wof:name":"Aw Darah",
    "wof:placetype":"locality"
},
  "geometry": {"coordinates":[67.62448000000001,34.57424],"type":"Point"}
}