{
  "type": "Feature",
  "properties": {
    "gn:admin1_code":"11",
    "gn:admin2_code":"2013",
    "gn:asciiname":"Girgi",
    "gn:country_code":"AF",
    "gn:dem":2466,
    "gn:feature_class":"P",
    "gn:feature_code":"PPL",
    "gn:name":"Girg\u012b",
    "gn:population":0,
    "gn:timezone":"Asia/Kabul",
    "iso:country":"AF",
    "name:und_x_variant":[
        "Girg\u012b",
        "\u06af\u0631\u06af\u06cc",
        "Gerg\u012b",
        "Girgi"
    ],
    "wof:name":"Girgi",
    "wof:placetype":"locality"
},
  "geometry": {"coordinates":[63.3328,33.76191],"type":"Point"}
}