{
  "type": "Feature",
  "properties": {
    "gn:admin1_code":"01",
    "gn:admin2_code":"1112.0",
    "gn:asciiname":"Bamistan",
    "gn:country_code":"AF",
    "gn:dem":2508,
    "gn:feature_class":"P",
    "gn:feature_code":"PPL",
    "gn:name":"B\u0101mist\u0101n",
    "gn:population":0,
    "gn:timezone":"Asia/Kabul",
    "iso:country":"AF",
    "name:und_x_variant":[
        "B\u0101mist\u0101n",
        "\u0628\u0627\u0645\u0633\u062a\u0627\u0646",
        "B\u0101mest\u0101n"
    ],
    "wof:name":"Bamistan",
    "wof:placetype":"locality"
},
  "geometry": {"coordinates":[70.46279,37.65486],"type":"Point"}
}