{
  "type": "Feature",
  "properties": {
    "gn:admin1_code":"09",
    "gn:admin2_code":"2706",
    "gn:asciiname":"Sarbuz",
    "gn:country_code":"AF",
    "gn:dem":2266,
    "gn:feature_class":"P",
    "gn:feature_code":"PPL",
    "gn:name":"Sarb\u016bz",
    "gn:population":0,
    "gn:timezone":"Asia/Kabul",
    "iso:country":"AF",
    "name:und_x_variant":[
        "Sarb\u016bz",
        "\u0633\u0631\u0628\u0648\u0632",
        "Sa\u1e5fb\u016bz"
    ],
    "wof:name":"Sarbuz",
    "wof:placetype":"locality"
},
  "geometry": {"coordinates":[65.39803000000001,33.62116],"type":"Point"}
}