{
  "type": "Feature",
  "properties": {
    "gn:admin1_code":"18",
    "gn:admin2_code":"807.0",
    "gn:asciiname":"Sematse",
    "gn:country_code":"AF",
    "gn:dem":1122,
    "gn:feature_class":"P",
    "gn:feature_code":"PPL",
    "gn:name":"S\u00eamats\u0113",
    "gn:population":0,
    "gn:timezone":"Asia/Kabul",
    "iso:country":"AF",
    "name:fas_x_preferred":[
        "\u0633\u0645\u0686\u06cc"
    ],
    "name:und_x_variant":[
        "Semache",
        "S\u011bmac\u0113",
        "Semats\u0113",
        "S\u00eamats\u0113",
        "\u0633\u0645\u0685\u06d0"
    ],
    "wof:name":"Sematse",
    "wof:placetype":"locality"
},
  "geometry": {"coordinates":[70.29995,34.23576],"type":"Point"}
}