{
  "type": "Feature",
  "properties": {
    "gn:admin1_code":"26",
    "gn:admin2_code":"1212",
    "gn:asciiname":"Yakah Shor",
    "gn:country_code":"AF",
    "gn:dem":791,
    "gn:feature_class":"P",
    "gn:feature_code":"PPL",
    "gn:name":"Yakah Sh\u014dr",
    "gn:population":0,
    "gn:timezone":"Asia/Kabul",
    "iso:country":"AF",
    "name:fas_x_preferred":[
        "\u064a\u0643\u0647 \u0634\u0648\u0631"
    ],
    "name:rus_x_preferred":[
        "\u042f\u043a\u043a\u0430\u0448\u043e\u0440"
    ],
    "name:und_x_variant":[
        "Yakka \u0160or",
        "Yakka Shor",
        "Yakkashor",
        "Yekkeh Sh\u016br",
        "Yakah Sh\u014dr",
        "\u06cc\u06a9\u0647 \u0634\u0648\u0631"
    ],
    "wof:name":"Yakah Shor",
    "wof:placetype":"locality"
},
  "geometry": {"coordinates":[69.47310999999999,36.98745],"type":"Point"}
}