{
  "type": "Feature",
  "properties": {
    "gn:admin1_code":"19",
    "gn:admin2_code":"2204.0",
    "gn:asciiname":"Nur Muhammad",
    "gn:country_code":"AF",
    "gn:dem":483,
    "gn:feature_class":"P",
    "gn:feature_code":"PPL",
    "gn:name":"N\u016br Mu\u1e29ammad",
    "gn:population":0,
    "gn:timezone":"Asia/Kabul",
    "iso:country":"AF",
    "name:und_x_variant":[
        "N\u016b\u1e5fmoh\u1e0f",
        "N\u016br Mu\u1e29ammad",
        "\u0646\u0648\u0631 \u0645\u062d\u0645\u062f",
        "N\u016br Mo\u1e29ammad"
    ],
    "wof:name":"Nur Muhammad",
    "wof:placetype":"locality"
},
  "geometry": {"coordinates":[62.08639,31.21023],"type":"Point"}
}