{
  "type": "Feature",
  "properties": {
    "gn:admin1_code":"19",
    "gn:admin2_code":"2202.0",
    "gn:asciiname":"Haji Muhammad A'zam",
    "gn:country_code":"AF",
    "gn:dem":486,
    "gn:feature_class":"P",
    "gn:feature_code":"PPL",
    "gn:name":"Haji Muhammad A'zam",
    "gn:population":0,
    "gn:timezone":"Asia/Kabul",
    "iso:country":"AF",
    "name:afr_x_preferred":[
        "\u1e28\u0101j\u012b Mu\u1e29ammad\u00a0A\u2018z\u0327am"
    ],
    "name:und_x_variant":[
        "H\u0331\u0101ji Mo\u1e96\u1e0f A\u2019\u1e95am",
        "\u1e28\u0101jj\u012b Mo\u1e29ammad A\u2018z\u0327am"
    ],
    "wof:name":"Haji Muhammad A'zam",
    "wof:placetype":"locality"
},
  "geometry": {"coordinates":[61.90511,31.04837],"type":"Point"}
}