{
  "type": "Feature",
  "properties": {
    "gn:admin1_code":"36",
    "gn:admin2_code":"704",
    "gn:asciiname":"Ghorke Khulah",
    "gn:country_code":"AF",
    "gn:dem":1842,
    "gn:feature_class":"P",
    "gn:feature_code":"PPL",
    "gn:name":"Gh\u014drk\u0113 Kh\u016blah",
    "gn:population":0,
    "gn:timezone":"Asia/Kabul",
    "iso:country":"AF",
    "name:fas_x_preferred":[
        "\u063a\u0648\u0631\u0643\u06cc \u062e\u0648\u0644\u0647"
    ],
    "name:und_x_variant":[
        "Gorkekhula",
        "Gh\u014d\u1e5fk\u0113 Kholeh",
        "Gh\u016brk\u0113 Kh\u016blah",
        "Gh\u016brk\u012b Kholeh",
        "Gh\u014drk\u0113 Kh\u016blah",
        "\u063a\u0648\u0631\u06a9\u06d0 \u062e\u0648\u0644\u0647"
    ],
    "wof:name":"Ghorke Khulah",
    "wof:placetype":"locality"
},
  "geometry": {"coordinates":[69.47118,33.3682],"type":"Point"}
}