{
  "type": "Feature",
  "properties": {
    "gn:admin1_code":"18",
    "gn:admin2_code":"809.0",
    "gn:asciiname":"Baru",
    "gn:country_code":"AF",
    "gn:dem":678,
    "gn:feature_class":"P",
    "gn:feature_code":"PPL",
    "gn:name":"Baru",
    "gn:population":0,
    "gn:timezone":"Asia/Kabul",
    "iso:country":"AF",
    "name:und_x_variant":[
        "B\u0101ru",
        "B\u0101r\u016b",
        "\u0628\u0627\u0631\u0648"
    ],
    "wof:name":"Baru",
    "wof:placetype":"locality"
},
  "geometry": {"coordinates":[70.64017,34.25673],"type":"Point"}
}