{
  "type": "Feature",
  "properties": {
    "gn:admin1_code":"2",
    "gn:admin2_code":"1906.0",
    "gn:asciiname":"Charkh Ab",
    "gn:country_code":"AF",
    "gn:dem":425,
    "gn:feature_class":"P",
    "gn:feature_code":"PPL",
    "gn:name":"Charkh \u0100b",
    "gn:population":0,
    "gn:timezone":"Asia/Kabul",
    "iso:country":"AF",
    "name:und_x_variant":[
        "Ca\u1e5fkh \u0100b",
        "Charkh \u0100b",
        "\u0686\u0631\u062e \u0622\u0628"
    ],
    "wof:name":"Charkh Ab",
    "wof:placetype":"locality"
},
  "geometry": {"coordinates":[63.17755,35.74184],"type":"Point"}
}