{
  "type": "Feature",
  "properties": {
    "gn:admin1_code":"06",
    "gn:admin2_code":"2105",
    "gn:asciiname":"Qaryah-ye Sar Chashmah",
    "gn:country_code":"AF",
    "gn:dem":1150,
    "gn:feature_class":"P",
    "gn:feature_code":"PPL",
    "gn:name":"Qaryah-ye Sar Chashmah",
    "gn:population":0,
    "gn:timezone":"Asia/Kabul",
    "iso:country":"AF",
    "name:rus_x_preferred":[
        "Kar\u2019yayi-Sarchashma"
    ],
    "name:und_x_variant":[
        "Qaryeh-ye Sar Chashmeh",
        "Qarya-i-Sar \u010ca\u0161ma",
        "Qaryeh-ye Sar Cheshmeh",
        "Qaryah-ye Sar Chashmah",
        "\u0642\u0631\u06cc\u0647 \u0633\u0631 \u0686\u0634\u0645\u0647"
    ],
    "wof:name":"Qaryah-ye Sar Chashmah",
    "wof:placetype":"locality"
},
  "geometry": {"coordinates":[63.11166,32.92601],"type":"Point"}
}