{
  "type": "Feature",
  "properties": {
    "gn:admin1_code":"41",
    "gn:admin2_code":"3401.0",
    "gn:asciiname":"Jowqol",
    "gn:country_code":"AF",
    "gn:dem":2620,
    "gn:feature_class":"P",
    "gn:feature_code":"PPL",
    "gn:name":"Jowq\u014dl",
    "gn:population":0,
    "gn:timezone":"Asia/Kabul",
    "iso:country":"AF",
    "name:und_x_variant":[
        "Jawq\u014dl",
        "Jowq\u014dl",
        "\u062c\u0648\u0642\u0648\u0644",
        "Jawqowl"
    ],
    "wof:name":"Jowqol",
    "wof:placetype":"locality"
},
  "geometry": {"coordinates":[66.06408,33.8514],"type":"Point"}
}