{
  "type": "Feature",
  "properties": {
    "gn:admin1_code":"10",
    "gn:admin2_code":"2302",
    "gn:asciiname":"Tambah",
    "gn:country_code":"AF",
    "gn:dem":861,
    "gn:feature_class":"P",
    "gn:feature_code":"PPL",
    "gn:name":"Tambah",
    "gn:population":0,
    "gn:timezone":"Asia/Kabul",
    "iso:country":"AF",
    "name:und_x_variant":[
        "\u062a\u0645\u0628\u0647",
        "Tamba"
    ],
    "wof:name":"Tambah",
    "wof:placetype":"locality"
},
  "geometry": {"coordinates":[64.77457,31.93339000000001],"type":"Point"}
}