{
  "type": "Feature",
  "properties": {
    "gn:admin1_code":"28",
    "gn:admin2_code":"2510.0",
    "gn:asciiname":"Baluch Kelay",
    "gn:country_code":"AF",
    "gn:dem":1819,
    "gn:feature_class":"P",
    "gn:feature_code":"PPL",
    "gn:name":"Bal\u016bch K\u00ealay",
    "gn:population":0,
    "gn:timezone":"Asia/Kabul",
    "iso:country":"AF",
    "name:und_x_variant":[
        "Bal\u016b\u010d Kalay",
        "Bal\u016bch K\u00ealay",
        "\u0628\u0644\u0648\u0686 \u06a9\u0644\u06cc",
        "Bal\u016bch Kalay"
    ],
    "wof:name":"Baluch Kelay",
    "wof:placetype":"locality"
},
  "geometry": {"coordinates":[67.25185999999999,32.7684],"type":"Point"}
}