{
  "type": "Feature",
  "properties": {
    "gn:admin1_code":"01",
    "gn:admin2_code":"1114.0",
    "gn:asciiname":"Dasht-e Pahn",
    "gn:country_code":"AF",
    "gn:dem":2406,
    "gn:feature_class":"P",
    "gn:feature_code":"PPL",
    "gn:name":"Dasht-e Pahn",
    "gn:population":0,
    "gn:timezone":"Asia/Kabul",
    "iso:country":"AF",
    "name:und_x_variant":[
        "Da\u0161t-i-Pahn",
        "Dasht-e Pahn",
        "\u062f\u0634\u062a \u067e\u0647\u0646"
    ],
    "wof:name":"Dasht-e Pahn",
    "wof:placetype":"locality"
},
  "geometry": {"coordinates":[70.76328000000002,37.1478],"type":"Point"}
}