{
  "type": "Feature",
  "properties": {
    "gn:admin1_code":"09",
    "gn:admin2_code":"2701",
    "gn:asciiname":"Gandawak",
    "gn:country_code":"AF",
    "gn:dem":2884,
    "gn:feature_class":"P",
    "gn:feature_code":"PPL",
    "gn:name":"Gand\u0101wak",
    "gn:population":0,
    "gn:timezone":"Asia/Kabul",
    "iso:country":"AF",
    "name:und_x_variant":[
        "Gand\u0101wak",
        "\u06af\u0646\u0689\u0627\u0648\u06a9",
        "Gand\u0101bak"
    ],
    "wof:name":"Gandawak",
    "wof:placetype":"locality"
},
  "geometry": {"coordinates":[65.71664,34.95177],"type":"Point"}
}