{
  "type": "Feature",
  "properties": {
    "gn:admin1_code":"30",
    "gn:admin2_code":"1607",
    "gn:asciiname":"Gul-e Kah",
    "gn:country_code":"AF",
    "gn:dem":334,
    "gn:feature_class":"P",
    "gn:feature_code":"PPL",
    "gn:name":"Gul-e K\u0101h",
    "gn:population":0,
    "gn:timezone":"Asia/Kabul",
    "iso:country":"AF",
    "name:fas_x_preferred":[
        "\u06af\u0644 \u06a9\u0627\u0647"
    ],
    "name:rus_x_preferred":[
        "\u0413\u0443\u043b\u0438-\u041a\u0430\u0445"
    ],
    "name:und_x_variant":[
        "Gul-i-Kah",
        "Guli-Kakh",
        "Gol-e K\u0101h",
        "Gul-e K\u0101h"
    ],
    "wof:name":"Gul-e Kah",
    "wof:placetype":"locality"
},
  "geometry": {"coordinates":[66.73975,36.76585],"type":"Point"}
}