{
  "type": "Feature",
  "properties": {
    "gn:admin1_code":"40",
    "gn:admin2_code":"307.0",
    "gn:asciiname":"Qal'ah-ye Asun",
    "gn:country_code":"AF",
    "gn:dem":2908,
    "gn:feature_class":"P",
    "gn:feature_code":"PPL",
    "gn:name":"Qal\u2018ah-ye \u0100sun",
    "gn:population":0,
    "gn:timezone":"Asia/Kabul",
    "iso:country":"AF",
    "name:und_x_variant":[
        "Kalaasun",
        "Qal\u2018a-i-\u0100sun",
        "Qal\u2018a \u0100sun",
        "Qal\u2018eh-ye \u0100san",
        "Qal\u2018ah-ye \u0100sun",
        "\u0642\u0644\u0639\u0647 \u0622\u0633\u0646"
    ],
    "wof:name":"Qal'ah-ye Asun",
    "wof:placetype":"locality"
},
  "geometry": {"coordinates":[68.49249,34.7089],"type":"Point"}
}