{
  "type": "Feature",
  "properties": {
    "gn:admin1_code":"40",
    "gn:admin2_code":"306.0",
    "gn:asciiname":"Bayakmurdah",
    "gn:country_code":"AF",
    "gn:dem":2659,
    "gn:feature_class":"P",
    "gn:feature_code":"PPL",
    "gn:name":"Bayakmurdah",
    "gn:population":0,
    "gn:timezone":"Asia/Kabul",
    "iso:country":"AF",
    "name:und_x_variant":[
        "Bayakmu\u1e5f\u1e0fa",
        "Beyakmordeh",
        "Bayakmurdah",
        "\u0628\u06cc\u06a9\u0645\u0631\u062f\u0647"
    ],
    "wof:name":"Bayakmurdah",
    "wof:placetype":"locality"
},
  "geometry": {"coordinates":[68.47230999999999,35.0027],"type":"Point"}
}