{
  "type": "Feature",
  "properties": {
    "gn:admin1_code":"11",
    "gn:admin2_code":"2014.0",
    "gn:asciiname":"Tutak",
    "gn:country_code":"AF",
    "gn:dem":1058,
    "gn:feature_class":"P",
    "gn:feature_code":"PPL",
    "gn:name":"T\u016btak",
    "gn:population":0,
    "gn:timezone":"Asia/Kabul",
    "iso:country":"AF",
    "name:nld_x_preferred":[
        "Tutak"
    ],
    "name:pnb_x_preferred":[
        "\u0636\u0644\u0639 \u06af\u0631\u06af\u0631"
    ],
    "name:tur_x_preferred":[
        "Tutak"
    ],
    "name:und_x_variant":[
        "T\u016btak",
        "\u062a\u0648\u062a\u06a9"
    ],
    "wof:name":"Tutak",
    "wof:placetype":"locality"
},
  "geometry": {"coordinates":[61.79194,32.9763],"type":"Point"}
}