{
  "type": "Feature",
  "properties": {
    "gn:admin1_code":"10",
    "gn:admin2_code":"2305.0",
    "gn:asciiname":"Lwar Giriian",
    "gn:country_code":"AF",
    "gn:dem":1678,
    "gn:feature_class":"P",
    "gn:feature_code":"PPL",
    "gn:name":"Lwa\u1e5f Giri\u012b\u0101n",
    "gn:population":0,
    "gn:timezone":"Asia/Kabul",
    "iso:country":"AF",
    "name:rus_x_preferred":[
        "L\u2019vargir\u2019yan"
    ],
    "name:und_x_variant":[
        "Lwar Ge\u1e5fy\u0101n",
        "Lwa\u1e5f Giri\u012b\u0101n",
        "\u0644\u0648\u0693 \u06af\u0631\u06cc\u0627\u0646",
        "Lwar Ger\u012b\u0101n"
    ],
    "wof:name":"Lwar Giriian",
    "wof:placetype":"locality"
},
  "geometry": {"coordinates":[65.07879,32.73362],"type":"Point"}
}