{
  "type": "Feature",
  "properties": {
    "gn:admin1_code":"19",
    "gn:admin2_code":"2203.0",
    "gn:asciiname":"Aday",
    "gn:country_code":"AF",
    "gn:dem":499,
    "gn:feature_class":"P",
    "gn:feature_code":"PPL",
    "gn:name":"Aday",
    "gn:population":0,
    "gn:timezone":"Asia/Kabul",
    "iso:country":"AF",
    "name:und_x_variant":[
        "\u0627\u062f\u06cc",
        "Ad\u012b"
    ],
    "wof:name":"Aday",
    "wof:placetype":"locality"
},
  "geometry": {"coordinates":[61.82568000000001,30.75383],"type":"Point"}
}