{
  "type": "Feature",
  "properties": {
    "gn:admin1_code":"03",
    "gn:admin2_code":"1309.0",
    "gn:asciiname":"Shinwari",
    "gn:country_code":"AF",
    "gn:dem":978,
    "gn:feature_class":"P",
    "gn:feature_code":"PPL",
    "gn:name":"Shinw\u0101r\u012b",
    "gn:population":0,
    "gn:timezone":"Asia/Kabul",
    "iso:country":"AF",
    "name:ceb_x_preferred":[
        "Shinwari"
    ],
    "name:swe_x_preferred":[
        "Shinwari"
    ],
    "name:und_x_variant":[
        "Shinw\u0101r\u012b",
        "\u0634\u0646\u0648\u0627\u0631\u06cc"
    ],
    "wof:name":"Shinwari",
    "wof:placetype":"locality"
},
  "geometry": {"coordinates":[69.03559,36.08197],"type":"Point"}
}