{
  "type": "Feature",
  "properties": {
    "gn:admin1_code":"11",
    "gn:admin2_code":"2013.0",
    "gn:asciiname":"Kalah Kuhak",
    "gn:country_code":"AF",
    "gn:dem":2065,
    "gn:feature_class":"P",
    "gn:feature_code":"PPL",
    "gn:name":"Kalah K\u016bhak",
    "gn:population":0,
    "gn:timezone":"Asia/Kabul",
    "iso:country":"AF",
    "name:und_x_variant":[
        "Kalak\u014dhak",
        "Kalah K\u016bhak"
    ],
    "wof:name":"Kalah Kuhak",
    "wof:placetype":"locality"
},
  "geometry": {"coordinates":[63.05028000000001,33.6825],"type":"Point"}
}