{
  "type": "Feature",
  "properties": {
    "gn:admin1_code":"23",
    "gn:admin2_code":"2403.0",
    "gn:asciiname":"Atsakzo Soznay",
    "gn:country_code":"AF",
    "gn:dem":1226,
    "gn:feature_class":"P",
    "gn:feature_code":"PPL",
    "gn:name":"Atsakz\u014d S\u014dznay",
    "gn:population":0,
    "gn:timezone":"Asia/Kabul",
    "iso:country":"AF",
    "name:fas_x_preferred":[
        "\u0627\u0686\u062c\u0632\u0648 \u0633\u0648\u0632\u0646\u06cc"
    ],
    "name:und_x_variant":[
        "Achakzusoznay",
        "Acakzo S\u014dznay",
        "Atsakz\u014d S\u014dznay",
        "\u0627\u0685\u06a9\u0632\u0648 \u0633\u0648\u0632\u0646\u06cc",
        "Atsajzo S\u016bznay"
    ],
    "wof:name":"Atsakzo Soznay",
    "wof:placetype":"locality"
},
  "geometry": {"coordinates":[65.76015,31.90419],"type":"Point"}
}