{
  "type": "Feature",
  "properties": {
    "gn:admin1_code":"29",
    "gn:admin2_code":"2909",
    "gn:asciiname":"Demianay",
    "gn:country_code":"AF",
    "gn:dem":2094,
    "gn:feature_class":"P",
    "gn:feature_code":"PPL",
    "gn:name":"\u1e0e\u00eam\u012b\u0101nay",
    "gn:population":0,
    "gn:timezone":"Asia/Kabul",
    "iso:country":"AF",
    "name:rus_x_preferred":[
        "Dim\u2019yanay"
    ],
    "name:und_x_variant":[
        "\u1e0e\u00eamy\u0101nay",
        "Demy\u0101nay",
        "\u1e0e\u00eam\u012b\u0101nay",
        "\u0689\u0645\u06cc\u0627\u0646\u06cc"
    ],
    "wof:name":"Demianay",
    "wof:placetype":"locality"
},
  "geometry": {"coordinates":[69.26223,32.88113],"type":"Point"}
}