{
  "type": "Feature",
  "properties": {
    "gn:admin1_code":"23",
    "gn:admin2_code":"2410",
    "gn:asciiname":"Iraki Kelay",
    "gn:country_code":"AF",
    "gn:dem":955,
    "gn:feature_class":"P",
    "gn:feature_code":"PPL",
    "gn:name":"Ir\u0101k\u012b K\u00ealay",
    "gn:population":0,
    "gn:timezone":"Asia/Kabul",
    "iso:country":"AF",
    "name:pus_x_preferred":[
        "\u0627\u0631\u0627\u06a9\u06cc \u06a9\u0644\u06cc"
    ],
    "name:und_x_variant":[
        "E\u1e5f\u0101ki Kalay",
        "Ir\u0101q\u012b K\u00ealay",
        "Ir\u0101k\u012b K\u00ealay"
    ],
    "wof:name":"Iraki Kelay",
    "wof:placetype":"locality"
},
  "geometry": {"coordinates":[65.89012,29.92622],"type":"Point"}
}