{
  "type": "Feature",
  "properties": {
    "gn:admin1_code":"11",
    "gn:admin2_code":"2014",
    "gn:asciiname":"Siyah Sar-e Bala",
    "gn:country_code":"AF",
    "gn:dem":1087,
    "gn:feature_class":"P",
    "gn:feature_code":"PPL",
    "gn:name":"Siy\u0101h S\u0101r-e B\u0101l\u0101",
    "gn:population":0,
    "gn:timezone":"Asia/Kabul",
    "iso:country":"AF",
    "name:und_x_variant":[
        "Seyah S\u0101\u1e5f B\u0101l\u0101",
        "S\u012b\u0101h S\u0101r B\u0101l\u0101",
        "Siakhsar-Bala",
        "S\u012b\u0101h S\u0101r-e B\u0101l\u0101",
        "\u0633\u06cc\u0627\u0647 \u0633\u0627\u0631 \u0628\u0627\u0644\u0627",
        "Siy\u0101h S\u0101r-e B\u0101l\u0101"
    ],
    "wof:name":"Siyah Sar-e Bala",
    "wof:placetype":"locality"
},
  "geometry": {"coordinates":[62.27688000000001,33.29425999999999],"type":"Point"}
}