{
  "type": "Feature",
  "properties": {
    "gn:admin1_code":"42",
    "gn:admin2_code":"3304",
    "gn:asciiname":"Now Dahanak",
    "gn:country_code":"AF",
    "gn:dem":2629,
    "gn:feature_class":"P",
    "gn:feature_code":"PPLA2",
    "gn:name":"Now Dah\u0101nak",
    "gn:population":0,
    "gn:timezone":"Asia/Kabul",
    "iso:country":"AF",
    "name:und_x_variant":[
        "Navadanak",
        "Nawd\u0101nak",
        "N\u0101w D\u0101nak",
        "Now Dah\u0101nak",
        "\u0646\u0648 \u062f\u0647\u0627\u0646\u06a9",
        "Now D\u0101nak",
        "\u0646\u0648 \u062f\u0627\u0646\u06a9"
    ],
    "wof:name":"Now Dahanak",
    "wof:placetype":"locality"
},
  "geometry": {"coordinates":[70.00511,35.62398],"type":"Point"}
}