{
  "type": "Feature",
  "properties": {
    "gn:admin1_code":"23",
    "gn:admin2_code":"2413",
    "gn:asciiname":"Neko Wulah",
    "gn:country_code":"AF",
    "gn:dem":1900,
    "gn:feature_class":"P",
    "gn:feature_code":"PPL",
    "gn:name":"N\u0113k\u014d Wulah",
    "gn:population":0,
    "gn:timezone":"Asia/Kabul",
    "iso:country":"AF",
    "name:fas_x_preferred":[
        "\u0646\u064a\u0643\u0648 \u0648\u0644\u0647"
    ],
    "name:und_x_variant":[
        "Nekuvula",
        "N\u0113ko Wola",
        "N\u0113k\u014d Wulah",
        "\u0646\u06d0\u06a9\u0648 \u0648\u0644\u0647",
        "N\u012bk\u016b Wolah"
    ],
    "wof:name":"Neko Wulah",
    "wof:placetype":"locality"
},
  "geometry": {"coordinates":[67.29465,31.61654],"type":"Point"}
}