{
  "type": "Feature",
  "properties": {
    "gn:admin1_code":"28",
    "gn:admin2_code":"2503",
    "gn:asciiname":"Jilah",
    "gn:country_code":"AF",
    "gn:dem":2171,
    "gn:feature_class":"P",
    "gn:feature_code":"PPL",
    "gn:name":"Jilah",
    "gn:population":0,
    "gn:timezone":"Asia/Kabul",
    "iso:country":"AF",
    "name:und_x_variant":[
        "Dzhila",
        "Jila",
        "Jilah",
        "\u062c\u0644\u0647"
    ],
    "wof:name":"Jilah",
    "wof:placetype":"locality"
},
  "geometry": {"coordinates":[67.15835,32.54994],"type":"Point"}
}