{
  "type": "Feature",
  "properties": {
    "gn:admin1_code":"05",
    "gn:admin2_code":"2806",
    "gn:asciiname":"Gird Bayd",
    "gn:country_code":"AF",
    "gn:dem":2783,
    "gn:feature_class":"P",
    "gn:feature_code":"PPL",
    "gn:name":"Gird Bayd",
    "gn:population":0,
    "gn:timezone":"Asia/Kabul",
    "iso:country":"AF",
    "name:und_x_variant":[
        "Ge\u1e5f\u1e0fb\u0113\u1e0f",
        "Girdbed",
        "Gardb\u0113d",
        "Gird Bayd",
        "\u06af\u0631\u062f \u0628\u06cc\u062f"
    ],
    "wof:name":"Gird Bayd",
    "wof:placetype":"locality"
},
  "geometry": {"coordinates":[66.51897,34.18137],"type":"Point"}
}