{
  "type": "Feature",
  "properties": {
    "gn:admin1_code":"3",
    "gn:admin2_code":"1303.0",
    "gn:asciiname":"Barati",
    "gn:country_code":"AF",
    "gn:dem":1653,
    "gn:feature_class":"P",
    "gn:feature_code":"PPL",
    "gn:name":"Barati",
    "gn:population":0,
    "gn:timezone":"Asia/Kabul",
    "iso:country":"AF",
    "name:rus_x_preferred":[
        "\u0411\u0430\u0440\u0430\u0442\u0438"
    ],
    "name:und_x_variant":[
        "Bar\u0101ti",
        "\u0411\u0430\u0440\u0430\u0442\u0438"
    ],
    "wof:name":"Barati",
    "wof:placetype":"locality"
},
  "geometry": {"coordinates":[68.43944,36.00222],"type":"Point"}
}