{
  "type": "Feature",
  "properties": {
    "gn:admin1_code":"09",
    "gn:admin2_code":"2706",
    "gn:asciiname":"Sabagh-e Khasah",
    "gn:country_code":"AF",
    "gn:dem":2477,
    "gn:feature_class":"P",
    "gn:feature_code":"PPL",
    "gn:name":"\u015eab\u0101gh-e Kh\u0101\u015fah",
    "gn:population":0,
    "gn:timezone":"Asia/Kabul",
    "iso:country":"AF",
    "name:und_x_variant":[
        "Saf\u0101b\u0101ghe Kh\u0101sa",
        "Sabb\u0101gh-e Kh\u0101seh",
        "Sab\u0101ghe Kh\u0101sa",
        "\u015eab\u0101gh-e Kh\u0101\u015fah",
        "\u0635\u0628\u0627\u063a \u062e\u0627\u0635\u0647",
        "\u015eaf\u0101 B\u0101gh-e Kh\u0101\u015feh"
    ],
    "wof:name":"Sabagh-e Khasah",
    "wof:placetype":"locality"
},
  "geometry": {"coordinates":[65.04134999999999,33.55260999999999],"type":"Point"}
}