{
  "type": "Feature",
  "properties": {
    "gn:admin1_code":"19",
    "gn:admin2_code":"2204.0",
    "gn:asciiname":"Nazar Khan Dano",
    "gn:country_code":"AF",
    "gn:dem":485,
    "gn:feature_class":"P",
    "gn:feature_code":"PPL",
    "gn:name":"Naz\u0327ar Kh\u0101n Dan\u014d",
    "gn:population":0,
    "gn:timezone":"Asia/Kabul",
    "iso:country":"AF",
    "name:und_x_variant":[
        "Naz\u0327ar Kh\u0101n Dan\u014d",
        "\u0646\u0638\u0631 \u062e\u0627\u0646 \u062f\u0646\u0648",
        "Naz\u0327ar Kh\u0101n Danno"
    ],
    "wof:name":"Nazar Khan Dano",
    "wof:placetype":"locality"
},
  "geometry": {"coordinates":[62.11884000000001,31.2141],"type":"Point"}
}