{
  "type": "Feature",
  "properties": {
    "gn:admin1_code":"19",
    "gn:admin2_code":"2205",
    "gn:asciiname":"Kuchnay Razay",
    "gn:country_code":"AF",
    "gn:dem":562,
    "gn:feature_class":"P",
    "gn:feature_code":"PPL",
    "gn:name":"K\u016bchnay R\u0101\u1e95ay",
    "gn:population":0,
    "gn:timezone":"Asia/Kabul",
    "iso:country":"AF",
    "name:und_x_variant":[
        "R\u0101zan\u012b",
        "Kucnay R\u0101\u1e0f\u1e95ay",
        "Razai",
        "K\u016bchnay R\u0101\u1e95ay",
        "\u06a9\u0648\u0686\u0646\u06cc \u0631\u0627\u0636\u06cc",
        "K\u016bchnay R\u0101\u1e95\u012b"
    ],
    "wof:name":"Kuchnay Razay",
    "wof:placetype":"locality"
},
  "geometry": {"coordinates":[62.69955,31.46404],"type":"Point"}
}