{
  "type": "Feature",
  "properties": {
    "gn:admin1_code":"01",
    "gn:admin2_code":"1116",
    "gn:asciiname":"Hazarah-ye Darah-ye Bagh",
    "gn:country_code":"AF",
    "gn:dem":1806,
    "gn:feature_class":"P",
    "gn:feature_code":"PPL",
    "gn:name":"Haz\u0101rah-ye Darah-ye B\u0101gh",
    "gn:population":0,
    "gn:timezone":"Asia/Kabul",
    "iso:country":"AF",
    "name:und_x_variant":[
        "Haz\u0101\u1e5fa-i-\u1e0ea\u1e5f\u1e5fah-i-B\u0101gh",
        "Haz\u0101reh-ye-Darreh-ye-B\u0101gh",
        "Hez\u0101reh-ye Darreh-ye B\u0101gh",
        "Haz\u0101rah-ye Darah-ye B\u0101gh",
        "\u0647\u0632\u0627\u0631\u06c0 \u062f\u0631\u06c0 \u0628\u0627\u063a"
    ],
    "wof:name":"Hazarah-ye Darah-ye Bagh",
    "wof:placetype":"locality"
},
  "geometry": {"coordinates":[70.40595999999999,36.89062],"type":"Point"}
}