{
  "type": "Feature",
  "properties": {
    "gn:admin1_code":"41",
    "gn:admin2_code":"3408",
    "gn:asciiname":"Tarni",
    "gn:country_code":"AF",
    "gn:dem":2956,
    "gn:feature_class":"P",
    "gn:feature_code":"PPL",
    "gn:name":"Tarn\u012b",
    "gn:population":0,
    "gn:timezone":"Asia/Kabul",
    "iso:country":"AF",
    "name:und_x_variant":[
        "Tarn\u012b",
        "\u062a\u0631\u0646\u06cc"
    ],
    "wof:name":"Tarni",
    "wof:placetype":"locality"
},
  "geometry": {"coordinates":[65.91897,34.21216],"type":"Point"}
}