{
  "type": "Feature",
  "properties": {
    "gn:admin1_code":"39",
    "gn:admin2_code":"2602",
    "gn:asciiname":"Loy Ghoyinah",
    "gn:country_code":"AF",
    "gn:dem":1646,
    "gn:feature_class":"P",
    "gn:feature_code":"PPL",
    "gn:name":"L\u014dy Gh\u014dyinah",
    "gn:population":0,
    "gn:timezone":"Asia/Kabul",
    "iso:country":"AF",
    "name:und_x_variant":[
        "L\u014dy Gh\u014dyena",
        "L\u016by Gh\u016byena",
        "L\u016by Gh\u016byeneh",
        "L\u014dy Gh\u014dyinah",
        "\u0644\u0648\u06cc \u063a\u0648\u06cc\u0646\u0647"
    ],
    "wof:name":"Loy Ghoyinah",
    "wof:placetype":"locality"
},
  "geometry": {"coordinates":[66.14877,33.10842],"type":"Point"}
}