{
  "type": "Feature",
  "properties": {
    "gn:admin1_code":"06",
    "gn:admin2_code":"2104",
    "gn:asciiname":"Qaryah-ye Kishtwaj",
    "gn:country_code":"AF",
    "gn:dem":2010,
    "gn:feature_class":"P",
    "gn:feature_code":"PPL",
    "gn:name":"Qaryah-ye Kishtw\u0101j",
    "gn:population":0,
    "gn:timezone":"Asia/Kabul",
    "iso:country":"AF",
    "name:und_x_variant":[
        "Qa\u1e5fya-i-Kes\u0304tw\u0101j",
        "Qaryeh-ye Keshtw\u0101j",
        "Qaryah-ye Kishtw\u0101j",
        "\u0642\u0631\u06cc\u06c0 \u06a9\u0634\u062a\u0648\u0627\u062c"
    ],
    "wof:name":"Qaryah-ye Kishtwaj",
    "wof:placetype":"locality"
},
  "geometry": {"coordinates":[63.52498000000001,33.32402],"type":"Point"}
}