{
  "type": "Feature",
  "properties": {
    "gn:admin1_code":"8",
    "gn:admin2_code":"608.0",
    "gn:asciiname":"Chinah",
    "gn:country_code":"AF",
    "gn:dem":2317,
    "gn:feature_class":"P",
    "gn:feature_code":"PPL",
    "gn:name":"Ch\u012bnah",
    "gn:population":0,
    "gn:timezone":"Asia/Kabul",
    "iso:country":"AF",
    "name:fas_x_preferred":[
        "\u0686\u064a\u0646\u0647"
    ],
    "name:rus_x_preferred":[
        "\u0427\u0438\u043d\u0430"
    ],
    "name:und_x_variant":[
        "China",
        "\u010cina",
        "Ch\u012bneh",
        "Ch\u012bnah",
        "\u0686\u06cc\u0646\u0647"
    ],
    "wof:name":"Chinah",
    "wof:placetype":"locality"
},
  "geometry": {"coordinates":[67.84875,33.08398],"type":"Point"}
}