{
  "type": "Feature",
  "properties": {
    "gn:admin1_code":"02",
    "gn:admin2_code":"1904",
    "gn:asciiname":"Sabur Khanah",
    "gn:country_code":"AF",
    "gn:dem":1839,
    "gn:feature_class":"P",
    "gn:feature_code":"PPL",
    "gn:name":"\u015eab\u016br Kh\u0101nah",
    "gn:population":0,
    "gn:timezone":"Asia/Kabul",
    "iso:country":"AF",
    "name:und_x_variant":[
        "Sab\u016brkh\u0101na",
        "\u015eab\u016br Kh\u0101nah",
        "\u0635\u0628\u0648\u0631 \u062e\u0627\u0646\u0647",
        "\u015eab\u016br Kh\u0101neh"
    ],
    "wof:name":"Sabur Khanah",
    "wof:placetype":"locality"
},
  "geometry": {"coordinates":[64.02632,34.8231],"type":"Point"}
}