{
  "type": "Feature",
  "properties": {
    "gn:admin1_code":"38",
    "gn:admin2_code":"3004.0",
    "gn:asciiname":"Bala Murghab",
    "gn:country_code":"AF",
    "gn:dem":2390,
    "gn:feature_class":"P",
    "gn:feature_code":"PPL",
    "gn:name":"B\u0101l\u0101 Murgh\u0101b",
    "gn:population":0,
    "gn:timezone":"Asia/Kabul",
    "iso:country":"AF",
    "name:ast_x_preferred":[
        "Bala Murghab"
    ],
    "name:fas_x_preferred":[
        "\u0628\u0627\u0644\u0627 \u0645\u0631\u063a\u0627\u0628"
    ],
    "name:ita_x_preferred":[
        "Murghab"
    ],
    "name:spa_x_preferred":[
        "B\u0101l\u0101 Mor\u0121\u0101b"
    ],
    "name:und_x_variant":[
        "Balamurgab",
        "B\u0101l\u0101mu\u1e5fgh\u0101b",
        "\u0628\u0627\u0644\u0627 \u0645\u0631\u063a\u0627\u0628",
        "B\u0101l\u0101 Morgh\u0101b",
        "B\u0101l\u0101 Murgh\u0101b"
    ],
    "wof:name":"Bala Murghab",
    "wof:placetype":"locality"
},
  "geometry": {"coordinates":[70.14821999999999,35.34734],"type":"Point"}
}