{
  "type": "Feature",
  "properties": {
    "gn:admin1_code":"28",
    "gn:admin2_code":"2506.0",
    "gn:asciiname":"Fateh Khan Kelay",
    "gn:country_code":"AF",
    "gn:dem":1472,
    "gn:feature_class":"P",
    "gn:feature_code":"PPL",
    "gn:name":"Fate\u1e29 Kh\u0101n K\u00ealay",
    "gn:population":0,
    "gn:timezone":"Asia/Kabul",
    "iso:country":"AF",
    "name:und_x_variant":[
        "Fate\u1e29kh\u0101n Kalay",
        "Fatekhkhankalay",
        "Fate\u1e29 Kh\u0101n K\u00ealay",
        "\u0641\u062a\u062d \u062e\u0627\u0646 \u06a9\u0644\u06cc",
        "Fat\u1e29kh\u0101n Kalay"
    ],
    "wof:name":"Fateh Khan Kelay",
    "wof:placetype":"locality"
},
  "geometry": {"coordinates":[66.53664999999999,31.80671],"type":"Point"}
}