{
  "type": "Feature",
  "properties": {
    "gn:admin1_code":"08",
    "gn:admin2_code":"613",
    "gn:asciiname":"Deh Andar",
    "gn:country_code":"AF",
    "gn:dem":2035,
    "gn:feature_class":"P",
    "gn:feature_code":"PPL",
    "gn:name":"Deh Anda\u1e5f",
    "gn:population":0,
    "gn:timezone":"Asia/Kabul",
    "iso:country":"AF",
    "name:fas_x_preferred":[
        "\u062f\u0647\u0654\u0654 \u0627\u0646\u062f\u0631"
    ],
    "name:und_x_variant":[
        "Dekhandar",
        "Deh Andar",
        "Deh Anda\u1e5f",
        "\u062f\u0647 \u0627\u0646\u062f\u0693"
    ],
    "wof:name":"Deh Andar",
    "wof:placetype":"locality"
},
  "geometry": {"coordinates":[68.14118000000001,33.0922],"type":"Point"}
}