{
  "type": "Feature",
  "properties": {
    "gn:admin1_code":"14",
    "gn:admin2_code":"201.0",
    "gn:asciiname":"Khanan Khel",
    "gn:country_code":"AF",
    "gn:dem":1473,
    "gn:feature_class":"P",
    "gn:feature_code":"PPL",
    "gn:name":"Kh\u0101n\u0101n Kh\u0113l",
    "gn:population":0,
    "gn:timezone":"Asia/Kabul",
    "iso:country":"AF",
    "name:fas_x_preferred":[
        "\u062e\u0627\u0646\u0627\u0646 \u062e\u064a\u0644"
    ],
    "name:rus_x_preferred":[
        "Khanankheyl\u2019"
    ],
    "name:und_x_variant":[
        "Kh\u0101n\u0101nkh\u0113l",
        "Kh\u0101n\u0101nkheyl",
        "Kh\u0101n\u0101n Kh\u0113l",
        "\u062e\u0627\u0646\u0627\u0646 \u062e\u06d0\u0644"
    ],
    "wof:name":"Khanan Khel",
    "wof:placetype":"locality"
},
  "geometry": {"coordinates":[69.33781,35.02265],"type":"Point"}
}