{
  "type": "Feature",
  "properties": {
    "gn:admin1_code":"41",
    "gn:admin2_code":"3409.0",
    "gn:asciiname":"Top",
    "gn:country_code":"AF",
    "gn:dem":2160,
    "gn:feature_class":"P",
    "gn:feature_code":"PPL",
    "gn:name":"T\u014dp",
    "gn:population":0,
    "gn:timezone":"Asia/Kabul",
    "iso:country":"AF",
    "name:und_x_variant":[
        "J\u014dp",
        "J\u016bp",
        "T\u014dp",
        "\u062a\u0648\u067e"
    ],
    "wof:name":"Top",
    "wof:placetype":"locality"
},
  "geometry": {"coordinates":[66.70788,33.80398],"type":"Point"}
}