{
  "type": "Feature",
  "properties": {
    "gn:admin1_code":"18",
    "gn:admin2_code":"803.0",
    "gn:asciiname":"Buday Now",
    "gn:country_code":"AF",
    "gn:dem":1835,
    "gn:feature_class":"P",
    "gn:feature_code":"PPL",
    "gn:name":"Bu\u1e0fay Now",
    "gn:population":0,
    "gn:timezone":"Asia/Kabul",
    "iso:country":"AF",
    "name:fas_x_preferred":[
        "\u0628\u062f\u06cc \u0646\u0648"
    ],
    "name:und_x_variant":[
        "Buday-Nau",
        "Boday-naw",
        "Bu\u1e0fa\u012b Naw",
        "Boday Now",
        "Bu\u1e0fay Now",
        "\u0628\u0689\u06cc \u0646\u0648",
        "B\u016b\u1e0fay Now",
        "\u0628\u0648\u0689\u06cc \u0646\u0648"
    ],
    "wof:name":"Buday Now",
    "wof:placetype":"locality"
},
  "geometry": {"coordinates":[69.70817,34.30029],"type":"Point"}
}