{
  "type": "Feature",
  "properties": {
    "gn:admin1_code":"08",
    "gn:admin2_code":"604",
    "gn:asciiname":"Utah Pur",
    "gn:country_code":"AF",
    "gn:dem":3251,
    "gn:feature_class":"P",
    "gn:feature_code":"PPL",
    "gn:name":"\u016atah P\u016br",
    "gn:population":0,
    "gn:timezone":"Asia/Kabul",
    "iso:country":"AF",
    "name:und_x_variant":[
        "\u016atah P\u016br",
        "\u016atap\u016b\u1e5f",
        "Utapur",
        "Owtahp\u016br",
        "\u0627\u0648\u062a\u0647 \u067e\u0648\u0631"
    ],
    "wof:name":"Utah Pur",
    "wof:placetype":"locality"
},
  "geometry": {"coordinates":[67.67114000000001,34.10081],"type":"Point"}
}