{
  "type": "Feature",
  "properties": {
    "gn:admin1_code":"10",
    "gn:admin2_code":"2304",
    "gn:asciiname":"Wasak Kelay",
    "gn:country_code":"AF",
    "gn:dem":1013,
    "gn:feature_class":"P",
    "gn:feature_code":"PPL",
    "gn:name":"Wasak K\u00ealay",
    "gn:population":0,
    "gn:timezone":"Asia/Kabul",
    "iso:country":"AF",
    "name:und_x_variant":[
        "Vasakkili",
        "Wasak K\u00ealay",
        "\u0648\u0633\u06a9 \u06a9\u0644\u06cc",
        "Wasak Keli"
    ],
    "wof:name":"Wasak Kelay",
    "wof:placetype":"locality"
},
  "geometry": {"coordinates":[64.75791,32.36338],"type":"Point"}
}