{
  "type": "Feature",
  "properties": {
    "gn:admin1_code":"23",
    "gn:admin2_code":"2401.0",
    "gn:asciiname":"Baladay",
    "gn:country_code":"AF",
    "gn:dem":986,
    "gn:feature_class":"P",
    "gn:feature_code":"PPL",
    "gn:name":"Baladay",
    "gn:population":0,
    "gn:timezone":"Asia/Kabul",
    "iso:country":"AF",
    "name:und_x_variant":[
        "Baladeh",
        "Balada",
        "Baladay",
        "\u0628\u0644\u062f\u06cc"
    ],
    "wof:name":"Baladay",
    "wof:placetype":"locality"
},
  "geometry": {"coordinates":[65.7184,31.54778],"type":"Point"}
}