{
  "type": "Feature",
  "properties": {
    "gn:admin1_code":"28",
    "gn:admin2_code":"2502",
    "gn:asciiname":"Miran",
    "gn:country_code":"AF",
    "gn:dem":2185,
    "gn:feature_class":"P",
    "gn:feature_code":"PPL",
    "gn:name":"Mir\u0101n",
    "gn:population":0,
    "gn:timezone":"Asia/Kabul",
    "iso:country":"AF",
    "name:und_x_variant":[
        "Mir\u0101n",
        "\u0645\u0631\u0627\u0646",
        "Mer\u0101n"
    ],
    "wof:name":"Miran",
    "wof:placetype":"locality"
},
  "geometry": {"coordinates":[67.38375000000001,32.67743],"type":"Point"}
}