{
  "type": "Feature",
  "properties": {
    "gn:admin1_code":"8",
    "gn:admin2_code":"611.0",
    "gn:asciiname":"Chamri",
    "gn:country_code":"AF",
    "gn:dem":2035,
    "gn:feature_class":"P",
    "gn:feature_code":"PPL",
    "gn:name":"Ch\u0101m\u1e5f\u012b",
    "gn:population":0,
    "gn:timezone":"Asia/Kabul",
    "iso:country":"AF",
    "name:und_x_variant":[
        "\u010camri",
        "\u0686\u0627\u0645\u0693\u06cc",
        "Cham\u1e5f\u012b",
        "Chamr\u012b",
        "\u0686\u0645\u0693\u06cc",
        "Ch\u0101m\u1e5f\u012b"
    ],
    "wof:name":"Chamri",
    "wof:placetype":"locality"
},
  "geometry": {"coordinates":[68.11305,32.82400999999999],"type":"Point"}
}