{
  "type": "Feature",
  "properties": {
    "gn:admin1_code":"28",
    "gn:admin2_code":"2510.0",
    "gn:asciiname":"Chanay",
    "gn:country_code":"AF",
    "gn:dem":2580,
    "gn:feature_class":"P",
    "gn:feature_code":"PPL",
    "gn:name":"Ch\u0101nay",
    "gn:population":0,
    "gn:timezone":"Asia/Kabul",
    "iso:country":"AF",
    "name:ara_x_preferred":[
        "\u0634\u0627\u0646\u0627\u064a"
    ],
    "name:bug_x_preferred":[
        "Chanay"
    ],
    "name:cat_x_preferred":[
        "Chanay"
    ],
    "name:ceb_x_preferred":[
        "Chanay"
    ],
    "name:deu_x_preferred":[
        "Chanay"
    ],
    "name:eus_x_preferred":[
        "Chanay"
    ],
    "name:fas_x_preferred":[
        "\u0634\u0627\u0646\u06cc"
    ],
    "name:fin_x_preferred":[
        "Chanay"
    ],
    "name:fra_x_preferred":[
        "Chanay"
    ],
    "name:glg_x_preferred":[
        "Chanay"
    ],
    "name:hun_x_preferred":[
        "Chanay"
    ],
    "name:hye_x_preferred":[
        "\u0547\u0561\u0576\u0565"
    ],
    "name:ind_x_preferred":[
        "Chanay"
    ],
    "name:ita_x_preferred":[
        "Chanay"
    ],
    "name:lat_x_preferred":[
        "Chanay"
    ],
    "name:lmo_x_preferred":[
        "Chanay"
    ],
    "name:ltz_x_preferred":[
        "Chanay"
    ],
    "name:mlg_x_preferred":[
        "Chanay"
    ],
    "name:msa_x_preferred":[
        "Chanay"
    ],
    "name:nld_x_preferred":[
        "Chanay"
    ],
    "name:oci_x_preferred":[
        "Chanay"
    ],
    "name:pam_x_preferred":[
        "Chanay"
    ],
    "name:pol_x_preferred":[
        "Chanay"
    ],
    "name:por_x_preferred":[
        "Chanay"
    ],
    "name:ron_x_preferred":[
        "Chanay"
    ],
    "name:rus_x_preferred":[
        "\u0428\u0430\u043d\u0435"
    ],
    "name:slk_x_preferred":[
        "Chanay"
    ],
    "name:sme_x_preferred":[
        "Chanay"
    ],
    "name:spa_x_preferred":[
        "Chanay"
    ],
    "name:sqi_x_preferred":[
        "Chanay"
    ],
    "name:srp_x_preferred":[
        "\u0428\u0430\u043d\u0435"
    ],
    "name:swe_x_preferred":[
        "Chanay"
    ],
    "name:tgl_x_preferred":[
        "Chanay"
    ],
    "name:tur_x_preferred":[
        "Chanay"
    ],
    "name:ukr_x_preferred":[
        "\u0428\u0430\u043d\u0435"
    ],
    "name:und_x_variant":[
        "\u010c\u0101nay",
        "Ch\u0101nay",
        "\u0686\u0627\u0646\u06cc"
    ],
    "name:urd_x_preferred":[
        "\u0634\u0627\u0646\u0627\u0626\u06d2"
    ],
    "name:uzb_x_preferred":[
        "Chanay"
    ],
    "name:vie_x_preferred":[
        "Chanay"
    ],
    "name:vol_x_preferred":[
        "Chanay"
    ],
    "name:war_x_preferred":[
        "Chanay"
    ],
    "name:zea_x_preferred":[
        "Chanay"
    ],
    "wof:name":"Chanay",
    "wof:placetype":"locality"
},
  "geometry": {"coordinates":[67.07089999999999,32.81339000000001],"type":"Point"}
}