{
  "type": "Feature",
  "properties": {
    "gn:admin1_code":"28",
    "gn:admin2_code":"2510.0",
    "gn:asciiname":"Chanay",
    "gn:country_code":"AF",
    "gn:dem":2580,
    "gn:feature_class":"P",
    "gn:feature_code":"PPL",
    "gn:name":"Ch\u0101nay",
    "gn:population":0,
    "gn:timezone":"Asia/Kabul",
    "iso:country":"AF",
    "name:und_x_variant":[
        "\u010c\u0101nay",
        "Ch\u0101nay",
        "\u0686\u0627\u0646\u06cc"
    ],
    "wof:name":"Chanay",
    "wof:placetype":"locality"
},
  "geometry": {"coordinates":[67.07089999999999,32.81339000000001],"type":"Point"}
}