{
  "type": "Feature",
  "properties": {
    "gn:admin1_code":"33",
    "gn:admin2_code":"3107",
    "gn:asciiname":"Toli",
    "gn:country_code":"AF",
    "gn:dem":1151,
    "gn:feature_class":"P",
    "gn:feature_code":"PPL",
    "gn:name":"T\u014dl\u012b",
    "gn:population":0,
    "gn:timezone":"Asia/Kabul",
    "iso:country":"AF",
    "name:und_x_variant":[
        "T\u014dli",
        "Towl\u012b",
        "T\u014dl\u012b",
        "\u062a\u0648\u0644\u06cc"
    ],
    "wof:name":"Toli",
    "wof:placetype":"locality"
},
  "geometry": {"coordinates":[66.59300999999999,35.9676],"type":"Point"}
}