{
  "type": "Feature",
  "properties": {
    "gn:admin1_code":"02",
    "gn:admin2_code":"1904",
    "gn:asciiname":"Durqaha",
    "gn:country_code":"AF",
    "gn:dem":1693,
    "gn:feature_class":"P",
    "gn:feature_code":"PPL",
    "gn:name":"Durqah\u0101",
    "gn:population":0,
    "gn:timezone":"Asia/Kabul",
    "iso:country":"AF",
    "name:und_x_variant":[
        "Durqah\u0101",
        "\u062f\u0631\u0642\u0647\u0627",
        "\u1e0eu\u1e5fqah\u0101"
    ],
    "wof:name":"Durqaha",
    "wof:placetype":"locality"
},
  "geometry": {"coordinates":[64.33038000000001,35.15649000000001],"type":"Point"}
}