{
  "type": "Feature",
  "properties": {
    "gn:admin1_code":"41",
    "gn:admin2_code":"3403",
    "gn:asciiname":"Sar Ab",
    "gn:country_code":"AF",
    "gn:dem":2670,
    "gn:feature_class":"P",
    "gn:feature_code":"PPL",
    "gn:name":"Sar \u0100b",
    "gn:population":0,
    "gn:timezone":"Asia/Kabul",
    "iso:country":"AF",
    "name:und_x_variant":[
        "Sarab",
        "Sar \u0100b",
        "Sar\u0101b",
        "\u0633\u0631 \u0622\u0628"
    ],
    "wof:name":"Sar Ab",
    "wof:placetype":"locality"
},
  "geometry": {"coordinates":[66.36833,34.21753],"type":"Point"}
}