{
  "type": "Feature",
  "properties": {
    "gn:admin1_code":"08",
    "gn:admin2_code":"606",
    "gn:asciiname":"Shinyah",
    "gn:country_code":"AF",
    "gn:dem":2977,
    "gn:feature_class":"P",
    "gn:feature_code":"PPL",
    "gn:name":"Sh\u012bnyah",
    "gn:population":0,
    "gn:timezone":"Asia/Kabul",
    "iso:country":"AF",
    "name:und_x_variant":[
        "\u0160enya",
        "Shenya",
        "Shenyah",
        "Sh\u012bnyah",
        "\u0634\u06cc\u0646\u06cc\u0647"
    ],
    "wof:name":"Shinyah",
    "wof:placetype":"locality"
},
  "geometry": {"coordinates":[67.42586,33.37528],"type":"Point"}
}