{
  "type": "Feature",
  "properties": {
    "gn:admin1_code":"23",
    "gn:admin2_code":"2411",
    "gn:asciiname":"Khudaydad Khan Kelay",
    "gn:country_code":"AF",
    "gn:dem":1091,
    "gn:feature_class":"P",
    "gn:feature_code":"PPL",
    "gn:name":"Khud\u0101yd\u0101d Kh\u0101n K\u00ealay",
    "gn:population":0,
    "gn:timezone":"Asia/Kabul",
    "iso:country":"AF",
    "name:fas_x_preferred":[
        "\u0642\u0631\u06cc\u06c0 \u062e\u062f\u0627\u06cc\u062f\u0627\u062f \u062e\u0627\u0646"
    ],
    "name:und_x_variant":[
        "Khod\u0101d\u0101dkh\u0101n Kalay",
        "Khudaydadkhan-Kalay",
        "Khud\u0101yd\u0101d Kh\u0101n K\u00ealay",
        "\u062e\u062f\u0627\u06cc\u062f\u0627\u062f \u062e\u0627\u0646 \u06a9\u0644\u06cc",
        "Khod\u0101yd\u0101dkh\u0101n Kalay"
    ],
    "wof:name":"Khudaydad Khan Kelay",
    "wof:placetype":"locality"
},
  "geometry": {"coordinates":[66.0184,31.11916],"type":"Point"}
}