{
  "type": "Feature",
  "properties": {
    "gn:admin1_code":"28",
    "gn:admin2_code":"2506.0",
    "gn:asciiname":"Kalachah",
    "gn:country_code":"AF",
    "gn:dem":1320,
    "gn:feature_class":"P",
    "gn:feature_code":"PPL",
    "gn:name":"Kal\u0101chah",
    "gn:population":0,
    "gn:timezone":"Asia/Kabul",
    "iso:country":"AF",
    "name:und_x_variant":[
        "Kal\u0101cha",
        "Kal\u0101\u010da",
        "Kalacha",
        "\u06a9\u0644\u0627\u0686\u0647",
        "Kal\u0101cheh",
        "Kal\u0101chah"
    ],
    "wof:name":"Kalachah",
    "wof:placetype":"locality"
},
  "geometry": {"coordinates":[66.35274,31.84361],"type":"Point"}
}