{
  "type": "Feature",
  "properties": {
    "gn:admin1_code":"08",
    "gn:admin2_code":"602",
    "gn:asciiname":"Khwajah Qol",
    "gn:country_code":"AF",
    "gn:dem":2888,
    "gn:feature_class":"P",
    "gn:feature_code":"PPL",
    "gn:name":"Khw\u0101jah Q\u014dl",
    "gn:population":0,
    "gn:timezone":"Asia/Kabul",
    "iso:country":"AF",
    "name:rus_x_preferred":[
        "\u0425\u043e\u0434\u0436\u0430\u043a\u0443\u043b\u044c"
    ],
    "name:und_x_variant":[
        "Kh\u014djaq\u014dl",
        "Khowjehqowl",
        "Khodzhakul\u2019",
        "Khv\u0101jehqowl",
        "Khw\u0101jah Q\u014dl",
        "\u062e\u0648\u0627\u062c\u0647 \u0642\u0648\u0644"
    ],
    "wof:name":"Khwajah Qol",
    "wof:placetype":"locality"
},
  "geometry": {"coordinates":[67.96569000000001,33.53496],"type":"Point"}
}