{
  "type": "Feature",
  "properties": {
    "gn:admin1_code":"41",
    "gn:admin2_code":"3409.0",
    "gn:asciiname":"Qal'ah-ye Khaybar",
    "gn:country_code":"AF",
    "gn:dem":1904,
    "gn:feature_class":"P",
    "gn:feature_code":"PPL",
    "gn:name":"Qal\u2018ah-ye Khaybar",
    "gn:population":0,
    "gn:timezone":"Asia/Kabul",
    "iso:country":"AF",
    "name:und_x_variant":[
        "Qal\u2018a-i Khayba\u1e5f",
        "Qal\u2018eh-ye Kheybar",
        "Qal\u2018ah-ye Khaybar",
        "\u0642\u0644\u0639\u06c0 \u062e\u06cc\u0628\u0631"
    ],
    "wof:name":"Qal'ah-ye Khaybar",
    "wof:placetype":"locality"
},
  "geometry": {"coordinates":[66.64220999999999,33.68127],"type":"Point"}
}