{
  "type": "Feature",
  "properties": {
    "gn:admin1_code":"08",
    "gn:admin2_code":"601",
    "gn:asciiname":"Rowzah",
    "gn:country_code":"AF",
    "gn:dem":2282,
    "gn:feature_class":"P",
    "gn:feature_code":"PPL",
    "gn:name":"Row\u1e95ah",
    "gn:population":0,
    "gn:timezone":"Asia/Kabul",
    "iso:country":"AF",
    "name:fas_x_preferred":[
        "\u0631\u0648\u0636\u0647"
    ],
    "name:und_x_variant":[
        "\u1e5eaw\u1e0f\u1e95a",
        "Rauza",
        "Row\u1e95ah",
        "Row\u1e95eh"
    ],
    "wof:name":"Rowzah",
    "wof:placetype":"locality"
},
  "geometry": {"coordinates":[68.45321,33.58362],"type":"Point"}
}