{
  "type": "Feature",
  "properties": {
    "gn:admin1_code":"24",
    "gn:admin2_code":"1402.0",
    "gn:asciiname":"Aftab Lagh",
    "gn:country_code":"AF",
    "gn:dem":377,
    "gn:feature_class":"P",
    "gn:feature_code":"PPL",
    "gn:name":"\u0100ft\u0101b Lagh",
    "gn:population":0,
    "gn:timezone":"Asia/Kabul",
    "iso:country":"AF",
    "name:und_x_variant":[
        "\u0100ft\u0101b Lagh",
        "\u0622\u0641\u062a\u0627\u0628 \u0644\u063a",
        "\u0100ttab Lagh"
    ],
    "wof:name":"Aftab Lagh",
    "wof:placetype":"locality"
},
  "geometry": {"coordinates":[69.08136,37.17009],"type":"Point"}
}