{
  "type": "Feature",
  "properties": {
    "gn:admin1_code":"27",
    "gn:admin2_code":"404",
    "gn:asciiname":"Dewal",
    "gn:country_code":"AF",
    "gn:dem":3000,
    "gn:feature_class":"P",
    "gn:feature_code":"PPL",
    "gn:name":"D\u0113w\u0101l",
    "gn:population":0,
    "gn:timezone":"Asia/Kabul",
    "iso:country":"AF",
    "name:fas_x_preferred":[
        "\u062f\u06cc\u0648\u0644"
    ],
    "name:rus_x_preferred":[
        "Deval\u2019"
    ],
    "name:und_x_variant":[
        "\u1e0e\u0113w\u0101l",
        "D\u012bv\u0101l",
        "Dayw\u0101l",
        "D\u012bv\u0101r",
        "D\u0113w\u0101l",
        "\u062f\u06d0\u0648\u0627\u0644"
    ],
    "wof:name":"Dewal",
    "wof:placetype":"locality"
},
  "geometry": {"coordinates":[67.60315,34.3891],"type":"Point"}
}