{
  "type": "Feature",
  "properties": {
    "gn:admin1_code":"36",
    "gn:admin2_code":"702",
    "gn:asciiname":"Zafar Khel",
    "gn:country_code":"AF",
    "gn:dem":2186,
    "gn:feature_class":"P",
    "gn:feature_code":"PPL",
    "gn:name":"Z\u0327afar Kh\u0113l",
    "gn:population":0,
    "gn:timezone":"Asia/Kabul",
    "iso:country":"AF",
    "name:fas_x_preferred":[
        "\u0638\u0641\u0631 \u062e\u064a\u0644"
    ],
    "name:rus_x_preferred":[
        "Zafarkheyl\u2019"
    ],
    "name:und_x_variant":[
        "\u1e94afa\u1e5fkh\u0113l",
        "Z\u0327afar Kheyl",
        "Z\u0327afar Kh\u0113l",
        "\u0638\u0641\u0631 \u062e\u06d0\u0644"
    ],
    "wof:name":"Zafar Khel",
    "wof:placetype":"locality"
},
  "geometry": {"coordinates":[69.10264000000001,33.46151],"type":"Point"}
}