{
  "type": "Feature",
  "properties": {
    "gn:admin1_code":"09",
    "gn:admin2_code":"2703",
    "gn:asciiname":"Jarah Gak",
    "gn:country_code":"AF",
    "gn:dem":2450,
    "gn:feature_class":"P",
    "gn:feature_code":"PPL",
    "gn:name":"Jarah Gak",
    "gn:population":0,
    "gn:timezone":"Asia/Kabul",
    "iso:country":"AF",
    "name:und_x_variant":[
        "\u062c\u0631\u0647 \u06af\u06a9",
        "Ja\u1e5fagak"
    ],
    "wof:name":"Jarah Gak",
    "wof:placetype":"locality"
},
  "geometry": {"coordinates":[63.90658000000001,33.93611],"type":"Point"}
}