{
  "type": "Feature",
  "properties": {
    "gn:admin1_code":"07",
    "gn:admin2_code":"1804",
    "gn:asciiname":"Khwajah Puchaqli",
    "gn:country_code":"AF",
    "gn:dem":1258,
    "gn:feature_class":"P",
    "gn:feature_code":"PPL",
    "gn:name":"Khw\u0101jah P\u016bch\u0101ql\u012b",
    "gn:population":0,
    "gn:timezone":"Asia/Kabul",
    "iso:country":"AF",
    "name:und_x_variant":[
        "Khw\u0101ja P\u016b\u010d\u0101qli (1)",
        "Khw\u0101ja P\u016bc\u0101ql\u012b",
        "Khv\u0101jeh P\u016bch\u0101ql\u012b",
        "Khw\u0101jah P\u016bch\u0101ql\u012b",
        "\u062e\u0648\u0627\u062c\u0647 \u067e\u0648\u0686\u0627\u0642\u0644\u06cc"
    ],
    "wof:name":"Khwajah Puchaqli",
    "wof:placetype":"locality"
},
  "geometry": {"coordinates":[64.53623,35.65130999999999],"type":"Point"}
}