{
  "type": "Feature",
  "properties": {
    "gn:admin1_code":"23",
    "gn:admin2_code":"2407",
    "gn:asciiname":"Shahrak",
    "gn:country_code":"AF",
    "gn:dem":963,
    "gn:feature_class":"P",
    "gn:feature_code":"PPL",
    "gn:name":"Sh\u0101hrak",
    "gn:population":0,
    "gn:timezone":"Asia/Kabul",
    "iso:country":"AF",
    "name:msa_x_preferred":[
        "Shahrak"
    ],
    "name:rus_x_preferred":[
        "\u0428\u0430\u0445\u0440\u0430\u043a"
    ],
    "name:tgk_x_preferred":[
        "\u04b6\u0430\u043c\u043e\u0430\u0442\u0438 \u0428\u0430\u04b3\u0440\u0430\u043a"
    ],
    "name:und_x_variant":[
        "\u0160\u0101hrak",
        "Shakhrak",
        "Sh\u0101hrak",
        "\u0634\u0627\u0647\u0631\u06a9"
    ],
    "name:urd_x_preferred":[
        "\u0634\u0627\u06c1\u0631\u06a9"
    ],
    "wof:name":"Shahrak",
    "wof:placetype":"locality"
},
  "geometry": {"coordinates":[64.87559,31.8075],"type":"Point"}
}