{
  "type": "Feature",
  "properties": {
    "gn:admin1_code":"30",
    "gn:admin2_code":"1609.0",
    "gn:asciiname":"Baba 'Iwaz",
    "gn:country_code":"AF",
    "gn:dem":585,
    "gn:feature_class":"P",
    "gn:feature_code":"PPL",
    "gn:name":"B\u0101b\u0101 \u2018Iwa\u1e95",
    "gn:population":0,
    "gn:timezone":"Asia/Kabul",
    "iso:country":"AF",
    "name:und_x_variant":[
        "B\u0101b\u0101 \u2018Iwa\u1e95",
        "\u0628\u0627\u0628\u0627 \u0639\u0648\u0636",
        "B\u0101b\u0101 Ewaz"
    ],
    "wof:name":"Baba 'Iwaz",
    "wof:placetype":"locality"
},
  "geometry": {"coordinates":[66.87305000000001,36.35967],"type":"Point"}
}