{
  "type": "Feature",
  "properties": {
    "gn:admin1_code":"29",
    "gn:admin2_code":"2902",
    "gn:asciiname":"Satak",
    "gn:country_code":"AF",
    "gn:dem":2172,
    "gn:feature_class":"P",
    "gn:feature_code":"PPL",
    "gn:name":"Satak",
    "gn:population":0,
    "gn:timezone":"Asia/Kabul",
    "iso:country":"AF",
    "name:und_x_variant":[
        "\u0633\u062a\u06a9",
        "Satak"
    ],
    "wof:name":"Satak",
    "wof:placetype":"locality"
},
  "geometry": {"coordinates":[68.50289000000001,32.92214],"type":"Point"}
}