{
  "type": "Feature",
  "properties": {
    "gn:admin1_code":"8",
    "gn:admin2_code":"614.0",
    "gn:asciiname":"Rahim Khel",
    "gn:country_code":"AF",
    "gn:dem":2080,
    "gn:feature_class":"P",
    "gn:feature_code":"PPL",
    "gn:name":"Ra\u1e29\u012bm Kh\u0113l",
    "gn:population":0,
    "gn:timezone":"Asia/Kabul",
    "iso:country":"AF",
    "name:rus_x_preferred":[
        "N\u2019yazi"
    ],
    "name:rus_x_variant":[
        "Rakhimkheyl\u2019"
    ],
    "name:und_x_variant":[
        "Ny\u0101zi",
        "\u1e5eah\u012bmkh\u0113l",
        "Rah\u1e29\u012bm Kheyl",
        "Ra\u1e29\u012bm Kh\u0113l",
        "\u0631\u062d\u06cc\u0645 \u062e\u06d0\u0644",
        "Niy\u0101z\u012b",
        "\u0646\u06cc\u0627\u0632\u06cc"
    ],
    "wof:name":"Rahim Khel",
    "wof:placetype":"locality"
},
  "geometry": {"coordinates":[68.5549,33.32548],"type":"Point"}
}