{
  "type": "Feature",
  "properties": {
    "gn:admin1_code":"29",
    "gn:admin2_code":"2904",
    "gn:asciiname":"Khutkandi",
    "gn:country_code":"AF",
    "gn:dem":2212,
    "gn:feature_class":"P",
    "gn:feature_code":"PPL",
    "gn:name":"Khu\u1e6fkand\u012b",
    "gn:population":0,
    "gn:timezone":"Asia/Kabul",
    "iso:country":"AF",
    "name:und_x_variant":[
        "\u062e\u067c\u06a9\u0646\u062f\u06cc",
        "Khutkandi",
        "Khu\u1e6fkand\u012b"
    ],
    "wof:name":"Khutkandi",
    "wof:placetype":"locality"
},
  "geometry": {"coordinates":[68.31863,32.37654000000001],"type":"Point"}
}