{
  "type": "Feature",
  "properties": {
    "gn:admin1_code":"29",
    "gn:admin2_code":"2906.0",
    "gn:asciiname":"Vraza",
    "gn:country_code":"AF",
    "gn:dem":1794,
    "gn:feature_class":"P",
    "gn:feature_code":"PPL",
    "gn:name":"Vraza",
    "gn:population":0,
    "gn:timezone":"Asia/Kabul",
    "iso:country":"AF",
    "name:fas_x_preferred":[
        "\u0648\u0631\u0627\u0698\u0647"
    ],
    "name:und_x_variant":[
        "Wr\u0101\u017eeh",
        "Vraza",
        "\u0648\u0631\u0627\u0696\u0647",
        "Wr\u0101z\u0332h\u0332eh",
        "Wr\u0101z\u0332h\u0332\u00eah"
    ],
    "wof:name":"Vraza",
    "wof:placetype":"locality"
},
  "geometry": {"coordinates":[68.99446,32.15036],"type":"Point"}
}