{
  "type": "Feature",
  "properties": {
    "gn:admin1_code":"41",
    "gn:admin2_code":"3405",
    "gn:asciiname":"Marghah",
    "gn:country_code":"AF",
    "gn:dem":2143,
    "gn:feature_class":"P",
    "gn:feature_code":"PPL",
    "gn:name":"Marghah",
    "gn:population":0,
    "gn:timezone":"Asia/Kabul",
    "iso:country":"AF",
    "name:und_x_variant":[
        "Ma\u1e5fgha",
        "Marghah",
        "\u0645\u0631\u063a\u0647"
    ],
    "wof:name":"Marghah",
    "wof:placetype":"locality"
},
  "geometry": {"coordinates":[65.55356,33.81394],"type":"Point"}
}