{
  "type": "Feature",
  "properties": {
    "gn:admin1_code":"29",
    "gn:admin2_code":"2909",
    "gn:asciiname":"Khan Shirin",
    "gn:country_code":"AF",
    "gn:dem":2177,
    "gn:feature_class":"P",
    "gn:feature_code":"PPL",
    "gn:name":"Kh\u0101n Sh\u012br\u012bn",
    "gn:population":0,
    "gn:timezone":"Asia/Kabul",
    "iso:country":"AF",
    "name:und_x_variant":[
        "Kh\u0101n\u0161er\u012bn",
        "Khanishrin",
        "Kh\u0101n Sh\u012br\u012bn",
        "Kh\u0101nsh\u012br\u012bn",
        "\u062e\u0627\u0646 \u0634\u06cc\u0631\u06cc\u0646"
    ],
    "wof:name":"Khan Shirin",
    "wof:placetype":"locality"
},
  "geometry": {"coordinates":[69.25664,32.5485],"type":"Point"}
}