{
  "type": "Feature",
  "properties": {
    "gn:admin1_code":"09",
    "gn:admin2_code":"2701",
    "gn:asciiname":"Katalak",
    "gn:country_code":"AF",
    "gn:dem":2318,
    "gn:feature_class":"P",
    "gn:feature_code":"PPL",
    "gn:name":"Katalak",
    "gn:population":0,
    "gn:timezone":"Asia/Kabul",
    "iso:country":"AF",
    "name:und_x_variant":[
        "\u06a9\u062a\u0644\u06a9"
    ],
    "wof:name":"Katalak",
    "wof:placetype":"locality"
},
  "geometry": {"coordinates":[64.64180999999999,34.63394],"type":"Point"}
}