{
  "type": "Feature",
  "properties": {
    "gn:admin1_code":"34",
    "gn:admin2_code":"1015.0",
    "gn:asciiname":"Nangeh Sar",
    "gn:country_code":"AF",
    "gn:dem":1044,
    "gn:feature_class":"P",
    "gn:feature_code":"PPL",
    "gn:name":"N\u0101ng\u00eah Sar",
    "gn:population":0,
    "gn:timezone":"Asia/Kabul",
    "iso:country":"AF",
    "name:und_x_variant":[
        "N\u0101ng\u00eah Sar",
        "\u0646\u0627\u0646\u06af\u0647 \u0633\u0631",
        "N\u0101ngah Sar"
    ],
    "wof:name":"Nangeh Sar",
    "wof:placetype":"locality"
},
  "geometry": {"coordinates":[71.06688,34.69748],"type":"Point"}
}