{
  "type": "Feature",
  "properties": {
    "gn:admin1_code":"37",
    "gn:admin2_code":"3207.0",
    "gn:asciiname":"Shobi Kala",
    "gn:country_code":"AF",
    "gn:dem":1078,
    "gn:feature_class":"P",
    "gn:feature_code":"PPL",
    "gn:name":"Sh\u014db\u012b Kal\u0101",
    "gn:population":0,
    "gn:timezone":"Asia/Kabul",
    "iso:country":"AF",
    "name:fas_x_preferred":[
        "\u0642\u0644\u0639\u0647\u0654 \u0634\u0648\u0628\u06cc"
    ],
    "name:und_x_variant":[
        "\u0160obi Kal\u0101",
        "Shobikala",
        "Sho\u2018b\u012b Kal\u0101",
        "Showb\u012b Kal\u0101",
        "Sh\u014db\u012b Kal\u0101",
        "\u0634\u0648\u0628\u06cc \u06a9\u0644\u0627"
    ],
    "wof:name":"Shobi Kala",
    "wof:placetype":"locality"
},
  "geometry": {"coordinates":[70.08213000000001,33.45367],"type":"Point"}
}