{
  "type": "Feature",
  "properties": {
    "gn:admin1_code":"40",
    "gn:admin2_code":"306.0",
    "gn:asciiname":"Dahan-e 'Aruq",
    "gn:country_code":"AF",
    "gn:dem":2400,
    "gn:feature_class":"P",
    "gn:feature_code":"PPL",
    "gn:name":"Dahan-e \u2018Aruq",
    "gn:population":0,
    "gn:timezone":"Asia/Kabul",
    "iso:country":"AF",
    "name:und_x_variant":[
        "Dakhani-Aruk",
        "\u1e0eahane \u2018A\u1e5fuq",
        "Dahan-e \u2018Aroq",
        "Dahan-e \u2018Aruq",
        "\u062f\u0647\u0646 \u063a\u0631\u0642"
    ],
    "wof:name":"Dahan-e 'Aruq",
    "wof:placetype":"locality"
},
  "geometry": {"coordinates":[68.47797,34.90689],"type":"Point"}
}