{
  "type": "Feature",
  "properties": {
    "gn:admin1_code":"41",
    "gn:admin2_code":"3408.0",
    "gn:asciiname":"Rah Naw-e Kiligan",
    "gn:country_code":"AF",
    "gn:dem":2753,
    "gn:feature_class":"P",
    "gn:feature_code":"PPL",
    "gn:name":"R\u0101h N\u0101w-e Kilig\u0101n",
    "gn:population":0,
    "gn:timezone":"Asia/Kabul",
    "iso:country":"AF",
    "name:und_x_variant":[
        "Ranave Kiligan",
        "R\u0101h N\u0101w-e Kelig\u0101n",
        "R\u0101n\u0101w-e Kelig\u0101n",
        "R\u0101h N\u0101w-e Kilig\u0101n",
        "\u0631\u0627\u0647 \u0646\u0627\u0648 \u06a9\u0644\u06af\u0627\u0646"
    ],
    "wof:name":"Rah Naw-e Kiligan",
    "wof:placetype":"locality"
},
  "geometry": {"coordinates":[66.2732,34.24395999999999],"type":"Point"}
}