{
  "type": "Feature",
  "properties": {
    "gn:admin1_code":"08",
    "gn:admin2_code":"606",
    "gn:asciiname":"Nayk",
    "gn:country_code":"AF",
    "gn:dem":2762,
    "gn:feature_class":"P",
    "gn:feature_code":"PPL",
    "gn:name":"Nayk",
    "gn:population":0,
    "gn:timezone":"Asia/Kabul",
    "iso:country":"AF",
    "name:und_x_variant":[
        "\u0646\u06cc\u06a9",
        "Nayak"
    ],
    "wof:name":"Nayk",
    "wof:placetype":"locality"
},
  "geometry": {"coordinates":[67.45954,33.3144],"type":"Point"}
}