{
  "type": "Feature",
  "properties": {
    "gn:admin1_code":"30",
    "gn:admin2_code":"1606",
    "gn:asciiname":"Mishak",
    "gn:country_code":"AF",
    "gn:dem":335,
    "gn:feature_class":"P",
    "gn:feature_code":"PPL",
    "gn:name":"M\u012bshak",
    "gn:population":0,
    "gn:timezone":"Asia/Kabul",
    "iso:country":"AF",
    "name:fas_x_preferred":[
        "\u0645\u064a\u0634\u06a9"
    ],
    "name:rus_x_preferred":[
        "\u041c\u044b\u0448\u0430\u043a"
    ],
    "name:und_x_variant":[
        "Myshak",
        "M\u012bshak",
        "Mishak",
        "\u0645\u0634\u06a9"
    ],
    "wof:name":"Mishak",
    "wof:placetype":"locality"
},
  "geometry": {"coordinates":[66.88030999999999,36.81317],"type":"Point"}
}