{
  "type": "Feature",
  "properties": {
    "gn:admin1_code":"01",
    "gn:admin2_code":"1119.0",
    "gn:asciiname":"Pas-e Nang",
    "gn:country_code":"AF",
    "gn:dem":2742,
    "gn:feature_class":"P",
    "gn:feature_code":"PPL",
    "gn:name":"Pas-e Nang",
    "gn:population":0,
    "gn:timezone":"Asia/Kabul",
    "iso:country":"AF",
    "name:und_x_variant":[
        "Pas-i-Nang",
        "Pas-e Nang",
        "\u067e\u0633 \u0646\u0646\u06af"
    ],
    "wof:name":"Pas-e Nang",
    "wof:placetype":"locality"
},
  "geometry": {"coordinates":[70.63989000000002,37.38905],"type":"Point"}
}