{
  "type": "Feature",
  "properties": {
    "gn:admin1_code":"28",
    "gn:admin2_code":"2506",
    "gn:asciiname":"Nazargul Kelay",
    "gn:country_code":"AF",
    "gn:dem":1304,
    "gn:feature_class":"P",
    "gn:feature_code":"PPL",
    "gn:name":"Naz\u0327argul K\u00ealay",
    "gn:population":0,
    "gn:timezone":"Asia/Kabul",
    "iso:country":"AF",
    "name:rus_x_preferred":[
        "Nazarkul\u2019kalay"
    ],
    "name:und_x_variant":[
        "Na\u1e95a\u1e5fgul Kalay",
        "\u0646\u0638\u0631\u06af\u0644 \u06a9\u0644\u06cc",
        "Naz\u0327argol Kalay",
        "Naz\u0327argul K\u00ealay"
    ],
    "wof:name":"Nazargul Kelay",
    "wof:placetype":"locality"
},
  "geometry": {"coordinates":[66.33974000000001,31.83674],"type":"Point"}
}