{
  "type": "Feature",
  "properties": {
    "gn:admin1_code":"03",
    "gn:admin2_code":"1307",
    "gn:asciiname":"Sher Qolak",
    "gn:country_code":"AF",
    "gn:dem":1711,
    "gn:feature_class":"P",
    "gn:feature_code":"PPL",
    "gn:name":"Sh\u0113r Q\u014dlak",
    "gn:population":0,
    "gn:timezone":"Asia/Kabul",
    "iso:country":"AF",
    "name:und_x_variant":[
        "\u0160\u0113rqolak",
        "Sh\u0113rq\u014dlak",
        "Sherkulak",
        "Sh\u012br Qowlak",
        "Shayr Q\u014dlak",
        "\u0634\u06cc\u0631 \u0642\u0648\u0644\u06a9",
        "Sh\u0113r Q\u014dlak"
    ],
    "wof:name":"Sher Qolak",
    "wof:placetype":"locality"
},
  "geometry": {"coordinates":[68.97306999999999,35.77557],"type":"Point"}
}