{
  "type": "Feature",
  "properties": {
    "gn:admin1_code":"38",
    "gn:admin2_code":"3004",
    "gn:asciiname":"Linar",
    "gn:country_code":"AF",
    "gn:dem":2378,
    "gn:feature_class":"P",
    "gn:feature_code":"PPL",
    "gn:name":"Linar",
    "gn:population":0,
    "gn:timezone":"Asia/Kabul",
    "iso:country":"AF",
    "name:und_x_variant":[
        "Lin\u0101r",
        "\u0644\u0646\u0631",
        "Linar"
    ],
    "wof:name":"Linar",
    "wof:placetype":"locality"
},
  "geometry": {"coordinates":[70.14348000000001,35.35597999999999],"type":"Point"}
}