{
  "type": "Feature",
  "properties": {
    "gn:admin1_code":"05",
    "gn:admin2_code":"2804",
    "gn:asciiname":"Ziarat",
    "gn:country_code":"AF",
    "gn:dem":3001,
    "gn:feature_class":"P",
    "gn:feature_code":"PPL",
    "gn:name":"Z\u012b\u0101rat",
    "gn:population":0,
    "gn:timezone":"Asia/Kabul",
    "iso:country":"AF",
    "name:ben_x_preferred":[
        "\u099c\u09bf\u09af\u09bc\u09be\u09b0\u09a4"
    ],
    "name:ceb_x_preferred":[
        "Zi\u0101rat"
    ],
    "name:fas_x_preferred":[
        "\u0632\u064a\u0627\u0631\u062a"
    ],
    "name:fas_x_variant":[
        "\u0632\u06cc\u0627\u0631\u062a"
    ],
    "name:fra_x_preferred":[
        "Ziarat"
    ],
    "name:ind_x_preferred":[
        "Ziarat"
    ],
    "name:ita_x_preferred":[
        "Ziarat"
    ],
    "name:msa_x_preferred":[
        "Ziarat"
    ],
    "name:pnb_x_preferred":[
        "\u062a\u0635\u06cc\u0644 \u0632\u06cc\u0627\u0631\u062a"
    ],
    "name:rus_x_preferred":[
        "\u0417\u0438\u0430\u0440\u0430\u0442"
    ],
    "name:spa_x_preferred":[
        "Ziarat"
    ],
    "name:swe_x_preferred":[
        "Ziarat"
    ],
    "name:und_x_variant":[
        "Zy\u0101\u1e5fat",
        "Ziarat",
        "Z\u012b\u0101rat"
    ],
    "name:urd_x_preferred":[
        "\u0632\u06cc\u0627\u0631\u062a"
    ],
    "wof:name":"Ziarat",
    "wof:placetype":"locality"
},
  "geometry": {"coordinates":[67.09697,34.64323],"type":"Point"}
}