{
  "type": "Feature",
  "properties": {
    "gn:admin1_code":"05",
    "gn:admin2_code":"2804",
    "gn:asciiname":"Ziarat",
    "gn:country_code":"AF",
    "gn:dem":3001,
    "gn:feature_class":"P",
    "gn:feature_code":"PPL",
    "gn:name":"Z\u012b\u0101rat",
    "gn:population":0,
    "gn:timezone":"Asia/Kabul",
    "iso:country":"AF",
    "name:fas_x_preferred":[
        "\u0632\u064a\u0627\u0631\u062a"
    ],
    "name:und_x_variant":[
        "Zy\u0101\u1e5fat",
        "Ziarat",
        "Z\u012b\u0101rat"
    ],
    "wof:name":"Ziarat",
    "wof:placetype":"locality"
},
  "geometry": {"coordinates":[67.09697,34.64323],"type":"Point"}
}