{
  "type": "Feature",
  "properties": {
    "gn:admin1_code":"40",
    "gn:admin2_code":"307",
    "gn:asciiname":"Sar-e Ghujur",
    "gn:country_code":"AF",
    "gn:dem":2886,
    "gn:feature_class":"P",
    "gn:feature_code":"PPL",
    "gn:name":"Sar-e Ghuj\u016br",
    "gn:population":0,
    "gn:timezone":"Asia/Kabul",
    "iso:country":"AF",
    "name:und_x_variant":[
        "Sa\u1e5fe Ghoj\u016b\u1e5f",
        "Sar-e Ghowj\u016br",
        "Sari-Gudzhur",
        "Sar-e Ghujowr",
        "Sar-e Ghoj\u016br",
        "Sar-e Ghuj\u016br",
        "\u0633\u0631 \u063a\u062c\u0648\u0631"
    ],
    "wof:name":"Sar-e Ghujur",
    "wof:placetype":"locality"
},
  "geometry": {"coordinates":[68.3276,34.74753],"type":"Point"}
}