{
  "type": "Feature",
  "properties": {
    "gn:admin1_code":"13",
    "gn:admin2_code":"107",
    "gn:asciiname":"Qal'ah-ye Intifat",
    "gn:country_code":"AF",
    "gn:dem":1753,
    "gn:feature_class":"P",
    "gn:feature_code":"PPL",
    "gn:name":"Qal\u2018ah-ye Intif\u0101t",
    "gn:population":0,
    "gn:timezone":"Asia/Kabul",
    "iso:country":"AF",
    "name:fas_x_preferred":[
        "\u0642\u0644\u0639\u06c0 \u0627\u0646\u062a\u0641\u0627\u0626\u06cc"
    ],
    "name:und_x_variant":[
        "Kalayi-Intifat",
        "Qal\u0101-i-Entef\u0101t",
        "Qal\u0101-ye Entef\u0101\u2019\u012b",
        "Qal\u0101-i-Entef\u0101i",
        "Qal\u2018ah-ye Intif\u0101\u2019\u0101t",
        "Qal\u2018eh-ye Entef\u0101\u2019\u012b",
        "Qal\u2018ah-ye Intif\u0101t",
        "\u0642\u0644\u0639\u06c0 \u0627\u0646\u062a\u0641\u0627\u062a"
    ],
    "wof:name":"Qal'ah-ye Intifat",
    "wof:placetype":"locality"
},
  "geometry": {"coordinates":[69.15733,34.68190999999999],"type":"Point"}
}