{
  "type": "Feature",
  "properties": {
    "gn:admin1_code":"13",
    "gn:admin2_code":"102",
    "gn:asciiname":"Joybar",
    "gn:country_code":"AF",
    "gn:dem":1677,
    "gn:feature_class":"P",
    "gn:feature_code":"PPL",
    "gn:name":"J\u014dyb\u0101r",
    "gn:population":0,
    "gn:timezone":"Asia/Kabul",
    "iso:country":"AF",
    "name:und_x_variant":[
        "Dzhoybar",
        "J\u014dyb\u0101\u1e5f",
        "J\u016byb\u0101r",
        "\u062c\u0648\u06cc\u0628\u0627\u0631",
        "J\u014dyb\u0101r"
    ],
    "wof:name":"Joybar",
    "wof:placetype":"locality"
},
  "geometry": {"coordinates":[69.22235000000001,34.70453],"type":"Point"}
}