{
  "type": "Feature",
  "properties": {
    "gn:admin1_code":"09",
    "gn:admin2_code":"2704",
    "gn:asciiname":"Jilan",
    "gn:country_code":"AF",
    "gn:dem":2151,
    "gn:feature_class":"P",
    "gn:feature_code":"PPL",
    "gn:name":"J\u012bl\u0101n",
    "gn:population":0,
    "gn:timezone":"Asia/Kabul",
    "iso:country":"AF",
    "name:und_x_variant":[
        "J\u012bl\u0101n",
        "\u062c\u06cc\u0644\u0627\u0646"
    ],
    "wof:name":"Jilan",
    "wof:placetype":"locality"
},
  "geometry": {"coordinates":[63.7316,33.43275999999999],"type":"Point"}
}