{
  "type": "Feature",
  "properties": {
    "gn:admin1_code":"33",
    "gn:admin2_code":"3106",
    "gn:asciiname":"Qiz-Qal'ah",
    "gn:country_code":"AF",
    "gn:dem":1579,
    "gn:feature_class":"P",
    "gn:feature_code":"PPL",
    "gn:name":"Qiz-Qal\u2018ah",
    "gn:population":0,
    "gn:timezone":"Asia/Kabul",
    "iso:country":"AF",
    "name:und_x_variant":[
        "Qez-Qala",
        "Qez Qal\u2018eh",
        "Qiz-Qal\u2018ah",
        "\u0642\u0632 \u0642\u0644\u0639\u0647"
    ],
    "wof:name":"Qiz-Qal'ah",
    "wof:placetype":"locality"
},
  "geometry": {"coordinates":[65.62534000000001,36.01102],"type":"Point"}
}