{
  "type": "Feature",
  "properties": {
    "gn:admin1_code":"10",
    "gn:admin2_code":"2305.0",
    "gn:asciiname":"Asmanian",
    "gn:country_code":"AF",
    "gn:dem":1561,
    "gn:feature_class":"P",
    "gn:feature_code":"PPL",
    "gn:name":"\u0100sm\u0101n\u012b\u0101n",
    "gn:population":0,
    "gn:timezone":"Asia/Kabul",
    "iso:country":"AF",
    "name:fas_x_preferred":[
        "\u0622\u0633\u0645\u0627\u0646\u064a\u0627\u0646"
    ],
    "name:rus_x_preferred":[
        "\u0410\u0441\u043c\u0430\u043d\u044c\u044f\u043d"
    ],
    "name:und_x_variant":[
        "\u0100sm\u0101ny\u0101n",
        "Asman\u2019yan",
        "\u0100sm\u0101n\u012b\u0101n",
        "\u0622\u0633\u0645\u0627\u0646\u06cc\u0627\u0646"
    ],
    "wof:name":"Asmanian",
    "wof:placetype":"locality"
},
  "geometry": {"coordinates":[65.08445999999999,33.08687],"type":"Point"}
}