{
  "type": "Feature",
  "properties": {
    "gn:admin1_code":"08",
    "gn:admin2_code":"617",
    "gn:asciiname":"Dewlak",
    "gn:country_code":"AF",
    "gn:dem":2722,
    "gn:feature_class":"P",
    "gn:feature_code":"PPL",
    "gn:name":"D\u0113wlak",
    "gn:population":0,
    "gn:timezone":"Asia/Kabul",
    "iso:country":"AF",
    "name:und_x_variant":[
        "Devlak",
        "D\u012bvlak",
        "\u1e0e\u0113wlak",
        "Daywlak",
        "\u062f\u06cc\u0648\u0644\u06a9",
        "D\u0113wlak"
    ],
    "wof:name":"Dewlak",
    "wof:placetype":"locality"
},
  "geometry": {"coordinates":[68.07321,33.63576],"type":"Point"}
}