{
  "type": "Feature",
  "properties": {
    "gn:admin1_code":"18",
    "gn:admin2_code":"818.0",
    "gn:asciiname":"Za Khel",
    "gn:country_code":"AF",
    "gn:dem":531,
    "gn:feature_class":"P",
    "gn:feature_code":"PPL",
    "gn:name":"Z\u0101 Kh\u0113l",
    "gn:population":0,
    "gn:timezone":"Asia/Kabul",
    "iso:country":"AF",
    "name:fas_x_preferred":[
        "\u0632\u0627 \u062e\u064a\u0644"
    ],
    "name:rus_x_preferred":[
        "Zakheyl\u2019"
    ],
    "name:und_x_variant":[
        "Z\u0101 Kh\u0113l",
        "Z\u0101kheyl",
        "Z\u0101kh\u0113l",
        "\u0632\u0627 \u062e\u06d0\u0644"
    ],
    "wof:name":"Za Khel",
    "wof:placetype":"locality"
},
  "geometry": {"coordinates":[70.56141,34.39817],"type":"Point"}
}