{
  "type": "Feature",
  "properties": {
    "gn:admin1_code":"28",
    "gn:admin2_code":"2509",
    "gn:asciiname":"Shamali Isma'ili",
    "gn:country_code":"AF",
    "gn:dem":2114,
    "gn:feature_class":"P",
    "gn:feature_code":"PPL",
    "gn:name":"Sham\u0101l\u012b Ism\u0101\u2018\u012bl\u012b",
    "gn:population":0,
    "gn:timezone":"Asia/Kabul",
    "iso:country":"AF",
    "name:und_x_variant":[
        "Samali Esm\u0101\u2018\u012blay",
        "Shamali-Ismailay",
        "Sham\u0101l\u012b Esm\u0101\u2018\u012blay",
        "Sham\u0101l\u012b Ism\u0101\u2018\u012bl\u012b",
        "Shom\u0101l\u012b Esm\u0101\u2018\u012blay",
        "\u0634\u0645\u0627\u0644\u06cc \u0627\u0633\u0645\u0627\u0639\u06cc\u0644\u06cc"
    ],
    "wof:name":"Shamali Isma'ili",
    "wof:placetype":"locality"
},
  "geometry": {"coordinates":[67.5508,31.79163],"type":"Point"}
}