{
  "type": "Feature",
  "properties": {
    "gn:admin1_code":"8",
    "gn:admin2_code":"608.0",
    "gn:asciiname":"Edil Khel",
    "gn:country_code":"AF",
    "gn:dem":1983,
    "gn:feature_class":"P",
    "gn:feature_code":"PPL",
    "gn:name":"\u0112dil Kh\u0113l",
    "gn:population":0,
    "gn:timezone":"Asia/Kabul",
    "iso:country":"AF",
    "name:rus_x_preferred":[
        "Edil\u2019kheyl\u2019"
    ],
    "name:und_x_variant":[
        "E\u1e0felkh\u0113l",
        "\u0112dil Kh\u0113l",
        "\u0627\u06d0\u062f\u0644 \u062e\u06d0\u0644",
        "E\u1e0fel Kheyl"
    ],
    "wof:name":"Edil Khel",
    "wof:placetype":"locality"
},
  "geometry": {"coordinates":[67.74499,32.79493],"type":"Point"}
}