{
  "type": "Feature",
  "properties": {
    "gn:admin1_code":"41",
    "gn:admin2_code":"3409",
    "gn:asciiname":"Taghaspi",
    "gn:country_code":"AF",
    "gn:dem":2261,
    "gn:feature_class":"P",
    "gn:feature_code":"PPL",
    "gn:name":"Taghasp\u012b",
    "gn:population":0,
    "gn:timezone":"Asia/Kabul",
    "iso:country":"AF",
    "name:und_x_variant":[
        "Taq\u0101saf\u0113d",
        "Taghasp\u012b",
        "\u062a\u063a\u0633\u067e\u06cc",
        "Taq\u0101 Safayd",
        "\u062a\u0642\u0627 \u0633\u0641\u06cc\u062f"
    ],
    "wof:name":"Taghaspi",
    "wof:placetype":"locality"
},
  "geometry": {"coordinates":[66.2615,33.92901],"type":"Point"}
}