{
  "type": "Feature",
  "properties": {
    "gn:admin1_code":"14",
    "gn:admin2_code":"204.0",
    "gn:asciiname":"Babah Sat",
    "gn:country_code":"AF",
    "gn:dem":2386,
    "gn:feature_class":"P",
    "gn:feature_code":"PPL",
    "gn:name":"B\u0101bah S\u0101t",
    "gn:population":0,
    "gn:timezone":"Asia/Kabul",
    "iso:country":"AF",
    "name:fas_x_preferred":[
        "\u0628\u0627\u0628\u0627\u0633\u0627\u062a"
    ],
    "name:rus_x_preferred":[
        "\u0411\u0430\u0431\u0430\u0441\u0430\u0442"
    ],
    "name:und_x_variant":[
        "Babasat",
        "B\u0101b\u0101s\u0101t",
        "B\u0101bah S\u0101t",
        "\u0628\u0627\u0628\u0647 \u0633\u0627\u062a"
    ],
    "wof:name":"Babah Sat",
    "wof:placetype":"locality"
},
  "geometry": {"coordinates":[69.56016,35.08229],"type":"Point"}
}