{
  "type": "Feature",
  "properties": {
    "gn:admin1_code":"7",
    "gn:admin2_code":"1804.0",
    "gn:asciiname":"Khwajah Puchaqli",
    "gn:country_code":"AF",
    "gn:dem":1326,
    "gn:feature_class":"P",
    "gn:feature_code":"PPL",
    "gn:name":"Khw\u0101jah P\u016bch\u0101ql\u012b",
    "gn:population":0,
    "gn:timezone":"Asia/Kabul",
    "iso:country":"AF",
    "name:und_x_variant":[
        "Khw\u0101ja P\u016bc\u0101qli (2)",
        "Khv\u0101jeh P\u016bch\u0101ql\u012b Two",
        "Khw\u0101jah P\u016bch\u0101ql\u012b",
        "\u062e\u0648\u0627\u062c\u0647 \u067e\u0648\u0686\u0627\u0642\u0644\u06cc"
    ],
    "wof:name":"Khwajah Puchaqli",
    "wof:placetype":"locality"
},
  "geometry": {"coordinates":[64.5318,35.63044],"type":"Point"}
}