{
  "type": "Feature",
  "properties": {
    "gn:admin1_code":"23",
    "gn:admin2_code":"2408.0",
    "gn:asciiname":"Haji Salam Khan",
    "gn:country_code":"AF",
    "gn:dem":929,
    "gn:feature_class":"P",
    "gn:feature_code":"PPL",
    "gn:name":"\u1e28\u0101j\u012b Sal\u0101m Kh\u0101n",
    "gn:population":0,
    "gn:timezone":"Asia/Kabul",
    "iso:country":"AF",
    "name:und_x_variant":[
        "Sal\u0101mkh\u0101n",
        "\u1e28\u0101ji Sal\u0101mkh\u0101n",
        "Khadzhi-Salamkhan",
        "Haj\u012b\u012b Sal\u0101mkh\u0101n",
        "\u1e28\u0101j\u012b Sal\u0101m Kh\u0101n",
        "\u062d\u0627\u062c\u06cc \u0633\u0644\u0627\u0645 \u062e\u0627\u0646",
        "\u1e28\u0101jj\u012b Sal\u0101mkh\u0101n"
    ],
    "wof:name":"Haji Salam Khan",
    "wof:placetype":"locality"
},
  "geometry": {"coordinates":[65.42208000000001,31.50154],"type":"Point"}
}