{
  "type": "Feature",
  "properties": {
    "gn:admin1_code":"23",
    "gn:admin2_code":"2414.0",
    "gn:asciiname":"Khishkhatu",
    "gn:country_code":"AF",
    "gn:dem":2149,
    "gn:feature_class":"P",
    "gn:feature_code":"PPL",
    "gn:name":"Khishkh\u0101t\u016b",
    "gn:population":0,
    "gn:timezone":"Asia/Kabul",
    "iso:country":"AF",
    "name:und_x_variant":[
        "Khe\u0161kh\u0101tu",
        "Khishkh\u0101t\u016b",
        "\u062e\u0634\u062e\u0627\u062a\u0648",
        "Kheshkh\u0101t\u016b"
    ],
    "wof:name":"Khishkhatu",
    "wof:placetype":"locality"
},
  "geometry": {"coordinates":[66.42726999999999,32.39639],"type":"Point"}
}