{
  "type": "Feature",
  "properties": {
    "gn:admin1_code":"08",
    "gn:admin2_code":"611",
    "gn:asciiname":"Landah Khel",
    "gn:country_code":"AF",
    "gn:dem":2089,
    "gn:feature_class":"P",
    "gn:feature_code":"PPL",
    "gn:name":"Lan\u1e0fah Kh\u0113l",
    "gn:population":0,
    "gn:timezone":"Asia/Kabul",
    "iso:country":"AF",
    "name:rus_x_preferred":[
        "Landakheyl\u2019"
    ],
    "name:und_x_variant":[
        "Lan\u1e0fakh\u0113l",
        "Lan\u1e0fah Kh\u0113l",
        "\u0644\u0646\u0689\u0647 \u062e\u06d0\u0644",
        "Landah Kheyl"
    ],
    "wof:name":"Landah Khel",
    "wof:placetype":"locality"
},
  "geometry": {"coordinates":[67.92908,32.9834],"type":"Point"}
}