{
  "type": "Feature",
  "properties": {
    "gn:admin1_code":"03",
    "gn:admin2_code":"1306.0",
    "gn:asciiname":"Takhtah Sang",
    "gn:country_code":"AF",
    "gn:dem":1762,
    "gn:feature_class":"P",
    "gn:feature_code":"PPL",
    "gn:name":"Takhtah Sang",
    "gn:population":0,
    "gn:timezone":"Asia/Kabul",
    "iso:country":"AF",
    "name:und_x_variant":[
        "Takhteh Sang",
        "Takhtah Sang",
        "\u062a\u062e\u062a\u0647 \u0633\u0646\u06af",
        "Takhtasang"
    ],
    "wof:name":"Takhtah Sang",
    "wof:placetype":"locality"
},
  "geometry": {"coordinates":[68.94107,35.48701],"type":"Point"}
}