{
  "type": "Feature",
  "properties": {
    "gn:admin1_code":"11",
    "gn:admin2_code":"2005",
    "gn:asciiname":"Gajah",
    "gn:country_code":"AF",
    "gn:dem":1757,
    "gn:feature_class":"P",
    "gn:feature_code":"PPL",
    "gn:name":"Gajah",
    "gn:population":0,
    "gn:timezone":"Asia/Kabul",
    "iso:country":"AF",
    "name:ind_x_preferred":[
        "Gajah"
    ],
    "name:und_x_variant":[
        "\u06af\u062c\u0647",
        "Gaja",
        "G\u0101jah",
        "\u06af\u0627\u062c\u0647"
    ],
    "wof:name":"Gajah",
    "wof:placetype":"locality"
},
  "geometry": {"coordinates":[62.86452,34.54411],"type":"Point"}
}