{
  "type": "Feature",
  "properties": {
    "gn:admin1_code":"41",
    "gn:admin2_code":"3404",
    "gn:asciiname":"Gardak",
    "gn:country_code":"AF",
    "gn:dem":1597,
    "gn:feature_class":"P",
    "gn:feature_code":"PPL",
    "gn:name":"Gardak",
    "gn:population":0,
    "gn:timezone":"Asia/Kabul",
    "iso:country":"AF",
    "name:ceb_x_preferred":[
        "Gardak"
    ],
    "name:swe_x_preferred":[
        "Gardak"
    ],
    "name:und_x_variant":[
        "\u06af\u0631\u062f\u06a9",
        "Ga\u1e5f\u1e0fak"
    ],
    "wof:name":"Gardak",
    "wof:placetype":"locality"
},
  "geometry": {"coordinates":[65.50813000000001,33.33957],"type":"Point"}
}