{
  "type": "Feature",
  "properties": {
    "gn:admin1_code":"29",
    "gn:admin2_code":"2910.0",
    "gn:asciiname":"Dogar Kelay",
    "gn:country_code":"AF",
    "gn:dem":2039,
    "gn:feature_class":"P",
    "gn:feature_code":"PPL",
    "gn:name":"D\u014dgar K\u00ealay",
    "gn:population":0,
    "gn:timezone":"Asia/Kabul",
    "iso:country":"AF",
    "wof:name":"Dogar Kelay",
    "wof:placetype":"locality"
},
  "geometry": {"coordinates":[69.43823,32.99067],"type":"Point"}
}