{
  "type": "Feature",
  "properties": {
    "gn:admin1_code":"23",
    "gn:admin2_code":"2410.0",
    "gn:asciiname":"Bahadurzi",
    "gn:country_code":"AF",
    "gn:dem":991,
    "gn:feature_class":"P",
    "gn:feature_code":"PPL",
    "gn:name":"Bah\u0101durz\u012b",
    "gn:population":0,
    "gn:timezone":"Asia/Kabul",
    "iso:country":"AF",
    "name:und_x_variant":[
        "Bah\u0101\u1e0fu\u1e5fzi",
        "Bah\u0101dorza\u012b",
        "Bah\u0101dorzay",
        "Bah\u0101durz\u012b",
        "\u0628\u0647\u0627\u062f\u0631\u0632\u06cc",
        "Bah\u0101dorz\u012b"
    ],
    "wof:name":"Bahadurzi",
    "wof:placetype":"locality"
},
  "geometry": {"coordinates":[66.02105,30.1805],"type":"Point"}
}