{
  "type": "Feature",
  "properties": {
    "gn:admin1_code":"18",
    "gn:admin2_code":"806.0",
    "gn:asciiname":"Halim Mama Kelay",
    "gn:country_code":"AF",
    "gn:dem":965,
    "gn:feature_class":"P",
    "gn:feature_code":"PPL",
    "gn:name":"\u1e28al\u012bm M\u0101m\u0101 K\u00ealay",
    "gn:population":0,
    "gn:timezone":"Asia/Kabul",
    "iso:country":"AF",
    "name:fas_x_preferred":[
        "\u062d\u0644\u064a\u0645 \u0645\u0627\u0645\u0627 \u0643\u0644\u06cc"
    ],
    "name:und_x_variant":[
        "Khalimmama-Kalay",
        "\u1e28al\u012bm M\u0101m\u0101 Kalay",
        "\u062d\u0644\u064a\u0645 \u0645\u0627\u0645\u0627 \u0643\u0644\u06cc",
        "\u1e28al\u012bm M\u0101m\u0101 K\u00ealay",
        "\u062d\u0644\u06cc\u0645 \u0645\u0627\u0645\u0627 \u06a9\u0644\u06cc"
    ],
    "wof:name":"Halim Mama Kelay",
    "wof:placetype":"locality"
},
  "geometry": {"coordinates":[70.36128000000001,34.26076],"type":"Point"}
}