{
  "type": "Feature",
  "properties": {
    "gn:admin1_code":"06",
    "gn:admin2_code":"2108",
    "gn:asciiname":"Janabad",
    "gn:country_code":"AF",
    "gn:dem":579,
    "gn:feature_class":"P",
    "gn:feature_code":"PPL",
    "gn:name":"J\u0101n\u0101b\u0101d",
    "gn:population":0,
    "gn:timezone":"Asia/Kabul",
    "iso:country":"AF",
    "name:und_x_variant":[
        "J\u0101n\u0101b\u0101d",
        "\u062c\u0627\u0646 \u0622\u0628\u0627\u062f"
    ],
    "wof:name":"Janabad",
    "wof:placetype":"locality"
},
  "geometry": {"coordinates":[61.28079,32.25316],"type":"Point"}
}