{
  "type": "Feature",
  "properties": {
    "gn:admin1_code":"28",
    "gn:admin2_code":"2502",
    "gn:asciiname":"Sayghan",
    "gn:country_code":"AF",
    "gn:dem":2127,
    "gn:feature_class":"P",
    "gn:feature_code":"PPL",
    "gn:name":"Saygh\u0101n",
    "gn:population":0,
    "gn:timezone":"Asia/Kabul",
    "iso:country":"AF",
    "name:und_x_variant":[
        "Saygan",
        "Saygh\u0101n",
        "\u0633\u06cc\u063a\u0627\u0646"
    ],
    "wof:name":"Sayghan",
    "wof:placetype":"locality"
},
  "geometry": {"coordinates":[67.59284,32.53479],"type":"Point"}
}