{
  "type": "Feature",
  "properties": {
    "gn:admin1_code":"1",
    "gn:admin2_code":"1107.0",
    "gn:asciiname":"Darmadar",
    "gn:country_code":"AF",
    "gn:dem":2847,
    "gn:feature_class":"P",
    "gn:feature_code":"PPL",
    "gn:name":"D\u0101rmad\u0101r",
    "gn:population":0,
    "gn:timezone":"Asia/Kabul",
    "iso:country":"AF",
    "name:ben_x_preferred":[
        "\u09a6\u09be\u09b0\u09ae\u09be\u09a6\u09be\u09b0"
    ],
    "name:por_x_preferred":[
        "Darmadar"
    ],
    "name:und_x_variant":[
        "D\u0101rmad\u0101r",
        "\u062f\u0627\u0631\u0645\u062f\u0627\u0631"
    ],
    "wof:name":"Darmadar",
    "wof:placetype":"locality"
},
  "geometry": {"coordinates":[71.43904999999999,37.2199],"type":"Point"}
}