{
  "type": "Feature",
  "properties": {
    "gn:admin1_code":"05",
    "gn:admin2_code":"2804",
    "gn:asciiname":"Naqum",
    "gn:country_code":"AF",
    "gn:dem":3039,
    "gn:feature_class":"P",
    "gn:feature_code":"PPL",
    "gn:name":"Naq\u016bm",
    "gn:population":0,
    "gn:timezone":"Asia/Kabul",
    "iso:country":"AF",
    "name:und_x_variant":[
        "Nakum",
        "Naq\u016bm",
        "Naqowm",
        "\u0646\u0642\u0648\u0645"
    ],
    "wof:name":"Naqum",
    "wof:placetype":"locality"
},
  "geometry": {"coordinates":[66.89604,34.59532],"type":"Point"}
}