{
  "type": "Feature",
  "properties": {
    "gn:admin1_code":"32",
    "gn:admin2_code":"1503",
    "gn:asciiname":"Naw-e Ghor",
    "gn:country_code":"AF",
    "gn:dem":2229,
    "gn:feature_class":"P",
    "gn:feature_code":"PPL",
    "gn:name":"N\u0101w-e Gh\u014dr",
    "gn:population":0,
    "gn:timezone":"Asia/Kabul",
    "iso:country":"AF",
    "name:und_x_variant":[
        "Nawe Gh\u014d\u1e5f",
        "Nawe Gh\u016br",
        "N\u0101w-e Gh\u014dr",
        "\u0646\u0627\u0648 \u063a\u0648\u0631"
    ],
    "wof:name":"Naw-e Ghor",
    "wof:placetype":"locality"
},
  "geometry": {"coordinates":[67.35273000000001,35.77577],"type":"Point"}
}