{
  "type": "Feature",
  "properties": {
    "gn:admin1_code":"05",
    "gn:admin2_code":"2806.0",
    "gn:asciiname":"Nimqolak",
    "gn:country_code":"AF",
    "gn:dem":2792,
    "gn:feature_class":"P",
    "gn:feature_code":"PPL",
    "gn:name":"N\u012bmq\u014dlak",
    "gn:population":0,
    "gn:timezone":"Asia/Kabul",
    "iso:country":"AF",
    "name:und_x_variant":[
        "Nimkulak",
        "N\u012bmqowlak",
        "N\u012bmq\u014dlak",
        "\u0646\u06cc\u0645\u0642\u0648\u0644\u06a9"
    ],
    "wof:name":"Nimqolak",
    "wof:placetype":"locality"
},
  "geometry": {"coordinates":[67.21545,34.20877],"type":"Point"}
}