{
  "type": "Feature",
  "properties": {
    "gn:admin1_code":"18",
    "gn:admin2_code":"811.0",
    "gn:asciiname":"Krapay Kala",
    "gn:country_code":"AF",
    "gn:dem":1549,
    "gn:feature_class":"P",
    "gn:feature_code":"PPL",
    "gn:name":"K\u1e5fapay Kal\u0101",
    "gn:population":0,
    "gn:timezone":"Asia/Kabul",
    "iso:country":"AF",
    "name:fas_x_preferred":[
        "\u0642\u0644\u0639\u0647\u0654 \u0643\u0631\u067e\u06cc"
    ],
    "name:und_x_variant":[
        "Krapaykala",
        "Krapay Kal\u0101",
        "K\u1e5fapay Kal\u0101",
        "\u06a9\u0693\u067e\u06cc \u06a9\u0644\u0627"
    ],
    "wof:name":"Krapay Kala",
    "wof:placetype":"locality"
},
  "geometry": {"coordinates":[70.81805,34.00689000000001],"type":"Point"}
}