{
  "type": "Feature",
  "properties": {
    "gn:admin1_code":"34",
    "gn:admin2_code":"1004.0",
    "gn:asciiname":"Katsunah",
    "gn:country_code":"AF",
    "gn:dem":2872,
    "gn:feature_class":"P",
    "gn:feature_code":"PPL",
    "gn:name":"Kats\u016bnah",
    "gn:population":0,
    "gn:timezone":"Asia/Kabul",
    "iso:country":"AF",
    "name:fas_x_preferred":[
        "\u0643\u0686\u0648\u0646\u0647"
    ],
    "name:und_x_variant":[
        "Kac\u014dna",
        "Kats\u016bnah",
        "\u0643\u0686\u0648\u0646\u0647"
    ],
    "wof:name":"Katsunah",
    "wof:placetype":"locality"
},
  "geometry": {"coordinates":[71.41169000000002,34.93264],"type":"Point"}
}