{
  "type": "Feature",
  "properties": {
    "gn:admin1_code":"18",
    "gn:admin2_code":"818.0",
    "gn:asciiname":"Ghat Sar",
    "gn:country_code":"AF",
    "gn:dem":527,
    "gn:feature_class":"P",
    "gn:feature_code":"PPL",
    "gn:name":"Gha\u1e6f Sar",
    "gn:population":0,
    "gn:timezone":"Asia/Kabul",
    "iso:country":"AF",
    "name:fas_x_preferred":[
        "\u0633\u0631\u0654 \u063a\u062a"
    ],
    "name:und_x_variant":[
        "Gatsar",
        "Gha\u1e6f Sar",
        "Ghat Sar",
        "\u063a\u062a \u0633\u0631",
        "\u063a\u067c \u0633\u0631"
    ],
    "wof:name":"Ghat Sar",
    "wof:placetype":"locality"
},
  "geometry": {"coordinates":[70.62300999999999,34.4358],"type":"Point"}
}