{
  "type": "Feature",
  "properties": {
    "gn:admin1_code":"14",
    "gn:admin2_code":"204.0",
    "gn:asciiname":"Zakariya Khel",
    "gn:country_code":"AF",
    "gn:dem":2629,
    "gn:feature_class":"P",
    "gn:feature_code":"PPL",
    "gn:name":"Z\u0304akariy\u0101 Kh\u0113l",
    "gn:population":0,
    "gn:timezone":"Asia/Kabul",
    "iso:country":"AF",
    "name:fas_x_preferred":[
        "\u0630\u0643\u0631\u064a\u0627 \u062e\u064a\u0644"
    ],
    "name:rus_x_preferred":[
        "\u0417\u0438\u043a\u0440\u0438\u0430\u0445\u0435\u0439\u043b\u044c"
    ],
    "name:und_x_variant":[
        "Zikriakheyl\u2019",
        "Zek\u1e5fy\u0101kh\u0113l",
        "Z\u0304ekr\u012b\u0101kheyl",
        "Z\u0304akariy\u0101 Kh\u0113l",
        "\u0630\u06a9\u0631\u06cc\u0627 \u062e\u06d0\u0644"
    ],
    "wof:name":"Zakariya Khel",
    "wof:placetype":"locality"
},
  "geometry": {"coordinates":[69.73862,35.03488],"type":"Point"}
}