{
  "type": "Feature",
  "properties": {
    "gn:admin1_code":"10",
    "gn:admin2_code":"2301.0",
    "gn:asciiname":"Barang",
    "gn:country_code":"AF",
    "gn:dem":814,
    "gn:feature_class":"P",
    "gn:feature_code":"PPL",
    "gn:name":"Barang",
    "gn:population":0,
    "gn:timezone":"Asia/Kabul",
    "iso:country":"AF",
    "name:ceb_x_preferred":[
        "Barang"
    ],
    "name:fas_x_preferred":[
        "\u0628\u0631\u0646\u06af"
    ],
    "name:nld_x_preferred":[
        "Barang"
    ],
    "name:swe_x_preferred":[
        "Barang"
    ],
    "name:und_x_variant":[
        "Ba\u1e5fang"
    ],
    "wof:name":"Barang",
    "wof:placetype":"locality"
},
  "geometry": {"coordinates":[64.73721,31.64262],"type":"Point"}
}