{
  "type": "Feature",
  "properties": {
    "gn:admin1_code":"26",
    "gn:admin2_code":"1201.0",
    "gn:asciiname":"Andarabiya",
    "gn:country_code":"AF",
    "gn:dem":915,
    "gn:feature_class":"P",
    "gn:feature_code":"PPL",
    "gn:name":"Andar\u0101biy\u0101",
    "gn:population":0,
    "gn:timezone":"Asia/Kabul",
    "iso:country":"AF",
    "name:und_x_variant":[
        "Andar\u0101biy\u0101",
        "\u0627\u0646\u062f\u0631\u0627\u0628\u06cc\u0627",
        "An\u1e0fa\u1e5f\u0101biy\u0101"
    ],
    "wof:name":"Andarabiya",
    "wof:placetype":"locality"
},
  "geometry": {"coordinates":[69.64112,36.66513],"type":"Point"}
}