{
  "type": "Feature",
  "properties": {
    "gn:admin1_code":"05",
    "gn:admin2_code":"2805",
    "gn:asciiname":"Qonghar",
    "gn:country_code":"AF",
    "gn:dem":3063,
    "gn:feature_class":"P",
    "gn:feature_code":"PPL",
    "gn:name":"Q\u014dnghar",
    "gn:population":0,
    "gn:timezone":"Asia/Kabul",
    "iso:country":"AF",
    "name:und_x_variant":[
        "Q\u014dngha\u1e5f",
        "Kongar",
        "Q\u014dnghar",
        "Qownghar",
        "\u0642\u0648\u0646\u063a\u0631"
    ],
    "wof:name":"Qonghar",
    "wof:placetype":"locality"
},
  "geometry": {"coordinates":[67.12796,34.38553],"type":"Point"}
}