{
  "type": "Feature",
  "properties": {
    "gn:admin1_code":"40",
    "gn:admin2_code":"305.0",
    "gn:asciiname":"Bagh-e Kham",
    "gn:country_code":"AF",
    "gn:dem":1973,
    "gn:feature_class":"P",
    "gn:feature_code":"PPL",
    "gn:name":"B\u0101gh-e Kham",
    "gn:population":0,
    "gn:timezone":"Asia/Kabul",
    "iso:country":"AF",
    "name:und_x_variant":[
        "Bagi-Kham",
        "B\u0101gh-e Kham",
        "\u0628\u0627\u063a \u062e\u0645"
    ],
    "wof:name":"Bagh-e Kham",
    "wof:placetype":"locality"
},
  "geometry": {"coordinates":[68.72696999999999,34.9911],"type":"Point"}
}