{
  "type": "Feature",
  "properties": {
    "gn:admin1_code":"30",
    "gn:admin2_code":"1610",
    "gn:asciiname":"Naymirak",
    "gn:country_code":"AF",
    "gn:dem":1350,
    "gn:feature_class":"P",
    "gn:feature_code":"PPL",
    "gn:name":"Naym\u012brak",
    "gn:population":0,
    "gn:timezone":"Asia/Kabul",
    "iso:country":"AF",
    "name:und_x_variant":[
        "Naymi\u1e5fak",
        "Naym\u012brak",
        "\u0646\u06cc\u0645\u06cc\u0631\u06a9"
    ],
    "wof:name":"Naymirak",
    "wof:placetype":"locality"
},
  "geometry": {"coordinates":[66.85139000000001,36.00203],"type":"Point"}
}