{
  "type": "Feature",
  "properties": {
    "gn:admin1_code":"8",
    "gn:admin2_code":"602.0",
    "gn:asciiname":"Faqir Shah",
    "gn:country_code":"AF",
    "gn:dem":2775,
    "gn:feature_class":"P",
    "gn:feature_code":"PPL",
    "gn:name":"Faq\u012br Sh\u0101h",
    "gn:population":0,
    "gn:timezone":"Asia/Kabul",
    "iso:country":"AF",
    "name:fas_x_preferred":[
        "\u0641\u0642\u064a\u0631 \u0634\u0627\u0647"
    ],
    "name:und_x_variant":[
        "Faq\u012brsah",
        "Faq\u012br\u0161\u0101h",
        "Fakirshakh",
        "Faq\u012br Sh\u0101h",
        "\u0641\u0642\u06cc\u0631 \u0634\u0627\u0647"
    ],
    "wof:name":"Faqir Shah",
    "wof:placetype":"locality"
},
  "geometry": {"coordinates":[68.02333,33.5853],"type":"Point"}
}