{
  "type": "Feature",
  "properties": {
    "gn:admin1_code":"30",
    "gn:admin2_code":"1609",
    "gn:asciiname":"Kochak Qizil",
    "gn:country_code":"AF",
    "gn:dem":939,
    "gn:feature_class":"P",
    "gn:feature_code":"PPL",
    "gn:name":"K\u014dchak Qizil",
    "gn:population":0,
    "gn:timezone":"Asia/Kabul",
    "iso:country":"AF",
    "name:und_x_variant":[
        "Kochek Qizil (1)",
        "K\u016bchek Qezel",
        "K\u014dchak Qizil",
        "\u06a9\u0648\u0686\u06a9 \u0642\u0632\u0644"
    ],
    "wof:name":"Kochak Qizil",
    "wof:placetype":"locality"
},
  "geometry": {"coordinates":[66.67740000000001,36.22665],"type":"Point"}
}