{
  "type": "Feature",
  "properties": {
    "gn:admin1_code":"36",
    "gn:admin2_code":"706.0",
    "gn:asciiname":"Chilam",
    "gn:country_code":"AF",
    "gn:dem":1962,
    "gn:feature_class":"P",
    "gn:feature_code":"PPL",
    "gn:name":"Chilam",
    "gn:population":0,
    "gn:timezone":"Asia/Kabul",
    "iso:country":"AF",
    "name:und_x_variant":[
        "\u010celam",
        "Chilam",
        "Chelam",
        "\u0686\u0644\u0645"
    ],
    "wof:name":"Chilam",
    "wof:placetype":"locality"
},
  "geometry": {"coordinates":[69.80658000000001,33.68264],"type":"Point"}
}