{
  "type": "Feature",
  "properties": {
    "gn:admin1_code":"37",
    "gn:admin2_code":"3211",
    "gn:asciiname":"Lezikalay",
    "gn:country_code":"AF",
    "gn:dem":1415,
    "gn:feature_class":"P",
    "gn:feature_code":"PPL",
    "gn:name":"Lezikalay",
    "gn:population":0,
    "gn:timezone":"Asia/Kabul",
    "iso:country":"AF",
    "name:fas_x_preferred":[
        "\u0644\u0698\u06cc \u0643\u0644\u06cc"
    ],
    "name:und_x_variant":[
        "L\u0113\u017ei Kalay",
        "Lezikalay",
        "L\u0113z\u0332h\u0332\u012b K\u00ealay",
        "Leyz\u0332h\u0332\u012b Kalay",
        "\u0644\u06cc\u0696\u06cc \u0643\u0644\u06cc"
    ],
    "wof:name":"Lezikalay",
    "wof:placetype":"locality"
},
  "geometry": {"coordinates":[69.86184,33.20358],"type":"Point"}
}