{
  "type": "Feature",
  "properties": {
    "gn:admin1_code":"8",
    "gn:admin2_code":"617.0",
    "gn:asciiname":"Shir Dagh",
    "gn:country_code":"AF",
    "gn:dem":2541,
    "gn:feature_class":"P",
    "gn:feature_code":"PPL",
    "gn:name":"Sh\u012br D\u0101gh",
    "gn:population":0,
    "gn:timezone":"Asia/Kabul",
    "iso:country":"AF",
    "name:fas_x_preferred":[
        "\u0634\u064a\u0631 \u062f\u0627\u063a"
    ],
    "name:und_x_variant":[
        "\u0160\u012brd\u0101gh",
        "Shirdag",
        "Sh\u012br D\u0101gh",
        "Sh\u012brd\u0101gh"
    ],
    "wof:name":"Shir Dagh",
    "wof:placetype":"locality"
},
  "geometry": {"coordinates":[68.27543,33.70983],"type":"Point"}
}