{
  "type": "Feature",
  "properties": {
    "gn:admin1_code":"6",
    "gn:admin2_code":"2109.0",
    "gn:asciiname":"Borkham",
    "gn:country_code":"AF",
    "gn:dem":556,
    "gn:feature_class":"P",
    "gn:feature_code":"PPL",
    "gn:name":"B\u014drkham",
    "gn:population":0,
    "gn:timezone":"Asia/Kabul",
    "iso:country":"AF",
    "name:fas_x_preferred":[
        "\u0628\u0648\u0631\u062e\u0645"
    ],
    "name:und_x_variant":[
        "B\u014d\u1e5fkham",
        "Bowrkham",
        "B\u014drkham",
        "\u0628\u0648\u0631\u062e\u0645"
    ],
    "wof:name":"Borkham",
    "wof:placetype":"locality"
},
  "geometry": {"coordinates":[61.63254000000001,31.92202],"type":"Point"}
}