{
  "type": "Feature",
  "properties": {
    "gn:admin1_code":"8",
    "gn:admin2_code":"607.0",
    "gn:asciiname":"Nay Qol",
    "gn:country_code":"AF",
    "gn:dem":2649,
    "gn:feature_class":"P",
    "gn:feature_code":"PPL",
    "gn:name":"Nay Q\u014dl",
    "gn:population":0,
    "gn:timezone":"Asia/Kabul",
    "iso:country":"AF",
    "name:und_x_variant":[
        "Nay Q\u014dl",
        "Nayqowl",
        "\u0646\u06cc \u0642\u0648\u0644"
    ],
    "wof:name":"Nay Qol",
    "wof:placetype":"locality"
},
  "geometry": {"coordinates":[67.3537,33.10024],"type":"Point"}
}