{
  "type": "Feature",
  "properties": {
    "gn:admin1_code":"40",
    "gn:admin2_code":"308.0",
    "gn:asciiname":"Badzhauri",
    "gn:country_code":"AF",
    "gn:dem":1482,
    "gn:feature_class":"P",
    "gn:feature_code":"PPL",
    "gn:name":"Badzhauri",
    "gn:population":0,
    "gn:timezone":"Asia/Kabul",
    "iso:country":"AF",
    "name:und_x_variant":[
        "B\u0101jaw\u1e5f\u012b",
        "B\u0101jawri",
        "B\u0101jow\u1e5f\u012b",
        "\u0628\u0627\u062c\u0648\u0693\u06cc",
        "B\u0101jowr\u012b",
        "\u0628\u0627\u062c\u0648\u0631\u06cc"
    ],
    "wof:name":"Badzhauri",
    "wof:placetype":"locality"
},
  "geometry": {"coordinates":[69.31116,34.98474],"type":"Point"}
}