{
  "type": "Feature",
  "properties": {
    "gn:admin1_code":"29",
    "gn:admin2_code":"2905",
    "gn:asciiname":"Payamad",
    "gn:country_code":"AF",
    "gn:dem":2117,
    "gn:feature_class":"P",
    "gn:feature_code":"PPL",
    "gn:name":"P\u0101yamad",
    "gn:population":0,
    "gn:timezone":"Asia/Kabul",
    "iso:country":"AF",
    "name:fas_x_preferred":[
        "\u067e\u0627\u064a\u0627\u0645\u062f"
    ],
    "name:und_x_variant":[
        "\u067e\u0627\u06cc\u0645\u062f",
        "P\u0101yamad"
    ],
    "wof:name":"Payamad",
    "wof:placetype":"locality"
},
  "geometry": {"coordinates":[68.88334999999999,32.11199000000001],"type":"Point"}
}