{
  "type": "Feature",
  "properties": {
    "gn:admin1_code":"10",
    "gn:admin2_code":"2303",
    "gn:asciiname":"Lab-e Joy",
    "gn:country_code":"AF",
    "gn:dem":1057,
    "gn:feature_class":"P",
    "gn:feature_code":"PPL",
    "gn:name":"Lab-e J\u014dy",
    "gn:population":0,
    "gn:timezone":"Asia/Kabul",
    "iso:country":"AF",
    "name:und_x_variant":[
        "Labi-Dzhoy",
        "Lager Joh",
        "Lab-e J\u014dy",
        "\u0644\u0628 \u062c\u0648\u06cc",
        "Lab-e J\u016by"
    ],
    "wof:name":"Lab-e Joy",
    "wof:placetype":"locality"
},
  "geometry": {"coordinates":[65.13548,32.42515],"type":"Point"}
}