{
  "type": "Feature",
  "properties": {
    "gn:admin1_code":"28",
    "gn:admin2_code":"2501.0",
    "gn:asciiname":"Kakaran Kelay",
    "gn:country_code":"AF",
    "gn:dem":1558,
    "gn:feature_class":"P",
    "gn:feature_code":"PPL",
    "gn:name":"K\u0101ka\u1e5f\u0101n K\u00ealay",
    "gn:population":0,
    "gn:timezone":"Asia/Kabul",
    "iso:country":"AF",
    "name:und_x_variant":[
        "K\u0101ka\u1e5f\u0101n K\u00ealay",
        "\u06a9\u0627\u06a9\u0693\u0627\u0646 \u06a9\u0644\u06cc",
        "K\u0101kar\u0101n Kalay"
    ],
    "wof:name":"Kakaran Kelay",
    "wof:placetype":"locality"
},
  "geometry": {"coordinates":[66.82692,31.99548],"type":"Point"}
}