{
  "type": "Feature",
  "properties": {
    "gn:admin1_code":"18",
    "gn:admin2_code":"822",
    "gn:asciiname":"Shubdiyani",
    "gn:country_code":"AF",
    "gn:dem":585,
    "gn:feature_class":"P",
    "gn:feature_code":"PPL",
    "gn:name":"Shubdiy\u0101n\u012b",
    "gn:population":0,
    "gn:timezone":"Asia/Kabul",
    "iso:country":"AF",
    "name:fas_x_preferred":[
        "\u0634\u0628\u062f\u064a\u0627\u0646\u06cc"
    ],
    "name:rus_x_preferred":[
        "Shubd\u2019yani"
    ],
    "name:und_x_variant":[
        "\u0160ubdy\u0101ni",
        "Shubdy\u0101n\u012b",
        "Shubdiy\u0101n\u012b",
        "\u0634\u0628\u062f\u06cc\u0627\u0646\u06cc"
    ],
    "wof:name":"Shubdiyani",
    "wof:placetype":"locality"
},
  "geometry": {"coordinates":[70.72341,34.23909],"type":"Point"}
}