{
  "type": "Feature",
  "properties": {
    "gn:admin1_code":"3",
    "gn:admin2_code":"1305.0",
    "gn:asciiname":"Diktur",
    "gn:country_code":"AF",
    "gn:dem":1274,
    "gn:feature_class":"P",
    "gn:feature_code":"PPL",
    "gn:name":"Dikt\u016br",
    "gn:population":0,
    "gn:timezone":"Asia/Kabul",
    "iso:country":"AF",
    "name:und_x_variant":[
        "Dikt\u016br",
        "\u062f\u06a9\u062a\u0648\u0631",
        "\u1e0eekt\u016b\u1e5f"
    ],
    "wof:name":"Diktur",
    "wof:placetype":"locality"
},
  "geometry": {"coordinates":[68.15196999999999,35.34745],"type":"Point"}
}