{
  "type": "Feature",
  "properties": {
    "gn:admin1_code":"39",
    "gn:admin2_code":"2603",
    "gn:asciiname":"Lwar Bariki",
    "gn:country_code":"AF",
    "gn:dem":2179,
    "gn:feature_class":"P",
    "gn:feature_code":"PPL",
    "gn:name":"Lwa\u1e5f B\u0101r\u012bk\u012b",
    "gn:population":0,
    "gn:timezone":"Asia/Kabul",
    "iso:country":"AF",
    "name:und_x_variant":[
        "Lowa\u1e5f B\u0101r\u012bk\u012b",
        "Lwa\u1e5f B\u0101r\u012bk\u012b",
        "\u0644\u0648\u0693 \u0628\u0631\u06cc\u06a9\u06cc"
    ],
    "wof:name":"Lwar Bariki",
    "wof:placetype":"locality"
},
  "geometry": {"coordinates":[66.59340999999999,33.03097],"type":"Point"}
}