{
  "type": "Feature",
  "properties": {
    "gn:admin1_code":"11",
    "gn:admin2_code":"2005.0",
    "gn:asciiname":"Qasab",
    "gn:country_code":"AF",
    "gn:dem":1209,
    "gn:feature_class":"P",
    "gn:feature_code":"PPL",
    "gn:name":"Qa\u015f\u0101b",
    "gn:population":0,
    "gn:timezone":"Asia/Kabul",
    "iso:country":"AF",
    "name:ceb_x_preferred":[
        "Qasab"
    ],
    "name:fas_x_preferred":[
        "\u0642\u0635\u0627\u0628"
    ],
    "name:swe_x_preferred":[
        "Qasab"
    ],
    "name:und_x_variant":[
        "Kasab",
        "Qa\u015f\u015f\u0101b",
        "Qa\u015f\u0101b"
    ],
    "wof:name":"Qasab",
    "wof:placetype":"locality"
},
  "geometry": {"coordinates":[62.46864,34.45185],"type":"Point"}
}