{
  "type": "Feature",
  "properties": {
    "gn:admin1_code":"01",
    "gn:admin2_code":"1123",
    "gn:asciiname":"Shaydukan",
    "gn:country_code":"AF",
    "gn:dem":1546,
    "gn:feature_class":"P",
    "gn:feature_code":"PPL",
    "gn:name":"Shayduk\u0101n",
    "gn:population":0,
    "gn:timezone":"Asia/Kabul",
    "iso:country":"AF",
    "name:und_x_variant":[
        "Say\u1e0fak\u0101n",
        "Sha\u012bolokan",
        "Shayduk\u0101n",
        "\u0634\u06cc\u062f\u06a9\u0627\u0646"
    ],
    "wof:name":"Shaydukan",
    "wof:placetype":"locality"
},
  "geometry": {"coordinates":[70.24250000000001,36.56975],"type":"Point"}
}