{
  "type": "Feature",
  "properties": {
    "gn:admin1_code":"30",
    "gn:admin2_code":"1605",
    "gn:asciiname":"Nakhchirabad",
    "gn:country_code":"AF",
    "gn:dem":308,
    "gn:feature_class":"P",
    "gn:feature_code":"PPL",
    "gn:name":"Nakhch\u012br\u0101b\u0101d",
    "gn:population":0,
    "gn:timezone":"Asia/Kabul",
    "iso:country":"AF",
    "name:und_x_variant":[
        "Nakhch\u012br\u0101b\u0101d",
        "Nakhj\u012br\u0101b\u0101d",
        "\u0646\u062e\u0686\u06cc\u0631 \u0622\u0628\u0627\u062f"
    ],
    "wof:name":"Nakhchirabad",
    "wof:placetype":"locality"
},
  "geometry": {"coordinates":[66.88815,37.01077],"type":"Point"}
}