{
  "type": "Feature",
  "properties": {
    "gn:admin1_code":"13",
    "gn:admin2_code":"107.0",
    "gn:asciiname":"Qal'ah-ye Haji",
    "gn:country_code":"AF",
    "gn:dem":1994,
    "gn:feature_class":"P",
    "gn:feature_code":"PPL",
    "gn:name":"Qal\u2018ah-ye H\u0101j\u012b",
    "gn:population":0,
    "gn:timezone":"Asia/Kabul",
    "iso:country":"AF",
    "name:und_x_variant":[
        "Qal\u2018ah-ye H\u0101j\u012b",
        "\u0642\u0644\u0639\u0647 \u062d\u0627\u062c\u06cc"
    ],
    "wof:name":"Qal'ah-ye Haji",
    "wof:placetype":"locality"
},
  "geometry": {"coordinates":[69.03134,34.62144],"type":"Point"}
}