{
  "type": "Feature",
  "properties": {
    "gn:admin1_code":"03",
    "gn:admin2_code":"1303.0",
    "gn:asciiname":"Tajikha-ye Kol-e Amchi",
    "gn:country_code":"AF",
    "gn:dem":627,
    "gn:feature_class":"P",
    "gn:feature_code":"PPL",
    "gn:name":"T\u0101jikh\u0101-ye K\u014dl-e Amch\u012b",
    "gn:population":0,
    "gn:timezone":"Asia/Kabul",
    "iso:country":"AF",
    "name:und_x_variant":[
        "Tadzhikkhan-Kuli-Amchi",
        "T\u0101jek-h\u0101-i-Kole Am\u010di",
        "T\u0101jekh\u0101-ye Kowl-e Amchi",
        "T\u0101jikh\u0101-ye K\u014dl-e Amch\u012b",
        "\u062a\u0627\u062c\u06a9 \u0647\u0627\u06cc \u06a9\u0648\u0644 \u0627\u0645\u0686\u06cc"
    ],
    "wof:name":"Tajikha-ye Kol-e Amchi",
    "wof:placetype":"locality"
},
  "geometry": {"coordinates":[68.55082,35.96879000000001],"type":"Point"}
}