{
  "type": "Feature",
  "properties": {
    "gn:admin1_code":"32",
    "gn:admin2_code":"1501",
    "gn:asciiname":"Tutah",
    "gn:country_code":"AF",
    "gn:dem":1109,
    "gn:feature_class":"P",
    "gn:feature_code":"PPL",
    "gn:name":"T\u016btah",
    "gn:population":0,
    "gn:timezone":"Asia/Kabul",
    "iso:country":"AF",
    "name:und_x_variant":[
        "T\u016bta",
        "Towteh",
        "T\u016btah",
        "\u062a\u0648\u062a\u0647"
    ],
    "wof:name":"Tutah",
    "wof:placetype":"locality"
},
  "geometry": {"coordinates":[68.03303000000001,36.32138],"type":"Point"}
}