{
  "type": "Feature",
  "properties": {
    "gn:admin1_code":"3",
    "gn:admin2_code":"1311.0",
    "gn:asciiname":"Chaharshambah Tepah",
    "gn:country_code":"AF",
    "gn:dem":525,
    "gn:feature_class":"P",
    "gn:feature_code":"PPL",
    "gn:name":"Chah\u0101rshambah Tepah",
    "gn:population":0,
    "gn:timezone":"Asia/Kabul",
    "iso:country":"AF",
    "name:fas_x_preferred":[
        "\u062a\u067e\u06c0 \u0686\u0647\u0627\u0631 \u0634\u0646\u0628\u0647"
    ],
    "name:rus_x_preferred":[
        "\u0427\u0430\u0445\u0430\u0440\u0448\u0430\u043c\u0431\u0430-\u0422\u0435\u043f\u0430"
    ],
    "name:und_x_variant":[
        "Chakharshamba-Tepa",
        "\u010cah\u0101r \u0160amba T\u0113pa",
        "Chah\u0101r Shambeh Tappeh",
        "Chah\u0101r Shanbeh Tappeh",
        "Chah\u0101rshambah Tepah",
        "\u0686\u0647\u0627\u0631 \u0634\u0646\u0628\u0647 \u062a\u067e\u0647"
    ],
    "wof:name":"Chaharshambah Tepah",
    "wof:placetype":"locality"
},
  "geometry": {"coordinates":[68.83471,36.29819000000001],"type":"Point"}
}