{
  "type": "Feature",
  "properties": {
    "gn:admin1_code":"27",
    "gn:admin2_code":"403.0",
    "gn:asciiname":"Chahar Paskhah",
    "gn:country_code":"AF",
    "gn:dem":3324,
    "gn:feature_class":"P",
    "gn:feature_code":"PPL",
    "gn:name":"Chah\u0101r Paskhah",
    "gn:population":0,
    "gn:timezone":"Asia/Kabul",
    "iso:country":"AF",
    "name:und_x_variant":[
        "\u010cah\u0101rpaskha",
        "Chakharpaskha",
        "Chah\u0101rpaskheh",
        "Chah\u0101r Paskhah",
        "\u0686\u0647\u0627\u0631 \u067e\u0633\u062e\u0647"
    ],
    "wof:name":"Chahar Paskhah",
    "wof:placetype":"locality"
},
  "geometry": {"coordinates":[68.23555,34.44152],"type":"Point"}
}