{
  "type": "Feature",
  "properties": {
    "gn:admin1_code":"37",
    "gn:admin2_code":"3207",
    "gn:asciiname":"Kadam Tanah",
    "gn:country_code":"AF",
    "gn:dem":1141,
    "gn:feature_class":"P",
    "gn:feature_code":"PPL",
    "gn:name":"Kadam T\u0101\u1e49ah",
    "gn:population":0,
    "gn:timezone":"Asia/Kabul",
    "iso:country":"AF",
    "name:fas_x_preferred":[
        "\u06a9\u062f\u0645 \u062a\u0627\u0646\u0647"
    ],
    "name:und_x_variant":[
        "Pogranichnyy Post Kadamtana",
        "Ka\u1e0fam T\u0101\u1e49a",
        "Kadam T\u0101\u1e49ah",
        "Kadam T\u0101nah",
        "\u06a9\u062f\u0645 \u062a\u0627\u06bc\u0647"
    ],
    "wof:name":"Kadam Tanah",
    "wof:placetype":"locality"
},
  "geometry": {"coordinates":[70.29809,33.39227],"type":"Point"}
}