{
  "type": "Feature",
  "properties": {
    "gn:admin1_code":"33",
    "gn:admin2_code":"3103",
    "gn:asciiname":"Kohistanat",
    "gn:country_code":"AF",
    "gn:dem":2184,
    "gn:feature_class":"P",
    "gn:feature_code":"PPL",
    "gn:name":"K\u014dhist\u0101n\u0101t",
    "gn:population":0,
    "gn:timezone":"Asia/Kabul",
    "iso:country":"AF",
    "name:und_x_variant":[
        "Kohest\u0101n\u0101t",
        "K\u016bhest\u0101n\u0101t",
        "K\u014dhist\u0101n\u0101t"
    ],
    "wof:name":"Kohistanat",
    "wof:placetype":"locality"
},
  "geometry": {"coordinates":[65.86667,35.81667],"type":"Point"}
}