{
  "type": "Feature",
  "properties": {
    "gn:admin1_code":"13",
    "gn:admin2_code":"110.0",
    "gn:asciiname":"Qal'ah-ye Khangal",
    "gn:country_code":"AF",
    "gn:dem":1811,
    "gn:feature_class":"P",
    "gn:feature_code":"PPL",
    "gn:name":"Qal\u2018ah-ye Kh\u0101ngal",
    "gn:population":0,
    "gn:timezone":"Asia/Kabul",
    "iso:country":"AF",
    "name:und_x_variant":[
        "Karezdzhadzhi",
        "K\u0101rayz-e J\u0101j\u012b",
        "K\u0101r\u012bz J\u0101ji",
        "K\u0101r\u0113z-e J\u0101j\u012b",
        "\u06a9\u0627\u0631\u06d0\u0632 \u062c\u0627\u062c\u06cc",
        "Qal\u2018ah-ye Kh\u0101ngal",
        "\u0642\u0644\u0639\u0647 \u062e\u0627\u0646\u06af\u0644"
    ],
    "wof:name":"Qal'ah-ye Khangal",
    "wof:placetype":"locality"
},
  "geometry": {"coordinates":[69.29611,34.47282],"type":"Point"}
}