{
  "type": "Feature",
  "properties": {
    "gn:admin1_code":"05",
    "gn:admin2_code":"2802",
    "gn:asciiname":"Jow Qol",
    "gn:country_code":"AF",
    "gn:dem":3056,
    "gn:feature_class":"P",
    "gn:feature_code":"PPL",
    "gn:name":"Jow Q\u014dl",
    "gn:population":0,
    "gn:timezone":"Asia/Kabul",
    "iso:country":"AF",
    "name:rus_x_preferred":[
        "Dzhaukul\u2019"
    ],
    "name:und_x_variant":[
        "Jawq\u014dl",
        "Jaokul",
        "Jow Qowl",
        "Jow Q\u014dl",
        "Jawqul",
        "\u062c\u0648 \u0642\u0648\u0644"
    ],
    "wof:name":"Jow Qol",
    "wof:placetype":"locality"
},
  "geometry": {"coordinates":[68.03574999999999,34.73631],"type":"Point"}
}