{
  "type": "Feature",
  "properties": {
    "gn:admin1_code":"28",
    "gn:admin2_code":"2511",
    "gn:asciiname":"Lakey Kelay",
    "gn:country_code":"AF",
    "gn:dem":2029,
    "gn:feature_class":"P",
    "gn:feature_code":"PPL",
    "gn:name":"Lak\u00eay K\u00ealay",
    "gn:population":0,
    "gn:timezone":"Asia/Kabul",
    "iso:country":"AF",
    "name:fas_x_preferred":[
        "\u0642\u0631\u064a\u06c0 \u0644\u0643\u06cc"
    ],
    "name:und_x_variant":[
        "Lakaykalay",
        "Lak\u0113y Kalay",
        "Lak\u00eay K\u00ealay",
        "\u0644\u06a9\u06cd \u06a9\u0644\u06cc"
    ],
    "wof:name":"Lakey Kelay",
    "wof:placetype":"locality"
},
  "geometry": {"coordinates":[67.45011,32.0161],"type":"Point"}
}