{
  "type": "Feature",
  "properties": {
    "gn:admin1_code":"18",
    "gn:admin2_code":"814.0",
    "gn:asciiname":"Khitgai",
    "gn:country_code":"AF",
    "gn:dem":425,
    "gn:feature_class":"P",
    "gn:feature_code":"PPL",
    "gn:name":"Khitga\u012b",
    "gn:population":0,
    "gn:timezone":"Asia/Kabul",
    "iso:country":"AF",
    "name:fas_x_preferred":[
        "\u062e\u062a\u06af\u06cc"
    ],
    "name:und_x_variant":[
        "Khetgay",
        "Kh\u00eatga\u012b",
        "Khitga\u012b"
    ],
    "wof:name":"Khitgai",
    "wof:placetype":"locality"
},
  "geometry": {"coordinates":[71.06910999999999,34.21408],"type":"Point"}
}