{
  "type": "Feature",
  "properties": {
    "gn:admin1_code":"13",
    "gn:admin2_code":"108.0",
    "gn:asciiname":"Shah Mazar",
    "gn:country_code":"AF",
    "gn:dem":2034,
    "gn:feature_class":"P",
    "gn:feature_code":"PPL",
    "gn:name":"Sh\u0101h Maz\u0101r",
    "gn:population":0,
    "gn:timezone":"Asia/Kabul",
    "iso:country":"AF",
    "name:und_x_variant":[
        "Sh\u0101h Maz\u0101r",
        "\u0634\u0627\u0647 \u0645\u0632\u0627\u0631"
    ],
    "wof:name":"Shah Mazar",
    "wof:placetype":"locality"
},
  "geometry": {"coordinates":[69.00289000000001,34.55063],"type":"Point"}
}