{
  "type": "Feature",
  "properties": {
    "gn:admin1_code":"37",
    "gn:admin2_code":"3204",
    "gn:asciiname":"Manah",
    "gn:country_code":"AF",
    "gn:dem":2043,
    "gn:feature_class":"P",
    "gn:feature_code":"PPL",
    "gn:name":"Ma\u1e49ah",
    "gn:population":0,
    "gn:timezone":"Asia/Kabul",
    "iso:country":"AF",
    "name:ceb_x_preferred":[
        "Manah"
    ],
    "name:swe_x_preferred":[
        "Manah"
    ],
    "name:und_x_variant":[
        "Mana",
        "Ma\u1e49a",
        "\u0645\u06bc\u0647",
        "Ma\u1e49ah"
    ],
    "wof:name":"Manah",
    "wof:placetype":"locality"
},
  "geometry": {"coordinates":[69.48473,33.14076],"type":"Point"}
}