{
  "type": "Feature",
  "properties": {
    "gn:admin1_code":"5",
    "gn:admin2_code":"2806.0",
    "gn:asciiname":"Siyah Qol",
    "gn:country_code":"AF",
    "gn:dem":3203,
    "gn:feature_class":"P",
    "gn:feature_code":"PPL",
    "gn:name":"Siy\u0101h Q\u014dl",
    "gn:population":0,
    "gn:timezone":"Asia/Kabul",
    "iso:country":"AF",
    "name:und_x_variant":[
        "Sy\u0101hq\u014dl",
        "S\u012b\u0101h Q\u014dl",
        "S\u012b\u0101hqowl",
        "Siy\u0101h Q\u014dl",
        "\u0633\u064a\u0627\u0647 \u0642\u0648\u0644"
    ],
    "wof:name":"Siyah Qol",
    "wof:placetype":"locality"
},
  "geometry": {"coordinates":[66.93304000000001,33.99108],"type":"Point"}
}