{
  "type": "Feature",
  "properties": {
    "gn:admin1_code":"3",
    "gn:admin2_code":"1310.0",
    "gn:asciiname":"Shorah Chah",
    "gn:country_code":"AF",
    "gn:dem":1343,
    "gn:feature_class":"P",
    "gn:feature_code":"PPL",
    "gn:name":"Sh\u014drah Ch\u0101h",
    "gn:population":0,
    "gn:timezone":"Asia/Kabul",
    "iso:country":"AF",
    "name:und_x_variant":[
        "S\u014d\u1e5fac\u0101h (1)",
        "Sh\u016breh Ch\u0101h (1)",
        "Sh\u014drah Ch\u0101h",
        "\u0634\u0648\u0631\u0647 \u0686\u0627\u0647"
    ],
    "wof:name":"Shorah Chah",
    "wof:placetype":"locality"
},
  "geometry": {"coordinates":[69.13911999999999,36.09994],"type":"Point"}
}