{
  "type": "Feature",
  "properties": {
    "gn:admin1_code":"10",
    "gn:admin2_code":"2302.0",
    "gn:asciiname":"'Abdul 'Aziz Kelay",
    "gn:country_code":"AF",
    "gn:dem":792,
    "gn:feature_class":"P",
    "gn:feature_code":"PPL",
    "gn:name":"\u2018Abdul \u2018Az\u012bz K\u00ealay",
    "gn:population":0,
    "gn:timezone":"Asia/Kabul",
    "iso:country":"AF",
    "name:fas_x_preferred":[
        "\u0642\u0631\u064a\u06c0 \u0639\u0628\u062f \u0627\u0644\u0639\u0632\u06cc\u0632"
    ],
    "name:rus_x_preferred":[
        "Abdul\u2019aziz-Kalay"
    ],
    "name:und_x_variant":[
        "\u2018Aziz Kalay",
        "\u2018Ab\u1e0ful \u2018Az\u012bz Kalay",
        "\u2018Abdul \u2018Az\u012bz K\u00ealay",
        "\u0639\u0628\u062f\u0644 \u0639\u0632\u06cc\u0632 \u06a9\u0644\u06cc",
        "\u2018Abdol \u2018Az\u012bz Kalay"
    ],
    "wof:name":"'Abdul 'Aziz Kelay",
    "wof:placetype":"locality"
},
  "geometry": {"coordinates":[64.36251,31.68418],"type":"Point"}
}