{
  "type": "Feature",
  "properties": {
    "gn:admin1_code":"24",
    "gn:admin2_code":"1402.0",
    "gn:asciiname":"Kalbat",
    "gn:country_code":"AF",
    "gn:dem":391,
    "gn:feature_class":"P",
    "gn:feature_code":"PPL",
    "gn:name":"Kalb\u0101t",
    "gn:population":0,
    "gn:timezone":"Asia/Kabul",
    "iso:country":"AF",
    "name:und_x_variant":[
        "Kalb\u0101t",
        "\u06a9\u0644\u0628\u0627\u062a"
    ],
    "wof:name":"Kalbat",
    "wof:placetype":"locality"
},
  "geometry": {"coordinates":[69.16554000000001,37.10637],"type":"Point"}
}