{
  "type": "Feature",
  "properties": {
    "gn:admin1_code":"10",
    "gn:admin2_code":"2308",
    "gn:asciiname":"Hukumat-e Nad 'Ali",
    "gn:country_code":"AF",
    "gn:dem":797,
    "gn:feature_class":"P",
    "gn:feature_code":"PPLA2",
    "gn:name":"\u1e28uk\u016bmat-e N\u0101d \u2018Al\u012b",
    "gn:population":0,
    "gn:timezone":"Asia/Kabul",
    "iso:country":"AF",
    "name:pus_x_preferred":[
        "N\u0101d-e \u2018Al\u012b"
    ],
    "name:und_x_variant":[
        "\u1e28ok\u016bmat-e N\u0101d-e \u2018Al\u012b",
        "Khukumati-Nadi-Ali",
        "N\u0101d-i-Al\u012b",
        "\u1e28ok\u016bmat\u012b N\u0101d-e \u2018Ali",
        "N\u0101de Ali",
        "N\u0101d\u2018al\u012b",
        "\u062d\u0643\u0648\u0645\u062a\u0654 \u0646\u0627\u062f\u0654 \u0639\u0644\u06cc",
        "\u1e28ok\u016bmat\u012b N\u0101d-e \u2018Al\u012b",
        "\u062d\u06a9\u0648\u0645\u062a\u06cc \u0646\u0627\u062f \u0639\u0644\u06cc",
        "\u1e28ok\u016bmat-e N\u0101d \u2018Al\u012b",
        "\u062d\u0643\u0648\u0645\u062a \u0646\u0627\u062f \u0639\u0644\u06cc",
        "\u1e28uk\u016bmat-e N\u0101d \u2018Al\u012b",
        "N\u0101d \u2018Al\u012b",
        "\u0646\u0627\u062f \u0639\u0644\u06cc"
    ],
    "wof:name":"Hukumat-e Nad 'Ali",
    "wof:placetype":"locality"
},
  "geometry": {"coordinates":[64.23981999999999,31.64286],"type":"Point"}
}