{
  "type": "Feature",
  "properties": {
    "gn:admin1_code":"18",
    "gn:admin2_code":"802.0",
    "gn:asciiname":"Kalatah",
    "gn:country_code":"AF",
    "gn:dem":856,
    "gn:feature_class":"P",
    "gn:feature_code":"PPL",
    "gn:name":"Kalatah",
    "gn:population":0,
    "gn:timezone":"Asia/Kabul",
    "iso:country":"AF",
    "name:fas_x_preferred":[
        "\u0643\u0644\u062a\u0647"
    ],
    "name:und_x_variant":[
        "\u06a9\u0644\u062a\u0647",
        "Kalata"
    ],
    "wof:name":"Kalatah",
    "wof:placetype":"locality"
},
  "geometry": {"coordinates":[70.16764999999999,34.3845],"type":"Point"}
}