{
  "type": "Feature",
  "properties": {
    "gn:admin1_code":"18",
    "gn:admin2_code":"803.0",
    "gn:asciiname":"Shaykhan",
    "gn:country_code":"AF",
    "gn:dem":1856,
    "gn:feature_class":"P",
    "gn:feature_code":"PPL",
    "gn:name":"Shaykh\u0101n",
    "gn:population":0,
    "gn:timezone":"Asia/Kabul",
    "iso:country":"AF",
    "name:fas_x_preferred":[
        "\u0634\u064a\u062e\u0627\u0646"
    ],
    "name:und_x_variant":[
        "\u0160aykh\u0101n",
        "Shaykhan",
        "Shaykh\u0101n",
        "Sheykh\u0101n",
        "\u0634\u064a\u062e\u0627\u0646",
        "\u0634\u06cc\u062e\u0627\u0646"
    ],
    "wof:name":"Shaykhan",
    "wof:placetype":"locality"
},
  "geometry": {"coordinates":[69.87736,34.24077],"type":"Point"}
}