{
  "type": "Feature",
  "properties": {
    "gn:admin1_code":"39",
    "gn:admin2_code":"2604.0",
    "gn:asciiname":"Darwan",
    "gn:country_code":"AF",
    "gn:dem":1176,
    "gn:feature_class":"P",
    "gn:feature_code":"PPL",
    "gn:name":"D\u0101rw\u0101n",
    "gn:population":0,
    "gn:timezone":"Asia/Kabul",
    "iso:country":"AF",
    "name:fas_x_preferred":[
        "\u062f\u0631\u0648\u0627\u0646"
    ],
    "name:und_x_variant":[
        "\u1e0e\u0101\u1e5fw\u0101n",
        "Darvan",
        "D\u0101rw\u0101n",
        "\u062f\u0627\u0631\u0648\u0627\u0646",
        "Darv\u0101n"
    ],
    "wof:name":"Darwan",
    "wof:placetype":"locality"
},
  "geometry": {"coordinates":[65.74386,32.98274],"type":"Point"}
}