{
  "type": "Feature",
  "properties": {
    "gn:admin1_code":"29",
    "gn:admin2_code":"2914.0",
    "gn:asciiname":"Bada Khunah",
    "gn:country_code":"AF",
    "gn:dem":2393,
    "gn:feature_class":"P",
    "gn:feature_code":"PPL",
    "gn:name":"Ba\u1e0f\u0101 Kh\u016bnah",
    "gn:population":0,
    "gn:timezone":"Asia/Kabul",
    "iso:country":"AF",
    "name:und_x_variant":[
        "Badakhuna",
        "Bad\u0101 Khona",
        "\u0628\u0689\u0627 \u062e\u0648\u0646\u0647",
        "Bad\u0101 Kh\u0101neh",
        "Ba\u1e0f\u0101 Kh\u016bnah",
        "Bad\u0101 Kh\u0101nah"
    ],
    "wof:name":"Bada Khunah",
    "wof:placetype":"locality"
},
  "geometry": {"coordinates":[68.98594,33.0973],"type":"Point"}
}