{
  "type": "Feature",
  "properties": {
    "gn:admin1_code":"35",
    "gn:admin2_code":"902.0",
    "gn:asciiname":"'Aziz Khan Kelay",
    "gn:country_code":"AF",
    "gn:dem":615,
    "gn:feature_class":"P",
    "gn:feature_code":"PPL",
    "gn:name":"\u2018Az\u012bz Kh\u0101n K\u00ealay",
    "gn:population":0,
    "gn:timezone":"Asia/Kabul",
    "iso:country":"AF",
    "name:und_x_variant":[
        "Azizkhankalay",
        "\u2018Az\u012bzkh\u0101n Kalay",
        "\u2018Az\u012bz Kh\u0101n K\u00ealay",
        "\u0639\u0632\u06cc\u0632 \u062e\u0627\u0646 \u06a9\u0644\u06cc",
        "Nah\u0101l-e \u2018Az\u012bz Kh\u0101n",
        "\u0646\u0647\u0627\u0644 \u0639\u0632\u06cc\u0632 \u062e\u0627\u0646"
    ],
    "wof:name":"'Aziz Khan Kelay",
    "wof:placetype":"locality"
},
  "geometry": {"coordinates":[70.35647,34.51213],"type":"Point"}
}