{
  "type": "Feature",
  "properties": {
    "gn:admin1_code":"2",
    "gn:admin2_code":"1906.0",
    "gn:asciiname":"Chilunak",
    "gn:country_code":"AF",
    "gn:dem":906,
    "gn:feature_class":"P",
    "gn:feature_code":"PPL",
    "gn:name":"Chil\u016bnak",
    "gn:population":0,
    "gn:timezone":"Asia/Kabul",
    "iso:country":"AF",
    "name:und_x_variant":[
        "\u010cil\u016bnak",
        "Chil\u016bnak",
        "\u0686\u0644\u0648\u0646\u06a9",
        "Ch\u012bl\u016bnak"
    ],
    "wof:name":"Chilunak",
    "wof:placetype":"locality"
},
  "geometry": {"coordinates":[63.52876,35.51353],"type":"Point"}
}