{
  "type": "Feature",
  "properties": {
    "gn:admin1_code":"01",
    "gn:admin2_code":"1128.0",
    "gn:asciiname":"Anj",
    "gn:country_code":"AF",
    "gn:dem":2293,
    "gn:feature_class":"P",
    "gn:feature_code":"PPL",
    "gn:name":"Anj",
    "gn:population":0,
    "gn:timezone":"Asia/Kabul",
    "iso:country":"AF",
    "name:und_x_variant":[
        "\u0627\u0646\u062c"
    ],
    "wof:name":"Anj",
    "wof:placetype":"locality"
},
  "geometry": {"coordinates":[70.41339000000001,37.49708],"type":"Point"}
}