{
  "type": "Feature",
  "properties": {
    "gn:admin1_code":"26",
    "gn:admin2_code":"1215",
    "gn:asciiname":"Qal'ah-ye Mamay",
    "gn:country_code":"AF",
    "gn:dem":593,
    "gn:feature_class":"P",
    "gn:feature_code":"PPL",
    "gn:name":"Qal\u2018ah-ye M\u0101may",
    "gn:population":0,
    "gn:timezone":"Asia/Kabul",
    "iso:country":"AF",
    "name:und_x_variant":[
        "Qala-i-M\u0101may",
        "Qal\u2018eh-ye M\u0101mah",
        "Qala M\u0101may",
        "Qal\u2018eh-ye M\u0101mey",
        "Qal\u2018ah-ye M\u0101may",
        "\u0642\u0644\u0639\u06c0 \u0645\u0627\u0645\u06cc"
    ],
    "wof:name":"Qal'ah-ye Mamay",
    "wof:placetype":"locality"
},
  "geometry": {"coordinates":[69.60686,36.99071],"type":"Point"}
}