{
  "type": "Feature",
  "properties": {
    "gn:admin1_code":"11",
    "gn:admin2_code":"2005",
    "gn:asciiname":"Ma'lumah",
    "gn:country_code":"AF",
    "gn:dem":1547,
    "gn:feature_class":"P",
    "gn:feature_code":"PPL",
    "gn:name":"Ma\u2018l\u016bmah",
    "gn:population":0,
    "gn:timezone":"Asia/Kabul",
    "iso:country":"AF",
    "name:und_x_variant":[
        "Ma\u2018l\u016bma",
        "Maluma",
        "Ma\u2018l\u016bmeh",
        "Ma\u2018l\u016bmah",
        "\u0645\u0639\u0644\u0648\u0645\u0647"
    ],
    "wof:name":"Ma'lumah",
    "wof:placetype":"locality"
},
  "geometry": {"coordinates":[62.70458000000001,34.48661],"type":"Point"}
}