{
  "type": "Feature",
  "properties": {
    "gn:admin1_code":"9",
    "gn:admin2_code":"2707.0",
    "gn:asciiname":"Pesh Band",
    "gn:country_code":"AF",
    "gn:dem":3152,
    "gn:feature_class":"P",
    "gn:feature_code":"PPL",
    "gn:name":"P\u0113sh Band",
    "gn:population":0,
    "gn:timezone":"Asia/Kabul",
    "iso:country":"AF",
    "name:und_x_variant":[
        "P\u0113\u0161band",
        "Peshband",
        "Paysh Band",
        "P\u012bshband",
        "P\u0113sh Band",
        "\u067e\u06d0\u0634 \u0628\u0646\u062f"
    ],
    "wof:name":"Pesh Band",
    "wof:placetype":"locality"
},
  "geometry": {"coordinates":[66.55044000000001,34.52442],"type":"Point"}
}