{
  "type": "Feature",
  "properties": {
    "gn:admin1_code":"8",
    "gn:admin2_code":"607.0",
    "gn:asciiname":"Towp",
    "gn:cc2":"AF",
    "gn:country_code":"AF",
    "gn:dem":2985,
    "gn:feature_class":"P",
    "gn:feature_code":"PPL",
    "gn:name":"Towp",
    "gn:population":0,
    "gn:timezone":"Asia/Kabul",
    "iso:country":"AF",
    "name:und_x_variant":[
        "T\u014dp",
        "Towp"
    ],
    "wof:name":"Towp",
    "wof:placetype":"locality"
},
  "geometry": {"coordinates":[67.38389000000001,33.23722],"type":"Point"}
}