{
  "type": "Feature",
  "properties": {
    "gn:admin1_code":"31",
    "gn:admin2_code":"1702.0",
    "gn:asciiname":"Khwajah Du Koh-e Now",
    "gn:country_code":"AF",
    "gn:dem":301,
    "gn:feature_class":"P",
    "gn:feature_code":"PPL",
    "gn:name":"Khw\u0101jah D\u016b K\u014dh-e Now",
    "gn:population":0,
    "gn:timezone":"Asia/Kabul",
    "iso:country":"AF",
    "name:und_x_variant":[
        "Khw\u0101jah D\u014d K\u014dh Now",
        "Khv\u0101jeh Do K\u016bh-e Now",
        "Khw\u0101jah D\u016b K\u014dh-e Now",
        "\u062e\u0648\u0627\u062c\u0647 \u062f\u0648 \u06a9\u0648\u0647 \u0646\u0648"
    ],
    "wof:name":"Khwajah Du Koh-e Now",
    "wof:placetype":"locality"
},
  "geometry": {"coordinates":[65.57836,36.8426],"type":"Point"}
}