{
  "type": "Feature",
  "properties": {
    "gn:admin1_code":"41",
    "gn:admin2_code":"3407.0",
    "gn:asciiname":"Ghowuch",
    "gn:country_code":"AF",
    "gn:dem":2485,
    "gn:feature_class":"P",
    "gn:feature_code":"PPL",
    "gn:name":"Ghowuch",
    "gn:population":0,
    "gn:timezone":"Asia/Kabul",
    "iso:country":"AF",
    "name:und_x_variant":[
        "Ghawu\u010d",
        "Ghowch",
        "Ghawuch",
        "Ghowuch",
        "\u063a\u0648\u0686"
    ],
    "wof:name":"Ghowuch",
    "wof:placetype":"locality"
},
  "geometry": {"coordinates":[66.66096999999999,33.87902],"type":"Point"}
}