{
  "type": "Feature",
  "properties": {
    "gn:admin1_code":"27",
    "gn:admin2_code":"403.0",
    "gn:asciiname":"Ray Shutur",
    "gn:country_code":"AF",
    "gn:dem":3321,
    "gn:feature_class":"P",
    "gn:feature_code":"PPL",
    "gn:name":"R\u0101y Shutur",
    "gn:population":0,
    "gn:timezone":"Asia/Kabul",
    "iso:country":"AF",
    "name:und_x_variant":[
        "Rayshutur",
        "R\u0101y\u0161otur",
        "R\u0101h-e Shotor",
        "Ashtur",
        "R\u0101y Shutur",
        "\u0631\u0627\u06cc \u0634\u062a\u0631"
    ],
    "wof:name":"Ray Shutur",
    "wof:placetype":"locality"
},
  "geometry": {"coordinates":[68.20537,34.61645],"type":"Point"}
}