{
  "type": "Feature",
  "properties": {
    "gn:admin1_code":"13",
    "gn:admin2_code":"111.0",
    "gn:asciiname":"Malik Khel",
    "gn:country_code":"AF",
    "gn:dem":2156,
    "gn:feature_class":"P",
    "gn:feature_code":"PPL",
    "gn:name":"Malik Kh\u0113l",
    "gn:population":0,
    "gn:timezone":"Asia/Kabul",
    "iso:country":"AF",
    "name:rus_x_preferred":[
        "Malikkheyl\u2019"
    ],
    "name:und_x_variant":[
        "Malekkh\u0113l",
        "Malik Kh\u0113l",
        "\u0645\u0644\u06a9 \u062e\u06d0\u0644"
    ],
    "wof:name":"Malik Khel",
    "wof:placetype":"locality"
},
  "geometry": {"coordinates":[69.39310999999999,34.38166],"type":"Point"}
}