{
  "type": "Feature",
  "properties": {
    "gn:admin1_code":"05",
    "gn:admin2_code":"2806.0",
    "gn:asciiname":"Dahan-e Ragardu",
    "gn:country_code":"AF",
    "gn:dem":3022,
    "gn:feature_class":"P",
    "gn:feature_code":"PPL",
    "gn:name":"Dah\u0101n-e R\u0101gard\u016b",
    "gn:population":0,
    "gn:timezone":"Asia/Kabul",
    "iso:country":"AF",
    "name:und_x_variant":[
        "Dakhani-Ragardu",
        "\u1e0eahane \u1e5e\u0101ga\u1e5f\u1e0fu",
        "Dahan-e R\u0101hgard",
        "Dahan-e R\u0101h Gard\u016b",
        "Dah\u0101n-e R\u0101gard\u016b",
        "\u062f\u0647\u0627\u0646 \u0631\u0627\u06af\u0631\u062f\u0648"
    ],
    "wof:name":"Dahan-e Ragardu",
    "wof:placetype":"locality"
},
  "geometry": {"coordinates":[67.11360999999999,34.27678],"type":"Point"}
}