{
  "type": "Feature",
  "properties": {
    "gn:admin1_code":"14",
    "gn:admin2_code":"204",
    "gn:asciiname":"Pashah'i",
    "gn:country_code":"AF",
    "gn:dem":1792,
    "gn:feature_class":"P",
    "gn:feature_code":"PPL",
    "gn:name":"Pashah\u2019\u012b",
    "gn:population":0,
    "gn:timezone":"Asia/Kabul",
    "iso:country":"AF",
    "name:fas_x_preferred":[
        "\u067e\u0627\u0634\u0627\u0626\u06cc"
    ],
    "name:rus_x_preferred":[
        "\u041f\u0430\u0448\u0430\u0438"
    ],
    "name:und_x_variant":[
        "Pashai",
        "Pa\u0161a\u2019i",
        "P\u0101sh\u0101\u2019\u012b",
        "Pashah\u2019\u012b",
        "\u067e\u0634\u0647 \u0626\u06cc"
    ],
    "wof:name":"Pashah'i",
    "wof:placetype":"locality"
},
  "geometry": {"coordinates":[69.62039,35.0041],"type":"Point"}
}