{
  "type": "Feature",
  "properties": {
    "gn:admin1_code":"14",
    "gn:admin2_code":"204.0",
    "gn:asciiname":"Yasin Khel",
    "gn:country_code":"AF",
    "gn:dem":2176,
    "gn:feature_class":"P",
    "gn:feature_code":"PPL",
    "gn:name":"Y\u0101s\u012bn Kh\u0113l",
    "gn:population":0,
    "gn:timezone":"Asia/Kabul",
    "iso:country":"AF",
    "name:fas_x_preferred":[
        "\u064a\u0627\u0633\u064a\u0646 \u062e\u064a\u0644"
    ],
    "name:rus_x_preferred":[
        "\u042f\u0441\u0438\u043d\u0445\u0435\u0439\u043b\u044c"
    ],
    "name:und_x_variant":[
        "Yasinkheyl\u2019",
        "Y\u0101s\u012bn Kh\u0113l",
        "Y\u0101s\u012bnkheyl",
        "\u06cc\u0627\u0633\u06cc\u0646 \u062e\u06d0\u0644"
    ],
    "wof:name":"Yasin Khel",
    "wof:placetype":"locality"
},
  "geometry": {"coordinates":[69.57539,35.06257],"type":"Point"}
}