{
  "type": "Feature",
  "properties": {
    "gn:admin1_code":"29",
    "gn:admin2_code":"2915",
    "gn:asciiname":"Koti Khel",
    "gn:country_code":"AF",
    "gn:dem":2121,
    "gn:feature_class":"P",
    "gn:feature_code":"PPL",
    "gn:name":"K\u014d\u1e6f\u012b Kh\u0113l",
    "gn:population":0,
    "gn:timezone":"Asia/Kabul",
    "iso:country":"AF",
    "name:rus_x_preferred":[
        "Kotikheyl\u2019"
    ],
    "name:und_x_variant":[
        "Kotikh\u0113l",
        "\u06a9\u0648\u067c\u06cc \u062e\u06d0\u0644",
        "Kowt\u012b Kheyl",
        "K\u014d\u1e6f\u012b Kh\u0113l"
    ],
    "wof:name":"Koti Khel",
    "wof:placetype":"locality"
},
  "geometry": {"coordinates":[68.81558000000001,33.24792],"type":"Point"}
}