{
  "type": "Feature",
  "properties": {
    "gn:admin1_code":"41",
    "gn:admin2_code":"3408",
    "gn:asciiname":"Siyah Kharak-e Naw Bala",
    "gn:country_code":"AF",
    "gn:dem":2649,
    "gn:feature_class":"P",
    "gn:feature_code":"PPL",
    "gn:name":"Siy\u0101h Kharak-e N\u0101w B\u0101l\u0101",
    "gn:population":0,
    "gn:timezone":"Asia/Kabul",
    "iso:country":"AF",
    "name:und_x_variant":[
        "Siakhkhuraki-Naubala",
        "Sy\u0101hkho\u1e5fake",
        "Sy\u0101hkho\u1e5fake Nawb\u0101l\u0101",
        "S\u012b\u0101h Kharak-e N\u0101w B\u0101l\u0101",
        "S\u012b\u0101hkharak-e N\u0101wb\u0101l\u0101",
        "Siy\u0101h Kharak-e N\u0101w B\u0101l\u0101",
        "\u0633\u064a\u0627\u0647 \u062e\u0631\u06a9 \u0646\u0627\u0648 \u0628\u0627\u0644\u0627"
    ],
    "wof:name":"Siyah Kharak-e Naw Bala",
    "wof:placetype":"locality"
},
  "geometry": {"coordinates":[66.09318,34.25622],"type":"Point"}
}