{
  "type": "Feature",
  "properties": {
    "gn:admin1_code":"10",
    "gn:admin2_code":"2303",
    "gn:asciiname":"Karez-e 'Abdul Malik",
    "gn:country_code":"AF",
    "gn:dem":1051,
    "gn:feature_class":"P",
    "gn:feature_code":"PPL",
    "gn:name":"K\u0101r\u0113z-e \u2018Abdul Malik",
    "gn:population":0,
    "gn:timezone":"Asia/Kabul",
    "iso:country":"AF",
    "name:rus_x_preferred":[
        "Karezi-Abdul\u2019malik"
    ],
    "name:und_x_variant":[
        "Abdul Masek",
        "K\u0101\u1e5f\u0113ze \u2018Ab\u1e0ful Malek",
        "K\u0101r\u0113z-e \u2018Abdul Malik",
        "\u06a9\u0627\u0631\u06d0\u0632 \u0639\u0628\u062f\u0644 \u0645\u0644\u06a9",
        "K\u0101r\u012bz-e \u2018Abd ol Malek"
    ],
    "wof:name":"Karez-e 'Abdul Malik",
    "wof:placetype":"locality"
},
  "geometry": {"coordinates":[64.99930999999999,32.37548],"type":"Point"}
}