{
  "type": "Feature",
  "properties": {
    "gn:admin1_code":"08",
    "gn:admin2_code":"605",
    "gn:asciiname":"Gulmir",
    "gn:country_code":"AF",
    "gn:dem":2451,
    "gn:feature_class":"P",
    "gn:feature_code":"PPL",
    "gn:name":"Gulm\u012br",
    "gn:population":0,
    "gn:timezone":"Asia/Kabul",
    "iso:country":"AF",
    "name:und_x_variant":[
        "Gulmi\u1e5f",
        "Golm\u012br",
        "Gulm\u012br",
        "\u06af\u0644\u0645\u06cc\u0631"
    ],
    "wof:name":"Gulmir",
    "wof:placetype":"locality"
},
  "geometry": {"coordinates":[67.05119999999999,33.40322],"type":"Point"}
}