{
  "type": "Feature",
  "properties": {
    "gn:admin1_code":"02",
    "gn:admin2_code":"1904.0",
    "gn:asciiname":"Seyyed Sakhaman",
    "gn:country_code":"AF",
    "gn:dem":1969,
    "gn:feature_class":"P",
    "gn:feature_code":"PPL",
    "gn:name":"Seyyed Sakh\u0101man",
    "gn:population":0,
    "gn:timezone":"Asia/Kabul",
    "iso:country":"AF",
    "name:und_x_variant":[
        "Say\u1e0f Sakhk\u0101man",
        "Seyyed Sakh\u0101man"
    ],
    "wof:name":"Seyyed Sakhaman",
    "wof:placetype":"locality"
},
  "geometry": {"coordinates":[64.16868000000001,34.8394],"type":"Point"}
}