{
  "type": "Feature",
  "properties": {
    "gn:admin1_code":"40",
    "gn:admin2_code":"308.0",
    "gn:asciiname":"Qal'ah-ye Malik",
    "gn:country_code":"AF",
    "gn:dem":1503,
    "gn:feature_class":"P",
    "gn:feature_code":"PPL",
    "gn:name":"Qal\u2018ah-ye Malik",
    "gn:population":0,
    "gn:timezone":"Asia/Kabul",
    "iso:country":"AF",
    "name:fas_x_preferred":[
        "\u0642\u0644\u0639\u06c0 \u0645\u0644\u0643"
    ],
    "name:und_x_variant":[
        "Kalayi-Malik",
        "Qal\u2018a Malek",
        "Qal\u2018eh-ye Malak",
        "\u0642\u0644\u0639\u06c0 \u0645\u0644\u0643",
        "\u0642\u0644\u0639\u06c0 \u0645\u0644\u06a9",
        "Qal\u2018ah-ye Malik"
    ],
    "wof:name":"Qal'ah-ye Malik",
    "wof:placetype":"locality"
},
  "geometry": {"coordinates":[69.20437,34.97191],"type":"Point"}
}