{
  "type": "Feature",
  "properties": {
    "gn:admin1_code":"23",
    "gn:admin2_code":"2413",
    "gn:asciiname":"Kwat",
    "gn:country_code":"AF",
    "gn:dem":1926,
    "gn:feature_class":"P",
    "gn:feature_code":"PPL",
    "gn:name":"Kwat",
    "gn:population":0,
    "gn:timezone":"Asia/Kabul",
    "iso:country":"AF",
    "name:und_x_variant":[
        "Kvat",
        "Kwat",
        "\u06a9\u0648\u062a"
    ],
    "wof:name":"Kwat",
    "wof:placetype":"locality"
},
  "geometry": {"coordinates":[67.07701,31.25176],"type":"Point"}
}