{
  "type": "Feature",
  "properties": {
    "gn:admin1_code":"08",
    "gn:admin2_code":"615",
    "gn:asciiname":"Karim Dad Kala",
    "gn:country_code":"AF",
    "gn:dem":2114,
    "gn:feature_class":"P",
    "gn:feature_code":"PPL",
    "gn:name":"Kar\u012bm D\u0101d Kal\u0101",
    "gn:population":0,
    "gn:timezone":"Asia/Kabul",
    "iso:country":"AF",
    "name:und_x_variant":[
        "Karimdadkala",
        "Kar\u012bmd\u0101d Kal\u0101",
        "Ka\u1e5f\u012bm\u1e0f\u0101\u1e0f Kal\u0101",
        "Kar\u012bm D\u0101d Kal\u0101",
        "\u06a9\u0631\u06cc\u0645 \u062f\u0627\u062f \u06a9\u0644\u0627"
    ],
    "wof:name":"Karim Dad Kala",
    "wof:placetype":"locality"
},
  "geometry": {"coordinates":[68.61538,33.42528],"type":"Point"}
}