{
  "type": "Feature",
  "properties": {
    "gn:admin1_code":"9",
    "gn:admin2_code":"2701.0",
    "gn:asciiname":"Asya Bayd",
    "gn:country_code":"AF",
    "gn:dem":2259,
    "gn:feature_class":"P",
    "gn:feature_code":"PPL",
    "gn:name":"\u0100sy\u0101 Bayd",
    "gn:population":0,
    "gn:timezone":"Asia/Kabul",
    "iso:country":"AF",
    "name:und_x_variant":[
        "\u0100sy\u0101b\u0113\u1e0f",
        "\u0100s\u012b\u0101b\u012bd",
        "\u0100sy\u0101b\u012bd",
        "\u0100sy\u0101 Bayd",
        "\u0622\u0633\u06cc\u0627 \u0628\u06cc\u062f"
    ],
    "wof:name":"Asya Bayd",
    "wof:placetype":"locality"
},
  "geometry": {"coordinates":[64.56953,34.65998],"type":"Point"}
}