{
  "type": "Feature",
  "properties": {
    "gn:admin1_code":"41",
    "gn:admin2_code":"3401.0",
    "gn:asciiname":"Maysh-e Sufla",
    "gn:country_code":"AF",
    "gn:dem":2197,
    "gn:feature_class":"P",
    "gn:feature_code":"PPL",
    "gn:name":"Maysh-e Sufl\u00e1",
    "gn:population":0,
    "gn:timezone":"Asia/Kabul",
    "iso:country":"AF",
    "name:und_x_variant":[
        "M\u0113\u0161e Sufl\u0101",
        "M\u012bsh-e Sofl\u0101",
        "Maysh-e Sufl\u00e1",
        "\u0645\u06cc\u0634 \u0633\u0641\u0644\u0649"
    ],
    "wof:name":"Maysh-e Sufla",
    "wof:placetype":"locality"
},
  "geometry": {"coordinates":[66.10637,33.76911],"type":"Point"}
}