{
  "type": "Feature",
  "properties": {
    "gn:admin1_code":"23",
    "gn:admin2_code":"2413.0",
    "gn:asciiname":"Paturi",
    "gn:country_code":"AF",
    "gn:dem":1703,
    "gn:feature_class":"P",
    "gn:feature_code":"PPL",
    "gn:name":"P\u0101t\u016b\u1e5f\u012b",
    "gn:population":0,
    "gn:timezone":"Asia/Kabul",
    "iso:country":"AF",
    "name:und_x_variant":[
        "P\u0101t\u016bri",
        "P\u0101t\u016b\u1e5f\u012b",
        "P\u0101towr\u012b",
        "\u067e\u0627\u062a\u0648\u0693\u06cc"
    ],
    "wof:name":"Paturi",
    "wof:placetype":"locality"
},
  "geometry": {"coordinates":[67.02667,31.44056],"type":"Point"}
}