{
  "type": "Feature",
  "properties": {
    "gn:admin1_code":"41",
    "gn:admin2_code":"3402",
    "gn:asciiname":"Ghayro",
    "gn:country_code":"AF",
    "gn:dem":1332,
    "gn:feature_class":"P",
    "gn:feature_code":"PPL",
    "gn:name":"Ghayr\u014d",
    "gn:population":0,
    "gn:timezone":"Asia/Kabul",
    "iso:country":"AF",
    "name:und_x_variant":[
        "Ghayr\u014d",
        "\u063a\u06cc\u0631\u0648",
        "Ghay\u1e5fo"
    ],
    "wof:name":"Ghayro",
    "wof:placetype":"locality"
},
  "geometry": {"coordinates":[66.26294,33.39509],"type":"Point"}
}