{
  "type": "Feature",
  "properties": {
    "gn:admin1_code":"28",
    "gn:admin2_code":"2506.0",
    "gn:asciiname":"Tirwuki",
    "gn:country_code":"AF",
    "gn:dem":1272,
    "gn:feature_class":"P",
    "gn:feature_code":"PPL",
    "gn:name":"Tirwuk\u012b",
    "gn:population":0,
    "gn:timezone":"Asia/Kabul",
    "iso:country":"AF",
    "name:und_x_variant":[
        "Tirvuki",
        "\u062a\u0631\u0648\u06a9\u06cc",
        "Terwok\u012b",
        "Tirwuk\u012b",
        "Tirwok\u012b"
    ],
    "wof:name":"Tirwuki",
    "wof:placetype":"locality"
},
  "geometry": {"coordinates":[66.34466,31.78729],"type":"Point"}
}