{
  "type": "Feature",
  "properties": {
    "gn:admin1_code":"8",
    "gn:admin2_code":"615.0",
    "gn:asciiname":"'Aziz Godalay",
    "gn:country_code":"AF",
    "gn:dem":2100,
    "gn:feature_class":"P",
    "gn:feature_code":"PPL",
    "gn:name":"\u2018Az\u012bz G\u014d\u1e0falay",
    "gn:population":0,
    "gn:timezone":"Asia/Kabul",
    "iso:country":"AF",
    "name:und_x_variant":[
        "Azizgudale",
        "\u2018Az\u012bz Godal\u0113",
        "\u2018Az\u012bz G\u014d\u1e0falay",
        "\u0639\u0632\u06cc\u0632 \u06af\u0648\u0689\u0644\u06cc"
    ],
    "wof:name":"'Aziz Godalay",
    "wof:placetype":"locality"
},
  "geometry": {"coordinates":[68.59003,33.38995999999999],"type":"Point"}
}