{
  "type": "Feature",
  "properties": {
    "gn:admin1_code":"28",
    "gn:admin2_code":"2501.0",
    "gn:asciiname":"Akhtar Muhammad Kelay",
    "gn:country_code":"AF",
    "gn:dem":1682,
    "gn:feature_class":"P",
    "gn:feature_code":"PPL",
    "gn:name":"Akhtar Mu\u1e29ammad K\u00ealay",
    "gn:population":0,
    "gn:timezone":"Asia/Kabul",
    "iso:country":"AF",
    "name:fas_x_preferred":[
        "\u0642\u0631\u064a\u06c0 \u0627\u062e\u062a\u0631 \u0645\u062d\u0645\u062f"
    ],
    "name:und_x_variant":[
        "Akhtarmukhammed-Kalay",
        "Akhtar Mu\u1e29ammad K\u00ealay",
        "\u0627\u062e\u062a\u0631 \u0645\u062d\u0645\u062f \u06a9\u0644\u06cc",
        "Akhtar Mo\u1e29ammad Kalay"
    ],
    "wof:name":"Akhtar Muhammad Kelay",
    "wof:placetype":"locality"
},
  "geometry": {"coordinates":[67.13221999999999,32.2588],"type":"Point"}
}