{
  "type": "Feature",
  "properties": {
    "gn:admin1_code":"05",
    "gn:admin2_code":"2804",
    "gn:asciiname":"Lorizard",
    "gn:country_code":"AF",
    "gn:dem":2559,
    "gn:feature_class":"P",
    "gn:feature_code":"PPL",
    "gn:name":"L\u014drizard",
    "gn:population":0,
    "gn:timezone":"Asia/Kabul",
    "iso:country":"AF",
    "name:und_x_variant":[
        "L\u014d\u1e5feza\u1e5f\u1e0f",
        "Lorizard",
        "L\u014dr-e Zard",
        "L\u016br-e Zard",
        "L\u014drizard",
        "\u0644\u0648\u0631\u0632\u0631\u062f"
    ],
    "wof:name":"Lorizard",
    "wof:placetype":"locality"
},
  "geometry": {"coordinates":[66.72229,34.7499],"type":"Point"}
}