{
  "type": "Feature",
  "properties": {
    "gn:admin1_code":"18",
    "gn:admin2_code":"805.0",
    "gn:asciiname":"Nowe Kazhah",
    "gn:country_code":"AF",
    "gn:dem":1223,
    "gn:feature_class":"P",
    "gn:feature_code":"PPL",
    "gn:name":"Now\u0113 Kaz\u0332h\u0332ah",
    "gn:population":0,
    "gn:timezone":"Asia/Kabul",
    "iso:country":"AF",
    "name:fas_x_preferred":[
        "\u0646\u0648\u06cc \u0643\u0698\u0647"
    ],
    "name:und_x_variant":[
        "Naw\u0113 Kazha",
        "Naw\u0113 Ka\u017ea",
        "Nave-Kaza",
        "Naw\u0113 Kazhah",
        "\u0646\u0648\u06cc \u0643\u0698\u0647",
        "Now\u0113 Kaz\u0332h\u0332ah",
        "\u0646\u0648\u06d0 \u06a9\u0696\u0647"
    ],
    "wof:name":"Nowe Kazhah",
    "wof:placetype":"locality"
},
  "geometry": {"coordinates":[70.19129000000001,34.25591],"type":"Point"}
}