{
  "type": "Feature",
  "properties": {
    "gn:admin1_code":"29",
    "gn:admin2_code":"2909.0",
    "gn:asciiname":"Muhabbat Kot",
    "gn:country_code":"AF",
    "gn:dem":2125,
    "gn:feature_class":"P",
    "gn:feature_code":"PPL",
    "gn:name":"Mu\u1e29abbat K\u014d\u1e6f",
    "gn:population":0,
    "gn:timezone":"Asia/Kabul",
    "iso:country":"AF",
    "name:und_x_variant":[
        "Mukhabbatkot",
        "Mo\u1e29abbat K\u014dt",
        "Mu\u1e29abat K\u014d\u1e6f",
        "Mo\u1e29abbat Kowt",
        "Mo\u1e29abat K\u014d\u1e6f",
        "Mu\u1e29abbat K\u014d\u1e6f",
        "\u0645\u062d\u0628\u062a \u06a9\u0648\u067c"
    ],
    "wof:name":"Muhabbat Kot",
    "wof:placetype":"locality"
},
  "geometry": {"coordinates":[69.25565,32.91472],"type":"Point"}
}