{
  "type": "Feature",
  "properties": {
    "gn:admin1_code":"09",
    "gn:admin2_code":"2706",
    "gn:asciiname":"Sar-e Ghargharow",
    "gn:country_code":"AF",
    "gn:dem":2614,
    "gn:feature_class":"P",
    "gn:feature_code":"PPL",
    "gn:name":"Sar-e Ghargharow",
    "gn:population":0,
    "gn:timezone":"Asia/Kabul",
    "iso:country":"AF",
    "name:fas_x_preferred":[
        "\u0633\u0631\u0654 \u063a\u0631\u063a\u0631\u0627\u0628"
    ],
    "name:und_x_variant":[
        "Sa\u1e5fe Gha\u1e5fgha\u1e5faw",
        "Sari-Gargarav",
        "Sar-e Ghargharow",
        "\u0633\u0631 \u063a\u0631\u063a\u0631\u0648",
        "Sar-e Gharghar\u0101b"
    ],
    "wof:name":"Sar-e Ghargharow",
    "wof:placetype":"locality"
},
  "geometry": {"coordinates":[64.86743,33.44081],"type":"Point"}
}