{
  "type": "Feature",
  "properties": {
    "gn:admin1_code":"30",
    "gn:admin2_code":"1607.0",
    "gn:asciiname":"Burluk",
    "gn:country_code":"AF",
    "gn:dem":308,
    "gn:feature_class":"P",
    "gn:feature_code":"PPL",
    "gn:name":"Burluk",
    "gn:population":0,
    "gn:timezone":"Asia/Kabul",
    "iso:country":"AF",
    "name:und_x_variant":[
        "\u0628\u0631\u0644\u06a9"
    ],
    "wof:name":"Burluk",
    "wof:placetype":"locality"
},
  "geometry": {"coordinates":[66.56446,36.92663],"type":"Point"}
}