{
  "type": "Feature",
  "properties": {
    "gn:admin1_code":"10",
    "gn:admin2_code":"2306.0",
    "gn:asciiname":"Maslahat",
    "gn:country_code":"AF",
    "gn:dem":1610,
    "gn:feature_class":"P",
    "gn:feature_code":"PPL",
    "gn:name":"Ma\u015fla\u1e29at",
    "gn:population":0,
    "gn:timezone":"Asia/Kabul",
    "iso:country":"AF",
    "name:und_x_variant":[
        "Maslakhat",
        "Ma\u015fla\u1e29at",
        "\u0645\u0635\u0644\u062d\u062a"
    ],
    "wof:name":"Maslahat",
    "wof:placetype":"locality"
},
  "geometry": {"coordinates":[64.26059000000001,32.5027],"type":"Point"}
}