{
  "type": "Feature",
  "properties": {
    "gn:admin1_code":"05",
    "gn:admin2_code":"2804",
    "gn:asciiname":"Sar-e Bum",
    "gn:country_code":"AF",
    "gn:dem":2457,
    "gn:feature_class":"P",
    "gn:feature_code":"PPL",
    "gn:name":"Sar-e B\u016bm",
    "gn:population":0,
    "gn:timezone":"Asia/Kabul",
    "iso:country":"AF",
    "name:und_x_variant":[
        "Sari-Bum",
        "Sar-e B\u016bm",
        "\u0633\u0631 \u0628\u0648\u0645"
    ],
    "wof:name":"Sar-e Bum",
    "wof:placetype":"locality"
},
  "geometry": {"coordinates":[66.68144000000001,34.82824],"type":"Point"}
}