{
  "type": "Feature",
  "properties": {
    "gn:admin1_code":"11",
    "gn:admin2_code":"2012",
    "gn:asciiname":"Karez-e Baluch",
    "gn:country_code":"AF",
    "gn:dem":1501,
    "gn:feature_class":"P",
    "gn:feature_code":"PPL",
    "gn:name":"K\u0101r\u0113z-e Bal\u016bch",
    "gn:population":0,
    "gn:timezone":"Asia/Kabul",
    "iso:country":"AF",
    "name:und_x_variant":[
        "K\u0101r\u012bz Bul\u016bch",
        "K\u0101r\u012bz Bal\u016bch",
        "K\u0101r\u0113z-e Bal\u016bch",
        "\u06a9\u0627\u0631\u06d0\u0632 \u0628\u0644\u0648\u0686",
        "K\u0101\u1e5f\u0113ze Bal\u016bc",
        "K\u0101r\u012bz-e Bal\u016bch"
    ],
    "wof:name":"Karez-e Baluch",
    "wof:placetype":"locality"
},
  "geometry": {"coordinates":[63.01452,34.33649],"type":"Point"}
}