{
  "type": "Feature",
  "properties": {
    "gn:admin1_code":"01",
    "gn:admin2_code":"1109.0",
    "gn:asciiname":"Finjan",
    "gn:country_code":"AF",
    "gn:dem":2323,
    "gn:feature_class":"P",
    "gn:feature_code":"PPL",
    "gn:name":"Finj\u0101n",
    "gn:population":0,
    "gn:timezone":"Asia/Kabul",
    "iso:country":"AF",
    "name:und_x_variant":[
        "Finj\u0101n",
        "\u0641\u0646\u062c\u0627\u0646"
    ],
    "wof:name":"Finjan",
    "wof:placetype":"locality"
},
  "geometry": {"coordinates":[71.46630999999999,37.33752],"type":"Point"}
}