{
  "type": "Feature",
  "properties": {
    "gn:admin1_code":"01",
    "gn:admin2_code":"1114.0",
    "gn:asciiname":"Wurnel",
    "gn:country_code":"AF",
    "gn:dem":2178,
    "gn:feature_class":"P",
    "gn:feature_code":"PPL",
    "gn:name":"Wurn\u0113l",
    "gn:population":0,
    "gn:timezone":"Asia/Kabul",
    "iso:country":"AF",
    "name:und_x_variant":[
        "\u0648\u0631\u0646\u06d0\u0644",
        "Wu\u1e5fn\u0113l",
        "Wurn\u0113l"
    ],
    "wof:name":"Wurnel",
    "wof:placetype":"locality"
},
  "geometry": {"coordinates":[70.80998000000002,37.13344],"type":"Point"}
}