{
  "type": "Feature",
  "properties": {
    "gn:admin1_code":"23",
    "gn:admin2_code":"2413.0",
    "gn:asciiname":"Zirak",
    "gn:country_code":"AF",
    "gn:dem":1721,
    "gn:feature_class":"P",
    "gn:feature_code":"PPL",
    "gn:name":"Z\u012brak",
    "gn:population":0,
    "gn:timezone":"Asia/Kabul",
    "iso:country":"AF",
    "name:pus_x_preferred":[
        "\u0632\u064a\u0631\u06a9"
    ],
    "name:und_x_variant":[
        "\u0632\u0631\u06a9",
        "Z\u012brak"
    ],
    "wof:name":"Zirak",
    "wof:placetype":"locality"
},
  "geometry": {"coordinates":[67.24084000000001,31.66672],"type":"Point"}
}