{
  "type": "Feature",
  "properties": {
    "gn:admin1_code":"2",
    "gn:admin2_code":"1902.0",
    "gn:asciiname":"Bismillah",
    "gn:country_code":"AF",
    "gn:dem":782,
    "gn:feature_class":"P",
    "gn:feature_code":"PPL",
    "gn:name":"Bismill\u0101h",
    "gn:population":0,
    "gn:timezone":"Asia/Kabul",
    "iso:country":"AF",
    "name:fra_x_preferred":[
        "Bismillah"
    ],
    "name:pan_x_preferred":[
        "\u0a2c\u0a3f\u0a38\u0a2e\u0a3f\u0a71\u0a32\u0a3e\u0a39"
    ],
    "name:und_x_variant":[
        "Bismill\u0101h",
        "\u0628\u0633\u0645 \ufdf2",
        "Besmell\u0101h"
    ],
    "wof:name":"Bismillah",
    "wof:placetype":"locality"
},
  "geometry": {"coordinates":[63.04676,35.05217],"type":"Point"}
}