{
  "type": "Feature",
  "properties": {
    "gn:admin1_code":"05",
    "gn:admin2_code":"2805",
    "gn:asciiname":"Koshah",
    "gn:country_code":"AF",
    "gn:dem":2849,
    "gn:feature_class":"P",
    "gn:feature_code":"PPL",
    "gn:name":"K\u014dshah",
    "gn:population":0,
    "gn:timezone":"Asia/Kabul",
    "iso:country":"AF",
    "name:und_x_variant":[
        "Kosha",
        "Ko\u0161a",
        "K\u016bsheh",
        "K\u014dshah",
        "\u06a9\u0648\u0634\u0647"
    ],
    "wof:name":"Koshah",
    "wof:placetype":"locality"
},
  "geometry": {"coordinates":[67.104,34.41299],"type":"Point"}
}