{
  "type": "Feature",
  "properties": {
    "gn:admin1_code":"8",
    "gn:admin2_code":"606.0",
    "gn:asciiname":"Hasan Baluch",
    "gn:country_code":"AF",
    "gn:dem":3011,
    "gn:feature_class":"P",
    "gn:feature_code":"PPL",
    "gn:name":"\u1e28asan Bal\u016bch",
    "gn:population":0,
    "gn:timezone":"Asia/Kabul",
    "iso:country":"AF",
    "name:und_x_variant":[
        "Hasan Bal\u016b\u010d",
        "\u1e28asan-e Bal\u016bch",
        "\u1e28asan Bal\u016bch",
        "\u062d\u0633\u0646 \u0628\u0644\u0648\u0686"
    ],
    "wof:name":"Hasan Baluch",
    "wof:placetype":"locality"
},
  "geometry": {"coordinates":[67.35934,33.26635],"type":"Point"}
}