{
  "type": "Feature",
  "properties": {
    "gn:admin1_code":"08",
    "gn:admin2_code":"607.0",
    "gn:asciiname":"Ulizar",
    "gn:country_code":"AF",
    "gn:dem":2986,
    "gn:feature_class":"P",
    "gn:feature_code":"PPL",
    "gn:name":"\u016aliz\u0101r",
    "gn:population":0,
    "gn:timezone":"Asia/Kabul",
    "iso:country":"AF",
    "name:fas_x_preferred":[
        "\u0627\u0644\u0632\u0627\u0631"
    ],
    "name:rus_x_preferred":[
        "\u0423\u043b\u0438\u0437\u0430\u0440"
    ],
    "name:und_x_variant":[
        "\u016alez\u0101\u1e5f",
        "Ulizar",
        "Olez\u0101r",
        "\u016aliz\u0101r",
        "\u0627\u0648\u0644\u0632\u0627\u0631"
    ],
    "wof:name":"Ulizar",
    "wof:placetype":"locality"
},
  "geometry": {"coordinates":[67.61232,33.28605],"type":"Point"}
}