{
  "type": "Feature",
  "properties": {
    "gn:admin1_code":"26",
    "gn:admin2_code":"1202.0",
    "gn:asciiname":"Chahar Chinar",
    "gn:country_code":"AF",
    "gn:dem":857,
    "gn:feature_class":"P",
    "gn:feature_code":"PPL",
    "gn:name":"Chah\u0101r Chin\u0101r",
    "gn:population":0,
    "gn:timezone":"Asia/Kabul",
    "iso:country":"AF",
    "name:rus_x_preferred":[
        "\u0427\u0430\u0445\u0430\u0440\u0447\u0438\u043d\u0430\u0440"
    ],
    "name:und_x_variant":[
        "\u010cah\u0101r \u010cen\u0101r",
        "Chakharchinar",
        "Chah\u0101r Chen\u0101r",
        "Chah\u0101r Chin\u0101r",
        "\u0686\u0647\u0627\u0631 \u0686\u0646\u0627\u0631"
    ],
    "wof:name":"Chahar Chinar",
    "wof:placetype":"locality"
},
  "geometry": {"coordinates":[69.41589,36.56181],"type":"Point"}
}