{
  "type": "Feature",
  "properties": {
    "gn:admin1_code":"10",
    "gn:admin2_code":"2302.0",
    "gn:asciiname":"Gharbi Muhammad 'Omar Kelay",
    "gn:country_code":"AF",
    "gn:dem":804,
    "gn:feature_class":"P",
    "gn:feature_code":"PPL",
    "gn:name":"Gharb\u012b Mu\u1e29ammad \u2018Omar K\u00ealay",
    "gn:population":0,
    "gn:timezone":"Asia/Kabul",
    "iso:country":"AF",
    "name:fas_x_preferred":[
        "\u0642\u0631\u064a\u06c0 \u0645\u062d\u0645\u062f \u0639\u0645\u0631 \u063a\u0631\u0628\u06cc"
    ],
    "name:und_x_variant":[
        "Gha\u1e5fbi Mo\u1e29amma\u1e0f \u2018Oma\u1e5f Kalay",
        "Garbi-Mukhammedumar-Kalay",
        "Gharb\u012b Mu\u1e29ammad \u2018Omar K\u00ealay",
        "\u063a\u0631\u0628\u06cc \u0645\u062d\u0645\u062f \u0639\u0645\u0631 \u06a9\u0644\u06cc",
        "Mo\u1e29ammad \u2018Omar Kalay-e Gharb\u012b"
    ],
    "wof:name":"Gharbi Muhammad 'Omar Kelay",
    "wof:placetype":"locality"
},
  "geometry": {"coordinates":[64.38471,31.71139],"type":"Point"}
}