{
  "type": "Feature",
  "properties": {
    "gn:admin1_code":"11",
    "gn:admin2_code":"2016.0",
    "gn:asciiname":"Baydak",
    "gn:country_code":"AF",
    "gn:dem":1753,
    "gn:feature_class":"P",
    "gn:feature_code":"PPL",
    "gn:name":"Baydak",
    "gn:population":0,
    "gn:timezone":"Asia/Kabul",
    "iso:country":"AF",
    "name:fas_x_preferred":[
        "\u0628\u06cc\u062f\u06a9"
    ],
    "name:und_x_variant":[
        "B\u0113\u1e0fak",
        "Baydak",
        "\u0628\u06cc\u062f\u06a9",
        "B\u012bdak"
    ],
    "wof:name":"Baydak",
    "wof:placetype":"locality"
},
  "geometry": {"coordinates":[62.52303000000001,34.69557],"type":"Point"}
}