{
  "type": "Feature",
  "properties": {
    "gn:admin1_code":"09",
    "gn:admin2_code":"2707",
    "gn:asciiname":"Gulnaychah",
    "gn:country_code":"AF",
    "gn:dem":2744,
    "gn:feature_class":"P",
    "gn:feature_code":"PPL",
    "gn:name":"Gulnaychah",
    "gn:population":0,
    "gn:timezone":"Asia/Kabul",
    "iso:country":"AF",
    "name:rus_x_preferred":[
        "Gul\u2019naycha"
    ],
    "name:und_x_variant":[
        "Gulnay\u010da",
        "Golnaycheh",
        "Gulnaychah",
        "\u06af\u0644\u0646\u06cc\u0686\u0647"
    ],
    "wof:name":"Gulnaychah",
    "wof:placetype":"locality"
},
  "geometry": {"coordinates":[66.16459,34.60907],"type":"Point"}
}