{
  "type": "Feature",
  "properties": {
    "gn:admin1_code":"11",
    "gn:admin2_code":"2007",
    "gn:asciiname":"Howzchah",
    "gn:country_code":"AF",
    "gn:dem":1270,
    "gn:feature_class":"P",
    "gn:feature_code":"PPL",
    "gn:name":"\u1e28ow\u1e95chah",
    "gn:population":0,
    "gn:timezone":"Asia/Kabul",
    "iso:country":"AF",
    "name:und_x_variant":[
        "H\u0331aw\u1e0f\u1e95cah",
        "\u1e28ow\u1e95chah",
        "\u062d\u0648\u0636\u0686\u0647",
        "\u1e28ow\u1e95 Ch\u0101h"
    ],
    "wof:name":"Howzchah",
    "wof:placetype":"locality"
},
  "geometry": {"coordinates":[61.73833000000001,34.85191],"type":"Point"}
}