{
  "type": "Feature",
  "properties": {
    "gn:admin1_code":"23",
    "gn:admin2_code":"2405.0",
    "gn:asciiname":"Khushay",
    "gn:country_code":"AF",
    "gn:dem":1432,
    "gn:feature_class":"P",
    "gn:feature_code":"PPL",
    "gn:name":"Khushay",
    "gn:population":0,
    "gn:timezone":"Asia/Kabul",
    "iso:country":"AF",
    "name:fas_x_preferred":[
        "\u062e\u0633\u06cc"
    ],
    "name:und_x_variant":[
        "\u062e\u0634\u06cc",
        "Khosay"
    ],
    "wof:name":"Khushay",
    "wof:placetype":"locality"
},
  "geometry": {"coordinates":[65.54128,31.96705],"type":"Point"}
}