{
  "type": "Feature",
  "properties": {
    "gn:admin1_code":"05",
    "gn:admin2_code":"2806.0",
    "gn:asciiname":"Shine Rabat",
    "gn:country_code":"AF",
    "gn:dem":2400,
    "gn:feature_class":"P",
    "gn:feature_code":"PPL",
    "gn:name":"Shin\u0113 Rab\u0101\u0163",
    "gn:population":0,
    "gn:timezone":"Asia/Kabul",
    "iso:country":"AF",
    "name:und_x_variant":[
        "\u0160en\u0113 Rob\u0101t",
        "Sheney Rob\u0101\u0163",
        "Shin\u0113 Rab\u0101\u0163",
        "\u0634\u06cc\u0646\u06d0 \u0631\u0628\u0627\u0637"
    ],
    "wof:name":"Shine Rabat",
    "wof:placetype":"locality"
},
  "geometry": {"coordinates":[67.25126,34.24045],"type":"Point"}
}