{
  "type": "Feature",
  "properties": {
    "gn:admin1_code":"9",
    "gn:admin2_code":"2706.0",
    "gn:asciiname":"Dahan-e Saybak",
    "gn:country_code":"AF",
    "gn:dem":2749,
    "gn:feature_class":"P",
    "gn:feature_code":"PPL",
    "gn:name":"Dah\u0101n-e Saybak",
    "gn:population":0,
    "gn:timezone":"Asia/Kabul",
    "iso:country":"AF",
    "name:und_x_variant":[
        "\u1e0eahane S\u0113bak",
        "Dah\u0101n-e Saybak",
        "\u062f\u0647\u0627\u0646 \u0633\u06cc\u0628\u06a9",
        "Dahan-e S\u012bbak"
    ],
    "wof:name":"Dahan-e Saybak",
    "wof:placetype":"locality"
},
  "geometry": {"coordinates":[65.41659,33.89867],"type":"Point"}
}