{
  "type": "Feature",
  "properties": {
    "gn:admin1_code":"18",
    "gn:admin2_code":"804.0",
    "gn:asciiname":"Qazian",
    "gn:country_code":"AF",
    "gn:dem":1317,
    "gn:feature_class":"P",
    "gn:feature_code":"PPL",
    "gn:name":"Q\u0101\u1e95\u012b\u0101n",
    "gn:population":0,
    "gn:timezone":"Asia/Kabul",
    "iso:country":"AF",
    "name:fas_x_preferred":[
        "\u0642\u0627\u0636\u064a\u0627\u0646"
    ],
    "name:pnb_x_preferred":[
        "\u0642\u0627\u0636\u064a\u0627\u06ba"
    ],
    "name:rus_x_preferred":[
        "Kaz\u2019yan"
    ],
    "name:und_x_variant":[
        "Q\u0101\u1e0f\u1e95y\u0101n",
        "Q\u0101\u1e95\u012b\u0101n",
        "\u0642\u0627\u0636\u06cc\u0627\u0646"
    ],
    "name:urd_x_preferred":[
        "\u0642\u0627\u0636\u06cc\u0627\u06ba"
    ],
    "wof:name":"Qazian",
    "wof:placetype":"locality"
},
  "geometry": {"coordinates":[70.01730000000001,34.28626],"type":"Point"}
}