{
  "type": "Feature",
  "properties": {
    "gn:admin1_code":"13",
    "gn:admin2_code":"107.0",
    "gn:asciiname":"Nazim Khel",
    "gn:country_code":"AF",
    "gn:dem":2232,
    "gn:feature_class":"P",
    "gn:feature_code":"PPL",
    "gn:name":"Naz\u0327\u012bm Kh\u0113l",
    "gn:population":0,
    "gn:timezone":"Asia/Kabul",
    "iso:country":"AF",
    "name:rus_x_preferred":[
        "Nazimkheyl\u2019"
    ],
    "name:und_x_variant":[
        "Na\u1e95\u012bmkh\u0113l",
        "Naz\u0327im Kh\u0113l",
        "Naz\u0327\u012bmkheyl",
        "Naz\u0327\u012bm Kh\u0113l",
        "\u0646\u0638\u06cc\u0645 \u062e\u06d0\u0644"
    ],
    "wof:name":"Nazim Khel",
    "wof:placetype":"locality"
},
  "geometry": {"coordinates":[68.99401999999999,34.68732],"type":"Point"}
}