{
  "type": "Feature",
  "properties": {
    "gn:admin1_code":"8",
    "gn:admin2_code":"606.0",
    "gn:asciiname":"Bilowghu",
    "gn:country_code":"AF",
    "gn:dem":2922,
    "gn:feature_class":"P",
    "gn:feature_code":"PPL",
    "gn:name":"Bilowgh\u016b",
    "gn:population":0,
    "gn:timezone":"Asia/Kabul",
    "iso:country":"AF",
    "name:und_x_variant":[
        "Bilowgh\u016b",
        "\u0628\u0644\u0648\u063a\u0648",
        "Belawghu"
    ],
    "wof:name":"Bilowghu",
    "wof:placetype":"locality"
},
  "geometry": {"coordinates":[67.44685,33.44396],"type":"Point"}
}