{
  "type": "Feature",
  "properties": {
    "gn:admin1_code":"17",
    "gn:admin2_code":"504.0",
    "gn:asciiname":"Akhund Khel",
    "gn:country_code":"AF",
    "gn:dem":2767,
    "gn:feature_class":"P",
    "gn:feature_code":"PPL",
    "gn:name":"\u0100kh\u016bnd Kh\u0113l",
    "gn:population":0,
    "gn:timezone":"Asia/Kabul",
    "iso:country":"AF",
    "name:fas_x_preferred":[
        "\u0622\u062e\u0648\u0646\u062f \u062e\u064a\u0644"
    ],
    "name:rus_x_preferred":[
        "Akhundkheyl\u2019"
    ],
    "name:und_x_variant":[
        "\u0100khun\u1e0fkh\u0113l",
        "\u0100kh\u016bnd Kh\u0113l",
        "Akhvond Kheyl",
        "\u0622\u062e\u0648\u0646\u062f \u062e\u06d0\u0644"
    ],
    "wof:name":"Akhund Khel",
    "wof:placetype":"locality"
},
  "geometry": {"coordinates":[69.35647,33.94386],"type":"Point"}
}