{
  "type": "Feature",
  "properties": {
    "gn:admin1_code":"34",
    "gn:admin2_code":"1002",
    "gn:asciiname":"Marah Warah",
    "gn:country_code":"AF",
    "gn:dem":863,
    "gn:feature_class":"P",
    "gn:feature_code":"PPL",
    "gn:name":"Marah Warah",
    "gn:population":0,
    "gn:timezone":"Asia/Kabul",
    "iso:country":"AF",
    "name:und_x_variant":[
        "Maravara",
        "Marawarah",
        "Ma\u1e5fawa\u1e5fa",
        "Marwura",
        "Marwura Alaqadari",
        "Marawarra",
        "Marah Warah"
    ],
    "wof:name":"Marah Warah",
    "wof:placetype":"locality"
},
  "geometry": {"coordinates":[71.18000000000001,34.89],"type":"Point"}
}