{
  "type": "Feature",
  "properties": {
    "gn:admin1_code":"03",
    "gn:admin2_code":"1312",
    "gn:asciiname":"Awlad",
    "gn:country_code":"AF",
    "gn:dem":1672,
    "gn:feature_class":"P",
    "gn:feature_code":"PPL",
    "gn:name":"Awl\u0101d",
    "gn:population":0,
    "gn:timezone":"Asia/Kabul",
    "iso:country":"AF",
    "name:und_x_variant":[
        "Awl\u0101\u1e0f",
        "Owl\u0101d",
        "Awl\u0101d",
        "\u0627\u0648\u0644\u0627\u062f"
    ],
    "wof:name":"Awlad",
    "wof:placetype":"locality"
},
  "geometry": {"coordinates":[69.35479000000001,35.67166],"type":"Point"}
}