{
  "type": "Feature",
  "properties": {
    "gn:admin1_code":"2",
    "gn:admin2_code":"1906.0",
    "gn:asciiname":"Chakaw",
    "gn:country_code":"AF",
    "gn:dem":1760,
    "gn:feature_class":"P",
    "gn:feature_code":"PPL",
    "gn:name":"Chak\u0101w",
    "gn:population":0,
    "gn:timezone":"Asia/Kabul",
    "iso:country":"AF",
    "name:und_x_variant":[
        "Cak\u0101w",
        "Chak\u0101w",
        "\u0686\u06a9\u0627\u0648",
        "Chak\u0101b"
    ],
    "wof:name":"Chakaw",
    "wof:placetype":"locality"
},
  "geometry": {"coordinates":[64.01572,35.41419000000001],"type":"Point"}
}