{
  "type": "Feature",
  "properties": {
    "gn:admin1_code":"5",
    "gn:admin2_code":"2806.0",
    "gn:asciiname":"Ghalghu",
    "gn:country_code":"AF",
    "gn:dem":2628,
    "gn:feature_class":"P",
    "gn:feature_code":"PPL",
    "gn:name":"Ghalgh\u016b",
    "gn:population":0,
    "gn:timezone":"Asia/Kabul",
    "iso:country":"AF",
    "name:und_x_variant":[
        "Ghalgh\u016b",
        "\u063a\u0644\u063a\u0648",
        "Ghalghu"
    ],
    "wof:name":"Ghalghu",
    "wof:placetype":"locality"
},
  "geometry": {"coordinates":[67.10087,33.99487],"type":"Point"}
}