{
  "type": "Feature",
  "properties": {
    "gn:admin1_code":"5",
    "gn:admin2_code":"2805.0",
    "gn:asciiname":"Dahan-e Khug",
    "gn:country_code":"AF",
    "gn:dem":2950,
    "gn:feature_class":"P",
    "gn:feature_code":"PPL",
    "gn:name":"Dahan-e Kh\u016bg",
    "gn:population":0,
    "gn:timezone":"Asia/Kabul",
    "iso:country":"AF",
    "name:und_x_variant":[
        "\u1e0eahane Kh\u016bg",
        "Dakhani-Khug",
        "Dahan-e N\u0101w-e Kh\u016bg",
        "Dahan-e Kh\u016bk",
        "Dahan-e Kh\u016bg",
        "\u062f\u0647\u0646 \u062e\u0648\u06af",
        "Dah\u0101nah-ye Kh\u016bg",
        "\u062f\u0647\u0627\u0646\u0647 \u062e\u0648\u06af"
    ],
    "wof:name":"Dahan-e Khug",
    "wof:placetype":"locality"
},
  "geometry": {"coordinates":[66.83725,34.4423],"type":"Point"}
}