{
  "type": "Feature",
  "properties": {
    "gn:admin1_code":"02",
    "gn:admin2_code":"1906",
    "gn:asciiname":"Murichaq",
    "gn:country_code":"AF",
    "gn:dem":401,
    "gn:feature_class":"P",
    "gn:feature_code":"PPL",
    "gn:name":"M\u016brich\u0101q",
    "gn:population":0,
    "gn:timezone":"Asia/Kabul",
    "iso:country":"AF",
    "name:pus_x_preferred":[
        "M\u016br\u012bch\u0101q"
    ],
    "name:und_x_variant":[
        "M\u0101r-o-Ch\u0101k",
        "M\u016b\u1e5fic\u0101q",
        "M\u0101ric\u0101q",
        "Mar\u016bch\u0101k",
        "\u0645\u0648\u0631\u064a\u0686\u0627\u0642",
        "M\u016brich\u0101q",
        "\u0645\u0648\u0631\u0686\u0627\u0642"
    ],
    "wof:name":"Murichaq",
    "wof:placetype":"locality"
},
  "geometry": {"coordinates":[63.14265,35.8104],"type":"Point"}
}