{
  "type": "Feature",
  "properties": {
    "gn:admin1_code":"31",
    "gn:admin2_code":"1701",
    "gn:asciiname":"Zakah",
    "gn:country_code":"AF",
    "gn:dem":435,
    "gn:feature_class":"P",
    "gn:feature_code":"PPL",
    "gn:name":"Z\u0304akah",
    "gn:population":0,
    "gn:timezone":"Asia/Kabul",
    "iso:country":"AF",
    "name:und_x_variant":[
        "Zaka",
        "Z\u0304akah",
        "\u0630\u06a9\u0647"
    ],
    "wof:name":"Zakah",
    "wof:placetype":"locality"
},
  "geometry": {"coordinates":[65.79886999999999,36.4674],"type":"Point"}
}