{
  "type": "Feature",
  "properties": {
    "gn:admin1_code":"09",
    "gn:admin2_code":"2702",
    "gn:asciiname":"Tabarghistan",
    "gn:country_code":"AF",
    "gn:dem":2344,
    "gn:feature_class":"P",
    "gn:feature_code":"PPL",
    "gn:name":"Tabarghist\u0101n",
    "gn:population":0,
    "gn:timezone":"Asia/Kabul",
    "iso:country":"AF",
    "name:und_x_variant":[
        "Tabargistan",
        "Tabarghist\u0101n",
        "\u062a\u0628\u0631\u063a\u0633\u062a\u0627\u0646",
        "Tabarghest\u0101n"
    ],
    "wof:name":"Tabarghistan",
    "wof:placetype":"locality"
},
  "geometry": {"coordinates":[64.21471,34.19185],"type":"Point"}
}