{
  "type": "Feature",
  "properties": {
    "gn:admin1_code":"41",
    "gn:admin2_code":"3409.0",
    "gn:asciiname":"Qumurghu",
    "gn:country_code":"AF",
    "gn:dem":2114,
    "gn:feature_class":"P",
    "gn:feature_code":"PPL",
    "gn:name":"Q\u016bm\u016brgh\u016b",
    "gn:population":0,
    "gn:timezone":"Asia/Kabul",
    "iso:country":"AF",
    "name:und_x_variant":[
        "Q\u016bm\u016b\u1e5fghu",
        "Qowmow\u1e5fghu",
        "Q\u016bm\u016brgh\u016b",
        "\u0642\u0648\u0645\u0648\u0631\u063a\u0648"
    ],
    "wof:name":"Qumurghu",
    "wof:placetype":"locality"
},
  "geometry": {"coordinates":[66.49290999999999,33.76039],"type":"Point"}
}