{
  "type": "Feature",
  "properties": {
    "gn:admin1_code":"8",
    "gn:admin2_code":"604.0",
    "gn:asciiname":"Barigav",
    "gn:country_code":"AF",
    "gn:dem":3156,
    "gn:feature_class":"P",
    "gn:feature_code":"PPL",
    "gn:name":"Barigav",
    "gn:population":0,
    "gn:timezone":"Asia/Kabul",
    "iso:country":"AF",
    "name:rus_x_preferred":[
        "\u0411\u0430\u0440\u0438\u0433\u0430\u0432"
    ],
    "name:und_x_variant":[
        "B\u0101rik\u0101o Deh",
        "Ba\u1e5fig\u0101w",
        "Barigav",
        "Bar\u012b G\u0101v"
    ],
    "wof:name":"Barigav",
    "wof:placetype":"locality"
},
  "geometry": {"coordinates":[67.81999999999999,33.87],"type":"Point"}
}