{
  "type": "Feature",
  "properties": {
    "gn:admin1_code":"08",
    "gn:admin2_code":"604",
    "gn:asciiname":"Qafak",
    "gn:country_code":"AF",
    "gn:dem":3206,
    "gn:feature_class":"P",
    "gn:feature_code":"PPL",
    "gn:name":"Qafak",
    "gn:population":0,
    "gn:timezone":"Asia/Kabul",
    "iso:country":"AF",
    "name:und_x_variant":[
        "Kafak",
        "Qafak",
        "\u0642\u0641\u06a9"
    ],
    "wof:name":"Qafak",
    "wof:placetype":"locality"
},
  "geometry": {"coordinates":[67.4032,34.06976],"type":"Point"}
}