{
  "type": "Feature",
  "properties": {
    "gn:admin1_code":"31",
    "gn:admin2_code":"1708",
    "gn:asciiname":"Shaykhabad",
    "gn:country_code":"AF",
    "gn:dem":305,
    "gn:feature_class":"P",
    "gn:feature_code":"PPL",
    "gn:name":"Shaykh\u0101b\u0101d",
    "gn:population":0,
    "gn:timezone":"Asia/Kabul",
    "iso:country":"AF",
    "name:und_x_variant":[
        "Sheikh\u0101b\u0101d",
        "Sheykh\u0101b\u0101d",
        "Shaykh\u0101b\u0101d",
        "\u0634\u06cc\u062e \u0622\u0628\u0627\u062f"
    ],
    "wof:name":"Shaykhabad",
    "wof:placetype":"locality"
},
  "geometry": {"coordinates":[66.37298,36.83629000000001],"type":"Point"}
}