{
  "type": "Feature",
  "properties": {
    "gn:admin1_code":"28",
    "gn:admin2_code":"2505",
    "gn:asciiname":"Sokhtah",
    "gn:country_code":"AF",
    "gn:dem":1659,
    "gn:feature_class":"P",
    "gn:feature_code":"PPL",
    "gn:name":"S\u014dkhtah",
    "gn:population":0,
    "gn:timezone":"Asia/Kabul",
    "iso:country":"AF",
    "name:und_x_variant":[
        "Ookhta",
        "S\u016bkhteh",
        "S\u014dkhtah",
        "\u0633\u0648\u062e\u062a\u0647",
        "S\u014dkht\u0101"
    ],
    "wof:name":"Sokhtah",
    "wof:placetype":"locality"
},
  "geometry": {"coordinates":[66.41513,32.26829],"type":"Point"}
}