{
  "type": "Feature",
  "properties": {
    "gn:admin1_code":"03",
    "gn:admin2_code":"1305",
    "gn:asciiname":"Wado",
    "gn:country_code":"AF",
    "gn:dem":1366,
    "gn:feature_class":"P",
    "gn:feature_code":"PPL",
    "gn:name":"W\u0101d\u014d",
    "gn:population":0,
    "gn:timezone":"Asia/Kabul",
    "iso:country":"AF",
    "name:ceb_x_preferred":[
        "Wado"
    ],
    "name:nld_x_preferred":[
        "Wado"
    ],
    "name:swe_x_preferred":[
        "Wado"
    ],
    "name:und_x_variant":[
        "W\u0101d\u014d",
        "\u0648\u0627\u062f\u0648",
        "W\u0101do"
    ],
    "wof:name":"Wado",
    "wof:placetype":"locality"
},
  "geometry": {"coordinates":[68.26465,35.48807],"type":"Point"}
}