{
  "type": "Feature",
  "properties": {
    "gn:admin1_code":"11",
    "gn:admin2_code":"2005",
    "gn:asciiname":"Khwajah Chahar Shanbah",
    "gn:country_code":"AF",
    "gn:dem":1707,
    "gn:feature_class":"P",
    "gn:feature_code":"PPL",
    "gn:name":"Khw\u0101jah Chah\u0101r Shanbah",
    "gn:population":0,
    "gn:timezone":"Asia/Kabul",
    "iso:country":"AF",
    "name:und_x_variant":[
        "Khw\u0101ja Cah\u0101\u1e5f S\u0304ambeh",
        "Khv\u0101jeh Chah\u0101r Shanbeh",
        "Khw\u0101jah Chah\u0101r Shanbah",
        "\u062e\u0648\u0627\u062c\u0647 \u0686\u0647\u0627\u0631 \u0634\u0646\u0628\u0647"
    ],
    "wof:name":"Khwajah Chahar Shanbah",
    "wof:placetype":"locality"
},
  "geometry": {"coordinates":[62.90032,34.53322],"type":"Point"}
}