{
  "type": "Feature",
  "properties": {
    "gn:admin1_code":"8",
    "gn:admin2_code":"605.0",
    "gn:asciiname":"Dahan-e Gurgak",
    "gn:country_code":"AF",
    "gn:dem":2887,
    "gn:feature_class":"P",
    "gn:feature_code":"PPL",
    "gn:name":"Dah\u0101n-e Gurgak",
    "gn:population":0,
    "gn:timezone":"Asia/Kabul",
    "iso:country":"AF",
    "name:und_x_variant":[
        "Dah\u0101n-e Gurgak",
        "\u062f\u0647\u0627\u0646 \u06af\u0631\u06af\u06a9",
        "Dahan-e Gurgak"
    ],
    "wof:name":"Dahan-e Gurgak",
    "wof:placetype":"locality"
},
  "geometry": {"coordinates":[67.39324999999999,33.62995],"type":"Point"}
}