{
  "type": "Feature",
  "properties": {
    "gn:admin1_code":"28",
    "gn:admin2_code":"2504.0",
    "gn:asciiname":"Mulla Khel",
    "gn:country_code":"AF",
    "gn:dem":2261,
    "gn:feature_class":"P",
    "gn:feature_code":"PPL",
    "gn:name":"Mull\u0101 Kh\u0113l",
    "gn:population":0,
    "gn:timezone":"Asia/Kabul",
    "iso:country":"AF",
    "name:fas_x_preferred":[
        "\u0645\u0644\u0627 \u062e\u064a\u0644"
    ],
    "name:rus_x_preferred":[
        "Mullakheyl\u2019"
    ],
    "name:und_x_variant":[
        "Mull\u0101 Kh\u0113l",
        "\u0645\u0644\u0627 \u062e\u06d0\u0644",
        "Moll\u0101 Kheyl"
    ],
    "wof:name":"Mulla Khel",
    "wof:placetype":"locality"
},
  "geometry": {"coordinates":[66.7932,32.6558],"type":"Point"}
}