{
  "type": "Feature",
  "properties": {
    "gn:admin1_code":"42",
    "gn:admin2_code":"3306.0",
    "gn:asciiname":"Asalat Khel",
    "gn:country_code":"AF",
    "gn:dem":2016,
    "gn:feature_class":"P",
    "gn:feature_code":"PPL",
    "gn:name":"A\u015f\u0101lat Kh\u0113l",
    "gn:population":0,
    "gn:timezone":"Asia/Kabul",
    "iso:country":"AF",
    "name:fas_x_preferred":[
        "\u0627\u0633\u0627\u0644\u062a \u062e\u064a\u0644"
    ],
    "name:rus_x_preferred":[
        "Asalatkheyl\u2019"
    ],
    "name:und_x_variant":[
        "As\u0101tetkh\u0113t",
        "A\u015f\u0101latkh\u0113l",
        "As\u0101letkh\u0113l",
        "As\u0101letkheyl",
        "A\u015f\u0101lat Kh\u0113l",
        "\u0627\u0635\u0627\u0644\u062a \u062e\u06d0\u0644"
    ],
    "wof:name":"Asalat Khel",
    "wof:placetype":"locality"
},
  "geometry": {"coordinates":[69.44135,35.22459],"type":"Point"}
}