{
  "type": "Feature",
  "properties": {
    "gn:admin1_code":"26",
    "gn:admin2_code":"1201.0",
    "gn:asciiname":"Chob Bur",
    "gn:country_code":"AF",
    "gn:dem":868,
    "gn:feature_class":"P",
    "gn:feature_code":"PPL",
    "gn:name":"Ch\u014db Bur",
    "gn:population":0,
    "gn:timezone":"Asia/Kabul",
    "iso:country":"AF",
    "name:rus_x_preferred":[
        "\u0427\u043e\u0431\u0431\u0443\u0440"
    ],
    "name:und_x_variant":[
        "\u010cob Bur",
        "Chobbur",
        "Ch\u016bb Bor",
        "Ch\u014db Bur",
        "\u0686\u0648\u0628 \u0628\u0631"
    ],
    "wof:name":"Chob Bur",
    "wof:placetype":"locality"
},
  "geometry": {"coordinates":[69.59594,36.73899],"type":"Point"}
}