{
  "type": "Feature",
  "properties": {
    "gn:admin1_code":"02",
    "gn:admin2_code":"1906",
    "gn:asciiname":"Pa'in Panayrak",
    "gn:country_code":"AF",
    "gn:dem":765,
    "gn:feature_class":"P",
    "gn:feature_code":"PPL",
    "gn:name":"P\u0101\u2019\u012bn Panayrak",
    "gn:population":0,
    "gn:timezone":"Asia/Kabul",
    "iso:country":"AF",
    "name:und_x_variant":[
        "P\u0101\u2019\u012bn Panayrak",
        "\u067e\u0627\u0626\u06cc\u0646 \u067e\u0646\u06cc\u0631\u06a9",
        "P\u0101\u2019\u012bn Pan\u0113\u1e5fak"
    ],
    "wof:name":"Pa'in Panayrak",
    "wof:placetype":"locality"
},
  "geometry": {"coordinates":[63.56237,35.56081],"type":"Point"}
}