{
  "type": "Feature",
  "properties": {
    "gn:admin1_code":"5",
    "gn:admin2_code":"2806.0",
    "gn:asciiname":"Amrod-e 'Ulya",
    "gn:country_code":"AF",
    "gn:dem":2462,
    "gn:feature_class":"P",
    "gn:feature_code":"PPL",
    "gn:name":"Amr\u014dd-e \u2018Uly\u0101",
    "gn:population":0,
    "gn:timezone":"Asia/Kabul",
    "iso:country":"AF",
    "name:und_x_variant":[
        "Amrudi-Ulia",
        "Am\u1e5f\u014d\u1e0fe \u2018Uly\u0101",
        "Amr\u014dd-e \u2018Oly\u0101",
        "Amr\u016bd-e \u2018Oly\u0101",
        "Amr\u014dd-e \u2018Uly\u0101",
        "\u0627\u0645\u0631\u0648\u062f \u0639\u0644\u06cc\u0627"
    ],
    "wof:name":"Amrod-e 'Ulya",
    "wof:placetype":"locality"
},
  "geometry": {"coordinates":[66.95194000000001,34.20083],"type":"Point"}
}