{
  "type": "Feature",
  "properties": {
    "gn:admin1_code":"05",
    "gn:admin2_code":"2805",
    "gn:asciiname":"Siyah Guli",
    "gn:country_code":"AF",
    "gn:dem":3196,
    "gn:feature_class":"P",
    "gn:feature_code":"PPL",
    "gn:name":"Siy\u0101h Gul\u012b",
    "gn:population":0,
    "gn:timezone":"Asia/Kabul",
    "iso:country":"AF",
    "name:und_x_variant":[
        "Sy\u0101h Goli",
        "Siakhguli",
        "S\u012b\u0101h Gul\u012b",
        "S\u012b\u0101h Gol\u012b",
        "\u0633\u06cc\u0627\u0647 \u06af\u0648\u0644\u06cc",
        "S\u012b\u0101h G\u014dl\u012b",
        "Siy\u0101h Gul\u012b",
        "\u0633\u064a\u0627\u0647 \u06af\u0644\u06cc"
    ],
    "wof:name":"Siyah Guli",
    "wof:placetype":"locality"
},
  "geometry": {"coordinates":[66.81692,34.49930999999999],"type":"Point"}
}