{
  "type": "Feature",
  "properties": {
    "gn:admin1_code":"32",
    "gn:admin2_code":"1504.0",
    "gn:asciiname":"Madri",
    "gn:country_code":"AF",
    "gn:dem":1410,
    "gn:feature_class":"P",
    "gn:feature_code":"PPL",
    "gn:name":"Madr\u012b",
    "gn:population":0,
    "gn:timezone":"Asia/Kabul",
    "iso:country":"AF",
    "name:und_x_variant":[
        "Madri (2)",
        "Madr\u012b",
        "\u0645\u062f\u0631\u06cc"
    ],
    "wof:name":"Madri",
    "wof:placetype":"locality"
},
  "geometry": {"coordinates":[67.28159000000001,36.10078],"type":"Point"}
}