{
  "type": "Feature",
  "properties": {
    "gn:admin1_code":"27",
    "gn:admin2_code":"404.0",
    "gn:asciiname":"Nawer Ghaybi",
    "gn:country_code":"AF",
    "gn:dem":3008,
    "gn:feature_class":"P",
    "gn:feature_code":"PPL",
    "gn:name":"N\u0101w\u00ear Ghayb\u012b",
    "gn:population":0,
    "gn:timezone":"Asia/Kabul",
    "iso:country":"AF",
    "name:und_x_variant":[
        "Nawgu\u1e5f Ghaybi",
        "Navurgaybi",
        "Nawu\u1e5f Ghaybi",
        "N\u0101wur Ghayb\u012b",
        "N\u0101wur Gheyb\u012b",
        "N\u0101w\u00ear Ghayb\u012b",
        "\u0646\u0627\u0648\u0631 \u063a\u06cc\u0628\u06cc"
    ],
    "wof:name":"Nawer Ghaybi",
    "wof:placetype":"locality"
},
  "geometry": {"coordinates":[67.77245000000001,34.35631],"type":"Point"}
}