{
  "type": "Feature",
  "properties": {
    "gn:admin1_code":"03",
    "gn:admin2_code":"1303",
    "gn:asciiname":"Ganji",
    "gn:country_code":"AF",
    "gn:dem":1310,
    "gn:feature_class":"P",
    "gn:feature_code":"PPL",
    "gn:name":"Ganj\u012b",
    "gn:population":0,
    "gn:timezone":"Asia/Kabul",
    "iso:country":"AF",
    "name:ceb_x_preferred":[
        "Ganji"
    ],
    "name:fas_x_preferred":[
        "\u06af\u0646\u062c\u06cc"
    ],
    "name:swe_x_preferred":[
        "Ganji"
    ],
    "name:und_x_variant":[
        "Gandzhi",
        "Ganj\u012b"
    ],
    "wof:name":"Ganji",
    "wof:placetype":"locality"
},
  "geometry": {"coordinates":[68.53631999999999,35.79075],"type":"Point"}
}