{
  "type": "Feature",
  "properties": {
    "gn:admin1_code":"10",
    "gn:admin2_code":"2305",
    "gn:asciiname":"Sadmanay",
    "gn:country_code":"AF",
    "gn:dem":1979,
    "gn:feature_class":"P",
    "gn:feature_code":"PPL",
    "gn:name":"\u015eadmanay",
    "gn:population":0,
    "gn:timezone":"Asia/Kabul",
    "iso:country":"AF",
    "name:fas_x_preferred":[
        "\u0635\u062f \u0645\u0646\u06cc"
    ],
    "name:rus_x_preferred":[
        "\u0421\u0430\u0434\u043c\u0430\u043d\u0430\u0439"
    ],
    "name:und_x_variant":[
        "\u015eadmaneh",
        "\u015eadmanay",
        "\u0635\u062f\u0645\u0646\u06cc"
    ],
    "wof:name":"Sadmanay",
    "wof:placetype":"locality"
},
  "geometry": {"coordinates":[65.00458,33.14508],"type":"Point"}
}