{
  "type": "Feature",
  "properties": {
    "gn:admin1_code":"38",
    "gn:admin2_code":"3001",
    "gn:asciiname":"Kantiway-ye 'Ulya",
    "gn:country_code":"AF",
    "gn:dem":2460,
    "gn:feature_class":"P",
    "gn:feature_code":"PPL",
    "gn:name":"K\u0101ntiw\u0101y-ye \u2018Uly\u0101",
    "gn:population":0,
    "gn:timezone":"Asia/Kabul",
    "iso:country":"AF",
    "name:und_x_variant":[
        "Kti",
        "K\u0101n\u012btw\u0101",
        "K\u0101n\u012bw\u0101",
        "K\u0101nt\u012bw\u0101",
        "K\u0101ntiw-ye \u2018Oly\u0101",
        "K\u0101ntiw\u0101y \u2019Uly\u0101",
        "Kantivay-Ulia",
        "\u06a9\u0627\u0646\u062a\u0648\u0627\u06cc \u0639\u0644\u06cc\u0627",
        "K\u0101nt\u012bw\u0101-ye \u2018Oly\u0101",
        "K\u0101ntiw\u0101y-ye \u2018Oly\u0101",
        "K\u0101ntiw\u0101y-ye \u2018Uly\u0101"
    ],
    "wof:name":"Kantiway-ye 'Ulya",
    "wof:placetype":"locality"
},
  "geometry": {"coordinates":[70.73716,35.32264],"type":"Point"}
}