{
  "type": "Feature",
  "properties": {
    "gn:admin1_code":"10",
    "gn:admin2_code":"2302.0",
    "gn:asciiname":"Karim Karez",
    "gn:country_code":"AF",
    "gn:dem":917,
    "gn:feature_class":"P",
    "gn:feature_code":"PPL",
    "gn:name":"Kar\u012bm K\u0101r\u0113z",
    "gn:population":0,
    "gn:timezone":"Asia/Kabul",
    "iso:country":"AF",
    "name:und_x_variant":[
        "Kar\u012bm K\u0101r\u0113z",
        "\u06a9\u0631\u06cc\u0645 \u06a9\u0627\u0631\u06d0\u0632"
    ],
    "wof:name":"Karim Karez",
    "wof:placetype":"locality"
},
  "geometry": {"coordinates":[64.84708000000001,31.97131],"type":"Point"}
}