{
  "type": "Feature",
  "properties": {
    "gn:admin1_code":"11",
    "gn:admin2_code":"2004",
    "gn:asciiname":"Lorah",
    "gn:country_code":"AF",
    "gn:dem":1380,
    "gn:feature_class":"P",
    "gn:feature_code":"PPL",
    "gn:name":"L\u014d\u1e5fah",
    "gn:population":0,
    "gn:timezone":"Asia/Kabul",
    "iso:country":"AF",
    "name:und_x_variant":[
        "Lora",
        "L\u014drah",
        "Lowrah",
        "L\u014d\u1e5fah",
        "\u0644\u0648\u0693\u0647"
    ],
    "wof:name":"Lorah",
    "wof:placetype":"locality"
},
  "geometry": {"coordinates":[62.61309,34.13761],"type":"Point"}
}