{
  "type": "Feature",
  "properties": {
    "gn:admin1_code":"36",
    "gn:admin2_code":"706.0",
    "gn:asciiname":"Mushay",
    "gn:country_code":"AF",
    "gn:dem":1958,
    "gn:feature_class":"P",
    "gn:feature_code":"PPL",
    "gn:name":"M\u016bshay",
    "gn:population":0,
    "gn:timezone":"Asia/Kabul",
    "iso:country":"AF",
    "name:und_x_variant":[
        "M\u016b\u0161ay",
        "Mushay",
        "M\u016bshay",
        "\u0645\u0648\u0634\u06cc"
    ],
    "wof:name":"Mushay",
    "wof:placetype":"locality"
},
  "geometry": {"coordinates":[69.78088000000001,33.67184],"type":"Point"}
}