{
  "type": "Feature",
  "properties": {
    "gn:admin1_code":"23",
    "gn:admin2_code":"2405.0",
    "gn:asciiname":"La'l Muhammad Kelay",
    "gn:country_code":"AF",
    "gn:dem":1455,
    "gn:feature_class":"P",
    "gn:feature_code":"PPL",
    "gn:name":"La\u2018l Mu\u1e29ammad K\u00ealay",
    "gn:population":0,
    "gn:timezone":"Asia/Kabul",
    "iso:country":"AF",
    "name:fas_x_preferred":[
        "\u0642\u0631\u064a\u06c0 \u0644\u0639\u0644 \u0645\u062d\u0645\u062f"
    ],
    "name:rus_x_preferred":[
        "Lal\u2019-Mukhammed-Kalay"
    ],
    "name:und_x_variant":[
        "La\u2018l Mu\u1e29ammad K\u00ealay",
        "\u0644\u0639\u0644 \u0645\u062d\u0645\u062f \u06a9\u0644\u06cc",
        "La\u2018l Mo\u1e29ammad Kalay"
    ],
    "wof:name":"La'l Muhammad Kelay",
    "wof:placetype":"locality"
},
  "geometry": {"coordinates":[65.63308000000001,31.9971],"type":"Point"}
}