{
  "type": "Feature",
  "properties": {
    "gn:admin1_code":"08",
    "gn:admin2_code":"606",
    "gn:asciiname":"Pay Bum",
    "gn:country_code":"AF",
    "gn:dem":3035,
    "gn:feature_class":"P",
    "gn:feature_code":"PPL",
    "gn:name":"P\u0101y B\u016bm",
    "gn:population":0,
    "gn:timezone":"Asia/Kabul",
    "iso:country":"AF",
    "name:fas_x_preferred":[
        "\u067e\u0627\u0626 \u0628\u0648\u0645"
    ],
    "name:fas_x_variant":[
        "\u067e\u0627\u064a\u0628\u0648\u0645"
    ],
    "name:rus_x_preferred":[
        "\u041f\u0430\u0439\u0431\u0443\u043c"
    ],
    "name:und_x_variant":[
        "Paybum",
        "P\u0101y B\u016bm",
        "\u067e\u0627\u06cc \u0628\u0648\u0645"
    ],
    "wof:name":"Pay Bum",
    "wof:placetype":"locality"
},
  "geometry": {"coordinates":[67.52242,33.50464],"type":"Point"}
}