{
  "type": "Feature",
  "properties": {
    "gn:admin1_code":"35",
    "gn:admin2_code":"902.0",
    "gn:asciiname":"Karimabad",
    "gn:country_code":"AF",
    "gn:dem":637,
    "gn:feature_class":"P",
    "gn:feature_code":"PPL",
    "gn:name":"Kar\u012bm\u0101b\u0101d",
    "gn:population":0,
    "gn:timezone":"Asia/Kabul",
    "iso:country":"AF",
    "name:aze_x_preferred":[
        "K\u0259rimabad"
    ],
    "name:deu_x_preferred":[
        "Karimabad"
    ],
    "name:fas_x_preferred":[
        "\u06a9\u0631\u06cc\u0645\u200c\u0622\u0628\u0627\u062f"
    ],
    "name:ita_x_preferred":[
        "Karimabad"
    ],
    "name:und_x_variant":[
        "Kar\u012bm\u0101b\u0101d",
        "\u06a9\u0631\u06cc\u0645 \u0622\u0628\u0627\u062f"
    ],
    "wof:name":"Karimabad",
    "wof:placetype":"locality"
},
  "geometry": {"coordinates":[70.21850000000001,34.52033],"type":"Point"}
}