{
  "type": "Feature",
  "properties": {
    "gn:admin1_code":"05",
    "gn:admin2_code":"2806",
    "gn:asciiname":"Lukhak",
    "gn:country_code":"AF",
    "gn:dem":2837,
    "gn:feature_class":"P",
    "gn:feature_code":"PPL",
    "gn:name":"Lukhak",
    "gn:population":0,
    "gn:timezone":"Asia/Kabul",
    "iso:country":"AF",
    "name:und_x_variant":[
        "Lokhak",
        "Lukhak",
        "\u0644\u062e\u06a9"
    ],
    "wof:name":"Lukhak",
    "wof:placetype":"locality"
},
  "geometry": {"coordinates":[67.12668000000001,34.21864],"type":"Point"}
}