{
  "type": "Feature",
  "properties": {
    "gn:admin1_code":"23",
    "gn:admin2_code":"2413.0",
    "gn:asciiname":"Zorvam",
    "gn:country_code":"AF",
    "gn:dem":1595,
    "gn:feature_class":"P",
    "gn:feature_code":"PPL",
    "gn:name":"Zorvam",
    "gn:population":0,
    "gn:timezone":"Asia/Kabul",
    "iso:country":"AF",
    "name:und_x_variant":[
        "Z\u014drw\u0101m",
        "Zorvam",
        "Z\u014d\u1e5f W\u0101m",
        "Z\u016brw\u0101m",
        "\u0632\u0648\u0693 \u0648\u0627\u0645"
    ],
    "wof:name":"Zorvam",
    "wof:placetype":"locality"
},
  "geometry": {"coordinates":[66.93666999999999,31.43917],"type":"Point"}
}