{
  "type": "Feature",
  "properties": {
    "gn:admin1_code":"05",
    "gn:admin2_code":"2801",
    "gn:asciiname":"Kadalak",
    "gn:country_code":"AF",
    "gn:dem":2834,
    "gn:feature_class":"P",
    "gn:feature_code":"PPL",
    "gn:name":"Kadalak",
    "gn:population":0,
    "gn:timezone":"Asia/Kabul",
    "iso:country":"AF",
    "name:und_x_variant":[
        "\u06a9\u062f\u0644\u06a9"
    ],
    "wof:name":"Kadalak",
    "wof:placetype":"locality"
},
  "geometry": {"coordinates":[67.64469,34.8445],"type":"Point"}
}