{
  "type": "Feature",
  "properties": {
    "gn:admin1_code":"10",
    "gn:admin2_code":"2302.0",
    "gn:asciiname":"Masizi",
    "gn:country_code":"AF",
    "gn:dem":813,
    "gn:feature_class":"P",
    "gn:feature_code":"PPL",
    "gn:name":"Masiz\u012b",
    "gn:population":0,
    "gn:timezone":"Asia/Kabul",
    "iso:country":"AF",
    "name:fas_x_preferred":[
        "\u0645\u0633\u064a\u0632\u06cc"
    ],
    "name:und_x_variant":[
        "Maoizi",
        "Mastzi",
        "Masiza\u012b",
        "\u0645\u0633\u0632\u06cc",
        "Mas\u012bz\u012b",
        "Masiz\u012b"
    ],
    "wof:name":"Masizi",
    "wof:placetype":"locality"
},
  "geometry": {"coordinates":[64.49949000000001,31.76802],"type":"Point"}
}