{
  "type": "Feature",
  "properties": {
    "gn:admin1_code":"23",
    "gn:admin2_code":"2403",
    "gn:asciiname":"Tangay",
    "gn:country_code":"AF",
    "gn:dem":1551,
    "gn:feature_class":"P",
    "gn:feature_code":"PPL",
    "gn:name":"Tangay",
    "gn:population":0,
    "gn:timezone":"Asia/Kabul",
    "iso:country":"AF",
    "name:und_x_variant":[
        "Tanga\u012b",
        "\u062a\u0646\u06af\u06cc",
        "Tangi",
        "Tangay"
    ],
    "wof:name":"Tangay",
    "wof:placetype":"locality"
},
  "geometry": {"coordinates":[66.11395,32.13283],"type":"Point"}
}