{
  "type": "Feature",
  "properties": {
    "gn:admin1_code":"18",
    "gn:admin2_code":"810.0",
    "gn:asciiname":"Akhundzadahgan",
    "gn:country_code":"AF",
    "gn:dem":977,
    "gn:feature_class":"P",
    "gn:feature_code":"PPL",
    "gn:name":"\u0100kh\u016bndz\u0101dahg\u0101n",
    "gn:population":0,
    "gn:timezone":"Asia/Kabul",
    "iso:country":"AF",
    "name:fas_x_preferred":[
        "\u0622\u062e\u0648\u0646\u062f\u0632\u0627\u062f\u06af\u0627\u0646"
    ],
    "name:und_x_variant":[
        "\u0100khun\u1e0fz\u0101\u1e0fag\u0101n",
        "Akhunzadagan",
        "\u0100khvondz\u0101deg\u0101n",
        "\u0100kh\u016bndz\u0101dahg\u0101n",
        "\u0622\u062e\u0648\u0646\u062f\u0632\u0627\u062f\u0647 \u06af\u0627\u0646"
    ],
    "wof:name":"Akhundzadahgan",
    "wof:placetype":"locality"
},
  "geometry": {"coordinates":[70.75201,34.09656],"type":"Point"}
}