{
  "type": "Feature",
  "properties": {
    "gn:admin1_code":"41",
    "gn:admin2_code":"3408.0",
    "gn:asciiname":"Dahan-e Naw Seb",
    "gn:country_code":"AF",
    "gn:dem":2660,
    "gn:feature_class":"P",
    "gn:feature_code":"PPL",
    "gn:name":"Dahan-e N\u0101w S\u0113b",
    "gn:population":0,
    "gn:timezone":"Asia/Kabul",
    "iso:country":"AF",
    "name:und_x_variant":[
        "Dakhani-Nauseb",
        "\u1e0eahane Naws\u0113b",
        "Dahan-e N\u0101w Sayb",
        "Dahan-e Nows\u012bb",
        "Dahan-e N\u0101w S\u0113b",
        "\u062f\u0647\u0646 \u0646\u0627\u0648 \u0633\u06d0\u0628"
    ],
    "wof:name":"Dahan-e Naw Seb",
    "wof:placetype":"locality"
},
  "geometry": {"coordinates":[66.05932,34.30458],"type":"Point"}
}