{
  "type": "Feature",
  "properties": {
    "gn:admin1_code":"6",
    "gn:admin2_code":"2102.0",
    "gn:asciiname":"Moghulabad",
    "gn:country_code":"AF",
    "gn:dem":735,
    "gn:feature_class":"P",
    "gn:feature_code":"PPL",
    "gn:name":"Moghul\u0101b\u0101d",
    "gn:population":0,
    "gn:timezone":"Asia/Kabul",
    "iso:country":"AF",
    "name:und_x_variant":[
        "Razvaliny Mugulabad",
        "Moghul\u0101b\u0101\u1e0f",
        "Moghol \u0100b\u0101d",
        "Moghul\u0101b\u0101d",
        "\u0645\u063a\u0644 \u0622\u0628\u0627\u062f"
    ],
    "wof:name":"Moghulabad",
    "wof:placetype":"locality"
},
  "geometry": {"coordinates":[63.03949,32.21628],"type":"Point"}
}