{
  "type": "Feature",
  "properties": {
    "gn:admin1_code":"24",
    "gn:admin2_code":"1406.0",
    "gn:asciiname":"Khuk Darah",
    "gn:country_code":"AF",
    "gn:dem":658,
    "gn:feature_class":"P",
    "gn:feature_code":"PPL",
    "gn:name":"Kh\u016bk Darah",
    "gn:population":0,
    "gn:timezone":"Asia/Kabul",
    "iso:country":"AF",
    "name:fas_x_preferred":[
        "\u062e\u0648\u0643 \u062f\u0631\u0647"
    ],
    "name:rus_x_preferred":[
        "\u0425\u0443\u043a\u0434\u0430\u0440\u0430"
    ],
    "name:und_x_variant":[
        "Khukdara",
        "Kh\u016bk \u1e0ea\u1e5f\u1e5fah",
        "Kh\u016bk Darreh",
        "Kh\u016bk Darah",
        "\u062e\u0648\u06a9 \u062f\u0631\u0647"
    ],
    "wof:name":"Khuk Darah",
    "wof:placetype":"locality"
},
  "geometry": {"coordinates":[69.11784,36.60794],"type":"Point"}
}