{
  "type": "Feature",
  "properties": {
    "gn:admin1_code":"35",
    "gn:admin2_code":"901.0",
    "gn:asciiname":"Aba Khel",
    "gn:country_code":"AF",
    "gn:dem":820,
    "gn:feature_class":"P",
    "gn:feature_code":"PPL",
    "gn:name":"Ab\u0101 Kh\u0113l",
    "gn:population":0,
    "gn:timezone":"Asia/Kabul",
    "iso:country":"AF",
    "name:ceb_x_preferred":[
        "Aba Khel"
    ],
    "name:rus_x_preferred":[
        "Abakheyl\u2019"
    ],
    "name:und_x_variant":[
        "\u0627\u0628\u0627 \u062e\u06d0\u0644",
        "Ab\u0101kheyl",
        "Ab\u0101 Kh\u0113l"
    ],
    "wof:name":"Aba Khel",
    "wof:placetype":"locality"
},
  "geometry": {"coordinates":[70.28761999999999,34.74503],"type":"Point"}
}