{
  "type": "Feature",
  "properties": {
    "gn:admin1_code":"23",
    "gn:admin2_code":"2410",
    "gn:asciiname":"Kundil Kala",
    "gn:country_code":"AF",
    "gn:dem":959,
    "gn:feature_class":"P",
    "gn:feature_code":"PPL",
    "gn:name":"Kundil Kal\u0101",
    "gn:population":0,
    "gn:timezone":"Asia/Kabul",
    "iso:country":"AF",
    "name:pus_x_preferred":[
        "\u06a9\u0646\u062f\u0644 \u06a9\u0644\u0627"
    ],
    "name:und_x_variant":[
        "Kun\u1e0fel",
        "Kondel Kalay",
        "Kun\u1e0fel Kal\u0101",
        "Kondel Kal\u0101",
        "Kundil Kal\u0101"
    ],
    "wof:name":"Kundil Kala",
    "wof:placetype":"locality"
},
  "geometry": {"coordinates":[65.96184000000001,29.94379],"type":"Point"}
}