{
  "type": "Feature",
  "properties": {
    "gn:admin1_code":"34",
    "gn:admin2_code":"1010.0",
    "gn:asciiname":"Aw Mar",
    "gn:country_code":"AF",
    "gn:dem":1057,
    "gn:feature_class":"P",
    "gn:feature_code":"PPL",
    "gn:name":"Aw M\u0101r",
    "gn:population":0,
    "gn:timezone":"Asia/Kabul",
    "iso:country":"AF",
    "wof:name":"Aw Mar",
    "wof:placetype":"locality"
},
  "geometry": {"coordinates":[70.94906999999998,34.92804],"type":"Point"}
}