{
  "type": "Feature",
  "properties": {
    "gn:admin1_code":"24",
    "gn:admin2_code":"1405.0",
    "gn:asciiname":"Birkah",
    "gn:country_code":"AF",
    "gn:dem":521,
    "gn:feature_class":"P",
    "gn:feature_code":"PPL",
    "gn:name":"Birkah",
    "gn:population":0,
    "gn:timezone":"Asia/Kabul",
    "iso:country":"AF",
    "name:rus_x_preferred":[
        "\u0411\u0438\u0440\u043a\u0430"
    ],
    "name:und_x_variant":[
        "Birka",
        "Berkah",
        "Be\u1e5fka",
        "Berkeh",
        "Birkah",
        "\u0628\u0631\u06a9\u0647"
    ],
    "wof:name":"Birkah",
    "wof:placetype":"locality"
},
  "geometry": {"coordinates":[68.93493000000001,36.48152],"type":"Point"}
}