{
  "type": "Feature",
  "properties": {
    "gn:admin1_code":"01",
    "gn:admin2_code":"1113.0",
    "gn:asciiname":"Khak Pitaw",
    "gn:country_code":"AF",
    "gn:dem":1969,
    "gn:feature_class":"P",
    "gn:feature_code":"PPL",
    "gn:name":"Kh\u0101k Pit\u0101w",
    "gn:population":0,
    "gn:timezone":"Asia/Kabul",
    "iso:country":"AF",
    "name:und_x_variant":[
        "Kh\u0101k P\u0113t\u0101w",
        "Kh\u0101k P\u0113t\u0101v",
        "Kh\u0101k Pit\u0101w",
        "\u062e\u0627\u06a9 \u067e\u062a\u0627\u0648"
    ],
    "wof:name":"Khak Pitaw",
    "wof:placetype":"locality"
},
  "geometry": {"coordinates":[70.10678,37.37271],"type":"Point"}
}