{
  "type": "Feature",
  "properties": {
    "gn:admin1_code":"10",
    "gn:admin2_code":"2305.0",
    "gn:asciiname":"Sher Yak",
    "gn:country_code":"AF",
    "gn:dem":1411,
    "gn:feature_class":"P",
    "gn:feature_code":"PPL",
    "gn:name":"Sh\u0113r Yak",
    "gn:population":0,
    "gn:timezone":"Asia/Kabul",
    "iso:country":"AF",
    "name:rus_x_preferred":[
        "Shir\u2019yak"
    ],
    "name:und_x_variant":[
        "\u0160\u012bryak",
        "Shayr Yak",
        "\u0634\u06cc\u0631 \u06cc\u06a9",
        "Sh\u012bryak",
        "Sh\u0113r Yak"
    ],
    "wof:name":"Sher Yak",
    "wof:placetype":"locality"
},
  "geometry": {"coordinates":[64.96556,32.66364],"type":"Point"}
}