{
  "type": "Feature",
  "properties": {
    "gn:admin1_code":"37",
    "gn:admin2_code":"3201.0",
    "gn:asciiname":"Kamar Kala",
    "gn:country_code":"AF",
    "gn:dem":1048,
    "gn:feature_class":"P",
    "gn:feature_code":"PPL",
    "gn:name":"Kamar Kal\u0101",
    "gn:population":0,
    "gn:timezone":"Asia/Kabul",
    "iso:country":"AF",
    "name:fas_x_preferred":[
        "\u0642\u0644\u0639\u0647\u0654 \u0643\u0645\u0631"
    ],
    "name:und_x_variant":[
        "Kamarkala",
        "Kamar Kal\u0101",
        "Kama\u1e5f Kal\u0101",
        "\u06a9\u0645\u0631 \u06a9\u0644\u0627"
    ],
    "wof:name":"Kamar Kala",
    "wof:placetype":"locality"
},
  "geometry": {"coordinates":[70.0762,33.34993],"type":"Point"}
}