{
  "type": "Feature",
  "properties": {
    "gn:admin1_code":"27",
    "gn:admin2_code":"404.0",
    "gn:asciiname":"Sar-e Bay",
    "gn:country_code":"AF",
    "gn:dem":2961,
    "gn:feature_class":"P",
    "gn:feature_code":"PPL",
    "gn:name":"Sar-e B\u0101y",
    "gn:population":0,
    "gn:timezone":"Asia/Kabul",
    "iso:country":"AF",
    "name:und_x_variant":[
        "Sari-Bai",
        "Sar-e B\u0101y",
        "Sar-e B\u0101\u2018\u012b",
        "\u0633\u0631 \u0628\u0627\u06cc"
    ],
    "wof:name":"Sar-e Bay",
    "wof:placetype":"locality"
},
  "geometry": {"coordinates":[67.77101,34.4826],"type":"Point"}
}