{
  "type": "Feature",
  "properties": {
    "gn:admin1_code":"36",
    "gn:admin2_code":"702.0",
    "gn:asciiname":"Mullayan",
    "gn:country_code":"AF",
    "gn:dem":2182,
    "gn:feature_class":"P",
    "gn:feature_code":"PPL",
    "gn:name":"Mull\u0101y\u0101n",
    "gn:population":0,
    "gn:timezone":"Asia/Kabul",
    "iso:country":"AF",
    "name:fas_x_preferred":[
        "\u0645\u0644\u0627\u06cc\u0627\u0646"
    ],
    "name:und_x_variant":[
        "\u0645\u0644\u0627\u06cc\u0627\u0646",
        "Moll\u0101y\u0101n",
        "Mull\u0101y\u0101n"
    ],
    "wof:name":"Mullayan",
    "wof:placetype":"locality"
},
  "geometry": {"coordinates":[69.09782,33.47078],"type":"Point"}
}