{
  "type": "Feature",
  "properties": {
    "gn:admin1_code":"27",
    "gn:admin2_code":"404",
    "gn:asciiname":"Sumuchak",
    "gn:country_code":"AF",
    "gn:dem":2994,
    "gn:feature_class":"P",
    "gn:feature_code":"PPL",
    "gn:name":"Sum\u016bchak",
    "gn:population":0,
    "gn:timezone":"Asia/Kabul",
    "iso:country":"AF",
    "name:und_x_variant":[
        "Som\u016b\u010dak",
        "Sumuchak",
        "Som\u016bchak",
        "Sum\u016bchak",
        "\u0633\u0645\u0648\u0686\u06a9"
    ],
    "wof:name":"Sumuchak",
    "wof:placetype":"locality"
},
  "geometry": {"coordinates":[67.99078,34.35788],"type":"Point"}
}