{
  "type": "Feature",
  "properties": {
    "gn:admin1_code":"01",
    "gn:admin2_code":"1115.0",
    "gn:asciiname":"Qarah Kamar",
    "gn:country_code":"AF",
    "gn:dem":1026,
    "gn:feature_class":"P",
    "gn:feature_code":"PPL",
    "gn:name":"Qarah Kamar",
    "gn:population":0,
    "gn:timezone":"Asia/Kabul",
    "iso:country":"AF",
    "name:und_x_variant":[
        "Qa\u1e5fa Kamar",
        "Qareh Kamar",
        "Qarah Kamar",
        "\u0642\u0631\u0647 \u06a9\u0645\u0631"
    ],
    "wof:name":"Qarah Kamar",
    "wof:placetype":"locality"
},
  "geometry": {"coordinates":[70.2706,37.19902],"type":"Point"}
}