{
  "type": "Feature",
  "properties": {
    "gn:admin1_code":"9",
    "gn:admin2_code":"2706.0",
    "gn:asciiname":"Dahan-e Nulur",
    "gn:country_code":"AF",
    "gn:dem":1760,
    "gn:feature_class":"P",
    "gn:feature_code":"PPL",
    "gn:name":"Dah\u0101n-e N\u016bl\u016br",
    "gn:population":0,
    "gn:timezone":"Asia/Kabul",
    "iso:country":"AF",
    "name:und_x_variant":[
        "Dah\u0101n-e N\u016bl\u016br",
        "\u062f\u0647\u0627\u0646 \u0646\u0648\u0644\u0648\u0631",
        "\u1e0eahane N\u016bl\u016b\u1e5f"
    ],
    "wof:name":"Dahan-e Nulur",
    "wof:placetype":"locality"
},
  "geometry": {"coordinates":[65.51229000000001,33.64991],"type":"Point"}
}