{
  "type": "Feature",
  "properties": {
    "gn:admin1_code":"18",
    "gn:admin2_code":"810.0",
    "gn:asciiname":"Waro Kalo",
    "gn:country_code":"AF",
    "gn:dem":934,
    "gn:feature_class":"P",
    "gn:feature_code":"PPL",
    "gn:name":"Wa\u1e5f\u014d Kal\u014d",
    "gn:population":0,
    "gn:timezone":"Asia/Kabul",
    "iso:country":"AF",
    "name:fas_x_preferred":[
        "\u0642\u0644\u0639\u0647\u0654 \u062e\u0648\u0631\u062f"
    ],
    "name:und_x_variant":[
        "Varu-Kalu",
        "Waro Kalo",
        "Wa\u1e5f\u014d Kal\u014d",
        "\u0648\u0693\u0648 \u06a9\u0644\u0648"
    ],
    "wof:name":"Waro Kalo",
    "wof:placetype":"locality"
},
  "geometry": {"coordinates":[70.71661,34.13097],"type":"Point"}
}