{
  "type": "Feature",
  "properties": {
    "gn:admin1_code":"37",
    "gn:admin2_code":"3204",
    "gn:asciiname":"Ragay",
    "gn:country_code":"AF",
    "gn:dem":1679,
    "gn:feature_class":"P",
    "gn:feature_code":"PPL",
    "gn:name":"Ragay",
    "gn:population":0,
    "gn:timezone":"Asia/Kabul",
    "iso:country":"AF",
    "name:fas_x_preferred":[
        "\u0631\u06af\u06cc"
    ],
    "name:und_x_variant":[
        "\u1e5eagay"
    ],
    "wof:name":"Ragay",
    "wof:placetype":"locality"
},
  "geometry": {"coordinates":[69.54009000000001,33.21814000000001],"type":"Point"}
}