{
  "type": "Feature",
  "properties": {
    "gn:admin1_code":"11",
    "gn:admin2_code":"2012",
    "gn:asciiname":"Tagab-e Yari",
    "gn:country_code":"AF",
    "gn:dem":1500,
    "gn:feature_class":"P",
    "gn:feature_code":"PPL",
    "gn:name":"Tag\u0101b-e Y\u0101r\u012b",
    "gn:population":0,
    "gn:timezone":"Asia/Kabul",
    "iso:country":"AF",
    "name:und_x_variant":[
        "Nayak",
        "Tag\u0101b-e Y\u0101r\u012b",
        "\u062a\u06af\u0627\u0628 \u06cc\u0627\u0631\u06cc",
        "Nayk",
        "\u0646\u06cc\u06a9"
    ],
    "wof:name":"Tagab-e Yari",
    "wof:placetype":"locality"
},
  "geometry": {"coordinates":[63.28203000000001,34.4636],"type":"Point"}
}