{
  "type": "Feature",
  "properties": {
    "gn:admin1_code":"30",
    "gn:admin2_code":"1603",
    "gn:asciiname":"Mirza Kamar",
    "gn:country_code":"AF",
    "gn:dem":1032,
    "gn:feature_class":"P",
    "gn:feature_code":"PPL",
    "gn:name":"M\u012brz\u0101 Kamar",
    "gn:population":0,
    "gn:timezone":"Asia/Kabul",
    "iso:country":"AF",
    "name:und_x_variant":[
        "M\u012brz\u0101 Kamar",
        "\u0645\u06cc\u0631\u0632\u0627 \u06a9\u0645\u0631"
    ],
    "wof:name":"Mirza Kamar",
    "wof:placetype":"locality"
},
  "geometry": {"coordinates":[66.75774,36.02585],"type":"Point"}
}