{
  "type": "Feature",
  "properties": {
    "gn:admin1_code":"34",
    "gn:admin2_code":"1004.0",
    "gn:asciiname":"Siyan",
    "gn:country_code":"AF",
    "gn:dem":1746,
    "gn:feature_class":"P",
    "gn:feature_code":"PPL",
    "gn:name":"Siy\u0101n",
    "gn:population":0,
    "gn:timezone":"Asia/Kabul",
    "iso:country":"AF",
    "name:fas_x_preferred":[
        "\u0633\u064a\u0627\u0646"
    ],
    "name:rus_x_preferred":[
        "S\u2019yan"
    ],
    "name:und_x_variant":[
        "Sy\u0101n",
        "S\u012b\u0101n",
        "Siy\u0101n"
    ],
    "wof:name":"Siyan",
    "wof:placetype":"locality"
},
  "geometry": {"coordinates":[71.46298,34.97490999999999],"type":"Point"}
}