{
  "type": "Feature",
  "properties": {
    "gn:admin1_code":"40",
    "gn:admin2_code":"301.0",
    "gn:asciiname":"Khanahha-ye Darab",
    "gn:country_code":"AF",
    "gn:dem":2143,
    "gn:feature_class":"P",
    "gn:feature_code":"PPL",
    "gn:name":"Kh\u0101nahh\u0101-ye D\u0101r\u0101b",
    "gn:population":0,
    "gn:timezone":"Asia/Kabul",
    "iso:country":"AF",
    "name:und_x_variant":[
        "Kh\u0101nah\u0101-i-\u1e0e\u0101\u1e5f\u0101b",
        "Khanakhayi-Darab",
        "Kh\u0101nahh\u0101-ye Dar \u0100b",
        "Kh\u0101nehh\u0101-ye D\u0101r\u0101b",
        "Kh\u0101nahh\u0101-ye D\u0101r\u0101b",
        "\u062e\u0627\u0646\u0647 \u0647\u0627\u06cc \u062f\u0627\u0631\u0627\u0628"
    ],
    "wof:name":"Khanahha-ye Darab",
    "wof:placetype":"locality"
},
  "geometry": {"coordinates":[69.10008000000001,34.96474],"type":"Point"}
}