{
  "type": "Feature",
  "properties": {
    "gn:admin1_code":"08",
    "gn:admin2_code":"604",
    "gn:asciiname":"Sar-e Top",
    "gn:country_code":"AF",
    "gn:dem":3019,
    "gn:feature_class":"P",
    "gn:feature_code":"PPL",
    "gn:name":"Sar-e T\u014dp",
    "gn:population":0,
    "gn:timezone":"Asia/Kabul",
    "iso:country":"AF",
    "name:fas_x_preferred":[
        "\u0633\u0631\u0654 \u062a\u0648\u067e"
    ],
    "name:rus_x_preferred":[
        "\u0421\u0430\u0440\u0438-\u0422\u043e\u043f"
    ],
    "name:und_x_variant":[
        "Sa\u1e5fe T\u014dp",
        "Sari-Top",
        "Sar-e T\u016bp",
        "Sar-e T\u014dp",
        "\u0633\u0631 \u062a\u0648\u067e"
    ],
    "wof:name":"Sar-e Top",
    "wof:placetype":"locality"
},
  "geometry": {"coordinates":[67.51483,33.7414],"type":"Point"}
}