{
  "type": "Feature",
  "properties": {
    "gn:admin1_code":"40",
    "gn:admin2_code":"306",
    "gn:asciiname":"Kotak",
    "gn:country_code":"AF",
    "gn:dem":2905,
    "gn:feature_class":"P",
    "gn:feature_code":"PPL",
    "gn:name":"K\u014dtak",
    "gn:population":0,
    "gn:timezone":"Asia/Kabul",
    "iso:country":"AF",
    "name:ceb_x_preferred":[
        "Kotak"
    ],
    "name:deu_x_preferred":[
        "Kotak"
    ],
    "name:swe_x_preferred":[
        "Kotak"
    ],
    "name:und_x_variant":[
        "Kowtak",
        "K\u014dtak",
        "\u06a9\u0648\u062a\u06a9"
    ],
    "wof:name":"Kotak",
    "wof:placetype":"locality"
},
  "geometry": {"coordinates":[68.43321,34.96584],"type":"Point"}
}