{
  "type": "Feature",
  "properties": {
    "gn:admin1_code":"08",
    "gn:admin2_code":"616",
    "gn:asciiname":"Mast Khel",
    "gn:country_code":"AF",
    "gn:dem":2553,
    "gn:feature_class":"P",
    "gn:feature_code":"PPL",
    "gn:name":"Mast Kh\u0113l",
    "gn:population":0,
    "gn:timezone":"Asia/Kabul",
    "iso:country":"AF",
    "name:rus_x_preferred":[
        "Mastkheyl\u2019"
    ],
    "name:und_x_variant":[
        "Mastkh\u0113l",
        "Mast Kh\u0113l",
        "Mast Kheyl",
        "\u0645\u0633\u062a \u062e\u06d0\u0644"
    ],
    "wof:name":"Mast Khel",
    "wof:placetype":"locality"
},
  "geometry": {"coordinates":[68.62019000000001,33.6836],"type":"Point"}
}