{
  "type": "Feature",
  "properties": {
    "gn:admin1_code":"41",
    "gn:admin2_code":"3406.0",
    "gn:asciiname":"Band-e Say",
    "gn:country_code":"AF",
    "gn:dem":2077,
    "gn:feature_class":"P",
    "gn:feature_code":"PPL",
    "gn:name":"Band-e Say",
    "gn:population":0,
    "gn:timezone":"Asia/Kabul",
    "iso:country":"AF",
    "name:und_x_variant":[
        "\u0628\u0646\u062f \u0633\u06cc"
    ],
    "wof:name":"Band-e Say",
    "wof:placetype":"locality"
},
  "geometry": {"coordinates":[65.81737,33.64919],"type":"Point"}
}