{
  "type": "Feature",
  "properties": {
    "gn:admin1_code":"07",
    "gn:admin2_code":"1802",
    "gn:asciiname":"Qanjigh 'Ali",
    "gn:country_code":"AF",
    "gn:dem":652,
    "gn:feature_class":"P",
    "gn:feature_code":"PPL",
    "gn:name":"Qanjigh \u2018Al\u012b",
    "gn:population":0,
    "gn:timezone":"Asia/Kabul",
    "iso:country":"AF",
    "name:und_x_variant":[
        "Kunj\u0101gha Ali",
        "Kunj\u0101gha",
        "Qanjigh \u2018Al\u012b",
        "\u0642\u0646\u062c\u063a \u0639\u0644\u06cc",
        "Qanjegh \u2018Al\u012b"
    ],
    "wof:name":"Qanjigh 'Ali",
    "wof:placetype":"locality"
},
  "geometry": {"coordinates":[64.65761999999999,36.05381],"type":"Point"}
}