{
  "type": "Feature",
  "properties": {
    "gn:admin1_code":"01",
    "gn:admin2_code":"1114.0",
    "gn:asciiname":"Silemait",
    "gn:country_code":"AF",
    "gn:dem":2052,
    "gn:feature_class":"P",
    "gn:feature_code":"PPL",
    "gn:name":"Sil\u0113m\u0101\u012bt",
    "gn:population":0,
    "gn:timezone":"Asia/Kabul",
    "iso:country":"AF",
    "name:und_x_variant":[
        "\u0633\u0644\u06d0\u0645\u0627\u06cc\u062a",
        "Sel\u0113m\u0101yt",
        "Sil\u0113ma\u012bt",
        "Sil\u0113m\u0101yt",
        "Sil\u0113m\u0101\u012bt"
    ],
    "wof:name":"Silemait",
    "wof:placetype":"locality"
},
  "geometry": {"coordinates":[70.75351999999999,37.18343],"type":"Point"}
}