{
  "type": "Feature",
  "properties": {
    "gn:admin1_code":"38",
    "gn:admin2_code":"3005.0",
    "gn:asciiname":"Bachancha",
    "gn:country_code":"AF",
    "gn:dem":2057,
    "gn:feature_class":"P",
    "gn:feature_code":"PPL",
    "gn:name":"Bachanch\u0101",
    "gn:population":0,
    "gn:timezone":"Asia/Kabul",
    "iso:country":"AF",
    "name:und_x_variant":[
        "Ba\u010dan\u010d\u0101",
        "Bachanch\u0101",
        "\u0628\u0686\u0646\u062c\u0627"
    ],
    "wof:name":"Bachancha",
    "wof:placetype":"locality"
},
  "geometry": {"coordinates":[71.33641,35.64213],"type":"Point"}
}