{
  "type": "Feature",
  "properties": {
    "gn:admin1_code":"26",
    "gn:admin2_code":"1205",
    "gn:asciiname":"Sar Dasht",
    "gn:country_code":"AF",
    "gn:dem":2231,
    "gn:feature_class":"P",
    "gn:feature_code":"PPL",
    "gn:name":"Sar Dasht",
    "gn:population":0,
    "gn:timezone":"Asia/Kabul",
    "iso:country":"AF",
    "name:und_x_variant":[
        "Sarda\u0161t",
        "Sar Dasht",
        "\u0633\u0631 \u062f\u0634\u062a"
    ],
    "wof:name":"Sar Dasht",
    "wof:placetype":"locality"
},
  "geometry": {"coordinates":[70.01244,36.07196],"type":"Point"}
}