{
  "type": "Feature",
  "properties": {
    "gn:admin1_code":"41",
    "gn:admin2_code":"3409.0",
    "gn:asciiname":"Top",
    "gn:country_code":"AF",
    "gn:dem":2017,
    "gn:feature_class":"P",
    "gn:feature_code":"PPL",
    "gn:name":"T\u014dp",
    "gn:population":0,
    "gn:timezone":"Asia/Kabul",
    "iso:country":"AF",
    "name:und_x_variant":[
        "T\u014dp",
        "\u1e6e\u016bp",
        "\u062a\u0648\u067e"
    ],
    "wof:name":"Top",
    "wof:placetype":"locality"
},
  "geometry": {"coordinates":[66.67079,33.72468],"type":"Point"}
}