{
  "type": "Feature",
  "properties": {
    "gn:admin1_code":"09",
    "gn:admin2_code":"2710",
    "gn:asciiname":"Kashkar",
    "gn:country_code":"AF",
    "gn:dem":2686,
    "gn:feature_class":"P",
    "gn:feature_code":"PPL",
    "gn:name":"Kashkar",
    "gn:population":0,
    "gn:timezone":"Asia/Kabul",
    "iso:country":"AF",
    "name:ara_x_preferred":[
        "\u0643\u0633\u0643\u0631"
    ],
    "name:cat_x_preferred":[
        "Kaskar"
    ],
    "name:fra_x_preferred":[
        "Kaskar"
    ],
    "name:ita_x_preferred":[
        "Kaskar"
    ],
    "name:und_x_variant":[
        "Ka\u0161kar",
        "Razvaliny Kashkar",
        "Kashkar",
        "\u06a9\u0634\u06a9\u0631"
    ],
    "wof:name":"Kashkar",
    "wof:placetype":"locality"
},
  "geometry": {"coordinates":[64.79318000000001,34.34467],"type":"Point"}
}