{
  "type": "Feature",
  "properties": {
    "gn:admin1_code":"35",
    "gn:admin2_code":"905",
    "gn:asciiname":"Gundali",
    "gn:country_code":"AF",
    "gn:dem":1501,
    "gn:feature_class":"P",
    "gn:feature_code":"PPL",
    "gn:name":"Gundali",
    "gn:population":0,
    "gn:timezone":"Asia/Kabul",
    "iso:country":"AF",
    "name:und_x_variant":[
        "Gund\u0101li",
        "G\u014dn\u1e0f\u0101l\u012b",
        "Gondal\u012b",
        "G\u016bnd\u0101l\u012b",
        "\u06af\u0648\u0646\u062f\u0627\u0644\u06cc"
    ],
    "wof:name":"Gundali",
    "wof:placetype":"locality"
},
  "geometry": {"coordinates":[70.08402,34.90020999999999],"type":"Point"}
}