{
  "type": "Feature",
  "properties": {
    "gn:admin1_code":"23",
    "gn:admin2_code":"2405",
    "gn:asciiname":"Lam",
    "gn:country_code":"AF",
    "gn:dem":1457,
    "gn:feature_class":"P",
    "gn:feature_code":"PPL",
    "gn:name":"L\u0101m",
    "gn:population":0,
    "gn:timezone":"Asia/Kabul",
    "iso:country":"AF",
    "name:ceb_x_preferred":[
        "Lam"
    ],
    "name:dan_x_preferred":[
        "Lam"
    ],
    "name:fra_x_preferred":[
        "Lam"
    ],
    "name:nld_x_preferred":[
        "Lam"
    ],
    "name:nor_x_preferred":[
        "Lam"
    ],
    "name:pol_x_preferred":[
        "Lam"
    ],
    "name:por_x_preferred":[
        "Lam"
    ],
    "name:swe_x_preferred":[
        "Lam"
    ],
    "name:und_x_variant":[
        "L\u0101m",
        "\u0644\u0627\u0645"
    ],
    "name:vie_x_preferred":[
        "Lam"
    ],
    "wof:name":"Lam",
    "wof:placetype":"locality"
},
  "geometry": {"coordinates":[65.38123,32.16149],"type":"Point"}
}