{
  "type": "Feature",
  "properties": {
    "gn:admin1_code":"27",
    "gn:admin2_code":"404.0",
    "gn:asciiname":"Haqdad",
    "gn:country_code":"AF",
    "gn:dem":2965,
    "gn:feature_class":"P",
    "gn:feature_code":"PPL",
    "gn:name":"\u1e28aqd\u0101d",
    "gn:population":0,
    "gn:timezone":"Asia/Kabul",
    "iso:country":"AF",
    "name:und_x_variant":[
        "Khakdad",
        "\u1e28aqd\u0101d",
        "\u062d\u0642\u062f\u0627\u062f"
    ],
    "wof:name":"Haqdad",
    "wof:placetype":"locality"
},
  "geometry": {"coordinates":[67.74039,34.36112],"type":"Point"}
}