{
  "type": "Feature",
  "properties": {
    "gn:admin1_code":"29",
    "gn:admin2_code":"2906.0",
    "gn:asciiname":"'Alizayu Kelay",
    "gn:country_code":"AF",
    "gn:dem":2294,
    "gn:feature_class":"P",
    "gn:feature_code":"PPL",
    "gn:name":"\u2018Al\u012bzay\u016b K\u00ealay",
    "gn:population":0,
    "gn:timezone":"Asia/Kabul",
    "iso:country":"AF",
    "name:fas_x_preferred":[
        "\u2018Al\u012bzay\u016b K\u00ealay"
    ],
    "name:fas_x_variant":[
        "\u0639\u0644\u06cc\u0632\u06cc\u0648 \u06a9\u0644\u06cc"
    ],
    "name:und_x_variant":[
        "Alizayu-Kalay",
        "Alizayo Kalay",
        "\u0639\u0644\u06cc\u0632\u06cc\u0648 \u06a9\u0644\u06cc"
    ],
    "wof:name":"'Alizayu Kelay",
    "wof:placetype":"locality"
},
  "geometry": {"coordinates":[68.92075,32.77637],"type":"Point"}
}