{
  "type": "Feature",
  "properties": {
    "gn:admin1_code":"18",
    "gn:admin2_code":"820",
    "gn:asciiname":"Janshagal",
    "gn:country_code":"AF",
    "gn:dem":1521,
    "gn:feature_class":"P",
    "gn:feature_code":"PPL",
    "gn:name":"J\u0101nshagal",
    "gn:population":0,
    "gn:timezone":"Asia/Kabul",
    "iso:country":"AF",
    "name:rus_x_preferred":[
        "Dzhanshagal\u2019"
    ],
    "name:und_x_variant":[
        "J\u0101n\u0161agal",
        "J\u0101nshagal",
        "\u062c\u0627\u0646\u0634\u06af\u0644"
    ],
    "wof:name":"Janshagal",
    "wof:placetype":"locality"
},
  "geometry": {"coordinates":[70.54295,34.71198],"type":"Point"}
}