{
  "type": "Feature",
  "properties": {
    "gn:admin1_code":"18",
    "gn:admin2_code":"802.0",
    "gn:asciiname":"Chahar Bagh-e Safa",
    "gn:country_code":"AF",
    "gn:dem":614,
    "gn:feature_class":"P",
    "gn:feature_code":"PPL",
    "gn:name":"Chah\u0101r B\u0101gh-e \u015eaf\u0101",
    "gn:population":0,
    "gn:timezone":"Asia/Kabul",
    "iso:country":"AF",
    "name:fas_x_preferred":[
        "\u0686\u0647\u0627\u0631\u0628\u0627\u063a \u0635\u0641\u0627"
    ],
    "name:und_x_variant":[
        "\u010cah\u0101rb\u0101ghe \u015eaf\u0101",
        "Chakharbagi-Safa",
        "Chah\u0101r B\u0101gh-e \u015eaf\u0101",
        "\u0686\u0647\u0627\u0631 \u0628\u0627\u063a \u0635\u0641\u0627"
    ],
    "wof:name":"Chahar Bagh-e Safa",
    "wof:placetype":"locality"
},
  "geometry": {"coordinates":[70.38028,34.42824],"type":"Point"}
}