{
  "type": "Feature",
  "properties": {
    "gn:admin1_code":"13",
    "gn:admin2_code":"107.0",
    "gn:asciiname":"Safar Khel",
    "gn:country_code":"AF",
    "gn:dem":1864,
    "gn:feature_class":"P",
    "gn:feature_code":"PPL",
    "gn:name":"Safar Kh\u0113l",
    "gn:population":0,
    "gn:timezone":"Asia/Kabul",
    "iso:country":"AF",
    "name:fas_x_preferred":[
        "\u0633\u0641\u0631 \u062e\u064a\u0644"
    ],
    "name:rus_x_preferred":[
        "Safarkheyl\u2019"
    ],
    "name:und_x_variant":[
        "Safa\u1e5fkh\u0113l",
        "Safarkheyl",
        "\u0633\u0641\u0631 \u062e\u06d0\u0644",
        "Safar Kh\u0113l"
    ],
    "wof:name":"Safar Khel",
    "wof:placetype":"locality"
},
  "geometry": {"coordinates":[69.07093,34.69655],"type":"Point"}
}