{
  "type": "Feature",
  "properties": {
    "gn:admin1_code":"13",
    "gn:admin2_code":"108.0",
    "gn:asciiname":"Nadir Khel",
    "gn:country_code":"AF",
    "gn:dem":2315,
    "gn:feature_class":"P",
    "gn:feature_code":"PPL",
    "gn:name":"N\u0101dir Kh\u0113l",
    "gn:population":0,
    "gn:timezone":"Asia/Kabul",
    "iso:country":"AF",
    "name:rus_x_preferred":[
        "Nadirkheyl\u2019"
    ],
    "name:und_x_variant":[
        "N\u0101\u1e0fe\u1e5fkh\u0113l",
        "N\u0101dir Kh\u0113l",
        "N\u0101derkheyl",
        "\u0646\u0627\u062f\u0631 \u062e\u06d0\u0644"
    ],
    "wof:name":"Nadir Khel",
    "wof:placetype":"locality"
},
  "geometry": {"coordinates":[68.97549000000001,34.59647],"type":"Point"}
}