{
  "type": "Feature",
  "properties": {
    "gn:admin1_code":"40",
    "gn:admin2_code":"305.0",
    "gn:asciiname":"Balakhisar",
    "gn:country_code":"AF",
    "gn:dem":2191,
    "gn:feature_class":"P",
    "gn:feature_code":"PPL",
    "gn:name":"Balakhisar",
    "gn:population":0,
    "gn:timezone":"Asia/Kabul",
    "iso:country":"AF",
    "name:und_x_variant":[
        "B\u0101l\u0101\u1e29e\u015f\u0101r",
        "B\u0101l\u0101 \u1e28i\u015f\u0101r",
        "\u0628\u0627\u0644\u0627 \u062d\u0635\u0627\u0631"
    ],
    "wof:name":"Balakhisar",
    "wof:placetype":"locality"
},
  "geometry": {"coordinates":[68.83802,34.94848],"type":"Point"}
}