{
  "type": "Feature",
  "properties": {
    "gn:admin1_code":"8",
    "gn:admin2_code":"611.0",
    "gn:asciiname":"Sherjan Kala",
    "gn:country_code":"AF",
    "gn:dem":2024,
    "gn:feature_class":"P",
    "gn:feature_code":"PPL",
    "gn:name":"Sh\u0113rj\u0101n Kal\u0101",
    "gn:population":0,
    "gn:timezone":"Asia/Kabul",
    "iso:country":"AF",
    "name:und_x_variant":[
        "S\u0113\u1e5fj\u0101n Kal\u0101",
        "Sherdzhankala",
        "\u0634\u06cc\u0631\u062c\u0627\u0646 \u06a9\u0644\u0627",
        "Sh\u012brj\u0101n Kal\u0101",
        "Shayrj\u0101n Kal\u0101",
        "Sh\u0113rj\u0101n Kal\u0101"
    ],
    "wof:name":"Sherjan Kala",
    "wof:placetype":"locality"
},
  "geometry": {"coordinates":[68.09453000000001,32.82282],"type":"Point"}
}