{
  "type": "Feature",
  "properties": {
    "gn:admin1_code":"33",
    "gn:admin2_code":"3102.0",
    "gn:asciiname":"Dah Mardah",
    "gn:country_code":"AF",
    "gn:dem":1716,
    "gn:feature_class":"P",
    "gn:feature_code":"PPL",
    "gn:name":"Dah Mardah",
    "gn:population":0,
    "gn:timezone":"Asia/Kabul",
    "iso:country":"AF",
    "name:und_x_variant":[
        "\u1e0eahma\u1e5f\u1e0fa",
        "Dahmardeh",
        "Dah Mardah",
        "\u062f\u0647 \u0645\u0631\u062f\u0647"
    ],
    "wof:name":"Dah Mardah",
    "wof:placetype":"locality"
},
  "geometry": {"coordinates":[66.28952,35.77707],"type":"Point"}
}