{
  "type": "Feature",
  "properties": {
    "gn:admin1_code":"01",
    "gn:admin2_code":"1103",
    "gn:asciiname":"Sar-e Howz",
    "gn:country_code":"AF",
    "gn:dem":1783,
    "gn:feature_class":"P",
    "gn:feature_code":"PPL",
    "gn:name":"Sar-e \u1e28ow\u1e95",
    "gn:population":0,
    "gn:timezone":"Asia/Kabul",
    "iso:country":"AF",
    "name:und_x_variant":[
        "Sa\u1e5f-i-Haw\u1e0f\u1e95",
        "\u0633\u0631 \u062d\u0648\u0636",
        "Sar-e \u1e28ow\u1e95"
    ],
    "wof:name":"Sar-e Howz",
    "wof:placetype":"locality"
},
  "geometry": {"coordinates":[70.82021999999998,36.95298],"type":"Point"}
}