{
  "type": "Feature",
  "properties": {
    "gn:admin1_code":"8",
    "gn:admin2_code":"604.0",
    "gn:asciiname":"Jaybginah",
    "gn:country_code":"AF",
    "gn:dem":2932,
    "gn:feature_class":"P",
    "gn:feature_code":"PPL",
    "gn:name":"Jaybginah",
    "gn:population":0,
    "gn:timezone":"Asia/Kabul",
    "iso:country":"AF",
    "name:und_x_variant":[
        "J\u0113bgina",
        "J\u012bbg\u012bnah",
        "Jaybginah",
        "\u062c\u06cc\u0628\u06af\u0646\u0647"
    ],
    "wof:name":"Jaybginah",
    "wof:placetype":"locality"
},
  "geometry": {"coordinates":[67.44473000000001,33.68047],"type":"Point"}
}