{
  "type": "Feature",
  "properties": {
    "gn:admin1_code":"08",
    "gn:admin2_code":"607",
    "gn:asciiname":"Tabqos",
    "gn:country_code":"AF",
    "gn:dem":2750,
    "gn:feature_class":"P",
    "gn:feature_code":"PPL",
    "gn:name":"Tabq\u014ds",
    "gn:population":0,
    "gn:timezone":"Asia/Kabul",
    "iso:country":"AF",
    "name:und_x_variant":[
        "Tabq\u014ds",
        "\u062b\u0628\u0642\u0648\u0633",
        "Tapq\u016bs"
    ],
    "wof:name":"Tabqos",
    "wof:placetype":"locality"
},
  "geometry": {"coordinates":[67.49285,33.01766],"type":"Point"}
}