{
  "type": "Feature",
  "properties": {
    "gn:admin1_code":"03",
    "gn:admin2_code":"1302.0",
    "gn:asciiname":"Shishran",
    "gn:country_code":"AF",
    "gn:dem":2168,
    "gn:feature_class":"P",
    "gn:feature_code":"PPL",
    "gn:name":"Shishr\u0101n",
    "gn:population":0,
    "gn:timezone":"Asia/Kabul",
    "iso:country":"AF",
    "name:und_x_variant":[
        "Ses\u1e5f\u0101n",
        "Sheshr\u0101n",
        "Shishr\u0101n",
        "\u0634\u0634\u0631\u0627\u0646"
    ],
    "wof:name":"Shishran",
    "wof:placetype":"locality"
},
  "geometry": {"coordinates":[69.44308000000001,35.56935],"type":"Point"}
}