{
  "type": "Feature",
  "properties": {
    "gn:admin1_code":"32",
    "gn:admin2_code":"1506",
    "gn:asciiname":"Rabatak",
    "gn:country_code":"AF",
    "gn:dem":978,
    "gn:feature_class":"P",
    "gn:feature_code":"PPL",
    "gn:name":"Rab\u0101\u0163ak",
    "gn:population":0,
    "gn:timezone":"Asia/Kabul",
    "iso:country":"AF",
    "name:fas_x_preferred":[
        "\u0631\u0628\u0627\u0637\u06a9"
    ],
    "name:rus_x_preferred":[
        "\u0420\u0430\u0431\u0430\u0442\u0430\u043a"
    ],
    "name:und_x_variant":[
        "Rib\u0101t",
        "\u1e5eab\u0101\u1e6fak",
        "Rabatak",
        "Rob\u0101t",
        "Rob\u0101\u0163ak",
        "Rab\u0101\u0163ak"
    ],
    "wof:name":"Rabatak",
    "wof:placetype":"locality"
},
  "geometry": {"coordinates":[68.40349000000001,36.14938],"type":"Point"}
}