{
  "type": "Feature",
  "properties": {
    "gn:admin1_code":"18",
    "gn:admin2_code":"803",
    "gn:asciiname":"Shan Shobay",
    "gn:country_code":"AF",
    "gn:dem":2055,
    "gn:feature_class":"P",
    "gn:feature_code":"PPL",
    "gn:name":"Shan Sh\u014dbay",
    "gn:population":0,
    "gn:timezone":"Asia/Kabul",
    "iso:country":"AF",
    "name:fas_x_preferred":[
        "\u0634\u0646\u0634\u0648\u0628\u06cc"
    ],
    "name:und_x_variant":[
        "\u0160an\u0161obay",
        "Shanshobay",
        "Shan Sh\u014dbay",
        "Shansh\u014dba\u012b",
        "Shansh\u016bbay",
        "\u0634\u0646 \u0634\u0648\u0628\u06cc"
    ],
    "wof:name":"Shan Shobay",
    "wof:placetype":"locality"
},
  "geometry": {"coordinates":[69.89991999999999,34.22214],"type":"Point"}
}