{
  "type": "Feature",
  "properties": {
    "gn:admin1_code":"09",
    "gn:admin2_code":"2705",
    "gn:asciiname":"Sar-e Bayshah",
    "gn:country_code":"AF",
    "gn:dem":2135,
    "gn:feature_class":"P",
    "gn:feature_code":"PPL",
    "gn:name":"Sar-e Bayshah",
    "gn:population":0,
    "gn:timezone":"Asia/Kabul",
    "iso:country":"AF",
    "name:und_x_variant":[
        "Sare B\u0113\u0161a",
        "Sari-Besha",
        "Sar-e Bayshah",
        "\u0633\u0631 \u0628\u06cc\u0634\u0647",
        "Sar-e B\u012bsheh"
    ],
    "wof:name":"Sar-e Bayshah",
    "wof:placetype":"locality"
},
  "geometry": {"coordinates":[64.0454,33.58942],"type":"Point"}
}