{
  "type": "Feature",
  "properties": {
    "gn:admin1_code":"9",
    "gn:admin2_code":"2707.0",
    "gn:asciiname":"Qal'ahchah-ye Ghar",
    "gn:country_code":"AF",
    "gn:dem":2971,
    "gn:feature_class":"P",
    "gn:feature_code":"PPL",
    "gn:name":"Qal\u2018ahchah-ye Gh\u0101r",
    "gn:population":0,
    "gn:timezone":"Asia/Kabul",
    "iso:country":"AF",
    "name:und_x_variant":[
        "Qal\u2019a\u010da-i-Gh\u0101r",
        "Kalachayi-Gar",
        "Qal\u2018ahchah-ye Gh\u0101r",
        "Qal\u2018ehcheh-ye Gh\u0101r",
        "Qal\u2018ah Chah-ye Gh\u0101r",
        "\u0642\u0644\u0639\u0647 \u0686\u06c0 \u063a\u0627\u0631",
        "Qal\u2018ah-ye Chah Gh\u0101r",
        "\u0642\u0644\u0639\u06c0 \u0686\u0647 \u063a\u0627\u0631",
        "\u0642\u0644\u0639\u0647\u0686\u0647 \u063a\u0627\u0631"
    ],
    "wof:name":"Qal'ahchah-ye Ghar",
    "wof:placetype":"locality"
},
  "geometry": {"coordinates":[66.12671999999999,34.49014],"type":"Point"}
}