{
  "type": "Feature",
  "properties": {
    "gn:admin1_code":"09",
    "gn:admin2_code":"2705",
    "gn:asciiname":"Panj Charagh",
    "gn:country_code":"AF",
    "gn:dem":2394,
    "gn:feature_class":"P",
    "gn:feature_code":"PPL",
    "gn:name":"Panj Char\u0101gh",
    "gn:population":0,
    "gn:timezone":"Asia/Kabul",
    "iso:country":"AF",
    "name:und_x_variant":[
        "Panj\u010dar\u0101gh",
        "Panj\u0113a\u1e5f\u0101gh",
        "Pandzhcharag",
        "Panj Char\u0101gh",
        "\u067e\u0646\u062c \u0686\u0631\u0627\u063a",
        "Panjcher\u0101gh"
    ],
    "wof:name":"Panj Charagh",
    "wof:placetype":"locality"
},
  "geometry": {"coordinates":[64.35698000000001,33.36968],"type":"Point"}
}