{
  "type": "Feature",
  "properties": {
    "gn:admin1_code":"08",
    "gn:admin2_code":"607",
    "gn:asciiname":"Qunag-e Sufla",
    "gn:country_code":"AF",
    "gn:dem":2493,
    "gn:feature_class":"P",
    "gn:feature_code":"PPL",
    "gn:name":"Q\u016bn\u0101g-e Sufl\u00e1",
    "gn:population":0,
    "gn:timezone":"Asia/Kabul",
    "iso:country":"AF",
    "name:und_x_variant":[
        "Kunagi-Sufla",
        "Q\u016bn\u0101ge Sufl\u0101",
        "Q\u016bn\u0101g-e Sufl\u00e1",
        "\u0642\u0648\u0646\u0627\u06af \u0633\u0641\u0644\u0649",
        "Q\u016bn\u0101g-e Sofl\u0101"
    ],
    "wof:name":"Qunag-e Sufla",
    "wof:placetype":"locality"
},
  "geometry": {"coordinates":[67.39631,32.98567],"type":"Point"}
}