{
  "type": "Feature",
  "properties": {
    "gn:admin1_code":"34",
    "gn:admin2_code":"1015",
    "gn:asciiname":"Dunay",
    "gn:country_code":"AF",
    "gn:dem":786,
    "gn:feature_class":"P",
    "gn:feature_code":"PPL",
    "gn:name":"Dunay",
    "gn:population":0,
    "gn:timezone":"Asia/Kabul",
    "iso:country":"AF",
    "name:ceb_x_preferred":[
        "Dunay"
    ],
    "name:fas_x_preferred":[
        "\u062f\u0648\u0646\u0626\u06cc"
    ],
    "name:swe_x_preferred":[
        "Dunay"
    ],
    "name:und_x_variant":[
        "D\u014dna\u2019\u012b",
        "\u1e0e\u014dna\u2019\u012b"
    ],
    "wof:name":"Dunay",
    "wof:placetype":"locality"
},
  "geometry": {"coordinates":[71.09399999999999,34.76133],"type":"Point"}
}