{
  "type": "Feature",
  "properties": {
    "gn:admin1_code":"38",
    "gn:admin2_code":"3004",
    "gn:asciiname":"Kowrbiz",
    "gn:country_code":"AF",
    "gn:dem":1752,
    "gn:feature_class":"P",
    "gn:feature_code":"PPL",
    "gn:name":"Kowrbiz",
    "gn:population":0,
    "gn:timezone":"Asia/Kabul",
    "iso:country":"AF",
    "name:und_x_variant":[
        "Kaurbiz",
        "K\u014drbayz",
        "Kawrbez",
        "Kowrbiz",
        "\u06a9\u0648\u0631\u0628\u0632"
    ],
    "wof:name":"Kowrbiz",
    "wof:placetype":"locality"
},
  "geometry": {"coordinates":[70.17440000000001,35.20882],"type":"Point"}
}