{
  "type": "Feature",
  "properties": {
    "gn:admin1_code":"31",
    "gn:admin2_code":"1704",
    "gn:asciiname":"Harun-e Duwum",
    "gn:country_code":"AF",
    "gn:dem":280,
    "gn:feature_class":"P",
    "gn:feature_code":"PPL",
    "gn:name":"H\u0101r\u016bn-e Duwum",
    "gn:population":0,
    "gn:timezone":"Asia/Kabul",
    "iso:country":"AF",
    "name:und_x_variant":[
        "H\u0101r\u016bn-i-Dowom",
        "H\u0101r\u016bn-e Dovvom",
        "H\u0101r\u016bn-e Duwum",
        "\u0647\u0627\u0631\u0648\u0646 \u062f\u0648\u0645"
    ],
    "wof:name":"Harun-e Duwum",
    "wof:placetype":"locality"
},
  "geometry": {"coordinates":[66.09486,37.01108],"type":"Point"}
}