{
  "type": "Feature",
  "properties": {
    "gn:admin1_code":"40",
    "gn:admin2_code":"305",
    "gn:asciiname":"Taykhan",
    "gn:country_code":"AF",
    "gn:dem":2331,
    "gn:feature_class":"P",
    "gn:feature_code":"PPL",
    "gn:name":"Taykh\u0101n",
    "gn:population":0,
    "gn:timezone":"Asia/Kabul",
    "iso:country":"AF",
    "name:und_x_variant":[
        "Taykh\u0101n",
        "\u062a\u06cc\u062e\u0627\u0646"
    ],
    "wof:name":"Taykhan",
    "wof:placetype":"locality"
},
  "geometry": {"coordinates":[68.78963,34.91794],"type":"Point"}
}