{
  "type": "Feature",
  "properties": {
    "gn:admin1_code":"36",
    "gn:admin2_code":"710",
    "gn:asciiname":"Wuleswali Sayyid Karam",
    "gn:country_code":"AF",
    "gn:dem":2458,
    "gn:feature_class":"P",
    "gn:feature_code":"PPLA2",
    "gn:name":"Wul\u00easw\u0101l\u012b Sayyid Karam",
    "gn:population":0,
    "gn:timezone":"Asia/Kabul",
    "iso:country":"AF",
    "name:fas_x_preferred":[
        "\u0648\u0644\u0648\u0633\u0648\u0644\u06cc \u0633\u064a\u062f \u0643\u0631\u0645"
    ],
    "name:und_x_variant":[
        "Sayed Karam",
        "Seyyed Karam",
        "Say\u1e0f Ka\u1e5fam",
        "Wolusw\u0101li Say\u1e0fka\u1e5fam",
        "Vulusvali Saidkaram",
        "Wolusw\u0101l\u012b Seyyed Karam",
        "Wul\u00easw\u0101l\u012b Sayyid Karam",
        "\u0648\u0644\u0633\u0648\u0627\u0644\u06cc \u0633\u06cc\u062f \u06a9\u0631\u0645"
    ],
    "wof:name":"Wuleswali Sayyid Karam",
    "wof:placetype":"locality"
},
  "geometry": {"coordinates":[69.36881,33.69056],"type":"Point"}
}