{
  "type": "Feature",
  "properties": {
    "gn:admin1_code":"18",
    "gn:admin2_code":"807.0",
    "gn:asciiname":"Godrah",
    "gn:country_code":"AF",
    "gn:dem":2176,
    "gn:feature_class":"P",
    "gn:feature_code":"PPL",
    "gn:name":"G\u014ddrah",
    "gn:population":0,
    "gn:timezone":"Asia/Kabul",
    "iso:country":"AF",
    "wof:name":"Godrah",
    "wof:placetype":"locality"
},
  "geometry": {"coordinates":[70.21845999999999,34.06317],"type":"Point"}
}