{
  "type": "Feature",
  "properties": {
    "gn:admin1_code":"02",
    "gn:admin2_code":"1906",
    "gn:asciiname":"Khwajah Pistah",
    "gn:country_code":"AF",
    "gn:dem":1090,
    "gn:feature_class":"P",
    "gn:feature_code":"PPL",
    "gn:name":"Khw\u0101jah Pistah",
    "gn:population":0,
    "gn:timezone":"Asia/Kabul",
    "iso:country":"AF",
    "name:und_x_variant":[
        "Khw\u0101ja Pista",
        "Khw\u0101jah Pistah",
        "\u062e\u0648\u0627\u062c\u0647 \u067e\u0633\u062a\u0647",
        "Khv\u0101jeh Pistah"
    ],
    "wof:name":"Khwajah Pistah",
    "wof:placetype":"locality"
},
  "geometry": {"coordinates":[63.60064000000001,35.49569],"type":"Point"}
}