{
  "type": "Feature",
  "properties": {
    "gn:admin1_code":"01",
    "gn:admin2_code":"1112.0",
    "gn:asciiname":"Kandayl",
    "gn:country_code":"AF",
    "gn:dem":2047,
    "gn:feature_class":"P",
    "gn:feature_code":"PPL",
    "gn:name":"Kandayl",
    "gn:population":0,
    "gn:timezone":"Asia/Kabul",
    "iso:country":"AF",
    "name:und_x_variant":[
        "\u06a9\u0646\u062f\u06cc\u0644",
        "Kan\u1e0f\u0113l"
    ],
    "wof:name":"Kandayl",
    "wof:placetype":"locality"
},
  "geometry": {"coordinates":[70.39752,37.6053],"type":"Point"}
}