{
  "type": "Feature",
  "properties": {
    "gn:admin1_code":"8",
    "gn:admin2_code":"604.0",
    "gn:asciiname":"Sang-e Laku",
    "gn:country_code":"AF",
    "gn:dem":2774,
    "gn:feature_class":"P",
    "gn:feature_code":"PPL",
    "gn:name":"Sang-e L\u0101k\u016b",
    "gn:population":0,
    "gn:timezone":"Asia/Kabul",
    "iso:country":"AF",
    "name:und_x_variant":[
        "Sangi-Laku",
        "Sang-e L\u0101ku",
        "Sang-e L\u0101k\u014d",
        "Sang-e L\u0101k\u016b",
        "\u0633\u0646\u06af \u0644\u0627\u06a9\u0648"
    ],
    "wof:name":"Sang-e Laku",
    "wof:placetype":"locality"
},
  "geometry": {"coordinates":[68.02552,34.08423],"type":"Point"}
}