{
  "type": "Feature",
  "properties": {
    "gn:admin1_code":"30",
    "gn:admin2_code":"1603",
    "gn:asciiname":"Towkhurdah",
    "gn:country_code":"AF",
    "gn:dem":1903,
    "gn:feature_class":"P",
    "gn:feature_code":"PPL",
    "gn:name":"Towkhurdah",
    "gn:population":0,
    "gn:timezone":"Asia/Kabul",
    "iso:country":"AF",
    "name:und_x_variant":[
        "Tawkhu\u1e5f\u1e0fa",
        "Tawkhu\u1e5f\u1e0fah",
        "Towkhurdah",
        "\u062a\u0648\u062e\u0631\u062f\u0647"
    ],
    "wof:name":"Towkhurdah",
    "wof:placetype":"locality"
},
  "geometry": {"coordinates":[66.75537,35.8781],"type":"Point"}
}