{
  "type": "Feature",
  "properties": {
    "gn:admin1_code":"28",
    "gn:admin2_code":"2501",
    "gn:asciiname":"Landay Karez",
    "gn:country_code":"AF",
    "gn:dem":1678,
    "gn:feature_class":"P",
    "gn:feature_code":"PPL",
    "gn:name":"Lan\u1e0fay K\u0101r\u0113z",
    "gn:population":0,
    "gn:timezone":"Asia/Kabul",
    "iso:country":"AF",
    "name:fas_x_preferred":[
        "\u0643\u0627\u0631\u064a\u0632\u0654 \u0644\u0646\u062f\u06cc"
    ],
    "name:und_x_variant":[
        "Landay K\u0101\u1e5f\u0113z",
        "Lan\u1e0fay K\u0101r\u0113z",
        "\u0644\u0646\u0689\u06cc \u06a9\u0627\u0631\u06cc\u0632",
        "Lan\u1e0fay K\u0101r\u012bz"
    ],
    "wof:name":"Landay Karez",
    "wof:placetype":"locality"
},
  "geometry": {"coordinates":[67.11085,32.21855],"type":"Point"}
}