{
  "type": "Feature",
  "properties": {
    "gn:admin1_code":"01",
    "gn:admin2_code":"1120.0",
    "gn:asciiname":"Nashir",
    "gn:country_code":"AF",
    "gn:dem":1948,
    "gn:feature_class":"P",
    "gn:feature_code":"PPL",
    "gn:name":"Nashir",
    "gn:population":0,
    "gn:timezone":"Asia/Kabul",
    "iso:country":"AF",
    "name:und_x_variant":[
        "Nase\u1e5f",
        "N\u0101\u015fer",
        "Nashir",
        "\u0646\u0634\u0631"
    ],
    "wof:name":"Nashir",
    "wof:placetype":"locality"
},
  "geometry": {"coordinates":[70.49486999999998,37.99833],"type":"Point"}
}