{
  "type": "Feature",
  "properties": {
    "gn:admin1_code":"01",
    "gn:admin2_code":"1115.0",
    "gn:asciiname":"Chatraq",
    "gn:country_code":"AF",
    "gn:dem":1656,
    "gn:feature_class":"P",
    "gn:feature_code":"PPL",
    "gn:name":"Chatr\u0101q",
    "gn:population":0,
    "gn:timezone":"Asia/Kabul",
    "iso:country":"AF",
    "name:und_x_variant":[
        "Cat\u1e5f\u0101q",
        "\u0686\u062a\u0631\u0627\u0642",
        "Chat\u1e5f\u0101q",
        "Chatr\u0101q"
    ],
    "wof:name":"Chatraq",
    "wof:placetype":"locality"
},
  "geometry": {"coordinates":[70.57358000000001,37.05065],"type":"Point"}
}