{
  "type": "Feature",
  "properties": {
    "gn:admin1_code":"8",
    "gn:admin2_code":"602.0",
    "gn:asciiname":"Qal'ah-ye Now-e Ahangaran",
    "gn:country_code":"AF",
    "gn:dem":2641,
    "gn:feature_class":"P",
    "gn:feature_code":"PPL",
    "gn:name":"Qal\u2018ah-ye Now-e \u0100hangar\u0101n",
    "gn:population":0,
    "gn:timezone":"Asia/Kabul",
    "iso:country":"AF",
    "name:fas_x_preferred":[
        "\u0642\u0644\u0639\u0647\u0654 \u0646\u0648\u06cc \u0622\u0647\u0646\u06af\u0631\u0627\u0646"
    ],
    "name:und_x_variant":[
        "Kala-Navi-Akhangaran",
        "Qal\u2018eh-ye Now-e \u0100hangar\u0101n",
        "Qal\u2018a-i-Nawe \u0100hanga\u1e5f\u0101n",
        "Qal\u2018a Nawe \u0100hanga\u1e5f\u0101n",
        "Qal\u2018eh Now-ye \u0100hangar\u0101n",
        "Qal\u2018ah-ye Now-e \u0100hangar\u0101n",
        "\u0642\u0644\u0639\u06c0 \u0646\u0648 \u0622\u0647\u0646\u06af\u0631\u0627\u0646"
    ],
    "wof:name":"Qal'ah-ye Now-e Ahangaran",
    "wof:placetype":"locality"
},
  "geometry": {"coordinates":[68.23363000000001,33.60852],"type":"Point"}
}