{
  "type": "Feature",
  "properties": {
    "gn:admin1_code":"05",
    "gn:admin2_code":"2801",
    "gn:asciiname":"Qarghanatu",
    "gn:country_code":"AF",
    "gn:dem":3328,
    "gn:feature_class":"P",
    "gn:feature_code":"PPL",
    "gn:name":"Qarghanatu",
    "gn:population":0,
    "gn:timezone":"Asia/Kabul",
    "iso:country":"AF",
    "name:fas_x_preferred":[
        "\u0642\u0631\u063a\u0646\u0647\u062a\u0648"
    ],
    "name:und_x_variant":[
        "Karghanatu",
        "Qa\u1e5fghanatu",
        "Qarghaneh T\u016b",
        "Qarghanatu",
        "Qarghanaht\u016b",
        "\u0642\u0631\u063a\u0646\u0647\u062a\u0648",
        "Qarghaneht\u016b"
    ],
    "wof:name":"Qarghanatu",
    "wof:placetype":"locality"
},
  "geometry": {"coordinates":[67.38333,34.78333],"type":"Point"}
}