{
  "type": "Feature",
  "properties": {
    "gn:admin1_code":"13",
    "gn:admin2_code":"113.0",
    "gn:asciiname":"Deh-e Baghal-e Koh",
    "gn:country_code":"AF",
    "gn:dem":2098,
    "gn:feature_class":"P",
    "gn:feature_code":"PPL",
    "gn:name":"Deh-e Baghal-e K\u014dh",
    "gn:population":0,
    "gn:timezone":"Asia/Kabul",
    "iso:country":"AF",
    "name:fas_x_preferred":[
        "\u062f\u0647\u0654 \u0628\u063a\u0644\u0654 \u0643\u0648\u0647"
    ],
    "name:und_x_variant":[
        "Dekhi-Bagali-Kokh",
        "\u1e0eehe Baghale Koh",
        "Deh-e Baghale K\u016bh",
        "\u062f\u0647 \u0628\u063a\u0644 \u06a9\u0648\u0647",
        "Deh-e Baghal-e K\u014dh"
    ],
    "wof:name":"Deh-e Baghal-e Koh",
    "wof:placetype":"locality"
},
  "geometry": {"coordinates":[69.02294999999999,34.7512],"type":"Point"}
}