{
  "type": "Feature",
  "properties": {
    "gn:admin1_code":"8",
    "gn:admin2_code":"614.0",
    "gn:asciiname":"Mazdur Kala",
    "gn:country_code":"AF",
    "gn:dem":2093,
    "gn:feature_class":"P",
    "gn:feature_code":"PPL",
    "gn:name":"Mazd\u016br Kal\u0101",
    "gn:population":0,
    "gn:timezone":"Asia/Kabul",
    "iso:country":"AF",
    "name:und_x_variant":[
        "Maz\u1e0f\u016b\u1e5f Kal\u0101",
        "Mazdur",
        "Mozd\u016br Kal\u0101",
        "Mazd\u016br Kal\u0101",
        "\u0645\u0632\u062f\u0648\u0631 \u06a9\u0644\u0627"
    ],
    "wof:name":"Mazdur Kala",
    "wof:placetype":"locality"
},
  "geometry": {"coordinates":[68.60741999999999,33.31889],"type":"Point"}
}