{
  "type": "Feature",
  "properties": {
    "gn:admin1_code":"09",
    "gn:admin2_code":"2706.0",
    "gn:asciiname":"Qal-e Ramah",
    "gn:country_code":"AF",
    "gn:dem":2804,
    "gn:feature_class":"P",
    "gn:feature_code":"PPL",
    "gn:name":"Q\u0101l-e Ramah",
    "gn:population":0,
    "gn:timezone":"Asia/Kabul",
    "iso:country":"AF",
    "name:und_x_variant":[
        "Q\u0101l-e Ramah",
        "\u0642\u0627\u0644 \u0631\u0645\u0647"
    ],
    "wof:name":"Qal-e Ramah",
    "wof:placetype":"locality"
},
  "geometry": {"coordinates":[65.11323,33.83545],"type":"Point"}
}