{
  "type": "Feature",
  "properties": {
    "gn:admin1_code":"09",
    "gn:admin2_code":"2710",
    "gn:asciiname":"Gor Zarak",
    "gn:country_code":"AF",
    "gn:dem":2842,
    "gn:feature_class":"P",
    "gn:feature_code":"PPL",
    "gn:name":"G\u014dr Z\u0101rak",
    "gn:population":0,
    "gn:timezone":"Asia/Kabul",
    "iso:country":"AF",
    "name:und_x_variant":[
        "G\u014d\u1e5fz\u0101\u1e5fak",
        "G\u014dr Z\u0101rak",
        "\u06af\u0648\u0631 \u0632\u0627\u0631\u06a9",
        "G\u016brz\u0101rak"
    ],
    "wof:name":"Gor Zarak",
    "wof:placetype":"locality"
},
  "geometry": {"coordinates":[65.11511999999999,34.27845],"type":"Point"}
}