{
  "type": "Feature",
  "properties": {
    "gn:admin1_code":"5",
    "gn:admin2_code":"2806.0",
    "gn:asciiname":"Barjoy",
    "gn:country_code":"AF",
    "gn:dem":2741,
    "gn:feature_class":"P",
    "gn:feature_code":"PPL",
    "gn:name":"Barj\u014dy",
    "gn:population":0,
    "gn:timezone":"Asia/Kabul",
    "iso:country":"AF",
    "name:und_x_variant":[
        "Bardzhoy",
        "Ba\u1e5fj\u014dy",
        "Barj\u014dy",
        "\u0628\u062f\u062c\u0648\u06cc"
    ],
    "wof:name":"Barjoy",
    "wof:placetype":"locality"
},
  "geometry": {"coordinates":[66.73905999999999,34.07217],"type":"Point"}
}