{
  "type": "Feature",
  "properties": {
    "gn:admin1_code":"11",
    "gn:admin2_code":"2001.0",
    "gn:asciiname":"Puran-e Khasah",
    "gn:country_code":"AF",
    "gn:dem":916,
    "gn:feature_class":"P",
    "gn:feature_code":"PPL",
    "gn:name":"P\u016br\u0101n-e Kha\u015fah",
    "gn:population":0,
    "gn:timezone":"Asia/Kabul",
    "iso:country":"AF",
    "name:fas_x_preferred":[
        "\u067e\u0648\u0631\u0627\u0646\u0654 \u062e\u0627\u0635\u0647"
    ],
    "name:und_x_variant":[
        "Purani-Khasa",
        "P\u016b\u1e5f\u0101n-i-Kh\u0101\u015fa",
        "P\u016br\u0101n-e Kha\u015fah",
        "\u067e\u0648\u0631\u0627\u0646 \u062e\u0635\u0647"
    ],
    "wof:name":"Puran-e Khasah",
    "wof:placetype":"locality"
},
  "geometry": {"coordinates":[62.13778000000001,34.32858],"type":"Point"}
}