{
  "type": "Feature",
  "properties": {
    "gn:admin1_code":"02",
    "gn:admin2_code":"1904",
    "gn:asciiname":"Kazak",
    "gn:country_code":"AF",
    "gn:dem":2016,
    "gn:feature_class":"P",
    "gn:feature_code":"PPL",
    "gn:name":"K\u0101zak",
    "gn:population":0,
    "gn:timezone":"Asia/Kabul",
    "iso:country":"AF",
    "name:und_x_variant":[
        "K\u0101zak",
        "\u06a9\u0627\u0632\u06a9"
    ],
    "wof:name":"Kazak",
    "wof:placetype":"locality"
},
  "geometry": {"coordinates":[64.40729,35.04781],"type":"Point"}
}