{
  "type": "Feature",
  "properties": {
    "gn:admin1_code":"5",
    "gn:admin2_code":"2806.0",
    "gn:asciiname":"Sar-e Warghah",
    "gn:country_code":"AF",
    "gn:dem":2842,
    "gn:feature_class":"P",
    "gn:feature_code":"PPL",
    "gn:name":"Sar-e Warghah",
    "gn:population":0,
    "gn:timezone":"Asia/Kabul",
    "iso:country":"AF",
    "name:und_x_variant":[
        "Sa\u1e5fe Wa\u1e5fgha",
        "Sa\u1e5fe Wa\u1e5fghah",
        "Sar-e Warghah",
        "\u0633\u0631 \u0648\u0631\u063a\u0647"
    ],
    "wof:name":"Sar-e Warghah",
    "wof:placetype":"locality"
},
  "geometry": {"coordinates":[67.0685,33.99679],"type":"Point"}
}