{
  "type": "Feature",
  "properties": {
    "gn:admin1_code":"29",
    "gn:admin2_code":"2916.0",
    "gn:asciiname":"Shawal Karez",
    "gn:country_code":"AF",
    "gn:dem":2114,
    "gn:feature_class":"P",
    "gn:feature_code":"PPL",
    "gn:name":"Sh\u0101w\u0101l K\u0101r\u0113z",
    "gn:population":0,
    "gn:timezone":"Asia/Kabul",
    "iso:country":"AF",
    "name:rus_x_preferred":[
        "Shaval\u2019karez"
    ],
    "name:und_x_variant":[
        "S\u0101w\u0101l K\u0101\u1e5f\u0113z",
        "\u0634\u0627\u0648\u0627\u0644 \u06a9\u0627\u0631\u06d0\u0632",
        "Sh\u0101w\u0101l K\u0101r\u012bz",
        "Sh\u0101w\u0101l K\u0101r\u0113z"
    ],
    "wof:name":"Shawal Karez",
    "wof:placetype":"locality"
},
  "geometry": {"coordinates":[68.48862,32.64298],"type":"Point"}
}