{
  "type": "Feature",
  "properties": {
    "gn:admin1_code":"34",
    "gn:admin2_code":"1015.0",
    "gn:asciiname":"Sangar",
    "gn:country_code":"AF",
    "gn:dem":778,
    "gn:feature_class":"P",
    "gn:feature_code":"PPL",
    "gn:name":"Sangar",
    "gn:population":0,
    "gn:timezone":"Asia/Kabul",
    "iso:country":"AF",
    "name:fas_x_preferred":[
        "\u0633\u0646\u06af\u0631"
    ],
    "wof:name":"Sangar",
    "wof:placetype":"locality"
},
  "geometry": {"coordinates":[71.10018000000002,34.77268],"type":"Point"}
}