{
  "type": "Feature",
  "properties": {
    "gn:admin1_code":"41",
    "gn:admin2_code":"3404",
    "gn:asciiname":"Tangi",
    "gn:country_code":"AF",
    "gn:dem":1224,
    "gn:feature_class":"P",
    "gn:feature_code":"PPL",
    "gn:name":"Tang\u012b",
    "gn:population":0,
    "gn:timezone":"Asia/Kabul",
    "iso:country":"AF",
    "name:bre_x_preferred":[
        "Tangi"
    ],
    "name:ceb_x_preferred":[
        "Tangi"
    ],
    "name:fra_x_preferred":[
        "Tangi"
    ],
    "name:ita_x_preferred":[
        "Tangi"
    ],
    "name:swe_x_preferred":[
        "Tangi"
    ],
    "name:tgl_x_preferred":[
        "Tangi"
    ],
    "name:und_x_variant":[
        "Tang\u012b",
        "\u062a\u0646\u06af\u06cc",
        "Tangi"
    ],
    "wof:name":"Tangi",
    "wof:placetype":"locality"
},
  "geometry": {"coordinates":[65.60517,33.18033],"type":"Point"}
}