{
  "type": "Feature",
  "properties": {
    "gn:admin1_code":"27",
    "gn:admin2_code":"404.0",
    "gn:asciiname":"Gardan-e Qadah",
    "gn:country_code":"AF",
    "gn:dem":2805,
    "gn:feature_class":"P",
    "gn:feature_code":"PPL",
    "gn:name":"Gardan-e Q\u0101dah",
    "gn:population":0,
    "gn:timezone":"Asia/Kabul",
    "iso:country":"AF",
    "name:und_x_variant":[
        "Gardani-Koda",
        "Ga\u1e5f\u1e0fane Q\u0101\u1e0fa",
        "Gardan-e Q\u0101dah",
        "Gardan-e Q\u0101deh",
        "\u06af\u0631\u062f\u0646 \u0642\u0627\u062f\u0647"
    ],
    "wof:name":"Gardan-e Qadah",
    "wof:placetype":"locality"
},
  "geometry": {"coordinates":[67.67919999999999,34.49719],"type":"Point"}
}