{
  "type": "Feature",
  "properties": {
    "gn:admin1_code":"33",
    "gn:admin2_code":"3104",
    "gn:asciiname":"El Turkak",
    "gn:country_code":"AF",
    "gn:dem":1896,
    "gn:feature_class":"P",
    "gn:feature_code":"PPL",
    "gn:name":"\u0112l Turkak",
    "gn:population":0,
    "gn:timezone":"Asia/Kabul",
    "iso:country":"AF",
    "name:und_x_variant":[
        "\u0112l Turkak",
        "\u0627\u06cc\u0644 \u062a\u0631\u06a9\u06a9",
        "Eltu\u1e5fkak"
    ],
    "wof:name":"El Turkak",
    "wof:placetype":"locality"
},
  "geometry": {"coordinates":[66.49389000000001,35.50581],"type":"Point"}
}