{
  "type": "Feature",
  "properties": {
    "gn:admin1_code":"17",
    "gn:admin2_code":"506",
    "gn:asciiname":"Spando Kats",
    "gn:country_code":"AF",
    "gn:dem":2091,
    "gn:feature_class":"P",
    "gn:feature_code":"PPL",
    "gn:name":"Sp\u0101nd\u014d Kats",
    "gn:population":0,
    "gn:timezone":"Asia/Kabul",
    "iso:country":"AF",
    "name:fas_x_preferred":[
        "\u062f\u0634\u062a\u0654\u0654 \u0633\u064a\u0644\u0627\u0628\u06cc \u0633\u067e\u0627\u0646\u062f"
    ],
    "name:und_x_variant":[
        "Espand-e Kach R\u016byeh",
        "Spandukach",
        "Aspando Kats",
        "Sp\u0101ndow Kats",
        "Sp\u0101n\u1e0fo Kac",
        "Sp\u0101nd\u014d Kats",
        "Sp\u0101ndo Kats",
        "\u0633\u067e\u0627\u0646\u062f\u0648 \u06a9\u0685"
    ],
    "wof:name":"Spando Kats",
    "wof:placetype":"locality"
},
  "geometry": {"coordinates":[69.7244,34.23061],"type":"Point"}
}