{
  "type": "Feature",
  "properties": {
    "gn:admin1_code":"30",
    "gn:admin2_code":"1605",
    "gn:asciiname":"Khayrabad",
    "gn:country_code":"AF",
    "gn:dem":313,
    "gn:feature_class":"P",
    "gn:feature_code":"PPL",
    "gn:name":"Khayrabad",
    "gn:population":0,
    "gn:timezone":"Asia/Kabul",
    "iso:country":"AF",
    "name:fas_x_preferred":[
        "\u062e\u06cc\u0631\u0622\u0628\u0627\u062f"
    ],
    "name:por_x_preferred":[
        "Kheyrabad"
    ],
    "name:rus_x_preferred":[
        "\u0425\u0430\u0439\u0440\u0430\u0431\u0430\u0434"
    ],
    "name:und_x_variant":[
        "Khay\u1e5f\u0101b\u0101\u1e0f",
        "Khair\u0101b\u0101d",
        "Kheyr\u0101b\u0101d",
        "Kha\u012br\u0101b\u0101d",
        "\u062e\u064a\u0631\u0622\u0628\u0627\u062f"
    ],
    "wof:name":"Khayrabad",
    "wof:placetype":"locality"
},
  "geometry": {"coordinates":[67.05667,36.96667],"type":"Point"}
}