{
  "type": "Feature",
  "properties": {
    "gn:admin1_code":"40",
    "gn:admin2_code":"308.0",
    "gn:asciiname":"Qarah Baghi Rabat",
    "gn:country_code":"AF",
    "gn:dem":1535,
    "gn:feature_class":"P",
    "gn:feature_code":"PPL",
    "gn:name":"Qarah B\u0101gh\u012b Rab\u0101\u0163",
    "gn:population":0,
    "gn:timezone":"Asia/Kabul",
    "iso:country":"AF",
    "name:fas_x_preferred":[
        "\u0642\u0631\u0647\u0628\u0627\u063a \u0631\u0628\u0627\u0637"
    ],
    "name:und_x_variant":[
        "Karabagi-Rabat",
        "Qarehb\u0101gh\u012b",
        "Qa\u1e5fab\u0101gh\u012b \u1e5eab\u0101\u1e6f",
        "Qarahb\u0101gh\u012b Rob\u0101\u0163",
        "Qarehb\u0101gh\u012b Rob\u0101\u0163",
        "\u0642\u0631\u0647\u0628\u0627\u063a \u0631\u0628\u0627\u0637",
        "Qarah B\u0101gh\u012b Rab\u0101\u0163",
        "\u0642\u0631\u0647 \u0628\u0627\u063a\u06cc \u0631\u0628\u0627\u0637"
    ],
    "wof:name":"Qarah Baghi Rabat",
    "wof:placetype":"locality"
},
  "geometry": {"coordinates":[69.1754,34.91375],"type":"Point"}
}