{
  "type": "Feature",
  "properties": {
    "gn:admin1_code":"05",
    "gn:admin2_code":"2805",
    "gn:asciiname":"Surkh Sang",
    "gn:country_code":"AF",
    "gn:dem":3102,
    "gn:feature_class":"P",
    "gn:feature_code":"PPL",
    "gn:name":"Surkh Sang",
    "gn:population":0,
    "gn:timezone":"Asia/Kabul",
    "iso:country":"AF",
    "name:und_x_variant":[
        "Su\u1e5fkhsang",
        "Surkhsang",
        "Surkh Sang",
        "Sorkhsang",
        "\u0633\u0631\u062e \u0633\u0646\u06af"
    ],
    "wof:name":"Surkh Sang",
    "wof:placetype":"locality"
},
  "geometry": {"coordinates":[67.21165000000001,34.488],"type":"Point"}
}