{
  "type": "Feature",
  "properties": {
    "gn:admin1_code":"01",
    "gn:admin2_code":"1112.0",
    "gn:asciiname":"Chidek Dur",
    "gn:country_code":"AF",
    "gn:dem":2676,
    "gn:feature_class":"P",
    "gn:feature_code":"PPL",
    "gn:name":"Chid\u0113k Dur",
    "gn:population":0,
    "gn:timezone":"Asia/Kabul",
    "iso:country":"AF",
    "name:und_x_variant":[
        "Ce\u1e0f\u0113k \u1e0eu\u1e5f",
        "\u0686\u062f\u06d0\u06a9 \u062f\u0631",
        "Che\u1e0f\u0113k \u1e0eu\u1e5f",
        "Chid\u0113k Dur"
    ],
    "wof:name":"Chidek Dur",
    "wof:placetype":"locality"
},
  "geometry": {"coordinates":[70.68453000000002,37.58719],"type":"Point"}
}