{
  "type": "Feature",
  "properties": {
    "gn:admin1_code":"6",
    "gn:admin2_code":"2104.0",
    "gn:asciiname":"Awshu",
    "gn:country_code":"AF",
    "gn:dem":2192,
    "gn:feature_class":"P",
    "gn:feature_code":"PPL",
    "gn:name":"Awsh\u016b",
    "gn:population":0,
    "gn:timezone":"Asia/Kabul",
    "iso:country":"AF",
    "name:und_x_variant":[
        "Aw\u0161\u016b",
        "Awsh\u016b",
        "\u0627\u0648\u0634\u0648",
        "Awshow"
    ],
    "wof:name":"Awshu",
    "wof:placetype":"locality"
},
  "geometry": {"coordinates":[63.97569,32.9948],"type":"Point"}
}