{
  "type": "Feature",
  "properties": {
    "gn:admin1_code":"26",
    "gn:admin2_code":"1202",
    "gn:asciiname":"Jagdah Kamar",
    "gn:country_code":"AF",
    "gn:dem":583,
    "gn:feature_class":"P",
    "gn:feature_code":"PPL",
    "gn:name":"Jagdah Kamar",
    "gn:population":0,
    "gn:timezone":"Asia/Kabul",
    "iso:country":"AF",
    "name:fas_x_preferred":[
        "\u062c\u06af\u062f\u0647 \u0643\u0645\u0631"
    ],
    "name:rus_x_preferred":[
        "\u0414\u0436\u0430\u0433\u0434\u0430\u043a\u0430\u043c\u0430\u0440"
    ],
    "name:und_x_variant":[
        "Dzhagdakamar",
        "Jag\u1e0fa Kama\u1e5f",
        "Jagdah Kamar",
        "\u062c\u06af\u062f\u0647 \u06a9\u0645\u0631"
    ],
    "wof:name":"Jagdah Kamar",
    "wof:placetype":"locality"
},
  "geometry": {"coordinates":[69.22568000000001,36.72744],"type":"Point"}
}