{
  "type": "Feature",
  "properties": {
    "gn:admin1_code":"36",
    "gn:admin2_code":"701",
    "gn:asciiname":"Zavu",
    "gn:country_code":"AF",
    "gn:dem":2529,
    "gn:feature_class":"P",
    "gn:feature_code":"PPL",
    "gn:name":"Zavu",
    "gn:population":0,
    "gn:timezone":"Asia/Kabul",
    "iso:country":"AF",
    "name:und_x_variant":[
        "Z\u0101w\u016b",
        "Zavu",
        "\u0632\u0627\u0648\u0648"
    ],
    "wof:name":"Zavu",
    "wof:placetype":"locality"
},
  "geometry": {"coordinates":[69.35523000000001,33.55102],"type":"Point"}
}