{
  "type": "Feature",
  "properties": {
    "gn:admin1_code":"18",
    "gn:admin2_code":"802.0",
    "gn:asciiname":"'Ali Gul",
    "gn:country_code":"AF",
    "gn:dem":622,
    "gn:feature_class":"P",
    "gn:feature_code":"PPL",
    "gn:name":"\u2018Al\u012b Gul",
    "gn:population":0,
    "gn:timezone":"Asia/Kabul",
    "iso:country":"AF",
    "name:rus_x_preferred":[
        "Aligul\u2019"
    ],
    "name:und_x_variant":[
        "\u2018Aligul",
        "\u2018Al\u012bgol",
        "\u2018Al\u012b Gul",
        "\u0639\u0644\u06cc \u06af\u0644"
    ],
    "wof:name":"'Ali Gul",
    "wof:placetype":"locality"
},
  "geometry": {"coordinates":[70.36636999999999,34.41983],"type":"Point"}
}