{
  "type": "Feature",
  "properties": {
    "gn:admin1_code":"01",
    "gn:admin2_code":"1119",
    "gn:asciiname":"Wakhindew",
    "gn:country_code":"AF",
    "gn:dem":2331,
    "gn:feature_class":"P",
    "gn:feature_code":"PPL",
    "gn:name":"Wakh\u012bnd\u0113w",
    "gn:population":0,
    "gn:timezone":"Asia/Kabul",
    "iso:country":"AF",
    "name:und_x_variant":[
        "\u0648\u062e\u06cc\u0646\u062f\u06d0\u0648",
        "Wakh\u012br\u1e0f\u0113w",
        "Wakh\u012bnd\u0113w"
    ],
    "wof:name":"Wakhindew",
    "wof:placetype":"locality"
},
  "geometry": {"coordinates":[70.54906,37.4697],"type":"Point"}
}