{
  "type": "Feature",
  "properties": {
    "gn:admin1_code":"14",
    "gn:admin2_code":"207.0",
    "gn:asciiname":"Arazi",
    "gn:country_code":"AF",
    "gn:dem":1525,
    "gn:feature_class":"P",
    "gn:feature_code":"PPL",
    "gn:name":"Arazi",
    "gn:population":0,
    "gn:timezone":"Asia/Kabul",
    "iso:country":"AF",
    "name:ces_x_preferred":[
        "Arazi"
    ],
    "name:deu_x_preferred":[
        "Arazi"
    ],
    "name:fra_x_preferred":[
        "Arazi"
    ],
    "name:heb_x_preferred":[
        "\u05d0\u05e8\u05d6\u05d9"
    ],
    "name:pol_x_preferred":[
        "Arazi"
    ],
    "name:und_x_variant":[
        "A\u1e5f\u0101\u1e0f\u1e95i",
        "Ar\u0101\u1e95\u012b",
        "\u0627\u0631\u0627\u0636\u06cc"
    ],
    "wof:name":"Arazi",
    "wof:placetype":"locality"
},
  "geometry": {"coordinates":[69.35226999999999,35.07149],"type":"Point"}
}