{
  "type": "Feature",
  "properties": {
    "gn:admin1_code":"37",
    "gn:admin2_code":"3208.0",
    "gn:asciiname":"Sandzelai",
    "gn:country_code":"AF",
    "gn:dem":1431,
    "gn:feature_class":"P",
    "gn:feature_code":"PPL",
    "gn:name":"Sandz\u00eala\u012b",
    "gn:population":0,
    "gn:timezone":"Asia/Kabul",
    "iso:country":"AF",
    "name:fas_x_preferred":[
        "\u0633\u0648\u0646\u0632\u0644\u06cc"
    ],
    "name:und_x_variant":[
        "Sundzhalay",
        "Sunjalay",
        "Sandz\u00eala\u012b",
        "Sundzalay",
        "\u0633\u0646\u0681\u0644\u06cc"
    ],
    "wof:name":"Sandzelai",
    "wof:placetype":"locality"
},
  "geometry": {"coordinates":[69.66905,33.30727],"type":"Point"}
}