{
  "type": "Feature",
  "properties": {
    "gn:admin1_code":"28",
    "gn:admin2_code":"2507.0",
    "gn:asciiname":"Bao Kala",
    "gn:country_code":"AF",
    "gn:dem":1853,
    "gn:feature_class":"P",
    "gn:feature_code":"PPL",
    "gn:name":"B\u0101\u014d Kal\u0101",
    "gn:population":0,
    "gn:timezone":"Asia/Kabul",
    "iso:country":"AF",
    "name:fas_x_preferred":[
        "\u0642\u0644\u0639\u0647\u0654 \u0628\u0627\u0648"
    ],
    "name:und_x_variant":[
        "Baukala",
        "B\u0101\u014d Kal\u0101",
        "\u0628\u0627\u0648 \u06a9\u0644\u0627",
        "B\u0101o Kal\u0101"
    ],
    "wof:name":"Bao Kala",
    "wof:placetype":"locality"
},
  "geometry": {"coordinates":[67.0561,31.98714],"type":"Point"}
}