{
  "type": "Feature",
  "properties": {
    "gn:admin1_code":"40",
    "gn:admin2_code":"308",
    "gn:asciiname":"Hasan Khel",
    "gn:country_code":"AF",
    "gn:dem":1476,
    "gn:feature_class":"P",
    "gn:feature_code":"PPL",
    "gn:name":"\u1e28asan Kh\u0113l",
    "gn:population":0,
    "gn:timezone":"Asia/Kabul",
    "iso:country":"AF",
    "name:fas_x_preferred":[
        "\u062d\u0633\u0646 \u062e\u064a\u0644"
    ],
    "name:rus_x_preferred":[
        "Khasankheyl\u2019"
    ],
    "name:und_x_variant":[
        "\u1e28asan Kh\u0113l",
        "\u1e28asankheyl",
        "\u062d\u0633\u0646 \u062e\u06d0\u0644"
    ],
    "wof:name":"Hasan Khel",
    "wof:placetype":"locality"
},
  "geometry": {"coordinates":[69.28574,34.9582],"type":"Point"}
}