{
  "type": "Feature",
  "properties": {
    "gn:admin1_code":"38",
    "gn:admin2_code":"3008",
    "gn:asciiname":"Kotahlay",
    "gn:country_code":"AF",
    "gn:dem":997,
    "gn:feature_class":"P",
    "gn:feature_code":"PPL",
    "gn:name":"K\u014d\u1e6fahlay",
    "gn:population":0,
    "gn:timezone":"Asia/Kabul",
    "iso:country":"AF",
    "name:und_x_variant":[
        "K\u014dtalay",
        "Kotalay",
        "Kowtalay",
        "K\u014d\u1e6fahlay",
        "\u06a9\u0648\u067c\u0647 \u0644\u06cc"
    ],
    "wof:name":"Kotahlay",
    "wof:placetype":"locality"
},
  "geometry": {"coordinates":[70.38367,34.91986],"type":"Point"}
}