{
  "type": "Feature",
  "properties": {
    "gn:admin1_code":"08",
    "gn:admin2_code":"602",
    "gn:asciiname":"Gidargu",
    "gn:country_code":"AF",
    "gn:dem":2923,
    "gn:feature_class":"P",
    "gn:feature_code":"PPL",
    "gn:name":"Gidarg\u016b",
    "gn:population":0,
    "gn:timezone":"Asia/Kabul",
    "iso:country":"AF",
    "name:rus_x_preferred":[
        "\u0413\u0438\u0434\u0430\u0440\u0433\u0443"
    ],
    "name:und_x_variant":[
        "G\u012bdargu",
        "Gidarg\u016b",
        "\u06af\u062f\u0631\u06af\u0648"
    ],
    "wof:name":"Gidargu",
    "wof:placetype":"locality"
},
  "geometry": {"coordinates":[67.95355000000001,33.55192],"type":"Point"}
}