{
  "type": "Feature",
  "properties": {
    "gn:admin1_code":"14",
    "gn:admin2_code":"204.0",
    "gn:asciiname":"Sherwani-ye Bala",
    "gn:country_code":"AF",
    "gn:dem":1786,
    "gn:feature_class":"P",
    "gn:feature_code":"PPLA2",
    "gn:name":"Sh\u0113rw\u0101n\u012b-ye B\u0101l\u0101",
    "gn:population":0,
    "gn:timezone":"Asia/Kabul",
    "iso:country":"AF",
    "name:fas_x_preferred":[
        "\u0634\u064a\u0631\u0648\u0627\u0646\u06cc \u0628\u0627\u0644\u0627"
    ],
    "name:rus_x_preferred":[
        "\u0428\u0435\u0440\u0432\u0430\u043d\u0438-\u0411\u0430\u043b\u0430"
    ],
    "name:und_x_variant":[
        "Shervani-Bala",
        "\u0160\u0113rw\u0101ni B\u0101l\u0101",
        "Sh\u012brv\u0101n\u012b B\u0101l\u0101",
        "Shayrw\u0101n-e B\u0101l\u0101",
        "\u0634\u06cc\u0631\u0648\u0627\u0646 \u0628\u0627\u0644\u0627",
        "Shayrw\u0101n\u012b-ye B\u0101l\u0101",
        "Shayrw\u0101n\u012b",
        "\u0634\u064a\u0631\u0648\u0627\u0646\u06cc",
        "Sh\u0113rw\u0101n\u012b-ye B\u0101l\u0101"
    ],
    "wof:name":"Sherwani-ye Bala",
    "wof:placetype":"locality"
},
  "geometry": {"coordinates":[69.59934,35.01468],"type":"Point"}
}