{
  "type": "Feature",
  "properties": {
    "gn:admin1_code":"37",
    "gn:admin2_code":"3205",
    "gn:asciiname":"Narai Motay",
    "gn:country_code":"AF",
    "gn:dem":2102,
    "gn:feature_class":"P",
    "gn:feature_code":"PPL",
    "gn:name":"Nara\u012b M\u014dtay",
    "gn:population":0,
    "gn:timezone":"Asia/Kabul",
    "iso:country":"AF",
    "name:und_x_variant":[
        "Naraymotay",
        "Na\u1e5fay M\u014dtay",
        "Nara\u012b M\u016btay",
        "N\u0101ray Mowtay",
        "Nara\u012b M\u014dtay",
        "\u0646\u0631\u06cc \u0645\u0648\u062a\u06cc"
    ],
    "wof:name":"Narai Motay",
    "wof:placetype":"locality"
},
  "geometry": {"coordinates":[69.69423,33.55958],"type":"Point"}
}