{
  "type": "Feature",
  "properties": {
    "gn:admin1_code":"01",
    "gn:admin2_code":"1119",
    "gn:asciiname":"Talik Dasht",
    "gn:country_code":"AF",
    "gn:dem":2581,
    "gn:feature_class":"P",
    "gn:feature_code":"PPL",
    "gn:name":"Talik Dasht",
    "gn:population":0,
    "gn:timezone":"Asia/Kabul",
    "iso:country":"AF",
    "name:und_x_variant":[
        "Talek \u1e0eas\u0304t",
        "\u062a\u0644\u06a9 \u062f\u0634\u062a",
        "Talek Dasht",
        "Talik Dasht"
    ],
    "wof:name":"Talik Dasht",
    "wof:placetype":"locality"
},
  "geometry": {"coordinates":[70.64653,37.3838],"type":"Point"}
}