{
  "type": "Feature",
  "properties": {
    "gn:admin1_code":"08",
    "gn:admin2_code":"604",
    "gn:asciiname":"Qarah Qol",
    "gn:country_code":"AF",
    "gn:dem":3303,
    "gn:feature_class":"P",
    "gn:feature_code":"PPL",
    "gn:name":"Qarah Q\u014dl",
    "gn:population":0,
    "gn:timezone":"Asia/Kabul",
    "iso:country":"AF",
    "name:rus_x_preferred":[
        "Karakul\u2019"
    ],
    "name:und_x_variant":[
        "Qa\u1e5faq\u014dl",
        "Qarah-Qowl",
        "Qarehqowl",
        "Qarah Q\u014dl",
        "\u0642\u0631\u0647 \u0642\u0648\u0644"
    ],
    "wof:name":"Qarah Qol",
    "wof:placetype":"locality"
},
  "geometry": {"coordinates":[67.70402,34.15997],"type":"Point"}
}