{
  "type": "Feature",
  "properties": {
    "gn:admin1_code":"18",
    "gn:admin2_code":"810.0",
    "gn:asciiname":"Landay",
    "gn:country_code":"AF",
    "gn:dem":1628,
    "gn:feature_class":"P",
    "gn:feature_code":"PPL",
    "gn:name":"Lan\u1e0fay",
    "gn:population":0,
    "gn:timezone":"Asia/Kabul",
    "iso:country":"AF",
    "name:fas_x_preferred":[
        "\u0644\u0646\u062f\u06cc"
    ],
    "name:slv_x_preferred":[
        "Landaj"
    ],
    "name:und_x_variant":[
        "Lan\u1e0fay",
        "\u0644\u0646\u0689\u06cc",
        "Landay"
    ],
    "wof:name":"Landay",
    "wof:placetype":"locality"
},
  "geometry": {"coordinates":[70.59846999999998,34.05264],"type":"Point"}
}