{
  "type": "Feature",
  "properties": {
    "gn:admin1_code":"08",
    "gn:admin2_code":"613",
    "gn:asciiname":"Malang Khel",
    "gn:country_code":"AF",
    "gn:dem":2050,
    "gn:feature_class":"P",
    "gn:feature_code":"PPL",
    "gn:name":"Malang Kh\u0113l",
    "gn:population":0,
    "gn:timezone":"Asia/Kabul",
    "iso:country":"AF",
    "name:fas_x_preferred":[
        "\u0645\u0644\u0646\u06af \u062e\u064a\u0644"
    ],
    "name:rus_x_preferred":[
        "Malangkheyl\u2019"
    ],
    "name:und_x_variant":[
        "Malang Kh\u0113l",
        "Malang Kheyl",
        "\u0645\u0644\u0646\u06af \u062e\u06d0\u0644"
    ],
    "wof:name":"Malang Khel",
    "wof:placetype":"locality"
},
  "geometry": {"coordinates":[68.09499,33.0929],"type":"Point"}
}