{
  "type": "Feature",
  "properties": {
    "gn:admin1_code":"28",
    "gn:asciiname":"Sar-e Qadi",
    "gn:country_code":"AF",
    "gn:dem":2596,
    "gn:feature_class":"P",
    "gn:feature_code":"PPL",
    "gn:name":"Sar-e Q\u0101\u1e0fi",
    "gn:population":0,
    "gn:timezone":"Asia/Kabul",
    "iso:country":"AF",
    "wof:name":"Sar-e Qadi",
    "wof:placetype":"locality"
},
  "geometry": {"coordinates":[67.39583,33.02333],"type":"Point"}
}