{
  "type": "Feature",
  "properties": {
    "gn:admin1_code":"06",
    "gn:admin2_code":"2104",
    "gn:asciiname":"Kajari",
    "gn:country_code":"AF",
    "gn:dem":2064,
    "gn:feature_class":"P",
    "gn:feature_code":"PPL",
    "gn:name":"Kaj\u0101r\u012b",
    "gn:population":0,
    "gn:timezone":"Asia/Kabul",
    "iso:country":"AF",
    "name:und_x_variant":[
        "Kaj\u0101r\u012b",
        "\u06a9\u062c\u0627\u0631\u06cc",
        "Kaj\u0101\u1e5f\u012b"
    ],
    "wof:name":"Kajari",
    "wof:placetype":"locality"
},
  "geometry": {"coordinates":[63.56886,33.35609],"type":"Point"}
}