{
  "type": "Feature",
  "properties": {
    "gn:admin1_code":"39",
    "gn:admin2_code":"2601.0",
    "gn:asciiname":"Solah-ye Shamali",
    "gn:country_code":"AF",
    "gn:dem":1378,
    "gn:feature_class":"P",
    "gn:feature_code":"PPL",
    "gn:name":"S\u014dlah-ye Sham\u0101l\u012b",
    "gn:population":0,
    "gn:timezone":"Asia/Kabul",
    "iso:country":"AF",
    "name:fas_x_preferred":[
        "\u0633\u0648\u0644\u06c0 \u0634\u0645\u0627\u0644\u06cc"
    ],
    "name:und_x_variant":[
        "Sola-i-\u0160am\u0101li",
        "Solayi-Shamali",
        "S\u014dlah-ye Sham\u0101l\u012b",
        "\u0633\u0648\u0644\u0647 \u0634\u0645\u0627\u0644\u06cc",
        "S\u016bleh-ye Shom\u0101l\u012b"
    ],
    "wof:name":"Solah-ye Shamali",
    "wof:placetype":"locality"
},
  "geometry": {"coordinates":[65.92185000000001,32.6185],"type":"Point"}
}