{
  "type": "Feature",
  "properties": {
    "gn:admin1_code":"41",
    "gn:admin2_code":"3409.0",
    "gn:asciiname":"Tughe",
    "gn:country_code":"AF",
    "gn:dem":1966,
    "gn:feature_class":"P",
    "gn:feature_code":"PPL",
    "gn:name":"Tugh\u0113",
    "gn:population":0,
    "gn:timezone":"Asia/Kabul",
    "iso:country":"AF",
    "wof:name":"Tughe",
    "wof:placetype":"locality"
},
  "geometry": {"coordinates":[66.27979000000001,33.91476],"type":"Point"}
}