{
  "type": "Feature",
  "properties": {
    "gn:admin1_code":"18",
    "gn:admin2_code":"819",
    "gn:asciiname":"Sheywah",
    "gn:country_code":"AF",
    "gn:dem":602,
    "gn:feature_class":"P",
    "gn:feature_code":"PPLA2",
    "gn:name":"Sheywah",
    "gn:population":0,
    "gn:timezone":"Asia/Kabul",
    "iso:country":"AF",
    "name:fas_x_preferred":[
        "\u0634\u064a\u0648\u0647"
    ],
    "name:und_x_variant":[
        "Sh\u0113wah",
        "K\u016bz Konar",
        "\u0160\u0113wa",
        "Sheywah",
        "Shewa",
        "Sheva",
        "Sh\u012bveh",
        "\u0634\u064a\u0648\u0647",
        "S\u0332h\u0332\u0113wah",
        "\u069a\u06d0\u0648\u0647"
    ],
    "wof:name":"Sheywah",
    "wof:placetype":"locality"
},
  "geometry": {"coordinates":[70.58859,34.57169],"type":"Point"}
}