{
  "type": "Feature",
  "properties": {
    "gn:admin1_code":"27",
    "gn:admin2_code":"404",
    "gn:asciiname":"Sanginak",
    "gn:country_code":"AF",
    "gn:dem":3229,
    "gn:feature_class":"P",
    "gn:feature_code":"PPL",
    "gn:name":"Sang\u012bnak",
    "gn:population":0,
    "gn:timezone":"Asia/Kabul",
    "iso:country":"AF",
    "name:und_x_variant":[
        "Sang\u012bnak",
        "\u0633\u0646\u06af\u06cc\u0646\u06a9"
    ],
    "wof:name":"Sanginak",
    "wof:placetype":"locality"
},
  "geometry": {"coordinates":[67.61539999999999,34.57383],"type":"Point"}
}