{
  "type": "Feature",
  "properties": {
    "gn:admin1_code":"07",
    "gn:admin2_code":"1802",
    "gn:asciiname":"Tarakhchi",
    "gn:country_code":"AF",
    "gn:dem":715,
    "gn:feature_class":"P",
    "gn:feature_code":"PPL",
    "gn:name":"Tarakhch\u012b",
    "gn:population":0,
    "gn:timezone":"Asia/Kabul",
    "iso:country":"AF",
    "name:und_x_variant":[
        "Tarakhch\u012b",
        "\u062a\u0631\u062e\u0686\u06cc"
    ],
    "wof:name":"Tarakhchi",
    "wof:placetype":"locality"
},
  "geometry": {"coordinates":[64.75686,36.02545999999999],"type":"Point"}
}