{
  "type": "Feature",
  "properties": {
    "gn:admin1_code":"41",
    "gn:admin2_code":"3409.0",
    "gn:asciiname":"Jaryah Khanah",
    "gn:country_code":"AF",
    "gn:dem":2571,
    "gn:feature_class":"P",
    "gn:feature_code":"PPL",
    "gn:name":"Jaryah Kh\u0101nah",
    "gn:population":0,
    "gn:timezone":"Asia/Kabul",
    "iso:country":"AF",
    "name:und_x_variant":[
        "Ja\u1e5fyakh\u0101na",
        "Jar\u012beh Kh\u0101neh",
        "Jaryah Kh\u0101nah",
        "\u062c\u0631\u06cc\u0647 \u062e\u0627\u0646\u0647"
    ],
    "wof:name":"Jaryah Khanah",
    "wof:placetype":"locality"
},
  "geometry": {"coordinates":[66.29961999999999,33.81285],"type":"Point"}
}