{
  "type": "Feature",
  "properties": {
    "gn:admin1_code":"23",
    "gn:admin2_code":"2415.0",
    "gn:asciiname":"Karam Karez",
    "gn:country_code":"AF",
    "gn:dem":1424,
    "gn:feature_class":"P",
    "gn:feature_code":"PPL",
    "gn:name":"Karam K\u0101r\u0113z",
    "gn:population":0,
    "gn:timezone":"Asia/Kabul",
    "iso:country":"AF",
    "name:fas_x_preferred":[
        "\u0643\u0631\u0645 \u0643\u0627\u0631\u064a\u0632"
    ],
    "name:und_x_variant":[
        "Karamkarez",
        "Ka\u1e5fam K\u0101\u1e5f\u0113z",
        "Karam K\u0101r\u0113z",
        "\u06a9\u0631\u0645 \u06a9\u0627\u0631\u06d0\u0632",
        "Karam K\u0101r\u012bz"
    ],
    "wof:name":"Karam Karez",
    "wof:placetype":"locality"
},
  "geometry": {"coordinates":[65.59378000000001,32.49803],"type":"Point"}
}