{
  "type": "Feature",
  "properties": {
    "gn:admin1_code":"41",
    "gn:admin2_code":"3403.0",
    "gn:asciiname":"Dahan-e Siyah Qol",
    "gn:country_code":"AF",
    "gn:dem":2509,
    "gn:feature_class":"P",
    "gn:feature_code":"PPL",
    "gn:name":"Dahan-e Siy\u0101h Q\u014dl",
    "gn:population":0,
    "gn:timezone":"Asia/Kabul",
    "iso:country":"AF",
    "name:rus_x_preferred":[
        "Dakhani-Siakhkul\u2019"
    ],
    "name:und_x_variant":[
        "\u1e0eahane Sy\u0101hq\u014dl",
        "Dah\u0101n-e S\u012b\u0101h Q\u014dl",
        "Dahan-e S\u012b\u0101hqowl",
        "Dahan-e Siy\u0101h Q\u014dl",
        "\u062f\u0647\u0646 \u0633\u064a\u0627\u0647 \u0642\u0648\u0644"
    ],
    "wof:name":"Dahan-e Siyah Qol",
    "wof:placetype":"locality"
},
  "geometry": {"coordinates":[66.1737,34.01992],"type":"Point"}
}