{
  "type": "Feature",
  "properties": {
    "gn:admin1_code":"8",
    "gn:admin2_code":"608.0",
    "gn:asciiname":"'Isa Khel",
    "gn:country_code":"AF",
    "gn:dem":2003,
    "gn:feature_class":"P",
    "gn:feature_code":"PPL",
    "gn:name":"\u2018\u012as\u00e1 Kh\u0113l",
    "gn:population":0,
    "gn:timezone":"Asia/Kabul",
    "iso:country":"AF",
    "name:und_x_variant":[
        "\u2018Is\u0101kh\u0113l",
        "\u2018Is\u00e1 Kheyl",
        "\u2018\u012as\u00e1 Kh\u0113l",
        "\u0639\u06cc\u0633\u0649 \u062e\u06d0\u0644"
    ],
    "wof:name":"'Isa Khel",
    "wof:placetype":"locality"
},
  "geometry": {"coordinates":[67.84285,32.83076],"type":"Point"}
}