{
  "type": "Feature",
  "properties": {
    "gn:admin1_code":"10",
    "gn:admin2_code":"2304",
    "gn:asciiname":"Karez Ghulam",
    "gn:country_code":"AF",
    "gn:dem":963,
    "gn:feature_class":"P",
    "gn:feature_code":"PPL",
    "gn:name":"K\u0101r\u0113z Ghul\u0101m",
    "gn:population":0,
    "gn:timezone":"Asia/Kabul",
    "iso:country":"AF",
    "name:und_x_variant":[
        "K\u0101\u1e5f\u0113z Ghol\u0101m",
        "Karezgulyam",
        "K\u0101r\u0113z Ghul\u0101m",
        "\u06a9\u0627\u0631\u06d0\u0632 \u063a\u0644\u0627\u0645",
        "K\u0101r\u012bz Ghol\u0101m"
    ],
    "wof:name":"Karez Ghulam",
    "wof:placetype":"locality"
},
  "geometry": {"coordinates":[64.76881,32.19884],"type":"Point"}
}