{
  "type": "Feature",
  "properties": {
    "gn:admin1_code":"09",
    "gn:admin2_code":"2707",
    "gn:asciiname":"Qal'ah-ye Ghighunak",
    "gn:country_code":"AF",
    "gn:dem":2694,
    "gn:feature_class":"P",
    "gn:feature_code":"PPL",
    "gn:name":"Qal\u2018ah-ye Gh\u012bghunak",
    "gn:population":0,
    "gn:timezone":"Asia/Kabul",
    "iso:country":"AF",
    "name:und_x_variant":[
        "Qal\u2018a-i-Ghighonak",
        "Kalayi-Gigunak",
        "Qal\u2018ah-ye Gha\u012bghonak",
        "Qal\u2018eh-ye Ghighonak",
        "Qal\u2018ah-ye Gh\u012bghunak",
        "\u0642\u0644\u0639\u06c0 \u063a\u06cc\u063a\u0648\u0646\u06a9"
    ],
    "wof:name":"Qal'ah-ye Ghighunak",
    "wof:placetype":"locality"
},
  "geometry": {"coordinates":[66.20039,34.66596],"type":"Point"}
}