{
  "type": "Feature",
  "properties": {
    "gn:admin1_code":"9",
    "gn:admin2_code":"2707.0",
    "gn:asciiname":"Deh-e Mirdad",
    "gn:country_code":"AF",
    "gn:dem":2924,
    "gn:feature_class":"P",
    "gn:feature_code":"PPL",
    "gn:name":"Deh-e M\u012brd\u0101d",
    "gn:population":0,
    "gn:timezone":"Asia/Kabul",
    "iso:country":"AF",
    "name:und_x_variant":[
        "Dekhimirdad",
        "Deh-e M\u012brd\u0101d",
        "Deh M\u012brd\u0101d",
        "\u062f\u0647 \u0645\u06cc\u0631\u062f\u0627\u062f"
    ],
    "wof:name":"Deh-e Mirdad",
    "wof:placetype":"locality"
},
  "geometry": {"coordinates":[66.55149,34.60804],"type":"Point"}
}