{
  "type": "Feature",
  "properties": {
    "gn:admin1_code":"13",
    "gn:admin2_code":"108",
    "gn:asciiname":"Khaldari Bala",
    "gn:country_code":"AF",
    "gn:dem":2110,
    "gn:feature_class":"P",
    "gn:feature_code":"PPL",
    "gn:name":"Kh\u0101ld\u0101r\u012b B\u0101l\u0101",
    "gn:population":0,
    "gn:timezone":"Asia/Kabul",
    "iso:country":"AF",
    "name:rus_x_preferred":[
        "Khal\u2019dari-Bala"
    ],
    "name:und_x_variant":[
        "Kh\u0101l\u1e0f\u0101\u1e5f\u012b",
        "Kh\u0101l\u1e0f\u0101\u1e5f\u012b B\u0101l\u0101",
        "Kh\u0101ld\u0101r\u012b B\u0101l\u0101",
        "Kh\u0101ld\u0101r\u012b-ye B\u0101l\u0101",
        "\u062e\u0627\u0644\u062f\u0627\u0631\u06cc \u0628\u0627\u0644\u0627"
    ],
    "wof:name":"Khaldari Bala",
    "wof:placetype":"locality"
},
  "geometry": {"coordinates":[68.97258000000001,34.55185],"type":"Point"}
}