{
  "type": "Feature",
  "properties": {
    "gn:admin1_code":"08",
    "gn:admin2_code":"606",
    "gn:asciiname":"Jelgah",
    "gn:country_code":"AF",
    "gn:dem":2848,
    "gn:feature_class":"P",
    "gn:feature_code":"PPL",
    "gn:name":"J\u00ealgah",
    "gn:population":0,
    "gn:timezone":"Asia/Kabul",
    "iso:country":"AF",
    "name:und_x_variant":[
        "Jelgah-e Malang",
        "J\u011blga",
        "J\u0113lgeh",
        "Jelgah",
        "Jolgeh",
        "J\u00ealgah",
        "\u062c\u0644\u06af\u0647"
    ],
    "wof:name":"Jelgah",
    "wof:placetype":"locality"
},
  "geometry": {"coordinates":[67.08861999999999,33.11712],"type":"Point"}
}