{
  "type": "Feature",
  "properties": {
    "gn:admin1_code":"41",
    "gn:admin2_code":"3409.0",
    "gn:asciiname":"Dahan-e Rabatak",
    "gn:country_code":"AF",
    "gn:dem":2273,
    "gn:feature_class":"P",
    "gn:feature_code":"PPL",
    "gn:name":"Dah\u0101n-e Rab\u0101\u0163ak",
    "gn:population":0,
    "gn:timezone":"Asia/Kabul",
    "iso:country":"AF",
    "name:und_x_variant":[
        "Dahan-e Reb\u0101\u0163ak",
        "\u1e0eahane \u1e5eob\u0101\u1e6fak",
        "Dahan-e Rob\u0101\u0163ak",
        "Dah\u0101n-e Rab\u0101\u0163ak",
        "\u062f\u0647\u0627\u0646 \u0631\u0628\u0627\u0637\u06a9"
    ],
    "wof:name":"Dahan-e Rabatak",
    "wof:placetype":"locality"
},
  "geometry": {"coordinates":[66.32233000000001,33.7378],"type":"Point"}
}