{
  "type": "Feature",
  "properties": {
    "gn:admin1_code":"10",
    "gn:admin2_code":"2302.0",
    "gn:asciiname":"Haji 'Abdur Rahim Tak",
    "gn:country_code":"AF",
    "gn:dem":818,
    "gn:feature_class":"P",
    "gn:feature_code":"PPL",
    "gn:name":"\u1e28\u0101j\u012b \u2018Abdur Ra\u1e29\u012bm \u1e6eak",
    "gn:population":0,
    "gn:timezone":"Asia/Kabul",
    "iso:country":"AF",
    "name:und_x_variant":[
        "Khadzhi-Abdurrakhim-Tak",
        "\u1e28\u0101ji \u2018Ab\u1e0fu\u1e5f\u1e5fa\u1e29\u012bm Tak",
        "\u1e28\u0101j\u012b \u2018Abdur Ra\u1e29\u012bm \u1e6eak",
        "\u062d\u0627\u062c\u06cc \u0639\u0628\u062f \u0627\u0644\u0631\u062d\u06cc\u0645 \u067c\u06a9",
        "\u1e28\u0101jj\u012b \u2018Abdorra\u1e29\u012bm Tak"
    ],
    "wof:name":"Haji 'Abdur Rahim Tak",
    "wof:placetype":"locality"
},
  "geometry": {"coordinates":[64.61664,31.68691],"type":"Point"}
}