{
  "type": "Feature",
  "properties": {
    "gn:admin1_code":"31",
    "gn:admin2_code":"1710.0",
    "gn:asciiname":"Alaili",
    "gn:country_code":"AF",
    "gn:dem":294,
    "gn:feature_class":"P",
    "gn:feature_code":"PPL",
    "gn:name":"Ala\u012bl\u012b",
    "gn:population":0,
    "gn:timezone":"Asia/Kabul",
    "iso:country":"AF",
    "name:und_x_variant":[
        "Alailee",
        "Ala\u012bl\u012b",
        "\u0627\u0644\u064a\u0644\u06cc"
    ],
    "wof:name":"Alaili",
    "wof:placetype":"locality"
},
  "geometry": {"coordinates":[66.10361,36.8575],"type":"Point"}
}