{
  "type": "Feature",
  "properties": {
    "gn:admin1_code":"13",
    "gn:admin2_code":"101.0",
    "gn:asciiname":"Qal'ah-ye Muhammad Hasan",
    "gn:country_code":"AF",
    "gn:dem":1834,
    "gn:feature_class":"P",
    "gn:feature_code":"PPL",
    "gn:name":"Qal\u2018ah-ye Mu\u1e29ammad \u1e28asan",
    "gn:population":0,
    "gn:timezone":"Asia/Kabul",
    "iso:country":"AF",
    "name:und_x_variant":[
        "Qal\u2018ah-ye Mu\u1e29ammad \u1e28asan",
        "\u0642\u0644\u0639\u0647 \u0645\u062d\u0645\u062f \u062d\u0633\u0646",
        "Qal\u2018ah-ye Mu\u1e29amma\u1e0f \u1e28asan"
    ],
    "wof:name":"Qal'ah-ye Muhammad Hasan",
    "wof:placetype":"locality"
},
  "geometry": {"coordinates":[69.18555000000001,34.49286],"type":"Point"}
}