{
  "type": "Feature",
  "properties": {
    "gn:admin1_code":"08",
    "gn:admin2_code":"613",
    "gn:asciiname":"Siyah Kaykah",
    "gn:country_code":"AF",
    "gn:dem":2892,
    "gn:feature_class":"P",
    "gn:feature_code":"PPL",
    "gn:name":"Siy\u0101h Kaykah",
    "gn:population":0,
    "gn:timezone":"Asia/Kabul",
    "iso:country":"AF",
    "name:rus_x_preferred":[
        "\u0421\u0438\u0430\u0445\u043a\u0435\u043a\u0430"
    ],
    "name:und_x_variant":[
        "Siakhkeka",
        "Sy\u0101hk\u0113ka",
        "S\u012b\u0101hk\u0113kah",
        "S\u012b\u0101h Kaykah",
        "\u0633\u06cc\u0627\u0647 \u06a9\u06cc\u06a9\u0647",
        "Siy\u0101h Kaykah"
    ],
    "wof:name":"Siyah Kaykah",
    "wof:placetype":"locality"
},
  "geometry": {"coordinates":[67.88036,33.31414],"type":"Point"}
}