{
  "type": "Feature",
  "properties": {
    "gn:admin1_code":"28",
    "gn:admin2_code":"2506",
    "gn:asciiname":"Srah Shah",
    "gn:country_code":"AF",
    "gn:dem":1589,
    "gn:feature_class":"P",
    "gn:feature_code":"PPL",
    "gn:name":"Srah Sh\u0101h",
    "gn:population":0,
    "gn:timezone":"Asia/Kabul",
    "iso:country":"AF",
    "name:und_x_variant":[
        "Srashakh",
        "Sra \u0160\u0101h",
        "Srah Sh\u0101h",
        "\u0633\u0631\u0647 \u0634\u0627\u0647"
    ],
    "wof:name":"Srah Shah",
    "wof:placetype":"locality"
},
  "geometry": {"coordinates":[66.76136,32.08183],"type":"Point"}
}