{
  "type": "Feature",
  "properties": {
    "gn:admin1_code":"1",
    "gn:admin2_code":"1104.0",
    "gn:asciiname":"Tili",
    "gn:country_code":"AF",
    "gn:dem":2926,
    "gn:feature_class":"P",
    "gn:feature_code":"PPL",
    "gn:name":"Til\u012b",
    "gn:population":0,
    "gn:timezone":"Asia/Kabul",
    "iso:country":"AF",
    "name:und_x_variant":[
        "\u062a\u0644\u06cc",
        "Tili",
        "Til\u012b"
    ],
    "wof:name":"Tili",
    "wof:placetype":"locality"
},
  "geometry": {"coordinates":[70.82403000000002,35.8054],"type":"Point"}
}