{
  "type": "Feature",
  "properties": {
    "gn:admin1_code":"37",
    "gn:admin2_code":"3205",
    "gn:asciiname":"Morak",
    "gn:country_code":"AF",
    "gn:dem":2413,
    "gn:feature_class":"P",
    "gn:feature_code":"PPL",
    "gn:name":"M\u014d\u1e5fak",
    "gn:population":0,
    "gn:timezone":"Asia/Kabul",
    "iso:country":"AF",
    "name:und_x_variant":[
        "M\u014drak",
        "Morak",
        "Mow\u1e5fak",
        "M\u014d\u1e5fak",
        "\u0645\u0648\u0693\u06a9"
    ],
    "wof:name":"Morak",
    "wof:placetype":"locality"
},
  "geometry": {"coordinates":[69.61851999999999,33.5836],"type":"Point"}
}