{
  "type": "Feature",
  "properties": {
    "gn:admin1_code":"8",
    "gn:admin2_code":"607.0",
    "gn:asciiname":"Galaband",
    "gn:country_code":"AF",
    "gn:dem":2429,
    "gn:feature_class":"P",
    "gn:feature_code":"PPL",
    "gn:name":"Galaband",
    "gn:population":0,
    "gn:timezone":"Asia/Kabul",
    "iso:country":"AF",
    "name:und_x_variant":[
        "\u06af\u0644\u0628\u0646\u062f",
        "Galaban\u1e0f"
    ],
    "wof:name":"Galaband",
    "wof:placetype":"locality"
},
  "geometry": {"coordinates":[67.51801999999999,32.93727],"type":"Point"}
}