{
  "type": "Feature",
  "properties": {
    "gn:admin1_code":"37",
    "gn:admin2_code":"3202.0",
    "gn:asciiname":"'Ali Sangi",
    "gn:country_code":"AF",
    "gn:dem":1447,
    "gn:feature_class":"P",
    "gn:feature_code":"PPL",
    "gn:name":"\u2018Al\u012b Sang\u012b",
    "gn:population":0,
    "gn:timezone":"Asia/Kabul",
    "iso:country":"AF",
    "name:und_x_variant":[
        "Alisangi",
        "\u2018Al\u012b Sang\u012b",
        "\u0639\u0644\u06cc \u0633\u0646\u06af\u06cc"
    ],
    "wof:name":"'Ali Sangi",
    "wof:placetype":"locality"
},
  "geometry": {"coordinates":[70.08802,33.61186],"type":"Point"}
}