{
  "type": "Feature",
  "properties": {
    "gn:admin1_code":"29",
    "gn:admin2_code":"2901.0",
    "gn:asciiname":"Niyazi",
    "gn:country_code":"AF",
    "gn:dem":2138,
    "gn:feature_class":"P",
    "gn:feature_code":"PPL",
    "gn:name":"Niy\u0101z\u012b",
    "gn:population":0,
    "gn:timezone":"Asia/Kabul",
    "iso:country":"AF",
    "name:rus_x_preferred":[
        "N\u2019yazi"
    ],
    "name:und_x_variant":[
        "Ny\u0101zi",
        "\u0646\u06cc\u0627\u0632\u06cc",
        "N\u012b\u0101z\u012b",
        "Niy\u0101z\u012b"
    ],
    "wof:name":"Niyazi",
    "wof:placetype":"locality"
},
  "geometry": {"coordinates":[68.75009,33.15682],"type":"Point"}
}