{
  "type": "Feature",
  "properties": {
    "gn:admin1_code":"29",
    "gn:admin2_code":"2901.0",
    "gn:asciiname":"Niyazi",
    "gn:country_code":"AF",
    "gn:dem":2138,
    "gn:feature_class":"P",
    "gn:feature_code":"PPL",
    "gn:name":"Niy\u0101z\u012b",
    "gn:population":0,
    "gn:timezone":"Asia/Kabul",
    "iso:country":"AF",
    "name:ara_x_preferred":[
        "\u0646\u064a\u0627\u0632\u064a"
    ],
    "name:azb_x_preferred":[
        "\u0646\u06cc\u0627\u0632\u06cc"
    ],
    "name:aze_x_preferred":[
        "Niyazi"
    ],
    "name:deu_x_preferred":[
        "Knyaz Hac\u0131b\u0259yov"
    ],
    "name:fas_x_preferred":[
        "\u0646\u06cc\u0627\u0632\u06cc"
    ],
    "name:fra_x_preferred":[
        "Niazi"
    ],
    "name:hye_x_preferred":[
        "\u0546\u056b\u0575\u0561\u0566\u056b"
    ],
    "name:ita_x_preferred":[
        "Niyazi"
    ],
    "name:kat_x_preferred":[
        "\u10dc\u10d8\u10d0\u10d6\u10d8"
    ],
    "name:pol_x_preferred":[
        "Niyazi"
    ],
    "name:rus_x_preferred":[
        "N\u2019yazi"
    ],
    "name:rus_x_variant":[
        "\u0422\u0430\u0433\u0438\u0437\u0430\u0434\u0435-\u0413\u0430\u0434\u0436\u0438\u0431\u0435\u043a\u043e\u0432"
    ],
    "name:spa_x_preferred":[
        "Niyazi"
    ],
    "name:tur_x_preferred":[
        "Niyazi"
    ],
    "name:und_x_variant":[
        "Ny\u0101zi",
        "\u0646\u06cc\u0627\u0632\u06cc",
        "N\u012b\u0101z\u012b",
        "Niy\u0101z\u012b"
    ],
    "wof:name":"Niyazi",
    "wof:placetype":"locality"
},
  "geometry": {"coordinates":[68.75009,33.15682],"type":"Point"}
}