{
  "type": "Feature",
  "properties": {
    "gn:admin1_code":"09",
    "gn:admin2_code":"2702",
    "gn:asciiname":"Sarmalan",
    "gn:country_code":"AF",
    "gn:dem":2583,
    "gn:feature_class":"P",
    "gn:feature_code":"PPL",
    "gn:name":"Sarm\u0101l\u0101n",
    "gn:population":0,
    "gn:timezone":"Asia/Kabul",
    "iso:country":"AF",
    "name:und_x_variant":[
        "Sarm\u0101l\u0101n",
        "\u0633\u0631\u0645\u0627\u0644\u0627\u0646"
    ],
    "wof:name":"Sarmalan",
    "wof:placetype":"locality"
},
  "geometry": {"coordinates":[64.13663000000001,33.90837],"type":"Point"}
}