{
  "type": "Feature",
  "properties": {
    "gn:admin1_code":"03",
    "gn:admin2_code":"1304",
    "gn:asciiname":"Lar-e Badak",
    "gn:country_code":"AF",
    "gn:dem":972,
    "gn:feature_class":"P",
    "gn:feature_code":"PPL",
    "gn:name":"Lar-e Badak",
    "gn:population":0,
    "gn:timezone":"Asia/Kabul",
    "iso:country":"AF",
    "name:und_x_variant":[
        "\u0644\u0631 \u0628\u062f\u06a9"
    ],
    "wof:name":"Lar-e Badak",
    "wof:placetype":"locality"
},
  "geometry": {"coordinates":[68.45312,35.58212],"type":"Point"}
}