{
  "type": "Feature",
  "properties": {
    "gn:admin1_code":"37",
    "gn:admin2_code":"3212.0",
    "gn:asciiname":"A'i Khel",
    "gn:country_code":"AF",
    "gn:dem":2268,
    "gn:feature_class":"P",
    "gn:feature_code":"PPL",
    "gn:name":"\u0100\u2019\u012b Kh\u0113l",
    "gn:population":0,
    "gn:timezone":"Asia/Kabul",
    "iso:country":"AF",
    "name:fas_x_preferred":[
        "\u0639\u0644\u06cc \u062e\u064a\u0644"
    ],
    "name:rus_x_preferred":[
        "Aykhel\u2019"
    ],
    "name:und_x_variant":[
        "\u0100\u2019ikh\u0113l",
        "\u0100\u2019\u012b Kh\u0113l",
        "\u2018\u0100l\u012b Kheyl",
        "\u0622\u0626\u06cc \u062e\u06d0\u0644"
    ],
    "wof:name":"A'i Khel",
    "wof:placetype":"locality"
},
  "geometry": {"coordinates":[69.64145000000001,33.46722],"type":"Point"}
}