{
  "type": "Feature",
  "properties": {
    "gn:admin1_code":"34",
    "gn:admin2_code":"1005.0",
    "gn:asciiname":"Kirchigal Khune",
    "gn:country_code":"AF",
    "gn:dem":1761,
    "gn:feature_class":"P",
    "gn:feature_code":"PPL",
    "gn:name":"Kirch\u012bgal Kh\u016bn\u0113",
    "gn:population":0,
    "gn:timezone":"Asia/Kabul",
    "iso:country":"AF",
    "name:fas_x_preferred":[
        "\u0643\u0631\u0686\u06af\u0644 \u062e\u0648\u0646\u06cc"
    ],
    "name:rus_x_preferred":[
        "Kerchigal\u2019khune"
    ],
    "name:und_x_variant":[
        "Ker\u010digal Kh\u016bn\u0113",
        "Kerch\u012bgal Kh\u016bn\u0113",
        "Kerchigal Kh\u016bn\u0113",
        "Kirch\u012bgal Kh\u016bn\u0113",
        "\u06a9\u0631\u0686\u06cc\u06af\u0644 \u062e\u0648\u0646\u06d0"
    ],
    "wof:name":"Kirchigal Khune",
    "wof:placetype":"locality"
},
  "geometry": {"coordinates":[71.58834,35.22039],"type":"Point"}
}