{
  "type": "Feature",
  "properties": {
    "gn:admin1_code":"28",
    "gn:admin2_code":"2506.0",
    "gn:asciiname":"Haji Mayan Shah Kelay",
    "gn:country_code":"AF",
    "gn:dem":1299,
    "gn:feature_class":"P",
    "gn:feature_code":"PPL",
    "gn:name":"\u1e28\u0101j\u012b Mayan Sh\u0101h K\u00ealay",
    "gn:population":0,
    "gn:timezone":"Asia/Kabul",
    "iso:country":"AF",
    "name:und_x_variant":[
        "Khadzhimayanshakh-Kalay",
        "\u1e28\u0101ji Mayan Sh\u0101h Kalay",
        "H\u0101ji Mayan \u0160\u0101h Kalay",
        "\u062d\u0627\u062c\u06cc \u0645\u06cc\u0646 \u0634\u0627\u0647 \u06a9\u0644\u06cc",
        "\u1e28\u0101jj\u012b Mayan Sh\u0101h Kalay",
        "\u1e28\u0101j\u012b Mayan Sh\u0101h K\u00ealay"
    ],
    "wof:name":"Haji Mayan Shah Kelay",
    "wof:placetype":"locality"
},
  "geometry": {"coordinates":[66.41516999999999,31.82919],"type":"Point"}
}