{
  "type": "Feature",
  "properties": {
    "gn:admin1_code":"29",
    "gn:admin2_code":"2907",
    "gn:asciiname":"Dowlat Khowani",
    "gn:country_code":"AF",
    "gn:dem":2240,
    "gn:feature_class":"P",
    "gn:feature_code":"PPL",
    "gn:name":"Dowlat Khow\u0101n\u012b",
    "gn:population":0,
    "gn:timezone":"Asia/Kabul",
    "iso:country":"AF",
    "name:und_x_variant":[
        "Dowla\u1e6f Khaw\u0101n\u012b",
        "Daulat-Khavani",
        "\u1e0eawlat Khaw\u0101ni",
        "\u062f\u0648\u0644\u062a \u062e\u0648\u0627\u0646\u06cc",
        "Dowlat Khv\u0101n\u012b",
        "Dowlat Khow\u0101n\u012b"
    ],
    "wof:name":"Dowlat Khowani",
    "wof:placetype":"locality"
},
  "geometry": {"coordinates":[68.70469,32.87076],"type":"Point"}
}