{
  "type": "Feature",
  "properties": {
    "gn:admin1_code":"01",
    "gn:admin2_code":"1108.0",
    "gn:asciiname":"Rubabi",
    "gn:country_code":"AF",
    "gn:dem":1517,
    "gn:feature_class":"P",
    "gn:feature_code":"PPL",
    "gn:name":"Rub\u0101b\u012b",
    "gn:population":0,
    "gn:timezone":"Asia/Kabul",
    "iso:country":"AF",
    "name:und_x_variant":[
        "\u1e5eub\u0101bi",
        "\u0631\u0628\u0627\u0628\u06cc",
        "Rob\u0101b\u012b",
        "Rub\u0101b\u012b"
    ],
    "wof:name":"Rubabi",
    "wof:placetype":"locality"
},
  "geometry": {"coordinates":[70.90136,37.00875],"type":"Point"}
}