{
  "type": "Feature",
  "properties": {
    "gn:admin1_code":"08",
    "gn:admin2_code":"604",
    "gn:asciiname":"Qashkhal Beg",
    "gn:country_code":"AF",
    "gn:dem":3326,
    "gn:feature_class":"P",
    "gn:feature_code":"PPL",
    "gn:name":"Q\u0101shkh\u0101l B\u0113g",
    "gn:population":0,
    "gn:timezone":"Asia/Kabul",
    "iso:country":"AF",
    "name:fas_x_preferred":[
        "\u0642\u0627\u0634\u062e\u0627\u0644 \u0628\u064a\u06af"
    ],
    "name:fas_x_variant":[
        "\u0642\u0627\u0634 \u062e\u0627\u0644 \u0628\u064a\u06af"
    ],
    "name:rus_x_preferred":[
        "\u041a\u0430\u0448\u0445\u0430\u043b\u044c\u0431\u0435\u043a"
    ],
    "name:und_x_variant":[
        "Kashkhal\u2019bek",
        "Q\u0101\u0161kh\u0101lb\u0113g",
        "Q\u0101shkh\u0101lbeyg",
        "Q\u0101shkh\u0101l B\u0113g",
        "\u0642\u0627\u0634\u062e\u0627\u0644 \u0628\u06d0\u06af"
    ],
    "wof:name":"Qashkhal Beg",
    "wof:placetype":"locality"
},
  "geometry": {"coordinates":[67.99666999999999,33.71942],"type":"Point"}
}