{
  "type": "Feature",
  "properties": {
    "gn:admin1_code":"11",
    "gn:admin2_code":"2016.0",
    "gn:asciiname":"Darah-ye Jowal",
    "gn:country_code":"AF",
    "gn:dem":1324,
    "gn:feature_class":"P",
    "gn:feature_code":"PPL",
    "gn:name":"Darah-ye Jow\u0101l",
    "gn:population":0,
    "gn:timezone":"Asia/Kabul",
    "iso:country":"AF",
    "name:und_x_variant":[
        "Da\u1e5f\u1e5fah-i-Jow\u0101l",
        "Darah-ye Jow\u0101l",
        "\u062f\u0631\u06c0 \u062c\u0648\u0627\u0644",
        "Darreh-ye Jov\u0101l"
    ],
    "wof:name":"Darah-ye Jowal",
    "wof:placetype":"locality"
},
  "geometry": {"coordinates":[62.67966,34.72098],"type":"Point"}
}