{
  "type": "Feature",
  "properties": {
    "gn:admin1_code":"37",
    "gn:admin2_code":"3202.0",
    "gn:asciiname":"Ster Kelay",
    "gn:country_code":"AF",
    "gn:dem":1447,
    "gn:feature_class":"P",
    "gn:feature_code":"PPL",
    "gn:name":"St\u00ear K\u00ealay",
    "gn:population":0,
    "gn:timezone":"Asia/Kabul",
    "iso:country":"AF",
    "name:und_x_variant":[
        "Ste\u1e5f Kalay",
        "S\u1e5f\u0113h Kalay",
        "Sterkalay",
        "St\u0113r K\u00ealay",
        "Sur Kalay",
        "St\u00ear K\u00ealay",
        "\u0633\u062a\u0631 \u06a9\u0644\u06cc"
    ],
    "wof:name":"Ster Kelay",
    "wof:placetype":"locality"
},
  "geometry": {"coordinates":[70.08513000000001,33.60165],"type":"Point"}
}