{
  "type": "Feature",
  "properties": {
    "gn:admin1_code":"40",
    "gn:admin2_code":"307.0",
    "gn:asciiname":"Sumuchak",
    "gn:country_code":"AF",
    "gn:dem":2394,
    "gn:feature_class":"P",
    "gn:feature_code":"PPL",
    "gn:name":"Sum\u016bchak",
    "gn:population":0,
    "gn:timezone":"Asia/Kabul",
    "iso:country":"AF",
    "name:und_x_variant":[
        "Somu\u010dak",
        "Somochak",
        "Somuchak",
        "Sum\u016bchak",
        "\u0633\u0645\u0648\u0686\u06a9"
    ],
    "wof:name":"Sumuchak",
    "wof:placetype":"locality"
},
  "geometry": {"coordinates":[68.73976999999999,34.84536],"type":"Point"}
}