{
  "type": "Feature",
  "properties": {
    "gn:admin1_code":"08",
    "gn:admin2_code":"609",
    "gn:asciiname":"Hotak-e Sufla",
    "gn:country_code":"AF",
    "gn:dem":1934,
    "gn:feature_class":"P",
    "gn:feature_code":"PPL",
    "gn:name":"H\u014dtak-e Sufl\u00e1",
    "gn:population":0,
    "gn:timezone":"Asia/Kabul",
    "iso:country":"AF",
    "name:und_x_variant":[
        "Khotaki-Sufla",
        "H\u014dtke Sufl\u0101",
        "H\u014dtake Sufl\u0101",
        "H\u014dtak-e Sufl\u00e1",
        "\u0647\u0648\u062a\u06a9 \u0633\u0641\u0644\u0649",
        "H\u016btak-e Sofl\u00e1"
    ],
    "wof:name":"Hotak-e Sufla",
    "wof:placetype":"locality"
},
  "geometry": {"coordinates":[67.68680000000001,32.64068],"type":"Point"}
}