{
  "type": "Feature",
  "properties": {
    "gn:admin1_code":"5",
    "gn:admin2_code":"2805.0",
    "gn:asciiname":"Dahan-e Borughsanak",
    "gn:country_code":"AF",
    "gn:dem":2778,
    "gn:feature_class":"P",
    "gn:feature_code":"PPL",
    "gn:name":"Dahan-e B\u014dr\u016bghsanak",
    "gn:population":0,
    "gn:timezone":"Asia/Kabul",
    "iso:country":"AF",
    "name:und_x_variant":[
        "\u1e0eahane B\u014d\u1e5f\u016bghsanak",
        "Dakhani-Burugsanak",
        "Dahan-e Borowghsanak",
        "Dahan-e Bargh\u014d Sang",
        "Dahan-e B\u014dr\u016bghsanak",
        "\u062f\u0647\u0646 \u0628\u0648\u0631\u0648\u063a\u0633\u0646\u06a9",
        "Dahanah-ye B\u014dr\u016bghsang",
        "\u062f\u0647\u0646\u06c0 \u0628\u0648\u0631\u0648\u063a\u0633\u0646\u06af"
    ],
    "wof:name":"Dahan-e Borughsanak",
    "wof:placetype":"locality"
},
  "geometry": {"coordinates":[66.98874000000001,34.38912],"type":"Point"}
}