{
  "type": "Feature",
  "properties": {
    "gn:admin1_code":"41",
    "gn:admin2_code":"3408",
    "gn:asciiname":"Qurghan-e 'Ulya",
    "gn:country_code":"AF",
    "gn:dem":2454,
    "gn:feature_class":"P",
    "gn:feature_code":"PPL",
    "gn:name":"Qurgh\u0101n-e \u2018Uly\u0101",
    "gn:population":0,
    "gn:timezone":"Asia/Kabul",
    "iso:country":"AF",
    "name:und_x_variant":[
        "Kurgani-Ulia",
        "Qu\u1e5fgh\u0101ne \u2018Uly\u0101",
        "Qurgh\u0101n-e \u2018Oly\u0101",
        "Qurgh\u0101n-e \u2018Uly\u0101",
        "\u0642\u0631\u063a\u0627\u0646 \u0639\u0644\u064a\u0627"
    ],
    "wof:name":"Qurghan-e 'Ulya",
    "wof:placetype":"locality"
},
  "geometry": {"coordinates":[66.13621999999999,34.2636],"type":"Point"}
}