{
  "type": "Feature",
  "properties": {
    "gn:admin1_code":"8",
    "gn:admin2_code":"607.0",
    "gn:asciiname":"Baghuchar",
    "gn:country_code":"AF",
    "gn:dem":2805,
    "gn:feature_class":"P",
    "gn:feature_code":"PPL",
    "gn:name":"B\u0101gh\u016bch\u0101r",
    "gn:population":0,
    "gn:timezone":"Asia/Kabul",
    "iso:country":"AF",
    "name:und_x_variant":[
        "B\u0101gh\u016b\u010d\u0101r",
        "B\u0101gh\u016bch\u0101r",
        "\u0628\u0627\u063a\u0648\u0686\u0627\u0631"
    ],
    "wof:name":"Baghuchar",
    "wof:placetype":"locality"
},
  "geometry": {"coordinates":[67.45939,33.21938],"type":"Point"}
}