{
  "type": "Feature",
  "properties": {
    "gn:admin1_code":"37",
    "gn:admin2_code":"3201.0",
    "gn:asciiname":"Qal'ah-ye Hindu",
    "gn:country_code":"AF",
    "gn:dem":1161,
    "gn:feature_class":"P",
    "gn:feature_code":"PPL",
    "gn:name":"Qal\u2018ah-ye Hind\u016b",
    "gn:population":0,
    "gn:timezone":"Asia/Kabul",
    "iso:country":"AF",
    "name:fas_x_preferred":[
        "\u0642\u0644\u0626\u06c0 \u0647\u0646\u062f\u0648"
    ],
    "name:und_x_variant":[
        "Kalayi-Khundi",
        "Qal\u2019a-i-Hin\u1e0fu",
        "Qal\u2018ah-ye Hind\u016b",
        "Qal\u2019eh-ye Hend\u016b",
        "\u0642\u0644\u0639\u06c0 \u0647\u0646\u062f\u0648"
    ],
    "wof:name":"Qal'ah-ye Hindu",
    "wof:placetype":"locality"
},
  "geometry": {"coordinates":[69.93995,33.3366],"type":"Point"}
}