{
  "type": "Feature",
  "properties": {
    "gn:admin1_code":"27",
    "gn:admin2_code":"406",
    "gn:asciiname":"Topur",
    "gn:country_code":"AF",
    "gn:dem":2348,
    "gn:feature_class":"P",
    "gn:feature_code":"PPL",
    "gn:name":"Topur",
    "gn:population":0,
    "gn:timezone":"Asia/Kabul",
    "iso:country":"AF",
    "name:und_x_variant":[
        "T\u014dp\u016b\u1e5f",
        "T\u014dp\u016br",
        "Towp\u016br",
        "\u1e6e\u014dp\u016br",
        "\u067c\u0648\u067e\u0648\u0631",
        "Topur"
    ],
    "wof:name":"Topur",
    "wof:placetype":"locality"
},
  "geometry": {"coordinates":[68.50779,34.03655],"type":"Point"}
}