{
  "type": "Feature",
  "properties": {
    "gn:admin1_code":"02",
    "gn:admin2_code":"1903",
    "gn:asciiname":"Gumbaz",
    "gn:country_code":"AF",
    "gn:dem":1472,
    "gn:feature_class":"P",
    "gn:feature_code":"PPL",
    "gn:name":"Gumbaz\u0304",
    "gn:population":0,
    "gn:timezone":"Asia/Kabul",
    "iso:country":"AF",
    "name:fas_x_preferred":[
        "\u06af\u0645\u0628\u0627\u0632"
    ],
    "name:und_x_variant":[
        "Gumbaz\u0304",
        "Gumbaz",
        "Gumbat",
        "Gombaz\u0304",
        "\u06af\u0645\u0628\u0630",
        "Gonbaz\u0304"
    ],
    "wof:name":"Gumbaz",
    "wof:placetype":"locality"
},
  "geometry": {"coordinates":[63.7153,34.85336],"type":"Point"}
}