{
  "type": "Feature",
  "properties": {
    "gn:admin1_code":"27",
    "gn:admin2_code":"402",
    "gn:asciiname":"Khar Olang",
    "gn:country_code":"AF",
    "gn:dem":2401,
    "gn:feature_class":"P",
    "gn:feature_code":"PPL",
    "gn:name":"Khar \u014clang",
    "gn:population":0,
    "gn:timezone":"Asia/Kabul",
    "iso:country":"AF",
    "name:und_x_variant":[
        "Kharvalang",
        "Khar \u014clang",
        "Kharwalang",
        "\u062e\u0631 \u0627\u0648\u0644\u0646\u06af"
    ],
    "wof:name":"Khar Olang",
    "wof:placetype":"locality"
},
  "geometry": {"coordinates":[68.62439999999999,34.46593],"type":"Point"}
}