{
  "type": "Feature",
  "properties": {
    "gn:admin1_code":"33",
    "gn:admin2_code":"3103.0",
    "gn:asciiname":"Badkhanak",
    "gn:country_code":"AF",
    "gn:dem":2404,
    "gn:feature_class":"P",
    "gn:feature_code":"PPL",
    "gn:name":"B\u0101dkh\u0101nak",
    "gn:population":0,
    "gn:timezone":"Asia/Kabul",
    "iso:country":"AF",
    "name:und_x_variant":[
        "B\u0101dkh\u0101nak",
        "\u0628\u0627\u062f\u062e\u0627\u0646\u06a9",
        "B\u0101\u1e0fkh\u0101nak"
    ],
    "wof:name":"Badkhanak",
    "wof:placetype":"locality"
},
  "geometry": {"coordinates":[65.79781,35.53054],"type":"Point"}
}