{
  "type": "Feature",
  "properties": {
    "gn:admin1_code":"09",
    "gn:admin2_code":"2706",
    "gn:asciiname":"Kaj",
    "gn:country_code":"AF",
    "gn:dem":2202,
    "gn:feature_class":"P",
    "gn:feature_code":"PPL",
    "gn:name":"Kaj",
    "gn:population":0,
    "gn:timezone":"Asia/Kabul",
    "iso:country":"AF",
    "name:ceb_x_preferred":[
        "Kaj"
    ],
    "name:dan_x_preferred":[
        "Kaj"
    ],
    "name:pol_x_preferred":[
        "Kaj"
    ],
    "name:swe_x_preferred":[
        "Kaj"
    ],
    "name:und_x_variant":[
        "\u06a9\u062c"
    ],
    "wof:name":"Kaj",
    "wof:placetype":"locality"
},
  "geometry": {"coordinates":[65.29527,33.75653],"type":"Point"}
}