{
  "type": "Feature",
  "properties": {
    "gn:admin1_code":"18",
    "gn:admin2_code":"822.0",
    "gn:asciiname":"Sayyid Ahmad Khel",
    "gn:country_code":"AF",
    "gn:dem":928,
    "gn:feature_class":"P",
    "gn:feature_code":"PPL",
    "gn:name":"Sayyid A\u1e29mad Kh\u0113l",
    "gn:population":0,
    "gn:timezone":"Asia/Kabul",
    "iso:country":"AF",
    "name:fas_x_preferred":[
        "\u0633\u064a\u062f \u0627\u062d\u0645\u062f \u062e\u064a\u0644"
    ],
    "name:rus_x_preferred":[
        "Saidakhmedkheyl\u2019"
    ],
    "name:und_x_variant":[
        "Say\u1e0fa\u1e29ma\u1e0fkh\u0113l",
        "Seyyeda\u1e29madkheyl",
        "Sayyid A\u1e29mad Kh\u0113l",
        "\u0633\u06cc\u062f \u0627\u062d\u0645\u062f \u062e\u06d0\u0644"
    ],
    "wof:name":"Sayyid Ahmad Khel",
    "wof:placetype":"locality"
},
  "geometry": {"coordinates":[70.59621,34.14051],"type":"Point"}
}