{
  "type": "Feature",
  "properties": {
    "gn:admin1_code":"23",
    "gn:admin2_code":"2412.0",
    "gn:asciiname":"Alghamchi",
    "gn:country_code":"AF",
    "gn:dem":1461,
    "gn:feature_class":"P",
    "gn:feature_code":"PPL",
    "gn:name":"Alghamch\u012b",
    "gn:population":0,
    "gn:timezone":"Asia/Kabul",
    "iso:country":"AF",
    "name:und_x_variant":[
        "Algham\u010di",
        "Al\u2019gamchi",
        "Alghamch\u012b",
        "\u0627\u0644\u063a\u0645\u0686\u06cc",
        "Alghamchi"
    ],
    "wof:name":"Alghamchi",
    "wof:placetype":"locality"
},
  "geometry": {"coordinates":[66.75053,31.64142],"type":"Point"}
}