{
  "type": "Feature",
  "properties": {
    "gn:admin1_code":"28",
    "gn:admin2_code":"2509",
    "gn:asciiname":"Loy Kelay",
    "gn:country_code":"AF",
    "gn:dem":2083,
    "gn:feature_class":"P",
    "gn:feature_code":"PPL",
    "gn:name":"L\u014dy K\u00ealay",
    "gn:population":0,
    "gn:timezone":"Asia/Kabul",
    "iso:country":"AF",
    "name:und_x_variant":[
        "L\u014dy Kalay",
        "L\u014dy K\u00ealay",
        "\u0644\u0648\u06cc \u06a9\u0644\u06cc",
        "L\u016by Kalay"
    ],
    "wof:name":"Loy Kelay",
    "wof:placetype":"locality"
},
  "geometry": {"coordinates":[67.65803000000001,32.00785],"type":"Point"}
}