{
  "type": "Feature",
  "properties": {
    "gn:admin1_code":"27",
    "gn:admin2_code":"403",
    "gn:asciiname":"Otopur",
    "gn:country_code":"AF",
    "gn:dem":3080,
    "gn:feature_class":"P",
    "gn:feature_code":"PPL",
    "gn:name":"Otopur",
    "gn:population":0,
    "gn:timezone":"Asia/Kabul",
    "iso:country":"AF",
    "name:und_x_variant":[
        "\u014ct\u014dp\u016b\u1e5f",
        "Otopur",
        "Owtowp\u016br",
        "Wotahp\u016br",
        "\u014ct\u014dp\u016br",
        "\u0627\u0648\u062a\u0648\u067e\u0648\u0631"
    ],
    "wof:name":"Otopur",
    "wof:placetype":"locality"
},
  "geometry": {"coordinates":[68.07933,34.44453],"type":"Point"}
}