{
  "type": "Feature",
  "properties": {
    "gn:admin1_code":"11",
    "gn:admin2_code":"2015",
    "gn:asciiname":"Nurianah",
    "gn:country_code":"AF",
    "gn:dem":2511,
    "gn:feature_class":"P",
    "gn:feature_code":"PPL",
    "gn:name":"N\u016br\u012b\u0101nah",
    "gn:population":0,
    "gn:timezone":"Asia/Kabul",
    "iso:country":"AF",
    "name:und_x_variant":[
        "N\u016bry\u0101na",
        "N\u016br\u012b\u0101nah",
        "\u0646\u0648\u0631\u06cc\u0627\u0646\u0647",
        "N\u016bry\u0101nah"
    ],
    "wof:name":"Nurianah",
    "wof:placetype":"locality"
},
  "geometry": {"coordinates":[64.29324,34.54832],"type":"Point"}
}