{
  "type": "Feature",
  "properties": {
    "gn:admin1_code":"06",
    "gn:admin2_code":"2111",
    "gn:asciiname":"De Hindu Qal'ah",
    "gn:country_code":"AF",
    "gn:dem":671,
    "gn:feature_class":"P",
    "gn:feature_code":"PPL",
    "gn:name":"D\u00ea Hind\u016b Qal\u2018ah",
    "gn:population":0,
    "gn:timezone":"Asia/Kabul",
    "iso:country":"AF",
    "name:und_x_variant":[
        "Khindukala",
        "\u1e0ee Hen\u1e0f\u016b Qal\u2018a",
        "De Hend\u016b Qal\u2018eh",
        "D\u00ea Hind\u016b Qal\u2018ah",
        "\u062f \u0647\u0646\u062f\u0648 \u0642\u0644\u0639\u0647"
    ],
    "wof:name":"De Hindu Qal'ah",
    "wof:placetype":"locality"
},
  "geometry": {"coordinates":[62.06613,32.55963],"type":"Point"}
}