{
  "type": "Feature",
  "properties": {
    "gn:admin1_code":"05",
    "gn:admin2_code":"2805",
    "gn:asciiname":"Petab wa Kachari",
    "gn:country_code":"AF",
    "gn:dem":2699,
    "gn:feature_class":"P",
    "gn:feature_code":"PPL",
    "gn:name":"P\u0113t\u0101b wa Kach\u0101r\u012b",
    "gn:population":0,
    "gn:timezone":"Asia/Kabul",
    "iso:country":"AF",
    "name:und_x_variant":[
        "Petav-va-Kachari",
        "P\u012bt\u0101b va Kach\u0101r\u012b",
        "P\u0113t\u0101b wa Ka\u010d\u0101ri",
        "P\u0113t\u0101b wa Kach\u0101r\u012b",
        "\u067e\u06cc\u062a\u0627\u0628 \u0648 \u06a9\u0686\u0627\u0631\u06cc",
        "P\u0113t\u0101b wah Kach\u0101r\u012b"
    ],
    "wof:name":"Petab wa Kachari",
    "wof:placetype":"locality"
},
  "geometry": {"coordinates":[66.74113,34.32189],"type":"Point"}
}