{
  "type": "Feature",
  "properties": {
    "gn:admin1_code":"32",
    "gn:admin2_code":"1503",
    "gn:asciiname":"Qara'i",
    "gn:country_code":"AF",
    "gn:dem":1682,
    "gn:feature_class":"P",
    "gn:feature_code":"PPL",
    "gn:name":"Qara\u2019\u012b",
    "gn:population":0,
    "gn:timezone":"Asia/Kabul",
    "iso:country":"AF",
    "name:und_x_variant":[
        "Qara\u2019\u012b",
        "\u0642\u0631\u0626\u06cc",
        "Qa\u1e5fa\u2018i"
    ],
    "wof:name":"Qara'i",
    "wof:placetype":"locality"
},
  "geometry": {"coordinates":[67.32503,35.82865],"type":"Point"}
}