{
  "type": "Feature",
  "properties": {
    "gn:admin1_code":"34",
    "gn:admin2_code":"1003.0",
    "gn:asciiname":"Pitaw Kelay",
    "gn:country_code":"AF",
    "gn:dem":1835,
    "gn:feature_class":"P",
    "gn:feature_code":"PPL",
    "gn:name":"Pit\u0101w K\u00ealay",
    "gn:population":0,
    "gn:timezone":"Asia/Kabul",
    "iso:country":"AF",
    "name:fas_x_preferred":[
        "\u0642\u0631\u064a\u06c0 \u067e\u062a\u0627\u0648"
    ],
    "name:und_x_variant":[
        "Petaukalay",
        "P\u0113t\u0101w Kalay",
        "\u067e\u062a\u0627\u0648 \u06a9\u0644\u06cc",
        "P\u012bt\u0101w Kalay",
        "Pit\u0101w K\u00ealay"
    ],
    "wof:name":"Pitaw Kelay",
    "wof:placetype":"locality"
},
  "geometry": {"coordinates":[71.44303000000002,35.0671],"type":"Point"}
}