{
  "type": "Feature",
  "properties": {
    "gn:admin1_code":"9",
    "gn:admin2_code":"2703.0",
    "gn:asciiname":"Dahan-e Kuhnah",
    "gn:country_code":"AF",
    "gn:dem":2408,
    "gn:feature_class":"P",
    "gn:feature_code":"PPL",
    "gn:name":"Dah\u0101n-e Kuhnah",
    "gn:population":0,
    "gn:timezone":"Asia/Kabul",
    "iso:country":"AF",
    "name:und_x_variant":[
        "Dahane Kuhna",
        "Dah\u0101n-e Kuhnah",
        "\u062f\u0647\u0627\u0646 \u06a9\u0647\u0646\u0647",
        "Dahan-e Kohneh"
    ],
    "wof:name":"Dahan-e Kuhnah",
    "wof:placetype":"locality"
},
  "geometry": {"coordinates":[63.96515,34.00319],"type":"Point"}
}