{
  "type": "Feature",
  "properties": {
    "gn:admin1_code":"13",
    "gn:admin2_code":"112.0",
    "gn:asciiname":"Qaysar Kelay",
    "gn:country_code":"AF",
    "gn:dem":1060,
    "gn:feature_class":"P",
    "gn:feature_code":"PPL",
    "gn:name":"Qay\u015far K\u00ealay",
    "gn:population":0,
    "gn:timezone":"Asia/Kabul",
    "iso:country":"AF",
    "name:und_x_variant":[
        "Qay\u015far K\u00ealay",
        "\u0642\u06cc\u0635\u0631 \u06a9\u0644\u06cc"
    ],
    "wof:name":"Qaysar Kelay",
    "wof:placetype":"locality"
},
  "geometry": {"coordinates":[69.66914,34.61205],"type":"Point"}
}