{
  "type": "Feature",
  "properties": {
    "gn:admin1_code":"17",
    "gn:admin2_code":"505.0",
    "gn:asciiname":"Dardar",
    "gn:country_code":"AF",
    "gn:dem":2021,
    "gn:feature_class":"P",
    "gn:feature_code":"PPL",
    "gn:name":"Dardar",
    "gn:population":0,
    "gn:timezone":"Asia/Kabul",
    "iso:country":"AF",
    "name:und_x_variant":[
        "Razvaliny Dardar",
        "Dardar",
        "\u062f\u0631\u062f\u0631"
    ],
    "wof:name":"Dardar",
    "wof:placetype":"locality"
},
  "geometry": {"coordinates":[69.17941,34.12219],"type":"Point"}
}