{
  "type": "Feature",
  "properties": {
    "gn:admin1_code":"6",
    "gn:admin2_code":"2104.0",
    "gn:asciiname":"Ab Mazar",
    "gn:country_code":"AF",
    "gn:dem":1884,
    "gn:feature_class":"P",
    "gn:feature_code":"PPL",
    "gn:name":"\u0100b Maz\u0101r",
    "gn:population":0,
    "gn:timezone":"Asia/Kabul",
    "iso:country":"AF",
    "name:fas_x_preferred":[
        "\u0622\u0628\u200c\u0645\u0632\u0627\u0631"
    ],
    "name:und_x_variant":[
        "\u0100b Maz\u0101r"
    ],
    "name:urd_x_preferred":[
        "\u0622\u0628 \u0645\u0632\u0627\u0631"
    ],
    "wof:name":"Ab Mazar",
    "wof:placetype":"locality"
},
  "geometry": {"coordinates":[63.7647,33.34353],"type":"Point"}
}