{
  "type": "Feature",
  "properties": {
    "gn:admin1_code":"8",
    "gn:admin2_code":"607.0",
    "gn:asciiname":"Aghel-e Mulla",
    "gn:country_code":"AF",
    "gn:dem":2414,
    "gn:feature_class":"P",
    "gn:feature_code":"PPL",
    "gn:name":"\u0100gh\u0113l-e Mull\u0101",
    "gn:population":0,
    "gn:timezone":"Asia/Kabul",
    "iso:country":"AF",
    "name:und_x_variant":[
        "\u0100gh\u0113le Mol\u0101",
        "Ageli-Mulla",
        "\u0100gh\u0113l-e Mull\u0101",
        "\u0622\u063a\u06d0\u0644 \u0645\u0644\u0627",
        "\u0100ghel-e Moll\u0101"
    ],
    "wof:name":"Aghel-e Mulla",
    "wof:placetype":"locality"
},
  "geometry": {"coordinates":[67.52095,32.93376],"type":"Point"}
}