{
  "type": "Feature",
  "properties": {
    "gn:admin1_code":"32",
    "gn:admin2_code":"1504.0",
    "gn:asciiname":"Kochah Ariq",
    "gn:country_code":"AF",
    "gn:dem":1257,
    "gn:feature_class":"P",
    "gn:feature_code":"PPL",
    "gn:name":"K\u014dchah \u0100r\u012bq",
    "gn:population":0,
    "gn:timezone":"Asia/Kabul",
    "iso:country":"AF",
    "name:und_x_variant":[
        "K\u014dchah \u0100r\u012bq",
        "\u06a9\u0648\u0686\u0647 \u0622\u0631\u06cc\u0642"
    ],
    "wof:name":"Kochah Ariq",
    "wof:placetype":"locality"
},
  "geometry": {"coordinates":[67.22495000000001,36.09942],"type":"Point"}
}