{
  "type": "Feature",
  "properties": {
    "gn:admin1_code":"05",
    "gn:admin2_code":"2805",
    "gn:asciiname":"Gumab",
    "gn:country_code":"AF",
    "gn:dem":2732,
    "gn:feature_class":"P",
    "gn:feature_code":"PPL",
    "gn:name":"Gum\u0101b",
    "gn:population":0,
    "gn:timezone":"Asia/Kabul",
    "iso:country":"AF",
    "name:und_x_variant":[
        "Gum\u0101w",
        "Gumau",
        "Gum\u0101b",
        "\u06af\u0645\u0622\u0628"
    ],
    "wof:name":"Gumab",
    "wof:placetype":"locality"
},
  "geometry": {"coordinates":[66.50924999999999,34.2762],"type":"Point"}
}