{
  "type": "Feature",
  "properties": {
    "gn:admin1_code":"29",
    "gn:admin2_code":"2911.0",
    "gn:asciiname":"Zarin Kot",
    "gn:country_code":"AF",
    "gn:dem":2158,
    "gn:feature_class":"P",
    "gn:feature_code":"PPL",
    "gn:name":"Zar\u012bn K\u014d\u1e6f",
    "gn:population":0,
    "gn:timezone":"Asia/Kabul",
    "iso:country":"AF",
    "name:und_x_variant":[
        "Za\u1e5f\u012bn K\u014dt",
        "Zarinkot",
        "Zarr\u012bn Kowt",
        "Zar\u012bn K\u014d\u1e6f",
        "\u0632\u0631\u06cc\u0646 \u06a9\u0648\u067c"
    ],
    "wof:name":"Zarin Kot",
    "wof:placetype":"locality"
},
  "geometry": {"coordinates":[69.24647,32.94357],"type":"Point"}
}