{
  "type": "Feature",
  "properties": {
    "gn:admin1_code":"28",
    "gn:admin2_code":"2503",
    "gn:asciiname":"Mali Khel",
    "gn:country_code":"AF",
    "gn:dem":1647,
    "gn:feature_class":"P",
    "gn:feature_code":"PPL",
    "gn:name":"Mal\u012b Kh\u0113l",
    "gn:population":0,
    "gn:timezone":"Asia/Kabul",
    "iso:country":"AF",
    "name:fas_x_preferred":[
        "\u0645\u0644\u06cc \u062e\u064a\u0644"
    ],
    "name:und_x_variant":[
        "Malikh\u0113l",
        "Mal\u012b Kh\u0113l",
        "\u0645\u0644\u06cc \u062e\u06d0\u0644",
        "Mal\u012b Kheyl"
    ],
    "wof:name":"Mali Khel",
    "wof:placetype":"locality"
},
  "geometry": {"coordinates":[66.97532,32.53391],"type":"Point"}
}