{
  "type": "Feature",
  "properties": {
    "gn:admin1_code":"01",
    "gn:admin2_code":"1109",
    "gn:asciiname":"Ghar Jawin",
    "gn:country_code":"AF",
    "gn:dem":2869,
    "gn:feature_class":"P",
    "gn:feature_code":"PPL",
    "gn:name":"Gh\u0101r Jaw\u012bn",
    "gn:population":0,
    "gn:timezone":"Asia/Kabul",
    "iso:country":"AF",
    "name:por_x_preferred":[
        "Ghar Javin"
    ],
    "name:und_x_variant":[
        "Garjw\u0101n",
        "Gh\u0101\u1e5f Jaw\u012bn",
        "Garjiwan",
        "Gh\u0101r Jabin",
        "Gh\u0101r Jav\u012bn",
        "Gh\u0101r Jaw\u012bn",
        "\u063a\u0627\u0631 \u062c\u0648\u06cc\u0646"
    ],
    "wof:name":"Ghar Jawin",
    "wof:placetype":"locality"
},
  "geometry": {"coordinates":[71.44401999999999,37.47818],"type":"Point"}
}