{
  "type": "Feature",
  "properties": {
    "gn:admin1_code":"30",
    "gn:admin2_code":"1603.0",
    "gn:asciiname":"Koh-e Talak",
    "gn:country_code":"AF",
    "gn:dem":2227,
    "gn:feature_class":"P",
    "gn:feature_code":"PPL",
    "gn:name":"K\u014dh-e Talak",
    "gn:population":0,
    "gn:timezone":"Asia/Kabul",
    "iso:country":"AF",
    "name:und_x_variant":[
        "Kohe Talak",
        "K\u016bh-e Talak",
        "K\u014dh-e Talak",
        "\u06a9\u0648\u0647 \u062a\u0644\u06a9"
    ],
    "wof:name":"Koh-e Talak",
    "wof:placetype":"locality"
},
  "geometry": {"coordinates":[66.76720999999999,35.77757000000001],"type":"Point"}
}