{
  "type": "Feature",
  "properties": {
    "gn:admin1_code":"8",
    "gn:admin2_code":"601.0",
    "gn:asciiname":"Qal'ah-ye Sher Muhammad Khan",
    "gn:country_code":"AF",
    "gn:dem":2123,
    "gn:feature_class":"P",
    "gn:feature_code":"PPL",
    "gn:name":"Qal\u2018ah-ye Sh\u0113r Mu\u1e29ammad Kh\u0101n",
    "gn:population":0,
    "gn:timezone":"Asia/Kabul",
    "iso:country":"AF",
    "name:fas_x_preferred":[
        "\u0642\u0644\u0639\u0647\u0654 \u0634\u064a\u0631 \u0645\u062d\u0645\u062f \u062e\u0627\u0646"
    ],
    "name:und_x_variant":[
        "Kalayi-Shermukhammedkhan",
        "Qal\u2018a-i-\u0160\u0113rmohammed-kh\u0101n",
        "Qal\u2018a-i-S\u0113\u1e5fmohamma\u1e0f-kh\u0101n",
        "Qal\u2018ah-ye Shayr Mu\u1e29ammad Kh\u0101n",
        "Qal\u2018eh-ye Sh\u012br Mo\u1e29ammad Kh\u0101n",
        "Qal\u2018ah-ye Sh\u0113r Mu\u1e29ammad Kh\u0101n",
        "\u0642\u0644\u0639\u0647 \u0634\u06d0\u0631 \u0645\u062d\u0645\u062f \u062e\u0627\u0646"
    ],
    "wof:name":"Qal'ah-ye Sher Muhammad Khan",
    "wof:placetype":"locality"
},
  "geometry": {"coordinates":[68.48253000000001,33.45772],"type":"Point"}
}