{
  "type": "Feature",
  "properties": {
    "gn:admin1_code":"28",
    "gn:admin2_code":"2509",
    "gn:asciiname":"Iraki",
    "gn:country_code":"AF",
    "gn:dem":2142,
    "gn:feature_class":"P",
    "gn:feature_code":"PPL",
    "gn:name":"Iraki",
    "gn:population":0,
    "gn:timezone":"Asia/Kabul",
    "iso:country":"AF",
    "name:und_x_variant":[
        "\u2018Ir\u0101q\u012b",
        "\u2018E\u1e5f\u0101qi"
    ],
    "wof:name":"Iraki",
    "wof:placetype":"locality"
},
  "geometry": {"coordinates":[67.56860999999999,31.61028],"type":"Point"}
}