{
  "type": "Feature",
  "properties": {
    "gn:admin1_code":"06",
    "gn:admin2_code":"2104",
    "gn:asciiname":"Nalows",
    "gn:country_code":"AF",
    "gn:dem":1991,
    "gn:feature_class":"P",
    "gn:feature_code":"PPL",
    "gn:name":"Nalows",
    "gn:population":0,
    "gn:timezone":"Asia/Kabul",
    "iso:country":"AF",
    "name:und_x_variant":[
        "\u0646\u0644\u0648\u0633",
        "Nalaws"
    ],
    "wof:name":"Nalows",
    "wof:placetype":"locality"
},
  "geometry": {"coordinates":[63.57331,33.37518],"type":"Point"}
}