{
  "type": "Feature",
  "properties": {
    "gn:admin1_code":"08",
    "gn:admin2_code":"614",
    "gn:asciiname":"Muchun Khel",
    "gn:country_code":"AF",
    "gn:dem":2097,
    "gn:feature_class":"P",
    "gn:feature_code":"PPL",
    "gn:name":"Much\u016bn Kh\u0113l",
    "gn:population":0,
    "gn:timezone":"Asia/Kabul",
    "iso:country":"AF",
    "name:fas_x_preferred":[
        "\u0645\u0686\u0648\u0646 \u062e\u064a\u0644"
    ],
    "name:rus_x_preferred":[
        "Muchunkheyl\u2019"
    ],
    "name:und_x_variant":[
        "Mo\u010dunkh\u0113l",
        "Moch\u016bn Kh\u0113l",
        "Moch\u016bn Kheyl",
        "Much\u016bn Kh\u0113l",
        "\u0645\u0686\u0648\u0646 \u062e\u06d0\u0644"
    ],
    "wof:name":"Muchun Khel",
    "wof:placetype":"locality"
},
  "geometry": {"coordinates":[68.39213000000001,33.40192],"type":"Point"}
}