{
  "type": "Feature",
  "properties": {
    "gn:admin1_code":"8",
    "gn:admin2_code":"614.0",
    "gn:asciiname":"'Ali Beg",
    "gn:country_code":"AF",
    "gn:dem":2089,
    "gn:feature_class":"P",
    "gn:feature_code":"PPL",
    "gn:name":"\u2018Al\u012b B\u0113g",
    "gn:population":0,
    "gn:timezone":"Asia/Kabul",
    "iso:country":"AF",
    "name:fas_x_preferred":[
        "\u0639\u0644\u06cc \u0628\u064a\u06af"
    ],
    "name:und_x_variant":[
        "Alibek",
        "\u2018Alib\u0113g",
        "\u2018Al\u012b B\u0113g",
        "\u2018Al\u012b Beyg"
    ],
    "wof:name":"'Ali Beg",
    "wof:placetype":"locality"
},
  "geometry": {"coordinates":[68.41459,33.37276],"type":"Point"}
}