{
  "type": "Feature",
  "properties": {
    "gn:admin1_code":"28",
    "gn:admin2_code":"2510",
    "gn:asciiname":"'Ulum-e Lala Kelay",
    "gn:country_code":"AF",
    "gn:dem":2536,
    "gn:feature_class":"P",
    "gn:feature_code":"PPL",
    "gn:name":"\u2018Ul\u016bm-e L\u0101l\u0101 K\u00ealay",
    "gn:population":0,
    "gn:timezone":"Asia/Kabul",
    "iso:country":"AF",
    "name:und_x_variant":[
        "Ulumi-Lalakalay",
        "\u2018Ul\u016bm-e L\u0101l\u0101 K\u00ealay",
        "\u0639\u0644\u0648\u0645 \u0644\u0627\u0644\u0627 \u06a9\u0644\u06cc",
        "\u2018Ol\u016bm-e L\u0101l\u0101 Kalay"
    ],
    "wof:name":"'Ulum-e Lala Kelay",
    "wof:placetype":"locality"
},
  "geometry": {"coordinates":[67.11246,32.87262],"type":"Point"}
}