{
  "type": "Feature",
  "properties": {
    "gn:admin1_code":"28",
    "gn:admin2_code":"2509.0",
    "gn:asciiname":"Baso Khel Wulah",
    "gn:country_code":"AF",
    "gn:dem":2268,
    "gn:feature_class":"P",
    "gn:feature_code":"PPL",
    "gn:name":"Bas\u014d Kh\u0113l Wulah",
    "gn:population":0,
    "gn:timezone":"Asia/Kabul",
    "iso:country":"AF",
    "name:rus_x_preferred":[
        "Basokheyl\u2019vula"
    ],
    "name:und_x_variant":[
        "Bas\u014dkh\u0113l Wola",
        "Bas\u014d Kh\u0113l Walah",
        "Basowkheyl Wolah",
        "Bas\u014d Kh\u0113l Wulah",
        "\u0628\u0633\u0648 \u062e\u06d0\u0644 \u0648\u0644\u0647"
    ],
    "wof:name":"Baso Khel Wulah",
    "wof:placetype":"locality"
},
  "geometry": {"coordinates":[67.92115,31.94576],"type":"Point"}
}