{
  "type": "Feature",
  "properties": {
    "gn:admin1_code":"18",
    "gn:admin2_code":"820.0",
    "gn:asciiname":"Gorkhal",
    "gn:country_code":"AF",
    "gn:dem":1331,
    "gn:feature_class":"P",
    "gn:feature_code":"PPL",
    "gn:name":"G\u014drkhal",
    "gn:population":0,
    "gn:timezone":"Asia/Kabul",
    "iso:country":"AF",
    "name:und_x_variant":[
        "G\u014d\u1e5fkhal",
        "G\u016b\u1e5fkhal",
        "G\u014drkhal",
        "\u06af\u0648\u0631\u062e\u0644",
        "K\u014drkhal",
        "\u06a9\u0648\u0631\u062e\u0644"
    ],
    "wof:name":"Gorkhal",
    "wof:placetype":"locality"
},
  "geometry": {"coordinates":[70.55819,34.71159],"type":"Point"}
}