{
  "type": "Feature",
  "properties": {
    "gn:admin1_code":"9",
    "gn:admin2_code":"2707.0",
    "gn:asciiname":"Kazim",
    "gn:country_code":"AF",
    "gn:dem":2734,
    "gn:feature_class":"P",
    "gn:feature_code":"PPL",
    "gn:name":"K\u0101z\u0327im",
    "gn:population":0,
    "gn:timezone":"Asia/Kabul",
    "iso:country":"AF",
    "name:und_x_variant":[
        "K\u0101z\u0327em",
        "K\u0101z\u0327im",
        "\u06a9\u0627\u0638\u0645"
    ],
    "wof:name":"Kazim",
    "wof:placetype":"locality"
},
  "geometry": {"coordinates":[66.17506999999999,34.62421],"type":"Point"}
}