{
  "type": "Feature",
  "properties": {
    "gn:admin1_code":"03",
    "gn:admin2_code":"1301",
    "gn:asciiname":"Qazaq",
    "gn:country_code":"AF",
    "gn:dem":586,
    "gn:feature_class":"P",
    "gn:feature_code":"PPL",
    "gn:name":"Qaz\u0101q",
    "gn:population":0,
    "gn:timezone":"Asia/Kabul",
    "iso:country":"AF",
    "name:rus_x_preferred":[
        "\u041a\u0430\u0437\u0430\u043a"
    ],
    "name:swe_x_preferred":[
        "Qazaq"
    ],
    "name:und_x_variant":[
        "Qaz\u0101q",
        "Kazak",
        "Qazz\u0101q",
        "\u0642\u0632\u0627\u0642"
    ],
    "wof:name":"Qazaq",
    "wof:placetype":"locality"
},
  "geometry": {"coordinates":[68.65057,36.02648],"type":"Point"}
}