{
  "type": "Feature",
  "properties": {
    "gn:admin1_code":"41",
    "gn:admin2_code":"3407",
    "gn:asciiname":"Siyah Qol",
    "gn:country_code":"AF",
    "gn:dem":3261,
    "gn:feature_class":"P",
    "gn:feature_code":"PPL",
    "gn:name":"Siy\u0101h Q\u014dl",
    "gn:population":0,
    "gn:timezone":"Asia/Kabul",
    "iso:country":"AF",
    "name:und_x_variant":[
        "Shy\u0101hq\u014dl",
        "Sy\u0101hq\u014dl",
        "S\u012b\u0101h Q\u014dl",
        "S\u012b\u0101h Qowl",
        "Siy\u0101h Q\u014dl",
        "\u0633\u064a\u0627\u0647 \u0642\u0648\u0644"
    ],
    "wof:name":"Siyah Qol",
    "wof:placetype":"locality"
},
  "geometry": {"coordinates":[66.76971999999999,33.98637],"type":"Point"}
}