{
  "type": "Feature",
  "properties": {
    "gn:admin1_code":"9",
    "gn:admin2_code":"2707.0",
    "gn:asciiname":"Munar",
    "gn:country_code":"AF",
    "gn:dem":2900,
    "gn:feature_class":"P",
    "gn:feature_code":"PPL",
    "gn:name":"Mun\u0101r",
    "gn:population":0,
    "gn:timezone":"Asia/Kabul",
    "iso:country":"AF",
    "name:und_x_variant":[
        "Mon\u0101\u1e5f",
        "Men\u0101r",
        "Mun\u0101r",
        "\u0645\u0646\u0627\u0631"
    ],
    "wof:name":"Munar",
    "wof:placetype":"locality"
},
  "geometry": {"coordinates":[66.1052,34.53285],"type":"Point"}
}