{
  "type": "Feature",
  "properties": {
    "gn:admin1_code":"9",
    "gn:admin2_code":"2706.0",
    "gn:asciiname":"Chaghan",
    "gn:country_code":"AF",
    "gn:dem":2219,
    "gn:feature_class":"P",
    "gn:feature_code":"PPL",
    "gn:name":"Ch\u0101gh\u0101n",
    "gn:population":0,
    "gn:timezone":"Asia/Kabul",
    "iso:country":"AF",
    "name:fas_x_preferred":[
        "\u0686\u063a\u0627\u0646"
    ],
    "name:msa_x_preferred":[
        "Chaghan"
    ],
    "name:und_x_variant":[
        "\u1e0c\u0101gh\u0101n",
        "Ch\u0101gh\u0101n",
        "\u0686\u0627\u063a\u0627\u0646"
    ],
    "wof:name":"Chaghan",
    "wof:placetype":"locality"
},
  "geometry": {"coordinates":[65.61865999999999,33.68718],"type":"Point"}
}