{
  "type": "Feature",
  "properties": {
    "gn:admin1_code":"41",
    "gn:admin2_code":"3409",
    "gn:asciiname":"Jowz",
    "gn:country_code":"AF",
    "gn:dem":2488,
    "gn:feature_class":"P",
    "gn:feature_code":"PPL",
    "gn:name":"Jowz",
    "gn:population":0,
    "gn:timezone":"Asia/Kabul",
    "iso:country":"AF",
    "name:ara_x_preferred":[
        "\u062c\u0648\u0632"
    ],
    "name:ceb_x_preferred":[
        "Jowz"
    ],
    "name:fas_x_preferred":[
        "\u062c\u0648\u0632"
    ],
    "name:swe_x_preferred":[
        "Jowz"
    ],
    "name:und_x_variant":[
        "Jawz"
    ],
    "wof:name":"Jowz",
    "wof:placetype":"locality"
},
  "geometry": {"coordinates":[66.4645,33.81089],"type":"Point"}
}