{
  "type": "Feature",
  "properties": {
    "gn:admin1_code":"05",
    "gn:admin2_code":"2806",
    "gn:asciiname":"Pusht-e Barghasu",
    "gn:country_code":"AF",
    "gn:dem":3043,
    "gn:feature_class":"P",
    "gn:feature_code":"PPL",
    "gn:name":"Pusht-e Barghas\u016b",
    "gn:population":0,
    "gn:timezone":"Asia/Kabul",
    "iso:country":"AF",
    "name:und_x_variant":[
        "Pushti-Bargasu",
        "Pu\u0161te Barghasu",
        "Pusht-e Barghahs\u016b",
        "Pusht-e Barghas\u016b",
        "\u067e\u0634\u062a \u0628\u0631\u063a\u0633\u0648"
    ],
    "wof:name":"Pusht-e Barghasu",
    "wof:placetype":"locality"
},
  "geometry": {"coordinates":[66.67539000000001,34.00553],"type":"Point"}
}