{
  "type": "Feature",
  "properties": {
    "gn:admin1_code":"41",
    "gn:admin2_code":"3409",
    "gn:asciiname":"Karez",
    "gn:country_code":"AF",
    "gn:dem":2682,
    "gn:feature_class":"P",
    "gn:feature_code":"PPL",
    "gn:name":"K\u0101r\u0113z",
    "gn:population":0,
    "gn:timezone":"Asia/Kabul",
    "iso:country":"AF",
    "name:und_x_variant":[
        "K\u0101\u1e5f\u0113z",
        "K\u0101r\u012bz",
        "K\u0101r\u0113z",
        "\u06a9\u0627\u0631\u06d0\u0632"
    ],
    "wof:name":"Karez",
    "wof:placetype":"locality"
},
  "geometry": {"coordinates":[66.37459,33.72971],"type":"Point"}
}