{
  "type": "Feature",
  "properties": {
    "gn:admin1_code":"06",
    "gn:admin2_code":"2105",
    "gn:asciiname":"Tapah",
    "gn:country_code":"AF",
    "gn:dem":793,
    "gn:feature_class":"P",
    "gn:feature_code":"PPL",
    "gn:name":"Tapah",
    "gn:population":0,
    "gn:timezone":"Asia/Kabul",
    "iso:country":"AF",
    "name:und_x_variant":[
        "Tappeh",
        "Tapah",
        "\u062a\u067e\u0647",
        "Tapa"
    ],
    "wof:name":"Tapah",
    "wof:placetype":"locality"
},
  "geometry": {"coordinates":[62.57604,32.73104],"type":"Point"}
}