{
  "type": "Feature",
  "properties": {
    "gn:admin1_code":"9",
    "gn:admin2_code":"2703.0",
    "gn:asciiname":"Dahanah-ye Kotah",
    "gn:country_code":"AF",
    "gn:dem":1848,
    "gn:feature_class":"P",
    "gn:feature_code":"PPL",
    "gn:name":"Dah\u0101nah-ye K\u014dt\u0101h",
    "gn:population":0,
    "gn:timezone":"Asia/Kabul",
    "iso:country":"AF",
    "name:und_x_variant":[
        "Dahana-i-K\u014dt\u0101h",
        "Dah\u0101nah-ye K\u014dt\u0101h",
        "\u062f\u0647\u0627\u0646\u06c0 \u06a9\u0648\u062a\u0627\u0647",
        "Dahaneh-ye K\u016bt\u0101h"
    ],
    "wof:name":"Dahanah-ye Kotah",
    "wof:placetype":"locality"
},
  "geometry": {"coordinates":[63.48757,34.02703],"type":"Point"}
}