{
  "type": "Feature",
  "properties": {
    "gn:admin1_code":"31",
    "gn:admin2_code":"1708",
    "gn:asciiname":"Kushkah",
    "gn:country_code":"AF",
    "gn:dem":322,
    "gn:feature_class":"P",
    "gn:feature_code":"PPL",
    "gn:name":"Kushkah",
    "gn:population":0,
    "gn:timezone":"Asia/Kabul",
    "iso:country":"AF",
    "name:und_x_variant":[
        "\u06a9\u0634\u06a9\u0647",
        "Kushka"
    ],
    "wof:name":"Kushkah",
    "wof:placetype":"locality"
},
  "geometry": {"coordinates":[66.56673000000001,36.79644],"type":"Point"}
}