{
  "type": "Feature",
  "properties": {
    "gn:admin1_code":"26",
    "gn:admin2_code":"1202",
    "gn:asciiname":"Jamanqiyah",
    "gn:country_code":"AF",
    "gn:dem":877,
    "gn:feature_class":"P",
    "gn:feature_code":"PPL",
    "gn:name":"Jam\u0101nqiyah",
    "gn:population":0,
    "gn:timezone":"Asia/Kabul",
    "iso:country":"AF",
    "name:fas_x_preferred":[
        "\u062c\u0645\u0627\u0646\u0642\u064a\u0647"
    ],
    "name:rus_x_preferred":[
        "\u0414\u0436\u0430\u043c\u0430\u043d\u043a\u0438\u044f"
    ],
    "name:und_x_variant":[
        "Dzhamankiya",
        "Jam\u0101nqeya",
        "Jam\u0101nqeyah",
        "Jam\u0101nqiyah",
        "\u062c\u0645\u0627\u0646\u0642\u06cc\u0647"
    ],
    "wof:name":"Jamanqiyah",
    "wof:placetype":"locality"
},
  "geometry": {"coordinates":[69.43597,36.54655],"type":"Point"}
}