{
  "type": "Feature",
  "properties": {
    "gn:admin1_code":"09",
    "gn:admin2_code":"2701",
    "gn:asciiname":"Ghukakzar",
    "gn:country_code":"AF",
    "gn:dem":2501,
    "gn:feature_class":"P",
    "gn:feature_code":"PPL",
    "gn:name":"Gh\u016bkakz\u0101r",
    "gn:population":0,
    "gn:timezone":"Asia/Kabul",
    "iso:country":"AF",
    "name:und_x_variant":[
        "Gh\u016bkakz\u0101r",
        "\u063a\u0648\u06a9\u06a9\u0632\u0627\u0631",
        "Gh\u016bkakz\u0101\u1e5f"
    ],
    "wof:name":"Ghukakzar",
    "wof:placetype":"locality"
},
  "geometry": {"coordinates":[64.89856999999999,34.52291],"type":"Point"}
}