{
  "type": "Feature",
  "properties": {
    "gn:admin1_code":"08",
    "gn:admin2_code":"607",
    "gn:asciiname":"Tangi",
    "gn:country_code":"AF",
    "gn:dem":2534,
    "gn:feature_class":"P",
    "gn:feature_code":"PPL",
    "gn:name":"Tang\u012b",
    "gn:population":0,
    "gn:timezone":"Asia/Kabul",
    "iso:country":"AF",
    "name:und_x_variant":[
        "Tang\u012b",
        "\u062a\u0646\u06af\u06cc",
        "Tangi"
    ],
    "wof:name":"Tangi",
    "wof:placetype":"locality"
},
  "geometry": {"coordinates":[67.44197,33.04272],"type":"Point"}
}