{
  "type": "Feature",
  "properties": {
    "gn:admin1_code":"09",
    "gn:admin2_code":"2706",
    "gn:asciiname":"Obotu",
    "gn:country_code":"AF",
    "gn:dem":2728,
    "gn:feature_class":"P",
    "gn:feature_code":"PPL",
    "gn:name":"Ob\u014dt\u016b",
    "gn:population":0,
    "gn:timezone":"Asia/Kabul",
    "iso:country":"AF",
    "name:und_x_variant":[
        "\u014cb\u014dtu",
        "Ob\u014dt\u016b",
        "\u0627\u0628\u0648\u062a\u0648",
        "Owb\u016btu"
    ],
    "wof:name":"Obotu",
    "wof:placetype":"locality"
},
  "geometry": {"coordinates":[64.98638000000001,33.71734],"type":"Point"}
}