{
  "type": "Feature",
  "properties": {
    "gn:admin1_code":"28",
    "gn:admin2_code":"2502.0",
    "gn:asciiname":"Bazugay",
    "gn:country_code":"AF",
    "gn:dem":2021,
    "gn:feature_class":"P",
    "gn:feature_code":"PPL",
    "gn:name":"B\u0101z\u016bgay",
    "gn:population":0,
    "gn:timezone":"Asia/Kabul",
    "iso:country":"AF",
    "name:und_x_variant":[
        "B\u0101z\u016bgay",
        "\u0628\u0627\u0632\u0648\u06af\u06cc"
    ],
    "wof:name":"Bazugay",
    "wof:placetype":"locality"
},
  "geometry": {"coordinates":[67.36181999999999,32.25819],"type":"Point"}
}