{
  "type": "Feature",
  "properties": {
    "gn:admin1_code":"07",
    "gn:admin2_code":"1804",
    "gn:asciiname":"Sayyad-e Naqi",
    "gn:country_code":"AF",
    "gn:dem":1220,
    "gn:feature_class":"P",
    "gn:feature_code":"PPL",
    "gn:name":"\u015eayy\u0101d-e Naq\u012b",
    "gn:population":0,
    "gn:timezone":"Asia/Kabul",
    "iso:country":"AF",
    "name:und_x_variant":[
        "Say\u0101\u1e0f-i-Naqi",
        "\u015eayy\u0101d-e Naq\u012b",
        "\u0635\u064a\u0627\u062f \u0646\u0642\u06cc"
    ],
    "wof:name":"Sayyad-e Naqi",
    "wof:placetype":"locality"
},
  "geometry": {"coordinates":[64.53639,35.67244],"type":"Point"}
}