{
  "type": "Feature",
  "properties": {
    "gn:admin1_code":"13",
    "gn:admin2_code":"101.0",
    "gn:asciiname":"Bagh-e Sowdagar",
    "gn:country_code":"AF",
    "gn:dem":1821,
    "gn:feature_class":"P",
    "gn:feature_code":"PPL",
    "gn:name":"B\u0101gh-e Sowd\u0101gar",
    "gn:population":0,
    "gn:timezone":"Asia/Kabul",
    "iso:country":"AF",
    "name:fas_x_preferred":[
        "\u0628\u06a9\u06cc \u0633\u0648\u062f\u06af\u0631"
    ],
    "name:und_x_variant":[
        "B\u0101gh-e Sowd\u0101gar",
        "Baki-Savdagar",
        "\u0628\u0627\u063a \u0633\u0648\u062f\u0627\u06af\u0631"
    ],
    "wof:name":"Bagh-e Sowdagar",
    "wof:placetype":"locality"
},
  "geometry": {"coordinates":[69.11669000000001,34.49433],"type":"Point"}
}