{
  "type": "Feature",
  "properties": {
    "gn:admin1_code":"17",
    "gn:admin2_code":"501",
    "gn:asciiname":"Mirwal",
    "gn:country_code":"AF",
    "gn:dem":2028,
    "gn:feature_class":"P",
    "gn:feature_code":"PPL",
    "gn:name":"M\u012brw\u0101l",
    "gn:population":0,
    "gn:timezone":"Asia/Kabul",
    "iso:country":"AF",
    "name:rus_x_preferred":[
        "Mirval\u2019"
    ],
    "name:und_x_variant":[
        "M\u012brw\u0101l",
        "\u0645\u06cc\u0631\u0648\u0627\u0644"
    ],
    "wof:name":"Mirwal",
    "wof:placetype":"locality"
},
  "geometry": {"coordinates":[68.94284,34.12926],"type":"Point"}
}