{
  "type": "Feature",
  "properties": {
    "gn:admin1_code":"09",
    "gn:admin2_code":"2705",
    "gn:asciiname":"Ranji-ye Pa'in",
    "gn:country_code":"AF",
    "gn:dem":2101,
    "gn:feature_class":"P",
    "gn:feature_code":"PPL",
    "gn:name":"Ranj\u012b-ye P\u0101\u2019\u012bn",
    "gn:population":0,
    "gn:timezone":"Asia/Kabul",
    "iso:country":"AF",
    "name:und_x_variant":[
        "Randzhi-Pain",
        "\u1e5eanj\u012b P\u0101\u2019\u012bn",
        "Ranj\u012b-ye P\u0101\u2019\u012bn",
        "\u0631\u0646\u062c\u06cc \u067e\u0627\u0626\u06cc\u0646",
        "Ranj-e P\u0101\u2019\u012bn"
    ],
    "wof:name":"Ranji-ye Pa'in",
    "wof:placetype":"locality"
},
  "geometry": {"coordinates":[64.20860999999999,33.45655],"type":"Point"}
}