{
  "type": "Feature",
  "properties": {
    "gn:admin1_code":"08",
    "gn:admin2_code":"606",
    "gn:asciiname":"Gharsang",
    "gn:country_code":"AF",
    "gn:dem":3148,
    "gn:feature_class":"P",
    "gn:feature_code":"PPL",
    "gn:name":"Gh\u0101rsang",
    "gn:population":0,
    "gn:timezone":"Asia/Kabul",
    "iso:country":"AF",
    "name:und_x_variant":[
        "Gh\u0101rsang",
        "\u063a\u0627\u0631\u0633\u0646\u06af",
        "Gharsang"
    ],
    "wof:name":"Gharsang",
    "wof:placetype":"locality"
},
  "geometry": {"coordinates":[67.21420000000001,33.2539],"type":"Point"}
}