{
  "type": "Feature",
  "properties": {
    "gn:admin1_code":"9",
    "gn:admin2_code":"2707.0",
    "gn:asciiname":"Paytow Shor",
    "gn:country_code":"AF",
    "gn:dem":3000,
    "gn:feature_class":"P",
    "gn:feature_code":"PPL",
    "gn:name":"Paytow Sh\u014dr",
    "gn:population":0,
    "gn:timezone":"Asia/Kabul",
    "iso:country":"AF",
    "name:und_x_variant":[
        "Petaushor",
        "Petaw\u0161or",
        "P\u0113t\u0101wsh\u016br",
        "Paytow Sh\u014dr",
        "\u067e\u06cc\u062a\u0648 \u0634\u0648\u0631"
    ],
    "wof:name":"Paytow Shor",
    "wof:placetype":"locality"
},
  "geometry": {"coordinates":[66.19913000000001,34.44838],"type":"Point"}
}