{
  "type": "Feature",
  "properties": {
    "gn:admin1_code":"42",
    "gn:admin2_code":"3304",
    "gn:asciiname":"Deh-e Yari",
    "gn:country_code":"AF",
    "gn:dem":3161,
    "gn:feature_class":"P",
    "gn:feature_code":"PPL",
    "gn:name":"Deh-e Y\u0101r\u012b",
    "gn:population":0,
    "gn:timezone":"Asia/Kabul",
    "iso:country":"AF",
    "name:und_x_variant":[
        "Razvaliny Dekhi-Yari",
        "Deh Y\u0101ri",
        "Deh-e Y\u0101r\u012b",
        "\u062f\u0647 \u06cc\u0627\u0631\u06cc"
    ],
    "wof:name":"Deh-e Yari",
    "wof:placetype":"locality"
},
  "geometry": {"coordinates":[70.07007,35.62386],"type":"Point"}
}