{
  "type": "Feature",
  "properties": {
    "gn:admin1_code":"32",
    "gn:admin2_code":"1504",
    "gn:asciiname":"Duganah",
    "gn:country_code":"AF",
    "gn:dem":2052,
    "gn:feature_class":"P",
    "gn:feature_code":"PPL",
    "gn:name":"D\u016bg\u0101nah",
    "gn:population":0,
    "gn:timezone":"Asia/Kabul",
    "iso:country":"AF",
    "name:und_x_variant":[
        "\u1e0eog\u0101na",
        "Dog\u0101neh",
        "D\u016bg\u0101nah",
        "\u062f\u0648\u06af\u0627\u0646\u0647"
    ],
    "wof:name":"Duganah",
    "wof:placetype":"locality"
},
  "geometry": {"coordinates":[67.09689,35.846],"type":"Point"}
}