{
  "type": "Feature",
  "properties": {
    "gn:admin1_code":"10",
    "gn:admin2_code":"2311.0",
    "gn:asciiname":"Pasto Khan Kelay",
    "gn:country_code":"AF",
    "gn:dem":721,
    "gn:feature_class":"P",
    "gn:feature_code":"PPL",
    "gn:name":"Past\u014d Kh\u0101n K\u00ealay",
    "gn:population":0,
    "gn:timezone":"Asia/Kabul",
    "iso:country":"AF",
    "name:und_x_variant":[
        "Past\u014dkh\u0101n Kalay",
        "Past\u014d Kh\u0101n K\u00ealay",
        "\u067e\u0633\u062a\u0648 \u062e\u0627\u0646 \u06a9\u0644\u06cc",
        "Past\u016b Kh\u0101n Kalay"
    ],
    "wof:name":"Pasto Khan Kelay",
    "wof:placetype":"locality"
},
  "geometry": {"coordinates":[64.17766,31.19935],"type":"Point"}
}