{
  "type": "Feature",
  "properties": {
    "gn:admin1_code":"5",
    "gn:admin2_code":"2801.0",
    "gn:asciiname":"Ab-Bala",
    "gn:country_code":"AF",
    "gn:dem":2989,
    "gn:feature_class":"P",
    "gn:feature_code":"PPL",
    "gn:name":"Ab-Bala",
    "gn:population":0,
    "gn:timezone":"Asia/Kabul",
    "iso:country":"AF",
    "name:und_x_variant":[
        "\u0100b B\u0101l\u0101",
        "\u0622\u0628 \u0628\u0627\u0644\u0627"
    ],
    "wof:name":"Ab-Bala",
    "wof:placetype":"locality"
},
  "geometry": {"coordinates":[67.73614999999999,34.7254],"type":"Point"}
}