{
  "type": "Feature",
  "properties": {
    "gn:admin1_code":"23",
    "gn:admin2_code":"2416.0",
    "gn:asciiname":"Nurzay",
    "gn:country_code":"AF",
    "gn:dem":955,
    "gn:feature_class":"P",
    "gn:feature_code":"PPL",
    "gn:name":"Nurzay",
    "gn:population":0,
    "gn:timezone":"Asia/Kabul",
    "iso:country":"AF",
    "name:und_x_variant":[
        "N\u016brza\u012b",
        "\u0646\u0648\u0631\u0632\u06cc",
        "N\u016brza\u2019i",
        "N\u016brza\u2019\u012b",
        "\u0646\u0648\u0631\u0632\u0626\u06cc"
    ],
    "wof:name":"Nurzay",
    "wof:placetype":"locality"
},
  "geometry": {"coordinates":[65.44416,31.57331],"type":"Point"}
}