{
  "type": "Feature",
  "properties": {
    "gn:admin1_code":"5",
    "gn:admin2_code":"2802.0",
    "gn:asciiname":"Kuhnah Qal'ah",
    "gn:country_code":"AF",
    "gn:dem":2822,
    "gn:feature_class":"P",
    "gn:feature_code":"PPL",
    "gn:name":"Kuhnah Qal\u2018ah",
    "gn:population":0,
    "gn:timezone":"Asia/Kabul",
    "iso:country":"AF",
    "name:und_x_variant":[
        "Kuhnaqal\u2018a",
        "Kukhnakala",
        "Kohnehqal\u2018eh",
        "Kuhnah Qal\u2018ah",
        "\u06a9\u0647\u0646\u0647 \u0642\u0644\u0639\u0647"
    ],
    "wof:name":"Kuhnah Qal'ah",
    "wof:placetype":"locality"
},
  "geometry": {"coordinates":[68.2235,34.89105],"type":"Point"}
}