{
  "type": "Feature",
  "properties": {
    "gn:admin1_code":"23",
    "gn:admin2_code":"2411.0",
    "gn:asciiname":"Mandz Shelah",
    "gn:country_code":"AF",
    "gn:dem":1756,
    "gn:feature_class":"P",
    "gn:feature_code":"PPL",
    "gn:name":"Mandz Sh\u0113lah",
    "gn:population":0,
    "gn:timezone":"Asia/Kabul",
    "iso:country":"AF",
    "name:und_x_variant":[
        "Mandzhshela",
        "M\u0101nj \u0160\u0113l\u011bh",
        "M\u0101nj Sh\u0113lah",
        "Mandz Sh\u0113lah",
        "Mandz Shaylah",
        "\u0645\u0646\u0681 \u0634\u06d0\u0644\u0647"
    ],
    "wof:name":"Mandz Shelah",
    "wof:placetype":"locality"
},
  "geometry": {"coordinates":[66.658,31.18128],"type":"Point"}
}