{
  "type": "Feature",
  "properties": {
    "gn:admin1_code":"13",
    "gn:admin2_code":"101.0",
    "gn:asciiname":"Qal'ah-ye Shukurullah",
    "gn:country_code":"AF",
    "gn:dem":1810,
    "gn:feature_class":"P",
    "gn:feature_code":"PPL",
    "gn:name":"Qal\u2018ah-ye Shukurull\u0101h",
    "gn:population":0,
    "gn:timezone":"Asia/Kabul",
    "iso:country":"AF",
    "name:fas_x_preferred":[
        "\u0642\u0644\u0639\u0647\u0654 \u0634\u06a9\u0631\ufdf2 \u062e\u0627\u0646"
    ],
    "name:und_x_variant":[
        "Qal\u2018ah-ye Shukurull\u0101h",
        "Kalayi-Shukrullakhan",
        "\u0642\u0644\u0639\u0647 \u0634\u06a9\u0631\u0627\u0644\u0644\u0647"
    ],
    "wof:name":"Qal'ah-ye Shukurullah",
    "wof:placetype":"locality"
},
  "geometry": {"coordinates":[69.15168,34.49505],"type":"Point"}
}