{
  "type": "Feature",
  "properties": {
    "gn:admin1_code":"11",
    "gn:admin2_code":"2001",
    "gn:asciiname":"Rabat-e Kashmir",
    "gn:country_code":"AF",
    "gn:dem":880,
    "gn:feature_class":"P",
    "gn:feature_code":"PPL",
    "gn:name":"Rab\u0101\u0163-e Kashm\u012br",
    "gn:population":0,
    "gn:timezone":"Asia/Kabul",
    "iso:country":"AF",
    "name:und_x_variant":[
        "Rab\u0101t-i-Ka\u0161mir",
        "Rob\u0101\u0163-i-Kashm\u012br",
        "Rabati-Kashmir",
        "Rab\u0101\u0163-e Kashm\u012br",
        "\u0631\u0628\u0627\u0637 \u06a9\u0634\u0645\u06cc\u0631",
        "Rob\u0101\u0163-e Keshm\u012br"
    ],
    "wof:name":"Rabat-e Kashmir",
    "wof:placetype":"locality"
},
  "geometry": {"coordinates":[62.00654,34.31566],"type":"Point"}
}