{
  "type": "Feature",
  "properties": {
    "gn:admin1_code":"27",
    "gn:admin2_code":"409",
    "gn:asciiname":"Seh Deh",
    "gn:country_code":"AF",
    "gn:dem":2452,
    "gn:feature_class":"P",
    "gn:feature_code":"PPL",
    "gn:name":"Seh Deh",
    "gn:population":0,
    "gn:timezone":"Asia/Kabul",
    "iso:country":"AF",
    "name:fas_x_preferred":[
        "\u0633\u0647 \u062f\u0647"
    ],
    "name:und_x_variant":[
        "Sindekh",
        "Seh Deh"
    ],
    "wof:name":"Seh Deh",
    "wof:placetype":"locality"
},
  "geometry": {"coordinates":[68.39603000000001,33.80185],"type":"Point"}
}