{
  "type": "Feature",
  "properties": {
    "gn:admin1_code":"10",
    "gn:admin2_code":"2305",
    "gn:asciiname":"Khwajah Angal",
    "gn:country_code":"AF",
    "gn:dem":1359,
    "gn:feature_class":"P",
    "gn:feature_code":"PPL",
    "gn:name":"Khw\u0101jah Angal",
    "gn:population":0,
    "gn:timezone":"Asia/Kabul",
    "iso:country":"AF",
    "name:rus_x_preferred":[
        "Khodzhaangal\u2019"
    ],
    "name:und_x_variant":[
        "Khw\u0101ja Angal",
        "Khw\u0101jah Angal",
        "\u062e\u0648\u0627\u062c\u0647 \u0627\u0646\u06af\u0644",
        "Khv\u0101jeh Angal"
    ],
    "wof:name":"Khwajah Angal",
    "wof:placetype":"locality"
},
  "geometry": {"coordinates":[64.84633000000001,32.93125999999999],"type":"Point"}
}