{
  "type": "Feature",
  "properties": {
    "gn:admin1_code":"05",
    "gn:admin2_code":"2806",
    "gn:asciiname":"Marg-e Zanu",
    "gn:country_code":"AF",
    "gn:dem":3126,
    "gn:feature_class":"P",
    "gn:feature_code":"PPL",
    "gn:name":"Marg-e Zan\u016b",
    "gn:population":0,
    "gn:timezone":"Asia/Kabul",
    "iso:country":"AF",
    "name:und_x_variant":[
        "Margi-Zanu",
        "Marg-e Zan\u016b",
        "\u0645\u0631\u06af \u0632\u0646\u0648"
    ],
    "wof:name":"Marg-e Zanu",
    "wof:placetype":"locality"
},
  "geometry": {"coordinates":[67.14695999999999,34.29185],"type":"Point"}
}