{
  "type": "Feature",
  "properties": {
    "gn:admin1_code":"33",
    "gn:admin2_code":"3104",
    "gn:asciiname":"Tay-e Luch",
    "gn:country_code":"AF",
    "gn:dem":2175,
    "gn:feature_class":"P",
    "gn:feature_code":"PPL",
    "gn:name":"Tay-e Luch",
    "gn:population":0,
    "gn:timezone":"Asia/Kabul",
    "iso:country":"AF",
    "name:und_x_variant":[
        "\u062a\u06cc \u0644\u0686",
        "Taye Luc"
    ],
    "wof:name":"Tay-e Luch",
    "wof:placetype":"locality"
},
  "geometry": {"coordinates":[66.34300999999999,35.39635999999999],"type":"Point"}
}