{
  "type": "Feature",
  "properties": {
    "gn:admin1_code":"01",
    "gn:admin2_code":"1111",
    "gn:asciiname":"Sayl Don",
    "gn:country_code":"AF",
    "gn:dem":2535,
    "gn:feature_class":"P",
    "gn:feature_code":"PPL",
    "gn:name":"Sayl D\u014dn",
    "gn:population":0,
    "gn:timezone":"Asia/Kabul",
    "iso:country":"AF",
    "name:und_x_variant":[
        "S\u0113l \u1e0e\u014dn",
        "Seyl D\u016bn",
        "Sayl D\u014dn",
        "\u0633\u06cc\u0644 \u062f\u0648\u0646"
    ],
    "wof:name":"Sayl Don",
    "wof:placetype":"locality"
},
  "geometry": {"coordinates":[70.41259000000002,37.75252],"type":"Point"}
}