{
  "type": "Feature",
  "properties": {
    "gn:admin1_code":"09",
    "gn:admin2_code":"2702",
    "gn:asciiname":"Shibirg",
    "gn:country_code":"AF",
    "gn:dem":2236,
    "gn:feature_class":"P",
    "gn:feature_code":"PPL",
    "gn:name":"Shibirg",
    "gn:population":0,
    "gn:timezone":"Asia/Kabul",
    "iso:country":"AF",
    "name:und_x_variant":[
        "Qeshl\u0101q-e Sheberg",
        "\u0160eberg",
        "Shewarg",
        "Sibarga",
        "Shibirg",
        "\u0634\u0628\u0631\u06af",
        "Sheberg"
    ],
    "wof:name":"Shibirg",
    "wof:placetype":"locality"
},
  "geometry": {"coordinates":[64.08558000000001,34.24624],"type":"Point"}
}