{
  "type": "Feature",
  "properties": {
    "gn:admin1_code":"03",
    "gn:admin2_code":"1301.0",
    "gn:asciiname":"Ibrahim Khel",
    "gn:country_code":"AF",
    "gn:dem":589,
    "gn:feature_class":"P",
    "gn:feature_code":"PPL",
    "gn:name":"Ibr\u0101h\u012bm Kh\u0113l",
    "gn:population":0,
    "gn:timezone":"Asia/Kabul",
    "iso:country":"AF",
    "name:rus_x_preferred":[
        "Ibrakhimkheil\u2019"
    ],
    "name:und_x_variant":[
        "Eb\u1e5f\u0101h\u012bmkh\u0113l",
        "Ebr\u0101h\u012bmkheyl",
        "Ibr\u0101h\u012bm Kh\u0113l",
        "\u0627\u0628\u0631\u0627\u0647\u06cc\u0645 \u062e\u06d0\u0644"
    ],
    "wof:name":"Ibrahim Khel",
    "wof:placetype":"locality"
},
  "geometry": {"coordinates":[68.63025,35.996],"type":"Point"}
}