{
  "type": "Feature",
  "properties": {
    "gn:admin1_code":"42",
    "gn:admin2_code":"3306.0",
    "gn:asciiname":"Burjia Khel",
    "gn:country_code":"AF",
    "gn:dem":1934,
    "gn:feature_class":"P",
    "gn:feature_code":"PPL",
    "gn:name":"Burj\u012b\u0101 Kh\u0113l",
    "gn:population":0,
    "gn:timezone":"Asia/Kabul",
    "iso:country":"AF",
    "name:fas_x_preferred":[
        "\u0628\u0631\u062c\u064a\u0627 \u062e\u064a\u0644"
    ],
    "name:rus_x_preferred":[
        "Burdzh\u2019yakheyl\u2019"
    ],
    "name:und_x_variant":[
        "Bu\u1e5fjy\u0101kh\u0113l",
        "Borjy\u0101 Kheyl",
        "Burj\u012b\u0101 Kh\u0113l",
        "\u0628\u0631\u062c\u06cc\u0627 \u062e\u06d0\u0644"
    ],
    "wof:name":"Burjia Khel",
    "wof:placetype":"locality"
},
  "geometry": {"coordinates":[69.41885000000001,35.21788],"type":"Point"}
}