{
  "type": "Feature",
  "properties": {
    "gn:admin1_code":"05",
    "gn:admin2_code":"2805",
    "gn:asciiname":"Dew Khanah",
    "gn:country_code":"AF",
    "gn:dem":2923,
    "gn:feature_class":"P",
    "gn:feature_code":"PPL",
    "gn:name":"D\u0113w Kh\u0101nah",
    "gn:population":0,
    "gn:timezone":"Asia/Kabul",
    "iso:country":"AF",
    "name:und_x_variant":[
        "Deo Kh\u0101na",
        "Devkhana",
        "\u1e0e\u0113wkh\u0101na",
        "Deyw Kh\u0101nah",
        "D\u012bvkh\u0101neh",
        "D\u0113w Kh\u0101nah",
        "\u062f\u06d0\u0648 \u062e\u0627\u0646\u0647"
    ],
    "wof:name":"Dew Khanah",
    "wof:placetype":"locality"
},
  "geometry": {"coordinates":[66.93684,34.47586],"type":"Point"}
}