{
  "type": "Feature",
  "properties": {
    "gn:admin1_code":"10",
    "gn:admin2_code":"2305",
    "gn:asciiname":"Showay",
    "gn:country_code":"AF",
    "gn:dem":1429,
    "gn:feature_class":"P",
    "gn:feature_code":"PPL",
    "gn:name":"Sh\u014dway",
    "gn:population":0,
    "gn:timezone":"Asia/Kabul",
    "iso:country":"AF",
    "name:und_x_variant":[
        "Shovay",
        "\u0160oway",
        "Sh\u014dway",
        "\u0634\u0648\u0648\u06cc",
        "Sh\u016bway"
    ],
    "wof:name":"Showay",
    "wof:placetype":"locality"
},
  "geometry": {"coordinates":[64.97449,32.69413],"type":"Point"}
}