{
  "type": "Feature",
  "properties": {
    "gn:admin1_code":"7",
    "gn:admin2_code":"1804.0",
    "gn:asciiname":"Sinjitak",
    "gn:country_code":"AF",
    "gn:dem":970,
    "gn:feature_class":"P",
    "gn:feature_code":"PPL",
    "gn:name":"Sinjitak",
    "gn:population":0,
    "gn:timezone":"Asia/Kabul",
    "iso:country":"AF",
    "name:und_x_variant":[
        "\u0633\u0646\u062c\u062a\u06a9",
        "Senjetak"
    ],
    "wof:name":"Sinjitak",
    "wof:placetype":"locality"
},
  "geometry": {"coordinates":[63.99858,35.65875],"type":"Point"}
}