{
  "type": "Feature",
  "properties": {
    "gn:admin1_code":"29",
    "gn:admin2_code":"2914",
    "gn:asciiname":"Shpar",
    "gn:country_code":"AF",
    "gn:dem":2730,
    "gn:feature_class":"P",
    "gn:feature_code":"PPL",
    "gn:name":"Shpa\u1e5f",
    "gn:population":0,
    "gn:timezone":"Asia/Kabul",
    "iso:country":"AF",
    "name:fas_x_preferred":[
        "\u0634\u067e\u0631"
    ],
    "name:und_x_variant":[
        "\u0160par",
        "Shpar",
        "Shpa\u1e5f",
        "\u0634\u067e\u0693",
        "\u0634\u067e\u0631"
    ],
    "wof:name":"Shpar",
    "wof:placetype":"locality"
},
  "geometry": {"coordinates":[69.09668000000001,33.14519],"type":"Point"}
}