{
  "type": "Feature",
  "properties": {
    "gn:admin1_code":"09",
    "gn:admin2_code":"2705",
    "gn:asciiname":"Surkh Dewal",
    "gn:country_code":"AF",
    "gn:dem":2618,
    "gn:feature_class":"P",
    "gn:feature_code":"PPL",
    "gn:name":"Surkh D\u0113w\u0101l",
    "gn:population":0,
    "gn:timezone":"Asia/Kabul",
    "iso:country":"AF",
    "name:fas_x_preferred":[
        "\u0633\u0631\u062e \u062f\u064a\u0648\u0627\u0631"
    ],
    "name:rus_x_preferred":[
        "Surkhdeval\u2019"
    ],
    "name:und_x_variant":[
        "Su\u1e5fkh\u1e0f\u0113w\u0101l",
        "Sorkhd\u012bv\u0101r",
        "Surkh Dayw\u0101l",
        "\u0633\u0631\u062e \u062f\u06cc\u0648\u0627\u0644",
        "Sorkhd\u012bv\u0101l",
        "Surkh D\u0113w\u0101l"
    ],
    "wof:name":"Surkh Dewal",
    "wof:placetype":"locality"
},
  "geometry": {"coordinates":[64.67009,33.40761],"type":"Point"}
}