{
  "type": "Feature",
  "properties": {
    "gn:admin1_code":"23",
    "gn:admin2_code":"2408.0",
    "gn:asciiname":"Haji Habibullah",
    "gn:country_code":"AF",
    "gn:dem":934,
    "gn:feature_class":"P",
    "gn:feature_code":"PPL",
    "gn:name":"\u1e28\u0101j\u012b \u1e28ab\u012bbull\u0101h",
    "gn:population":0,
    "gn:timezone":"Asia/Kabul",
    "iso:country":"AF",
    "name:fas_x_preferred":[
        "\u062d\u0627\u062c\u06cc \u062d\u0628\u064a\u0628 \u0627\u0644\u0644\u0647"
    ],
    "name:und_x_variant":[
        "Khadzhi-Khabibulla",
        "\u1e28\u0101j\u012b \u1e28ab\u012bbull\u0101h",
        "\u062d\u0627\u062c\u06cc \u062d\u0628\u06cc\u0628 \u0627\u0644\u0644\u0640\u0647",
        "\u1e28\u0101jj\u012b \u1e28ab\u012bboll\u0101h"
    ],
    "wof:name":"Haji Habibullah",
    "wof:placetype":"locality"
},
  "geometry": {"coordinates":[65.45354,31.52517000000001],"type":"Point"}
}