{
  "type": "Feature",
  "properties": {
    "gn:admin1_code":"13",
    "gn:admin2_code":"108.0",
    "gn:asciiname":"Qasim Khan",
    "gn:country_code":"AF",
    "gn:dem":1997,
    "gn:feature_class":"P",
    "gn:feature_code":"PPL",
    "gn:name":"Q\u0101sim Kh\u0101n",
    "gn:population":0,
    "gn:timezone":"Asia/Kabul",
    "iso:country":"AF",
    "name:und_x_variant":[
        "Kasimkhan",
        "Q\u0101sim Kh\u0101n",
        "Q\u0101semkh\u0101n",
        "\u0642\u0627\u0633\u0645 \u062e\u0627\u0646"
    ],
    "wof:name":"Qasim Khan",
    "wof:placetype":"locality"
},
  "geometry": {"coordinates":[68.99569,34.49725],"type":"Point"}
}