{
  "type": "Feature",
  "properties": {
    "gn:admin1_code":"18",
    "gn:admin2_code":"808",
    "gn:asciiname":"Ghoshtarah",
    "gn:country_code":"AF",
    "gn:dem":1295,
    "gn:feature_class":"P",
    "gn:feature_code":"PPL",
    "gn:name":"Gh\u014ds\u0332h\u0332tarah",
    "gn:population":0,
    "gn:timezone":"Asia/Kabul",
    "iso:country":"AF",
    "name:fas_x_preferred":[
        "\u063a\u0648\u0634\u062a\u0631\u0647"
    ],
    "name:und_x_variant":[
        "Goshtara",
        "Gho\u0161tara",
        "Gh\u016bshtara",
        "Gh\u014dshtara",
        "Gh\u016bshtarah",
        "Gh\u014ds\u0332h\u0332tarah",
        "\u063a\u0648\u069a\u062a\u0631\u0647"
    ],
    "wof:name":"Ghoshtarah",
    "wof:placetype":"locality"
},
  "geometry": {"coordinates":[70.46544,34.12751],"type":"Point"}
}