{
  "type": "Feature",
  "properties": {
    "gn:admin1_code":"18",
    "gn:admin2_code":"810.0",
    "gn:asciiname":"Lukhi",
    "gn:country_code":"AF",
    "gn:dem":703,
    "gn:feature_class":"P",
    "gn:feature_code":"PPL",
    "gn:name":"Lukh\u012b",
    "gn:population":0,
    "gn:timezone":"Asia/Kabul",
    "iso:country":"AF",
    "name:und_x_variant":[
        "Lokhi",
        "Lukh\u012b",
        "\u0644\u062e\u06cc",
        "L\u014dkh\u012b",
        "\u0644\u0648\u062e\u06cc"
    ],
    "wof:name":"Lukhi",
    "wof:placetype":"locality"
},
  "geometry": {"coordinates":[70.68819000000001,34.19231],"type":"Point"}
}