{
  "type": "Feature",
  "properties": {
    "gn:admin1_code":"08",
    "gn:admin2_code":"606",
    "gn:asciiname":"Sang Deh",
    "gn:country_code":"AF",
    "gn:dem":3024,
    "gn:feature_class":"P",
    "gn:feature_code":"PPL",
    "gn:name":"Sang Deh",
    "gn:population":0,
    "gn:timezone":"Asia/Kabul",
    "iso:country":"AF",
    "name:und_x_variant":[
        "\u0633\u0646\u06af \u062f\u0647",
        "Sang\u1e0feh"
    ],
    "wof:name":"Sang Deh",
    "wof:placetype":"locality"
},
  "geometry": {"coordinates":[67.38238,33.46642],"type":"Point"}
}