{
  "type": "Feature",
  "properties": {
    "gn:admin1_code":"37",
    "gn:admin2_code":"3205",
    "gn:asciiname":"Palah",
    "gn:country_code":"AF",
    "gn:dem":2373,
    "gn:feature_class":"P",
    "gn:feature_code":"PPL",
    "gn:name":"Palah",
    "gn:population":0,
    "gn:timezone":"Asia/Kabul",
    "iso:country":"AF",
    "name:und_x_variant":[
        "Pala",
        "\u067e\u0644\u0647"
    ],
    "wof:name":"Palah",
    "wof:placetype":"locality"
},
  "geometry": {"coordinates":[69.64218000000001,33.60594],"type":"Point"}
}