{
  "type": "Feature",
  "properties": {
    "gn:admin1_code":"17",
    "gn:admin2_code":"501.0",
    "gn:asciiname":"Akbar Khel",
    "gn:country_code":"AF",
    "gn:dem":2584,
    "gn:feature_class":"P",
    "gn:feature_code":"PPL",
    "gn:name":"Akbar Kh\u0113l",
    "gn:population":0,
    "gn:timezone":"Asia/Kabul",
    "iso:country":"AF",
    "name:fas_x_preferred":[
        "\u0627\u0643\u0628\u0631 \u062e\u064a\u0644"
    ],
    "name:rus_x_preferred":[
        "Akbarkheyl\u2019"
    ],
    "name:und_x_variant":[
        "Akba\u1e5fkh\u0113l",
        "Akbar Kheyl",
        "Akbar Kh\u0113l",
        "\u0627\u06a9\u0628\u0631 \u062e\u06d0\u0644"
    ],
    "wof:name":"Akbar Khel",
    "wof:placetype":"locality"
},
  "geometry": {"coordinates":[69.16764999999999,33.82328],"type":"Point"}
}