{
  "type": "Feature",
  "properties": {
    "gn:admin1_code":"29",
    "gn:admin2_code":"2904.0",
    "gn:asciiname":"Laki Kelay",
    "gn:country_code":"AF",
    "gn:dem":2275,
    "gn:feature_class":"P",
    "gn:feature_code":"PPL",
    "gn:name":"Lak\u012b K\u00ealay",
    "gn:population":0,
    "gn:timezone":"Asia/Kabul",
    "iso:country":"AF",
    "name:und_x_variant":[
        "\u0644\u06a9\u06cc \u06a9\u0644\u06cc",
        "Lakay Kalay",
        "Lak\u012b K\u00ealay"
    ],
    "wof:name":"Laki Kelay",
    "wof:placetype":"locality"
},
  "geometry": {"coordinates":[68.35786999999999,32.32302],"type":"Point"}
}