{
  "type": "Feature",
  "properties": {
    "gn:admin1_code":"09",
    "gn:admin2_code":"2706",
    "gn:asciiname":"Du Burar",
    "gn:country_code":"AF",
    "gn:dem":2689,
    "gn:feature_class":"P",
    "gn:feature_code":"PPL",
    "gn:name":"D\u016b Bur\u0101r",
    "gn:population":0,
    "gn:timezone":"Asia/Kabul",
    "iso:country":"AF",
    "name:fas_x_preferred":[
        "\u062f\u0648 \u0628\u0631\u0627\u062f\u0631"
    ],
    "name:und_x_variant":[
        "Dow Bar\u0101r",
        "Duburar",
        "Dobr\u0101r",
        "Do Bar\u0101dar",
        "D\u016b Bur\u0101r",
        "\u062f\u0648 \u0628\u0631\u0627\u0631",
        "Do Bar\u0101r"
    ],
    "wof:name":"Du Burar",
    "wof:placetype":"locality"
},
  "geometry": {"coordinates":[64.60223000000001,33.3097],"type":"Point"}
}