{
  "type": "Feature",
  "properties": {
    "gn:admin1_code":"19",
    "gn:admin2_code":"2201",
    "gn:asciiname":"Sardar Ibrahim",
    "gn:country_code":"AF",
    "gn:dem":487,
    "gn:feature_class":"P",
    "gn:feature_code":"PPL",
    "gn:name":"Sard\u0101r Ibr\u0101h\u012bm",
    "gn:population":0,
    "gn:timezone":"Asia/Kabul",
    "iso:country":"AF",
    "name:und_x_variant":[
        "Sard\u0101r Ibr\u0101h\u012bm",
        "Sard\u0101r Ebr\u0101h\u012bm",
        "\u0633\u0631\u062f\u0627\u0631 \u0627\u0628\u0631\u0627\u0647\u06cc\u0645"
    ],
    "wof:name":"Sardar Ibrahim",
    "wof:placetype":"locality"
},
  "geometry": {"coordinates":[61.8547,30.99057],"type":"Point"}
}