{
  "type": "Feature",
  "properties": {
    "gn:admin1_code":"03",
    "gn:admin2_code":"1307.0",
    "gn:asciiname":"Mirwa",
    "gn:country_code":"AF",
    "gn:dem":1708,
    "gn:feature_class":"P",
    "gn:feature_code":"PPL",
    "gn:name":"M\u012brw\u0101",
    "gn:population":0,
    "gn:timezone":"Asia/Kabul",
    "iso:country":"AF",
    "name:und_x_variant":[
        "M\u012brwa",
        "M\u012brwah",
        "M\u012brw\u0101",
        "\u0645\u06cc\u0631\u0648\u0627"
    ],
    "wof:name":"Mirwa",
    "wof:placetype":"locality"
},
  "geometry": {"coordinates":[69.29815000000001,35.62674000000001],"type":"Point"}
}