{
  "type": "Feature",
  "properties": {
    "gn:admin1_code":"10",
    "gn:admin2_code":"2304.0",
    "gn:asciiname":"Wech Karez",
    "gn:country_code":"AF",
    "gn:dem":997,
    "gn:feature_class":"P",
    "gn:feature_code":"PPL",
    "gn:name":"W\u00each K\u0101r\u0113z",
    "gn:population":0,
    "gn:timezone":"Asia/Kabul",
    "iso:country":"AF",
    "name:und_x_variant":[
        "Vachkarez",
        "Wa\u010d K\u0101r\u0113z",
        "W\u00each K\u0101r\u0113z",
        "\u0648\u0686 \u06a9\u0627\u0631\u06d0\u0632",
        "Wach K\u0101r\u012bz"
    ],
    "wof:name":"Wech Karez",
    "wof:placetype":"locality"
},
  "geometry": {"coordinates":[64.81801999999999,32.28632],"type":"Point"}
}