{
  "type": "Feature",
  "properties": {
    "gn:admin1_code":"39",
    "gn:admin2_code":"2602",
    "gn:asciiname":"Hasanak Kelay",
    "gn:country_code":"AF",
    "gn:dem":2131,
    "gn:feature_class":"P",
    "gn:feature_code":"PPL",
    "gn:name":"\u1e28asanak K\u00ealay",
    "gn:population":0,
    "gn:timezone":"Asia/Kabul",
    "iso:country":"AF",
    "name:fas_x_preferred":[
        "\u0642\u0631\u064a\u06c0 \u062d\u0633\u0646\u0643"
    ],
    "name:und_x_variant":[
        "Khasanakkalay",
        "\u1e28asanak K\u00ealay",
        "\u062d\u0633\u0646\u06a9 \u06a9\u0644\u06cc",
        "\u1e28asanak Kalay"
    ],
    "wof:name":"Hasanak Kelay",
    "wof:placetype":"locality"
},
  "geometry": {"coordinates":[66.24069,32.59836],"type":"Point"}
}