{
  "type": "Feature",
  "properties": {
    "gn:admin1_code":"42",
    "gn:admin2_code":"3304.0",
    "gn:asciiname":"Kosur",
    "gn:country_code":"AF",
    "gn:dem":2851,
    "gn:feature_class":"P",
    "gn:feature_code":"PPL",
    "gn:name":"K\u014ds\u016br",
    "gn:population":0,
    "gn:timezone":"Asia/Kabul",
    "iso:country":"AF",
    "name:und_x_variant":[
        "K\u014ds\u016b\u1e5f",
        "K\u016bsowr",
        "\u06a9\u0648\u0633\u0648\u0631",
        "K\u014ds\u016br"
    ],
    "wof:name":"Kosur",
    "wof:placetype":"locality"
},
  "geometry": {"coordinates":[70.08249000000001,35.68525],"type":"Point"}
}