{
  "type": "Feature",
  "properties": {
    "gn:admin1_code":"8",
    "gn:admin2_code":"607.0",
    "gn:asciiname":"Zindah Murad",
    "gn:country_code":"AF",
    "gn:dem":2815,
    "gn:feature_class":"P",
    "gn:feature_code":"PPL",
    "gn:name":"Zindah Mur\u0101d",
    "gn:population":0,
    "gn:timezone":"Asia/Kabul",
    "iso:country":"AF",
    "name:und_x_variant":[
        "Zen\u1e0famo\u1e5f\u0101\u1e0f",
        "Zendeh Mor\u0101d",
        "Zindah Mur\u0101d",
        "\u0632\u0646\u062f\u0647 \u0645\u0631\u0627\u062f"
    ],
    "wof:name":"Zindah Murad",
    "wof:placetype":"locality"
},
  "geometry": {"coordinates":[67.37161999999999,33.22096],"type":"Point"}
}