{
  "type": "Feature",
  "properties": {
    "gn:admin1_code":"35",
    "gn:admin2_code":"902.0",
    "gn:asciiname":"Mapor Ka'bah",
    "gn:country_code":"AF",
    "gn:dem":644,
    "gn:feature_class":"P",
    "gn:feature_code":"PPL",
    "gn:name":"Map\u014dr Ka\u2018bah",
    "gn:population":0,
    "gn:timezone":"Asia/Kabul",
    "iso:country":"AF",
    "name:und_x_variant":[
        "Map\u014dr Ka\u2018bah",
        "\u0645\u067e\u0648\u0631 \u06a9\u0639\u0628\u0647"
    ],
    "wof:name":"Mapor Ka'bah",
    "wof:placetype":"locality"
},
  "geometry": {"coordinates":[70.28043000000001,34.53941],"type":"Point"}
}