{
  "type": "Feature",
  "properties": {
    "gn:admin1_code":"11",
    "gn:admin2_code":"2003",
    "gn:asciiname":"Ghulanji",
    "gn:country_code":"AF",
    "gn:dem":1186,
    "gn:feature_class":"P",
    "gn:feature_code":"PPL",
    "gn:name":"Gh\u016blanj\u012b",
    "gn:population":0,
    "gn:timezone":"Asia/Kabul",
    "iso:country":"AF",
    "name:und_x_variant":[
        "Gh\u016blanj\u012b",
        "\u063a\u0648\u0644\u0646 \u062c\u06cc",
        "Gh\u016blanji"
    ],
    "wof:name":"Ghulanji",
    "wof:placetype":"locality"
},
  "geometry": {"coordinates":[61.93005,33.92864],"type":"Point"}
}