{
  "type": "Feature",
  "properties": {
    "gn:admin1_code":"32",
    "gn:admin2_code":"1504.0",
    "gn:asciiname":"Qizil Say",
    "gn:country_code":"AF",
    "gn:dem":1613,
    "gn:feature_class":"P",
    "gn:feature_code":"PPL",
    "gn:name":"Qizil S\u0101y",
    "gn:population":0,
    "gn:timezone":"Asia/Kabul",
    "iso:country":"AF",
    "name:und_x_variant":[
        "Qizil Sai (2)",
        "Qezel S\u0101y (2)",
        "Qizil S\u0101y",
        "\u0642\u0632\u0644 \u0633\u0627\u06cc"
    ],
    "wof:name":"Qizil Say",
    "wof:placetype":"locality"
},
  "geometry": {"coordinates":[67.46333,36.16025],"type":"Point"}
}