{
  "type": "Feature",
  "properties": {
    "gn:admin1_code":"08",
    "gn:admin2_code":"604",
    "gn:asciiname":"Qushnak",
    "gn:country_code":"AF",
    "gn:dem":3431,
    "gn:feature_class":"P",
    "gn:feature_code":"PPL",
    "gn:name":"Q\u016bshnak",
    "gn:population":0,
    "gn:timezone":"Asia/Kabul",
    "iso:country":"AF",
    "name:fas_x_preferred":[
        "\u0642\u0648\u0634\u0646\u0643"
    ],
    "name:rus_x_preferred":[
        "\u041a\u0443\u0448\u043d\u0430\u043a"
    ],
    "name:und_x_variant":[
        "Kushnak",
        "Q\u016b\u0161nak",
        "Q\u016bshnak",
        "\u0642\u0648\u0634\u0646\u06a9"
    ],
    "wof:name":"Qushnak",
    "wof:placetype":"locality"
},
  "geometry": {"coordinates":[67.61185999999999,33.89114],"type":"Point"}
}