{
  "type": "Feature",
  "properties": {
    "gn:admin1_code":"13",
    "gn:admin2_code":"108.0",
    "gn:asciiname":"Qal'ah-ye Na'ib Salar",
    "gn:country_code":"AF",
    "gn:dem":2023,
    "gn:feature_class":"P",
    "gn:feature_code":"PPL",
    "gn:name":"Qal\u2018ah-ye N\u0101\u2019\u012bb S\u0101l\u0101r",
    "gn:population":0,
    "gn:timezone":"Asia/Kabul",
    "iso:country":"AF",
    "name:fas_x_preferred":[
        "\u0642\u0644\u0639\u06c0 \u0646\u0627\u0626\u0628 \u0633\u0627\u0644\u0627\u0631"
    ],
    "name:und_x_variant":[
        "Kala-Naibsalar",
        "Qal\u2018a N\u0101\u2019ebs\u0101l\u0101r",
        "Qal\u2018ah-ye N\u0101\u2019\u012bb S\u0101l\u0101r",
        "Qal\u2018eh-ye N\u0101\u2019ebs\u0101l\u0101r",
        "\u0642\u0644\u0639\u0647 \u0646\u0627\u0639\u06cc\u0628 \u0633\u0627\u0644\u0627\u0631"
    ],
    "wof:name":"Qal'ah-ye Na'ib Salar",
    "wof:placetype":"locality"
},
  "geometry": {"coordinates":[68.99904000000001,34.54408],"type":"Point"}
}