{
  "type": "Feature",
  "properties": {
    "gn:admin1_code":"11",
    "gn:admin2_code":"2013",
    "gn:asciiname":"Khulah-ye Salar",
    "gn:country_code":"AF",
    "gn:dem":2208,
    "gn:feature_class":"P",
    "gn:feature_code":"PPL",
    "gn:name":"Kh\u016blah-ye S\u0101l\u0101r",
    "gn:population":0,
    "gn:timezone":"Asia/Kabul",
    "iso:country":"AF",
    "name:und_x_variant":[
        "Parvar",
        "Khvolah-e S\u0101l\u0101r",
        "Pa\u1e5fwa\u1e5f",
        "Khola-i-S\u0101l\u0101\u1e5f",
        "Khulayi-Salar",
        "Kh\u016blah-ye S\u0101l\u0101r",
        "\u062e\u0648\u0644\u06c0 \u0633\u0627\u0644\u0627\u0631",
        "Kholah-e-S\u0101l\u0101r",
        "Kh\u016blah-ye Parwar",
        "\u062e\u0648\u0644\u06c0 \u067e\u0631\u0648\u0631"
    ],
    "wof:name":"Khulah-ye Salar",
    "wof:placetype":"locality"
},
  "geometry": {"coordinates":[63.18492,33.75181],"type":"Point"}
}