{
  "type": "Feature",
  "properties": {
    "gn:admin1_code":"28",
    "gn:admin2_code":"2507.0",
    "gn:asciiname":"Ghazgay Kelay",
    "gn:country_code":"AF",
    "gn:dem":1653,
    "gn:feature_class":"P",
    "gn:feature_code":"PPL",
    "gn:name":"Ghazgay K\u00ealay",
    "gn:population":0,
    "gn:timezone":"Asia/Kabul",
    "iso:country":"AF",
    "name:und_x_variant":[
        "Gazgaykalay",
        "Ghazgay K\u00ealay",
        "\u063a\u0632\u06af\u06cc \u06a9\u0644\u06cc",
        "Ghazgay Kalay"
    ],
    "wof:name":"Ghazgay Kelay",
    "wof:placetype":"locality"
},
  "geometry": {"coordinates":[66.9008,31.91949],"type":"Point"}
}