{
  "type": "Feature",
  "properties": {
    "gn:admin1_code":"06",
    "gn:admin2_code":"2103",
    "gn:asciiname":"Karbasi",
    "gn:country_code":"AF",
    "gn:dem":1282,
    "gn:feature_class":"P",
    "gn:feature_code":"PPL",
    "gn:name":"Karb\u0101s\u012b",
    "gn:population":0,
    "gn:timezone":"Asia/Kabul",
    "iso:country":"AF",
    "name:und_x_variant":[
        "Karb\u0101s\u012b",
        "\u06a9\u0631\u0628\u0627\u0633\u06cc"
    ],
    "wof:name":"Karbasi",
    "wof:placetype":"locality"
},
  "geometry": {"coordinates":[63.52585,32.79102],"type":"Point"}
}