{
  "type": "Feature",
  "properties": {
    "gn:admin1_code":"06",
    "gn:admin2_code":"2107",
    "gn:asciiname":"Karez-e 'Askak",
    "gn:country_code":"AF",
    "gn:dem":813,
    "gn:feature_class":"P",
    "gn:feature_code":"PPL",
    "gn:name":"K\u0101r\u0113z-e \u2018Askak",
    "gn:population":0,
    "gn:timezone":"Asia/Kabul",
    "iso:country":"AF",
    "name:fas_x_preferred":[
        "K\u0101r\u0113z-e \u2018Askak"
    ],
    "name:fas_x_variant":[
        "\u06a9\u0627\u0631\u06d0\u0632 \u0639\u0633\u06a9\u06a9"
    ],
    "name:und_x_variant":[
        "K\u0101r\u0113ze \u2018Askak",
        "K\u0101r\u012bz-e \u2018Askak",
        "\u06a9\u0627\u0631\u06d0\u0632 \u0639\u0633\u06a9\u06a9"
    ],
    "wof:name":"Karez-e 'Askak",
    "wof:placetype":"locality"
},
  "geometry": {"coordinates":[61.64394,32.84004],"type":"Point"}
}