{
  "type": "Feature",
  "properties": {
    "gn:admin1_code":"01",
    "gn:admin2_code":"1101.0",
    "gn:asciiname":"Chawush Darah",
    "gn:country_code":"AF",
    "gn:dem":2089,
    "gn:feature_class":"P",
    "gn:feature_code":"PPL",
    "gn:name":"Ch\u0101wush Darah",
    "gn:population":0,
    "gn:timezone":"Asia/Kabul",
    "iso:country":"AF",
    "name:und_x_variant":[
        "\u010cawu\u0161 Darrah",
        "\u0686\u0627\u0648\u0634 \u062f\u0631\u0647",
        "Chavosh Darreh",
        "Ch\u0101wush Darah"
    ],
    "wof:name":"Chawush Darah",
    "wof:placetype":"locality"
},
  "geometry": {"coordinates":[70.59444000000001,37.28023],"type":"Point"}
}