{
  "type": "Feature",
  "properties": {
    "gn:admin1_code":"09",
    "gn:admin2_code":"2707",
    "gn:asciiname":"Siyah Sang-e Bala",
    "gn:country_code":"AF",
    "gn:dem":3369,
    "gn:feature_class":"P",
    "gn:feature_code":"PPL",
    "gn:name":"Siy\u0101h Sang-e B\u0101l\u0101",
    "gn:population":0,
    "gn:timezone":"Asia/Kabul",
    "iso:country":"AF",
    "name:und_x_variant":[
        "Sy\u0101hsange B\u0101l\u0101",
        "Siakhsangi-Bala",
        "S\u012b\u0101h Sang-e B\u0101l\u0101",
        "\u0633\u06cc\u0627\u0647 \u0633\u0646\u06af \u0628\u0627\u0644\u0627",
        "Siy\u0101h Sang-e B\u0101l\u0101"
    ],
    "wof:name":"Siyah Sang-e Bala",
    "wof:placetype":"locality"
},
  "geometry": {"coordinates":[66.50824,34.43583],"type":"Point"}
}