{
  "type": "Feature",
  "properties": {
    "gn:admin1_code":"11",
    "gn:admin2_code":"2006",
    "gn:asciiname":"Kamar Zard",
    "gn:country_code":"AF",
    "gn:dem":1289,
    "gn:feature_class":"P",
    "gn:feature_code":"PPL",
    "gn:name":"Kamar Zard",
    "gn:population":0,
    "gn:timezone":"Asia/Kabul",
    "iso:country":"AF",
    "name:und_x_variant":[
        "Kamarzard",
        "Kamar Zard",
        "\u06a9\u0645\u0631 \u0632\u0631\u062f"
    ],
    "wof:name":"Kamar Zard",
    "wof:placetype":"locality"
},
  "geometry": {"coordinates":[62.04506,34.83212],"type":"Point"}
}