{
  "type": "Feature",
  "properties": {
    "gn:admin1_code":"09",
    "gn:admin2_code":"2710",
    "gn:asciiname":"Naw-e Galah Alif",
    "gn:country_code":"AF",
    "gn:dem":2563,
    "gn:feature_class":"P",
    "gn:feature_code":"PPL",
    "gn:name":"N\u0101w-e Galah Alif",
    "gn:population":0,
    "gn:timezone":"Asia/Kabul",
    "iso:country":"AF",
    "name:und_x_variant":[
        "Navi-Galaalif",
        "N\u0101we Gala Alef",
        "N\u0101w-e Galah Alif",
        "\u0646\u0627\u0648 \u06af\u0644\u0647 \u0627\u0644\u0641",
        "N\u0101w-e Galleh Alef"
    ],
    "wof:name":"Naw-e Galah Alif",
    "wof:placetype":"locality"
},
  "geometry": {"coordinates":[64.6819,33.96542],"type":"Point"}
}