{
  "type": "Feature",
  "properties": {
    "gn:admin1_code":"5",
    "gn:admin2_code":"2802.0",
    "gn:asciiname":"Bulolah",
    "gn:country_code":"AF",
    "gn:dem":2430,
    "gn:feature_class":"P",
    "gn:feature_code":"PPLA2",
    "gn:name":"Bul\u014dlah",
    "gn:population":0,
    "gn:timezone":"Asia/Kabul",
    "iso:country":"AF",
    "name:und_x_variant":[
        "Bol\u016bleh",
        "Bol\u014dla",
        "Bolowleh",
        "Bulola",
        "Bul\u014dlah",
        "\u0628\u0644\u0648\u0644\u0647"
    ],
    "wof:name":"Bulolah",
    "wof:placetype":"locality"
},
  "geometry": {"coordinates":[68.0879,34.87706],"type":"Point"}
}