{
  "type": "Feature",
  "properties": {
    "gn:admin1_code":"28",
    "gn:admin2_code":"2502.0",
    "gn:asciiname":"Ahmad Kala",
    "gn:country_code":"AF",
    "gn:dem":1898,
    "gn:feature_class":"P",
    "gn:feature_code":"PPL",
    "gn:name":"A\u1e29mad Kal\u0101",
    "gn:population":0,
    "gn:timezone":"Asia/Kabul",
    "iso:country":"AF",
    "name:und_x_variant":[
        "Akhmedkala",
        "A\u1e29mad Kal\u0101",
        "\u0627\u062d\u0645\u062f \u06a9\u0644\u0627"
    ],
    "wof:name":"Ahmad Kala",
    "wof:placetype":"locality"
},
  "geometry": {"coordinates":[67.56418000000001,32.58871],"type":"Point"}
}