{
  "type": "Feature",
  "properties": {
    "gn:admin1_code":"30",
    "gn:admin2_code":"1610.0",
    "gn:asciiname":"Bogusht",
    "gn:country_code":"AF",
    "gn:dem":1005,
    "gn:feature_class":"P",
    "gn:feature_code":"PPL",
    "gn:name":"B\u014dgusht",
    "gn:population":0,
    "gn:timezone":"Asia/Kabul",
    "iso:country":"AF",
    "name:und_x_variant":[
        "Bogosht",
        "B\u014dgusht",
        "\u0628\u0648\u06af\u0634\u062a"
    ],
    "wof:name":"Bogusht",
    "wof:placetype":"locality"
},
  "geometry": {"coordinates":[66.82443000000001,36.0169],"type":"Point"}
}