{
  "type": "Feature",
  "properties": {
    "gn:admin1_code":"07",
    "gn:admin2_code":"1804",
    "gn:asciiname":"Shakh",
    "gn:country_code":"AF",
    "gn:dem":1217,
    "gn:feature_class":"P",
    "gn:feature_code":"PPL",
    "gn:name":"Sh\u0101kh",
    "gn:population":0,
    "gn:timezone":"Asia/Kabul",
    "iso:country":"AF",
    "name:und_x_variant":[
        "Qala S\u0101kh",
        "Sakh",
        "Sh\u0101kh",
        "\u0634\u0627\u062e"
    ],
    "wof:name":"Shakh",
    "wof:placetype":"locality"
},
  "geometry": {"coordinates":[64.12038000000001,35.60364000000001],"type":"Point"}
}