{
  "type": "Feature",
  "properties": {
    "gn:admin1_code":"08",
    "gn:admin2_code":"607",
    "gn:asciiname":"Nay Qal'ah",
    "gn:country_code":"AF",
    "gn:dem":2865,
    "gn:feature_class":"P",
    "gn:feature_code":"PPL",
    "gn:name":"Nay Qal\u2018ah",
    "gn:population":0,
    "gn:timezone":"Asia/Kabul",
    "iso:country":"AF",
    "name:fas_x_preferred":[
        "\u0646\u064a\u0642\u0644\u0647"
    ],
    "name:rus_x_preferred":[
        "\u041d\u0430\u0439\u043a\u0430\u043b\u0430"
    ],
    "name:und_x_variant":[
        "Naykala",
        "Nayqala",
        "Nayqalah",
        "Nay Qal\u2018ah",
        "\u0646\u06cc \u0642\u0644\u0639\u0647"
    ],
    "wof:name":"Nay Qal'ah",
    "wof:placetype":"locality"
},
  "geometry": {"coordinates":[67.73335,33.22754],"type":"Point"}
}