{
  "type": "Feature",
  "properties": {
    "gn:admin1_code":"37",
    "gn:admin2_code":"3210.0",
    "gn:asciiname":"Sal Kelay",
    "gn:country_code":"AF",
    "gn:dem":1181,
    "gn:feature_class":"P",
    "gn:feature_code":"PPL",
    "gn:name":"Sal K\u00ealay",
    "gn:population":0,
    "gn:timezone":"Asia/Kabul",
    "iso:country":"AF",
    "name:rus_x_preferred":[
        "Sal\u2019kalay"
    ],
    "name:und_x_variant":[
        "Sal Kalay",
        "Sal K\u00ealay",
        "\u0633\u0644 \u06a9\u0644\u06cc"
    ],
    "wof:name":"Sal Kelay",
    "wof:placetype":"locality"
},
  "geometry": {"coordinates":[70.04925,33.51622],"type":"Point"}
}