{
  "type": "Feature",
  "properties": {
    "gn:admin1_code":"41",
    "gn:admin2_code":"3401.0",
    "gn:asciiname":"Biniqulak",
    "gn:country_code":"AF",
    "gn:dem":2230,
    "gn:feature_class":"P",
    "gn:feature_code":"PPL",
    "gn:name":"Biniqulak",
    "gn:population":0,
    "gn:timezone":"Asia/Kabul",
    "iso:country":"AF",
    "name:und_x_variant":[
        "\u0628\u0646\u0642\u0644\u06a9",
        "B\u012bn\u012bqolak"
    ],
    "wof:name":"Biniqulak",
    "wof:placetype":"locality"
},
  "geometry": {"coordinates":[66.12356,33.79908],"type":"Point"}
}