{
  "type": "Feature",
  "properties": {
    "gn:admin1_code":"39",
    "gn:admin2_code":"2603",
    "gn:asciiname":"Potian",
    "gn:country_code":"AF",
    "gn:dem":2737,
    "gn:feature_class":"P",
    "gn:feature_code":"PPL",
    "gn:name":"P\u014d\u1e6f\u012b\u0101n",
    "gn:population":0,
    "gn:timezone":"Asia/Kabul",
    "iso:country":"AF",
    "name:und_x_variant":[
        "P\u014dty\u0101n",
        "P\u014d\u1e6f\u012b\u0101n",
        "\u067e\u0648\u067c\u06cc\u0627\u0646",
        "Powty\u0101n"
    ],
    "wof:name":"Potian",
    "wof:placetype":"locality"
},
  "geometry": {"coordinates":[66.63432,33.2176],"type":"Point"}
}