{
  "type": "Feature",
  "properties": {
    "gn:admin1_code":"8",
    "gn:admin2_code":"614.0",
    "gn:asciiname":"Ghulam Sadiq Kelay",
    "gn:country_code":"AF",
    "gn:dem":2100,
    "gn:feature_class":"P",
    "gn:feature_code":"PPL",
    "gn:name":"Ghul\u0101m \u015ead\u012bq K\u00ealay",
    "gn:population":0,
    "gn:timezone":"Asia/Kabul",
    "iso:country":"AF",
    "name:fas_x_preferred":[
        "\u0642\u0631\u064a\u06c0 \u063a\u0644\u0627\u0645 \u0635\u062f\u064a\u0642"
    ],
    "name:und_x_variant":[
        "Gulyamsiddik-Kalay",
        "Ghul\u0101m \u015ead\u012bq K\u00ealay",
        "Ghol\u0101m \u015eedd\u012bq Kalay",
        "\u063a\u0644\u0627\u0645 \u0635\u062f\u064a\u0642 \u06a9\u0644\u06cc"
    ],
    "wof:name":"Ghulam Sadiq Kelay",
    "wof:placetype":"locality"
},
  "geometry": {"coordinates":[68.43991,33.39395],"type":"Point"}
}