{
  "type": "Feature",
  "properties": {
    "gn:admin1_code":"30",
    "gn:admin2_code":"1606",
    "gn:asciiname":"Zuzan",
    "gn:country_code":"AF",
    "gn:dem":345,
    "gn:feature_class":"P",
    "gn:feature_code":"PPL",
    "gn:name":"Zuzan",
    "gn:population":0,
    "gn:timezone":"Asia/Kabul",
    "iso:country":"AF",
    "name:rus_x_preferred":[
        "\u0417\u0443\u0437\u0430\u043d"
    ],
    "name:und_x_variant":[
        "Zozan",
        "Zuzan",
        "\u0632\u0632\u0646"
    ],
    "wof:name":"Zuzan",
    "wof:placetype":"locality"
},
  "geometry": {"coordinates":[66.94856999999999,36.76937],"type":"Point"}
}