{
  "type": "Feature",
  "properties": {
    "gn:admin1_code":"27",
    "gn:admin2_code":"409",
    "gn:asciiname":"Sa'adat Khel",
    "gn:country_code":"AF",
    "gn:dem":2467,
    "gn:feature_class":"P",
    "gn:feature_code":"PPL",
    "gn:name":"Sa\u2018\u0101dat Kh\u0113l",
    "gn:population":0,
    "gn:timezone":"Asia/Kabul",
    "iso:country":"AF",
    "name:rus_x_preferred":[
        "Saadatkheyl\u2019"
    ],
    "name:und_x_variant":[
        "Sa\u2018\u0101\u1e0fatkh\u0113l",
        "S\u2018\u0101dat Kh\u0113l",
        "Sa\u2018\u0101dat Kheyl",
        "\u0633\u0639\u0627\u062f\u062a \u062e\u064a\u0644",
        "Sa\u2018\u0101dat Kh\u0113l",
        "\u0633\u0639\u0627\u062f\u062a \u062e\u06d0\u0644"
    ],
    "wof:name":"Sa'adat Khel",
    "wof:placetype":"locality"
},
  "geometry": {"coordinates":[68.37756,33.80812],"type":"Point"}
}