{
  "type": "Feature",
  "properties": {
    "gn:admin1_code":"27",
    "gn:admin2_code":"408.0",
    "gn:asciiname":"Dzhoasia",
    "gn:country_code":"AF",
    "gn:dem":2331,
    "gn:feature_class":"P",
    "gn:feature_code":"PPL",
    "gn:name":"Dzhoasia",
    "gn:population":0,
    "gn:timezone":"Asia/Kabul",
    "iso:country":"AF",
    "name:und_x_variant":[
        "J\u014d-\u0101sy\u0101",
        "J\u014dy-e \u0100s\u012b\u0101b",
        "J\u016b \u0100s\u012b\u0101",
        "J\u014dy-e \u0100sy\u0101b",
        "\u062c\u0648\u06cc \u0622\u0633\u064a\u0627\u0628",
        "J\u014d \u0100sy\u0101",
        "\u062c\u0648 \u0622\u0633\u06cc\u0627"
    ],
    "wof:name":"Dzhoasia",
    "wof:placetype":"locality"
},
  "geometry": {"coordinates":[68.70729,34.35323],"type":"Point"}
}