{
  "type": "Feature",
  "properties": {
    "gn:admin1_code":"35",
    "gn:admin2_code":"902.0",
    "gn:asciiname":"Gohar Khan Bandah",
    "gn:country_code":"AF",
    "gn:dem":1334,
    "gn:feature_class":"P",
    "gn:feature_code":"PPL",
    "gn:name":"G\u014dhar Kh\u0101n B\u0101n\u1e0fah",
    "gn:population":0,
    "gn:timezone":"Asia/Kabul",
    "iso:country":"AF",
    "name:und_x_variant":[
        "G\u014dhar Kh\u0101n B\u0101n\u1e0fah",
        "\u06af\u0648\u0647\u0631 \u062e\u0627\u0646 \u0628\u0627\u0646\u0689\u0647"
    ],
    "wof:name":"Gohar Khan Bandah",
    "wof:placetype":"locality"
},
  "geometry": {"coordinates":[70.43796999999998,34.63867],"type":"Point"}
}