{
  "type": "Feature",
  "properties": {
    "gn:admin1_code":"10",
    "gn:admin2_code":"2303.0",
    "gn:asciiname":"Karez-e Naswarian",
    "gn:country_code":"AF",
    "gn:dem":1061,
    "gn:feature_class":"P",
    "gn:feature_code":"PPL",
    "gn:name":"K\u0101r\u0113z-e Nasw\u0101r\u012b\u0101n",
    "gn:population":0,
    "gn:timezone":"Asia/Kabul",
    "iso:country":"AF",
    "name:rus_x_preferred":[
        "Karezi-Nasvar\u2019yan"
    ],
    "name:und_x_variant":[
        "K\u0101\u1e5f\u0113ze Nasw\u0101\u1e5fy\u0101n",
        "K\u0101r\u0113z-e Nasw\u0101r\u012b\u0101n",
        "\u06a9\u0627\u0631\u06d0\u0632 \u0646\u0633\u0648\u0627\u0631\u06cc\u0627\u0646",
        "K\u0101r\u012bz-e Nasw\u0101\u1e5fy\u0101n"
    ],
    "wof:name":"Karez-e Naswarian",
    "wof:placetype":"locality"
},
  "geometry": {"coordinates":[64.94181,32.3766],"type":"Point"}
}