{
  "type": "Feature",
  "properties": {
    "gn:admin1_code":"23",
    "gn:admin2_code":"2413.0",
    "gn:asciiname":"Shaykhayinah",
    "gn:country_code":"AF",
    "gn:dem":1719,
    "gn:feature_class":"P",
    "gn:feature_code":"PPL",
    "gn:name":"Shaykhayinah",
    "gn:population":0,
    "gn:timezone":"Asia/Kabul",
    "iso:country":"AF",
    "name:fas_x_preferred":[
        "\u0633\u062e\u064a\u0646\u0647"
    ],
    "name:und_x_variant":[
        "Sheykhayina",
        "\u0160ekhayena",
        "Shaykhayinah",
        "\u0634\u06cc\u062e\u06cc\u0646\u0647",
        "Sekhayenah"
    ],
    "wof:name":"Shaykhayinah",
    "wof:placetype":"locality"
},
  "geometry": {"coordinates":[67.20281999999999,31.61573],"type":"Point"}
}