{
  "type": "Feature",
  "properties": {
    "gn:admin1_code":"37",
    "gn:admin2_code":"3211.0",
    "gn:asciiname":"Jan Kala",
    "gn:country_code":"AF",
    "gn:dem":1215,
    "gn:feature_class":"P",
    "gn:feature_code":"PPL",
    "gn:name":"J\u0101n Kal\u0101",
    "gn:population":0,
    "gn:timezone":"Asia/Kabul",
    "iso:country":"AF",
    "name:fas_x_preferred":[
        "\u0642\u0644\u0639\u06c0 \u0632\u0627\u0646"
    ],
    "name:und_x_variant":[
        "J\u0101n Kal\u0101",
        "Dzhankala",
        "Dz\u0101n Kal\u0101",
        "\u062c\u0627\u0646 \u06a9\u0644\u0627"
    ],
    "wof:name":"Jan Kala",
    "wof:placetype":"locality"
},
  "geometry": {"coordinates":[69.88773,33.28764],"type":"Point"}
}