{
  "type": "Feature",
  "properties": {
    "gn:admin1_code":"08",
    "gn:admin2_code":"603",
    "gn:asciiname":"Pay Mast 'Ali",
    "gn:country_code":"AF",
    "gn:dem":2323,
    "gn:feature_class":"P",
    "gn:feature_code":"PPL",
    "gn:name":"P\u0101y Mast \u2018Al\u012b",
    "gn:population":0,
    "gn:timezone":"Asia/Kabul",
    "iso:country":"AF",
    "name:fas_x_preferred":[
        "\u067e\u0627\u06cc \u0645\u0633\u062a \u0639\u0644\u06cc"
    ],
    "name:und_x_variant":[
        "Paymastali",
        "P\u0101y Mast \u2018Al\u012b",
        "P\u0101y Mast\u2018al\u012b"
    ],
    "wof:name":"Pay Mast 'Ali",
    "wof:placetype":"locality"
},
  "geometry": {"coordinates":[68.37906,33.71201],"type":"Point"}
}