{
  "type": "Feature",
  "properties": {
    "gn:admin1_code":"08",
    "gn:admin2_code":"616",
    "gn:asciiname":"Habib Khel",
    "gn:country_code":"AF",
    "gn:dem":2645,
    "gn:feature_class":"P",
    "gn:feature_code":"PPL",
    "gn:name":"\u1e28ab\u012bb Kh\u0113l",
    "gn:population":0,
    "gn:timezone":"Asia/Kabul",
    "iso:country":"AF",
    "name:rus_x_preferred":[
        "Khabibkheyl\u2019"
    ],
    "name:und_x_variant":[
        "\u1e28ab\u012bb Kh\u0113l",
        "\u1e28ab\u012bb Kheyl",
        "\u062d\u0628\u06cc\u0628 \u062e\u06d0\u0644"
    ],
    "wof:name":"Habib Khel",
    "wof:placetype":"locality"
},
  "geometry": {"coordinates":[68.63875999999999,33.6511],"type":"Point"}
}