{
  "type": "Feature",
  "properties": {
    "gn:admin1_code":"41",
    "gn:admin2_code":"3403.0",
    "gn:asciiname":"Khak-e Diljam",
    "gn:country_code":"AF",
    "gn:dem":2623,
    "gn:feature_class":"P",
    "gn:feature_code":"PPL",
    "gn:name":"Kh\u0101k-e Diljam",
    "gn:population":0,
    "gn:timezone":"Asia/Kabul",
    "iso:country":"AF",
    "name:und_x_variant":[
        "Kh\u0101k-e Diljam",
        "\u062e\u0627\u06a9 \u062f\u0644\u062c\u0645"
    ],
    "wof:name":"Khak-e Diljam",
    "wof:placetype":"locality"
},
  "geometry": {"coordinates":[66.34881999999999,34.22169],"type":"Point"}
}