{
  "type": "Feature",
  "properties": {
    "gn:admin1_code":"23",
    "gn:admin2_code":"2413.0",
    "gn:asciiname":"Abo Kala",
    "gn:country_code":"AF",
    "gn:dem":1743,
    "gn:feature_class":"P",
    "gn:feature_code":"PPL",
    "gn:name":"Ab\u014d Kal\u0101",
    "gn:population":0,
    "gn:timezone":"Asia/Kabul",
    "iso:country":"AF",
    "name:fas_x_preferred":[
        "\u0642\u0644\u0639\u0647\u0654 \u0627\u0628\u0648"
    ],
    "name:pus_x_preferred":[
        "\u0627\u0628\u0648 \u06a9\u0644\u0627"
    ],
    "name:und_x_variant":[
        "Abo Kal\u0101",
        "Abu Kh\u0101n",
        "Abu Chan",
        "Ab\u016b Kal\u0101",
        "Ab\u014d Kal\u0101",
        "\u0627\u0628\u0648 \u06a9\u0644\u0627"
    ],
    "wof:name":"Abo Kala",
    "wof:placetype":"locality"
},
  "geometry": {"coordinates":[67.22906999999999,31.62247],"type":"Point"}
}