{
  "type": "Feature",
  "properties": {
    "gn:admin1_code":"34",
    "gn:admin2_code":"1006.0",
    "gn:asciiname":"Dab Kelay",
    "gn:country_code":"AF",
    "gn:dem":2237,
    "gn:feature_class":"P",
    "gn:feature_code":"PPL",
    "gn:name":"Dab K\u00ealay",
    "gn:population":0,
    "gn:timezone":"Asia/Kabul",
    "iso:country":"AF",
    "name:fas_x_preferred":[
        "\u0642\u0631\u064a\u06c0 \u062f\u0628"
    ],
    "name:und_x_variant":[
        "Dabkalay",
        "\u062f\u0628 \u06a9\u0644\u06cc",
        "Dab Kalay",
        "Dab K\u00ealay"
    ],
    "wof:name":"Dab Kelay",
    "wof:placetype":"locality"
},
  "geometry": {"coordinates":[71.26009999999999,35.23373],"type":"Point"}
}