{
  "type": "Feature",
  "properties": {
    "gn:admin1_code":"26",
    "gn:admin2_code":"1215",
    "gn:asciiname":"Hazar Jomich",
    "gn:country_code":"AF",
    "gn:dem":1003,
    "gn:feature_class":"P",
    "gn:feature_code":"PPL",
    "gn:name":"Haz\u0101r J\u014dmich",
    "gn:population":0,
    "gn:timezone":"Asia/Kabul",
    "iso:country":"AF",
    "name:rus_x_preferred":[
        "\u0425\u0430\u0437\u0430\u0440\u0434\u0436\u043e\u043c\u0438\u0433"
    ],
    "name:und_x_variant":[
        "Haz\u0101r J\u014dmech",
        "Khazardzhomig",
        "Hez\u0101r Jowmech",
        "Haz\u0101r Jome\u010d",
        "Hez\u0101r J\u016bmech",
        "Haz\u0101r J\u014dmich",
        "\u0647\u0632\u0627\u0631 \u062c\u0648\u0645\u0686"
    ],
    "wof:name":"Hazar Jomich",
    "wof:placetype":"locality"
},
  "geometry": {"coordinates":[69.49766,36.90432],"type":"Point"}
}