{
  "type": "Feature",
  "properties": {
    "gn:admin1_code":"30",
    "gn:admin2_code":"1610.0",
    "gn:asciiname":"Aw-e Ahmad",
    "gn:country_code":"AF",
    "gn:dem":2020,
    "gn:feature_class":"P",
    "gn:feature_code":"PPL",
    "gn:name":"\u0100w-e A\u1e29mad",
    "gn:population":0,
    "gn:timezone":"Asia/Kabul",
    "iso:country":"AF",
    "name:und_x_variant":[
        "Awe A\u1e96ma\u1e0f",
        "\u0100v-e A\u1e29mad",
        "\u0100b-e A\u1e29mad",
        "\u0100w-e A\u1e29mad",
        "\u0622\u0648 \u0627\u062d\u0645\u062f"
    ],
    "wof:name":"Aw-e Ahmad",
    "wof:placetype":"locality"
},
  "geometry": {"coordinates":[66.88739,35.77073],"type":"Point"}
}