{
  "type": "Feature",
  "properties": {
    "gn:admin1_code":"34",
    "gn:admin2_code":"1008",
    "gn:asciiname":"Shamir Kot",
    "gn:country_code":"AF",
    "gn:dem":896,
    "gn:feature_class":"P",
    "gn:feature_code":"PPL",
    "gn:name":"Sh\u0101m\u012br K\u014d\u1e6f",
    "gn:population":0,
    "gn:timezone":"Asia/Kabul",
    "iso:country":"AF",
    "name:fas_x_preferred":[
        "\u0634\u0645\u064a\u0631 \u0643\u0648\u062a"
    ],
    "name:und_x_variant":[
        "\u0160\u0101m\u012br Kot",
        "Shamirkot",
        "Sham\u012br Kowt",
        "Sh\u0101m\u012br K\u014d\u1e6f",
        "\u0634\u0627\u0645\u06cc\u0631 \u06a9\u0648\u067c"
    ],
    "wof:name":"Shamir Kot",
    "wof:placetype":"locality"
},
  "geometry": {"coordinates":[71.09430999999999,34.92615],"type":"Point"}
}