{
  "type": "Feature",
  "properties": {
    "gn:admin1_code":"05",
    "gn:admin2_code":"2805",
    "gn:asciiname":"Par Joy",
    "gn:country_code":"AF",
    "gn:dem":2662,
    "gn:feature_class":"P",
    "gn:feature_code":"PPL",
    "gn:name":"Par J\u014dy",
    "gn:population":0,
    "gn:timezone":"Asia/Kabul",
    "iso:country":"AF",
    "name:und_x_variant":[
        "Pa\u1e5fj\u014dy",
        "Pardzhoy",
        "Bar J\u014dy",
        "Parj\u016by",
        "Par J\u014dy",
        "\u067e\u0631 \u062c\u0648\u06cc"
    ],
    "wof:name":"Par Joy",
    "wof:placetype":"locality"
},
  "geometry": {"coordinates":[67.01697,34.34545],"type":"Point"}
}