{
  "type": "Feature",
  "properties": {
    "gn:admin1_code":"14",
    "gn:admin2_code":"204.0",
    "gn:asciiname":"Kandi Khel",
    "gn:country_code":"AF",
    "gn:dem":2043,
    "gn:feature_class":"P",
    "gn:feature_code":"PPL",
    "gn:name":"Kan\u1e0f\u012b Kh\u0113l",
    "gn:population":0,
    "gn:timezone":"Asia/Kabul",
    "iso:country":"AF",
    "name:fas_x_preferred":[
        "\u0643\u0646\u062f\u06cc \u062e\u064a\u0644"
    ],
    "name:rus_x_preferred":[
        "\u041a\u0430\u043d\u0434\u0438\u0445\u0435\u0439\u043b\u044c"
    ],
    "name:und_x_variant":[
        "Kandikh\u0113l",
        "Kandikheyl\u2019",
        "Kand\u012bkheyl",
        "Kan\u1e0f\u012b Kh\u0113l",
        "\u06a9\u0646\u0689\u06cc \u062e\u06d0\u0644"
    ],
    "wof:name":"Kandi Khel",
    "wof:placetype":"locality"
},
  "geometry": {"coordinates":[69.63271999999999,35.0583],"type":"Point"}
}