{
  "type": "Feature",
  "properties": {
    "gn:admin1_code":"36",
    "gn:admin2_code":"707",
    "gn:asciiname":"Mazari Algad",
    "gn:country_code":"AF",
    "gn:dem":1888,
    "gn:feature_class":"P",
    "gn:feature_code":"PPL",
    "gn:name":"Maz\u0101r\u012b Alga\u1e0f",
    "gn:population":0,
    "gn:timezone":"Asia/Kabul",
    "iso:country":"AF",
    "name:rus_x_preferred":[
        "Mazaril\u2019gad"
    ],
    "name:und_x_variant":[
        "Maz\u0101r\u012b Alga\u1e0f",
        "Maz\u0101r\u012b Lga\u1e0f",
        "\u0645\u0632\u0627\u0631\u06cc \u0644\u06af\u0689"
    ],
    "wof:name":"Mazari Algad",
    "wof:placetype":"locality"
},
  "geometry": {"coordinates":[69.88858,33.76159000000001],"type":"Point"}
}