{
  "type": "Feature",
  "properties": {
    "gn:admin1_code":"2",
    "gn:admin2_code":"1903.0",
    "gn:asciiname":"Buyah",
    "gn:country_code":"AF",
    "gn:dem":1419,
    "gn:feature_class":"P",
    "gn:feature_code":"PPL",
    "gn:name":"B\u016byah",
    "gn:population":0,
    "gn:timezone":"Asia/Kabul",
    "iso:country":"AF",
    "name:und_x_variant":[
        "B\u016bya",
        "Buya",
        "B\u016byah",
        "\u0628\u0648\u06cc\u0647"
    ],
    "wof:name":"Buyah",
    "wof:placetype":"locality"
},
  "geometry": {"coordinates":[63.44934,34.73601],"type":"Point"}
}