{
  "type": "Feature",
  "properties": {
    "gn:admin1_code":"30",
    "gn:admin2_code":"1608",
    "gn:asciiname":"Tughdan 'Ali",
    "gn:country_code":"AF",
    "gn:dem":802,
    "gn:feature_class":"P",
    "gn:feature_code":"PPL",
    "gn:name":"Tughdan \u2018Al\u012b",
    "gn:population":0,
    "gn:timezone":"Asia/Kabul",
    "iso:country":"AF",
    "name:und_x_variant":[
        "Tughdan \u2018Al\u012b",
        "\u062a\u063a\u062f\u0646 \u0639\u0644\u06cc",
        "Toghdan \u2018Al\u012b"
    ],
    "wof:name":"Tughdan 'Ali",
    "wof:placetype":"locality"
},
  "geometry": {"coordinates":[66.36815,36.36296],"type":"Point"}
}