{
  "type": "Feature",
  "properties": {
    "gn:admin1_code":"28",
    "gn:admin2_code":"2506",
    "gn:asciiname":"Taghan-e Shamali",
    "gn:country_code":"AF",
    "gn:dem":1399,
    "gn:feature_class":"P",
    "gn:feature_code":"PPL",
    "gn:name":"T\u0101gh\u0101n-e Sham\u0101l\u012b",
    "gn:population":0,
    "gn:timezone":"Asia/Kabul",
    "iso:country":"AF",
    "name:und_x_variant":[
        "\u0160am\u0101li",
        "T\u0101gh\u0101n",
        "T\u0101gh\u0101n Sham\u0101li",
        "Tagan-Shamali",
        "\u062a\u0627\u063a\u0627\u0646 \u0634\u0645\u0627\u0644\u06cc",
        "T\u0101gh\u0101n-e Shom\u0101l\u012b",
        "T\u0101gh\u0101n-e Sham\u0101l\u012b"
    ],
    "wof:name":"Taghan-e Shamali",
    "wof:placetype":"locality"
},
  "geometry": {"coordinates":[66.49651999999999,31.90924],"type":"Point"}
}