{
  "type": "Feature",
  "properties": {
    "gn:admin1_code":"28",
    "gn:admin2_code":"2504.0",
    "gn:asciiname":"Sharqi Ghulam Nabi Kelay",
    "gn:country_code":"AF",
    "gn:dem":1779,
    "gn:feature_class":"P",
    "gn:feature_code":"PPL",
    "gn:name":"Sharq\u012b Ghul\u0101m Nab\u012b K\u00ealay",
    "gn:population":0,
    "gn:timezone":"Asia/Kabul",
    "iso:country":"AF",
    "name:und_x_variant":[
        "\u0160arqi Ghol\u0101m Nabi Kalay",
        "Sharki-Gulyamnabi-Kolay",
        "Sharq\u012b Ghul\u0101m Nab\u012b K\u00ealay",
        "\u0634\u0631\u0642\u06cc \u063a\u0644\u0627\u0645 \u0646\u0628\u06cc \u06a9\u0644\u06cc",
        "Sharq\u012b Ghol\u0101m Nab\u012b Kalay"
    ],
    "wof:name":"Sharqi Ghulam Nabi Kelay",
    "wof:placetype":"locality"
},
  "geometry": {"coordinates":[66.7188,32.51488],"type":"Point"}
}