{
  "type": "Feature",
  "properties": {
    "gn:admin1_code":"11",
    "gn:admin2_code":"2014",
    "gn:asciiname":"Karez-e Taylak",
    "gn:country_code":"AF",
    "gn:dem":1251,
    "gn:feature_class":"P",
    "gn:feature_code":"PPL",
    "gn:name":"K\u0101r\u0113z-e Taylak",
    "gn:population":0,
    "gn:timezone":"Asia/Kabul",
    "iso:country":"AF",
    "name:und_x_variant":[
        "K\u0101\u1e5f\u0113ze T\u0113lak",
        "K\u0101r\u012bz-e T\u0113lak",
        "K\u0101r\u0113z-e Taylak",
        "\u06a9\u0627\u0631\u06d0\u0632 \u062a\u06cc\u0644\u06a9"
    ],
    "wof:name":"Karez-e Taylak",
    "wof:placetype":"locality"
},
  "geometry": {"coordinates":[61.91214,33.16524],"type":"Point"}
}