{
  "type": "Feature",
  "properties": {
    "gn:admin1_code":"33",
    "gn:admin2_code":"3103.0",
    "gn:asciiname":"Bulokah",
    "gn:country_code":"AF",
    "gn:dem":2483,
    "gn:feature_class":"P",
    "gn:feature_code":"PPL",
    "gn:name":"Bul\u014dkah",
    "gn:population":0,
    "gn:timezone":"Asia/Kabul",
    "iso:country":"AF",
    "name:und_x_variant":[
        "Bol\u014dka",
        "Bol\u016bka",
        "Bul\u014dkah",
        "\u0628\u0644\u0648\u06a9\u0647"
    ],
    "wof:name":"Bulokah",
    "wof:placetype":"locality"
},
  "geometry": {"coordinates":[65.86064,35.3248],"type":"Point"}
}