{
  "type": "Feature",
  "properties": {
    "gn:admin1_code":"26",
    "gn:admin2_code":"1202",
    "gn:asciiname":"Qun Ghurbay",
    "gn:country_code":"AF",
    "gn:dem":1082,
    "gn:feature_class":"P",
    "gn:feature_code":"PPL",
    "gn:name":"Q\u016bn Ghurb\u0101y",
    "gn:population":0,
    "gn:timezone":"Asia/Kabul",
    "iso:country":"AF",
    "name:und_x_variant":[
        "Q\u016bn Ghu\u1e5fb\u0101y (4)",
        "Q\u016bn Ghurb\u0101y",
        "\u0642\u0648\u0646 \u063a\u0631\u0628\u0627\u06cc"
    ],
    "wof:name":"Qun Ghurbay",
    "wof:placetype":"locality"
},
  "geometry": {"coordinates":[69.37391,36.49844],"type":"Point"}
}