{
  "type": "Feature",
  "properties": {
    "gn:admin1_code":"09",
    "gn:admin2_code":"2707",
    "gn:asciiname":"Sokhtagi",
    "gn:country_code":"AF",
    "gn:dem":2779,
    "gn:feature_class":"P",
    "gn:feature_code":"PPL",
    "gn:name":"S\u014dkhtag\u012b",
    "gn:population":0,
    "gn:timezone":"Asia/Kabul",
    "iso:country":"AF",
    "name:und_x_variant":[
        "S\u014dkhtagi",
        "S\u014dkhtahg\u012b",
        "S\u016bkhteg\u012b",
        "S\u014dkhtag\u012b",
        "\u0633\u0648\u062e\u062a\u06af\u06cc"
    ],
    "wof:name":"Sokhtagi",
    "wof:placetype":"locality"
},
  "geometry": {"coordinates":[66.26545,34.63814],"type":"Point"}
}