{
  "type": "Feature",
  "properties": {
    "gn:admin1_code":"28",
    "gn:admin2_code":"2510",
    "gn:asciiname":"Sarab",
    "gn:country_code":"AF",
    "gn:dem":2769,
    "gn:feature_class":"P",
    "gn:feature_code":"PPL",
    "gn:name":"Sa\u1e5f\u0101b",
    "gn:population":0,
    "gn:timezone":"Asia/Kabul",
    "iso:country":"AF",
    "wof:name":"Sarab",
    "wof:placetype":"locality"
},
  "geometry": {"coordinates":[67.13333,33.05],"type":"Point"}
}