{
  "type": "Feature",
  "properties": {
    "gn:admin1_code":"41",
    "gn:admin2_code":"3408.0",
    "gn:asciiname":"Jar-e Karam Zar",
    "gn:country_code":"AF",
    "gn:dem":2334,
    "gn:feature_class":"P",
    "gn:feature_code":"PPL",
    "gn:name":"Jar-e Karam Z\u0101r",
    "gn:population":0,
    "gn:timezone":"Asia/Kabul",
    "iso:country":"AF",
    "name:und_x_variant":[
        "Dzhari-Karamzar",
        "Jar-e Karam Z\u0101r",
        "Jar-e Karamz\u0101r",
        "\u062c\u0631 \u06a9\u0631\u0645 \u0632\u0627\u0631"
    ],
    "wof:name":"Jar-e Karam Zar",
    "wof:placetype":"locality"
},
  "geometry": {"coordinates":[66.15469,34.1107],"type":"Point"}
}