{
  "type": "Feature",
  "properties": {
    "gn:admin1_code":"10",
    "gn:admin2_code":"2305",
    "gn:asciiname":"Dwazdah-Imam",
    "gn:country_code":"AF",
    "gn:dem":1671,
    "gn:feature_class":"P",
    "gn:feature_code":"PPL",
    "gn:name":"Dw\u0101zdah-Im\u0101m",
    "gn:population":0,
    "gn:timezone":"Asia/Kabul",
    "iso:country":"AF",
    "name:rus_x_preferred":[
        "\u0414\u0432\u0430\u0437\u0434\u0430\u0438\u043c\u0430\u043c"
    ],
    "name:und_x_variant":[
        "\u1e0ew\u0101z\u1e0fa-em\u0101m",
        "Dvazdaimam",
        "Dav\u0101zdah Em\u0101m",
        "Dw\u0101zdah-Im\u0101m",
        "\u062f\u0648\u0627\u0632\u062f\u0647 \u0627\u0645\u0627\u0645",
        "Dav\u0101zdeh Em\u0101m"
    ],
    "wof:name":"Dwazdah-Imam",
    "wof:placetype":"locality"
},
  "geometry": {"coordinates":[65.08604,33.15493],"type":"Point"}
}