{
  "type": "Feature",
  "properties": {
    "gn:admin1_code":"40",
    "gn:admin2_code":"303.0",
    "gn:asciiname":"Sumt-e Shah Mir",
    "gn:country_code":"AF",
    "gn:dem":1732,
    "gn:feature_class":"P",
    "gn:feature_code":"PPL",
    "gn:name":"Sumt-e Sh\u0101h M\u012br",
    "gn:population":0,
    "gn:timezone":"Asia/Kabul",
    "iso:country":"AF",
    "name:fas_x_preferred":[
        "\u0633\u0645\u062a\u0654 \u0634\u0627\u0647\u0645\u064a\u0631"
    ],
    "name:und_x_variant":[
        "Sumte \u0160\u0101hmir",
        "Sumti-Shakhmir",
        "Sumt-e Sh\u0101hm\u012br",
        "Sumt-e Sh\u0101h M\u012br",
        "\u0633\u0645\u062a \u0634\u0627\u0647 \u0645\u06cc\u0631"
    ],
    "wof:name":"Sumt-e Shah Mir",
    "wof:placetype":"locality"
},
  "geometry": {"coordinates":[69.21887,35.16253],"type":"Point"}
}