{
  "type": "Feature",
  "properties": {
    "gn:admin1_code":"8",
    "gn:admin2_code":"604.0",
    "gn:asciiname":"Chowak",
    "gn:country_code":"AF",
    "gn:dem":2968,
    "gn:feature_class":"P",
    "gn:feature_code":"PPL",
    "gn:name":"Chowak",
    "gn:population":0,
    "gn:timezone":"Asia/Kabul",
    "iso:country":"AF",
    "name:und_x_variant":[
        "Chavak",
        "\u010cawak",
        "Chahbak",
        "Chowak",
        "\u0686\u0648\u06a9"
    ],
    "wof:name":"Chowak",
    "wof:placetype":"locality"
},
  "geometry": {"coordinates":[67.55207,34.09413],"type":"Point"}
}