{
  "type": "Feature",
  "properties": {
    "gn:admin1_code":"08",
    "gn:admin2_code":"610.0",
    "gn:asciiname":"Srah Dargah",
    "gn:country_code":"AF",
    "gn:dem":2281,
    "gn:feature_class":"P",
    "gn:feature_code":"PPL",
    "gn:name":"Srah Darg\u0101h",
    "gn:population":0,
    "gn:timezone":"Asia/Kabul",
    "iso:country":"AF",
    "name:und_x_variant":[
        "Sradarga",
        "S\u1e5f\u0259h \u1e0ea\u1e5fg\u0101",
        "\u0633\u0631\u0647 \u062f\u0631\u06af\u0627\u0647",
        "Srah Darg\u0101",
        "Srah Darg\u0101h"
    ],
    "wof:name":"Srah Dargah",
    "wof:placetype":"locality"
},
  "geometry": {"coordinates":[68.04769,32.21132],"type":"Point"}
}