{
  "type": "Feature",
  "properties": {
    "gn:admin1_code":"18",
    "gn:admin2_code":"810.0",
    "gn:asciiname":"'Ulya Khel",
    "gn:country_code":"AF",
    "gn:dem":993,
    "gn:feature_class":"P",
    "gn:feature_code":"PPL",
    "gn:name":"\u2018Uly\u0101 Kh\u0113l",
    "gn:population":0,
    "gn:timezone":"Asia/Kabul",
    "iso:country":"AF",
    "name:fas_x_preferred":[
        "\u0627\u0644\u064a\u0627 \u062e\u064a\u0644"
    ],
    "name:rus_x_preferred":[
        "Al\u2019yakheyl\u2019"
    ],
    "name:und_x_variant":[
        "Aly\u0101kh\u0113l",
        "Aly\u0101kheyl",
        "\u2018Oly\u0101 Kh\u0113l",
        "\u2018Uly\u0101 Kh\u0113l",
        "\u0639\u0644\u06cc\u0627 \u062e\u06d0\u0644"
    ],
    "wof:name":"'Ulya Khel",
    "wof:placetype":"locality"
},
  "geometry": {"coordinates":[70.68941,34.12981],"type":"Point"}
}