{
  "type": "Feature",
  "properties": {
    "gn:admin1_code":"28",
    "gn:admin2_code":"2502",
    "gn:asciiname":"Shash Gaw",
    "gn:country_code":"AF",
    "gn:dem":1902,
    "gn:feature_class":"P",
    "gn:feature_code":"PPL",
    "gn:name":"Shash G\u0101w",
    "gn:population":0,
    "gn:timezone":"Asia/Kabul",
    "iso:country":"AF",
    "name:und_x_variant":[
        "\u0160a\u0161g\u0101w",
        "Shashgav",
        "Shash G\u0101w",
        "\u0634\u0634 \u06af\u0627\u0648",
        "Shesh G\u0101v"
    ],
    "wof:name":"Shash Gaw",
    "wof:placetype":"locality"
},
  "geometry": {"coordinates":[67.57495,32.59891],"type":"Point"}
}