{
  "type": "Feature",
  "properties": {
    "gn:admin1_code":"26",
    "gn:admin2_code":"1201.0",
    "gn:asciiname":"Qarah Parchow",
    "gn:country_code":"AF",
    "gn:dem":751,
    "gn:feature_class":"P",
    "gn:feature_code":"PPL",
    "gn:name":"Qarah Parchow",
    "gn:population":0,
    "gn:timezone":"Asia/Kabul",
    "iso:country":"AF",
    "name:fas_x_preferred":[
        "\u0642\u0631\u0647 \u067e\u0631\u0686\u0627\u0628"
    ],
    "name:rus_x_preferred":[
        "\u041a\u0430\u0440\u0430\u043f\u0430\u0440\u0447\u0430\u0432"
    ],
    "name:und_x_variant":[
        "Qara Par\u010daw",
        "Qareh Parchow",
        "Karaparchav",
        "Qareh Parch\u0101b",
        "Qarah Parchow",
        "\u0642\u0631\u0647 \u067e\u0631\u0686\u0648"
    ],
    "wof:name":"Qarah Parchow",
    "wof:placetype":"locality"
},
  "geometry": {"coordinates":[69.45746,36.79171],"type":"Point"}
}