{
  "type": "Feature",
  "properties": {
    "gn:admin1_code":"24",
    "gn:admin2_code":"1404",
    "gn:asciiname":"Gul Baq",
    "gn:country_code":"AF",
    "gn:dem":404,
    "gn:feature_class":"P",
    "gn:feature_code":"PPL",
    "gn:name":"Gul B\u0101q",
    "gn:population":0,
    "gn:timezone":"Asia/Kabul",
    "iso:country":"AF",
    "name:rus_x_preferred":[
        "\u0413\u0443\u043b\u044c\u0431\u0430\u043a"
    ],
    "name:und_x_variant":[
        "Gul B\u0101q",
        "Gul\u2019bak",
        "Gol B\u0101q",
        "Gul B\u0101gh",
        "\u06af\u0644 \u0628\u0627\u063a",
        "\u06af\u0644 \u0628\u0627\u0642"
    ],
    "wof:name":"Gul Baq",
    "wof:placetype":"locality"
},
  "geometry": {"coordinates":[68.82689999999999,36.63193],"type":"Point"}
}