{
  "type": "Feature",
  "properties": {
    "gn:admin1_code":"27",
    "gn:admin2_code":"404",
    "gn:asciiname":"Zerat",
    "gn:country_code":"AF",
    "gn:dem":3134,
    "gn:feature_class":"P",
    "gn:feature_code":"PPL",
    "gn:name":"Z\u0113r\u0101t",
    "gn:population":0,
    "gn:timezone":"Asia/Kabul",
    "iso:country":"AF",
    "name:und_x_variant":[
        "Z\u0113\u1e5f\u0101t",
        "Zerat",
        "Z\u0113r\u0101t",
        "Z\u012br\u0101t",
        "\u0632\u06cc\u0631\u0627\u062a"
    ],
    "wof:name":"Zerat",
    "wof:placetype":"locality"
},
  "geometry": {"coordinates":[67.56749000000001,34.27769],"type":"Point"}
}