{
  "type": "Feature",
  "properties": {
    "gn:admin1_code":"30",
    "gn:admin2_code":"1609",
    "gn:asciiname":"Qipchaq",
    "gn:country_code":"AF",
    "gn:dem":583,
    "gn:feature_class":"P",
    "gn:feature_code":"PPL",
    "gn:name":"Qipchaq",
    "gn:population":0,
    "gn:timezone":"Asia/Kabul",
    "iso:country":"AF",
    "name:und_x_variant":[
        "Oipchaq",
        "Qipchaq",
        "Qepchaq",
        "\u0642\u067e\u0686\u0642"
    ],
    "wof:name":"Qipchaq",
    "wof:placetype":"locality"
},
  "geometry": {"coordinates":[66.87661,36.33825],"type":"Point"}
}