{
  "type": "Feature",
  "properties": {
    "gn:admin1_code":"19",
    "gn:admin2_code":"2201.0",
    "gn:asciiname":"Ghulam Haidar",
    "gn:country_code":"AF",
    "gn:dem":486,
    "gn:feature_class":"P",
    "gn:feature_code":"PPL",
    "gn:name":"Ghul\u0101m \u1e28a\u012bdar",
    "gn:population":0,
    "gn:timezone":"Asia/Kabul",
    "iso:country":"AF",
    "name:und_x_variant":[
        "Ghol\u0101m\u1e96ay\u1e0far",
        "Ghul\u0101m \u1e28a\u012bdar",
        "Ghol\u0101m \u1e28aydar Kh\u0101n"
    ],
    "wof:name":"Ghulam Haidar",
    "wof:placetype":"locality"
},
  "geometry": {"coordinates":[61.86666999999999,30.985],"type":"Point"}
}