{
  "type": "Feature",
  "properties": {
    "gn:admin1_code":"36",
    "gn:admin2_code":"706.0",
    "gn:asciiname":"Khibay",
    "gn:country_code":"AF",
    "gn:dem":2020,
    "gn:feature_class":"P",
    "gn:feature_code":"PPL",
    "gn:name":"Khibay",
    "gn:population":0,
    "gn:timezone":"Asia/Kabul",
    "iso:country":"AF",
    "name:und_x_variant":[
        "Khebay",
        "\u062e\u0628\u06cc"
    ],
    "wof:name":"Khibay",
    "wof:placetype":"locality"
},
  "geometry": {"coordinates":[69.75668,33.65979],"type":"Point"}
}