{
  "type": "Feature",
  "properties": {
    "gn:admin1_code":"26",
    "gn:admin2_code":"1208",
    "gn:asciiname":"Yamchi",
    "gn:country_code":"AF",
    "gn:dem":817,
    "gn:feature_class":"P",
    "gn:feature_code":"PPL",
    "gn:name":"Y\u0101mch\u012b",
    "gn:population":0,
    "gn:timezone":"Asia/Kabul",
    "iso:country":"AF",
    "name:ara_x_preferred":[
        "\u064a\u0627\u0645\u062a\u0634\u064a"
    ],
    "name:azb_x_preferred":[
        "\u06cc\u0627\u0645\u0686\u06cc"
    ],
    "name:aze_x_preferred":[
        "Yam\u00e7\u0131"
    ],
    "name:fas_x_preferred":[
        "\u06cc\u0627\u0645\u0686\u06cc"
    ],
    "name:ita_x_preferred":[
        "Yamchi"
    ],
    "name:mlg_x_preferred":[
        "Yamchi"
    ],
    "name:msa_x_preferred":[
        "Yamchi"
    ],
    "name:rus_x_preferred":[
        "\u042f\u043c\u0447\u0438"
    ],
    "name:tur_x_preferred":[
        "Yam\u00e7\u0131"
    ],
    "name:und_x_variant":[
        "Y\u0101mci",
        "Y\u0101m\u010di (1)",
        "Y\u0101mch\u012b"
    ],
    "name:urd_x_preferred":[
        "\u06cc\u0627\u0645\u0686\u06cc"
    ],
    "wof:name":"Yamchi",
    "wof:placetype":"locality"
},
  "geometry": {"coordinates":[69.64624000000001,37.05717],"type":"Point"}
}