{
  "type": "Feature",
  "properties": {
    "gn:admin1_code":"5",
    "gn:admin2_code":"2805.0",
    "gn:asciiname":"Jangriq",
    "gn:country_code":"AF",
    "gn:dem":2796,
    "gn:feature_class":"P",
    "gn:feature_code":"PPL",
    "gn:name":"Jangr\u012bq",
    "gn:population":0,
    "gn:timezone":"Asia/Kabul",
    "iso:country":"AF",
    "name:und_x_variant":[
        "Dzhangrik",
        "Jangr\u012bq",
        "\u062c\u0646\u06af\u0631\u06cc\u0642"
    ],
    "wof:name":"Jangriq",
    "wof:placetype":"locality"
},
  "geometry": {"coordinates":[66.68295999999999,34.38171],"type":"Point"}
}