{
  "type": "Feature",
  "properties": {
    "gn:admin1_code":"05",
    "gn:admin2_code":"2806",
    "gn:asciiname":"Majnun",
    "gn:country_code":"AF",
    "gn:dem":2637,
    "gn:feature_class":"P",
    "gn:feature_code":"PPL",
    "gn:name":"Majn\u016bn",
    "gn:population":0,
    "gn:timezone":"Asia/Kabul",
    "iso:country":"AF",
    "name:und_x_variant":[
        "Madzhnun",
        "Majn\u014dn",
        "Majn\u016bn",
        "\u0645\u062c\u0646\u0648\u0646"
    ],
    "wof:name":"Majnun",
    "wof:placetype":"locality"
},
  "geometry": {"coordinates":[66.56395999999999,34.12886],"type":"Point"}
}