{
  "type": "Feature",
  "properties": {
    "gn:admin1_code":"31",
    "gn:admin2_code":"1708.0",
    "gn:asciiname":"'Aliabad",
    "gn:country_code":"AF",
    "gn:dem":312,
    "gn:feature_class":"P",
    "gn:feature_code":"PPL",
    "gn:name":"\u2018Al\u012b\u0101b\u0101d",
    "gn:population":0,
    "gn:timezone":"Asia/Kabul",
    "iso:country":"AF",
    "name:und_x_variant":[
        "\u2018Al\u012b\u0101b\u0101d",
        "\u0639\u0644\u06cc \u0622\u0628\u0627\u062f"
    ],
    "wof:name":"'Aliabad",
    "wof:placetype":"locality"
},
  "geometry": {"coordinates":[66.41191999999999,36.79976],"type":"Point"}
}