{
  "type": "Feature",
  "properties": {
    "gn:admin1_code":"27",
    "gn:admin2_code":"409",
    "gn:asciiname":"Khalimshar",
    "gn:country_code":"AF",
    "gn:dem":2485,
    "gn:feature_class":"P",
    "gn:feature_code":"PPL",
    "gn:name":"Khalimshar",
    "gn:population":0,
    "gn:timezone":"Asia/Kabul",
    "iso:country":"AF",
    "name:fas_x_preferred":[
        "\u062d\u0644\u0645 \u0634\u0627\u0631"
    ],
    "name:und_x_variant":[
        "Halem \u0160\u0101r",
        "\u1e28al\u012bm S\u0332h\u0332\u0101r",
        "\u1e28alem S\u0332h\u0332\u0101r",
        "\u062d\u0644\u0645 \u0634\u0627\u0631",
        "\u062d\u0644\u064a\u0645 \u069a\u0627\u0631"
    ],
    "wof:name":"Khalimshar",
    "wof:placetype":"locality"
},
  "geometry": {"coordinates":[68.29764,33.73039],"type":"Point"}
}