{
  "type": "Feature",
  "properties": {
    "gn:admin1_code":"29",
    "gn:admin2_code":"2916",
    "gn:asciiname":"Malang Kheyl",
    "gn:country_code":"AF",
    "gn:dem":2060,
    "gn:feature_class":"P",
    "gn:feature_code":"PPL",
    "gn:name":"Malang Kheyl",
    "gn:population":0,
    "gn:timezone":"Asia/Kabul",
    "iso:country":"AF",
    "name:rus_x_preferred":[
        "Mulangkheyl\u2019"
    ],
    "name:und_x_variant":[
        "Malangkh\u0113l",
        "Malankh\u0113l",
        "\u0645\u0644\u0646\u06af \u062e\u06d0\u0644",
        "Malang Kheyl"
    ],
    "wof:name":"Malang Kheyl",
    "wof:placetype":"locality"
},
  "geometry": {"coordinates":[68.40191999999999,32.78031],"type":"Point"}
}