{
  "type": "Feature",
  "properties": {
    "gn:admin1_code":"26",
    "gn:admin2_code":"1201.0",
    "gn:asciiname":"Bagi-Miri",
    "gn:country_code":"AF",
    "gn:dem":786,
    "gn:feature_class":"P",
    "gn:feature_code":"PPL",
    "gn:name":"Bagi-Miri",
    "gn:population":0,
    "gn:timezone":"Asia/Kabul",
    "iso:country":"AF",
    "name:rus_x_preferred":[
        "\u0411\u0430\u0433\u0438-\u041c\u0438\u0440\u0438"
    ],
    "name:und_x_variant":[
        "B\u0101gh-i-M\u012br",
        "B\u0101gh-i-M\u012b\u1e5fi",
        "Bagi-Miri",
        "B\u0101gh-e M\u012br\u012b"
    ],
    "wof:name":"Bagi-Miri",
    "wof:placetype":"locality"
},
  "geometry": {"coordinates":[69.34,36.74],"type":"Point"}
}