{
  "type": "Feature",
  "properties": {
    "gn:admin1_code":"30",
    "gn:admin2_code":"1609.0",
    "gn:asciiname":"Bahram Gor",
    "gn:country_code":"AF",
    "gn:dem":1012,
    "gn:feature_class":"P",
    "gn:feature_code":"PPL",
    "gn:name":"Bahr\u0101m G\u014dr",
    "gn:population":0,
    "gn:timezone":"Asia/Kabul",
    "iso:country":"AF",
    "name:und_x_variant":[
        "Bahr\u0101m Gor",
        "Bahr\u0101m-e G\u016br",
        "Bahr\u0101m G\u014dr",
        "\u0628\u0647\u0631\u0627\u0645 \u06af\u0648\u0631"
    ],
    "wof:name":"Bahram Gor",
    "wof:placetype":"locality"
},
  "geometry": {"coordinates":[67.06839000000001,36.20942],"type":"Point"}
}