{
  "type": "Feature",
  "properties": {
    "gn:admin1_code":"34",
    "gn:admin2_code":"1010.0",
    "gn:asciiname":"Kharah",
    "gn:country_code":"AF",
    "gn:dem":976,
    "gn:feature_class":"P",
    "gn:feature_code":"PPL",
    "gn:name":"Kh\u0101rah",
    "gn:population":0,
    "gn:timezone":"Asia/Kabul",
    "iso:country":"AF",
    "name:und_x_variant":[
        "Khara",
        "Kh\u0101\u1e5fa",
        "Kh\u0101rah",
        "\u062e\u0627\u0631\u0647"
    ],
    "wof:name":"Kharah",
    "wof:placetype":"locality"
},
  "geometry": {"coordinates":[70.99851,34.94043],"type":"Point"}
}