{
  "type": "Feature",
  "properties": {
    "gn:admin1_code":"34",
    "gn:admin2_code":"1013.0",
    "gn:asciiname":"Pakhalak Khwar",
    "gn:country_code":"AF",
    "gn:dem":1519,
    "gn:feature_class":"P",
    "gn:feature_code":"PPL",
    "gn:name":"Pakhalak Khwa\u1e5f",
    "gn:population":0,
    "gn:timezone":"Asia/Kabul",
    "iso:country":"AF",
    "name:fas_x_preferred":[
        "\u067e\u062e\u0644\u0643 \u062e\u0648\u0631"
    ],
    "name:und_x_variant":[
        "Pakhalakkhvar",
        "Pakhalak Khwa\u1e5f",
        "\u067e\u062e\u0644\u06a9 \u062e\u0648\u0693"
    ],
    "wof:name":"Pakhalak Khwar",
    "wof:placetype":"locality"
},
  "geometry": {"coordinates":[70.73003,34.69843],"type":"Point"}
}