{
  "type": "Feature",
  "properties": {
    "gn:admin1_code":"39",
    "gn:admin2_code":"2601.0",
    "gn:asciiname":"Ghulaman",
    "gn:country_code":"AF",
    "gn:dem":1316,
    "gn:feature_class":"P",
    "gn:feature_code":"PPL",
    "gn:name":"Ghul\u0101m\u0101n",
    "gn:population":0,
    "gn:timezone":"Asia/Kabul",
    "iso:country":"AF",
    "name:und_x_variant":[
        "Gulyaman",
        "Ghul\u0101m\u0101n",
        "\u063a\u0644\u0627\u0645\u0627\u0646",
        "Ghol\u0101m\u0101n"
    ],
    "wof:name":"Ghulaman",
    "wof:placetype":"locality"
},
  "geometry": {"coordinates":[65.88158,32.63485],"type":"Point"}
}