{
  "type": "Feature",
  "properties": {
    "gn:admin1_code":"09",
    "gn:admin2_code":"2703.0",
    "gn:asciiname":"Khel-e Gowmal",
    "gn:country_code":"AF",
    "gn:dem":1824,
    "gn:feature_class":"P",
    "gn:feature_code":"PPL",
    "gn:name":"Kh\u0113l-e Gowm\u0101l",
    "gn:population":0,
    "gn:timezone":"Asia/Kabul",
    "iso:country":"AF",
    "name:und_x_variant":[
        "Kh\u0113le Gawm\u0101l",
        "Kheyl-e G\u0101vm\u0101l",
        "Kh\u0113l-e Gowm\u0101l",
        "\u062e\u06d0\u0644 \u06af\u0648\u0645\u0627\u0644"
    ],
    "wof:name":"Khel-e Gowmal",
    "wof:placetype":"locality"
},
  "geometry": {"coordinates":[63.61921,34.11789],"type":"Point"}
}