{
  "type": "Feature",
  "properties": {
    "gn:admin1_code":"13",
    "gn:admin2_code":"109.0",
    "gn:asciiname":"Qal'ah-ye Na'im",
    "gn:country_code":"AF",
    "gn:dem":1819,
    "gn:feature_class":"P",
    "gn:feature_code":"PPLA2",
    "gn:name":"Qal\u2018ah-ye Na\u2018\u012bm",
    "gn:population":0,
    "gn:timezone":"Asia/Kabul",
    "iso:country":"AF",
    "name:und_x_variant":[
        "Kalanaim",
        "Qal\u2018eh Na\u2018\u012bm",
        "Qal\u2018ah-ye Na\u2018\u012bm",
        "Qal\u2018eh-ye Na\u2018\u012bm",
        "\u0642\u0644\u0639\u0647 \u0646\u0639\u064a\u0645"
    ],
    "wof:name":"Qal'ah-ye Na'im",
    "wof:placetype":"locality"
},
  "geometry": {"coordinates":[69.16705,34.39951],"type":"Point"}
}