{
  "type": "Feature",
  "properties": {
    "gn:admin1_code":"7",
    "gn:admin2_code":"1802.0",
    "gn:asciiname":"Aq Gunbaz (2)",
    "gn:country_code":"AF",
    "gn:dem":622,
    "gn:feature_class":"P",
    "gn:feature_code":"PPL",
    "gn:name":"Aq Gunbaz (2)",
    "gn:population":0,
    "gn:timezone":"Asia/Kabul",
    "iso:country":"AF",
    "wof:name":"Aq Gunbaz (2)",
    "wof:placetype":"locality"
},
  "geometry": {"coordinates":[64.55471999999999,36.015],"type":"Point"}
}