{
  "type": "Feature",
  "properties": {
    "gn:admin1_code":"34",
    "gn:admin2_code":"1004.0",
    "gn:asciiname":"Siyah Bandi",
    "gn:country_code":"AF",
    "gn:dem":1512,
    "gn:feature_class":"P",
    "gn:feature_code":"PPL",
    "gn:name":"Siy\u0101h Band\u012b",
    "gn:population":0,
    "gn:timezone":"Asia/Kabul",
    "iso:country":"AF",
    "name:rus_x_preferred":[
        "S\u2019yabandi"
    ],
    "name:und_x_variant":[
        "Sy\u0101ban\u1e0fi",
        "S\u012b\u0101h Band\u012b",
        "S\u012b\u0101hband\u012b",
        "Siy\u0101h Band\u012b",
        "\u0633\u064a\u0627\u0647 \u0628\u0646\u062f\u06cc"
    ],
    "wof:name":"Siyah Bandi",
    "wof:placetype":"locality"
},
  "geometry": {"coordinates":[71.39438,34.97135],"type":"Point"}
}