{
  "type": "Feature",
  "properties": {
    "gn:admin1_code":"18",
    "gn:admin2_code":"803",
    "gn:asciiname":"Kafar Khel",
    "gn:country_code":"AF",
    "gn:dem":2191,
    "gn:feature_class":"P",
    "gn:feature_code":"PPL",
    "gn:name":"K\u0101far Kh\u0113l",
    "gn:population":0,
    "gn:timezone":"Asia/Kabul",
    "iso:country":"AF",
    "name:fas_x_preferred":[
        "\u0643\u0627\u0641\u0631 \u062e\u064a\u0644"
    ],
    "name:rus_x_preferred":[
        "Kafarkheyl\u2019"
    ],
    "name:und_x_variant":[
        "K\u0101fa\u1e5fkh\u0113l",
        "K\u0101far Kh\u0113l",
        "K\u0101farkheyl",
        "\u06a9\u0627\u0641\u0631 \u062e\u06d0\u0644"
    ],
    "wof:name":"Kafar Khel",
    "wof:placetype":"locality"
},
  "geometry": {"coordinates":[69.63681,34.28111],"type":"Point"}
}