{
  "type": "Feature",
  "properties": {
    "gn:admin1_code":"41",
    "gn:admin2_code":"3403",
    "gn:asciiname":"Sar-e Talah",
    "gn:country_code":"AF",
    "gn:dem":2579,
    "gn:feature_class":"P",
    "gn:feature_code":"PPL",
    "gn:name":"Sar-e T\u0101lah",
    "gn:population":0,
    "gn:timezone":"Asia/Kabul",
    "iso:country":"AF",
    "name:und_x_variant":[
        "Sa\u1e5fe T\u0101la",
        "Sari-Tala",
        "Sar-e T\u0101lah",
        "Sar-e T\u0101leh",
        "\u0633\u0631 \u062a\u0627\u0644\u0647"
    ],
    "wof:name":"Sar-e Talah",
    "wof:placetype":"locality"
},
  "geometry": {"coordinates":[66.45469,34.08818],"type":"Point"}
}