{
  "type": "Feature",
  "properties": {
    "gn:admin1_code":"29",
    "gn:admin2_code":"2905.0",
    "gn:asciiname":"Baghgey",
    "gn:country_code":"AF",
    "gn:dem":2199,
    "gn:feature_class":"P",
    "gn:feature_code":"PPL",
    "gn:name":"B\u0101ghg\u00eay",
    "gn:population":0,
    "gn:timezone":"Asia/Kabul",
    "iso:country":"AF",
    "name:fas_x_preferred":[
        "\u0628\u0627\u063a\u06af\u06cc"
    ],
    "name:und_x_variant":[
        "Baggay",
        "\u0628\u0627\u063a\u06af\u06cd",
        "B\u0101ghgay",
        "B\u0101ghg\u00eay"
    ],
    "wof:name":"Baghgey",
    "wof:placetype":"locality"
},
  "geometry": {"coordinates":[68.61126,32.12191],"type":"Point"}
}