{
  "type": "Feature",
  "properties": {
    "gn:admin1_code":"03",
    "gn:admin2_code":"1308.0",
    "gn:asciiname":"Or",
    "gn:country_code":"AF",
    "gn:dem":2217,
    "gn:feature_class":"P",
    "gn:feature_code":"PPL",
    "gn:name":"\u014cr",
    "gn:population":0,
    "gn:timezone":"Asia/Kabul",
    "iso:country":"AF",
    "name:und_x_variant":[
        "\u014cr",
        "\u0627\u0648\u0631"
    ],
    "wof:name":"Or",
    "wof:placetype":"locality"
},
  "geometry": {"coordinates":[69.73806,36.0554],"type":"Point"}
}