{
  "type": "Feature",
  "properties": {
    "gn:admin1_code":"23",
    "gn:admin2_code":"2407",
    "gn:asciiname":"Gadian",
    "gn:country_code":"AF",
    "gn:dem":835,
    "gn:feature_class":"P",
    "gn:feature_code":"PPL",
    "gn:name":"G\u0101d\u012b\u0101n",
    "gn:population":0,
    "gn:timezone":"Asia/Kabul",
    "iso:country":"AF",
    "name:rus_x_preferred":[
        "Gad\u2019yan"
    ],
    "name:und_x_variant":[
        "G\u0101d\u012b\u0101n",
        "\u06af\u0627\u062f\u06cc\u0627\u0646",
        "G\u0101\u1e0fy\u0101n"
    ],
    "wof:name":"Gadian",
    "wof:placetype":"locality"
},
  "geometry": {"coordinates":[64.81118000000001,31.61534],"type":"Point"}
}