{
  "type": "Feature",
  "properties": {
    "gn:admin1_code":"28",
    "gn:admin2_code":"2504",
    "gn:asciiname":"Mirzayan",
    "gn:country_code":"AF",
    "gn:dem":2164,
    "gn:feature_class":"P",
    "gn:feature_code":"PPL",
    "gn:name":"M\u012brz\u0101y\u0101n",
    "gn:population":0,
    "gn:timezone":"Asia/Kabul",
    "iso:country":"AF",
    "name:und_x_variant":[
        "M\u012brz\u0101y\u0101n",
        "\u0645\u06cc\u0631\u0632\u0627\u06cc\u0627\u0646",
        "Mirz\u0101y\u0101n"
    ],
    "wof:name":"Mirzayan",
    "wof:placetype":"locality"
},
  "geometry": {"coordinates":[66.76518,32.63025],"type":"Point"}
}