{
  "type": "Feature",
  "properties": {
    "gn:admin1_code":"29",
    "gn:admin2_code":"2901",
    "gn:asciiname":"Shah Mod Khel",
    "gn:country_code":"AF",
    "gn:dem":2464,
    "gn:feature_class":"P",
    "gn:feature_code":"PPL",
    "gn:name":"Sh\u0101h M\u014dd Kh\u0113l",
    "gn:population":0,
    "gn:timezone":"Asia/Kabul",
    "iso:country":"AF",
    "name:und_x_variant":[
        "\u0160\u0101hmodkh\u0113l",
        "Shakhmodkheyl\u2019",
        "\u0634\u0627\u0647 \u0645\u062d\u0645\u062f \u062e\u06d0\u0644",
        "Sh\u0101h Mo\u1e29ammad Kheyl",
        "Sh\u0101h Mu\u1e29ammad Kh\u0113l",
        "Sh\u0101h M\u014dd Kh\u0113l",
        "\u0634\u0627\u0647 \u0645\u0648\u062f \u062e\u06d0\u0644"
    ],
    "wof:name":"Shah Mod Khel",
    "wof:placetype":"locality"
},
  "geometry": {"coordinates":[68.57420999999999,33.1426],"type":"Point"}
}