{
  "type": "Feature",
  "properties": {
    "gn:admin1_code":"41",
    "gn:admin2_code":"3403",
    "gn:asciiname":"Naw-e Qal'ah",
    "gn:country_code":"AF",
    "gn:dem":2746,
    "gn:feature_class":"P",
    "gn:feature_code":"PPL",
    "gn:name":"N\u0101w-e Qal\u2018ah",
    "gn:population":0,
    "gn:timezone":"Asia/Kabul",
    "iso:country":"AF",
    "name:und_x_variant":[
        "Naw\u0113 Qal\u2018a",
        "Navekala",
        "N\u0101w-e Qal\u2018ah",
        "N\u0101w-e Qal\u2018eh",
        "\u0646\u0627\u0648 \u0642\u0644\u0639\u0647"
    ],
    "wof:name":"Naw-e Qal'ah",
    "wof:placetype":"locality"
},
  "geometry": {"coordinates":[66.34249,34.28875],"type":"Point"}
}