{
  "type": "Feature",
  "properties": {
    "gn:admin1_code":"28",
    "gn:admin2_code":"2502.0",
    "gn:asciiname":"Baran Chinah",
    "gn:country_code":"AF",
    "gn:dem":1986,
    "gn:feature_class":"P",
    "gn:feature_code":"PPL",
    "gn:name":"B\u0101r\u0101n Ch\u012bnah",
    "gn:population":0,
    "gn:timezone":"Asia/Kabul",
    "iso:country":"AF",
    "name:und_x_variant":[
        "Baranchina",
        "B\u0101r\u0101n \u010cina",
        "B\u0101r\u0101n Ch\u012bnah",
        "\u0628\u0627\u0631\u0627\u0646 \u0686\u06cc\u0646\u0647",
        "B\u0101r\u0101n Ch\u012bneh"
    ],
    "wof:name":"Baran Chinah",
    "wof:placetype":"locality"
},
  "geometry": {"coordinates":[67.41043000000001,32.60613],"type":"Point"}
}