{
  "type": "Feature",
  "properties": {
    "gn:admin1_code":"03",
    "gn:admin2_code":"1308",
    "gn:asciiname":"Mir Shikar",
    "gn:country_code":"AF",
    "gn:dem":1637,
    "gn:feature_class":"P",
    "gn:feature_code":"PPL",
    "gn:name":"M\u012br Shik\u0101r",
    "gn:population":0,
    "gn:timezone":"Asia/Kabul",
    "iso:country":"AF",
    "name:und_x_variant":[
        "Mirshek\u0101r",
        "M\u012b\u1e5fsek\u0101\u1e5f",
        "M\u012br Shek\u0101r",
        "M\u012br Shik\u0101r",
        "\u0645\u06cc\u0631 \u0634\u06a9\u0627\u0631"
    ],
    "wof:name":"Mir Shikar",
    "wof:placetype":"locality"
},
  "geometry": {"coordinates":[69.49734000000001,35.96843],"type":"Point"}
}