{
  "type": "Feature",
  "properties": {
    "gn:admin1_code":"41",
    "gn:admin2_code":"3405.0",
    "gn:asciiname":"Kharzar",
    "gn:country_code":"AF",
    "gn:dem":2560,
    "gn:feature_class":"P",
    "gn:feature_code":"PPL",
    "gn:name":"Kharz\u0101r",
    "gn:population":0,
    "gn:timezone":"Asia/Kabul",
    "iso:country":"AF",
    "name:ceb_x_preferred":[
        "Kharzar"
    ],
    "name:fas_x_preferred":[
        "\u062e\u0627\u0631\u0632\u0627\u0631"
    ],
    "name:swe_x_preferred":[
        "Kharzar"
    ],
    "name:und_x_variant":[
        "Kharz\u0101r",
        "\u062e\u0631\u0632\u0627\u0631"
    ],
    "wof:name":"Kharzar",
    "wof:placetype":"locality"
},
  "geometry": {"coordinates":[66.04601,33.88423],"type":"Point"}
}