{
  "type": "Feature",
  "properties": {
    "gn:admin1_code":"23",
    "gn:admin2_code":"2411",
    "gn:asciiname":"Spinah Chinah",
    "gn:country_code":"AF",
    "gn:dem":1739,
    "gn:feature_class":"P",
    "gn:feature_code":"PPL",
    "gn:name":"Sp\u012bnah Ch\u012bnah",
    "gn:population":0,
    "gn:timezone":"Asia/Kabul",
    "iso:country":"AF",
    "name:und_x_variant":[
        "Sp\u012bna C\u0113n\u0113h",
        "Spinachena",
        "Sp\u012bnah Ch\u0113n\u0113h",
        "Sp\u012bnah Ch\u012bnah",
        "\u0633\u067e\u06cc\u0646\u0647 \u0686\u06cc\u0646\u0647"
    ],
    "wof:name":"Spinah Chinah",
    "wof:placetype":"locality"
},
  "geometry": {"coordinates":[66.66029,31.20159],"type":"Point"}
}