{
  "type": "Feature",
  "properties": {
    "gn:admin1_code":"23",
    "gn:admin2_code":"2405.0",
    "gn:asciiname":"Chahar Sang",
    "gn:country_code":"AF",
    "gn:dem":1433,
    "gn:feature_class":"P",
    "gn:feature_code":"PPL",
    "gn:name":"Chah\u0101r Sang",
    "gn:population":0,
    "gn:timezone":"Asia/Kabul",
    "iso:country":"AF",
    "name:fas_x_preferred":[
        "\u0686\u0627\u0631\u0633\u0646\u06af"
    ],
    "name:und_x_variant":[
        "\u010c\u0101rsang",
        "Charsan",
        "Ch\u0101r Sang",
        "\u0686\u0627\u0631 \u0633\u0646\u06af",
        "Chah\u0101r Sang",
        "\u0686\u0647\u0627\u0631 \u0633\u0646\u06af"
    ],
    "wof:name":"Chahar Sang",
    "wof:placetype":"locality"
},
  "geometry": {"coordinates":[65.52667,31.96617],"type":"Point"}
}