{
  "type": "Feature",
  "properties": {
    "gn:admin1_code":"10",
    "gn:admin2_code":"2310.0",
    "gn:asciiname":"Lich",
    "gn:country_code":"AF",
    "gn:dem":580,
    "gn:feature_class":"P",
    "gn:feature_code":"PPL",
    "gn:name":"Lich",
    "gn:population":0,
    "gn:timezone":"Asia/Kabul",
    "iso:country":"AF",
    "name:und_x_variant":[
        "Le\u010d",
        "Lich",
        "\u0644\u0686",
        "Lech"
    ],
    "wof:name":"Lich",
    "wof:placetype":"locality"
},
  "geometry": {"coordinates":[63.04205,30.24631],"type":"Point"}
}