{
  "type": "Feature",
  "properties": {
    "gn:admin1_code":"01",
    "gn:admin2_code":"1107.0",
    "gn:asciiname":"Walij",
    "gn:country_code":"AF",
    "gn:dem":2443,
    "gn:feature_class":"P",
    "gn:feature_code":"PPL",
    "gn:name":"Wal\u012bj",
    "gn:population":0,
    "gn:timezone":"Asia/Kabul",
    "iso:country":"AF",
    "name:und_x_variant":[
        "Wal\u012bj",
        "Valayj",
        "Valey",
        "Walayj",
        "\u0648\u0627\u064a\u062c"
    ],
    "wof:name":"Walij",
    "wof:placetype":"locality"
},
  "geometry": {"coordinates":[71.49453000000003,36.90381],"type":"Point"}
}