{
  "type": "Feature",
  "properties": {
    "gn:admin1_code":"3",
    "gn:admin2_code":"1305.0",
    "gn:asciiname":"Qarah",
    "gn:country_code":"AF",
    "gn:dem":1228,
    "gn:feature_class":"P",
    "gn:feature_code":"PPL",
    "gn:name":"Qarah",
    "gn:population":0,
    "gn:timezone":"Asia/Kabul",
    "iso:country":"AF",
    "name:ceb_x_preferred":[
        "Qarah"
    ],
    "name:sco_x_preferred":[
        "Qarah"
    ],
    "name:swe_x_preferred":[
        "Qarah"
    ],
    "name:und_x_variant":[
        "Qara",
        "Qareh",
        "\u0642\u0631\u0647"
    ],
    "wof:name":"Qarah",
    "wof:placetype":"locality"
},
  "geometry": {"coordinates":[68.20258000000001,35.36847],"type":"Point"}
}