{
  "type": "Feature",
  "properties": {
    "gn:admin1_code":"24",
    "gn:admin2_code":"1404",
    "gn:asciiname":"'Ayn ul Majar",
    "gn:country_code":"AF",
    "gn:dem":374,
    "gn:feature_class":"P",
    "gn:feature_code":"PPL",
    "gn:name":"\u2018Ayn ul Majar",
    "gn:population":0,
    "gn:timezone":"Asia/Kabul",
    "iso:country":"AF",
    "name:fas_x_preferred":[
        "\u0639\u06cc\u0646 \u0627\u0644\u0645\u062c\u0627\u0631"
    ],
    "name:rus_x_preferred":[
        "\u0410\u0439\u043d-\u0443\u043b\u044c-\u041c\u0430\u0434\u0436\u0430\u0440"
    ],
    "name:und_x_variant":[
        "\u2018Eynol Majar",
        "\u2018Aynul Maja\u1e5f",
        "Ayn-ul\u2019-Madzhar",
        "\u2018Ayn ol Majar",
        "\u2018Ayn ul Majar",
        "\u0639\u0649\u0646 \u0627\u0644\u0645\u062c\u0631"
    ],
    "wof:name":"'Ayn ul Majar",
    "wof:placetype":"locality"
},
  "geometry": {"coordinates":[68.68964,36.77471],"type":"Point"}
}