{
  "type": "Feature",
  "properties": {
    "gn:admin1_code":"23",
    "gn:admin2_code":"2411.0",
    "gn:asciiname":"Kshetah Siyahbat",
    "gn:country_code":"AF",
    "gn:dem":1367,
    "gn:feature_class":"P",
    "gn:feature_code":"PPL",
    "gn:name":"Ks\u0332h\u0332\u00eatah Siy\u0101hbat",
    "gn:population":0,
    "gn:timezone":"Asia/Kabul",
    "iso:country":"AF",
    "name:rus_x_preferred":[
        "Kshattas\u2019yabat"
    ],
    "name:und_x_variant":[
        "K\u0161atta Sy\u0101bat",
        "Ks\u0332h\u0332atah S\u012b\u0101bat",
        "Kshattah S\u012b\u0101bat",
        "Ks\u0332h\u0332\u00eatah S\u012b\u0101hbat",
        "\u06a9\u069a\u062a\u0647 \u0633\u064a\u0627\u0647 \u0628\u062a",
        "Ks\u0332h\u0332\u00eatah Siy\u0101hbat"
    ],
    "wof:name":"Kshetah Siyahbat",
    "wof:placetype":"locality"
},
  "geometry": {"coordinates":[66.51765999999999,31.26143],"type":"Point"}
}