{
  "type": "Feature",
  "properties": {
    "gn:admin1_code":"13",
    "gn:admin2_code":"108.0",
    "gn:asciiname":"Qal'ah-ye Jandah",
    "gn:country_code":"AF",
    "gn:dem":2399,
    "gn:feature_class":"P",
    "gn:feature_code":"PPL",
    "gn:name":"Qal\u2018ah-ye Jan\u1e0fah",
    "gn:population":0,
    "gn:timezone":"Asia/Kabul",
    "iso:country":"AF",
    "name:und_x_variant":[
        "Kaladzhanda",
        "Qal\u2018a Janda",
        "Qal\u2018eh-ye Janda",
        "Qal\u2018ah-ye Jandah",
        "Qal\u2018eh-ye Jandah",
        "Qal\u2018ah-ye Jan\u1e0fah",
        "\u0642\u0644\u0639\u0647 \u062c\u0646\u0689\u0647"
    ],
    "wof:name":"Qal'ah-ye Jandah",
    "wof:placetype":"locality"
},
  "geometry": {"coordinates":[68.90096,34.50465],"type":"Point"}
}