{
  "type": "Feature",
  "properties": {
    "gn:admin1_code":"11",
    "gn:admin2_code":"2001",
    "gn:asciiname":"Sara Now",
    "gn:country_code":"AF",
    "gn:dem":920,
    "gn:feature_class":"P",
    "gn:feature_code":"PPL",
    "gn:name":"Sar\u0101 Now",
    "gn:population":0,
    "gn:timezone":"Asia/Kabul",
    "iso:country":"AF",
    "name:und_x_variant":[
        "Sara-Nau",
        "Sa\u1e5f\u0101 Naw",
        "Sar\u0101 Now",
        "\u0633\u0631\u0627 \u0646\u0648"
    ],
    "wof:name":"Sara Now",
    "wof:placetype":"locality"
},
  "geometry": {"coordinates":[62.12056,34.35781],"type":"Point"}
}