{
  "type": "Feature",
  "properties": {
    "gn:admin1_code":"06",
    "gn:admin2_code":"2111",
    "gn:asciiname":"Na'l Dasht",
    "gn:country_code":"AF",
    "gn:dem":682,
    "gn:feature_class":"P",
    "gn:feature_code":"PPL",
    "gn:name":"Na\u2018l Dasht",
    "gn:population":0,
    "gn:timezone":"Asia/Kabul",
    "iso:country":"AF",
    "name:rus_x_preferred":[
        "Nal\u2019dasht"
    ],
    "name:und_x_variant":[
        "Na\u2018l Da\u0161t",
        "Na\u2018l Dasht",
        "\u0646\u0639\u0644 \u062f\u0634\u062a"
    ],
    "wof:name":"Na'l Dasht",
    "wof:placetype":"locality"
},
  "geometry": {"coordinates":[62.13604,32.55860999999999],"type":"Point"}
}