{
  "type": "Feature",
  "properties": {
    "gn:admin1_code":"08",
    "gn:admin2_code":"615",
    "gn:asciiname":"Shotan",
    "gn:country_code":"AF",
    "gn:dem":2477,
    "gn:feature_class":"P",
    "gn:feature_code":"PPL",
    "gn:name":"Sh\u014dtan",
    "gn:population":0,
    "gn:timezone":"Asia/Kabul",
    "iso:country":"AF",
    "name:und_x_variant":[
        "Shutan",
        "\u0160otan",
        "Shotan",
        "Sh\u014dtan",
        "\u0634\u0648\u062a\u0646"
    ],
    "wof:name":"Shotan",
    "wof:placetype":"locality"
},
  "geometry": {"coordinates":[68.6632,33.58626],"type":"Point"}
}