{
  "type": "Feature",
  "properties": {
    "gn:admin1_code":"01",
    "gn:admin2_code":"1120.0",
    "gn:asciiname":"Fi",
    "gn:country_code":"AF",
    "gn:dem":2261,
    "gn:feature_class":"P",
    "gn:feature_code":"PPL",
    "gn:name":"F\u012b",
    "gn:population":0,
    "gn:timezone":"Asia/Kabul",
    "iso:country":"AF",
    "name:und_x_variant":[
        "F\u012b",
        "\u0641\u06cc"
    ],
    "wof:name":"Fi",
    "wof:placetype":"locality"
},
  "geometry": {"coordinates":[70.52749,38.01577],"type":"Point"}
}