{
  "type": "Feature",
  "properties": {
    "gn:admin1_code":"41",
    "gn:admin2_code":"3407.0",
    "gn:asciiname":"Siyah Bumak",
    "gn:country_code":"AF",
    "gn:dem":2788,
    "gn:feature_class":"P",
    "gn:feature_code":"PPL",
    "gn:name":"Siy\u0101h B\u016bmak",
    "gn:population":0,
    "gn:timezone":"Asia/Kabul",
    "iso:country":"AF",
    "name:und_x_variant":[
        "Sy\u0101hb\u016bmak",
        "S\u012b\u0101h B\u016bmak",
        "Siy\u0101h B\u016bmak",
        "\u0633\u064a\u0627\u0647 \u0628\u0648\u0645\u06a9"
    ],
    "wof:name":"Siyah Bumak",
    "wof:placetype":"locality"
},
  "geometry": {"coordinates":[66.76035999999999,33.94809],"type":"Point"}
}