{
  "type": "Feature",
  "properties": {
    "gn:admin1_code":"23",
    "gn:admin2_code":"2403.0",
    "gn:asciiname":"Faqiran",
    "gn:country_code":"AF",
    "gn:dem":1377,
    "gn:feature_class":"P",
    "gn:feature_code":"PPL",
    "gn:name":"Faq\u012br\u0101n",
    "gn:population":0,
    "gn:timezone":"Asia/Kabul",
    "iso:country":"AF",
    "name:fas_x_preferred":[
        "\u0641\u0642\u064a\u0631\u0627\u0646"
    ],
    "name:und_x_variant":[
        "Fakiran",
        "Faq\u012br\u0101n",
        "\u0641\u0642\u06cc\u0631\u0627\u0646"
    ],
    "wof:name":"Faqiran",
    "wof:placetype":"locality"
},
  "geometry": {"coordinates":[65.86395999999999,32.08685],"type":"Point"}
}