{
  "type": "Feature",
  "properties": {
    "gn:admin1_code":"17",
    "gn:admin2_code":"505.0",
    "gn:asciiname":"'Ali Khel",
    "gn:country_code":"AF",
    "gn:dem":1985,
    "gn:feature_class":"P",
    "gn:feature_code":"PPL",
    "gn:name":"\u2018Al\u012b Kh\u0113l",
    "gn:population":0,
    "gn:timezone":"Asia/Kabul",
    "iso:country":"AF",
    "name:rus_x_preferred":[
        "Alikheyl\u2019"
    ],
    "name:und_x_variant":[
        "\u2018Ali Khehl",
        "\u2018Al\u012b Kh\u0113l",
        "\u0639\u0644\u06cc \u062e\u06d0\u0644"
    ],
    "wof:name":"'Ali Khel",
    "wof:placetype":"locality"
},
  "geometry": {"coordinates":[69.14784,34.10367],"type":"Point"}
}