{
  "type": "Feature",
  "properties": {
    "gn:admin1_code":"2",
    "gn:admin2_code":"1901.0",
    "gn:asciiname":"Chakaran",
    "gn:country_code":"AF",
    "gn:dem":862,
    "gn:feature_class":"P",
    "gn:feature_code":"PPL",
    "gn:name":"Ch\u0101kar\u0101n",
    "gn:population":0,
    "gn:timezone":"Asia/Kabul",
    "iso:country":"AF",
    "name:und_x_variant":[
        "C\u0101kar\u0101n",
        "Ch\u0101kar\u0101n",
        "\u0686\u0627\u06a9\u0631\u0627\u0646"
    ],
    "wof:name":"Chakaran",
    "wof:placetype":"locality"
},
  "geometry": {"coordinates":[63.14319,35.00279],"type":"Point"}
}