{
  "type": "Feature",
  "properties": {
    "gn:admin1_code":"9",
    "gn:admin2_code":"2703.0",
    "gn:asciiname":"Baluch",
    "gn:country_code":"AF",
    "gn:dem":1808,
    "gn:feature_class":"P",
    "gn:feature_code":"PPL",
    "gn:name":"Bal\u016bch",
    "gn:population":0,
    "gn:timezone":"Asia/Kabul",
    "iso:country":"AF",
    "name:und_x_variant":[
        "Bal\u016bc",
        "Bal\u016bch",
        "\u0628\u0644\u0648\u0686"
    ],
    "wof:name":"Baluch",
    "wof:placetype":"locality"
},
  "geometry": {"coordinates":[63.593,34.10148],"type":"Point"}
}