{
  "type": "Feature",
  "properties": {
    "gn:admin1_code":"10",
    "gn:admin2_code":"2303",
    "gn:asciiname":"Khinjakak",
    "gn:country_code":"AF",
    "gn:dem":1051,
    "gn:feature_class":"P",
    "gn:feature_code":"PPL",
    "gn:name":"Khinjakak",
    "gn:population":0,
    "gn:timezone":"Asia/Kabul",
    "iso:country":"AF",
    "name:und_x_variant":[
        "Khindzhakak",
        "Khinjakak",
        "\u062e\u0646\u062c\u06a9\u06a9",
        "Khenjakak"
    ],
    "wof:name":"Khinjakak",
    "wof:placetype":"locality"
},
  "geometry": {"coordinates":[65.12703,32.41659],"type":"Point"}
}