{
  "type": "Feature",
  "properties": {
    "gn:admin1_code":"41",
    "gn:admin2_code":"3408.0",
    "gn:asciiname":"Surkhabah",
    "gn:country_code":"AF",
    "gn:dem":2663,
    "gn:feature_class":"P",
    "gn:feature_code":"PPL",
    "gn:name":"Surkh\u0101bah",
    "gn:population":0,
    "gn:timezone":"Asia/Kabul",
    "iso:country":"AF",
    "name:und_x_variant":[
        "Su\u1e5fkh\u0101ba",
        "Surkhaba",
        "Surkh\u0101bah",
        "Sorkh\u0101beh",
        "\u0633\u0631\u062e\u0627\u0628\u0647"
    ],
    "wof:name":"Surkhabah",
    "wof:placetype":"locality"
},
  "geometry": {"coordinates":[66.04082,34.21351],"type":"Point"}
}