{
  "type": "Feature",
  "properties": {
    "gn:admin1_code":"09",
    "gn:admin2_code":"2707",
    "gn:asciiname":"Naw-e Jow",
    "gn:country_code":"AF",
    "gn:dem":3088,
    "gn:feature_class":"P",
    "gn:feature_code":"PPL",
    "gn:name":"N\u0101w-e Jow",
    "gn:population":0,
    "gn:timezone":"Asia/Kabul",
    "iso:country":"AF",
    "name:und_x_variant":[
        "Navi-Dzhau",
        "N\u0101w-e Jow",
        "Naw-e Jaw",
        "\u0646\u0627\u0648 \u062c\u0648"
    ],
    "wof:name":"Naw-e Jow",
    "wof:placetype":"locality"
},
  "geometry": {"coordinates":[66.49279,34.45929],"type":"Point"}
}