{
  "type": "Feature",
  "properties": {
    "gn:admin1_code":"41",
    "gn:admin2_code":"3408.0",
    "gn:asciiname":"Kudigak",
    "gn:country_code":"AF",
    "gn:dem":2766,
    "gn:feature_class":"P",
    "gn:feature_code":"PPL",
    "gn:name":"Kudigak",
    "gn:population":0,
    "gn:timezone":"Asia/Kabul",
    "iso:country":"AF",
    "name:und_x_variant":[
        "Kodagak",
        "Kod\u012bgak",
        "\u06a9\u062f\u06af\u06a9"
    ],
    "wof:name":"Kudigak",
    "wof:placetype":"locality"
},
  "geometry": {"coordinates":[66.01000999999999,34.21277],"type":"Point"}
}