{
  "type": "Feature",
  "properties": {
    "gn:admin1_code":"10",
    "gn:admin2_code":"2302.0",
    "gn:asciiname":"Jamal Kelay",
    "gn:country_code":"AF",
    "gn:dem":788,
    "gn:feature_class":"P",
    "gn:feature_code":"PPL",
    "gn:name":"Jam\u0101l K\u00ealay",
    "gn:population":0,
    "gn:timezone":"Asia/Kabul",
    "iso:country":"AF",
    "name:fas_x_preferred":[
        "\u0642\u0631\u064a\u06c0 \u062c\u0645\u0627\u0644"
    ],
    "name:rus_x_preferred":[
        "Dzhamal\u2019kalay"
    ],
    "name:und_x_variant":[
        "Jam\u0101l K\u00ealay",
        "\u062c\u0645\u0627\u0644 \u06a9\u0644\u06cc",
        "Jam\u0101l Kalay"
    ],
    "wof:name":"Jamal Kelay",
    "wof:placetype":"locality"
},
  "geometry": {"coordinates":[64.37134,31.67525],"type":"Point"}
}