{
  "type": "Feature",
  "properties": {
    "gn:admin1_code":"05",
    "gn:admin2_code":"2805",
    "gn:asciiname":"Surkh Zamin",
    "gn:country_code":"AF",
    "gn:dem":2799,
    "gn:feature_class":"P",
    "gn:feature_code":"PPL",
    "gn:name":"Surkh Zam\u012bn",
    "gn:population":0,
    "gn:timezone":"Asia/Kabul",
    "iso:country":"AF",
    "name:und_x_variant":[
        "Surkhzamin",
        "Su\u1e5fkhzam\u012bn",
        "Surkh Zam\u012bn",
        "\u0633\u0631\u062e \u0632\u0645\u06cc\u0646"
    ],
    "wof:name":"Surkh Zamin",
    "wof:placetype":"locality"
},
  "geometry": {"coordinates":[66.61634000000001,34.2641],"type":"Point"}
}