{
  "type": "Feature",
  "properties": {
    "gn:admin1_code":"27",
    "gn:admin2_code":"401.0",
    "gn:asciiname":"Amar Khel",
    "gn:country_code":"AF",
    "gn:dem":2154,
    "gn:feature_class":"P",
    "gn:feature_code":"PPL",
    "gn:name":"Amar Kh\u0113l",
    "gn:population":0,
    "gn:timezone":"Asia/Kabul",
    "iso:country":"AF",
    "name:rus_x_preferred":[
        "Amarkheyl\u2019"
    ],
    "name:und_x_variant":[
        "Ama\u1e5fkh\u0113l",
        "Amar Kh\u0113l",
        "Amarkheyl",
        "\u0627\u0645\u0631 \u062e\u06d0\u0644"
    ],
    "wof:name":"Amar Khel",
    "wof:placetype":"locality"
},
  "geometry": {"coordinates":[68.83779,34.37397],"type":"Point"}
}