{
  "type": "Feature",
  "properties": {
    "gn:admin1_code":"8",
    "gn:admin2_code":"604.0",
    "gn:asciiname":"Karez-e Nazar",
    "gn:country_code":"AF",
    "gn:dem":2801,
    "gn:feature_class":"P",
    "gn:feature_code":"PPL",
    "gn:name":"K\u0101r\u0113z-e Naz\u0327ar",
    "gn:population":0,
    "gn:timezone":"Asia/Kabul",
    "iso:country":"AF",
    "name:und_x_variant":[
        "Ka\u1e5f\u0113z Naza\u1e5f",
        "Kareznazar",
        "K\u0101r\u012bz Naz\u0327ar",
        "K\u0101r\u0113z-e Naz\u0327ar",
        "\u06a9\u0627\u0631\u06d0\u0632 \u0646\u0638\u0631"
    ],
    "wof:name":"Karez-e Nazar",
    "wof:placetype":"locality"
},
  "geometry": {"coordinates":[67.99644000000001,34.1085],"type":"Point"}
}