{
  "type": "Feature",
  "properties": {
    "gn:admin1_code":"29",
    "gn:admin2_code":"2909.0",
    "gn:asciiname":"'Isa Khel Sharqi",
    "gn:country_code":"AF",
    "gn:dem":2181,
    "gn:feature_class":"P",
    "gn:feature_code":"PPL",
    "gn:name":"\u2018\u012as\u00e1 Kh\u0113l Sharq\u012b",
    "gn:population":0,
    "gn:timezone":"Asia/Kabul",
    "iso:country":"AF",
    "name:rus_x_preferred":[
        "Isakheyl\u2019-Sharki"
    ],
    "name:und_x_variant":[
        "\u2018Is\u0101kh\u0113l \u0160arqi",
        "\u2018\u012as\u00e1kheyl-e Sharq\u012b",
        "\u2018\u012as\u00e1 Kh\u0113l Sharq\u012b",
        "\u0639\u06cc\u0633\u0649 \u062e\u06d0\u0644 \u0634\u0631\u0642\u06cc"
    ],
    "wof:name":"'Isa Khel Sharqi",
    "wof:placetype":"locality"
},
  "geometry": {"coordinates":[69.18101,32.68969],"type":"Point"}
}