{
  "type": "Feature",
  "properties": {
    "gn:admin1_code":"34",
    "gn:admin2_code":"1006.0",
    "gn:asciiname":"Udil",
    "gn:country_code":"AF",
    "gn:dem":1186,
    "gn:feature_class":"P",
    "gn:feature_code":"PPL",
    "gn:name":"\u016a\u1e0f\u012bl",
    "gn:population":0,
    "gn:timezone":"Asia/Kabul",
    "iso:country":"AF",
    "name:fas_x_preferred":[
        "\u0648\u062f\u064a\u0644"
    ],
    "name:rus_x_preferred":[
        "Udil\u2019"
    ],
    "name:und_x_variant":[
        "\u0627\u0648\u0689\u06cc\u0644",
        "\u016ad\u012bl",
        "\u016a\u1e0f\u012bl"
    ],
    "wof:name":"Udil",
    "wof:placetype":"locality"
},
  "geometry": {"coordinates":[71.34079,35.14321],"type":"Point"}
}