{
  "type": "Feature",
  "properties": {
    "gn:admin1_code":"41",
    "gn:admin2_code":"3409.0",
    "gn:asciiname":"Amrut",
    "gn:country_code":"AF",
    "gn:dem":2000,
    "gn:feature_class":"P",
    "gn:feature_code":"PPL",
    "gn:name":"Amr\u016bt",
    "gn:population":0,
    "gn:timezone":"Asia/Kabul",
    "iso:country":"AF",
    "name:und_x_variant":[
        "Jangalak",
        "Am\u1e5f\u016bt",
        "Amr\u016bt",
        "\u0627\u0645\u0631\u0648\u062a",
        "\u062c\u0646\u06af\u0644\u06a9"
    ],
    "wof:name":"Amrut",
    "wof:placetype":"locality"
},
  "geometry": {"coordinates":[66.68756999999999,33.66289],"type":"Point"}
}