{
  "type": "Feature",
  "properties": {
    "gn:admin1_code":"23",
    "gn:admin2_code":"2402.0",
    "gn:asciiname":"Bebani Kelay",
    "gn:country_code":"AF",
    "gn:dem":1173,
    "gn:feature_class":"P",
    "gn:feature_code":"PPL",
    "gn:name":"B\u0113b\u0101n\u012b K\u00ealay",
    "gn:population":0,
    "gn:timezone":"Asia/Kabul",
    "iso:country":"AF",
    "name:und_x_variant":[
        "Bebanikalay",
        "B\u0113b\u0101n\u012b K\u00ealay",
        "\u0628\u06d0\u0628\u0627\u0646\u06cc \u06a9\u0644\u06cc",
        "B\u0113b\u0101n\u012b Kalay"
    ],
    "wof:name":"Bebani Kelay",
    "wof:placetype":"locality"
},
  "geometry": {"coordinates":[66.15676999999999,31.62515],"type":"Point"}
}