{
  "type": "Feature",
  "properties": {
    "gn:admin1_code":"10",
    "gn:admin2_code":"2306",
    "gn:asciiname":"Zirak Karez",
    "gn:country_code":"AF",
    "gn:dem":989,
    "gn:feature_class":"P",
    "gn:feature_code":"PPL",
    "gn:name":"Z\u012brak K\u0101r\u0113z",
    "gn:population":0,
    "gn:timezone":"Asia/Kabul",
    "iso:country":"AF",
    "name:und_x_variant":[
        "Z\u012b\u1e5fak K\u0101\u1e5f\u0113z",
        "Zirakkarez",
        "Z\u012brak K\u0101r\u0113z",
        "\u0632\u06cc\u0631\u06a9 \u06a9\u0627\u0631\u06d0\u0632",
        "Z\u012brak K\u0101r\u012bz"
    ],
    "wof:name":"Zirak Karez",
    "wof:placetype":"locality"
},
  "geometry": {"coordinates":[64.43258,32.08575],"type":"Point"}
}