{
  "type": "Feature",
  "properties": {
    "gn:admin1_code":"24",
    "gn:admin2_code":"1402.0",
    "gn:asciiname":"Qyam Tumshuq",
    "gn:country_code":"AF",
    "gn:dem":359,
    "gn:feature_class":"P",
    "gn:feature_code":"PPL",
    "gn:name":"Qy\u0101m Tumshuq",
    "gn:population":0,
    "gn:timezone":"Asia/Kabul",
    "iso:country":"AF",
    "name:und_x_variant":[
        "Qy\u0101m Tum\u0161uq",
        "Qy\u0101m Tumshuq",
        "\u0642\u06cc\u0627\u0645 \u062a\u0645\u0634\u0642"
    ],
    "wof:name":"Qyam Tumshuq",
    "wof:placetype":"locality"
},
  "geometry": {"coordinates":[69.03225,37.21376],"type":"Point"}
}