{
  "type": "Feature",
  "properties": {
    "gn:admin1_code":"23",
    "gn:admin2_code":"2412",
    "gn:asciiname":"Obezan",
    "gn:country_code":"AF",
    "gn:dem":1585,
    "gn:feature_class":"P",
    "gn:feature_code":"PPL",
    "gn:name":"\u014cb\u0113zan",
    "gn:population":0,
    "gn:timezone":"Asia/Kabul",
    "iso:country":"AF",
    "name:und_x_variant":[
        "Ubezan",
        "\u014cb\u00eahzan",
        "Ob\u0113zan",
        "\u014cb\u0113zan",
        "\u0627\u0648\u0628\u06d0\u0632\u0646"
    ],
    "wof:name":"Obezan",
    "wof:placetype":"locality"
},
  "geometry": {"coordinates":[66.70496999999999,31.28905],"type":"Point"}
}