{
  "type": "Feature",
  "properties": {
    "gn:admin1_code":"31",
    "gn:admin2_code":"1711",
    "gn:asciiname":"Piazly Kol",
    "gn:country_code":"AF",
    "gn:dem":679,
    "gn:feature_class":"P",
    "gn:feature_code":"PPL",
    "gn:name":"P\u012b\u0101zly K\u014dl",
    "gn:population":0,
    "gn:timezone":"Asia/Kabul",
    "iso:country":"AF",
    "name:und_x_variant":[
        "P\u012b\u0101zly K\u014dl",
        "\u067e\u06cc\u0627\u0632\u0644\u06cc \u06a9\u0648\u0644",
        "Pi\u0101zly Kol"
    ],
    "wof:name":"Piazly Kol",
    "wof:placetype":"locality"
},
  "geometry": {"coordinates":[65.45213000000001,36.21612],"type":"Point"}
}