{
  "type": "Feature",
  "properties": {
    "gn:admin1_code":"5",
    "gn:admin2_code":"2806.0",
    "gn:asciiname":"Binaghol",
    "gn:country_code":"AF",
    "gn:dem":2878,
    "gn:feature_class":"P",
    "gn:feature_code":"PPL",
    "gn:name":"Bin\u0101gh\u014dl",
    "gn:population":0,
    "gn:timezone":"Asia/Kabul",
    "iso:country":"AF",
    "name:und_x_variant":[
        "Binagul\u2019",
        "Ben\u0101gh\u014dl",
        "B\u012bn\u0101gh\u014dl",
        "Bin\u0101gh\u014dl",
        "\u0628\u0646\u0627\u063a\u0648\u0644"
    ],
    "wof:name":"Binaghol",
    "wof:placetype":"locality"
},
  "geometry": {"coordinates":[66.66459999999999,34.22528],"type":"Point"}
}