{
  "type": "Feature",
  "properties": {
    "gn:admin1_code":"26",
    "gn:admin2_code":"1212.0",
    "gn:asciiname":"Tah-ye Koltak",
    "gn:country_code":"AF",
    "gn:dem":446,
    "gn:feature_class":"P",
    "gn:feature_code":"PPL",
    "gn:name":"Tah-ye K\u014dltak",
    "gn:population":0,
    "gn:timezone":"Asia/Kabul",
    "iso:country":"AF",
    "name:und_x_variant":[
        "Ta-i-K\u014dltak",
        "Ta-e K\u016bltak",
        "Tah-ye K\u014dltak",
        "\u062a\u06c0 \u06a9\u0648\u0644\u062a\u06a9"
    ],
    "wof:name":"Tah-ye Koltak",
    "wof:placetype":"locality"
},
  "geometry": {"coordinates":[69.41769000000001,37.13812],"type":"Point"}
}