{
  "type": "Feature",
  "properties": {
    "gn:admin1_code":"09",
    "gn:admin2_code":"2707",
    "gn:asciiname":"Siyah Sang",
    "gn:country_code":"AF",
    "gn:dem":3285,
    "gn:feature_class":"P",
    "gn:feature_code":"PPL",
    "gn:name":"Siy\u0101h Sang",
    "gn:population":0,
    "gn:timezone":"Asia/Kabul",
    "iso:country":"AF",
    "name:und_x_variant":[
        "Sy\u0101hsang",
        "Siakhsang",
        "S\u012b\u0101h Sang",
        "S\u012b\u0101hsang",
        "Siy\u0101h Sang",
        "\u0633\u06cc\u0627\u0647 \u0633\u0646\u06af"
    ],
    "wof:name":"Siyah Sang",
    "wof:placetype":"locality"
},
  "geometry": {"coordinates":[66.32779000000001,34.42337],"type":"Point"}
}