{
  "type": "Feature",
  "properties": {
    "gn:admin1_code":"08",
    "gn:admin2_code":"615",
    "gn:asciiname":"Ramak",
    "gn:country_code":"AF",
    "gn:dem":2183,
    "gn:feature_class":"P",
    "gn:feature_code":"PPLA2",
    "gn:name":"R\u0101mak",
    "gn:population":0,
    "gn:timezone":"Asia/Kabul",
    "iso:country":"AF",
    "name:fas_x_preferred":[
        "\u0631\u0627\u0645\u06a9"
    ],
    "name:spa_x_preferred":[
        "Ramak"
    ],
    "name:und_x_variant":[
        "Rahmak",
        "R\u0101mak",
        "\u0631\u0627\u0645\u06a9"
    ],
    "wof:name":"Ramak",
    "wof:placetype":"locality"
},
  "geometry": {"coordinates":[68.6264,33.52234],"type":"Point"}
}