{
  "type": "Feature",
  "properties": {
    "gn:admin1_code":"18",
    "gn:admin2_code":"802.0",
    "gn:asciiname":"Qal'ah-ye Now",
    "gn:country_code":"AF",
    "gn:dem":597,
    "gn:feature_class":"P",
    "gn:feature_code":"PPL",
    "gn:name":"Qal\u2018ah-ye Now",
    "gn:population":0,
    "gn:timezone":"Asia/Kabul",
    "iso:country":"AF",
    "name:fas_x_preferred":[
        "\u0642\u0644\u0639\u0647\u064b \u0646\u0648"
    ],
    "name:und_x_variant":[
        "Kalanau",
        "Qal\u2018a Naw",
        "Qal\u2018eh-ye Naw",
        "Qal\u2018ah-ye Now",
        "\u0642\u0644\u0639\u06c0 \u0646\u0648"
    ],
    "wof:name":"Qal'ah-ye Now",
    "wof:placetype":"locality"
},
  "geometry": {"coordinates":[70.38224,34.44201],"type":"Point"}
}