{
  "type": "Feature",
  "properties": {
    "gn:admin1_code":"28",
    "gn:admin2_code":"2511.0",
    "gn:asciiname":"Akhund Khel",
    "gn:country_code":"AF",
    "gn:dem":1975,
    "gn:feature_class":"P",
    "gn:feature_code":"PPL",
    "gn:name":"\u0100kh\u016bnd Kh\u0113l",
    "gn:population":0,
    "gn:timezone":"Asia/Kabul",
    "iso:country":"AF",
    "name:rus_x_preferred":[
        "Akhundkheyl\u2019"
    ],
    "name:und_x_variant":[
        "\u0100khun\u1e0fkh\u0113l",
        "\u0100kh\u016bnd Kh\u0113l",
        "\u0622\u062e\u0648\u0646\u062f \u062e\u06d0\u0644",
        "\u0100khvondkheyl"
    ],
    "wof:name":"Akhund Khel",
    "wof:placetype":"locality"
},
  "geometry": {"coordinates":[67.60521999999999,32.22756],"type":"Point"}
}