{
  "type": "Feature",
  "properties": {
    "gn:admin1_code":"23",
    "gn:admin2_code":"2413.0",
    "gn:asciiname":"Angu Khel",
    "gn:country_code":"AF",
    "gn:dem":1885,
    "gn:feature_class":"P",
    "gn:feature_code":"PPL",
    "gn:name":"Ang\u016b Kh\u0113l",
    "gn:population":0,
    "gn:timezone":"Asia/Kabul",
    "iso:country":"AF",
    "name:rus_x_preferred":[
        "Angukheyl\u2019"
    ],
    "name:und_x_variant":[
        "Ang\u016bkh\u0113l",
        "Ang\u016b Kh\u0113l",
        "Angow Kheyl",
        "\u0627\u0646\u06af\u0648 \u062e\u06d0\u0644"
    ],
    "wof:name":"Angu Khel",
    "wof:placetype":"locality"
},
  "geometry": {"coordinates":[67.02488000000001,31.48855],"type":"Point"}
}