{
  "type": "Feature",
  "properties": {
    "gn:admin1_code":"8",
    "gn:admin2_code":"617.0",
    "gn:asciiname":"Babasan",
    "gn:country_code":"AF",
    "gn:dem":2652,
    "gn:feature_class":"P",
    "gn:feature_code":"PPL",
    "gn:name":"Babasan",
    "gn:population":0,
    "gn:timezone":"Asia/Kabul",
    "iso:country":"AF",
    "name:fas_x_preferred":[
        "\u0628\u0627\u0628\u0627\u0633\u0627\u0646"
    ],
    "name:und_x_variant":[
        "B\u0101b\u0101s\u0101n"
    ],
    "wof:name":"Babasan",
    "wof:placetype":"locality"
},
  "geometry": {"coordinates":[68.18035999999999,33.71270999999999],"type":"Point"}
}