{
  "type": "Feature",
  "properties": {
    "gn:admin1_code":"17",
    "gn:admin2_code":"503.0",
    "gn:asciiname":"Delawar",
    "gn:country_code":"AF",
    "gn:dem":2047,
    "gn:feature_class":"P",
    "gn:feature_code":"PPL",
    "gn:name":"Del\u0101war",
    "gn:population":0,
    "gn:timezone":"Asia/Kabul",
    "iso:country":"AF",
    "wof:name":"Delawar",
    "wof:placetype":"locality"
},
  "geometry": {"coordinates":[68.83923,33.92107],"type":"Point"}
}