{
  "type": "Feature",
  "properties": {
    "gn:admin1_code":"06",
    "gn:admin2_code":"2102",
    "gn:asciiname":"Gorabad",
    "gn:country_code":"AF",
    "gn:dem":705,
    "gn:feature_class":"P",
    "gn:feature_code":"PPL",
    "gn:name":"Gorabad",
    "gn:population":0,
    "gn:timezone":"Asia/Kabul",
    "iso:country":"AF",
    "name:und_x_variant":[
        "Dzhakhi-Gazsani",
        "Gorabad",
        "J\u0101he Gaz S\u0101ni",
        "G\u014d\u1e5f\u0101b\u0101d",
        "G\u016br\u0101b\u0101d",
        "G\u014dr\u0101b\u0101d",
        "\u06af\u0648\u0631 \u0622\u0628\u0627\u062f",
        "J\u0101h-e Gaz S\u0101n\u012b",
        "\u062c\u0627\u0647 \u06af\u0632 \u0633\u0627\u0646\u06cc"
    ],
    "wof:name":"Gorabad",
    "wof:placetype":"locality"
},
  "geometry": {"coordinates":[62.83963000000001,32.21772],"type":"Point"}
}