{
  "type": "Feature",
  "properties": {
    "gn:admin1_code":"27",
    "gn:admin2_code":"406.0",
    "gn:asciiname":"Shukurdad",
    "gn:country_code":"AF",
    "gn:dem":2516,
    "gn:feature_class":"P",
    "gn:feature_code":"PPL",
    "gn:name":"Shukurd\u0101d",
    "gn:population":0,
    "gn:timezone":"Asia/Kabul",
    "iso:country":"AF",
    "name:und_x_variant":[
        "\u0160okurd\u0101d",
        "Shuk\u016brd\u0101d",
        "Shokord\u0101d",
        "Shukurd\u0101d",
        "\u0634\u06a9\u0631\u062f\u0627\u062f"
    ],
    "wof:name":"Shukurdad",
    "wof:placetype":"locality"
},
  "geometry": {"coordinates":[68.45255,34.10226],"type":"Point"}
}