{
  "type": "Feature",
  "properties": {
    "gn:admin1_code":"06",
    "gn:admin2_code":"2105",
    "gn:asciiname":"Kal Qal'ah",
    "gn:country_code":"AF",
    "gn:dem":767,
    "gn:feature_class":"P",
    "gn:feature_code":"PPL",
    "gn:name":"K\u0101l Qal\u2018ah",
    "gn:population":0,
    "gn:timezone":"Asia/Kabul",
    "iso:country":"AF",
    "name:rus_x_preferred":[
        "Kal\u2019kala"
    ],
    "name:und_x_variant":[
        "Qala-i-K\u0101l",
        "Kala-i-K\u0101l",
        "K\u0101l Qal\u2018a",
        "K\u0101l Qal\u2018eh",
        "K\u0101l Qal\u2018ah",
        "\u06a9\u0627\u0644 \u0642\u0644\u0639\u0647"
    ],
    "wof:name":"Kal Qal'ah",
    "wof:placetype":"locality"
},
  "geometry": {"coordinates":[62.53119,32.62777],"type":"Point"}
}