{
  "type": "Feature",
  "properties": {
    "gn:admin1_code":"09",
    "gn:admin2_code":"2701",
    "gn:asciiname":"Sar-e Ghalmin",
    "gn:country_code":"AF",
    "gn:dem":2114,
    "gn:feature_class":"P",
    "gn:feature_code":"PPL",
    "gn:name":"Sar-e Ghalm\u012bn",
    "gn:population":0,
    "gn:timezone":"Asia/Kabul",
    "iso:country":"AF",
    "name:und_x_variant":[
        "Kilmin",
        "Sar Tag\u0101b-e Ghalm\u012bn",
        "Ghalm\u012bn",
        "Ghelmin",
        "Sar-e Ghalm\u012bn",
        "\u0633\u0631\u063a\u0644\u0645\u06cc\u0646"
    ],
    "wof:name":"Sar-e Ghalmin",
    "wof:placetype":"locality"
},
  "geometry": {"coordinates":[65.31698,34.83567],"type":"Point"}
}