{
  "type": "Feature",
  "properties": {
    "gn:admin1_code":"10",
    "gn:admin2_code":"2312",
    "gn:asciiname":"Nokorzai",
    "gn:country_code":"AF",
    "gn:dem":901,
    "gn:feature_class":"P",
    "gn:feature_code":"PPL",
    "gn:name":"N\u014dk\u014drza\u012b",
    "gn:population":0,
    "gn:timezone":"Asia/Kabul",
    "iso:country":"AF",
    "name:und_x_variant":[
        "N\u014dk\u014d\u1e5fzay",
        "Nokorzay",
        "N\u014dk\u014drza\u012b",
        "\u0646\u0648\u06a9\u0648\u0631\u0632\u06cc",
        "N\u016bk\u016b\u1e5fzay"
    ],
    "wof:name":"Nokorzai",
    "wof:placetype":"locality"
},
  "geometry": {"coordinates":[64.9259,32.13167],"type":"Point"}
}