{
  "type": "Feature",
  "properties": {
    "gn:admin1_code":"27",
    "gn:admin2_code":"403",
    "gn:asciiname":"Pokah",
    "gn:country_code":"AF",
    "gn:dem":3154,
    "gn:feature_class":"P",
    "gn:feature_code":"PPL",
    "gn:name":"P\u014dkah",
    "gn:population":0,
    "gn:timezone":"Asia/Kabul",
    "iso:country":"AF",
    "name:und_x_variant":[
        "Poka",
        "P\u014dka",
        "P\u016bkeh",
        "P\u014dkah",
        "\u067e\u0648\u06a9\u0647"
    ],
    "wof:name":"Pokah",
    "wof:placetype":"locality"
},
  "geometry": {"coordinates":[68.36645,34.49147],"type":"Point"}
}