{
  "type": "Feature",
  "properties": {
    "gn:admin1_code":"37",
    "gn:admin2_code":"3208",
    "gn:asciiname":"Mir Goray",
    "gn:country_code":"AF",
    "gn:dem":1663,
    "gn:feature_class":"P",
    "gn:feature_code":"PPL",
    "gn:name":"M\u012br G\u014d\u1e5fay",
    "gn:population":0,
    "gn:timezone":"Asia/Kabul",
    "iso:country":"AF",
    "name:fas_x_preferred":[
        "\u0645\u064a\u0631 \u06af\u0648\u0631\u06cc"
    ],
    "name:und_x_variant":[
        "Mir-Goray",
        "M\u012b\u1e5f G\u014dray",
        "M\u012br G\u014dray",
        "M\u012br Gowray",
        "M\u012br G\u014d\u1e5fay",
        "\u0645\u064a\u0631 \u06af\u0648\u0693\u06cc"
    ],
    "wof:name":"Mir Goray",
    "wof:placetype":"locality"
},
  "geometry": {"coordinates":[69.6794,33.39977],"type":"Point"}
}