{
  "type": "Feature",
  "properties": {
    "gn:admin1_code":"14",
    "gn:admin2_code":"206.0",
    "gn:asciiname":"Kordak",
    "gn:country_code":"AF",
    "gn:dem":1978,
    "gn:feature_class":"P",
    "gn:feature_code":"PPL",
    "gn:name":"K\u014drdak",
    "gn:population":0,
    "gn:timezone":"Asia/Kabul",
    "iso:country":"AF",
    "name:fas_x_preferred":[
        "\u0643\u0648\u0631\u062f\u0643"
    ],
    "name:und_x_variant":[
        "K\u014d\u1e5f\u1e0fak",
        "Kordak",
        "Kowrdak",
        "K\u014drdak",
        "\u06a9\u0648\u0631\u062f\u06a9",
        "Kurdak",
        "\u06a9\u0631\u062f\u06a9"
    ],
    "wof:name":"Kordak",
    "wof:placetype":"locality"
},
  "geometry": {"coordinates":[69.75784,34.88628],"type":"Point"}
}