{
  "type": "Feature",
  "properties": {
    "gn:admin1_code":"9",
    "gn:admin2_code":"2703.0",
    "gn:asciiname":"Dahan-e Gaw Kush",
    "gn:country_code":"AF",
    "gn:dem":2150,
    "gn:feature_class":"P",
    "gn:feature_code":"PPL",
    "gn:name":"Dah\u0101n-e G\u0101w Kush",
    "gn:population":0,
    "gn:timezone":"Asia/Kabul",
    "iso:country":"AF",
    "name:und_x_variant":[
        "Dakhani-Gavkush",
        "Dahane G\u0101wkush",
        "Dahane G\u0101wku\u0161",
        "Dah\u0101n-e G\u0101w Kush",
        "\u062f\u0647\u0627\u0646 \u06af\u0627\u0648 \u06a9\u0634",
        "Dahan-e G\u0101vkosh"
    ],
    "wof:name":"Dahan-e Gaw Kush",
    "wof:placetype":"locality"
},
  "geometry": {"coordinates":[64.01463000000001,34.16378],"type":"Point"}
}