{
  "type": "Feature",
  "properties": {
    "gn:admin1_code":"24",
    "gn:admin2_code":"1406.0",
    "gn:asciiname":"Mulla Rasul",
    "gn:country_code":"AF",
    "gn:dem":450,
    "gn:feature_class":"P",
    "gn:feature_code":"PPL",
    "gn:name":"Mull\u0101 Ras\u016bl",
    "gn:population":0,
    "gn:timezone":"Asia/Kabul",
    "iso:country":"AF",
    "name:rus_x_preferred":[
        "\u041c\u0443\u043b\u043b\u0430-\u0420\u0430\u0441\u0443\u043b\u044c"
    ],
    "name:und_x_variant":[
        "Mulla-Rasul\u2019",
        "Mull\u0101 \u1e5eas\u016bl",
        "Moll\u0101 Ras\u016bl",
        "Mull\u0101 Ras\u016bl",
        "\u0645\u0644\u0627 \u0631\u0633\u0648\u0644"
    ],
    "wof:name":"Mulla Rasul",
    "wof:placetype":"locality"
},
  "geometry": {"coordinates":[69.05181,36.65251],"type":"Point"}
}