{
  "type": "Feature",
  "properties": {
    "gn:admin1_code":"23",
    "gn:admin2_code":"2412",
    "gn:asciiname":"Mulla Khalo Kelay",
    "gn:country_code":"AF",
    "gn:dem":1376,
    "gn:feature_class":"P",
    "gn:feature_code":"PPL",
    "gn:name":"Mull\u0101 Kh\u0101l\u014d K\u00ealay",
    "gn:population":0,
    "gn:timezone":"Asia/Kabul",
    "iso:country":"AF",
    "name:und_x_variant":[
        "Mullakhalu-Kalay",
        "Mull\u0101 Kh\u0101l\u014d K\u00ealay",
        "\u0645\u0644\u0627 \u062e\u0627\u0644\u0648 \u06a9\u0644\u06cc",
        "Mull\u0101kh\u0101lo Kalay"
    ],
    "wof:name":"Mulla Khalo Kelay",
    "wof:placetype":"locality"
},
  "geometry": {"coordinates":[66.67126999999999,31.55747],"type":"Point"}
}