{
  "type": "Feature",
  "properties": {
    "gn:admin1_code":"05",
    "gn:admin2_code":"2806.0",
    "gn:asciiname":"Siyah Kharak",
    "gn:country_code":"AF",
    "gn:dem":2869,
    "gn:feature_class":"P",
    "gn:feature_code":"PPL",
    "gn:name":"Siy\u0101h Kh\u0101rak",
    "gn:population":0,
    "gn:timezone":"Asia/Kabul",
    "iso:country":"AF",
    "name:und_x_variant":[
        "Siy\u0101h Kh\u0101rak",
        "S\u012b\u0101h Kh\u0101rak"
    ],
    "wof:name":"Siyah Kharak",
    "wof:placetype":"locality"
},
  "geometry": {"coordinates":[66.96124,34.2284],"type":"Point"}
}