{
  "type": "Feature",
  "properties": {
    "gn:admin1_code":"13",
    "gn:admin2_code":"108.0",
    "gn:asciiname":"Qaryah-ye Amir Muhammad",
    "gn:country_code":"AF",
    "gn:dem":2036,
    "gn:feature_class":"P",
    "gn:feature_code":"PPL",
    "gn:name":"Qaryah-ye Am\u012br Mu\u1e29ammad",
    "gn:population":0,
    "gn:timezone":"Asia/Kabul",
    "iso:country":"AF",
    "name:und_x_variant":[
        "Qaryah-ye Am\u012br Mu\u1e29ammad",
        "\u0642\u0631\u06cc\u0647 \u0627\u0645\u06cc\u0631 \u0645\u062d\u0645\u062f"
    ],
    "wof:name":"Qaryah-ye Amir Muhammad",
    "wof:placetype":"locality"
},
  "geometry": {"coordinates":[69.01015,34.55715],"type":"Point"}
}