{
  "type": "Feature",
  "properties": {
    "gn:admin1_code":"26",
    "gn:admin2_code":"1213",
    "gn:asciiname":"Khosti Qishlaq",
    "gn:country_code":"AF",
    "gn:dem":663,
    "gn:feature_class":"P",
    "gn:feature_code":"PPL",
    "gn:name":"Kh\u014dst\u012b Qishl\u0101q",
    "gn:population":0,
    "gn:timezone":"Asia/Kabul",
    "iso:country":"AF",
    "name:fas_x_preferred":[
        "\u062e\u0633\u062a\u06cc \u0642\u0634\u0644\u0627\u0642"
    ],
    "name:rus_x_preferred":[
        "\u0425\u043e\u0441\u0442\u044b\u043a\u044b\u0448\u043b\u0430\u043a"
    ],
    "name:und_x_variant":[
        "Khostykyshlak",
        "Khosti Qe\u0161l\u0101q",
        "Khost\u012b Qeshlag",
        "Khost\u012b Qeshl\u0101q",
        "Kh\u014dst\u012b Qishl\u0101q",
        "\u062e\u0648\u0633\u062a\u06cc \u0642\u0634\u0644\u0627\u0642"
    ],
    "wof:name":"Khosti Qishlaq",
    "wof:placetype":"locality"
},
  "geometry": {"coordinates":[69.38081,36.77808],"type":"Point"}
}