{
  "type": "Feature",
  "properties": {
    "gn:admin1_code":"06",
    "gn:admin2_code":"2101",
    "gn:asciiname":"Karez-e Dad Gul",
    "gn:country_code":"AF",
    "gn:dem":639,
    "gn:feature_class":"P",
    "gn:feature_code":"PPL",
    "gn:name":"K\u0101r\u0113z-e D\u0101d Gul",
    "gn:population":0,
    "gn:timezone":"Asia/Kabul",
    "iso:country":"AF",
    "name:und_x_variant":[
        "K\u0101r\u0113ze \u1e0e\u0101\u1e0f Gul",
        "K\u0101r\u012bz-e D\u0101d Gol",
        "K\u0101r\u0113z-e D\u0101d Gul",
        "\u06a9\u0627\u0631\u06d0\u0632 \u062f\u0627\u062f \u06af\u0644"
    ],
    "wof:name":"Karez-e Dad Gul",
    "wof:placetype":"locality"
},
  "geometry": {"coordinates":[61.94387,32.35536],"type":"Point"}
}