{
  "type": "Feature",
  "properties": {
    "gn:admin1_code":"41",
    "gn:admin2_code":"3403.0",
    "gn:asciiname":"Siyah Khak",
    "gn:country_code":"AF",
    "gn:dem":2806,
    "gn:feature_class":"P",
    "gn:feature_code":"PPL",
    "gn:name":"Siy\u0101h Kh\u0101k",
    "gn:population":0,
    "gn:timezone":"Asia/Kabul",
    "iso:country":"AF",
    "name:und_x_variant":[
        "Siakhkhak",
        "Sy\u0101hkh\u0101k",
        "S\u012b\u0101h Kh\u0101k",
        "S\u012b\u0101hkh\u0101k",
        "Siy\u0101h Kh\u0101k",
        "\u0633\u064a\u0627\u0647 \u062e\u0627\u06a9"
    ],
    "wof:name":"Siyah Khak",
    "wof:placetype":"locality"
},
  "geometry": {"coordinates":[66.46504,34.00386],"type":"Point"}
}