{
  "type": "Feature",
  "properties": {
    "gn:admin1_code":"41",
    "gn:admin2_code":"3403.0",
    "gn:asciiname":"Barik Joy",
    "gn:country_code":"AF",
    "gn:dem":2461,
    "gn:feature_class":"P",
    "gn:feature_code":"PPL",
    "gn:name":"B\u0101r\u012bk J\u014dy",
    "gn:population":0,
    "gn:timezone":"Asia/Kabul",
    "iso:country":"AF",
    "name:und_x_variant":[
        "B\u0101\u1e5f\u012bkj\u014dy",
        "Bankdzhoy",
        "B\u0101r\u012bk J\u014dy",
        "B\u0101r\u012bkj\u016by",
        "\u0628\u0627\u0631\u064a\u06a9 \u062c\u0648\u06cc"
    ],
    "wof:name":"Barik Joy",
    "wof:placetype":"locality"
},
  "geometry": {"coordinates":[66.34228,34.14499],"type":"Point"}
}