{
  "type": "Feature",
  "properties": {
    "gn:admin1_code":"10",
    "gn:admin2_code":"2302.0",
    "gn:asciiname":"Senderzai",
    "gn:country_code":"AF",
    "gn:dem":814,
    "gn:feature_class":"P",
    "gn:feature_code":"PPL",
    "gn:name":"S\u00eand\u00earza\u012b",
    "gn:population":0,
    "gn:timezone":"Asia/Kabul",
    "iso:country":"AF",
    "name:und_x_variant":[
        "S\u00eand\u00earza\u012b",
        "\u0633\u0646\u062f\u0631\u0632\u06cc",
        "Sende\u1e5fza\u2019i"
    ],
    "wof:name":"Senderzai",
    "wof:placetype":"locality"
},
  "geometry": {"coordinates":[64.53894,31.78877],"type":"Point"}
}