{
  "type": "Feature",
  "properties": {
    "gn:admin1_code":"27",
    "gn:admin2_code":"404",
    "gn:asciiname":"Ozhay-e 'Ulya",
    "gn:country_code":"AF",
    "gn:dem":2937,
    "gn:feature_class":"P",
    "gn:feature_code":"PPL",
    "gn:name":"\u014cz\u0332h\u0332ay-e \u2018Uly\u0101",
    "gn:population":0,
    "gn:timezone":"Asia/Kabul",
    "iso:country":"AF",
    "name:und_x_variant":[
        "Owzhay \u2018Oly\u0101",
        "Ozayi-Ulia",
        "O\u017eaye \u2018Uly\u0101",
        "Owzhay-e \u2018Oly\u0101",
        "\u014cz\u0332h\u0332ay-e \u2018Uly\u0101",
        "\u0627\u0648\u0696\u06cc \u0639\u0644\u06cc\u0627"
    ],
    "wof:name":"Ozhay-e 'Ulya",
    "wof:placetype":"locality"
},
  "geometry": {"coordinates":[67.88585999999999,34.23568],"type":"Point"}
}