{
  "type": "Feature",
  "properties": {
    "gn:admin1_code":"09",
    "gn:admin2_code":"2707",
    "gn:asciiname":"Naw-e Qadam",
    "gn:country_code":"AF",
    "gn:dem":3036,
    "gn:feature_class":"P",
    "gn:feature_code":"PPL",
    "gn:name":"N\u0101w-e Qadam",
    "gn:population":0,
    "gn:timezone":"Asia/Kabul",
    "iso:country":"AF",
    "name:und_x_variant":[
        "Navekadam",
        "N\u0101w\u0113 Qadam",
        "N\u0101w-e Qadam",
        "\u0646\u0627\u0648 \u0642\u062f\u0645",
        "Now\u0113 Qadam",
        "\u0646\u0648\u06cc \u0642\u062f\u0645"
    ],
    "wof:name":"Naw-e Qadam",
    "wof:placetype":"locality"
},
  "geometry": {"coordinates":[66.22463,34.42288],"type":"Point"}
}