{
  "type": "Feature",
  "properties": {
    "gn:admin1_code":"36",
    "gn:admin2_code":"702.0",
    "gn:asciiname":"Haki Khan Wal",
    "gn:country_code":"AF",
    "gn:dem":2161,
    "gn:feature_class":"P",
    "gn:feature_code":"PPL",
    "gn:name":"\u1e28ak\u012b Kh\u0101n W\u0101l",
    "gn:population":0,
    "gn:timezone":"Asia/Kabul",
    "iso:country":"AF",
    "name:fas_x_preferred":[
        "\u0647\u0643\u06cc \u062e\u0627\u0646 \u0648\u0627\u0644"
    ],
    "name:rus_x_preferred":[
        "Khakikhanval\u2019"
    ],
    "name:und_x_variant":[
        "\u1e28aq\u012b Kh\u0101n W\u0101l",
        "\u1e28ak\u012b Kh\u0101n W\u0101l",
        "\u062d\u0627\u06a9\u06cc \u062e\u0627\u0646 \u0648\u0627\u0644"
    ],
    "wof:name":"Haki Khan Wal",
    "wof:placetype":"locality"
},
  "geometry": {"coordinates":[69.02879,33.48415],"type":"Point"}
}