{
  "type": "Feature",
  "properties": {
    "gn:admin1_code":"10",
    "gn:admin2_code":"2311",
    "gn:asciiname":"Hirati",
    "gn:country_code":"AF",
    "gn:dem":684,
    "gn:feature_class":"P",
    "gn:feature_code":"PPL",
    "gn:name":"Hir\u0101t\u012b",
    "gn:population":0,
    "gn:timezone":"Asia/Kabul",
    "iso:country":"AF",
    "name:und_x_variant":[
        "Hir\u0101t\u012b",
        "\u0647\u0631\u0627\u062a\u06cc",
        "Her\u0101t\u012b"
    ],
    "wof:name":"Hirati",
    "wof:placetype":"locality"
},
  "geometry": {"coordinates":[64.13406999999999,30.89475],"type":"Point"}
}