{
  "type": "Feature",
  "properties": {
    "gn:admin1_code":"2",
    "gn:admin2_code":"1907.0",
    "gn:asciiname":"Ab Shorah",
    "gn:country_code":"AF",
    "gn:dem":668,
    "gn:feature_class":"P",
    "gn:feature_code":"PPL",
    "gn:name":"\u0100b Sh\u014drah",
    "gn:population":0,
    "gn:timezone":"Asia/Kabul",
    "iso:country":"AF",
    "name:und_x_variant":[
        "\u0100oshera",
        "\u0100bs\u0304\u0101\u1e5f",
        "\u0100b Sh\u016breh",
        "\u0100b S\u0304\u014d\u1e5fa",
        "\u0100b Sh\u014drah",
        "\u0622\u0628 \u0634\u0648\u0631\u0647",
        "\u0100bsh\u0101r"
    ],
    "wof:name":"Ab Shorah",
    "wof:placetype":"locality"
},
  "geometry": {"coordinates":[63.02479,35.19365],"type":"Point"}
}