{
  "type": "Feature",
  "properties": {
    "gn:admin1_code":"30",
    "gn:admin2_code":"1612",
    "gn:asciiname":"Zambukan",
    "gn:country_code":"AF",
    "gn:dem":379,
    "gn:feature_class":"P",
    "gn:feature_code":"PPL",
    "gn:name":"Zambukan",
    "gn:population":0,
    "gn:timezone":"Asia/Kabul",
    "iso:country":"AF",
    "name:rus_x_preferred":[
        "\u0417\u0430\u043c\u0431\u0443\u043a\u0430\u043d"
    ],
    "name:und_x_variant":[
        "Zambokan",
        "Zambukan",
        "\u0632\u0645\u0628\u06a9\u0646"
    ],
    "wof:name":"Zambukan",
    "wof:placetype":"locality"
},
  "geometry": {"coordinates":[66.93751999999999,36.70182],"type":"Point"}
}