{
  "type": "Feature",
  "properties": {
    "gn:admin1_code":"5",
    "gn:admin2_code":"2802.0",
    "gn:asciiname":"Dahan-e Muhammad-Kaychah",
    "gn:country_code":"AF",
    "gn:dem":2163,
    "gn:feature_class":"P",
    "gn:feature_code":"PPL",
    "gn:name":"Dah\u0101n-e Mu\u1e29ammad-Kaychah",
    "gn:population":0,
    "gn:timezone":"Asia/Kabul",
    "iso:country":"AF",
    "name:und_x_variant":[
        "Dahane Mahma\u1e0fkeca",
        "Dahan-e Ma\u1e29madkecheh",
        "Dah\u0101n-e Mu\u1e29ammad-Kaychah",
        "\u062f\u0647\u0627\u0646 \u0645\u062d\u0645\u062f \u06a9\u06cc\u0686\u0647"
    ],
    "wof:name":"Dahan-e Muhammad-Kaychah",
    "wof:placetype":"locality"
},
  "geometry": {"coordinates":[68.02173000000001,35.04875],"type":"Point"}
}