{
  "type": "Feature",
  "properties": {
    "gn:admin1_code":"24",
    "gn:admin2_code":"1404.0",
    "gn:asciiname":"Gharow Qishlaq",
    "gn:country_code":"AF",
    "gn:dem":400,
    "gn:feature_class":"P",
    "gn:feature_code":"PPL",
    "gn:name":"Gharow Qishl\u0101q",
    "gn:population":0,
    "gn:timezone":"Asia/Kabul",
    "iso:country":"AF",
    "name:fas_x_preferred":[
        "\u0642\u0634\u0644\u0627\u0642\u0654 \u063a\u0631\u0648"
    ],
    "name:rus_x_preferred":[
        "\u0413\u0430\u0440\u0430\u0432\u043a\u044b\u0448\u043b\u0430\u043a"
    ],
    "name:und_x_variant":[
        "Gharaw Qe\u0161l\u0101q",
        "Garavkyshlak",
        "Gharow Qeshl\u0101q",
        "Gharow Qishl\u0101q",
        "\u063a\u0631\u0648 \u0642\u0634\u0644\u0627\u0642"
    ],
    "wof:name":"Gharow Qishlaq",
    "wof:placetype":"locality"
},
  "geometry": {"coordinates":[68.82911,36.66076],"type":"Point"}
}