{
  "type": "Feature",
  "properties": {
    "gn:admin1_code":"8",
    "gn:admin2_code":"604.0",
    "gn:asciiname":"'Amro",
    "gn:country_code":"AF",
    "gn:dem":3159,
    "gn:feature_class":"P",
    "gn:feature_code":"PPL",
    "gn:name":"\u2018Amr\u014d",
    "gn:population":0,
    "gn:timezone":"Asia/Kabul",
    "iso:country":"AF",
    "name:rus_x_preferred":[
        "\u0410\u043c\u0440\u0443"
    ],
    "name:und_x_variant":[
        "Amru",
        "\u2018Amro",
        "\u2018Amr\u014d",
        "\u0639\u0645\u0631\u0648"
    ],
    "wof:name":"'Amro",
    "wof:placetype":"locality"
},
  "geometry": {"coordinates":[67.74476999999999,33.79018],"type":"Point"}
}