{
  "type": "Feature",
  "properties": {
    "gn:admin1_code":"18",
    "gn:admin2_code":"811.0",
    "gn:asciiname":"Lalmey",
    "gn:country_code":"AF",
    "gn:dem":1330,
    "gn:feature_class":"P",
    "gn:feature_code":"PPL",
    "gn:name":"Lalm\u00eay",
    "gn:population":0,
    "gn:timezone":"Asia/Kabul",
    "iso:country":"AF",
    "name:fas_x_preferred":[
        "\u0644\u0644\u0645\u06cc"
    ],
    "name:rus_x_preferred":[
        "Lal\u2019may"
    ],
    "name:und_x_variant":[
        "Lalmay",
        "Lalm\u00eay",
        "\u0644\u0644\u0645\u06cd"
    ],
    "wof:name":"Lalmey",
    "wof:placetype":"locality"
},
  "geometry": {"coordinates":[70.81634,34.02731],"type":"Point"}
}