{
  "type": "Feature",
  "properties": {
    "gn:admin1_code":"10",
    "gn:admin2_code":"2306",
    "gn:asciiname":"Now Zad",
    "gn:country_code":"AF",
    "gn:dem":1220,
    "gn:feature_class":"P",
    "gn:feature_code":"PPLA2",
    "gn:name":"Now Z\u0101d",
    "gn:population":0,
    "gn:timezone":"Asia/Kabul",
    "iso:country":"AF",
    "name:und_x_variant":[
        "N\u0101oz\u0101d",
        "Nozad",
        "Nau-Zad",
        "Naw Z\u0101\u1e0f",
        "Nauz\u0101d",
        "Now Z\u0101d",
        "\u0646\u0648 \u0632\u0627\u062f"
    ],
    "wof:name":"Now Zad",
    "wof:placetype":"locality"
},
  "geometry": {"coordinates":[64.46959,32.40315],"type":"Point"}
}