{
  "type": "Feature",
  "properties": {
    "gn:admin1_code":"41",
    "gn:admin2_code":"3405",
    "gn:asciiname":"Zabo",
    "gn:country_code":"AF",
    "gn:dem":2792,
    "gn:feature_class":"P",
    "gn:feature_code":"PPL",
    "gn:name":"Z\u0101b\u014d",
    "gn:population":0,
    "gn:timezone":"Asia/Kabul",
    "iso:country":"AF",
    "name:und_x_variant":[
        "Z\u0101b\u014d",
        "\u0632\u0627\u0628\u0648",
        "Z\u0101bo"
    ],
    "wof:name":"Zabo",
    "wof:placetype":"locality"
},
  "geometry": {"coordinates":[66.02354,33.92148],"type":"Point"}
}