{
  "type": "Feature",
  "properties": {
    "gn:admin1_code":"29",
    "gn:admin2_code":"2906.0",
    "gn:asciiname":"Baz Mir Khan Kowti",
    "gn:country_code":"AF",
    "gn:dem":2383,
    "gn:feature_class":"P",
    "gn:feature_code":"PPL",
    "gn:name":"B\u0101z M\u012br Kh\u0101n Kow\u1e6f\u012b",
    "gn:population":0,
    "gn:timezone":"Asia/Kabul",
    "iso:country":"AF",
    "name:fas_x_preferred":[
        "B\u0101z M\u012br Kh\u0101n Kow\u1e6f\u012b"
    ],
    "name:fas_x_variant":[
        "\u0628\u0627\u0632 \u0645\u06cc\u0631 \u062e\u0627\u0646 \u06a9\u0648\u067c\u06cc"
    ],
    "name:und_x_variant":[
        "Bazmirkhankote",
        "B\u0101zm\u012b\u1e5fkh\u0101n K\u014dt\u0113",
        "\u0628\u0627\u0632 \u0645\u06cc\u0631 \u062e\u0627\u0646 \u06a9\u0648\u067c\u06cc"
    ],
    "wof:name":"Baz Mir Khan Kowti",
    "wof:placetype":"locality"
},
  "geometry": {"coordinates":[68.9393,32.72553],"type":"Point"}
}