{
  "type": "Feature",
  "properties": {
    "gn:admin1_code":"28",
    "gn:admin2_code":"2504.0",
    "gn:asciiname":"Baluch Khune",
    "gn:country_code":"AF",
    "gn:dem":1682,
    "gn:feature_class":"P",
    "gn:feature_code":"PPL",
    "gn:name":"Bal\u016bch Kh\u016bn\u0113",
    "gn:population":0,
    "gn:timezone":"Asia/Kabul",
    "iso:country":"AF",
    "name:fas_x_preferred":[
        "\u0628\u0644\u0648\u0686 \u062e\u0627\u0646\u0647"
    ],
    "name:und_x_variant":[
        "Bal\u016b\u010d Kh\u016bn\u0113",
        "Balukhchune",
        "Bal\u016bch Kh\u0101neh",
        "Bal\u016bch Kh\u016bn\u0113",
        "\u0628\u0644\u0648\u0686 \u062e\u0648\u0646\u06d0"
    ],
    "wof:name":"Baluch Khune",
    "wof:placetype":"locality"
},
  "geometry": {"coordinates":[66.67274999999999,32.4642],"type":"Point"}
}