{
  "type": "Feature",
  "properties": {
    "gn:admin1_code":"18",
    "gn:admin2_code":"804.0",
    "gn:asciiname":"Kotahgay",
    "gn:country_code":"AF",
    "gn:dem":1298,
    "gn:feature_class":"P",
    "gn:feature_code":"PPL",
    "gn:name":"K\u014d\u1e6fahgay",
    "gn:population":0,
    "gn:timezone":"Asia/Kabul",
    "iso:country":"AF",
    "name:fas_x_preferred":[
        "\u0643\u0648\u062a\u06af\u06cc"
    ],
    "name:und_x_variant":[
        "Kotagay",
        "K\u014dtagae",
        "K\u014d\u1e6faga\u012b",
        "K\u016btagae",
        "K\u014d\u1e6fahgay",
        "\u06a9\u0648\u067c\u0647 \u06af\u06cc"
    ],
    "wof:name":"Kotahgay",
    "wof:placetype":"locality"
},
  "geometry": {"coordinates":[69.98872,34.32626],"type":"Point"}
}