{
  "type": "Feature",
  "properties": {
    "gn:admin1_code":"05",
    "gn:admin2_code":"2805",
    "gn:asciiname":"Shaynah",
    "gn:country_code":"AF",
    "gn:dem":2929,
    "gn:feature_class":"P",
    "gn:feature_code":"PPL",
    "gn:name":"Shaynah",
    "gn:population":0,
    "gn:timezone":"Asia/Kabul",
    "iso:country":"AF",
    "name:und_x_variant":[
        "\u0160ina",
        "Shina",
        "Shaynah",
        "Sh\u012bnah",
        "\u0634\u06cc\u0646\u0647"
    ],
    "wof:name":"Shaynah",
    "wof:placetype":"locality"
},
  "geometry": {"coordinates":[66.82653000000001,34.4428],"type":"Point"}
}