{
  "type": "Feature",
  "properties": {
    "gn:admin1_code":"36",
    "gn:admin2_code":"709",
    "gn:asciiname":"Waghz",
    "gn:country_code":"AF",
    "gn:dem":2320,
    "gn:feature_class":"P",
    "gn:feature_code":"PPL",
    "gn:name":"W\u0101ghz",
    "gn:population":0,
    "gn:timezone":"Asia/Kabul",
    "iso:country":"AF",
    "name:und_x_variant":[
        "Vagz",
        "W\u0101ghz",
        "\u0648\u0627\u063a\u0632"
    ],
    "wof:name":"Waghz",
    "wof:placetype":"locality"
},
  "geometry": {"coordinates":[69.63892,33.72946],"type":"Point"}
}