{
  "type": "Feature",
  "properties": {
    "gn:admin1_code":"9",
    "gn:admin2_code":"2705.0",
    "gn:asciiname":"Kalanzaikha",
    "gn:country_code":"AF",
    "gn:dem":2310,
    "gn:feature_class":"P",
    "gn:feature_code":"PPL",
    "gn:name":"Kalanzaikha",
    "gn:population":0,
    "gn:timezone":"Asia/Kabul",
    "iso:country":"AF",
    "name:und_x_variant":[
        "Kal\u0101n Z\u0101\u2019\u012bh\u0101",
        "\u06a9\u0644\u0627\u0646 \u0632\u0639\u06cc \u0647\u0627",
        "Kal\u0101nza\u012bh\u0101"
    ],
    "wof:name":"Kalanzaikha",
    "wof:placetype":"locality"
},
  "geometry": {"coordinates":[64.35491,33.17535],"type":"Point"}
}