{
  "type": "Feature",
  "properties": {
    "gn:admin1_code":"23",
    "gn:admin2_code":"2401",
    "gn:asciiname":"Regi",
    "gn:country_code":"AF",
    "gn:dem":990,
    "gn:feature_class":"P",
    "gn:feature_code":"PPL",
    "gn:name":"Regi",
    "gn:population":0,
    "gn:timezone":"Asia/Kabul",
    "iso:country":"AF",
    "name:fas_x_preferred":[
        "\u0631\u064a\u06af\u06cc"
    ],
    "name:und_x_variant":[
        "\u1e5e\u0113gi",
        "Regi",
        "Rayg\u012b",
        "R\u0113gay",
        "R\u0113g\u012b"
    ],
    "wof:name":"Regi",
    "wof:placetype":"locality"
},
  "geometry": {"coordinates":[65.68992,31.59847],"type":"Point"}
}