{
  "type": "Feature",
  "properties": {
    "gn:admin1_code":"09",
    "gn:admin2_code":"2707",
    "gn:asciiname":"Siyah Now",
    "gn:country_code":"AF",
    "gn:dem":3195,
    "gn:feature_class":"P",
    "gn:feature_code":"PPL",
    "gn:name":"Siy\u0101h Now",
    "gn:population":0,
    "gn:timezone":"Asia/Kabul",
    "iso:country":"AF",
    "name:und_x_variant":[
        "Sy\u0101hnaw",
        "S\u012b\u0101h N\u0101v",
        "Siakhnau",
        "S\u012b\u0101h Now",
        "\u0633\u06cc\u0627\u0647 \u0646\u0648",
        "Siy\u0101h Now"
    ],
    "wof:name":"Siyah Now",
    "wof:placetype":"locality"
},
  "geometry": {"coordinates":[65.89381999999999,34.36331],"type":"Point"}
}