{
  "type": "Feature",
  "properties": {
    "gn:admin1_code":"29",
    "gn:admin2_code":"2911.0",
    "gn:asciiname":"Milat-e Kalan",
    "gn:country_code":"AF",
    "gn:dem":2334,
    "gn:feature_class":"P",
    "gn:feature_code":"PPL",
    "gn:name":"Milat-e Kal\u0101n",
    "gn:population":0,
    "gn:timezone":"Asia/Kabul",
    "iso:country":"AF",
    "wof:name":"Milat-e Kalan",
    "wof:placetype":"locality"
},
  "geometry": {"coordinates":[69.17589,32.89428],"type":"Point"}
}