{
  "type": "Feature",
  "properties": {
    "gn:admin1_code":"09",
    "gn:admin2_code":"2703",
    "gn:asciiname":"Qishlaq-e Rah-e Khushk",
    "gn:country_code":"AF",
    "gn:dem":2009,
    "gn:feature_class":"P",
    "gn:feature_code":"PPL",
    "gn:name":"Qishl\u0101q-e R\u0101h-e Khushk",
    "gn:population":0,
    "gn:timezone":"Asia/Kabul",
    "iso:country":"AF",
    "name:und_x_variant":[
        "R\u0101he Khu\u0161k",
        "Qe\u0161l\u0101qe R\u0101he Khu\u0161k",
        "R\u0101h-e Khoshk",
        "Qeshl\u0101q-e R\u0101h-e Khoshk",
        "Qishl\u0101q-e R\u0101h-e Khushk",
        "\u0642\u0634\u0644\u0627\u0642 \u0631\u0627\u0647 \u062e\u0634\u06a9"
    ],
    "wof:name":"Qishlaq-e Rah-e Khushk",
    "wof:placetype":"locality"
},
  "geometry": {"coordinates":[63.50135,33.95697],"type":"Point"}
}