{
  "type": "Feature",
  "properties": {
    "gn:admin1_code":"23",
    "gn:admin2_code":"2411",
    "gn:asciiname":"Mel Mandah",
    "gn:cc2":"AF",
    "gn:country_code":"AF",
    "gn:dem":1143,
    "gn:feature_class":"P",
    "gn:feature_code":"PPL",
    "gn:name":"Mel Mandah",
    "gn:population":0,
    "gn:timezone":"Asia/Kabul",
    "iso:country":"AF",
    "name:und_x_variant":[
        "Mel M\u0101nda"
    ],
    "wof:name":"Mel Mandah",
    "wof:placetype":"locality"
},
  "geometry": {"coordinates":[66.08333,31.18333],"type":"Point"}
}