{
  "type": "Feature",
  "properties": {
    "gn:admin1_code":"38",
    "gn:admin2_code":"3008.0",
    "gn:asciiname":"Bagi",
    "gn:country_code":"AF",
    "gn:dem":1741,
    "gn:feature_class":"P",
    "gn:feature_code":"PPL",
    "gn:name":"Bag\u012b",
    "gn:population":0,
    "gn:timezone":"Asia/Kabul",
    "iso:country":"AF",
    "name:ceb_x_preferred":[
        "Bagi"
    ],
    "name:deu_x_preferred":[
        "Bagi"
    ],
    "name:swe_x_preferred":[
        "Bagi"
    ],
    "name:und_x_variant":[
        "Bag\u012b",
        "\u0628\u06af\u06cc"
    ],
    "wof:name":"Bagi",
    "wof:placetype":"locality"
},
  "geometry": {"coordinates":[70.49457,35.00367],"type":"Point"}
}