{
  "type": "Feature",
  "properties": {
    "gn:admin1_code":"27",
    "gn:admin2_code":"406",
    "gn:asciiname":"Lala Khel",
    "gn:country_code":"AF",
    "gn:dem":2213,
    "gn:feature_class":"P",
    "gn:feature_code":"PPL",
    "gn:name":"L\u0101l\u0101 Kh\u0113l",
    "gn:population":0,
    "gn:timezone":"Asia/Kabul",
    "iso:country":"AF",
    "name:rus_x_preferred":[
        "Lalakheyl\u2019"
    ],
    "name:und_x_variant":[
        "L\u0101l\u0101kh\u0113l",
        "L\u0101l\u0101 Kh\u0113l",
        "L\u0101l\u0101kheyl",
        "\u0644\u0627\u0644\u0627 \u062e\u06d0\u0644"
    ],
    "wof:name":"Lala Khel",
    "wof:placetype":"locality"
},
  "geometry": {"coordinates":[68.6476,34.12539],"type":"Point"}
}