{
  "type": "Feature",
  "properties": {
    "gn:admin1_code":"23",
    "gn:admin2_code":"2403",
    "gn:asciiname":"Shah Karez",
    "gn:country_code":"AF",
    "gn:dem":1306,
    "gn:feature_class":"P",
    "gn:feature_code":"PPL",
    "gn:name":"Sh\u0101h K\u0101r\u0113z",
    "gn:population":0,
    "gn:timezone":"Asia/Kabul",
    "iso:country":"AF",
    "name:und_x_variant":[
        "\u0160\u0101h K\u0101r\u0113z",
        "Shakhkarez",
        "Sh\u0101h K\u0101r\u0113z",
        "\u0634\u0627\u0647 \u06a9\u0627\u0631\u06d0\u0632",
        "Sh\u0101h K\u0101r\u012bz"
    ],
    "wof:name":"Shah Karez",
    "wof:placetype":"locality"
},
  "geometry": {"coordinates":[66.19528000000001,31.96917],"type":"Point"}
}