{
  "type": "Feature",
  "properties": {
    "gn:admin1_code":"01",
    "gn:admin2_code":"1123",
    "gn:asciiname":"Khel-e Asp",
    "gn:country_code":"AF",
    "gn:dem":1793,
    "gn:feature_class":"P",
    "gn:feature_code":"PPL",
    "gn:name":"Kh\u0113l-e Asp",
    "gn:population":0,
    "gn:timezone":"Asia/Kabul",
    "iso:country":"AF",
    "name:und_x_variant":[
        "Kh\u0113l-e Asp",
        "\u062e\u06d0\u0644 \u0627\u0633\u067e"
    ],
    "wof:name":"Khel-e Asp",
    "wof:placetype":"locality"
},
  "geometry": {"coordinates":[70.37696,36.57004000000001],"type":"Point"}
}