{
  "type": "Feature",
  "properties": {
    "gn:admin1_code":"03",
    "gn:admin2_code":"1308.0",
    "gn:asciiname":"Deh-e Mianah",
    "gn:country_code":"AF",
    "gn:dem":1700,
    "gn:feature_class":"P",
    "gn:feature_code":"PPL",
    "gn:name":"Deh-e M\u012b\u0101nah",
    "gn:population":0,
    "gn:timezone":"Asia/Kabul",
    "iso:country":"AF",
    "name:und_x_variant":[
        "\u1e0eehe My\u0101na",
        "Deh-e M\u012b\u0101neh",
        "Deh-e M\u012b\u0101nah",
        "\u062f\u0647 \u0645\u06cc\u0627\u0646\u0647"
    ],
    "wof:name":"Deh-e Mianah",
    "wof:placetype":"locality"
},
  "geometry": {"coordinates":[69.51371,35.93593],"type":"Point"}
}