{
  "type": "Feature",
  "properties": {
    "gn:admin1_code":"6",
    "gn:admin2_code":"2103.0",
    "gn:asciiname":"Bidikash",
    "gn:country_code":"AF",
    "gn:dem":1716,
    "gn:feature_class":"P",
    "gn:feature_code":"PPL",
    "gn:name":"B\u012bd\u012bkash",
    "gn:population":0,
    "gn:timezone":"Asia/Kabul",
    "iso:country":"AF",
    "name:und_x_variant":[
        "B\u012bd\u012bka\u0161",
        "B\u012bd\u012bkash",
        "\u0628\u06cc\u062f\u06cc \u06a9\u0634"
    ],
    "wof:name":"Bidikash",
    "wof:placetype":"locality"
},
  "geometry": {"coordinates":[63.67776,32.73439],"type":"Point"}
}