{
  "type": "Feature",
  "properties": {
    "gn:admin1_code":"05",
    "gn:admin2_code":"2805",
    "gn:asciiname":"Qaryah-ye Qoli",
    "gn:country_code":"AF",
    "gn:dem":3057,
    "gn:feature_class":"P",
    "gn:feature_code":"PPL",
    "gn:name":"Qaryah-ye Q\u014dl\u012b",
    "gn:population":0,
    "gn:timezone":"Asia/Kabul",
    "iso:country":"AF",
    "name:rus_x_preferred":[
        "Kar\u2019yakuli"
    ],
    "name:und_x_variant":[
        "Qa\u1e5fya-i-Qoli",
        "Qa\u1e5fya Qoli",
        "Qaryah-ye Q\u014dl\u012b",
        "Qaryeh-ye Qol\u012b",
        "\u0642\u0631\u064a\u0647 \u0642\u0648\u0644\u06cc"
    ],
    "wof:name":"Qaryah-ye Qoli",
    "wof:placetype":"locality"
},
  "geometry": {"coordinates":[67.13302,34.49310999999999],"type":"Point"}
}