{
  "type": "Feature",
  "properties": {
    "gn:admin1_code":"24",
    "gn:admin2_code":"1402.0",
    "gn:asciiname":"Joy-e Begum",
    "gn:country_code":"AF",
    "gn:dem":366,
    "gn:feature_class":"P",
    "gn:feature_code":"PPL",
    "gn:name":"J\u014dy-e B\u0113gum",
    "gn:population":0,
    "gn:timezone":"Asia/Kabul",
    "iso:country":"AF",
    "name:und_x_variant":[
        "Dzhuyi-Begum",
        "J\u014dy-i-B\u0113gum",
        "J\u016by-e Beygum",
        "J\u014dy-e B\u0113gum",
        "\u062c\u0648\u06cc \u0628\u06d0\u06af\u0645"
    ],
    "wof:name":"Joy-e Begum",
    "wof:placetype":"locality"
},
  "geometry": {"coordinates":[68.95010000000001,37.14312],"type":"Point"}
}