{
  "type": "Feature",
  "properties": {
    "gn:admin1_code":"28",
    "gn:admin2_code":"2501",
    "gn:asciiname":"Jahak",
    "gn:country_code":"AF",
    "gn:dem":1835,
    "gn:feature_class":"P",
    "gn:feature_code":"PPL",
    "gn:name":"Jahak",
    "gn:population":0,
    "gn:timezone":"Asia/Kabul",
    "iso:country":"AF",
    "name:fas_x_preferred":[
        "\u062c\u0647\u0643"
    ],
    "name:und_x_variant":[
        "Dzhakhak",
        "Jahak",
        "\u062c\u0647\u06a9"
    ],
    "wof:name":"Jahak",
    "wof:placetype":"locality"
},
  "geometry": {"coordinates":[67.15278000000001,32.12742],"type":"Point"}
}