{
  "type": "Feature",
  "properties": {
    "gn:admin1_code":"30",
    "gn:admin2_code":"1610",
    "gn:asciiname":"Shamalak",
    "gn:country_code":"AF",
    "gn:dem":1116,
    "gn:feature_class":"P",
    "gn:feature_code":"PPL",
    "gn:name":"Sham\u0101lak",
    "gn:population":0,
    "gn:timezone":"Asia/Kabul",
    "iso:country":"AF",
    "name:und_x_variant":[
        "Shamallak",
        "Shom\u0101lak",
        "Sham\u0101lak",
        "\u0634\u0645\u0627\u0644\u06a9"
    ],
    "wof:name":"Shamalak",
    "wof:placetype":"locality"
},
  "geometry": {"coordinates":[67.10168,36.0703],"type":"Point"}
}