{
  "type": "Feature",
  "properties": {
    "gn:admin1_code":"10",
    "gn:admin2_code":"2305.0",
    "gn:asciiname":"Bazgir",
    "gn:country_code":"AF",
    "gn:dem":1437,
    "gn:feature_class":"P",
    "gn:feature_code":"PPL",
    "gn:name":"B\u0101zg\u012br",
    "gn:population":0,
    "gn:timezone":"Asia/Kabul",
    "iso:country":"AF",
    "name:fas_x_preferred":[
        "\u0628\u0627\u0632\u06af\u064a\u0631"
    ],
    "name:und_x_variant":[
        "B\u0101zg\u012br",
        "\u0628\u0627\u0632\u06af\u06cc\u0631"
    ],
    "wof:name":"Bazgir",
    "wof:placetype":"locality"
},
  "geometry": {"coordinates":[64.97828,33.03316],"type":"Point"}
}