{
  "type": "Feature",
  "properties": {
    "gn:admin1_code":"8",
    "gn:admin2_code":"617.0",
    "gn:asciiname":"Atarghanah",
    "gn:country_code":"AF",
    "gn:dem":2662,
    "gn:feature_class":"P",
    "gn:feature_code":"PPL",
    "gn:name":"Atarghanah",
    "gn:population":0,
    "gn:timezone":"Asia/Kabul",
    "iso:country":"AF",
    "name:und_x_variant":[
        "Ata\u1e5fghana",
        "Atargana",
        "Atarghanah",
        "\u0627\u062a\u0631\u063a\u0646\u0647"
    ],
    "wof:name":"Atarghanah",
    "wof:placetype":"locality"
},
  "geometry": {"coordinates":[68.13088,33.66581],"type":"Point"}
}