{
  "type": "Feature",
  "properties": {
    "gn:admin1_code":"13",
    "gn:admin2_code":"108",
    "gn:asciiname":"Zarshakh",
    "gn:country_code":"AF",
    "gn:dem":2139,
    "gn:feature_class":"P",
    "gn:feature_code":"PPL",
    "gn:name":"Zarshakh",
    "gn:population":0,
    "gn:timezone":"Asia/Kabul",
    "iso:country":"AF",
    "name:und_x_variant":[
        "Zar\u0161akh",
        "Zar Shakh",
        "Zarshakh",
        "\u0632\u0631\u0634\u062e"
    ],
    "wof:name":"Zarshakh",
    "wof:placetype":"locality"
},
  "geometry": {"coordinates":[69.00684,34.59312],"type":"Point"}
}