{
  "type": "Feature",
  "properties": {
    "gn:admin1_code":"11",
    "gn:admin2_code":"2003",
    "gn:asciiname":"Gilkand",
    "gn:country_code":"AF",
    "gn:dem":1137,
    "gn:feature_class":"P",
    "gn:feature_code":"PPL",
    "gn:name":"Gilkand",
    "gn:population":0,
    "gn:timezone":"Asia/Kabul",
    "iso:country":"AF",
    "name:und_x_variant":[
        "\u06af\u0644\u06a9\u0646\u062f",
        "Gelkand"
    ],
    "wof:name":"Gilkand",
    "wof:placetype":"locality"
},
  "geometry": {"coordinates":[61.53244,33.87345999999999],"type":"Point"}
}