{
  "type": "Feature",
  "properties": {
    "gn:admin1_code":"8",
    "gn:admin2_code":"608.0",
    "gn:asciiname":"Samand Qal'ah",
    "gn:country_code":"AF",
    "gn:dem":1998,
    "gn:feature_class":"P",
    "gn:feature_code":"PPL",
    "gn:name":"Samand Qal\u2018ah",
    "gn:population":0,
    "gn:timezone":"Asia/Kabul",
    "iso:country":"AF",
    "name:und_x_variant":[
        "Saman\u1e0f Qal\u2018a",
        "Samandkala",
        "Samand Qal\u2018eh",
        "Samand Qal\u2018ah",
        "\u0633\u0645\u0646\u062f \u0642\u0644\u0639\u0647"
    ],
    "wof:name":"Samand Qal'ah",
    "wof:placetype":"locality"
},
  "geometry": {"coordinates":[67.78515,32.8249],"type":"Point"}
}