{
  "type": "Feature",
  "properties": {
    "gn:admin1_code":"41",
    "gn:admin2_code":"3408.0",
    "gn:asciiname":"Mamakah",
    "gn:country_code":"AF",
    "gn:dem":2626,
    "gn:feature_class":"P",
    "gn:feature_code":"PPL",
    "gn:name":"M\u0101makah",
    "gn:population":0,
    "gn:timezone":"Asia/Kabul",
    "iso:country":"AF",
    "name:und_x_variant":[
        "M\u0101maka",
        "Mamaka",
        "M\u0101mahkah",
        "M\u0101mehkah",
        "M\u0101makah",
        "\u0645\u0627\u0645\u06a9\u0647"
    ],
    "wof:name":"Mamakah",
    "wof:placetype":"locality"
},
  "geometry": {"coordinates":[66.04619,34.2844],"type":"Point"}
}