{
  "type": "Feature",
  "properties": {
    "gn:admin1_code":"27",
    "gn:admin2_code":"401.0",
    "gn:asciiname":"Chahar Deh",
    "gn:country_code":"AF",
    "gn:dem":2511,
    "gn:feature_class":"P",
    "gn:feature_code":"PPL",
    "gn:name":"Chah\u0101r Deh",
    "gn:population":0,
    "gn:timezone":"Asia/Kabul",
    "iso:country":"AF",
    "name:und_x_variant":[
        "\u010cah\u0101rdeh",
        "Chakhardekh",
        "Chah\u0101r Deh",
        "Chah\u0101rdeh",
        "\u0686\u0647\u0627\u0631 \u062f\u0647"
    ],
    "wof:name":"Chahar Deh",
    "wof:placetype":"locality"
},
  "geometry": {"coordinates":[68.79774999999999,34.49378],"type":"Point"}
}