{
  "type": "Feature",
  "properties": {
    "gn:admin1_code":"18",
    "gn:admin2_code":"809",
    "gn:asciiname":"Kaday",
    "gn:country_code":"AF",
    "gn:dem":875,
    "gn:feature_class":"P",
    "gn:feature_code":"PPL",
    "gn:name":"Ka\u1e0fay",
    "gn:population":0,
    "gn:timezone":"Asia/Kabul",
    "iso:country":"AF",
    "name:fas_x_preferred":[
        "\u0643\u062f\u06cc"
    ],
    "name:und_x_variant":[
        "Ka\u1e0fay",
        "\u06a9\u0689\u06cc",
        "Kaday"
    ],
    "wof:name":"Kaday",
    "wof:placetype":"locality"
},
  "geometry": {"coordinates":[70.51241,34.23915],"type":"Point"}
}