{
  "type": "Feature",
  "properties": {
    "gn:admin1_code":"41",
    "gn:admin2_code":"3403.0",
    "gn:asciiname":"Nawah",
    "gn:country_code":"AF",
    "gn:dem":2633,
    "gn:feature_class":"P",
    "gn:feature_code":"PPL",
    "gn:name":"N\u0101wah",
    "gn:population":0,
    "gn:timezone":"Asia/Kabul",
    "iso:country":"AF",
    "name:und_x_variant":[
        "N\u0101wa",
        "N\u0101wah",
        "\u0646\u0627\u0648\u0647",
        "N\u0101veh"
    ],
    "wof:name":"Nawah",
    "wof:placetype":"locality"
},
  "geometry": {"coordinates":[66.40815000000001,33.99541],"type":"Point"}
}