{
  "type": "Feature",
  "properties": {
    "gn:admin1_code":"08",
    "gn:admin2_code":"613",
    "gn:asciiname":"Qarah Bagh",
    "gn:country_code":"AF",
    "gn:dem":2089,
    "gn:feature_class":"P",
    "gn:feature_code":"PPLA2",
    "gn:name":"Qarah B\u0101gh",
    "gn:population":0,
    "gn:timezone":"Asia/Kabul",
    "iso:country":"AF",
    "name:fas_x_preferred":[
        "\u0642\u0631\u0647 \u0628\u0627\u063a"
    ],
    "name:und_x_variant":[
        "Karabag",
        "Qa\u1e5fab\u0101gh",
        "Qarah B\u0101gh",
        "Qarehb\u0101gh"
    ],
    "wof:name":"Qarah Bagh",
    "wof:placetype":"locality"
},
  "geometry": {"coordinates":[68.10798,33.19801],"type":"Point"}
}