{
  "type": "Feature",
  "properties": {
    "gn:admin1_code":"08",
    "gn:admin2_code":"613",
    "gn:asciiname":"Qarah Bagh",
    "gn:country_code":"AF",
    "gn:dem":2089,
    "gn:feature_class":"P",
    "gn:feature_code":"PPLA2",
    "gn:name":"Qarah B\u0101gh",
    "gn:population":0,
    "gn:timezone":"Asia/Kabul",
    "iso:country":"AF",
    "name:aze_x_preferred":[
        "Qaraba\u011f vulusvalisi"
    ],
    "name:ben_x_preferred":[
        "\u0995\u09be\u09b0\u09ac\u09be\u0997 \u099c\u09c7\u09b2\u09be"
    ],
    "name:fas_x_preferred":[
        "\u0642\u0631\u0647 \u0628\u0627\u063a"
    ],
    "name:fas_x_variant":[
        "\u0648\u0644\u0633\u0648\u0627\u0644\u06cc \u0642\u0631\u0647\u200c\u0628\u0627\u063a"
    ],
    "name:msa_x_preferred":[
        "Daerah Qarabagh"
    ],
    "name:pol_x_preferred":[
        "Qarabagh"
    ],
    "name:pus_x_preferred":[
        "\u0642\u0631\u0647 \u0628\u0627\u063a \u0648\u0644\u0633\u0648\u0627\u0644\u06cd"
    ],
    "name:tur_x_preferred":[
        "Karaba\u011f il\u00e7esi"
    ],
    "name:und_x_variant":[
        "Karabag",
        "Qa\u1e5fab\u0101gh",
        "Qarah B\u0101gh",
        "Qarehb\u0101gh"
    ],
    "name:urd_x_preferred":[
        "\u0642\u0631\u06c1 \u0628\u0627\u063a \u0636\u0644\u0639"
    ],
    "name:vie_x_preferred":[
        "Qarabagh"
    ],
    "wof:name":"Qarah Bagh",
    "wof:placetype":"locality"
},
  "geometry": {"coordinates":[68.10798,33.19801],"type":"Point"}
}