{
  "type": "Feature",
  "properties": {
    "gn:admin1_code":"18",
    "gn:admin2_code":"807.0",
    "gn:asciiname":"Pachir wa Agam",
    "gn:country_code":"AF",
    "gn:dem":1241,
    "gn:feature_class":"P",
    "gn:feature_code":"PPLA2",
    "gn:name":"Pach\u012br wa \u0100g\u0101m",
    "gn:population":0,
    "gn:timezone":"Asia/Kabul",
    "iso:country":"AF",
    "name:und_x_variant":[
        "Ag\u0101m",
        "Pa\u010d\u012bro Ag\u0101m",
        "Pach\u012ber Agam",
        "Pachiro Agam",
        "Pach\u012br \u0100g\u0101m",
        "Pachiro Ag\u0101m",
        "Pach\u012br Aw \u0100g\u0101m",
        "Pach\u012br\u014d Ag\u0101m",
        "\u067e\u0686\u06cc\u0631\u0648 \u0627\u06af\u0627\u0645",
        "\u0627\u06af\u0627\u0645",
        "Pach\u012br wa \u0100g\u0101m",
        "\u067e\u0686\u064a\u0631 \u0648 \u0622\u06af\u0627\u0645"
    ],
    "wof:name":"Pachir wa Agam",
    "wof:placetype":"locality"
},
  "geometry": {"coordinates":[70.27806,34.20011],"type":"Point"}
}