{
  "type": "Feature",
  "properties": {
    "gn:admin1_code":"29",
    "gn:admin2_code":"2901.0",
    "gn:asciiname":"Fatimah Khel",
    "gn:country_code":"AF",
    "gn:dem":2147,
    "gn:feature_class":"P",
    "gn:feature_code":"PPL",
    "gn:name":"F\u0101\u0163imah Kh\u0113l",
    "gn:population":0,
    "gn:timezone":"Asia/Kabul",
    "iso:country":"AF",
    "name:rus_x_preferred":[
        "Fatimakheyl\u2019"
    ],
    "name:und_x_variant":[
        "F\u0101\u1e6fema Kh\u0113l",
        "\u0641\u0627\u0637\u0645\u0647 \u062e\u06d0\u0644",
        "F\u0101\u0163emeh Kheyl",
        "F\u0101\u0163imah Kh\u0113l"
    ],
    "wof:name":"Fatimah Khel",
    "wof:placetype":"locality"
},
  "geometry": {"coordinates":[68.79496,33.15938],"type":"Point"}
}