{
  "type": "Feature",
  "properties": {
    "gn:admin1_code":"6",
    "gn:admin2_code":"2104.0",
    "gn:asciiname":"Bayri",
    "gn:country_code":"AF",
    "gn:dem":1911,
    "gn:feature_class":"P",
    "gn:feature_code":"PPL",
    "gn:name":"Bayr\u012b",
    "gn:population":0,
    "gn:timezone":"Asia/Kabul",
    "iso:country":"AF",
    "name:und_x_variant":[
        "Bayr\u012b",
        "\u0628\u06cc\u0631\u06cc",
        "Bay\u1e5f\u012b"
    ],
    "wof:name":"Bayri",
    "wof:placetype":"locality"
},
  "geometry": {"coordinates":[63.64464,33.35592],"type":"Point"}
}