{
  "type": "Feature",
  "properties": {
    "gn:admin1_code":"33",
    "gn:admin2_code":"3103",
    "gn:asciiname":"Shorah List",
    "gn:country_code":"AF",
    "gn:dem":2606,
    "gn:feature_class":"P",
    "gn:feature_code":"PPL",
    "gn:name":"Sh\u014drah List",
    "gn:population":0,
    "gn:timezone":"Asia/Kabul",
    "iso:country":"AF",
    "name:und_x_variant":[
        "Sa\u014d\u1e5falest",
        "Sh\u016bralest",
        "Sh\u014drah List",
        "\u0634\u0648\u0631\u0647 \u0644\u0633\u062a",
        "Sh\u014drah Layst",
        "\u0634\u0648\u0631\u0647 \u0644\u06cc\u0633\u062a"
    ],
    "wof:name":"Shorah List",
    "wof:placetype":"locality"
},
  "geometry": {"coordinates":[65.94858000000001,35.30431],"type":"Point"}
}