{
  "type": "Feature",
  "properties": {
    "gn:admin1_code":"09",
    "gn:admin2_code":"2705",
    "gn:asciiname":"Safedarak",
    "gn:country_code":"AF",
    "gn:dem":2516,
    "gn:feature_class":"P",
    "gn:feature_code":"PPL",
    "gn:name":"Saf\u0113d\u0101rak",
    "gn:population":0,
    "gn:timezone":"Asia/Kabul",
    "iso:country":"AF",
    "name:und_x_variant":[
        "Saf\u0113\u1e0f\u0101\u1e5fak",
        "Safayd\u0101rak",
        "\u0633\u0641\u06d0\u062f\u0627\u0631\u06a9",
        "Sef\u012bd\u0101rak",
        "Saf\u0113d\u0101rak"
    ],
    "wof:name":"Safedarak",
    "wof:placetype":"locality"
},
  "geometry": {"coordinates":[64.19913000000001,33.58515],"type":"Point"}
}