{
  "type": "Feature",
  "properties": {
    "gn:admin1_code":"08",
    "gn:admin2_code":"604",
    "gn:asciiname":"Khisar",
    "gn:country_code":"AF",
    "gn:dem":3021,
    "gn:feature_class":"P",
    "gn:feature_code":"PPL",
    "gn:name":"Khisar",
    "gn:population":0,
    "gn:timezone":"Asia/Kabul",
    "iso:country":"AF",
    "name:ceb_x_preferred":[
        "Hesar"
    ],
    "name:fas_x_preferred":[
        "\u062d\u0635\u0627\u0631"
    ],
    "name:kur_x_preferred":[
        "Hesar"
    ],
    "name:swe_x_preferred":[
        "Hesar"
    ],
    "name:und_x_variant":[
        "\u1e28e\u015f\u0101r",
        "\u1e28i\u015f\u0101r",
        "\u062d\u0635\u0627\u0631"
    ],
    "wof:name":"Khisar",
    "wof:placetype":"locality"
},
  "geometry": {"coordinates":[67.61411,34.11906],"type":"Point"}
}