{
  "type": "Feature",
  "properties": {
    "gn:admin1_code":"30",
    "gn:admin2_code":"1603",
    "gn:asciiname":"Hazaramurdah",
    "gn:country_code":"AF",
    "gn:dem":2635,
    "gn:feature_class":"P",
    "gn:feature_code":"PPL",
    "gn:name":"Haz\u0101ramurdah",
    "gn:population":0,
    "gn:timezone":"Asia/Kabul",
    "iso:country":"AF",
    "name:und_x_variant":[
        "Haz\u0101\u1e5famu\u1e5f\u1e0fa",
        "Haz\u0101rehmordeh",
        "Haz\u0101ramurdah",
        "\u0647\u0632\u0627\u0631\u0645\u0631\u062f\u0647"
    ],
    "wof:name":"Hazaramurdah",
    "wof:placetype":"locality"
},
  "geometry": {"coordinates":[66.62406,35.70917],"type":"Point"}
}