{
  "type": "Feature",
  "properties": {
    "gn:admin1_code":"01",
    "gn:admin2_code":"1104",
    "gn:asciiname":"Velu",
    "gn:country_code":"AF",
    "gn:dem":2852,
    "gn:feature_class":"P",
    "gn:feature_code":"PPL",
    "gn:name":"Velu",
    "gn:population":0,
    "gn:timezone":"Asia/Kabul",
    "iso:country":"AF",
    "name:fra_x_preferred":[
        "Velu"
    ],
    "name:ukr_x_preferred":[
        "\u0412\u0435\u043b\u044e"
    ],
    "name:und_x_variant":[
        "\u0648\u06d0\u0644\u0648",
        "W\u0113lo",
        "W\u0113l\u014d"
    ],
    "wof:name":"Velu",
    "wof:placetype":"locality"
},
  "geometry": {"coordinates":[70.89975,35.92413],"type":"Point"}
}