{
  "type": "Feature",
  "properties": {
    "gn:admin1_code":"26",
    "gn:admin2_code":"1205",
    "gn:asciiname":"Mulkuk",
    "gn:country_code":"AF",
    "gn:dem":2156,
    "gn:feature_class":"P",
    "gn:feature_code":"PPL",
    "gn:name":"Mulk\u016bk",
    "gn:population":0,
    "gn:timezone":"Asia/Kabul",
    "iso:country":"AF",
    "name:und_x_variant":[
        "Mulk\u016bk",
        "Molk\u016bk",
        "\u0645\u0644\u06a9\u0648\u06a9"
    ],
    "wof:name":"Mulkuk",
    "wof:placetype":"locality"
},
  "geometry": {"coordinates":[69.86095999999999,36.1993],"type":"Point"}
}