{
  "type": "Feature",
  "properties": {
    "gn:admin1_code":"41",
    "gn:admin2_code":"3406",
    "gn:asciiname":"Faizabad",
    "gn:country_code":"AF",
    "gn:dem":1393,
    "gn:feature_class":"P",
    "gn:feature_code":"PPL",
    "gn:name":"Fa\u012b\u1e95\u0101b\u0101d",
    "gn:population":0,
    "gn:timezone":"Asia/Kabul",
    "iso:country":"AF",
    "name:und_x_variant":[
        "Fay\u1e0f\u1e95\u0101b\u0101d",
        "Fay\u1e95\u0101b\u0101d",
        "\u0641\u06cc\u0636 \u0622\u0628\u0627\u062f",
        "Fey\u1e95\u0101b\u0101d",
        "Fa\u012b\u1e95\u0101b\u0101d"
    ],
    "wof:name":"Faizabad",
    "wof:placetype":"locality"
},
  "geometry": {"coordinates":[65.69594000000001,33.42679],"type":"Point"}
}