{
  "type": "Feature",
  "properties": {
    "gn:admin1_code":"08",
    "gn:admin2_code":"619",
    "gn:asciiname":"Qal'ah-ye Mulla",
    "gn:country_code":"AF",
    "gn:dem":2530,
    "gn:feature_class":"P",
    "gn:feature_code":"PPL",
    "gn:name":"Qal\u2018ah-ye Mull\u0101",
    "gn:population":0,
    "gn:timezone":"Asia/Kabul",
    "iso:country":"AF",
    "name:und_x_variant":[
        "Qal\u2018a Mull\u0101",
        "Kalamulla",
        "Qal\u2018a-i-Mull\u0101",
        "Qal\u2018ah-ye Mull\u0101",
        "Qal\u2018eh-ye Moll\u0101",
        "\u0642\u0644\u0639\u0647 \u0645\u0644\u0627"
    ],
    "wof:name":"Qal'ah-ye Mulla",
    "wof:placetype":"locality"
},
  "geometry": {"coordinates":[68.28029000000001,33.61797],"type":"Point"}
}