{
  "type": "Feature",
  "properties": {
    "gn:admin1_code":"13",
    "gn:admin2_code":"104.0",
    "gn:asciiname":"Qal'ah-ye Farhad",
    "gn:country_code":"AF",
    "gn:dem":1585,
    "gn:feature_class":"P",
    "gn:feature_code":"PPL",
    "gn:name":"Qal\u2018ah-ye Farh\u0101d",
    "gn:population":0,
    "gn:timezone":"Asia/Kabul",
    "iso:country":"AF",
    "name:fas_x_preferred":[
        "\u0642\u0644\u0639\u06c0 \u0641\u0631\u0647\u0627\u0686"
    ],
    "name:und_x_variant":[
        "Kalayi-Farkhad",
        "Qal\u0101-i-Fa\u1e5fh\u0101c",
        "Qal\u0101-i-Fa\u1e5fh\u0101\u1e0f",
        "Qal\u2018eh-ye Farh\u0101c",
        "Qal\u2018eh-ye Fa\u1e5fh\u0101ts",
        "\u0642\u0644\u0639\u06c0 \u0641\u0631\u0647\u0627\u062f",
        "Qal\u2018ah-ye Farh\u0101d"
    ],
    "wof:name":"Qal'ah-ye Farhad",
    "wof:placetype":"locality"
},
  "geometry": {"coordinates":[69.14702,34.79876],"type":"Point"}
}