{
  "type": "Feature",
  "properties": {
    "gn:admin1_code":"13",
    "gn:admin2_code":"104.0",
    "gn:asciiname":"Qal'ah-ye Farhad",
    "gn:country_code":"AF",
    "gn:dem":1585,
    "gn:feature_class":"P",
    "gn:feature_code":"PPL",
    "gn:name":"Qal\u2018ah-ye Farh\u0101d",
    "gn:population":0,
    "gn:timezone":"Asia/Kabul",
    "iso:country":"AF",
    "wof:name":"Qal'ah-ye Farhad",
    "wof:placetype":"locality"
},
  "geometry": {"coordinates":[69.14702,34.79875999999999],"type":"Point"}
}