{
  "type": "Feature",
  "properties": {
    "gn:admin1_code":"42",
    "gn:admin2_code":"3301.0",
    "gn:asciiname":"Changaram",
    "gn:country_code":"AF",
    "gn:dem":2006,
    "gn:feature_class":"P",
    "gn:feature_code":"PPL",
    "gn:name":"Changaram",
    "gn:population":0,
    "gn:timezone":"Asia/Kabul",
    "iso:country":"AF",
    "name:rus_x_preferred":[
        "\u0427\u0430\u043d\u0433\u0430\u0440\u0430\u043c"
    ],
    "name:und_x_variant":[
        "\u010cangaram",
        "Changaram",
        "\u0686\u0646\u06af\u0631\u0645"
    ],
    "wof:name":"Changaram",
    "wof:placetype":"locality"
},
  "geometry": {"coordinates":[69.54589,35.33225],"type":"Point"}
}