{
  "type": "Feature",
  "properties": {
    "gn:admin1_code":"41",
    "gn:admin2_code":"3409.0",
    "gn:asciiname":"Deh",
    "gn:country_code":"AF",
    "gn:dem":2620,
    "gn:feature_class":"P",
    "gn:feature_code":"PPL",
    "gn:name":"Deh",
    "gn:population":0,
    "gn:timezone":"Asia/Kabul",
    "iso:country":"AF",
    "name:snd_x_preferred":[
        "\u062f\u064a\u06be"
    ],
    "name:und_x_variant":[
        "\u062f\u0647"
    ],
    "wof:name":"Deh",
    "wof:placetype":"locality"
},
  "geometry": {"coordinates":[66.43396,33.80736],"type":"Point"}
}