{
  "type": "Feature",
  "properties": {
    "gn:admin1_code":"05",
    "gn:admin2_code":"2805",
    "gn:asciiname":"Ghargharah-ye Faqiro",
    "gn:country_code":"AF",
    "gn:dem":3352,
    "gn:feature_class":"P",
    "gn:feature_code":"PPL",
    "gn:name":"Ghargharah-ye Faq\u012br\u014d",
    "gn:population":0,
    "gn:timezone":"Asia/Kabul",
    "iso:country":"AF",
    "name:fas_x_preferred":[
        "\u063a\u0631\u063a\u0631\u06c0 \u0641\u0642\u064a\u0631"
    ],
    "name:rus_x_preferred":[
        "\u0413\u0430\u0440\u0433\u0430\u0440\u0430\u0439\u0438-\u0424\u0430\u043a\u0438\u0440\u0443"
    ],
    "name:und_x_variant":[
        "Gargarayi-Fakiru",
        "Gha\u1e5fgha\u1e5fa-i-Faqi\u1e5fo",
        "Ghargharah-ye Faq\u012br\u014d",
        "Gharghareh-ye Faq\u012bro",
        "\u063a\u0631\u063a\u0631\u0647 \u0641\u0642\u064a\u0631\u0648"
    ],
    "wof:name":"Ghargharah-ye Faqiro",
    "wof:placetype":"locality"
},
  "geometry": {"coordinates":[67.05265,34.54977],"type":"Point"}
}