{
  "type": "Feature",
  "properties": {
    "gn:admin1_code":"34",
    "gn:admin2_code":"1006.0",
    "gn:asciiname":"Satu",
    "gn:country_code":"AF",
    "gn:dem":1287,
    "gn:feature_class":"P",
    "gn:feature_code":"PPL",
    "gn:name":"Satu",
    "gn:population":0,
    "gn:timezone":"Asia/Kabul",
    "iso:country":"AF",
    "name:fas_x_preferred":[
        "\u0633\u0627\u062a\u0648"
    ],
    "name:fin_x_preferred":[
        "Satu"
    ],
    "name:ind_x_preferred":[
        "Satu"
    ],
    "name:jpn_x_preferred":[
        "\u30b5\u30c8\u30a5"
    ],
    "name:ron_x_preferred":[
        "Satu"
    ],
    "name:und_x_variant":[
        "S\u0101tu",
        "S\u0101t\u016b"
    ],
    "wof:name":"Satu",
    "wof:placetype":"locality"
},
  "geometry": {"coordinates":[71.44071,35.15213],"type":"Point"}
}