{
  "type": "Feature",
  "properties": {
    "gn:admin1_code":"23",
    "gn:admin2_code":"2409.0",
    "gn:asciiname":"Reg 'Alaqahdari",
    "gn:country_code":"AF",
    "gn:dem":919,
    "gn:feature_class":"P",
    "gn:feature_code":"PPL",
    "gn:name":"R\u0113g \u2018Al\u0101qahd\u0101r\u012b",
    "gn:population":0,
    "gn:timezone":"Asia/Kabul",
    "iso:country":"AF",
    "name:fra_x_preferred":[
        "Reg Alaqadari"
    ],
    "name:pus_x_preferred":[
        "\u0631\u06d0\u06af \u0639\u0644\u0627\u0642\u0647 \u062f\u0627\u0631\u06cc"
    ],
    "name:und_x_variant":[
        "Reg \u2018\u0100l\u0101qad\u0101ri",
        "R\u012bg \u2018Al\u0101qehd\u0101r\u012b",
        "R\u0113g \u2018Al\u0101qahd\u0101r\u012b"
    ],
    "wof:name":"Reg 'Alaqahdari",
    "wof:placetype":"locality"
},
  "geometry": {"coordinates":[65.69139,29.73],"type":"Point"}
}