{
  "type": "Feature",
  "properties": {
    "gn:admin1_code":"05",
    "gn:admin2_code":"2805.0",
    "gn:asciiname":"Surkh Lar",
    "gn:country_code":"AF",
    "gn:dem":3005,
    "gn:feature_class":"P",
    "gn:feature_code":"PPL",
    "gn:name":"Surkh L\u0101r",
    "gn:population":0,
    "gn:timezone":"Asia/Kabul",
    "iso:country":"AF",
    "name:und_x_variant":[
        "Surkhlar",
        "Su\u1e5fkhla\u1e5f",
        "Surkh L\u0101r",
        "Sorkhl\u0101r",
        "\u0633\u0631\u062e \u0644\u0627\u0631"
    ],
    "wof:name":"Surkh Lar",
    "wof:placetype":"locality"
},
  "geometry": {"coordinates":[67.13736,34.47872],"type":"Point"}
}