{
  "type": "Feature",
  "properties": {
    "gn:admin1_code":"26",
    "gn:admin2_code":"1206",
    "gn:asciiname":"Khurmab",
    "gn:country_code":"AF",
    "gn:dem":1622,
    "gn:feature_class":"P",
    "gn:feature_code":"PPL",
    "gn:name":"Khurm\u0101b",
    "gn:population":0,
    "gn:timezone":"Asia/Kabul",
    "iso:country":"AF",
    "name:und_x_variant":[
        "Khurm\u0101b",
        "Khu\u1e5fm\u0101b (1)",
        "Khorm\u0101b",
        "\u062e\u0631\u0645\u0627\u0628"
    ],
    "wof:name":"Khurmab",
    "wof:placetype":"locality"
},
  "geometry": {"coordinates":[69.99508,36.58093],"type":"Point"}
}