{
  "type": "Feature",
  "properties": {
    "gn:admin1_code":"33",
    "gn:admin2_code":"3104",
    "gn:asciiname":"Shaykh Sang",
    "gn:country_code":"AF",
    "gn:dem":2414,
    "gn:feature_class":"P",
    "gn:feature_code":"PPL",
    "gn:name":"Shaykh Sang",
    "gn:population":0,
    "gn:timezone":"Asia/Kabul",
    "iso:country":"AF",
    "name:und_x_variant":[
        "S\u0304aykhsang",
        "Sheykh Sang",
        "Shaykh Sang",
        "\u0634\u06cc\u062e \u0633\u0646\u06af"
    ],
    "wof:name":"Shaykh Sang",
    "wof:placetype":"locality"
},
  "geometry": {"coordinates":[66.61341,35.67312000000001],"type":"Point"}
}