{
  "type": "Feature",
  "properties": {
    "gn:admin1_code":"23",
    "gn:admin2_code":"2411",
    "gn:asciiname":"Hanifa Kelay",
    "gn:country_code":"AF",
    "gn:dem":1219,
    "gn:feature_class":"P",
    "gn:feature_code":"PPL",
    "gn:name":"\u1e28anif\u0101 K\u00ealay",
    "gn:population":0,
    "gn:timezone":"Asia/Kabul",
    "iso:country":"AF",
    "name:fas_x_preferred":[
        "\u0642\u0631\u06cc\u06c0 \u062d\u0646\u06cc\u0641\u0647"
    ],
    "name:und_x_variant":[
        "Khanifakalay",
        "\u1e28anif\u0101 K\u00ealay",
        "\u062d\u0646\u0641\u0627 \u06a9\u0644\u06cc",
        "\u1e28an\u012bf\u0101 Kalay"
    ],
    "wof:name":"Hanifa Kelay",
    "wof:placetype":"locality"
},
  "geometry": {"coordinates":[66.38391,31.04489],"type":"Point"}
}