{
  "type": "Feature",
  "properties": {
    "gn:admin1_code":"36",
    "gn:admin2_code":"704.0",
    "gn:asciiname":"Torah Shpah",
    "gn:country_code":"AF",
    "gn:dem":1884,
    "gn:feature_class":"P",
    "gn:feature_code":"PPL",
    "gn:name":"T\u014drah Shpah",
    "gn:population":0,
    "gn:timezone":"Asia/Kabul",
    "iso:country":"AF",
    "name:fas_x_preferred":[
        "\u062a\u0648\u0631\u0647 \u0633\u067e\u0647"
    ],
    "name:und_x_variant":[
        "Torashpa",
        "Tora \u0160pa",
        "T\u016brah Spah",
        "T\u014drah Shpah",
        "\u062a\u0648\u0631\u0647 \u0634\u067e\u0647"
    ],
    "wof:name":"Torah Shpah",
    "wof:placetype":"locality"
},
  "geometry": {"coordinates":[69.45755,33.37834],"type":"Point"}
}