{
  "type": "Feature",
  "properties": {
    "gn:admin1_code":"39",
    "gn:admin2_code":"2603.0",
    "gn:asciiname":"Baykho",
    "gn:country_code":"AF",
    "gn:dem":2654,
    "gn:feature_class":"P",
    "gn:feature_code":"PPL",
    "gn:name":"B\u0101ykh\u014d",
    "gn:population":0,
    "gn:timezone":"Asia/Kabul",
    "iso:country":"AF",
    "name:fas_x_preferred":[
        "\u0628\u0627\u064a\u062e\u0648"
    ],
    "name:und_x_variant":[
        "Baykhu",
        "B\u0101ykh\u014d",
        "\u0628\u0627\u06cc\u062e\u0648",
        "B\u0101ykho"
    ],
    "wof:name":"Baykho",
    "wof:placetype":"locality"
},
  "geometry": {"coordinates":[66.80804000000001,32.92171],"type":"Point"}
}