{
  "type": "Feature",
  "properties": {
    "gn:admin1_code":"28",
    "gn:admin2_code":"2506.0",
    "gn:asciiname":"Dolah",
    "gn:country_code":"AF",
    "gn:dem":1356,
    "gn:feature_class":"P",
    "gn:feature_code":"PPL",
    "gn:name":"\u1e0e\u014dlah",
    "gn:population":0,
    "gn:timezone":"Asia/Kabul",
    "iso:country":"AF",
    "name:und_x_variant":[
        "Dala",
        "D\u014dla",
        "\u0689\u0648\u0644\u0647",
        "Dowlah",
        "\u1e0e\u014dlah"
    ],
    "wof:name":"Dolah",
    "wof:placetype":"locality"
},
  "geometry": {"coordinates":[66.49775,31.88743],"type":"Point"}
}