{
  "type": "Feature",
  "properties": {
    "gn:admin1_code":"14",
    "gn:admin2_code":"204.0",
    "gn:asciiname":"Hamahnag",
    "gn:country_code":"AF",
    "gn:dem":1802,
    "gn:feature_class":"P",
    "gn:feature_code":"PPL",
    "gn:name":"Hamahnag",
    "gn:population":0,
    "gn:timezone":"Asia/Kabul",
    "iso:country":"AF",
    "name:fas_x_preferred":[
        "\u0647\u0645\u0646\u06af"
    ],
    "name:und_x_variant":[
        "Khamanag",
        "Hamah Nag",
        "Hamanag",
        "Hamahnag",
        "\u0647\u0645\u0647 \u0646\u06af"
    ],
    "wof:name":"Hamahnag",
    "wof:placetype":"locality"
},
  "geometry": {"coordinates":[69.66174000000001,34.95786],"type":"Point"}
}