{
  "type": "Feature",
  "properties": {
    "gn:admin1_code":"23",
    "gn:admin2_code":"2412.0",
    "gn:asciiname":"Parwarzai",
    "gn:country_code":"AF",
    "gn:dem":1258,
    "gn:feature_class":"P",
    "gn:feature_code":"PPL",
    "gn:name":"Parwa\u1e5fza\u012b",
    "gn:population":0,
    "gn:timezone":"Asia/Kabul",
    "iso:country":"AF",
    "name:und_x_variant":[
        "Parvarzay",
        "Parwa\u1e5fzay",
        "\u067e\u0631\u0648\u0693\u0632\u06cc",
        "Parwarzay",
        "Parwa\u1e5fza\u012b"
    ],
    "wof:name":"Parwarzai",
    "wof:placetype":"locality"
},
  "geometry": {"coordinates":[66.43584,31.4739],"type":"Point"}
}