{
  "type": "Feature",
  "properties": {
    "gn:admin1_code":"08",
    "gn:admin2_code":"609",
    "gn:asciiname":"Latif",
    "gn:country_code":"AF",
    "gn:dem":1958,
    "gn:feature_class":"P",
    "gn:feature_code":"PPL",
    "gn:name":"La\u0163\u012bf",
    "gn:population":0,
    "gn:timezone":"Asia/Kabul",
    "iso:country":"AF",
    "name:und_x_variant":[
        "La\u0163\u012bf",
        "\u0644\u0637\u06cc\u0641"
    ],
    "wof:name":"Latif",
    "wof:placetype":"locality"
},
  "geometry": {"coordinates":[67.65889,32.69715],"type":"Point"}
}