{
  "type": "Feature",
  "properties": {
    "gn:admin1_code":"09",
    "gn:admin2_code":"2705",
    "gn:asciiname":"'Orusmah",
    "gn:country_code":"AF",
    "gn:dem":2232,
    "gn:feature_class":"P",
    "gn:feature_code":"PPL",
    "gn:name":"\u2018Or\u016bsmah",
    "gn:population":0,
    "gn:timezone":"Asia/Kabul",
    "iso:country":"AF",
    "name:und_x_variant":[
        "Urusma",
        "\u2018O\u1e5f\u016bsma",
        "\u2018Or\u016bsmah",
        "\u0639\u0631\u0648\u0633\u0645\u0647",
        "\u2018Orowsm\u0101"
    ],
    "wof:name":"'Orusmah",
    "wof:placetype":"locality"
},
  "geometry": {"coordinates":[64.52998000000001,33.55283],"type":"Point"}
}