{
  "type": "Feature",
  "properties": {
    "gn:admin1_code":"11",
    "gn:admin2_code":"2014",
    "gn:asciiname":"Deh-e Shafi'",
    "gn:country_code":"AF",
    "gn:dem":1138,
    "gn:feature_class":"P",
    "gn:feature_code":"PPL",
    "gn:name":"Deh-e Shaf\u012b\u2018",
    "gn:population":0,
    "gn:timezone":"Asia/Kabul",
    "iso:country":"AF",
    "name:fas_x_preferred":[
        "\u0642\u0631\u064a\u06c0 \u0634\u0641\u06cc"
    ],
    "name:und_x_variant":[
        "Dehe \u0160afi",
        "Dekhi-Shafi",
        "Deh-e Shaf\u012b",
        "Deh-e Shaf\u012b\u2018",
        "\u062f\u0647 \u0634\u0641\u06cc\u0639",
        "Deh-e Shaf\u2018\u012b",
        "\u062f\u0647 \u0634\u0641\u0639\u06cc"
    ],
    "wof:name":"Deh-e Shafi'",
    "wof:placetype":"locality"
},
  "geometry": {"coordinates":[62.31251999999999,33.3727],"type":"Point"}
}