{
  "type": "Feature",
  "properties": {
    "gn:admin1_code":"09",
    "gn:admin2_code":"2707",
    "gn:asciiname":"Naziran",
    "gn:country_code":"AF",
    "gn:dem":2714,
    "gn:feature_class":"P",
    "gn:feature_code":"PPL",
    "gn:name":"Naziran",
    "gn:population":0,
    "gn:timezone":"Asia/Kabul",
    "iso:country":"AF",
    "name:und_x_variant":[
        "N\u0101z\u0327er\u0101n",
        "N\u0101z\u0327ir\u0101n",
        "\u0646\u0627\u0638\u0631\u0627\u0646"
    ],
    "wof:name":"Naziran",
    "wof:placetype":"locality"
},
  "geometry": {"coordinates":[66.13388,34.58819],"type":"Point"}
}