{
  "type": "Feature",
  "properties": {
    "gn:admin1_code":"01",
    "gn:admin2_code":"1113.0",
    "gn:asciiname":"Rabat-e Gulak",
    "gn:country_code":"AF",
    "gn:dem":1513,
    "gn:feature_class":"P",
    "gn:feature_code":"PPL",
    "gn:name":"Rab\u0101\u0163-e Gulak",
    "gn:population":0,
    "gn:timezone":"Asia/Kabul",
    "iso:country":"AF",
    "name:und_x_variant":[
        "\u1e5eab\u0101\u1e6f-i-Gulak",
        "Rob\u0101\u0163-e Golak",
        "Rab\u0101\u0163-e Gulak",
        "\u0631\u0628\u0627\u0637 \u06af\u0644\u06a9"
    ],
    "wof:name":"Rabat-e Gulak",
    "wof:placetype":"locality"
},
  "geometry": {"coordinates":[70.18604000000001,37.24126],"type":"Point"}
}