{
  "type": "Feature",
  "properties": {
    "gn:admin1_code":"41",
    "gn:admin2_code":"3408.0",
    "gn:asciiname":"Dahan-Badak",
    "gn:country_code":"AF",
    "gn:dem":2595,
    "gn:feature_class":"P",
    "gn:feature_code":"PPL",
    "gn:name":"Dahan-Badak",
    "gn:population":0,
    "gn:timezone":"Asia/Kabul",
    "iso:country":"AF",
    "name:und_x_variant":[
        "Dakhanbadak",
        "Dahan-Badak",
        "\u062f\u0647\u0646 \u0628\u062f\u06a9",
        "Dahan B\u0101dak"
    ],
    "wof:name":"Dahan-Badak",
    "wof:placetype":"locality"
},
  "geometry": {"coordinates":[65.85302,34.26045],"type":"Point"}
}