{
  "type": "Feature",
  "properties": {
    "gn:admin1_code":"39",
    "gn:admin2_code":"2604",
    "gn:asciiname":"Jangalak",
    "gn:country_code":"AF",
    "gn:dem":1106,
    "gn:feature_class":"P",
    "gn:feature_code":"PPL",
    "gn:name":"Jangalak",
    "gn:population":0,
    "gn:timezone":"Asia/Kabul",
    "iso:country":"AF",
    "name:fas_x_preferred":[
        "\u062c\u0646\u06af\u0644\u0643"
    ],
    "name:und_x_variant":[
        "Dzhangalak",
        "Jangalak",
        "\u062c\u0646\u06af\u0644\u06a9"
    ],
    "wof:name":"Jangalak",
    "wof:placetype":"locality"
},
  "geometry": {"coordinates":[65.55117,32.9031],"type":"Point"}
}