{
  "type": "Feature",
  "properties": {
    "gn:admin1_code":"24",
    "gn:admin2_code":"1402.0",
    "gn:asciiname":"Chatal",
    "gn:country_code":"AF",
    "gn:dem":338,
    "gn:feature_class":"P",
    "gn:feature_code":"PPL",
    "gn:name":"Chatal",
    "gn:population":0,
    "gn:timezone":"Asia/Kabul",
    "iso:country":"AF",
    "wof:name":"Chatal",
    "wof:placetype":"locality"
},
  "geometry": {"coordinates":[68.90000000000001,37.23333],"type":"Point"}
}