{
  "type": "Feature",
  "properties": {
    "gn:admin1_code":"14",
    "gn:admin2_code":"205.0",
    "gn:asciiname":"Sinzai",
    "gn:country_code":"AF",
    "gn:dem":1323,
    "gn:feature_class":"P",
    "gn:feature_code":"PPL",
    "gn:name":"S\u012bnza\u012b",
    "gn:population":0,
    "gn:timezone":"Asia/Kabul",
    "iso:country":"AF",
    "name:und_x_variant":[
        "Sh\u012bnz\u0101\u2019\u012b",
        "Sinzai",
        "S\u012bn Za\u2019i",
        "S\u012bnza\u012b",
        "\u0633\u06cc\u0646\u0632\u06cc"
    ],
    "wof:name":"Sinzai",
    "wof:placetype":"locality"
},
  "geometry": {"coordinates":[69.65731,34.8549],"type":"Point"}
}