{
  "type": "Feature",
  "properties": {
    "gn:admin1_code":"8",
    "gn:admin2_code":"612.0",
    "gn:asciiname":"Chambar-e Payindah",
    "gn:country_code":"AF",
    "gn:dem":2066,
    "gn:feature_class":"P",
    "gn:feature_code":"PPL",
    "gn:name":"Chambar-e P\u0101yindah",
    "gn:population":0,
    "gn:timezone":"Asia/Kabul",
    "iso:country":"AF",
    "name:fas_x_preferred":[
        "\u0686\u0646\u0628\u0631\u0654\u0654 \u067e\u0627\u064a\u0646\u062f\u0647"
    ],
    "name:und_x_variant":[
        "\u010cambare P\u0101yendah",
        "Chambari-Payinda",
        "Chanbar-e P\u0101yandah",
        "Chanbar-e P\u0101yandeh",
        "Chambar-e P\u0101yendah",
        "\u0686\u0645\u0628\u0631 \u067e\u0627\u06cc\u0646\u062f\u0647",
        "Chambar-e P\u0101yindah"
    ],
    "wof:name":"Chambar-e Payindah",
    "wof:placetype":"locality"
},
  "geometry": {"coordinates":[68.23576,33.05083],"type":"Point"}
}