{
  "type": "Feature",
  "properties": {
    "gn:admin1_code":"06",
    "gn:admin2_code":"2105",
    "gn:asciiname":"Qaryah-ye Karez",
    "gn:country_code":"AF",
    "gn:dem":956,
    "gn:feature_class":"P",
    "gn:feature_code":"PPL",
    "gn:name":"Qaryah-ye K\u0101r\u0113z",
    "gn:population":0,
    "gn:timezone":"Asia/Kabul",
    "iso:country":"AF",
    "name:rus_x_preferred":[
        "Kar\u2019yayi-Karez"
    ],
    "name:und_x_variant":[
        "Qa\u1e5fya-i-K\u0101\u1e5f\u0113z",
        "Qaryeh-ye K\u0101r\u012bz",
        "Qaryah-ye K\u0101r\u0113z",
        "\u0642\u0631\u06cc\u0647 \u06a9\u0627\u0631\u06d0\u0632"
    ],
    "wof:name":"Qaryah-ye Karez",
    "wof:placetype":"locality"
},
  "geometry": {"coordinates":[63.06879,32.84458],"type":"Point"}
}