{
  "type": "Feature",
  "properties": {
    "gn:admin1_code":"11",
    "gn:admin2_code":"2001.0",
    "gn:asciiname":"Qal'ah-ye Habib Khan",
    "gn:country_code":"AF",
    "gn:dem":876,
    "gn:feature_class":"P",
    "gn:feature_code":"PPL",
    "gn:name":"Qal\u2018ah-ye \u1e28ab\u012bb Kh\u0101n",
    "gn:population":0,
    "gn:timezone":"Asia/Kabul",
    "iso:country":"AF",
    "name:und_x_variant":[
        "Qal\u2018a-i-Hab\u012bb Kh\u0101n",
        "Qal\u2018eh-ye \u1e28ab\u012bb Kh\u0101n",
        "Qal\u2018ah-ye \u1e28ab\u012bb Kh\u0101n",
        "\u0642\u0644\u0639\u06c0 \u062d\u0628\u06cc\u0628 \u062e\u0627\u0646"
    ],
    "wof:name":"Qal'ah-ye Habib Khan",
    "wof:placetype":"locality"
},
  "geometry": {"coordinates":[61.9866,34.36232],"type":"Point"}
}