{
  "type": "Feature",
  "properties": {
    "gn:admin1_code":"07",
    "gn:admin2_code":"1802",
    "gn:asciiname":"Powgani",
    "gn:country_code":"AF",
    "gn:dem":1511,
    "gn:feature_class":"P",
    "gn:feature_code":"PPL",
    "gn:name":"Powg\u0101n\u012b",
    "gn:population":0,
    "gn:timezone":"Asia/Kabul",
    "iso:country":"AF",
    "name:und_x_variant":[
        "Pawg\u0101ni",
        "Powg\u0101n\u012b",
        "\u067e\u0648\u06af\u0627\u0646\u06cc",
        "P\u014drg\u0101n\u012b",
        "\u067e\u0648\u0631\u06af\u0627\u0646\u06cc"
    ],
    "wof:name":"Powgani",
    "wof:placetype":"locality"
},
  "geometry": {"coordinates":[64.82513,35.7797],"type":"Point"}
}