{
  "type": "Feature",
  "properties": {
    "gn:admin1_code":"11",
    "gn:admin2_code":"2012",
    "gn:asciiname":"Hulang Wali",
    "gn:country_code":"AF",
    "gn:dem":1448,
    "gn:feature_class":"P",
    "gn:feature_code":"PPL",
    "gn:name":"H\u016blang Wal\u012b",
    "gn:population":0,
    "gn:timezone":"Asia/Kabul",
    "iso:country":"AF",
    "name:und_x_variant":[
        "H\u016blang-wali",
        "H\u016blang-val\u012b",
        "H\u016blang Wal\u012b",
        "\u0647\u0648\u0644\u0646\u06af \u0648\u0644\u06cc"
    ],
    "wof:name":"Hulang Wali",
    "wof:placetype":"locality"
},
  "geometry": {"coordinates":[63.43909,34.37345999999999],"type":"Point"}
}