{
  "type": "Feature",
  "properties": {
    "gn:admin1_code":"09",
    "gn:admin2_code":"2702",
    "gn:asciiname":"Kaminj",
    "gn:country_code":"AF",
    "gn:dem":1786,
    "gn:feature_class":"P",
    "gn:feature_code":"PPL",
    "gn:name":"Kaminj",
    "gn:population":0,
    "gn:timezone":"Asia/Kabul",
    "iso:country":"AF",
    "name:und_x_variant":[
        "Kamindzh",
        "K\u0101minj",
        "Kamenj",
        "Kaminj",
        "\u06a9\u0645\u0646\u062c"
    ],
    "wof:name":"Kaminj",
    "wof:placetype":"locality"
},
  "geometry": {"coordinates":[64.367,34.38442],"type":"Point"}
}