{
  "type": "Feature",
  "properties": {
    "gn:admin1_code":"30",
    "gn:admin2_code":"1606",
    "gn:asciiname":"Maidan",
    "gn:country_code":"AF",
    "gn:dem":321,
    "gn:feature_class":"P",
    "gn:feature_code":"PPL",
    "gn:name":"Ma\u012bd\u0101n",
    "gn:population":0,
    "gn:timezone":"Asia/Kabul",
    "iso:country":"AF",
    "name:fas_x_preferred":[
        "\u0645\u06cc\u062f\u0627\u0646"
    ],
    "name:por_x_preferred":[
        "Meydan"
    ],
    "name:rus_x_preferred":[
        "\u041c\u0430\u0439\u0434\u0430\u043d"
    ],
    "name:und_x_variant":[
        "Maydan",
        "Meyd\u0101n",
        "\u0645\u06cc\u062f\u0627\u0646",
        "Ma\u012bd\u0101n"
    ],
    "wof:name":"Maidan",
    "wof:placetype":"locality"
},
  "geometry": {"coordinates":[66.91788000000001,36.90572],"type":"Point"}
}