{
  "type": "Feature",
  "properties": {
    "gn:admin1_code":"28",
    "gn:admin2_code":"2510",
    "gn:asciiname":"Haidaray",
    "gn:country_code":"AF",
    "gn:dem":2591,
    "gn:feature_class":"P",
    "gn:feature_code":"PPL",
    "gn:name":"\u1e28a\u012bdaray",
    "gn:population":0,
    "gn:timezone":"Asia/Kabul",
    "iso:country":"AF",
    "name:und_x_variant":[
        "Khaydaray",
        "Ha\u1e0fa\u1e5fay",
        "\u1e28a\u012bdaray",
        "\u062d\u06cc\u062f\u0631\u06cc",
        "\u1e28aydaray"
    ],
    "wof:name":"Haidaray",
    "wof:placetype":"locality"
},
  "geometry": {"coordinates":[67.15138,32.82909],"type":"Point"}
}