{
  "type": "Feature",
  "properties": {
    "gn:admin1_code":"23",
    "gn:admin2_code":"2412.0",
    "gn:asciiname":"Akizai",
    "gn:country_code":"AF",
    "gn:dem":1605,
    "gn:feature_class":"P",
    "gn:feature_code":"PPL",
    "gn:name":"Akiza\u012b",
    "gn:population":0,
    "gn:timezone":"Asia/Kabul",
    "iso:country":"AF",
    "name:und_x_variant":[
        "Akiza\u012b",
        "\u0627\u06a9\u0632\u06cc",
        "Akizay"
    ],
    "wof:name":"Akizai",
    "wof:placetype":"locality"
},
  "geometry": {"coordinates":[66.81373000000001,31.63405],"type":"Point"}
}