{
  "type": "Feature",
  "properties": {
    "gn:admin1_code":"01",
    "gn:admin2_code":"1113.0",
    "gn:asciiname":"Kol Darah",
    "gn:country_code":"AF",
    "gn:dem":1845,
    "gn:feature_class":"P",
    "gn:feature_code":"PPL",
    "gn:name":"K\u014dl Darah",
    "gn:population":0,
    "gn:timezone":"Asia/Kabul",
    "iso:country":"AF",
    "name:und_x_variant":[
        "K\u014dl Darrah",
        "Kowl Darreh",
        "K\u014dl Darah",
        "\u06a9\u0648\u0644 \u062f\u0631\u0647"
    ],
    "wof:name":"Kol Darah",
    "wof:placetype":"locality"
},
  "geometry": {"coordinates":[70.11724,37.41108],"type":"Point"}
}