{
  "type": "Feature",
  "properties": {
    "gn:admin1_code":"01",
    "gn:admin2_code":"1112.0",
    "gn:asciiname":"Seh Ab Dasht",
    "gn:country_code":"AF",
    "gn:dem":2461,
    "gn:feature_class":"P",
    "gn:feature_code":"PPL",
    "gn:name":"Seh \u0100b Dasht",
    "gn:population":0,
    "gn:timezone":"Asia/Kabul",
    "iso:country":"AF",
    "name:und_x_variant":[
        "Seh Ab Da\u0161t",
        "Seh \u0100b Dasht",
        "\u0633\u0647 \u0622\u0628 \u062f\u0634\u062a"
    ],
    "wof:name":"Seh Ab Dasht",
    "wof:placetype":"locality"
},
  "geometry": {"coordinates":[70.54541999999999,37.60479],"type":"Point"}
}