{
  "type": "Feature",
  "properties": {
    "gn:admin1_code":"08",
    "gn:admin2_code":"618",
    "gn:asciiname":"Gudal-e Shamsher",
    "gn:country_code":"AF",
    "gn:dem":2324,
    "gn:feature_class":"P",
    "gn:feature_code":"PPL",
    "gn:name":"Gudal-e Shamsh\u0113r",
    "gn:population":0,
    "gn:timezone":"Asia/Kabul",
    "iso:country":"AF",
    "name:fas_x_preferred":[
        "\u06af\u062f\u0644\u06cc \u0634\u0645\u0634\u064a\u0631"
    ],
    "name:und_x_variant":[
        "Godale \u0160am\u0161\u0113r",
        "Gudali-Shamsher",
        "Godal-e Shamshayr",
        "Godal-e Shamsh\u012br",
        "Gudal-e Shamsh\u0113r",
        "\u06af\u062f\u0644 \u0634\u0645\u0634\u064a\u0631"
    ],
    "wof:name":"Gudal-e Shamsher",
    "wof:placetype":"locality"
},
  "geometry": {"coordinates":[68.27054,33.46223],"type":"Point"}
}