{
  "type": "Feature",
  "properties": {
    "gn:admin1_code":"40",
    "gn:admin2_code":"303.0",
    "gn:asciiname":"Kaftar Khanah",
    "gn:country_code":"AF",
    "gn:dem":2531,
    "gn:feature_class":"P",
    "gn:feature_code":"PPL",
    "gn:name":"Kaftar Kh\u0101nah",
    "gn:population":0,
    "gn:timezone":"Asia/Kabul",
    "iso:country":"AF",
    "name:fas_x_preferred":[
        "\u0643\u0641\u062a\u0631 \u062e\u0627\u0646\u0647"
    ],
    "name:und_x_variant":[
        "Kaftarkhana",
        "Kafta\u1e5fkh\u0101na",
        "Kaftar Kh\u0101neh",
        "Kaftar Kh\u0101nah",
        "\u06a9\u0641\u062a\u0631 \u062e\u0627\u0646\u0647"
    ],
    "wof:name":"Kaftar Khanah",
    "wof:placetype":"locality"
},
  "geometry": {"coordinates":[69.14731,35.2625],"type":"Point"}
}