{
  "type": "Feature",
  "properties": {
    "gn:admin1_code":"11",
    "gn:admin2_code":"2006.0",
    "gn:asciiname":"Bayrjinak",
    "gn:country_code":"AF",
    "gn:dem":698,
    "gn:feature_class":"P",
    "gn:feature_code":"PPL",
    "gn:name":"Bayrj\u012bnak",
    "gn:population":0,
    "gn:timezone":"Asia/Kabul",
    "iso:country":"AF",
    "name:und_x_variant":[
        "B\u0113\u1e5fjinak",
        "Berdzhinak",
        "Bayrj\u012bnak",
        "\u0628\u06cc\u0631\u062c\u06cc\u0646\u06a9",
        "B\u012brjinak"
    ],
    "wof:name":"Bayrjinak",
    "wof:placetype":"locality"
},
  "geometry": {"coordinates":[62.21706999999999,35.22208],"type":"Point"}
}