{
  "type": "Feature",
  "properties": {
    "gn:admin1_code":"42",
    "gn:admin2_code":"3303",
    "gn:asciiname":"Izriah",
    "gn:country_code":"AF",
    "gn:dem":2654,
    "gn:feature_class":"P",
    "gn:feature_code":"PPL",
    "gn:name":"Izr\u012bah",
    "gn:population":0,
    "gn:timezone":"Asia/Kabul",
    "iso:country":"AF",
    "name:fas_x_preferred":[
        "\u0627\u0632\u0631\u064a\u0647"
    ],
    "name:rus_x_preferred":[
        "\u0418\u0437\u0440\u0438\u0430"
    ],
    "name:und_x_variant":[
        "Izria",
        "Ez\u1e5fya",
        "Ezryah",
        "Izr\u012bah",
        "\u0627\u0632\u0631\u06cc\u0647"
    ],
    "wof:name":"Izriah",
    "wof:placetype":"locality"
},
  "geometry": {"coordinates":[69.75236,35.47801],"type":"Point"}
}