{
  "type": "Feature",
  "properties": {
    "gn:admin1_code":"01",
    "gn:admin2_code":"1110.0",
    "gn:asciiname":"Sidyah",
    "gn:country_code":"AF",
    "gn:dem":2113,
    "gn:feature_class":"P",
    "gn:feature_code":"PPL",
    "gn:name":"Sidyah",
    "gn:population":0,
    "gn:timezone":"Asia/Kabul",
    "iso:country":"AF",
    "name:und_x_variant":[
        "Se\u1e0fya",
        "Sedyeh",
        "Sidyah",
        "\u0633\u062f\u06cc\u0647"
    ],
    "wof:name":"Sidyah",
    "wof:placetype":"locality"
},
  "geometry": {"coordinates":[70.84208000000002,38.31489000000001],"type":"Point"}
}