{
  "type": "Feature",
  "properties": {
    "gn:admin1_code":"27",
    "gn:admin2_code":"404.0",
    "gn:asciiname":"Ab Pay",
    "gn:country_code":"AF",
    "gn:dem":2843,
    "gn:feature_class":"P",
    "gn:feature_code":"PPL",
    "gn:name":"\u0100b P\u0101y",
    "gn:population":0,
    "gn:timezone":"Asia/Kabul",
    "iso:country":"AF",
    "name:und_x_variant":[
        "Awp\u0101y",
        "Avpay",
        "\u0100b P\u0101y",
        "\u0100bp\u0101y",
        "\u0622\u0628 \u067e\u0627\u06cc"
    ],
    "wof:name":"Ab Pay",
    "wof:placetype":"locality"
},
  "geometry": {"coordinates":[68.12639,34.27476],"type":"Point"}
}