{
  "type": "Feature",
  "properties": {
    "gn:admin1_code":"01",
    "gn:admin2_code":"1115.0",
    "gn:asciiname":"Turugh",
    "gn:country_code":"AF",
    "gn:dem":1700,
    "gn:feature_class":"P",
    "gn:feature_code":"PPL",
    "gn:name":"\u0162\u016brugh",
    "gn:population":0,
    "gn:timezone":"Asia/Kabul",
    "iso:country":"AF",
    "name:und_x_variant":[
        "\u0162\u016brugh",
        "\u0637\u0648\u0631\u063a",
        "\u1e6e\u016b\u1e5fugh (2)"
    ],
    "wof:name":"Turugh",
    "wof:placetype":"locality"
},
  "geometry": {"coordinates":[70.46395,37.12781],"type":"Point"}
}