{
  "type": "Feature",
  "properties": {
    "gn:admin1_code":"7",
    "gn:admin2_code":"1802.0",
    "gn:asciiname":"Archatu",
    "gn:country_code":"AF",
    "gn:dem":1515,
    "gn:feature_class":"P",
    "gn:feature_code":"PPL",
    "gn:name":"Archat\u016b",
    "gn:population":0,
    "gn:timezone":"Asia/Kabul",
    "iso:country":"AF",
    "name:und_x_variant":[
        "A\u1e5fcat\u016b",
        "Archat\u016b",
        "\u0627\u0631\u0686\u062a\u0648"
    ],
    "wof:name":"Archatu",
    "wof:placetype":"locality"
},
  "geometry": {"coordinates":[64.79228000000001,35.77511],"type":"Point"}
}