{
  "type": "Feature",
  "properties": {
    "gn:admin1_code":"09",
    "gn:admin2_code":"2706",
    "gn:asciiname":"Matak",
    "gn:country_code":"AF",
    "gn:dem":2429,
    "gn:feature_class":"P",
    "gn:feature_code":"PPL",
    "gn:name":"Ma\u1e6fak",
    "gn:population":0,
    "gn:timezone":"Asia/Kabul",
    "iso:country":"AF",
    "name:ceb_x_preferred":[
        "Pulau Matak"
    ],
    "name:fra_x_preferred":[
        "Matak"
    ],
    "name:ita_x_preferred":[
        "Matak"
    ],
    "name:spa_x_preferred":[
        "Matak"
    ],
    "name:swe_x_preferred":[
        "Pulau Matak"
    ],
    "name:und_x_variant":[
        "Ma\u1e6fak",
        "\u0645\u067c\u06a9"
    ],
    "name:vie_x_preferred":[
        "\u0110\u1ea3o Matak"
    ],
    "name:zho_x_preferred":[
        "\u99ac\u5854\u514b\u5cf6"
    ],
    "wof:name":"Matak",
    "wof:placetype":"locality"
},
  "geometry": {"coordinates":[65.12617,33.57073],"type":"Point"}
}