{
  "type": "Feature",
  "properties": {
    "gn:admin1_code":"11",
    "gn:admin2_code":"2005",
    "gn:asciiname":"Jandah Khan",
    "gn:country_code":"AF",
    "gn:dem":1020,
    "gn:feature_class":"P",
    "gn:feature_code":"PPL",
    "gn:name":"Jandah Kh\u0101n",
    "gn:population":0,
    "gn:timezone":"Asia/Kabul",
    "iso:country":"AF",
    "name:und_x_variant":[
        "Dzhandakhan",
        "Jan\u1e0fa Kh\u0101n",
        "Jandeh Kh\u0101n",
        "Jandah Kh\u0101n",
        "\u062c\u0646\u062f\u0647 \u062e\u0627\u0646"
    ],
    "wof:name":"Jandah Khan",
    "wof:placetype":"locality"
},
  "geometry": {"coordinates":[62.44809,34.32513],"type":"Point"}
}