{
  "type": "Feature",
  "properties": {
    "gn:admin1_code":"03",
    "gn:admin2_code":"1308",
    "gn:asciiname":"Deh-e Lala",
    "gn:country_code":"AF",
    "gn:dem":1818,
    "gn:feature_class":"P",
    "gn:feature_code":"PPL",
    "gn:name":"Deh-e L\u0101l\u0101",
    "gn:population":0,
    "gn:timezone":"Asia/Kabul",
    "iso:country":"AF",
    "name:und_x_variant":[
        "\u1e0eehe L\u0101l\u0101",
        "Deh L\u0101l\u0101",
        "Deh-e L\u0101l\u0101",
        "\u062f\u0647 \u0644\u0627\u0644\u0627"
    ],
    "wof:name":"Deh-e Lala",
    "wof:placetype":"locality"
},
  "geometry": {"coordinates":[69.66028,35.94260999999999],"type":"Point"}
}