{
  "type": "Feature",
  "properties": {
    "gn:admin1_code":"13",
    "gn:admin2_code":"112",
    "gn:asciiname":"Jurobay",
    "gn:country_code":"AF",
    "gn:dem":2207,
    "gn:feature_class":"P",
    "gn:feature_code":"PPL",
    "gn:name":"Jur\u014dbay",
    "gn:population":0,
    "gn:timezone":"Asia/Kabul",
    "iso:country":"AF",
    "name:und_x_variant":[
        "Dzhurobay",
        "Jor\u014dbay",
        "Jorowbay",
        "Jur\u014dbay",
        "\u062c\u0631\u0648\u0628\u06cc"
    ],
    "wof:name":"Jurobay",
    "wof:placetype":"locality"
},
  "geometry": {"coordinates":[69.61783,34.35435],"type":"Point"}
}