{
  "type": "Feature",
  "properties": {
    "gn:admin1_code":"41",
    "gn:admin2_code":"3407",
    "gn:asciiname":"Kirmak",
    "gn:country_code":"AF",
    "gn:dem":2627,
    "gn:feature_class":"P",
    "gn:feature_code":"PPL",
    "gn:name":"Kirmak",
    "gn:population":0,
    "gn:timezone":"Asia/Kabul",
    "iso:country":"AF",
    "name:und_x_variant":[
        "Karmak",
        "Kermak",
        "Kirmak",
        "\u06a9\u0631\u0645\u06a9"
    ],
    "wof:name":"Kirmak",
    "wof:placetype":"locality"
},
  "geometry": {"coordinates":[66.55062,33.8597],"type":"Point"}
}