{
  "type": "Feature",
  "properties": {
    "gn:admin1_code":"17",
    "gn:admin2_code":"501",
    "gn:asciiname":"Ud Khel",
    "gn:country_code":"AF",
    "gn:dem":1914,
    "gn:feature_class":"P",
    "gn:feature_code":"PPL",
    "gn:name":"Ud Kh\u0113l",
    "gn:population":0,
    "gn:timezone":"Asia/Kabul",
    "iso:country":"AF",
    "name:fas_x_preferred":[
        "\u0627\u062f \u062e\u06cc\u0644"
    ],
    "name:rus_x_preferred":[
        "Udkheyl\u2019"
    ],
    "name:und_x_variant":[
        "U\u1e0fkh\u0113l",
        "D\u0101w\u016bd Kh\u0113l",
        "Udkheyl",
        "Ud Kh\u0113l",
        "\u0627\u062f \u062e\u06d0\u0644"
    ],
    "wof:name":"Ud Khel",
    "wof:placetype":"locality"
},
  "geometry": {"coordinates":[69.02691,33.97150999999999],"type":"Point"}
}