{
  "type": "Feature",
  "properties": {
    "gn:admin1_code":"11",
    "gn:admin2_code":"2006.0",
    "gn:asciiname":"Ayubi",
    "gn:country_code":"AF",
    "gn:dem":1235,
    "gn:feature_class":"P",
    "gn:feature_code":"PPL",
    "gn:name":"Ay\u016bb\u012b",
    "gn:population":0,
    "gn:timezone":"Asia/Kabul",
    "iso:country":"AF",
    "name:und_x_variant":[
        "Ay\u016bb\u012b",
        "\u0627\u06cc\u0648\u0628\u06cc",
        "\u2018Ay\u016bb\u012b"
    ],
    "wof:name":"Ayubi",
    "wof:placetype":"locality"
},
  "geometry": {"coordinates":[62.03286,34.84684],"type":"Point"}
}