{
  "type": "Feature",
  "properties": {
    "gn:admin1_code":"32",
    "gn:admin2_code":"1502.0",
    "gn:asciiname":"Alashah",
    "gn:country_code":"AF",
    "gn:dem":797,
    "gn:feature_class":"P",
    "gn:feature_code":"PPL",
    "gn:name":"Al\u0101shah",
    "gn:population":0,
    "gn:timezone":"Asia/Kabul",
    "iso:country":"AF",
    "name:und_x_variant":[
        "Al\u0101shah",
        "\u0627\u0644\u0627\u0634\u0647"
    ],
    "wof:name":"Alashah",
    "wof:placetype":"locality"
},
  "geometry": {"coordinates":[68.06994,36.49587],"type":"Point"}
}