{
  "type": "Feature",
  "properties": {
    "gn:admin1_code":"01",
    "gn:admin2_code":"1126.0",
    "gn:asciiname":"Marghuzar",
    "gn:country_code":"AF",
    "gn:dem":1028,
    "gn:feature_class":"P",
    "gn:feature_code":"PPL",
    "gn:name":"Marghuz\u0101r",
    "gn:population":0,
    "gn:timezone":"Asia/Kabul",
    "iso:country":"AF",
    "name:und_x_variant":[
        "Marghuz\u0101r",
        "\u0645\u0631\u063a\u0632\u0627\u0631",
        "Ma\u1e5fghuz\u0101\u1e5f"
    ],
    "wof:name":"Marghuzar",
    "wof:placetype":"locality"
},
  "geometry": {"coordinates":[70.26303,37.19957],"type":"Point"}
}