{
  "type": "Feature",
  "properties": {
    "gn:admin1_code":"17",
    "gn:admin2_code":"501.0",
    "gn:asciiname":"Khoshi Chinahha-ye Pa'in",
    "gn:country_code":"AF",
    "gn:dem":1911,
    "gn:feature_class":"P",
    "gn:feature_code":"PPL",
    "gn:name":"Kh\u014dsh\u012b Ch\u012bnahh\u0101-ye P\u0101\u2019\u012bn",
    "gn:population":0,
    "gn:timezone":"Asia/Kabul",
    "iso:country":"AF",
    "wof:name":"Khoshi Chinahha-ye Pa'in",
    "wof:placetype":"locality"
},
  "geometry": {"coordinates":[69.04172,34.00936],"type":"Point"}
}