{
  "type": "Feature",
  "properties": {
    "gn:admin1_code":"07",
    "gn:admin2_code":"1808",
    "gn:asciiname":"Hasan Quduq",
    "gn:country_code":"AF",
    "gn:dem":748,
    "gn:feature_class":"P",
    "gn:feature_code":"PPL",
    "gn:name":"\u1e28asan Q\u016bd\u016bq",
    "gn:population":0,
    "gn:timezone":"Asia/Kabul",
    "iso:country":"AF",
    "name:und_x_variant":[
        "\u1e28asan Q\u016bd\u016bq",
        "\u062d\u0633\u0646 \u0642\u0648\u062f\u0648\u0642",
        "Hasan Quduq"
    ],
    "wof:name":"Hasan Quduq",
    "wof:placetype":"locality"
},
  "geometry": {"coordinates":[65.06454000000001,36.13573],"type":"Point"}
}