{
  "type": "Feature",
  "properties": {
    "gn:admin1_code":"23",
    "gn:admin2_code":"2407",
    "gn:asciiname":"Khali Zar",
    "gn:country_code":"AF",
    "gn:dem":923,
    "gn:feature_class":"P",
    "gn:feature_code":"PPL",
    "gn:name":"Kh\u0101l\u012b Z\u0101r",
    "gn:population":0,
    "gn:timezone":"Asia/Kabul",
    "iso:country":"AF",
    "name:und_x_variant":[
        "Khalizar",
        "Kh\u0101l\u012b Z\u0101r",
        "\u062e\u0627\u0644\u06cc \u0632\u0627\u0631"
    ],
    "wof:name":"Khali Zar",
    "wof:placetype":"locality"
},
  "geometry": {"coordinates":[64.86811999999999,31.7717],"type":"Point"}
}