{
  "type": "Feature",
  "properties": {
    "gn:admin1_code":"5",
    "gn:admin2_code":"2805.0",
    "gn:asciiname":"Baghalak",
    "gn:country_code":"AF",
    "gn:dem":2826,
    "gn:feature_class":"P",
    "gn:feature_code":"PPL",
    "gn:name":"Baghalak",
    "gn:population":0,
    "gn:timezone":"Asia/Kabul",
    "iso:country":"AF",
    "name:und_x_variant":[
        "Bagalak",
        "Baghalak",
        "\u0628\u063a\u0644\u06a9"
    ],
    "wof:name":"Baghalak",
    "wof:placetype":"locality"
},
  "geometry": {"coordinates":[66.79404,34.37128],"type":"Point"}
}