{
  "type": "Feature",
  "properties": {
    "gn:admin1_code":"08",
    "gn:admin2_code":"614",
    "gn:asciiname":"Shahbaz",
    "gn:country_code":"AF",
    "gn:dem":2071,
    "gn:feature_class":"P",
    "gn:feature_code":"PPL",
    "gn:name":"Shahb\u0101z",
    "gn:population":0,
    "gn:timezone":"Asia/Kabul",
    "iso:country":"AF",
    "name:fas_x_preferred":[
        "\u0634\u0647\u0628\u0627\u0632"
    ],
    "name:und_x_variant":[
        "\u0160ahb\u0101z",
        "Shakhbaz",
        "Shahb\u0101z"
    ],
    "wof:name":"Shahbaz",
    "wof:placetype":"locality"
},
  "geometry": {"coordinates":[68.49069,33.30601],"type":"Point"}
}