{
  "type": "Feature",
  "properties": {
    "gn:admin1_code":"8",
    "gn:admin2_code":"604.0",
    "gn:asciiname":"Dam-e Joy",
    "gn:country_code":"AF",
    "gn:dem":2906,
    "gn:feature_class":"P",
    "gn:feature_code":"PPL",
    "gn:name":"Dam-e J\u014dy",
    "gn:population":0,
    "gn:timezone":"Asia/Kabul",
    "iso:country":"AF",
    "name:fas_x_preferred":[
        "\u062f\u0645\u0654 \u062c\u0648\u06cc"
    ],
    "name:rus_x_preferred":[
        "\u0414\u0430\u043c\u0438-\u0414\u0436\u043e\u0439"
    ],
    "name:und_x_variant":[
        "\u1e0eame J\u014dy",
        "Dami-Dzhoy",
        "Dam-e J\u016by",
        "Dam-e J\u014dy",
        "\u062f\u0645 \u062c\u0648\u06cc"
    ],
    "wof:name":"Dam-e Joy",
    "wof:placetype":"locality"
},
  "geometry": {"coordinates":[67.52803,33.95776],"type":"Point"}
}