{
  "type": "Feature",
  "properties": {
    "gn:admin1_code":"08",
    "gn:admin2_code":"604",
    "gn:asciiname":"Qal'ah-ye Kuhnah-ye Raqol",
    "gn:country_code":"AF",
    "gn:dem":3271,
    "gn:feature_class":"P",
    "gn:feature_code":"PPL",
    "gn:name":"Qal\u2018ah-ye Kuhnah-ye R\u0101q\u014dl",
    "gn:population":0,
    "gn:timezone":"Asia/Kabul",
    "iso:country":"AF",
    "name:fas_x_preferred":[
        "\u0642\u0644\u0639\u0647\u0654 \u0643\u0647\u0646\u06c0 \u0631\u0627\u0642\u0648\u0644"
    ],
    "name:und_x_variant":[
        "Qal\u2018a-i-Kuhna-i-\u1e5e\u0101q\u014dl",
        "Qal\u2018a Kuhna-i-\u1e5e\u0101q\u014dl",
        "Qal\u2018eh-ye Kohneh-ye R\u0101qowl",
        "Qal\u2018ah-ye Kuhnah-ye R\u0101q\u014dl",
        "\u0642\u0644\u0639\u06c0 \u06a9\u0647\u0646\u06c0 \u0631\u0627\u0642\u0648\u0644"
    ],
    "wof:name":"Qal'ah-ye Kuhnah-ye Raqol",
    "wof:placetype":"locality"
},
  "geometry": {"coordinates":[67.75206999999999,33.86686],"type":"Point"}
}