{
  "type": "Feature",
  "properties": {
    "gn:admin1_code":"24",
    "gn:admin2_code":"1406",
    "gn:asciiname":"Zangay Say",
    "gn:country_code":"AF",
    "gn:dem":966,
    "gn:feature_class":"P",
    "gn:feature_code":"PPL",
    "gn:name":"Zangay S\u0101y",
    "gn:population":0,
    "gn:timezone":"Asia/Kabul",
    "iso:country":"AF",
    "name:und_x_variant":[
        "Zangay S\u0101y",
        "\u0632\u0646\u06af\u06cc \u0633\u0627\u06cc",
        "Zangi S\u0101y"
    ],
    "wof:name":"Zangay Say",
    "wof:placetype":"locality"
},
  "geometry": {"coordinates":[69.12009,36.43852],"type":"Point"}
}