{
  "type": "Feature",
  "properties": {
    "gn:admin1_code":"41",
    "gn:admin2_code":"3406.0",
    "gn:asciiname":"Chah-e Gurg",
    "gn:country_code":"AF",
    "gn:dem":1519,
    "gn:feature_class":"P",
    "gn:feature_code":"PPL",
    "gn:name":"Ch\u0101h-e Gurg",
    "gn:population":0,
    "gn:timezone":"Asia/Kabul",
    "iso:country":"AF",
    "name:und_x_variant":[
        "C\u0101he Gu\u1e5fg",
        "Ch\u0101h-e Gurg",
        "\u0686\u0627\u0647 \u06af\u0631\u06af",
        "Ch\u0101h-e Gorg"
    ],
    "wof:name":"Chah-e Gurg",
    "wof:placetype":"locality"
},
  "geometry": {"coordinates":[65.65108000000001,33.5693],"type":"Point"}
}