{
  "type": "Feature",
  "properties": {
    "gn:admin1_code":"23",
    "gn:admin2_code":"2410.0",
    "gn:asciiname":"Tal-e Rah",
    "gn:country_code":"AF",
    "gn:dem":1658,
    "gn:feature_class":"P",
    "gn:feature_code":"PPL",
    "gn:name":"Tal-e R\u0101h",
    "gn:population":0,
    "gn:timezone":"Asia/Kabul",
    "iso:country":"AF",
    "name:und_x_variant":[
        "K\u0101r\u012bz-e Bara Kh\u0101nah",
        "Barakh\u0101na K\u0101r\u012bz",
        "Bara Khan",
        "Bara Kh\u0101n Kili",
        "Tal-e Rah",
        "B\u0101rah Kh\u0101n Kil\u012b",
        "Tal-e R\u0101h",
        "\u062a\u0644 \u0631\u0627\u0647"
    ],
    "wof:name":"Tal-e Rah",
    "wof:placetype":"locality"
},
  "geometry": {"coordinates":[66.25851999999999,29.89982],"type":"Point"}
}