{
  "type": "Feature",
  "properties": {
    "gn:admin1_code":"28",
    "gn:admin2_code":"2510",
    "gn:asciiname":"Fazil Khan Kelay",
    "gn:country_code":"AF",
    "gn:dem":2629,
    "gn:feature_class":"P",
    "gn:feature_code":"PPL",
    "gn:name":"F\u0101\u1e95il Kh\u0101n K\u00ealay",
    "gn:population":0,
    "gn:timezone":"Asia/Kabul",
    "iso:country":"AF",
    "name:rus_x_preferred":[
        "Fazil\u2019khankalay"
    ],
    "name:und_x_variant":[
        "F\u0101\u1e0f\u1e95elkh\u0101n Kalay",
        "F\u0101\u1e95il Kh\u0101n K\u00ealay",
        "\u0641\u0627\u0636\u0644 \u062e\u0627\u0646 \u06a9\u0644\u06cc",
        "F\u0101\u1e95el Kh\u0101n Kalay"
    ],
    "wof:name":"Fazil Khan Kelay",
    "wof:placetype":"locality"
},
  "geometry": {"coordinates":[67.00935,32.76234],"type":"Point"}
}