{
  "type": "Feature",
  "properties": {
    "gn:admin1_code":"23",
    "gn:admin2_code":"2411",
    "gn:asciiname":"Sharghilay",
    "gn:country_code":"AF",
    "gn:dem":1360,
    "gn:feature_class":"P",
    "gn:feature_code":"PPL",
    "gn:name":"Sh\u0101rghilay",
    "gn:population":0,
    "gn:timezone":"Asia/Kabul",
    "iso:country":"AF",
    "name:und_x_variant":[
        "S\u0304\u0101\u1e5fghelay",
        "Shargilay",
        "Sh\u0101rgh\u00ealay",
        "Sh\u0101rghelay",
        "Sh\u0101rghilay",
        "\u0634\u0627\u0631\u063a\u0644\u06cc"
    ],
    "wof:name":"Sharghilay",
    "wof:placetype":"locality"
},
  "geometry": {"coordinates":[66.59222,31.07917],"type":"Point"}
}