{
  "type": "Feature",
  "properties": {
    "gn:admin1_code":"37",
    "gn:admin2_code":"3201.0",
    "gn:asciiname":"Zor Kelay",
    "gn:country_code":"AF",
    "gn:dem":1123,
    "gn:feature_class":"P",
    "gn:feature_code":"PPL",
    "gn:name":"Z\u014d\u1e5f K\u00ealay",
    "gn:population":0,
    "gn:timezone":"Asia/Kabul",
    "iso:country":"AF",
    "name:fas_x_preferred":[
        "\u0642\u0631\u064a\u06c0 \u0632\u0648\u0631"
    ],
    "name:und_x_variant":[
        "Z\u014dr Kalay",
        "Zor-Kalay",
        "Z\u014d\u1e5f K\u00ealay",
        "Z\u016b\u1e5f Kalay",
        "\u0632\u0648\u0693 \u06a9\u0644\u06cc"
    ],
    "wof:name":"Zor Kelay",
    "wof:placetype":"locality"
},
  "geometry": {"coordinates":[69.98209,33.3196],"type":"Point"}
}