{
  "type": "Feature",
  "properties": {
    "gn:admin1_code":"27",
    "gn:admin2_code":"401",
    "gn:asciiname":"Tebah",
    "gn:country_code":"AF",
    "gn:dem":2273,
    "gn:feature_class":"P",
    "gn:feature_code":"PPL",
    "gn:name":"T\u0113bah",
    "gn:population":0,
    "gn:timezone":"Asia/Kabul",
    "iso:country":"AF",
    "name:und_x_variant":[
        "T\u0113ba",
        "Teba",
        "T\u0113bah",
        "Tepah \u2018Us\u0304m\u0101n Kh\u0113l",
        "\u062a\u06d0\u0628\u0647"
    ],
    "wof:name":"Tebah",
    "wof:placetype":"locality"
},
  "geometry": {"coordinates":[68.77939000000001,34.45314],"type":"Point"}
}