{
  "type": "Feature",
  "properties": {
    "gn:admin1_code":"5",
    "gn:admin2_code":"2804.0",
    "gn:asciiname":"Dahan-e Darah-ye Siyah",
    "gn:country_code":"AF",
    "gn:dem":2254,
    "gn:feature_class":"P",
    "gn:feature_code":"PPL",
    "gn:name":"Dahan-e Darah-ye Siy\u0101h",
    "gn:population":0,
    "gn:timezone":"Asia/Kabul",
    "iso:country":"AF",
    "name:und_x_variant":[
        "Dakhani-Darrasiakh",
        "\u1e0eahane Dary\u0101 Sy\u0101h",
        "\u1e0eahane \u1e0ea\u1e5f\u1e5fahe Sy\u0101h",
        "\u1e0eahane \u1e0ea\u1e5f\u1e5fah Sy\u0101h",
        "Dahan-e Darah-ye S\u012b\u0101h",
        "Dahan-e Darreh-ye S\u012b\u0101h",
        "Dahan-e Darah-ye Siy\u0101h",
        "\u062f\u0647\u0646 \u062f\u0631\u0647 \u0633\u064a\u0627\u0647"
    ],
    "wof:name":"Dahan-e Darah-ye Siyah",
    "wof:placetype":"locality"
},
  "geometry": {"coordinates":[66.5352,34.9596],"type":"Point"}
}