{
  "type": "Feature",
  "properties": {
    "gn:admin1_code":"8",
    "gn:admin2_code":"606.0",
    "gn:asciiname":"Chaktamur",
    "gn:country_code":"AF",
    "gn:dem":2841,
    "gn:feature_class":"P",
    "gn:feature_code":"PPL",
    "gn:name":"Chaktam\u016br",
    "gn:population":0,
    "gn:timezone":"Asia/Kabul",
    "iso:country":"AF",
    "name:und_x_variant":[
        "\u010caktam\u016br",
        "Chaktam\u016br",
        "\u0686\u06a9\u062a\u0645\u0648\u0631"
    ],
    "wof:name":"Chaktamur",
    "wof:placetype":"locality"
},
  "geometry": {"coordinates":[66.96865,33.02846],"type":"Point"}
}