{
  "type": "Feature",
  "properties": {
    "gn:admin1_code":"27",
    "gn:admin2_code":"407",
    "gn:asciiname":"Haidar Khel",
    "gn:country_code":"AF",
    "gn:dem":2194,
    "gn:feature_class":"P",
    "gn:feature_code":"PPL",
    "gn:name":"\u1e28a\u012bdar Kh\u0113l",
    "gn:population":0,
    "gn:timezone":"Asia/Kabul",
    "iso:country":"AF",
    "name:rus_x_preferred":[
        "Khaydarkheyl\u2019"
    ],
    "name:und_x_variant":[
        "\u1e28ay\u1e0fa\u1e5fkh\u0113l",
        "\u1e28a\u012bdar Kh\u0113l",
        "\u1e28eydarkheyl",
        "\u062d\u064a\u062f\u0631 \u062e\u06d0\u0644"
    ],
    "wof:name":"Haidar Khel",
    "wof:placetype":"locality"
},
  "geometry": {"coordinates":[68.70159,33.96048],"type":"Point"}
}