{
  "type": "Feature",
  "properties": {
    "gn:admin1_code":"10",
    "gn:admin2_code":"2304.0",
    "gn:asciiname":"Regay",
    "gn:country_code":"AF",
    "gn:dem":936,
    "gn:feature_class":"P",
    "gn:feature_code":"PPL",
    "gn:name":"R\u0113gay",
    "gn:population":0,
    "gn:timezone":"Asia/Kabul",
    "iso:country":"AF",
    "name:und_x_variant":[
        "Raygay",
        "\u0631\u06cc\u06af\u06cc",
        "R\u0113gay"
    ],
    "wof:name":"Regay",
    "wof:placetype":"locality"
},
  "geometry": {"coordinates":[64.80521999999999,32.19641],"type":"Point"}
}