{
  "type": "Feature",
  "properties": {
    "gn:admin1_code":"32",
    "gn:admin2_code":"1504",
    "gn:asciiname":"Mas'ud",
    "gn:country_code":"AF",
    "gn:dem":1771,
    "gn:feature_class":"P",
    "gn:feature_code":"PPL",
    "gn:name":"Mas\u2018\u016bd",
    "gn:population":0,
    "gn:timezone":"Asia/Kabul",
    "iso:country":"AF",
    "name:und_x_variant":[
        "Masud (1)",
        "Mas\u2018\u016bd",
        "\u0645\u0633\u0639\u0648\u062f"
    ],
    "wof:name":"Mas'ud",
    "wof:placetype":"locality"
},
  "geometry": {"coordinates":[67.31344,36.02434],"type":"Point"}
}