{
  "type": "Feature",
  "properties": {
    "gn:admin1_code":"27",
    "gn:admin2_code":"404.0",
    "gn:asciiname":"Chab Now",
    "gn:country_code":"AF",
    "gn:dem":3066,
    "gn:feature_class":"P",
    "gn:feature_code":"PPL",
    "gn:name":"Chab Now",
    "gn:population":0,
    "gn:timezone":"Asia/Kabul",
    "iso:country":"AF",
    "name:fas_x_preferred":[
        "\u0686\u0628\u0646\u0648"
    ],
    "name:rus_x_preferred":[
        "\u0427\u0430\u0431\u043d\u0430\u0443"
    ],
    "name:und_x_variant":[
        "\u010cabnaw",
        "Chabnau",
        "Chabnaw",
        "Chab Now",
        "Chabnow",
        "\u0686\u0628\u0646\u0648",
        "\u0686\u0628 \u0646\u0648"
    ],
    "wof:name":"Chab Now",
    "wof:placetype":"locality"
},
  "geometry": {"coordinates":[67.38021999999999,34.56525999999999],"type":"Point"}
}