{
  "type": "Feature",
  "properties": {
    "gn:admin1_code":"1",
    "gn:admin2_code":"1120.0",
    "gn:asciiname":"Bakharo",
    "gn:country_code":"AF",
    "gn:dem":2467,
    "gn:feature_class":"P",
    "gn:feature_code":"PPL",
    "gn:name":"B\u0101khar\u014d",
    "gn:population":0,
    "gn:timezone":"Asia/Kabul",
    "iso:country":"AF",
    "name:ben_x_preferred":[
        "\u09ac\u09be\u0996\u09be\u09b0\u0989"
    ],
    "name:por_x_preferred":[
        "Bakharow"
    ],
    "name:und_x_variant":[
        "Bokhar",
        "B\u0101kha\u1e5f\u014d",
        "\u0628\u0627\u062e\u0631\u0648",
        "B\u0101khar\u014d"
    ],
    "wof:name":"Bakharo",
    "wof:placetype":"locality"
},
  "geometry": {"coordinates":[70.62756999999998,37.97655],"type":"Point"}
}