{
  "type": "Feature",
  "properties": {
    "gn:admin1_code":"36",
    "gn:admin2_code":"702.0",
    "gn:asciiname":"Fatih Khel",
    "gn:country_code":"AF",
    "gn:dem":2220,
    "gn:feature_class":"P",
    "gn:feature_code":"PPL",
    "gn:name":"Fati\u1e29 Kh\u0113l",
    "gn:population":0,
    "gn:timezone":"Asia/Kabul",
    "iso:country":"AF",
    "name:fas_x_preferred":[
        "\u0641\u062a\u062d \u062e\u064a\u0644"
    ],
    "name:rus_x_preferred":[
        "Fatekhkheyl\u2019"
    ],
    "name:und_x_variant":[
        "Fati\u1e29 Kh\u0113l",
        "Pate\u1e29 Kh\u0113l",
        "Fate\u1e29 Kh\u0113l",
        "Pate\u1e29 Kheyl",
        "\u0641\u062a\u062d \u062e\u06d0\u0644"
    ],
    "wof:name":"Fatih Khel",
    "wof:placetype":"locality"
},
  "geometry": {"coordinates":[69.14008000000001,33.46001],"type":"Point"}
}