{
  "type": "Feature",
  "properties": {
    "gn:admin1_code":"29",
    "gn:admin2_code":"2901",
    "gn:asciiname":"Mirza",
    "gn:country_code":"AF",
    "gn:dem":2146,
    "gn:feature_class":"P",
    "gn:feature_code":"PPL",
    "gn:name":"M\u012brz\u0101",
    "gn:population":0,
    "gn:timezone":"Asia/Kabul",
    "iso:country":"AF",
    "name:und_x_variant":[
        "\u0645\u06cc\u0631\u0632\u0627",
        "M\u012brz\u0101"
    ],
    "wof:name":"Mirza",
    "wof:placetype":"locality"
},
  "geometry": {"coordinates":[68.76805999999999,33.13746],"type":"Point"}
}