{
  "type": "Feature",
  "properties": {
    "gn:admin1_code":"08",
    "gn:admin2_code":"609",
    "gn:asciiname":"Spedar",
    "gn:country_code":"AF",
    "gn:dem":1942,
    "gn:feature_class":"P",
    "gn:feature_code":"PPL",
    "gn:name":"Sp\u0113d\u0101r",
    "gn:population":0,
    "gn:timezone":"Asia/Kabul",
    "iso:country":"AF",
    "name:und_x_variant":[
        "Sp\u0113d\u0101r",
        "\u0633\u067e\u06d0\u062f\u0627\u0631",
        "Sp\u0113\u1e0f\u0101\u1e5f"
    ],
    "wof:name":"Spedar",
    "wof:placetype":"locality"
},
  "geometry": {"coordinates":[67.73689,32.67231],"type":"Point"}
}