{
  "type": "Feature",
  "properties": {
    "gn:admin1_code":"31",
    "gn:admin2_code":"1703",
    "gn:asciiname":"Jigdah Bulaq",
    "gn:country_code":"AF",
    "gn:dem":1753,
    "gn:feature_class":"P",
    "gn:feature_code":"PPL",
    "gn:name":"Jigdah B\u016bl\u0101q",
    "gn:population":0,
    "gn:timezone":"Asia/Kabul",
    "iso:country":"AF",
    "name:und_x_variant":[
        "Jig\u1e0fa Bul\u0101q",
        "J\u012bgdah Bol\u0101q",
        "Jigdah B\u016bl\u0101q",
        "\u062c\u06af\u062f\u0647 \u0628\u0648\u0644\u0627\u0642"
    ],
    "wof:name":"Jigdah Bulaq",
    "wof:placetype":"locality"
},
  "geometry": {"coordinates":[65.45753000000001,35.99914000000001],"type":"Point"}
}