{
  "type": "Feature",
  "properties": {
    "gn:admin1_code":"27",
    "gn:admin2_code":"402",
    "gn:asciiname":"Qal'ah-ye Surkh-e Pa'in",
    "gn:country_code":"AF",
    "gn:dem":2539,
    "gn:feature_class":"P",
    "gn:feature_code":"PPL",
    "gn:name":"Qal\u2018ah-ye Surkh-e P\u0101\u2019\u012bn",
    "gn:population":0,
    "gn:timezone":"Asia/Kabul",
    "iso:country":"AF",
    "name:und_x_variant":[
        "Kalasurkhi-Pain",
        "Qal\u2018eh-ye Surkhe P\u0101\u2019in",
        "Qal\u2018a Su\u1e5fkhe P\u0101\u2019\u012bn",
        "Qal\u2018a-i-Su\u1e5fkhe P\u0101\u2019\u012bn",
        "Qal\u2018eh-ye Sorkh-e P\u0101\u2019\u012bn",
        "Qal\u2018ah-ye Surkh-e P\u0101\u2019\u012bn",
        "\u0642\u0644\u0639\u0647 \u0633\u0631\u062e \u067e\u0627\u0626\u06cc\u0646"
    ],
    "wof:name":"Qal'ah-ye Surkh-e Pa'in",
    "wof:placetype":"locality"
},
  "geometry": {"coordinates":[68.65959000000001,34.53602],"type":"Point"}
}