{
  "type": "Feature",
  "properties": {
    "gn:admin1_code":"29",
    "gn:admin2_code":"2907.0",
    "gn:asciiname":"Baha'uddin",
    "gn:country_code":"AF",
    "gn:dem":2696,
    "gn:feature_class":"P",
    "gn:feature_code":"PPL",
    "gn:name":"Bah\u0101\u2019udd\u012bn",
    "gn:population":0,
    "gn:timezone":"Asia/Kabul",
    "iso:country":"AF",
    "name:fas_x_preferred":[
        "Bah\u0101\u2019udd\u012bn"
    ],
    "name:fas_x_variant":[
        "\u0628\u0647\u0627\u0621 \u0627\u0644\u062f\u06cc\u0646"
    ],
    "name:und_x_variant":[
        "Bah\u0101wu\u1e0f\u1e0f\u012bn",
        "Bah\u0101we\u1e0f\u1e0f\u012bn",
        "Bakhavuddin",
        "Bah\u0101\u2019 od D\u012bn",
        "\u0628\u0647\u0627\u0621 \u0627\u0644\u062f\u06cc\u0646"
    ],
    "wof:name":"Baha'uddin",
    "wof:placetype":"locality"
},
  "geometry": {"coordinates":[68.78654,32.85006],"type":"Point"}
}