{
  "type": "Feature",
  "properties": {
    "gn:admin1_code":"8",
    "gn:admin2_code":"619.0",
    "gn:asciiname":"'Ali Khan Khel",
    "gn:country_code":"AF",
    "gn:dem":2343,
    "gn:feature_class":"P",
    "gn:feature_code":"PPL",
    "gn:name":"\u2018Al\u012b Kh\u0101n Kh\u0113l",
    "gn:population":0,
    "gn:timezone":"Asia/Kabul",
    "iso:country":"AF",
    "name:fas_x_preferred":[
        "\u0639\u0644\u06cc \u062e\u0627\u0646 \u062e\u064a\u0644"
    ],
    "name:rus_x_preferred":[
        "Alikhankheyl\u2019"
    ],
    "name:und_x_variant":[
        "\u2018Alikh\u0101nkh\u0113l",
        "\u2018Al\u012b Kh\u0101n Kh\u0113l",
        "\u2018Al\u012bkh\u0101n Kheyl",
        "\u0639\u0644\u06cc \u062e\u0627\u0646 \u062e\u06d0\u0644"
    ],
    "wof:name":"'Ali Khan Khel",
    "wof:placetype":"locality"
},
  "geometry": {"coordinates":[68.32224000000001,33.5604],"type":"Point"}
}