{
  "type": "Feature",
  "properties": {
    "gn:admin1_code":"18",
    "gn:admin2_code":"807.0",
    "gn:asciiname":"Shakiryan",
    "gn:country_code":"AF",
    "gn:dem":1124,
    "gn:feature_class":"P",
    "gn:feature_code":"PPL",
    "gn:name":"Sh\u0101kiry\u0101n",
    "gn:population":0,
    "gn:timezone":"Asia/Kabul",
    "iso:country":"AF",
    "name:fas_x_preferred":[
        "\u0634\u0627\u0643\u0631\u064a\u0627\u0646"
    ],
    "name:und_x_variant":[
        "\u0160\u0101kery\u0101n",
        "Sh\u0101ke\u1e5fy\u0101n",
        "Shakirian",
        "Sh\u0101ker\u012b\u0101n",
        "Sh\u0101kiry\u0101n",
        "\u0634\u0627\u06a9\u0631\u06cc\u0627\u0646"
    ],
    "wof:name":"Shakiryan",
    "wof:placetype":"locality"
},
  "geometry": {"coordinates":[70.3043,34.23008],"type":"Point"}
}