{
  "type": "Feature",
  "properties": {
    "gn:admin1_code":"01",
    "gn:admin2_code":"1119",
    "gn:asciiname":"Madichut",
    "gn:country_code":"AF",
    "gn:dem":2468,
    "gn:feature_class":"P",
    "gn:feature_code":"PPL",
    "gn:name":"Madich\u016bt",
    "gn:population":0,
    "gn:timezone":"Asia/Kabul",
    "iso:country":"AF",
    "name:und_x_variant":[
        "Ma\u1e0fic\u016bt",
        "\u0645\u062f\u0686\u0648\u062a",
        "Mad\u012bch\u016bt",
        "Madich\u016bt"
    ],
    "wof:name":"Madichut",
    "wof:placetype":"locality"
},
  "geometry": {"coordinates":[70.65640999999999,37.49148],"type":"Point"}
}