{
  "type": "Feature",
  "properties": {
    "gn:admin1_code":"23",
    "gn:admin2_code":"2411",
    "gn:asciiname":"Patan Khel",
    "gn:country_code":"AF",
    "gn:dem":1332,
    "gn:feature_class":"P",
    "gn:feature_code":"PPL",
    "gn:name":"Pa\u1e6f\u0101n Kh\u0113l",
    "gn:population":0,
    "gn:timezone":"Asia/Kabul",
    "iso:country":"AF",
    "name:und_x_variant":[
        "Path\u0101n Khel",
        "Pat\u0101nkh\u0113l",
        "Pa\u1e6f\u0101n Kh\u0113l",
        "Pa\u1e6f\u0101n Kheyl",
        "\u067e\u067c\u0627\u0646 \u062e\u06d0\u0644"
    ],
    "wof:name":"Patan Khel",
    "wof:placetype":"locality"
},
  "geometry": {"coordinates":[66.56338000000001,31.07008],"type":"Point"}
}