{
  "type": "Feature",
  "properties": {
    "gn:admin1_code":"23",
    "gn:admin2_code":"2411.0",
    "gn:asciiname":"Surkai Gwal",
    "gn:country_code":"AF",
    "gn:dem":2009,
    "gn:feature_class":"P",
    "gn:feature_code":"PPL",
    "gn:name":"S\u016brka\u012b Gw\u0101l",
    "gn:population":0,
    "gn:timezone":"Asia/Kabul",
    "iso:country":"AF",
    "name:rus_x_preferred":[
        "Surkaygval\u2019"
    ],
    "name:und_x_variant":[
        "S\u016brka\u012b Gw\u0101l",
        "S\u016brkay Gw\u0101l",
        "\u0633\u0648\u0631\u06a9\u06cc \u06af\u0648\u0627\u0644"
    ],
    "wof:name":"Surkai Gwal",
    "wof:placetype":"locality"
},
  "geometry": {"coordinates":[66.70860999999999,31.22],"type":"Point"}
}