{
  "type": "Feature",
  "properties": {
    "gn:admin1_code":"13",
    "gn:admin2_code":"105.0",
    "gn:asciiname":"Baghariq-e Sufla",
    "gn:country_code":"AF",
    "gn:dem":1566,
    "gn:feature_class":"P",
    "gn:feature_code":"PPL",
    "gn:name":"B\u0101gh\u0101riq-e Sufl\u00e1",
    "gn:population":0,
    "gn:timezone":"Asia/Kabul",
    "iso:country":"AF",
    "name:fas_x_preferred":[
        "\u0628\u0627\u063a\u0627\u0631\u0642\u0654 \u0633\u0641\u0644\u0649"
    ],
    "name:und_x_variant":[
        "Bagariki-Sufla",
        "B\u0101gh\u0101\u1e5feqe Sufl\u0101",
        "B\u0101gh\u0101req-e Sofl\u00e1",
        "\u0628\u0627\u063a\u0627\u0631\u0642 \u0633\u0641\u0644\u0649",
        "B\u0101gh\u0101riq-e Sufl\u00e1"
    ],
    "wof:name":"Baghariq-e Sufla",
    "wof:placetype":"locality"
},
  "geometry": {"coordinates":[69.16330000000001,34.8176],"type":"Point"}
}