{
  "type": "Feature",
  "properties": {
    "gn:admin1_code":"34",
    "gn:admin2_code":"1003.0",
    "gn:asciiname":"Wech Naw",
    "gn:country_code":"AF",
    "gn:dem":1326,
    "gn:feature_class":"P",
    "gn:feature_code":"PPL",
    "gn:name":"W\u00each N\u0101w",
    "gn:population":0,
    "gn:timezone":"Asia/Kabul",
    "iso:country":"AF",
    "name:fas_x_preferred":[
        "\u0634\u064a\u0644\u06c0 \u0648\u0686"
    ],
    "name:und_x_variant":[
        "Uchnau",
        "U\u010d N\u0101w",
        "\u0648\u0686 \u0646\u0627\u0648",
        "Uch N\u0101w",
        "W\u00each N\u0101w"
    ],
    "wof:name":"Wech Naw",
    "wof:placetype":"locality"
},
  "geometry": {"coordinates":[71.3925,35.09028],"type":"Point"}
}