{
  "type": "Feature",
  "properties": {
    "gn:admin1_code":"03",
    "gn:admin2_code":"1311",
    "gn:asciiname":"Khuda Dad Khel",
    "gn:country_code":"AF",
    "gn:dem":512,
    "gn:feature_class":"P",
    "gn:feature_code":"PPL",
    "gn:name":"Khud\u0101 D\u0101d Kh\u0113l",
    "gn:population":0,
    "gn:timezone":"Asia/Kabul",
    "iso:country":"AF",
    "name:fas_x_preferred":[
        "\u062e\u062f\u0627\u062f\u0627\u062f \u062e\u064a\u0644"
    ],
    "name:rus_x_preferred":[
        "\u0425\u0443\u0434\u0430\u0434\u0430\u0434\u0445\u0435\u0439\u043b\u044c"
    ],
    "name:und_x_variant":[
        "Khu\u1e0f\u0101 \u1e0e\u0101\u1e0f Kh\u0113l",
        "Khudadadkheyl\u2019",
        "Khod\u0101 D\u0101d Kheyl",
        "Khud\u0101 D\u0101d Kh\u0113l",
        "\u062e\u062f\u0627 \u062f\u0627\u062f \u062e\u06d0\u0644"
    ],
    "wof:name":"Khuda Dad Khel",
    "wof:placetype":"locality"
},
  "geometry": {"coordinates":[68.70440000000001,36.25372],"type":"Point"}
}