{
  "type": "Feature",
  "properties": {
    "gn:admin1_code":"08",
    "gn:admin2_code":"604",
    "gn:asciiname":"Sang Qal'ah",
    "gn:country_code":"AF",
    "gn:dem":3159,
    "gn:feature_class":"P",
    "gn:feature_code":"PPL",
    "gn:name":"Sang Qal\u2018ah",
    "gn:population":0,
    "gn:timezone":"Asia/Kabul",
    "iso:country":"AF",
    "name:fas_x_preferred":[
        "\u0642\u0644\u0639\u0647\u0654 \u0633\u0646\u06af"
    ],
    "name:rus_x_preferred":[
        "\u0421\u0430\u043d\u0433\u043a\u0430\u043b\u0430"
    ],
    "name:und_x_variant":[
        "Sangkala",
        "Sangqal\u0101",
        "Sangqal\u2018eh",
        "Sang Qal\u2018ah",
        "\u0633\u0646\u06af \u0642\u0644\u0639\u0647"
    ],
    "wof:name":"Sang Qal'ah",
    "wof:placetype":"locality"
},
  "geometry": {"coordinates":[67.72632,33.74493],"type":"Point"}
}