{
  "type": "Feature",
  "properties": {
    "gn:admin1_code":"29",
    "gn:admin2_code":"2910.0",
    "gn:asciiname":"Waghost",
    "gn:country_code":"AF",
    "gn:dem":2144,
    "gn:feature_class":"P",
    "gn:feature_code":"PPL",
    "gn:name":"Wagh\u014dst",
    "gn:population":0,
    "gn:timezone":"Asia/Kabul",
    "iso:country":"AF",
    "name:und_x_variant":[
        "Vagost",
        "Wagh\u014dst",
        "Wagh\u016bst",
        "\u0648\u063a\u0648\u0633\u062a"
    ],
    "wof:name":"Waghost",
    "wof:placetype":"locality"
},
  "geometry": {"coordinates":[69.35231999999999,32.9584],"type":"Point"}
}