{
  "type": "Feature",
  "properties": {
    "gn:admin1_code":"23",
    "gn:admin2_code":"2411",
    "gn:asciiname":"Sayyid Muhammad Kelay",
    "gn:country_code":"AF",
    "gn:dem":1193,
    "gn:feature_class":"P",
    "gn:feature_code":"PPL",
    "gn:name":"Sayyid Mu\u1e29ammad K\u00ealay",
    "gn:population":0,
    "gn:timezone":"Asia/Kabul",
    "iso:country":"AF",
    "name:rus_x_preferred":[
        "\u0421\u0430\u0438\u0434\u043c\u0443\u0445\u0430\u043c\u043c\u0435\u0434-\u041a\u0430\u043b\u0430\u0439"
    ],
    "name:und_x_variant":[
        "Say\u1e0fmo\u1e96\u1e0f Kalay",
        "Saidmukhammed-Kalay",
        "Tor Barghai Afghan Outpost",
        "Say\u1e0fmo\u1e29amme\u1e0f Kalay",
        "Sayyid Mu\u1e29ammad K\u00ealay",
        "Seyyed Mo\u1e29ammad Kalay",
        "\u0633\u06cc\u062f \u0645\u062d\u0645\u062f \u06a9\u0644\u06cc"
    ],
    "wof:name":"Sayyid Muhammad Kelay",
    "wof:placetype":"locality"
},
  "geometry": {"coordinates":[66.32333,30.89611],"type":"Point"}
}