{
  "type": "Feature",
  "properties": {
    "gn:admin1_code":"29",
    "gn:admin2_code":"2909.0",
    "gn:asciiname":"Rozi Khan Kala",
    "gn:country_code":"AF",
    "gn:dem":2063,
    "gn:feature_class":"P",
    "gn:feature_code":"PPL",
    "gn:name":"R\u014dz\u012b Kh\u0101n Kal\u0101",
    "gn:population":0,
    "gn:timezone":"Asia/Kabul",
    "iso:country":"AF",
    "name:fas_x_preferred":[
        "\u0631\u0648\u0636\u0647 \u062e\u0627\u0646 \u0643\u0644\u0627"
    ],
    "name:und_x_variant":[
        "\u1e5e\u014dzikh\u0101n Kal\u0101",
        "Rozikhankala",
        "R\u014dz\u00eah Kh\u0101n Kal\u0101",
        "Row\u1e95ehkh\u0101n Kal\u0101",
        "R\u014dz\u012b Kh\u0101n Kal\u0101",
        "\u0631\u0648\u0632\u06cc \u062e\u0627\u0646 \u0643\u0644\u0627",
        "\u0631\u0648\u0636\u0647 \u062e\u0627\u0646 \u0643\u0644\u0627"
    ],
    "wof:name":"Rozi Khan Kala",
    "wof:placetype":"locality"
},
  "geometry": {"coordinates":[69.20281999999999,32.4893],"type":"Point"}
}