{
  "type": "Feature",
  "properties": {
    "gn:admin1_code":"5",
    "gn:admin2_code":"2806.0",
    "gn:asciiname":"Qol-e Muhammad",
    "gn:country_code":"AF",
    "gn:dem":2916,
    "gn:feature_class":"P",
    "gn:feature_code":"PPL",
    "gn:name":"Q\u014dl-e Mu\u1e29ammad",
    "gn:population":0,
    "gn:timezone":"Asia/Kabul",
    "iso:country":"AF",
    "name:und_x_variant":[
        "Kuli-Mukhammad",
        "Q\u014dle Mo\u1e29amme\u1e0f",
        "Q\u014dle Mo\u1e29\u1e0f",
        "Qowl-e Mo\u1e29ammad",
        "Q\u014dl-e Mu\u1e29ammad-e Sufl\u00e1",
        "Q\u014dl-e Mu\u1e29ammad",
        "\u0642\u0648\u0644 \u0645\u062d\u0645\u062f"
    ],
    "wof:name":"Qol-e Muhammad",
    "wof:placetype":"locality"
},
  "geometry": {"coordinates":[66.78896999999999,34.09636],"type":"Point"}
}