{
  "type": "Feature",
  "properties": {
    "gn:admin1_code":"29",
    "gn:admin2_code":"2901.0",
    "gn:asciiname":"Malikan",
    "gn:country_code":"AF",
    "gn:dem":2144,
    "gn:feature_class":"P",
    "gn:feature_code":"PPL",
    "gn:name":"Malik\u0101n",
    "gn:population":0,
    "gn:timezone":"Asia/Kabul",
    "iso:country":"AF",
    "name:und_x_variant":[
        "\u0645\u0644\u06a9\u0627\u0646",
        "Malek\u0101n",
        "Malik\u0101n"
    ],
    "wof:name":"Malikan",
    "wof:placetype":"locality"
},
  "geometry": {"coordinates":[68.78008,33.16064],"type":"Point"}
}