{
  "type": "Feature",
  "properties": {
    "gn:admin1_code":"17",
    "gn:admin2_code":"507.0",
    "gn:asciiname":"Chala Khel",
    "gn:country_code":"AF",
    "gn:dem":2428,
    "gn:feature_class":"P",
    "gn:feature_code":"PPL",
    "gn:name":"Ch\u0101l\u0101 Kh\u0113l",
    "gn:population":0,
    "gn:timezone":"Asia/Kabul",
    "iso:country":"AF",
    "name:rus_x_preferred":[
        "Chalakheyl\u2019"
    ],
    "name:und_x_variant":[
        "\u010c\u0101l\u0101kh\u0113l",
        "Ch\u0101l\u0101 Kheyl",
        "Ch\u0101l\u0101 Kh\u0113l",
        "Ch\u0101l\u0101kh\u0113l",
        "\u0686\u0627\u0644\u0627 \u062e\u06d0\u0644"
    ],
    "wof:name":"Chala Khel",
    "wof:placetype":"locality"
},
  "geometry": {"coordinates":[68.86499999999999,33.72587],"type":"Point"}
}