{
  "type": "Feature",
  "properties": {
    "gn:admin1_code":"42",
    "gn:admin2_code":"3307",
    "gn:asciiname":"Gul Zangar",
    "gn:country_code":"AF",
    "gn:dem":2397,
    "gn:feature_class":"P",
    "gn:feature_code":"PPL",
    "gn:name":"Gul Zangar",
    "gn:population":0,
    "gn:timezone":"Asia/Kabul",
    "iso:country":"AF",
    "name:fas_x_preferred":[
        "\u06af\u0644\u0632\u0646\u06af\u0631"
    ],
    "name:rus_x_preferred":[
        "\u0413\u0443\u043b\u044c\u0437\u0430\u043d\u0433\u0430\u0440"
    ],
    "name:und_x_variant":[
        "Gulzanga\u1e5f",
        "Gul\u2019zangar",
        "Golzangar",
        "Gul Zangar",
        "\u06af\u0644 \u0632\u0646\u06af\u0631"
    ],
    "wof:name":"Gul Zangar",
    "wof:placetype":"locality"
},
  "geometry": {"coordinates":[69.51517,35.22334],"type":"Point"}
}