{
  "type": "Feature",
  "properties": {
    "gn:admin1_code":"29",
    "gn:admin2_code":"2908",
    "gn:asciiname":"Zarkhay",
    "gn:country_code":"AF",
    "gn:dem":2318,
    "gn:feature_class":"P",
    "gn:feature_code":"PPL",
    "gn:name":"Zarkhay",
    "gn:population":0,
    "gn:timezone":"Asia/Kabul",
    "iso:country":"AF",
    "name:und_x_variant":[
        "Yusuf",
        "Y\u014dsuf",
        "Zarkhay",
        "\u0632\u0631\u062e\u06cc",
        "\u06cc\u0648\u0633\u0641"
    ],
    "wof:name":"Zarkhay",
    "wof:placetype":"locality"
},
  "geometry": {"coordinates":[69.02529,32.72455],"type":"Point"}
}