{
  "type": "Feature",
  "properties": {
    "gn:admin1_code":"40",
    "gn:admin2_code":"301.0",
    "gn:asciiname":"Deh-e Qazi",
    "gn:country_code":"AF",
    "gn:dem":1501,
    "gn:feature_class":"P",
    "gn:feature_code":"PPL",
    "gn:name":"Deh-e Q\u0101\u1e95\u012b",
    "gn:population":0,
    "gn:timezone":"Asia/Kabul",
    "iso:country":"AF",
    "name:und_x_variant":[
        "\u1e0eehe Q\u0101\u1e0f\u1e95i",
        "Dekhi-Kazi",
        "Deh-e Q\u0101\u1e95i",
        "Deh-e Q\u0101\u1e95\u012b",
        "\u062f\u0647 \u0642\u0627\u0636\u06cc"
    ],
    "wof:name":"Deh-e Qazi",
    "wof:placetype":"locality"
},
  "geometry": {"coordinates":[69.24388,35.01649],"type":"Point"}
}