{
  "type": "Feature",
  "properties": {
    "gn:admin1_code":"08",
    "gn:admin2_code":"610",
    "gn:asciiname":"Khushkhali",
    "gn:country_code":"AF",
    "gn:dem":2019,
    "gn:feature_class":"P",
    "gn:feature_code":"PPL",
    "gn:name":"Khushkhali",
    "gn:population":0,
    "gn:timezone":"Asia/Kabul",
    "iso:country":"AF",
    "name:und_x_variant":[
        "Khus\u0304h\u0101",
        "Khushkhali",
        "Khu\u0161\u0101li",
        "Kh\u014dsh\u1e29\u0101l\u012b",
        "\u062e\u0648\u0634\u062d\u0627\u0644\u06cc",
        "Khvosh\u1e29\u0101l\u012b"
    ],
    "wof:name":"Khushkhali",
    "wof:placetype":"locality"
},
  "geometry": {"coordinates":[67.78408,32.41622],"type":"Point"}
}