{
  "type": "Feature",
  "properties": {
    "gn:admin1_code":"10",
    "gn:admin2_code":"2302",
    "gn:asciiname":"Qazi Muhammad Akhundzadah",
    "gn:country_code":"AF",
    "gn:dem":835,
    "gn:feature_class":"P",
    "gn:feature_code":"PPL",
    "gn:name":"Q\u0101\u1e95\u012b Mu\u1e29ammad \u0100kh\u016bndz\u0101dah",
    "gn:population":0,
    "gn:timezone":"Asia/Kabul",
    "iso:country":"AF",
    "name:und_x_variant":[
        "Kozi-Mukhammed-Akhundzada",
        "Q\u0101\u1e95\u012b Mo\u1e29ammad \u0100khvon",
        "Q\u0101\u1e0f\u1e95i Mo\u1e29amma\u1e0f \u0100khun\u1e0fz\u0101\u1e0fah",
        "Q\u0101a\u1e95i Mo\u1e29amma\u1e0f \u0100khun\u1e0fz\u0101\u1e0fah",
        "Q\u0101\u1e95\u012b Mu\u1e29ammad \u0100kh\u016bndz\u0101dah",
        "\u0642\u0627\u0636\u06cc \u0645\u062d\u0645\u062f \u0622\u062e\u0648\u0646\u062f\u0632\u0627\u062f\u0647",
        "Q\u0101\u1e95\u012b Mo\u1e29ammad \u0100khvondz\u0101deh"
    ],
    "wof:name":"Qazi Muhammad Akhundzadah",
    "wof:placetype":"locality"
},
  "geometry": {"coordinates":[64.65219,31.72168],"type":"Point"}
}