{
  "type": "Feature",
  "properties": {
    "gn:admin1_code":"38",
    "gn:admin2_code":"3004",
    "gn:asciiname":"Now Kozung",
    "gn:country_code":"AF",
    "gn:dem":1638,
    "gn:feature_class":"P",
    "gn:feature_code":"PPL",
    "gn:name":"Now K\u014dzung",
    "gn:population":0,
    "gn:timezone":"Asia/Kabul",
    "iso:country":"AF",
    "name:und_x_variant":[
        "Naukuzung",
        "Now K\u014dzung",
        "Nawkozung",
        "\u0646\u0648\u06a9\u0648\u0632\u0646\u06af",
        "Nowk\u014dzung"
    ],
    "wof:name":"Now Kozung",
    "wof:placetype":"locality"
},
  "geometry": {"coordinates":[70.24160000000001,35.19],"type":"Point"}
}