{
  "type": "Feature",
  "properties": {
    "gn:admin1_code":"32",
    "gn:admin2_code":"1504",
    "gn:asciiname":"Torah",
    "gn:country_code":"AF",
    "gn:dem":1788,
    "gn:feature_class":"P",
    "gn:feature_code":"PPL",
    "gn:name":"T\u014drah",
    "gn:population":0,
    "gn:timezone":"Asia/Kabul",
    "iso:country":"AF",
    "name:und_x_variant":[
        "T\u014d\u1e5fa",
        "Towrah",
        "T\u014drah",
        "\u062a\u0648\u0631\u0647"
    ],
    "wof:name":"Torah",
    "wof:placetype":"locality"
},
  "geometry": {"coordinates":[67.17412,35.88869000000001],"type":"Point"}
}