{
  "type": "Feature",
  "properties": {
    "gn:admin1_code":"10",
    "gn:admin2_code":"2303",
    "gn:asciiname":"Kochai",
    "gn:country_code":"AF",
    "gn:dem":993,
    "gn:feature_class":"P",
    "gn:feature_code":"PPL",
    "gn:name":"Kochai",
    "gn:population":0,
    "gn:timezone":"Asia/Kabul",
    "iso:country":"AF",
    "name:und_x_variant":[
        "Kh\u014dc\u0101si",
        "Kochai",
        "Kho\u010d\u0101\u2019i",
        "Khochai",
        "Kh\u014dch\u0101\u2019\u012b",
        "\u062e\u0648\u0686\u0627\u0626\u06cc",
        "Khvoch\u0101\u2019\u012b"
    ],
    "wof:name":"Kochai",
    "wof:placetype":"locality"
},
  "geometry": {"coordinates":[64.97971,32.30143],"type":"Point"}
}