{
  "type": "Feature",
  "properties": {
    "gn:admin1_code":"01",
    "gn:admin2_code":"1111",
    "gn:asciiname":"Deh Khwahan",
    "gn:country_code":"AF",
    "gn:dem":1047,
    "gn:feature_class":"P",
    "gn:feature_code":"PPLA2",
    "gn:name":"Deh Khw\u0101h\u0101n",
    "gn:population":0,
    "gn:timezone":"Asia/Kabul",
    "iso:country":"AF",
    "name:pus_x_preferred":[
        "Khv\u0101h\u0101n"
    ],
    "name:und_x_variant":[
        "Khv\u0101h\u0101n",
        "\u1e0eeh Kh\u0101h\u0101n",
        "Qala Khwahan",
        "\u062e\u0648\u0627\u0647\u0627\u0646",
        "Deh Kh\u0101h\u0101n",
        "\u062f\u0647 \u062e\u0627\u0647\u0627\u0646",
        "Khw\u0101h\u0101n",
        "Deh Khw\u0101h\u0101n",
        "\u062f\u0647 \u062e\u0648\u0627\u0647\u0627\u0646"
    ],
    "wof:name":"Deh Khwahan",
    "wof:placetype":"locality"
},
  "geometry": {"coordinates":[70.21875,37.88965],"type":"Point"}
}