{
  "type": "Feature",
  "properties": {
    "gn:admin1_code":"01",
    "gn:admin2_code":"1111",
    "gn:asciiname":"Deh Khwahan",
    "gn:country_code":"AF",
    "gn:dem":1047,
    "gn:feature_class":"P",
    "gn:feature_code":"PPLA2",
    "gn:name":"Deh Khw\u0101h\u0101n",
    "gn:population":0,
    "gn:timezone":"Asia/Kabul",
    "iso:country":"AF",
    "name:ben_x_preferred":[
        "\u0996\u0993\u09af\u09bc\u09be\u09b9\u09be\u09a8 \u099c\u09c7\u09b2\u09be"
    ],
    "name:ceb_x_preferred":[
        "Khw\u0101h\u0101n"
    ],
    "name:deu_x_preferred":[
        "Khwahan"
    ],
    "name:ell_x_preferred":[
        "\u03a0\u03b5\u03c1\u03b9\u03bf\u03c7\u03ae \u03a7\u03bf\u03c5\u03b1\u03c7\u03ac\u03bd"
    ],
    "name:fas_x_preferred":[
        "\u0648\u0644\u0633\u0648\u0627\u0644\u06cc \u062e\u0648\u0627\u0647\u0627\u0646"
    ],
    "name:fra_x_preferred":[
        "Khwahan"
    ],
    "name:ind_x_preferred":[
        "Khwahan"
    ],
    "name:msa_x_preferred":[
        "Daerah Khwahan"
    ],
    "name:pol_x_preferred":[
        "Chwahan"
    ],
    "name:pus_x_preferred":[
        "Khv\u0101h\u0101n"
    ],
    "name:pus_x_variant":[
        "\u062e\u0648\u0627\u0647\u0627\u0646 \u0648\u0644\u0633\u0648\u0627\u0644\u06cd"
    ],
    "name:rus_x_preferred":[
        "\u0425\u0432\u0430\u0445\u0430\u043d"
    ],
    "name:swe_x_preferred":[
        "Khw\u0101h\u0101n"
    ],
    "name:tgk_x_preferred":[
        "\u041d\u043e\u04b3\u0438\u044f\u0438 \u0425\u0432\u043e\u04b3\u043e\u043d"
    ],
    "name:tur_x_preferred":[
        "Hevahan"
    ],
    "name:ukr_x_preferred":[
        "\u0425\u0430\u0445\u0430\u043d \u0420\u0430\u0439\u043e\u043d"
    ],
    "name:und_x_variant":[
        "Khv\u0101h\u0101n",
        "\u1e0eeh Kh\u0101h\u0101n",
        "Qala Khwahan",
        "\u062e\u0648\u0627\u0647\u0627\u0646",
        "Deh Kh\u0101h\u0101n",
        "\u062f\u0647 \u062e\u0627\u0647\u0627\u0646",
        "Khw\u0101h\u0101n",
        "Deh Khw\u0101h\u0101n",
        "\u062f\u0647 \u062e\u0648\u0627\u0647\u0627\u0646"
    ],
    "name:urd_x_preferred":[
        "\u062e\u0648\u0627\u06c1\u0627\u0646 \u0636\u0644\u0639"
    ],
    "name:vie_x_preferred":[
        "Khwahan"
    ],
    "wof:name":"Deh Khwahan",
    "wof:placetype":"locality"
},
  "geometry": {"coordinates":[70.21875,37.88965],"type":"Point"}
}