{
  "type": "Feature",
  "properties": {
    "gn:admin1_code":"26",
    "gn:admin2_code":"1217",
    "gn:asciiname":"Shulish Darah",
    "gn:country_code":"AF",
    "gn:dem":1329,
    "gn:feature_class":"P",
    "gn:feature_code":"PPL",
    "gn:name":"Sh\u016blish Darah",
    "gn:population":0,
    "gn:timezone":"Asia/Kabul",
    "iso:country":"AF",
    "name:rus_x_preferred":[
        "\u0428\u0443\u043b\u0438\u0448\u0434\u0430\u0440\u0430"
    ],
    "name:und_x_variant":[
        "Sh\u016blesh Darreh",
        "Shulishdara",
        "\u0160\u016ble\u0161 Darrah",
        "Sh\u016blesh Darrah",
        "Sh\u016blish Darah",
        "\u0634\u0648\u0644\u0634 \u062f\u0631\u0647"
    ],
    "wof:name":"Shulish Darah",
    "wof:placetype":"locality"
},
  "geometry": {"coordinates":[69.59373000000001,36.61595],"type":"Point"}
}