{
  "type": "Feature",
  "properties": {
    "gn:admin1_code":"39",
    "gn:admin2_code":"2604",
    "gn:asciiname":"Zamburay",
    "gn:country_code":"AF",
    "gn:dem":1431,
    "gn:feature_class":"P",
    "gn:feature_code":"PPL",
    "gn:name":"Zamb\u016bray",
    "gn:population":0,
    "gn:timezone":"Asia/Kabul",
    "iso:country":"AF",
    "name:und_x_variant":[
        "Zamb\u016bray",
        "Zamburay",
        "\u0632\u0645\u0628\u0648\u0631\u06cc"
    ],
    "wof:name":"Zamburay",
    "wof:placetype":"locality"
},
  "geometry": {"coordinates":[65.32647,32.87675],"type":"Point"}
}