{
  "type": "Feature",
  "properties": {
    "gn:admin1_code":"07",
    "gn:admin2_code":"1803",
    "gn:asciiname":"Haji Khwajah",
    "gn:country_code":"AF",
    "gn:dem":742,
    "gn:feature_class":"P",
    "gn:feature_code":"PPL",
    "gn:name":"\u1e28\u0101j\u012b Khw\u0101jah",
    "gn:population":0,
    "gn:timezone":"Asia/Kabul",
    "iso:country":"AF",
    "name:und_x_variant":[
        "H\u0331\u0101ji Khw\u0101ja",
        "\u1e28\u0101jj\u012b Khv\u0101jeh",
        "\u1e28\u0101j\u012b Khw\u0101jah",
        "\u062d\u0627\u062c\u06cc \u062e\u0648\u0627\u062c\u0647"
    ],
    "wof:name":"Haji Khwajah",
    "wof:placetype":"locality"
},
  "geometry": {"coordinates":[64.40791,35.91898],"type":"Point"}
}