{
  "type": "Feature",
  "properties": {
    "gn:admin1_code":"03",
    "gn:admin2_code":"1307",
    "gn:asciiname":"Dzangalak",
    "gn:country_code":"AF",
    "gn:dem":1688,
    "gn:feature_class":"P",
    "gn:feature_code":"PPL",
    "gn:name":"Dzangalak",
    "gn:population":0,
    "gn:timezone":"Asia/Kabul",
    "iso:country":"AF",
    "name:und_x_variant":[
        "\u0681\u0646\u06af\u0644\u06a9",
        "Jangalak"
    ],
    "wof:name":"Dzangalak",
    "wof:placetype":"locality"
},
  "geometry": {"coordinates":[69.20441,35.59108],"type":"Point"}
}