{
  "type": "Feature",
  "properties": {
    "gn:admin1_code":"36",
    "gn:admin2_code":"702",
    "gn:asciiname":"Zin Tizhah",
    "gn:country_code":"AF",
    "gn:dem":2607,
    "gn:feature_class":"P",
    "gn:feature_code":"PPL",
    "gn:name":"Z\u012bn T\u012bz\u0332h\u0332ah",
    "gn:population":0,
    "gn:timezone":"Asia/Kabul",
    "iso:country":"AF",
    "name:und_x_variant":[
        "Z\u012bn Ti\u017ea",
        "Zintnza",
        "Z\u012bn Tiz\u0332h\u0332ah",
        "Z\u012bn T\u012bz\u0332h\u0332ah",
        "\u0632\u06cc\u0646 \u062a\u06cc\u0696\u0647"
    ],
    "wof:name":"Zin Tizhah",
    "wof:placetype":"locality"
},
  "geometry": {"coordinates":[68.85583000000001,33.57884],"type":"Point"}
}