{
  "type": "Feature",
  "properties": {
    "gn:admin1_code":"01",
    "gn:admin2_code":"1124",
    "gn:asciiname":"Zugham Darah",
    "gn:country_code":"AF",
    "gn:dem":1746,
    "gn:feature_class":"P",
    "gn:feature_code":"PPL",
    "gn:name":"Z\u0304\u016bgh\u0101m Darah",
    "gn:population":0,
    "gn:timezone":"Asia/Kabul",
    "iso:country":"AF",
    "name:und_x_variant":[
        "Z\u0304\u016bgh\u0101m \u1e0ea\u1e5f\u1e5fah",
        "Z\u0304\u016bgh\u0101m Darreh",
        "Z\u0304\u016bgh\u0101m Darah",
        "\u0630\u0648\u063a\u0627\u0645 \u062f\u0631\u0647"
    ],
    "wof:name":"Zugham Darah",
    "wof:placetype":"locality"
},
  "geometry": {"coordinates":[70.33344,36.86803],"type":"Point"}
}