{
  "type": "Feature",
  "properties": {
    "gn:admin1_code":"30",
    "gn:admin2_code":"1603",
    "gn:asciiname":"Wutkay",
    "gn:country_code":"AF",
    "gn:dem":1465,
    "gn:feature_class":"P",
    "gn:feature_code":"PPL",
    "gn:name":"Wutkay",
    "gn:population":0,
    "gn:timezone":"Asia/Kabul",
    "iso:country":"AF",
    "name:und_x_variant":[
        "\u0648\u062a\u06a9\u06cc",
        "Wutkay"
    ],
    "wof:name":"Wutkay",
    "wof:placetype":"locality"
},
  "geometry": {"coordinates":[66.65791,35.80441],"type":"Point"}
}