{
  "type": "Feature",
  "properties": {
    "gn:admin1_code":"11",
    "gn:admin2_code":"2014",
    "gn:asciiname":"Deh-e 'Abdul 'Aziz",
    "gn:country_code":"AF",
    "gn:dem":1126,
    "gn:feature_class":"P",
    "gn:feature_code":"PPL",
    "gn:name":"Deh-e \u2018Abdul \u2018Az\u012bz",
    "gn:population":0,
    "gn:timezone":"Asia/Kabul",
    "iso:country":"AF",
    "name:fas_x_preferred":[
        "\u0642\u0631\u064a\u06c0 \u0639\u0628\u062f \u0627\u0644 \u0639\u0632\u06cc\u0632"
    ],
    "name:rus_x_preferred":[
        "Dekhi-Abdul\u2019aziz"
    ],
    "name:und_x_variant":[
        "\u1e0eehe \u2018Ab\u1e0ful \u2018Az\u012bz",
        "Deh-e \u2018Abd ol \u2018Az\u012bz",
        "Deh-e \u2018Abdul \u2018Az\u012bz",
        "\u062f\u0647 \u0639\u0628\u062f\u0627\u0644\u0639\u0632\u06cc\u0632",
        "\u0642\u0631\u064a\u06c0 \u0639\u0628\u062f \u0627\u0644 \u0639\u0632\u06cc\u0632"
    ],
    "wof:name":"Deh-e 'Abdul 'Aziz",
    "wof:placetype":"locality"
},
  "geometry": {"coordinates":[62.31634,33.3404],"type":"Point"}
}