{
  "type": "Feature",
  "properties": {
    "gn:admin1_code":"07",
    "gn:admin2_code":"1814",
    "gn:asciiname":"Yakah Tut",
    "gn:country_code":"AF",
    "gn:dem":299,
    "gn:feature_class":"P",
    "gn:feature_code":"PPL",
    "gn:name":"Yakah T\u016bt",
    "gn:population":0,
    "gn:timezone":"Asia/Kabul",
    "iso:country":"AF",
    "name:und_x_variant":[
        "Yaka T\u016bt",
        "Yakah T\u016bt",
        "\u06cc\u06a9\u0647 \u062a\u0648\u062a",
        "Yekkeh T\u016bt"
    ],
    "wof:name":"Yakah Tut",
    "wof:placetype":"locality"
},
  "geometry": {"coordinates":[65.05664,36.98096],"type":"Point"}
}