{
  "type": "Feature",
  "properties": {
    "gn:admin1_code":"8",
    "gn:admin2_code":"614.0",
    "gn:asciiname":"Khudzai",
    "gn:country_code":"AF",
    "gn:dem":2098,
    "gn:feature_class":"P",
    "gn:feature_code":"PPL",
    "gn:name":"Khudz\u0101\u012b",
    "gn:population":0,
    "gn:timezone":"Asia/Kabul",
    "iso:country":"AF",
    "name:fas_x_preferred":[
        "\u062e\u0648\u0632\u06cc"
    ],
    "name:und_x_variant":[
        "Khuzai",
        "Khu\u1e0fz\u0101\u2018i",
        "Kh\u014ddza\u012b",
        "Khowdz\u0101\u2019\u012b",
        "Khudz\u0101\u012b",
        "\u062e\u062f\u0632\u0627\u06cc"
    ],
    "wof:name":"Khudzai",
    "wof:placetype":"locality"
},
  "geometry": {"coordinates":[68.37996,33.39325],"type":"Point"}
}