{
  "type": "Feature",
  "properties": {
    "gn:admin1_code":"30",
    "gn:admin2_code":"1603.0",
    "gn:asciiname":"Khozaylas",
    "gn:country_code":"AF",
    "gn:dem":2093,
    "gn:feature_class":"P",
    "gn:feature_code":"PPL",
    "gn:name":"Khozayl\u0101s",
    "gn:population":0,
    "gn:timezone":"Asia/Kabul",
    "iso:country":"AF",
    "wof:name":"Khozaylas",
    "wof:placetype":"locality"
},
  "geometry": {"coordinates":[66.64221999999999,35.74861],"type":"Point"}
}