{
  "type": "Feature",
  "properties": {
    "gn:admin1_code":"27",
    "gn:admin2_code":"404",
    "gn:asciiname":"Lukh",
    "gn:country_code":"AF",
    "gn:dem":3017,
    "gn:feature_class":"P",
    "gn:feature_code":"PPL",
    "gn:name":"Lukh",
    "gn:population":0,
    "gn:timezone":"Asia/Kabul",
    "iso:country":"AF",
    "name:fas_x_preferred":[
        "\u0644\u062e"
    ],
    "name:rus_x_preferred":[
        "\u041b\u0443\u0445"
    ],
    "name:und_x_variant":[
        "\u0644\u062e"
    ],
    "wof:name":"Lukh",
    "wof:placetype":"locality"
},
  "geometry": {"coordinates":[67.44960999999999,34.56035],"type":"Point"}
}