{
  "type": "Feature",
  "properties": {
    "gn:admin1_code":"01",
    "gn:admin2_code":"1119.0",
    "gn:asciiname":"Salet",
    "gn:country_code":"AF",
    "gn:dem":2454,
    "gn:feature_class":"P",
    "gn:feature_code":"PPL",
    "gn:name":"\u015e\u0101l\u0113t",
    "gn:population":0,
    "gn:timezone":"Asia/Kabul",
    "iso:country":"AF",
    "name:und_x_variant":[
        "\u0635\u0627\u0644\u06d0\u062a",
        "S\u0101l\u0113t",
        "\u015e\u0101l\u0113t"
    ],
    "wof:name":"Salet",
    "wof:placetype":"locality"
},
  "geometry": {"coordinates":[70.56097,37.44858],"type":"Point"}
}