{
  "type": "Feature",
  "properties": {
    "gn:admin1_code":"5",
    "gn:admin2_code":"2804.0",
    "gn:asciiname":"Rashyu",
    "gn:country_code":"AF",
    "gn:dem":2537,
    "gn:feature_class":"P",
    "gn:feature_code":"PPL",
    "gn:name":"R\u0101shy\u016b",
    "gn:population":0,
    "gn:timezone":"Asia/Kabul",
    "iso:country":"AF",
    "name:rus_x_preferred":[
        "Rash\u2019yu"
    ],
    "name:und_x_variant":[
        "R\u0101\u0161yu",
        "R\u0101shy\u016b",
        "R\u0101shyow",
        "\u0631\u0627\u0634\u064a\u0648"
    ],
    "wof:name":"Rashyu",
    "wof:placetype":"locality"
},
  "geometry": {"coordinates":[66.67684,34.82537],"type":"Point"}
}