{
  "type": "Feature",
  "properties": {
    "gn:admin1_code":"34",
    "gn:admin2_code":"1004.0",
    "gn:asciiname":"Tsowunah",
    "gn:country_code":"AF",
    "gn:dem":1823,
    "gn:feature_class":"P",
    "gn:feature_code":"PPL",
    "gn:name":"Tsowunah",
    "gn:population":0,
    "gn:timezone":"Asia/Kabul",
    "iso:country":"AF",
    "name:fas_x_preferred":[
        "\u0686\u0648\u0646\u0647"
    ],
    "name:und_x_variant":[
        "Cawona",
        "Chavuna",
        "\u0685\u0648\u0646\u0647",
        "Tsawonah",
        "Tsowunah",
        "\u0685\u0648\u0648\u0646\u0647"
    ],
    "wof:name":"Tsowunah",
    "wof:placetype":"locality"
},
  "geometry": {"coordinates":[71.46695,35.02479],"type":"Point"}
}