{
  "type": "Feature",
  "properties": {
    "gn:admin1_code":"35",
    "gn:admin2_code":"905.0",
    "gn:asciiname":"Mukah",
    "gn:country_code":"AF",
    "gn:dem":1723,
    "gn:feature_class":"P",
    "gn:feature_code":"PPL",
    "gn:name":"M\u016bkah",
    "gn:population":0,
    "gn:timezone":"Asia/Kabul",
    "iso:country":"AF",
    "name:fas_x_preferred":[
        "\u0645\u0648\u06a9\u0627\u062d"
    ],
    "name:ind_x_preferred":[
        "Mukah"
    ],
    "name:msa_x_preferred":[
        "Mukah"
    ],
    "name:und_x_variant":[
        "Muka",
        "M\u016bka",
        "M\u016bkah",
        "\u0645\u0648\u06a9\u0647"
    ],
    "name:vie_x_preferred":[
        "Mukah"
    ],
    "wof:name":"Mukah",
    "wof:placetype":"locality"
},
  "geometry": {"coordinates":[70.01514,34.8201],"type":"Point"}
}