{
  "type": "Feature",
  "properties": {
    "gn:admin1_code":"27",
    "gn:admin2_code":"404",
    "gn:asciiname":"Jandad",
    "gn:country_code":"AF",
    "gn:dem":3026,
    "gn:feature_class":"P",
    "gn:feature_code":"PPL",
    "gn:name":"J\u0101nd\u0101d",
    "gn:population":0,
    "gn:timezone":"Asia/Kabul",
    "iso:country":"AF",
    "name:und_x_variant":[
        "Dzhandad",
        "J\u0101nd\u0101d",
        "\u062c\u0627\u0646\u062f\u0627\u062f"
    ],
    "wof:name":"Jandad",
    "wof:placetype":"locality"
},
  "geometry": {"coordinates":[67.90148000000001,34.31457],"type":"Point"}
}