{
  "type": "Feature",
  "properties": {
    "gn:admin1_code":"29",
    "gn:admin2_code":"2901",
    "gn:asciiname":"Muhammad Akbar Kala",
    "gn:country_code":"AF",
    "gn:dem":2517,
    "gn:feature_class":"P",
    "gn:feature_code":"PPL",
    "gn:name":"Mu\u1e29ammad Akbar Kal\u0101",
    "gn:population":0,
    "gn:timezone":"Asia/Kabul",
    "iso:country":"AF",
    "name:und_x_variant":[
        "Mo\u1e29\u1e0f Akba\u1e5f Kal\u0101",
        "Mukhammedakbar-Kala",
        "\u0645\u062d\u0645\u062f \u0627\u06a9\u0628\u0631 \u06a9\u0644\u0627",
        "Mo\u1e29ammad Akbar Kal\u0101",
        "Mu\u1e29ammad Akbar Kal\u0101"
    ],
    "wof:name":"Muhammad Akbar Kala",
    "wof:placetype":"locality"
},
  "geometry": {"coordinates":[68.55594000000001,33.14097],"type":"Point"}
}