{
  "type": "Feature",
  "properties": {
    "gn:admin1_code":"27",
    "gn:admin2_code":"406",
    "gn:asciiname":"Sufi Khel",
    "gn:country_code":"AF",
    "gn:dem":2475,
    "gn:feature_class":"P",
    "gn:feature_code":"PPL",
    "gn:name":"\u015e\u016bf\u012b Kh\u0113l",
    "gn:population":0,
    "gn:timezone":"Asia/Kabul",
    "iso:country":"AF",
    "name:rus_x_preferred":[
        "Sufikheyl\u2019"
    ],
    "name:und_x_variant":[
        "\u015e\u016bfikh\u0113l",
        "\u015e\u016bf\u012b Kh\u0113l",
        "\u015e\u016bf\u012bkheyl",
        "\u0635\u0648\u0641\u06cc \u062e\u06d0\u0644"
    ],
    "wof:name":"Sufi Khel",
    "wof:placetype":"locality"
},
  "geometry": {"coordinates":[68.53350999999999,34.02662],"type":"Point"}
}