{
  "type": "Feature",
  "properties": {
    "gn:admin1_code":"19",
    "gn:admin2_code":"2203",
    "gn:asciiname":"Lat",
    "gn:country_code":"AF",
    "gn:dem":557,
    "gn:feature_class":"P",
    "gn:feature_code":"PPL",
    "gn:name":"L\u0101\u1e6f",
    "gn:population":0,
    "gn:timezone":"Asia/Kabul",
    "iso:country":"AF",
    "name:deu_x_preferred":[
        "Lat"
    ],
    "name:fra_x_preferred":[
        "Lat"
    ],
    "name:ind_x_preferred":[
        "Lat"
    ],
    "name:jpn_x_preferred":[
        "\u30e9\u30c3\u30c8"
    ],
    "name:msa_x_preferred":[
        "Lat"
    ],
    "wof:name":"Lat",
    "wof:placetype":"locality"
},
  "geometry": {"coordinates":[62.66667,30.16667],"type":"Point"}
}