{
  "type": "Feature",
  "properties": {
    "gn:admin1_code":"33",
    "gn:admin2_code":"3102",
    "gn:asciiname":"Firishqan",
    "gn:country_code":"AF",
    "gn:dem":1180,
    "gn:feature_class":"P",
    "gn:feature_code":"PPL",
    "gn:name":"Firishq\u0101n",
    "gn:population":0,
    "gn:timezone":"Asia/Kabul",
    "iso:country":"AF",
    "name:und_x_variant":[
        "Qaryeh-ye Fereshq\u0101n Kal\u0101n",
        "Fereshg\u0101n-e Kal\u0101n",
        "Fa\u1e5fas\u0304g\u0101n",
        "Farisk\u0101n",
        "Fe\u1e5fes\u0304q\u0101n",
        "Fereshg\u0101n",
        "Fereshq\u0101n",
        "Firishq\u0101n",
        "\u0641\u0631\u0634\u0642\u0627\u0646"
    ],
    "wof:name":"Firishqan",
    "wof:placetype":"locality"
},
  "geometry": {"coordinates":[66.43733,35.96482],"type":"Point"}
}