{
  "type": "Feature",
  "properties": {
    "gn:admin1_code":"26",
    "gn:admin2_code":"1203",
    "gn:asciiname":"Kokah Bulaq",
    "gn:country_code":"AF",
    "gn:dem":1176,
    "gn:feature_class":"P",
    "gn:feature_code":"PPL",
    "gn:name":"K\u014dkah B\u016bl\u0101q",
    "gn:population":0,
    "gn:timezone":"Asia/Kabul",
    "iso:country":"AF",
    "name:und_x_variant":[
        "K\u014dkabol\u0101q",
        "Kowkeh B\u016bl\u0101q",
        "K\u016bk Bol\u0101q",
        "Kowkah Bol\u0101q",
        "Kowk-e B\u016bl\u0101q",
        "K\u014dkah B\u016bl\u0101q",
        "\u06a9\u0648\u06a9\u0647 \u0628\u0648\u0644\u0627\u0642"
    ],
    "wof:name":"Kokah Bulaq",
    "wof:placetype":"locality"
},
  "geometry": {"coordinates":[69.26042,36.3138],"type":"Point"}
}