{
  "type": "Feature",
  "properties": {
    "gn:admin1_code":"23",
    "gn:admin2_code":"2401.0",
    "gn:asciiname":"Bala Deh",
    "gn:country_code":"AF",
    "gn:dem":1011,
    "gn:feature_class":"P",
    "gn:feature_code":"PPL",
    "gn:name":"B\u0101l\u0101 Deh",
    "gn:population":0,
    "gn:timezone":"Asia/Kabul",
    "iso:country":"AF",
    "name:und_x_variant":[
        "Kohe Neg\u0101r Deh",
        "Bala-Dekh",
        "Kohe Neg\u0101\u1e5f",
        "B\u0101l\u0101 Deh",
        "\u0628\u0627\u0644\u0627 \u062f\u0647",
        "K\u014dh-e Nig\u0101r",
        "\u06a9\u0648\u0647 \u0646\u06af\u0627\u0631"
    ],
    "wof:name":"Bala Deh",
    "wof:placetype":"locality"
},
  "geometry": {"coordinates":[65.68259999999999,31.62351],"type":"Point"}
}