{
  "type": "Feature",
  "properties": {
    "gn:admin1_code":"5",
    "gn:admin2_code":"2806.0",
    "gn:asciiname":"Sad Barg",
    "gn:country_code":"AF",
    "gn:dem":2989,
    "gn:feature_class":"P",
    "gn:feature_code":"PPL",
    "gn:name":"\u015ead Barg",
    "gn:population":0,
    "gn:timezone":"Asia/Kabul",
    "iso:country":"AF",
    "name:und_x_variant":[
        "Sadbarg",
        "\u015ead Barg",
        "\u015eadbarg",
        "\u0635\u062f \u0628\u0631\u06af"
    ],
    "wof:name":"Sad Barg",
    "wof:placetype":"locality"
},
  "geometry": {"coordinates":[66.82024,34.17413],"type":"Point"}
}