{
  "type": "Feature",
  "properties": {
    "gn:gn_country":"AF",
    "gn:gn_fcode":"PPLX",
    "gn:gn_pop":0,
    "iso:country":"AF",
    "qs_pg:aaroncc":"AF",
    "qs_pg:gn_country":"AF",
    "qs_pg:gn_fcode":"PPLX",
    "qs_pg:gn_pop":0,
    "qs_pg:name":"B\u012bb\u012b Mahr\u016b",
    "qs_pg:name_adm0":"Afghanistan",
    "qs_pg:name_adm1":"Kabul",
    "qs_pg:photos":151,
    "qs_pg:photos_1k":31,
    "qs_pg:photos_9k":1,
    "qs_pg:photos_9r":4,
    "qs_pg:photos_all":151,
    "qs_pg:photos_sr":4,
    "qs_pg:pop_sr":0,
    "qs_pg:qs_pg_placetype":"neighbourhood",
    "qs_pg:qs_pg_placetype_gp":"Suburb",
    "qs_pg:woe_adm0":23424739,
    "woe:adm0_id":23424739,
    "woe:name_adm0":"Afghanistan",
    "woe:name_adm1":"Kabul",
    "woe:placetype":"Suburb",
    "wof:name":"B\u012bb\u012b Mahr\u016b",
    "wof:placetype":"neighbourhood"
},
  "geometry": {"coordinates":[69.20287999999999,34.54121],"type":"Point"}
}