{
  "type": "Feature",
  "properties": {
    "gn:admin1_code":"42",
    "gn:admin2_code":"3306.0",
    "gn:asciiname":"Qal'ah-ye Afghan",
    "gn:country_code":"AF",
    "gn:dem":2174,
    "gn:feature_class":"P",
    "gn:feature_code":"PPL",
    "gn:name":"Qal\u2018ah-ye Afgh\u0101n",
    "gn:population":0,
    "gn:timezone":"Asia/Kabul",
    "iso:country":"AF",
    "name:fas_x_preferred":[
        "\u0642\u0644\u0639\u0647\u0654 \u0627\u0641\u063a\u0627\u0646"
    ],
    "name:und_x_variant":[
        "Kalaafgan",
        "Qal\u2018a Afgh\u0101n",
        "Qal\u2018eh-ye Afgh\u0101n",
        "Qal\u2018ah-ye Afgh\u0101n",
        "\u0642\u0644\u0639\u06c0 \u0627\u0641\u063a\u0627\u0646"
    ],
    "wof:name":"Qal'ah-ye Afghan",
    "wof:placetype":"locality"
},
  "geometry": {"coordinates":[69.33719000000001,35.1814],"type":"Point"}
}