{
  "type": "Feature",
  "properties": {
    "gn:admin1_code":"33",
    "gn:admin2_code":"3101.0",
    "gn:asciiname":"Chahar Say",
    "gn:country_code":"AF",
    "gn:dem":1228,
    "gn:feature_class":"P",
    "gn:feature_code":"PPL",
    "gn:name":"Chah\u0101r S\u0101y",
    "gn:population":0,
    "gn:timezone":"Asia/Kabul",
    "iso:country":"AF",
    "name:und_x_variant":[
        "Ch\u0101r Sai (2)",
        "Chah\u0101r S\u0101y (2)",
        "Chah\u0101r S\u0101y",
        "\u0686\u0647\u0627\u0631 \u0633\u0627\u06cc"
    ],
    "wof:name":"Chahar Say",
    "wof:placetype":"locality"
},
  "geometry": {"coordinates":[66.22014,36.26562],"type":"Point"}
}