{
  "type": "Feature",
  "properties": {
    "gn:admin1_code":"28",
    "gn:admin2_code":"2506.0",
    "gn:asciiname":"Spin Khune",
    "gn:country_code":"AF",
    "gn:dem":1469,
    "gn:feature_class":"P",
    "gn:feature_code":"PPL",
    "gn:name":"Sp\u012bn Kh\u016bn\u0113",
    "gn:population":0,
    "gn:timezone":"Asia/Kabul",
    "iso:country":"AF",
    "name:und_x_variant":[
        "\u0633\u067e\u06cc\u0646 \u062e\u0648\u0646\u06d0",
        "Sp\u012bn Kh\u016bn\u0113"
    ],
    "wof:name":"Spin Khune",
    "wof:placetype":"locality"
},
  "geometry": {"coordinates":[66.64171,31.96892],"type":"Point"}
}