{
  "type": "Feature",
  "properties": {
    "gn:admin1_code":"41",
    "gn:admin2_code":"3408",
    "gn:asciiname":"Gul Khwajah",
    "gn:country_code":"AF",
    "gn:dem":2656,
    "gn:feature_class":"P",
    "gn:feature_code":"PPL",
    "gn:name":"Gul Khw\u0101jah",
    "gn:population":0,
    "gn:timezone":"Asia/Kabul",
    "iso:country":"AF",
    "name:rus_x_preferred":[
        "Gul\u2019khodzha"
    ],
    "name:und_x_variant":[
        "Gulkw\u0101ja",
        "Gulkhw\u0101ja",
        "Gul Khw\u0101jah",
        "\u06af\u0644 \u062e\u0648\u0627\u062c\u0647",
        "Golkhv\u0101jeh"
    ],
    "wof:name":"Gul Khwajah",
    "wof:placetype":"locality"
},
  "geometry": {"coordinates":[65.90805,34.13245999999999],"type":"Point"}
}