{
  "type": "Feature",
  "properties": {
    "gn:admin1_code":"30",
    "gn:admin2_code":"1607.0",
    "gn:asciiname":"Galah Joy",
    "gn:country_code":"AF",
    "gn:dem":331,
    "gn:feature_class":"P",
    "gn:feature_code":"PPL",
    "gn:name":"Galah J\u014dy",
    "gn:population":0,
    "gn:timezone":"Asia/Kabul",
    "iso:country":"AF",
    "name:fas_x_preferred":[
        "\u06af\u0644\u0647 \u062c\u0648\u06cc"
    ],
    "name:rus_x_preferred":[
        "\u0413\u0430\u043b\u0430\u0434\u0436\u0443\u0439"
    ],
    "name:und_x_variant":[
        "Galajoy",
        "Galadzhuy",
        "Galah J\u014dy"
    ],
    "wof:name":"Galah Joy",
    "wof:placetype":"locality"
},
  "geometry": {"coordinates":[66.75192,36.80121],"type":"Point"}
}