{
  "type": "Feature",
  "properties": {
    "gn:admin1_code":"8",
    "gn:admin2_code":"607.0",
    "gn:asciiname":"Nalah",
    "gn:country_code":"AF",
    "gn:dem":2646,
    "gn:feature_class":"P",
    "gn:feature_code":"PPL",
    "gn:name":"N\u0101lah",
    "gn:population":0,
    "gn:timezone":"Asia/Kabul",
    "iso:country":"AF",
    "name:und_x_variant":[
        "N\u0101la",
        "N\u0101lah",
        "\u0646\u0627\u0644\u0647"
    ],
    "wof:name":"Nalah",
    "wof:placetype":"locality"
},
  "geometry": {"coordinates":[67.44412,33.15162],"type":"Point"}
}