{
  "type": "Feature",
  "properties": {
    "gn:admin1_code":"01",
    "gn:admin2_code":"1122.0",
    "gn:asciiname":"Afrij",
    "gn:country_code":"AF",
    "gn:dem":1733,
    "gn:feature_class":"P",
    "gn:feature_code":"PPL",
    "gn:name":"Afr\u012bj",
    "gn:population":0,
    "gn:timezone":"Asia/Kabul",
    "iso:country":"AF",
    "name:und_x_variant":[
        "Afr\u012bj",
        "\u0627\u0641\u0631\u06cc\u062c"
    ],
    "wof:name":"Afrij",
    "wof:placetype":"locality"
},
  "geometry": {"coordinates":[71.02606,37.02036],"type":"Point"}
}