{
  "type": "Feature",
  "properties": {
    "gn:admin1_code":"19",
    "gn:admin2_code":"2205.0",
    "gn:asciiname":"Qamar od Din Nikeh",
    "gn:cc2":"AF",
    "gn:country_code":"AF",
    "gn:dem":626,
    "gn:feature_class":"P",
    "gn:feature_code":"PPL",
    "gn:name":"Qamar od D\u012bn N\u012bkeh",
    "gn:population":0,
    "gn:timezone":"Asia/Kabul",
    "iso:country":"AF",
    "name:und_x_variant":[
        "Qama\u1e5fu\u1e0f\u1e0fin Nikeh",
        "Qamar od D\u012bn N\u012bkeh"
    ],
    "wof:name":"Qamar od Din Nikeh",
    "wof:placetype":"locality"
},
  "geometry": {"coordinates":[63.02083,31.68306],"type":"Point"}
}