{
  "type": "Feature",
  "properties": {
    "gn:admin1_code":"05",
    "gn:admin2_code":"2801",
    "gn:asciiname":"Sharah",
    "gn:country_code":"AF",
    "gn:dem":3165,
    "gn:feature_class":"P",
    "gn:feature_code":"PPL",
    "gn:name":"Sh\u0101r\u0101h",
    "gn:population":0,
    "gn:timezone":"Asia/Kabul",
    "iso:country":"AF",
    "name:fas_x_preferred":[
        "\u0634\u0627\u0647\u0631\u0627\u0647"
    ],
    "name:rus_x_preferred":[
        "\u0428\u0430\u0440\u0430"
    ],
    "name:und_x_variant":[
        "\u0160\u0101r\u0101h",
        "Shara",
        "Sh\u0101r\u0101h",
        "Sh\u0101hr\u0101h",
        "\u0634\u0627\u0631\u0627\u0647"
    ],
    "wof:name":"Sharah",
    "wof:placetype":"locality"
},
  "geometry": {"coordinates":[67.43056999999999,34.81108],"type":"Point"}
}