{
  "type": "Feature",
  "properties": {
    "gn:admin1_code":"34",
    "gn:admin2_code":"1009.0",
    "gn:asciiname":"Koldar",
    "gn:country_code":"AF",
    "gn:dem":2007,
    "gn:feature_class":"P",
    "gn:feature_code":"PPL",
    "gn:name":"K\u014dldar",
    "gn:population":0,
    "gn:timezone":"Asia/Kabul",
    "iso:country":"AF",
    "name:und_x_variant":[
        "K\u014dldar",
        "Kordar",
        "K\u016bldar",
        "\u06a9\u0648\u0644\u062f\u0631"
    ],
    "wof:name":"Koldar",
    "wof:placetype":"locality"
},
  "geometry": {"coordinates":[70.65725999999999,35.00345],"type":"Point"}
}