{
  "type": "Feature",
  "properties": {
    "gn:admin1_code":"23",
    "gn:admin2_code":"2403.0",
    "gn:asciiname":"Chughak",
    "gn:country_code":"AF",
    "gn:dem":1273,
    "gn:feature_class":"P",
    "gn:feature_code":"PPL",
    "gn:name":"Ch\u016bghak",
    "gn:population":0,
    "gn:timezone":"Asia/Kabul",
    "iso:country":"AF",
    "name:und_x_variant":[
        "Chugak",
        "\u010c\u016bghak",
        "Choghak",
        "Ch\u016bghak",
        "\u0686\u0648\u063a\u06a9"
    ],
    "wof:name":"Chughak",
    "wof:placetype":"locality"
},
  "geometry": {"coordinates":[65.86223000000001,31.98426],"type":"Point"}
}