{
  "type": "Feature",
  "properties": {
    "gn:admin1_code":"40",
    "gn:admin2_code":"305",
    "gn:asciiname":"Duabi Ghorband",
    "gn:country_code":"AF",
    "gn:dem":2032,
    "gn:feature_class":"P",
    "gn:feature_code":"PPL",
    "gn:name":"D\u016b\u0101b\u012b Gh\u014drband",
    "gn:population":0,
    "gn:timezone":"Asia/Kabul",
    "iso:country":"AF",
    "name:und_x_variant":[
        "Kala Do\u0101b",
        "Qala Do\u0101b",
        "Duabi-Gorband",
        "Qal\u2018eh-ye Do \u0100b",
        "\u1e0eo\u0101bi Gh\u014d\u1e5fban\u1e0f",
        "Do \u0100b\u012b Ghowr Band",
        "D\u014d\u0101b\u012b Gh\u014drband",
        "D\u016b\u0101b\u012b Gh\u014drband",
        "\u062f\u0648\u0622\u0628\u06cc \u063a\u0648\u0631\u0628\u0646\u062f"
    ],
    "wof:name":"Duabi Ghorband",
    "wof:placetype":"locality"
},
  "geometry": {"coordinates":[68.6397,34.96270999999999],"type":"Point"}
}