{
  "type": "Feature",
  "properties": {
    "gn:admin1_code":"6",
    "gn:admin2_code":"2105.0",
    "gn:asciiname":"Bagh-e Rais",
    "gn:country_code":"AF",
    "gn:dem":1475,
    "gn:feature_class":"P",
    "gn:feature_code":"PPL",
    "gn:name":"B\u0101gh-e Ra\u012bs",
    "gn:population":0,
    "gn:timezone":"Asia/Kabul",
    "iso:country":"AF",
    "name:und_x_variant":[
        "Bagi-Rais",
        "Baghe Rays",
        "B\u0101gh-e Ra\u012bs",
        "\u0628\u0627\u063a \u0631\u06cc\u0633",
        "B\u0101gh-e Ra\u2019\u012bs"
    ],
    "wof:name":"Bagh-e Rais",
    "wof:placetype":"locality"
},
  "geometry": {"coordinates":[63.1164,33.10163],"type":"Point"}
}