{
  "type": "Feature",
  "properties": {
    "gn:admin1_code":"34",
    "gn:admin2_code":"1014.0",
    "gn:asciiname":"Kacha Khel",
    "gn:country_code":"AF",
    "gn:dem":1161,
    "gn:feature_class":"P",
    "gn:feature_code":"PPL",
    "gn:name":"Kach\u0101 Kh\u0113l",
    "gn:population":0,
    "gn:timezone":"Asia/Kabul",
    "iso:country":"AF",
    "name:fas_x_preferred":[
        "\u06a9\u0686\u0627 \u062e\u06cc\u0644"
    ],
    "name:rus_x_preferred":[
        "Kachakheyl\u2019"
    ],
    "name:und_x_variant":[
        "Ka\u010d\u0101kh\u0113l",
        "Kach\u0101kh\u0113l",
        "Kach\u0101 Kh\u0113l",
        "\u06a9\u0686\u0627 \u062e\u06d0\u0644",
        "Kats\u0101 Kh\u0113l",
        "\u06a9\u0685\u0627 \u062e\u06d0\u0644"
    ],
    "wof:name":"Kacha Khel",
    "wof:placetype":"locality"
},
  "geometry": {"coordinates":[70.95671999999998,34.59543],"type":"Point"}
}