{
  "type": "Feature",
  "properties": {
    "gn:admin1_code":"10",
    "gn:admin2_code":"2311",
    "gn:asciiname":"De Loy Wiyaleh Kelay",
    "gn:country_code":"AF",
    "gn:dem":655,
    "gn:feature_class":"P",
    "gn:feature_code":"PPL",
    "gn:name":"D\u00ea L\u014dy Wiy\u0101l\u00eah K\u00ealay",
    "gn:population":0,
    "gn:timezone":"Asia/Kabul",
    "iso:country":"AF",
    "name:und_x_variant":[
        "Nazar Mo\u1e96amma\u1e0f Kh\u0101n Kalay",
        "\u1e0ee L\u014dy Wy\u0101la Kalay",
        "De Lowy Way\u0101lah Kalay",
        "D\u00ea L\u014dy Wiy\u0101l\u00eah K\u00ealay",
        "\u062f \u0644\u0648\u06cc \u0648\u06cc\u0627\u0644\u0647 \u06a9\u0644\u06cc",
        "D\u00ea L\u016by Wiy\u0101lah Kalay",
        "Naz\u0327ar Mu\u1e29ammad Kh\u0101n K\u00ealay",
        "\u0646\u0638\u0631 \u0645\u062d\u0645\u062f \u062e\u0627\u0646 \u06a9\u0644\u06cc"
    ],
    "wof:name":"De Loy Wiyaleh Kelay",
    "wof:placetype":"locality"
},
  "geometry": {"coordinates":[64.00375,30.59297],"type":"Point"}
}