{
  "type": "Feature",
  "properties": {
    "gn:admin1_code":"05",
    "gn:admin2_code":"2805.0",
    "gn:asciiname":"Now-e Deh",
    "gn:country_code":"AF",
    "gn:dem":3229,
    "gn:feature_class":"P",
    "gn:feature_code":"PPL",
    "gn:name":"Now-e Deh",
    "gn:population":0,
    "gn:timezone":"Asia/Kabul",
    "iso:country":"AF",
    "name:und_x_variant":[
        "Navi-Dekh",
        "N\u0101w-e Deh",
        "Naw-e Deh",
        "Now-e Deh",
        "\u0646\u0648 \u062f\u0647"
    ],
    "wof:name":"Now-e Deh",
    "wof:placetype":"locality"
},
  "geometry": {"coordinates":[67.1974,34.47628],"type":"Point"}
}