{
  "type": "Feature",
  "properties": {
    "gn:admin1_code":"01",
    "gn:admin2_code":"1126.0",
    "gn:asciiname":"Nalah",
    "gn:country_code":"AF",
    "gn:dem":1641,
    "gn:feature_class":"P",
    "gn:feature_code":"PPL",
    "gn:name":"N\u0101lah",
    "gn:population":0,
    "gn:timezone":"Asia/Kabul",
    "iso:country":"AF",
    "name:und_x_variant":[
        "N\u0101lah",
        "\u0646\u0627\u0644\u0647",
        "N\u0101l\u0101"
    ],
    "wof:name":"Nalah",
    "wof:placetype":"locality"
},
  "geometry": {"coordinates":[70.42469,37.29548],"type":"Point"}
}