{
  "type": "Feature",
  "properties": {
    "gn:admin1_code":"41",
    "gn:admin2_code":"3409.0",
    "gn:asciiname":"Kantalzar",
    "gn:country_code":"AF",
    "gn:dem":2461,
    "gn:feature_class":"P",
    "gn:feature_code":"PPL",
    "gn:name":"Kan\u1e6falz\u0101r",
    "gn:population":0,
    "gn:timezone":"Asia/Kabul",
    "iso:country":"AF",
    "name:und_x_variant":[
        "Kan\u1e6falz\u0101r",
        "\u06a9\u0646\u067c\u0644\u0632\u0627\u0631",
        "Kantalz\u0101\u1e5f"
    ],
    "wof:name":"Kantalzar",
    "wof:placetype":"locality"
},
  "geometry": {"coordinates":[66.49003,33.7938],"type":"Point"}
}