{
  "type": "Feature",
  "properties": {
    "gn:admin1_code":"23",
    "gn:admin2_code":"2401",
    "gn:asciiname":"Karz-e Sufla",
    "gn:country_code":"AF",
    "gn:dem":996,
    "gn:feature_class":"P",
    "gn:feature_code":"PPL",
    "gn:name":"Karz-e Sufl\u00e1",
    "gn:population":0,
    "gn:timezone":"Asia/Kabul",
    "iso:country":"AF",
    "name:und_x_variant":[
        "Karzi-Sufla",
        "Ka\u1e5fze Sufl\u0101",
        "Karz-e Sufl\u00e1",
        "\u06a9\u0631\u0632 \u0633\u0641\u0644\u0649",
        "Karz-e Sofl\u00e1"
    ],
    "wof:name":"Karz-e Sufla",
    "wof:placetype":"locality"
},
  "geometry": {"coordinates":[65.75816999999999,31.57511],"type":"Point"}
}