{
  "type": "Feature",
  "properties": {
    "gn:admin1_code":"35",
    "gn:admin2_code":"904.0",
    "gn:asciiname":"Khojil Khandu",
    "gn:country_code":"AF",
    "gn:dem":1651,
    "gn:feature_class":"P",
    "gn:feature_code":"PPL",
    "gn:name":"Kh\u014djil Khand\u016b",
    "gn:population":0,
    "gn:timezone":"Asia/Kabul",
    "iso:country":"AF",
    "name:rus_x_preferred":[
        "Khodzhil\u2019khandu"
    ],
    "name:und_x_variant":[
        "Khojil Khand\u016b",
        "Kh\u014dj\u0113l Khandu",
        "Kh\u014djil Khand\u016b",
        "\u062e\u0648\u062c\u0644 \u062e\u0646\u062f\u0648"
    ],
    "wof:name":"Khojil Khandu",
    "wof:placetype":"locality"
},
  "geometry": {"coordinates":[70.05905,34.96206],"type":"Point"}
}