{
  "type": "Feature",
  "properties": {
    "gn:admin1_code":"08",
    "gn:admin2_code":"611",
    "gn:asciiname":"Ghatah Kala",
    "gn:country_code":"AF",
    "gn:dem":2027,
    "gn:feature_class":"P",
    "gn:feature_code":"PPL",
    "gn:name":"Gha\u1e6fah Kal\u0101",
    "gn:population":0,
    "gn:timezone":"Asia/Kabul",
    "iso:country":"AF",
    "name:und_x_variant":[
        "Gatakala",
        "Ghata Kal\u0101",
        "\u063a\u067c\u0647 \u06a9\u0644\u0627",
        "Gha\u1e6fah Kal\u0101"
    ],
    "wof:name":"Ghatah Kala",
    "wof:placetype":"locality"
},
  "geometry": {"coordinates":[68.0872,32.83009000000001],"type":"Point"}
}