{
  "type": "Feature",
  "properties": {
    "gn:admin1_code":"11",
    "gn:admin2_code":"2014",
    "gn:asciiname":"Wakhal Sahid",
    "gn:country_code":"AF",
    "gn:dem":1432,
    "gn:feature_class":"P",
    "gn:feature_code":"PPL",
    "gn:name":"W\u0101khal Sah\u012bd",
    "gn:population":0,
    "gn:timezone":"Asia/Kabul",
    "iso:country":"AF",
    "name:und_x_variant":[
        "W\u0101khal Sah\u012bd",
        "\u0648\u0627\u062e\u0644 \u0633\u0647\u06cc\u062f",
        "W\u0101khal Shah\u012bd",
        "\u0648\u0627\u062e\u0644 \u0634\u0647\u06cc\u062f"
    ],
    "wof:name":"Wakhal Sahid",
    "wof:placetype":"locality"
},
  "geometry": {"coordinates":[62.66088000000001,33.42063],"type":"Point"}
}