{
  "type": "Feature",
  "properties": {
    "gn:admin1_code":"10",
    "gn:admin2_code":"2303.0",
    "gn:asciiname":"Lalazi",
    "gn:country_code":"AF",
    "gn:dem":910,
    "gn:feature_class":"P",
    "gn:feature_code":"PPL",
    "gn:name":"Lalazi",
    "gn:population":0,
    "gn:timezone":"Asia/Kabul",
    "iso:country":"AF",
    "name:und_x_variant":[
        "L\u0101l\u0101za\u012b",
        "\u0644\u0627\u0644\u0627\u0632\u06cc",
        "L\u0101l\u0101zi"
    ],
    "wof:name":"Lalazi",
    "wof:placetype":"locality"
},
  "geometry": {"coordinates":[64.94589000000001,32.17537],"type":"Point"}
}