{
  "type": "Feature",
  "properties": {
    "gn:admin1_code":"32",
    "gn:admin2_code":"1504.0",
    "gn:asciiname":"Chakabi",
    "gn:country_code":"AF",
    "gn:dem":1938,
    "gn:feature_class":"P",
    "gn:feature_code":"PPL",
    "gn:name":"Chak\u0101b\u012b",
    "gn:population":0,
    "gn:timezone":"Asia/Kabul",
    "iso:country":"AF",
    "name:und_x_variant":[
        "Cak\u0101bi",
        "Chak\u0101b\u012b",
        "\u0686\u06a9\u0627\u0628\u06cc"
    ],
    "wof:name":"Chakabi",
    "wof:placetype":"locality"
},
  "geometry": {"coordinates":[67.44524,35.99079000000001],"type":"Point"}
}