{
  "type": "Feature",
  "properties": {
    "gn:admin1_code":"01",
    "gn:admin2_code":"1116",
    "gn:asciiname":"Yamchian",
    "gn:country_code":"AF",
    "gn:dem":1925,
    "gn:feature_class":"P",
    "gn:feature_code":"PPL",
    "gn:name":"Y\u0101mch\u012b\u0101n",
    "gn:population":0,
    "gn:timezone":"Asia/Kabul",
    "iso:country":"AF",
    "name:und_x_variant":[
        "Yam\u010dy\u0101n",
        "Yamchy\u0101n",
        "Y\u0101mch\u012b\u0101n",
        "\u06cc\u0627\u0645\u0686\u06cc\u0627\u0646"
    ],
    "wof:name":"Yamchian",
    "wof:placetype":"locality"
},
  "geometry": {"coordinates":[70.45453000000001,36.835],"type":"Point"}
}