{
  "type": "Feature",
  "properties": {
    "gn:admin1_code":"10",
    "gn:admin2_code":"2305",
    "gn:asciiname":"Takht Khulah",
    "gn:country_code":"AF",
    "gn:dem":1635,
    "gn:feature_class":"P",
    "gn:feature_code":"PPL",
    "gn:name":"Takht Kh\u016blah",
    "gn:population":0,
    "gn:timezone":"Asia/Kabul",
    "iso:country":"AF",
    "name:fas_x_preferred":[
        "\u062f\u0647\u0627\u0646\u0654 \u062a\u062e\u062a"
    ],
    "name:rus_x_preferred":[
        "\u0422\u0430\u0445\u0442\u0445\u0443\u043b\u0430"
    ],
    "name:und_x_variant":[
        "Takhtkhula",
        "Takht Khol\u0113h",
        "Takht Kh\u016blah",
        "\u062a\u062e\u062a \u062e\u0648\u0644\u0647",
        "Takht Khulah"
    ],
    "wof:name":"Takht Khulah",
    "wof:placetype":"locality"
},
  "geometry": {"coordinates":[65.10080000000001,33.15265],"type":"Point"}
}