{
  "type": "Feature",
  "properties": {
    "gn:admin1_code":"01",
    "gn:admin2_code":"1125",
    "gn:asciiname":"Safed Darah",
    "gn:country_code":"AF",
    "gn:dem":2276,
    "gn:feature_class":"P",
    "gn:feature_code":"PPL",
    "gn:name":"Saf\u0113d Darah",
    "gn:population":0,
    "gn:timezone":"Asia/Kabul",
    "iso:country":"AF",
    "name:und_x_variant":[
        "Saf\u0113\u1e0f \u1e0ea\u1e5f\u1e5fah",
        "Saf\u012bd Darreh",
        "Safed Darra",
        "Safe\u1e0f\u1e0fa\u1e5fa",
        "\u0633\u0641\u06d0\u062f \u062f\u0631\u0647",
        "Sef\u012bd Darreh",
        "Safayd Darah",
        "Saf\u0113d Darah"
    ],
    "wof:name":"Safed Darah",
    "wof:placetype":"locality"
},
  "geometry": {"coordinates":[71.15378,36.64242],"type":"Point"}
}