{
  "type": "Feature",
  "properties": {
    "gn:admin1_code":"41",
    "gn:admin2_code":"3409.0",
    "gn:asciiname":"Nala",
    "gn:country_code":"AF",
    "gn:dem":2332,
    "gn:feature_class":"P",
    "gn:feature_code":"PPL",
    "gn:name":"N\u0101l\u0101",
    "gn:population":0,
    "gn:timezone":"Asia/Kabul",
    "iso:country":"AF",
    "name:und_x_variant":[
        "N\u0101l\u0101",
        "\u0646\u0627\u0644\u0627"
    ],
    "wof:name":"Nala",
    "wof:placetype":"locality"
},
  "geometry": {"coordinates":[66.34350000000001,33.89094],"type":"Point"}
}