{
  "type": "Feature",
  "properties": {
    "gn:admin1_code":"41",
    "gn:admin2_code":"3409.0",
    "gn:asciiname":"Nala",
    "gn:country_code":"AF",
    "gn:dem":2332,
    "gn:feature_class":"P",
    "gn:feature_code":"PPL",
    "gn:name":"N\u0101l\u0101",
    "gn:population":0,
    "gn:timezone":"Asia/Kabul",
    "iso:country":"AF",
    "name:hin_x_preferred":[
        "\u0928\u0932-\u0926\u092e\u092f\u0928\u094d\u0924\u0940"
    ],
    "name:ind_x_preferred":[
        "Nala"
    ],
    "name:mai_x_preferred":[
        "\u0928\u0932-\u0926\u092e\u092f\u0928\u094d\u0924\u0940"
    ],
    "name:mal_x_preferred":[
        "\u0d28\u0d33\u0d7b"
    ],
    "name:rus_x_preferred":[
        "\u041d\u0430\u043b\u0430"
    ],
    "name:san_x_preferred":[
        "\u0928\u0932\u0903"
    ],
    "name:spa_x_preferred":[
        "Nala"
    ],
    "name:tam_x_preferred":[
        "\u0ba8\u0bb3\u0ba9\u0bcd"
    ],
    "name:tel_x_preferred":[
        "\u0c28\u0c32\u0c41\u0c21\u0c41"
    ],
    "name:und_x_variant":[
        "N\u0101l\u0101",
        "\u0646\u0627\u0644\u0627"
    ],
    "wof:name":"Nala",
    "wof:placetype":"locality"
},
  "geometry": {"coordinates":[66.34350000000001,33.89094],"type":"Point"}
}