{
  "type": "Feature",
  "properties": {
    "gn:admin1_code":"30",
    "gn:admin2_code":"1608",
    "gn:asciiname":"Kurchah",
    "gn:country_code":"AF",
    "gn:dem":932,
    "gn:feature_class":"P",
    "gn:feature_code":"PPL",
    "gn:name":"Kurchah",
    "gn:population":0,
    "gn:timezone":"Asia/Kabul",
    "iso:country":"AF",
    "name:und_x_variant":[
        "Kurcha",
        "Kurchah",
        "\u06a9\u0631\u0686\u0647"
    ],
    "wof:name":"Kurchah",
    "wof:placetype":"locality"
},
  "geometry": {"coordinates":[66.56777,36.4508],"type":"Point"}
}