{
  "type": "Feature",
  "properties": {
    "gn:admin1_code":"18",
    "gn:admin2_code":"808.0",
    "gn:asciiname":"Gagrah",
    "gn:country_code":"AF",
    "gn:dem":1297,
    "gn:feature_class":"P",
    "gn:feature_code":"PPL",
    "gn:name":"G\u0101grah",
    "gn:population":0,
    "gn:timezone":"Asia/Kabul",
    "iso:country":"AF",
    "name:und_x_variant":[
        "Gagra",
        "G\u0101g\u1e5fa",
        "G\u0101grah",
        "\u06af\u0627\u06af\u0631\u0647"
    ],
    "wof:name":"Gagrah",
    "wof:placetype":"locality"
},
  "geometry": {"coordinates":[70.434,34.118],"type":"Point"}
}