{
  "type": "Feature",
  "properties": {
    "gn:admin1_code":"08",
    "gn:admin2_code":"601",
    "gn:asciiname":"Qanat-e Ghulam Jan",
    "gn:country_code":"AF",
    "gn:dem":2314,
    "gn:feature_class":"P",
    "gn:feature_code":"PPL",
    "gn:name":"Qan\u0101t-e Ghul\u0101m J\u0101n",
    "gn:population":0,
    "gn:timezone":"Asia/Kabul",
    "iso:country":"AF",
    "name:und_x_variant":[
        "Kanati-Gulyamdzhan",
        "Qan\u0101t-e Ghul\u0101m J\u0101n",
        "Qan\u0101t-e Ghol\u0101mj\u0101n",
        "\u0642\u0646\u0627\u062a \u063a\u0644\u0627\u0645 \u062c\u0627\u0646"
    ],
    "wof:name":"Qanat-e Ghulam Jan",
    "wof:placetype":"locality"
},
  "geometry": {"coordinates":[68.36396999999999,33.61311],"type":"Point"}
}