{
  "type": "Feature",
  "properties": {
    "gn:admin1_code":"11",
    "gn:admin2_code":"2006",
    "gn:asciiname":"Khudro",
    "gn:country_code":"AF",
    "gn:dem":1148,
    "gn:feature_class":"P",
    "gn:feature_code":"PPL",
    "gn:name":"Khudr\u014d",
    "gn:population":0,
    "gn:timezone":"Asia/Kabul",
    "iso:country":"AF",
    "name:und_x_variant":[
        "Khu\u1e0f\u1e5fo",
        "Khudru",
        "Khudr\u014d",
        "\u062e\u062f\u0631\u0648",
        "Khvodrow"
    ],
    "wof:name":"Khudro",
    "wof:placetype":"locality"
},
  "geometry": {"coordinates":[62.16526,34.80824],"type":"Point"}
}