{
  "type": "Feature",
  "properties": {
    "gn:admin1_code":"34",
    "gn:admin2_code":"1007.0",
    "gn:asciiname":"Gowijah",
    "gn:country_code":"AF",
    "gn:dem":1379,
    "gn:feature_class":"P",
    "gn:feature_code":"PPL",
    "gn:name":"Gowijah",
    "gn:population":0,
    "gn:timezone":"Asia/Kabul",
    "iso:country":"AF",
    "name:fas_x_preferred":[
        "\u06af\u0648\u062c\u06cc"
    ],
    "name:und_x_variant":[
        "Gaweja",
        "Gavedzha",
        "Gaw\u00eajah",
        "Gawejah",
        "Gowijah",
        "\u06af\u0648\u062c\u0647"
    ],
    "wof:name":"Gowijah",
    "wof:placetype":"locality"
},
  "geometry": {"coordinates":[71.33617,34.93827],"type":"Point"}
}