{
  "type": "Feature",
  "properties": {
    "gn:admin1_code":"09",
    "gn:admin2_code":"2702",
    "gn:asciiname":"Masjid Nigar",
    "gn:country_code":"AF",
    "gn:dem":2684,
    "gn:feature_class":"P",
    "gn:feature_code":"PPL",
    "gn:name":"Masjid Nig\u0101r",
    "gn:population":0,
    "gn:timezone":"Asia/Kabul",
    "iso:country":"AF",
    "name:fas_x_preferred":[
        "Masjed Neg\u0101r"
    ],
    "name:und_x_variant":[
        "Masjed Negar",
        "Masje\u1e0fe Neg\u0101r",
        "Masdzhidnigar",
        "Masjid Nig\u0101r",
        "\u0645\u0633\u062c\u062f \u0646\u06af\u0627\u0631"
    ],
    "wof:name":"Masjid Nigar",
    "wof:placetype":"locality"
},
  "geometry": {"coordinates":[64.49231999999999,34.05303],"type":"Point"}
}