{
  "type": "Feature",
  "properties": {
    "gn:admin1_code":"24",
    "gn:admin2_code":"1401.0",
    "gn:asciiname":"Kata Khel",
    "gn:country_code":"AF",
    "gn:dem":416,
    "gn:feature_class":"P",
    "gn:feature_code":"PPL",
    "gn:name":"Kat\u0101 Kh\u0113l",
    "gn:population":0,
    "gn:timezone":"Asia/Kabul",
    "iso:country":"AF",
    "name:fas_x_preferred":[
        "\u0643\u062a\u0627 \u062e\u064a\u0644"
    ],
    "name:rus_x_preferred":[
        "\u041a\u0430\u0442\u0430\u0445\u0435\u0438\u043b\u044c"
    ],
    "name:und_x_variant":[
        "Kat\u0101 Kh\u0113l",
        "Katakheil\u2019",
        "Kat\u0101 Kheyl",
        "\u06a9\u062a\u0627 \u062e\u06d0\u0644"
    ],
    "wof:name":"Kata Khel",
    "wof:placetype":"locality"
},
  "geometry": {"coordinates":[68.94206,36.67462],"type":"Point"}
}