{
  "type": "Feature",
  "properties": {
    "gn:admin1_code":"9",
    "gn:admin2_code":"2707.0",
    "gn:asciiname":"Shinyah Burnah",
    "gn:country_code":"AF",
    "gn:dem":2783,
    "gn:feature_class":"P",
    "gn:feature_code":"PPL",
    "gn:name":"Sh\u012bnyah Burnah",
    "gn:population":0,
    "gn:timezone":"Asia/Kabul",
    "iso:country":"AF",
    "name:rus_x_preferred":[
        "Shin\u2019yaburna"
    ],
    "name:und_x_variant":[
        "\u0160\u012bnya Burna",
        "Sh\u012bnyah Burnah",
        "Shin\u2019yaburna",
        "\u0634\u06cc\u0646\u06cc\u0647 \u0628\u0631\u0646\u0647"
    ],
    "wof:name":"Shinyah Burnah",
    "wof:placetype":"locality"
},
  "geometry": {"coordinates":[66.33010999999999,34.3392],"type":"Point"}
}