{
  "type": "Feature",
  "properties": {
    "gn:admin1_code":"01",
    "gn:admin2_code":"1103",
    "gn:asciiname":"Nowak",
    "gn:country_code":"AF",
    "gn:dem":2132,
    "gn:feature_class":"P",
    "gn:feature_code":"PPL",
    "gn:name":"Nowak",
    "gn:population":0,
    "gn:timezone":"Asia/Kabul",
    "iso:country":"AF",
    "name:und_x_variant":[
        "Nawak",
        "\u0646\u0648\u06a9",
        "N\u0101vak",
        "Nowak"
    ],
    "wof:name":"Nowak",
    "wof:placetype":"locality"
},
  "geometry": {"coordinates":[70.97468000000001,36.71987],"type":"Point"}
}