{
  "type": "Feature",
  "properties": {
    "gn:admin1_code":"06",
    "gn:admin2_code":"2108",
    "gn:asciiname":"Karez-e Tapah-ye Siyah",
    "gn:country_code":"AF",
    "gn:dem":588,
    "gn:feature_class":"P",
    "gn:feature_code":"PPL",
    "gn:name":"K\u0101r\u0113z-e Tapah-ye Siy\u0101h",
    "gn:population":0,
    "gn:timezone":"Asia/Kabul",
    "iso:country":"AF",
    "name:und_x_variant":[
        "K\u0101\u1e5f\u0113ze Tapa-i-Sy\u0101h",
        "K\u0101r\u012bz-e Tappeh-ye S\u012b\u0101h",
        "K\u0101r\u0113z-e Tapah-ye S\u012b\u0101h",
        "\u06a9\u0627\u0631\u06d0\u0632 \u062a\u067e\u0647 \u0633\u06cc\u0627\u0647",
        "K\u0101r\u0113z-e Tapah-ye Siy\u0101h"
    ],
    "wof:name":"Karez-e Tapah-ye Siyah",
    "wof:placetype":"locality"
},
  "geometry": {"coordinates":[61.29751,32.32299],"type":"Point"}
}