{
  "type": "Feature",
  "properties": {
    "gn:admin1_code":"27",
    "gn:admin2_code":"403",
    "gn:asciiname":"Panj asya",
    "gn:country_code":"AF",
    "gn:dem":2895,
    "gn:feature_class":"P",
    "gn:feature_code":"PPL",
    "gn:name":"Panj \u0101sy\u0101",
    "gn:population":0,
    "gn:timezone":"Asia/Kabul",
    "iso:country":"AF",
    "name:und_x_variant":[
        "Pandzhasia",
        "Panjasia",
        "Panj\u0101sy\u0101",
        "Panj\u0101s\u012b\u0101b",
        "Panj\u0101h S\u012b\u0101h",
        "Panj \u0101sy\u0101",
        "\u067e\u0646\u062c \u0622\u0633\u06cc\u0627"
    ],
    "wof:name":"Panj asya",
    "wof:placetype":"locality"
},
  "geometry": {"coordinates":[68.05984000000001,34.49479],"type":"Point"}
}