{
  "type": "Feature",
  "properties": {
    "gn:admin1_code":"41",
    "gn:admin2_code":"3402.0",
    "gn:asciiname":"Dahan-e Ushay",
    "gn:country_code":"AF",
    "gn:dem":1987,
    "gn:feature_class":"P",
    "gn:feature_code":"PPL",
    "gn:name":"Dah\u0101n-e \u016ashay",
    "gn:population":0,
    "gn:timezone":"Asia/Kabul",
    "iso:country":"AF",
    "name:und_x_variant":[
        "\u1e0eahane \u016as\u0304ay",
        "Dah\u0101n-e \u016ashay",
        "\u062f\u0647\u0627\u0646 \u0627\u0648\u0634\u06cc",
        "Dahan-e \u016ashay"
    ],
    "wof:name":"Dahan-e Ushay",
    "wof:placetype":"locality"
},
  "geometry": {"coordinates":[65.95279000000001,33.56844],"type":"Point"}
}