{
  "type": "Feature",
  "properties": {
    "gn:admin1_code":"02",
    "gn:admin2_code":"1904",
    "gn:asciiname":"Malghal",
    "gn:country_code":"AF",
    "gn:dem":1802,
    "gn:feature_class":"P",
    "gn:feature_code":"PPL",
    "gn:name":"Malgh\u0101l",
    "gn:population":0,
    "gn:timezone":"Asia/Kabul",
    "iso:country":"AF",
    "name:und_x_variant":[
        "Malgh\u0101l",
        "\u0645\u0644\u063a\u0627\u0644"
    ],
    "wof:name":"Malghal",
    "wof:placetype":"locality"
},
  "geometry": {"coordinates":[64.20396,35.23656],"type":"Point"}
}