{
  "type": "Feature",
  "properties": {
    "gn:admin1_code":"27",
    "gn:admin2_code":"407",
    "gn:asciiname":"Shash Gaw",
    "gn:country_code":"AF",
    "gn:dem":2466,
    "gn:feature_class":"P",
    "gn:feature_code":"PPL",
    "gn:name":"Shash G\u0101w",
    "gn:population":0,
    "gn:timezone":"Asia/Kabul",
    "iso:country":"AF",
    "name:und_x_variant":[
        "Shashgao",
        "\u0160a\u0161g\u0101w",
        "Shashgav",
        "Shash G\u0101w",
        "Shesh G\u0101v",
        "\u0634\u0634 \u06af\u0627\u0648"
    ],
    "wof:name":"Shash Gaw",
    "wof:placetype":"locality"
},
  "geometry": {"coordinates":[68.54640999999999,33.73779],"type":"Point"}
}