{
  "type": "Feature",
  "properties": {
    "gn:admin1_code":"01",
    "gn:admin2_code":"1102",
    "gn:asciiname":"Gandah Qol",
    "gn:country_code":"AF",
    "gn:dem":1696,
    "gn:feature_class":"P",
    "gn:feature_code":"PPL",
    "gn:name":"Gandah Q\u014dl",
    "gn:population":0,
    "gn:timezone":"Asia/Kabul",
    "iso:country":"AF",
    "name:und_x_variant":[
        "Ganda Qowl",
        "Ganda Q\u014dl",
        "Gandeh Qowl",
        "Gandah Q\u014dl",
        "\u06af\u0646\u062f\u0647 \u0642\u0648\u0644"
    ],
    "wof:name":"Gandah Qol",
    "wof:placetype":"locality"
},
  "geometry": {"coordinates":[70.21288,36.86387],"type":"Point"}
}