{
  "type": "Feature",
  "properties": {
    "gn:admin1_code":"13",
    "gn:admin2_code":"110.0",
    "gn:asciiname":"Husain Khel",
    "gn:country_code":"AF",
    "gn:dem":1788,
    "gn:feature_class":"P",
    "gn:feature_code":"PPL",
    "gn:name":"\u1e28usa\u012bn Kh\u0113l",
    "gn:population":0,
    "gn:timezone":"Asia/Kabul",
    "iso:country":"AF",
    "name:und_x_variant":[
        "K\u0101rtah-ye Ghul\u0101m J\u0101n",
        "\u06a9\u0627\u0631\u062a\u06c0 \u063a\u0644\u0627\u0645 \u062c\u0627\u0646",
        "\u1e28usa\u012bn Kh\u0113l",
        "\u062d\u0633\u064a\u0646 \u062e\u06d0\u0644"
    ],
    "wof:name":"Husain Khel",
    "wof:placetype":"locality"
},
  "geometry": {"coordinates":[69.29745,34.49332],"type":"Point"}
}