{
  "type": "Feature",
  "properties": {
    "gn:admin1_code":"11",
    "gn:admin2_code":"2014.0",
    "gn:asciiname":"Qal'ah-ye Rahmdil",
    "gn:country_code":"AF",
    "gn:dem":1075,
    "gn:feature_class":"P",
    "gn:feature_code":"PPL",
    "gn:name":"Qal\u2018ah-ye Ra\u1e29mdil",
    "gn:population":0,
    "gn:timezone":"Asia/Kabul",
    "iso:country":"AF",
    "name:fas_x_preferred":[
        "\u0642\u0644\u063a\u0647\u0654 \u0631\u062d\u0645\u062f\u0644"
    ],
    "name:rus_x_preferred":[
        "Kalayi-Rakhmdil\u2019"
    ],
    "name:und_x_variant":[
        "Qal\u2018a-i-\u1e5ea\u1e29m\u1e0fel",
        "Qal\u2018eh-ye Ra\u1e29mdel",
        "Qal\u2018ah-ye Ra\u1e29mdil",
        "\u0642\u0644\u0639\u06c0 \u0631\u062d\u0645\u062f\u0644",
        "\u0642\u0644\u063a\u0647\u0654 \u0631\u062d\u0645\u062f\u0644"
    ],
    "wof:name":"Qal'ah-ye Rahmdil",
    "wof:placetype":"locality"
},
  "geometry": {"coordinates":[62.13015,33.30611],"type":"Point"}
}