{
  "type": "Feature",
  "properties": {
    "gn:admin1_code":"08",
    "gn:admin2_code":"618",
    "gn:asciiname":"Sperah",
    "gn:country_code":"AF",
    "gn:dem":2290,
    "gn:feature_class":"P",
    "gn:feature_code":"PPL",
    "gn:name":"Sp\u0113rah",
    "gn:population":0,
    "gn:timezone":"Asia/Kabul",
    "iso:country":"AF",
    "name:fas_x_preferred":[
        "\u0633\u067e\u064a\u0631\u0647"
    ],
    "name:und_x_variant":[
        "Sp\u0113\u1e5fa",
        "Spera",
        "Sp\u0113rah",
        "\u0633\u067e\u06d0\u0631\u0647"
    ],
    "wof:name":"Sperah",
    "wof:placetype":"locality"
},
  "geometry": {"coordinates":[68.23643,33.35998],"type":"Point"}
}