{
  "type": "Feature",
  "properties": {
    "gn:admin1_code":"09",
    "gn:admin2_code":"2706",
    "gn:asciiname":"Falayzi",
    "gn:country_code":"AF",
    "gn:dem":2589,
    "gn:feature_class":"P",
    "gn:feature_code":"PPL",
    "gn:name":"F\u0101layz\u012b",
    "gn:population":0,
    "gn:timezone":"Asia/Kabul",
    "iso:country":"AF",
    "name:fas_x_preferred":[
        "\u067e\u0627\u0644\u064a\u0632\u06cc"
    ],
    "name:und_x_variant":[
        "Falezi",
        "F\u0101l\u0113zi",
        "P\u0101l\u012bz\u012b",
        "F\u0101layz\u012b",
        "\u0641\u0627\u0644\u06cc\u0632\u06cc",
        "F\u0101l\u012bz\u012b"
    ],
    "wof:name":"Falayzi",
    "wof:placetype":"locality"
},
  "geometry": {"coordinates":[64.83345,33.42522],"type":"Point"}
}