{
  "type": "Feature",
  "properties": {
    "gn:admin1_code":"09",
    "gn:admin2_code":"2710",
    "gn:asciiname":"Qishlaq-e Kuhnah",
    "gn:country_code":"AF",
    "gn:dem":2573,
    "gn:feature_class":"P",
    "gn:feature_code":"PPL",
    "gn:name":"Qishl\u0101q-e Kuhnah",
    "gn:population":0,
    "gn:timezone":"Asia/Kabul",
    "iso:country":"AF",
    "name:und_x_variant":[
        "Qos\u0304 Kuhna",
        "Qosh Kohneh",
        "Qishl\u0101q-e Kuhnah",
        "\u0642\u0634\u0644\u0627\u0642 \u06a9\u0647\u0646\u0647"
    ],
    "wof:name":"Qishlaq-e Kuhnah",
    "wof:placetype":"locality"
},
  "geometry": {"coordinates":[64.58754999999999,34.52881],"type":"Point"}
}