{
  "type": "Feature",
  "properties": {
    "gn:admin1_code":"13",
    "gn:admin2_code":"101.0",
    "gn:asciiname":"Qal'ah-ye Abdullah",
    "gn:country_code":"AF",
    "gn:dem":1801,
    "gn:feature_class":"P",
    "gn:feature_code":"PPL",
    "gn:name":"Qal\u2018ah-ye Abdull\u0101h",
    "gn:population":0,
    "gn:timezone":"Asia/Kabul",
    "iso:country":"AF",
    "name:und_x_variant":[
        "Qal\u2018ah-ye Abdull\u0101h",
        "\u0642\u0644\u0639\u0647 \u0627\u0628\u062f\u0627\u0644\u0644\u0647"
    ],
    "wof:name":"Qal'ah-ye Abdullah",
    "wof:placetype":"locality"
},
  "geometry": {"coordinates":[69.18933,34.50362],"type":"Point"}
}