{
  "type": "Feature",
  "properties": {
    "gn:admin1_code":"41",
    "gn:admin2_code":"3407",
    "gn:asciiname":"Kalan Qol",
    "gn:country_code":"AF",
    "gn:dem":2628,
    "gn:feature_class":"P",
    "gn:feature_code":"PPL",
    "gn:name":"Kal\u0101n Q\u014dl",
    "gn:population":0,
    "gn:timezone":"Asia/Kabul",
    "iso:country":"AF",
    "name:und_x_variant":[
        "Kal\u0101nq\u014dl",
        "Kal\u0101n Q\u014dl",
        "Kal\u0101nqowl",
        "\u06a9\u0644\u0627\u0646 \u0642\u0648\u0644"
    ],
    "wof:name":"Kalan Qol",
    "wof:placetype":"locality"
},
  "geometry": {"coordinates":[66.81344,33.88806],"type":"Point"}
}