{
  "type": "Feature",
  "properties": {
    "gn:admin1_code":"2",
    "gn:admin2_code":"1903.0",
    "gn:asciiname":"Chahak",
    "gn:country_code":"AF",
    "gn:dem":2019,
    "gn:feature_class":"P",
    "gn:feature_code":"PPL",
    "gn:name":"Ch\u0101hak",
    "gn:population":0,
    "gn:timezone":"Asia/Kabul",
    "iso:country":"AF",
    "name:und_x_variant":[
        "\u010c\u0101hak",
        "Chakhak",
        "Ch\u0101hak",
        "\u0686\u0627\u0647\u06a9"
    ],
    "wof:name":"Chahak",
    "wof:placetype":"locality"
},
  "geometry": {"coordinates":[63.91883000000001,34.74528],"type":"Point"}
}