{
  "type": "Feature",
  "properties": {
    "gn:admin1_code":"3",
    "gn:admin2_code":"1303.0",
    "gn:asciiname":"Pashimandara",
    "gn:country_code":"AF",
    "gn:dem":689,
    "gn:feature_class":"P",
    "gn:feature_code":"PPL",
    "gn:name":"Pashimandara",
    "gn:population":0,
    "gn:timezone":"Asia/Kabul",
    "iso:country":"AF",
    "wof:name":"Pashimandara",
    "wof:placetype":"locality"
},
  "geometry": {"coordinates":[68.52417,35.95333],"type":"Point"}
}