{
  "type": "Feature",
  "properties": {
    "gn:admin1_code":"19",
    "gn:admin2_code":"2204",
    "gn:asciiname":"Mulla Rasul",
    "gn:country_code":"AF",
    "gn:dem":482,
    "gn:feature_class":"P",
    "gn:feature_code":"PPL",
    "gn:name":"Mull\u0101 Ras\u016bl",
    "gn:population":0,
    "gn:timezone":"Asia/Kabul",
    "iso:country":"AF",
    "name:und_x_variant":[
        "Mull\u0101 \u1e5eas\u016bl",
        "Mull\u0101 Ras\u016bl",
        "\u0645\u0644\u0627 \u0631\u0633\u0648\u0644",
        "Moll\u0101 Ras\u016bl"
    ],
    "wof:name":"Mulla Rasul",
    "wof:placetype":"locality"
},
  "geometry": {"coordinates":[62.08561,31.21996],"type":"Point"}
}