{
  "type": "Feature",
  "properties": {
    "gn:admin1_code":"08",
    "gn:admin2_code":"607",
    "gn:asciiname":"Tamqol",
    "gn:country_code":"AF",
    "gn:dem":2812,
    "gn:feature_class":"P",
    "gn:feature_code":"PPL",
    "gn:name":"T\u0101mq\u014dl",
    "gn:population":0,
    "gn:timezone":"Asia/Kabul",
    "iso:country":"AF",
    "name:fas_x_preferred":[
        "\u062a\u0627\u0645 \u0642\u0648\u0644"
    ],
    "name:rus_x_preferred":[
        "\u0422\u0430\u043c\u043a\u0443\u043b\u044c"
    ],
    "name:und_x_variant":[
        "Tamkul\u2019",
        "T\u0101mq\u014dl",
        "T\u0101mqowl",
        "\u062a\u0627\u0645\u0642\u0648\u0644",
        "\u062a\u0627\u0645 \u0642\u0648\u0644"
    ],
    "wof:name":"Tamqol",
    "wof:placetype":"locality"
},
  "geometry": {"coordinates":[67.6283,33.09979000000001],"type":"Point"}
}