{
  "type": "Feature",
  "properties": {
    "gn:admin1_code":"13",
    "gn:admin2_code":"101.0",
    "gn:asciiname":"Qal'ah-ye Logari",
    "gn:country_code":"AF",
    "gn:dem":1834,
    "gn:feature_class":"P",
    "gn:feature_code":"PPL",
    "gn:name":"Qal\u2018ah-ye L\u014dgar\u012b",
    "gn:population":0,
    "gn:timezone":"Asia/Kabul",
    "iso:country":"AF",
    "name:und_x_variant":[
        "Kalalogari",
        "Qal\u2018eh L\u014dga\u1e5fi",
        "Qal\u2018eh-ye L\u014dgari",
        "Qal\u2018eh-ye Lowgar\u012b",
        "Qal\u2018ah-ye L\u014dgar\u012b",
        "\u0642\u0644\u0639\u0647 \u0644\u0648\u06af\u0631\u06cc"
    ],
    "wof:name":"Qal'ah-ye Logari",
    "wof:placetype":"locality"
},
  "geometry": {"coordinates":[69.13298,34.44197],"type":"Point"}
}