{
  "type": "Feature",
  "properties": {
    "gn:admin1_code":"23",
    "gn:admin2_code":"2413.0",
    "gn:asciiname":"Abdul Baqi Khan Kelay",
    "gn:country_code":"AF",
    "gn:dem":1837,
    "gn:feature_class":"P",
    "gn:feature_code":"PPL",
    "gn:name":"Abdul B\u0101q\u012b Kh\u0101n K\u00ealay",
    "gn:population":0,
    "gn:timezone":"Asia/Kabul",
    "iso:country":"AF",
    "name:rus_x_preferred":[
        "Abdul\u2019bakikhan-Kalay"
    ],
    "name:und_x_variant":[
        "Ab\u1e0ful B\u0101qikh\u0101n Kalay",
        "Abdul B\u0101q\u012b Kh\u0101n K\u00ealay",
        "Abdol B\u0101q\u012bkh\u0101n Kalay",
        "\u0639\u0628\u062f\u0644 \u0628\u0627\u0642\u06cc \u062e\u0627\u0646 \u06a9\u0644\u06cc"
    ],
    "wof:name":"Abdul Baqi Khan Kelay",
    "wof:placetype":"locality"
},
  "geometry": {"coordinates":[67.02239,31.47858],"type":"Point"}
}