{
  "type": "Feature",
  "properties": {
    "gn:admin1_code":"36",
    "gn:admin2_code":"703.0",
    "gn:asciiname":"Lambali Kot",
    "gn:country_code":"AF",
    "gn:dem":2426,
    "gn:feature_class":"P",
    "gn:feature_code":"PPL",
    "gn:name":"Lambal\u012b K\u014d\u1e6f",
    "gn:population":0,
    "gn:timezone":"Asia/Kabul",
    "iso:country":"AF",
    "name:fas_x_preferred":[
        "\u0644\u0645\u0628\u0644\u06cc \u0643\u0648\u062a"
    ],
    "name:und_x_variant":[
        "Lambalikot",
        "Lambali K\u014dt",
        "Lambali Kowt",
        "Lambal\u012b K\u014d\u1e6f",
        "\u0644\u0645\u0628\u0644\u06cc \u06a9\u0648\u067c"
    ],
    "wof:name":"Lambali Kot",
    "wof:placetype":"locality"
},
  "geometry": {"coordinates":[69.36771,33.43660999999999],"type":"Point"}
}