{
  "type": "Feature",
  "properties": {
    "gn:admin1_code":"9",
    "gn:admin2_code":"2701.0",
    "gn:asciiname":"Chargan",
    "gn:country_code":"AF",
    "gn:dem":2471,
    "gn:feature_class":"P",
    "gn:feature_code":"PPL",
    "gn:name":"Ch\u0101rg\u0101n",
    "gn:population":0,
    "gn:timezone":"Asia/Kabul",
    "iso:country":"AF",
    "name:und_x_variant":[
        "C\u0101\u1e5fg\u0101n",
        "Ch\u0101rg\u0101n",
        "\u0686\u0627\u0631\u06af\u0627\u0646"
    ],
    "wof:name":"Chargan",
    "wof:placetype":"locality"
},
  "geometry": {"coordinates":[65.84645,35.03558],"type":"Point"}
}