{
  "type": "Feature",
  "properties": {
    "gn:admin1_code":"41",
    "gn:admin2_code":"3405",
    "gn:asciiname":"Sar-e Bayri",
    "gn:country_code":"AF",
    "gn:dem":2147,
    "gn:feature_class":"P",
    "gn:feature_code":"PPL",
    "gn:name":"Sar-e Bayr\u012b",
    "gn:population":0,
    "gn:timezone":"Asia/Kabul",
    "iso:country":"AF",
    "name:und_x_variant":[
        "Sar-e Bayr\u012b",
        "\u0633\u0631 \u0628\u06cc\u0631\u06cc",
        "Sar-e B\u0113\u1e5fi"
    ],
    "wof:name":"Sar-e Bayri",
    "wof:placetype":"locality"
},
  "geometry": {"coordinates":[65.80683000000001,33.93745999999999],"type":"Point"}
}