{
  "type": "Feature",
  "properties": {
    "gn:admin1_code":"8",
    "gn:admin2_code":"611.0",
    "gn:asciiname":"Dalani",
    "gn:country_code":"AF",
    "gn:dem":2031,
    "gn:feature_class":"P",
    "gn:feature_code":"PPL",
    "gn:name":"D\u0101l\u0101n\u012b",
    "gn:population":0,
    "gn:timezone":"Asia/Kabul",
    "iso:country":"AF",
    "name:fas_x_preferred":[
        "D\u0101l\u0101n\u012b"
    ],
    "name:fas_x_variant":[
        "\u062f\u0627\u0644\u0627\u0646\u06cc"
    ],
    "name:und_x_variant":[
        "\u062f\u0627\u0644\u0627\u0646\u06cc"
    ],
    "wof:name":"Dalani",
    "wof:placetype":"locality"
},
  "geometry": {"coordinates":[68.01961999999999,32.97226],"type":"Point"}
}