{
  "type": "Feature",
  "properties": {
    "gn:admin1_code":"35",
    "gn:admin2_code":"903.0",
    "gn:asciiname":"Chitila",
    "gn:country_code":"AF",
    "gn:dem":1536,
    "gn:feature_class":"P",
    "gn:feature_code":"PPL",
    "gn:name":"Chitila",
    "gn:population":0,
    "gn:timezone":"Asia/Kabul",
    "iso:country":"AF",
    "name:azb_x_preferred":[
        "\u06a9\u06cc\u062a\u06cc\u0644\u0647"
    ],
    "name:ceb_x_preferred":[
        "Ora\u0219 Chitila"
    ],
    "name:deu_x_preferred":[
        "Chitila"
    ],
    "name:fas_x_preferred":[
        "\u06a9\u06cc\u062a\u06cc\u0644\u0647"
    ],
    "name:fra_x_preferred":[
        "Chitila"
    ],
    "name:hun_x_preferred":[
        "Chitila"
    ],
    "name:ind_x_preferred":[
        "Chitila"
    ],
    "name:ita_x_preferred":[
        "Chitila"
    ],
    "name:msa_x_preferred":[
        "Chitila"
    ],
    "name:nld_x_preferred":[
        "Chitila"
    ],
    "name:pol_x_preferred":[
        "Chitila"
    ],
    "name:ron_x_preferred":[
        "Chitila"
    ],
    "name:rus_x_preferred":[
        "\u041a\u0438\u0442\u0438\u043b\u0430"
    ],
    "name:spa_x_preferred":[
        "Chitila"
    ],
    "name:srp_x_preferred":[
        "\u041e\u043f\u0448\u0442\u0438\u043d\u0430 \u041a\u0438\u0442\u0438\u043b\u0430"
    ],
    "name:ukr_x_preferred":[
        "\u041a\u0456\u0442\u0456\u043b\u0430"
    ],
    "name:und_x_variant":[
        "\u010cetel\u0101",
        "Chetel\u0101",
        "Ch\u012bt\u012bl\u0101",
        "\u0686\u06cc\u062a\u06cc\u0644\u0627"
    ],
    "name:vie_x_preferred":[
        "Chitila"
    ],
    "name:zho_x_preferred":[
        "\u57fa\u8482\u62c9"
    ],
    "wof:name":"Chitila",
    "wof:placetype":"locality"
},
  "geometry": {"coordinates":[70.4832,34.84078],"type":"Point"}
}