{
  "type": "Feature",
  "properties": {
    "gn:admin1_code":"35",
    "gn:admin2_code":"903.0",
    "gn:asciiname":"Chitila",
    "gn:country_code":"AF",
    "gn:dem":1536,
    "gn:feature_class":"P",
    "gn:feature_code":"PPL",
    "gn:name":"Chitila",
    "gn:population":0,
    "gn:timezone":"Asia/Kabul",
    "iso:country":"AF",
    "name:und_x_variant":[
        "\u010cetel\u0101",
        "Chitila",
        "Chetel\u0101",
        "Ch\u012bt\u012bl\u0101",
        "\u0686\u06cc\u062a\u06cc\u0644\u0627"
    ],
    "wof:name":"Chitila",
    "wof:placetype":"locality"
},
  "geometry": {"coordinates":[70.4832,34.84078],"type":"Point"}
}