{
  "type": "Feature",
  "properties": {
    "gn:admin1_code":"29",
    "gn:admin2_code":"2905",
    "gn:asciiname":"Khusa Tsah",
    "gn:country_code":"AF",
    "gn:dem":2149,
    "gn:feature_class":"P",
    "gn:feature_code":"PPL",
    "gn:name":"Kh\u016bs\u0101 Ts\u0101h",
    "gn:population":0,
    "gn:timezone":"Asia/Kabul",
    "iso:country":"AF",
    "name:und_x_variant":[
        "Khusachakh",
        "Kh\u016bs\u0101 C\u0101",
        "Kh\u016bs\u0101 Ts\u0101h",
        "Kh\u016bs\u0101 Ts\u0101",
        "\u062e\u0648\u0633\u0627 \u0685\u0627\u0647"
    ],
    "wof:name":"Khusa Tsah",
    "wof:placetype":"locality"
},
  "geometry": {"coordinates":[68.90384,31.96272],"type":"Point"}
}