{
  "type": "Feature",
  "properties": {
    "gn:admin1_code":"8",
    "gn:admin2_code":"607.0",
    "gn:asciiname":"Busid",
    "gn:country_code":"AF",
    "gn:dem":2512,
    "gn:feature_class":"P",
    "gn:feature_code":"PPL",
    "gn:name":"B\u016bs\u012bd",
    "gn:population":0,
    "gn:timezone":"Asia/Kabul",
    "iso:country":"AF",
    "name:fas_x_preferred":[
        "\u0628\u0648\u0633\u064a\u062f"
    ],
    "name:rus_x_preferred":[
        "\u0411\u0443\u0441\u0438\u0434"
    ],
    "name:und_x_variant":[
        "B\u016bs\u012bd",
        "\u0628\u0648\u0633\u06cc\u062f"
    ],
    "wof:name":"Busid",
    "wof:placetype":"locality"
},
  "geometry": {"coordinates":[67.55739,33.12422],"type":"Point"}
}