{
  "type": "Feature",
  "properties": {
    "gn:admin1_code":"01",
    "gn:admin2_code":"1121.0",
    "gn:asciiname":"Hujmak",
    "gn:country_code":"AF",
    "gn:dem":1819,
    "gn:feature_class":"P",
    "gn:feature_code":"PPL",
    "gn:name":"\u1e28ujmak",
    "gn:population":0,
    "gn:timezone":"Asia/Kabul",
    "iso:country":"AF",
    "name:und_x_variant":[
        "Huimak",
        "\u1e28ujmak",
        "\u062d\u062c\u0645\u06a9"
    ],
    "wof:name":"Hujmak",
    "wof:placetype":"locality"
},
  "geometry": {"coordinates":[70.55719000000001,38.14108],"type":"Point"}
}