{
  "type": "Feature",
  "properties": {
    "gn:admin1_code":"10",
    "gn:admin2_code":"2306.0",
    "gn:asciiname":"Mutah",
    "gn:country_code":"AF",
    "gn:dem":1321,
    "gn:feature_class":"P",
    "gn:feature_code":"PPL",
    "gn:name":"M\u016btah",
    "gn:population":0,
    "gn:timezone":"Asia/Kabul",
    "iso:country":"AF",
    "name:und_x_variant":[
        "Muta",
        "M\u016bta",
        "M\u016btah",
        "\u0645\u0648\u062a\u0647"
    ],
    "wof:name":"Mutah",
    "wof:placetype":"locality"
},
  "geometry": {"coordinates":[64.48736,32.52993],"type":"Point"}
}