{
  "type": "Feature",
  "properties": {
    "gn:admin1_code":"10",
    "gn:admin2_code":"2312.0",
    "gn:asciiname":"Potay",
    "gn:country_code":"AF",
    "gn:dem":910,
    "gn:feature_class":"P",
    "gn:feature_code":"PPL",
    "gn:name":"Potay",
    "gn:population":0,
    "gn:timezone":"Asia/Kabul",
    "iso:country":"AF",
    "name:und_x_variant":[
        "P\u014dtay",
        "Potay",
        "P\u014d\u1e6fa\u012b",
        "\u067e\u0648\u067c\u06cc",
        "P\u016btay"
    ],
    "wof:name":"Potay",
    "wof:placetype":"locality"
},
  "geometry": {"coordinates":[64.95085999999999,32.1542],"type":"Point"}
}