{
  "type": "Feature",
  "properties": {
    "gn:admin1_code":"28",
    "gn:admin2_code":"2509.0",
    "gn:asciiname":"Daday",
    "gn:country_code":"AF",
    "gn:dem":2358,
    "gn:feature_class":"P",
    "gn:feature_code":"PPL",
    "gn:name":"D\u0101day",
    "gn:population":0,
    "gn:timezone":"Asia/Kabul",
    "iso:country":"AF",
    "name:und_x_variant":[
        "D\u0101day",
        "\u062f\u0627\u062f\u06cc"
    ],
    "wof:name":"Daday",
    "wof:placetype":"locality"
},
  "geometry": {"coordinates":[67.84222,31.94755],"type":"Point"}
}