{
  "type": "Feature",
  "properties": {
    "gn:admin1_code":"28",
    "gn:admin2_code":"2509.0",
    "gn:asciiname":"Daday",
    "gn:country_code":"AF",
    "gn:dem":2358,
    "gn:feature_class":"P",
    "gn:feature_code":"PPL",
    "gn:name":"D\u0101day",
    "gn:population":0,
    "gn:timezone":"Asia/Kabul",
    "iso:country":"AF",
    "name:aze_x_preferred":[
        "Daday"
    ],
    "name:ceb_x_preferred":[
        "Daday \u0130l\u00e7esi"
    ],
    "name:deu_x_preferred":[
        "Daday"
    ],
    "name:fra_x_preferred":[
        "Daday"
    ],
    "name:mrj_x_preferred":[
        "\u0414\u0430\u0434\u0430\u0439"
    ],
    "name:msa_x_preferred":[
        "Daday"
    ],
    "name:nld_x_preferred":[
        "Daday"
    ],
    "name:nor_x_preferred":[
        "Daday"
    ],
    "name:pnb_x_preferred":[
        "\u0636\u0644\u0639 \u062f\u0627\u062f\u06d2"
    ],
    "name:swa_x_preferred":[
        "Daday"
    ],
    "name:tur_x_preferred":[
        "Daday"
    ],
    "name:und_x_variant":[
        "D\u0101day",
        "\u062f\u0627\u062f\u06cc"
    ],
    "name:urd_x_preferred":[
        "\u062f\u0627\u062f\u06d2"
    ],
    "name:vie_x_preferred":[
        "Daday"
    ],
    "wof:name":"Daday",
    "wof:placetype":"locality"
},
  "geometry": {"coordinates":[67.84222,31.94755],"type":"Point"}
}