{
  "type": "Feature",
  "properties": {
    "gn:admin1_code":"27",
    "gn:admin2_code":"404",
    "gn:asciiname":"Irgin",
    "gn:country_code":"AF",
    "gn:dem":3033,
    "gn:feature_class":"P",
    "gn:feature_code":"PPL",
    "gn:name":"Irg\u012bn",
    "gn:population":0,
    "gn:timezone":"Asia/Kabul",
    "iso:country":"AF",
    "name:fas_x_preferred":[
        "\u0627\u0631\u06af\u064a\u0646"
    ],
    "name:rus_x_preferred":[
        "\u0418\u0440\u0433\u0438\u043d"
    ],
    "name:und_x_variant":[
        "Erg\u012bn",
        "Irg\u012bn"
    ],
    "wof:name":"Irgin",
    "wof:placetype":"locality"
},
  "geometry": {"coordinates":[67.40444000000001,34.58565],"type":"Point"}
}