{
  "type": "Feature",
  "properties": {
    "gn:admin1_code":"23",
    "gn:admin2_code":"2411.0",
    "gn:asciiname":"Mowlazai",
    "gn:country_code":"AF",
    "gn:dem":1206,
    "gn:feature_class":"P",
    "gn:feature_code":"PPL",
    "gn:name":"Mowl\u0101za\u012b",
    "gn:population":0,
    "gn:timezone":"Asia/Kabul",
    "iso:country":"AF",
    "name:fas_x_preferred":[
        "\u0645\u0648\u0644\u0627\u0632\u06cc"
    ],
    "name:und_x_variant":[
        "Maulazay",
        "Mawl\u0101zay",
        "Mowl\u0101za\u012b"
    ],
    "wof:name":"Mowlazai",
    "wof:placetype":"locality"
},
  "geometry": {"coordinates":[66.15841,31.20321],"type":"Point"}
}