{
  "type": "Feature",
  "properties": {
    "gn:admin1_code":"9",
    "gn:admin2_code":"2705.0",
    "gn:asciiname":"Ghaybayliha",
    "gn:country_code":"AF",
    "gn:dem":2287,
    "gn:feature_class":"P",
    "gn:feature_code":"PPL",
    "gn:name":"Ghaybayl\u012bh\u0101",
    "gn:population":0,
    "gn:timezone":"Asia/Kabul",
    "iso:country":"AF",
    "name:und_x_variant":[
        "Gaybelikha",
        "Ghaybayl\u012bh\u0101",
        "\u063a\u06cc\u0628\u06cc\u0644\u064a\u0647\u0627",
        "Ghayb\u0113l\u012bh\u0101"
    ],
    "wof:name":"Ghaybayliha",
    "wof:placetype":"locality"
},
  "geometry": {"coordinates":[64.34824999999999,33.17335],"type":"Point"}
}