{
  "type": "Feature",
  "properties": {
    "gn:admin1_code":"13",
    "gn:admin2_code":"102.0",
    "gn:asciiname":"Qal'ah-ye Sharaf",
    "gn:country_code":"AF",
    "gn:dem":1768,
    "gn:feature_class":"P",
    "gn:feature_code":"PPL",
    "gn:name":"Qal\u2018ah-ye Sharaf",
    "gn:population":0,
    "gn:timezone":"Asia/Kabul",
    "iso:country":"AF",
    "name:und_x_variant":[
        "Qal\u2018ah-ye Sharaf",
        "\u0642\u0644\u0639\u0647 \u0634\u0631\u0641"
    ],
    "wof:name":"Qal'ah-ye Sharaf",
    "wof:placetype":"locality"
},
  "geometry": {"coordinates":[69.24134000000001,34.61084],"type":"Point"}
}