{
  "type": "Feature",
  "properties": {
    "gn:admin1_code":"09",
    "gn:admin2_code":"2701",
    "gn:asciiname":"Shakhalmand",
    "gn:country_code":"AF",
    "gn:dem":2396,
    "gn:feature_class":"P",
    "gn:feature_code":"PPL",
    "gn:name":"Shakhalmand",
    "gn:population":0,
    "gn:timezone":"Asia/Kabul",
    "iso:country":"AF",
    "name:und_x_variant":[
        "S\u0304akhalman\u1e0f",
        "S\u0304aykh A\u1e96ma\u1e0f",
        "Shakhalmand",
        "\u0634\u062e\u0644\u0645\u0646\u062f",
        "Shaykh A\u1e29mad",
        "\u0634\u06cc\u062e \u0627\u062d\u0645\u062f"
    ],
    "wof:name":"Shakhalmand",
    "wof:placetype":"locality"
},
  "geometry": {"coordinates":[65.29788000000001,34.47198],"type":"Point"}
}