{
  "type": "Feature",
  "properties": {
    "gn:admin1_code":"06",
    "gn:admin2_code":"2104",
    "gn:asciiname":"Sanjit",
    "gn:country_code":"AF",
    "gn:dem":1808,
    "gn:feature_class":"P",
    "gn:feature_code":"PPL",
    "gn:name":"Sanjit",
    "gn:population":0,
    "gn:timezone":"Asia/Kabul",
    "iso:country":"AF",
    "name:und_x_variant":[
        "\u0633\u0646\u062c\u062a",
        "Sanjet"
    ],
    "wof:name":"Sanjit",
    "wof:placetype":"locality"
},
  "geometry": {"coordinates":[63.84371,33.32945],"type":"Point"}
}