{
  "type": "Feature",
  "properties": {
    "gn:admin1_code":"23",
    "gn:admin2_code":"2413.0",
    "gn:asciiname":"Chinah",
    "gn:country_code":"AF",
    "gn:dem":1917,
    "gn:feature_class":"P",
    "gn:feature_code":"PPL",
    "gn:name":"Ch\u012bnah",
    "gn:population":0,
    "gn:timezone":"Asia/Kabul",
    "iso:country":"AF",
    "name:und_x_variant":[
        "China",
        "\u010cina",
        "Ch\u012bnah",
        "Chinah",
        "\u0686\u06cc\u0646\u0647"
    ],
    "wof:name":"Chinah",
    "wof:placetype":"locality"
},
  "geometry": {"coordinates":[67.22071,31.38531],"type":"Point"}
}