{
  "type": "Feature",
  "properties": {
    "gn:admin1_code":"07",
    "gn:admin2_code":"1812",
    "gn:asciiname":"Towachi",
    "gn:country_code":"AF",
    "gn:dem":308,
    "gn:feature_class":"P",
    "gn:feature_code":"PPL",
    "gn:name":"Towach\u012b",
    "gn:population":0,
    "gn:timezone":"Asia/Kabul",
    "iso:country":"AF",
    "name:und_x_variant":[
        "Towach\u012b",
        "\u062a\u0648\u0686\u06cc",
        "Tawachi",
        "Tawach\u012b"
    ],
    "wof:name":"Towachi",
    "wof:placetype":"locality"
},
  "geometry": {"coordinates":[65.14293000000001,36.93611],"type":"Point"}
}