{
  "type": "Feature",
  "properties": {
    "gn:admin1_code":"28",
    "gn:admin2_code":"2507",
    "gn:asciiname":"Gira Bandah",
    "gn:country_code":"AF",
    "gn:dem":2141,
    "gn:feature_class":"P",
    "gn:feature_code":"PPL",
    "gn:name":"Gi\u1e5f\u0101 Bandah",
    "gn:population":0,
    "gn:timezone":"Asia/Kabul",
    "iso:country":"AF",
    "name:fas_x_preferred":[
        "\u06af\u0631\u0627\u0628\u0646\u062f\u0647"
    ],
    "name:und_x_variant":[
        "Ger\u0101ban\u1e0fa",
        "Girabanda",
        "Gi\u1e5f\u0101 Bandah",
        "\u06af\u0631\u0627 \u0628\u0627\u0646\u062f\u0647",
        "Ge\u1e5f\u0101bandah",
        "\u06af\u0693\u0627\u0628\u0646\u062f\u0647"
    ],
    "wof:name":"Gira Bandah",
    "wof:placetype":"locality"
},
  "geometry": {"coordinates":[67.13638,31.98855],"type":"Point"}
}