{
  "type": "Feature",
  "properties": {
    "gn:admin1_code":"07",
    "gn:admin2_code":"1804",
    "gn:asciiname":"Tah-e Qol",
    "gn:country_code":"AF",
    "gn:dem":2011,
    "gn:feature_class":"P",
    "gn:feature_code":"PPL",
    "gn:name":"Tah-e Q\u014dl",
    "gn:population":0,
    "gn:timezone":"Asia/Kabul",
    "iso:country":"AF",
    "name:und_x_variant":[
        "Tah-i-Q\u014dl",
        "Tah-e Qowl",
        "Tah-e Q\u014dl",
        "\u062a\u0647 \u0642\u0648\u0644"
    ],
    "wof:name":"Tah-e Qol",
    "wof:placetype":"locality"
},
  "geometry": {"coordinates":[64.51210999999999,35.52332],"type":"Point"}
}