{
  "type": "Feature",
  "properties": {
    "gn:admin1_code":"32",
    "gn:admin2_code":"1504",
    "gn:asciiname":"Guzar",
    "gn:country_code":"AF",
    "gn:dem":1450,
    "gn:feature_class":"P",
    "gn:feature_code":"PPL",
    "gn:name":"Guz\u0304ar",
    "gn:population":0,
    "gn:timezone":"Asia/Kabul",
    "iso:country":"AF",
    "name:kir_x_preferred":[
        "\u0413\u0443\u0437\u0430\u0440"
    ],
    "name:und_x_variant":[
        "Goz\u0304ar",
        "Guz\u0304ar",
        "\u06af\u0630\u0631"
    ],
    "name:uzb_x_preferred":[
        "Guzar"
    ],
    "wof:name":"Guzar",
    "wof:placetype":"locality"
},
  "geometry": {"coordinates":[67.33166999999999,36.13262],"type":"Point"}
}