{
  "type": "Feature",
  "properties": {
    "gn:admin1_code":"05",
    "gn:admin2_code":"2804",
    "gn:asciiname":"Shatu",
    "gn:country_code":"AF",
    "gn:dem":3003,
    "gn:feature_class":"P",
    "gn:feature_code":"PPL",
    "gn:name":"Shatu",
    "gn:population":0,
    "gn:timezone":"Asia/Kabul",
    "iso:country":"AF",
    "name:ceb_x_preferred":[
        "Shatu"
    ],
    "name:swe_x_preferred":[
        "Shatu"
    ],
    "name:und_x_variant":[
        "S\u0101t\u016b",
        "Sh\u0101htu",
        "Shatu",
        "Sh\u0101t\u016b",
        "Sh\u0101tow",
        "\u0633\u0627\u062a\u0648"
    ],
    "name:zho_x_preferred":[
        "\u6c99\u571f\u9547"
    ],
    "wof:name":"Shatu",
    "wof:placetype":"locality"
},
  "geometry": {"coordinates":[66.96356999999999,34.59058],"type":"Point"}
}