{
  "type": "Feature",
  "properties": {
    "gn:admin1_code":"6",
    "gn:admin2_code":"2104.0",
    "gn:asciiname":"Khurmah Jan",
    "gn:country_code":"AF",
    "gn:dem":2020,
    "gn:feature_class":"P",
    "gn:feature_code":"PPL",
    "gn:name":"Khu\u1e5fmah J\u0101n",
    "gn:population":0,
    "gn:timezone":"Asia/Kabul",
    "iso:country":"AF",
    "name:und_x_variant":[
        "Khorma J\u0101n",
        "Khu\u1e5fmah J\u0101n",
        "\u062e\u0693\u0645\u0647 \u062c\u0627\u0646",
        "Khormah J\u0101n"
    ],
    "wof:name":"Khurmah Jan",
    "wof:placetype":"locality"
},
  "geometry": {"coordinates":[63.92499,32.97645],"type":"Point"}
}