{
  "type": "Feature",
  "properties": {
    "gn:admin1_code":"28",
    "gn:admin2_code":"2506",
    "gn:asciiname":"Shahi Kelay",
    "gn:country_code":"AF",
    "gn:dem":1323,
    "gn:feature_class":"P",
    "gn:feature_code":"PPL",
    "gn:name":"Sh\u0101h\u012b K\u00ealay",
    "gn:population":0,
    "gn:timezone":"Asia/Kabul",
    "iso:country":"AF",
    "name:und_x_variant":[
        "\u0160\u0101hi Kalay",
        "Shakhkalay",
        "Sh\u0101h Kalay",
        "\u0634\u0627\u0647\u06cc \u06a9\u0644\u06cc",
        "Sh\u0101hi Kalay",
        "Sh\u0101h\u012b K\u00ealay"
    ],
    "wof:name":"Shahi Kelay",
    "wof:placetype":"locality"
},
  "geometry": {"coordinates":[66.46972,31.85155],"type":"Point"}
}