{
  "type": "Feature",
  "properties": {
    "gn:admin1_code":"13",
    "gn:admin2_code":"111",
    "gn:asciiname":"Khak-e Jabar-e Bala",
    "gn:country_code":"AF",
    "gn:dem":2308,
    "gn:feature_class":"P",
    "gn:feature_code":"PPL",
    "gn:name":"Kh\u0101k-e Jab\u0101r-e B\u0101l\u0101",
    "gn:population":0,
    "gn:timezone":"Asia/Kabul",
    "iso:country":"AF",
    "name:fas_x_preferred":[
        "\u062e\u0627\u06a9\u0654\u0654 \u062c\u0628\u0627\u0631 \u0628\u0627\u0644\u0627"
    ],
    "name:und_x_variant":[
        "Khaki-Dzhabar-Bala",
        "Kh\u0101ke Jab\u0101\u1e5f B\u0101l\u0101",
        "Kh\u0101k-e Jab\u0101r B\u0101l\u0101",
        "Kh\u0101k-e Jabb\u0101r B\u0101l\u0101",
        "Kh\u0101k-e Jab\u0101r-e B\u0101l\u0101",
        "\u062e\u0627\u06a9 \u062c\u0628\u0627\u0631 \u0628\u0627\u0644\u0627"
    ],
    "wof:name":"Khak-e Jabar-e Bala",
    "wof:placetype":"locality"
},
  "geometry": {"coordinates":[69.50471999999999,34.40037],"type":"Point"}
}