{
  "type": "Feature",
  "properties": {
    "gn:admin1_code":"08",
    "gn:admin2_code":"607",
    "gn:asciiname":"Sherabad",
    "gn:country_code":"AF",
    "gn:dem":2833,
    "gn:feature_class":"P",
    "gn:feature_code":"PPL",
    "gn:name":"Sh\u0113r\u0101b\u0101d",
    "gn:population":0,
    "gn:timezone":"Asia/Kabul",
    "iso:country":"AF",
    "name:rus_x_preferred":[
        "\u0428\u0435\u0440\u0430\u0431\u0430\u0434"
    ],
    "name:und_x_variant":[
        "\u0160\u0113r\u0101b\u0101d",
        "Sherabad",
        "Sh\u012br\u0101b\u0101d",
        "Shayr\u0101b\u0101d",
        "\u0634\u06cc\u0631 \u0622\u0628\u0627\u062f",
        "Sh\u0113r\u0101b\u0101d"
    ],
    "wof:name":"Sherabad",
    "wof:placetype":"locality"
},
  "geometry": {"coordinates":[67.58225999999999,33.25025],"type":"Point"}
}