{
  "type": "Feature",
  "properties": {
    "gn:admin1_code":"30",
    "gn:admin2_code":"1605",
    "gn:asciiname":"Khushilabad",
    "gn:country_code":"AF",
    "gn:dem":312,
    "gn:feature_class":"P",
    "gn:feature_code":"PPL",
    "gn:name":"Khush\u012bl\u0101b\u0101d",
    "gn:population":0,
    "gn:timezone":"Asia/Kabul",
    "iso:country":"AF",
    "name:fas_x_preferred":[
        "\u062e\u0634\u064a\u0644 \u0622\u0628\u0627\u062f"
    ],
    "name:rus_x_preferred":[
        "\u0425\u043e\u0448\u0435\u043b\u0430\u0431\u0430\u0434"
    ],
    "name:und_x_variant":[
        "Khoshelabad",
        "Khosh\u012bl\u0101b\u0101d",
        "Khush\u012bl\u0101b\u0101d"
    ],
    "wof:name":"Khushilabad",
    "wof:placetype":"locality"
},
  "geometry": {"coordinates":[66.78706,36.9611],"type":"Point"}
}