{
  "type": "Feature",
  "properties": {
    "gn:admin1_code":"27",
    "gn:admin2_code":"403.0",
    "gn:asciiname":"Burjak",
    "gn:country_code":"AF",
    "gn:dem":3273,
    "gn:feature_class":"P",
    "gn:feature_code":"PPL",
    "gn:name":"Burjak",
    "gn:population":0,
    "gn:timezone":"Asia/Kabul",
    "iso:country":"AF",
    "name:und_x_variant":[
        "Bu\u1e5fjak",
        "Burdzhak",
        "Borjak",
        "Burjak",
        "\u0628\u0631\u062c\u06a9"
    ],
    "wof:name":"Burjak",
    "wof:placetype":"locality"
},
  "geometry": {"coordinates":[68.19738000000001,34.58896],"type":"Point"}
}