{
  "type": "Feature",
  "properties": {
    "gn:admin1_code":"01",
    "gn:admin2_code":"1117.0",
    "gn:asciiname":"Kishkyon",
    "gn:country_code":"AF",
    "gn:dem":1940,
    "gn:feature_class":"P",
    "gn:feature_code":"PPL",
    "gn:name":"Kishky\u014dn",
    "gn:population":0,
    "gn:timezone":"Asia/Kabul",
    "iso:country":"AF",
    "name:und_x_variant":[
        "Kisky\u014dn",
        "Kisky\u016bn",
        "Kishky\u014dn",
        "\u06a9\u0634\u06a9\u06cc\u0648\u0646"
    ],
    "wof:name":"Kishkyon",
    "wof:placetype":"locality"
},
  "geometry": {"coordinates":[71.02328,38.3979],"type":"Point"}
}