{
  "type": "Feature",
  "properties": {
    "gn:admin1_code":"39",
    "gn:admin2_code":"2604",
    "gn:asciiname":"Sekzi",
    "gn:country_code":"AF",
    "gn:dem":1153,
    "gn:feature_class":"P",
    "gn:feature_code":"PPL",
    "gn:name":"S\u00eakz\u012b",
    "gn:population":0,
    "gn:timezone":"Asia/Kabul",
    "iso:country":"AF",
    "name:und_x_variant":[
        "Sheykhz\u012b",
        "S\u00eakz\u012b",
        "\u0633\u06a9\u0632\u06cc",
        "S\u0113kzi"
    ],
    "wof:name":"Sekzi",
    "wof:placetype":"locality"
},
  "geometry": {"coordinates":[65.50757,33.02591],"type":"Point"}
}