{
  "type": "Feature",
  "properties": {
    "gn:admin1_code":"11",
    "gn:admin2_code":"2014",
    "gn:asciiname":"Qal'ah-ye Now",
    "gn:country_code":"AF",
    "gn:dem":1119,
    "gn:feature_class":"P",
    "gn:feature_code":"PPL",
    "gn:name":"Qal\u2018ah-ye Now",
    "gn:population":0,
    "gn:timezone":"Asia/Kabul",
    "iso:country":"AF",
    "name:und_x_variant":[
        "Qal\u2018a-i-naw",
        "Qal\u2018eh-ye Naw",
        "Qal\u2018eh-ye Now",
        "Qal\u2018ah-ye Now",
        "\u0642\u0644\u0639\u06c0 \u0646\u0648"
    ],
    "wof:name":"Qal'ah-ye Now",
    "wof:placetype":"locality"
},
  "geometry": {"coordinates":[61.96041,33.29828],"type":"Point"}
}