{
  "type": "Feature",
  "properties": {
    "gn:admin1_code":"27",
    "gn:admin2_code":"404",
    "gn:asciiname":"Ziaratak",
    "gn:country_code":"AF",
    "gn:dem":3104,
    "gn:feature_class":"P",
    "gn:feature_code":"PPL",
    "gn:name":"Z\u012b\u0101ratak",
    "gn:population":0,
    "gn:timezone":"Asia/Kabul",
    "iso:country":"AF",
    "name:und_x_variant":[
        "Zy\u0101\u1e5fatak",
        "Ziaratak",
        "Z\u012b\u0101ratak",
        "\u0632\u06cc\u0627\u0631\u062a\u06a9"
    ],
    "wof:name":"Ziaratak",
    "wof:placetype":"locality"
},
  "geometry": {"coordinates":[67.70480000000001,34.57091],"type":"Point"}
}