{
  "type": "Feature",
  "properties": {
    "gn:admin1_code":"23",
    "gn:admin2_code":"2412.0",
    "gn:asciiname":"Kar",
    "gn:country_code":"AF",
    "gn:dem":1663,
    "gn:feature_class":"P",
    "gn:feature_code":"PPL",
    "gn:name":"Kar",
    "gn:population":0,
    "gn:timezone":"Asia/Kabul",
    "iso:country":"AF",
    "name:und_x_variant":[
        "K\u0101\u1e5f",
        "K\u0101r",
        "\u06a9\u0627\u0693"
    ],
    "wof:name":"Kar",
    "wof:placetype":"locality"
},
  "geometry": {"coordinates":[66.67954,31.2636],"type":"Point"}
}