{
  "type": "Feature",
  "properties": {
    "gn:admin1_code":"27",
    "gn:admin2_code":"403.0",
    "gn:asciiname":"Dahan-e Bum",
    "gn:country_code":"AF",
    "gn:dem":2816,
    "gn:feature_class":"P",
    "gn:feature_code":"PPL",
    "gn:name":"Dahan-e B\u016bm",
    "gn:population":0,
    "gn:timezone":"Asia/Kabul",
    "iso:country":"AF",
    "name:und_x_variant":[
        "Dakhani-Bum",
        "Dahan-e B\u016bm",
        "\u062f\u0647\u0646 \u0628\u0648\u0645"
    ],
    "wof:name":"Dahan-e Bum",
    "wof:placetype":"locality"
},
  "geometry": {"coordinates":[68.26394999999999,34.66798],"type":"Point"}
}