{
  "type": "Feature",
  "properties": {
    "gn:admin1_code":"26",
    "gn:admin2_code":"1208.0",
    "gn:asciiname":"Kayshan",
    "gn:country_code":"AF",
    "gn:dem":1324,
    "gn:feature_class":"P",
    "gn:feature_code":"PPL",
    "gn:name":"Kaysh\u0101n",
    "gn:population":0,
    "gn:timezone":"Asia/Kabul",
    "iso:country":"AF",
    "name:und_x_variant":[
        "K\u0113\u0161\u0101n",
        "K\u0113sh\u0101n",
        "Kaysh\u0101n",
        "\u06a9\u06cc\u0634\u0627\u0646"
    ],
    "wof:name":"Kayshan",
    "wof:placetype":"locality"
},
  "geometry": {"coordinates":[69.83610999999999,37.26891],"type":"Point"}
}