{
  "type": "Feature",
  "properties": {
    "gn:admin1_code":"08",
    "gn:admin2_code":"612",
    "gn:asciiname":"Disi",
    "gn:country_code":"AF",
    "gn:dem":2338,
    "gn:feature_class":"P",
    "gn:feature_code":"PPL",
    "gn:name":"Disi",
    "gn:population":0,
    "gn:timezone":"Asia/Kabul",
    "iso:country":"AF",
    "name:bar_x_preferred":[
        "Disi"
    ],
    "name:ceb_x_preferred":[
        "Disi"
    ],
    "name:deu_x_preferred":[
        "Disi"
    ],
    "name:swe_x_preferred":[
        "Disi"
    ],
    "name:und_x_variant":[
        "\u062f\u06cc\u0633\u06cc",
        "D\u012bs\u012b"
    ],
    "wof:name":"Disi",
    "wof:placetype":"locality"
},
  "geometry": {"coordinates":[68.42415,33.02047],"type":"Point"}
}