{
  "type": "Feature",
  "properties": {
    "gn:admin1_code":"27",
    "gn:admin2_code":"403.0",
    "gn:asciiname":"Dahan-e Kafaran",
    "gn:country_code":"AF",
    "gn:dem":3290,
    "gn:feature_class":"P",
    "gn:feature_code":"PPL",
    "gn:name":"Dahan-e K\u0101far\u0101n",
    "gn:population":0,
    "gn:timezone":"Asia/Kabul",
    "iso:country":"AF",
    "name:und_x_variant":[
        "Dakhani-Kafaran",
        "Dahan-e K\u0101far\u0101n",
        "\u062f\u0647\u0646 \u06a9\u0627\u0641\u0631\u0627\u0646"
    ],
    "wof:name":"Dahan-e Kafaran",
    "wof:placetype":"locality"
},
  "geometry": {"coordinates":[67.98421999999999,34.52962],"type":"Point"}
}