{
  "type": "Feature",
  "properties": {
    "gn:gn_country":"AF",
    "gn:gn_fcode":"PPLA2",
    "gn:gn_pop":15967,
    "gn:population":15967,
    "iso:country":"AF",
    "name:eng_x_preferred":[
        "Shahrak"
    ],
    "name:msa_x_preferred":[
        "Shahrak"
    ],
    "name:nld_x_preferred":[
        "Shahrak"
    ],
    "name:rus_x_preferred":[
        "\u0428\u0430\u0445\u0440\u0430\u043a"
    ],
    "name:tgk_x_preferred":[
        "\u04b6\u0430\u043c\u043e\u0430\u0442\u0438 \u0428\u0430\u04b3\u0440\u0430\u043a"
    ],
    "name:unk_x_variant":[
        "Qal\u2018eh Shah\u0101rak"
    ],
    "name:urd_x_preferred":[
        "\u0634\u0627\u06c1\u0631\u06a9"
    ],
    "qs_pg:aaroncc":"AF",
    "qs_pg:gn_country":"AF",
    "qs_pg:gn_fcode":"PPLA2",
    "qs_pg:gn_pop":15967,
    "qs_pg:name":"Shahrak",
    "qs_pg:photos_9r":0,
    "qs_pg:photos_sr":0,
    "qs_pg:pop_sr":6,
    "qs_pg:qs_pg_placetype":"locality",
    "wof:name":"Shahrak",
    "wof:placetype":"locality",
    "wof:population":15967
},
  "geometry": {"coordinates":[64.3052,34.10738],"type":"Point"}
}