{
  "type": "Feature",
  "properties": {
    "gn:admin1_code":"03",
    "gn:admin2_code":"1307",
    "gn:asciiname":"Qishnahabad",
    "gn:country_code":"AF",
    "gn:dem":1499,
    "gn:feature_class":"P",
    "gn:feature_code":"PPL",
    "gn:name":"Qishnah\u0101b\u0101d",
    "gn:population":0,
    "gn:timezone":"Asia/Kabul",
    "iso:country":"AF",
    "name:und_x_variant":[
        "Kish\u0101n\u0101b\u0101d",
        "Qeshna\u0101bad",
        "Qesna\u0101b\u0101\u1e0f",
        "Qeshneh\u0101b\u0101d",
        "Qishnah\u0101b\u0101d",
        "\u0642\u0634\u0646\u0647 \u0622\u0628\u0627\u062f"
    ],
    "wof:name":"Qishnahabad",
    "wof:placetype":"locality"
},
  "geometry": {"coordinates":[69.21086,35.6204],"type":"Point"}
}