{
  "type": "Feature",
  "properties": {
    "gn:admin1_code":"18",
    "gn:admin2_code":"810.0",
    "gn:asciiname":"Batan",
    "gn:country_code":"AF",
    "gn:dem":1303,
    "gn:feature_class":"P",
    "gn:feature_code":"PPL",
    "gn:name":"Ba\u1e6fan",
    "gn:population":0,
    "gn:timezone":"Asia/Kabul",
    "iso:country":"AF",
    "name:fas_x_preferred":[
        "\u0628\u062a\u0646"
    ],
    "name:und_x_variant":[
        "Ba\u1e6fan",
        "\u0628\u067c\u0646",
        "Batan"
    ],
    "wof:name":"Batan",
    "wof:placetype":"locality"
},
  "geometry": {"coordinates":[70.64889000000002,34.08133],"type":"Point"}
}