{
  "type": "Feature",
  "properties": {
    "gn:admin1_code":"29",
    "gn:admin2_code":"2901",
    "gn:asciiname":"Muhammad Khel",
    "gn:country_code":"AF",
    "gn:dem":2138,
    "gn:feature_class":"P",
    "gn:feature_code":"PPL",
    "gn:name":"Mu\u1e29ammad Kh\u0113l",
    "gn:population":0,
    "gn:timezone":"Asia/Kabul",
    "iso:country":"AF",
    "name:rus_x_preferred":[
        "Mukhammedkheyl\u2019"
    ],
    "name:und_x_variant":[
        "Mo\u1e96\u1e0f-kh\u0113l",
        "Mo\u1e29amma\u1e0f-kh\u0113l",
        "Mo\u1e29ammad Kheyl",
        "Mu\u1e29ammad Kh\u0113l",
        "\u0645\u062d\u0645\u062f \u062e\u06d0\u0644"
    ],
    "wof:name":"Muhammad Khel",
    "wof:placetype":"locality"
},
  "geometry": {"coordinates":[68.73283000000001,33.17904],"type":"Point"}
}