{
  "type": "Feature",
  "properties": {
    "gn:admin1_code":"36",
    "gn:admin2_code":"704.0",
    "gn:asciiname":"Mastakah",
    "gn:country_code":"AF",
    "gn:dem":2215,
    "gn:feature_class":"P",
    "gn:feature_code":"PPL",
    "gn:name":"Mastakah",
    "gn:population":0,
    "gn:timezone":"Asia/Kabul",
    "iso:country":"AF",
    "name:fas_x_preferred":[
        "\u0645\u0633\u062a\u06a9\u0647"
    ],
    "name:und_x_variant":[
        "Mastaka",
        "Mastakah"
    ],
    "wof:name":"Mastakah",
    "wof:placetype":"locality"
},
  "geometry": {"coordinates":[69.49599000000001,33.46400999999999],"type":"Point"}
}