{
  "type": "Feature",
  "properties": {
    "gn:admin1_code":"23",
    "gn:admin2_code":"2403.0",
    "gn:asciiname":"Khugiani",
    "gn:country_code":"AF",
    "gn:dem":1163,
    "gn:feature_class":"P",
    "gn:feature_code":"PPL",
    "gn:name":"Kh\u016bg\u012b\u0101n\u012b",
    "gn:population":0,
    "gn:timezone":"Asia/Kabul",
    "iso:country":"AF",
    "wof:name":"Khugiani",
    "wof:placetype":"locality"
},
  "geometry": {"coordinates":[65.98806,31.94944000000001],"type":"Point"}
}