{
  "type": "Feature",
  "properties": {
    "gn:admin1_code":"28",
    "gn:admin2_code":"2511",
    "gn:asciiname":"Kishali",
    "gn:country_code":"AF",
    "gn:dem":2177,
    "gn:feature_class":"P",
    "gn:feature_code":"PPL",
    "gn:name":"Kish\u0101l\u012b",
    "gn:population":0,
    "gn:timezone":"Asia/Kabul",
    "iso:country":"AF",
    "name:fas_x_preferred":[
        "\u0643\u0634\u0627\u0644\u06cc"
    ],
    "name:und_x_variant":[
        "Ke\u0161\u0101li",
        "Kish\u0101l\u012b",
        "\u06a9\u0634\u0627\u0644\u06cc",
        "Kesh\u0101l\u012b"
    ],
    "wof:name":"Kishali",
    "wof:placetype":"locality"
},
  "geometry": {"coordinates":[67.47766,32.29715],"type":"Point"}
}