{
  "type": "Feature",
  "properties": {
    "gn:admin1_code":"11",
    "gn:admin2_code":"2013.0",
    "gn:asciiname":"Tagaw-e Shash Yar",
    "gn:country_code":"AF",
    "gn:dem":2284,
    "gn:feature_class":"P",
    "gn:feature_code":"PPL",
    "gn:name":"Tag\u0101w-e Shash Y\u0101r",
    "gn:population":0,
    "gn:timezone":"Asia/Kabul",
    "iso:country":"AF",
    "name:rus_x_preferred":[
        "Tagavi-Shish\u2019yar"
    ],
    "name:und_x_variant":[
        "Tag\u0101we \u0160e\u0161y\u0101r",
        "Tag\u0101w-e Shash Y\u0101r",
        "\u062a\u06af\u0627\u0648 \u0634\u0634 \u06cc\u0627\u0631",
        "Tag\u0101b-e Sheshy\u0101r"
    ],
    "wof:name":"Tagaw-e Shash Yar",
    "wof:placetype":"locality"
},
  "geometry": {"coordinates":[63.39955,33.82691],"type":"Point"}
}