{
  "type": "Feature",
  "properties": {
    "gn:admin1_code":"41",
    "gn:admin2_code":"3409.0",
    "gn:asciiname":"Ilah-Ghulam 'Ali",
    "gn:country_code":"AF",
    "gn:dem":1799,
    "gn:feature_class":"P",
    "gn:feature_code":"PPL",
    "gn:name":"Ilah-Ghul\u0101m \u2018Al\u012b",
    "gn:population":0,
    "gn:timezone":"Asia/Kabul",
    "iso:country":"AF",
    "name:und_x_variant":[
        "Ila-ghol\u0101m\u2018ali",
        "Ilah Ghol\u0101m \u2018Al\u012b",
        "Ilah-Ghul\u0101m \u2018Al\u012b",
        "\u0627\u0644\u0647 \u063a\u0644\u0627\u0645 \u0639\u0644\u06cc"
    ],
    "wof:name":"Ilah-Ghulam 'Ali",
    "wof:placetype":"locality"
},
  "geometry": {"coordinates":[66.67412,33.70774],"type":"Point"}
}