{
  "type": "Feature",
  "properties": {
    "gn:admin1_code":"08",
    "gn:admin2_code":"604",
    "gn:asciiname":"Wagh",
    "gn:country_code":"AF",
    "gn:dem":3230,
    "gn:feature_class":"P",
    "gn:feature_code":"PPL",
    "gn:name":"W\u0101gh",
    "gn:population":0,
    "gn:timezone":"Asia/Kabul",
    "iso:country":"AF",
    "name:rus_x_preferred":[
        "\u0412\u0430\u0433"
    ],
    "name:und_x_variant":[
        "Vag",
        "W\u0101gh",
        "\u0648\u0627\u063a"
    ],
    "wof:name":"Wagh",
    "wof:placetype":"locality"
},
  "geometry": {"coordinates":[67.68444000000001,33.60175],"type":"Point"}
}