{
  "type": "Feature",
  "properties": {
    "gn:admin1_code":"24",
    "gn:admin2_code":"1402.0",
    "gn:asciiname":"Ishkili",
    "gn:country_code":"AF",
    "gn:dem":369,
    "gn:feature_class":"P",
    "gn:feature_code":"PPL",
    "gn:name":"Ishkil\u012b",
    "gn:population":0,
    "gn:timezone":"Asia/Kabul",
    "iso:country":"AF",
    "name:und_x_variant":[
        "I\u0161kili",
        "Ishkili",
        "Ishkil\u012b",
        "\u0627\u0634\u06a9\u0644\u06cc"
    ],
    "wof:name":"Ishkili",
    "wof:placetype":"locality"
},
  "geometry": {"coordinates":[69.03355000000001,37.19141],"type":"Point"}
}