{
  "type": "Feature",
  "properties": {
    "gn:admin1_code":"18",
    "gn:admin2_code":"810.0",
    "gn:asciiname":"Dago Menah",
    "gn:country_code":"AF",
    "gn:dem":2508,
    "gn:feature_class":"P",
    "gn:feature_code":"PPL",
    "gn:name":"\u1e0e\u0101g\u014d M\u0113nah",
    "gn:population":0,
    "gn:timezone":"Asia/Kabul",
    "iso:country":"AF",
    "name:fas_x_preferred":[
        "\u0645\u0633\u0643\u0646\u0654 \u062f\u0627\u06af"
    ],
    "name:und_x_variant":[
        "Dagumena",
        "D\u0101go M\u0113na",
        "D\u0101g\u014d M\u0113nah",
        "D\u0101go M\u0113nah",
        "\u062f\u0627\u06af\u0648 \u0645\u06d0\u0646\u0647",
        "\u1e0e\u0101g\u014d M\u0113nah",
        "\u0689\u0627\u06af\u0648 \u0645\u06d0\u0646\u0647"
    ],
    "wof:name":"Dago Menah",
    "wof:placetype":"locality"
},
  "geometry": {"coordinates":[70.52985,33.99881],"type":"Point"}
}