{
  "type": "Feature",
  "properties": {
    "gn:admin1_code":"30",
    "gn:admin2_code":"1611",
    "gn:asciiname":"Qalin Qaq",
    "gn:country_code":"AF",
    "gn:dem":1453,
    "gn:feature_class":"P",
    "gn:feature_code":"PPL",
    "gn:name":"Q\u0101l\u012bn Q\u0101q",
    "gn:population":0,
    "gn:timezone":"Asia/Kabul",
    "iso:country":"AF",
    "name:und_x_variant":[
        "Qalin Q\u0101q (2)",
        "Qalin Q\u0101q",
        "Q\u0101l\u012bn Q\u0101q",
        "\u0642\u0627\u0644\u06cc\u0646 \u0642\u0627\u0642"
    ],
    "wof:name":"Qalin Qaq",
    "wof:placetype":"locality"
},
  "geometry": {"coordinates":[67.27800999999999,36.21545],"type":"Point"}
}