{
  "type": "Feature",
  "properties": {
    "gn:admin1_code":"06",
    "gn:admin2_code":"2105",
    "gn:asciiname":"Gim Sabz",
    "gn:country_code":"AF",
    "gn:dem":894,
    "gn:feature_class":"P",
    "gn:feature_code":"PPL",
    "gn:name":"G\u012bm Sabz",
    "gn:population":0,
    "gn:timezone":"Asia/Kabul",
    "iso:country":"AF",
    "name:und_x_variant":[
        "Gimsabz",
        "Gim Sabz",
        "G\u012bm Sabz",
        "\u06af\u06cc\u0645 \u0633\u0628\u0632"
    ],
    "wof:name":"Gim Sabz",
    "wof:placetype":"locality"
},
  "geometry": {"coordinates":[62.81114,32.58155],"type":"Point"}
}