{
  "type": "Feature",
  "properties": {
    "gn:admin1_code":"41",
    "gn:admin2_code":"3409",
    "gn:asciiname":"Sar-e Bum",
    "gn:country_code":"AF",
    "gn:dem":2232,
    "gn:feature_class":"P",
    "gn:feature_code":"PPL",
    "gn:name":"Sar-e B\u016bm",
    "gn:population":0,
    "gn:timezone":"Asia/Kabul",
    "iso:country":"AF",
    "name:und_x_variant":[
        "Sar-e B\u016bm",
        "\u0633\u0631 \u0628\u0648\u0645"
    ],
    "wof:name":"Sar-e Bum",
    "wof:placetype":"locality"
},
  "geometry": {"coordinates":[66.30896,33.71962],"type":"Point"}
}