{
  "type": "Feature",
  "properties": {
    "gn:admin1_code":"01",
    "gn:admin2_code":"1125",
    "gn:asciiname":"Rubat-e Chihil Tan",
    "gn:country_code":"AF",
    "gn:dem":2532,
    "gn:feature_class":"P",
    "gn:feature_code":"PPL",
    "gn:name":"Rub\u0101\u0163-e Chihil Tan",
    "gn:population":0,
    "gn:timezone":"Asia/Kabul",
    "iso:country":"AF",
    "name:und_x_variant":[
        "\u1e5eab\u0101t-i-Ceheltan",
        "Rob\u0101\u0163-i-Ceheltan",
        "\u0631\u0628\u0627\u0637 \u0686\u0647\u0644 \u062a\u0646",
        "Rob\u0101\u0163-e Chehel Tan",
        "Rab\u0101\u0163-e Chehel Tan",
        "Rub\u0101\u0163-e Chihil Tan"
    ],
    "wof:name":"Rubat-e Chihil Tan",
    "wof:placetype":"locality"
},
  "geometry": {"coordinates":[71.24191999999999,36.60005],"type":"Point"}
}