{
  "type": "Feature",
  "properties": {
    "gn:admin1_code":"40",
    "gn:admin2_code":"308.0",
    "gn:asciiname":"Now Deh",
    "gn:country_code":"AF",
    "gn:dem":1481,
    "gn:feature_class":"P",
    "gn:feature_code":"PPL",
    "gn:name":"Now Deh",
    "gn:population":0,
    "gn:timezone":"Asia/Kabul",
    "iso:country":"AF",
    "name:und_x_variant":[
        "Naudekh",
        "Nawdeh",
        "Now Deh",
        "\u0646\u0648 \u062f\u0647"
    ],
    "wof:name":"Now Deh",
    "wof:placetype":"locality"
},
  "geometry": {"coordinates":[69.2538,34.96267],"type":"Point"}
}