{
  "type": "Feature",
  "properties": {
    "gn:admin1_code":"27",
    "gn:admin2_code":"408",
    "gn:asciiname":"Sar Darah",
    "gn:country_code":"AF",
    "gn:dem":2502,
    "gn:feature_class":"P",
    "gn:feature_code":"PPL",
    "gn:name":"Sar Darah",
    "gn:population":0,
    "gn:timezone":"Asia/Kabul",
    "iso:country":"AF",
    "name:und_x_variant":[
        "Sardarra",
        "Sa\u1e5f \u1e0ea\u1e5f\u1e5fah",
        "Sar Darah",
        "Sar Darreh",
        "\u0633\u0631 \u062f\u0631\u0647"
    ],
    "wof:name":"Sar Darah",
    "wof:placetype":"locality"
},
  "geometry": {"coordinates":[68.66614,34.40681],"type":"Point"}
}