{
  "type": "Feature",
  "properties": {
    "gn:admin1_code":"06",
    "gn:admin2_code":"2104",
    "gn:asciiname":"Qaryah-ye Fil Kush",
    "gn:country_code":"AF",
    "gn:dem":1201,
    "gn:feature_class":"P",
    "gn:feature_code":"PPL",
    "gn:name":"Qaryah-ye F\u012bl Kush",
    "gn:population":0,
    "gn:timezone":"Asia/Kabul",
    "iso:country":"AF",
    "name:und_x_variant":[
        "Qa\u1e5fya-i-F\u012bl Kus\u0304",
        "Qaryah-ye F\u012bl Kush",
        "\u0642\u0631\u06cc\u06c0 \u0641\u06cc\u0644 \u06a9\u0634",
        "Qaryeh-ye F\u012bl Kosh"
    ],
    "wof:name":"Qaryah-ye Fil Kush",
    "wof:placetype":"locality"
},
  "geometry": {"coordinates":[63.55855,33.16188],"type":"Point"}
}