{
  "type": "Feature",
  "properties": {
    "gn:admin1_code":"8",
    "gn:admin2_code":"603.0",
    "gn:asciiname":"Chihil Gunbad",
    "gn:country_code":"AF",
    "gn:dem":2325,
    "gn:feature_class":"P",
    "gn:feature_code":"PPL",
    "gn:name":"Chihil Gunbad",
    "gn:population":0,
    "gn:timezone":"Asia/Kabul",
    "iso:country":"AF",
    "name:fas_x_preferred":[
        "\u0686\u0647\u0644 \u06af\u0646\u0628\u062f"
    ],
    "name:rus_x_preferred":[
        "Chikhil\u2019gulebad"
    ],
    "name:und_x_variant":[
        "\u010cehel Gumbad",
        "Chehel Gunbad",
        "Chehel Gonbad",
        "Chihil Gunbad"
    ],
    "wof:name":"Chihil Gunbad",
    "wof:placetype":"locality"
},
  "geometry": {"coordinates":[68.38885999999999,33.72745],"type":"Point"}
}