{
  "type": "Feature",
  "properties": {
    "gn:admin1_code":"01",
    "gn:admin2_code":"1104",
    "gn:asciiname":"Rubat-e Pa'in",
    "gn:country_code":"AF",
    "gn:dem":2252,
    "gn:feature_class":"P",
    "gn:feature_code":"PPL",
    "gn:name":"Rub\u0101\u0163-e P\u0101\u2019\u012bn",
    "gn:population":0,
    "gn:timezone":"Asia/Kabul",
    "iso:country":"AF",
    "name:und_x_variant":[
        "Lower Ribat",
        "Rib\u0101t-i-P\u0101\u012bn",
        "Rabat-Nishnij",
        "Rob\u0101\u0163-e P\u0101y\u0101n",
        "Rub\u0101\u0163-e P\u0101\u2019\u012bn",
        "\u0631\u0628\u0627\u0637\u0650 \u067e\u0627\u0626\u06cc\u0646"
    ],
    "wof:name":"Rubat-e Pa'in",
    "wof:placetype":"locality"
},
  "geometry": {"coordinates":[70.79751,36.27782],"type":"Point"}
}