{
  "type": "Feature",
  "properties": {
    "gn:admin1_code":"39",
    "gn:admin2_code":"2601.0",
    "gn:asciiname":"Kochkin",
    "gn:country_code":"AF",
    "gn:dem":1376,
    "gn:feature_class":"P",
    "gn:feature_code":"PPL",
    "gn:name":"K\u014dchk\u012bn",
    "gn:population":0,
    "gn:timezone":"Asia/Kabul",
    "iso:country":"AF",
    "name:fas_x_preferred":[
        "\u0643\u0648\u0686\u0643\u064a\u0646"
    ],
    "name:und_x_variant":[
        "Kodk\u012bn",
        "Ko\u010dk\u012bn",
        "Kochkin",
        "K\u014dchk\u012bn",
        "\u06a9\u0648\u0686\u06a9\u06cc\u0646",
        "K\u016bchk\u012bn"
    ],
    "wof:name":"Kochkin",
    "wof:placetype":"locality"
},
  "geometry": {"coordinates":[65.93108000000001,32.6682],"type":"Point"}
}