{
  "type": "Feature",
  "properties": {
    "gn:admin1_code":"11",
    "gn:admin2_code":"2011.0",
    "gn:asciiname":"Humese Bala",
    "gn:country_code":"AF",
    "gn:dem":1566,
    "gn:feature_class":"P",
    "gn:feature_code":"PPL",
    "gn:name":"H\u016bm\u0113se B\u0101l\u0101",
    "gn:population":0,
    "gn:timezone":"Asia/Kabul",
    "iso:country":"AF",
    "wof:name":"Humese Bala",
    "wof:placetype":"locality"
},
  "geometry": {"coordinates":[62.72971999999999,33.50833],"type":"Point"}
}