{
  "type": "Feature",
  "properties": {
    "gn:admin1_code":"37",
    "gn:admin2_code":"3202",
    "gn:asciiname":"Sikandarah",
    "gn:country_code":"AF",
    "gn:dem":1779,
    "gn:feature_class":"P",
    "gn:feature_code":"PPL",
    "gn:name":"Sikandarah",
    "gn:population":0,
    "gn:timezone":"Asia/Kabul",
    "iso:country":"AF",
    "name:und_x_variant":[
        "Sekandara",
        "Sekan Darreh",
        "Sekan\u1e0fa\u1e5fa",
        "Sikandarah",
        "Sekan\u1e0fa\u1e5fah",
        "\u0633\u06a9\u0646\u062f\u0631\u0647"
    ],
    "wof:name":"Sikandarah",
    "wof:placetype":"locality"
},
  "geometry": {"coordinates":[70.01210999999999,33.67776],"type":"Point"}
}