{
  "type": "Feature",
  "properties": {
    "gn:admin1_code":"27",
    "gn:admin2_code":"409",
    "gn:asciiname":"Foladbeg",
    "gn:country_code":"AF",
    "gn:dem":2552,
    "gn:feature_class":"P",
    "gn:feature_code":"PPL",
    "gn:name":"F\u014dl\u0101db\u0113g",
    "gn:population":0,
    "gn:timezone":"Asia/Kabul",
    "iso:country":"AF",
    "name:fas_x_preferred":[
        "\u0641\u0648\u0644\u0627\u062f\u0628\u064a\u06af"
    ],
    "name:und_x_variant":[
        "F\u014dl\u0101\u1e0fb\u0113g",
        "Fuladbek",
        "F\u014dl\u0101d B\u0113g",
        "F\u016bl\u0101dbeyg",
        "\u0641\u0648\u0644\u0627\u062f\u0628\u064a\u06af",
        "F\u014dl\u0101db\u0113g",
        "\u0641\u0648\u0644\u0627\u062f\u0628\u06d0\u06a9"
    ],
    "wof:name":"Foladbeg",
    "wof:placetype":"locality"
},
  "geometry": {"coordinates":[68.39831,33.85232],"type":"Point"}
}