{
  "type": "Feature",
  "properties": {
    "gn:admin1_code":"34",
    "gn:admin2_code":"1012.0",
    "gn:asciiname":"Watahgal",
    "gn:country_code":"AF",
    "gn:dem":1796,
    "gn:feature_class":"P",
    "gn:feature_code":"PPL",
    "gn:name":"W\u0101tahgal",
    "gn:population":0,
    "gn:timezone":"Asia/Kabul",
    "iso:country":"AF",
    "wof:name":"Watahgal",
    "wof:placetype":"locality"
},
  "geometry": {"coordinates":[70.88069,34.77918],"type":"Point"}
}