{
  "type": "Feature",
  "properties": {
    "gn:admin1_code":"07",
    "gn:admin2_code":"1802",
    "gn:asciiname":"Shah Folad",
    "gn:country_code":"AF",
    "gn:dem":956,
    "gn:feature_class":"P",
    "gn:feature_code":"PPL",
    "gn:name":"Sh\u0101h F\u014dl\u0101d",
    "gn:population":0,
    "gn:timezone":"Asia/Kabul",
    "iso:country":"AF",
    "name:und_x_variant":[
        "S\u0101h F\u014dl\u0101\u1e0f",
        "Sh\u0101h F\u016bl\u0101d",
        "Sh\u0101h F\u014dl\u0101d",
        "\u0634\u0627\u0647 \u0641\u0648\u0644\u0627\u062f"
    ],
    "wof:name":"Shah Folad",
    "wof:placetype":"locality"
},
  "geometry": {"coordinates":[64.84093,35.88957],"type":"Point"}
}