{
  "type": "Feature",
  "properties": {
    "gn:admin1_code":"23",
    "gn:admin2_code":"2411",
    "gn:asciiname":"Mowladad Kelay",
    "gn:country_code":"AF",
    "gn:dem":1208,
    "gn:feature_class":"P",
    "gn:feature_code":"PPL",
    "gn:name":"Mowl\u0101d\u0101d K\u00ealay",
    "gn:population":0,
    "gn:timezone":"Asia/Kabul",
    "iso:country":"AF",
    "name:fas_x_preferred":[
        "\u0642\u0631\u06cc\u06c0 \u0645\u0648\u0644\u0627\u062f\u0627\u062f"
    ],
    "name:und_x_variant":[
        "Mauladadkalay",
        "Mawl\u0101\u1e0f\u0101\u1e0f Kalay",
        "Mowl\u0101d\u0101d K\u00ealay",
        "\u0645\u0648\u0644\u0627\u062f\u0627\u062f \u06a9\u0644\u06cc",
        "Mowl\u0101d\u0101d Kalay"
    ],
    "wof:name":"Mowladad Kelay",
    "wof:placetype":"locality"
},
  "geometry": {"coordinates":[66.35988,31.03664],"type":"Point"}
}