{
  "type": "Feature",
  "properties": {
    "gn:admin1_code":"27",
    "gn:admin2_code":"409",
    "gn:asciiname":"Khwajah Ab",
    "gn:country_code":"AF",
    "gn:dem":2380,
    "gn:feature_class":"P",
    "gn:feature_code":"PPL",
    "gn:name":"Khw\u0101jah \u0100b",
    "gn:population":0,
    "gn:timezone":"Asia/Kabul",
    "iso:country":"AF",
    "name:fas_x_preferred":[
        "\u062e\u0648\u0627\u062c\u0647 \u0622\u0628"
    ],
    "name:und_x_variant":[
        "Khw\u0101ja \u0100b",
        "Khodzhaab",
        "Khw\u0101jah \u0100b",
        "Khv\u0101jeh \u0100b"
    ],
    "wof:name":"Khwajah Ab",
    "wof:placetype":"locality"
},
  "geometry": {"coordinates":[68.40572,33.73836],"type":"Point"}
}