{
  "type": "Feature",
  "properties": {
    "gn:admin1_code":"24",
    "gn:admin2_code":"1401",
    "gn:asciiname":"Khwajah Ghaltan",
    "gn:country_code":"AF",
    "gn:dem":402,
    "gn:feature_class":"P",
    "gn:feature_code":"PPL",
    "gn:name":"Khw\u0101jah Ghal\u0163\u0101n",
    "gn:population":0,
    "gn:timezone":"Asia/Kabul",
    "iso:country":"AF",
    "name:rus_x_preferred":[
        "\u0425\u043e\u0434\u0436\u0430-\u0413\u0430\u043b\u044c\u0442\u0430\u043d"
    ],
    "name:und_x_variant":[
        "Khodzha-Gal\u2019tan",
        "Khw\u0101ja Ghal\u1e6f\u0101n",
        "Khv\u0101jeh Ghal\u0163\u0101n",
        "Khw\u0101jah Ghal\u0163\u0101n",
        "\u062e\u0648\u0627\u062c\u0647 \u063a\u0644\u0637\u0627\u0646"
    ],
    "wof:name":"Khwajah Ghaltan",
    "wof:placetype":"locality"
},
  "geometry": {"coordinates":[68.93703000000001,36.73154],"type":"Point"}
}