{
  "type": "Feature",
  "properties": {
    "gn:admin1_code":"29",
    "gn:admin2_code":"2918",
    "gn:asciiname":"Palaw",
    "gn:country_code":"AF",
    "gn:dem":2134,
    "gn:feature_class":"P",
    "gn:feature_code":"PPL",
    "gn:name":"Pal\u0101w",
    "gn:population":0,
    "gn:timezone":"Asia/Kabul",
    "iso:country":"AF",
    "name:und_x_variant":[
        "Palau",
        "\u067e\u0644\u0627\u0648",
        "Pal\u0101w"
    ],
    "wof:name":"Palaw",
    "wof:placetype":"locality"
},
  "geometry": {"coordinates":[68.62648,32.96119],"type":"Point"}
}