{
  "type": "Feature",
  "properties": {
    "gn:admin1_code":"37",
    "gn:admin2_code":"3207",
    "gn:asciiname":"Towr Owbeh",
    "gn:country_code":"AF",
    "gn:dem":1034,
    "gn:feature_class":"P",
    "gn:feature_code":"PPL",
    "gn:name":"Towr Owbeh",
    "gn:population":0,
    "gn:timezone":"Asia/Kabul",
    "iso:country":"AF",
    "name:fas_x_preferred":[
        "\u062a\u0648\u0631\u0647 \u0627\u0648\u0628\u0647"
    ],
    "name:und_x_variant":[
        "Vaz\u012br Kel\u012b",
        "Tora Tega",
        "Waz\u012br Kili",
        "T\u014d\u1e5f\u0113 \u014cbeh",
        "Tor-i-oba",
        "Tore Oba",
        "Toresbe",
        "Towr Owbeh",
        "\u062a\u0648\u0631\u0647 \u0627\u0648\u0628\u0647",
        "T\u014dr\u0113 \u014cb\u00eah",
        "\u062a\u0648\u0631\u06d0 \u0627\u0648\u0628\u0647"
    ],
    "wof:name":"Towr Owbeh",
    "wof:placetype":"locality"
},
  "geometry": {"coordinates":[70.13468,33.41755999999999],"type":"Point"}
}