{
  "type": "Feature",
  "properties": {
    "gn:admin1_code":"09",
    "gn:admin2_code":"2703",
    "gn:asciiname":"Haftanak",
    "gn:country_code":"AF",
    "gn:dem":2476,
    "gn:feature_class":"P",
    "gn:feature_code":"PPL",
    "gn:name":"Haftanak",
    "gn:population":0,
    "gn:timezone":"Asia/Kabul",
    "iso:country":"AF",
    "name:und_x_variant":[
        "\u0647\u0641\u062a\u0646\u06a9"
    ],
    "wof:name":"Haftanak",
    "wof:placetype":"locality"
},
  "geometry": {"coordinates":[63.69293,33.90975],"type":"Point"}
}