{
  "type": "Feature",
  "properties": {
    "gn:admin1_code":"39",
    "gn:admin2_code":"2605.0",
    "gn:asciiname":"Barikay",
    "gn:country_code":"AF",
    "gn:dem":1060,
    "gn:feature_class":"P",
    "gn:feature_code":"PPL",
    "gn:name":"Barikay",
    "gn:population":0,
    "gn:timezone":"Asia/Kabul",
    "iso:country":"AF",
    "name:und_x_variant":[
        "B\u0101r\u012bk\u012b",
        "\u0628\u0627\u0631\u06cc\u06a9\u06cc"
    ],
    "wof:name":"Barikay",
    "wof:placetype":"locality"
},
  "geometry": {"coordinates":[65.43857,32.65429],"type":"Point"}
}