{
  "type": "Feature",
  "properties": {
    "gn:admin1_code":"23",
    "gn:admin2_code":"2407",
    "gn:asciiname":"Gach Karez Kelay",
    "gn:country_code":"AF",
    "gn:dem":926,
    "gn:feature_class":"P",
    "gn:feature_code":"PPL",
    "gn:name":"Gach K\u0101r\u0113z K\u00ealay",
    "gn:population":0,
    "gn:timezone":"Asia/Kabul",
    "iso:country":"AF",
    "name:und_x_variant":[
        "Gachkarezkalay",
        "Ga\u010d K\u0101r\u0113z Kalay",
        "Gach K\u0101r\u0113z K\u00ealay",
        "\u06af\u0686 \u06a9\u0627\u0631\u06d0\u0632 \u06a9\u0644\u06cc",
        "Gach K\u0101r\u012bz Kalay"
    ],
    "wof:name":"Gach Karez Kelay",
    "wof:placetype":"locality"
},
  "geometry": {"coordinates":[64.97806,31.64458],"type":"Point"}
}