{
  "type": "Feature",
  "properties": {
    "gn:admin1_code":"11",
    "gn:admin2_code":"2001",
    "gn:asciiname":"Sufian",
    "gn:country_code":"AF",
    "gn:dem":903,
    "gn:feature_class":"P",
    "gn:feature_code":"PPL",
    "gn:name":"Sufian",
    "gn:population":0,
    "gn:timezone":"Asia/Kabul",
    "iso:country":"AF",
    "name:fas_x_preferred":[
        "\u0635\u0648\u0641\u064a\u0627\u0646"
    ],
    "name:und_x_variant":[
        "S\u016bfy\u0101n",
        "Sufian",
        "\u015e\u016bf\u012b\u0101n"
    ],
    "wof:name":"Sufian",
    "wof:placetype":"locality"
},
  "geometry": {"coordinates":[62.09083,34.335],"type":"Point"}
}