{
  "type": "Feature",
  "properties": {
    "gn:admin1_code":"23",
    "gn:admin2_code":"2416.0",
    "gn:asciiname":"Atsakzai-ye Gharbi",
    "gn:country_code":"AF",
    "gn:dem":936,
    "gn:feature_class":"P",
    "gn:feature_code":"PPL",
    "gn:name":"Atsakza\u012b-ye Gharb\u012b",
    "gn:population":0,
    "gn:timezone":"Asia/Kabul",
    "iso:country":"AF",
    "name:fas_x_preferred":[
        "\u0627\u0686\u064a\u0643\u0632\u0626 \u063a\u0631\u0628\u06cc"
    ],
    "name:und_x_variant":[
        "Acekzi",
        "Gha\u1e5fbi",
        "Ac\u0113kzi Gha\u1e5fbi",
        "Achikzi",
        "Atsakza\u012b-ye Gharb\u012b",
        "\u0627\u0685\u06a9\u0632\u06cc \u063a\u0631\u0628\u06cc",
        "Ats\u0113kzi Gharb\u012b"
    ],
    "wof:name":"Atsakzai-ye Gharbi",
    "wof:placetype":"locality"
},
  "geometry": {"coordinates":[65.29853,31.54671],"type":"Point"}
}