{
  "type": "Feature",
  "properties": {
    "gn:admin1_code":"41",
    "gn:admin2_code":"3403",
    "gn:asciiname":"Qal'ah",
    "gn:country_code":"AF",
    "gn:dem":2267,
    "gn:feature_class":"P",
    "gn:feature_code":"PPL",
    "gn:name":"Qal\u2018ah",
    "gn:population":0,
    "gn:timezone":"Asia/Kabul",
    "iso:country":"AF",
    "name:und_x_variant":[
        "Qal\u2019a",
        "Qal\u2018ah",
        "\u0642\u0644\u0639\u0647",
        "Qal\u2018eh"
    ],
    "wof:name":"Qal'ah",
    "wof:placetype":"locality"
},
  "geometry": {"coordinates":[66.17063,33.8923],"type":"Point"}
}