{
  "type": "Feature",
  "properties": {
    "gn:admin1_code":"24",
    "gn:admin2_code":"1406.0",
    "gn:asciiname":"Andar Abi",
    "gn:country_code":"AF",
    "gn:dem":748,
    "gn:feature_class":"P",
    "gn:feature_code":"PPL",
    "gn:name":"Andar \u0100b\u012b",
    "gn:population":0,
    "gn:timezone":"Asia/Kabul",
    "iso:country":"AF",
    "name:fas_x_preferred":[
        "\u0627\u0646\u062f\u0631\u0627\u0628\u06cc"
    ],
    "name:rus_x_preferred":[
        "\u0410\u043d\u0434\u0430\u0440\u0430\u0431\u0438"
    ],
    "name:und_x_variant":[
        "Andarabi",
        "Andar \u0100b\u012b",
        "\u0627\u0646\u062f\u0631 \u0622\u0628\u06cc"
    ],
    "wof:name":"Andar Abi",
    "wof:placetype":"locality"
},
  "geometry": {"coordinates":[69.07951,36.51727],"type":"Point"}
}