{
  "type": "Feature",
  "properties": {
    "gn:admin1_code":"07",
    "gn:admin2_code":"1804",
    "gn:asciiname":"Yozbigi",
    "gn:country_code":"AF",
    "gn:dem":1388,
    "gn:feature_class":"P",
    "gn:feature_code":"PPL",
    "gn:name":"Y\u014dzbig\u012b",
    "gn:population":0,
    "gn:timezone":"Asia/Kabul",
    "iso:country":"AF",
    "name:und_x_variant":[
        "Y\u016bzbeg\u012b",
        "Y\u014dzbeg\u012b",
        "Y\u016bzbeyg\u012b",
        "Y\u014dzbig\u012b",
        "\u06cc\u0648\u0632\u0628\u06af\u06cc"
    ],
    "wof:name":"Yozbigi",
    "wof:placetype":"locality"
},
  "geometry": {"coordinates":[64.29940999999999,35.63528],"type":"Point"}
}