{
  "type": "Feature",
  "properties": {
    "gn:admin1_code":"18",
    "gn:admin2_code":"821.0",
    "gn:asciiname":"Sur Dewal",
    "gn:country_code":"AF",
    "gn:dem":573,
    "gn:feature_class":"P",
    "gn:feature_code":"PPL",
    "gn:name":"S\u016br D\u0113w\u0101l",
    "gn:population":0,
    "gn:timezone":"Asia/Kabul",
    "iso:country":"AF",
    "name:fas_x_preferred":[
        "\u0633\u0631 \u062f\u064a\u0648\u0627\u0644"
    ],
    "name:rus_x_preferred":[
        "Surdeval\u2019"
    ],
    "name:und_x_variant":[
        "Sar D\u0113w\u0101l",
        "S\u016b\u1e5f \u1e0e\u0113w\u0101l",
        "S\u016br Dayw\u0101l",
        "Sar D\u012bv\u0101l",
        "S\u016br D\u0113w\u0101l",
        "\u0633\u0648\u0631 \u062f\u064a\u0648\u0627\u0644"
    ],
    "wof:name":"Sur Dewal",
    "wof:placetype":"locality"
},
  "geometry": {"coordinates":[70.56520999999999,34.34828],"type":"Point"}
}