{
  "type": "Feature",
  "properties": {
    "gn:admin1_code":"13",
    "gn:admin2_code":"105.0",
    "gn:asciiname":"Qaziyan",
    "gn:country_code":"AF",
    "gn:dem":1754,
    "gn:feature_class":"P",
    "gn:feature_code":"PPL",
    "gn:name":"Q\u0101\u1e95iy\u0101n",
    "gn:population":0,
    "gn:timezone":"Asia/Kabul",
    "iso:country":"AF",
    "name:rus_x_preferred":[
        "Kaz\u2019yan"
    ],
    "name:und_x_variant":[
        "Q\u0101\u1e0f\u1e95y\u0101n",
        "Q\u0101\u1e95\u012b\u0101n",
        "\u0642\u0627\u0636\u06cc\u0627\u0646",
        "Q\u0101\u1e95iy\u0101n"
    ],
    "wof:name":"Qaziyan",
    "wof:placetype":"locality"
},
  "geometry": {"coordinates":[69.10796999999999,34.89576],"type":"Point"}
}