{
  "type": "Feature",
  "properties": {
    "gn:admin1_code":"09",
    "gn:admin2_code":"2701.0",
    "gn:asciiname":"Isparf",
    "gn:country_code":"AF",
    "gn:dem":2114,
    "gn:feature_class":"P",
    "gn:feature_code":"PPL",
    "gn:name":"Isparf",
    "gn:population":0,
    "gn:timezone":"Asia/Kabul",
    "iso:country":"AF",
    "name:und_x_variant":[
        "\u0627\u0633\u067e\u0631\u0641"
    ],
    "wof:name":"Isparf",
    "wof:placetype":"locality"
},
  "geometry": {"coordinates":[65.80088000000001,35.00795],"type":"Point"}
}