{
  "type": "Feature",
  "properties": {
    "gn:admin1_code":"5",
    "gn:admin2_code":"2804.0",
    "gn:asciiname":"War-e Zaq",
    "gn:country_code":"AF",
    "gn:dem":2702,
    "gn:feature_class":"P",
    "gn:feature_code":"PPL",
    "gn:name":"War-e Z\u0101q",
    "gn:population":0,
    "gn:timezone":"Asia/Kabul",
    "iso:country":"AF",
    "name:und_x_variant":[
        "Vari-Zak",
        "War-e Z\u0101q",
        "\u0648\u0631 \u0632\u0627\u0642"
    ],
    "wof:name":"War-e Zaq",
    "wof:placetype":"locality"
},
  "geometry": {"coordinates":[66.97974000000001,34.70376],"type":"Point"}
}