{
  "type": "Feature",
  "properties": {
    "gn:admin1_code":"23",
    "gn:admin2_code":"2402",
    "gn:asciiname":"Makwan Kelay",
    "gn:country_code":"AF",
    "gn:dem":1089,
    "gn:feature_class":"P",
    "gn:feature_code":"PPL",
    "gn:name":"M\u0101kw\u0101n K\u00ealay",
    "gn:population":0,
    "gn:timezone":"Asia/Kabul",
    "iso:country":"AF",
    "name:fas_x_preferred":[
        "\u0642\u0631\u06cc\u06c0 \u0645\u0627\u06a9\u0648\u0627\u0646"
    ],
    "name:und_x_variant":[
        "M\u0101k\u016b",
        "M\u0101kw\u0101n",
        "Makvankalay",
        "M\u0101k\u016b\u0101n",
        "Makun",
        "\u0645\u0627\u06a9\u0648\u0627\u0646 \u06a9\u0644\u06cc",
        "M\u0101kw\u0101n Kalay",
        "M\u0101kw\u0101n K\u00ealay"
    ],
    "wof:name":"Makwan Kelay",
    "wof:placetype":"locality"
},
  "geometry": {"coordinates":[66.02261,31.41556],"type":"Point"}
}