{
  "type": "Feature",
  "properties": {
    "gn:admin1_code":"11",
    "gn:admin2_code":"2014",
    "gn:asciiname":"Qaryah-ye Sajawast",
    "gn:country_code":"AF",
    "gn:dem":1416,
    "gn:feature_class":"P",
    "gn:feature_code":"PPL",
    "gn:name":"Qaryah-ye Saj\u0101wast",
    "gn:population":0,
    "gn:timezone":"Asia/Kabul",
    "iso:country":"AF",
    "name:und_x_variant":[
        "Qa\u1e5fya-i-Saj\u0101wast",
        "Qaryeh-ye Saj\u0101wast",
        "Qaryeh-ye Sajavast",
        "Qaryah-ye Saj\u0101wast",
        "\u0642\u0631\u06cc\u06c0 \u0633\u062c\u0627\u0648\u0633\u062a"
    ],
    "wof:name":"Qaryah-ye Sajawast",
    "wof:placetype":"locality"
},
  "geometry": {"coordinates":[62.98033,33.27445],"type":"Point"}
}