{
  "type": "Feature",
  "properties": {
    "gn:admin1_code":"01",
    "gn:admin2_code":"1126.0",
    "gn:asciiname":"Gazanak",
    "gn:country_code":"AF",
    "gn:dem":1998,
    "gn:feature_class":"P",
    "gn:feature_code":"PPL",
    "gn:name":"Gaz\u0101nak",
    "gn:population":0,
    "gn:timezone":"Asia/Kabul",
    "iso:country":"AF",
    "name:und_x_variant":[
        "\u06af\u0632\u0627\u0646\u06a9",
        "Gaz\u0101nak"
    ],
    "wof:name":"Gazanak",
    "wof:placetype":"locality"
},
  "geometry": {"coordinates":[70.51446,37.28505],"type":"Point"}
}