{
  "type": "Feature",
  "properties": {
    "gn:admin1_code":"26",
    "gn:admin2_code":"1209.0",
    "gn:asciiname":"Argasa",
    "gn:country_code":"AF",
    "gn:dem":1479,
    "gn:feature_class":"P",
    "gn:feature_code":"PPL",
    "gn:name":"Argas\u0101",
    "gn:population":0,
    "gn:timezone":"Asia/Kabul",
    "iso:country":"AF",
    "name:und_x_variant":[
        "Argas\u0101",
        "\u0627\u0631\u06af\u0633\u0627"
    ],
    "wof:name":"Argasa",
    "wof:placetype":"locality"
},
  "geometry": {"coordinates":[69.89985,37.44286],"type":"Point"}
}