{
  "type": "Feature",
  "properties": {
    "gn:admin1_code":"37",
    "gn:admin2_code":"3205",
    "gn:asciiname":"Mandzazai",
    "gn:country_code":"AF",
    "gn:dem":1900,
    "gn:feature_class":"P",
    "gn:feature_code":"PPL",
    "gn:name":"Mandzaza\u012b",
    "gn:population":0,
    "gn:timezone":"Asia/Kabul",
    "iso:country":"AF",
    "name:und_x_variant":[
        "Manjazay",
        "Mandzhazay",
        "Mandzaza\u012b",
        "Mandzazay",
        "\u0645\u0646\u0681\u0632\u06cc"
    ],
    "wof:name":"Mandzazai",
    "wof:placetype":"locality"
},
  "geometry": {"coordinates":[69.72736999999999,33.54886],"type":"Point"}
}