{
  "type": "Feature",
  "properties": {
    "gn:admin1_code":"09",
    "gn:admin2_code":"2705",
    "gn:asciiname":"Ghowlagh",
    "gn:country_code":"AF",
    "gn:dem":2496,
    "gn:feature_class":"P",
    "gn:feature_code":"PPL",
    "gn:name":"Ghowl\u0101gh",
    "gn:population":0,
    "gn:timezone":"Asia/Kabul",
    "iso:country":"AF",
    "name:und_x_variant":[
        "Gaulag",
        "Ghawl\u0101gh",
        "Ghowl\u0101gh",
        "\u063a\u0648\u0644\u0627\u063a",
        "Gh\u0101bl\u0101gh"
    ],
    "wof:name":"Ghowlagh",
    "wof:placetype":"locality"
},
  "geometry": {"coordinates":[64.59258,33.73275],"type":"Point"}
}