{
  "type": "Feature",
  "properties": {
    "gn:admin1_code":"39",
    "gn:admin2_code":"2601.0",
    "gn:asciiname":"Talani",
    "gn:country_code":"AF",
    "gn:dem":1285,
    "gn:feature_class":"P",
    "gn:feature_code":"PPL",
    "gn:name":"Talani",
    "gn:population":0,
    "gn:timezone":"Asia/Kabul",
    "iso:country":"AF",
    "name:und_x_variant":[
        "T\u0101l\u0101n\u012b",
        "\u062a\u0627\u0644\u0627\u0646\u06cc",
        "T\u0101l\u0101ni"
    ],
    "wof:name":"Talani",
    "wof:placetype":"locality"
},
  "geometry": {"coordinates":[65.82545,32.61985],"type":"Point"}
}