{
  "type": "Feature",
  "properties": {
    "gn:admin1_code":"26",
    "gn:admin2_code":"1208.0",
    "gn:asciiname":"Dasht-e Chinar",
    "gn:country_code":"AF",
    "gn:dem":1433,
    "gn:feature_class":"P",
    "gn:feature_code":"PPL",
    "gn:name":"Dasht-e Chin\u0101r",
    "gn:population":0,
    "gn:timezone":"Asia/Kabul",
    "iso:country":"AF",
    "name:und_x_variant":[
        "Da\u0161t-i-\u010cen\u0101r (1)",
        "Dasht-e Chen\u0101r (1)",
        "Dasht-e Chin\u0101r",
        "\u062f\u0634\u062a \u0686\u0646\u0627\u0631"
    ],
    "wof:name":"Dasht-e Chinar",
    "wof:placetype":"locality"
},
  "geometry": {"coordinates":[69.97549000000001,37.02029],"type":"Point"}
}