{
  "type": "Feature",
  "properties": {
    "gn:admin1_code":"27",
    "gn:admin2_code":"404.0",
    "gn:asciiname":"Bum",
    "gn:country_code":"AF",
    "gn:dem":2805,
    "gn:feature_class":"P",
    "gn:feature_code":"PPL",
    "gn:name":"B\u016bm",
    "gn:population":0,
    "gn:timezone":"Asia/Kabul",
    "iso:country":"AF",
    "name:und_x_variant":[
        "B\u016bm",
        "\u0628\u0648\u0645"
    ],
    "wof:name":"Bum",
    "wof:placetype":"locality"
},
  "geometry": {"coordinates":[67.95829999999999,34.42649],"type":"Point"}
}