{
  "type": "Feature",
  "properties": {
    "gn:admin1_code":"8",
    "gn:admin2_code":"609.0",
    "gn:asciiname":"Aminullah Chambar",
    "gn:country_code":"AF",
    "gn:dem":2020,
    "gn:feature_class":"P",
    "gn:feature_code":"PPL",
    "gn:name":"Am\u012bnull\u0101h Chambar",
    "gn:population":0,
    "gn:timezone":"Asia/Kabul",
    "iso:country":"AF",
    "name:und_x_variant":[
        "Am\u012bnull\u0101h \u010cambar",
        "Aminulla-Chambar",
        "Am\u012bnull\u0101h Chambar",
        "\u0627\u0645\u06cc\u0646 \u0627\u0644\u0644\u0640\u0647 \u0686\u0645\u0628\u0631",
        "Am\u012bnoll\u0101h Chambar"
    ],
    "wof:name":"Aminullah Chambar",
    "wof:placetype":"locality"
},
  "geometry": {"coordinates":[67.77761,32.59212],"type":"Point"}
}