{
  "type": "Feature",
  "properties": {
    "gn:admin1_code":"36",
    "gn:admin2_code":"701.0",
    "gn:asciiname":"Darah",
    "gn:country_code":"AF",
    "gn:dem":2687,
    "gn:feature_class":"P",
    "gn:feature_code":"PPL",
    "gn:name":"Darah",
    "gn:population":0,
    "gn:timezone":"Asia/Kabul",
    "iso:country":"AF",
    "name:und_x_variant":[
        "Darra",
        "Dara",
        "\u1e0ea\u1e5fa",
        "Darreh",
        "Darah",
        "\u062f\u0631\u0647"
    ],
    "wof:name":"Darah",
    "wof:placetype":"locality"
},
  "geometry": {"coordinates":[69.32810000000001,33.51345],"type":"Point"}
}