{
  "type": "Feature",
  "properties": {
    "gn:admin1_code":"32",
    "gn:admin2_code":"1503",
    "gn:asciiname":"Gul Darah",
    "gn:country_code":"AF",
    "gn:dem":2206,
    "gn:feature_class":"P",
    "gn:feature_code":"PPL",
    "gn:name":"Gul Darah",
    "gn:population":0,
    "gn:timezone":"Asia/Kabul",
    "iso:country":"AF",
    "name:und_x_variant":[
        "Gul\u1e0fa\u1e5fa",
        "Goldarreh",
        "Gul Darah",
        "\u06af\u0644 \u062f\u0631\u0647"
    ],
    "wof:name":"Gul Darah",
    "wof:placetype":"locality"
},
  "geometry": {"coordinates":[67.15078000000001,35.78889],"type":"Point"}
}