{
  "type": "Feature",
  "properties": {
    "gn:admin1_code":"27",
    "gn:admin2_code":"402",
    "gn:asciiname":"Jagha'in",
    "gn:country_code":"AF",
    "gn:dem":2529,
    "gn:feature_class":"P",
    "gn:feature_code":"PPL",
    "gn:name":"J\u0101gha\u2019\u012bn",
    "gn:population":0,
    "gn:timezone":"Asia/Kabul",
    "iso:country":"AF",
    "name:und_x_variant":[
        "Dzhagain",
        "J\u0101gheyn",
        "J\u0101gha\u2019\u012bn",
        "\u062c\u0627\u0626\u06cc\u0646"
    ],
    "wof:name":"Jagha'in",
    "wof:placetype":"locality"
},
  "geometry": {"coordinates":[68.58348000000001,34.43818],"type":"Point"}
}