{
  "type": "Feature",
  "properties": {
    "gn:admin1_code":"14",
    "gn:admin2_code":"206",
    "gn:asciiname":"Kalan-Sat",
    "gn:country_code":"AF",
    "gn:dem":1753,
    "gn:feature_class":"P",
    "gn:feature_code":"PPL",
    "gn:name":"Kal\u0101n-S\u0101\u1e6f",
    "gn:population":0,
    "gn:timezone":"Asia/Kabul",
    "iso:country":"AF",
    "name:fas_x_preferred":[
        "\u0643\u0644\u0627\u0646 \u0633\u0627\u062a"
    ],
    "name:und_x_variant":[
        "Kal\u0101n S\u0101\u1e6f",
        "Kal\u0101n S\u0101t",
        "Kal\u0101n-S\u0101\u1e6f",
        "\u06a9\u0644\u0627\u0646 \u0633\u0627\u067c"
    ],
    "wof:name":"Kalan-Sat",
    "wof:placetype":"locality"
},
  "geometry": {"coordinates":[69.73634,34.91666],"type":"Point"}
}