{
  "type": "Feature",
  "properties": {
    "gn:admin1_code":"18",
    "gn:admin2_code":"810.0",
    "gn:asciiname":"Gaway",
    "gn:country_code":"AF",
    "gn:dem":1329,
    "gn:feature_class":"P",
    "gn:feature_code":"PPL",
    "gn:name":"G\u0101way",
    "gn:population":0,
    "gn:timezone":"Asia/Kabul",
    "iso:country":"AF",
    "name:und_x_variant":[
        "Gavay",
        "G\u0101way",
        "\u06af\u0627\u0648\u06cc"
    ],
    "wof:name":"Gaway",
    "wof:placetype":"locality"
},
  "geometry": {"coordinates":[70.66011,34.06894],"type":"Point"}
}