{
  "type": "Feature",
  "properties": {
    "gn:admin1_code":"41",
    "gn:admin2_code":"3408",
    "gn:asciiname":"Paytow Joy",
    "gn:country_code":"AF",
    "gn:dem":2632,
    "gn:feature_class":"P",
    "gn:feature_code":"PPL",
    "gn:name":"Paytow J\u014dy",
    "gn:population":0,
    "gn:timezone":"Asia/Kabul",
    "iso:country":"AF",
    "name:und_x_variant":[
        "Petaudzhoy",
        "P\u0113tawj\u014dy",
        "Paytow J\u014dy",
        "\u067e\u06cc\u062a\u0648 \u062c\u0648\u06cc",
        "P\u012bt\u0101v J\u016by"
    ],
    "wof:name":"Paytow Joy",
    "wof:placetype":"locality"
},
  "geometry": {"coordinates":[65.86315999999999,34.26730999999999],"type":"Point"}
}