{
  "type": "Feature",
  "properties": {
    "gn:admin1_code":"08",
    "gn:admin2_code":"607",
    "gn:asciiname":"Lowto",
    "gn:country_code":"AF",
    "gn:dem":2501,
    "gn:feature_class":"P",
    "gn:feature_code":"PPL",
    "gn:name":"Lowto",
    "gn:population":0,
    "gn:timezone":"Asia/Kabul",
    "iso:country":"AF",
    "name:und_x_variant":[
        "L\u014dto",
        "Lowto",
        "L\u014d\u1e6f\u014d",
        "\u0644\u0648\u067c\u0648"
    ],
    "wof:name":"Lowto",
    "wof:placetype":"locality"
},
  "geometry": {"coordinates":[67.30098000000001,33.05906],"type":"Point"}
}