{
  "type": "Feature",
  "properties": {
    "gn:admin1_code":"28",
    "gn:admin2_code":"2506.0",
    "gn:asciiname":"Haji 'Abdullah",
    "gn:country_code":"AF",
    "gn:dem":1302,
    "gn:feature_class":"P",
    "gn:feature_code":"PPL",
    "gn:name":"\u1e28\u0101j\u012b \u2018Abdull\u0101h",
    "gn:population":0,
    "gn:timezone":"Asia/Kabul",
    "iso:country":"AF",
    "name:und_x_variant":[
        "Khadzhi-Abdulla",
        "\u1e28\u0101ji \u2019Ab\u1e0full\u0101h",
        "\u062d\u0627\u062c\u06cc \u0639\u0628\u062f\u0627\u0644\u0644\u0640\u0647",
        "\u1e28\u0101jj\u012b \u2018Abdoll\u0101h",
        "\u1e28\u0101j\u012b \u2018Abdull\u0101h"
    ],
    "wof:name":"Haji 'Abdullah",
    "wof:placetype":"locality"
},
  "geometry": {"coordinates":[66.39258000000001,31.84677000000001],"type":"Point"}
}