{
  "type": "Feature",
  "properties": {
    "gn:admin1_code":"10",
    "gn:admin2_code":"2312",
    "gn:asciiname":"Mian Roday",
    "gn:country_code":"AF",
    "gn:dem":892,
    "gn:feature_class":"P",
    "gn:feature_code":"PPL",
    "gn:name":"M\u012b\u0101n R\u014dday",
    "gn:population":0,
    "gn:timezone":"Asia/Kabul",
    "iso:country":"AF",
    "name:und_x_variant":[
        "My\u0101n \u1e5e\u014d\u1e0fay",
        "Mian-Roday",
        "M\u012b\u0101n R\u014dday",
        "\u0645\u06cc\u0627\u0646 \u0631\u0648\u062f\u06cc",
        "M\u012b\u0101n R\u016bd"
    ],
    "wof:name":"Mian Roday",
    "wof:placetype":"locality"
},
  "geometry": {"coordinates":[64.88105999999999,32.11858],"type":"Point"}
}