{
  "type": "Feature",
  "properties": {
    "gn:admin1_code":"41",
    "gn:admin2_code":"3401.0",
    "gn:asciiname":"Jowzak",
    "gn:country_code":"AF",
    "gn:dem":1921,
    "gn:feature_class":"P",
    "gn:feature_code":"PPL",
    "gn:name":"Jowzak",
    "gn:population":0,
    "gn:timezone":"Asia/Kabul",
    "iso:country":"AF",
    "name:ceb_x_preferred":[
        "Jowzak"
    ],
    "name:swe_x_preferred":[
        "Jowzak"
    ],
    "name:und_x_variant":[
        "\u062c\u0648\u0632\u06a9",
        "Jawzak"
    ],
    "wof:name":"Jowzak",
    "wof:placetype":"locality"
},
  "geometry": {"coordinates":[66.17026,33.76316],"type":"Point"}
}