{
  "type": "Feature",
  "properties": {
    "gn:admin1_code":"27",
    "gn:admin2_code":"406",
    "gn:asciiname":"Gird Ab",
    "gn:country_code":"AF",
    "gn:dem":2126,
    "gn:feature_class":"P",
    "gn:feature_code":"PPL",
    "gn:name":"Gird \u0100b",
    "gn:population":0,
    "gn:timezone":"Asia/Kabul",
    "iso:country":"AF",
    "name:und_x_variant":[
        "Girdab",
        "Gerd\u0101b",
        "Gird \u0100b",
        "\u06af\u0631\u062f \u0622\u0628"
    ],
    "wof:name":"Gird Ab",
    "wof:placetype":"locality"
},
  "geometry": {"coordinates":[68.69968,34.14958],"type":"Point"}
}