{
  "type": "Feature",
  "properties": {
    "gn:admin1_code":"37",
    "gn:admin2_code":"3201",
    "gn:asciiname":"Patak",
    "gn:country_code":"AF",
    "gn:dem":1405,
    "gn:feature_class":"P",
    "gn:feature_code":"PPL",
    "gn:name":"Patak",
    "gn:population":0,
    "gn:timezone":"Asia/Kabul",
    "iso:country":"AF",
    "name:fas_x_preferred":[
        "\u067e\u0627\u062a\u0643"
    ],
    "name:und_x_variant":[
        "\u067e\u062a\u06a9"
    ],
    "wof:name":"Patak",
    "wof:placetype":"locality"
},
  "geometry": {"coordinates":[69.86151,33.43237],"type":"Point"}
}