{
  "type": "Feature",
  "properties": {
    "gn:admin1_code":"02",
    "gn:admin2_code":"1902.0",
    "gn:asciiname":"Kokcha'il",
    "gn:country_code":"AF",
    "gn:dem":1193,
    "gn:feature_class":"P",
    "gn:feature_code":"PPL",
    "gn:name":"K\u014dkch\u0101\u2019\u012bl",
    "gn:population":0,
    "gn:timezone":"Asia/Kabul",
    "iso:country":"AF",
    "name:und_x_variant":[
        "K\u014dkc\u0101\u2019\u012bl",
        "Kowkch\u0101\u2019\u012bl",
        "K\u014dkch\u0101\u2019\u012bl",
        "\u06a9\u0648\u06a9\u0686\u0627\u0626\u06cc\u0644",
        "K\u014dcha\u012bl",
        "\u06a9\u0648\u0686\u0627\u06cc\u0644"
    ],
    "wof:name":"Kokcha'il",
    "wof:placetype":"locality"
},
  "geometry": {"coordinates":[62.86309,34.87207],"type":"Point"}
}