{
  "type": "Feature",
  "properties": {
    "gn:admin1_code":"31",
    "gn:admin2_code":"1701",
    "gn:asciiname":"Qarqin",
    "gn:country_code":"AF",
    "gn:dem":388,
    "gn:feature_class":"P",
    "gn:feature_code":"PPL",
    "gn:name":"Qarq\u012bn",
    "gn:population":0,
    "gn:timezone":"Asia/Kabul",
    "iso:country":"AF",
    "name:ast_x_preferred":[
        "Qarqin"
    ],
    "name:ceb_x_preferred":[
        "Qarq\u012bn"
    ],
    "name:fas_x_preferred":[
        "\u0642\u0631\u0642\u06cc\u0646"
    ],
    "name:spa_x_preferred":[
        "Qarq\u012bn"
    ],
    "name:swe_x_preferred":[
        "Qarq\u012bn"
    ],
    "wof:name":"Qarqin",
    "wof:placetype":"locality"
},
  "geometry": {"coordinates":[65.81477,36.55828],"type":"Point"}
}