{
  "type": "Feature",
  "properties": {
    "gn:admin1_code":"31",
    "gn:admin2_code":"1701",
    "gn:asciiname":"Qarqin",
    "gn:country_code":"AF",
    "gn:dem":388,
    "gn:feature_class":"P",
    "gn:feature_code":"PPL",
    "gn:name":"Qarq\u012bn",
    "gn:population":0,
    "gn:timezone":"Asia/Kabul",
    "iso:country":"AF",
    "name:und_x_variant":[
        "Qarq\u012bn",
        "\u0642\u0631\u0642\u06cc\u0646",
        "Qarqin"
    ],
    "wof:name":"Qarqin",
    "wof:placetype":"locality"
},
  "geometry": {"coordinates":[65.81477,36.55828],"type":"Point"}
}