{
  "type": "Feature",
  "properties": {
    "gn:admin1_code":"13",
    "gn:admin2_code":"102",
    "gn:asciiname":"Rustam Qal'ah",
    "gn:country_code":"AF",
    "gn:dem":1873,
    "gn:feature_class":"P",
    "gn:feature_code":"PPL",
    "gn:name":"Rustam Qal\u2018ah",
    "gn:population":0,
    "gn:timezone":"Asia/Kabul",
    "iso:country":"AF",
    "name:fas_x_preferred":[
        "\u0631\u0633\u062a\u0645 \u0642\u0644\u0639\u0647"
    ],
    "name:und_x_variant":[
        "\u1e5eustam Qal\u2018a",
        "Rustamkalay",
        "Rostam Qal\u2018ah",
        "Rostam Qal\u2018eh",
        "Rustam Qal\u2018ah"
    ],
    "wof:name":"Rustam Qal'ah",
    "wof:placetype":"locality"
},
  "geometry": {"coordinates":[69.33919,34.67869],"type":"Point"}
}