{
  "type": "Feature",
  "properties": {
    "gn:admin1_code":"11",
    "gn:admin2_code":"2006",
    "gn:asciiname":"Qal'ah-ye Girdak",
    "gn:country_code":"AF",
    "gn:dem":1154,
    "gn:feature_class":"P",
    "gn:feature_code":"PPL",
    "gn:name":"Qal\u2018ah-ye Girdak",
    "gn:population":0,
    "gn:timezone":"Asia/Kabul",
    "iso:country":"AF",
    "name:fas_x_preferred":[
        "\u0642\u0644\u0639\u0647\u0654 \u06af\u064a\u0631\u062f\u0643"
    ],
    "name:und_x_variant":[
        "Kalayi-Girdak",
        "Qal\u2018a-i-Gi\u1e5f\u1e0fak",
        "Qal\u2018ah-ye Girdak",
        "\u0642\u0644\u0639\u06c0 \u06af\u0631\u062f\u06a9",
        "Qal\u2018eh-ye G\u012brdak"
    ],
    "wof:name":"Qal'ah-ye Girdak",
    "wof:placetype":"locality"
},
  "geometry": {"coordinates":[62.05421,34.86095],"type":"Point"}
}