{
  "type": "Feature",
  "properties": {
    "gn:admin1_code":"26",
    "gn:admin2_code":"1210.0",
    "gn:asciiname":"Khwajah Hafiz",
    "gn:country_code":"AF",
    "gn:dem":484,
    "gn:feature_class":"P",
    "gn:feature_code":"PPL",
    "gn:name":"Khw\u0101jah \u1e28\u0101fiz\u0327",
    "gn:population":0,
    "gn:timezone":"Asia/Kabul",
    "iso:country":"AF",
    "name:und_x_variant":[
        "Khw\u0101jah \u1e28\u0101fiz\u0327",
        "\u062e\u0648\u0627\u062c\u0647 \u062d\u0627\u0641\u0638",
        "Khv\u0101jeh \u1e28\u0101fez\u0327"
    ],
    "wof:name":"Khwajah Hafiz",
    "wof:placetype":"locality"
},
  "geometry": {"coordinates":[69.63899000000001,37.48464],"type":"Point"}
}