{
  "type": "Feature",
  "properties": {
    "gn:admin1_code":"41",
    "gn:admin2_code":"3407.0",
    "gn:asciiname":"Deh Rang",
    "gn:country_code":"AF",
    "gn:dem":2291,
    "gn:feature_class":"P",
    "gn:feature_code":"PPL",
    "gn:name":"Deh Rang",
    "gn:population":0,
    "gn:timezone":"Asia/Kabul",
    "iso:country":"AF",
    "name:und_x_variant":[
        "\u062f\u0647 \u0631\u0646\u06af"
    ],
    "wof:name":"Deh Rang",
    "wof:placetype":"locality"
},
  "geometry": {"coordinates":[67.04353,33.87879],"type":"Point"}
}