{
  "type": "Feature",
  "properties": {
    "gn:admin1_code":"08",
    "gn:admin2_code":"607",
    "gn:asciiname":"Saydo",
    "gn:country_code":"AF",
    "gn:dem":3136,
    "gn:feature_class":"P",
    "gn:feature_code":"PPL",
    "gn:name":"Sayd\u014d",
    "gn:population":0,
    "gn:timezone":"Asia/Kabul",
    "iso:country":"AF",
    "name:und_x_variant":[
        "Sayd\u014d",
        "\u0633\u06cc\u062f\u0648",
        "Say\u1e0fo"
    ],
    "wof:name":"Saydo",
    "wof:placetype":"locality"
},
  "geometry": {"coordinates":[67.26455,33.24476],"type":"Point"}
}