{
  "type": "Feature",
  "properties": {
    "gn:admin1_code":"28",
    "gn:admin2_code":"2511",
    "gn:asciiname":"Dina Khel",
    "gn:country_code":"AF",
    "gn:dem":2174,
    "gn:feature_class":"P",
    "gn:feature_code":"PPL",
    "gn:name":"Din\u0101 Kh\u0113l",
    "gn:population":0,
    "gn:timezone":"Asia/Kabul",
    "iso:country":"AF",
    "name:fas_x_preferred":[
        "\u062f\u0646\u0627 \u062e\u064a\u0644"
    ],
    "name:und_x_variant":[
        "\u1e0ein\u0101kh\u0113l",
        "Din\u0101 Kh\u0113l",
        "\u062f\u0646\u0627 \u062e\u06d0\u0644",
        "Din\u0101 Kheyl"
    ],
    "wof:name":"Dina Khel",
    "wof:placetype":"locality"
},
  "geometry": {"coordinates":[67.44141999999999,32.27359000000001],"type":"Point"}
}