{
  "type": "Feature",
  "properties": {
    "gn:admin1_code":"39",
    "gn:admin2_code":"2605.0",
    "gn:asciiname":"Aduzai",
    "gn:country_code":"AF",
    "gn:dem":1043,
    "gn:feature_class":"P",
    "gn:feature_code":"PPL",
    "gn:name":"Ad\u016bza\u012b",
    "gn:population":0,
    "gn:timezone":"Asia/Kabul",
    "iso:country":"AF",
    "name:und_x_variant":[
        "A\u1e0f\u016bza\u2018i",
        "Aduzai",
        "Ad\u016bza\u012b",
        "\u0627\u062f\u0648\u0632\u06cc",
        "Ad\u016bzay"
    ],
    "wof:name":"Aduzai",
    "wof:placetype":"locality"
},
  "geometry": {"coordinates":[65.39241,32.55179],"type":"Point"}
}