{
  "type": "Feature",
  "properties": {
    "gn:admin1_code":"27",
    "gn:admin2_code":"409.0",
    "gn:asciiname":"Dahanah",
    "gn:country_code":"AF",
    "gn:dem":2614,
    "gn:feature_class":"P",
    "gn:feature_code":"PPL",
    "gn:name":"Dah\u0101nah",
    "gn:population":0,
    "gn:timezone":"Asia/Kabul",
    "iso:country":"AF",
    "name:und_x_variant":[
        "Dakhana",
        "\u1e0eahana",
        "Dahanah",
        "Dahaneh",
        "Dah\u0101nah",
        "\u062f\u0647\u0627\u0646\u0647"
    ],
    "wof:name":"Dahanah",
    "wof:placetype":"locality"
},
  "geometry": {"coordinates":[68.35706999999999,33.85765],"type":"Point"}
}