{
  "type": "Feature",
  "properties": {
    "gn:country":"AF",
    "gn:fcode":"PPLA",
    "gn:pop":13247,
    "iso:country":"AF",
    "name:ara_x_preferred":[
        "\u0628\u0648\u0644\u064a \u0639\u0644\u0645"
    ],
    "name:ast_x_preferred":[
        "Pul-i-Alam"
    ],
    "name:ben_x_preferred":[
        "\u09b2\u09cb\u0993\u0997\u09be\u09b0 \u09aa\u09cd\u09b0\u09a6\u09c7\u09b6"
    ],
    "name:cat_x_preferred":[
        "Pol-e Alam"
    ],
    "name:dan_x_preferred":[
        "Pul-i-Alam"
    ],
    "name:deu_x_preferred":[
        "Pul-i-Alam"
    ],
    "name:ell_x_preferred":[
        "\u03a0\u03bf\u03c5\u03bb-\u03b9-\u0391\u03bb\u03ac\u03bc"
    ],
    "name:eng_x_preferred":[
        "Pul-i-Alam"
    ],
    "name:epo_x_preferred":[
        "Pul-i Alam"
    ],
    "name:est_x_preferred":[
        "Pul-i \u2018Alam"
    ],
    "name:fas_x_preferred":[
        "\u067e\u0644 \u0639\u0644\u0645"
    ],
    "name:fin_x_preferred":[
        "Pul-i-Alam"
    ],
    "name:fra_x_preferred":[
        "Pol-\u00e9 'Alam"
    ],
    "name:guj_x_preferred":[
        "\u0aaa\u0ac1\u0ab2-\u0a8f-\u0a86\u0ab2\u0aae"
    ],
    "name:hin_x_preferred":[
        "\u092a\u0941\u0932-\u090f-\u0906\u0932\u092e"
    ],
    "name:ind_x_preferred":[
        "Pul-i-Alam"
    ],
    "name:ita_x_preferred":[
        "Pul-i-Alam"
    ],
    "name:jpn_x_preferred":[
        "\u30d7\u30ea\u30a2\u30e9\u30e0"
    ],
    "name:kan_x_preferred":[
        "\u0caa\u0cc1\u0cb2\u0ccd-\u0c87-\u0c86\u0cb2\u0c82"
    ],
    "name:kor_x_preferred":[
        "\ud480\ub9ac\uc544\ub78c"
    ],
    "name:lav_x_preferred":[
        "Puli Alama"
    ],
    "name:lit_x_preferred":[
        "Puli Alamas"
    ],
    "name:mar_x_preferred":[
        "\u092a\u0941\u0932-\u090f-\u0906\u0932\u092e"
    ],
    "name:msa_x_preferred":[
        "Pul-i-Alam"
    ],
    "name:nld_x_preferred":[
        "Pul-i-Alam"
    ],
    "name:nob_x_preferred":[
        "Pol-e Alam"
    ],
    "name:pol_x_preferred":[
        "Pol-e Alam"
    ],
    "name:por_x_preferred":[
        "Pol-e 'Alam"
    ],
    "name:rus_x_preferred":[
        "\u041f\u0443\u043b\u0438-\u0410\u043b\u0430\u043c"
    ],
    "name:sin_x_preferred":[
        "\u0db4\u0dbd\u0dca-\u0d85\u0dba\u0dd2-\u0d85\u0dbd\u0db8\u0dca"
    ],
    "name:spa_x_preferred":[
        "Pul-i-Alam"
    ],
    "name:swe_x_preferred":[
        "Pul-e \u2018Alam"
    ],
    "name:tam_x_preferred":[
        "\u0baa\u0bc1\u0bb2\u0bcd-\u0b90 \u0b85\u0bb2\u0bae\u0bcd"
    ],
    "name:tel_x_preferred":[
        "\u0c2a\u0c41\u0c32\u0c4d-\u0c10-\u0c06\u0c32\u0c02"
    ],
    "name:tha_x_preferred":[
        "\u0e1b\u0e39\u0e25\u0e34\u0e01\u0e19\u0e35\u0e48-\u0e21\u0e2d\u0e07\u0e15\u0e23\u0e32\u0e0a\u0e40\u0e0a\u0e48"
    ],
    "name:tur_x_preferred":[
        "Pul-i Alem"
    ],
    "name:ukr_x_preferred":[
        "\u041f\u0443\u043b\u0456-\u0410\u043b\u0430\u043c"
    ],
    "name:unk_x_variant":[
        "Pule Alam"
    ],
    "name:urd_x_preferred":[
        "\u067e\u0644 \u0639\u0644\u0645"
    ],
    "name:vie_x_preferred":[
        "Qu\u1eadn Puli Alam"
    ],
    "name:war_x_preferred":[
        "Pul-i-Alam"
    ],
    "name:zho_x_preferred":[
        "\u4f69\u723e\u57c3\u963f\u6797"
    ],
    "qs:name":"Pul-e \u2018Alam",
    "qs:photos_9r":0,
    "qs:photos_sr":0,
    "qs:pop_sr":"6",
    "wd:wordcount":137,
    "wof:name":"Pul-e \u2018Alam",
    "wof:placetype":"locality",
    "wof:population":13247
},
  "geometry": {"coordinates":[69.02274,33.99529],"type":"Point"}
}