{
  "type": "Feature",
  "properties": {
    "gn:admin1_code":"28",
    "gn:admin2_code":"2506.0",
    "gn:asciiname":"Kharanukotay",
    "gn:country_code":"AF",
    "gn:dem":1429,
    "gn:feature_class":"P",
    "gn:feature_code":"PPL",
    "gn:name":"Kharanukotay",
    "gn:population":0,
    "gn:timezone":"Asia/Kabul",
    "iso:country":"AF",
    "name:und_x_variant":[
        "Kh\u0101\u1e5f\u0101no K\u014dtey",
        "\u062e\u0627\u0631\u0627\u0646\u0648 \u06a9\u0648\u067c\u06cd",
        "Kh\u0101r\u0101no K\u016btey",
        "Kh\u0101r\u0101n\u014d K\u014d\u1e6f\u00eay"
    ],
    "wof:name":"Kharanukotay",
    "wof:placetype":"locality"
},
  "geometry": {"coordinates":[66.68803,31.94975],"type":"Point"}
}