{
  "type": "Feature",
  "properties": {
    "gn:admin1_code":"10",
    "gn:admin2_code":"2311",
    "gn:asciiname":"Ghulam Nabi Kelay",
    "gn:country_code":"AF",
    "gn:dem":671,
    "gn:feature_class":"P",
    "gn:feature_code":"PPL",
    "gn:name":"Ghul\u0101m Nab\u012b K\u00ealay",
    "gn:population":0,
    "gn:timezone":"Asia/Kabul",
    "iso:country":"AF",
    "name:und_x_variant":[
        "Ghul\u0101m Nab\u012b K\u00ealay",
        "\u063a\u0644\u0627\u0645 \u0646\u0628\u06cc \u06a9\u0644\u06cc",
        "Ghol\u0101m Nabi Kalay"
    ],
    "wof:name":"Ghulam Nabi Kelay",
    "wof:placetype":"locality"
},
  "geometry": {"coordinates":[64.11896,30.73231],"type":"Point"}
}