{
  "type": "Feature",
  "properties": {
    "gn:admin1_code":"13",
    "gn:admin2_code":"110.0",
    "gn:asciiname":"Wilayati",
    "gn:country_code":"AF",
    "gn:dem":1806,
    "gn:feature_class":"P",
    "gn:feature_code":"PPL",
    "gn:name":"Wil\u0101yat\u012b",
    "gn:population":0,
    "gn:timezone":"Asia/Kabul",
    "iso:country":"AF",
    "name:und_x_variant":[
        "Wel\u0101yati",
        "Vilayati",
        "Vel\u0101yat\u012b",
        "Wil\u0101yat\u012b",
        "\u0648\u0644\u0627\u06cc\u062a\u06cc"
    ],
    "wof:name":"Wilayati",
    "wof:placetype":"locality"
},
  "geometry": {"coordinates":[69.20514,34.46907],"type":"Point"}
}