{
  "type": "Feature",
  "properties": {
    "gn:admin1_code":"30",
    "gn:admin2_code":"1609.0",
    "gn:asciiname":"Jaltur",
    "gn:country_code":"AF",
    "gn:dem":1146,
    "gn:feature_class":"P",
    "gn:feature_code":"PPL",
    "gn:name":"Jaltur",
    "gn:population":0,
    "gn:timezone":"Asia/Kabul",
    "iso:country":"AF",
    "name:und_x_variant":[
        "Jaltor (2)",
        "Jaltur",
        "\u062c\u0644\u062a\u0631"
    ],
    "wof:name":"Jaltur",
    "wof:placetype":"locality"
},
  "geometry": {"coordinates":[66.76755,36.1493],"type":"Point"}
}