{
  "type": "Feature",
  "properties": {
    "gn:admin1_code":"5",
    "gn:admin2_code":"2806.0",
    "gn:asciiname":"Damurdah",
    "gn:country_code":"AF",
    "gn:dem":3257,
    "gn:feature_class":"P",
    "gn:feature_code":"PPL",
    "gn:name":"D\u0101murdah",
    "gn:population":0,
    "gn:timezone":"Asia/Kabul",
    "iso:country":"AF",
    "name:und_x_variant":[
        "\u1e0e\u0101mu\u1e5f\u1e0fa",
        "Damurda",
        "D\u0101mordeh",
        "D\u0101murdah",
        "\u062f\u0627\u0645\u0631\u062f\u0647"
    ],
    "wof:name":"Damurdah",
    "wof:placetype":"locality"
},
  "geometry": {"coordinates":[67.37464,34.14249],"type":"Point"}
}