{
  "type": "Feature",
  "properties": {
    "gn:admin1_code":"01",
    "gn:admin2_code":"1119.0",
    "gn:asciiname":"Chadew-e Pa'in",
    "gn:country_code":"AF",
    "gn:dem":2515,
    "gn:feature_class":"P",
    "gn:feature_code":"PPL",
    "gn:name":"Chad\u0113w-e P\u0101\u2019\u012bn",
    "gn:population":0,
    "gn:timezone":"Asia/Kabul",
    "iso:country":"AF",
    "name:und_x_variant":[
        "Ca\u1e0f\u0113w-i-P\u0101\u2019\u012bn",
        "\u0686\u062f\u06d0\u0648 \u067e\u0627\u0626\u06cc\u0646",
        "Chad\u0113w-e P\u0101\u2019\u012bn"
    ],
    "wof:name":"Chadew-e Pa'in",
    "wof:placetype":"locality"
},
  "geometry": {"coordinates":[70.70050999999999,37.38606],"type":"Point"}
}