{
  "type": "Feature",
  "properties": {
    "gn:admin1_code":"08",
    "gn:admin2_code":"613",
    "gn:asciiname":"Khunian",
    "gn:country_code":"AF",
    "gn:dem":2124,
    "gn:feature_class":"P",
    "gn:feature_code":"PPL",
    "gn:name":"Kh\u016bn\u012b\u0101n",
    "gn:population":0,
    "gn:timezone":"Asia/Kabul",
    "iso:country":"AF",
    "name:fas_x_preferred":[
        "\u062e\u0648\u0646\u064a\u0627\u0646"
    ],
    "name:rus_x_preferred":[
        "Khun\u2019yan"
    ],
    "name:und_x_variant":[
        "Kh\u016bny\u0101n",
        "Kh\u016bn\u012b\u0101n",
        "\u062e\u0648\u0646\u06cc\u0627\u0646"
    ],
    "wof:name":"Khunian",
    "wof:placetype":"locality"
},
  "geometry": {"coordinates":[68.04949999999999,33.15295],"type":"Point"}
}