{
  "type": "Feature",
  "properties": {
    "gn:admin1_code":"05",
    "gn:admin2_code":"2805.0",
    "gn:asciiname":"Ghargharah-ye Zamin",
    "gn:country_code":"AF",
    "gn:dem":3292,
    "gn:feature_class":"P",
    "gn:feature_code":"PPL",
    "gn:name":"Ghargharah-ye \u1e94\u0101m\u012bn",
    "gn:population":0,
    "gn:timezone":"Asia/Kabul",
    "iso:country":"AF",
    "name:fas_x_preferred":[
        "\u063a\u0631\u063a\u0631\u06c0 \u0636\u0627\u0645\u0646"
    ],
    "name:rus_x_preferred":[
        "\u0413\u0430\u0440\u0433\u0430\u0440\u0430\u0439\u0438-\u0417\u0430\u043c\u0438\u043d"
    ],
    "name:und_x_variant":[
        "Gha\u1e5fgha\u1e5fah-e \u1e94\u0101men",
        "Gargarayi-Zamin",
        "Gha\u1e5fgha\u1e5fa-i-\u1e0e\u1e95\u0101men",
        "Ghargharah-ye \u1e94\u0101m\u012bn",
        "Gharghareh-ye \u1e94\u0101men",
        "\u063a\u0631\u063a\u0631\u0647 \u0636\u0627\u0645\u064a\u0646"
    ],
    "wof:name":"Ghargharah-ye Zamin",
    "wof:placetype":"locality"
},
  "geometry": {"coordinates":[67.06950000000001,34.54763],"type":"Point"}
}