{
  "type": "Feature",
  "properties": {
    "gn:admin1_code":"28",
    "gn:admin2_code":"2507",
    "gn:asciiname":"Payo Khan Kala",
    "gn:country_code":"AF",
    "gn:dem":1909,
    "gn:feature_class":"P",
    "gn:feature_code":"PPL",
    "gn:name":"P\u0101y\u014d Kh\u0101n Kal\u0101",
    "gn:population":0,
    "gn:timezone":"Asia/Kabul",
    "iso:country":"AF",
    "name:fas_x_preferred":[
        "\u0642\u0644\u0639\u0647\u0654 \u067e\u0627\u064a\u0648 \u062e\u0627\u0646"
    ],
    "name:und_x_variant":[
        "P\u0101y\u014d Kh\u0101n Kal\u0101",
        "\u067e\u0627\u06cc\u0648 \u062e\u0627\u0646 \u06a9\u0644\u0627",
        "P\u0101yow Kh\u0101n Kal\u0101"
    ],
    "wof:name":"Payo Khan Kala",
    "wof:placetype":"locality"
},
  "geometry": {"coordinates":[67.21186999999999,31.94672000000001],"type":"Point"}
}