{
  "type": "Feature",
  "properties": {
    "gn:admin1_code":"27",
    "gn:admin2_code":"409",
    "gn:asciiname":"Lalkay",
    "gn:country_code":"AF",
    "gn:dem":2590,
    "gn:feature_class":"P",
    "gn:feature_code":"PPL",
    "gn:name":"L\u0101lkay",
    "gn:population":0,
    "gn:timezone":"Asia/Kabul",
    "iso:country":"AF",
    "name:fas_x_preferred":[
        "\u0644\u0627\u0644\u0643\u06cc"
    ],
    "name:rus_x_preferred":[
        "Lal\u2019kay"
    ],
    "name:und_x_variant":[
        "L\u0101lkay",
        "\u0644\u0627\u0644\u0643\u06cc",
        "\u0644\u0627\u0644\u06a9\u06cc"
    ],
    "wof:name":"Lalkay",
    "wof:placetype":"locality"
},
  "geometry": {"coordinates":[68.41665999999999,33.87387],"type":"Point"}
}