{
  "type": "Feature",
  "properties": {
    "gn:admin1_code":"23",
    "gn:admin2_code":"2411.0",
    "gn:asciiname":"Bakhtiar Chowdah",
    "gn:country_code":"AF",
    "gn:dem":1240,
    "gn:feature_class":"P",
    "gn:feature_code":"PPL",
    "gn:name":"Bakht\u012b\u0101r Chowdah",
    "gn:population":0,
    "gn:timezone":"Asia/Kabul",
    "iso:country":"AF",
    "name:und_x_variant":[
        "Bakhtiar-Chauda",
        "Bakhty\u0101r Caw\u1e0fa",
        "Bakht\u012b\u0101r Chowdah",
        "\u0628\u062e\u062a\u06cc\u0627\u0631 \u0686\u0648\u062f\u0647",
        "Bakht\u012b\u0101r Chawdah"
    ],
    "wof:name":"Bakhtiar Chowdah",
    "wof:placetype":"locality"
},
  "geometry": {"coordinates":[66.40259,31.14622],"type":"Point"}
}