{
  "type": "Feature",
  "properties": {
    "gn:admin1_code":"05",
    "gn:admin2_code":"2806",
    "gn:asciiname":"Jaqarghan",
    "gn:country_code":"AF",
    "gn:dem":2755,
    "gn:feature_class":"P",
    "gn:feature_code":"PPL",
    "gn:name":"Jaqargh\u0101n",
    "gn:population":0,
    "gn:timezone":"Asia/Kabul",
    "iso:country":"AF",
    "name:und_x_variant":[
        "Dzhakargan",
        "Jaqargh\u0101n",
        "\u062c\u0642\u0631\u063a\u0627\u0646"
    ],
    "wof:name":"Jaqarghan",
    "wof:placetype":"locality"
},
  "geometry": {"coordinates":[67.31035,34.04064],"type":"Point"}
}