{
  "type": "Feature",
  "properties": {
    "gn:admin1_code":"34",
    "gn:admin2_code":"1004.0",
    "gn:asciiname":"Dambar Baba",
    "gn:country_code":"AF",
    "gn:dem":922,
    "gn:feature_class":"P",
    "gn:feature_code":"PPL",
    "gn:name":"\u1e0eambar B\u0101b\u0101",
    "gn:population":0,
    "gn:timezone":"Asia/Kabul",
    "iso:country":"AF",
    "name:fas_x_preferred":[
        "\u062f\u0645\u0628\u0631 \u0628\u0627\u0628\u0627"
    ],
    "name:und_x_variant":[
        "Dambarbaba",
        "Dambar B\u0101b\u0101",
        "\u1e0eambar B\u0101b\u0101",
        "\u0689\u0645\u0628\u0631 \u0628\u0627\u0628\u0627"
    ],
    "wof:name":"Dambar Baba",
    "wof:placetype":"locality"
},
  "geometry": {"coordinates":[71.31962,34.99277],"type":"Point"}
}