{
  "type": "Feature",
  "properties": {
    "gn:admin1_code":"29",
    "gn:admin2_code":"2909",
    "gn:asciiname":"Pawas",
    "gn:country_code":"AF",
    "gn:dem":1727,
    "gn:feature_class":"P",
    "gn:feature_code":"PPL",
    "gn:name":"P\u0101was",
    "gn:population":0,
    "gn:timezone":"Asia/Kabul",
    "iso:country":"AF",
    "name:und_x_variant":[
        "Dwa Kindun Tangai",
        "Pavas",
        "P\u0101was",
        "\u067e\u0627\u0648\u0633"
    ],
    "wof:name":"Pawas",
    "wof:placetype":"locality"
},
  "geometry": {"coordinates":[69.44891,32.8971],"type":"Point"}
}