{
  "type": "Feature",
  "properties": {
    "gn:admin1_code":"28",
    "gn:admin2_code":"2505",
    "gn:asciiname":"Loy Jilgah",
    "gn:country_code":"AF",
    "gn:dem":1612,
    "gn:feature_class":"P",
    "gn:feature_code":"PPL",
    "gn:name":"L\u014dy Jilgah",
    "gn:population":0,
    "gn:timezone":"Asia/Kabul",
    "iso:country":"AF",
    "name:rus_x_preferred":[
        "Loy-Dzhil\u2019ga"
    ],
    "name:und_x_variant":[
        "L\u014dy Jelga",
        "L\u014dy Jilgah",
        "\u0644\u0648\u06cc \u062c\u0644\u06af\u0647",
        "L\u016by Jolgeh"
    ],
    "wof:name":"Loy Jilgah",
    "wof:placetype":"locality"
},
  "geometry": {"coordinates":[66.6117,32.20026],"type":"Point"}
}