{
  "type": "Feature",
  "properties": {
    "gn:admin1_code":"27",
    "gn:admin2_code":"407",
    "gn:asciiname":"Yawez",
    "gn:country_code":"AF",
    "gn:dem":2301,
    "gn:feature_class":"P",
    "gn:feature_code":"PPL",
    "gn:name":"Y\u0101w\u0113z",
    "gn:population":0,
    "gn:timezone":"Asia/Kabul",
    "iso:country":"AF",
    "name:und_x_variant":[
        "Yavez",
        "Y\u0101w\u012bz",
        "Y\u0101w\u0113z",
        "\u06cc\u0627\u0648\u06d0\u0632"
    ],
    "wof:name":"Yawez",
    "wof:placetype":"locality"
},
  "geometry": {"coordinates":[68.64155,34.00547],"type":"Point"}
}