{
  "type": "Feature",
  "properties": {
    "gn:admin1_code":"24",
    "gn:admin2_code":"1401.0",
    "gn:asciiname":"Charm Gari",
    "gn:country_code":"AF",
    "gn:dem":384,
    "gn:feature_class":"P",
    "gn:feature_code":"PPL",
    "gn:name":"Charm Gar\u012b",
    "gn:population":0,
    "gn:timezone":"Asia/Kabul",
    "iso:country":"AF",
    "name:rus_x_preferred":[
        "\u0427\u0430\u0440\u043c\u0433\u0430\u0440\u0438"
    ],
    "name:und_x_variant":[
        "Charmgari",
        "\u010carm Gari",
        "Charm Gar\u012b",
        "\u0686\u0631\u0645 \u06af\u0631\u06cc"
    ],
    "wof:name":"Charm Gari",
    "wof:placetype":"locality"
},
  "geometry": {"coordinates":[68.88030000000001,36.74866],"type":"Point"}
}