{
  "type": "Feature",
  "properties": {
    "gn:admin1_code":"34",
    "gn:admin2_code":"1014",
    "gn:asciiname":"Kander",
    "gn:country_code":"AF",
    "gn:dem":708,
    "gn:feature_class":"P",
    "gn:feature_code":"PPL",
    "gn:name":"Kan\u1e0f\u00ear",
    "gn:population":0,
    "gn:timezone":"Asia/Kabul",
    "iso:country":"AF",
    "name:als_x_preferred":[
        "Kander"
    ],
    "name:ceb_x_preferred":[
        "Kander"
    ],
    "name:dan_x_preferred":[
        "Kander"
    ],
    "name:deu_x_preferred":[
        "Kander"
    ],
    "name:epo_x_preferred":[
        "Kander"
    ],
    "name:fas_x_preferred":[
        "\u06a9\u0646\u062f\u06cc\u0631"
    ],
    "name:fra_x_preferred":[
        "Kander"
    ],
    "name:heb_x_preferred":[
        "\u05e7\u05e0\u05d3\u05e8"
    ],
    "name:nld_x_preferred":[
        "Kander"
    ],
    "name:rus_x_preferred":[
        "\u041a\u0430\u043d\u0434\u0435\u0440"
    ],
    "name:swe_x_preferred":[
        "Kander"
    ],
    "name:und_x_variant":[
        "Kandir",
        "Kand\u0113r",
        "Kan\u1e0f\u00ear",
        "\u06a9\u0646\u0689\u0631"
    ],
    "wof:name":"Kander",
    "wof:placetype":"locality"
},
  "geometry": {"coordinates":[70.86967,34.62730999999999],"type":"Point"}
}