{
  "type": "Feature",
  "properties": {
    "gn:admin1_code":"07",
    "gn:admin2_code":"1804",
    "gn:asciiname":"Korda Qal'ah",
    "gn:country_code":"AF",
    "gn:dem":1054,
    "gn:feature_class":"P",
    "gn:feature_code":"PPL",
    "gn:name":"K\u014drd\u0101 Qal\u2018ah",
    "gn:population":0,
    "gn:timezone":"Asia/Kabul",
    "iso:country":"AF",
    "name:und_x_variant":[
        "K\u014d\u1e5f\u1e0f\u0101 Qal\u2018a",
        "K\u016brd\u0101 Qal\u2018eh",
        "K\u014drd\u0101 Qal\u2018ah",
        "\u06a9\u0648\u0631\u062f\u0627 \u0642\u0644\u0639\u0647"
    ],
    "wof:name":"Korda Qal'ah",
    "wof:placetype":"locality"
},
  "geometry": {"coordinates":[64.539,35.74798],"type":"Point"}
}