{
  "type": "Feature",
  "properties": {
    "gn:admin1_code":"05",
    "gn:admin2_code":"2806.0",
    "gn:asciiname":"Dasht-e Jame'",
    "gn:country_code":"AF",
    "gn:dem":2530,
    "gn:feature_class":"P",
    "gn:feature_code":"PPL",
    "gn:name":"Dasht-e J\u0101me\u2018",
    "gn:population":0,
    "gn:timezone":"Asia/Kabul",
    "iso:country":"AF",
    "wof:name":"Dasht-e Jame'",
    "wof:placetype":"locality"
},
  "geometry": {"coordinates":[67.25660000000001,34.27237],"type":"Point"}
}