{
  "type": "Feature",
  "properties": {
    "gn:admin1_code":"29",
    "gn:admin2_code":"2916",
    "gn:asciiname":"Khanjakay Junubi",
    "gn:country_code":"AF",
    "gn:dem":2027,
    "gn:feature_class":"P",
    "gn:feature_code":"PPL",
    "gn:name":"Khanjakay Jun\u016bb\u012b",
    "gn:population":0,
    "gn:timezone":"Asia/Kabul",
    "iso:country":"AF",
    "name:und_x_variant":[
        "Khandzhakay-Dzhanubi",
        "Khanjakay Jan\u016bbi",
        "\u062e\u0646\u062c\u06a9\u06cc \u062c\u0646\u0648\u0628\u06cc",
        "Khanjakay Jon\u016bb\u012b",
        "Khanjakay Jun\u016bb\u012b"
    ],
    "wof:name":"Khanjakay Junubi",
    "wof:placetype":"locality"
},
  "geometry": {"coordinates":[68.29144000000001,32.71493],"type":"Point"}
}