{
  "type": "Feature",
  "properties": {
    "gn:admin1_code":"40",
    "gn:admin2_code":"307.0",
    "gn:asciiname":"Ziatah",
    "gn:country_code":"AF",
    "gn:dem":2369,
    "gn:feature_class":"P",
    "gn:feature_code":"PPL",
    "gn:name":"Z\u012b\u0101tah",
    "gn:population":0,
    "gn:timezone":"Asia/Kabul",
    "iso:country":"AF",
    "name:und_x_variant":[
        "Zayata",
        "Zayatah",
        "Z\u012b\u0101tah",
        "\u0632\u06cc\u0627\u062a\u0647"
    ],
    "wof:name":"Ziatah",
    "wof:placetype":"locality"
},
  "geometry": {"coordinates":[68.56588000000001,34.78740999999999],"type":"Point"}
}