{
  "type": "Feature",
  "properties": {
    "gn:admin1_code":"36",
    "gn:admin2_code":"704",
    "gn:asciiname":"Kandow Kot",
    "gn:country_code":"AF",
    "gn:dem":2460,
    "gn:feature_class":"P",
    "gn:feature_code":"PPL",
    "gn:name":"Kan\u1e0fow K\u014d\u1e6f",
    "gn:population":0,
    "gn:timezone":"Asia/Kabul",
    "iso:country":"AF",
    "name:fas_x_preferred":[
        "\u06a9\u0646\u062f\u0648 \u0643\u0648\u062a"
    ],
    "name:und_x_variant":[
        "Kandaw K\u014dt",
        "Kandavkot",
        "Kan\u1e0faw Kowt",
        "Kan\u1e0fow K\u014d\u1e6f",
        "\u06a9\u0646\u0689\u0648 \u06a9\u0648\u067c"
    ],
    "wof:name":"Kandow Kot",
    "wof:placetype":"locality"
},
  "geometry": {"coordinates":[69.34595,33.39198],"type":"Point"}
}