{
  "type": "Feature",
  "properties": {
    "gn:admin1_code":"9",
    "gn:admin2_code":"2705.0",
    "gn:asciiname":"Tangisurkh",
    "gn:country_code":"AF",
    "gn:dem":2523,
    "gn:feature_class":"P",
    "gn:feature_code":"PPL",
    "gn:name":"Tangisurkh",
    "gn:population":0,
    "gn:timezone":"Asia/Kabul",
    "iso:country":"AF",
    "wof:name":"Tangisurkh",
    "wof:placetype":"locality"
},
  "geometry": {"coordinates":[64.74221999999999,33.57667],"type":"Point"}
}