{
  "type": "Feature",
  "properties": {
    "gn:admin1_code":"30",
    "gn:admin2_code":"1611",
    "gn:asciiname":"Oymout",
    "gn:country_code":"AF",
    "gn:dem":1271,
    "gn:feature_class":"P",
    "gn:feature_code":"PPL",
    "gn:name":"\u014cymo\u016bt",
    "gn:population":0,
    "gn:timezone":"Asia/Kabul",
    "iso:country":"AF",
    "name:und_x_variant":[
        "Oimout",
        "\u014cymo\u016bt",
        "\u0627\u0648\u06cc\u0645\u0648\u062a"
    ],
    "wof:name":"Oymout",
    "wof:placetype":"locality"
},
  "geometry": {"coordinates":[67.158,36.30184000000001],"type":"Point"}
}