{
  "type": "Feature",
  "properties": {
    "gn:admin1_code":"41",
    "gn:admin2_code":"3403",
    "gn:asciiname":"Now Shah",
    "gn:country_code":"AF",
    "gn:dem":2671,
    "gn:feature_class":"P",
    "gn:feature_code":"PPL",
    "gn:name":"Now Sh\u0101h",
    "gn:population":0,
    "gn:timezone":"Asia/Kabul",
    "iso:country":"AF",
    "name:und_x_variant":[
        "Now Sh\u0101h",
        "Naushakh",
        "Naw\u0161\u0101h",
        "N\u0101w Sh\u0101h",
        "Nowsh\u0101h",
        "\u0646\u0648 \u0634\u0627\u0647"
    ],
    "wof:name":"Now Shah",
    "wof:placetype":"locality"
},
  "geometry": {"coordinates":[66.46168,34.19925],"type":"Point"}
}