{
  "type": "Feature",
  "properties": {
    "gn:admin1_code":"10",
    "gn:admin2_code":"2312.0",
    "gn:asciiname":"Anjarak",
    "gn:country_code":"AF",
    "gn:dem":1073,
    "gn:feature_class":"P",
    "gn:feature_code":"PPL",
    "gn:name":"Anjarak",
    "gn:population":0,
    "gn:timezone":"Asia/Kabul",
    "iso:country":"AF",
    "name:und_x_variant":[
        "Andzharak",
        "Anjarak",
        "\u0627\u0646\u062c\u0631\u06a9",
        "Anja\u1e5fak"
    ],
    "wof:name":"Anjarak",
    "wof:placetype":"locality"
},
  "geometry": {"coordinates":[65.07011999999999,32.14117],"type":"Point"}
}