{
  "type": "Feature",
  "properties": {
    "gn:admin1_code":"01",
    "gn:admin2_code":"1121.0",
    "gn:asciiname":"Mayling-e Pa'in",
    "gn:country_code":"AF",
    "gn:dem":2317,
    "gn:feature_class":"P",
    "gn:feature_code":"PPL",
    "gn:name":"M\u0101yling-e P\u0101\u2019\u012bn",
    "gn:population":0,
    "gn:timezone":"Asia/Kabul",
    "iso:country":"AF",
    "name:und_x_variant":[
        "M\u0101yling-i-P\u0101\u2018in",
        "M\u0101yling-e P\u0101\u2019\u012bn",
        "\u0645\u0627\u06cc\u0644\u0646\u06af \u067e\u0627\u0626\u06cc\u0646"
    ],
    "wof:name":"Mayling-e Pa'in",
    "wof:placetype":"locality"
},
  "geometry": {"coordinates":[70.58471,38.19133],"type":"Point"}
}