{
  "type": "Feature",
  "properties": {
    "gn:admin1_code":"30",
    "gn:admin2_code":"1603.0",
    "gn:asciiname":"Balanddariq",
    "gn:country_code":"AF",
    "gn:dem":982,
    "gn:feature_class":"P",
    "gn:feature_code":"PPL",
    "gn:name":"Balanddariq",
    "gn:population":0,
    "gn:timezone":"Asia/Kabul",
    "iso:country":"AF",
    "name:und_x_variant":[
        "\u0628\u0644\u0646\u062f\u062f\u0631\u0642",
        "Balan\u1e0f\u1e0fa\u1e5feq"
    ],
    "wof:name":"Balanddariq",
    "wof:placetype":"locality"
},
  "geometry": {"coordinates":[66.68321,35.946],"type":"Point"}
}