{
  "type": "Feature",
  "properties": {
    "gn:admin1_code":"40",
    "gn:admin2_code":"309",
    "gn:asciiname":"Iskan Darah",
    "gn:country_code":"AF",
    "gn:dem":2104,
    "gn:feature_class":"P",
    "gn:feature_code":"PPL",
    "gn:name":"Iskan Darah",
    "gn:population":0,
    "gn:timezone":"Asia/Kabul",
    "iso:country":"AF",
    "name:fas_x_preferred":[
        "\u0627\u0633\u0643\u0627\u0645 \u062f\u0631\u0647"
    ],
    "name:und_x_variant":[
        "Iskandara",
        "Eskan\u1e0fa\u1e5fa",
        "Eskan Darah",
        "Eskandarreh",
        "\u0627\u0633\u0643\u0627\u0645 \u062f\u0631\u0647",
        "Iskan Darah",
        "\u0627\u0633\u06a9\u0646 \u062f\u0631\u0647"
    ],
    "wof:name":"Iskan Darah",
    "wof:placetype":"locality"
},
  "geometry": {"coordinates":[69.48575,34.84755],"type":"Point"}
}