{
  "type": "Feature",
  "properties": {
    "gn:admin1_code":"14",
    "gn:admin2_code":"206",
    "gn:asciiname":"Sabarjal",
    "gn:country_code":"AF",
    "gn:dem":2552,
    "gn:feature_class":"P",
    "gn:feature_code":"PPL",
    "gn:name":"Sabarjal",
    "gn:population":0,
    "gn:timezone":"Asia/Kabul",
    "iso:country":"AF",
    "name:rus_x_preferred":[
        "Sabardzhal\u2019"
    ],
    "name:und_x_variant":[
        "Saba\u1e5fjal",
        "Sabarjal",
        "\u0633\u0628\u0631\u062c\u0644"
    ],
    "wof:name":"Sabarjal",
    "wof:placetype":"locality"
},
  "geometry": {"coordinates":[69.85172,34.89945],"type":"Point"}
}