{
  "type": "Feature",
  "properties": {
    "gn:admin1_code":"13",
    "gn:admin2_code":"103.0",
    "gn:asciiname":"Deh-e Mir",
    "gn:country_code":"AF",
    "gn:dem":1643,
    "gn:feature_class":"P",
    "gn:feature_code":"PPL",
    "gn:name":"Deh-e M\u012br",
    "gn:population":0,
    "gn:timezone":"Asia/Kabul",
    "iso:country":"AF",
    "name:fas_x_preferred":[
        "\u062f\u0647\u0654 \u0645\u064a\u0631"
    ],
    "name:und_x_variant":[
        "Dekhi-Mir",
        "Deh-e M\u012br",
        "\u062f\u0647 \u0645\u06cc\u0631"
    ],
    "wof:name":"Deh-e Mir",
    "wof:placetype":"locality"
},
  "geometry": {"coordinates":[69.12938,34.76081],"type":"Point"}
}