{
  "type": "Feature",
  "properties": {
    "gn:admin1_code":"6",
    "gn:admin2_code":"2108.0",
    "gn:asciiname":"Ja'farak",
    "gn:country_code":"AF",
    "gn:dem":626,
    "gn:feature_class":"P",
    "gn:feature_code":"PPL",
    "gn:name":"Ja\u2018farak",
    "gn:population":0,
    "gn:timezone":"Asia/Kabul",
    "iso:country":"AF",
    "name:und_x_variant":[
        "Ja\u2018farak",
        "\u062c\u0639\u0641\u0631\u06a9"
    ],
    "wof:name":"Ja'farak",
    "wof:placetype":"locality"
},
  "geometry": {"coordinates":[61.47943000000001,32.37699],"type":"Point"}
}