{
  "type": "Feature",
  "properties": {
    "gn:admin1_code":"34",
    "gn:admin2_code":"1012.0",
    "gn:asciiname":"Manu",
    "gn:country_code":"AF",
    "gn:dem":1439,
    "gn:feature_class":"P",
    "gn:feature_code":"PPL",
    "gn:name":"Manu",
    "gn:population":0,
    "gn:timezone":"Asia/Kabul",
    "iso:country":"AF",
    "name:fas_x_preferred":[
        "\u0645\u0627\u0646\u0648"
    ],
    "name:und_x_variant":[
        "M\u0101\u1e49o",
        "M\u0101\u1e49\u014d",
        "\u0645\u0627\u06bc\u0648"
    ],
    "wof:name":"Manu",
    "wof:placetype":"locality"
},
  "geometry": {"coordinates":[70.92515,34.74225],"type":"Point"}
}