{
  "type": "Feature",
  "properties": {
    "gn:admin1_code":"34",
    "gn:admin2_code":"1012.0",
    "gn:asciiname":"Manu",
    "gn:country_code":"AF",
    "gn:dem":1439,
    "gn:feature_class":"P",
    "gn:feature_code":"PPL",
    "gn:name":"Manu",
    "gn:population":0,
    "gn:timezone":"Asia/Kabul",
    "iso:country":"AF",
    "name:ben_x_preferred":[
        "\u09ae\u09a8\u09c1"
    ],
    "name:bre_x_preferred":[
        "Manu"
    ],
    "name:bul_x_preferred":[
        "\u041c\u0430\u043d\u0443"
    ],
    "name:cat_x_preferred":[
        "Manu"
    ],
    "name:ceb_x_preferred":[
        "Manu"
    ],
    "name:deu_x_preferred":[
        "Manu"
    ],
    "name:fas_x_preferred":[
        "\u0645\u0627\u0646\u0648"
    ],
    "name:fin_x_preferred":[
        "Manu"
    ],
    "name:fra_x_preferred":[
        "Manu"
    ],
    "name:heb_x_preferred":[
        "\u05de\u05e0\u05d5"
    ],
    "name:ita_x_preferred":[
        "Manu"
    ],
    "name:nld_x_preferred":[
        "Manu"
    ],
    "name:nor_x_preferred":[
        "Manu"
    ],
    "name:por_x_preferred":[
        "Manu"
    ],
    "name:ron_x_preferred":[
        "Manu"
    ],
    "name:rus_x_preferred":[
        "\u041c\u0430\u043d\u0443"
    ],
    "name:spa_x_preferred":[
        "Manu"
    ],
    "name:ukr_x_preferred":[
        "\u041c\u0430\u043d\u0443"
    ],
    "name:und_x_variant":[
        "M\u0101\u1e49o",
        "M\u0101\u1e49\u014d",
        "\u0645\u0627\u06bc\u0648"
    ],
    "wof:name":"Manu",
    "wof:placetype":"locality"
},
  "geometry": {"coordinates":[70.92515,34.74225],"type":"Point"}
}