{
  "type": "Feature",
  "properties": {
    "gn:admin1_code":"26",
    "gn:admin2_code":"1208",
    "gn:asciiname":"Shera Talah",
    "gn:country_code":"AF",
    "gn:dem":847,
    "gn:feature_class":"P",
    "gn:feature_code":"PPL",
    "gn:name":"Sh\u0113r\u0101 Talah",
    "gn:population":0,
    "gn:timezone":"Asia/Kabul",
    "iso:country":"AF",
    "name:und_x_variant":[
        "S\u0113\u1e5f\u0101 Tala",
        "S\u0113\u1e5f\u0101 Talah",
        "Shayr\u0101 Talah",
        "\u0634\u06cc\u0631\u0627 \u062a\u0644\u0647",
        "Sh\u0113r\u0101 Talah"
    ],
    "wof:name":"Shera Talah",
    "wof:placetype":"locality"
},
  "geometry": {"coordinates":[69.61045,37.11777],"type":"Point"}
}