{
  "type": "Feature",
  "properties": {
    "gn:admin1_code":"33",
    "gn:admin2_code":"3106.0",
    "gn:asciiname":"Bilan Ghor",
    "gn:country_code":"AF",
    "gn:dem":1046,
    "gn:feature_class":"P",
    "gn:feature_code":"PPL",
    "gn:name":"Bilan Gh\u014dr",
    "gn:population":0,
    "gn:timezone":"Asia/Kabul",
    "iso:country":"AF",
    "name:und_x_variant":[
        "Belanghor (3)",
        "Belanghor",
        "Bilan Gh\u014dr",
        "\u0628\u0644\u0646 \u063a\u0648\u0631"
    ],
    "wof:name":"Bilan Ghor",
    "wof:placetype":"locality"
},
  "geometry": {"coordinates":[65.82384999999999,36.09978],"type":"Point"}
}