{
  "type": "Feature",
  "properties": {
    "gn:admin1_code":"41",
    "gn:admin2_code":"3409",
    "gn:asciiname":"Gildan",
    "gn:country_code":"AF",
    "gn:dem":1903,
    "gn:feature_class":"P",
    "gn:feature_code":"PPL",
    "gn:name":"Gild\u0101n",
    "gn:population":0,
    "gn:timezone":"Asia/Kabul",
    "iso:country":"AF",
    "name:deu_x_preferred":[
        "Gildan Activewear"
    ],
    "name:fra_x_preferred":[
        "Gildan"
    ],
    "name:spa_x_preferred":[
        "Gildan Activewear"
    ],
    "name:und_x_variant":[
        "Gild\u0101n",
        "\u06af\u0644\u062f\u0627\u0646",
        "Geld\u0101n"
    ],
    "wof:name":"Gildan",
    "wof:placetype":"locality"
},
  "geometry": {"coordinates":[66.52804999999999,33.63471],"type":"Point"}
}