{
  "type": "Feature",
  "properties": {
    "gn:admin1_code":"09",
    "gn:admin2_code":"2707",
    "gn:asciiname":"Mianah Bum-e Sufla",
    "gn:country_code":"AF",
    "gn:dem":2836,
    "gn:feature_class":"P",
    "gn:feature_code":"PPL",
    "gn:name":"M\u012b\u0101nah B\u016bm-e Sufl\u00e1",
    "gn:population":0,
    "gn:timezone":"Asia/Kabul",
    "iso:country":"AF",
    "name:und_x_variant":[
        "My\u0101nab\u016bme Sufl\u0101",
        "Mianabumi-Sufla",
        "M\u012b\u0101nehb\u016bm-e Sofl\u00e1",
        "M\u012b\u0101nah B\u016bm-e Sufl\u00e1",
        "\u0645\u06cc\u0627\u0646\u0647 \u0628\u0648\u0645 \u0633\u0641\u0644\u0649"
    ],
    "wof:name":"Mianah Bum-e Sufla",
    "wof:placetype":"locality"
},
  "geometry": {"coordinates":[66.11433000000001,34.43241],"type":"Point"}
}