{
  "type": "Feature",
  "properties": {
    "gn:admin1_code":"02",
    "gn:admin2_code":"1906",
    "gn:asciiname":"Mal Darah-ye Kuchi",
    "gn:country_code":"AF",
    "gn:dem":605,
    "gn:feature_class":"P",
    "gn:feature_code":"PPL",
    "gn:name":"M\u0101l Darah-ye K\u016bch\u012b",
    "gn:population":0,
    "gn:timezone":"Asia/Kabul",
    "iso:country":"AF",
    "name:und_x_variant":[
        "M\u0101l Darah-ye K\u016bch\u012b",
        "\u0645\u0627\u0644 \u062f\u0631\u06c0 \u06a9\u0648\u0686\u06cc",
        "M\u0101y Darreh-ye K\u016bch\u012b",
        "M\u0101i-\u1e0ea\u1e5f\u1e5fah-i-K\u016bc\u012b"
    ],
    "wof:name":"Mal Darah-ye Kuchi",
    "wof:placetype":"locality"
},
  "geometry": {"coordinates":[63.46477,35.61552000000001],"type":"Point"}
}