{
  "type": "Feature",
  "properties": {
    "gn:admin1_code":"27",
    "gn:admin2_code":"404.0",
    "gn:asciiname":"Baraki",
    "gn:country_code":"AF",
    "gn:dem":2894,
    "gn:feature_class":"P",
    "gn:feature_code":"PPL",
    "gn:name":"Barak\u012b",
    "gn:population":0,
    "gn:timezone":"Asia/Kabul",
    "iso:country":"AF",
    "name:und_x_variant":[
        "Barak\u012b",
        "\u0628\u0631\u06a9\u06cc"
    ],
    "wof:name":"Baraki",
    "wof:placetype":"locality"
},
  "geometry": {"coordinates":[67.89973000000001,34.36269],"type":"Point"}
}