{
  "type": "Feature",
  "properties": {
    "gn:admin1_code":"23",
    "gn:admin2_code":"2413.0",
    "gn:asciiname":"Karah",
    "gn:country_code":"AF",
    "gn:dem":2010,
    "gn:feature_class":"P",
    "gn:feature_code":"PPL",
    "gn:name":"K\u0101\u1e5fah",
    "gn:population":0,
    "gn:timezone":"Asia/Kabul",
    "iso:country":"AF",
    "name:fas_x_preferred":[
        "\u06a9\u0631\u0627\u0647"
    ],
    "name:und_x_variant":[
        "K\u0101ra",
        "K\u0101\u1e5fah",
        "K\u0101rah",
        "\u06a9\u0627\u0693\u0647"
    ],
    "wof:name":"Karah",
    "wof:placetype":"locality"
},
  "geometry": {"coordinates":[67.31833,31.34222],"type":"Point"}
}