{
  "type": "Feature",
  "properties": {
    "gn:admin1_code":"29",
    "gn:admin2_code":"2910.0",
    "gn:asciiname":"Ragheh",
    "gn:country_code":"AF",
    "gn:dem":2031,
    "gn:feature_class":"P",
    "gn:feature_code":"PPL",
    "gn:name":"R\u0101gh\u00eah",
    "gn:population":0,
    "gn:timezone":"Asia/Kabul",
    "iso:country":"AF",
    "name:und_x_variant":[
        "Raga",
        "R\u0101gheh",
        "R\u0101gh\u00eah",
        "\u0631\u0627\u063a\u0647"
    ],
    "wof:name":"Ragheh",
    "wof:placetype":"locality"
},
  "geometry": {"coordinates":[69.37461999999999,32.95296],"type":"Point"}
}