{
  "type": "Feature",
  "properties": {
    "gn:admin1_code":"09",
    "gn:admin2_code":"2705",
    "gn:asciiname":"Pushtay",
    "gn:country_code":"AF",
    "gn:dem":2405,
    "gn:feature_class":"P",
    "gn:feature_code":"PPL",
    "gn:name":"Pusht\u0101y",
    "gn:population":0,
    "gn:timezone":"Asia/Kabul",
    "iso:country":"AF",
    "name:und_x_variant":[
        "Pu\u0161t\u0101y",
        "Pushtay",
        "Pusht\u0101y",
        "\u067e\u0634\u062a\u0627\u06cc",
        "Posht\u0101y"
    ],
    "wof:name":"Pushtay",
    "wof:placetype":"locality"
},
  "geometry": {"coordinates":[64.21384999999999,33.61868],"type":"Point"}
}