{
  "type": "Feature",
  "properties": {
    "gn:admin1_code":"13",
    "gn:admin2_code":"101.0",
    "gn:asciiname":"Qaryah-ye Wasilabad",
    "gn:country_code":"AF",
    "gn:dem":1825,
    "gn:feature_class":"P",
    "gn:feature_code":"PPL",
    "gn:name":"Qaryah-ye W\u0101\u015fil\u0101b\u0101d",
    "gn:population":0,
    "gn:timezone":"Asia/Kabul",
    "iso:country":"AF",
    "name:und_x_variant":[
        "Vaysalabad",
        "Wa\u015fal\u0101b\u0101d",
        "Waysal\u0101b\u0101d",
        "Wa\u012bsal\u0101b\u0101d",
        "\u0648\u06cc\u0633\u0644 \u0622\u0628\u0627\u062f",
        "Qaryah-ye W\u0101\u015fil\u0101b\u0101d",
        "\u0642\u0631\u06cc\u0647 \u0648\u0627\u0635\u0644 \u0622\u0628\u0627\u062f"
    ],
    "wof:name":"Qaryah-ye Wasilabad",
    "wof:placetype":"locality"
},
  "geometry": {"coordinates":[69.16439,34.49002],"type":"Point"}
}