{
  "type": "Feature",
  "properties": {
    "gn:admin1_code":"03",
    "gn:admin2_code":"1303",
    "gn:asciiname":"Qishlaq Sard Aw",
    "gn:country_code":"AF",
    "gn:dem":1629,
    "gn:feature_class":"P",
    "gn:feature_code":"PPL",
    "gn:name":"Qishl\u0101q Sard \u0100w",
    "gn:population":0,
    "gn:timezone":"Asia/Kabul",
    "iso:country":"AF",
    "name:und_x_variant":[
        "Sardau",
        "Qo\u0161 Sardaw",
        "Qosh Sardaw",
        "Qishl\u0101q Sard \u0100w",
        "\u0642\u0634\u0644\u0627\u0642 \u0633\u0631\u062f \u0622\u0648"
    ],
    "wof:name":"Qishlaq Sard Aw",
    "wof:placetype":"locality"
},
  "geometry": {"coordinates":[68.65954000000001,35.71557],"type":"Point"}
}