{
  "type": "Feature",
  "properties": {
    "gn:admin1_code":"02",
    "gn:admin2_code":"1904",
    "gn:asciiname":"Qishlaq-e Ab Pudah",
    "gn:country_code":"AF",
    "gn:dem":1225,
    "gn:feature_class":"P",
    "gn:feature_code":"PPL",
    "gn:name":"Qishl\u0101q-e \u0100b P\u016bdah",
    "gn:population":0,
    "gn:timezone":"Asia/Kabul",
    "iso:country":"AF",
    "name:und_x_variant":[
        "Qishl\u0101q-e \u0100b P\u016bdah",
        "\u0642\u0634\u0644\u0627\u0642 \u0622\u0628 \u067e\u0648\u062f\u0647",
        "Qeshl\u0101qe"
    ],
    "wof:name":"Qishlaq-e Ab Pudah",
    "wof:placetype":"locality"
},
  "geometry": {"coordinates":[64.12698,34.99054],"type":"Point"}
}