{
  "type": "Feature",
  "properties": {
    "gn:admin1_code":"8",
    "gn:admin2_code":"607.0",
    "gn:asciiname":"Siyah Sang",
    "gn:country_code":"AF",
    "gn:dem":2925,
    "gn:feature_class":"P",
    "gn:feature_code":"PPL",
    "gn:name":"Siy\u0101h Sang",
    "gn:population":0,
    "gn:timezone":"Asia/Kabul",
    "iso:country":"AF",
    "name:und_x_variant":[
        "Sy\u0101hsang",
        "S\u012b\u0101h Sang",
        "\u0633\u06cc\u0627\u0647 \u0633\u0646\u06af",
        "Siy\u0101h Sang"
    ],
    "wof:name":"Siyah Sang",
    "wof:placetype":"locality"
},
  "geometry": {"coordinates":[67.30568000000001,33.22062],"type":"Point"}
}