{
  "type": "Feature",
  "properties": {
    "gn:admin1_code":"40",
    "gn:admin2_code":"305",
    "gn:asciiname":"Lich",
    "gn:country_code":"AF",
    "gn:dem":2074,
    "gn:feature_class":"P",
    "gn:feature_code":"PPL",
    "gn:name":"L\u012bch",
    "gn:population":0,
    "gn:timezone":"Asia/Kabul",
    "iso:country":"AF",
    "name:bul_x_preferred":[
        "\u041b\u0438\u0447"
    ],
    "name:cat_x_preferred":[
        "Lich"
    ],
    "name:ces_x_preferred":[
        "Lich"
    ],
    "name:deu_x_preferred":[
        "Lich"
    ],
    "name:epo_x_preferred":[
        "Li\u0109o"
    ],
    "name:fin_x_preferred":[
        "Lich"
    ],
    "name:fra_x_preferred":[
        "Liche"
    ],
    "name:heb_x_preferred":[
        "\u05dc\u05d9\u05e5'"
    ],
    "name:ita_x_preferred":[
        "Lich"
    ],
    "name:lit_x_preferred":[
        "Li\u010das"
    ],
    "name:pol_x_preferred":[
        "Licz"
    ],
    "name:por_x_preferred":[
        "Lich"
    ],
    "name:ron_x_preferred":[
        "Lich"
    ],
    "name:rus_x_preferred":[
        "\u041b\u0438\u0447"
    ],
    "name:spa_x_preferred":[
        "Liche"
    ],
    "name:ukr_x_preferred":[
        "\u041b\u0456\u0447"
    ],
    "name:und_x_variant":[
        "L\u012b\u010d",
        "L\u012bch",
        "\u0644\u06cc\u0686"
    ],
    "wof:name":"Lich",
    "wof:placetype":"locality"
},
  "geometry": {"coordinates":[68.74563000000001,35.00694],"type":"Point"}
}