{
  "type": "Feature",
  "properties": {
    "gn:admin1_code":"19",
    "gn:admin2_code":"2205",
    "gn:asciiname":"Landay",
    "gn:country_code":"AF",
    "gn:dem":643,
    "gn:feature_class":"P",
    "gn:feature_code":"PPL",
    "gn:name":"Lan\u1e0fay",
    "gn:population":0,
    "gn:timezone":"Asia/Kabul",
    "iso:country":"AF",
    "name:fas_x_preferred":[
        "Lan\u1e0fay"
    ],
    "name:fas_x_variant":[
        "Land\u012b",
        "\u0644\u0646\u0689\u06cc"
    ],
    "name:und_x_variant":[
        "\u0644\u0646\u0689\u06cc"
    ],
    "wof:name":"Landay",
    "wof:placetype":"locality"
},
  "geometry": {"coordinates":[62.99766999999999,31.72714],"type":"Point"}
}