{
  "type": "Feature",
  "properties": {
    "gn:admin1_code":"33",
    "gn:admin2_code":"3101",
    "gn:asciiname":"Korak",
    "gn:country_code":"AF",
    "gn:dem":549,
    "gn:feature_class":"P",
    "gn:feature_code":"PPL",
    "gn:name":"K\u014drak",
    "gn:population":0,
    "gn:timezone":"Asia/Kabul",
    "iso:country":"AF",
    "name:und_x_variant":[
        "K\u014drak",
        "\u06a9\u0648\u0631\u06a9",
        "Korak"
    ],
    "wof:name":"Korak",
    "wof:placetype":"locality"
},
  "geometry": {"coordinates":[65.86649,36.303],"type":"Point"}
}