{
  "type": "Feature",
  "properties": {
    "gn:admin1_code":"33",
    "gn:admin2_code":"3103",
    "gn:asciiname":"Kalah Khanah",
    "gn:country_code":"AF",
    "gn:dem":2513,
    "gn:feature_class":"P",
    "gn:feature_code":"PPL",
    "gn:name":"Kalah Kh\u0101nah",
    "gn:population":0,
    "gn:timezone":"Asia/Kabul",
    "iso:country":"AF",
    "name:und_x_variant":[
        "Kalakh\u0101na",
        "Kal\u0101kh\u0101neh",
        "Kalah Kh\u0101nah",
        "\u06a9\u0644\u0647 \u062e\u0627\u0646\u0647"
    ],
    "wof:name":"Kalah Khanah",
    "wof:placetype":"locality"
},
  "geometry": {"coordinates":[65.86301,35.63839],"type":"Point"}
}