{
  "type": "Feature",
  "properties": {
    "gn:admin1_code":"41",
    "gn:admin2_code":"3407.0",
    "gn:asciiname":"Rapatan",
    "gn:country_code":"AF",
    "gn:dem":2615,
    "gn:feature_class":"P",
    "gn:feature_code":"PPL",
    "gn:name":"Rapat\u0101n",
    "gn:population":0,
    "gn:timezone":"Asia/Kabul",
    "iso:country":"AF",
    "name:und_x_variant":[
        "Rapat\u0101n",
        "\u0631\u067e\u062a\u0627\u0646"
    ],
    "wof:name":"Rapatan",
    "wof:placetype":"locality"
},
  "geometry": {"coordinates":[66.92508000000001,33.87916],"type":"Point"}
}