{
  "type": "Feature",
  "properties": {
    "gn:admin1_code":"05",
    "gn:admin2_code":"2804",
    "gn:asciiname":"Naychah Bulaq",
    "gn:country_code":"AF",
    "gn:dem":3007,
    "gn:feature_class":"P",
    "gn:feature_code":"PPL",
    "gn:name":"Naychah B\u016bl\u0101q",
    "gn:population":0,
    "gn:timezone":"Asia/Kabul",
    "iso:country":"AF",
    "name:und_x_variant":[
        "Naycabol\u0101q",
        "Neycheh Bol\u0101q",
        "Naychah B\u016bl\u0101q",
        "\u0646\u06cc\u0686\u0647 \u0628\u0648\u0644\u0627\u0642"
    ],
    "wof:name":"Naychah Bulaq",
    "wof:placetype":"locality"
},
  "geometry": {"coordinates":[66.65776,35.10087],"type":"Point"}
}