{
  "type": "Feature",
  "properties": {
    "gn:admin1_code":"08",
    "gn:admin2_code":"614",
    "gn:asciiname":"Telbah",
    "gn:country_code":"AF",
    "gn:dem":2076,
    "gn:feature_class":"P",
    "gn:feature_code":"PPL",
    "gn:name":"T\u0113lbah",
    "gn:population":0,
    "gn:timezone":"Asia/Kabul",
    "iso:country":"AF",
    "name:fas_x_preferred":[
        "\u062a\u064a\u0644\u0628\u0647"
    ],
    "name:rus_x_preferred":[
        "Tel\u2019ba"
    ],
    "name:und_x_variant":[
        "T\u0113lba",
        "T\u0113lbah",
        "\u062a\u06d0\u0644\u0628\u0647"
    ],
    "wof:name":"Telbah",
    "wof:placetype":"locality"
},
  "geometry": {"coordinates":[68.40651,33.33265],"type":"Point"}
}