{
  "type": "Feature",
  "properties": {
    "gn:admin1_code":"39",
    "gn:admin2_code":"2603.0",
    "gn:asciiname":"Dahan-e Sangu",
    "gn:country_code":"AF",
    "gn:dem":2297,
    "gn:feature_class":"P",
    "gn:feature_code":"PPL",
    "gn:name":"Dahan-e Sang\u016b",
    "gn:population":0,
    "gn:timezone":"Asia/Kabul",
    "iso:country":"AF",
    "name:und_x_variant":[
        "Dahan-e Sang\u016b",
        "\u062f\u0647\u0646 \u0633\u0646\u06af\u0648"
    ],
    "wof:name":"Dahan-e Sangu",
    "wof:placetype":"locality"
},
  "geometry": {"coordinates":[66.75834999999999,33.15300999999999],"type":"Point"}
}