{
  "type": "Feature",
  "properties": {
    "gn:admin1_code":"8",
    "gn:admin2_code":"607.0",
    "gn:asciiname":"Siyah Top",
    "gn:country_code":"AF",
    "gn:dem":2758,
    "gn:feature_class":"P",
    "gn:feature_code":"PPL",
    "gn:name":"Siy\u0101h T\u014dp",
    "gn:population":0,
    "gn:timezone":"Asia/Kabul",
    "iso:country":"AF",
    "name:und_x_variant":[
        "Sy\u0101t\u014dp",
        "S\u012b\u0101towp",
        "S\u012b\u0101h T\u014dp",
        "\u0633\u06cc\u0627\u0647 \u062a\u0648\u067e",
        "Siy\u0101h T\u014dp"
    ],
    "wof:name":"Siyah Top",
    "wof:placetype":"locality"
},
  "geometry": {"coordinates":[67.41060999999999,33.25819],"type":"Point"}
}