{
  "type": "Feature",
  "properties": {
    "gn:admin1_code":"06",
    "gn:admin2_code":"2103",
    "gn:asciiname":"Qaryah-ye Sa'id",
    "gn:country_code":"AF",
    "gn:dem":1785,
    "gn:feature_class":"P",
    "gn:feature_code":"PPL",
    "gn:name":"Qaryah-ye Sa\u2018\u012bd",
    "gn:population":0,
    "gn:timezone":"Asia/Kabul",
    "iso:country":"AF",
    "name:und_x_variant":[
        "Qa\u1e5fya-i- Sa\u2018\u012bd",
        "Qaryah-ye Sa\u2018\u012bd",
        "\u0642\u0631\u06cc\u0647 \u0633\u0639\u06cc\u062f",
        "Qaryeh-ye Sa\u2018\u012bd"
    ],
    "wof:name":"Qaryah-ye Sa'id",
    "wof:placetype":"locality"
},
  "geometry": {"coordinates":[63.83524,32.74325],"type":"Point"}
}