{
  "type": "Feature",
  "properties": {
    "gn:admin1_code":"23",
    "gn:admin2_code":"2413",
    "gn:asciiname":"Garang",
    "gn:country_code":"AF",
    "gn:dem":1709,
    "gn:feature_class":"P",
    "gn:feature_code":"PPL",
    "gn:name":"Ga\u1e5fang",
    "gn:population":0,
    "gn:timezone":"Asia/Kabul",
    "iso:country":"AF",
    "name:fas_x_preferred":[
        "\u06af\u0631\u0646\u06af"
    ],
    "name:fra_x_preferred":[
        "Garang"
    ],
    "name:pus_x_preferred":[
        "\u06af\u0693\u0646\u06af"
    ],
    "name:und_x_variant":[
        "Ga\u1e5fang"
    ],
    "wof:name":"Garang",
    "wof:placetype":"locality"
},
  "geometry": {"coordinates":[67.16136,31.62829],"type":"Point"}
}