{
  "type": "Feature",
  "properties": {
    "gn:admin1_code":"26",
    "gn:admin2_code":"1208",
    "gn:asciiname":"Sanguli",
    "gn:country_code":"AF",
    "gn:dem":1587,
    "gn:feature_class":"P",
    "gn:feature_code":"PPL",
    "gn:name":"Sangul\u012b",
    "gn:population":0,
    "gn:timezone":"Asia/Kabul",
    "iso:country":"AF",
    "name:und_x_variant":[
        "Sangoli",
        "Shangoli",
        "Sangul\u012b",
        "\u0633\u0646\u06af\u0644\u06cc"
    ],
    "wof:name":"Sanguli",
    "wof:placetype":"locality"
},
  "geometry": {"coordinates":[69.75919,37.06058],"type":"Point"}
}