{
  "type": "Feature",
  "properties": {
    "gn:admin1_code":"28",
    "gn:admin2_code":"2504.0",
    "gn:asciiname":"Andar",
    "gn:country_code":"AF",
    "gn:dem":2484,
    "gn:feature_class":"P",
    "gn:feature_code":"PPL",
    "gn:name":"Anda\u1e5f",
    "gn:population":0,
    "gn:timezone":"Asia/Kabul",
    "iso:country":"AF",
    "name:fas_x_preferred":[
        "\u0627\u0646\u062f\u0631"
    ],
    "name:und_x_variant":[
        "Anda\u1e5f",
        "\u0627\u0646\u062f\u0693",
        "An\u1e0far"
    ],
    "wof:name":"Andar",
    "wof:placetype":"locality"
},
  "geometry": {"coordinates":[66.64869,32.61216],"type":"Point"}
}