{
  "type": "Feature",
  "properties": {
    "gn:admin1_code":"08",
    "gn:admin2_code":"613",
    "gn:asciiname":"Nowaz",
    "gn:country_code":"AF",
    "gn:dem":2037,
    "gn:feature_class":"P",
    "gn:feature_code":"PPL",
    "gn:name":"Now\u0101z",
    "gn:population":0,
    "gn:timezone":"Asia/Kabul",
    "iso:country":"AF",
    "name:und_x_variant":[
        "Nav\u0101z",
        "Navaz",
        "Naw\u0101z",
        "Now\u0101z",
        "\u0646\u0648\u0627\u0632"
    ],
    "wof:name":"Nowaz",
    "wof:placetype":"locality"
},
  "geometry": {"coordinates":[68.18689999999999,33.11667],"type":"Point"}
}