{
  "type": "Feature",
  "properties": {
    "gn:admin1_code":"23",
    "gn:admin2_code":"2401",
    "gn:asciiname":"Pir-e Paymal",
    "gn:country_code":"AF",
    "gn:dem":1026,
    "gn:feature_class":"P",
    "gn:feature_code":"PPL",
    "gn:name":"P\u012br-e P\u0101ym\u0101l",
    "gn:population":0,
    "gn:timezone":"Asia/Kabul",
    "iso:country":"AF",
    "name:fas_x_preferred":[
        "\u067e\u064a\u0631\u0654 \u067e\u0627\u064a\u0645\u0627\u0644"
    ],
    "name:rus_x_preferred":[
        "Piri-Paymal\u2019"
    ],
    "name:und_x_variant":[
        "P\u012br-e P\u0101ym\u0101l",
        "\u067e\u06cc\u0631 \u067e\u0627\u06cc\u0645\u0627\u0644"
    ],
    "wof:name":"Pir-e Paymal",
    "wof:placetype":"locality"
},
  "geometry": {"coordinates":[65.65269000000001,31.64007],"type":"Point"}
}