{
  "type": "Feature",
  "properties": {
    "gn:admin1_code":"32",
    "gn:admin2_code":"1503",
    "gn:asciiname":"Tangi Ya'qub",
    "gn:country_code":"AF",
    "gn:dem":1316,
    "gn:feature_class":"P",
    "gn:feature_code":"PPL",
    "gn:name":"Tang\u012b Ya\u2018q\u016bb",
    "gn:population":0,
    "gn:timezone":"Asia/Kabul",
    "iso:country":"AF",
    "name:und_x_variant":[
        "Tang\u012b Ya\u2018q\u016bb",
        "\u062a\u0646\u06af\u06cc \u06cc\u0639\u0642\u0648\u0628"
    ],
    "wof:name":"Tangi Ya'qub",
    "wof:placetype":"locality"
},
  "geometry": {"coordinates":[67.28663,35.9221],"type":"Point"}
}