{
  "type": "Feature",
  "properties": {
    "gn:admin1_code":"41",
    "gn:admin2_code":"3405.0",
    "gn:asciiname":"Dahan-e Sabzak",
    "gn:country_code":"AF",
    "gn:dem":2344,
    "gn:feature_class":"P",
    "gn:feature_code":"PPL",
    "gn:name":"Dah\u0101n-e Sabzak",
    "gn:population":0,
    "gn:timezone":"Asia/Kabul",
    "iso:country":"AF",
    "name:und_x_variant":[
        "Dah\u0101n-e Sabzak",
        "\u062f\u0647\u0627\u0646 \u0633\u0628\u0632\u06a9",
        "Dahan-e Sabzak"
    ],
    "wof:name":"Dahan-e Sabzak",
    "wof:placetype":"locality"
},
  "geometry": {"coordinates":[65.8147,33.74145],"type":"Point"}
}