{
  "type": "Feature",
  "properties": {
    "gn:admin1_code":"41",
    "gn:admin2_code":"3407.0",
    "gn:asciiname":"Bulbuli",
    "gn:country_code":"AF",
    "gn:dem":2804,
    "gn:feature_class":"P",
    "gn:feature_code":"PPL",
    "gn:name":"Bulbul\u012b",
    "gn:population":0,
    "gn:timezone":"Asia/Kabul",
    "iso:country":"AF",
    "name:und_x_variant":[
        "Bulboli",
        "Bulbul\u012b",
        "Bolbol\u012b",
        "\u0628\u0644\u0628\u0644\u06cc"
    ],
    "wof:name":"Bulbuli",
    "wof:placetype":"locality"
},
  "geometry": {"coordinates":[66.93445,33.90675],"type":"Point"}
}