{
  "type": "Feature",
  "properties": {
    "gn:admin1_code":"10",
    "gn:admin2_code":"2305.0",
    "gn:asciiname":"Buhari Qol",
    "gn:country_code":"AF",
    "gn:dem":2064,
    "gn:feature_class":"P",
    "gn:feature_code":"PPL",
    "gn:name":"Buh\u0101r\u012b Q\u014dl",
    "gn:population":0,
    "gn:timezone":"Asia/Kabul",
    "iso:country":"AF",
    "name:rus_x_preferred":[
        "\u0411\u0443\u0445\u0430\u0440\u0438\u043a\u0443\u043b\u044c"
    ],
    "name:und_x_variant":[
        "Bukharikul\u2019",
        "Boh\u0101\u1e5fi Q\u014dl",
        "Buh\u0101r\u012b Q\u014dl",
        "\u0628\u0647\u0627\u0631\u06cc \u0642\u0648\u0644",
        "Boh\u0101r\u012b Qowl"
    ],
    "wof:name":"Buhari Qol",
    "wof:placetype":"locality"
},
  "geometry": {"coordinates":[65.23891,33.2881],"type":"Point"}
}