{
  "type": "Feature",
  "properties": {
    "gn:admin1_code":"29",
    "gn:admin2_code":"2916.0",
    "gn:asciiname":"Sher 'Ali Kala",
    "gn:country_code":"AF",
    "gn:dem":2052,
    "gn:feature_class":"P",
    "gn:feature_code":"PPL",
    "gn:name":"Sh\u0113r \u2018Al\u012b Kal\u0101",
    "gn:population":0,
    "gn:timezone":"Asia/Kabul",
    "iso:country":"AF",
    "name:und_x_variant":[
        "Se\u1e5f \u2018Ali Kal\u0101",
        "Sheralikala",
        "\u0634\u06cc\u0631\u0639\u0644\u06cc \u06a9\u0644\u0627",
        "Sh\u012br \u2018Al\u012b Kal\u0101",
        "Shayr \u2018Al\u012b Kal\u0101",
        "Sh\u0113r \u2018Al\u012b Kal\u0101"
    ],
    "wof:name":"Sher 'Ali Kala",
    "wof:placetype":"locality"
},
  "geometry": {"coordinates":[68.41332,32.76957],"type":"Point"}
}