{
  "type": "Feature",
  "properties": {
    "gn:admin1_code":"23",
    "gn:admin2_code":"2412.0",
    "gn:asciiname":"Chopanzai",
    "gn:country_code":"AF",
    "gn:dem":1319,
    "gn:feature_class":"P",
    "gn:feature_code":"PPL",
    "gn:name":"Ch\u014dp\u0101nza\u012b",
    "gn:population":0,
    "gn:timezone":"Asia/Kabul",
    "iso:country":"AF",
    "name:und_x_variant":[
        "\u010cop\u0101nzay",
        "Chupanzay",
        "Ch\u014dp\u0101nza\u012b",
        "\u0686\u0648\u067e\u0627\u0646\u0632\u06cc",
        "Chop\u0101nzay"
    ],
    "wof:name":"Chopanzai",
    "wof:placetype":"locality"
},
  "geometry": {"coordinates":[66.59605000000001,31.55967],"type":"Point"}
}