{
  "type": "Feature",
  "properties": {
    "gn:admin1_code":"29",
    "gn:admin2_code":"2901.0",
    "gn:asciiname":"Shahab ud Din",
    "gn:country_code":"AF",
    "gn:dem":2133,
    "gn:feature_class":"P",
    "gn:feature_code":"PPL",
    "gn:name":"Shah\u0101b ud D\u012bn",
    "gn:population":0,
    "gn:timezone":"Asia/Kabul",
    "iso:country":"AF",
    "name:und_x_variant":[
        "\u0160ah\u0101budd\u012bn",
        "Shakhabuddin",
        "\u0634\u0647\u0627\u0628 \u0627\u0644\u062f\u06cc\u0646",
        "Shah\u0101b od D\u012bn",
        "Shah\u0101b ud D\u012bn"
    ],
    "wof:name":"Shahab ud Din",
    "wof:placetype":"locality"
},
  "geometry": {"coordinates":[68.78282,33.19379],"type":"Point"}
}