{
  "type": "Feature",
  "properties": {
    "gn:admin1_code":"05",
    "gn:admin2_code":"2803",
    "gn:asciiname":"Kahmard Wuluswali",
    "gn:country_code":"AF",
    "gn:dem":1748,
    "gn:feature_class":"P",
    "gn:feature_code":"PPL",
    "gn:name":"Kahmard Wulusw\u0101l\u012b",
    "gn:population":0,
    "gn:timezone":"Asia/Kabul",
    "iso:country":"AF",
    "name:und_x_variant":[
        "Kahmard Wolusw\u0101l\u012b",
        "\u06a9\u0647\u0645\u0631\u062f \u0648\u0644\u0633\u0648\u0627\u0644\u06cc",
        "Kahmard Woluswal\u012b",
        "Kahmard",
        "\u06a9\u0647\u0645\u0631\u062f",
        "Kahmard Wulusw\u0101l\u012b"
    ],
    "wof:name":"Kahmard Wuluswali",
    "wof:placetype":"locality"
},
  "geometry": {"coordinates":[67.64182,35.32754],"type":"Point"}
}