{
  "type": "Feature",
  "properties": {
    "gn:admin1_code":"32",
    "gn:admin2_code":"1504",
    "gn:asciiname":"Sandal",
    "gn:country_code":"AF",
    "gn:dem":1508,
    "gn:feature_class":"P",
    "gn:feature_code":"PPL",
    "gn:name":"Sandal",
    "gn:population":0,
    "gn:timezone":"Asia/Kabul",
    "iso:country":"AF",
    "name:und_x_variant":[
        "\u0633\u0646\u062f\u0644"
    ],
    "wof:name":"Sandal",
    "wof:placetype":"locality"
},
  "geometry": {"coordinates":[67.32826,36.11884000000001],"type":"Point"}
}