{
  "type": "Feature",
  "properties": {
    "gn:admin1_code":"23",
    "gn:admin2_code":"2405.0",
    "gn:asciiname":"Tseri Dagh",
    "gn:country_code":"AF",
    "gn:dem":1511,
    "gn:feature_class":"P",
    "gn:feature_code":"PPL",
    "gn:name":"Ts\u0113r\u012b D\u0101gh",
    "gn:population":0,
    "gn:timezone":"Asia/Kabul",
    "iso:country":"AF",
    "name:und_x_variant":[
        "C\u0113\u1e5fi \u1e0e\u0101gh",
        "Cheridag",
        "Ts\u0113r\u012b D\u0101gh",
        "\u0685\u06d0\u0631\u06cc \u062f\u0627\u063a",
        "Ts\u0113\u1e5fi D\u0101gh"
    ],
    "wof:name":"Tseri Dagh",
    "wof:placetype":"locality"
},
  "geometry": {"coordinates":[65.40697,32.15750999999999],"type":"Point"}
}