{
  "type": "Feature",
  "properties": {
    "gn:admin1_code":"26",
    "gn:admin2_code":"1208.0",
    "gn:asciiname":"Sayyidabad",
    "gn:country_code":"AF",
    "gn:dem":1855,
    "gn:feature_class":"P",
    "gn:feature_code":"PPL",
    "gn:name":"Sayyid\u0101b\u0101d",
    "gn:population":0,
    "gn:timezone":"Asia/Kabul",
    "iso:country":"AF",
    "name:und_x_variant":[
        "Saye\u1e0f\u0101b\u0101\u1e0f",
        "Seyyed\u0101b\u0101d",
        "Sayyid\u0101b\u0101d",
        "\u0633\u06cc\u062f \u0622\u0628\u0627\u062f"
    ],
    "wof:name":"Sayyidabad",
    "wof:placetype":"locality"
},
  "geometry": {"coordinates":[69.90239,37.24726],"type":"Point"}
}