{
  "type": "Feature",
  "properties": {
    "gn:admin1_code":"42",
    "gn:admin2_code":"3302",
    "gn:asciiname":"Zardi",
    "gn:country_code":"AF",
    "gn:dem":2040,
    "gn:feature_class":"P",
    "gn:feature_code":"PPL",
    "gn:name":"Zard\u012b",
    "gn:population":0,
    "gn:timezone":"Asia/Kabul",
    "iso:country":"AF",
    "name:rus_x_preferred":[
        "\u0417\u0430\u0440\u0434\u0438"
    ],
    "name:und_x_variant":[
        "Zard\u012b",
        "Zardi",
        "\u0632\u0631\u062f\u06cc"
    ],
    "wof:name":"Zardi",
    "wof:placetype":"locality"
},
  "geometry": {"coordinates":[69.61951999999999,35.35023],"type":"Point"}
}