{
  "type": "Feature",
  "properties": {
    "gn:admin1_code":"27",
    "gn:admin2_code":"407",
    "gn:asciiname":"Siyah Chob",
    "gn:country_code":"AF",
    "gn:dem":2617,
    "gn:feature_class":"P",
    "gn:feature_code":"PPL",
    "gn:name":"Siy\u0101h Ch\u014db",
    "gn:population":0,
    "gn:timezone":"Asia/Kabul",
    "iso:country":"AF",
    "name:und_x_variant":[
        "Syah\u010dob",
        "Siakhchob",
        "S\u012b\u0101h Ch\u014db",
        "S\u012b\u0101h Ch\u016bb",
        "Siy\u0101h Ch\u014db",
        "\u0633\u064a\u0627\u0647 \u0686\u0648\u0628"
    ],
    "wof:name":"Siyah Chob",
    "wof:placetype":"locality"
},
  "geometry": {"coordinates":[68.60715999999999,33.72797],"type":"Point"}
}