{
  "type": "Feature",
  "properties": {
    "gn:admin1_code":"8",
    "gn:admin2_code":"607.0",
    "gn:asciiname":"Baghalah",
    "gn:country_code":"AF",
    "gn:dem":3037,
    "gn:feature_class":"P",
    "gn:feature_code":"PPL",
    "gn:name":"Baghalah",
    "gn:population":0,
    "gn:timezone":"Asia/Kabul",
    "iso:country":"AF",
    "name:rus_x_preferred":[
        "\u0411\u0430\u0433\u0430\u043b\u0430"
    ],
    "name:und_x_variant":[
        "Bagala",
        "Baghala",
        "Baghaleh",
        "\u0628\u063a\u0644\u0647"
    ],
    "wof:name":"Baghalah",
    "wof:placetype":"locality"
},
  "geometry": {"coordinates":[67.65786999999999,33.35505999999999],"type":"Point"}
}