{
  "type": "Feature",
  "properties": {
    "gn:admin1_code":"01",
    "gn:admin2_code":"1126.0",
    "gn:asciiname":"Khar Chang",
    "gn:country_code":"AF",
    "gn:dem":1940,
    "gn:feature_class":"P",
    "gn:feature_code":"PPL",
    "gn:name":"Khar Chang",
    "gn:population":0,
    "gn:timezone":"Asia/Kabul",
    "iso:country":"AF",
    "name:und_x_variant":[
        "Kha\u1e5f Cang",
        "Khar Chang",
        "\u062e\u0631 \u0686\u0646\u06af"
    ],
    "wof:name":"Khar Chang",
    "wof:placetype":"locality"
},
  "geometry": {"coordinates":[70.53144,37.27751],"type":"Point"}
}