{
  "type": "Feature",
  "properties": {
    "gn:admin1_code":"18",
    "gn:admin2_code":"808.0",
    "gn:asciiname":"Rawgay",
    "gn:country_code":"AF",
    "gn:dem":1372,
    "gn:feature_class":"P",
    "gn:feature_code":"PPL",
    "gn:name":"R\u0101wgay",
    "gn:population":0,
    "gn:timezone":"Asia/Kabul",
    "iso:country":"AF",
    "name:und_x_variant":[
        "Raugay",
        "R\u0101wga\u012b",
        "R\u0101wgay",
        "\u0631\u0627\u0648\u06af\u06cc"
    ],
    "wof:name":"Rawgay",
    "wof:placetype":"locality"
},
  "geometry": {"coordinates":[70.45596,34.12316],"type":"Point"}
}