{
  "type": "Feature",
  "properties": {
    "gn:admin1_code":"23",
    "gn:admin2_code":"2414",
    "gn:asciiname":"Zamto Kelay",
    "gn:country_code":"AF",
    "gn:dem":1925,
    "gn:feature_class":"P",
    "gn:feature_code":"PPLA2",
    "gn:name":"Zamt\u014d K\u00ealay",
    "gn:population":0,
    "gn:timezone":"Asia/Kabul",
    "iso:country":"AF",
    "name:und_x_variant":[
        "Zamtukalay",
        "Zamt\u014d K\u00ealay",
        "\u0632\u0645\u062a\u0648 \u06a9\u0644\u06cc",
        "Zamto Kalay",
        "Zamt\u014d",
        "\u0632\u0645\u062a\u0648"
    ],
    "wof:name":"Zamto Kelay",
    "wof:placetype":"locality"
},
  "geometry": {"coordinates":[66.17708,32.3726],"type":"Point"}
}