{
  "type": "Feature",
  "properties": {
    "gn:admin1_code":"05",
    "gn:admin2_code":"2801",
    "gn:asciiname":"Katuk",
    "gn:country_code":"AF",
    "gn:dem":3182,
    "gn:feature_class":"P",
    "gn:feature_code":"PPL",
    "gn:name":"Katuk",
    "gn:population":0,
    "gn:timezone":"Asia/Kabul",
    "iso:country":"AF",
    "name:deu_x_preferred":[
        "Katok"
    ],
    "name:und_x_variant":[
        "K\u0101towk-e Sabz \u0100b",
        "Katok",
        "Katuk",
        "\u06a9\u062a\u06a9"
    ],
    "wof:name":"Katuk",
    "wof:placetype":"locality"
},
  "geometry": {"coordinates":[67.68241999999999,34.7296],"type":"Point"}
}