{
  "type": "Feature",
  "properties": {
    "gn:admin1_code":"37",
    "gn:admin2_code":"3211.0",
    "gn:asciiname":"Muhammad Khan Kelay",
    "gn:country_code":"AF",
    "gn:dem":1207,
    "gn:feature_class":"P",
    "gn:feature_code":"PPL",
    "gn:name":"Mu\u1e29ammad Kh\u0101n K\u00ealay",
    "gn:population":0,
    "gn:timezone":"Asia/Kabul",
    "iso:country":"AF",
    "name:fas_x_preferred":[
        "\u0642\u0631\u064a\u06c0 \u0645\u062d\u0645\u062f \u062e\u0627\u0646"
    ],
    "name:und_x_variant":[
        "Mukhammedkhan-Kalay",
        "Mo\u1e29amme\u1e0f-kh\u0101n Kalay",
        "Mu\u1e29ammad Kh\u0101n K\u00ealay",
        "Mo\u1e29ammad Kh\u0101n Kalay",
        "Mo\u1e29ammad Kh\u0101n K\u00ealay",
        "\u0645\u062d\u0645\u062f \u062e\u0627\u062f \u06a9\u0644\u06cc"
    ],
    "wof:name":"Muhammad Khan Kelay",
    "wof:placetype":"locality"
},
  "geometry": {"coordinates":[69.95281,33.28476],"type":"Point"}
}