{
  "type": "Feature",
  "properties": {
    "gn:admin1_code":"34",
    "gn:admin2_code":"1011.0",
    "gn:asciiname":"Bar Bajgal",
    "gn:country_code":"AF",
    "gn:dem":1216,
    "gn:feature_class":"P",
    "gn:feature_code":"PPL",
    "gn:name":"Bar B\u0101jgal",
    "gn:population":0,
    "gn:timezone":"Asia/Kabul",
    "iso:country":"AF",
    "name:fas_x_preferred":[
        "\u0628\u0631 \u0628\u0627\u062c\u06af\u0644"
    ],
    "name:rus_x_preferred":[
        "Bar-Badzhgal\u2019"
    ],
    "name:und_x_variant":[
        "Bar B\u0101jgal"
    ],
    "wof:name":"Bar Bajgal",
    "wof:placetype":"locality"
},
  "geometry": {"coordinates":[71.01271,34.7939],"type":"Point"}
}