{
  "type": "Feature",
  "properties": {
    "gn:admin1_code":"36",
    "gn:admin2_code":"708",
    "gn:asciiname":"Serangor",
    "gn:country_code":"AF",
    "gn:dem":1958,
    "gn:feature_class":"P",
    "gn:feature_code":"PPL",
    "gn:name":"S\u00earang\u014d\u1e5f",
    "gn:population":0,
    "gn:timezone":"Asia/Kabul",
    "iso:country":"AF",
    "name:und_x_variant":[
        "Se\u1e5fang\u014dr",
        "Serangor",
        "S\u00earang\u014d\u1e5f",
        "Serang\u016b\u1e5f",
        "S\u00earang\u014dr",
        "Sayr Ang\u014dr",
        "\u0633\u0631\u0646\u06af\u0648\u0631",
        "\u0633\u06cc\u0631 \u0627\u0646\u06af\u0648\u0631",
        "\u0633\u0631\u0646\u06af\u0648\u0693"
    ],
    "wof:name":"Serangor",
    "wof:placetype":"locality"
},
  "geometry": {"coordinates":[69.84501999999999,33.73231],"type":"Point"}
}