{
  "type": "Feature",
  "properties": {
    "gn:admin1_code":"01",
    "gn:admin2_code":"1107",
    "gn:asciiname":"Nitsun",
    "gn:country_code":"AF",
    "gn:dem":2948,
    "gn:feature_class":"P",
    "gn:feature_code":"PPL",
    "gn:name":"Nits\u016bn",
    "gn:population":0,
    "gn:timezone":"Asia/Kabul",
    "iso:country":"AF",
    "name:und_x_variant":[
        "Nets\u016bn",
        "\u0646\u062a\u0633\u0648\u0646",
        "Nits\u016bn"
    ],
    "wof:name":"Nitsun",
    "wof:placetype":"locality"
},
  "geometry": {"coordinates":[71.48613,36.67592],"type":"Point"}
}