{
  "type": "Feature",
  "properties": {
    "gn:admin1_code":"05",
    "gn:admin2_code":"2806.0",
    "gn:asciiname":"Qol-e Bayan-e Burnah",
    "gn:country_code":"AF",
    "gn:dem":2982,
    "gn:feature_class":"P",
    "gn:feature_code":"PPL",
    "gn:name":"Q\u014dl-e Bay\u0101n-e Burnah",
    "gn:population":0,
    "gn:timezone":"Asia/Kabul",
    "iso:country":"AF",
    "name:und_x_variant":[
        "Kuli-Bayani-Burna",
        "Q\u014dle Bay\u0101ne Bu\u1e5fna",
        "Q\u014dl-e Bay\u0101n-e Burnah",
        "Qowl-e Bay\u0101n-e Borneh",
        "\u0642\u0648\u0644 \u0628\u06cc\u0627\u0646 \u0628\u0631\u0646\u0647"
    ],
    "wof:name":"Qol-e Bayan-e Burnah",
    "wof:placetype":"locality"
},
  "geometry": {"coordinates":[67.22104,34.27099],"type":"Point"}
}