{
  "type": "Feature",
  "properties": {
    "gn:admin1_code":"6",
    "gn:admin2_code":"2104.0",
    "gn:asciiname":"Baharkhan",
    "gn:country_code":"AF",
    "gn:dem":2650,
    "gn:feature_class":"P",
    "gn:feature_code":"PPL",
    "gn:name":"Bah\u0101rkh\u0101n",
    "gn:population":0,
    "gn:timezone":"Asia/Kabul",
    "iso:country":"AF",
    "name:und_x_variant":[
        "Bakharkhan",
        "Bah\u0101rkh\u0101n",
        "\u0628\u0647\u0627\u0631\u062e\u0627\u0646"
    ],
    "wof:name":"Baharkhan",
    "wof:placetype":"locality"
},
  "geometry": {"coordinates":[64.27786,33.04079],"type":"Point"}
}