{
  "type": "Feature",
  "properties": {
    "gn:admin1_code":"28",
    "gn:admin2_code":"2506.0",
    "gn:asciiname":"Khanizai",
    "gn:country_code":"AF",
    "gn:dem":1235,
    "gn:feature_class":"P",
    "gn:feature_code":"PPL",
    "gn:name":"Kh\u0101niza\u012b",
    "gn:population":0,
    "gn:timezone":"Asia/Kabul",
    "iso:country":"AF",
    "name:und_x_variant":[
        "Khanizay",
        "\u062e\u0627\u0646\u0632\u06cc",
        "Kh\u0101n\u012bzay",
        "Kh\u0101niza\u012b",
        "Kh\u0101nizay"
    ],
    "wof:name":"Khanizai",
    "wof:placetype":"locality"
},
  "geometry": {"coordinates":[66.27404,31.78247],"type":"Point"}
}