{
  "type": "Feature",
  "properties": {
    "gn:admin1_code":"10",
    "gn:admin2_code":"2306",
    "gn:asciiname":"Shaykh 'Ali",
    "gn:country_code":"AF",
    "gn:dem":988,
    "gn:feature_class":"P",
    "gn:feature_code":"PPL",
    "gn:name":"Shaykh \u2018Al\u012b",
    "gn:population":0,
    "gn:timezone":"Asia/Kabul",
    "iso:country":"AF",
    "name:und_x_variant":[
        "\u0160\u0113kh \u2018Al\u012b",
        "Sheykh-Ali",
        "Shaykh \u2018Al\u012b",
        "\u0634\u06cc\u062e \u0639\u0644\u06cc",
        "Sheykh \u2018Al\u012b"
    ],
    "wof:name":"Shaykh 'Ali",
    "wof:placetype":"locality"
},
  "geometry": {"coordinates":[64.58199999999999,32.10478],"type":"Point"}
}