{
  "type": "Feature",
  "properties": {
    "gn:admin1_code":"29",
    "gn:admin2_code":"2908",
    "gn:asciiname":"Ranah Tazay",
    "gn:country_code":"AF",
    "gn:dem":2552,
    "gn:feature_class":"P",
    "gn:feature_code":"PPL",
    "gn:name":"Ra\u1e49ah Tazay",
    "gn:population":0,
    "gn:timezone":"Asia/Kabul",
    "iso:country":"AF",
    "name:und_x_variant":[
        "Ranatazzay",
        "\u1e5ea\u1e49a Tazzay",
        "Ra\u1e49ah Tazay",
        "Ranah Tazzay",
        "\u0631\u06bc\u0647 \u062a\u0632\u06cc"
    ],
    "wof:name":"Ranah Tazay",
    "wof:placetype":"locality"
},
  "geometry": {"coordinates":[69.01385999999999,32.76752],"type":"Point"}
}