{
  "type": "Feature",
  "properties": {
    "gn:admin1_code":"13",
    "gn:admin2_code":"114.0",
    "gn:asciiname":"Rahmatabad",
    "gn:country_code":"AF",
    "gn:dem":1841,
    "gn:feature_class":"P",
    "gn:feature_code":"PPL",
    "gn:name":"Ra\u1e29mat\u0101b\u0101d",
    "gn:population":0,
    "gn:timezone":"Asia/Kabul",
    "iso:country":"AF",
    "name:ceb_x_preferred":[
        "Rahmatabad"
    ],
    "name:fas_x_preferred":[
        "\u0631\u062d\u0645\u062a\u200c\u0622\u0628\u0627\u062f"
    ],
    "name:swe_x_preferred":[
        "Rahmatabad"
    ],
    "name:und_x_variant":[
        "Rakhmatabad",
        "Ra\u1e29mat\u0101b\u0101d",
        "\u0631\u062d\u0645\u062a \u0627\u0628\u0627\u062f"
    ],
    "wof:name":"Rahmatabad",
    "wof:placetype":"locality"
},
  "geometry": {"coordinates":[69.14972,34.32208],"type":"Point"}
}