{
  "type": "Feature",
  "properties": {
    "gn:admin1_code":"28",
    "gn:admin2_code":"2501.0",
    "gn:asciiname":"Tsirayludin",
    "gn:country_code":"AF",
    "gn:dem":1852,
    "gn:feature_class":"P",
    "gn:feature_code":"PPL",
    "gn:name":"Tsirayludin",
    "gn:population":0,
    "gn:timezone":"Asia/Kabul",
    "iso:country":"AF",
    "name:fas_x_preferred":[
        "\u0686\u06cc\u0631\u06cc \u0644\u0648\u062f\u064a\u0646"
    ],
    "name:und_x_variant":[
        "Ceray L\u016b\u1e0f\u012bn",
        "Che\u1e5fay L\u016b\u1e0f\u012bn",
        "Tsirayludin",
        "Ts\u0113\u1e5f\u00eay L\u016bd\u012bn",
        "\u0685\u06d0\u0693\u06cd \u0644\u0648\u062f\u06cc\u0646",
        "Ts\u0113\u1e5fay Lowd\u012bn"
    ],
    "wof:name":"Tsirayludin",
    "wof:placetype":"locality"
},
  "geometry": {"coordinates":[66.77356999999999,32.29932],"type":"Point"}
}