{
  "type": "Feature",
  "properties": {
    "gn:admin1_code":"11",
    "gn:admin2_code":"2014",
    "gn:asciiname":"Pay Kushk",
    "gn:country_code":"AF",
    "gn:dem":1069,
    "gn:feature_class":"P",
    "gn:feature_code":"PPL",
    "gn:name":"P\u0101y Kushk",
    "gn:population":0,
    "gn:timezone":"Asia/Kabul",
    "iso:country":"AF",
    "name:fas_x_preferred":[
        "\u067e\u0627\u06cc \u0643\u0648\u0634\u0643"
    ],
    "name:und_x_variant":[
        "P\u0101y Koshk",
        "Paykushk",
        "P\u0101y Ku\u0161k",
        "P\u0101y K\u016bshk",
        "P\u0101y Kushk",
        "\u067e\u0627\u06cc \u06a9\u0634\u06a9",
        "\u067e\u0627\u06cc \u0643\u0648\u0634\u0643"
    ],
    "wof:name":"Pay Kushk",
    "wof:placetype":"locality"
},
  "geometry": {"coordinates":[62.15262,33.29356],"type":"Point"}
}