{
  "type": "Feature",
  "properties": {
    "gn:admin1_code":"29",
    "gn:admin2_code":"2917",
    "gn:asciiname":"Derakht-e Yahya",
    "gn:cc2":"AF",
    "gn:country_code":"AF",
    "gn:dem":2116,
    "gn:feature_class":"P",
    "gn:feature_code":"PPL",
    "gn:name":"Derakht-e Ya\u1e29y\u00e1",
    "gn:population":0,
    "gn:timezone":"Asia/Kabul",
    "iso:country":"AF",
    "name:und_x_variant":[
        "Darakht-e Ya\u1e29y\u00e1",
        "Seyyed\u0101n Derakht-e Ya\u1e29ya",
        "Yehya Wana",
        "Yahya Wana Post",
        "Ya\u1e29y\u00e1 Vannah",
        "Yahya",
        "Derakht-e Ya\u1e29y\u00e1"
    ],
    "wof:name":"Derakht-e Yahya",
    "wof:placetype":"locality"
},
  "geometry": {"coordinates":[68.13333,31.81667],"type":"Point"}
}