{
  "type": "Feature",
  "properties": {
    "iso:country":"AF",
    "name:und_x_variant":[
        "Al\u0101\u2019u\u1e0f\u1e0f\u012bne B\u0101l\u0101"
    ],
    "qs:gn_country":"AF",
    "qs:gn_fcode":"PPLX",
    "qs:gn_pop":0,
    "qs:name":"\u2018Al\u0101' od D\u012bn-e B\u0101l\u0101",
    "qs:name_adm0":"Afghanistan",
    "qs:name_adm1":"Kabul",
    "qs:photos":158,
    "qs:photos_1k":32,
    "qs:photos_9k":1,
    "qs:photos_9r":4,
    "qs:photos_all":158,
    "qs:photos_sr":4,
    "qs:placetype":"Suburb",
    "qs:pop_sr":"0",
    "qs:woe_adm0":23424739,
    "wof:name":"\u2018Al\u0101' od D\u012bn-e B\u0101l\u0101",
    "wof:placetype":"neighbourhood"
},
  "geometry": {"coordinates":[69.13028,34.48833],"type":"Point"}
}