{
  "type": "Feature",
  "properties": {
    "gn:admin1_code":"11",
    "gn:admin2_code":"2003",
    "gn:asciiname":"Gosh Mir",
    "gn:country_code":"AF",
    "gn:dem":919,
    "gn:feature_class":"P",
    "gn:feature_code":"PPL",
    "gn:name":"G\u014dsh M\u012br",
    "gn:population":0,
    "gn:timezone":"Asia/Kabul",
    "iso:country":"AF",
    "name:und_x_variant":[
        "Go\u0161 M\u012br",
        "G\u014dsh M\u012br",
        "Gushmir",
        "\u06af\u0648\u0634 \u0645\u06cc\u0631",
        "G\u016bsh M\u012br"
    ],
    "wof:name":"Gosh Mir",
    "wof:placetype":"locality"
},
  "geometry": {"coordinates":[62.15628,34.27263],"type":"Point"}
}