{
  "type": "Feature",
  "properties": {
    "gn:admin1_code":"10",
    "gn:admin2_code":"2302",
    "gn:asciiname":"Faqir Pa'in Kelay",
    "gn:country_code":"AF",
    "gn:dem":817,
    "gn:feature_class":"P",
    "gn:feature_code":"PPL",
    "gn:name":"Faq\u012br P\u0101\u2019\u012bn K\u00ealay",
    "gn:population":0,
    "gn:timezone":"Asia/Kabul",
    "iso:country":"AF",
    "name:und_x_variant":[
        "Fakirpayan-Kalay",
        "Faq\u012br P\u0101\u2019\u012bn K\u00ealay",
        "\u0641\u0642\u06cc\u0631 \u067e\u0627\u0626\u06cc\u0646 \u06a9\u0644\u06cc",
        "Faq\u012b\u1e5f P\u0101y\u0101n Kalay"
    ],
    "wof:name":"Faqir Pa'in Kelay",
    "wof:placetype":"locality"
},
  "geometry": {"coordinates":[64.5256,31.76503],"type":"Point"}
}