{
  "type": "Feature",
  "properties": {
    "gn:admin1_code":"05",
    "gn:admin2_code":"2805.0",
    "gn:asciiname":"Tak Tekah",
    "gn:country_code":"AF",
    "gn:dem":3174,
    "gn:feature_class":"P",
    "gn:feature_code":"PPL",
    "gn:name":"Tak Tekah",
    "gn:population":0,
    "gn:timezone":"Asia/Kabul",
    "iso:country":"AF",
    "wof:name":"Tak Tekah",
    "wof:placetype":"locality"
},
  "geometry": {"coordinates":[67.36794999999999,34.35666],"type":"Point"}
}