{
  "type": "Feature",
  "properties": {
    "gn:admin1_code":"28",
    "gn:admin2_code":"2501",
    "gn:asciiname":"Mandeh",
    "gn:country_code":"AF",
    "gn:dem":1646,
    "gn:feature_class":"P",
    "gn:feature_code":"PPL",
    "gn:name":"M\u0101nd\u00eah",
    "gn:population":0,
    "gn:timezone":"Asia/Kabul",
    "iso:country":"AF",
    "name:und_x_variant":[
        "Mandekh",
        "M\u0101n\u1e0f\u0113h",
        "M\u0101nd\u00eah",
        "\u0645\u0627\u0646\u062f\u0647",
        "M\u0101ndah"
    ],
    "wof:name":"Mandeh",
    "wof:placetype":"locality"
},
  "geometry": {"coordinates":[67.00411,32.09592],"type":"Point"}
}