{
  "type": "Feature",
  "properties": {
    "gn:admin1_code":"30",
    "gn:admin2_code":"1613",
    "gn:asciiname":"Taghir Patah",
    "gn:country_code":"AF",
    "gn:dem":293,
    "gn:feature_class":"P",
    "gn:feature_code":"PPL",
    "gn:name":"T\u0101ghir Patah",
    "gn:population":0,
    "gn:timezone":"Asia/Kabul",
    "iso:country":"AF",
    "name:und_x_variant":[
        "Tagirpata",
        "T\u0101ghir Pata",
        "T\u0101ghir Patah",
        "\u062a\u0627\u063a\u0631 \u067e\u062a\u0647"
    ],
    "name:uzb_x_preferred":[
        "Tog\u2018irpata"
    ],
    "wof:name":"Taghir Patah",
    "wof:placetype":"locality"
},
  "geometry": {"coordinates":[67.26815999999999,37.15683],"type":"Point"}
}