{
  "type": "Feature",
  "properties": {
    "gn:admin1_code":"30",
    "gn:admin2_code":"1615",
    "gn:asciiname":"Rijan",
    "gn:country_code":"AF",
    "gn:dem":1237,
    "gn:feature_class":"P",
    "gn:feature_code":"PPL",
    "gn:name":"Rijan",
    "gn:population":0,
    "gn:timezone":"Asia/Kabul",
    "iso:country":"AF",
    "name:fas_x_preferred":[
        "\u0631\u064a\u062c\u0646"
    ],
    "name:fas_x_variant":[
        "\u0631\u06cc\u062c\u0627\u0646"
    ],
    "name:rus_x_preferred":[
        "\u0420\u0438\u0434\u0436\u0430\u043d"
    ],
    "name:und_x_variant":[
        "Ridzhan",
        "R\u012bjan",
        "Rijan",
        "\u0631\u062c\u0646"
    ],
    "wof:name":"Rijan",
    "wof:placetype":"locality"
},
  "geometry": {"coordinates":[67.19293,36.55207],"type":"Point"}
}