{
  "type": "Feature",
  "properties": {
    "gn:admin1_code":"08",
    "gn:admin2_code":"614",
    "gn:asciiname":"Seh Pay",
    "gn:country_code":"AF",
    "gn:dem":2083,
    "gn:feature_class":"P",
    "gn:feature_code":"PPL",
    "gn:name":"Seh P\u0101y",
    "gn:population":0,
    "gn:timezone":"Asia/Kabul",
    "iso:country":"AF",
    "name:fas_x_preferred":[
        "\u0633\u0647 \u067e\u0627\u06cc"
    ],
    "name:und_x_variant":[
        "Sikhpay",
        "Seh P\u0101y"
    ],
    "wof:name":"Seh Pay",
    "wof:placetype":"locality"
},
  "geometry": {"coordinates":[68.42358,33.34797],"type":"Point"}
}