{
  "type": "Feature",
  "properties": {
    "gn:admin1_code":"18",
    "gn:admin2_code":"806",
    "gn:asciiname":"Khafizan",
    "gn:country_code":"AF",
    "gn:dem":909,
    "gn:feature_class":"P",
    "gn:feature_code":"PPLA2",
    "gn:name":"Khafizan",
    "gn:population":0,
    "gn:timezone":"Asia/Kabul",
    "iso:country":"AF",
    "name:und_x_variant":[
        "\u1e28\u0101fez\u0327\u0101n",
        "\u1e28\u0101fiz\u0327\u0101n",
        "\u062d\u0627\u0641\u0638\u0627\u0646"
    ],
    "wof:name":"Khafizan",
    "wof:placetype":"locality"
},
  "geometry": {"coordinates":[70.37246999999998,34.28665],"type":"Point"}
}