{
  "type": "Feature",
  "properties": {
    "gn:admin1_code":"01",
    "gn:admin2_code":"1103",
    "gn:asciiname":"Ter Giran",
    "gn:country_code":"AF",
    "gn:dem":1832,
    "gn:feature_class":"P",
    "gn:feature_code":"PPL",
    "gn:name":"T\u0113r Gir\u0101n",
    "gn:population":0,
    "gn:timezone":"Asia/Kabul",
    "iso:country":"AF",
    "name:und_x_variant":[
        "T\u0113\u1e5f Ge\u1e5f\u0101n",
        "\u062a\u06d0\u0631 \u06af\u0631\u0627\u0646",
        "T\u012br Ger\u0101n",
        "T\u0113r Gir\u0101n"
    ],
    "wof:name":"Ter Giran",
    "wof:placetype":"locality"
},
  "geometry": {"coordinates":[70.88661999999999,36.68039],"type":"Point"}
}