{
  "type": "Feature",
  "properties": {
    "gn:admin1_code":"03",
    "gn:admin2_code":"1309",
    "gn:asciiname":"Qajir Khanah",
    "gn:country_code":"AF",
    "gn:dem":1337,
    "gn:feature_class":"P",
    "gn:feature_code":"PPL",
    "gn:name":"Qaj\u012br Kh\u0101nah",
    "gn:population":0,
    "gn:timezone":"Asia/Kabul",
    "iso:country":"AF",
    "name:und_x_variant":[
        "Qaj\u012b\u1e5fkh\u0101na",
        "Qaj\u012br Kh\u0101neh",
        "Qaj\u012br Kh\u0101nah",
        "\u0642\u062c\u06cc\u0631 \u062e\u0627\u0646\u0647"
    ],
    "wof:name":"Qajir Khanah",
    "wof:placetype":"locality"
},
  "geometry": {"coordinates":[69.04286999999999,35.96086],"type":"Point"}
}