{
  "type": "Feature",
  "properties": {
    "gn:admin1_code":"01",
    "gn:admin2_code":"1122.0",
    "gn:asciiname":"Busht",
    "gn:country_code":"AF",
    "gn:dem":1819,
    "gn:feature_class":"P",
    "gn:feature_code":"PPL",
    "gn:name":"B\u016bsht",
    "gn:population":0,
    "gn:timezone":"Asia/Kabul",
    "iso:country":"AF",
    "name:und_x_variant":[
        "B\u016b\u0161t",
        "B\u016bsht",
        "\u0628\u0648\u0634\u062a"
    ],
    "wof:name":"Busht",
    "wof:placetype":"locality"
},
  "geometry": {"coordinates":[71.065,37.04167],"type":"Point"}
}