{
  "type": "Feature",
  "properties": {
    "gn:admin1_code":"39",
    "gn:admin2_code":"2603",
    "gn:asciiname":"Rahm Quli",
    "gn:country_code":"AF",
    "gn:dem":2641,
    "gn:feature_class":"P",
    "gn:feature_code":"PPL",
    "gn:name":"Ra\u1e29m Qul\u012b",
    "gn:population":0,
    "gn:timezone":"Asia/Kabul",
    "iso:country":"AF",
    "name:und_x_variant":[
        "Ra\u1e29m Qul\u012b",
        "\u0631\u062d\u0645 \u0642\u0644\u06cc"
    ],
    "wof:name":"Rahm Quli",
    "wof:placetype":"locality"
},
  "geometry": {"coordinates":[66.65229000000001,33.20419],"type":"Point"}
}