{
  "type": "Feature",
  "properties": {
    "gn:admin1_code":"05",
    "gn:admin2_code":"2806.0",
    "gn:asciiname":"Shinyah Sabzi",
    "gn:country_code":"AF",
    "gn:dem":2601,
    "gn:feature_class":"P",
    "gn:feature_code":"PPL",
    "gn:name":"Sh\u012bnyah Sabz\u012b",
    "gn:population":0,
    "gn:timezone":"Asia/Kabul",
    "iso:country":"AF",
    "name:rus_x_preferred":[
        "Shin\u2019yasabzi"
    ],
    "name:und_x_variant":[
        "\u0160inya Sabzi",
        "Shaynah Sabz\u012b",
        "Sh\u012bnyeh Sabz\u012b",
        "Sh\u012bnyah Sabz\u012b",
        "\u0634\u0646\u06cc\u0647 \u0633\u0628\u0632\u06cc"
    ],
    "wof:name":"Shinyah Sabzi",
    "wof:placetype":"locality"
},
  "geometry": {"coordinates":[67.19553000000001,34.26002],"type":"Point"}
}