{
  "type": "Feature",
  "properties": {
    "gn:admin1_code":"27",
    "gn:admin2_code":"407",
    "gn:asciiname":"Naveshor",
    "gn:country_code":"AF",
    "gn:dem":2418,
    "gn:feature_class":"P",
    "gn:feature_code":"PPL",
    "gn:name":"Naveshor",
    "gn:population":0,
    "gn:timezone":"Asia/Kabul",
    "iso:country":"AF",
    "name:und_x_variant":[
        "Naw\u0113 \u0160or",
        "Naw\u0113 S\u0332h\u0332\u014dr",
        "Naw\u0113 S\u0332h\u0332\u016br",
        "Now\u0113 S\u0332h\u0332\u014dr",
        "\u0646\u0648\u06d0 \u069a\u0648\u0631"
    ],
    "wof:name":"Naveshor",
    "wof:placetype":"locality"
},
  "geometry": {"coordinates":[68.61162,33.82562],"type":"Point"}
}