{
  "type": "Feature",
  "properties": {
    "gn:admin1_code":"08",
    "gn:admin2_code":"605",
    "gn:asciiname":"Dungah",
    "gn:country_code":"AF",
    "gn:dem":2857,
    "gn:feature_class":"P",
    "gn:feature_code":"PPL",
    "gn:name":"\u1e0eungah",
    "gn:population":0,
    "gn:timezone":"Asia/Kabul",
    "iso:country":"AF",
    "name:und_x_variant":[
        "Dunga",
        "\u1e0eongah",
        "\u1e0eungah",
        "\u0689\u0646\u06af\u0647"
    ],
    "wof:name":"Dungah",
    "wof:placetype":"locality"
},
  "geometry": {"coordinates":[67.35086,33.59366],"type":"Point"}
}