{
  "type": "Feature",
  "properties": {
    "gn:admin1_code":"03",
    "gn:admin2_code":"1307",
    "gn:asciiname":"Dawuti",
    "gn:country_code":"AF",
    "gn:dem":1528,
    "gn:feature_class":"P",
    "gn:feature_code":"PPL",
    "gn:name":"D\u0101wut\u012b",
    "gn:population":0,
    "gn:timezone":"Asia/Kabul",
    "iso:country":"AF",
    "name:und_x_variant":[
        "D\u0101wut\u012b",
        "\u062f\u0627\u0648\u062a\u06cc",
        "D\u0101woti"
    ],
    "wof:name":"Dawuti",
    "wof:placetype":"locality"
},
  "geometry": {"coordinates":[69.13332,35.60978],"type":"Point"}
}