{
  "type": "Feature",
  "properties": {
    "gn:admin1_code":"29",
    "gn:admin2_code":"2912.0",
    "gn:asciiname":"Salam Khan Kelay",
    "gn:country_code":"AF",
    "gn:dem":2057,
    "gn:feature_class":"P",
    "gn:feature_code":"PPL",
    "gn:name":"Sal\u0101m Kh\u0101n K\u00ealay",
    "gn:population":0,
    "gn:timezone":"Asia/Kabul",
    "iso:country":"AF",
    "name:und_x_variant":[
        "Salamkhankalay",
        "\u0633\u0644\u0627\u0645 \u062e\u0627\u0646 \u06a9\u0644\u06cc",
        "Sal\u0101m Kh\u0101n Kalay",
        "Sal\u0101m Kh\u0101n K\u00ealay"
    ],
    "wof:name":"Salam Khan Kelay",
    "wof:placetype":"locality"
},
  "geometry": {"coordinates":[69.37518,33.1594],"type":"Point"}
}