{
  "type": "Feature",
  "properties": {
    "gn:admin1_code":"01",
    "gn:admin2_code":"1116.0",
    "gn:asciiname":"Alani",
    "gn:country_code":"AF",
    "gn:dem":1496,
    "gn:feature_class":"P",
    "gn:feature_code":"PPL",
    "gn:name":"Al\u0101n\u012b",
    "gn:population":0,
    "gn:timezone":"Asia/Kabul",
    "iso:country":"AF",
    "name:und_x_variant":[
        "Al\u0101n\u012b",
        "\u0627\u0644\u0627\u0646\u06cc",
        "All\u0101ni"
    ],
    "wof:name":"Alani",
    "wof:placetype":"locality"
},
  "geometry": {"coordinates":[70.23336999999999,37.01162],"type":"Point"}
}