{
  "type": "Feature",
  "properties": {
    "gn:admin1_code":"11",
    "gn:admin2_code":"2014.0",
    "gn:asciiname":"Barikzai",
    "gn:country_code":"AF",
    "gn:dem":1061,
    "gn:feature_class":"P",
    "gn:feature_code":"PPL",
    "gn:name":"B\u0101rikza\u012b",
    "gn:population":0,
    "gn:timezone":"Asia/Kabul",
    "iso:country":"AF",
    "name:fas_x_preferred":[
        "\u0628\u0627\u0631\u0643\u0632\u06cc"
    ],
    "name:und_x_variant":[
        "B\u0101rekz\u0101\u2019i",
        "B\u0101rikza\u012b",
        "\u0628\u0627\u0631\u06a9\u0632\u06cc",
        "B\u0101r\u012bk Z\u0101\u2019\u012b",
        "\u0628\u0627\u0631\u06cc\u06a9 \u0632\u0627\u0626\u06cc"
    ],
    "wof:name":"Barikzai",
    "wof:placetype":"locality"
},
  "geometry": {"coordinates":[62.15035,33.28038],"type":"Point"}
}