{
  "type": "Feature",
  "properties": {
    "gn:admin1_code":"8",
    "gn:admin2_code":"608.0",
    "gn:asciiname":"Shamali Abul Kala",
    "gn:country_code":"AF",
    "gn:dem":2014,
    "gn:feature_class":"P",
    "gn:feature_code":"PPL",
    "gn:name":"Sham\u0101l\u012b Abul Kal\u0101",
    "gn:population":0,
    "gn:timezone":"Asia/Kabul",
    "iso:country":"AF",
    "name:rus_x_preferred":[
        "Shamali-Abdul\u2019kala"
    ],
    "name:und_x_variant":[
        "\u0160am\u0101li Abul Kal\u0101",
        "Sham\u0101l\u012b Abul Kal\u0101",
        "\u0634\u0645\u0627\u0644\u06cc \u0627\u0628\u0644 \u06a9\u0644\u0627",
        "Shom\u0101l\u012b Abol Kal\u0101"
    ],
    "wof:name":"Shamali Abul Kala",
    "wof:placetype":"locality"
},
  "geometry": {"coordinates":[67.78944,32.85270999999999],"type":"Point"}
}