{
  "type": "Feature",
  "properties": {
    "gn:admin1_code":"27",
    "gn:admin2_code":"407",
    "gn:asciiname":"Randzai Khel",
    "gn:country_code":"AF",
    "gn:dem":1997,
    "gn:feature_class":"P",
    "gn:feature_code":"PPL",
    "gn:name":"Randza\u012b Kh\u0113l",
    "gn:population":0,
    "gn:timezone":"Asia/Kabul",
    "iso:country":"AF",
    "name:und_x_variant":[
        "Ranj\u0101y Kheyl",
        "\u1e5eanjaykh\u0113l",
        "Randz\u0101y Kheyl",
        "Randza\u012b Kh\u0113l",
        "\u0631\u0646\u0681\u06cc \u062e\u06d0\u0644"
    ],
    "wof:name":"Randzai Khel",
    "wof:placetype":"locality"
},
  "geometry": {"coordinates":[68.81865999999999,33.99321],"type":"Point"}
}