{
  "type": "Feature",
  "properties": {
    "gn:admin1_code":"34",
    "gn:admin2_code":"1009.0",
    "gn:asciiname":"Sulaiman Shah",
    "gn:country_code":"AF",
    "gn:dem":1781,
    "gn:feature_class":"P",
    "gn:feature_code":"PPL",
    "gn:name":"Sula\u012bm\u0101n Sh\u0101h",
    "gn:population":0,
    "gn:timezone":"Asia/Kabul",
    "iso:country":"AF",
    "name:heb_x_preferred":[
        "\u05e1\u05dc\u05d9\u05de\u05d0\u05df \u05e9\u05d0\u05d4"
    ],
    "name:und_x_variant":[
        "Sol\u0113m\u0101n\u0161\u0101h",
        "Suleymanshakh",
        "Sal\u0113m\u0101nsh\u0101h",
        "Sula\u012bm\u0101n Sh\u0101h",
        "\u0633\u0644\u06cc\u0645\u0627\u0646 \u0634\u0627\u0647"
    ],
    "name:urd_x_preferred":[
        "\u0634\u06c1\u0627\u0628 \u0627\u0644\u062f\u06cc\u0646 \u0633\u0644\u06cc\u0645\u0627\u0646 \u0634\u0627\u06c1"
    ],
    "wof:name":"Sulaiman Shah",
    "wof:placetype":"locality"
},
  "geometry": {"coordinates":[70.76208000000003,34.89149],"type":"Point"}
}