{
  "type": "Feature",
  "properties": {
    "gn:admin1_code":"26",
    "gn:admin2_code":"1212.0",
    "gn:asciiname":"Tam 'Ali",
    "gn:country_code":"AF",
    "gn:dem":524,
    "gn:feature_class":"P",
    "gn:feature_code":"PPL",
    "gn:name":"Tam \u2018Al\u012b",
    "gn:population":0,
    "gn:timezone":"Asia/Kabul",
    "iso:country":"AF",
    "name:und_x_variant":[
        "Tam \u2018Al\u012b",
        "\u062a\u0645 \u0639\u0644\u06cc"
    ],
    "wof:name":"Tam 'Ali",
    "wof:placetype":"locality"
},
  "geometry": {"coordinates":[69.47556,37.05147],"type":"Point"}
}