{
  "type": "Feature",
  "properties": {
    "gn:admin1_code":"11",
    "gn:admin2_code":"2014",
    "gn:asciiname":"Jiz Gharah",
    "gn:country_code":"AF",
    "gn:dem":1842,
    "gn:feature_class":"P",
    "gn:feature_code":"PPL",
    "gn:name":"Jiz Gharah",
    "gn:population":0,
    "gn:timezone":"Asia/Kabul",
    "iso:country":"AF",
    "name:und_x_variant":[
        "\u062c\u0632 \u063a\u0631\u0647",
        "Jez Gharah"
    ],
    "wof:name":"Jiz Gharah",
    "wof:placetype":"locality"
},
  "geometry": {"coordinates":[62.87331999999999,33.48589],"type":"Point"}
}