{
  "type": "Feature",
  "properties": {
    "gn:admin1_code":"23",
    "gn:admin2_code":"2410",
    "gn:asciiname":"Shaykhzi",
    "gn:country_code":"AF",
    "gn:dem":998,
    "gn:feature_class":"P",
    "gn:feature_code":"PPL",
    "gn:name":"Shaykhz\u012b",
    "gn:population":0,
    "gn:timezone":"Asia/Kabul",
    "iso:country":"AF",
    "name:und_x_variant":[
        "S\u0113khzi",
        "Sheykhz\u012b",
        "Sh\u0113khza\u012b",
        "Shaykhz\u012b",
        "\u0634\u06cc\u062e\u0632\u06cc"
    ],
    "wof:name":"Shaykhzi",
    "wof:placetype":"locality"
},
  "geometry": {"coordinates":[66.09784999999999,30.19004],"type":"Point"}
}