{
  "type": "Feature",
  "properties": {
    "gn:admin1_code":"7",
    "gn:admin2_code":"1804.0",
    "gn:asciiname":"Sawur",
    "gn:country_code":"AF",
    "gn:dem":1279,
    "gn:feature_class":"P",
    "gn:feature_code":"PPL",
    "gn:name":"Saw\u016br",
    "gn:population":0,
    "gn:timezone":"Asia/Kabul",
    "iso:country":"AF",
    "name:fas_x_preferred":[
        "\u0633\u0648\u0631"
    ],
    "name:und_x_variant":[
        "Saw\u016b\u1e5f",
        "\u015eab\u016br",
        "Saw\u016br",
        "\u0633\u0648\u0648\u0631",
        "Sowar"
    ],
    "wof:name":"Sawur",
    "wof:placetype":"locality"
},
  "geometry": {"coordinates":[64.34772,35.70348],"type":"Point"}
}