{
  "type": "Feature",
  "properties": {
    "gn:admin1_code":"35",
    "gn:admin2_code":"903.0",
    "gn:asciiname":"Aram Khel",
    "gn:country_code":"AF",
    "gn:dem":980,
    "gn:feature_class":"P",
    "gn:feature_code":"PPL",
    "gn:name":"Ar\u0101m Kh\u0113l",
    "gn:population":0,
    "gn:timezone":"Asia/Kabul",
    "iso:country":"AF",
    "name:rus_x_preferred":[
        "Aramkheyl\u2019"
    ],
    "name:und_x_variant":[
        "A\u1e5f\u0101mkh\u0113l",
        "\u0627\u0631\u0627\u0645 \u062e\u06d0\u0644",
        "\u0100r\u0101mkheyl",
        "Ar\u0101m Kh\u0113l",
        "\u0100r\u0101m Kh\u0113l"
    ],
    "wof:name":"Aram Khel",
    "wof:placetype":"locality"
},
  "geometry": {"coordinates":[70.37281999999998,34.7732],"type":"Point"}
}