{
  "type": "Feature",
  "properties": {
    "gn:admin1_code":"07",
    "gn:admin2_code":"1807",
    "gn:asciiname":"Dobah",
    "gn:country_code":"AF",
    "gn:dem":1312,
    "gn:feature_class":"P",
    "gn:feature_code":"PPL",
    "gn:name":"D\u014dbah",
    "gn:population":0,
    "gn:timezone":"Asia/Kabul",
    "iso:country":"AF",
    "name:und_x_variant":[
        "\u1e0e\u014dbah",
        "Do\u0101b",
        "Do \u0100beh",
        "D\u014dbah",
        "\u062f\u0648\u0628\u0647"
    ],
    "wof:name":"Dobah",
    "wof:placetype":"locality"
},
  "geometry": {"coordinates":[65.24799,35.73751],"type":"Point"}
}