{
  "type": "Feature",
  "properties": {
    "gn:admin1_code":"10",
    "gn:admin2_code":"2309.0",
    "gn:asciiname":"Dastagir Khan Kelay",
    "gn:country_code":"AF",
    "gn:dem":732,
    "gn:feature_class":"P",
    "gn:feature_code":"PPL",
    "gn:name":"Dastag\u012br Kh\u0101n K\u00ealay",
    "gn:population":0,
    "gn:timezone":"Asia/Kabul",
    "iso:country":"AF",
    "name:und_x_variant":[
        "Dastag\u012br Kh\u0101n K\u00ealay",
        "\u062f\u0633\u062a\u06af\u06cc\u0631 \u062e\u0627\u0646 \u06a9\u0644\u06cc",
        "Dastag\u012br Kh\u0101n Kalay"
    ],
    "wof:name":"Dastagir Khan Kelay",
    "wof:placetype":"locality"
},
  "geometry": {"coordinates":[64.24873000000001,31.31247],"type":"Point"}
}