{
  "type": "Feature",
  "properties": {
    "gn:admin1_code":"17",
    "gn:admin2_code":"501.0",
    "gn:asciiname":"Abchakan",
    "gn:country_code":"AF",
    "gn:dem":2558,
    "gn:feature_class":"P",
    "gn:feature_code":"PPL",
    "gn:name":"Abchak\u0101n",
    "gn:population":0,
    "gn:timezone":"Asia/Kabul",
    "iso:country":"AF",
    "name:fas_x_preferred":[
        "\u0627\u0628\u0686\u0643\u0627\u0646"
    ],
    "name:und_x_variant":[
        "Chakan Abeh\u012b Kh\u0101neh",
        "\u0100b Chek\u0101n",
        "Chakan Abehi Kh\u0101na",
        "Abchakan",
        "Ab\u010dak\u0101n",
        "Abchak\u0101n",
        "\u0627\u0628\u0686\u0643\u0627\u0646"
    ],
    "wof:name":"Abchakan",
    "wof:placetype":"locality"
},
  "geometry": {"coordinates":[69.23175999999999,33.89335],"type":"Point"}
}