{
  "type": "Feature",
  "properties": {
    "gn:admin1_code":"18",
    "gn:admin2_code":"817",
    "gn:asciiname":"Spi Aw",
    "gn:country_code":"AF",
    "gn:dem":550,
    "gn:feature_class":"P",
    "gn:feature_code":"PPL",
    "gn:name":"Sp\u012b \u0100w",
    "gn:population":0,
    "gn:timezone":"Asia/Kabul",
    "iso:country":"AF",
    "name:fas_x_preferred":[
        "\u0633\u067e\u064a\u0627"
    ],
    "name:und_x_variant":[
        "Sipiav",
        "Sipi\u0101w",
        "Seh P\u0101y \u0100w",
        "Seh P\u0101h-e \u0100w",
        "Sp\u012b \u0100w",
        "\u0633\u067e\u06cc \u0622\u0648"
    ],
    "wof:name":"Spi Aw",
    "wof:placetype":"locality"
},
  "geometry": {"coordinates":[70.73513,34.26309000000001],"type":"Point"}
}