{
  "type": "Feature",
  "properties": {
    "gn:admin1_code":"09",
    "gn:admin2_code":"2707",
    "gn:asciiname":"Joy-e Badal",
    "gn:country_code":"AF",
    "gn:dem":2785,
    "gn:feature_class":"P",
    "gn:feature_code":"PPL",
    "gn:name":"J\u014dy-e Badal",
    "gn:population":0,
    "gn:timezone":"Asia/Kabul",
    "iso:country":"AF",
    "name:und_x_variant":[
        "Dzhoyi-Badal\u2019",
        "J\u014dye Ba\u1e0fal",
        "J\u014dy-ye Badal",
        "J\u016by-ye Badal",
        "J\u014dy-e Badal",
        "\u062c\u0648\u06cc \u0628\u062f\u0644"
    ],
    "wof:name":"Joy-e Badal",
    "wof:placetype":"locality"
},
  "geometry": {"coordinates":[66.26061,34.49089],"type":"Point"}
}