{
  "type": "Feature",
  "properties": {
    "gn:admin1_code":"32",
    "gn:admin2_code":"1504.0",
    "gn:asciiname":"Ahingaran",
    "gn:country_code":"AF",
    "gn:dem":1483,
    "gn:feature_class":"P",
    "gn:feature_code":"PPL",
    "gn:name":"\u0100hingar\u0101n",
    "gn:population":0,
    "gn:timezone":"Asia/Kabul",
    "iso:country":"AF",
    "name:und_x_variant":[
        "\u0100henga\u1e5f\u0101n",
        "\u0100hangar\u0101n",
        "\u0100hingar\u0101n",
        "\u0622\u0647\u0646\u06af\u0631\u0627\u0646"
    ],
    "wof:name":"Ahingaran",
    "wof:placetype":"locality"
},
  "geometry": {"coordinates":[67.36765,35.95452],"type":"Point"}
}