{
  "type": "Feature",
  "properties": {
    "gn:admin1_code":"33",
    "gn:admin2_code":"3106",
    "gn:asciiname":"Pahlawan Tash",
    "gn:country_code":"AF",
    "gn:dem":699,
    "gn:feature_class":"P",
    "gn:feature_code":"PPL",
    "gn:name":"Pahlaw\u0101n T\u0101sh",
    "gn:population":0,
    "gn:timezone":"Asia/Kabul",
    "iso:country":"AF",
    "name:und_x_variant":[
        "Pahlaw\u0101n T\u0101sh",
        "Pahlaw\u0101n T\u0101sh (1)",
        "Pahlav\u0101n T\u0101sh",
        "\u067e\u0647\u0644\u0648\u0627\u0646 \u062a\u0627\u0634"
    ],
    "wof:name":"Pahlawan Tash",
    "wof:placetype":"locality"
},
  "geometry": {"coordinates":[65.65536999999999,36.20215],"type":"Point"}
}