{
  "type": "Feature",
  "properties": {
    "gn:admin1_code":"35",
    "gn:admin2_code":"902.0",
    "gn:asciiname":"Qabilah",
    "gn:country_code":"AF",
    "gn:dem":626,
    "gn:feature_class":"P",
    "gn:feature_code":"PPL",
    "gn:name":"Qab\u012blah",
    "gn:population":0,
    "gn:timezone":"Asia/Kabul",
    "iso:country":"AF",
    "name:und_x_variant":[
        "Qab\u012blah",
        "\u0642\u0628\u06cc\u0644\u0647"
    ],
    "wof:name":"Qabilah",
    "wof:placetype":"locality"
},
  "geometry": {"coordinates":[70.26189000000001,34.52372],"type":"Point"}
}