{
  "type": "Feature",
  "properties": {
    "gn:admin1_code":"09",
    "gn:admin2_code":"2707",
    "gn:asciiname":"Minah Talah",
    "gn:country_code":"AF",
    "gn:dem":2737,
    "gn:feature_class":"P",
    "gn:feature_code":"PPL",
    "gn:name":"M\u012bnah T\u0101lah",
    "gn:population":0,
    "gn:timezone":"Asia/Kabul",
    "iso:country":"AF",
    "name:und_x_variant":[
        "Minatala",
        "Menat\u0101la",
        "M\u0113nah T\u0101lah",
        "M\u012bnah T\u0101lah",
        "\u0645\u064a\u0646\u0647 \u062a\u0627\u0644\u0647"
    ],
    "wof:name":"Minah Talah",
    "wof:placetype":"locality"
},
  "geometry": {"coordinates":[66.37482,34.3241],"type":"Point"}
}