{
  "type": "Feature",
  "properties": {
    "gn:admin1_code":"11",
    "gn:admin2_code":"2007",
    "gn:asciiname":"Karez-e Dashak",
    "gn:country_code":"AF",
    "gn:dem":835,
    "gn:feature_class":"P",
    "gn:feature_code":"PPL",
    "gn:name":"K\u0101r\u0113z-e D\u0101shak",
    "gn:population":0,
    "gn:timezone":"Asia/Kabul",
    "iso:country":"AF",
    "name:und_x_variant":[
        "Kar\u0113z-i-D\u0101shak",
        "K\u0101r\u012bz-e D\u0101shak",
        "K\u0101rayz-e D\u0101shak",
        "K\u0101r\u0113z-e D\u0101shak",
        "\u06a9\u0627\u0631\u06d0\u0632\u0650 \u062f\u0627\u0634\u06a9"
    ],
    "wof:name":"Karez-e Dashak",
    "wof:placetype":"locality"
},
  "geometry": {"coordinates":[61.27092,35.38155],"type":"Point"}
}