{
  "type": "Feature",
  "properties": {
    "gn:admin1_code":"23",
    "gn:admin2_code":"2409.0",
    "gn:asciiname":"Pay Sarak",
    "gn:country_code":"AF",
    "gn:dem":930,
    "gn:feature_class":"P",
    "gn:feature_code":"PPL",
    "gn:name":"P\u0101y Sarak",
    "gn:population":0,
    "gn:timezone":"Asia/Kabul",
    "iso:country":"AF",
    "name:pus_x_preferred":[
        "\u067e\u0627\u06cc \u0633\u0631\u06a9"
    ],
    "name:und_x_variant":[
        "P\u0101y Sarak"
    ],
    "wof:name":"Pay Sarak",
    "wof:placetype":"locality"
},
  "geometry": {"coordinates":[65.74176,29.8256],"type":"Point"}
}