{
  "type": "Feature",
  "properties": {
    "gn:admin1_code":"09",
    "gn:admin2_code":"2710",
    "gn:asciiname":"Siyah Nawer",
    "gn:country_code":"AF",
    "gn:dem":2592,
    "gn:feature_class":"P",
    "gn:feature_code":"PPL",
    "gn:name":"Siy\u0101h N\u0101w\u00ear",
    "gn:population":0,
    "gn:timezone":"Asia/Kabul",
    "iso:country":"AF",
    "name:und_x_variant":[
        "Sy\u0101hn\u0101wu\u1e5f",
        "S\u012b\u0101h N\u0101w\u00ear",
        "\u0633\u06cc\u0627\u0647 \u0646\u0627\u0648\u0631",
        "S\u012b\u0101h N\u0101vor",
        "Siy\u0101h N\u0101w\u00ear"
    ],
    "wof:name":"Siyah Nawer",
    "wof:placetype":"locality"
},
  "geometry": {"coordinates":[65.36128000000001,33.92597],"type":"Point"}
}