{
  "type": "Feature",
  "properties": {
    "gn:admin1_code":"11",
    "gn:admin2_code":"2014.0",
    "gn:asciiname":"Abistan-e Pa'in",
    "gn:country_code":"AF",
    "gn:dem":1140,
    "gn:feature_class":"P",
    "gn:feature_code":"PPL",
    "gn:name":"\u0100bist\u0101n-e P\u0101\u2019\u012bn",
    "gn:population":0,
    "gn:timezone":"Asia/Kabul",
    "iso:country":"AF",
    "name:und_x_variant":[
        "\u0100bist\u0101n-e P\u0101\u2019\u012bn",
        "\u0622\u0628\u0633\u062a\u0627\u0646 \u067e\u0627\u0626\u06cc\u0646",
        "\u0100best\u0101n"
    ],
    "wof:name":"Abistan-e Pa'in",
    "wof:placetype":"locality"
},
  "geometry": {"coordinates":[61.9526,33.34082],"type":"Point"}
}