{
  "type": "Feature",
  "properties": {
    "gn:admin1_code":"05",
    "gn:admin2_code":"2804",
    "gn:asciiname":"Ghorband",
    "gn:country_code":"AF",
    "gn:dem":2303,
    "gn:feature_class":"P",
    "gn:feature_code":"PPL",
    "gn:name":"Gh\u014drband",
    "gn:population":0,
    "gn:timezone":"Asia/Kabul",
    "iso:country":"AF",
    "name:und_x_variant":[
        "Gh\u014d\u1e5fban\u1e0f",
        "Ghowrband",
        "Gh\u014drband",
        "\u063a\u0648\u0631\u0628\u0646\u062f"
    ],
    "wof:name":"Ghorband",
    "wof:placetype":"locality"
},
  "geometry": {"coordinates":[66.44346999999999,35.05312],"type":"Point"}
}