{
  "type": "Feature",
  "properties": {
    "gn:admin1_code":"08",
    "gn:admin2_code":"604",
    "gn:asciiname":"Pudinah",
    "gn:country_code":"AF",
    "gn:dem":2712,
    "gn:feature_class":"P",
    "gn:feature_code":"PPL",
    "gn:name":"P\u016bd\u012bnah",
    "gn:population":0,
    "gn:timezone":"Asia/Kabul",
    "iso:country":"AF",
    "name:und_x_variant":[
        "Pudina",
        "Po\u1e0fina",
        "Pod\u012bneh",
        "P\u014dd\u012bnah",
        "P\u016bd\u012bnah",
        "\u067e\u0648\u062f\u06cc\u0646\u0647"
    ],
    "wof:name":"Pudinah",
    "wof:placetype":"locality"
},
  "geometry": {"coordinates":[68.07909000000001,34.05599],"type":"Point"}
}