{
  "type": "Feature",
  "properties": {
    "gn:admin1_code":"28",
    "gn:admin2_code":"2506.0",
    "gn:asciiname":"Muhammadzai",
    "gn:country_code":"AF",
    "gn:dem":1394,
    "gn:feature_class":"P",
    "gn:feature_code":"PPL",
    "gn:name":"Mu\u1e29ammadza\u012b",
    "gn:population":0,
    "gn:timezone":"Asia/Kabul",
    "iso:country":"AF",
    "name:und_x_variant":[
        "Mukhammedzay",
        "\u0645\u062d\u0645\u062f\u0632\u06cc",
        "Mo\u1e29ammadzay",
        "Mu\u1e29ammadza\u012b"
    ],
    "wof:name":"Muhammadzai",
    "wof:placetype":"locality"
},
  "geometry": {"coordinates":[66.62680999999999,31.93274000000001],"type":"Point"}
}