{
  "type": "Feature",
  "properties": {
    "gn:admin1_code":"08",
    "gn:admin2_code":"613",
    "gn:asciiname":"Jamal",
    "gn:country_code":"AF",
    "gn:dem":2139,
    "gn:feature_class":"P",
    "gn:feature_code":"PPL",
    "gn:name":"Jam\u0101l",
    "gn:population":0,
    "gn:timezone":"Asia/Kabul",
    "iso:country":"AF",
    "name:ara_x_preferred":[
        "\u062c\u0645\u0627\u0644"
    ],
    "name:aze_x_preferred":[
        "Camal"
    ],
    "name:bul_x_preferred":[
        "\u0414\u0436\u0430\u043c\u0430\u043b"
    ],
    "name:deu_x_preferred":[
        "Dscham\u0101l"
    ],
    "name:fas_x_preferred":[
        "\u062c\u0645\u0627\u0644"
    ],
    "name:ita_x_preferred":[
        "Jamal"
    ],
    "name:rus_x_preferred":[
        "Dzhamal\u2019"
    ],
    "name:rus_x_variant":[
        "\u0414\u0436\u0430\u043c\u0430\u043b\u044c"
    ],
    "name:swe_x_preferred":[
        "Jamal"
    ],
    "name:tur_x_preferred":[
        "Cem\u00e2l"
    ],
    "name:und_x_variant":[
        "Jam\u0101l"
    ],
    "wof:name":"Jamal",
    "wof:placetype":"locality"
},
  "geometry": {"coordinates":[68.10566,33.24418],"type":"Point"}
}