{
  "type": "Feature",
  "properties": {
    "gn:admin1_code":"08",
    "gn:admin2_code":"613",
    "gn:asciiname":"Jamal",
    "gn:country_code":"AF",
    "gn:dem":2139,
    "gn:feature_class":"P",
    "gn:feature_code":"PPL",
    "gn:name":"Jam\u0101l",
    "gn:population":0,
    "gn:timezone":"Asia/Kabul",
    "iso:country":"AF",
    "name:fas_x_preferred":[
        "\u062c\u0645\u0627\u0644"
    ],
    "name:rus_x_preferred":[
        "Dzhamal\u2019"
    ],
    "name:und_x_variant":[
        "Jam\u0101l"
    ],
    "wof:name":"Jamal",
    "wof:placetype":"locality"
},
  "geometry": {"coordinates":[68.10566,33.24418],"type":"Point"}
}