{
  "type": "Feature",
  "properties": {
    "gn:admin1_code":"35",
    "gn:admin2_code":"902.0",
    "gn:asciiname":"Qal'ah-ye Fayz Muhammad Khan",
    "gn:country_code":"AF",
    "gn:dem":605,
    "gn:feature_class":"P",
    "gn:feature_code":"PPL",
    "gn:name":"Qal\u2018ah-ye Fay\u1e95 Mu\u1e29ammad Kh\u0101n",
    "gn:population":0,
    "gn:timezone":"Asia/Kabul",
    "iso:country":"AF",
    "name:und_x_variant":[
        "Qal\u2018ah-ye Fay\u1e95 Mu\u1e29ammad Kh\u0101n",
        "\u0642\u0644\u0639\u06c0 \u0641\u06cc\u0636 \u0645\u062d\u0645\u062f \u062e\u0627\u0646"
    ],
    "wof:name":"Qal'ah-ye Fayz Muhammad Khan",
    "wof:placetype":"locality"
},
  "geometry": {"coordinates":[70.30619,34.5039],"type":"Point"}
}