{
  "type": "Feature",
  "properties": {
    "gn:admin1_code":"03",
    "gn:admin2_code":"1307",
    "gn:asciiname":"Qulba",
    "gn:country_code":"AF",
    "gn:dem":2224,
    "gn:feature_class":"P",
    "gn:feature_code":"PPL",
    "gn:name":"Qulb\u0101",
    "gn:population":0,
    "gn:timezone":"Asia/Kabul",
    "iso:country":"AF",
    "name:und_x_variant":[
        "Qulb\u0101",
        "\u0642\u0644\u0628\u0627"
    ],
    "wof:name":"Qulba",
    "wof:placetype":"locality"
},
  "geometry": {"coordinates":[69.28579000000001,35.5381],"type":"Point"}
}