{
  "type": "Feature",
  "properties": {
    "gn:admin1_code":"41",
    "gn:admin2_code":"3407.0",
    "gn:asciiname":"Barg",
    "gn:country_code":"AF",
    "gn:dem":2764,
    "gn:feature_class":"P",
    "gn:feature_code":"PPL",
    "gn:name":"Barg",
    "gn:population":0,
    "gn:timezone":"Asia/Kabul",
    "iso:country":"AF",
    "name:und_x_variant":[
        "Ba\u1e5fg",
        "Barg",
        "Ba\u1e5fq",
        "\u0628\u0631\u06af"
    ],
    "wof:name":"Barg",
    "wof:placetype":"locality"
},
  "geometry": {"coordinates":[66.72499000000001,33.89664],"type":"Point"}
}