{
  "type": "Feature",
  "properties": {
    "gn:admin1_code":"36",
    "gn:admin2_code":"711.0",
    "gn:asciiname":"Seway",
    "gn:country_code":"AF",
    "gn:dem":2397,
    "gn:feature_class":"P",
    "gn:feature_code":"PPL",
    "gn:name":"S\u0113way",
    "gn:population":0,
    "gn:timezone":"Asia/Kabul",
    "iso:country":"AF",
    "name:fas_x_preferred":[
        "\u0633\u064a\u0648\u06cc"
    ],
    "name:und_x_variant":[
        "Sevay",
        "S\u0113way",
        "\u0633\u06d0\u0648\u06cc"
    ],
    "wof:name":"Seway",
    "wof:placetype":"locality"
},
  "geometry": {"coordinates":[69.63263000000001,34.00465],"type":"Point"}
}