{
  "type": "Feature",
  "properties": {
    "gn:admin1_code":"36",
    "gn:admin2_code":"701.0",
    "gn:asciiname":"Laghar",
    "gn:country_code":"AF",
    "gn:dem":2309,
    "gn:feature_class":"P",
    "gn:feature_code":"PPL",
    "gn:name":"Laghar",
    "gn:population":0,
    "gn:timezone":"Asia/Kabul",
    "iso:country":"AF",
    "name:fas_x_preferred":[
        "\u0644\u0627\u063a\u0631"
    ],
    "name:msa_x_preferred":[
        "Laghar"
    ],
    "name:und_x_variant":[
        "Lagar",
        "Lagha\u1e5f",
        "Laghar",
        "\u0644\u063a\u0631"
    ],
    "name:urd_x_preferred":[
        "\u0644\u0627\u06af\u06be\u0627\u0631"
    ],
    "wof:name":"Laghar",
    "wof:placetype":"locality"
},
  "geometry": {"coordinates":[69.22979000000001,33.56774],"type":"Point"}
}