{
  "type": "Feature",
  "properties": {
    "gn:admin1_code":"27",
    "gn:admin2_code":"408",
    "gn:asciiname":"Khamo",
    "gn:country_code":"AF",
    "gn:dem":2338,
    "gn:feature_class":"P",
    "gn:feature_code":"PPL",
    "gn:name":"Kham\u014d",
    "gn:population":0,
    "gn:timezone":"Asia/Kabul",
    "iso:country":"AF",
    "name:und_x_variant":[
        "Khamu",
        "Kham\u014d",
        "Kham\u016b",
        "\u062e\u0645\u0648"
    ],
    "wof:name":"Khamo",
    "wof:placetype":"locality"
},
  "geometry": {"coordinates":[68.70267,34.35487],"type":"Point"}
}