{
  "type": "Feature",
  "properties": {
    "gn:admin1_code":"18",
    "gn:admin2_code":"810.0",
    "gn:asciiname":"Tsaperai",
    "gn:country_code":"AF",
    "gn:dem":1795,
    "gn:feature_class":"P",
    "gn:feature_code":"PPL",
    "gn:name":"Tsap\u00eara\u012b",
    "gn:population":0,
    "gn:timezone":"Asia/Kabul",
    "iso:country":"AF",
    "name:fas_x_preferred":[
        "\u0686\u067e\u0631\u06cc"
    ],
    "name:und_x_variant":[
        "Cape\u1e5fi",
        "Chapiri",
        "Tsaperi",
        "Tsap\u00eara\u012b",
        "\u0685\u067e\u0631\u06cc"
    ],
    "wof:name":"Tsaperai",
    "wof:placetype":"locality"
},
  "geometry": {"coordinates":[70.62600999999999,34.0166],"type":"Point"}
}