{
  "type": "Feature",
  "properties": {
    "gn:admin1_code":"23",
    "gn:admin2_code":"2412",
    "gn:asciiname":"Loy Deh",
    "gn:country_code":"AF",
    "gn:dem":1229,
    "gn:feature_class":"P",
    "gn:feature_code":"PPL",
    "gn:name":"L\u014dy Deh",
    "gn:population":0,
    "gn:timezone":"Asia/Kabul",
    "iso:country":"AF",
    "name:und_x_variant":[
        "Lowy Deh",
        "L\u014dy \u1e0eeh",
        "Loy-Dekh",
        "L\u014dy Deh",
        "\u0644\u0648\u06cc \u062f\u0647",
        "L\u016by Deh"
    ],
    "wof:name":"Loy Deh",
    "wof:placetype":"locality"
},
  "geometry": {"coordinates":[66.38944000000001,31.59178],"type":"Point"}
}