{
  "type": "Feature",
  "properties": {
    "gn:admin1_code":"36",
    "gn:admin2_code":"702",
    "gn:asciiname":"Shaykh Nurwal",
    "gn:country_code":"AF",
    "gn:dem":2195,
    "gn:feature_class":"P",
    "gn:feature_code":"PPL",
    "gn:name":"Shaykh N\u016brw\u0101l",
    "gn:population":0,
    "gn:timezone":"Asia/Kabul",
    "iso:country":"AF",
    "name:fas_x_preferred":[
        "\u0634\u06cc\u062e \u0646\u0648\u0631\u0648\u0627\u0644"
    ],
    "name:rus_x_preferred":[
        "Sheykh-Nuval\u2019"
    ],
    "name:und_x_variant":[
        "\u0160\u0113kh-n\u016brw\u0101l",
        "\u0634\u06cc\u062e \u0646\u0648\u0631\u0648\u0627\u0644",
        "Shaykh N\u016br W\u0101l",
        "Sheykh N\u016brw\u0101l",
        "Sh\u0113kh N\u016br W\u0101l",
        "Shaykh N\u016brw\u0101l"
    ],
    "wof:name":"Shaykh Nurwal",
    "wof:placetype":"locality"
},
  "geometry": {"coordinates":[69.10980000000001,33.44673],"type":"Point"}
}