{
  "type": "Feature",
  "properties": {
    "gn:admin1_code":"18",
    "gn:admin2_code":"811.0",
    "gn:asciiname":"Baro Kelay",
    "gn:country_code":"AF",
    "gn:dem":1336,
    "gn:feature_class":"P",
    "gn:feature_code":"PPL",
    "gn:name":"B\u0101r\u014d K\u00ealay",
    "gn:population":0,
    "gn:timezone":"Asia/Kabul",
    "iso:country":"AF",
    "name:fas_x_preferred":[
        "\u0642\u0631\u064a\u06c0 \u0628\u0627\u0631\u0648"
    ],
    "name:und_x_variant":[
        "Barukalay",
        "B\u0101ro Kalay",
        "B\u0101r\u014d K\u00ealay",
        "\u0628\u0627\u0631\u0648 \u06a9\u0644\u06cc"
    ],
    "wof:name":"Baro Kelay",
    "wof:placetype":"locality"
},
  "geometry": {"coordinates":[70.82576999999998,34.02617],"type":"Point"}
}