{
  "type": "Feature",
  "properties": {
    "gn:admin1_code":"41",
    "gn:admin2_code":"3409.0",
    "gn:asciiname":"Nowtakah",
    "gn:country_code":"AF",
    "gn:dem":2247,
    "gn:feature_class":"P",
    "gn:feature_code":"PPL",
    "gn:name":"Nowtakah",
    "gn:population":0,
    "gn:timezone":"Asia/Kabul",
    "iso:country":"AF",
    "wof:name":"Nowtakah",
    "wof:placetype":"locality"
},
  "geometry": {"coordinates":[66.37278000000001,33.88667],"type":"Point"}
}