{
  "type": "Feature",
  "properties": {
    "gn:admin1_code":"07",
    "gn:admin2_code":"1802",
    "gn:asciiname":"Hazarah Mir-e Shikar",
    "gn:country_code":"AF",
    "gn:dem":1370,
    "gn:feature_class":"P",
    "gn:feature_code":"PPL",
    "gn:name":"Haz\u0101rah M\u012br-e Shikar",
    "gn:population":0,
    "gn:timezone":"Asia/Kabul",
    "iso:country":"AF",
    "name:und_x_variant":[
        "Haz\u0101reh M\u012br-e Shekar",
        "Haz\u0101\u1e5fa M\u012b\u1e5f-i-S\u0304ek\u0101\u1e5f",
        "Hez\u0101reh M\u012br-e Shekar",
        "Haz\u0101rah M\u012br-e Shikar",
        "\u0647\u0632\u0627\u0631\u0647 \u0645\u064a\u0631 \u0634\u06a9\u0631"
    ],
    "wof:name":"Hazarah Mir-e Shikar",
    "wof:placetype":"locality"
},
  "geometry": {"coordinates":[64.64471,35.76529],"type":"Point"}
}