{
  "type": "Feature",
  "properties": {
    "gn:admin1_code":"1",
    "gn:admin2_code":"1103.0",
    "gn:asciiname":"Arkhow",
    "gn:country_code":"AF",
    "gn:dem":2270,
    "gn:feature_class":"P",
    "gn:feature_code":"PPL",
    "gn:name":"Arkhow",
    "gn:population":0,
    "gn:timezone":"Asia/Kabul",
    "iso:country":"AF",
    "name:und_x_variant":[
        "\u0627\u0631\u062e\u0627\u0648",
        "A\u1e5fkhaw",
        "Arkhow",
        "\u0627\u0631\u062e\u0648"
    ],
    "wof:name":"Arkhow",
    "wof:placetype":"locality"
},
  "geometry": {"coordinates":[70.97709999999999,36.73747],"type":"Point"}
}