{
  "type": "Feature",
  "properties": {
    "gn:admin1_code":"09",
    "gn:admin2_code":"2703",
    "gn:asciiname":"Piazi",
    "gn:country_code":"AF",
    "gn:dem":1811,
    "gn:feature_class":"P",
    "gn:feature_code":"PPL",
    "gn:name":"P\u012b\u0101z\u012b",
    "gn:population":0,
    "gn:timezone":"Asia/Kabul",
    "iso:country":"AF",
    "name:und_x_variant":[
        "Py\u0101zi",
        "P\u012b\u0101z\u012b",
        "\u067e\u06cc\u0627\u0632\u06cc"
    ],
    "wof:name":"Piazi",
    "wof:placetype":"locality"
},
  "geometry": {"coordinates":[63.52701,34.05957],"type":"Point"}
}