{
  "type": "Feature",
  "properties": {
    "gn:admin1_code":"18",
    "gn:admin2_code":"818",
    "gn:asciiname":"Tangay",
    "gn:country_code":"AF",
    "gn:dem":1180,
    "gn:feature_class":"P",
    "gn:feature_code":"PPL",
    "gn:name":"Tangay",
    "gn:population":0,
    "gn:timezone":"Asia/Kabul",
    "iso:country":"AF",
    "name:fas_x_preferred":[
        "\u062a\u0646\u06af\u06cc"
    ],
    "name:und_x_variant":[
        "Tanga\u012b"
    ],
    "wof:name":"Tangay",
    "wof:placetype":"locality"
},
  "geometry": {"coordinates":[70.68693,34.49930999999999],"type":"Point"}
}