{
  "type": "Feature",
  "properties": {
    "gn:admin1_code":"18",
    "gn:admin2_code":"818.0",
    "gn:asciiname":"Bazis Khel",
    "gn:country_code":"AF",
    "gn:dem":527,
    "gn:feature_class":"P",
    "gn:feature_code":"PPL",
    "gn:name":"B\u0101z\u012bs Kh\u0113l",
    "gn:population":0,
    "gn:timezone":"Asia/Kabul",
    "iso:country":"AF",
    "name:fas_x_preferred":[
        "\u0628\u0627\u0632\u064a\u0633 \u062e\u064a\u0644"
    ],
    "name:rus_x_preferred":[
        "Baziskhel\u2019"
    ],
    "name:und_x_variant":[
        "B\u0101z\u012bskh\u0113l",
        "B\u0101z\u012bd Kh\u0113l",
        "B\u0101z\u012bskheyl",
        "B\u0101z\u012bs Kh\u0113l",
        "\u0628\u0627\u0632\u064a\u0633 \u062e\u06d0\u0644"
    ],
    "wof:name":"Bazis Khel",
    "wof:placetype":"locality"
},
  "geometry": {"coordinates":[70.64089,34.43357],"type":"Point"}
}