{
  "type": "Feature",
  "properties": {
    "gn:admin1_code":"09",
    "gn:admin2_code":"2707",
    "gn:asciiname":"Pam",
    "gn:country_code":"AF",
    "gn:dem":3034,
    "gn:feature_class":"P",
    "gn:feature_code":"PPL",
    "gn:name":"P\u0101m",
    "gn:population":0,
    "gn:timezone":"Asia/Kabul",
    "iso:country":"AF",
    "name:und_x_variant":[
        "P\u0101m",
        "\u067e\u0627\u0645"
    ],
    "wof:name":"Pam",
    "wof:placetype":"locality"
},
  "geometry": {"coordinates":[66.16016,34.40625],"type":"Point"}
}