{
  "type": "Feature",
  "properties": {
    "gn:admin1_code":"06",
    "gn:admin2_code":"2104",
    "gn:asciiname":"Sarzibi",
    "gn:country_code":"AF",
    "gn:dem":1781,
    "gn:feature_class":"P",
    "gn:feature_code":"PPL",
    "gn:name":"Sarz\u012bb\u012b",
    "gn:population":0,
    "gn:timezone":"Asia/Kabul",
    "iso:country":"AF",
    "name:und_x_variant":[
        "Sarz\u012bb\u012b",
        "\u0633\u0631\u0632\u06cc\u0628\u06cc"
    ],
    "wof:name":"Sarzibi",
    "wof:placetype":"locality"
},
  "geometry": {"coordinates":[63.76671,33.33019],"type":"Point"}
}