{
  "type": "Feature",
  "properties": {
    "gn:admin1_code":"28",
    "gn:admin2_code":"2502",
    "gn:asciiname":"Payindah Khel",
    "gn:country_code":"AF",
    "gn:dem":1851,
    "gn:feature_class":"P",
    "gn:feature_code":"PPL",
    "gn:name":"P\u0101yindah Kh\u0113l",
    "gn:population":0,
    "gn:timezone":"Asia/Kabul",
    "iso:country":"AF",
    "name:fas_x_preferred":[
        "\u067e\u0627\u064a\u0646\u062f\u0647 \u062e\u064a\u0644"
    ],
    "name:rus_x_preferred":[
        "Payindakheyl\u2019"
    ],
    "name:und_x_variant":[
        "P\u0101yen\u1e0fakh\u0113l",
        "P\u0101yendah Kh\u0113l",
        "\u067e\u0627\u06cc\u0646\u062f\u0647 \u062e\u06d0\u0644",
        "P\u0101yandeh Kheyl",
        "P\u0101yindah Kh\u0113l"
    ],
    "wof:name":"Payindah Khel",
    "wof:placetype":"locality"
},
  "geometry": {"coordinates":[67.38379,32.48860999999999],"type":"Point"}
}