{
  "type": "Feature",
  "properties": {
    "gn:admin1_code":"41",
    "gn:admin2_code":"3408.0",
    "gn:asciiname":"Dahan-e Kun-e Gaw",
    "gn:country_code":"AF",
    "gn:dem":2676,
    "gn:feature_class":"P",
    "gn:feature_code":"PPL",
    "gn:name":"Dahan-e K\u016bn-e G\u0101w",
    "gn:population":0,
    "gn:timezone":"Asia/Kabul",
    "iso:country":"AF",
    "name:und_x_variant":[
        "\u1e0eahane K\u016bne G\u0101w",
        "Dakhani-Kuni-Gav",
        "Dahan-e K\u016bn-e G\u0101w",
        "Dahan-e K\u016bn-e G\u0101v",
        "\u062f\u0647\u0646 \u06a9\u0648\u0646 \u06af\u0627\u0648"
    ],
    "wof:name":"Dahan-e Kun-e Gaw",
    "wof:placetype":"locality"
},
  "geometry": {"coordinates":[66.3201,34.31463],"type":"Point"}
}