{
  "type": "Feature",
  "properties": {
    "gn:admin1_code":"5",
    "gn:admin2_code":"2806.0",
    "gn:asciiname":"Mir Ahmadi",
    "gn:country_code":"AF",
    "gn:dem":3204,
    "gn:feature_class":"P",
    "gn:feature_code":"PPL",
    "gn:name":"M\u012br A\u1e29mad\u012b",
    "gn:population":0,
    "gn:timezone":"Asia/Kabul",
    "iso:country":"AF",
    "name:fas_x_preferred":[
        "\u0645\u06cc\u0631\u0627\u062d\u0645\u062f\u06cc"
    ],
    "name:und_x_variant":[
        "Mirakhmedi",
        "M\u012br A\u1e29mad\u012b",
        "M\u012br\u0101\u1e29mad\u012b",
        "\u0645\u06cc\u0631 \u0627\u062d\u0645\u062f\u06cc"
    ],
    "wof:name":"Mir Ahmadi",
    "wof:placetype":"locality"
},
  "geometry": {"coordinates":[66.86976999999999,34.04133],"type":"Point"}
}