{
  "type": "Feature",
  "properties": {
    "gn:admin1_code":"01",
    "gn:admin2_code":"1112.0",
    "gn:asciiname":"Nisheb Dur",
    "gn:country_code":"AF",
    "gn:dem":2535,
    "gn:feature_class":"P",
    "gn:feature_code":"PPL",
    "gn:name":"Nish\u0113b Dur",
    "gn:population":0,
    "gn:timezone":"Asia/Kabul",
    "iso:country":"AF",
    "name:und_x_variant":[
        "Nes\u0113b \u1e0eu\u1e5f",
        "\u0646\u0634\u06d0\u0628 \u062f\u0631",
        "Nesh\u012bb \u1e0eu\u1e5f",
        "Nish\u0113b Dur"
    ],
    "wof:name":"Nisheb Dur",
    "wof:placetype":"locality"
},
  "geometry": {"coordinates":[70.6019,37.58364],"type":"Point"}
}