{
  "type": "Feature",
  "properties": {
    "gn:admin1_code":"33",
    "gn:admin2_code":"3104",
    "gn:asciiname":"Sadlar",
    "gn:country_code":"AF",
    "gn:dem":1662,
    "gn:feature_class":"P",
    "gn:feature_code":"PPL",
    "gn:name":"\u015eadlar",
    "gn:population":0,
    "gn:timezone":"Asia/Kabul",
    "iso:country":"AF",
    "name:und_x_variant":[
        "\u015eadlar",
        "\u0635\u062f\u0644\u0631",
        "Sa\u1e0fla\u1e5f"
    ],
    "wof:name":"Sadlar",
    "wof:placetype":"locality"
},
  "geometry": {"coordinates":[66.49629,35.46962],"type":"Point"}
}