{
  "type": "Feature",
  "properties": {
    "gn:admin1_code":"27",
    "gn:admin2_code":"406",
    "gn:asciiname":"Mirza Beg",
    "gn:country_code":"AF",
    "gn:dem":2673,
    "gn:feature_class":"P",
    "gn:feature_code":"PPL",
    "gn:name":"M\u012brz\u0101 B\u0113g",
    "gn:population":0,
    "gn:timezone":"Asia/Kabul",
    "iso:country":"AF",
    "name:und_x_variant":[
        "Mirzabek",
        "Mi\u1e5fz\u0101b\u0113k",
        "M\u012brz\u0101 B\u0113g",
        "M\u012brz\u0101beyg",
        "M\u012brz\u0101 Bayg",
        "\u0645\u06cc\u0631\u0632\u0627 \u0628\u06d0\u06af"
    ],
    "wof:name":"Mirza Beg",
    "wof:placetype":"locality"
},
  "geometry": {"coordinates":[68.34369000000001,34.01877],"type":"Point"}
}