{
  "type": "Feature",
  "properties": {
    "gn:admin1_code":"07",
    "gn:admin2_code":"1802",
    "gn:asciiname":"Qal'ah-ye Niaz Beg",
    "gn:country_code":"AF",
    "gn:dem":1252,
    "gn:feature_class":"P",
    "gn:feature_code":"PPL",
    "gn:name":"Qal\u2018ah-ye N\u012b\u0101z B\u0113g",
    "gn:population":0,
    "gn:timezone":"Asia/Kabul",
    "iso:country":"AF",
    "name:und_x_variant":[
        "Qala Ni\u0101z Beg",
        "Kala N\u012b\u0101z Beg",
        "Qal\u2018a-i-Ny\u0101z B\u0113g",
        "Kala-i-Niaz Beg",
        "Qal\u2018eh-ye N\u012b\u0101z Beyg",
        "Qal\u2018ah-ye N\u012b\u0101z B\u0113g",
        "\u0642\u0644\u0639\u06c0 \u0646\u06cc\u0627\u0632 \u0628\u06d0\u06af"
    ],
    "wof:name":"Qal'ah-ye Niaz Beg",
    "wof:placetype":"locality"
},
  "geometry": {"coordinates":[64.91973,35.72508],"type":"Point"}
}