{
  "type": "Feature",
  "properties": {
    "gn:admin1_code":"8",
    "gn:admin2_code":"612.0",
    "gn:asciiname":"Chambaran",
    "gn:country_code":"AF",
    "gn:dem":2114,
    "gn:feature_class":"P",
    "gn:feature_code":"PPL",
    "gn:name":"Chambar\u0101n",
    "gn:population":0,
    "gn:timezone":"Asia/Kabul",
    "iso:country":"AF",
    "name:fas_x_preferred":[
        "\u0686\u0646\u0628\u0631\u0627\u0646"
    ],
    "name:und_x_variant":[
        "\u010cambar\u0101n",
        "Chambaran",
        "Chanbar\u0101n",
        "Chambar\u0101n",
        "\u0686\u0645\u0628\u0631\u0627\u0646",
        "\u0686\u0646\u0628\u0631\u0627\u0646"
    ],
    "wof:name":"Chambaran",
    "wof:placetype":"locality"
},
  "geometry": {"coordinates":[68.30417,33.03917],"type":"Point"}
}