{
  "type": "Feature",
  "properties": {
    "gn:admin1_code":"05",
    "gn:admin2_code":"2804",
    "gn:asciiname":"Surkh Qal'ah",
    "gn:country_code":"AF",
    "gn:dem":3089,
    "gn:feature_class":"P",
    "gn:feature_code":"PPL",
    "gn:name":"Surkh Qal\u2018ah",
    "gn:population":0,
    "gn:timezone":"Asia/Kabul",
    "iso:country":"AF",
    "name:und_x_variant":[
        "Su\u1e5fkhqal\u2018a",
        "Surkhkala",
        "Surkh Qal\u2018ah",
        "Sorkhqal\u2018eh",
        "\u0633\u0631\u062e \u0642\u0644\u0639\u0647"
    ],
    "wof:name":"Surkh Qal'ah",
    "wof:placetype":"locality"
},
  "geometry": {"coordinates":[66.90401999999999,34.59781],"type":"Point"}
}