{
  "type": "Feature",
  "properties": {
    "gn:admin1_code":"36",
    "gn:admin2_code":"704.0",
    "gn:asciiname":"Haki Kelay",
    "gn:country_code":"AF",
    "gn:dem":2247,
    "gn:feature_class":"P",
    "gn:feature_code":"PPL",
    "gn:name":"H\u0101k\u012b K\u00ealay",
    "gn:population":0,
    "gn:timezone":"Asia/Kabul",
    "iso:country":"AF",
    "name:und_x_variant":[
        "H\u0101k\u012b K\u00ealay",
        "\u0647\u0627\u06a9\u06cc \u06a9\u0644\u06cc"
    ],
    "wof:name":"Haki Kelay",
    "wof:placetype":"locality"
},
  "geometry": {"coordinates":[69.36351999999999,33.34067],"type":"Point"}
}