{
  "type": "Feature",
  "properties": {
    "gn:admin1_code":"13",
    "gn:admin2_code":"110.0",
    "gn:asciiname":"Dowlat Za'i",
    "gn:country_code":"AF",
    "gn:dem":1792,
    "gn:feature_class":"P",
    "gn:feature_code":"PPL",
    "gn:name":"Dowlat Z\u0101\u2019\u012b",
    "gn:population":0,
    "gn:timezone":"Asia/Kabul",
    "iso:country":"AF",
    "name:und_x_variant":[
        "Dowlat Z\u0101\u2019\u012b",
        "\u062f\u0648\u0644\u062a \u0632\u0627\u0626\u06cc",
        "Dowlatza\u012b"
    ],
    "wof:name":"Dowlat Za'i",
    "wof:placetype":"locality"
},
  "geometry": {"coordinates":[69.25855,34.47157],"type":"Point"}
}