{
  "type": "Feature",
  "properties": {
    "gn:admin1_code":"02",
    "gn:admin2_code":"1903",
    "gn:asciiname":"Tadzhikkha",
    "gn:country_code":"AF",
    "gn:dem":1449,
    "gn:feature_class":"P",
    "gn:feature_code":"PPL",
    "gn:name":"Tadzhikkha",
    "gn:population":0,
    "gn:timezone":"Asia/Kabul",
    "iso:country":"AF",
    "name:und_x_variant":[
        "T\u0101j\u012bkh\u0101",
        "\u062a\u0627\u062c\u06cc\u06a9\u0647\u0627"
    ],
    "wof:name":"Tadzhikkha",
    "wof:placetype":"locality"
},
  "geometry": {"coordinates":[63.64497,34.84923],"type":"Point"}
}