{
  "type": "Feature",
  "properties": {
    "gn:admin1_code":"02",
    "gn:admin2_code":"1903",
    "gn:asciiname":"Shamira",
    "gn:country_code":"AF",
    "gn:dem":722,
    "gn:feature_class":"P",
    "gn:feature_code":"PPL",
    "gn:name":"Sham\u012br\u0101",
    "gn:population":0,
    "gn:timezone":"Asia/Kabul",
    "iso:country":"AF",
    "name:und_x_variant":[
        "S\u0304ami\u1e5fa",
        "Sham\u012brah",
        "Sham\u012br\u0101",
        "\u0634\u0645\u06cc\u0631\u0627",
        "Sam\u012br\u0101",
        "\u0633\u0645\u06cc\u0631\u0627"
    ],
    "wof:name":"Shamira",
    "wof:placetype":"locality"
},
  "geometry": {"coordinates":[63.4578,35.19335],"type":"Point"}
}