{
  "type": "Feature",
  "properties": {
    "gn:admin1_code":"41",
    "gn:admin2_code":"3406",
    "gn:asciiname":"Shinyah",
    "gn:country_code":"AF",
    "gn:dem":1664,
    "gn:feature_class":"P",
    "gn:feature_code":"PPL",
    "gn:name":"Sh\u012bnyah",
    "gn:population":0,
    "gn:timezone":"Asia/Kabul",
    "iso:country":"AF",
    "name:und_x_variant":[
        "\u0160inya",
        "Sh\u012bnyah",
        "\u0634\u06cc\u0646\u06cc\u0647",
        "Shinyah"
    ],
    "wof:name":"Shinyah",
    "wof:placetype":"locality"
},
  "geometry": {"coordinates":[65.83779,33.43159],"type":"Point"}
}