{
  "type": "Feature",
  "properties": {
    "gn:admin1_code":"32",
    "gn:admin2_code":"1503.0",
    "gn:asciiname":"Changab",
    "gn:country_code":"AF",
    "gn:dem":2538,
    "gn:feature_class":"P",
    "gn:feature_code":"PPL",
    "gn:name":"Chang\u0101b",
    "gn:population":0,
    "gn:timezone":"Asia/Kabul",
    "iso:country":"AF",
    "name:und_x_variant":[
        "Cang\u0101b",
        "Chang\u0101b",
        "\u0686\u0646\u06af\u0627\u0628"
    ],
    "wof:name":"Changab",
    "wof:placetype":"locality"
},
  "geometry": {"coordinates":[67.37391,35.71104000000001],"type":"Point"}
}