{
  "type": "Feature",
  "properties": {
    "gn:admin1_code":"11",
    "gn:admin2_code":"2011.0",
    "gn:asciiname":"Chashmah-ye Khwajah Murad",
    "gn:country_code":"AF",
    "gn:dem":1603,
    "gn:feature_class":"P",
    "gn:feature_code":"PPL",
    "gn:name":"Chashmah-ye Khw\u0101jah Mur\u0101d",
    "gn:population":0,
    "gn:timezone":"Asia/Kabul",
    "iso:country":"AF",
    "name:und_x_variant":[
        "\u010ca\u0161ma-i-Khw\u0101ja Mur\u0101d",
        "Chashmayi-Khodzha-Murad",
        "Chashmeh-ye Khw\u0101ja Mur\u0101d",
        "Cheshmeh-ye Khv\u0101jeh Mor\u0101d",
        "Chashmah-ye Khw\u0101jah Mur\u0101d",
        "\u0686\u0634\u0645\u0647 \u062e\u0648\u0627\u062c\u0647 \u0645\u0631\u0627\u062f"
    ],
    "wof:name":"Chashmah-ye Khwajah Murad",
    "wof:placetype":"locality"
},
  "geometry": {"coordinates":[62.47537,33.56332],"type":"Point"}
}