{
  "type": "Feature",
  "properties": {
    "gn:admin1_code":"36",
    "gn:admin2_code":"705",
    "gn:asciiname":"Sirkay",
    "gn:country_code":"AF",
    "gn:dem":2722,
    "gn:feature_class":"P",
    "gn:feature_code":"PPL",
    "gn:name":"Sirkay",
    "gn:population":0,
    "gn:timezone":"Asia/Kabul",
    "iso:country":"AF",
    "name:fas_x_preferred":[
        "\u0633\u0631\u0646\u06cc"
    ],
    "name:und_x_variant":[
        "Se\u1e5fkay",
        "Sirkay",
        "\u0633\u0631\u06a9\u06cc"
    ],
    "wof:name":"Sirkay",
    "wof:placetype":"locality"
},
  "geometry": {"coordinates":[69.40104000000001,33.78906],"type":"Point"}
}