{
  "type": "Feature",
  "properties": {
    "gn:admin1_code":"08",
    "gn:admin2_code":"607",
    "gn:asciiname":"Qaryah-ye Baba",
    "gn:country_code":"AF",
    "gn:dem":2639,
    "gn:feature_class":"P",
    "gn:feature_code":"PPL",
    "gn:name":"Qaryah-ye B\u0101b\u0101",
    "gn:population":0,
    "gn:timezone":"Asia/Kabul",
    "iso:country":"AF",
    "name:und_x_variant":[
        "Qa\u1e5fya-i-B\u0101ba",
        "Qaryeh-ye B\u0101b\u0101",
        "Qaryah-ye B\u0101b\u0101",
        "\u0642\u0631\u06cc\u06c0 \u0628\u0627\u0628\u0627"
    ],
    "wof:name":"Qaryah-ye Baba",
    "wof:placetype":"locality"
},
  "geometry": {"coordinates":[67.25128000000001,33.03183],"type":"Point"}
}