{
  "type": "Feature",
  "properties": {
    "gn:admin1_code":"26",
    "gn:admin2_code":"1205",
    "gn:asciiname":"Sar-e Tang",
    "gn:country_code":"AF",
    "gn:dem":1684,
    "gn:feature_class":"P",
    "gn:feature_code":"PPL",
    "gn:name":"Sar-e Tang",
    "gn:population":0,
    "gn:timezone":"Asia/Kabul",
    "iso:country":"AF",
    "name:und_x_variant":[
        "\u0633\u0631 \u062a\u0646\u06af"
    ],
    "wof:name":"Sar-e Tang",
    "wof:placetype":"locality"
},
  "geometry": {"coordinates":[69.96696999999999,36.29067],"type":"Point"}
}