{
  "type": "Feature",
  "properties": {
    "gn:admin1_code":"29",
    "gn:admin2_code":"2907.0",
    "gn:asciiname":"Khadal",
    "gn:country_code":"AF",
    "gn:dem":2552,
    "gn:feature_class":"P",
    "gn:feature_code":"PPL",
    "gn:name":"Kh\u0101dal",
    "gn:population":0,
    "gn:timezone":"Asia/Kabul",
    "iso:country":"AF",
    "name:fas_x_preferred":[
        "Kh\u0101dal"
    ],
    "name:fas_x_variant":[
        "\u062e\u0627\u062f\u0644"
    ],
    "name:rus_x_preferred":[
        "Khadal\u2019"
    ],
    "name:und_x_variant":[
        "Khadal\u2019",
        "Kh\u0101dal",
        "\u062e\u0627\u062f\u0644"
    ],
    "wof:name":"Khadal",
    "wof:placetype":"locality"
},
  "geometry": {"coordinates":[68.81921,32.91056],"type":"Point"}
}