{
  "type": "Feature",
  "properties": {
    "gn:admin1_code":"23",
    "gn:admin2_code":"2403",
    "gn:asciiname":"Khwajahza'i",
    "gn:country_code":"AF",
    "gn:dem":1150,
    "gn:feature_class":"P",
    "gn:feature_code":"PPL",
    "gn:name":"Khw\u0101jahz\u0101\u2019\u012b",
    "gn:population":0,
    "gn:timezone":"Asia/Kabul",
    "iso:country":"AF",
    "name:fas_x_preferred":[
        "\u062e\u0648\u0627\u062c\u0647 \u0632\u0627\u0626\u06cc"
    ],
    "name:und_x_variant":[
        "Kh\u0101j\u0101zai",
        "Khodzhazai",
        "Khv\u0101jeh Ze\u2019\u012b",
        "Khw\u0101jaz\u0101\u2019i",
        "Khv\u0101jeh Z\u0101\u2019\u012b",
        "Khw\u0101jahz\u0101\u2019\u012b",
        "\u062e\u0648\u0627\u062c\u0647\u0632\u0627\u0639\u06cc",
        "\u062e\u0648\u0627\u062c\u0647 \u0632\u0627\u0626\u06cc"
    ],
    "wof:name":"Khwajahza'i",
    "wof:placetype":"locality"
},
  "geometry": {"coordinates":[65.98510999999999,31.92143],"type":"Point"}
}