{
  "type": "Feature",
  "properties": {
    "gn:admin1_code":"05",
    "gn:admin2_code":"2806.0",
    "gn:asciiname":"Alogak",
    "gn:country_code":"AF",
    "gn:dem":2658,
    "gn:feature_class":"P",
    "gn:feature_code":"PPL",
    "gn:name":"\u0100l\u014dgak",
    "gn:population":0,
    "gn:timezone":"Asia/Kabul",
    "iso:country":"AF",
    "name:und_x_variant":[
        "Al\u014dgak",
        "Alogak",
        "\u0100l\u016bgak",
        "\u0100l\u014dgak",
        "\u0622\u0644\u0648 \u06af\u06a9"
    ],
    "wof:name":"Alogak",
    "wof:placetype":"locality"
},
  "geometry": {"coordinates":[67.16752,34.22617],"type":"Point"}
}