{
  "type": "Feature",
  "properties": {
    "gn:admin1_code":"28",
    "gn:admin2_code":"2508.0",
    "gn:asciiname":"Dzangal Kelay",
    "gn:country_code":"AF",
    "gn:dem":1831,
    "gn:feature_class":"P",
    "gn:feature_code":"PPL",
    "gn:name":"Dzangal K\u00ealay",
    "gn:population":0,
    "gn:timezone":"Asia/Kabul",
    "iso:country":"AF",
    "name:fas_x_preferred":[
        "\u0632\u0646\u06af\u0644 \u0643\u0644\u06cc"
    ],
    "name:rus_x_preferred":[
        "Dzhangal\u2019kalay"
    ],
    "name:und_x_variant":[
        "Jangal Kalay",
        "Dzangal K\u00ealay",
        "\u0681\u0646\u06af\u0644 \u06a9\u0644\u06cc",
        "Dzangal Kalay",
        "\u0632\u0646\u06af\u0644 \u0643\u0644\u06cc",
        "Dzhangal\u2019kalay"
    ],
    "wof:name":"Dzangal Kelay",
    "wof:placetype":"locality"
},
  "geometry": {"coordinates":[67.35292,31.75057],"type":"Point"}
}