{
  "type": "Feature",
  "properties": {
    "gn:admin1_code":"36",
    "gn:admin2_code":"708.0",
    "gn:asciiname":"Tsamkani",
    "gn:country_code":"AF",
    "gn:dem":1716,
    "gn:feature_class":"P",
    "gn:feature_code":"PPLA2",
    "gn:name":"Tsamkan\u012b",
    "gn:population":0,
    "gn:timezone":"Asia/Kabul",
    "iso:country":"AF",
    "name:und_x_variant":[
        "Dzamkan\u012b",
        "Sakmanni Parao",
        "Qal\u2018eh-ye Chamkan\u012b",
        "Chamkani",
        "P\u012br Sar\u0101i",
        "\u010camkani",
        "Pir Serai",
        "Chakmani",
        "Chamkan\u012b",
        "Tsamkan\u012b",
        "\u0686\u0645\u06a9\u0646\u06cc",
        "\u0685\u0645\u06a9\u0646\u06cc"
    ],
    "wof:name":"Tsamkani",
    "wof:placetype":"locality"
},
  "geometry": {"coordinates":[69.81671,33.80298],"type":"Point"}
}