{
  "type": "Feature",
  "properties": {
    "gn:admin1_code":"17",
    "gn:admin2_code":"502.0",
    "gn:asciiname":"Sar Asyab",
    "gn:country_code":"AF",
    "gn:dem":2127,
    "gn:feature_class":"P",
    "gn:feature_code":"PPL",
    "gn:name":"Sar \u0100sy\u0101b",
    "gn:population":0,
    "gn:timezone":"Asia/Kabul",
    "iso:country":"AF",
    "name:und_x_variant":[
        "Sar \u0100s\u012b\u0101b",
        "Sar \u0100sy\u0101b",
        "\u0633\u0631 \u0622\u0633\u064a\u0627\u0628"
    ],
    "wof:name":"Sar Asyab",
    "wof:placetype":"locality"
},
  "geometry": {"coordinates":[68.94424000000001,33.78619],"type":"Point"}
}