{
  "type": "Feature",
  "properties": {
    "gn:admin1_code":"05",
    "gn:admin2_code":"2804.0",
    "gn:asciiname":"Zardigah",
    "gn:country_code":"AF",
    "gn:dem":3132,
    "gn:feature_class":"P",
    "gn:feature_code":"PPL",
    "gn:name":"Zard\u012bg\u0101h",
    "gn:population":0,
    "gn:timezone":"Asia/Kabul",
    "iso:country":"AF",
    "name:fas_x_preferred":[
        "\u0632\u0631\u062f\u064a\u06af\u0627\u0647"
    ],
    "name:rus_x_preferred":[
        "\u0417\u0430\u0440\u0434\u0438\u0433\u0430\u0445"
    ],
    "name:und_x_variant":[
        "Zardigakh",
        "Zard\u012bg\u0101h"
    ],
    "wof:name":"Zardigah",
    "wof:placetype":"locality"
},
  "geometry": {"coordinates":[67.15929,34.99838],"type":"Point"}
}