{
  "type": "Feature",
  "properties": {
    "gn:admin1_code":"8",
    "gn:admin2_code":"609.0",
    "gn:asciiname":"Aray",
    "gn:country_code":"AF",
    "gn:dem":1961,
    "gn:feature_class":"P",
    "gn:feature_code":"PPL",
    "gn:name":"Aray",
    "gn:population":0,
    "gn:timezone":"Asia/Kabul",
    "iso:country":"AF",
    "name:und_x_variant":[
        "\u0627\u0631\u06cc"
    ],
    "wof:name":"Aray",
    "wof:placetype":"locality"
},
  "geometry": {"coordinates":[67.76769,32.74688],"type":"Point"}
}