{
  "type": "Feature",
  "properties": {
    "gn:admin1_code":"08",
    "gn:admin2_code":"611",
    "gn:asciiname":"Ushlan",
    "gn:country_code":"AF",
    "gn:dem":2033,
    "gn:feature_class":"P",
    "gn:feature_code":"PPL",
    "gn:name":"Ushl\u0101n",
    "gn:population":0,
    "gn:timezone":"Asia/Kabul",
    "iso:country":"AF",
    "name:und_x_variant":[
        "U\u0161l\u0101n",
        "\u0627\u0634\u0644\u0627\u0646",
        "Ushl\u0101n"
    ],
    "wof:name":"Ushlan",
    "wof:placetype":"locality"
},
  "geometry": {"coordinates":[68.15049,32.76555],"type":"Point"}
}