{
  "type": "Feature",
  "properties": {
    "gn:admin1_code":"08",
    "gn:admin2_code":"614",
    "gn:asciiname":"Mulla Kala",
    "gn:country_code":"AF",
    "gn:dem":2090,
    "gn:feature_class":"P",
    "gn:feature_code":"PPL",
    "gn:name":"Mull\u0101 Kal\u0101",
    "gn:population":0,
    "gn:timezone":"Asia/Kabul",
    "iso:country":"AF",
    "name:und_x_variant":[
        "Mullakala",
        "Mol\u0101 Kal\u0101",
        "Moll\u0101 Kal\u0101",
        "Mull\u0101 Kal\u0101",
        "\u0645\u0644\u0627 \u06a9\u0644\u0627"
    ],
    "wof:name":"Mulla Kala",
    "wof:placetype":"locality"
},
  "geometry": {"coordinates":[68.56255,33.36846],"type":"Point"}
}