{
  "type": "Feature",
  "properties": {
    "gn:admin1_code":"40",
    "gn:admin2_code":"307.0",
    "gn:asciiname":"Malakh Khordah",
    "gn:country_code":"AF",
    "gn:dem":3097,
    "gn:feature_class":"P",
    "gn:feature_code":"PPL",
    "gn:name":"Malakh Kh\u014drdah",
    "gn:population":0,
    "gn:timezone":"Asia/Kabul",
    "iso:country":"AF",
    "name:und_x_variant":[
        "Mallakhkhorda",
        "Malakh-kh\u014d\u1e5f\u1e0fa",
        "Malakh Khvordeh",
        "Malakh Kh\u014drdah",
        "\u0645\u0644\u062e \u062e\u0648\u0631\u062f\u0647"
    ],
    "wof:name":"Malakh Khordah",
    "wof:placetype":"locality"
},
  "geometry": {"coordinates":[68.42333000000001,34.66954],"type":"Point"}
}