{
  "type": "Feature",
  "properties": {
    "gn:admin1_code":"13",
    "gn:admin2_code":"101.0",
    "gn:asciiname":"Chihil Sutun",
    "gn:country_code":"AF",
    "gn:dem":1882,
    "gn:feature_class":"P",
    "gn:feature_code":"PPL",
    "gn:name":"Chihil Sut\u016bn",
    "gn:population":0,
    "gn:timezone":"Asia/Kabul",
    "iso:country":"AF",
    "name:rus_x_preferred":[
        "Chikhil\u2019sutun"
    ],
    "name:und_x_variant":[
        "\u010cehelsot\u016bn",
        "Chehelsot\u016bn",
        "Chehel Sot\u016bn",
        "Chehelset\u016bn",
        "Chihil Sut\u016bn",
        "\u0686\u0647\u0644 \u0633\u062a\u0648\u0646"
    ],
    "wof:name":"Chihil Sutun",
    "wof:placetype":"locality"
},
  "geometry": {"coordinates":[69.16183000000001,34.4639],"type":"Point"}
}