{
  "type": "Feature",
  "properties": {
    "gn:admin1_code":"27",
    "gn:admin2_code":"403.0",
    "gn:asciiname":"Banaqash",
    "gn:country_code":"AF",
    "gn:dem":3058,
    "gn:feature_class":"P",
    "gn:feature_code":"PPL",
    "gn:name":"Banaq\u0101sh",
    "gn:population":0,
    "gn:timezone":"Asia/Kabul",
    "iso:country":"AF",
    "name:und_x_variant":[
        "Banakash",
        "Banaq\u0101s\u0304",
        "Baneh Q\u0101sh",
        "Ban\u0101g\u016bsh",
        "Banaq\u0101sh",
        "\u0628\u0646\u0642\u0627\u0634"
    ],
    "wof:name":"Banaqash",
    "wof:placetype":"locality"
},
  "geometry": {"coordinates":[68.11474,34.51103],"type":"Point"}
}