{
  "type": "Feature",
  "properties": {
    "gn:admin1_code":"01",
    "gn:admin2_code":"1115.0",
    "gn:asciiname":"Uzun Qol",
    "gn:country_code":"AF",
    "gn:dem":1800,
    "gn:feature_class":"P",
    "gn:feature_code":"PPL",
    "gn:name":"\u016az\u016bn Q\u014dl",
    "gn:population":0,
    "gn:timezone":"Asia/Kabul",
    "iso:country":"AF",
    "name:und_x_variant":[
        "\u016az\u016bn Q\u014dl",
        "\u016cz\u016bn Q\u016bl",
        "\u0627\u0648\u0632\u0648\u0646 \u0642\u0648\u0644"
    ],
    "wof:name":"Uzun Qol",
    "wof:placetype":"locality"
},
  "geometry": {"coordinates":[70.32099000000001,37.13851],"type":"Point"}
}