{
  "type": "Feature",
  "properties": {
    "gn:admin1_code":"28",
    "gn:admin2_code":"2503.0",
    "gn:asciiname":"Bar Ghantu",
    "gn:country_code":"AF",
    "gn:dem":1815,
    "gn:feature_class":"P",
    "gn:feature_code":"PPL",
    "gn:name":"Bar Ghant\u016b",
    "gn:population":0,
    "gn:timezone":"Asia/Kabul",
    "iso:country":"AF",
    "name:fas_x_preferred":[
        "\u0628\u0631\u063a\u0646\u062a\u0648"
    ],
    "name:und_x_variant":[
        "Bargantu",
        "Bar Ghant\u016b",
        "\u0628\u0631 \u063a\u0646\u062a\u0648",
        "Barghantu"
    ],
    "wof:name":"Bar Ghantu",
    "wof:placetype":"locality"
},
  "geometry": {"coordinates":[66.97138000000001,32.4136],"type":"Point"}
}