{
  "type": "Feature",
  "properties": {
    "gn:admin1_code":"13",
    "gn:admin2_code":"106.0",
    "gn:asciiname":"Istalif",
    "gn:country_code":"AF",
    "gn:dem":1690,
    "gn:feature_class":"P",
    "gn:feature_code":"PPL",
    "gn:name":"Ist\u0101lif",
    "gn:population":0,
    "gn:timezone":"Asia/Kabul",
    "iso:country":"AF",
    "name:cat_x_preferred":[
        "Istalif"
    ],
    "name:deu_x_preferred":[
        "Istalif"
    ],
    "name:fas_x_preferred":[
        "\u0627\u0633\u062a\u0627\u0644\u0641"
    ],
    "name:fra_x_preferred":[
        "Istalif"
    ],
    "name:und_x_variant":[
        "Ist\u0101lef",
        "Est\u0101lef",
        "\u0627\u0633\u062a\u0627\u0644\u0641",
        "Ist\u0101lif"
    ],
    "wof:name":"Istalif",
    "wof:placetype":"locality"
},
  "geometry": {"coordinates":[69.10138000000001,34.84213],"type":"Point"}
}