{
  "type": "Feature",
  "properties": {
    "gn:admin1_code":"06",
    "gn:admin2_code":"2103",
    "gn:asciiname":"Wulak",
    "gn:country_code":"AF",
    "gn:dem":1179,
    "gn:feature_class":"P",
    "gn:feature_code":"PPL",
    "gn:name":"Wulak",
    "gn:population":0,
    "gn:timezone":"Asia/Kabul",
    "iso:country":"AF",
    "name:und_x_variant":[
        "Vulak",
        "Wolak",
        "Wulak",
        "\u0648\u0644\u06a9",
        "W\u0101lak",
        "\u0648\u0627\u0644\u06a9"
    ],
    "wof:name":"Wulak",
    "wof:placetype":"locality"
},
  "geometry": {"coordinates":[63.06394,32.57737],"type":"Point"}
}