{
  "type": "Feature",
  "properties": {
    "gn:admin1_code":"05",
    "gn:admin2_code":"2806.0",
    "gn:asciiname":"Nawahgak",
    "gn:country_code":"AF",
    "gn:dem":2753,
    "gn:feature_class":"P",
    "gn:feature_code":"PPL",
    "gn:name":"N\u0101wahgak",
    "gn:population":0,
    "gn:timezone":"Asia/Kabul",
    "iso:country":"AF",
    "name:und_x_variant":[
        "Navagak",
        "Naw\u0101gak",
        "N\u0101wahgak",
        "\u0646\u0627\u0648\u0647 \u06af\u06a9"
    ],
    "wof:name":"Nawahgak",
    "wof:placetype":"locality"
},
  "geometry": {"coordinates":[67.31115,34.11604000000001],"type":"Point"}
}