{
  "type": "Feature",
  "properties": {
    "gn:admin1_code":"08",
    "gn:admin2_code":"619",
    "gn:asciiname":"Siyah Gul",
    "gn:country_code":"AF",
    "gn:dem":2274,
    "gn:feature_class":"P",
    "gn:feature_code":"PPL",
    "gn:name":"Siy\u0101h Gul",
    "gn:population":0,
    "gn:timezone":"Asia/Kabul",
    "iso:country":"AF",
    "name:fas_x_preferred":[
        "\u0633\u064a\u0627\u0647 \u06af\u0644"
    ],
    "name:rus_x_preferred":[
        "Siakhgil\u2019"
    ],
    "name:und_x_variant":[
        "Sy\u0101hgel",
        "S\u012b\u0101h Gel",
        "S\u012b\u0101hgel",
        "Siy\u0101h Gul"
    ],
    "wof:name":"Siyah Gul",
    "wof:placetype":"locality"
},
  "geometry": {"coordinates":[68.33549000000001,33.5128],"type":"Point"}
}