{
  "type": "Feature",
  "properties": {
    "gn:admin1_code":"23",
    "gn:admin2_code":"2405.0",
    "gn:asciiname":"Atalay",
    "gn:country_code":"AF",
    "gn:dem":1563,
    "gn:feature_class":"P",
    "gn:feature_code":"PPL",
    "gn:name":"Atalay",
    "gn:population":0,
    "gn:timezone":"Asia/Kabul",
    "iso:country":"AF",
    "name:und_x_variant":[
        "\u0627\u062a\u0644\u06cc"
    ],
    "wof:name":"Atalay",
    "wof:placetype":"locality"
},
  "geometry": {"coordinates":[65.43363000000001,32.18564],"type":"Point"}
}