{
  "type": "Feature",
  "properties": {
    "gn:admin1_code":"27",
    "gn:admin2_code":"406.0",
    "gn:asciiname":"Fazil Khel",
    "gn:country_code":"AF",
    "gn:dem":2291,
    "gn:feature_class":"P",
    "gn:feature_code":"PPL",
    "gn:name":"F\u0101\u1e95il Kh\u0113l",
    "gn:population":0,
    "gn:timezone":"Asia/Kabul",
    "iso:country":"AF",
    "name:rus_x_preferred":[
        "Fazil\u2019kheyl\u2019"
    ],
    "name:und_x_variant":[
        "F\u0101\u1e0f\u1e95elkh\u0113l",
        "F\u0101\u1e95el Kh\u0113l",
        "F\u0101\u1e95elkheyl",
        "F\u0101\u1e95il Kh\u0113l",
        "\u0641\u0627\u0636\u0644 \u062e\u06d0\u0644"
    ],
    "wof:name":"Fazil Khel",
    "wof:placetype":"locality"
},
  "geometry": {"coordinates":[68.51298,34.05260999999999],"type":"Point"}
}