{
  "type": "Feature",
  "properties": {
    "gn:admin1_code":"34",
    "gn:admin2_code":"1013.0",
    "gn:asciiname":"Mamagul Khwar",
    "gn:country_code":"AF",
    "gn:dem":2014,
    "gn:feature_class":"P",
    "gn:feature_code":"PPL",
    "gn:name":"M\u0101m\u0101gul Khwa\u1e5f",
    "gn:population":0,
    "gn:timezone":"Asia/Kabul",
    "iso:country":"AF",
    "name:fas_x_preferred":[
        "\u0645\u0627\u0645\u0627 \u06af\u0644 \u062e\u0648\u0631"
    ],
    "name:rus_x_preferred":[
        "Mamagul\u2019khvar"
    ],
    "name:und_x_variant":[
        "M\u0101m\u0101gul Khwar",
        "M\u0101m\u0101 Gol Khwa\u1e5f",
        "M\u0101m\u0101gul Khwa\u1e5f",
        "\u0645\u0627\u0645\u0627\u06af\u0644 \u062e\u0648\u0693"
    ],
    "wof:name":"Mamagul Khwar",
    "wof:placetype":"locality"
},
  "geometry": {"coordinates":[70.6927,34.72456],"type":"Point"}
}