{
  "type": "Feature",
  "properties": {
    "gn:admin1_code":"18",
    "gn:admin2_code":"802",
    "gn:asciiname":"Ghundey Kala",
    "gn:country_code":"AF",
    "gn:dem":860,
    "gn:feature_class":"P",
    "gn:feature_code":"PPL",
    "gn:name":"Ghun\u1e0f\u00eay Kal\u0101",
    "gn:population":0,
    "gn:timezone":"Asia/Kabul",
    "iso:country":"AF",
    "name:fas_x_preferred":[
        "\u063a\u0631\u0654 \u0643\u0644\u0627"
    ],
    "name:und_x_variant":[
        "Garkala",
        "Gha\u1e5f Kal\u0101",
        "Ghar-e Kal\u0101",
        "Ghun\u1e0f\u00eay Kal\u0101",
        "\u063a\u0646\u0689\u06cd \u06a9\u0644\u0627",
        "Ghar Kal\u0101",
        "\u063a\u0631 \u06a9\u0644\u0627"
    ],
    "wof:name":"Ghundey Kala",
    "wof:placetype":"locality"
},
  "geometry": {"coordinates":[70.15968000000001,34.38267],"type":"Point"}
}