{
  "type": "Feature",
  "properties": {
    "gn:admin1_code":"41",
    "gn:admin2_code":"3406",
    "gn:asciiname":"Zarkanak",
    "gn:country_code":"AF",
    "gn:dem":1444,
    "gn:feature_class":"P",
    "gn:feature_code":"PPL",
    "gn:name":"Zarkanak",
    "gn:population":0,
    "gn:timezone":"Asia/Kabul",
    "iso:country":"AF",
    "name:und_x_variant":[
        "\u0632\u0631\u06a9\u0646\u06a9",
        "Zarkanak",
        "Za\u1e5fkanak",
        "Zar Khanak"
    ],
    "wof:name":"Zarkanak",
    "wof:placetype":"locality"
},
  "geometry": {"coordinates":[65.68619,33.50025],"type":"Point"}
}