{
  "type": "Feature",
  "properties": {
    "gn:admin1_code":"9",
    "gn:admin2_code":"2703.0",
    "gn:asciiname":"Khwajahha",
    "gn:country_code":"AF",
    "gn:dem":2263,
    "gn:feature_class":"P",
    "gn:feature_code":"PPL",
    "gn:name":"Khw\u0101jahh\u0101",
    "gn:population":0,
    "gn:timezone":"Asia/Kabul",
    "iso:country":"AF",
    "name:und_x_variant":[
        "Khw\u0101jah\u0101",
        "Khv\u0101jehh\u0101",
        "Khw\u0101jahh\u0101",
        "\u062e\u0648\u0627\u062c\u0647 \u0647\u0627"
    ],
    "wof:name":"Khwajahha",
    "wof:placetype":"locality"
},
  "geometry": {"coordinates":[63.71007,33.9734],"type":"Point"}
}