{
  "type": "Feature",
  "properties": {
    "gn:admin1_code":"41",
    "gn:admin2_code":"3403.0",
    "gn:asciiname":"Baloch",
    "gn:country_code":"AF",
    "gn:dem":2655,
    "gn:feature_class":"P",
    "gn:feature_code":"PPL",
    "gn:name":"Bal\u014dch",
    "gn:population":0,
    "gn:timezone":"Asia/Kabul",
    "iso:country":"AF",
    "name:ceb_x_preferred":[
        "Baloch"
    ],
    "name:deu_x_preferred":[
        "Baloch"
    ],
    "name:swe_x_preferred":[
        "Baloch"
    ],
    "name:und_x_variant":[
        "Balo\u010d",
        "Bal\u014dch",
        "Bal\u016bch",
        "\u0628\u0644\u0648\u0686"
    ],
    "name:urd_x_preferred":[
        "\u0628\u0644\u0648\u0686"
    ],
    "wof:name":"Baloch",
    "wof:placetype":"locality"
},
  "geometry": {"coordinates":[66.30104,34.08581],"type":"Point"}
}