{
  "type": "Feature",
  "properties": {
    "gn:admin1_code":"35",
    "gn:admin2_code":"901.0",
    "gn:asciiname":"Deh-e Pashah'i",
    "gn:country_code":"AF",
    "gn:dem":749,
    "gn:feature_class":"P",
    "gn:feature_code":"PPL",
    "gn:name":"Deh-e Pashah\u2019\u012b",
    "gn:population":0,
    "gn:timezone":"Asia/Kabul",
    "iso:country":"AF",
    "name:und_x_variant":[
        "Deh-ye",
        "Dehe Pa\u0161a\u2019i",
        "Dekhi-Pashai",
        "Deh-ye Pasha\u2018i",
        "Deh-e Pashah\u2019\u012b",
        "\u062f\u0647 \u067e\u0634\u0647 \u0626\u06cc",
        "Pashah\u2019\u012b",
        "\u067e\u0634\u0647 \u0626\u06cc"
    ],
    "wof:name":"Deh-e Pashah'i",
    "wof:placetype":"locality"
},
  "geometry": {"coordinates":[70.21051999999999,34.6571],"type":"Point"}
}