{
  "type": "Feature",
  "properties": {
    "gn:admin1_code":"30",
    "gn:admin2_code":"1606.0",
    "gn:asciiname":"Bukah",
    "gn:country_code":"AF",
    "gn:dem":341,
    "gn:feature_class":"P",
    "gn:feature_code":"PPL",
    "gn:name":"Bukah",
    "gn:population":0,
    "gn:timezone":"Asia/Kabul",
    "iso:country":"AF",
    "name:fas_x_preferred":[
        "\u0628\u0643\u0647"
    ],
    "name:rus_x_preferred":[
        "\u0411\u043e\u043a\u0430"
    ],
    "name:und_x_variant":[
        "Uzumshakh",
        "Bokah",
        "Boka",
        "Bukah",
        "\u0627\u0632\u0645\u0634\u062e"
    ],
    "wof:name":"Bukah",
    "wof:placetype":"locality"
},
  "geometry": {"coordinates":[66.81877,36.75787],"type":"Point"}
}