{
  "type": "Feature",
  "properties": {
    "gn:admin1_code":"36",
    "gn:admin2_code":"701",
    "gn:asciiname":"Muhammad Raza Khel",
    "gn:country_code":"AF",
    "gn:dem":2674,
    "gn:feature_class":"P",
    "gn:feature_code":"PPL",
    "gn:name":"Mu\u1e29ammad Ra\u1e95\u0101 Kh\u0113l",
    "gn:population":0,
    "gn:timezone":"Asia/Kabul",
    "iso:country":"AF",
    "name:fas_x_preferred":[
        "\u0645\u062d\u0645\u062f \u0631\u0636\u0627 \u062e\u064a\u0644"
    ],
    "name:rus_x_preferred":[
        "Mukhkhammod-Razakheyl\u2019"
    ],
    "name:und_x_variant":[
        "Mohamma\u1e0f-\u1e5fa\u1e0f\u1e95\u0101kh\u0113l",
        "Mo\u1e29amme\u1e0f-\u1e5fa\u1e0f\u1e95\u0101kh\u0113l",
        "Mo\u1e29ammad Re\u1e95\u0101 Kheyl",
        "Mu\u1e29ammad Ra\u1e95\u0101 Kh\u0113l",
        "\u0645\u062d\u0645\u062f \u0631\u0636\u0627 \u062e\u06d0\u0644"
    ],
    "wof:name":"Muhammad Raza Khel",
    "wof:placetype":"locality"
},
  "geometry": {"coordinates":[69.19068,33.69347],"type":"Point"}
}