{
  "type": "Feature",
  "properties": {
    "gn:admin1_code":"5",
    "gn:admin2_code":"2806.0",
    "gn:asciiname":"Rashak",
    "gn:country_code":"AF",
    "gn:dem":2977,
    "gn:feature_class":"P",
    "gn:feature_code":"PPL",
    "gn:name":"Rashak",
    "gn:population":0,
    "gn:timezone":"Asia/Kabul",
    "iso:country":"AF",
    "name:und_x_variant":[
        "Ra\u0161ak",
        "Rashak",
        "\u0631\u0634\u06a9"
    ],
    "wof:name":"Rashak",
    "wof:placetype":"locality"
},
  "geometry": {"coordinates":[66.77750999999999,34.11759],"type":"Point"}
}