{
  "type": "Feature",
  "properties": {
    "gn:admin1_code":"31",
    "gn:admin2_code":"1710.0",
    "gn:asciiname":"Bakawul",
    "gn:country_code":"AF",
    "gn:dem":291,
    "gn:feature_class":"P",
    "gn:feature_code":"PPL",
    "gn:name":"Bakawul",
    "gn:population":0,
    "gn:timezone":"Asia/Kabul",
    "iso:country":"AF",
    "name:und_x_variant":[
        "\u0628\u06a9\u0648\u0644"
    ],
    "wof:name":"Bakawul",
    "wof:placetype":"locality"
},
  "geometry": {"coordinates":[66.09439999999999,36.89642],"type":"Point"}
}