{
  "type": "Feature",
  "properties": {
    "gn:admin1_code":"26",
    "gn:admin2_code":"1206",
    "gn:asciiname":"Shingan",
    "gn:country_code":"AF",
    "gn:dem":1446,
    "gn:feature_class":"P",
    "gn:feature_code":"PPL",
    "gn:name":"Shing\u0101n",
    "gn:population":0,
    "gn:timezone":"Asia/Kabul",
    "iso:country":"AF",
    "name:und_x_variant":[
        "Shing\u0101n",
        "\u0634\u0646\u06af\u0627\u0646",
        "Sing\u0101n"
    ],
    "wof:name":"Shingan",
    "wof:placetype":"locality"
},
  "geometry": {"coordinates":[69.94339000000001,36.56791],"type":"Point"}
}