{
  "type": "Feature",
  "properties": {
    "gn:admin1_code":"35",
    "gn:admin2_code":"903",
    "gn:asciiname":"Ja'alam",
    "gn:country_code":"AF",
    "gn:dem":978,
    "gn:feature_class":"P",
    "gn:feature_code":"PPL",
    "gn:name":"J\u0101\u2018alam",
    "gn:population":0,
    "gn:timezone":"Asia/Kabul",
    "iso:country":"AF",
    "name:und_x_variant":[
        "L\u0101\u2018alam",
        "Dzhaalam",
        "J\u0101\u2018alam",
        "\u062c\u0627\u0639\u0644\u0645"
    ],
    "wof:name":"Ja'alam",
    "wof:placetype":"locality"
},
  "geometry": {"coordinates":[70.38226,34.89994],"type":"Point"}
}