{
  "type": "Feature",
  "properties": {
    "gn:admin1_code":"06",
    "gn:admin2_code":"2103",
    "gn:asciiname":"Kuchnay Khaling",
    "gn:country_code":"AF",
    "gn:dem":1135,
    "gn:feature_class":"P",
    "gn:feature_code":"PPL",
    "gn:name":"K\u016bchnay Khaling",
    "gn:population":0,
    "gn:timezone":"Asia/Kabul",
    "iso:country":"AF",
    "name:und_x_variant":[
        "Kuchnay-Khaling",
        "Ku\u010dnay Khaleng",
        "K\u016bchnay Khaleng",
        "K\u016bchnay Khaling",
        "\u06a9\u0648\u0686\u0646\u06cc \u062e\u0644\u0646\u06af",
        "K\u016bchnay Khalinj",
        "\u06a9\u0648\u0686\u0646\u06cc \u062e\u0644\u0646\u062c"
    ],
    "wof:name":"Kuchnay Khaling",
    "wof:placetype":"locality"
},
  "geometry": {"coordinates":[63.04264000000001,32.58900999999999],"type":"Point"}
}