{
  "type": "Feature",
  "properties": {
    "gn:admin1_code":"41",
    "gn:admin2_code":"3406",
    "gn:asciiname":"Now-e Rah",
    "gn:country_code":"AF",
    "gn:dem":3044,
    "gn:feature_class":"P",
    "gn:feature_code":"PPL",
    "gn:name":"Now-e R\u0101h",
    "gn:population":0,
    "gn:timezone":"Asia/Kabul",
    "iso:country":"AF",
    "name:und_x_variant":[
        "Nawe \u1e5e\u0101h",
        "Now-e R\u0101h",
        "\u0646\u0648 \u0631\u0627\u0647",
        "Now R\u0101h"
    ],
    "wof:name":"Now-e Rah",
    "wof:placetype":"locality"
},
  "geometry": {"coordinates":[65.92886999999999,33.77746],"type":"Point"}
}