{
  "type": "Feature",
  "properties": {
    "gn:admin1_code":"05",
    "gn:admin2_code":"2804",
    "gn:asciiname":"Marghi",
    "gn:country_code":"AF",
    "gn:dem":2233,
    "gn:feature_class":"P",
    "gn:feature_code":"PPL",
    "gn:name":"Margh\u012b",
    "gn:population":0,
    "gn:timezone":"Asia/Kabul",
    "iso:country":"AF",
    "name:und_x_variant":[
        "Margi",
        "Margh\u012b",
        "\u0645\u0631\u063a\u06cc"
    ],
    "wof:name":"Marghi",
    "wof:placetype":"locality"
},
  "geometry": {"coordinates":[66.52404,34.97398],"type":"Point"}
}