{
  "type": "Feature",
  "properties": {
    "gn:admin1_code":"41",
    "gn:admin2_code":"3407.0",
    "gn:asciiname":"Shah Nawer",
    "gn:country_code":"AF",
    "gn:dem":2714,
    "gn:feature_class":"P",
    "gn:feature_code":"PPL",
    "gn:name":"Sh\u0101h N\u0101w\u00ear",
    "gn:population":0,
    "gn:timezone":"Asia/Kabul",
    "iso:country":"AF",
    "name:und_x_variant":[
        "\u0160\u0101nawur",
        "Sh\u0101h N\u0101wur",
        "Sh\u0101nawur",
        "\u0634\u0627\u0647 \u0646\u0627\u0648\u0631",
        "Sh\u0101h N\u0101w\u00ear"
    ],
    "wof:name":"Shah Nawer",
    "wof:placetype":"locality"
},
  "geometry": {"coordinates":[66.89536,33.92066],"type":"Point"}
}