{
  "type": "Feature",
  "properties": {
    "gn:admin1_code":"26",
    "gn:admin2_code":"1206.0",
    "gn:asciiname":"Kandakow",
    "gn:country_code":"AF",
    "gn:dem":1042,
    "gn:feature_class":"P",
    "gn:feature_code":"PPL",
    "gn:name":"Kandakow",
    "gn:population":0,
    "gn:timezone":"Asia/Kabul",
    "iso:country":"AF",
    "name:und_x_variant":[
        "\u06a9\u0646\u062f\u06a9\u0648",
        "Kan\u1e0fakaw"
    ],
    "wof:name":"Kandakow",
    "wof:placetype":"locality"
},
  "geometry": {"coordinates":[69.77715999999999,36.63191],"type":"Point"}
}