{
  "type": "Feature",
  "properties": {
    "gn:admin1_code":"03",
    "gn:admin2_code":"1304",
    "gn:asciiname":"Jolan",
    "gn:country_code":"AF",
    "gn:dem":2271,
    "gn:feature_class":"P",
    "gn:feature_code":"PPL",
    "gn:name":"J\u014dl\u0101n",
    "gn:population":0,
    "gn:timezone":"Asia/Kabul",
    "iso:country":"AF",
    "name:fas_x_preferred":[
        "\u062c\u0648\u0644\u0627\u0646"
    ],
    "name:und_x_variant":[
        "Qal\u2018eh-ye Jowl\u0101n",
        "Kala J\u0101ol\u0101n",
        "Qala Jaol\u0101n",
        "J\u014dl\u0101n",
        "Jowl\u0101n",
        "\u062c\u0648\u0644\u0627\u0646"
    ],
    "wof:name":"Jolan",
    "wof:placetype":"locality"
},
  "geometry": {"coordinates":[68.32029,35.62426],"type":"Point"}
}