{
  "type": "Feature",
  "properties": {
    "gn:admin1_code":"41",
    "gn:admin2_code":"3404.0",
    "gn:asciiname":"Chinaran",
    "gn:country_code":"AF",
    "gn:dem":1971,
    "gn:feature_class":"P",
    "gn:feature_code":"PPL",
    "gn:name":"Chin\u0101r\u0101n",
    "gn:population":0,
    "gn:timezone":"Asia/Kabul",
    "iso:country":"AF",
    "name:rus_x_preferred":[
        "\u0427\u0438\u043d\u0430\u0440\u0430\u043d"
    ],
    "name:und_x_variant":[
        "\u010cin\u0101r\u0101n",
        "Chin\u0101r\u0101n",
        "\u0686\u0646\u0627\u0631\u0627\u0646",
        "Chen\u0101r\u0101n"
    ],
    "wof:name":"Chinaran",
    "wof:placetype":"locality"
},
  "geometry": {"coordinates":[65.32873000000001,33.3562],"type":"Point"}
}