{
  "type": "Feature",
  "properties": {
    "gn:admin1_code":"09",
    "gn:admin2_code":"2702",
    "gn:asciiname":"Tangi Azaw",
    "gn:country_code":"AF",
    "gn:dem":2320,
    "gn:feature_class":"P",
    "gn:feature_code":"PPL",
    "gn:name":"Tang\u012b Az\u0101w",
    "gn:population":0,
    "gn:timezone":"Asia/Kabul",
    "iso:country":"AF",
    "name:und_x_variant":[
        "Rob\u0101\u0163-e Tang\u012b Azow",
        "Tang\u012b Az\u0101w",
        "Rab\u0101\u0163-e Tang\u012b Azow",
        "Tangi Az\u0101o",
        "Rab\u0101\u1e6fe Tangi Az\u0101w",
        "Tangi-Azau",
        "\u062a\u0646\u06af\u06cc \u0627\u0632\u0627\u0648",
        "Tang\u012b-e \u2018Az\u0304\u0101b"
    ],
    "wof:name":"Tangi Azaw",
    "wof:placetype":"locality"
},
  "geometry": {"coordinates":[64.20786,34.12425],"type":"Point"}
}