{
  "type": "Feature",
  "properties": {
    "gn:admin1_code":"40",
    "gn:admin2_code":"307",
    "gn:asciiname":"Kharakin",
    "gn:country_code":"AF",
    "gn:dem":2207,
    "gn:feature_class":"P",
    "gn:feature_code":"PPL",
    "gn:name":"Kharak\u012bn",
    "gn:population":0,
    "gn:timezone":"Asia/Kabul",
    "iso:country":"AF",
    "name:und_x_variant":[
        "Kharak\u012bn",
        "\u062e\u0631\u06a9\u06cc\u0646"
    ],
    "wof:name":"Kharakin",
    "wof:placetype":"locality"
},
  "geometry": {"coordinates":[68.64429,34.84842],"type":"Point"}
}