{
  "type": "Feature",
  "properties": {
    "gn:admin1_code":"35",
    "gn:admin2_code":"902.0",
    "gn:asciiname":"Muhammad Shah Bandah",
    "gn:country_code":"AF",
    "gn:dem":1733,
    "gn:feature_class":"P",
    "gn:feature_code":"PPL",
    "gn:name":"Mu\u1e29ammad Sh\u0101h B\u0101n\u1e0fah",
    "gn:population":0,
    "gn:timezone":"Asia/Kabul",
    "iso:country":"AF",
    "name:und_x_variant":[
        "Mu\u1e29ammad Sh\u0101h B\u0101n\u1e0fah",
        "\u0645\u062d\u0645\u062f \u0634\u0627\u0647 \u0628\u0627\u0646\u0689\u0647"
    ],
    "wof:name":"Muhammad Shah Bandah",
    "wof:placetype":"locality"
},
  "geometry": {"coordinates":[70.44471,34.66005999999999],"type":"Point"}
}