{
  "type": "Feature",
  "properties": {
    "gn:admin1_code":"35",
    "gn:admin2_code":"901",
    "gn:asciiname":"Maydani",
    "gn:country_code":"AF",
    "gn:dem":784,
    "gn:feature_class":"P",
    "gn:feature_code":"PPL",
    "gn:name":"Maydani",
    "gn:population":0,
    "gn:timezone":"Asia/Kabul",
    "iso:country":"AF",
    "name:und_x_variant":[
        "May\u1e0f\u0101ni",
        "Maydani",
        "Meyd\u0101n\u012b",
        "Ma\u012bd\u0101n\u012b",
        "\u0645\u06cc\u062f\u0627\u0646\u06cc"
    ],
    "wof:name":"Maydani",
    "wof:placetype":"locality"
},
  "geometry": {"coordinates":[70.2396,34.70446],"type":"Point"}
}