{
  "type": "Feature",
  "properties": {
    "gn:admin1_code":"9",
    "gn:admin2_code":"2706.0",
    "gn:asciiname":"Ab-Paran",
    "gn:country_code":"AF",
    "gn:dem":2621,
    "gn:feature_class":"P",
    "gn:feature_code":"PPL",
    "gn:name":"\u0100b-Par\u0101n",
    "gn:population":0,
    "gn:timezone":"Asia/Kabul",
    "iso:country":"AF",
    "name:und_x_variant":[
        "Abparan",
        "\u0100b-Par\u0101n",
        "\u0622\u0628 \u067e\u0631\u0627\u0646"
    ],
    "wof:name":"Ab-Paran",
    "wof:placetype":"locality"
},
  "geometry": {"coordinates":[64.65655,33.34932],"type":"Point"}
}