{
  "type": "Feature",
  "properties": {
    "gn:admin1_code":"05",
    "gn:admin2_code":"2802",
    "gn:asciiname":"Joy-e Shadi",
    "gn:country_code":"AF",
    "gn:dem":2266,
    "gn:feature_class":"P",
    "gn:feature_code":"PPL",
    "gn:name":"J\u014dy-e Sh\u0101d\u012b",
    "gn:population":0,
    "gn:timezone":"Asia/Kabul",
    "iso:country":"AF",
    "name:fas_x_preferred":[
        "\u062c\u0648\u06cc \u0634\u0627\u062f\u06cc"
    ],
    "name:und_x_variant":[
        "Dzhoyishadi",
        "Joye\u0161\u0101di",
        "J\u014dy-e Sh\u0101d\u012b",
        "J\u016by-ye Sh\u0101d\u012b",
        "J\u014dy-ye Sh\u0101d\u012b",
        "\u062c\u0648\u06cc \u0634\u0627\u062f\u06cc"
    ],
    "wof:name":"Joy-e Shadi",
    "wof:placetype":"locality"
},
  "geometry": {"coordinates":[67.99472,34.9957],"type":"Point"}
}