{
  "type": "Feature",
  "properties": {
    "gn:admin1_code":"08",
    "gn:admin2_code":"604.0",
    "gn:asciiname":"Nalah",
    "gn:country_code":"AF",
    "gn:dem":2865,
    "gn:feature_class":"P",
    "gn:feature_code":"PPL",
    "gn:name":"N\u0101lah",
    "gn:population":0,
    "gn:timezone":"Asia/Kabul",
    "iso:country":"AF",
    "name:und_x_variant":[
        "Nala",
        "N\u0101la",
        "N\u0101leh",
        "N\u0101lah",
        "\u0646\u0627\u0644\u0647"
    ],
    "wof:name":"Nalah",
    "wof:placetype":"locality"
},
  "geometry": {"coordinates":[67.35411999999999,34.03896],"type":"Point"}
}