{
  "type": "Feature",
  "properties": {
    "gn:admin1_code":"23",
    "gn:admin2_code":"2416.0",
    "gn:asciiname":"Haji 'Abdul Ahad Khan",
    "gn:country_code":"AF",
    "gn:dem":926,
    "gn:feature_class":"P",
    "gn:feature_code":"PPL",
    "gn:name":"\u1e28\u0101j\u012b \u2018Abdul A\u1e29ad Kh\u0101n",
    "gn:population":0,
    "gn:timezone":"Asia/Kabul",
    "iso:country":"AF",
    "name:und_x_variant":[
        "Khadzhi-Abduladkhan",
        "\u1e28\u0101ji \u2018Ab\u1e0fula\u1e29a\u1e0fkh\u0101n",
        "\u1e28\u0101j\u012b \u2018Abdul A\u1e29ad Kh\u0101n",
        "\u062d\u0627\u062c\u06cc \u0639\u0628\u062f\u0644 \u0627\u062d\u062f \u062e\u0627\u0646",
        "\u1e28\u0101jj\u012b \u2018Abdola\u1e29adkh\u0101n"
    ],
    "wof:name":"Haji 'Abdul Ahad Khan",
    "wof:placetype":"locality"
},
  "geometry": {"coordinates":[65.34061,31.52735],"type":"Point"}
}