{
  "type": "Feature",
  "properties": {
    "gn:admin1_code":"18",
    "gn:admin2_code":"810.0",
    "gn:asciiname":"Pesha",
    "gn:country_code":"AF",
    "gn:dem":2008,
    "gn:feature_class":"P",
    "gn:feature_code":"PPL",
    "gn:name":"Pesha",
    "gn:population":0,
    "gn:timezone":"Asia/Kabul",
    "iso:country":"AF",
    "name:fas_x_preferred":[
        "\u067e\u064a\u0634\u0647"
    ],
    "name:und_x_variant":[
        "P\u0113\u0161a",
        "P\u0113s\u0332h\u0332ah",
        "P\u0113shah",
        "\u067e\u06d0\u069a\u0647"
    ],
    "wof:name":"Pesha",
    "wof:placetype":"locality"
},
  "geometry": {"coordinates":[70.64556,33.99921],"type":"Point"}
}