{
  "type": "Feature",
  "properties": {
    "gn:admin1_code":"40",
    "gn:admin2_code":"301",
    "gn:asciiname":"Deh-e Mulla Yosuf",
    "gn:country_code":"AF",
    "gn:dem":1519,
    "gn:feature_class":"P",
    "gn:feature_code":"PPL",
    "gn:name":"Deh-e Mull\u0101 Y\u014dsuf",
    "gn:population":0,
    "gn:timezone":"Asia/Kabul",
    "iso:country":"AF",
    "name:fas_x_preferred":[
        "\u062f\u0647 \u0645\u0644\u0627 \u064a\u0648\u0633\u0641"
    ],
    "name:und_x_variant":[
        "Moll\u0101 Y\u016bsof",
        "\u1e0eehe Mol\u0101y\u014dsuf",
        "Mol\u0101y\u014dsuf",
        "Dekhi-Mullayusuf",
        "Deh-e Moll\u0101 Y\u016bsef",
        "Deh-e Mull\u0101 Y\u014dsuf",
        "\u062f\u0647 \u0645\u0644\u0627 \u06cc\u0648\u0633\u0641"
    ],
    "wof:name":"Deh-e Mulla Yosuf",
    "wof:placetype":"locality"
},
  "geometry": {"coordinates":[69.20413000000001,35.03175],"type":"Point"}
}