{
  "type": "Feature",
  "properties": {
    "gn:admin1_code":"34",
    "gn:admin2_code":"1004.0",
    "gn:asciiname":"Dandah",
    "gn:country_code":"AF",
    "gn:dem":2442,
    "gn:feature_class":"P",
    "gn:feature_code":"PPL",
    "gn:name":"\u1e0ean\u1e0fah",
    "gn:population":0,
    "gn:timezone":"Asia/Kabul",
    "iso:country":"AF",
    "name:fas_x_preferred":[
        "\u062f\u0646\u062f\u0647"
    ],
    "name:und_x_variant":[
        "Danda",
        "Dandah",
        "\u1e0ean\u1e0fah",
        "\u0689\u0646\u0689\u0647"
    ],
    "wof:name":"Dandah",
    "wof:placetype":"locality"
},
  "geometry": {"coordinates":[71.43795,34.94716],"type":"Point"}
}