{
  "type": "Feature",
  "properties": {
    "gn:admin1_code":"41",
    "gn:admin2_code":"3408",
    "gn:asciiname":"Kumronak",
    "gn:country_code":"AF",
    "gn:dem":2585,
    "gn:feature_class":"P",
    "gn:feature_code":"PPL",
    "gn:name":"Kumr\u014dnak",
    "gn:population":0,
    "gn:timezone":"Asia/Kabul",
    "iso:country":"AF",
    "name:und_x_variant":[
        "Kum\u1e5f\u014dnak",
        "Kumronak",
        "Kumr\u014dnak",
        "\u06a9\u0645\u0631\u0648\u0646\u06a9",
        "Komr\u016bnak"
    ],
    "wof:name":"Kumronak",
    "wof:placetype":"locality"
},
  "geometry": {"coordinates":[65.7984,34.11665],"type":"Point"}
}