{
  "type": "Feature",
  "properties": {
    "gn:admin1_code":"11",
    "gn:admin2_code":"2014",
    "gn:asciiname":"Ishtabad",
    "gn:country_code":"AF",
    "gn:dem":1113,
    "gn:feature_class":"P",
    "gn:feature_code":"PPL",
    "gn:name":"Isht\u0101b\u0101d",
    "gn:population":0,
    "gn:timezone":"Asia/Kabul",
    "iso:country":"AF",
    "name:und_x_variant":[
        "E\u0161t \u0100b\u0101d",
        "Esht \u0100b\u0101d",
        "Isht\u0101b\u0101d",
        "\u0627\u0634\u062a \u0622\u0628\u0627\u062f"
    ],
    "wof:name":"Ishtabad",
    "wof:placetype":"locality"
},
  "geometry": {"coordinates":[62.26199,33.35335],"type":"Point"}
}