{
  "type": "Feature",
  "properties": {
    "gn:admin1_code":"17",
    "gn:admin2_code":"507",
    "gn:asciiname":"Yerganah",
    "gn:country_code":"AF",
    "gn:dem":2685,
    "gn:feature_class":"P",
    "gn:feature_code":"PPL",
    "gn:name":"Yerganah",
    "gn:population":0,
    "gn:timezone":"Asia/Kabul",
    "iso:country":"AF",
    "name:und_x_variant":[
        "Ye\u1e5fgana",
        "Yirgana",
        "Yarganah",
        "Ye\u1e5fganah",
        "Yerganah",
        "\u06cc\u0631\u06af\u0646\u0647"
    ],
    "wof:name":"Yerganah",
    "wof:placetype":"locality"
},
  "geometry": {"coordinates":[68.78005,33.6454],"type":"Point"}
}