{
  "type": "Feature",
  "properties": {
    "gn:admin1_code":"08",
    "gn:admin2_code":"607",
    "gn:asciiname":"Seh Payah",
    "gn:country_code":"AF",
    "gn:dem":2569,
    "gn:feature_class":"P",
    "gn:feature_code":"PPL",
    "gn:name":"Seh P\u0101yah",
    "gn:population":0,
    "gn:timezone":"Asia/Kabul",
    "iso:country":"AF",
    "name:fas_x_preferred":[
        "\u0633\u0647 \u067e\u0627\u064a\u0647"
    ],
    "name:rus_x_preferred":[
        "\u0421\u0438\u0445\u043f\u0430\u044f"
    ],
    "name:und_x_variant":[
        "Sehp\u0101ya",
        "Sikhpaya",
        "Sehp\u0101yeh",
        "Seh P\u0101yah",
        "\u0633\u0647 \u067e\u0627\u06cc\u0647"
    ],
    "wof:name":"Seh Payah",
    "wof:placetype":"locality"
},
  "geometry": {"coordinates":[67.55199999999999,33.18122],"type":"Point"}
}