{
  "type": "Feature",
  "properties": {
    "gn:admin1_code":"11",
    "gn:admin2_code":"2014",
    "gn:asciiname":"Deh-e Lakah-ye Kadanak",
    "gn:country_code":"AF",
    "gn:dem":1170,
    "gn:feature_class":"P",
    "gn:feature_code":"PPL",
    "gn:name":"Deh-e Lakah-ye K\u0101d\u0101nak",
    "gn:population":0,
    "gn:timezone":"Asia/Kabul",
    "iso:country":"AF",
    "name:und_x_variant":[
        "Dehe Laka-i-K\u0101d\u0101nak",
        "Deh-e Laka-ye K\u0101d\u0101nak",
        "Deh-e Lakah-ye K\u0101d\u0101nak",
        "\u062f\u0647 \u0644\u06a9\u06c0 \u06a9\u0627\u062f\u0627\u0646\u06a9"
    ],
    "wof:name":"Deh-e Lakah-ye Kadanak",
    "wof:placetype":"locality"
},
  "geometry": {"coordinates":[61.98716,33.39862],"type":"Point"}
}