{
  "type": "Feature",
  "properties": {
    "gn:admin1_code":"28",
    "gn:admin2_code":"2511",
    "gn:asciiname":"Miyanzeh",
    "gn:country_code":"AF",
    "gn:dem":1972,
    "gn:feature_class":"P",
    "gn:feature_code":"PPL",
    "gn:name":"Miy\u0101nz\u00eah",
    "gn:population":0,
    "gn:timezone":"Asia/Kabul",
    "iso:country":"AF",
    "name:und_x_variant":[
        "My\u0101nzeh",
        "Mianza",
        "Miy\u0101nz\u00eah",
        "\u0645\u06cc\u0627\u0646\u0632\u0647",
        "M\u012b\u0101nzeh",
        "My\u0101nz\u00eah"
    ],
    "wof:name":"Miyanzeh",
    "wof:placetype":"locality"
},
  "geometry": {"coordinates":[67.60092,32.30963],"type":"Point"}
}