{
  "type": "Feature",
  "properties": {
    "gn:admin1_code":"13",
    "gn:admin2_code":"107",
    "gn:asciiname":"Ghazah",
    "gn:country_code":"AF",
    "gn:dem":2146,
    "gn:feature_class":"P",
    "gn:feature_code":"PPL",
    "gn:name":"Gh\u0101zah",
    "gn:population":0,
    "gn:timezone":"Asia/Kabul",
    "iso:country":"AF",
    "name:und_x_variant":[
        "Gaza",
        "Gh\u0101za",
        "Gh\u0101zah",
        "Gh\u0101zeh",
        "\u063a\u0627\u0632\u0647"
    ],
    "wof:name":"Ghazah",
    "wof:placetype":"locality"
},
  "geometry": {"coordinates":[69.00425,34.64286],"type":"Point"}
}