{
  "type": "Feature",
  "properties": {
    "gn:admin1_code":"8",
    "gn:admin2_code":"608.0",
    "gn:asciiname":"Chambar-e Mulla Muhammad Jan",
    "gn:country_code":"AF",
    "gn:dem":1990,
    "gn:feature_class":"P",
    "gn:feature_code":"PPL",
    "gn:name":"Chambar-e Mull\u0101 Mu\u1e29ammad J\u0101n",
    "gn:population":0,
    "gn:timezone":"Asia/Kabul",
    "iso:country":"AF",
    "name:und_x_variant":[
        "\u010cambare Mull\u0101 Mohammad J\u0101n",
        "Chambari-Mulla-Mukhammeddzhan",
        "Chanbar-e Moll\u0101 Mo\u1e29ammad J\u0101n",
        "Chambar-e Mull\u0101 Mu\u1e29ammad J\u0101n",
        "\u0686\u0645\u0628\u0631 \u0645\u0644\u0627 \u0645\u062d\u0645\u062f \u062c\u0627\u0646"
    ],
    "wof:name":"Chambar-e Mulla Muhammad Jan",
    "wof:placetype":"locality"
},
  "geometry": {"coordinates":[67.82318000000001,32.79531],"type":"Point"}
}