{
  "type": "Feature",
  "properties": {
    "gn:admin1_code":"06",
    "gn:admin2_code":"2109",
    "gn:asciiname":"Saliyan",
    "gn:country_code":"AF",
    "gn:dem":477,
    "gn:feature_class":"P",
    "gn:feature_code":"PPL",
    "gn:name":"Saliy\u0101n",
    "gn:population":0,
    "gn:timezone":"Asia/Kabul",
    "iso:country":"AF",
    "name:und_x_variant":[
        "Sal\u012b\u0101n",
        "Sal\u012by\u0101n",
        "\u015e\u0101li\u1e29\u0101n",
        "\u015e\u0101l\u012b\u0101n",
        "Saliy\u0101n",
        "\u0633\u0644\u06cc\u0627\u0646"
    ],
    "wof:name":"Saliyan",
    "wof:placetype":"locality"
},
  "geometry": {"coordinates":[61.56536,31.49094],"type":"Point"}
}