{
  "type": "Feature",
  "properties": {
    "gn:admin1_code":"39",
    "gn:admin2_code":"2603.0",
    "gn:asciiname":"Chakah",
    "gn:country_code":"AF",
    "gn:dem":2815,
    "gn:feature_class":"P",
    "gn:feature_code":"PPL",
    "gn:name":"Ch\u0101kah",
    "gn:population":0,
    "gn:timezone":"Asia/Kabul",
    "iso:country":"AF",
    "name:fas_x_preferred":[
        "\u0686\u0627\u0643\u0647"
    ],
    "name:und_x_variant":[
        "\u010c\u0101ka",
        "Saka",
        "Ch\u0101kah",
        "\u0686\u0627\u06a9\u0647"
    ],
    "wof:name":"Chakah",
    "wof:placetype":"locality"
},
  "geometry": {"coordinates":[66.78505,32.83647],"type":"Point"}
}