{
  "type": "Feature",
  "properties": {
    "gn:admin1_code":"10",
    "gn:admin2_code":"2302",
    "gn:asciiname":"Surkhabad",
    "gn:country_code":"AF",
    "gn:dem":935,
    "gn:feature_class":"P",
    "gn:feature_code":"PPL",
    "gn:name":"Surkh\u0101b\u0101d",
    "gn:population":0,
    "gn:timezone":"Asia/Kabul",
    "iso:country":"AF",
    "name:und_x_variant":[
        "Su\u1e5fkh\u0101b\u0101\u1e0f",
        "Surkhabad",
        "Surkh\u0101b\u0101d",
        "\u0633\u0631\u062e \u0622\u0628\u0627\u062f",
        "Sorkh\u0101b\u0101d"
    ],
    "wof:name":"Surkhabad",
    "wof:placetype":"locality"
},
  "geometry": {"coordinates":[64.86678000000001,31.97725],"type":"Point"}
}