{
  "type": "Feature",
  "properties": {
    "gn:admin1_code":"13",
    "gn:admin2_code":"108.0",
    "gn:asciiname":"'Isa Khel",
    "gn:country_code":"AF",
    "gn:dem":2214,
    "gn:feature_class":"P",
    "gn:feature_code":"PPL",
    "gn:name":"\u2018\u012as\u00e1 Kh\u0113l",
    "gn:population":0,
    "gn:timezone":"Asia/Kabul",
    "iso:country":"AF",
    "name:rus_x_preferred":[
        "Isakheyl\u2019"
    ],
    "name:und_x_variant":[
        "\u2018Is\u0101kh\u0113l",
        "\u2018Is\u00e1kheyl",
        "\u2018\u012as\u00e1 Kh\u0113l",
        "\u0639\u06cc\u0633\u06cc \u062e\u06d0\u0644"
    ],
    "wof:name":"'Isa Khel",
    "wof:placetype":"locality"
},
  "geometry": {"coordinates":[68.98151999999999,34.5875],"type":"Point"}
}