{
  "type": "Feature",
  "properties": {
    "gn:admin1_code":"3",
    "gn:admin2_code":"1303.0",
    "gn:asciiname":"Darah-ye Kalan",
    "gn:country_code":"AF",
    "gn:dem":814,
    "gn:feature_class":"P",
    "gn:feature_code":"PPL",
    "gn:name":"Darah-ye Kal\u0101n",
    "gn:population":0,
    "gn:timezone":"Asia/Kabul",
    "iso:country":"AF",
    "name:und_x_variant":[
        "Qaluq",
        "Darreh-ye Kal\u0101n",
        "Darah-ye Kal\u0101n",
        "\u062f\u0631\u06c0 \u06a9\u0644\u0627\u0646",
        "\u0642\u0644\u0642"
    ],
    "wof:name":"Darah-ye Kalan",
    "wof:placetype":"locality"
},
  "geometry": {"coordinates":[68.48654000000001,35.89718],"type":"Point"}
}