{
  "type": "Feature",
  "properties": {
    "gn:admin1_code":"40",
    "gn:admin2_code":"305.0",
    "gn:asciiname":"Baqal Qol",
    "gn:country_code":"AF",
    "gn:dem":2566,
    "gn:feature_class":"P",
    "gn:feature_code":"PPL",
    "gn:name":"B\u0101qal Q\u014dl",
    "gn:population":0,
    "gn:timezone":"Asia/Kabul",
    "iso:country":"AF",
    "name:rus_x_preferred":[
        "Bakal\u2019kul\u2019"
    ],
    "name:und_x_variant":[
        "B\u0101qalq\u014dl",
        "B\u0101qalqowl",
        "B\u0101qal Q\u014dl",
        "\u0628\u0627\u0642\u0644 \u0642\u0648\u0644"
    ],
    "wof:name":"Baqal Qol",
    "wof:placetype":"locality"
},
  "geometry": {"coordinates":[68.92716,34.92992],"type":"Point"}
}