{
  "type": "Feature",
  "properties": {
    "gn:admin1_code":"30",
    "gn:admin2_code":"1609",
    "gn:asciiname":"Siyah Aw",
    "gn:country_code":"AF",
    "gn:dem":553,
    "gn:feature_class":"P",
    "gn:feature_code":"PPL",
    "gn:name":"Siy\u0101h \u0100w",
    "gn:population":0,
    "gn:timezone":"Asia/Kabul",
    "iso:country":"AF",
    "name:und_x_variant":[
        "Siy\u0101h Au",
        "S\u012b\u0101h \u0100b",
        "S\u012b\u0101h \u0100w",
        "\u0633\u06cc\u0627\u0647 \u0622\u0648",
        "Siy\u0101h \u0100w"
    ],
    "wof:name":"Siyah Aw",
    "wof:placetype":"locality"
},
  "geometry": {"coordinates":[66.92171,36.38889],"type":"Point"}
}