{
  "type": "Feature",
  "properties": {
    "gn:admin1_code":"3",
    "gn:admin2_code":"1311.0",
    "gn:asciiname":"Quchi",
    "gn:country_code":"AF",
    "gn:dem":638,
    "gn:feature_class":"P",
    "gn:feature_code":"PPL",
    "gn:name":"Q\u016bch\u012b",
    "gn:population":0,
    "gn:timezone":"Asia/Kabul",
    "iso:country":"AF",
    "name:ara_x_preferred":[
        "\u0642\u0648\u062a\u0634\u064a"
    ],
    "name:fas_x_preferred":[
        "\u0642\u0686\u06cc"
    ],
    "name:fas_x_variant":[
        "\u0642\u0648\u0686\u06cc"
    ],
    "name:rus_x_preferred":[
        "\u041a\u0443\u0447\u0438"
    ],
    "name:und_x_variant":[
        "Kuchi",
        "Qu\u010di",
        "Quch\u012b",
        "Q\u016bch\u012b",
        "\u0642\u0648\u0686\u06cc"
    ],
    "wof:name":"Quchi",
    "wof:placetype":"locality"
},
  "geometry": {"coordinates":[68.88083,36.2332],"type":"Point"}
}