{
  "type": "Feature",
  "properties": {
    "gn:admin1_code":"40",
    "gn:admin2_code":"305.0",
    "gn:asciiname":"Sadwar",
    "gn:country_code":"AF",
    "gn:dem":1935,
    "gn:feature_class":"P",
    "gn:feature_code":"PPL",
    "gn:name":"\u015eadw\u0101r",
    "gn:population":0,
    "gn:timezone":"Asia/Kabul",
    "iso:country":"AF",
    "name:und_x_variant":[
        "Sadvar",
        "Sadw\u0101r",
        "\u015eadw\u0101r",
        "\u0635\u062f\u0648\u0627\u0631"
    ],
    "wof:name":"Sadwar",
    "wof:placetype":"locality"
},
  "geometry": {"coordinates":[68.89321,34.99193],"type":"Point"}
}