{
  "type": "Feature",
  "properties": {
    "gn:admin1_code":"11",
    "gn:admin2_code":"2014",
    "gn:asciiname":"Jambaran",
    "gn:country_code":"AF",
    "gn:dem":1153,
    "gn:feature_class":"P",
    "gn:feature_code":"PPL",
    "gn:name":"Jambar\u0101n",
    "gn:population":0,
    "gn:timezone":"Asia/Kabul",
    "iso:country":"AF",
    "name:und_x_variant":[
        "Dzhambaran",
        "Jambar\u0101n",
        "\u062c\u0645\u0628\u0631\u0627\u0646"
    ],
    "wof:name":"Jambaran",
    "wof:placetype":"locality"
},
  "geometry": {"coordinates":[62.32608000000001,33.39864],"type":"Point"}
}