{
  "type": "Feature",
  "properties": {
    "gn:admin1_code":"23",
    "gn:admin2_code":"2411",
    "gn:asciiname":"Zarah Kala",
    "gn:country_code":"AF",
    "gn:dem":1155,
    "gn:feature_class":"P",
    "gn:feature_code":"PPL",
    "gn:name":"Zarah Kal\u0101",
    "gn:population":0,
    "gn:timezone":"Asia/Kabul",
    "iso:country":"AF",
    "name:rus_x_preferred":[
        "\u0417\u0430\u0440\u0430-\u041a\u0430\u043b\u0430"
    ],
    "name:und_x_variant":[
        "Zara Kal\u0101",
        "Dost Muhammad Kil\u012b",
        "Zara-Kala",
        "Zarah Kal\u0101",
        "\u0632\u0631\u0647 \u06a9\u0644\u0627"
    ],
    "wof:name":"Zarah Kala",
    "wof:placetype":"locality"
},
  "geometry": {"coordinates":[66.26694000000001,30.99528],"type":"Point"}
}