{
  "type": "Feature",
  "properties": {
    "gn:admin1_code":"40",
    "gn:admin2_code":"307",
    "gn:asciiname":"Khanjak",
    "gn:country_code":"AF",
    "gn:dem":2248,
    "gn:feature_class":"P",
    "gn:feature_code":"PPL",
    "gn:name":"Khanjak",
    "gn:population":0,
    "gn:timezone":"Asia/Kabul",
    "iso:country":"AF",
    "name:und_x_variant":[
        "Khanja",
        "Khandzhak",
        "Khanjak",
        "\u062e\u0646\u062c\u06a9"
    ],
    "wof:name":"Khanjak",
    "wof:placetype":"locality"
},
  "geometry": {"coordinates":[68.74042,34.90338],"type":"Point"}
}