{
  "type": "Feature",
  "properties": {
    "gn:admin1_code":"5",
    "gn:admin2_code":"2801.0",
    "gn:asciiname":"Baba Dost",
    "gn:country_code":"AF",
    "gn:dem":2912,
    "gn:feature_class":"P",
    "gn:feature_code":"PPL",
    "gn:name":"B\u0101b\u0101 D\u014dst",
    "gn:population":0,
    "gn:timezone":"Asia/Kabul",
    "iso:country":"AF",
    "name:und_x_variant":[
        "Babadost",
        "B\u0101bad\u014dst",
        "B\u0101b\u0101 D\u014dst",
        "B\u0101b\u0101d\u016bst",
        "\u0628\u0627\u0628\u0627 \u062f\u0648\u0633\u062a"
    ],
    "wof:name":"Baba Dost",
    "wof:placetype":"locality"
},
  "geometry": {"coordinates":[67.66005,34.7506],"type":"Point"}
}