{
  "type": "Feature",
  "properties": {
    "gn:admin1_code":"03",
    "gn:admin2_code":"1304",
    "gn:asciiname":"Iskar",
    "gn:country_code":"AF",
    "gn:dem":1241,
    "gn:feature_class":"P",
    "gn:feature_code":"PPL",
    "gn:name":"Isk\u0101r",
    "gn:population":0,
    "gn:timezone":"Asia/Kabul",
    "iso:country":"AF",
    "name:und_x_variant":[
        "Qowl-e Esk\u0101r",
        "Iskar",
        "Isk\u0101r",
        "Esk\u0101r",
        "\u0627\u0633\u06a9\u0627\u0631"
    ],
    "wof:name":"Iskar",
    "wof:placetype":"locality"
},
  "geometry": {"coordinates":[68.52304000000001,35.55455999999999],"type":"Point"}
}