{
  "type": "Feature",
  "properties": {
    "gn:admin1_code":"09",
    "gn:admin2_code":"2703",
    "gn:asciiname":"Qal'ah-ye Shakh",
    "gn:country_code":"AF",
    "gn:dem":1726,
    "gn:feature_class":"P",
    "gn:feature_code":"PPL",
    "gn:name":"Qal\u2018ah-ye Sh\u0101kh",
    "gn:population":0,
    "gn:timezone":"Asia/Kabul",
    "iso:country":"AF",
    "name:und_x_variant":[
        "Qal\u2018a-i-Sakh",
        "Qal\u2018ah-ye Sh\u0101kh",
        "\u0642\u0644\u0639\u06c0 \u0634\u0627\u062e",
        "Qal\u2018eh-ye Sh\u0101kh"
    ],
    "wof:name":"Qal'ah-ye Shakh",
    "wof:placetype":"locality"
},
  "geometry": {"coordinates":[63.49601,34.14684],"type":"Point"}
}