{
  "type": "Feature",
  "properties": {
    "gn:admin1_code":"27",
    "gn:admin2_code":"406",
    "gn:asciiname":"Idil",
    "gn:country_code":"AF",
    "gn:dem":2459,
    "gn:feature_class":"P",
    "gn:feature_code":"PPL",
    "gn:name":"Idil",
    "gn:population":0,
    "gn:timezone":"Asia/Kabul",
    "iso:country":"AF",
    "name:rus_x_preferred":[
        "Idil\u2019"
    ],
    "name:und_x_variant":[
        "\u012adel",
        "Edel",
        "Idil",
        "\u0627\u062f\u0644"
    ],
    "wof:name":"Idil",
    "wof:placetype":"locality"
},
  "geometry": {"coordinates":[68.62221,34.22020999999999],"type":"Point"}
}