{
  "type": "Feature",
  "properties": {
    "gn:admin1_code":"05",
    "gn:admin2_code":"2806.0",
    "gn:asciiname":"Shaywak-e Pa'in",
    "gn:country_code":"AF",
    "gn:dem":2740,
    "gn:feature_class":"P",
    "gn:feature_code":"PPL",
    "gn:name":"Shaywak-e P\u0101\u2019\u012bn",
    "gn:population":0,
    "gn:timezone":"Asia/Kabul",
    "iso:country":"AF",
    "wof:name":"Shaywak-e Pa'in",
    "wof:placetype":"locality"
},
  "geometry": {"coordinates":[66.92910000000001,34.19836],"type":"Point"}
}