{
  "type": "Feature",
  "properties": {
    "gn:admin1_code":"01",
    "gn:admin2_code":"1104",
    "gn:asciiname":"Qal'ah-ye Shah",
    "gn:country_code":"AF",
    "gn:dem":2916,
    "gn:feature_class":"P",
    "gn:feature_code":"PPL",
    "gn:name":"Qal\u2018ah-ye Sh\u0101h",
    "gn:population":0,
    "gn:timezone":"Asia/Kabul",
    "iso:country":"AF",
    "name:und_x_variant":[
        "Ql Sh\u0101h",
        "Qal\u2019a-i-\u0160\u0101h",
        "Kalashakh",
        "\u0642\u0644\u0639\u0647 \u0634\u0627\u0647",
        "Qal\u2018eh-ye Sh\u0101h",
        "Qal\u2018ah-ye Sh\u0101h"
    ],
    "wof:name":"Qal'ah-ye Shah",
    "wof:placetype":"locality"
},
  "geometry": {"coordinates":[70.83448,35.82097],"type":"Point"}
}