{
  "type": "Feature",
  "properties": {
    "gn:admin1_code":"23",
    "gn:admin2_code":"2412",
    "gn:asciiname":"Dawutay",
    "gn:country_code":"AF",
    "gn:dem":1247,
    "gn:feature_class":"P",
    "gn:feature_code":"PPL",
    "gn:name":"D\u0101w\u016btay",
    "gn:population":0,
    "gn:timezone":"Asia/Kabul",
    "iso:country":"AF",
    "name:und_x_variant":[
        "Davutay",
        "D\u014dw\u016btay",
        "\u1e0e\u0101w\u016btay",
        "Dow\u016btay",
        "\u062f\u0648\u0648\u062a\u06cc",
        "\u1e0e\u016bwow\u1e6fay",
        "D\u0101w\u016btay",
        "\u062f\u0627\u0648\u0648\u062a\u06cc"
    ],
    "wof:name":"Dawutay",
    "wof:placetype":"locality"
},
  "geometry": {"coordinates":[66.42069000000001,31.51457000000001],"type":"Point"}
}