{
  "type": "Feature",
  "properties": {
    "gn:admin1_code":"10",
    "gn:admin2_code":"2306.0",
    "gn:asciiname":"Khawi",
    "gn:cc2":"AF",
    "gn:country_code":"AF",
    "gn:dem":1729,
    "gn:feature_class":"P",
    "gn:feature_code":"PPL",
    "gn:name":"Kh\u0101wi",
    "gn:population":0,
    "gn:timezone":"Asia/Kabul",
    "iso:country":"AF",
    "name:und_x_variant":[
        "Khavi"
    ],
    "wof:name":"Khawi",
    "wof:placetype":"locality"
},
  "geometry": {"coordinates":[64.25556,32.54389],"type":"Point"}
}