{
  "type": "Feature",
  "properties": {
    "gn:admin1_code":"14",
    "gn:admin2_code":"204.0",
    "gn:asciiname":"Sharif Khel",
    "gn:country_code":"AF",
    "gn:dem":1800,
    "gn:feature_class":"P",
    "gn:feature_code":"PPL",
    "gn:name":"Shar\u012bf Kh\u0113l",
    "gn:population":0,
    "gn:timezone":"Asia/Kabul",
    "iso:country":"AF",
    "name:fas_x_preferred":[
        "\u0634\u0631\u064a\u0641 \u062e\u064a\u0644"
    ],
    "name:rus_x_preferred":[
        "\u0428\u0430\u0440\u0438\u0444\u0445\u0435\u0439\u043b\u044c"
    ],
    "name:und_x_variant":[
        "Sharifkheyl\u2019",
        "\u0160ar\u012bfkh\u0113l",
        "Shar\u012bfkheyl",
        "Shar\u012bf Kh\u0113l",
        "\u0634\u0631\u06cc\u0641 \u062e\u06d0\u0644"
    ],
    "wof:name":"Sharif Khel",
    "wof:placetype":"locality"
},
  "geometry": {"coordinates":[69.62595999999999,35.00716],"type":"Point"}
}