{
  "type": "Feature",
  "properties": {
    "gn:admin1_code":"18",
    "gn:admin2_code":"812.0",
    "gn:asciiname":"Tsobi",
    "gn:country_code":"AF",
    "gn:dem":1283,
    "gn:feature_class":"P",
    "gn:feature_code":"PPL",
    "gn:name":"Ts\u014db\u012b",
    "gn:population":0,
    "gn:timezone":"Asia/Kabul",
    "iso:country":"AF",
    "name:fas_x_preferred":[
        "\u0686\u0648\u0628\u06cc"
    ],
    "name:und_x_variant":[
        "Toatsobi",
        "C\u014dbi",
        "Tsobi",
        "Tsatsobi",
        "Ts\u014db\u012b",
        "Ts\u016bb\u012b",
        "\u0685\u0648\u0628\u06cc"
    ],
    "wof:name":"Tsobi",
    "wof:placetype":"locality"
},
  "geometry": {"coordinates":[71.02745999999998,34.06862],"type":"Point"}
}