{
  "type": "Feature",
  "properties": {
    "gn:admin1_code":"03",
    "gn:admin2_code":"1311",
    "gn:asciiname":"Turani",
    "gn:country_code":"AF",
    "gn:dem":542,
    "gn:feature_class":"P",
    "gn:feature_code":"PPL",
    "gn:name":"Turani",
    "gn:population":0,
    "gn:timezone":"Asia/Kabul",
    "iso:country":"AF",
    "name:rus_x_preferred":[
        "\u0422\u0443\u0440\u0430\u043d\u0438"
    ],
    "name:srp_x_preferred":[
        "\u0422\u0443\u0440\u0430\u043d\u0438"
    ],
    "name:und_x_variant":[
        "T\u016br\u0101n\u012b",
        "\u062a\u0648\u0631\u0627\u0646\u06cc",
        "Turani"
    ],
    "wof:name":"Turani",
    "wof:placetype":"locality"
},
  "geometry": {"coordinates":[68.75623,36.15278],"type":"Point"}
}