{
  "type": "Feature",
  "properties": {
    "gn:admin1_code":"09",
    "gn:admin2_code":"2706",
    "gn:asciiname":"Dughor",
    "gn:country_code":"AF",
    "gn:dem":2227,
    "gn:feature_class":"P",
    "gn:feature_code":"PPL",
    "gn:name":"Dugh\u014dr",
    "gn:population":0,
    "gn:timezone":"Asia/Kabul",
    "iso:country":"AF",
    "name:fas_x_preferred":[
        "\u062f\u0648\u063a\u0648\u0631"
    ],
    "name:rus_x_preferred":[
        "\u0414\u0443\u0433\u043e\u0440"
    ],
    "name:und_x_variant":[
        "\u1e0eogh\u014d\u1e5f",
        "Dugor",
        "Dugh\u014dr",
        "\u062f\u063a\u0648\u0631",
        "Dogh\u016br"
    ],
    "wof:name":"Dughor",
    "wof:placetype":"locality"
},
  "geometry": {"coordinates":[65.02722,33.39366],"type":"Point"}
}