{
  "type": "Feature",
  "properties": {
    "gn:admin1_code":"23",
    "gn:admin2_code":"2412.0",
    "gn:asciiname":"Banu Khel",
    "gn:country_code":"AF",
    "gn:dem":1408,
    "gn:feature_class":"P",
    "gn:feature_code":"PPL",
    "gn:name":"B\u0101n\u016b Kh\u0113l",
    "gn:population":0,
    "gn:timezone":"Asia/Kabul",
    "iso:country":"AF",
    "name:und_x_variant":[
        "Bannu Khel",
        "B\u0101n\u016bkh\u0113l",
        "Banukheyl\u2019",
        "\u0628\u0627\u0646\u0648\u062e\u06d0\u0644",
        "B\u0101n\u016b Kheyl",
        "B\u0101n\u016b Kh\u0113l"
    ],
    "wof:name":"Banu Khel",
    "wof:placetype":"locality"
},
  "geometry": {"coordinates":[66.72696999999999,31.56553],"type":"Point"}
}