{
  "type": "Feature",
  "properties": {
    "gn:admin1_code":"40",
    "gn:admin2_code":"301.0",
    "gn:asciiname":"Dzangal Bagh",
    "gn:country_code":"AF",
    "gn:dem":1543,
    "gn:feature_class":"P",
    "gn:feature_code":"PPL",
    "gn:name":"Dzangal B\u0101gh",
    "gn:population":0,
    "gn:timezone":"Asia/Kabul",
    "iso:country":"AF",
    "name:fas_x_preferred":[
        "\u0681\u0646\u06af\u0644 \u0628\u0627\u063a"
    ],
    "name:rus_x_preferred":[
        "Dzhangal\u2019bag"
    ],
    "name:und_x_variant":[
        "\u0681\u0646\u06af\u0644 \u0628\u0627\u063a",
        "Jangal B\u0101gh",
        "Dzangal B\u0101gh",
        "\u062c\u0646\u06af\u0644 \u0628\u0627\u063a"
    ],
    "wof:name":"Dzangal Bagh",
    "wof:placetype":"locality"
},
  "geometry": {"coordinates":[69.19694,35.05475999999999],"type":"Point"}
}