{
  "type": "Feature",
  "properties": {
    "gn:admin1_code":"40",
    "gn:admin2_code":"307.0",
    "gn:asciiname":"Howli",
    "gn:country_code":"AF",
    "gn:dem":2301,
    "gn:feature_class":"P",
    "gn:feature_code":"PPL",
    "gn:name":"\u1e28owl\u012b",
    "gn:population":0,
    "gn:timezone":"Asia/Kabul",
    "iso:country":"AF",
    "name:und_x_variant":[
        "Khauli",
        "\u1e28awli",
        "\u1e28avl\u012b",
        "\u1e28owl\u012b",
        "\u062d\u0648\u0644\u06cc"
    ],
    "wof:name":"Howli",
    "wof:placetype":"locality"
},
  "geometry": {"coordinates":[68.65975,34.79162],"type":"Point"}
}