{
  "type": "Feature",
  "properties": {
    "gn:admin1_code":"05",
    "gn:admin2_code":"2807",
    "gn:asciiname":"Qarwanah",
    "gn:country_code":"AF",
    "gn:dem":2088,
    "gn:feature_class":"P",
    "gn:feature_code":"PPL",
    "gn:name":"Qarw\u0101nah",
    "gn:population":0,
    "gn:timezone":"Asia/Kabul",
    "iso:country":"AF",
    "name:und_x_variant":[
        "Qarw\u0101na",
        "Qarw\u0101neh",
        "Qarw\u0101nah",
        "\u0642\u0631\u0648\u0627\u0646\u0647"
    ],
    "wof:name":"Qarwanah",
    "wof:placetype":"locality"
},
  "geometry": {"coordinates":[67.65203000000001,35.17052],"type":"Point"}
}