{
  "type": "Feature",
  "properties": {
    "gn:admin1_code":"8",
    "gn:admin2_code":"618.0",
    "gn:asciiname":"'Amzalak",
    "gn:country_code":"AF",
    "gn:dem":2548,
    "gn:feature_class":"P",
    "gn:feature_code":"PPL",
    "gn:name":"\u2018Amzalak",
    "gn:population":0,
    "gn:timezone":"Asia/Kabul",
    "iso:country":"AF",
    "name:fas_x_preferred":[
        "\u0627\u0645\u0632\u0644\u0643"
    ],
    "name:und_x_variant":[
        "Amzalak",
        "\u2018Amzalak",
        "\u0639\u0645\u0632\u0644\u06a9"
    ],
    "wof:name":"'Amzalak",
    "wof:placetype":"locality"
},
  "geometry": {"coordinates":[68.14608,33.46266],"type":"Point"}
}