{
  "type": "Feature",
  "properties": {
    "gn:admin1_code":"27",
    "gn:admin2_code":"402.0",
    "gn:asciiname":"Dar-e Mihraban",
    "gn:country_code":"AF",
    "gn:dem":2572,
    "gn:feature_class":"P",
    "gn:feature_code":"PPL",
    "gn:name":"Dar-e Mihrab\u0101n",
    "gn:population":0,
    "gn:timezone":"Asia/Kabul",
    "iso:country":"AF",
    "name:und_x_variant":[
        "Dari-Mikhraban",
        "Darah-ye Mehrab\u0101n",
        "Dar-e Mehrab\u0101n",
        "Dar-e Mihrab\u0101n",
        "\u062f\u0631 \u0645\u0647\u0631\u0628\u0627\u0646"
    ],
    "wof:name":"Dar-e Mihraban",
    "wof:placetype":"locality"
},
  "geometry": {"coordinates":[68.62451999999999,34.44197],"type":"Point"}
}