{
  "type": "Feature",
  "properties": {
    "gn:admin1_code":"41",
    "gn:admin2_code":"3406.0",
    "gn:asciiname":"Anar Joy",
    "gn:country_code":"AF",
    "gn:dem":1529,
    "gn:feature_class":"P",
    "gn:feature_code":"PPL",
    "gn:name":"An\u0101r J\u014dy",
    "gn:population":0,
    "gn:timezone":"Asia/Kabul",
    "iso:country":"AF",
    "name:und_x_variant":[
        "An\u0101\u1e5fj\u014dy",
        "An\u0101r J\u014dy",
        "\u0627\u0646\u0627\u0631 \u062c\u0648\u06cc",
        "An\u0101r J\u016by"
    ],
    "wof:name":"Anar Joy",
    "wof:placetype":"locality"
},
  "geometry": {"coordinates":[65.65101,33.57509],"type":"Point"}
}