{
  "type": "Feature",
  "properties": {
    "gn:admin1_code":"14",
    "gn:admin2_code":"201.0",
    "gn:asciiname":"Wali Khel",
    "gn:country_code":"AF",
    "gn:dem":1470,
    "gn:feature_class":"P",
    "gn:feature_code":"PPL",
    "gn:name":"Wal\u012b Kh\u0113l",
    "gn:population":0,
    "gn:timezone":"Asia/Kabul",
    "iso:country":"AF",
    "name:fas_x_preferred":[
        "\u0648\u0644\u06cc \u062e\u06cc\u0644"
    ],
    "name:rus_x_preferred":[
        "Valikheyl\u2019"
    ],
    "name:und_x_variant":[
        "Walikh\u0113l",
        "Walikheyl",
        "Wal\u012b Kh\u0113l",
        "\u0648\u0644\u06cc \u062e\u06d0\u0644"
    ],
    "wof:name":"Wali Khel",
    "wof:placetype":"locality"
},
  "geometry": {"coordinates":[69.34529000000001,35.02461],"type":"Point"}
}