{
  "type": "Feature",
  "properties": {
    "gn:admin1_code":"32",
    "gn:admin2_code":"1502.0",
    "gn:asciiname":"Qurug",
    "gn:country_code":"AF",
    "gn:dem":760,
    "gn:feature_class":"P",
    "gn:feature_code":"PPL",
    "gn:name":"Qurug",
    "gn:population":0,
    "gn:timezone":"Asia/Kabul",
    "iso:country":"AF",
    "name:und_x_variant":[
        "Qorog",
        "Qurug",
        "\u0642\u0631\u06af"
    ],
    "wof:name":"Qurug",
    "wof:placetype":"locality"
},
  "geometry": {"coordinates":[67.9965,36.5014],"type":"Point"}
}