{
  "type": "Feature",
  "properties": {
    "gn:admin1_code":"34",
    "gn:admin2_code":"1011.0",
    "gn:asciiname":"Narai Tangay",
    "gn:country_code":"AF",
    "gn:dem":2179,
    "gn:feature_class":"P",
    "gn:feature_code":"PPL",
    "gn:name":"Nara\u012b Tangay",
    "gn:population":0,
    "gn:timezone":"Asia/Kabul",
    "iso:country":"AF",
    "name:und_x_variant":[
        "Nara\u012b Tangay",
        "Nara\u012b Tanga\u012b"
    ],
    "wof:name":"Narai Tangay",
    "wof:placetype":"locality"
},
  "geometry": {"coordinates":[70.92613,34.80756],"type":"Point"}
}