{
  "type": "Feature",
  "properties": {
    "gn:admin1_code":"28",
    "gn:admin2_code":"2510.0",
    "gn:asciiname":"Sherzi",
    "gn:country_code":"AF",
    "gn:dem":1986,
    "gn:feature_class":"P",
    "gn:feature_code":"PPL",
    "gn:name":"Sh\u0113rz\u012b",
    "gn:population":0,
    "gn:timezone":"Asia/Kabul",
    "iso:country":"AF",
    "name:und_x_variant":[
        "\u0160\u0113rzi",
        "Sherzi",
        "Shayrz\u012b",
        "\u0634\u06cc\u0631\u0632\u06cc",
        "Sh\u012brz\u012b",
        "Sh\u0113rz\u012b"
    ],
    "wof:name":"Sherzi",
    "wof:placetype":"locality"
},
  "geometry": {"coordinates":[67.30195000000001,32.94921],"type":"Point"}
}