{
  "type": "Feature",
  "properties": {
    "gn:admin1_code":"36",
    "gn:admin2_code":"704",
    "gn:asciiname":"Surgori",
    "gn:country_code":"AF",
    "gn:dem":1899,
    "gn:feature_class":"P",
    "gn:feature_code":"PPL",
    "gn:name":"Surgori",
    "gn:population":0,
    "gn:timezone":"Asia/Kabul",
    "iso:country":"AF",
    "name:fas_x_preferred":[
        "\u0633\u0648\u0631 \u06af\u0648\u0631\u06cc"
    ],
    "name:und_x_variant":[
        "Su\u1e5f G\u014dri",
        "S\u016br G\u016b\u1e5f\u012b",
        "Su\u1e5f G\u016br\u012b",
        "S\u016br G\u014d\u1e5f\u012b",
        "\u0633\u0648\u0631 \u06af\u0648\u0693\u06cc"
    ],
    "wof:name":"Surgori",
    "wof:placetype":"locality"
},
  "geometry": {"coordinates":[69.499,33.35818],"type":"Point"}
}