{
  "type": "Feature",
  "properties": {
    "gn:admin1_code":"08",
    "gn:admin2_code":"604",
    "gn:asciiname":"Uchi Sang",
    "gn:country_code":"AF",
    "gn:dem":3099,
    "gn:feature_class":"P",
    "gn:feature_code":"PPL",
    "gn:name":"\u016ach\u012b Sang",
    "gn:population":0,
    "gn:timezone":"Asia/Kabul",
    "iso:country":"AF",
    "name:und_x_variant":[
        "\u016a\u010disang",
        "Uchisang",
        "\u016ach\u012b Sang",
        "Owch\u012bsang",
        "\u0627\u0648\u0686\u06cc \u0633\u0646\u06af"
    ],
    "wof:name":"Uchi Sang",
    "wof:placetype":"locality"
},
  "geometry": {"coordinates":[67.59158000000001,34.06772],"type":"Point"}
}