{
  "type": "Feature",
  "properties": {
    "gn:admin1_code":"17",
    "gn:asciiname":"Isma`il Khel",
    "gn:country_code":"AF",
    "gn:dem":2001,
    "gn:feature_class":"P",
    "gn:feature_code":"PPL",
    "gn:name":"Ism\u0101\u2018\u012bl Kh\u0113l",
    "gn:population":0,
    "gn:timezone":"Asia/Kabul",
    "iso:country":"AF",
    "name:rus_x_preferred":[
        "Smel\u2019kheyl\u2019"
    ],
    "name:und_x_variant":[
        "Esm\u0101\u2018\u012bl Kheyl",
        "Sm\u0113lkh\u0113l",
        "Esm\u0101\u2018\u012bl Kh\u0113l",
        "Ism\u0101\u2018\u012bl Kh\u0113l",
        "\u0627\u0633\u0645\u0627\u0639\u06cc\u0644 \u062e\u06d0\u0644"
    ],
    "wof:name":"Isma`il Khel",
    "wof:placetype":"locality"
},
  "geometry": {"coordinates":[69.081,34.31986],"type":"Point"}
}