{
  "type": "Feature",
  "properties": {
    "gn:admin1_code":"34",
    "gn:admin2_code":"1011.0",
    "gn:asciiname":"Kuz Narang",
    "gn:country_code":"AF",
    "gn:dem":761,
    "gn:feature_class":"P",
    "gn:feature_code":"PPL",
    "gn:name":"K\u016bz Narang",
    "gn:population":0,
    "gn:timezone":"Asia/Kabul",
    "iso:country":"AF",
    "name:fas_x_preferred":[
        "\u0643\u0648\u0632 \u0646\u0631\u0646\u06af"
    ],
    "name:fas_x_variant":[
        "\u0646\u0631\u0646\u0642\u0654 \u067e\u0627\u0626\u06cc\u0646"
    ],
    "name:und_x_variant":[
        "K\u016bz Na\u1e5fang",
        "K\u016bz Narang",
        "K\u016bz Na\u1e5fanq"
    ],
    "wof:name":"Kuz Narang",
    "wof:placetype":"locality"
},
  "geometry": {"coordinates":[71.02351,34.7482],"type":"Point"}
}