{
  "type": "Feature",
  "properties": {
    "gn:admin1_code":"37",
    "gn:admin2_code":"3203",
    "gn:asciiname":"Kochon",
    "gn:country_code":"AF",
    "gn:dem":2476,
    "gn:feature_class":"P",
    "gn:feature_code":"PPL",
    "gn:name":"K\u014dch\u014dn",
    "gn:population":0,
    "gn:timezone":"Asia/Kabul",
    "iso:country":"AF",
    "name:und_x_variant":[
        "Ko\u010don",
        "Kachan",
        "Kochan",
        "K\u014dch\u014dn",
        "Kowts\u016bn",
        "\u06a9\u0648\u0686\u0648\u0646"
    ],
    "wof:name":"Kochon",
    "wof:placetype":"locality"
},
  "geometry": {"coordinates":[69.62344,33.1546],"type":"Point"}
}