{
  "type": "Feature",
  "properties": {
    "gn:admin1_code":"09",
    "gn:admin2_code":"2706",
    "gn:asciiname":"'Omar Siyah",
    "gn:country_code":"AF",
    "gn:dem":2582,
    "gn:feature_class":"P",
    "gn:feature_code":"PPL",
    "gn:name":"\u2018Omar Siy\u0101h",
    "gn:population":0,
    "gn:timezone":"Asia/Kabul",
    "iso:country":"AF",
    "name:und_x_variant":[
        "Umarsiakh",
        "\u2018Oma\u1e5f-sy\u0101h",
        "\u2018Omar-S\u012b\u0101h",
        "\u0639\u0645\u0631 \u0633\u06cc\u0627\u0647",
        "\u2018Omar Siy\u0101h"
    ],
    "wof:name":"'Omar Siyah",
    "wof:placetype":"locality"
},
  "geometry": {"coordinates":[64.6276,33.31783],"type":"Point"}
}