{
  "type": "Feature",
  "properties": {
    "gn:admin1_code":"41",
    "gn:admin2_code":"3408.0",
    "gn:asciiname":"Sabz Joy",
    "gn:country_code":"AF",
    "gn:dem":2549,
    "gn:feature_class":"P",
    "gn:feature_code":"PPL",
    "gn:name":"Sabz J\u014dy",
    "gn:population":0,
    "gn:timezone":"Asia/Kabul",
    "iso:country":"AF",
    "name:und_x_variant":[
        "Sauzdzhoy",
        "Sawzj\u014dy",
        "Sabz J\u014dy",
        "Sabzj\u016by",
        "\u0633\u0628\u0632 \u062c\u0648\u06cc"
    ],
    "wof:name":"Sabz Joy",
    "wof:placetype":"locality"
},
  "geometry": {"coordinates":[66.25205,34.23277],"type":"Point"}
}