{
  "type": "Feature",
  "properties": {
    "gn:admin1_code":"05",
    "gn:admin2_code":"2804",
    "gn:asciiname":"Gorsang",
    "gn:country_code":"AF",
    "gn:dem":2182,
    "gn:feature_class":"P",
    "gn:feature_code":"PPL",
    "gn:name":"G\u014drsang",
    "gn:population":0,
    "gn:timezone":"Asia/Kabul",
    "iso:country":"AF",
    "name:und_x_variant":[
        "G\u014d\u1e5fsang",
        "G\u016brsang",
        "G\u014drsang",
        "\u06af\u0648\u0631\u0633\u0646\u06af"
    ],
    "wof:name":"Gorsang",
    "wof:placetype":"locality"
},
  "geometry": {"coordinates":[66.44846,35.04671],"type":"Point"}
}