{
  "type": "Feature",
  "properties": {
    "gn:admin1_code":"23",
    "gn:admin2_code":"2411",
    "gn:asciiname":"Mashi",
    "gn:country_code":"AF",
    "gn:dem":1199,
    "gn:feature_class":"P",
    "gn:feature_code":"PPL",
    "gn:name":"M\u0101sh\u012b",
    "gn:population":0,
    "gn:timezone":"Asia/Kabul",
    "iso:country":"AF",
    "name:fra_x_preferred":[
        "Mashi"
    ],
    "name:hau_x_preferred":[
        "Mashi"
    ],
    "name:ita_x_preferred":[
        "Mashi"
    ],
    "name:spa_x_preferred":[
        "Mashi"
    ],
    "name:und_x_variant":[
        "M\u0101s\u0304i",
        "M\u0101sh\u012b",
        "\u0645\u0627\u0634\u06cc"
    ],
    "wof:name":"Mashi",
    "wof:placetype":"locality"
},
  "geometry": {"coordinates":[66.32884,31.07191],"type":"Point"}
}