{
  "type": "Feature",
  "properties": {
    "gn:admin1_code":"32",
    "gn:admin2_code":"1503",
    "gn:asciiname":"Qal'ah Now",
    "gn:country_code":"AF",
    "gn:dem":2588,
    "gn:feature_class":"P",
    "gn:feature_code":"PPL",
    "gn:name":"Qal\u2018ah Now",
    "gn:population":0,
    "gn:timezone":"Asia/Kabul",
    "iso:country":"AF",
    "name:und_x_variant":[
        "Kala Nao",
        "Qala Nau",
        "Qal\u2018a-i-Naw",
        "Qala Naw",
        "Qal\u2018eh-ye Now",
        "Qal\u2018ah Now",
        "\u0642\u0644\u0639\u0647 \u0646\u0648"
    ],
    "wof:name":"Qal'ah Now",
    "wof:placetype":"locality"
},
  "geometry": {"coordinates":[67.14129,35.44349000000001],"type":"Point"}
}