{
  "type": "Feature",
  "properties": {
    "gn:admin1_code":"36",
    "gn:admin2_code":"704",
    "gn:asciiname":"Khand",
    "gn:country_code":"AF",
    "gn:dem":2091,
    "gn:feature_class":"P",
    "gn:feature_code":"PPL",
    "gn:name":"Khan\u1e0f",
    "gn:population":0,
    "gn:timezone":"Asia/Kabul",
    "iso:country":"AF",
    "name:fas_x_preferred":[
        "\u062e\u0646\u062f"
    ],
    "name:fra_x_preferred":[
        "Khand"
    ],
    "name:nld_x_preferred":[
        "Khand"
    ],
    "name:und_x_variant":[
        "Khan\u1e0f",
        "\u062e\u0646\u0689"
    ],
    "wof:name":"Khand",
    "wof:placetype":"locality"
},
  "geometry": {"coordinates":[69.48211999999999,33.44284],"type":"Point"}
}