{
  "type": "Feature",
  "properties": {
    "gn:admin1_code":"5",
    "gn:admin2_code":"2802.0",
    "gn:asciiname":"Bariki",
    "gn:country_code":"AF",
    "gn:dem":2344,
    "gn:feature_class":"P",
    "gn:feature_code":"PPL",
    "gn:name":"Bariki",
    "gn:population":0,
    "gn:timezone":"Asia/Kabul",
    "iso:country":"AF",
    "name:ceb_x_preferred":[
        "Bariki"
    ],
    "name:swe_x_preferred":[
        "Bariki"
    ],
    "name:und_x_variant":[
        "B\u0101r\u012bk\u012b",
        "\u0628\u0627\u0631\u064a\u06a9\u06cc"
    ],
    "wof:name":"Bariki",
    "wof:placetype":"locality"
},
  "geometry": {"coordinates":[68.04921999999999,34.88927],"type":"Point"}
}