{
  "type": "Feature",
  "properties": {
    "gn:admin1_code":"01",
    "gn:admin2_code":"1113",
    "gn:asciiname":"Zarangan",
    "gn:country_code":"AF",
    "gn:dem":1714,
    "gn:feature_class":"P",
    "gn:feature_code":"PPL",
    "gn:name":"Zarang\u0101n",
    "gn:population":0,
    "gn:timezone":"Asia/Kabul",
    "iso:country":"AF",
    "name:und_x_variant":[
        "Zarang\u0101n",
        "\u0632\u0631\u0646\u06af\u0627\u0646",
        "Z\u0101rangan"
    ],
    "wof:name":"Zarangan",
    "wof:placetype":"locality"
},
  "geometry": {"coordinates":[70.08872,37.28519],"type":"Point"}
}