{
  "type": "Feature",
  "properties": {
    "gn:admin1_code":"41",
    "gn:admin2_code":"3405",
    "gn:asciiname":"Now Darah",
    "gn:country_code":"AF",
    "gn:dem":2770,
    "gn:feature_class":"P",
    "gn:feature_code":"PPL",
    "gn:name":"Now Darah",
    "gn:population":0,
    "gn:timezone":"Asia/Kabul",
    "iso:country":"AF",
    "name:und_x_variant":[
        "Naw\u1e0fa\u1e5fa",
        "Now Darah",
        "\u0646\u0648 \u062f\u0631\u0647",
        "Now Darreh"
    ],
    "wof:name":"Now Darah",
    "wof:placetype":"locality"
},
  "geometry": {"coordinates":[66.05176999999999,33.91133],"type":"Point"}
}