{
  "type": "Feature",
  "properties": {
    "gn:admin1_code":"09",
    "gn:admin2_code":"2707",
    "gn:asciiname":"Tapah-ye Mazar",
    "gn:country_code":"AF",
    "gn:dem":3225,
    "gn:feature_class":"P",
    "gn:feature_code":"PPL",
    "gn:name":"Tapah-ye Maz\u0101r",
    "gn:population":0,
    "gn:timezone":"Asia/Kabul",
    "iso:country":"AF",
    "name:und_x_variant":[
        "Tapa-i-Maz\u0101\u1e5f",
        "Tapayi-Mazar",
        "Tapah-ye Maz\u0101r",
        "Tappeh-ye Maz\u0101r",
        "\u062a\u067e\u0647 \u0645\u0632\u0627\u0631"
    ],
    "wof:name":"Tapah-ye Mazar",
    "wof:placetype":"locality"
},
  "geometry": {"coordinates":[66.41759999999999,34.45534],"type":"Point"}
}