{
  "type": "Feature",
  "properties": {
    "gn:admin1_code":"08",
    "gn:admin2_code":"607",
    "gn:asciiname":"Qadi",
    "gn:country_code":"AF",
    "gn:dem":2509,
    "gn:feature_class":"P",
    "gn:feature_code":"PPL",
    "gn:name":"Q\u0101d\u012b",
    "gn:population":0,
    "gn:timezone":"Asia/Kabul",
    "iso:country":"AF",
    "name:und_x_variant":[
        "Q\u0101d\u012b",
        "\u0642\u0627\u062f\u06cc",
        "Q\u0101\u1e0fi"
    ],
    "wof:name":"Qadi",
    "wof:placetype":"locality"
},
  "geometry": {"coordinates":[67.42009,33.05212],"type":"Point"}
}