{
  "type": "Feature",
  "properties": {
    "gn:admin1_code":"09",
    "gn:admin2_code":"2710",
    "gn:asciiname":"Gharak-e 'Ulya",
    "gn:country_code":"AF",
    "gn:dem":2780,
    "gn:feature_class":"P",
    "gn:feature_code":"PPL",
    "gn:name":"Gh\u0101rak-e \u2018Uly\u0101",
    "gn:population":0,
    "gn:timezone":"Asia/Kabul",
    "iso:country":"AF",
    "name:und_x_variant":[
        "Garaki-Ulia",
        "Gh\u0101\u1e5fake \u2018Uly\u0101",
        "Ghowrak-e \u2018Oly\u0101",
        "Gh\u014d\u1e5fake Uly\u0101",
        "Gh\u0101rak-e \u2018Oly\u0101",
        "Gh\u0101rak-e \u2018Uly\u0101",
        "\u063a\u0627\u0631\u06a9 \u0639\u0644\u06cc\u0627"
    ],
    "wof:name":"Gharak-e 'Ulya",
    "wof:placetype":"locality"
},
  "geometry": {"coordinates":[64.93745,34.09898],"type":"Point"}
}