{
  "type": "Feature",
  "properties": {
    "gn:admin1_code":"39",
    "gn:admin2_code":"2603",
    "gn:asciiname":"Mianah",
    "gn:country_code":"AF",
    "gn:dem":3017,
    "gn:feature_class":"P",
    "gn:feature_code":"PPL",
    "gn:name":"M\u012b\u0101nah",
    "gn:population":0,
    "gn:timezone":"Asia/Kabul",
    "iso:country":"AF",
    "name:fas_x_preferred":[
        "\u0645\u064a\u0627\u0646\u0647"
    ],
    "name:und_x_variant":[
        "Miana",
        "My\u0101na",
        "M\u012b\u0101nah",
        "\u0645\u06cc\u0627\u0646\u0647",
        "M\u012b\u0101neh"
    ],
    "wof:name":"Mianah",
    "wof:placetype":"locality"
},
  "geometry": {"coordinates":[66.68689999999999,32.80784],"type":"Point"}
}