{
  "type": "Feature",
  "properties": {
    "gn:admin1_code":"08",
    "gn:admin2_code":"604",
    "gn:asciiname":"Surkhak-Bum",
    "gn:country_code":"AF",
    "gn:dem":3020,
    "gn:feature_class":"P",
    "gn:feature_code":"PPL",
    "gn:name":"Surkhak-B\u016bm",
    "gn:population":0,
    "gn:timezone":"Asia/Kabul",
    "iso:country":"AF",
    "name:und_x_variant":[
        "Su\u1e5fkhak-b\u016bm",
        "Surkhakbum",
        "Sorkhak B\u016bm",
        "Surkhak-B\u016bm",
        "\u0633\u0631\u062e\u06a9 \u0628\u0648\u0645"
    ],
    "wof:name":"Surkhak-Bum",
    "wof:placetype":"locality"
},
  "geometry": {"coordinates":[67.83174,34.13656],"type":"Point"}
}