{
  "type": "Feature",
  "properties": {
    "gn:admin1_code":"29",
    "gn:admin2_code":"2906",
    "gn:asciiname":"De Khalifah Dzay",
    "gn:country_code":"AF",
    "gn:dem":2478,
    "gn:feature_class":"P",
    "gn:feature_code":"PPL",
    "gn:name":"D\u00ea Khal\u012bfah Dz\u0101y",
    "gn:population":0,
    "gn:timezone":"Asia/Kabul",
    "iso:country":"AF",
    "name:und_x_variant":[
        "Khalifadzhay",
        "\u1e0ee Khalifa J\u0101y",
        "De Khal\u012bfeh J\u0101y",
        "\u062f \u062e\u0644\u06cc\u0641\u0647 \u0681\u0627\u06cc",
        "De Khal\u012bfeh Dz\u0101y",
        "D\u00ea Khal\u012bfah Dz\u0101y"
    ],
    "wof:name":"De Khalifah Dzay",
    "wof:placetype":"locality"
},
  "geometry": {"coordinates":[68.74009000000001,32.67156],"type":"Point"}
}