{
  "type": "Feature",
  "properties": {
    "gn:admin1_code":"06",
    "gn:admin2_code":"2101",
    "gn:asciiname":"Khwajah Ahmad",
    "gn:country_code":"AF",
    "gn:dem":588,
    "gn:feature_class":"P",
    "gn:feature_code":"PPL",
    "gn:name":"Khw\u0101jah A\u1e29mad",
    "gn:population":0,
    "gn:timezone":"Asia/Kabul",
    "iso:country":"AF",
    "name:fas_x_preferred":[
        "Khw\u0101jah A\u1e29mad"
    ],
    "name:fas_x_variant":[
        "\u062e\u0648\u0627\u062c\u0647 \u0627\u062d\u0645\u062f"
    ],
    "name:und_x_variant":[
        "Khw\u0101ja-a\u1e96ma\u1e0f (1)",
        "Khv\u0101jeh A\u1e29mad (1)"
    ],
    "wof:name":"Khwajah Ahmad",
    "wof:placetype":"locality"
},
  "geometry": {"coordinates":[61.84105,32.04498],"type":"Point"}
}