{
  "type": "Feature",
  "properties": {
    "gn:admin1_code":"9",
    "gn:admin2_code":"2706.0",
    "gn:asciiname":"Bar 'Ali",
    "gn:country_code":"AF",
    "gn:dem":2267,
    "gn:feature_class":"P",
    "gn:feature_code":"PPL",
    "gn:name":"Bar \u2018Al\u012b",
    "gn:population":0,
    "gn:timezone":"Asia/Kabul",
    "iso:country":"AF",
    "name:und_x_variant":[
        "Bar \u2018Al\u012b",
        "\u0628\u0631 \u0639\u0644\u06cc",
        "Bar \u2018Ali"
    ],
    "wof:name":"Bar 'Ali",
    "wof:placetype":"locality"
},
  "geometry": {"coordinates":[65.53274999999999,33.59247],"type":"Point"}
}