{
  "type": "Feature",
  "properties": {
    "gn:admin1_code":"26",
    "gn:admin2_code":"1201.0",
    "gn:asciiname":"Saray Sang",
    "gn:country_code":"AF",
    "gn:dem":792,
    "gn:feature_class":"P",
    "gn:feature_code":"PPL",
    "gn:name":"Sar\u0101y Sang",
    "gn:population":0,
    "gn:timezone":"Asia/Kabul",
    "iso:country":"AF",
    "name:rus_x_preferred":[
        "\u0421\u0430\u0440\u0430\u0439\u0441\u0430\u043d\u0433"
    ],
    "name:und_x_variant":[
        "Saraysang",
        "Sar\u0101y Sang",
        "\u0633\u0631\u0627\u06cc \u0633\u0646\u06af"
    ],
    "wof:name":"Saray Sang",
    "wof:placetype":"locality"
},
  "geometry": {"coordinates":[69.50488,36.76389],"type":"Point"}
}