{
  "type": "Feature",
  "properties": {
    "gn:admin1_code":"36",
    "gn:admin2_code":"701.0",
    "gn:asciiname":"Deray Pulari",
    "gn:country_code":"AF",
    "gn:dem":2298,
    "gn:feature_class":"P",
    "gn:feature_code":"PPL",
    "gn:name":"D\u00earay Pul\u0101r\u012b",
    "gn:population":0,
    "gn:timezone":"Asia/Kabul",
    "iso:country":"AF",
    "name:fas_x_preferred":[
        "\u062f\u0631\u06cc \u0686\u0644\u0627\u0631\u06cc"
    ],
    "name:und_x_variant":[
        "Deraypulari",
        "\u1e0ee\u1e5fay Pol\u0101\u1e5fi",
        "D\u00earay Pul\u0101r\u012b",
        "\u062f\u0631\u06cc \u067e\u0644\u0627\u0631\u06cc",
        "D\u012bray B\u014dl\u0101r\u012b",
        "\u062f\u06cc\u0631\u06cc \u0628\u0648\u0644\u0627\u0631\u06cc"
    ],
    "wof:name":"Deray Pulari",
    "wof:placetype":"locality"
},
  "geometry": {"coordinates":[69.22272,33.57095],"type":"Point"}
}