{
  "type": "Feature",
  "properties": {
    "gn:admin1_code":"23",
    "gn:admin2_code":"2405.0",
    "gn:asciiname":"Chah-e Muhammad",
    "gn:country_code":"AF",
    "gn:dem":1728,
    "gn:feature_class":"P",
    "gn:feature_code":"PPL",
    "gn:name":"Ch\u0101h-e Mu\u1e29ammad",
    "gn:population":0,
    "gn:timezone":"Asia/Kabul",
    "iso:country":"AF",
    "name:fas_x_preferred":[
        "\u0686\u0627\u06c0 \u0645\u062d\u0645\u062f"
    ],
    "name:und_x_variant":[
        "\u010c\u0101he Mohammad",
        "Chakhi-Mukhammed",
        "Ch\u0101h-e Mu\u1e29ammad",
        "\u0686\u0627\u0647 \u0645\u062d\u0645\u062f",
        "Ch\u0101h-e Mo\u1e29ammad"
    ],
    "wof:name":"Chah-e Muhammad",
    "wof:placetype":"locality"
},
  "geometry": {"coordinates":[65.56388000000001,32.13828],"type":"Point"}
}