{
  "type": "Feature",
  "properties": {
    "gn:admin1_code":"07",
    "gn:admin2_code":"1804",
    "gn:asciiname":"Wabuz Pa'in",
    "gn:country_code":"AF",
    "gn:dem":1395,
    "gn:feature_class":"P",
    "gn:feature_code":"PPL",
    "gn:name":"W\u0101b\u016bz P\u0101\u2019\u012bn",
    "gn:population":0,
    "gn:timezone":"Asia/Kabul",
    "iso:country":"AF",
    "name:und_x_variant":[
        "W\u0101b\u016bz P\u0101\u2019\u012bn",
        "\u0648\u0644\u0628\u0648\u0632 \u067e\u0627\u0626\u06cc\u0646",
        "W\u0101b\u016bz P\u0101\u2019in"
    ],
    "wof:name":"Wabuz Pa'in",
    "wof:placetype":"locality"
},
  "geometry": {"coordinates":[64.54499,35.60590999999999],"type":"Point"}
}