{
  "type": "Feature",
  "properties": {
    "gn:admin1_code":"08",
    "gn:admin2_code":"604",
    "gn:asciiname":"Qal'ah-ye Hajat",
    "gn:country_code":"AF",
    "gn:dem":3009,
    "gn:feature_class":"P",
    "gn:feature_code":"PPL",
    "gn:name":"Qal\u2018ah-ye \u1e28\u0101jat",
    "gn:population":0,
    "gn:timezone":"Asia/Kabul",
    "iso:country":"AF",
    "name:und_x_variant":[
        "Qal\u2018a-i-\u1e28\u0101jat",
        "Qal\u2018eh-ye \u1e28\u0101jjat",
        "Qal\u2018a \u1e28\u0101jat",
        "Kalakhadzhat",
        "Qal\u2018ah-ye \u1e28\u0101jat",
        "Qal\u2018eh-ye \u1e28\u0101jat",
        "\u0642\u0644\u0639\u0647 \u062d\u0627\u062c\u062a"
    ],
    "wof:name":"Qal'ah-ye Hajat",
    "wof:placetype":"locality"
},
  "geometry": {"coordinates":[68.09723000000001,33.91547],"type":"Point"}
}