{
  "type": "Feature",
  "properties": {
    "gn:admin1_code":"40",
    "gn:admin2_code":"304",
    "gn:asciiname":"Gowand",
    "gn:country_code":"AF",
    "gn:dem":2185,
    "gn:feature_class":"P",
    "gn:feature_code":"PPL",
    "gn:name":"Gowand",
    "gn:population":0,
    "gn:timezone":"Asia/Kabul",
    "iso:country":"AF",
    "name:und_x_variant":[
        "Gawan\u1e0f",
        "Gavand",
        "Gawand",
        "Gowand",
        "\u06af\u0648\u0646\u062f"
    ],
    "wof:name":"Gowand",
    "wof:placetype":"locality"
},
  "geometry": {"coordinates":[68.98139999999999,34.9891],"type":"Point"}
}