{
  "type": "Feature",
  "properties": {
    "gn:admin1_code":"05",
    "gn:admin2_code":"2805",
    "gn:asciiname":"Suru",
    "gn:country_code":"AF",
    "gn:dem":2970,
    "gn:feature_class":"P",
    "gn:feature_code":"PPL",
    "gn:name":"Suru",
    "gn:population":0,
    "gn:timezone":"Asia/Kabul",
    "iso:country":"AF",
    "name:und_x_variant":[
        "S\u014dr\u014d",
        "Suru",
        "S\u016br\u016b",
        "\u0633\u0648\u0631\u0648"
    ],
    "wof:name":"Suru",
    "wof:placetype":"locality"
},
  "geometry": {"coordinates":[67.0677,34.31974],"type":"Point"}
}