{
  "type": "Feature",
  "properties": {
    "gn:admin1_code":"17",
    "gn:admin2_code":"504",
    "gn:asciiname":"Shaykh Malay",
    "gn:country_code":"AF",
    "gn:dem":2711,
    "gn:feature_class":"P",
    "gn:feature_code":"PPL",
    "gn:name":"Shaykh Malay",
    "gn:population":0,
    "gn:timezone":"Asia/Kabul",
    "iso:country":"AF",
    "name:und_x_variant":[
        "\u0160aykhmalay",
        "Sheykhmalay",
        "Shaykhmalay",
        "Sh\u0113kh Malay",
        "Sheykh Malay",
        "Shaykh Malay",
        "\u0634\u06cc\u062e \u0645\u0644\u06cc"
    ],
    "wof:name":"Shaykh Malay",
    "wof:placetype":"locality"
},
  "geometry": {"coordinates":[69.31124,34.01954],"type":"Point"}
}