{
  "type": "Feature",
  "properties": {
    "gn:admin1_code":"9",
    "gn:admin2_code":"2705.0",
    "gn:asciiname":"Dahan-e Regi",
    "gn:country_code":"AF",
    "gn:dem":2378,
    "gn:feature_class":"P",
    "gn:feature_code":"PPL",
    "gn:name":"Dah\u0101n-e R\u0113g\u012b",
    "gn:population":0,
    "gn:timezone":"Asia/Kabul",
    "iso:country":"AF",
    "name:und_x_variant":[
        "\u1e0eahane \u1e5e\u0113gi",
        "Dakhani-Regi",
        "Dah\u0101n-e Rayg\u012b",
        "\u062f\u0647\u0627\u0646 \u0631\u06cc\u06af\u06cc",
        "Dahan-e R\u012bg\u012b",
        "Dah\u0101n-e R\u0113g\u012b"
    ],
    "wof:name":"Dahan-e Regi",
    "wof:placetype":"locality"
},
  "geometry": {"coordinates":[64.22691999999999,33.61843],"type":"Point"}
}