{
  "type": "Feature",
  "properties": {
    "gn:admin1_code":"09",
    "gn:admin2_code":"2707",
    "gn:asciiname":"Jazirah",
    "gn:country_code":"AF",
    "gn:dem":2998,
    "gn:feature_class":"P",
    "gn:feature_code":"PPL",
    "gn:name":"Jaz\u012brah",
    "gn:population":0,
    "gn:timezone":"Asia/Kabul",
    "iso:country":"AF",
    "name:und_x_variant":[
        "Dzhazira",
        "Jazi\u1e5fa",
        "Jaz\u012breh",
        "Jaz\u012brah",
        "\u062c\u0632\u06cc\u0631\u0647"
    ],
    "wof:name":"Jazirah",
    "wof:placetype":"locality"
},
  "geometry": {"coordinates":[66.1758,34.37677],"type":"Point"}
}