{
  "type": "Feature",
  "properties": {
    "gn:admin1_code":"27",
    "gn:admin2_code":"406.0",
    "gn:asciiname":"Chihil Gazi",
    "gn:country_code":"AF",
    "gn:dem":2462,
    "gn:feature_class":"P",
    "gn:feature_code":"PPL",
    "gn:name":"Chihil Gaz\u012b",
    "gn:population":0,
    "gn:timezone":"Asia/Kabul",
    "iso:country":"AF",
    "name:und_x_variant":[
        "\u010cehelgazi",
        "Chehelq\u0101\u1e95\u012b",
        "Chehel Gaz\u012b",
        "Chihil Gaz\u012b",
        "\u0686\u0647\u0644 \u06af\u0632\u06cc"
    ],
    "wof:name":"Chihil Gazi",
    "wof:placetype":"locality"
},
  "geometry": {"coordinates":[68.47351,34.15745],"type":"Point"}
}