{
  "type": "Feature",
  "properties": {
    "gn:admin1_code":"01",
    "gn:admin2_code":"1104",
    "gn:asciiname":"Sar-e Sang",
    "gn:country_code":"AF",
    "gn:dem":2414,
    "gn:feature_class":"P",
    "gn:feature_code":"PPL",
    "gn:name":"Sar-e Sang",
    "gn:population":0,
    "gn:timezone":"Asia/Kabul",
    "iso:country":"AF",
    "name:und_x_variant":[
        "Sa\u1e5fesang",
        "Sar Sang",
        "Sar-e Sang",
        "\u0633\u0631\u0650 \u0633\u0646\u06af"
    ],
    "wof:name":"Sar-e Sang",
    "wof:placetype":"locality"
},
  "geometry": {"coordinates":[70.79519000000001,36.20992],"type":"Point"}
}