{
  "type": "Feature",
  "properties": {
    "gn:admin1_code":"28",
    "gn:admin2_code":"2502",
    "gn:asciiname":"Ibrahim Khel Wusta",
    "gn:country_code":"AF",
    "gn:dem":2216,
    "gn:feature_class":"P",
    "gn:feature_code":"PPL",
    "gn:name":"Ibr\u0101h\u012bm Kh\u0113l Wus\u0163\u00e1",
    "gn:population":0,
    "gn:timezone":"Asia/Kabul",
    "iso:country":"AF",
    "name:rus_x_preferred":[
        "Ibrakhimkheyl\u2019 Vusta"
    ],
    "name:und_x_variant":[
        "Eb\u1e5f\u0101h\u012bmkh\u0113l Wus\u1e6f\u0101",
        "Ibr\u0101h\u012bm Kh\u0113l Wus\u0163\u00e1",
        "\u0627\u0628\u0631\u0627\u0647\u06cc\u0645 \u062e\u06d0\u0644 \u0648\u0633\u0637\u06cc",
        "Ebr\u0101h\u012bmkheyl-e Vos\u0163\u00e1"
    ],
    "wof:name":"Ibrahim Khel Wusta",
    "wof:placetype":"locality"
},
  "geometry": {"coordinates":[67.53371,32.46708],"type":"Point"}
}