{
  "type": "Feature",
  "properties": {
    "gn:admin1_code":"27",
    "gn:admin2_code":"404",
    "gn:asciiname":"Tay-e Mumbar",
    "gn:country_code":"AF",
    "gn:dem":3120,
    "gn:feature_class":"P",
    "gn:feature_code":"PPL",
    "gn:name":"Tay-e Mumbar",
    "gn:population":0,
    "gn:timezone":"Asia/Kabul",
    "iso:country":"AF",
    "name:fas_x_preferred":[
        "\u062a\u0626 \u0645\u0646\u0628\u0631"
    ],
    "name:rus_x_preferred":[
        "\u0422\u0438\u0439\u0438-\u041c\u0443\u043c\u0431\u0430\u0440"
    ],
    "name:und_x_variant":[
        "Tey-e Mumba\u1e5f",
        "Tiyi-Mumbar",
        "Tay-e Mumbar",
        "Tey-e Manbar",
        "\u062a\u0626 \u0645\u0646\u0628\u0631",
        "\u062a\u06cc \u0645\u0645\u0628\u0631"
    ],
    "wof:name":"Tay-e Mumbar",
    "wof:placetype":"locality"
},
  "geometry": {"coordinates":[67.41674,34.53769],"type":"Point"}
}