{
  "type": "Feature",
  "properties": {
    "gn:admin1_code":"2",
    "gn:admin2_code":"1905.0",
    "gn:asciiname":"Qal'ah-ye Wali",
    "gn:country_code":"AF",
    "gn:dem":628,
    "gn:feature_class":"P",
    "gn:feature_code":"PPL",
    "gn:name":"Qal\u2018ah-ye Wal\u012b",
    "gn:population":0,
    "gn:timezone":"Asia/Kabul",
    "iso:country":"AF",
    "name:und_x_variant":[
        "Qal\u2018a-i-Wali",
        "Qal\u2018ah-ye Wal\u012b",
        "\u0642\u0644\u0639\u06c0 \u0648\u0644\u06cc",
        "Qal\u2018eh-ye Val\u012b"
    ],
    "wof:name":"Qal'ah-ye Wali",
    "wof:placetype":"locality"
},
  "geometry": {"coordinates":[63.77474,35.75514000000001],"type":"Point"}
}