{
  "type": "Feature",
  "properties": {
    "gn:admin1_code":"26",
    "gn:admin2_code":"1204.0",
    "gn:asciiname":"Bazarak",
    "gn:country_code":"AF",
    "gn:dem":1049,
    "gn:feature_class":"P",
    "gn:feature_code":"PPL",
    "gn:name":"B\u0101z\u0101rak",
    "gn:population":0,
    "gn:timezone":"Asia/Kabul",
    "iso:country":"AF",
    "name:bel_x_preferred":[
        "\u0411\u0430\u0437\u0430\u0440\u0430\u043a"
    ],
    "name:cat_x_preferred":[
        "Bazarak"
    ],
    "name:epo_x_preferred":[
        "Bazarak"
    ],
    "name:fas_x_preferred":[
        "\u0628\u0627\u0632\u0627\u0631\u06a9"
    ],
    "name:fra_x_preferred":[
        "Bazarak"
    ],
    "name:hin_x_preferred":[
        "\u092c\u093e\u091c\u093c\u093e\u0930\u0915"
    ],
    "name:nld_x_preferred":[
        "Bazarak"
    ],
    "name:pol_x_preferred":[
        "Bazarak"
    ],
    "name:por_x_preferred":[
        "Bazarak"
    ],
    "name:rus_x_preferred":[
        "\u0411\u0430\u0437\u0430\u0440\u0430\u043a"
    ],
    "name:spa_x_preferred":[
        "Bazarak"
    ],
    "name:tur_x_preferred":[
        "Bazarek"
    ],
    "name:und_x_variant":[
        "B\u0101z\u0101rak",
        "\u0628\u0627\u0632\u0627\u0631\u06a9"
    ],
    "name:urd_x_preferred":[
        "\u0628\u0627\u0632\u0627\u0631\u06a9"
    ],
    "name:war_x_preferred":[
        "Bazarak"
    ],
    "wof:name":"Bazarak",
    "wof:placetype":"locality"
},
  "geometry": {"coordinates":[69.54774999999999,36.46613],"type":"Point"}
}