{
  "type": "Feature",
  "properties": {
    "gn:admin1_code":"03",
    "gn:admin2_code":"1303.0",
    "gn:asciiname":"Kharoto Kelay",
    "gn:country_code":"AF",
    "gn:dem":629,
    "gn:feature_class":"P",
    "gn:feature_code":"PPL",
    "gn:name":"Khar\u014d\u1e6f\u014d K\u00ealay",
    "gn:population":0,
    "gn:timezone":"Asia/Kabul",
    "iso:country":"AF",
    "name:und_x_variant":[
        "Kharotukalay",
        "Kha\u1e5f\u014dto Kalay",
        "Kha\u1e5fowto Kalay",
        "Khar\u014d\u1e6f\u014d K\u00ealay",
        "\u062e\u0631\u0648\u067c\u0648 \u06a9\u0644\u06cc"
    ],
    "wof:name":"Kharoto Kelay",
    "wof:placetype":"locality"
},
  "geometry": {"coordinates":[68.56896999999999,35.95022],"type":"Point"}
}