{
  "type": "Feature",
  "properties": {
    "gn:admin1_code":"30",
    "gn:admin2_code":"1610",
    "gn:asciiname":"Khawalak",
    "gn:country_code":"AF",
    "gn:dem":1800,
    "gn:feature_class":"P",
    "gn:feature_code":"PPL",
    "gn:name":"Khaw\u0101lak",
    "gn:population":0,
    "gn:timezone":"Asia/Kabul",
    "iso:country":"AF",
    "name:und_x_variant":[
        "Khaw\u0101lak",
        "Khav\u0101lak",
        "\u062e\u0648\u0627\u0644\u06a9"
    ],
    "wof:name":"Khawalak",
    "wof:placetype":"locality"
},
  "geometry": {"coordinates":[66.91834,35.96549],"type":"Point"}
}