{
  "type": "Feature",
  "properties": {
    "gn:admin1_code":"39",
    "gn:admin2_code":"2601.0",
    "gn:asciiname":"Hajiano Kelay",
    "gn:country_code":"AF",
    "gn:dem":1265,
    "gn:feature_class":"P",
    "gn:feature_code":"PPL",
    "gn:name":"\u1e28\u0101j\u012b\u0101n\u014d K\u00ealay",
    "gn:population":0,
    "gn:timezone":"Asia/Kabul",
    "iso:country":"AF",
    "name:fas_x_preferred":[
        "\u062d\u0627\u062c\u064a\u0627\u0646\u0648 \u0643\u0644\u06cc"
    ],
    "name:rus_x_preferred":[
        "Khadzh\u2019yanukalay"
    ],
    "name:und_x_variant":[
        "\u1e28\u0101j\u012b\u0101no Kalay",
        "\u1e28\u0101jy\u0101no Kalay",
        "\u1e28\u0101j\u012b\u0101n\u014d K\u00ealay",
        "\u062d\u0627\u062c\u06cc\u0627\u0646\u0648 \u06a9\u0644\u06cc",
        "\u1e28\u0101jj\u012b\u0101no Kalay"
    ],
    "wof:name":"Hajiano Kelay",
    "wof:placetype":"locality"
},
  "geometry": {"coordinates":[65.79333000000001,32.60129000000001],"type":"Point"}
}