{
  "type": "Feature",
  "properties": {
    "gn:admin1_code":"3",
    "gn:admin2_code":"1304.0",
    "gn:asciiname":"Darahgak",
    "gn:country_code":"AF",
    "gn:dem":876,
    "gn:feature_class":"P",
    "gn:feature_code":"PPL",
    "gn:name":"Darahgak",
    "gn:population":0,
    "gn:timezone":"Asia/Kabul",
    "iso:country":"AF",
    "name:und_x_variant":[
        "\u062f\u0631\u0647 \u06af\u06a9",
        "Daragak"
    ],
    "wof:name":"Darahgak",
    "wof:placetype":"locality"
},
  "geometry": {"coordinates":[68.63741999999999,35.60386],"type":"Point"}
}