{
  "type": "Feature",
  "properties": {
    "gn:admin1_code":"09",
    "gn:admin2_code":"2706",
    "gn:asciiname":"Surkhak",
    "gn:country_code":"AF",
    "gn:dem":2441,
    "gn:feature_class":"P",
    "gn:feature_code":"PPL",
    "gn:name":"Surkhak",
    "gn:population":0,
    "gn:timezone":"Asia/Kabul",
    "iso:country":"AF",
    "name:und_x_variant":[
        "Su\u1e5fkhak",
        "Surkhak",
        "\u0633\u0631\u062e\u06a9",
        "Sorkhak"
    ],
    "wof:name":"Surkhak",
    "wof:placetype":"locality"
},
  "geometry": {"coordinates":[65.22993000000001,33.60598],"type":"Point"}
}