{
  "type": "Feature",
  "properties": {
    "gn:admin1_code":"24",
    "gn:admin2_code":"1406",
    "gn:asciiname":"Jangal Bashi",
    "gn:country_code":"AF",
    "gn:dem":483,
    "gn:feature_class":"P",
    "gn:feature_code":"PPL",
    "gn:name":"Jangal B\u0101sh\u012b",
    "gn:population":0,
    "gn:timezone":"Asia/Kabul",
    "iso:country":"AF",
    "name:rus_x_preferred":[
        "\u0414\u0436\u0430\u043d\u0433\u0430\u043b\u044c\u0431\u0430\u0448\u0438"
    ],
    "name:und_x_variant":[
        "Dzhangal\u2019bashi",
        "Jangal B\u0101\u0161i",
        "Jangal B\u0101sh\u012b",
        "\u062c\u0646\u06af\u0644 \u0628\u0627\u0634\u06cc"
    ],
    "wof:name":"Jangal Bashi",
    "wof:placetype":"locality"
},
  "geometry": {"coordinates":[69.09415,36.69046],"type":"Point"}
}