{
  "type": "Feature",
  "properties": {
    "gn:admin1_code":"32",
    "gn:admin2_code":"1506",
    "gn:asciiname":"Surkhak Chashmah",
    "gn:country_code":"AF",
    "gn:dem":1874,
    "gn:feature_class":"P",
    "gn:feature_code":"PPL",
    "gn:name":"Surkhak Chashmah",
    "gn:population":0,
    "gn:timezone":"Asia/Kabul",
    "iso:country":"AF",
    "name:und_x_variant":[
        "Sorkhak Chashmeh",
        "Surkhak \u010ca\u0161ma",
        "Sorkhak Cheshmeh",
        "Surkhak Chashmah",
        "\u0633\u0631\u062e\u06a9 \u0686\u0634\u0645\u0647"
    ],
    "wof:name":"Surkhak Chashmah",
    "wof:placetype":"locality"
},
  "geometry": {"coordinates":[68.33376,36.08475],"type":"Point"}
}