{
  "type": "Feature",
  "properties": {
    "gn:admin1_code":"09",
    "gn:admin2_code":"2705",
    "gn:asciiname":"Kawan",
    "gn:country_code":"AF",
    "gn:dem":2210,
    "gn:feature_class":"P",
    "gn:feature_code":"PPL",
    "gn:name":"K\u0101w\u0101n",
    "gn:population":0,
    "gn:timezone":"Asia/Kabul",
    "iso:country":"AF",
    "name:und_x_variant":[
        "Kavan",
        "K\u0101w\u0101n",
        "\u06a9\u0627\u0648\u0627\u0646"
    ],
    "wof:name":"Kawan",
    "wof:placetype":"locality"
},
  "geometry": {"coordinates":[64.2657,33.20989],"type":"Point"}
}