{
  "type": "Feature",
  "properties": {
    "gn:admin1_code":"05",
    "gn:admin2_code":"2805",
    "gn:asciiname":"Kharzari",
    "gn:country_code":"AF",
    "gn:dem":2914,
    "gn:feature_class":"P",
    "gn:feature_code":"PPL",
    "gn:name":"Kh\u0101rz\u0101r\u012b",
    "gn:population":0,
    "gn:timezone":"Asia/Kabul",
    "iso:country":"AF",
    "name:und_x_variant":[
        "Kh\u0101rz\u0101r\u012b",
        "\u062e\u0627\u0631\u0632\u0627\u0631\u06cc",
        "Kh\u0101rz\u0101r",
        "\u062e\u0627\u0631\u0632\u0627\u0631"
    ],
    "wof:name":"Kharzari",
    "wof:placetype":"locality"
},
  "geometry": {"coordinates":[66.90827,34.38226],"type":"Point"}
}