{
  "type": "Feature",
  "properties": {
    "gn:admin1_code":"34",
    "gn:admin2_code":"1004",
    "gn:asciiname":"Zor Barawul",
    "gn:country_code":"AF",
    "gn:dem":2032,
    "gn:feature_class":"P",
    "gn:feature_code":"PPL",
    "gn:name":"Z\u014d\u1e5f Barawul",
    "gn:population":0,
    "gn:timezone":"Asia/Kabul",
    "iso:country":"AF",
    "name:fas_x_preferred":[
        "\u0632\u0648\u0631 \u0628\u0631\u0648\u0644"
    ],
    "name:rus_x_preferred":[
        "Zor-Baravul\u2019"
    ],
    "name:und_x_variant":[
        "Zar Barawul",
        "Z\u014dr Barawul",
        "Z\u014d\u1e5f Barawul",
        "Z\u016br Barawul",
        "\u0632\u0648\u0693 \u0628\u0631\u0648\u0644"
    ],
    "wof:name":"Zor Barawul",
    "wof:placetype":"locality"
},
  "geometry": {"coordinates":[71.505,35.0314],"type":"Point"}
}