{
  "type": "Feature",
  "properties": {
    "gn:admin1_code":"27",
    "gn:admin2_code":"409",
    "gn:asciiname":"Khidran",
    "gn:country_code":"AF",
    "gn:dem":2653,
    "gn:feature_class":"P",
    "gn:feature_code":"PPL",
    "gn:name":"Khidr\u0101n",
    "gn:population":0,
    "gn:timezone":"Asia/Kabul",
    "iso:country":"AF",
    "name:fas_x_preferred":[
        "\u062e\u062f\u0631\u0627\u0646"
    ],
    "name:und_x_variant":[
        "Khe\u1e95r\u0101n",
        "Khe\u1e0f\u1e5f\u0101n",
        "\u062e\u062f\u0631\u0627\u0646",
        "Khidr\u0101n"
    ],
    "wof:name":"Khidran",
    "wof:placetype":"locality"
},
  "geometry": {"coordinates":[68.30500000000001,33.82495],"type":"Point"}
}