{
  "type": "Feature",
  "properties": {
    "gn:admin1_code":"27",
    "gn:admin2_code":"406.0",
    "gn:asciiname":"Beranah",
    "gn:country_code":"AF",
    "gn:dem":2246,
    "gn:feature_class":"P",
    "gn:feature_code":"PPL",
    "gn:name":"B\u0113r\u0101nah",
    "gn:population":0,
    "gn:timezone":"Asia/Kabul",
    "iso:country":"AF",
    "name:und_x_variant":[
        "B\u0113\u1e5f\u0101na",
        "Berana",
        "B\u0113r\u0101nah",
        "\u0628\u06d0\u0631\u0627\u0646\u0647"
    ],
    "wof:name":"Beranah",
    "wof:placetype":"locality"
},
  "geometry": {"coordinates":[68.50431999999999,34.11437],"type":"Point"}
}