{
  "type": "Feature",
  "properties": {
    "gn:admin1_code":"36",
    "gn:admin2_code":"706.0",
    "gn:asciiname":"Barah Khel",
    "gn:country_code":"AF",
    "gn:dem":2082,
    "gn:feature_class":"P",
    "gn:feature_code":"PPL",
    "gn:name":"Barah Kh\u0113l",
    "gn:population":0,
    "gn:timezone":"Asia/Kabul",
    "iso:country":"AF",
    "name:rus_x_preferred":[
        "Barakheyl\u2019"
    ],
    "name:und_x_variant":[
        "Ba\u1e5fakh\u0113l",
        "Barah Kh\u0113l",
        "Barah Kheyl",
        "\u0628\u0631\u0647 \u062e\u06d0\u0644"
    ],
    "wof:name":"Barah Khel",
    "wof:placetype":"locality"
},
  "geometry": {"coordinates":[69.73017,33.65732],"type":"Point"}
}