{
  "type": "Feature",
  "properties": {
    "gn:admin1_code":"10",
    "gn:admin2_code":"2302",
    "gn:asciiname":"Haidarabad",
    "gn:country_code":"AF",
    "gn:dem":855,
    "gn:feature_class":"P",
    "gn:feature_code":"PPL",
    "gn:name":"\u1e28a\u012bdar\u0101b\u0101d",
    "gn:population":0,
    "gn:timezone":"Asia/Kabul",
    "iso:country":"AF",
    "name:und_x_variant":[
        "Haidar\u0101b\u0101d",
        "\u1e28ay\u1e0fa\u1e5f\u0101b\u0101\u1e0f",
        "Khaydarabad",
        "\u1e28a\u012bdar\u0101b\u0101d",
        "\u062d\u06cc\u062f\u0631 \u0622\u0628\u0627\u062f",
        "\u1e28eydar\u0101b\u0101d"
    ],
    "wof:name":"Haidarabad",
    "wof:placetype":"locality"
},
  "geometry": {"coordinates":[64.74370999999999,31.89586],"type":"Point"}
}