{
  "type": "Feature",
  "properties": {
    "gn:admin1_code":"08",
    "gn:admin2_code":"607",
    "gn:asciiname":"Madak",
    "gn:country_code":"AF",
    "gn:dem":2931,
    "gn:feature_class":"P",
    "gn:feature_code":"PPL",
    "gn:name":"Madak",
    "gn:population":0,
    "gn:timezone":"Asia/Kabul",
    "iso:country":"AF",
    "name:und_x_variant":[
        "Ma\u1e0fak",
        "Ma\u1e0fok",
        "Madak",
        "\u0645\u062f\u06a9"
    ],
    "wof:name":"Madak",
    "wof:placetype":"locality"
},
  "geometry": {"coordinates":[67.29021,33.11933],"type":"Point"}
}