{
  "type": "Feature",
  "properties": {
    "gn:admin1_code":"01",
    "gn:admin2_code":"1117.0",
    "gn:asciiname":"Pur Goj",
    "gn:country_code":"AF",
    "gn:dem":2698,
    "gn:feature_class":"P",
    "gn:feature_code":"PPL",
    "gn:name":"P\u016br G\u014dj",
    "gn:population":0,
    "gn:timezone":"Asia/Kabul",
    "iso:country":"AF",
    "name:und_x_variant":[
        "P\u016b\u1e5f G\u014dj",
        "P\u016br G\u016bj",
        "P\u016br G\u014dj",
        "\u067e\u0648\u0631 \u06af\u0648\u062c"
    ],
    "wof:name":"Pur Goj",
    "wof:placetype":"locality"
},
  "geometry": {"coordinates":[71.22841,38.07624000000001],"type":"Point"}
}