{
  "type": "Feature",
  "properties": {
    "gn:admin1_code":"32",
    "gn:admin2_code":"1501",
    "gn:asciiname":"Tash Tobah",
    "gn:country_code":"AF",
    "gn:dem":1003,
    "gn:feature_class":"P",
    "gn:feature_code":"PPL",
    "gn:name":"T\u0101sh T\u014dbah",
    "gn:population":0,
    "gn:timezone":"Asia/Kabul",
    "iso:country":"AF",
    "name:und_x_variant":[
        "T\u0101sh T\u014dba",
        "T\u0101sh Towbeh",
        "T\u0101sh T\u014dbah",
        "\u062a\u0627\u0634 \u062a\u0648\u0628\u0647"
    ],
    "wof:name":"Tash Tobah",
    "wof:placetype":"locality"
},
  "geometry": {"coordinates":[68.04728,36.26982],"type":"Point"}
}