{
  "type": "Feature",
  "properties": {
    "gn:admin1_code":"19",
    "gn:admin2_code":"2204",
    "gn:asciiname":"Khwajah Sar Joy",
    "gn:country_code":"AF",
    "gn:dem":499,
    "gn:feature_class":"P",
    "gn:feature_code":"PPL",
    "gn:name":"Khw\u0101jah Sar J\u014dy",
    "gn:population":0,
    "gn:timezone":"Asia/Kabul",
    "iso:country":"AF",
    "name:und_x_variant":[
        "Khv\u0101jeh-Sarj\u014dy",
        "Khw\u0101ja-Sa\u1e5fj\u014dy",
        "Khw\u0101jah Sar J\u014dy",
        "\u062e\u0648\u0627\u062c\u0647 \u0633\u0631 \u062c\u0648\u06cc",
        "Khv\u0101jeh Sarj\u016by"
    ],
    "wof:name":"Khwajah Sar Joy",
    "wof:placetype":"locality"
},
  "geometry": {"coordinates":[62.32506,31.33499],"type":"Point"}
}