{
  "type": "Feature",
  "properties": {
    "gn:admin1_code":"03",
    "gn:admin2_code":"1310",
    "gn:asciiname":"Saqaw",
    "gn:country_code":"AF",
    "gn:dem":1553,
    "gn:feature_class":"P",
    "gn:feature_code":"PPL",
    "gn:name":"Saq\u0101w",
    "gn:population":0,
    "gn:timezone":"Asia/Kabul",
    "iso:country":"AF",
    "name:und_x_variant":[
        "Saq\u0101w",
        "\u0633\u0642\u0627\u0648"
    ],
    "wof:name":"Saqaw",
    "wof:placetype":"locality"
},
  "geometry": {"coordinates":[69.18543000000001,36.12414],"type":"Point"}
}