{
  "type": "Feature",
  "properties": {
    "gn:admin1_code":"13",
    "gn:admin2_code":"101.0",
    "gn:asciiname":"Qal'ah-ye Barqi",
    "gn:country_code":"AF",
    "gn:dem":1791,
    "gn:feature_class":"P",
    "gn:feature_code":"PPL",
    "gn:name":"Qal\u2018ah-ye Barq\u012b",
    "gn:population":0,
    "gn:timezone":"Asia/Kabul",
    "iso:country":"AF",
    "name:fas_x_preferred":[
        "\u0642\u0644\u0639\u0628\u0631\u0642\u06cc"
    ],
    "name:und_x_variant":[
        "Qal\u2018ah-ye Barq\u012b",
        "Kalabarki",
        "\u0642\u0644\u0639\u0647 \u0628\u0631\u0642\u06cc"
    ],
    "wof:name":"Qal'ah-ye Barqi",
    "wof:placetype":"locality"
},
  "geometry": {"coordinates":[69.2272,34.49649],"type":"Point"}
}