{
  "type": "Feature",
  "properties": {
    "gn:admin1_code":"8",
    "gn:admin2_code":"604.0",
    "gn:asciiname":"Qol-e Kildi",
    "gn:country_code":"AF",
    "gn:dem":3139,
    "gn:feature_class":"P",
    "gn:feature_code":"PPL",
    "gn:name":"Q\u014dl-e K\u012bld\u012b",
    "gn:population":0,
    "gn:timezone":"Asia/Kabul",
    "iso:country":"AF",
    "name:rus_x_preferred":[
        "Kuli-Kil\u2019di"
    ],
    "name:und_x_variant":[
        "Q\u014dle K\u012bl\u1e0fi",
        "Qowl-e K\u012bld\u012b",
        "Q\u014dl-e K\u012bld\u012b",
        "\u0642\u0648\u0644 \u06a9\u06cc\u0644\u062f\u06cc"
    ],
    "wof:name":"Qol-e Kildi",
    "wof:placetype":"locality"
},
  "geometry": {"coordinates":[67.62149000000001,34.09163],"type":"Point"}
}