{
  "type": "Feature",
  "properties": {
    "gn:admin1_code":"42",
    "gn:admin2_code":"3303",
    "gn:asciiname":"Ghinju",
    "gn:country_code":"AF",
    "gn:dem":2246,
    "gn:feature_class":"P",
    "gn:feature_code":"PPL",
    "gn:name":"Ghinj\u016b",
    "gn:population":0,
    "gn:timezone":"Asia/Kabul",
    "iso:country":"AF",
    "name:rus_x_preferred":[
        "\u0413\u0438\u043d\u0434\u0436\u0443"
    ],
    "name:und_x_variant":[
        "Gindzhu",
        "Ghenju",
        "Ghinj\u016b",
        "\u063a\u0646\u062c\u0648"
    ],
    "wof:name":"Ghinju",
    "wof:placetype":"locality"
},
  "geometry": {"coordinates":[69.79419,35.47417],"type":"Point"}
}