{
  "type": "Feature",
  "properties": {
    "gn:admin1_code":"09",
    "gn:admin2_code":"2703",
    "gn:asciiname":"Spi Buz",
    "gn:country_code":"AF",
    "gn:dem":2081,
    "gn:feature_class":"P",
    "gn:feature_code":"PPL",
    "gn:name":"Sp\u012b Buz",
    "gn:population":0,
    "gn:timezone":"Asia/Kabul",
    "iso:country":"AF",
    "name:und_x_variant":[
        "Sp\u012b Buz",
        "\u0633\u067e\u06cc \u0628\u0632",
        "Spibuz"
    ],
    "wof:name":"Spi Buz",
    "wof:placetype":"locality"
},
  "geometry": {"coordinates":[63.91223000000001,34.15817],"type":"Point"}
}