{
  "type": "Feature",
  "properties": {
    "gn:admin1_code":"08",
    "gn:admin2_code":"604.0",
    "gn:asciiname":"Shibar",
    "gn:country_code":"AF",
    "gn:dem":2859,
    "gn:feature_class":"P",
    "gn:feature_code":"PPL",
    "gn:name":"Shib\u0101r",
    "gn:population":0,
    "gn:timezone":"Asia/Kabul",
    "iso:country":"AF",
    "name:und_x_variant":[
        "\u0160eb\u0101r",
        "Shibar",
        "Sheb\u0101r",
        "Shib\u0101r",
        "\u0634\u0628\u0627\u0631"
    ],
    "wof:name":"Shibar",
    "wof:placetype":"locality"
},
  "geometry": {"coordinates":[67.42100000000001,34.06365],"type":"Point"}
}