{
  "type": "Feature",
  "properties": {
    "gn:admin1_code":"18",
    "gn:admin2_code":"812.0",
    "gn:asciiname":"Dre Chine",
    "gn:country_code":"AF",
    "gn:dem":737,
    "gn:feature_class":"P",
    "gn:feature_code":"PPL",
    "gn:name":"Dr\u0113 Ch\u012bn\u0113",
    "gn:population":0,
    "gn:timezone":"Asia/Kabul",
    "iso:country":"AF",
    "name:fas_x_preferred":[
        "\u0633\u0647 \u0686\u0634\u0645\u0647"
    ],
    "name:und_x_variant":[
        "Dr\u0113 \u010cin\u0113",
        "Drechinegar",
        "Drechine",
        "Dr\u0113 Chin\u0113",
        "\u0633\u0647 \u0686\u0634\u0645\u0647",
        "Dr\u0113 Ch\u012bn\u0113",
        "\u062f\u0631\u06d0 \u0686\u06cc\u0646\u06d0"
    ],
    "wof:name":"Dre Chine",
    "wof:placetype":"locality"
},
  "geometry": {"coordinates":[70.98806999999999,34.14408],"type":"Point"}
}