{
  "type": "Feature",
  "properties": {
    "gn:admin1_code":"09",
    "gn:admin2_code":"2703.0",
    "gn:asciiname":"Takhrid",
    "gn:country_code":"AF",
    "gn:dem":2356,
    "gn:feature_class":"P",
    "gn:feature_code":"PPL",
    "gn:name":"Takhr\u012bd",
    "gn:population":0,
    "gn:timezone":"Asia/Kabul",
    "iso:country":"AF",
    "name:und_x_variant":[
        "Takhr\u012bd",
        "\u062a\u062e\u0631\u06cc\u062f",
        "Takh\u1e5f\u012b\u1e0f"
    ],
    "wof:name":"Takhrid",
    "wof:placetype":"locality"
},
  "geometry": {"coordinates":[63.67381999999999,34.0566],"type":"Point"}
}