{
  "type": "Feature",
  "properties": {
    "gn:admin1_code":"28",
    "gn:admin2_code":"2507",
    "gn:asciiname":"Kabiri Kelay",
    "gn:country_code":"AF",
    "gn:dem":2283,
    "gn:feature_class":"P",
    "gn:feature_code":"PPL",
    "gn:name":"Kab\u012br\u012b K\u00ealay",
    "gn:population":0,
    "gn:timezone":"Asia/Kabul",
    "iso:country":"AF",
    "name:fas_x_preferred":[
        "\u0642\u0631\u064a\u06c0 \u0643\u0628\u064a\u0631\u06cc"
    ],
    "name:und_x_variant":[
        "Kab\u012br\u012b Kalay",
        "Kab\u012br\u012b K\u00ealay",
        "\u06a9\u0628\u06cc\u0631\u06cc \u06a9\u0644\u06cc"
    ],
    "wof:name":"Kabiri Kelay",
    "wof:placetype":"locality"
},
  "geometry": {"coordinates":[67.32980000000001,32.13545],"type":"Point"}
}