{
  "type": "Feature",
  "properties": {
    "gn:admin1_code":"07",
    "gn:admin2_code":"1804",
    "gn:asciiname":"Tarakchi",
    "gn:country_code":"AF",
    "gn:dem":1747,
    "gn:feature_class":"P",
    "gn:feature_code":"PPL",
    "gn:name":"Tarakch\u012b",
    "gn:population":0,
    "gn:timezone":"Asia/Kabul",
    "iso:country":"AF",
    "name:und_x_variant":[
        "Ta\u1e5fakci",
        "Tarakch\u012b",
        "\u062a\u0631\u06a9\u0686\u06cc"
    ],
    "wof:name":"Tarakchi",
    "wof:placetype":"locality"
},
  "geometry": {"coordinates":[64.42615000000001,35.63955],"type":"Point"}
}