{
  "type": "Feature",
  "properties": {
    "gn:admin1_code":"10",
    "gn:admin2_code":"2306.0",
    "gn:asciiname":"Barghanah",
    "gn:country_code":"AF",
    "gn:dem":982,
    "gn:feature_class":"P",
    "gn:feature_code":"PPL",
    "gn:name":"Barghanah",
    "gn:population":0,
    "gn:timezone":"Asia/Kabul",
    "iso:country":"AF",
    "name:und_x_variant":[
        "Bargana",
        "Ba\u1e5fghana",
        "Barghanah",
        "\u0628\u0631\u063a\u0646\u0647",
        "Ba\u1e5fghanah"
    ],
    "wof:name":"Barghanah",
    "wof:placetype":"locality"
},
  "geometry": {"coordinates":[64.64315000000001,32.10439],"type":"Point"}
}