{
  "type": "Feature",
  "properties": {
    "gn:admin1_code":"09",
    "gn:admin2_code":"2705",
    "gn:asciiname":"Jar-e Mirza",
    "gn:country_code":"AF",
    "gn:dem":2620,
    "gn:feature_class":"P",
    "gn:feature_code":"PPL",
    "gn:name":"Jar-e M\u012brz\u0101",
    "gn:population":0,
    "gn:timezone":"Asia/Kabul",
    "iso:country":"AF",
    "name:und_x_variant":[
        "Dzhari-Mirza",
        "Jar-e M\u012brz\u0101",
        "\u062c\u0631 \u0645\u06cc\u0631\u0632\u0627",
        "Jar-e Mirz\u0101"
    ],
    "wof:name":"Jar-e Mirza",
    "wof:placetype":"locality"
},
  "geometry": {"coordinates":[64.41190999999999,33.60034],"type":"Point"}
}