{
  "type": "Feature",
  "properties": {
    "gn:admin1_code":"11",
    "gn:admin2_code":"2014",
    "gn:asciiname":"Karezak",
    "gn:country_code":"AF",
    "gn:dem":1528,
    "gn:feature_class":"P",
    "gn:feature_code":"PPL",
    "gn:name":"K\u0101r\u0113zak",
    "gn:population":0,
    "gn:timezone":"Asia/Kabul",
    "iso:country":"AF",
    "name:und_x_variant":[
        "K\u0101\u1e5f\u0113zak",
        "K\u0101r\u012bzak",
        "K\u0101r\u0113zak",
        "\u06a9\u0627\u0631\u06d0\u0632\u06a9"
    ],
    "wof:name":"Karezak",
    "wof:placetype":"locality"
},
  "geometry": {"coordinates":[62.61861,33.2091],"type":"Point"}
}