{
  "type": "Feature",
  "properties": {
    "gn:admin1_code":"9",
    "gn:admin2_code":"2707.0",
    "gn:asciiname":"Dangak",
    "gn:country_code":"AF",
    "gn:dem":2808,
    "gn:feature_class":"P",
    "gn:feature_code":"PPL",
    "gn:name":"Dangak",
    "gn:population":0,
    "gn:timezone":"Asia/Kabul",
    "iso:country":"AF",
    "name:ara_x_preferred":[
        "\u062f\u0627\u0646\u063a\u0627\u0643"
    ],
    "name:fin_x_preferred":[
        "Dangak"
    ],
    "name:und_x_variant":[
        "\u062f\u0646\u06af\u06a9"
    ],
    "wof:name":"Dangak",
    "wof:placetype":"locality"
},
  "geometry": {"coordinates":[66.29365,34.72079],"type":"Point"}
}