{
  "type": "Feature",
  "properties": {
    "gn:admin1_code":"37",
    "gn:admin2_code":"3213",
    "gn:asciiname":"Korgay",
    "gn:country_code":"AF",
    "gn:dem":1549,
    "gn:feature_class":"P",
    "gn:feature_code":"PPL",
    "gn:name":"K\u014drgay",
    "gn:population":0,
    "gn:timezone":"Asia/Kabul",
    "iso:country":"AF",
    "name:fas_x_preferred":[
        "\u0643\u0648\u0631\u06af\u06cc"
    ],
    "name:und_x_variant":[
        "K\u014d\u1e5fgay",
        "Korgay",
        "K\u016brga\u012b",
        "K\u016brgay",
        "\u0643\u0648\u0631\u06af\u06cc",
        "K\u014drgay"
    ],
    "wof:name":"Korgay",
    "wof:placetype":"locality"
},
  "geometry": {"coordinates":[69.57889,33.285],"type":"Point"}
}