{
  "type": "Feature",
  "properties": {
    "gn:admin1_code":"05",
    "gn:admin2_code":"2805.0",
    "gn:asciiname":"Lets",
    "gn:country_code":"AF",
    "gn:dem":2996,
    "gn:feature_class":"P",
    "gn:feature_code":"PPL",
    "gn:name":"L\u0113ts",
    "gn:population":0,
    "gn:timezone":"Asia/Kabul",
    "iso:country":"AF",
    "name:und_x_variant":[
        "Lech",
        "L\u0113ts",
        "L\u0113c",
        "\u0644\u06d0\u0685"
    ],
    "wof:name":"Lets",
    "wof:placetype":"locality"
},
  "geometry": {"coordinates":[67.13776999999999,34.46681],"type":"Point"}
}