{
  "type": "Feature",
  "properties": {
    "gn:admin1_code":"3",
    "gn:admin2_code":"1309.0",
    "gn:asciiname":"Turk-e Sayad",
    "gn:country_code":"AF",
    "gn:dem":996,
    "gn:feature_class":"P",
    "gn:feature_code":"PPL",
    "gn:name":"Turk-e \u015eay\u0101d",
    "gn:population":0,
    "gn:timezone":"Asia/Kabul",
    "iso:country":"AF",
    "name:und_x_variant":[
        "Turke Say\u0101\u1e0f",
        "Tork-e \u015eayy\u0101d",
        "Turk-e \u015eay\u0101d",
        "\u062a\u0631\u06a9 \u0635\u06cc\u0627\u062f"
    ],
    "wof:name":"Turk-e Sayad",
    "wof:placetype":"locality"
},
  "geometry": {"coordinates":[69.03659,36.06343],"type":"Point"}
}