{
  "type": "Feature",
  "properties": {
    "gn:admin1_code":"03",
    "gn:admin2_code":"1303",
    "gn:asciiname":"Shor Ab",
    "gn:country_code":"AF",
    "gn:dem":1625,
    "gn:feature_class":"P",
    "gn:feature_code":"PPL",
    "gn:name":"Sh\u014dr \u0100b",
    "gn:population":0,
    "gn:timezone":"Asia/Kabul",
    "iso:country":"AF",
    "name:und_x_variant":[
        "S\u0304\u014d\u1e5f\u0101b",
        "Sh\u016br\u0101b",
        "Sh\u014dr \u0100b",
        "\u0634\u0648\u0631 \u0622\u0628"
    ],
    "wof:name":"Shor Ab",
    "wof:placetype":"locality"
},
  "geometry": {"coordinates":[68.3967,35.79885],"type":"Point"}
}