{
  "type": "Feature",
  "properties": {
    "gn:admin1_code":"07",
    "gn:admin2_code":"1805",
    "gn:asciiname":"Ghal-e Siyah",
    "gn:country_code":"AF",
    "gn:dem":1725,
    "gn:feature_class":"P",
    "gn:feature_code":"PPL",
    "gn:name":"Gh\u0101l-e Siy\u0101h",
    "gn:population":0,
    "gn:timezone":"Asia/Kabul",
    "iso:country":"AF",
    "name:und_x_variant":[
        "Gh\u0101le Sy\u0101h",
        "Gh\u0101l-e S\u012b\u0101h",
        "\u063a\u0627\u0644 \u0633\u06cc\u0627\u0647",
        "Gh\u0101l-e Siy\u0101h"
    ],
    "wof:name":"Ghal-e Siyah",
    "wof:placetype":"locality"
},
  "geometry": {"coordinates":[64.45749000000001,35.23825],"type":"Point"}
}