{
  "type": "Feature",
  "properties": {
    "gn:admin1_code":"3",
    "gn:admin2_code":"1301.0",
    "gn:asciiname":"Gurgurak",
    "gn:country_code":"AF",
    "gn:dem":575,
    "gn:feature_class":"P",
    "gn:feature_code":"PPL",
    "gn:name":"Gurgurak",
    "gn:population":0,
    "gn:timezone":"Asia/Kabul",
    "iso:country":"AF",
    "name:fas_x_preferred":[
        "\u06af\u0648\u0631\u06af\u0631\u0643"
    ],
    "name:rus_x_preferred":[
        "\u0413\u0443\u0440\u0433\u0443\u0440\u0430\u043a"
    ],
    "name:und_x_variant":[
        "Gurgorak",
        "\u06af\u0631\u06af\u0631\u06a9"
    ],
    "wof:name":"Gurgurak",
    "wof:placetype":"locality"
},
  "geometry": {"coordinates":[68.57932,36.07517],"type":"Point"}
}