{
  "type": "Feature",
  "properties": {
    "gn:admin1_code":"02",
    "gn:admin2_code":"1902.0",
    "gn:asciiname":"Chilunak",
    "gn:country_code":"AF",
    "gn:dem":1585,
    "gn:feature_class":"P",
    "gn:feature_code":"PPL",
    "gn:name":"Chil\u016bnak",
    "gn:population":0,
    "gn:timezone":"Asia/Kabul",
    "iso:country":"AF",
    "name:und_x_variant":[
        "Cel\u016bnak",
        "Chel\u016bnak",
        "Chil\u016bnak",
        "\u0686\u0644\u0648\u0646\u06a9"
    ],
    "wof:name":"Chilunak",
    "wof:placetype":"locality"
},
  "geometry": {"coordinates":[62.90351,34.74625],"type":"Point"}
}