{
  "type": "Feature",
  "properties": {
    "gn:admin1_code":"41",
    "gn:admin2_code":"3403.0",
    "gn:asciiname":"Jowzari",
    "gn:country_code":"AF",
    "gn:dem":2607,
    "gn:feature_class":"P",
    "gn:feature_code":"PPL",
    "gn:name":"Jowzar\u012b",
    "gn:population":0,
    "gn:timezone":"Asia/Kabul",
    "iso:country":"AF",
    "name:und_x_variant":[
        "Jowzar\u012b",
        "\u062c\u0648\u0632\u0631\u06cc",
        "Jawza\u1e5f\u012b"
    ],
    "wof:name":"Jowzari",
    "wof:placetype":"locality"
},
  "geometry": {"coordinates":[66.35204,33.95178],"type":"Point"}
}