{
  "type": "Feature",
  "properties": {
    "gn:admin1_code":"06",
    "gn:admin2_code":"2104",
    "gn:asciiname":"Ghuji",
    "gn:country_code":"AF",
    "gn:dem":2068,
    "gn:feature_class":"P",
    "gn:feature_code":"PPL",
    "gn:name":"Gh\u016bj\u012b",
    "gn:population":0,
    "gn:timezone":"Asia/Kabul",
    "iso:country":"AF",
    "name:und_x_variant":[
        "Gh\u016bj\u012b",
        "\u063a\u0648\u062c\u06cc",
        "Gh\u016bji"
    ],
    "wof:name":"Ghuji",
    "wof:placetype":"locality"
},
  "geometry": {"coordinates":[63.96241,33.45046],"type":"Point"}
}