{
  "type": "Feature",
  "properties": {
    "gn:admin1_code":"05",
    "gn:admin2_code":"2806",
    "gn:asciiname":"Qal'ah",
    "gn:country_code":"AF",
    "gn:dem":2913,
    "gn:feature_class":"P",
    "gn:feature_code":"PPL",
    "gn:name":"Qal\u2018ah",
    "gn:population":0,
    "gn:timezone":"Asia/Kabul",
    "iso:country":"AF",
    "name:und_x_variant":[
        "Qal\u2018a",
        "Kala",
        "Qal\u2018ah",
        "\u0642\u0644\u0639\u0647"
    ],
    "wof:name":"Qal'ah",
    "wof:placetype":"locality"
},
  "geometry": {"coordinates":[66.67336999999999,34.01906],"type":"Point"}
}