{
  "type": "Feature",
  "properties": {
    "gn:admin1_code":"8",
    "gn:admin2_code":"606.0",
    "gn:asciiname":"Altarghanah",
    "gn:country_code":"AF",
    "gn:dem":2986,
    "gn:feature_class":"P",
    "gn:feature_code":"PPL",
    "gn:name":"Al\u1e6farghanah",
    "gn:population":0,
    "gn:timezone":"Asia/Kabul",
    "iso:country":"AF",
    "name:und_x_variant":[
        "Alta\u1e5fghana",
        "Alta\u1e5fghanah",
        "Al\u1e6farghanah",
        "\u0627\u0644\u067c\u0631\u063a\u0646\u0647"
    ],
    "wof:name":"Altarghanah",
    "wof:placetype":"locality"
},
  "geometry": {"coordinates":[67.18722,33.2844],"type":"Point"}
}