{
  "type": "Feature",
  "properties": {
    "gn:admin1_code":"29",
    "gn:admin2_code":"2916",
    "gn:asciiname":"Jalalzai",
    "gn:country_code":"AF",
    "gn:dem":2043,
    "gn:feature_class":"P",
    "gn:feature_code":"PPL",
    "gn:name":"Jal\u0101lza\u012b",
    "gn:population":0,
    "gn:timezone":"Asia/Kabul",
    "iso:country":"AF",
    "name:rus_x_preferred":[
        "Dzhalal\u2019zi"
    ],
    "name:und_x_variant":[
        "Jal\u0101lzay",
        "\u062c\u0644\u0627\u0644\u0632\u06cc",
        "Jal\u0101lz\u012b",
        "Jal\u0101lza\u012b"
    ],
    "wof:name":"Jalalzai",
    "wof:placetype":"locality"
},
  "geometry": {"coordinates":[68.39877,32.74804],"type":"Point"}
}