{
  "type": "Feature",
  "properties": {
    "gn:admin1_code":"41",
    "gn:admin2_code":"3409.0",
    "gn:asciiname":"Ikhtyaro",
    "gn:country_code":"AF",
    "gn:dem":1865,
    "gn:feature_class":"P",
    "gn:feature_code":"PPL",
    "gn:name":"Ikhty\u0101r\u014d",
    "gn:population":0,
    "gn:timezone":"Asia/Kabul",
    "iso:country":"AF",
    "name:und_x_variant":[
        "Ekhty\u0101\u1e5fo",
        "Ekht\u012b\u0101ro",
        "Ikhty\u0101r\u014d",
        "\u0627\u062e\u062a\u06cc\u0627\u0631\u0648"
    ],
    "wof:name":"Ikhtyaro",
    "wof:placetype":"locality"
},
  "geometry": {"coordinates":[66.58405999999999,33.65055],"type":"Point"}
}