{
  "type": "Feature",
  "properties": {
    "gn:admin1_code":"28",
    "gn:admin2_code":"2507",
    "gn:asciiname":"Suhai",
    "gn:country_code":"AF",
    "gn:dem":1889,
    "gn:feature_class":"P",
    "gn:feature_code":"PPL",
    "gn:name":"S\u016bha\u012b",
    "gn:population":0,
    "gn:timezone":"Asia/Kabul",
    "iso:country":"AF",
    "name:und_x_variant":[
        "Sukhay",
        "S\u016bhay",
        "\u0633\u0648\u0647\u06cc",
        "S\u016bha\u012b"
    ],
    "wof:name":"Suhai",
    "wof:placetype":"locality"
},
  "geometry": {"coordinates":[67.25055,31.95268],"type":"Point"}
}