{
  "type": "Feature",
  "properties": {
    "gn:admin1_code":"29",
    "gn:admin2_code":"2909.0",
    "gn:asciiname":"Malik Khel",
    "gn:country_code":"AF",
    "gn:dem":2013,
    "gn:feature_class":"P",
    "gn:feature_code":"PPL",
    "gn:name":"Malik Kh\u0113l",
    "gn:population":0,
    "gn:timezone":"Asia/Kabul",
    "iso:country":"AF",
    "name:und_x_variant":[
        "Malekkh\u0113l",
        "Malikkheyl\u2019",
        "Malik Kh\u0113l",
        "Malekkheyl"
    ],
    "wof:name":"Malik Khel",
    "wof:placetype":"locality"
},
  "geometry": {"coordinates":[69.25417,32.80944],"type":"Point"}
}