{
  "type": "Feature",
  "properties": {
    "gn:admin1_code":"29",
    "gn:admin2_code":"2913",
    "gn:asciiname":"Oshakay",
    "gn:country_code":"AF",
    "gn:dem":2656,
    "gn:feature_class":"P",
    "gn:feature_code":"PPL",
    "gn:name":"\u014cshakay",
    "gn:population":0,
    "gn:timezone":"Asia/Kabul",
    "iso:country":"AF",
    "name:und_x_variant":[
        "O\u0161akay",
        "Ushakay",
        "Oshakay",
        "\u014cshakay",
        "\u0627\u0648\u0634\u06a9\u06cc"
    ],
    "wof:name":"Oshakay",
    "wof:placetype":"locality"
},
  "geometry": {"coordinates":[69.22958,33.15181],"type":"Point"}
}