{
  "type": "Feature",
  "properties": {
    "gn:admin1_code":"29",
    "gn:admin2_code":"2918",
    "gn:asciiname":"Yahya Khel",
    "gn:country_code":"AF",
    "gn:dem":2136,
    "gn:feature_class":"P",
    "gn:feature_code":"PPLA2",
    "gn:name":"Ya\u1e29y\u00e1 Kh\u0113l",
    "gn:population":0,
    "gn:timezone":"Asia/Kabul",
    "iso:country":"AF",
    "name:rus_x_preferred":[
        "Yakh\u2019yakheyl\u2019"
    ],
    "name:und_x_variant":[
        "Ya\u1e29y\u0101kh\u0113l",
        "Ya Khel",
        "Ye\u1e29y\u0101kh\u0113l",
        "\u06cc\u062d\u06cc\u0649 \u062e\u06d0\u0644",
        "Ya\u1e29y\u0101 Kheyl",
        "Ya\u1e29y\u00e1 Kh\u0113l"
    ],
    "wof:name":"Yahya Khel",
    "wof:placetype":"locality"
},
  "geometry": {"coordinates":[68.64622,32.93742],"type":"Point"}
}