{
  "type": "Feature",
  "properties": {
    "gn:admin1_code":"11",
    "gn:admin2_code":"2014.0",
    "gn:asciiname":"Taj",
    "gn:country_code":"AF",
    "gn:dem":1081,
    "gn:feature_class":"P",
    "gn:feature_code":"PPL",
    "gn:name":"T\u0101j",
    "gn:population":0,
    "gn:timezone":"Asia/Kabul",
    "iso:country":"AF",
    "name:ces_x_preferred":[
        "Taj"
    ],
    "name:fra_x_preferred":[
        "Taj"
    ],
    "name:rus_x_preferred":[
        "\u0422\u0430\u0434\u0436"
    ],
    "name:und_x_variant":[
        "Tadzh",
        "T\u0101j",
        "\u062a\u0627\u062c"
    ],
    "wof:name":"Taj",
    "wof:placetype":"locality"
},
  "geometry": {"coordinates":[62.26413,33.29302],"type":"Point"}
}