{
  "type": "Feature",
  "properties": {
    "gn:admin1_code":"8",
    "gn:admin2_code":"609.0",
    "gn:asciiname":"Bala'ir",
    "gn:country_code":"AF",
    "gn:dem":1931,
    "gn:feature_class":"P",
    "gn:feature_code":"PPL",
    "gn:name":"Bal\u0101\u2019ir",
    "gn:population":0,
    "gn:timezone":"Asia/Kabul",
    "iso:country":"AF",
    "name:und_x_variant":[
        "Balair",
        "Bal\u0101\u2019ir",
        "\u0628\u0644\u0627\u0626\u0631",
        "Bal\u0101\u2019e\u1e5f"
    ],
    "wof:name":"Bala'ir",
    "wof:placetype":"locality"
},
  "geometry": {"coordinates":[67.62288000000001,32.64057],"type":"Point"}
}