{
  "type": "Feature",
  "properties": {
    "gn:admin1_code":"11",
    "gn:admin2_code":"2015",
    "gn:asciiname":"Kham-e Surkh",
    "gn:country_code":"AF",
    "gn:dem":2036,
    "gn:feature_class":"P",
    "gn:feature_code":"PPL",
    "gn:name":"Kham-e Surkh",
    "gn:population":0,
    "gn:timezone":"Asia/Kabul",
    "iso:country":"AF",
    "name:und_x_variant":[
        "Khame Su\u1e5fkh",
        "Khami-Surkh",
        "Kham-e Surkh",
        "\u062e\u0645 \u0633\u0631\u062e",
        "Kham-e Sorkh"
    ],
    "wof:name":"Kham-e Surkh",
    "wof:placetype":"locality"
},
  "geometry": {"coordinates":[64.07209,34.49065],"type":"Point"}
}