{
  "type": "Feature",
  "properties": {
    "gn:admin1_code":"30",
    "gn:admin2_code":"1606",
    "gn:asciiname":"Muhmandan",
    "gn:country_code":"AF",
    "gn:dem":326,
    "gn:feature_class":"P",
    "gn:feature_code":"PPL",
    "gn:name":"Muhmand\u0101n",
    "gn:population":0,
    "gn:timezone":"Asia/Kabul",
    "iso:country":"AF",
    "name:fas_x_preferred":[
        "\u0645\u062d\u0645\u0646\u062f\u0627\u0646"
    ],
    "name:rus_x_preferred":[
        "\u041c\u043e\u043c\u0430\u043d\u0434\u0430\u043d"
    ],
    "name:und_x_variant":[
        "Momandan",
        "Mo\u1e29mand\u0101n",
        "Mu\u1e29mand\u0101n",
        "Muhmand\u0101n",
        "\u0645\u0647\u0645\u0646\u062f\u0627\u0646"
    ],
    "wof:name":"Muhmandan",
    "wof:placetype":"locality"
},
  "geometry": {"coordinates":[66.84209,36.84845],"type":"Point"}
}