{
  "type": "Feature",
  "properties": {
    "gn:admin1_code":"08",
    "gn:admin2_code":"604.0",
    "gn:asciiname":"Zard Talah",
    "gn:country_code":"AF",
    "gn:dem":2879,
    "gn:feature_class":"P",
    "gn:feature_code":"PPL",
    "gn:name":"Zard T\u0101lah",
    "gn:population":0,
    "gn:timezone":"Asia/Kabul",
    "iso:country":"AF",
    "name:und_x_variant":[
        "Zardtala",
        "Za\u1e5f\u1e0ftala",
        "Zardtalah",
        "Zard T\u0101lah",
        "\u0632\u0631\u062f \u062a\u0627\u0644\u0647"
    ],
    "wof:name":"Zard Talah",
    "wof:placetype":"locality"
},
  "geometry": {"coordinates":[67.42910999999999,34.07677],"type":"Point"}
}