{
  "type": "Feature",
  "properties": {
    "gn:admin1_code":"27",
    "gn:admin2_code":"404.0",
    "gn:asciiname":"Shorqobi",
    "gn:country_code":"AF",
    "gn:dem":2907,
    "gn:feature_class":"P",
    "gn:feature_code":"PPL",
    "gn:name":"Sh\u014drq\u014db\u012b",
    "gn:population":0,
    "gn:timezone":"Asia/Kabul",
    "iso:country":"AF",
    "name:und_x_variant":[
        "\u0160orqobi",
        "Shorkobi",
        "Sh\u016brq\u016bb\u012b",
        "Sh\u014drq\u014db\u012b",
        "\u0634\u0648\u0631\u0642\u0648\u0628\u06cc"
    ],
    "wof:name":"Shorqobi",
    "wof:placetype":"locality"
},
  "geometry": {"coordinates":[67.89963,34.17905],"type":"Point"}
}