{
  "type": "Feature",
  "properties": {
    "gn:admin1_code":"09",
    "gn:admin2_code":"2704",
    "gn:asciiname":"Sarubi",
    "gn:country_code":"AF",
    "gn:dem":1834,
    "gn:feature_class":"P",
    "gn:feature_code":"PPL",
    "gn:name":"Sar\u016bb\u012b",
    "gn:population":0,
    "gn:timezone":"Asia/Kabul",
    "iso:country":"AF",
    "name:und_x_variant":[
        "Sa\u1e5f\u016bbi",
        "Sar\u016bb\u012b",
        "\u0633\u0631\u0648\u0628\u06cc",
        "Sarowb\u012b"
    ],
    "wof:name":"Sarubi",
    "wof:placetype":"locality"
},
  "geometry": {"coordinates":[63.66426,33.47924],"type":"Point"}
}