{
  "type": "Feature",
  "properties": {
    "gn:admin1_code":"24",
    "gn:admin2_code":"1405.0",
    "gn:asciiname":"Larkhabi",
    "gn:country_code":"AF",
    "gn:dem":401,
    "gn:feature_class":"P",
    "gn:feature_code":"PPL",
    "gn:name":"Larkh\u0101b\u012b",
    "gn:population":0,
    "gn:timezone":"Asia/Kabul",
    "iso:country":"AF",
    "name:rus_x_preferred":[
        "\u041b\u0430\u0440\u0445\u0430\u0431\u0438"
    ],
    "name:und_x_variant":[
        "Larkh\u0101b\u012b",
        "\u0644\u0631\u062e\u0627\u0628\u06cc"
    ],
    "wof:name":"Larkhabi",
    "wof:placetype":"locality"
},
  "geometry": {"coordinates":[68.88561,36.59209],"type":"Point"}
}