{
  "type": "Feature",
  "properties": {
    "gn:admin1_code":"18",
    "gn:admin2_code":"821.0",
    "gn:asciiname":"Biland Ghar",
    "gn:country_code":"AF",
    "gn:dem":553,
    "gn:feature_class":"P",
    "gn:feature_code":"PPL",
    "gn:name":"Biland Ghar",
    "gn:population":0,
    "gn:timezone":"Asia/Kabul",
    "iso:country":"AF",
    "name:fas_x_preferred":[
        "\u0643\u0648\u0647\u0654 \u0628\u0644\u0646\u062f"
    ],
    "name:und_x_variant":[
        "Beland",
        "Bilandgar",
        "Biland Ghar",
        "Beland Ghar",
        "\u0628\u0644\u0646\u062f \u063a\u0631"
    ],
    "wof:name":"Biland Ghar",
    "wof:placetype":"locality"
},
  "geometry": {"coordinates":[70.51113000000002,34.45001],"type":"Point"}
}