{
  "type": "Feature",
  "properties": {
    "gn:admin1_code":"5",
    "gn:admin2_code":"2806.0",
    "gn:asciiname":"Chahar Obeh",
    "gn:country_code":"AF",
    "gn:dem":2449,
    "gn:feature_class":"P",
    "gn:feature_code":"PPL",
    "gn:name":"Chah\u0101r \u014cb\u00eah",
    "gn:population":0,
    "gn:timezone":"Asia/Kabul",
    "iso:country":"AF",
    "name:und_x_variant":[
        "\u010caroba",
        "Charoba",
        "Chah\u0101r\u014dbah",
        "Chah\u0101r \u014cb\u00eah",
        "\u0686\u0647\u0627\u0631 \u0627\u0648\u0628\u0647"
    ],
    "wof:name":"Chahar Obeh",
    "wof:placetype":"locality"
},
  "geometry": {"coordinates":[66.54633000000001,34.11861],"type":"Point"}
}