{
  "type": "Feature",
  "properties": {
    "gn:admin1_code":"08",
    "gn:admin2_code":"610",
    "gn:asciiname":"Ikhtiyar Khel",
    "gn:country_code":"AF",
    "gn:dem":2054,
    "gn:feature_class":"P",
    "gn:feature_code":"PPL",
    "gn:name":"Ikhtiy\u0101r Kh\u0113l",
    "gn:population":0,
    "gn:timezone":"Asia/Kabul",
    "iso:country":"AF",
    "name:rus_x_preferred":[
        "Ikhtiarkheyl\u2019"
    ],
    "name:und_x_variant":[
        "Ekhty\u0101\u1e5fkh\u0113l",
        "Ikhtiy\u0101r Kh\u0113l",
        "\u0627\u062e\u062a\u06cc\u0627\u0631 \u062e\u06d0\u0644",
        "Ekht\u012b\u0101r Kheyl"
    ],
    "wof:name":"Ikhtiyar Khel",
    "wof:placetype":"locality"
},
  "geometry": {"coordinates":[67.98204,32.30039],"type":"Point"}
}