{
  "type": "Feature",
  "properties": {
    "gn:admin1_code":"28",
    "gn:admin2_code":"2507",
    "gn:asciiname":"Zhawerah",
    "gn:country_code":"AF",
    "gn:dem":2003,
    "gn:feature_class":"P",
    "gn:feature_code":"PPL",
    "gn:name":"Zhaw\u00earah",
    "gn:population":0,
    "gn:timezone":"Asia/Kabul",
    "iso:country":"AF",
    "name:fas_x_preferred":[
        "\u0632\u0648\u0631\u0647"
    ],
    "name:und_x_variant":[
        "Zavara",
        "Zawa\u1e5fa",
        "Zhaw\u00earah",
        "\u0698\u0648\u0631\u0647",
        "Zawarah"
    ],
    "wof:name":"Zhawerah",
    "wof:placetype":"locality"
},
  "geometry": {"coordinates":[67.03206,31.87578],"type":"Point"}
}