{
  "type": "Feature",
  "properties": {
    "gn:admin1_code":"01",
    "gn:admin2_code":"1101.0",
    "gn:asciiname":"Urusak",
    "gn:country_code":"AF",
    "gn:dem":1434,
    "gn:feature_class":"P",
    "gn:feature_code":"PPL",
    "gn:name":"Ur\u016bsak",
    "gn:population":0,
    "gn:timezone":"Asia/Kabul",
    "iso:country":"AF",
    "name:und_x_variant":[
        "\u0627\u0631\u0648\u0633\u06a9",
        "U\u1e5f\u016bsak",
        "Ur\u016bsak"
    ],
    "wof:name":"Urusak",
    "wof:placetype":"locality"
},
  "geometry": {"coordinates":[70.55559000000002,37.14512],"type":"Point"}
}