{
  "type": "Feature",
  "properties": {
    "gn:admin1_code":"26",
    "gn:admin2_code":"1217",
    "gn:asciiname":"Tutak",
    "gn:country_code":"AF",
    "gn:dem":1295,
    "gn:feature_class":"P",
    "gn:feature_code":"PPL",
    "gn:name":"T\u016btak",
    "gn:population":0,
    "gn:timezone":"Asia/Kabul",
    "iso:country":"AF",
    "name:und_x_variant":[
        "T\u016btak",
        "\u062a\u0648\u062a\u06a9"
    ],
    "wof:name":"Tutak",
    "wof:placetype":"locality"
},
  "geometry": {"coordinates":[69.72774,36.61067],"type":"Point"}
}