{
  "type": "Feature",
  "properties": {
    "gn:admin1_code":"36",
    "gn:admin2_code":"702",
    "gn:asciiname":"Shamal Zai",
    "gn:country_code":"AF",
    "gn:dem":2170,
    "gn:feature_class":"P",
    "gn:feature_code":"PPL",
    "gn:name":"Sham\u0101l Za\u012b",
    "gn:population":0,
    "gn:timezone":"Asia/Kabul",
    "iso:country":"AF",
    "name:fas_x_preferred":[
        "\u0634\u0645\u0644\u0632\u06cc"
    ],
    "name:rus_x_preferred":[
        "Shamal\u2019zi"
    ],
    "name:und_x_variant":[
        "\u0160amalzi",
        "Shamalzi",
        "Sham\u0101l Za\u012b",
        "\u0634\u0645\u0627\u0644 \u0632\u06cc"
    ],
    "wof:name":"Shamal Zai",
    "wof:placetype":"locality"
},
  "geometry": {"coordinates":[69.03785999999999,33.51099],"type":"Point"}
}