{
  "type": "Feature",
  "properties": {
    "gn:admin1_code":"05",
    "gn:admin2_code":"2805",
    "gn:asciiname":"Paysh Band",
    "gn:country_code":"AF",
    "gn:dem":2986,
    "gn:feature_class":"P",
    "gn:feature_code":"PPL",
    "gn:name":"Paysh Band",
    "gn:population":0,
    "gn:timezone":"Asia/Kabul",
    "iso:country":"AF",
    "name:und_x_variant":[
        "P\u0113\u0161band",
        "Peshband",
        "P\u012bsh Band",
        "Paysh Band",
        "\u067e\u06cc\u0634 \u0628\u0646\u062f"
    ],
    "wof:name":"Paysh Band",
    "wof:placetype":"locality"
},
  "geometry": {"coordinates":[66.66594000000001,34.4168],"type":"Point"}
}