{
  "type": "Feature",
  "properties": {
    "gn:admin1_code":"28",
    "gn:admin2_code":"2509",
    "gn:asciiname":"Tangay",
    "gn:country_code":"AF",
    "gn:dem":1987,
    "gn:feature_class":"P",
    "gn:feature_code":"PPL",
    "gn:name":"Tangay",
    "gn:population":0,
    "gn:timezone":"Asia/Kabul",
    "iso:country":"AF",
    "name:und_x_variant":[
        "Tanga\u012b",
        "Tangay",
        "\u062a\u0646\u06af\u06cc"
    ],
    "wof:name":"Tangay",
    "wof:placetype":"locality"
},
  "geometry": {"coordinates":[67.565,31.67361],"type":"Point"}
}