{
  "type": "Feature",
  "properties": {
    "gn:admin1_code":"2",
    "gn:admin2_code":"1906.0",
    "gn:asciiname":"Akaza'i",
    "gn:country_code":"AF",
    "gn:dem":452,
    "gn:feature_class":"P",
    "gn:feature_code":"PPL",
    "gn:name":"\u0100k\u0101z\u0101\u2019\u012b",
    "gn:population":0,
    "gn:timezone":"Asia/Kabul",
    "iso:country":"AF",
    "name:und_x_variant":[
        "\u0100k\u0101z\u0101\u2018i",
        "\u0100k\u0101z\u0101y\u012b",
        "\u0100k\u0101z\u0101\u2019\u012b",
        "\u0622\u06a9\u0627\u0632\u0627\u0626\u06cc",
        "\u0100k\u0101za\u012b"
    ],
    "wof:name":"Akaza'i",
    "wof:placetype":"locality"
},
  "geometry": {"coordinates":[63.29853000000001,35.62922000000001],"type":"Point"}
}