{
  "type": "Feature",
  "properties": {
    "gn:admin1_code":"7",
    "gn:admin2_code":"1804.0",
    "gn:asciiname":"Matu",
    "gn:country_code":"AF",
    "gn:dem":1003,
    "gn:feature_class":"P",
    "gn:feature_code":"PPL",
    "gn:name":"M\u0101t\u016b",
    "gn:population":0,
    "gn:timezone":"Asia/Kabul",
    "iso:country":"AF",
    "name:und_x_variant":[
        "M\u0101t\u016b",
        "\u0645\u0627\u062a\u0648"
    ],
    "wof:name":"Matu",
    "wof:placetype":"locality"
},
  "geometry": {"coordinates":[64.12913,35.7475],"type":"Point"}
}