{
  "type": "Feature",
  "properties": {
    "gn:admin1_code":"38",
    "gn:admin2_code":"3008.0",
    "gn:asciiname":"Shapawos",
    "gn:country_code":"AF",
    "gn:dem":3297,
    "gn:feature_class":"P",
    "gn:feature_code":"PPL",
    "gn:name":"Shap\u0101wos",
    "gn:population":0,
    "gn:timezone":"Asia/Kabul",
    "iso:country":"AF",
    "wof:name":"Shapawos",
    "wof:placetype":"locality"
},
  "geometry": {"coordinates":[70.43226999999997,35.12321],"type":"Point"}
}