{
  "type": "Feature",
  "properties": {
    "gn:admin1_code":"05",
    "gn:admin2_code":"2806.0",
    "gn:asciiname":"Gird",
    "gn:country_code":"AF",
    "gn:dem":2879,
    "gn:feature_class":"P",
    "gn:feature_code":"PPL",
    "gn:name":"Gird",
    "gn:population":0,
    "gn:timezone":"Asia/Kabul",
    "iso:country":"AF",
    "name:und_x_variant":[
        "Gerd",
        "Gird",
        "\u06af\u0631\u062f"
    ],
    "wof:name":"Gird",
    "wof:placetype":"locality"
},
  "geometry": {"coordinates":[67.00617,34.01114],"type":"Point"}
}