{
  "type": "Feature",
  "properties": {
    "gn:admin1_code":"11",
    "gn:admin2_code":"2007.0",
    "gn:asciiname":"Lush Abak",
    "gn:country_code":"AF",
    "gn:dem":1047,
    "gn:feature_class":"P",
    "gn:feature_code":"PPL",
    "gn:name":"L\u016bsh \u0100bak",
    "gn:population":0,
    "gn:timezone":"Asia/Kabul",
    "iso:country":"AF",
    "name:und_x_variant":[
        "L\u016bs\u0101bak",
        "L\u016bsh \u0100bak",
        "\u0644\u0648\u0634 \u0622\u0628\u06a9",
        "L\u016bsh\u0101bak"
    ],
    "wof:name":"Lush Abak",
    "wof:placetype":"locality"
},
  "geometry": {"coordinates":[61.9069,34.89686],"type":"Point"}
}