{
  "type": "Feature",
  "properties": {
    "gn:admin1_code":"37",
    "gn:admin2_code":"3209.0",
    "gn:asciiname":"Musa Khan Kelay",
    "gn:country_code":"AF",
    "gn:dem":1174,
    "gn:feature_class":"P",
    "gn:feature_code":"PPL",
    "gn:name":"M\u016bs\u00e1 Kh\u0101n K\u00ealay",
    "gn:population":0,
    "gn:timezone":"Asia/Kabul",
    "iso:country":"AF",
    "name:fas_x_preferred":[
        "\u0642\u0631\u064a\u06c0 \u0645\u0648\u0633\u0649 \u062e\u0627\u0646"
    ],
    "name:und_x_variant":[
        "Musakhankalay",
        "M\u016bs\u00e1 Kh\u0101n K\u00ealay",
        "M\u016bs\u00e1 Kh\u0101n Kalay",
        "\u0645\u0648\u0633\u0649 \u062e\u0627\u0646 \u06a9\u0644\u06cc"
    ],
    "wof:name":"Musa Khan Kelay",
    "wof:placetype":"locality"
},
  "geometry": {"coordinates":[69.96359,33.49913],"type":"Point"}
}