{
  "type": "Feature",
  "properties": {
    "gn:admin1_code":"39",
    "gn:admin2_code":"2603",
    "gn:asciiname":"Qarsid",
    "gn:country_code":"AF",
    "gn:dem":2819,
    "gn:feature_class":"P",
    "gn:feature_code":"PPL",
    "gn:name":"Qars\u012bd",
    "gn:population":0,
    "gn:timezone":"Asia/Kabul",
    "iso:country":"AF",
    "name:und_x_variant":[
        "Karsid",
        "Qars\u012bd",
        "\u0642\u0631\u0633\u06cc\u062f",
        "Qa\u1e5fs\u012b\u1e0f"
    ],
    "wof:name":"Qarsid",
    "wof:placetype":"locality"
},
  "geometry": {"coordinates":[66.64579999999999,32.7499],"type":"Point"}
}