{
  "type": "Feature",
  "properties": {
    "gn:admin1_code":"18",
    "gn:admin2_code":"809.0",
    "gn:asciiname":"Ghaljian",
    "gn:country_code":"AF",
    "gn:dem":758,
    "gn:feature_class":"P",
    "gn:feature_code":"PPL",
    "gn:name":"Ghalj\u012b\u0101n",
    "gn:population":0,
    "gn:timezone":"Asia/Kabul",
    "iso:country":"AF",
    "name:fas_x_preferred":[
        "\u063a\u0644\u062c\u064a\u0627\u0646"
    ],
    "name:rus_x_preferred":[
        "Gal\u2019dzh\u2019yan"
    ],
    "name:und_x_variant":[
        "Ghaljy\u0101n",
        "Ghalj\u012b\u0101n",
        "\u063a\u0644\u062c\u06cc\u0627\u0646",
        "Ghaliy\u0101n",
        "\u063a\u0644\u06cc\u0627\u0646"
    ],
    "wof:name":"Ghaljian",
    "wof:placetype":"locality"
},
  "geometry": {"coordinates":[70.57562,34.26425],"type":"Point"}
}