{
  "type": "Feature",
  "properties": {
    "gn:admin1_code":"41",
    "gn:admin2_code":"3401.0",
    "gn:asciiname":"Jowrqalam",
    "gn:country_code":"AF",
    "gn:dem":2291,
    "gn:feature_class":"P",
    "gn:feature_code":"PPL",
    "gn:name":"Jowrqalam",
    "gn:population":0,
    "gn:timezone":"Asia/Kabul",
    "iso:country":"AF",
    "name:und_x_variant":[
        "\u062c\u0648\u0631\u0642\u0644\u0645",
        "Jaw\u1e5fqalam"
    ],
    "wof:name":"Jowrqalam",
    "wof:placetype":"locality"
},
  "geometry": {"coordinates":[66.14831,33.85985],"type":"Point"}
}