{
  "type": "Feature",
  "properties": {
    "gn:admin1_code":"07",
    "gn:admin2_code":"1809",
    "gn:asciiname":"Jar Qal'ah",
    "gn:country_code":"AF",
    "gn:dem":453,
    "gn:feature_class":"P",
    "gn:feature_code":"PPL",
    "gn:name":"Jar Qal\u2018ah",
    "gn:population":0,
    "gn:timezone":"Asia/Kabul",
    "iso:country":"AF",
    "name:und_x_variant":[
        "Jar Qala",
        "Jar Qal\u2018ah",
        "\u062c\u0631 \u0642\u0644\u0639\u0647",
        "Jar Qal\u2018eh"
    ],
    "wof:name":"Jar Qal'ah",
    "wof:placetype":"locality"
},
  "geometry": {"coordinates":[64.9076,36.34954000000001],"type":"Point"}
}