{
  "type": "Feature",
  "properties": {
    "gn:admin1_code":"34",
    "gn:admin2_code":"1009.0",
    "gn:asciiname":"Chapah Darah",
    "gn:country_code":"AF",
    "gn:dem":1165,
    "gn:feature_class":"P",
    "gn:feature_code":"PPL",
    "gn:name":"Chapah Darah",
    "gn:population":0,
    "gn:timezone":"Asia/Kabul",
    "iso:country":"AF",
    "name:fas_x_preferred":[
        "\u0686\u067e\u0647 \u062f\u0631\u0647"
    ],
    "name:und_x_variant":[
        "Dar Chapah Darrah",
        "Capa \u1e0ea\u1e5fa",
        "Chapah Darrah",
        "Chapah Darah"
    ],
    "wof:name":"Chapah Darah",
    "wof:placetype":"locality"
},
  "geometry": {"coordinates":[70.78333000000001,34.95],"type":"Point"}
}