{
  "type": "Feature",
  "properties": {
    "gn:admin1_code":"11",
    "gn:admin2_code":"2011",
    "gn:asciiname":"Khagish",
    "gn:country_code":"AF",
    "gn:dem":1771,
    "gn:feature_class":"P",
    "gn:feature_code":"PPL",
    "gn:name":"Kh\u0101gish",
    "gn:population":0,
    "gn:timezone":"Asia/Kabul",
    "iso:country":"AF",
    "name:und_x_variant":[
        "Kh\u0101ge\u0161",
        "Kh\u0101gesh",
        "Kh\u0101gish",
        "\u062e\u0627\u06af\u06cc\u0634"
    ],
    "wof:name":"Khagish",
    "wof:placetype":"locality"
},
  "geometry": {"coordinates":[62.73526,33.56282],"type":"Point"}
}