{
  "type": "Feature",
  "properties": {
    "gn:admin1_code":"39",
    "gn:admin2_code":"2601.0",
    "gn:asciiname":"Khartut",
    "gn:country_code":"AF",
    "gn:dem":1305,
    "gn:feature_class":"P",
    "gn:feature_code":"PPL",
    "gn:name":"Kh\u0101rt\u016bt",
    "gn:population":0,
    "gn:timezone":"Asia/Kabul",
    "iso:country":"AF",
    "name:ceb_x_preferred":[
        "Khart\u016bt"
    ],
    "name:fas_x_preferred":[
        "\u062e\u0631\u062a\u0648\u062a"
    ],
    "name:swe_x_preferred":[
        "Khart\u016bt"
    ],
    "name:und_x_variant":[
        "Kh\u0101rt\u016bt",
        "\u062e\u0627\u0631\u062a\u0648\u062a"
    ],
    "wof:name":"Khartut",
    "wof:placetype":"locality"
},
  "geometry": {"coordinates":[65.67778,32.53319],"type":"Point"}
}