{
  "type": "Feature",
  "properties": {
    "gn:admin1_code":"23",
    "gn:admin2_code":"2407.0",
    "gn:asciiname":"'Ata Muhammad Karez",
    "gn:country_code":"AF",
    "gn:dem":893,
    "gn:feature_class":"P",
    "gn:feature_code":"PPL",
    "gn:name":"\u2018A\u0163\u0101 Mu\u1e29ammad K\u0101r\u0113z",
    "gn:population":0,
    "gn:timezone":"Asia/Kabul",
    "iso:country":"AF",
    "name:fas_x_preferred":[
        "\u0639\u0637\u0627 \u0645\u062d\u0645\u062f \u0643\u0627\u0631\u064a\u0632"
    ],
    "name:und_x_variant":[
        "Karez-v-Ata",
        "Ata K\u0101rez",
        "K\u0101rez-i-Ata",
        "Atamukhammed-Karez",
        "\u2018At\u0101mo\u1e29amma\u1e0f K\u0101\u1e5f\u0113z",
        "\u2018A\u0163\u0101 Mo\u1e29ammad K\u0101r\u012bz",
        "\u2018A\u0163\u0101 Mu\u1e29ammad K\u0101r\u0113z",
        "\u0639\u0637\u0627 \u0645\u062d\u0645\u062f \u06a9\u0627\u0631\u06d0\u0632"
    ],
    "wof:name":"'Ata Muhammad Karez",
    "wof:placetype":"locality"
},
  "geometry": {"coordinates":[65.16419999999999,31.53377],"type":"Point"}
}