{
  "type": "Feature",
  "properties": {
    "gn:admin1_code":"18",
    "gn:admin2_code":"802.0",
    "gn:asciiname":"Adam Khel",
    "gn:country_code":"AF",
    "gn:dem":681,
    "gn:feature_class":"P",
    "gn:feature_code":"PPL",
    "gn:name":"\u0100dam Kh\u0113l",
    "gn:population":0,
    "gn:timezone":"Asia/Kabul",
    "iso:country":"AF",
    "name:fas_x_preferred":[
        "\u0622\u062f\u0645 \u062e\u064a\u0644"
    ],
    "name:rus_x_preferred":[
        "Adamkheyl\u2019"
    ],
    "name:und_x_variant":[
        "A\u1e0famkh\u0113l",
        "\u0100damkheyl",
        "\u0622\u062f\u0645 \u062e\u064a\u0644",
        "\u0100dam Kh\u0113l",
        "\u0622\u062f\u0645 \u062e\u06d0\u0644"
    ],
    "wof:name":"Adam Khel",
    "wof:placetype":"locality"
},
  "geometry": {"coordinates":[70.30753,34.42562],"type":"Point"}
}