{
  "type": "Feature",
  "properties": {
    "gn:admin1_code":"10",
    "gn:admin2_code":"2304",
    "gn:asciiname":"Qaryah-ye Kunjak",
    "gn:country_code":"AF",
    "gn:dem":1020,
    "gn:feature_class":"P",
    "gn:feature_code":"PPL",
    "gn:name":"Qaryah-ye Kunjak",
    "gn:population":0,
    "gn:timezone":"Asia/Kabul",
    "iso:country":"AF",
    "name:rus_x_preferred":[
        "Kar\u2019yayi-Kundzhak"
    ],
    "name:und_x_variant":[
        "Qa\u1e5fya-i-Kunjak",
        "Qaryah-ye Kunjak",
        "\u0642\u0631\u06cc\u0647 \u06a9\u0646\u062c\u06a9",
        "Qaryeh-ye Kunjak"
    ],
    "wof:name":"Qaryah-ye Kunjak",
    "wof:placetype":"locality"
},
  "geometry": {"coordinates":[64.79245,32.35447],"type":"Point"}
}