{
  "type": "Feature",
  "properties": {
    "gn:admin1_code":"34",
    "gn:admin2_code":"1015.0",
    "gn:asciiname":"Chingay",
    "gn:country_code":"AF",
    "gn:dem":754,
    "gn:feature_class":"P",
    "gn:feature_code":"PPL",
    "gn:name":"Ch\u012bngay",
    "gn:population":0,
    "gn:timezone":"Asia/Kabul",
    "iso:country":"AF",
    "name:fas_x_preferred":[
        "\u0686\u06cc\u0646\u06af\u06cc"
    ],
    "name:und_x_variant":[
        "\u010c\u012bngay",
        "Chingay",
        "Ch\u012bnga\u012b",
        "Ch\u012bngay"
    ],
    "wof:name":"Chingay",
    "wof:placetype":"locality"
},
  "geometry": {"coordinates":[71.00619,34.70688],"type":"Point"}
}