{
  "type": "Feature",
  "properties": {
    "gn:admin1_code":"17",
    "gn:admin2_code":"502.0",
    "gn:asciiname":"Bandokah",
    "gn:country_code":"AF",
    "gn:dem":2046,
    "gn:feature_class":"P",
    "gn:feature_code":"PPL",
    "gn:name":"Ban\u1e0f\u014dkah",
    "gn:population":0,
    "gn:timezone":"Asia/Kabul",
    "iso:country":"AF",
    "name:und_x_variant":[
        "Bandoka",
        "Band\u014dka",
        "Band\u014dkah",
        "Bandowkah",
        "Ban\u1e0f\u014dkah",
        "\u0628\u0646\u0689\u0648\u06a9\u0647"
    ],
    "wof:name":"Bandokah",
    "wof:placetype":"locality"
},
  "geometry": {"coordinates":[68.9473,33.81414],"type":"Point"}
}