{
  "type": "Feature",
  "properties": {
    "gn:admin1_code":"06",
    "gn:admin2_code":"2105",
    "gn:asciiname":"Qaryah-ye Naju",
    "gn:country_code":"AF",
    "gn:dem":923,
    "gn:feature_class":"P",
    "gn:feature_code":"PPL",
    "gn:name":"Qaryah-ye N\u0101j\u016b",
    "gn:population":0,
    "gn:timezone":"Asia/Kabul",
    "iso:country":"AF",
    "name:rus_x_preferred":[
        "Kar\u2019yayi-Nadzhu"
    ],
    "name:und_x_variant":[
        "Qa\u1e5fya-i-N\u0101j\u016b",
        "Qaryeh-ye N\u0101j\u016b",
        "Qaryah-ye N\u0101j\u016b",
        "\u0642\u0631\u06cc\u06c0 \u0646\u0627\u062c\u0648"
    ],
    "wof:name":"Qaryah-ye Naju",
    "wof:placetype":"locality"
},
  "geometry": {"coordinates":[62.7766,32.91897],"type":"Point"}
}