{
  "type": "Feature",
  "properties": {
    "gn:admin1_code":"35",
    "gn:admin2_code":"901.0",
    "gn:asciiname":"Musa Khel",
    "gn:country_code":"AF",
    "gn:dem":803,
    "gn:feature_class":"P",
    "gn:feature_code":"PPL",
    "gn:name":"M\u016bs\u00e1 Kh\u0113l",
    "gn:population":0,
    "gn:timezone":"Asia/Kabul",
    "iso:country":"AF",
    "name:rus_x_preferred":[
        "Musakheyl\u2019"
    ],
    "name:und_x_variant":[
        "M\u016bs\u00e1 Kh\u0113l",
        "M\u016bs\u00e1kheyl",
        "\u0645\u0648\u0633\u0649 \u062e\u06d0\u0644"
    ],
    "wof:name":"Musa Khel",
    "wof:placetype":"locality"
},
  "geometry": {"coordinates":[70.17376999999999,34.67918],"type":"Point"}
}