{
  "type": "Feature",
  "properties": {
    "gn:admin1_code":"08",
    "gn:admin2_code":"613",
    "gn:asciiname":"Satar Kala",
    "gn:country_code":"AF",
    "gn:dem":2216,
    "gn:feature_class":"P",
    "gn:feature_code":"PPL",
    "gn:name":"Sat\u0101r Kal\u0101",
    "gn:population":0,
    "gn:timezone":"Asia/Kabul",
    "iso:country":"AF",
    "name:fas_x_preferred":[
        "\u0633\u062a\u0627\u0631 \u0643\u0644\u0627"
    ],
    "name:rus_x_preferred":[
        "\u0421\u0430\u0442\u0430\u0440\u043a\u0430\u043b\u0430"
    ],
    "name:und_x_variant":[
        "Sat\u0101\u1e5f Kal\u0101",
        "Satarkala",
        "Satt\u0101r Kal\u0101",
        "Sat\u0101r Kal\u0101",
        "\u0633\u062a\u0627\u0631 \u06a9\u0644\u0627"
    ],
    "wof:name":"Satar Kala",
    "wof:placetype":"locality"
},
  "geometry": {"coordinates":[67.94468000000001,33.12922],"type":"Point"}
}