{
  "type": "Feature",
  "properties": {
    "gn:admin1_code":"09",
    "gn:admin2_code":"2701",
    "gn:asciiname":"Qal-e Zubayd",
    "gn:country_code":"AF",
    "gn:dem":1988,
    "gn:feature_class":"P",
    "gn:feature_code":"PPL",
    "gn:name":"Q\u0101l-e Zubayd",
    "gn:population":0,
    "gn:timezone":"Asia/Kabul",
    "iso:country":"AF",
    "name:und_x_variant":[
        "Q\u0101l-e Zubayd",
        "\u0642\u0627\u0644 \u0632\u0628\u06cc\u062f",
        "Q\u0101l-e Zobay\u1e0f"
    ],
    "wof:name":"Qal-e Zubayd",
    "wof:placetype":"locality"
},
  "geometry": {"coordinates":[65.2884,34.9145],"type":"Point"}
}