{
  "type": "Feature",
  "properties": {
    "gn:admin1_code":"26",
    "gn:admin2_code":"1205.0",
    "gn:asciiname":"Askin-e Pa'in",
    "gn:country_code":"AF",
    "gn:dem":1833,
    "gn:feature_class":"P",
    "gn:feature_code":"PPL",
    "gn:name":"Ask\u012bn-e P\u0101\u2019\u012bn",
    "gn:population":0,
    "gn:timezone":"Asia/Kabul",
    "iso:country":"AF",
    "name:und_x_variant":[
        "Ask\u012bn-e P\u0101\u2019\u012bn",
        "\u0627\u0633\u06a9\u06cc\u0646 \u067e\u0627\u0626\u06cc\u0646",
        "Ask\u012bn-e P\u0101y\u0101n"
    ],
    "wof:name":"Askin-e Pa'in",
    "wof:placetype":"locality"
},
  "geometry": {"coordinates":[69.99314,36.21318],"type":"Point"}
}