{
  "type": "Feature",
  "properties": {
    "gn:admin1_code":"07",
    "gn:admin2_code":"1805",
    "gn:asciiname":"Qal'ah-ye Bandar",
    "gn:country_code":"AF",
    "gn:dem":1663,
    "gn:feature_class":"P",
    "gn:feature_code":"PPL",
    "gn:name":"Qal\u2018ah-ye Bandar",
    "gn:population":0,
    "gn:timezone":"Asia/Kabul",
    "iso:country":"AF",
    "name:und_x_variant":[
        "Qal\u2018a-i-Ban\u1e0fa\u1e5f",
        "Qal\u2018eh-ye Bandar",
        "Qal\u2018ah-ye Bandar",
        "\u0642\u0644\u0639\u06c0 \u0628\u0646\u062f\u0631"
    ],
    "wof:name":"Qal'ah-ye Bandar",
    "wof:placetype":"locality"
},
  "geometry": {"coordinates":[64.57073000000001,35.32922],"type":"Point"}
}