{
  "type": "Feature",
  "properties": {
    "gn:admin1_code":"28",
    "gn:admin2_code":"2505.0",
    "gn:asciiname":"Khinjakak",
    "gn:country_code":"AF",
    "gn:dem":1381,
    "gn:feature_class":"P",
    "gn:feature_code":"PPL",
    "gn:name":"Khinjakak",
    "gn:population":0,
    "gn:timezone":"Asia/Kabul",
    "iso:country":"AF",
    "name:und_x_variant":[
        "Khindzhakak",
        "Khinjakak",
        "\u062e\u0646\u062c\u06a9\u06a9",
        "Khenjakak"
    ],
    "wof:name":"Khinjakak",
    "wof:placetype":"locality"
},
  "geometry": {"coordinates":[66.42708,32.19167],"type":"Point"}
}