{
  "type": "Feature",
  "properties": {
    "gn:admin1_code":"05",
    "gn:admin2_code":"2801",
    "gn:asciiname":"Siyah Khartoghay",
    "gn:country_code":"AF",
    "gn:dem":2631,
    "gn:feature_class":"P",
    "gn:feature_code":"PPL",
    "gn:name":"Siy\u0101h Kh\u0101r\u0163\u014dgh\u0101y",
    "gn:population":0,
    "gn:timezone":"Asia/Kabul",
    "iso:country":"AF",
    "name:und_x_variant":[
        "Seyah Kh\u0101\u1e5f\u1e6f\u014dghay",
        "Siakhkhartogay",
        "S\u012b\u0101h Kh\u0101r\u0163\u014dgh\u0101y",
        "S\u012b\u0101hkh\u0101r\u0163owq\u012b",
        "\u0633\u06cc\u0627\u0647 \u062e\u0627\u0631\u0637\u0648\u063a\u06cc",
        "Siy\u0101h Kh\u0101r\u0163\u014dgh\u0101y"
    ],
    "wof:name":"Siyah Khartoghay",
    "wof:placetype":"locality"
},
  "geometry": {"coordinates":[67.91091,34.756],"type":"Point"}
}