{
  "type": "Feature",
  "properties": {
    "gn:admin1_code":"13",
    "gn:admin2_code":"112.0",
    "gn:asciiname":"Sar-e Jigdalik",
    "gn:country_code":"AF",
    "gn:dem":1701,
    "gn:feature_class":"P",
    "gn:feature_code":"PPL",
    "gn:name":"Sar-e Jigdalik",
    "gn:population":0,
    "gn:timezone":"Asia/Kabul",
    "iso:country":"AF",
    "name:fas_x_preferred":[
        "\u0633\u0631\u0654\u0654 \u062c\u06af\u062f\u0644\u0643"
    ],
    "name:und_x_variant":[
        "Sari-Dzhigdalik",
        "Sar-e Jigdalak",
        "Sar-e Jegdalek",
        "Sar-e Jigdalik",
        "\u0633\u0631 \u062c\u06af\u062f\u0644\u06a9"
    ],
    "wof:name":"Sar-e Jigdalik",
    "wof:placetype":"locality"
},
  "geometry": {"coordinates":[69.74677,34.41835],"type":"Point"}
}