{
  "type": "Feature",
  "properties": {
    "gn:admin1_code":"41",
    "gn:admin2_code":"3409",
    "gn:asciiname":"Qafzar",
    "gn:country_code":"AF",
    "gn:dem":3107,
    "gn:feature_class":"P",
    "gn:feature_code":"PPL",
    "gn:name":"Qafz\u0101r",
    "gn:population":0,
    "gn:timezone":"Asia/Kabul",
    "iso:country":"AF",
    "name:und_x_variant":[
        "Qafz\u0101r",
        "\u0642\u0641\u0632\u0627\u0631",
        "Qafz\u0101\u1e5f"
    ],
    "wof:name":"Qafzar",
    "wof:placetype":"locality"
},
  "geometry": {"coordinates":[66.4278,33.94132],"type":"Point"}
}