{
  "type": "Feature",
  "properties": {
    "gn:country":"AF",
    "gn:fcode":"PPLA2",
    "gn:population":3307,
    "iso:country":"AF",
    "name:ast_x_preferred":[
        "Dahaneh-ye Gawri"
    ],
    "name:ceb_x_preferred":[
        "\u1e28uk\u016bmat\u012b Dahanah-ye Gh\u014dr\u012b"
    ],
    "name:eng_x_preferred":[
        "Dahaneh-ye Ghowri"
    ],
    "name:fas_x_preferred":[
        "\u062f\u0647\u0646\u0647 \u063a\u0648\u0631\u06cc"
    ],
    "name:nld_x_preferred":[
        "Dahaneh-ye Ghowri"
    ],
    "name:spa_x_preferred":[
        "Dahaneh-ye \u0120awri"
    ],
    "name:swe_x_preferred":[
        "\u1e28uk\u016bmat\u012b Dahanah-ye Gh\u014dr\u012b"
    ],
    "name:und_x_variant":[
        "Hok\u016bmat\u012b \u1e0eahana-i-Gh\u014d\u1e5fi Dahana"
    ],
    "qs:name":"\u1e28uk\u016bmat\u012b Dahanah-ye Gh\u014dr\u012b",
    "qs:photos_9r":0,
    "qs:photos_sr":0,
    "qs:pop_sr":"4",
    "wof:name":"\u1e28uk\u016bmat\u012b Dahanah-ye Gh\u014dr\u012b",
    "wof:placetype":"locality",
    "wof:population":3307
},
  "geometry": {"coordinates":[68.48869000000001,35.90617],"type":"Point"}
}