{
  "type": "Feature",
  "properties": {
    "gn:admin1_code":"34",
    "gn:admin2_code":"1012.0",
    "gn:asciiname":"Amrey",
    "gn:country_code":"AF",
    "gn:dem":1138,
    "gn:feature_class":"P",
    "gn:feature_code":"PPL",
    "gn:name":"Amr\u00eay",
    "gn:population":0,
    "gn:timezone":"Asia/Kabul",
    "iso:country":"AF",
    "name:fas_x_preferred":[
        "\u0627\u0645\u0631\u06cc"
    ],
    "name:und_x_variant":[
        "Amray",
        "Am\u1e5fey",
        "Amr\u00eay",
        "\u0627\u0645\u0631\u06cd"
    ],
    "wof:name":"Amrey",
    "wof:placetype":"locality"
},
  "geometry": {"coordinates":[70.86537,34.75151],"type":"Point"}
}