{
  "type": "Feature",
  "properties": {
    "gn:admin1_code":"02",
    "gn:admin2_code":"1903",
    "gn:asciiname":"Tahkushak",
    "gn:country_code":"AF",
    "gn:dem":1966,
    "gn:feature_class":"P",
    "gn:feature_code":"PPL",
    "gn:name":"Tahkushak",
    "gn:population":0,
    "gn:timezone":"Asia/Kabul",
    "iso:country":"AF",
    "name:und_x_variant":[
        "Seh K\u016bshk",
        "Tahko\u0161ak",
        "Sehg\u014ds\u0304ak",
        "Takhkushak",
        "Tahkushak",
        "\u062a\u0647\u06a9\u0634\u06a9",
        "Tahkoshak"
    ],
    "wof:name":"Tahkushak",
    "wof:placetype":"locality"
},
  "geometry": {"coordinates":[63.7644,34.65791],"type":"Point"}
}