{
  "type": "Feature",
  "properties": {
    "gn:admin1_code":"10",
    "gn:admin2_code":"2305.0",
    "gn:asciiname":"Bashling",
    "gn:country_code":"AF",
    "gn:dem":1429,
    "gn:feature_class":"P",
    "gn:feature_code":"PPL",
    "gn:name":"B\u0101shling",
    "gn:population":0,
    "gn:timezone":"Asia/Kabul",
    "iso:country":"AF",
    "name:und_x_variant":[
        "B\u0101\u0161leng",
        "Bashling",
        "B\u0101shling",
        "\u0628\u0627\u0634\u0644\u0646\u06af",
        "B\u0101shleng"
    ],
    "wof:name":"Bashling",
    "wof:placetype":"locality"
},
  "geometry": {"coordinates":[64.88995,32.87518],"type":"Point"}
}