{
  "type": "Feature",
  "properties": {
    "gn:admin1_code":"39",
    "gn:admin2_code":"2605",
    "gn:asciiname":"Lublan",
    "gn:country_code":"AF",
    "gn:dem":1092,
    "gn:feature_class":"P",
    "gn:feature_code":"PPL",
    "gn:name":"Lubl\u0101n",
    "gn:population":0,
    "gn:timezone":"Asia/Kabul",
    "iso:country":"AF",
    "name:und_x_variant":[
        "Lubl\u0101n",
        "\u0644\u0628\u0644\u0627\u0646",
        "Labl\u0101n",
        "Lablan"
    ],
    "wof:name":"Lublan",
    "wof:placetype":"locality"
},
  "geometry": {"coordinates":[65.50020000000001,32.63606],"type":"Point"}
}