{
  "type": "Feature",
  "properties": {
    "gn:admin1_code":"01",
    "gn:admin2_code":"1110.0",
    "gn:asciiname":"Waj Kon",
    "gn:country_code":"AF",
    "gn:dem":2571,
    "gn:feature_class":"P",
    "gn:feature_code":"PPL",
    "gn:name":"W\u0101j K\u014dn",
    "gn:population":0,
    "gn:timezone":"Asia/Kabul",
    "iso:country":"AF",
    "name:und_x_variant":[
        "W\u0101j Kown",
        "W\u0101j K\u014dn",
        "\u0648\u0627\u062c \u06a9\u0648\u0646"
    ],
    "wof:name":"Waj Kon",
    "wof:placetype":"locality"
},
  "geometry": {"coordinates":[70.80571999999999,38.28289],"type":"Point"}
}