{
  "type": "Feature",
  "properties": {
    "gn:admin1_code":"08",
    "gn:admin2_code":"607",
    "gn:asciiname":"Ghikhtu",
    "gn:country_code":"AF",
    "gn:dem":2906,
    "gn:feature_class":"P",
    "gn:feature_code":"PPL",
    "gn:name":"Gh\u012bkht\u016b",
    "gn:population":0,
    "gn:timezone":"Asia/Kabul",
    "iso:country":"AF",
    "name:rus_x_preferred":[
        "\u0413\u0438\u0444\u0442\u0443"
    ],
    "name:und_x_variant":[
        "Giftu",
        "Gh\u012bkhtu",
        "Gh\u012bkht\u016b",
        "\u063a\u06cc\u062e\u062a\u0648"
    ],
    "wof:name":"Ghikhtu",
    "wof:placetype":"locality"
},
  "geometry": {"coordinates":[67.75906999999999,33.27104],"type":"Point"}
}