{
  "type": "Feature",
  "properties": {
    "gn:admin1_code":"13",
    "gn:admin2_code":"115.0",
    "gn:asciiname":"Nasir Khel",
    "gn:country_code":"AF",
    "gn:dem":1869,
    "gn:feature_class":"P",
    "gn:feature_code":"PPL",
    "gn:name":"N\u0101\u015fir Kh\u0113l",
    "gn:population":0,
    "gn:timezone":"Asia/Kabul",
    "iso:country":"AF",
    "name:fas_x_preferred":[
        "\u0646\u0627\u0635\u0631 \u062e\u064a\u0644"
    ],
    "name:rus_x_preferred":[
        "Nasirkheyl\u2019"
    ],
    "name:und_x_variant":[
        "N\u0101\u015fe\u1e5fkh\u0113l",
        "N\u0101\u015ferkheyl",
        "\u0646\u0627\u0635\u0631 \u062e\u06d0\u0644",
        "N\u0101\u015fir Kh\u0113l"
    ],
    "wof:name":"Nasir Khel",
    "wof:placetype":"locality"
},
  "geometry": {"coordinates":[69.06616,34.77491],"type":"Point"}
}