{
  "type": "Feature",
  "properties": {
    "gn:admin1_code":"01",
    "gn:admin2_code":"1128",
    "gn:asciiname":"Yasif",
    "gn:country_code":"AF",
    "gn:dem":1327,
    "gn:feature_class":"P",
    "gn:feature_code":"PPL",
    "gn:name":"Y\u0101s\u012bf",
    "gn:population":0,
    "gn:timezone":"Asia/Kabul",
    "iso:country":"AF",
    "name:und_x_variant":[
        "Yasiv",
        "Y\u0101s\u012bf",
        "\u06cc\u0627\u0633\u06cc\u0641"
    ],
    "name:urd_x_preferred":[
        "\u06cc\u0635\u0641"
    ],
    "wof:name":"Yasif",
    "wof:placetype":"locality"
},
  "geometry": {"coordinates":[70.40827,37.5788],"type":"Point"}
}