{
  "type": "Feature",
  "properties": {
    "gn:admin1_code":"38",
    "gn:admin2_code":"3004.0",
    "gn:asciiname":"Awposh",
    "gn:country_code":"AF",
    "gn:dem":1869,
    "gn:feature_class":"P",
    "gn:feature_code":"PPL",
    "gn:name":"Awp\u014dsh",
    "gn:population":0,
    "gn:timezone":"Asia/Kabul",
    "iso:country":"AF",
    "name:und_x_variant":[
        "Aupash",
        "Awp\u014dch",
        "Awpo\u0161",
        "Awp\u016bch",
        "Awp\u014dsh",
        "\u0627\u0648\u067e\u0648\u0634"
    ],
    "wof:name":"Awposh",
    "wof:placetype":"locality"
},
  "geometry": {"coordinates":[70.18077,35.17968],"type":"Point"}
}