{
  "type": "Feature",
  "properties": {
    "gn:admin1_code":"5",
    "gn:admin2_code":"2804.0",
    "gn:asciiname":"Dahan-e Espi Darak",
    "gn:country_code":"AF",
    "gn:dem":2146,
    "gn:feature_class":"P",
    "gn:feature_code":"PPL",
    "gn:name":"Dah\u0101n-e Esp\u012b Darak",
    "gn:population":0,
    "gn:timezone":"Asia/Kabul",
    "iso:country":"AF",
    "name:und_x_variant":[
        "Dah\u0101n-e Esp\u012b Darak",
        "\u062f\u0647\u0627\u0646 \u0627\u0633\u067e\u06cc\u062f\u0631\u06a9",
        "Dahan-e Espi\u1e0fa\u1e5fak"
    ],
    "wof:name":"Dahan-e Espi Darak",
    "wof:placetype":"locality"
},
  "geometry": {"coordinates":[66.40935999999999,35.08789],"type":"Point"}
}