{
  "type": "Feature",
  "properties": {
    "gn:admin1_code":"23",
    "gn:admin2_code":"2407",
    "gn:asciiname":"Mya Karez",
    "gn:country_code":"AF",
    "gn:dem":895,
    "gn:feature_class":"P",
    "gn:feature_code":"PPL",
    "gn:name":"My\u0101 K\u0101r\u0113z",
    "gn:population":0,
    "gn:timezone":"Asia/Kabul",
    "iso:country":"AF",
    "name:fas_x_preferred":[
        "\u0645\u064a\u0627 \u0643\u0631\u064a\u0632"
    ],
    "name:und_x_variant":[
        "My\u0101 K\u0101\u1e5f\u0113z",
        "Miakarez",
        "My\u0101 K\u0101r\u0113z",
        "\u0645\u06cc\u0627 \u06a9\u0627\u0631\u06d0\u0632",
        "M\u012b\u0101 Kar\u012bz",
        "Miy\u0101 K\u0101r\u0113z"
    ],
    "wof:name":"Mya Karez",
    "wof:placetype":"locality"
},
  "geometry": {"coordinates":[65.19504000000001,31.5237],"type":"Point"}
}