{
  "type": "Feature",
  "properties": {
    "gn:admin1_code":"06",
    "gn:admin2_code":"2109.0",
    "gn:asciiname":"Kunaw-e Sokhtah",
    "gn:country_code":"AF",
    "gn:dem":541,
    "gn:feature_class":"P",
    "gn:feature_code":"PPL",
    "gn:name":"K\u016bnaw-e S\u014dkhtah",
    "gn:population":0,
    "gn:timezone":"Asia/Kabul",
    "iso:country":"AF",
    "name:fas_x_preferred":[
        "K\u016bnaw-e S\u014dkhtah"
    ],
    "name:fas_x_variant":[
        "\u06a9\u0648\u0646\u0648 \u0633\u0648\u062e\u062a\u0647"
    ],
    "name:und_x_variant":[
        "K\u014dnawe S\u014dkhta",
        "K\u016bn\u0101b-e S\u016bkhteh"
    ],
    "wof:name":"Kunaw-e Sokhtah",
    "wof:placetype":"locality"
},
  "geometry": {"coordinates":[61.56745,31.84701],"type":"Point"}
}