{
  "type": "Feature",
  "properties": {
    "gn:admin1_code":"11",
    "gn:admin2_code":"2001.0",
    "gn:asciiname":"Bazirgun",
    "gn:country_code":"AF",
    "gn:dem":881,
    "gn:feature_class":"P",
    "gn:feature_code":"PPL",
    "gn:name":"B\u0101zirg\u016bn",
    "gn:population":0,
    "gn:timezone":"Asia/Kabul",
    "iso:country":"AF",
    "name:aze_x_preferred":[
        "Baz\u0259rgan"
    ],
    "name:fas_x_preferred":[
        "\u0628\u0627\u0632\u0631\u06af\u0627\u0646"
    ],
    "name:spa_x_preferred":[
        "Bazargan"
    ],
    "name:und_x_variant":[
        "B\u0101zerg\u016bn",
        "Bazirgun",
        "B\u0101zarg\u0101n",
        "B\u0101zirg\u016bn",
        "\u0628\u0627\u0632\u0631\u06af\u0648\u0646"
    ],
    "wof:name":"Bazirgun",
    "wof:placetype":"locality"
},
  "geometry": {"coordinates":[62.00572,34.35387],"type":"Point"}
}