{
  "type": "Feature",
  "properties": {
    "gn:admin1_code":"23",
    "gn:admin2_code":"2403.0",
    "gn:asciiname":"Boyinah",
    "gn:country_code":"AF",
    "gn:dem":1151,
    "gn:feature_class":"P",
    "gn:feature_code":"PPL",
    "gn:name":"B\u014dyinah",
    "gn:population":0,
    "gn:timezone":"Asia/Kabul",
    "iso:country":"AF",
    "name:und_x_variant":[
        "Boyyena",
        "B\u014dyena",
        "\u0628\u0648\u06cc\u0646\u0647",
        "B\u016byenah",
        "B\u014dyinah"
    ],
    "wof:name":"Boyinah",
    "wof:placetype":"locality"
},
  "geometry": {"coordinates":[66.04201999999999,31.95302],"type":"Point"}
}