{
  "type": "Feature",
  "properties": {
    "gn:admin1_code":"11",
    "gn:admin2_code":"2015",
    "gn:asciiname":"Saybdalak",
    "gn:country_code":"AF",
    "gn:dem":1813,
    "gn:feature_class":"P",
    "gn:feature_code":"PPL",
    "gn:name":"Saybdalak",
    "gn:population":0,
    "gn:timezone":"Asia/Kabul",
    "iso:country":"AF",
    "name:und_x_variant":[
        "S\u0113bdalak",
        "S\u012bbdalak",
        "Saybdalak",
        "\u0633\u06cc\u0628\u062f\u0644\u06a9"
    ],
    "wof:name":"Saybdalak",
    "wof:placetype":"locality"
},
  "geometry": {"coordinates":[63.68781,34.3114],"type":"Point"}
}