{
  "type": "Feature",
  "properties": {
    "gn:admin1_code":"11",
    "gn:admin2_code":"2003.0",
    "gn:asciiname":"Chakah",
    "gn:country_code":"AF",
    "gn:dem":893,
    "gn:feature_class":"P",
    "gn:feature_code":"PPL",
    "gn:name":"Chakah",
    "gn:population":0,
    "gn:timezone":"Asia/Kabul",
    "iso:country":"AF",
    "name:und_x_variant":[
        "\u010caka",
        "Chaka",
        "Chakah",
        "\u0686\u06a9\u0647"
    ],
    "wof:name":"Chakah",
    "wof:placetype":"locality"
},
  "geometry": {"coordinates":[62.00053000000001,34.28899000000001],"type":"Point"}
}