{
  "type": "Feature",
  "properties": {
    "gn:admin1_code":"8",
    "gn:admin2_code":"606.0",
    "gn:asciiname":"Mazar",
    "gn:country_code":"AF",
    "gn:dem":2975,
    "gn:feature_class":"P",
    "gn:feature_code":"PPL",
    "gn:name":"Maz\u0101r",
    "gn:population":0,
    "gn:timezone":"Asia/Kabul",
    "iso:country":"AF",
    "name:und_x_variant":[
        "Maz\u0101r",
        "\u0645\u0632\u0627\u0631"
    ],
    "wof:name":"Mazar",
    "wof:placetype":"locality"
},
  "geometry": {"coordinates":[67.15319000000001,33.27164],"type":"Point"}
}