{
  "type": "Feature",
  "properties": {
    "gn:admin1_code":"41",
    "gn:admin2_code":"3407.0",
    "gn:asciiname":"Mir Bay",
    "gn:country_code":"AF",
    "gn:dem":2814,
    "gn:feature_class":"P",
    "gn:feature_code":"PPL",
    "gn:name":"M\u012br B\u0101y",
    "gn:population":0,
    "gn:timezone":"Asia/Kabul",
    "iso:country":"AF",
    "name:und_x_variant":[
        "M\u012br B\u0101y",
        "M\u012brb\u0101y",
        "\u0645\u064a\u0631 \u0628\u0627\u06cc"
    ],
    "wof:name":"Mir Bay",
    "wof:placetype":"locality"
},
  "geometry": {"coordinates":[66.6806,33.9025],"type":"Point"}
}