{
  "type": "Feature",
  "properties": {
    "gn:admin1_code":"28",
    "gn:admin2_code":"2510",
    "gn:asciiname":"Jabar Khel",
    "gn:country_code":"AF",
    "gn:dem":2640,
    "gn:feature_class":"P",
    "gn:feature_code":"PPL",
    "gn:name":"Jab\u0101r Kh\u0113l",
    "gn:population":0,
    "gn:timezone":"Asia/Kabul",
    "iso:country":"AF",
    "name:fas_x_preferred":[
        "\u062c\u0628\u0627\u0631 \u062e\u064a\u0644"
    ],
    "name:rus_x_preferred":[
        "Dzhabbarkheyl\u2019"
    ],
    "name:und_x_variant":[
        "Jabb\u0101\u1e5fkh\u0113l",
        "Jab\u0101r Kh\u0113l",
        "\u062c\u0628\u0627\u0631 \u062e\u06d0\u0644",
        "Jabb\u0101r Kheyl"
    ],
    "wof:name":"Jabar Khel",
    "wof:placetype":"locality"
},
  "geometry": {"coordinates":[66.99533000000001,32.74899],"type":"Point"}
}