{
  "type": "Feature",
  "properties": {
    "gn:admin1_code":"11",
    "gn:admin2_code":"2005",
    "gn:asciiname":"Mahalah",
    "gn:country_code":"AF",
    "gn:dem":1088,
    "gn:feature_class":"P",
    "gn:feature_code":"PPL",
    "gn:name":"Ma\u1e29alah",
    "gn:population":0,
    "gn:timezone":"Asia/Kabul",
    "iso:country":"AF",
    "name:und_x_variant":[
        "Ma\u1e29alla",
        "Makhalla",
        "Ma\u1e29alah",
        "\u0645\u062d\u0644\u0647",
        "Ma\u1e29alleh"
    ],
    "wof:name":"Mahalah",
    "wof:placetype":"locality"
},
  "geometry": {"coordinates":[62.43969,34.39071],"type":"Point"}
}