{
  "type": "Feature",
  "properties": {
    "gn:admin1_code":"18",
    "gn:admin2_code":"806.0",
    "gn:asciiname":"Aghzo Kelay",
    "gn:country_code":"AF",
    "gn:dem":831,
    "gn:feature_class":"P",
    "gn:feature_code":"PPL",
    "gn:name":"Aghz\u014d K\u00ealay",
    "gn:population":0,
    "gn:timezone":"Asia/Kabul",
    "iso:country":"AF",
    "name:fas_x_preferred":[
        "\u0627\u063a\u0632\u0648 \u0643\u0644\u06cc"
    ],
    "name:und_x_variant":[
        "Agzukalay",
        "Aghzo Kalay",
        "Aghz\u014d K\u00ealay",
        "\u0627\u063a\u0632\u0648 \u06a9\u0644\u06cc"
    ],
    "wof:name":"Aghzo Kelay",
    "wof:placetype":"locality"
},
  "geometry": {"coordinates":[70.40814,34.30071],"type":"Point"}
}