{
  "type": "Feature",
  "properties": {
    "gn:admin1_code":"8",
    "gn:admin2_code":"604.0",
    "gn:asciiname":"Gulchindah",
    "gn:country_code":"AF",
    "gn:dem":3110,
    "gn:feature_class":"P",
    "gn:feature_code":"PPL",
    "gn:name":"Gulch\u012bndah",
    "gn:population":0,
    "gn:timezone":"Asia/Kabul",
    "iso:country":"AF",
    "name:und_x_variant":[
        "Gulc\u012bn\u1e0fa",
        "Golch\u012bndeh",
        "Gulch\u012bndah",
        "\u06af\u0644\u0686\u06cc\u0646\u062f\u0647"
    ],
    "wof:name":"Gulchindah",
    "wof:placetype":"locality"
},
  "geometry": {"coordinates":[67.31798000000001,33.94752],"type":"Point"}
}