{
  "type": "Feature",
  "properties": {
    "gn:admin1_code":"08",
    "gn:admin2_code":"601",
    "gn:asciiname":"Qachqala",
    "gn:country_code":"AF",
    "gn:dem":2177,
    "gn:feature_class":"P",
    "gn:feature_code":"PPL",
    "gn:name":"Qachqal\u0101",
    "gn:population":0,
    "gn:timezone":"Asia/Kabul",
    "iso:country":"AF",
    "name:fas_x_preferred":[
        "\u0642\u0686\u0642\u0644\u0627"
    ],
    "name:und_x_variant":[
        "Kachkala",
        "Qa\u010dqal\u0101",
        "Qachqal\u0101"
    ],
    "wof:name":"Qachqala",
    "wof:placetype":"locality"
},
  "geometry": {"coordinates":[68.38336,33.47356],"type":"Point"}
}