{
  "type": "Feature",
  "properties": {
    "gn:admin1_code":"10",
    "gn:admin2_code":"2302",
    "gn:asciiname":"Husaini Kala",
    "gn:country_code":"AF",
    "gn:dem":804,
    "gn:feature_class":"P",
    "gn:feature_code":"PPL",
    "gn:name":"\u1e28usa\u012bn\u012b Kal\u0101",
    "gn:population":0,
    "gn:timezone":"Asia/Kabul",
    "iso:country":"AF",
    "name:und_x_variant":[
        "Khuseynikala",
        "\u1e28osayni Kal\u0101",
        "\u1e28usa\u012bn\u012b Kal\u0101",
        "\u062d\u0633\u06cc\u0646\u06cc \u06a9\u0644\u0627",
        "\u1e28oseyn\u012b Kal\u0101"
    ],
    "wof:name":"Husaini Kala",
    "wof:placetype":"locality"
},
  "geometry": {"coordinates":[64.53363,31.66447],"type":"Point"}
}