{
  "type": "Feature",
  "properties": {
    "gn:admin1_code":"27",
    "gn:admin2_code":"403.0",
    "gn:asciiname":"Qambar 'Ali",
    "gn:country_code":"AF",
    "gn:dem":3116,
    "gn:feature_class":"P",
    "gn:feature_code":"PPL",
    "gn:name":"Qambar \u2018Al\u012b",
    "gn:population":0,
    "gn:timezone":"Asia/Kabul",
    "iso:country":"AF",
    "name:und_x_variant":[
        "Kambarali",
        "Qamba\u1e5f\u2019ali",
        "Qanbar\u2018al\u012b",
        "Qambar \u2018Al\u012b",
        "\u0642\u0645\u0628\u0631 \u0639\u0644\u06cc"
    ],
    "wof:name":"Qambar 'Ali",
    "wof:placetype":"locality"
},
  "geometry": {"coordinates":[68.18821,34.52107],"type":"Point"}
}