{
  "type": "Feature",
  "properties": {
    "gn:admin1_code":"38",
    "gn:admin2_code":"3004",
    "gn:asciiname":"Shargin",
    "gn:country_code":"AF",
    "gn:dem":2342,
    "gn:feature_class":"P",
    "gn:feature_code":"PPL",
    "gn:name":"Sharg\u012bn",
    "gn:population":0,
    "gn:timezone":"Asia/Kabul",
    "iso:country":"AF",
    "name:und_x_variant":[
        "\u0160arg\u012bn",
        "\u0634\u0631\u06af\u06cc\u0646",
        "Sharg\u012bn"
    ],
    "wof:name":"Shargin",
    "wof:placetype":"locality"
},
  "geometry": {"coordinates":[70.27252,35.38202000000001],"type":"Point"}
}