{
  "type": "Feature",
  "properties": {
    "gn:admin1_code":"27",
    "gn:admin2_code":"404.0",
    "gn:asciiname":"Shirum",
    "gn:country_code":"AF",
    "gn:dem":2696,
    "gn:feature_class":"P",
    "gn:feature_code":"PPL",
    "gn:name":"Shir\u016bm",
    "gn:population":0,
    "gn:timezone":"Asia/Kabul",
    "iso:country":"AF",
    "name:und_x_variant":[
        "\u0160ir\u016bm",
        "Shirum",
        "Sh\u012br\u014dm",
        "Sh\u012browm",
        "Shir\u016bm",
        "\u0634\u0631\u0648\u0645"
    ],
    "wof:name":"Shirum",
    "wof:placetype":"locality"
},
  "geometry": {"coordinates":[67.81078000000001,34.42464],"type":"Point"}
}