{
  "type": "Feature",
  "properties": {
    "gn:admin1_code":"03",
    "gn:admin2_code":"1301.0",
    "gn:asciiname":"Khugiyani",
    "gn:country_code":"AF",
    "gn:dem":609,
    "gn:feature_class":"P",
    "gn:feature_code":"PPL",
    "gn:name":"Kh\u016bgiy\u0101n\u012b",
    "gn:population":0,
    "gn:timezone":"Asia/Kabul",
    "iso:country":"AF",
    "name:und_x_variant":[
        "Khugiani",
        "Kh\u016bgy\u0101\u1e49i",
        "Kh\u016bgiy\u0101n\u012b",
        "\u062e\u0648\u06af\u06cc\u0627\u0646\u06cc"
    ],
    "wof:name":"Khugiyani",
    "wof:placetype":"locality"
},
  "geometry": {"coordinates":[68.67461,35.99024],"type":"Point"}
}