{
  "type": "Feature",
  "properties": {
    "gn:admin1_code":"28",
    "gn:admin2_code":"2502",
    "gn:asciiname":"Jum'ah Khan Kelay",
    "gn:country_code":"AF",
    "gn:dem":2217,
    "gn:feature_class":"P",
    "gn:feature_code":"PPL",
    "gn:name":"Jum\u2018ah Kh\u0101n K\u00ealay",
    "gn:population":0,
    "gn:timezone":"Asia/Kabul",
    "iso:country":"AF",
    "name:und_x_variant":[
        "Dzhumakhankalay",
        "Jum\u2018a Kh\u0101n Kalay",
        "Jum\u2018ah Kh\u0101n K\u00ealay",
        "\u062c\u0645\u0639\u0647 \u062e\u0627\u0646 \u06a9\u0644\u06cc",
        "Jom\u2018eh Kh\u0101n Kalay"
    ],
    "wof:name":"Jum'ah Khan Kelay",
    "wof:placetype":"locality"
},
  "geometry": {"coordinates":[67.54404,32.41551],"type":"Point"}
}