{
  "type": "Feature",
  "properties": {
    "gn:admin1_code":"08",
    "gn:admin2_code":"614",
    "gn:asciiname":"Loy-Shar",
    "gn:country_code":"AF",
    "gn:dem":2089,
    "gn:feature_class":"P",
    "gn:feature_code":"PPL",
    "gn:name":"Loy-Shar",
    "gn:population":0,
    "gn:timezone":"Asia/Kabul",
    "iso:country":"AF",
    "name:und_x_variant":[
        "Loy \u0160\u0101r",
        "Loy-Shar",
        "Lowy S\u0332h\u0332\u0101r",
        "L\u014dy S\u0332h\u0332\u0101r",
        "\u0644\u0648\u06cc \u069a\u0627\u0631"
    ],
    "wof:name":"Loy-Shar",
    "wof:placetype":"locality"
},
  "geometry": {"coordinates":[68.58278,33.27472],"type":"Point"}
}