{
  "type": "Feature",
  "properties": {
    "gn:admin1_code":"10",
    "gn:admin2_code":"2306",
    "gn:asciiname":"Qaryah-ye Kuli Siyah",
    "gn:country_code":"AF",
    "gn:dem":1686,
    "gn:feature_class":"P",
    "gn:feature_code":"PPL",
    "gn:name":"Qaryah-ye Kul\u012b Siy\u0101h",
    "gn:population":0,
    "gn:timezone":"Asia/Kabul",
    "iso:country":"AF",
    "name:rus_x_preferred":[
        "Kar\u2019yayi-Kulisiakh"
    ],
    "name:und_x_variant":[
        "Kowl-e S\u012b\u0101h",
        "Qa\u1e5fya-i-Kol\u012b Sy\u0101h",
        "K\u014dlisy\u0101h",
        "Kol\u012b S\u012b\u0101h",
        "Kalay S\u012b\u0101h",
        "Qaryah-ye Kul\u012b S\u012b\u0101h",
        "\u0642\u0631\u06cc\u0647 \u06a9\u0644\u06cc \u0633\u06cc\u0627\u0647",
        "Qary\u0101-ye Kol-e S\u012b\u0101h",
        "Qaryah-ye Kul\u012b Siy\u0101h"
    ],
    "wof:name":"Qaryah-ye Kuli Siyah",
    "wof:placetype":"locality"
},
  "geometry": {"coordinates":[64.21287,32.47131],"type":"Point"}
}