{
  "type": "Feature",
  "properties": {
    "gn:admin1_code":"37",
    "gn:admin2_code":"3201.0",
    "gn:asciiname":"Ali Khel",
    "gn:country_code":"AF",
    "gn:dem":1076,
    "gn:feature_class":"P",
    "gn:feature_code":"PPL",
    "gn:name":"Ali Khel",
    "gn:population":0,
    "gn:timezone":"Asia/Kabul",
    "iso:country":"AF",
    "name:fas_x_preferred":[
        "\u0639\u0644\u06cc \u062e\u064a\u0644"
    ],
    "wof:name":"Ali Khel",
    "wof:placetype":"locality"
},
  "geometry": {"coordinates":[70.03583,33.38361],"type":"Point"}
}