{
  "type": "Feature",
  "properties": {
    "gn:admin1_code":"27",
    "gn:admin2_code":"404",
    "gn:asciiname":"Ghargharah",
    "gn:country_code":"AF",
    "gn:dem":3065,
    "gn:feature_class":"P",
    "gn:feature_code":"PPL",
    "gn:name":"Ghargharah",
    "gn:population":0,
    "gn:timezone":"Asia/Kabul",
    "iso:country":"AF",
    "name:und_x_variant":[
        "Gargara",
        "Gharghareh",
        "Gha\u1e5fgha\u1e5fa",
        "Ghargharreh",
        "Ghargharah",
        "\u063a\u0631\u063a\u0631\u0647"
    ],
    "wof:name":"Ghargharah",
    "wof:placetype":"locality"
},
  "geometry": {"coordinates":[67.51902,34.59734],"type":"Point"}
}