{
  "type": "Feature",
  "properties": {
    "gn:admin1_code":"09",
    "gn:admin2_code":"2709",
    "gn:asciiname":"Olamghol",
    "gn:country_code":"AF",
    "gn:dem":2698,
    "gn:feature_class":"P",
    "gn:feature_code":"PPL",
    "gn:name":"\u014clamgh\u014dl",
    "gn:population":0,
    "gn:timezone":"Asia/Kabul",
    "iso:country":"AF",
    "name:und_x_variant":[
        "\u014clamgh\u014dl",
        "\u016alamgh\u016bl",
        "\u0627\u0648\u0644\u0645 \u063a\u0648\u0644"
    ],
    "wof:name":"Olamghol",
    "wof:placetype":"locality"
},
  "geometry": {"coordinates":[65.94006,34.53198],"type":"Point"}
}