{
  "type": "Feature",
  "properties": {
    "gn:admin1_code":"30",
    "gn:admin2_code":"1607",
    "gn:asciiname":"Labak",
    "gn:country_code":"AF",
    "gn:dem":322,
    "gn:feature_class":"P",
    "gn:feature_code":"PPL",
    "gn:name":"Labak",
    "gn:population":0,
    "gn:timezone":"Asia/Kabul",
    "iso:country":"AF",
    "name:fas_x_preferred":[
        "\u0644\u0628\u06a9"
    ],
    "name:und_x_variant":[
        "\u0644\u0628\u06a9"
    ],
    "name:urd_x_preferred":[
        "\u0644\u0627\u0628\u0627\u06a9"
    ],
    "wof:name":"Labak",
    "wof:placetype":"locality"
},
  "geometry": {"coordinates":[66.5804,36.78907],"type":"Point"}
}