{
  "type": "Feature",
  "properties": {
    "gn:admin1_code":"33",
    "gn:admin2_code":"3107",
    "gn:asciiname":"Koran",
    "gn:country_code":"AF",
    "gn:dem":1230,
    "gn:feature_class":"P",
    "gn:feature_code":"PPL",
    "gn:name":"K\u014dr\u0101n",
    "gn:population":0,
    "gn:timezone":"Asia/Kabul",
    "iso:country":"AF",
    "name:und_x_variant":[
        "K\u014d\u1e5f\u0101n",
        "Kow\u1e5f\u0101n",
        "K\u014dr\u0101n",
        "\u06a9\u0648\u0631\u0627\u0646"
    ],
    "wof:name":"Koran",
    "wof:placetype":"locality"
},
  "geometry": {"coordinates":[66.51996,35.92205999999999],"type":"Point"}
}