{
  "type": "Feature",
  "properties": {
    "gn:admin1_code":"29",
    "gn:admin2_code":"2915",
    "gn:asciiname":"Pudin",
    "gn:country_code":"AF",
    "gn:dem":2119,
    "gn:feature_class":"P",
    "gn:feature_code":"PPL",
    "gn:name":"Pud\u012bn",
    "gn:population":0,
    "gn:timezone":"Asia/Kabul",
    "iso:country":"AF",
    "name:und_x_variant":[
        "\u067e\u062f\u06cc\u0646",
        "Po\u1e0f\u012bn",
        "Pud\u012bn"
    ],
    "wof:name":"Pudin",
    "wof:placetype":"locality"
},
  "geometry": {"coordinates":[68.90052,33.29977],"type":"Point"}
}