{
  "type": "Feature",
  "properties": {
    "gn:admin1_code":"29",
    "gn:admin2_code":"2906.0",
    "gn:asciiname":"'Aziz Khan",
    "gn:country_code":"AF",
    "gn:dem":2461,
    "gn:feature_class":"P",
    "gn:feature_code":"PPL",
    "gn:name":"\u2018Az\u012bz Kh\u0101n",
    "gn:population":0,
    "gn:timezone":"Asia/Kabul",
    "iso:country":"AF",
    "name:fas_x_preferred":[
        "\u2018Az\u012bz Kh\u0101n"
    ],
    "name:fas_x_variant":[
        "\u0639\u0632\u06cc\u0632 \u062e\u0627\u0646"
    ],
    "name:und_x_variant":[
        "Azizkhan"
    ],
    "wof:name":"'Aziz Khan",
    "wof:placetype":"locality"
},
  "geometry": {"coordinates":[68.77381,32.66548],"type":"Point"}
}