{
  "type": "Feature",
  "properties": {
    "gn:admin1_code":"13",
    "gn:admin2_code":"108",
    "gn:asciiname":"Darah-ye Zargar",
    "gn:country_code":"AF",
    "gn:dem":2278,
    "gn:feature_class":"P",
    "gn:feature_code":"PPL",
    "gn:name":"Darah-ye Zargar",
    "gn:population":0,
    "gn:timezone":"Asia/Kabul",
    "iso:country":"AF",
    "name:und_x_variant":[
        "\u1e0ea\u1e5f\u1e5fah Za\u1e5fga\u1e5f",
        "\u1e0ea\u1e5f\u1e5fahe Za\u1e5fga\u1e5f",
        "Darrazargar",
        "Darreh-ye Zargar",
        "Darrah-ye Zargar",
        "Darah-ye Zargar",
        "\u062f\u0631\u0647 \u0632\u0631\u06af\u0631"
    ],
    "wof:name":"Darah-ye Zargar",
    "wof:placetype":"locality"
},
  "geometry": {"coordinates":[68.96717,34.59161],"type":"Point"}
}