{
  "type": "Feature",
  "properties": {
    "gn:admin1_code":"08",
    "gn:admin2_code":"601",
    "gn:asciiname":"Nughay-e Sufla",
    "gn:country_code":"AF",
    "gn:dem":2125,
    "gn:feature_class":"P",
    "gn:feature_code":"PPL",
    "gn:name":"N\u016bghay-e Sufl\u0101",
    "gn:population":0,
    "gn:timezone":"Asia/Kabul",
    "iso:country":"AF",
    "name:und_x_variant":[
        "N\u016bghaye Sufl\u0101",
        "N\u016bghaye",
        "Nugayi-Sufla",
        "N\u014dghay-e Sofl\u00e1",
        "N\u016bghay-e Sofl\u00e1",
        "N\u016bghay-e Sufl\u0101",
        "\u0646\u0648\u063a\u06cc \u0633\u0641\u0644\u0649"
    ],
    "wof:name":"Nughay-e Sufla",
    "wof:placetype":"locality"
},
  "geometry": {"coordinates":[68.39095999999999,33.44335],"type":"Point"}
}