{
  "type": "Feature",
  "properties": {
    "gn:admin1_code":"10",
    "gn:admin2_code":"2305.0",
    "gn:asciiname":"Chaktu",
    "gn:country_code":"AF",
    "gn:dem":1749,
    "gn:feature_class":"P",
    "gn:feature_code":"PPL",
    "gn:name":"Chakt\u016b",
    "gn:population":0,
    "gn:timezone":"Asia/Kabul",
    "iso:country":"AF",
    "name:fas_x_preferred":[
        "\u0686\u0643\u062a\u0648"
    ],
    "name:rus_x_preferred":[
        "\u0427\u0430\u043a\u0442\u0443"
    ],
    "name:und_x_variant":[
        "\u010caktu",
        "Chakt\u016b",
        "\u0686\u06a9\u062a\u0648"
    ],
    "wof:name":"Chaktu",
    "wof:placetype":"locality"
},
  "geometry": {"coordinates":[65.05173000000001,33.14217],"type":"Point"}
}