{
  "type": "Feature",
  "properties": {
    "gn:admin1_code":"6",
    "gn:admin2_code":"2108.0",
    "gn:asciiname":"Karez-e Sokhtah",
    "gn:country_code":"AF",
    "gn:dem":617,
    "gn:feature_class":"P",
    "gn:feature_code":"PPL",
    "gn:name":"K\u0101r\u0113z-e S\u014dkhtah",
    "gn:population":0,
    "gn:timezone":"Asia/Kabul",
    "iso:country":"AF",
    "name:fas_x_preferred":[
        "K\u0101r\u0113z-e S\u014dkhtah"
    ],
    "name:fas_x_variant":[
        "\u06a9\u0627\u0631\u06d0\u0632 \u0633\u0648\u062e\u062a\u0647"
    ],
    "name:und_x_variant":[
        "K\u0101r\u0113z-e S\u014dkhta",
        "K\u0101r\u012bz-e S\u016bkhteh",
        "\u06a9\u0627\u0631\u06d0\u0632 \u0633\u0648\u062e\u062a\u0647"
    ],
    "wof:name":"Karez-e Sokhtah",
    "wof:placetype":"locality"
},
  "geometry": {"coordinates":[61.67304,32.32875],"type":"Point"}
}