{
  "type": "Feature",
  "properties": {
    "gn:admin1_code":"18",
    "gn:admin2_code":"814",
    "gn:asciiname":"Kamah Dakah",
    "gn:country_code":"AF",
    "gn:dem":424,
    "gn:feature_class":"P",
    "gn:feature_code":"PPL",
    "gn:name":"Kamah Dakah",
    "gn:population":0,
    "gn:timezone":"Asia/Kabul",
    "iso:country":"AF",
    "name:fas_x_preferred":[
        "\u06a9\u0645\u0647 \u062f\u06a9\u0647"
    ],
    "name:und_x_variant":[
        "Kama \u1e0eaka",
        "Kam Dakka",
        "Kamah Dakah",
        "Kamah \u1e0eakah"
    ],
    "wof:name":"Kamah Dakah",
    "wof:placetype":"locality"
},
  "geometry": {"coordinates":[71.11964,34.22815],"type":"Point"}
}