{
  "type": "Feature",
  "properties": {
    "gn:admin1_code":"5",
    "gn:admin2_code":"2806.0",
    "gn:asciiname":"Dahan-e Hadyah",
    "gn:country_code":"AF",
    "gn:dem":2667,
    "gn:feature_class":"P",
    "gn:feature_code":"PPL",
    "gn:name":"Dahan-e Hadyah",
    "gn:population":0,
    "gn:timezone":"Asia/Kabul",
    "iso:country":"AF",
    "name:und_x_variant":[
        "\u1e0eahane Ha\u1e0fya",
        "Dakhani-Khad\u2019ya",
        "Dahan-e Hadyah",
        "\u062f\u0647\u0646 \u0647\u062f\u06cc\u0647"
    ],
    "wof:name":"Dahan-e Hadyah",
    "wof:placetype":"locality"
},
  "geometry": {"coordinates":[66.56236,34.21983],"type":"Point"}
}