{
  "type": "Feature",
  "properties": {
    "gn:admin1_code":"7",
    "gn:admin2_code":"1804.0",
    "gn:asciiname":"Chuqur Bulaq",
    "gn:country_code":"AF",
    "gn:dem":1872,
    "gn:feature_class":"P",
    "gn:feature_code":"PPL",
    "gn:name":"Chuqur B\u016bl\u0101q",
    "gn:population":0,
    "gn:timezone":"Asia/Kabul",
    "iso:country":"AF",
    "name:und_x_variant":[
        "Cuqu\u1e5f Bul\u0101q",
        "Choqor Bol\u0101q",
        "Chuqur B\u016bl\u0101q",
        "\u0686\u0642\u0631 \u0628\u0648\u0644\u0627\u0642"
    ],
    "wof:name":"Chuqur Bulaq",
    "wof:placetype":"locality"
},
  "geometry": {"coordinates":[64.46859000000001,35.61229],"type":"Point"}
}