{
  "type": "Feature",
  "properties": {
    "gn:admin1_code":"23",
    "gn:admin2_code":"2413.0",
    "gn:asciiname":"Regi",
    "gn:country_code":"AF",
    "gn:dem":1906,
    "gn:feature_class":"P",
    "gn:feature_code":"PPL",
    "gn:name":"R\u0113g\u012b",
    "gn:population":0,
    "gn:timezone":"Asia/Kabul",
    "iso:country":"AF",
    "name:cat_x_preferred":[
        "Reg\u00ed"
    ],
    "name:dan_x_preferred":[
        "Regi"
    ],
    "name:nld_x_preferred":[
        "Regi"
    ],
    "name:und_x_variant":[
        "\u1e5e\u0113gi",
        "R\u0113g\u012b",
        "R\u012bg\u012b",
        "Rayg\u012b",
        "\u0631\u06cc\u06af\u06cc"
    ],
    "wof:name":"Regi",
    "wof:placetype":"locality"
},
  "geometry": {"coordinates":[67.24021999999999,31.35556],"type":"Point"}
}