{
  "type": "Feature",
  "properties": {
    "gn:admin1_code":"01",
    "gn:admin2_code":"1126",
    "gn:asciiname":"Fazil Khwah",
    "gn:country_code":"AF",
    "gn:dem":2115,
    "gn:feature_class":"P",
    "gn:feature_code":"PPL",
    "gn:name":"Fa\u1e95il Khw\u0101h",
    "gn:population":0,
    "gn:timezone":"Asia/Kabul",
    "iso:country":"AF",
    "name:und_x_variant":[
        "Fa\u1e0f\u1e95el Khw\u0101h",
        "F\u0101\u1e95el Khv\u0101h",
        "Fa\u1e95il Khw\u0101h",
        "\u0641\u0636\u0644 \u062e\u0648\u0627\u0647"
    ],
    "wof:name":"Fazil Khwah",
    "wof:placetype":"locality"
},
  "geometry": {"coordinates":[70.4675,37.31909],"type":"Point"}
}