{
  "type": "Feature",
  "properties": {
    "gn:admin1_code":"10",
    "gn:admin2_code":"2304.0",
    "gn:asciiname":"Gumbate",
    "gn:country_code":"AF",
    "gn:dem":990,
    "gn:feature_class":"P",
    "gn:feature_code":"PPL",
    "gn:name":"Gumbat\u0113",
    "gn:population":0,
    "gn:timezone":"Asia/Kabul",
    "iso:country":"AF",
    "name:und_x_variant":[
        "Gumbat\u0113",
        "Gumbate",
        "\u06af\u0645\u0628\u062a\u06d0",
        "Gumbatey"
    ],
    "wof:name":"Gumbate",
    "wof:placetype":"locality"
},
  "geometry": {"coordinates":[64.83511999999999,32.26703],"type":"Point"}
}