{
  "type": "Feature",
  "properties": {
    "gn:admin1_code":"05",
    "gn:admin2_code":"2806",
    "gn:asciiname":"Kharah Sang",
    "gn:country_code":"AF",
    "gn:dem":3181,
    "gn:feature_class":"P",
    "gn:feature_code":"PPL",
    "gn:name":"Kharah Sang",
    "gn:population":0,
    "gn:timezone":"Asia/Kabul",
    "iso:country":"AF",
    "name:und_x_variant":[
        "Kharasang",
        "Kha\u1e5fasang",
        "Kharah Sang",
        "Kharehsang",
        "\u062e\u0631\u0647 \u0633\u0646\u06af"
    ],
    "wof:name":"Kharah Sang",
    "wof:placetype":"locality"
},
  "geometry": {"coordinates":[66.89856999999999,34.08655],"type":"Point"}
}