{
  "type": "Feature",
  "properties": {
    "gn:admin1_code":"5",
    "gn:admin2_code":"2805.0",
    "gn:asciiname":"Chahar Bala",
    "gn:country_code":"AF",
    "gn:dem":2845,
    "gn:feature_class":"P",
    "gn:feature_code":"PPL",
    "gn:name":"Chah\u0101r B\u0101l\u0101",
    "gn:population":0,
    "gn:timezone":"Asia/Kabul",
    "iso:country":"AF",
    "name:und_x_variant":[
        "\u010c\u0101rbal\u0101",
        "Charbala",
        "Ch\u0101rbal\u0101",
        "Chah\u0101rb\u0101l\u0101",
        "Chah\u0101r B\u0101l\u0101",
        "\u0686\u0627\u0631\u0628\u0644\u0627"
    ],
    "wof:name":"Chahar Bala",
    "wof:placetype":"locality"
},
  "geometry": {"coordinates":[66.94373,34.38268],"type":"Point"}
}