{
  "type": "Feature",
  "properties": {
    "gn:admin1_code":"17",
    "gn:admin2_code":"507",
    "gn:asciiname":"Ghurfan",
    "gn:country_code":"AF",
    "gn:dem":2745,
    "gn:feature_class":"P",
    "gn:feature_code":"PPL",
    "gn:name":"Ghurf\u0101n",
    "gn:population":0,
    "gn:timezone":"Asia/Kabul",
    "iso:country":"AF",
    "name:und_x_variant":[
        "Gurgan",
        "Ghurf\u0101n",
        "\u063a\u0631\u0641\u0627\u0646"
    ],
    "wof:name":"Ghurfan",
    "wof:placetype":"locality"
},
  "geometry": {"coordinates":[68.7679,33.78564],"type":"Point"}
}