{
  "type": "Feature",
  "properties": {
    "gn:admin1_code":"8",
    "gn:admin2_code":"611.0",
    "gn:asciiname":"Badam Kichah",
    "gn:country_code":"AF",
    "gn:dem":2047,
    "gn:feature_class":"P",
    "gn:feature_code":"PPL",
    "gn:name":"B\u0101d\u0101m Kichah",
    "gn:population":0,
    "gn:timezone":"Asia/Kabul",
    "iso:country":"AF",
    "name:und_x_variant":[
        "B\u0101d\u0101mki\u010da",
        "Badamkicha",
        "B\u0101d\u0101mk\u012bchay",
        "B\u0101d\u0101m Kichah",
        "\u0628\u0627\u062f\u0627\u0645 \u06a9\u0686\u0647",
        "B\u0101d\u0101mk\u012b Ch\u0101h",
        "\u0628\u0627\u062f\u0627\u0645\u06a9\u06cc \u0686\u0627\u0647"
    ],
    "wof:name":"Badam Kichah",
    "wof:placetype":"locality"
},
  "geometry": {"coordinates":[67.91025,32.91471],"type":"Point"}
}