{
  "type": "Feature",
  "properties": {
    "gn:admin1_code":"10",
    "gn:admin2_code":"2311.0",
    "gn:asciiname":"Amanullah Khan Kelay",
    "gn:country_code":"AF",
    "gn:dem":671,
    "gn:feature_class":"P",
    "gn:feature_code":"PPL",
    "gn:name":"Am\u0101null\u0101h Kh\u0101n K\u00ealay",
    "gn:population":0,
    "gn:timezone":"Asia/Kabul",
    "iso:country":"AF",
    "name:und_x_variant":[
        "Am\u0101nnull\u0101kh\u0101n Kalay",
        "Amm\u0101null\u0101kh\u0101n Kalay",
        "Am\u0101null\u0101h Kh\u0101n K\u00ealay",
        "\u0627\u0645\u0627\u0646\u0627\u0644\u0644\u0647 \u062e\u0627\u0646 \u06a9\u0644\u06cc",
        "Am\u0101noll\u0101h Kh\u0101n Kalay"
    ],
    "wof:name":"Amanullah Khan Kelay",
    "wof:placetype":"locality"
},
  "geometry": {"coordinates":[64.11704,30.7379],"type":"Point"}
}