{
  "type": "Feature",
  "properties": {
    "gn:admin1_code":"11",
    "gn:admin2_code":"2010",
    "gn:asciiname":"Nayak",
    "gn:country_code":"AF",
    "gn:dem":1048,
    "gn:feature_class":"P",
    "gn:feature_code":"PPL",
    "gn:name":"Nayak",
    "gn:population":0,
    "gn:timezone":"Asia/Kabul",
    "iso:country":"AF",
    "name:cat_x_preferred":[
        "Nayak"
    ],
    "name:ceb_x_preferred":[
        "Nayak"
    ],
    "name:deu_x_preferred":[
        "Nayak"
    ],
    "name:fra_x_preferred":[
        "Nayak"
    ],
    "name:hin_x_preferred":[
        "\u0928\u093e\u092f\u0915"
    ],
    "name:jpn_x_preferred":[
        "\u30ca\u30fc\u30e4\u30ab"
    ],
    "name:nld_x_preferred":[
        "Nayak"
    ],
    "name:swe_x_preferred":[
        "Nayak"
    ],
    "name:und_x_variant":[
        "\u0646\u06cc\u06a9",
        "Nah Yak",
        "Nayk",
        "\u0646\u0647 \u06cc\u06a9"
    ],
    "wof:name":"Nayak",
    "wof:placetype":"locality"
},
  "geometry": {"coordinates":[61.94083000000001,34.49583],"type":"Point"}
}