{
  "type": "Feature",
  "properties": {
    "gn:admin1_code":"27",
    "gn:admin2_code":"404",
    "gn:asciiname":"Surkh Paytow",
    "gn:country_code":"AF",
    "gn:dem":3264,
    "gn:feature_class":"P",
    "gn:feature_code":"PPL",
    "gn:name":"Surkh Paytow",
    "gn:population":0,
    "gn:timezone":"Asia/Kabul",
    "iso:country":"AF",
    "name:und_x_variant":[
        "Su\u1e5fkhp\u0113taw",
        "Sorkh P\u012bt\u0101b",
        "Surkhpetau",
        "Sorkhp\u0113taw",
        "Surkh Paytow",
        "\u0633\u0631\u062e \u067e\u064a\u062a\u0648"
    ],
    "wof:name":"Surkh Paytow",
    "wof:placetype":"locality"
},
  "geometry": {"coordinates":[67.4121,34.452],"type":"Point"}
}