{
  "type": "Feature",
  "properties": {
    "gn:admin1_code":"28",
    "gn:admin2_code":"2509.0",
    "gn:asciiname":"Kazheh Bilah",
    "gn:country_code":"AF",
    "gn:dem":1979,
    "gn:feature_class":"P",
    "gn:feature_code":"PPL",
    "gn:name":"K\u0101z\u0332h\u0332\u00eah Bilah",
    "gn:population":0,
    "gn:timezone":"Asia/Kabul",
    "iso:country":"AF",
    "name:fas_x_preferred":[
        "\u06a9\u0627\u0698\u0647 \u0628\u0644\u0647"
    ],
    "name:und_x_variant":[
        "K\u0101zeh Bela",
        "Kazibila",
        "K\u0101z\u0332h\u0332\u00eah Bilah",
        "\u06a9\u0627\u0696\u0647 \u0628\u0644\u0647",
        "K\u0101z\u0332h\u0332eh Belah"
    ],
    "wof:name":"Kazheh Bilah",
    "wof:placetype":"locality"
},
  "geometry": {"coordinates":[67.49011999999999,31.52464],"type":"Point"}
}