{
  "type": "Feature",
  "properties": {
    "gn:admin1_code":"34",
    "gn:admin2_code":"1006.0",
    "gn:asciiname":"Adirullah Kelay",
    "gn:country_code":"AF",
    "gn:dem":1244,
    "gn:feature_class":"P",
    "gn:feature_code":"PPL",
    "gn:name":"Adirull\u0101h K\u00ealay",
    "gn:population":0,
    "gn:timezone":"Asia/Kabul",
    "iso:country":"AF",
    "name:fas_x_preferred":[
        "\u0642\u0631\u064a\u06c0 \u0627\u062f\u0631 \u0627\u0644\u0644\u0647"
    ],
    "name:und_x_variant":[
        "Adirilla-Kalay",
        "\u0627\u062f\u0631\u0627\u0644\u0644\u0647 \u06a9\u0644\u06cc",
        "Aderell\u0101h Kalay",
        "Adirull\u0101h K\u00ealay"
    ],
    "wof:name":"Adirullah Kelay",
    "wof:placetype":"locality"
},
  "geometry": {"coordinates":[71.33135,35.14186],"type":"Point"}
}