{
  "type": "Feature",
  "properties": {
    "gn:admin1_code":"30",
    "gn:admin2_code":"1605",
    "gn:asciiname":"Islam",
    "gn:country_code":"AF",
    "gn:dem":309,
    "gn:feature_class":"P",
    "gn:feature_code":"PPL",
    "gn:name":"Isl\u0101m",
    "gn:population":0,
    "gn:timezone":"Asia/Kabul",
    "iso:country":"AF",
    "name:fas_x_preferred":[
        "\u0627\u0633\u0644\u0627\u0645"
    ],
    "name:rus_x_preferred":[
        "\u0418\u0441\u043b\u0430\u043c"
    ],
    "name:und_x_variant":[
        "Isl\u0101m",
        "Islam",
        "Esl\u0101m"
    ],
    "wof:name":"Islam",
    "wof:placetype":"locality"
},
  "geometry": {"coordinates":[66.67806999999999,36.97699],"type":"Point"}
}