{
  "type": "Feature",
  "properties": {
    "gn:admin1_code":"17",
    "gn:admin2_code":"501",
    "gn:asciiname":"Nay Karay",
    "gn:country_code":"AF",
    "gn:dem":2633,
    "gn:feature_class":"P",
    "gn:feature_code":"PPL",
    "gn:name":"Nay Karay",
    "gn:population":0,
    "gn:timezone":"Asia/Kabul",
    "iso:country":"AF",
    "name:fas_x_preferred":[
        "\u0646\u06cc \u06a9\u0631\u06cc"
    ],
    "name:und_x_variant":[
        "Naykaray",
        "Nay Karay",
        "Nay Ka\u1e5fay"
    ],
    "wof:name":"Nay Karay",
    "wof:placetype":"locality"
},
  "geometry": {"coordinates":[69.23989,33.86149],"type":"Point"}
}