{
  "type": "Feature",
  "properties": {
    "gn:admin1_code":"10",
    "gn:admin2_code":"2301",
    "gn:asciiname":"Miralzi",
    "gn:country_code":"AF",
    "gn:dem":788,
    "gn:feature_class":"P",
    "gn:feature_code":"PPL",
    "gn:name":"M\u012br\u0101lz\u012b",
    "gn:population":0,
    "gn:timezone":"Asia/Kabul",
    "iso:country":"AF",
    "name:rus_x_preferred":[
        "Miral\u2019zi"
    ],
    "name:und_x_variant":[
        "M\u012br\u0101lz\u012b",
        "\u0645\u06cc\u0631\u0627\u0644\u0632\u06cc",
        "Mi\u1e5f\u0101lzi"
    ],
    "wof:name":"Miralzi",
    "wof:placetype":"locality"
},
  "geometry": {"coordinates":[64.54784000000001,31.63912],"type":"Point"}
}