{
  "type": "Feature",
  "properties": {
    "gn:admin1_code":"08",
    "gn:admin2_code":"605",
    "gn:asciiname":"Musar Khel",
    "gn:country_code":"AF",
    "gn:dem":2718,
    "gn:feature_class":"P",
    "gn:feature_code":"PPL",
    "gn:name":"M\u016bsar Kh\u0113l",
    "gn:population":0,
    "gn:timezone":"Asia/Kabul",
    "iso:country":"AF",
    "name:und_x_variant":[
        "M\u016bsa\u1e5fkh\u0113l",
        "M\u016bsar Kheyl",
        "M\u016bsar Kh\u0113l",
        "\u0645\u0648\u0633\u0631\u062e\u06d0\u0644"
    ],
    "wof:name":"Musar Khel",
    "wof:placetype":"locality"
},
  "geometry": {"coordinates":[67.30556,33.60098],"type":"Point"}
}