{
  "type": "Feature",
  "properties": {
    "gn:admin1_code":"9",
    "gn:admin2_code":"2702.0",
    "gn:asciiname":"A'la Ghori",
    "gn:country_code":"AF",
    "gn:dem":2517,
    "gn:feature_class":"P",
    "gn:feature_code":"PPL",
    "gn:name":"A\u2018l\u00e1 Gh\u014dr\u012b",
    "gn:population":0,
    "gn:timezone":"Asia/Kabul",
    "iso:country":"AF",
    "name:und_x_variant":[
        "Alagori",
        "A\u2018l\u0101 Gh\u014d\u1e5fi",
        "A\u2018l\u00e1 Gh\u014dr\u012b",
        "\u0627\u0639\u0644\u0649 \u063a\u0648\u0631\u06cc",
        "A\u2018l\u0101 Ghowr\u012b"
    ],
    "wof:name":"A'la Ghori",
    "wof:placetype":"locality"
},
  "geometry": {"coordinates":[64.51777,33.89015],"type":"Point"}
}