{
  "type": "Feature",
  "properties": {
    "gn:admin1_code":"08",
    "gn:admin2_code":"602",
    "gn:asciiname":"Qalkhi",
    "gn:country_code":"AF",
    "gn:dem":2855,
    "gn:feature_class":"P",
    "gn:feature_code":"PPL",
    "gn:name":"Qalkh\u012b",
    "gn:population":0,
    "gn:timezone":"Asia/Kabul",
    "iso:country":"AF",
    "name:rus_x_preferred":[
        "\u041a\u0430\u043b\u044c\u0445\u0438"
    ],
    "name:und_x_variant":[
        "Kal\u2019khi",
        "Qalkhi Sa\u1e0f\u1e5fay",
        "Qalkh\u012b",
        "\u0642\u0644\u062e\u06cc"
    ],
    "wof:name":"Qalkhi",
    "wof:placetype":"locality"
},
  "geometry": {"coordinates":[67.97270999999999,33.5438],"type":"Point"}
}