{
  "type": "Feature",
  "properties": {
    "gn:admin1_code":"41",
    "gn:admin2_code":"3409.0",
    "gn:asciiname":"Deh-e Bagh",
    "gn:country_code":"AF",
    "gn:dem":2326,
    "gn:feature_class":"P",
    "gn:feature_code":"PPL",
    "gn:name":"Deh-e B\u0101gh",
    "gn:population":0,
    "gn:timezone":"Asia/Kabul",
    "iso:country":"AF",
    "name:und_x_variant":[
        "Deh-e B\u0101gh",
        "\u062f\u0647 \u0628\u0627\u063a"
    ],
    "wof:name":"Deh-e Bagh",
    "wof:placetype":"locality"
},
  "geometry": {"coordinates":[66.77533000000001,33.60235],"type":"Point"}
}