{
  "type": "Feature",
  "properties": {
    "gn:admin1_code":"01",
    "gn:admin2_code":"1115.0",
    "gn:asciiname":"Qosh Kham",
    "gn:country_code":"AF",
    "gn:dem":2236,
    "gn:feature_class":"P",
    "gn:feature_code":"PPL",
    "gn:name":"Q\u014dsh Kham",
    "gn:population":0,
    "gn:timezone":"Asia/Kabul",
    "iso:country":"AF",
    "name:und_x_variant":[
        "Q\u014ds Kham",
        "Q\u016bsh Kham",
        "Q\u014dsh Kham",
        "\u0642\u0648\u0634 \u062e\u0645"
    ],
    "wof:name":"Qosh Kham",
    "wof:placetype":"locality"
},
  "geometry": {"coordinates":[70.39734,36.97452],"type":"Point"}
}