{
  "type": "Feature",
  "properties": {
    "gn:admin1_code":"8",
    "gn:admin2_code":"614.0",
    "gn:asciiname":"Nakam",
    "gn:country_code":"AF",
    "gn:dem":2093,
    "gn:feature_class":"P",
    "gn:feature_code":"PPL",
    "gn:name":"N\u0101k\u0101m",
    "gn:population":0,
    "gn:timezone":"Asia/Kabul",
    "iso:country":"AF",
    "name:ces_x_preferred":[
        "Nakam"
    ],
    "name:deu_x_preferred":[
        "Nakam"
    ],
    "name:fas_x_preferred":[
        "\u0646\u0627\u06a9\u0627\u0645"
    ],
    "name:fra_x_preferred":[
        "Nakam"
    ],
    "name:heb_x_preferred":[
        "\u05d4\u05e0\u05d5\u05e7\u05de\u05d9\u05dd"
    ],
    "name:ron_x_preferred":[
        "Gruparea Nakam"
    ],
    "name:rus_x_preferred":[
        "\u041d\u043e\u043a\u043c\u0438\u043c"
    ],
    "name:spa_x_preferred":[
        "Nakam"
    ],
    "name:und_x_variant":[
        "N\u0101k\u0101m"
    ],
    "wof:name":"Nakam",
    "wof:placetype":"locality"
},
  "geometry": {"coordinates":[68.52509000000001,33.38646],"type":"Point"}
}