{
  "type": "Feature",
  "properties": {
    "gn:admin1_code":"08",
    "gn:admin2_code":"604.0",
    "gn:asciiname":"'Uliyad Qol",
    "gn:country_code":"AF",
    "gn:dem":2937,
    "gn:feature_class":"P",
    "gn:feature_code":"PPL",
    "gn:name":"\u2018Uliy\u0101d Q\u014dl",
    "gn:population":0,
    "gn:timezone":"Asia/Kabul",
    "iso:country":"AF",
    "name:rus_x_preferred":[
        "Uliadkul\u2019"
    ],
    "name:und_x_variant":[
        "\u2018Oley\u0101\u1e0fq\u014dl",
        "\u2018Oley\u0101dqowl",
        "\u2018Uliy\u0101d Q\u014dl",
        "\u0639\u0644\u06cc\u0627\u062f \u0642\u0648\u0644"
    ],
    "wof:name":"'Uliyad Qol",
    "wof:placetype":"locality"
},
  "geometry": {"coordinates":[67.38109,34.03153],"type":"Point"}
}