{
  "type": "Feature",
  "properties": {
    "gn:admin1_code":"01",
    "gn:admin2_code":"1119.0",
    "gn:asciiname":"Buzkush",
    "gn:country_code":"AF",
    "gn:dem":2628,
    "gn:feature_class":"P",
    "gn:feature_code":"PPL",
    "gn:name":"Buzkush",
    "gn:population":0,
    "gn:timezone":"Asia/Kabul",
    "iso:country":"AF",
    "name:und_x_variant":[
        "Buzku\u0161",
        "\u0628\u0648\u0632\u06a9\u0634",
        "Bozkosh",
        "Buzkush",
        "\u0628\u0632\u06a9\u0634"
    ],
    "wof:name":"Buzkush",
    "wof:placetype":"locality"
},
  "geometry": {"coordinates":[70.66961999999999,37.49638],"type":"Point"}
}