{
  "type": "Feature",
  "properties": {
    "gn:admin1_code":"28",
    "gn:admin2_code":"2509.0",
    "gn:asciiname":"Bashah",
    "gn:country_code":"AF",
    "gn:dem":2224,
    "gn:feature_class":"P",
    "gn:feature_code":"PPL",
    "gn:name":"B\u0101shah",
    "gn:population":0,
    "gn:timezone":"Asia/Kabul",
    "iso:country":"AF",
    "name:und_x_variant":[
        "B\u0101\u0161a",
        "Basha",
        "B\u0101shah",
        "\u0628\u0627\u0634\u0647"
    ],
    "wof:name":"Bashah",
    "wof:placetype":"locality"
},
  "geometry": {"coordinates":[67.83411,31.81901],"type":"Point"}
}