{
  "type": "Feature",
  "properties": {
    "gn:admin1_code":"32",
    "gn:admin2_code":"1504.0",
    "gn:asciiname":"Deh Khwab",
    "gn:country_code":"AF",
    "gn:dem":1273,
    "gn:feature_class":"P",
    "gn:feature_code":"PPL",
    "gn:name":"Deh Khw\u0101b",
    "gn:population":0,
    "gn:timezone":"Asia/Kabul",
    "iso:country":"AF",
    "name:und_x_variant":[
        "Deh Khw\u0101b (3)",
        "Deh Khv\u0101b (3)",
        "Deh Khw\u0101b",
        "\u062f\u0647 \u062e\u0648\u0627\u0628"
    ],
    "wof:name":"Deh Khwab",
    "wof:placetype":"locality"
},
  "geometry": {"coordinates":[67.22093000000001,36.09548],"type":"Point"}
}