{
  "type": "Feature",
  "properties": {
    "gn:admin1_code":"28",
    "gn:admin2_code":"2509",
    "gn:asciiname":"Natulai",
    "gn:country_code":"AF",
    "gn:dem":2052,
    "gn:feature_class":"P",
    "gn:feature_code":"PPL",
    "gn:name":"Nat\u016bla\u012b",
    "gn:population":0,
    "gn:timezone":"Asia/Kabul",
    "iso:country":"AF",
    "name:und_x_variant":[
        "Nat\u016bla\u012b",
        "Nat\u016blay",
        "\u0646\u062a\u0648\u0644\u06cc"
    ],
    "wof:name":"Natulai",
    "wof:placetype":"locality"
},
  "geometry": {"coordinates":[67.57733,31.81057],"type":"Point"}
}