{
  "type": "Feature",
  "properties": {
    "gn:admin1_code":"06",
    "gn:admin2_code":"2102",
    "gn:asciiname":"Sisanu",
    "gn:country_code":"AF",
    "gn:dem":713,
    "gn:feature_class":"P",
    "gn:feature_code":"PPL",
    "gn:name":"Sisan\u016b",
    "gn:population":0,
    "gn:timezone":"Asia/Kabul",
    "iso:country":"AF",
    "name:und_x_variant":[
        "Sisan\u016b",
        "\u0633\u0633\u0646\u0648",
        "Sesanu"
    ],
    "wof:name":"Sisanu",
    "wof:placetype":"locality"
},
  "geometry": {"coordinates":[62.91466,32.09677],"type":"Point"}
}