{
  "type": "Feature",
  "properties": {
    "gn:admin1_code":"03",
    "gn:admin2_code":"1304",
    "gn:asciiname":"Qalughu",
    "gn:country_code":"AF",
    "gn:dem":948,
    "gn:feature_class":"P",
    "gn:feature_code":"PPL",
    "gn:name":"Qalugh\u016b",
    "gn:population":0,
    "gn:timezone":"Asia/Kabul",
    "iso:country":"AF",
    "name:und_x_variant":[
        "Qalugh\u016b",
        "\u0642\u0644\u063a\u0648",
        "Qaloghu"
    ],
    "wof:name":"Qalughu",
    "wof:placetype":"locality"
},
  "geometry": {"coordinates":[68.49436999999999,35.59215],"type":"Point"}
}