{
  "type": "Feature",
  "properties": {
    "gn:admin1_code":"41",
    "gn:admin2_code":"3409",
    "gn:asciiname":"Kurag",
    "gn:country_code":"AF",
    "gn:dem":2357,
    "gn:feature_class":"P",
    "gn:feature_code":"PPL",
    "gn:name":"K\u016brag",
    "gn:population":0,
    "gn:timezone":"Asia/Kabul",
    "iso:country":"AF",
    "name:ara_x_preferred":[
        "\u0643\u0648\u0631\u063a"
    ],
    "name:ceb_x_preferred":[
        "K\u016brag"
    ],
    "name:fas_x_preferred":[
        "\u06a9\u0648\u0631\u06af"
    ],
    "name:msa_x_preferred":[
        "Kurag"
    ],
    "name:swe_x_preferred":[
        "K\u016brag"
    ],
    "name:und_x_variant":[
        "K\u016brag",
        "\u06a9\u0648\u0631\u06af"
    ],
    "wof:name":"Kurag",
    "wof:placetype":"locality"
},
  "geometry": {"coordinates":[66.65204,33.55215],"type":"Point"}
}