{
  "type": "Feature",
  "properties": {
    "gn:admin1_code":"29",
    "gn:admin2_code":"2918.0",
    "gn:asciiname":"Atalan",
    "gn:country_code":"AF",
    "gn:dem":2123,
    "gn:feature_class":"P",
    "gn:feature_code":"PPL",
    "gn:name":"Atal\u0101n",
    "gn:population":0,
    "gn:timezone":"Asia/Kabul",
    "iso:country":"AF",
    "name:ceb_x_preferred":[
        "Atalan"
    ],
    "name:kur_x_preferred":[
        "Atalan"
    ],
    "name:nld_x_preferred":[
        "Atalan"
    ],
    "name:tur_x_preferred":[
        "Atalan"
    ],
    "name:und_x_variant":[
        "\u0627\u062a\u0644\u0627\u0646",
        "Atal\u0101n"
    ],
    "name:vie_x_preferred":[
        "Atalan"
    ],
    "wof:name":"Atalan",
    "wof:placetype":"locality"
},
  "geometry": {"coordinates":[68.61828,32.91915],"type":"Point"}
}