{
  "type": "Feature",
  "properties": {
    "gn:admin1_code":"11",
    "gn:admin2_code":"2005",
    "gn:asciiname":"Machqandak",
    "gn:country_code":"AF",
    "gn:dem":1206,
    "gn:feature_class":"P",
    "gn:feature_code":"PPL",
    "gn:name":"Machqandak",
    "gn:population":0,
    "gn:timezone":"Asia/Kabul",
    "iso:country":"AF",
    "name:fas_x_preferred":[
        "\u0645\u0686 \u0642\u0646\u062f\u0643"
    ],
    "name:und_x_variant":[
        "Majkandarak",
        "Machkandaq",
        "Ma\u010dqandak",
        "Machkhandak",
        "Machqandak",
        "\u0645\u0686\u0642\u0646\u062f\u06a9",
        "\u0645\u0686 \u0642\u0646\u062f\u0643",
        "Machkandak"
    ],
    "wof:name":"Machqandak",
    "wof:placetype":"locality"
},
  "geometry": {"coordinates":[62.48873,34.44985],"type":"Point"}
}