{
  "type": "Feature",
  "properties": {
    "gn:admin1_code":"34",
    "gn:admin2_code":"1003.0",
    "gn:asciiname":"Warusht",
    "gn:country_code":"AF",
    "gn:dem":1787,
    "gn:feature_class":"P",
    "gn:feature_code":"PPL",
    "gn:name":"War\u016bsht",
    "gn:population":0,
    "gn:timezone":"Asia/Kabul",
    "iso:country":"AF",
    "name:fas_x_preferred":[
        "\u0648\u0631\u0648\u0634\u062a"
    ],
    "name:und_x_variant":[
        "Varusht",
        "War\u016b\u0161t",
        "Warowsht",
        "War\u016bsht"
    ],
    "wof:name":"Warusht",
    "wof:placetype":"locality"
},
  "geometry": {"coordinates":[71.29253,35.11466],"type":"Point"}
}