{
  "type": "Feature",
  "properties": {
    "gn:admin1_code":"11",
    "gn:admin2_code":"2002",
    "gn:asciiname":"Urdu Khan",
    "gn:country_code":"AF",
    "gn:dem":949,
    "gn:feature_class":"P",
    "gn:feature_code":"PPL",
    "gn:name":"Urd\u016b Kh\u0101n",
    "gn:population":0,
    "gn:timezone":"Asia/Kabul",
    "iso:country":"AF",
    "name:und_x_variant":[
        "Urdukhan",
        "U\u1e5fd\u016b Kh\u0101n",
        "Urd\u016b Kh\u0101n",
        "\u0627\u0631\u062f\u0648 \u062e\u0627\u0646"
    ],
    "wof:name":"Urdu Khan",
    "wof:placetype":"locality"
},
  "geometry": {"coordinates":[62.2774,34.31054],"type":"Point"}
}