{
  "type": "Feature",
  "properties": {
    "gn:admin1_code":"09",
    "gn:admin2_code":"2707",
    "gn:asciiname":"Munar-e 'Ulya",
    "gn:country_code":"AF",
    "gn:dem":2921,
    "gn:feature_class":"P",
    "gn:feature_code":"PPL",
    "gn:name":"Mun\u0101r-e \u2018Uly\u0101",
    "gn:population":0,
    "gn:timezone":"Asia/Kabul",
    "iso:country":"AF",
    "name:und_x_variant":[
        "Munari-Ulia",
        "Mon\u0101reh \u2018Oly\u0101",
        "Mon\u0101\u1e5fe \u2018Uly\u0101",
        "Mun\u0101r-e \u2018Oly\u0101",
        "Men\u0101reh \u2018Oly\u0101",
        "Mun\u0101r-e \u2018Uly\u0101",
        "\u0645\u0646\u0627\u0631 \u0639\u0644\u06cc\u0627"
    ],
    "wof:name":"Munar-e 'Ulya",
    "wof:placetype":"locality"
},
  "geometry": {"coordinates":[66.13422,34.71862],"type":"Point"}
}