{
  "type": "Feature",
  "properties": {
    "gn:admin1_code":"19",
    "gn:admin2_code":"2203",
    "gn:asciiname":"Qal'ah-ye Amir",
    "gn:country_code":"AF",
    "gn:dem":521,
    "gn:feature_class":"P",
    "gn:feature_code":"PPL",
    "gn:name":"Qal\u2018ah-ye Am\u012br",
    "gn:population":0,
    "gn:timezone":"Asia/Kabul",
    "iso:country":"AF",
    "name:und_x_variant":[
        "Qal\u2018a-i-Am\u012br",
        "Qal\u2018ah-ye Am\u012br",
        "\u0642\u0644\u0639\u06c0 \u0627\u0645\u06cc\u0631",
        "Qal\u2018eh-ye Am\u012br"
    ],
    "wof:name":"Qal'ah-ye Amir",
    "wof:placetype":"locality"
},
  "geometry": {"coordinates":[61.94264,30.2943],"type":"Point"}
}