{
  "type": "Feature",
  "properties": {
    "gn:admin1_code":"08",
    "gn:admin2_code":"610",
    "gn:asciiname":"Kalay",
    "gn:country_code":"AF",
    "gn:dem":2021,
    "gn:feature_class":"P",
    "gn:feature_code":"PPL",
    "gn:name":"Kalay",
    "gn:population":0,
    "gn:timezone":"Asia/Kabul",
    "iso:country":"AF",
    "name:epo_x_preferred":[
        "Kalej"
    ],
    "name:fra_x_preferred":[
        "Kalaymyo"
    ],
    "name:mya_x_preferred":[
        "\u1000\u101c\u1031\u1038\u1019\u103c\u102d\u102f\u1037"
    ],
    "name:pol_x_preferred":[
        "Kalay"
    ],
    "name:rus_x_preferred":[
        "\u041a\u0430\u043b\u0435\u043c\u044c\u043e"
    ],
    "name:tha_x_preferred":[
        "\u0e01\u0e30\u0e40\u0e25\u0e48"
    ],
    "name:ukr_x_preferred":[
        "\u041a\u0430\u043b\u0430\u0439"
    ],
    "wof:name":"Kalay",
    "wof:placetype":"locality"
},
  "geometry": {"coordinates":[67.94694,32.33167],"type":"Point"}
}