{
  "type": "Feature",
  "properties": {
    "gn:admin1_code":"36",
    "gn:admin2_code":"710",
    "gn:asciiname":"Shayistah Kala",
    "gn:country_code":"AF",
    "gn:dem":2543,
    "gn:feature_class":"P",
    "gn:feature_code":"PPL",
    "gn:name":"S\u0332h\u0332\u0101yistah Kal\u0101",
    "gn:population":0,
    "gn:timezone":"Asia/Kabul",
    "iso:country":"AF",
    "name:fas_x_preferred":[
        "\u0634\u0627\u064a\u0633\u062a\u0647 \u0643\u0644\u0627"
    ],
    "name:und_x_variant":[
        "\u0160\u0101yesta Kal\u0101",
        "Shayistakala",
        "Sh\u0101yesteh Kal\u0101",
        "S\u0332h\u0332\u0101yistah Kal\u0101",
        "\u069a\u0627\u06cc\u0634\u062a\u0647 \u06a9\u0644\u0627"
    ],
    "wof:name":"Shayistah Kala",
    "wof:placetype":"locality"
},
  "geometry": {"coordinates":[69.43765,33.69563],"type":"Point"}
}