{
  "type": "Feature",
  "properties": {
    "gn:admin1_code":"29",
    "gn:admin2_code":"2903",
    "gn:asciiname":"Dildar",
    "gn:country_code":"AF",
    "gn:dem":2023,
    "gn:feature_class":"P",
    "gn:feature_code":"PPL",
    "gn:name":"Dild\u0101r",
    "gn:population":0,
    "gn:timezone":"Asia/Kabul",
    "iso:country":"AF",
    "name:fas_x_preferred":[
        "Dild\u0101r"
    ],
    "name:fas_x_variant":[
        "\u062f\u0644\u062f\u0627\u0631"
    ],
    "name:rus_x_preferred":[
        "Dil\u2019dar"
    ],
    "wof:name":"Dildar",
    "wof:placetype":"locality"
},
  "geometry": {"coordinates":[68.10120000000001,32.39789],"type":"Point"}
}