{
  "type": "Feature",
  "properties": {
    "gn:admin1_code":"28",
    "gn:admin2_code":"2507",
    "gn:asciiname":"Lotah",
    "gn:country_code":"AF",
    "gn:dem":1860,
    "gn:feature_class":"P",
    "gn:feature_code":"PPL",
    "gn:name":"L\u014d\u1e6fah",
    "gn:population":0,
    "gn:timezone":"Asia/Kabul",
    "iso:country":"AF",
    "name:fas_x_preferred":[
        "\u0644\u0648\u062a\u0647"
    ],
    "name:und_x_variant":[
        "L\u014dta",
        "L\u014d\u1e6fah",
        "\u0644\u0648\u067c\u0647",
        "L\u016btah"
    ],
    "wof:name":"Lotah",
    "wof:placetype":"locality"
},
  "geometry": {"coordinates":[67.09104000000001,32.01886],"type":"Point"}
}