{
  "type": "Feature",
  "properties": {
    "gn:admin1_code":"37",
    "gn:admin2_code":"3201.0",
    "gn:asciiname":"Landay Kelay",
    "gn:country_code":"AF",
    "gn:dem":1142,
    "gn:feature_class":"P",
    "gn:feature_code":"PPL",
    "gn:name":"Lan\u1e0fay K\u00ealay",
    "gn:population":0,
    "gn:timezone":"Asia/Kabul",
    "iso:country":"AF",
    "name:fas_x_preferred":[
        "\u0642\u0631\u064a\u06c0 \u0644\u0646\u062f\u06cc"
    ],
    "name:und_x_variant":[
        "Landikalay",
        "Lan\u1e0fay K\u00ealay",
        "Lan\u1e0f\u012b Kalay",
        "\u0644\u0646\u0689\u06cc \u06a9\u0644\u06cc"
    ],
    "wof:name":"Landay Kelay",
    "wof:placetype":"locality"
},
  "geometry": {"coordinates":[69.95238000000001,33.3278],"type":"Point"}
}