{
  "type": "Feature",
  "properties": {
    "gn:admin1_code":"8",
    "gn:admin2_code":"619.0",
    "gn:asciiname":"Ghundi",
    "gn:country_code":"AF",
    "gn:dem":2311,
    "gn:feature_class":"P",
    "gn:feature_code":"PPL",
    "gn:name":"Ghund\u012b",
    "gn:population":0,
    "gn:timezone":"Asia/Kabul",
    "iso:country":"AF",
    "name:fas_x_preferred":[
        "\u063a\u0648\u0646\u062f\u06cc"
    ],
    "name:und_x_variant":[
        "Gunday",
        "Gh\u016bn\u1e0f\u012b",
        "Ghun\u1e0fi",
        "Ghund\u012b",
        "\u063a\u0646\u062f\u06cc"
    ],
    "wof:name":"Ghundi",
    "wof:placetype":"locality"
},
  "geometry": {"coordinates":[68.33771,33.5553],"type":"Point"}
}