{
  "type": "Feature",
  "properties": {
    "gn:admin1_code":"11",
    "gn:admin2_code":"2015",
    "gn:asciiname":"Sayb Dalak",
    "gn:country_code":"AF",
    "gn:dem":2250,
    "gn:feature_class":"P",
    "gn:feature_code":"PPL",
    "gn:name":"Sayb D\u0101lak",
    "gn:population":0,
    "gn:timezone":"Asia/Kabul",
    "iso:country":"AF",
    "name:und_x_variant":[
        "S\u0113b\u1e0f\u0101lak",
        "Sayb D\u0101lak",
        "\u0633\u06cc\u0628 \u062f\u0627\u0644\u06a9",
        "S\u012bbd\u0101lak"
    ],
    "wof:name":"Sayb Dalak",
    "wof:placetype":"locality"
},
  "geometry": {"coordinates":[63.95889,34.46485],"type":"Point"}
}