{
  "type": "Feature",
  "properties": {
    "gn:admin1_code":"01",
    "gn:admin2_code":"1112.0",
    "gn:asciiname":"Tinilar",
    "gn:country_code":"AF",
    "gn:dem":2501,
    "gn:feature_class":"P",
    "gn:feature_code":"PPL",
    "gn:name":"Tin\u012blar",
    "gn:population":0,
    "gn:timezone":"Asia/Kabul",
    "iso:country":"AF",
    "name:und_x_variant":[
        "\u062a\u0646\u06cc\u0644\u0631",
        "Ten\u012bla\u1e5f",
        "Tin\u012blar"
    ],
    "wof:name":"Tinilar",
    "wof:placetype":"locality"
},
  "geometry": {"coordinates":[70.60351999999997,37.65024],"type":"Point"}
}