{
  "type": "Feature",
  "properties": {
    "gn:admin1_code":"03",
    "gn:admin2_code":"1311",
    "gn:asciiname":"Kandakhari",
    "gn:country_code":"AF",
    "gn:dem":476,
    "gn:feature_class":"P",
    "gn:feature_code":"PPL",
    "gn:name":"Kandakhari",
    "gn:population":0,
    "gn:timezone":"Asia/Kabul",
    "iso:country":"AF",
    "name:fas_x_preferred":[
        "\u0642\u0646\u062f\u0647\u0627\u0631\u06cc"
    ],
    "name:rus_x_preferred":[
        "\u041a\u0430\u043d\u0434\u0430\u0445\u0430\u0440\u0438"
    ],
    "name:und_x_variant":[
        "Qandah\u0101r\u012bh\u0101",
        "Qandah\u0101r\u012bh\u0101-ye Jarr Khoshk\u2019",
        "Qandah\u0101r\u012b"
    ],
    "wof:name":"Kandakhari",
    "wof:placetype":"locality"
},
  "geometry": {"coordinates":[68.75,36.36],"type":"Point"}
}