{
  "type": "Feature",
  "properties": {
    "gn:admin1_code":"02",
    "gn:admin2_code":"1906",
    "gn:asciiname":"Mulla Uzi",
    "gn:country_code":"AF",
    "gn:dem":581,
    "gn:feature_class":"P",
    "gn:feature_code":"PPL",
    "gn:name":"Mull\u0101 \u016az\u012b",
    "gn:population":0,
    "gn:timezone":"Asia/Kabul",
    "iso:country":"AF",
    "name:und_x_variant":[
        "Mull\u0101 Uzi",
        "Moll\u0101 Uzi",
        "Mull\u0101 \u016az\u012b",
        "\u0645\u0644\u0627 \u0627\u0648\u0632\u06cc"
    ],
    "wof:name":"Mulla Uzi",
    "wof:placetype":"locality"
},
  "geometry": {"coordinates":[63.44596,35.3235],"type":"Point"}
}