{
  "type": "Feature",
  "properties": {
    "gn:admin1_code":"9",
    "gn:admin2_code":"2704.0",
    "gn:asciiname":"Damanah",
    "gn:country_code":"AF",
    "gn:dem":2320,
    "gn:feature_class":"P",
    "gn:feature_code":"PPL",
    "gn:name":"D\u0101manah",
    "gn:population":0,
    "gn:timezone":"Asia/Kabul",
    "iso:country":"AF",
    "name:und_x_variant":[
        "Damana",
        "\u1e0e\u0101mana",
        "D\u0101manah",
        "\u062f\u0627\u0645\u0646\u0647",
        "D\u0101maneh"
    ],
    "wof:name":"Damanah",
    "wof:placetype":"locality"
},
  "geometry": {"coordinates":[63.30785,33.61015],"type":"Point"}
}