{
  "type": "Feature",
  "properties": {
    "gn:admin1_code":"38",
    "gn:admin2_code":"3004.0",
    "gn:asciiname":"Shakarnal",
    "gn:country_code":"AF",
    "gn:dem":2183,
    "gn:feature_class":"P",
    "gn:feature_code":"PPL",
    "gn:name":"Shakarnal",
    "gn:population":0,
    "gn:timezone":"Asia/Kabul",
    "iso:country":"AF",
    "name:rus_x_preferred":[
        "Shakarnal\u2019"
    ],
    "name:und_x_variant":[
        "Saka\u1e5fnal",
        "\u0634\u06a9\u0631\u0646\u0644",
        "Shakarnal"
    ],
    "wof:name":"Shakarnal",
    "wof:placetype":"locality"
},
  "geometry": {"coordinates":[70.2355,35.35353],"type":"Point"}
}