{
  "type": "Feature",
  "properties": {
    "gn:admin1_code":"23",
    "gn:admin2_code":"2412.0",
    "gn:asciiname":"Oriyazi",
    "gn:country_code":"AF",
    "gn:dem":1405,
    "gn:feature_class":"P",
    "gn:feature_code":"PPL",
    "gn:name":"\u014criy\u0101z\u012b",
    "gn:population":0,
    "gn:timezone":"Asia/Kabul",
    "iso:country":"AF",
    "name:und_x_variant":[
        "Or\u2019yazi",
        "\u014c\u1e5fy\u0101zi",
        "\u014cr\u012b\u0101za\u012b",
        "\u0627\u0648\u0631\u06cc\u0627\u0632\u06cc",
        "\u016a\u1e5fy\u0101z\u012b",
        "\u014criy\u0101z\u012b"
    ],
    "wof:name":"Oriyazi",
    "wof:placetype":"locality"
},
  "geometry": {"coordinates":[66.70971,31.56455],"type":"Point"}
}