{
  "type": "Feature",
  "properties": {
    "gn:admin1_code":"23",
    "gn:admin2_code":"2412",
    "gn:asciiname":"Khowganay",
    "gn:country_code":"AF",
    "gn:dem":1160,
    "gn:feature_class":"P",
    "gn:feature_code":"PPL",
    "gn:name":"Khowg\u0101\u1e49ay",
    "gn:population":0,
    "gn:timezone":"Asia/Kabul",
    "iso:country":"AF",
    "name:und_x_variant":[
        "Chaohani",
        "Khauganay",
        "Khug\u012b\u0101ni",
        "Khawg\u0101\u1e49ay",
        "Khowg\u0101\u1e49ay",
        "Khaw\u0101nay",
        "\u062e\u0648\u06af\u0627\u06bc\u06cc",
        "Kh\u016bg\u012b\u0101n\u012b S\u0304\u0101n\u012b"
    ],
    "wof:name":"Khowganay",
    "wof:placetype":"locality"
},
  "geometry": {"coordinates":[66.20845,31.54787],"type":"Point"}
}