{
  "type": "Feature",
  "properties": {
    "gn:admin1_code":"5",
    "gn:admin2_code":"2805.0",
    "gn:asciiname":"Now-e Dil Khush",
    "gn:country_code":"AF",
    "gn:dem":3000,
    "gn:feature_class":"P",
    "gn:feature_code":"PPL",
    "gn:name":"Now-e Dil Kh\u016bsh",
    "gn:population":0,
    "gn:timezone":"Asia/Kabul",
    "iso:country":"AF",
    "name:rus_x_preferred":[
        "Navi-Dil\u2019khush"
    ],
    "name:und_x_variant":[
        "Nawe Delkhu\u0161",
        "Naw-e Delkhvosh",
        "Now-e Dil Kh\u016bsh",
        "\u0646\u0648 \u062f\u0644 \u062e\u0648\u0634",
        "N\u00eaw\u0113 Dil Kh\u014dsh",
        "\u0646\u0648\u06d0 \u062f\u0644 \u062e\u0648\u0634"
    ],
    "wof:name":"Now-e Dil Khush",
    "wof:placetype":"locality"
},
  "geometry": {"coordinates":[66.71191999999999,34.42921],"type":"Point"}
}