{
  "type": "Feature",
  "properties": {
    "gn:admin1_code":"8",
    "gn:admin2_code":"609.0",
    "gn:asciiname":"Khayruddin",
    "gn:country_code":"AF",
    "gn:dem":1940,
    "gn:feature_class":"P",
    "gn:feature_code":"PPL",
    "gn:name":"Khayrudd\u012bn",
    "gn:population":0,
    "gn:timezone":"Asia/Kabul",
    "iso:country":"AF",
    "name:und_x_variant":[
        "Khay\u1e5fu\u1e0f\u1e0fin",
        "Khayrudd\u012bn",
        "\u062e\u06cc\u0631\u0644\u062f\u06cc\u0646",
        "Kheyr od D\u012bn"
    ],
    "wof:name":"Khayruddin",
    "wof:placetype":"locality"
},
  "geometry": {"coordinates":[67.72565,32.66591],"type":"Point"}
}