{
  "type": "Feature",
  "properties": {
    "gn:admin1_code":"29",
    "gn:admin2_code":"2909.0",
    "gn:asciiname":"'Abbas Khan Kala",
    "gn:country_code":"AF",
    "gn:dem":2115,
    "gn:feature_class":"P",
    "gn:feature_code":"PPL",
    "gn:name":"\u2018Abb\u0101s Kh\u0101n Kal\u0101",
    "gn:population":0,
    "gn:timezone":"Asia/Kabul",
    "iso:country":"AF",
    "name:fas_x_preferred":[
        "\u0639\u0628\u0627\u0633 \u062e\u0627\u0646 \u06a9\u0644\u0627"
    ],
    "name:und_x_variant":[
        "Ab\u0101s Kh\u0101n Kala",
        "Abaskhankala",
        "\u0639\u0628\u0627\u0633 \u062e\u0627\u0646 \u06a9\u0644\u0627",
        "\u2018Abb\u0101s Kh\u0101n Kal\u0101"
    ],
    "wof:name":"'Abbas Khan Kala",
    "wof:placetype":"locality"
},
  "geometry": {"coordinates":[69.20979,32.50398],"type":"Point"}
}