{
  "type": "Feature",
  "properties": {
    "gn:admin1_code":"41",
    "gn:admin2_code":"3402.0",
    "gn:asciiname":"Barambah",
    "gn:country_code":"AF",
    "gn:dem":2023,
    "gn:feature_class":"P",
    "gn:feature_code":"PPL",
    "gn:name":"Barambah",
    "gn:population":0,
    "gn:timezone":"Asia/Kabul",
    "iso:country":"AF",
    "name:und_x_variant":[
        "Ba\u1e5famba",
        "Barambah",
        "\u0628\u0631\u0645\u0628\u0647"
    ],
    "wof:name":"Barambah",
    "wof:placetype":"locality"
},
  "geometry": {"coordinates":[66.65564999999999,33.43445],"type":"Point"}
}