{
  "type": "Feature",
  "properties": {
    "gn:admin1_code":"06",
    "gn:admin2_code":"2104",
    "gn:asciiname":"Sipawas",
    "gn:country_code":"AF",
    "gn:dem":2334,
    "gn:feature_class":"P",
    "gn:feature_code":"PPL",
    "gn:name":"Sip\u0101was",
    "gn:population":0,
    "gn:timezone":"Asia/Kabul",
    "iso:country":"AF",
    "name:und_x_variant":[
        "Sipavas",
        "Seh Pav\u0101z",
        "Sep\u0101vas",
        "Sep\u0101was",
        "Sep\u0101vos",
        "Sip\u0101was",
        "\u0633\u067e\u0627\u0648\u0633",
        "Sehp\u0101was"
    ],
    "wof:name":"Sipawas",
    "wof:placetype":"locality"
},
  "geometry": {"coordinates":[64.21219000000001,33.00533],"type":"Point"}
}