{
  "type": "Feature",
  "properties": {
    "gn:admin1_code":"30",
    "gn:admin2_code":"1610",
    "gn:asciiname":"Qal'ah-ye Wakil",
    "gn:country_code":"AF",
    "gn:dem":1867,
    "gn:feature_class":"P",
    "gn:feature_code":"PPL",
    "gn:name":"Qal\u2018ah-ye Wak\u012bl",
    "gn:population":0,
    "gn:timezone":"Asia/Kabul",
    "iso:country":"AF",
    "name:und_x_variant":[
        "Qal\u2018a-i-Wak\u012bl",
        "Qal\u2018eh-ye Vak\u012bl",
        "Qal\u2018ah-ye Wak\u012bl",
        "\u0642\u0644\u0639\u06c0 \u0648\u06a9\u06cc\u0644"
    ],
    "wof:name":"Qal'ah-ye Wakil",
    "wof:placetype":"locality"
},
  "geometry": {"coordinates":[67.06543000000001,35.94655],"type":"Point"}
}