{
  "type": "Feature",
  "properties": {
    "gn:admin1_code":"01",
    "gn:admin2_code":"1115.0",
    "gn:asciiname":"Kamunistan",
    "gn:country_code":"AF",
    "gn:dem":1295,
    "gn:feature_class":"P",
    "gn:feature_code":"PPL",
    "gn:name":"Kamunist\u0101n",
    "gn:population":0,
    "gn:timezone":"Asia/Kabul",
    "iso:country":"AF",
    "name:und_x_variant":[
        "Kamunist\u0101n",
        "\u06a9\u0645\u0646\u0633\u062a\u0627\u0646"
    ],
    "wof:name":"Kamunistan",
    "wof:placetype":"locality"
},
  "geometry": {"coordinates":[70.23536999999999,37.05965],"type":"Point"}
}