{
  "type": "Feature",
  "properties": {
    "gn:admin1_code":"08",
    "gn:admin2_code":"608",
    "gn:asciiname":"Gula Khel",
    "gn:country_code":"AF",
    "gn:dem":1987,
    "gn:feature_class":"P",
    "gn:feature_code":"PPL",
    "gn:name":"Gul\u0101 Kh\u0113l",
    "gn:population":0,
    "gn:timezone":"Asia/Kabul",
    "iso:country":"AF",
    "name:rus_x_preferred":[
        "Gulakheyl\u2019"
    ],
    "name:und_x_variant":[
        "Gol\u0101kh\u0113l",
        "Gol\u0101 Kheyl",
        "Gul\u0101 Kh\u0113l",
        "\u06af\u0644\u0627 \u062e\u06d0\u0644"
    ],
    "wof:name":"Gula Khel",
    "wof:placetype":"locality"
},
  "geometry": {"coordinates":[67.75731,32.8037],"type":"Point"}
}