{
  "type": "Feature",
  "properties": {
    "gn:admin1_code":"29",
    "gn:admin2_code":"2918.0",
    "gn:asciiname":"'Alaqahdari-ye Yahya Khel",
    "gn:country_code":"AF",
    "gn:dem":2137,
    "gn:feature_class":"P",
    "gn:feature_code":"PPL",
    "gn:name":"\u2018Al\u0101qahd\u0101r\u012b-ye Ya\u1e29y\u00e1 Kh\u0113l",
    "gn:population":0,
    "gn:timezone":"Asia/Kabul",
    "iso:country":"AF",
    "name:rus_x_preferred":[
        "Alakadari-Yakh\u2019yakheyl\u2019"
    ],
    "name:und_x_variant":[
        "\u2018Al\u0101qa\u1e0f\u0101\u1e5f\u012b Ya\u1e29y\u0101kh\u0113l",
        "\u2018Al\u0101ghehd\u0101r\u012b-ye Ya\u1e29y\u00e1 Kheyl",
        "\u0639\u0644\u0627\u0642\u0647 \u062f\u0627\u0631\u06cc \u06cc\u062d\u06cc\u0649 \u062e\u06d0\u0644",
        "\u2018Al\u0101qehd\u0101r\u012b-ye Ya\u1e29y\u0101 Kheyl",
        "\u2018Al\u0101qahd\u0101r\u012b-ye Ya\u1e29y\u00e1 Kh\u0113l"
    ],
    "wof:name":"'Alaqahdari-ye Yahya Khel",
    "wof:placetype":"locality"
},
  "geometry": {"coordinates":[68.64633000000001,32.93529],"type":"Point"}
}