{
  "type": "Feature",
  "properties": {
    "gn:admin1_code":"28",
    "gn:admin2_code":"2507.0",
    "gn:asciiname":"Karez-e Shaykh Ya'qub",
    "gn:country_code":"AF",
    "gn:dem":1895,
    "gn:feature_class":"P",
    "gn:feature_code":"PPL",
    "gn:name":"K\u0101r\u0113z-e Shaykh Ya\u2018q\u016bb",
    "gn:population":0,
    "gn:timezone":"Asia/Kabul",
    "iso:country":"AF",
    "name:fas_x_preferred":[
        "\u0643\u0627\u0631\u064a\u0632\u0654 \u0634\u064a\u062e \u06cc\u0639\u0642\u0648\u0628"
    ],
    "name:und_x_variant":[
        "Karezi-Sheykh-Yakub",
        "K\u0101\u1e5f\u0113ze Saykh Ya\u2018q\u016bb",
        "K\u0101r\u0113z-e Shaykh Ya\u2018q\u016bb",
        "\u06a9\u0627\u0631\u06d0\u0632 \u0634\u06cc\u062e \u06cc\u0639\u0642\u0648\u0628",
        "K\u0101r\u012bz-e Shaykh Ya\u2018q\u016bb"
    ],
    "wof:name":"Karez-e Shaykh Ya'qub",
    "wof:placetype":"locality"
},
  "geometry": {"coordinates":[67.24943,31.94648],"type":"Point"}
}