{
  "type": "Feature",
  "properties": {
    "gn:admin1_code":"02",
    "gn:admin2_code":"1902",
    "gn:asciiname":"Zaymat",
    "gn:country_code":"AF",
    "gn:dem":828,
    "gn:feature_class":"P",
    "gn:feature_code":"PPL",
    "gn:name":"Z\u0101ymat",
    "gn:population":0,
    "gn:timezone":"Asia/Kabul",
    "iso:country":"AF",
    "name:und_x_variant":[
        "Z\u0101ymat",
        "\u0632\u0627\u06cc\u0645\u062a",
        "Zaymat"
    ],
    "wof:name":"Zaymat",
    "wof:placetype":"locality"
},
  "geometry": {"coordinates":[63.04835,34.99693],"type":"Point"}
}