{
  "type": "Feature",
  "properties": {
    "gn:admin1_code":"08",
    "gn:admin2_code":"604",
    "gn:asciiname":"Dewal-e Muhammad Shah",
    "gn:country_code":"AF",
    "gn:dem":3323,
    "gn:feature_class":"P",
    "gn:feature_code":"PPL",
    "gn:name":"D\u0113w\u0101l-e Mu\u1e29ammad Sh\u0101h",
    "gn:population":0,
    "gn:timezone":"Asia/Kabul",
    "iso:country":"AF",
    "name:fas_x_preferred":[
        "\u062f\u064a\u0648\u0627\u0644\u0654 \u0645\u062d\u0645\u062f \u0634\u0627\u0647"
    ],
    "name:und_x_variant":[
        "Devali-Mukhammedshakh",
        "\u1e0e\u0113w\u0101le Mo\u1e29\u1e0f-S\u0304\u0101h",
        "\u1e0e\u0113w\u0101le Mo\u1e29amma\u1e0f-s\u0101h",
        "D\u012bv\u0101l-e Mo\u1e29ammad Sh\u0101h",
        "D\u0113w\u0101le Mohammed-\u0161\u0101h",
        "Dayw\u0101l-e Mu\u1e29ammad Sh\u0101h",
        "D\u0113w\u0101l-e Mo\u1e29ammad Sh\u0101h",
        "D\u0113w\u0101l-e Mu\u1e29ammad Sh\u0101h",
        "\u062f\u06d0\u0648\u0627\u0644 \u0645\u062d\u0645\u062f \u0634\u0627\u0647"
    ],
    "wof:name":"Dewal-e Muhammad Shah",
    "wof:placetype":"locality"
},
  "geometry": {"coordinates":[68.04606,33.76567],"type":"Point"}
}