{
  "type": "Feature",
  "properties": {
    "gn:admin1_code":"29",
    "gn:admin2_code":"2910.0",
    "gn:asciiname":"Khan Muhammad Kelay",
    "gn:country_code":"AF",
    "gn:dem":1929,
    "gn:feature_class":"P",
    "gn:feature_code":"PPL",
    "gn:name":"Kh\u0101n Mu\u1e29ammad K\u00ealay",
    "gn:population":0,
    "gn:timezone":"Asia/Kabul",
    "iso:country":"AF",
    "wof:name":"Khan Muhammad Kelay",
    "wof:placetype":"locality"
},
  "geometry": {"coordinates":[69.45975,32.96904],"type":"Point"}
}