{
  "type": "Feature",
  "properties": {
    "gn:admin1_code":"41",
    "gn:admin2_code":"3405",
    "gn:asciiname":"Surkh Qolak",
    "gn:country_code":"AF",
    "gn:dem":2426,
    "gn:feature_class":"P",
    "gn:feature_code":"PPL",
    "gn:name":"Surkh Q\u014dlak",
    "gn:population":0,
    "gn:timezone":"Asia/Kabul",
    "iso:country":"AF",
    "name:und_x_variant":[
        "Su\u1e5fkhq\u014dlak",
        "Surkh Q\u014dlak",
        "\u0633\u0631\u062e \u0642\u0648\u0644\u06a9",
        "Sorkh Qowlak"
    ],
    "wof:name":"Surkh Qolak",
    "wof:placetype":"locality"
},
  "geometry": {"coordinates":[65.78771999999999,33.85798],"type":"Point"}
}