{
  "type": "Feature",
  "properties": {
    "gn:admin1_code":"8",
    "gn:admin2_code":"604.0",
    "gn:asciiname":"Qabzar",
    "gn:country_code":"AF",
    "gn:dem":3315,
    "gn:feature_class":"P",
    "gn:feature_code":"PPL",
    "gn:name":"Qabz\u0101r",
    "gn:population":0,
    "gn:timezone":"Asia/Kabul",
    "iso:country":"AF",
    "name:und_x_variant":[
        "Kabzar",
        "Q\u0101bz\u0101r",
        "Qabz\u0101r",
        "\u0642\u0628\u0632\u0627\u0631"
    ],
    "wof:name":"Qabzar",
    "wof:placetype":"locality"
},
  "geometry": {"coordinates":[67.69186999999999,34.10592],"type":"Point"}
}