{
  "type": "Feature",
  "properties": {
    "gn:admin1_code":"23",
    "gn:admin2_code":"2414",
    "gn:asciiname":"Lajar",
    "gn:country_code":"AF",
    "gn:dem":1965,
    "gn:feature_class":"P",
    "gn:feature_code":"PPL",
    "gn:name":"Lajar",
    "gn:population":0,
    "gn:timezone":"Asia/Kabul",
    "iso:country":"AF",
    "name:und_x_variant":[
        "Ladzhar",
        "Lajar",
        "\u0644\u062c\u0631"
    ],
    "wof:name":"Lajar",
    "wof:placetype":"locality"
},
  "geometry": {"coordinates":[66.40445,32.31365],"type":"Point"}
}