{
  "type": "Feature",
  "properties": {
    "gn:admin1_code":"01",
    "gn:admin2_code":"1110",
    "gn:asciiname":"Kharkat-e Bala",
    "gn:country_code":"AF",
    "gn:dem":1922,
    "gn:feature_class":"P",
    "gn:feature_code":"PPL",
    "gn:name":"Kharkat-e B\u0101l\u0101",
    "gn:population":0,
    "gn:timezone":"Asia/Kabul",
    "iso:country":"AF",
    "name:und_x_variant":[
        "Khar Kate-e B\u0101l\u0101",
        "Kharkat-i-P\u0101la",
        "Khar Khat",
        "Khar Kat",
        "Kha\u1e5fkat-i-B\u0101l\u0101",
        "Kharkat-e B\u0101l\u0101",
        "\u062e\u0631\u06a9\u062a \u0628\u0627\u0644\u0627"
    ],
    "wof:name":"Kharkat-e Bala",
    "wof:placetype":"locality"
},
  "geometry": {"coordinates":[70.92799000000002,38.27428],"type":"Point"}
}