{
  "type": "Feature",
  "properties": {
    "gn:admin1_code":"18",
    "gn:admin2_code":"806.0",
    "gn:asciiname":"Masto Khel",
    "gn:country_code":"AF",
    "gn:dem":1019,
    "gn:feature_class":"P",
    "gn:feature_code":"PPL",
    "gn:name":"Mast\u014d Kh\u0113l",
    "gn:population":0,
    "gn:timezone":"Asia/Kabul",
    "iso:country":"AF",
    "name:fas_x_preferred":[
        "\u0645\u0633\u062a\u0648 \u062e\u064a\u0644"
    ],
    "name:rus_x_preferred":[
        "Mastokheyl\u2019"
    ],
    "name:und_x_variant":[
        "Mast\u014d Kh\u0113l",
        "Mastowkheyl",
        "\u0645\u0633\u062a\u0648 \u062e\u06d0\u0644"
    ],
    "wof:name":"Masto Khel",
    "wof:placetype":"locality"
},
  "geometry": {"coordinates":[70.34031999999999,34.25136],"type":"Point"}
}