{
  "type": "Feature",
  "properties": {
    "gn:admin1_code":"7",
    "gn:admin2_code":"1804.0",
    "gn:asciiname":"Bash-e Bilmast",
    "gn:country_code":"AF",
    "gn:dem":827,
    "gn:feature_class":"P",
    "gn:feature_code":"PPL",
    "gn:name":"B\u0101sh-e Bilmast",
    "gn:population":0,
    "gn:timezone":"Asia/Kabul",
    "iso:country":"AF",
    "name:und_x_variant":[
        "Bas\u0304-i-Belmast",
        "B\u0101sh-e Bilmast",
        "\u0628\u0627\u0634 \u0628\u0644\u0645\u0633\u062a",
        "Bash-e Belmast"
    ],
    "wof:name":"Bash-e Bilmast",
    "wof:placetype":"locality"
},
  "geometry": {"coordinates":[63.96543000000001,35.72543],"type":"Point"}
}