{
  "type": "Feature",
  "properties": {
    "gn:admin1_code":"8",
    "gn:admin2_code":"606.0",
    "gn:asciiname":"Gharsang",
    "gn:country_code":"AF",
    "gn:dem":3175,
    "gn:feature_class":"P",
    "gn:feature_code":"PPL",
    "gn:name":"Gh\u0101rsang",
    "gn:population":0,
    "gn:timezone":"Asia/Kabul",
    "iso:country":"AF",
    "name:und_x_variant":[
        "Gh\u0101rsang",
        "\u063a\u0627\u0631\u0633\u0646\u06af",
        "Gha\u1e5fsang"
    ],
    "wof:name":"Gharsang",
    "wof:placetype":"locality"
},
  "geometry": {"coordinates":[67.1148,33.22292],"type":"Point"}
}