{
  "type": "Feature",
  "properties": {
    "gn:admin1_code":"40",
    "gn:admin2_code":"302.0",
    "gn:asciiname":"Tutak",
    "gn:country_code":"AF",
    "gn:dem":1822,
    "gn:feature_class":"P",
    "gn:feature_code":"PPL",
    "gn:name":"T\u016btak",
    "gn:population":0,
    "gn:timezone":"Asia/Kabul",
    "iso:country":"AF",
    "name:fas_x_preferred":[
        "\u062a\u0648\u062a\u0643"
    ],
    "name:und_x_variant":[
        "T\u016btak",
        "\u062a\u0648\u062a\u06a9"
    ],
    "wof:name":"Tutak",
    "wof:placetype":"locality"
},
  "geometry": {"coordinates":[69.11604,35.09752],"type":"Point"}
}