{
  "type": "Feature",
  "properties": {
    "gn:admin1_code":"01",
    "gn:admin2_code":"1102",
    "gn:asciiname":"Gang Shahr",
    "gn:country_code":"AF",
    "gn:dem":1438,
    "gn:feature_class":"P",
    "gn:feature_code":"PPL",
    "gn:name":"Gang Shahr",
    "gn:population":0,
    "gn:timezone":"Asia/Kabul",
    "iso:country":"AF",
    "name:und_x_variant":[
        "Gang Sah\u1e5f",
        "Gang Shahr",
        "\u06af\u0646\u06af \u0634\u0647\u0631"
    ],
    "wof:name":"Gang Shahr",
    "wof:placetype":"locality"
},
  "geometry": {"coordinates":[70.15739000000001,36.69603],"type":"Point"}
}