{
  "type": "Feature",
  "properties": {
    "gn:admin1_code":"27",
    "gn:admin2_code":"409.0",
    "gn:asciiname":"Qal'ah-ye Kako",
    "gn:country_code":"AF",
    "gn:dem":2449,
    "gn:feature_class":"P",
    "gn:feature_code":"PPL",
    "gn:name":"Qal\u2018ah-ye K\u0101k\u014d",
    "gn:population":0,
    "gn:timezone":"Asia/Kabul",
    "iso:country":"AF",
    "name:und_x_variant":[
        "Kalakaku",
        "Qal\u2018a-i-Kako",
        "Qal\u2018a Kako",
        "Qal\u2018ah-ye K\u0101k\u014d",
        "Qal\u2018eh-ye K\u0101ko",
        "\u0642\u0644\u0639\u0647 \u0643\u0627\u0643\u0648"
    ],
    "wof:name":"Qal'ah-ye Kako",
    "wof:placetype":"locality"
},
  "geometry": {"coordinates":[68.30539,33.74631],"type":"Point"}
}