{
  "type": "Feature",
  "properties": {
    "gn:admin1_code":"29",
    "gn:admin2_code":"2909.0",
    "gn:asciiname":"Khwajar Khel",
    "gn:country_code":"AF",
    "gn:dem":2461,
    "gn:feature_class":"P",
    "gn:feature_code":"PPL",
    "gn:name":"Khw\u0101jar Kh\u0113l",
    "gn:population":0,
    "gn:timezone":"Asia/Kabul",
    "iso:country":"AF",
    "name:und_x_variant":[
        "Khodzharkheyl\u2019",
        "Khw\u0101jar Kh\u0113l",
        "Khw\u0101jah Kh\u0113l",
        "Khv\u0101jar Kheyl",
        "\u062e\u0648\u0627\u062c\u0631 \u062e\u06d0\u0644",
        "\u062e\u0648\u0627\u062c\u0647 \u062e\u06d0\u0644"
    ],
    "wof:name":"Khwajar Khel",
    "wof:placetype":"locality"
},
  "geometry": {"coordinates":[69.34295999999999,32.57606],"type":"Point"}
}