{
  "type": "Feature",
  "properties": {
    "gn:admin1_code":"3",
    "gn:admin2_code":"1305.0",
    "gn:asciiname":"Narm Qolak",
    "gn:country_code":"AF",
    "gn:dem":2151,
    "gn:feature_class":"P",
    "gn:feature_code":"PPL",
    "gn:name":"Narm Q\u014dlak",
    "gn:population":0,
    "gn:timezone":"Asia/Kabul",
    "iso:country":"AF",
    "name:und_x_variant":[
        "Na\u1e5fmq\u014dlak",
        "Narmqowlak",
        "Narm Q\u014dlak",
        "\u0646\u0631\u0645 \u0642\u0648\u0644\u06a9"
    ],
    "wof:name":"Narm Qolak",
    "wof:placetype":"locality"
},
  "geometry": {"coordinates":[68.14519,35.2245],"type":"Point"}
}