{
  "type": "Feature",
  "properties": {
    "gn:admin1_code":"37",
    "gn:admin2_code":"3201",
    "gn:asciiname":"Sash Khel",
    "gn:country_code":"AF",
    "gn:dem":1244,
    "gn:feature_class":"P",
    "gn:feature_code":"PPL",
    "gn:name":"Sash Kh\u0113l",
    "gn:population":0,
    "gn:timezone":"Asia/Kabul",
    "iso:country":"AF",
    "name:fas_x_preferred":[
        "\u0633\u0634 \u062e\u064a\u0644"
    ],
    "name:rus_x_preferred":[
        "Samkheyl\u2019"
    ],
    "name:und_x_variant":[
        "Sa\u0161kh\u0113l",
        "Sash Kh\u0113l",
        "Sash Kheyl",
        "\u0633\u0634 \u062e\u06d0\u0644"
    ],
    "wof:name":"Sash Khel",
    "wof:placetype":"locality"
},
  "geometry": {"coordinates":[69.91383,33.36943],"type":"Point"}
}