{
  "type": "Feature",
  "properties": {
    "gn:admin1_code":"35",
    "gn:admin2_code":"905.0",
    "gn:asciiname":"Tarang",
    "gn:country_code":"AF",
    "gn:dem":972,
    "gn:feature_class":"P",
    "gn:feature_code":"PPL",
    "gn:name":"Tarang",
    "gn:population":0,
    "gn:timezone":"Asia/Kabul",
    "iso:country":"AF",
    "name:hin_x_preferred":[
        "\u0924\u0930\u0902\u0917"
    ],
    "name:und_x_variant":[
        "\u062a\u0631\u0646\u06af"
    ],
    "wof:name":"Tarang",
    "wof:placetype":"locality"
},
  "geometry": {"coordinates":[70.11445999999999,34.75109],"type":"Point"}
}