{
  "type": "Feature",
  "properties": {
    "gn:admin1_code":"8",
    "gn:admin2_code":"609.0",
    "gn:asciiname":"Ahmaday",
    "gn:country_code":"AF",
    "gn:dem":1940,
    "gn:feature_class":"P",
    "gn:feature_code":"PPL",
    "gn:name":"A\u1e29maday",
    "gn:population":0,
    "gn:timezone":"Asia/Kabul",
    "iso:country":"AF",
    "name:und_x_variant":[
        "Akhmeday",
        "A\u1e29maday",
        "\u0627\u062d\u0645\u062f\u06cc",
        "A\u1e29ma\u1e0fay"
    ],
    "wof:name":"Ahmaday",
    "wof:placetype":"locality"
},
  "geometry": {"coordinates":[67.74195999999999,32.68236],"type":"Point"}
}