{
  "type": "Feature",
  "properties": {
    "gn:admin1_code":"29",
    "gn:admin2_code":"2906.0",
    "gn:asciiname":"Shawzeh Katsunah",
    "gn:country_code":"AF",
    "gn:dem":2463,
    "gn:feature_class":"P",
    "gn:feature_code":"PPL",
    "gn:name":"Sh\u0101wz\u00eah Kats\u016bnah",
    "gn:population":0,
    "gn:timezone":"Asia/Kabul",
    "iso:country":"AF",
    "name:fas_x_preferred":[
        "\u0634\u0627\u0648\u0632\u0647 \u0643\u0686\u0648\u0646\u0647"
    ],
    "name:und_x_variant":[
        "\u0160\u0101wzeh Kacona",
        "Shauza-Kachona",
        "\u0634\u0627\u0648\u0632\u0647 \u06a9\u0685\u0648\u0646\u0647",
        "Sh\u0101wzeh Katsownah",
        "Sh\u0101wz\u00eah Kats\u016bnah"
    ],
    "wof:name":"Shawzeh Katsunah",
    "wof:placetype":"locality"
},
  "geometry": {"coordinates":[68.56414000000001,32.32479],"type":"Point"}
}