{
  "type": "Feature",
  "properties": {
    "gn:admin1_code":"05",
    "gn:admin2_code":"2805.0",
    "gn:asciiname":"Qal'ah-ye Wakil",
    "gn:country_code":"AF",
    "gn:dem":2772,
    "gn:feature_class":"P",
    "gn:feature_code":"PPL",
    "gn:name":"Qal\u2018ah-ye Wak\u012bl",
    "gn:population":0,
    "gn:timezone":"Asia/Kabul",
    "iso:country":"AF",
    "name:rus_x_preferred":[
        "Kalavakil\u2019"
    ],
    "name:und_x_variant":[
        "Qal\u2018a Wak\u012bl",
        "Qal\u2018a-i-Wak\u012bl",
        "Qal\u2018ah-ye Wak\u012bl",
        "Qal\u2018eh-ye-Vak\u012bl",
        "\u0642\u0644\u0639\u0647 \u0648\u06a9\u064a\u0644"
    ],
    "wof:name":"Qal'ah-ye Wakil",
    "wof:placetype":"locality"
},
  "geometry": {"coordinates":[67.04756999999999,34.41404],"type":"Point"}
}