{
  "type": "Feature",
  "properties": {
    "gn:admin1_code":"10",
    "gn:admin2_code":"2313",
    "gn:asciiname":"Dewalak",
    "gn:country_code":"AF",
    "gn:dem":648,
    "gn:feature_class":"P",
    "gn:feature_code":"PPL",
    "gn:name":"D\u0113w\u0101lak",
    "gn:population":0,
    "gn:timezone":"Asia/Kabul",
    "iso:country":"AF",
    "name:und_x_variant":[
        "\u1e0eew\u0101lak",
        "Diw\u0101lak",
        "D\u0113w\u0101lak",
        "\u062f\u06d0\u0648\u0627\u0644\u06a9",
        "D\u012bv\u0101lak"
    ],
    "wof:name":"Dewalak",
    "wof:placetype":"locality"
},
  "geometry": {"coordinates":[63.93438,30.55701],"type":"Point"}
}