{
  "type": "Feature",
  "properties": {
    "gn:admin1_code":"41",
    "gn:admin2_code":"3404",
    "gn:asciiname":"Zard Sang",
    "gn:country_code":"AF",
    "gn:dem":1328,
    "gn:feature_class":"P",
    "gn:feature_code":"PPL",
    "gn:name":"Zard Sang",
    "gn:population":0,
    "gn:timezone":"Asia/Kabul",
    "iso:country":"AF",
    "name:und_x_variant":[
        "\u0632\u0631\u062f \u0633\u0646\u06af",
        "Zard Sang",
        "Za\u1e5f\u1e0fsang"
    ],
    "wof:name":"Zard Sang",
    "wof:placetype":"locality"
},
  "geometry": {"coordinates":[65.5108,33.20626],"type":"Point"}
}