{
  "type": "Feature",
  "properties": {
    "gn:admin1_code":"01",
    "gn:admin2_code":"1103",
    "gn:asciiname":"Pular",
    "gn:country_code":"AF",
    "gn:dem":2773,
    "gn:feature_class":"P",
    "gn:feature_code":"PPL",
    "gn:name":"P\u016blar",
    "gn:population":0,
    "gn:timezone":"Asia/Kabul",
    "iso:country":"AF",
    "name:und_x_variant":[
        "\u067e\u0648\u0644\u0631",
        "P\u016blar"
    ],
    "wof:name":"Pular",
    "wof:placetype":"locality"
},
  "geometry": {"coordinates":[70.98869000000001,36.79994],"type":"Point"}
}