{
  "type": "Feature",
  "properties": {
    "gn:admin1_code":"23",
    "gn:admin2_code":"2401.0",
    "gn:asciiname":"Hukumati Dand",
    "gn:country_code":"AF",
    "gn:dem":1004,
    "gn:feature_class":"P",
    "gn:feature_code":"PPL",
    "gn:name":"\u1e28uk\u016bmat\u012b \u1e0ean\u1e0f",
    "gn:population":0,
    "gn:timezone":"Asia/Kabul",
    "iso:country":"AF",
    "name:fas_x_preferred":[
        "\u062d\u0643\u0648\u0645\u062a\u06cc \u062f\u0646\u062f"
    ],
    "name:und_x_variant":[
        "\u1e28ok\u016bmat\u012b \u1e0ean\u1e0f",
        "\u062d\u06a9\u0648\u0645\u062a\u06cc \u0689\u0646\u0689",
        "\u1e28ok\u016bmat\u012b Dand",
        "Dand",
        "\u1e28uk\u016bmat\u012b \u1e0ean\u1e0f",
        "\u1e0ean\u1e0f",
        "\u0689\u0646\u0689"
    ],
    "wof:name":"Hukumati Dand",
    "wof:placetype":"locality"
},
  "geometry": {"coordinates":[65.68300000000001,31.61483],"type":"Point"}
}