{
  "type": "Feature",
  "properties": {
    "gn:admin1_code":"8",
    "gn:admin2_code":"606.0",
    "gn:asciiname":"Sabzak",
    "gn:country_code":"AF",
    "gn:dem":2827,
    "gn:feature_class":"P",
    "gn:feature_code":"PPL",
    "gn:name":"Sabzak",
    "gn:population":0,
    "gn:timezone":"Asia/Kabul",
    "iso:country":"AF",
    "name:ceb_x_preferred":[
        "Sabzak"
    ],
    "name:fas_x_preferred":[
        "\u0633\u0628\u0632\u06a9"
    ],
    "name:swe_x_preferred":[
        "Sabzak"
    ],
    "name:urd_x_preferred":[
        "\u0633\u0628\u0632\u0627\u06a9"
    ],
    "wof:name":"Sabzak",
    "wof:placetype":"locality"
},
  "geometry": {"coordinates":[67.40369,33.41501],"type":"Point"}
}