{
  "type": "Feature",
  "properties": {
    "gn:admin1_code":"26",
    "gn:admin2_code":"1208.0",
    "gn:asciiname":"Chalmah Qazaq",
    "gn:country_code":"AF",
    "gn:dem":1258,
    "gn:feature_class":"P",
    "gn:feature_code":"PPL",
    "gn:name":"Chalmah Qaz\u0101q",
    "gn:population":0,
    "gn:timezone":"Asia/Kabul",
    "iso:country":"AF",
    "name:und_x_variant":[
        "Chalmah Qaz\u0101q",
        "\u0686\u0644\u0645\u0647 \u0642\u0632\u0627\u0642"
    ],
    "wof:name":"Chalmah Qazaq",
    "wof:placetype":"locality"
},
  "geometry": {"coordinates":[69.99124999999999,37.00812],"type":"Point"}
}