{
  "type": "Feature",
  "properties": {
    "gn:admin1_code":"28",
    "gn:admin2_code":"2502",
    "gn:asciiname":"Qal'ah-ye Safar",
    "gn:country_code":"AF",
    "gn:dem":1949,
    "gn:feature_class":"P",
    "gn:feature_code":"PPL",
    "gn:name":"Qal\u2018ah-ye \u015eafar",
    "gn:population":0,
    "gn:timezone":"Asia/Kabul",
    "iso:country":"AF",
    "name:und_x_variant":[
        "Qal\u2018a-i-Safar",
        "Kalayi-Safar",
        "Qal\u2018ah-ye \u015eafar",
        "\u0642\u0644\u0639\u06c0 \u0635\u0641\u0631",
        "Qal\u2018eh-ye \u015eafar"
    ],
    "wof:name":"Qal'ah-ye Safar",
    "wof:placetype":"locality"
},
  "geometry": {"coordinates":[67.46736,32.63551],"type":"Point"}
}