{
  "type": "Feature",
  "properties": {
    "gn:admin1_code":"8",
    "gn:admin2_code":"614.0",
    "gn:asciiname":"Chanbar-e Din Muhammad",
    "gn:country_code":"AF",
    "gn:dem":2091,
    "gn:feature_class":"P",
    "gn:feature_code":"PPL",
    "gn:name":"Chanbar-e D\u012bn Mu\u1e29ammad",
    "gn:population":0,
    "gn:timezone":"Asia/Kabul",
    "iso:country":"AF",
    "name:und_x_variant":[
        "Camba\u1e5fe \u1e0e\u012bnmohamma\u1e0f",
        "Chambari-Dinmukhammed",
        "\u010cambare D\u012bnmohammed",
        "Chambar-e D\u012bn Mu\u1e29ammad",
        "Chanbar-e D\u012bn Mo\u1e29ammad",
        "Chanbar-e D\u012bn Mu\u1e29ammad",
        "\u0686\u0646\u0628\u0631 \u062f\u064a\u0646 \u0645\u062d\u0645\u062f"
    ],
    "wof:name":"Chanbar-e Din Muhammad",
    "wof:placetype":"locality"
},
  "geometry": {"coordinates":[68.38722,33.38142],"type":"Point"}
}