{
  "type": "Feature",
  "properties": {
    "gn:admin1_code":"41",
    "gn:admin2_code":"3406",
    "gn:asciiname":"Nowbir",
    "gn:country_code":"AF",
    "gn:dem":1723,
    "gn:feature_class":"P",
    "gn:feature_code":"PPL",
    "gn:name":"Nowbir",
    "gn:population":0,
    "gn:timezone":"Asia/Kabul",
    "iso:country":"AF",
    "name:und_x_variant":[
        "Nawbe\u1e5f",
        "Nawba\u1e5f",
        "Nowbir",
        "\u0646\u0648\u0628\u0631",
        "Nowbar"
    ],
    "wof:name":"Nowbir",
    "wof:placetype":"locality"
},
  "geometry": {"coordinates":[65.57234,33.47589],"type":"Point"}
}