{
  "type": "Feature",
  "properties": {
    "gn:admin1_code":"11",
    "gn:admin2_code":"2012",
    "gn:asciiname":"Khwajah Ispanah",
    "gn:country_code":"AF",
    "gn:dem":1927,
    "gn:feature_class":"P",
    "gn:feature_code":"PPL",
    "gn:name":"Khw\u0101jah Ispanah",
    "gn:population":0,
    "gn:timezone":"Asia/Kabul",
    "iso:country":"AF",
    "name:und_x_variant":[
        "Khw\u0101ja Espana",
        "Khv\u0101jeh Espanah",
        "Khw\u0101jah Ispanah",
        "\u062e\u0648\u0627\u062c\u0647 \u0627\u0633\u067e\u0646\u0647"
    ],
    "wof:name":"Khwajah Ispanah",
    "wof:placetype":"locality"
},
  "geometry": {"coordinates":[63.27307,34.21901],"type":"Point"}
}