{
  "type": "Feature",
  "properties": {
    "gn:admin1_code":"28",
    "gn:admin2_code":"2509.0",
    "gn:asciiname":"Galey",
    "gn:country_code":"AF",
    "gn:dem":2148,
    "gn:feature_class":"P",
    "gn:feature_code":"PPL",
    "gn:name":"Gal\u00eay",
    "gn:population":0,
    "gn:timezone":"Asia/Kabul",
    "iso:country":"AF",
    "name:und_x_variant":[
        "Galay",
        "Gal\u00eay",
        "\u06af\u0644\u06cd",
        "Gal\u0113y"
    ],
    "wof:name":"Galey",
    "wof:placetype":"locality"
},
  "geometry": {"coordinates":[67.72126,32.06717],"type":"Point"}
}