{
  "type": "Feature",
  "properties": {
    "gn:admin1_code":"34",
    "gn:admin2_code":"1011.0",
    "gn:asciiname":"Kuz Bajgal",
    "gn:country_code":"AF",
    "gn:dem":1080,
    "gn:feature_class":"P",
    "gn:feature_code":"PPL",
    "gn:name":"K\u016bz B\u0101jgal",
    "gn:population":0,
    "gn:timezone":"Asia/Kabul",
    "iso:country":"AF",
    "name:fas_x_preferred":[
        "\u0643\u0648\u0632 \u0628\u0627\u062c\u06af\u0644"
    ],
    "name:rus_x_preferred":[
        "Kuz-Badzhgal\u2019"
    ],
    "name:und_x_variant":[
        "K\u016bz B\u0101jgal"
    ],
    "wof:name":"Kuz Bajgal",
    "wof:placetype":"locality"
},
  "geometry": {"coordinates":[71.00929000000002,34.78601],"type":"Point"}
}