{
  "type": "Feature",
  "properties": {
    "gn:admin1_code":"8",
    "gn:admin2_code":"604.0",
    "gn:asciiname":"Bodak",
    "gn:country_code":"AF",
    "gn:dem":2966,
    "gn:feature_class":"P",
    "gn:feature_code":"PPL",
    "gn:name":"B\u014ddak",
    "gn:population":0,
    "gn:timezone":"Asia/Kabul",
    "iso:country":"AF",
    "name:und_x_variant":[
        "B\u014d\u1e0fak",
        "Bow\u1e0fak",
        "B\u014ddak",
        "\u0628\u0648\u062f\u06a9"
    ],
    "wof:name":"Bodak",
    "wof:placetype":"locality"
},
  "geometry": {"coordinates":[67.45477,33.67256],"type":"Point"}
}