{
  "type": "Feature",
  "properties": {
    "gn:admin1_code":"10",
    "gn:admin2_code":"2305.0",
    "gn:asciiname":"Jar-e Ghar",
    "gn:country_code":"AF",
    "gn:dem":1554,
    "gn:feature_class":"P",
    "gn:feature_code":"PPL",
    "gn:name":"Jar-e Gh\u0101r",
    "gn:population":0,
    "gn:timezone":"Asia/Kabul",
    "iso:country":"AF",
    "name:und_x_variant":[
        "Dzhari-Gar",
        "Jar-e Gh\u0101r",
        "\u062c\u0631 \u063a\u0627\u0631",
        "Ja\u1e5f\u0113 Ghar"
    ],
    "wof:name":"Jar-e Ghar",
    "wof:placetype":"locality"
},
  "geometry": {"coordinates":[65.02359,32.74681],"type":"Point"}
}