{
  "type": "Feature",
  "properties": {
    "gn:admin1_code":"32",
    "gn:admin2_code":"1503",
    "gn:asciiname":"Khwajah Gul",
    "gn:country_code":"AF",
    "gn:dem":1735,
    "gn:feature_class":"P",
    "gn:feature_code":"PPL",
    "gn:name":"Khw\u0101jah Gul",
    "gn:population":0,
    "gn:timezone":"Asia/Kabul",
    "iso:country":"AF",
    "name:und_x_variant":[
        "Khw\u0101jagul",
        "Khv\u0101jeh Gol",
        "Khw\u0101jah Gul",
        "\u062e\u0648\u0627\u062c\u0647 \u06af\u0644"
    ],
    "wof:name":"Khwajah Gul",
    "wof:placetype":"locality"
},
  "geometry": {"coordinates":[67.40163000000001,35.84975],"type":"Point"}
}