{
  "type": "Feature",
  "properties": {
    "gn:admin1_code":"40",
    "gn:admin2_code":"306.0",
    "gn:asciiname":"Katah Sang",
    "gn:country_code":"AF",
    "gn:dem":2379,
    "gn:feature_class":"P",
    "gn:feature_code":"PPL",
    "gn:name":"Katah Sang",
    "gn:population":0,
    "gn:timezone":"Asia/Kabul",
    "iso:country":"AF",
    "name:und_x_variant":[
        "Katasang",
        "Katahsang",
        "Katah Sang",
        "\u06a9\u062a\u0647 \u0633\u0646\u06af"
    ],
    "wof:name":"Katah Sang",
    "wof:placetype":"locality"
},
  "geometry": {"coordinates":[68.44229,34.91604],"type":"Point"}
}