{
  "type": "Feature",
  "properties": {
    "gn:admin1_code":"08",
    "gn:admin2_code":"607",
    "gn:asciiname":"Jowi",
    "gn:country_code":"AF",
    "gn:dem":2690,
    "gn:feature_class":"P",
    "gn:feature_code":"PPL",
    "gn:name":"Jow\u012b",
    "gn:population":0,
    "gn:timezone":"Asia/Kabul",
    "iso:country":"AF",
    "name:rus_x_preferred":[
        "\u0414\u0436\u0430\u0432\u0438"
    ],
    "name:und_x_variant":[
        "Dzhavi",
        "Jaw\u012b",
        "Jow\u012b",
        "\u062c\u0648\u06cc"
    ],
    "wof:name":"Jowi",
    "wof:placetype":"locality"
},
  "geometry": {"coordinates":[67.63033,33.04355],"type":"Point"}
}