{
  "type": "Feature",
  "properties": {
    "gn:admin1_code":"01",
    "gn:admin2_code":"1109.0",
    "gn:asciiname":"Pidrud",
    "gn:country_code":"AF",
    "gn:dem":2124,
    "gn:feature_class":"P",
    "gn:feature_code":"PPL",
    "gn:name":"Pidr\u016bd",
    "gn:population":0,
    "gn:timezone":"Asia/Kabul",
    "iso:country":"AF",
    "name:und_x_variant":[
        "Pidr\u016bd",
        "\u067e\u062f\u0631\u0648\u062f"
    ],
    "wof:name":"Pidrud",
    "wof:placetype":"locality"
},
  "geometry": {"coordinates":[71.50017,37.59085],"type":"Point"}
}