{
  "type": "Feature",
  "properties": {
    "gn:admin1_code":"05",
    "gn:admin2_code":"2806",
    "gn:asciiname":"Nisbatu",
    "gn:country_code":"AF",
    "gn:dem":2993,
    "gn:feature_class":"P",
    "gn:feature_code":"PPL",
    "gn:name":"Nisbat\u016b",
    "gn:population":0,
    "gn:timezone":"Asia/Kabul",
    "iso:country":"AF",
    "name:und_x_variant":[
        "Nesbat\u016b",
        "Nesbatu",
        "Nisbat\u016b",
        "\u0646\u0633\u0628\u062a\u0648"
    ],
    "wof:name":"Nisbatu",
    "wof:placetype":"locality"
},
  "geometry": {"coordinates":[66.98243000000001,34.12378],"type":"Point"}
}