{
  "type": "Feature",
  "properties": {
    "gn:admin1_code":"27",
    "gn:admin2_code":"405",
    "gn:asciiname":"Gardan Nisar",
    "gn:country_code":"AF",
    "gn:dem":2848,
    "gn:feature_class":"P",
    "gn:feature_code":"PPL",
    "gn:name":"Gardan Nis\u0304\u0101r",
    "gn:population":0,
    "gn:timezone":"Asia/Kabul",
    "iso:country":"AF",
    "name:und_x_variant":[
        "Gardannisar",
        "Gardan Nis\u0304\u0101r",
        "Gardan Nes\u0304\u0101r",
        "\u06af\u0631\u062f\u0646 \u0646\u062b\u0627\u0631"
    ],
    "wof:name":"Gardan Nisar",
    "wof:placetype":"locality"
},
  "geometry": {"coordinates":[68.30199,34.36577],"type":"Point"}
}