{
  "type": "Feature",
  "properties": {
    "gn:admin1_code":"42",
    "gn:admin2_code":"3305.0",
    "gn:asciiname":"Arzawah",
    "gn:country_code":"AF",
    "gn:dem":2520,
    "gn:feature_class":"P",
    "gn:feature_code":"PPL",
    "gn:name":"\u0100rz\u0101wah",
    "gn:population":0,
    "gn:timezone":"Asia/Kabul",
    "iso:country":"AF",
    "name:und_x_variant":[
        "Arzava",
        "\u0100\u1e5fz\u0101wa",
        "\u0100rz\u0101veh",
        "\u0100rz\u0101wah",
        "\u0622\u0631\u0632\u0627\u0648\u0647"
    ],
    "wof:name":"Arzawah",
    "wof:placetype":"locality"
},
  "geometry": {"coordinates":[69.28246,35.25023],"type":"Point"}
}