{
  "type": "Feature",
  "properties": {
    "gn:admin1_code":"08",
    "gn:admin2_code":"604.0",
    "gn:asciiname":"Garmak",
    "gn:country_code":"AF",
    "gn:dem":2827,
    "gn:feature_class":"P",
    "gn:feature_code":"PPL",
    "gn:name":"Garmak",
    "gn:population":0,
    "gn:timezone":"Asia/Kabul",
    "iso:country":"AF",
    "name:ceb_x_preferred":[
        "Garmak"
    ],
    "name:fas_x_preferred":[
        "\u06af\u0631\u0645\u06a9"
    ],
    "name:swe_x_preferred":[
        "Garmak"
    ],
    "wof:name":"Garmak",
    "wof:placetype":"locality"
},
  "geometry": {"coordinates":[67.44199,34.05364],"type":"Point"}
}