{
  "type": "Feature",
  "properties": {
    "gn:admin1_code":"01",
    "gn:admin2_code":"1119.0",
    "gn:asciiname":"Kushlar",
    "gn:country_code":"AF",
    "gn:dem":2364,
    "gn:feature_class":"P",
    "gn:feature_code":"PPL",
    "gn:name":"Kushlar",
    "gn:population":0,
    "gn:timezone":"Asia/Kabul",
    "iso:country":"AF",
    "name:und_x_variant":[
        "Kusla\u1e5f",
        "Kushlar",
        "\u06a9\u0634\u0644\u0631"
    ],
    "wof:name":"Kushlar",
    "wof:placetype":"locality"
},
  "geometry": {"coordinates":[70.65778,37.45642],"type":"Point"}
}