{
  "type": "Feature",
  "properties": {
    "gn:admin1_code":"30",
    "gn:admin2_code":"1603.0",
    "gn:asciiname":"Band-e Chap",
    "gn:country_code":"AF",
    "gn:dem":2113,
    "gn:feature_class":"P",
    "gn:feature_code":"PPL",
    "gn:name":"Band-e Chap",
    "gn:population":0,
    "gn:timezone":"Asia/Kabul",
    "iso:country":"AF",
    "name:und_x_variant":[
        "\u0628\u0646\u062f \u0686\u067e",
        "Ban\u1e0fe Cep"
    ],
    "wof:name":"Band-e Chap",
    "wof:placetype":"locality"
},
  "geometry": {"coordinates":[66.76246,35.8397],"type":"Point"}
}