{
  "type": "Feature",
  "properties": {
    "gn:admin1_code":"5",
    "gn:admin2_code":"2801.0",
    "gn:asciiname":"But-e Shamamah",
    "gn:country_code":"AF",
    "gn:dem":2507,
    "gn:feature_class":"P",
    "gn:feature_code":"PPL",
    "gn:name":"But-e Sh\u0101m\u0101mah",
    "gn:population":0,
    "gn:timezone":"Asia/Kabul",
    "iso:country":"AF",
    "name:und_x_variant":[
        "Bute \u0160\u0101m\u0101ma",
        "But-e Sh\u0101m\u0101mah",
        "Bot-e Sh\u0101m\u0101meh",
        "\u0628\u062a \u0634\u0627\u0645\u0645\u0647"
    ],
    "wof:name":"But-e Shamamah",
    "wof:placetype":"locality"
},
  "geometry": {"coordinates":[67.82677,34.8296],"type":"Point"}
}