{
  "type": "Feature",
  "properties": {
    "gn:admin1_code":"18",
    "gn:admin2_code":"801.0",
    "gn:asciiname":"Qal'ah-ye Muqam Khan",
    "gn:country_code":"AF",
    "gn:dem":601,
    "gn:feature_class":"P",
    "gn:feature_code":"PPL",
    "gn:name":"Qal\u2018ah-ye Muq\u0101m Kh\u0101n",
    "gn:population":0,
    "gn:timezone":"Asia/Kabul",
    "iso:country":"AF",
    "name:fas_x_preferred":[
        "\u0642\u0644\u0639\u0647\u064b \u0645\u0642\u0627\u0645 \u062e\u0627\u0646"
    ],
    "name:und_x_variant":[
        "Kalamukamkhan",
        "Qal\u2018a Moq\u0101mkh\u0101n",
        "Qal\u2018eh-ye Moq\u0101mkh\u0101n",
        "Qal\u2018ah-ye Muq\u0101m Kh\u0101n",
        "\u0642\u0644\u0639\u06c0 \u0645\u0642\u0627\u0645 \u062e\u0627\u0646"
    ],
    "wof:name":"Qal'ah-ye Muqam Khan",
    "wof:placetype":"locality"
},
  "geometry": {"coordinates":[70.46279,34.40038],"type":"Point"}
}