{
  "type": "Feature",
  "properties": {
    "gn:admin1_code":"37",
    "gn:admin2_code":"3209",
    "gn:asciiname":"Kurru",
    "gn:country_code":"AF",
    "gn:dem":1109,
    "gn:feature_class":"P",
    "gn:feature_code":"PPL",
    "gn:name":"Kur\u1e5f\u016b",
    "gn:population":0,
    "gn:timezone":"Asia/Kabul",
    "iso:country":"AF",
    "name:ceb_x_preferred":[
        "Kurru"
    ],
    "name:fas_x_preferred":[
        "\u0643\u0648\u0631\u0648"
    ],
    "name:swe_x_preferred":[
        "Kurru"
    ],
    "name:und_x_variant":[
        "\u0643\u0648\u0631\u0648",
        "Kur\u1e5f\u016b K\u00ealay",
        "Kurru",
        "Kur\u1e5f\u016b",
        "\u06a9\u0631\u0693\u0648"
    ],
    "wof:name":"Kurru",
    "wof:placetype":"locality"
},
  "geometry": {"coordinates":[70.0569,33.47927],"type":"Point"}
}