{
  "type": "Feature",
  "properties": {
    "gn:admin1_code":"33",
    "gn:admin2_code":"3103",
    "gn:asciiname":"Warwa",
    "gn:country_code":"AF",
    "gn:dem":1400,
    "gn:feature_class":"P",
    "gn:feature_code":"PPL",
    "gn:name":"W\u0101rw\u0101",
    "gn:population":0,
    "gn:timezone":"Asia/Kabul",
    "iso:country":"AF",
    "name:und_x_variant":[
        "W\u0101rw\u0101",
        "\u0648\u0627\u0631\u0648\u0627",
        "W\u0101\u1e5fw\u0101"
    ],
    "wof:name":"Warwa",
    "wof:placetype":"locality"
},
  "geometry": {"coordinates":[65.89659,35.85533],"type":"Point"}
}