{
  "type": "Feature",
  "properties": {
    "gn:admin1_code":"3",
    "gn:admin2_code":"1302.0",
    "gn:asciiname":"Chachan",
    "gn:country_code":"AF",
    "gn:dem":1983,
    "gn:feature_class":"P",
    "gn:feature_code":"PPL",
    "gn:name":"Ch\u0101ch\u0101n",
    "gn:population":0,
    "gn:timezone":"Asia/Kabul",
    "iso:country":"AF",
    "name:und_x_variant":[
        "\u010c\u0101c\u0101n",
        "Ch\u0101ch\u0101n",
        "\u0686\u0627\u0686\u0627\u0646"
    ],
    "wof:name":"Chachan",
    "wof:placetype":"locality"
},
  "geometry": {"coordinates":[69.45274000000001,35.61169],"type":"Point"}
}