{
  "type": "Feature",
  "properties": {
    "gn:admin1_code":"09",
    "gn:admin2_code":"2706",
    "gn:asciiname":"Ispibuz",
    "gn:country_code":"AF",
    "gn:dem":2254,
    "gn:feature_class":"P",
    "gn:feature_code":"PPL",
    "gn:name":"Isp\u012bbuz",
    "gn:population":0,
    "gn:timezone":"Asia/Kabul",
    "iso:country":"AF",
    "name:und_x_variant":[
        "Isp\u012bbuz",
        "\u0627\u0633\u067e\u06cc\u0628\u0632",
        "Espibuz"
    ],
    "wof:name":"Ispibuz",
    "wof:placetype":"locality"
},
  "geometry": {"coordinates":[65.41081,33.64465],"type":"Point"}
}