{
  "type": "Feature",
  "properties": {
    "gn:admin1_code":"13",
    "gn:admin2_code":"110.0",
    "gn:asciiname":"Qal'ah-ye Hasan Khan",
    "gn:country_code":"AF",
    "gn:dem":1791,
    "gn:feature_class":"P",
    "gn:feature_code":"PPLL",
    "gn:name":"Qal\u2018ah-ye \u1e28asan Kh\u0101n",
    "gn:population":0,
    "gn:timezone":"Asia/Kabul",
    "iso:country":"AF",
    "name:und_x_variant":[
        "Qal\u2018ah-ye \u1e28asan Kh\u0101n",
        "\u0642\u0644\u0639\u0647 \u062d\u0633\u0646 \u062e\u0627\u0646"
    ],
    "wof:name":"Qal'ah-ye Hasan Khan",
    "wof:placetype":"locality"
},
  "geometry": {"coordinates":[69.23699999999999,34.47875],"type":"Point"}
}