{
  "type": "Feature",
  "properties": {
    "gn:admin1_code":"11",
    "gn:admin2_code":"2007",
    "gn:asciiname":"Yoqhlan",
    "gn:country_code":"AF",
    "gn:dem":1026,
    "gn:feature_class":"P",
    "gn:feature_code":"PPL",
    "gn:name":"Y\u014dqhlan",
    "gn:population":0,
    "gn:timezone":"Asia/Kabul",
    "iso:country":"AF",
    "name:und_x_variant":[
        "Y\u014dqhlan",
        "\u06cc\u0648\u0642\u0647\u0644\u0646",
        "Yowqhlan"
    ],
    "wof:name":"Yoqhlan",
    "wof:placetype":"locality"
},
  "geometry": {"coordinates":[61.87218000000001,34.9294],"type":"Point"}
}