{
  "type": "Feature",
  "properties": {
    "gn:admin1_code":"05",
    "gn:admin2_code":"2804",
    "gn:asciiname":"Gardan-e 'Anbar",
    "gn:country_code":"AF",
    "gn:dem":2586,
    "gn:feature_class":"P",
    "gn:feature_code":"PPL",
    "gn:name":"Gardan-e \u2018Anbar",
    "gn:population":0,
    "gn:timezone":"Asia/Kabul",
    "iso:country":"AF",
    "name:und_x_variant":[
        "Ga\u1e5f\u1e0fane \u2018Ambar",
        "Gardani-Ambar",
        "Gardan-e \u2018Anbar",
        "\u06af\u0631\u062f\u0646 \u0639\u0646\u0628\u0631"
    ],
    "wof:name":"Gardan-e 'Anbar",
    "wof:placetype":"locality"
},
  "geometry": {"coordinates":[66.7664,34.72688],"type":"Point"}
}