{
  "type": "Feature",
  "properties": {
    "gn:admin1_code":"23",
    "gn:admin2_code":"2416",
    "gn:asciiname":"Sindzaray",
    "gn:country_code":"AF",
    "gn:dem":979,
    "gn:feature_class":"P",
    "gn:feature_code":"PPL",
    "gn:name":"Sindzaray",
    "gn:population":0,
    "gn:timezone":"Asia/Kabul",
    "iso:country":"AF",
    "name:fas_x_preferred":[
        "\u0633\u0646\u062c\u0631\u06cc"
    ],
    "name:und_x_variant":[
        "Sinjiri",
        "Sinjari",
        "Sindzharay",
        "Senjaray",
        "Sindzaray",
        "\u0633\u0646\u0681\u0631\u06cc"
    ],
    "wof:name":"Sindzaray",
    "wof:placetype":"locality"
},
  "geometry": {"coordinates":[65.52923,31.62136],"type":"Point"}
}