{
  "type": "Feature",
  "properties": {
    "gn:admin1_code":"10",
    "gn:admin2_code":"2302.0",
    "gn:asciiname":"Balochan",
    "gn:country_code":"AF",
    "gn:dem":843,
    "gn:feature_class":"P",
    "gn:feature_code":"PPL",
    "gn:name":"Bal\u014dch\u0101n",
    "gn:population":0,
    "gn:timezone":"Asia/Kabul",
    "iso:country":"AF",
    "name:und_x_variant":[
        "Balo\u010d\u0101n",
        "Balochan",
        "Bal\u014dch\u0101n",
        "\u0628\u0644\u0648\u0686\u0627\u0646",
        "Bal\u016bch\u0101n"
    ],
    "wof:name":"Balochan",
    "wof:placetype":"locality"
},
  "geometry": {"coordinates":[64.71529,31.75397],"type":"Point"}
}