{
  "type": "Feature",
  "properties": {
    "gn:admin1_code":"30",
    "gn:admin2_code":"1608.0",
    "gn:asciiname":"Bowrchi",
    "gn:country_code":"AF",
    "gn:dem":1000,
    "gn:feature_class":"P",
    "gn:feature_code":"PPL",
    "gn:name":"Bowrch\u012b",
    "gn:population":0,
    "gn:timezone":"Asia/Kabul",
    "iso:country":"AF",
    "name:por_x_preferred":[
        "Bawrchi"
    ],
    "name:und_x_variant":[
        "Bowrch\u012b",
        "\u0628\u0648\u0631\u0686\u06cc"
    ],
    "wof:name":"Bowrchi",
    "wof:placetype":"locality"
},
  "geometry": {"coordinates":[66.53959999999999,36.36227],"type":"Point"}
}