{
  "type": "Feature",
  "properties": {
    "gn:admin1_code":"10",
    "gn:admin2_code":"2303",
    "gn:asciiname":"Kokah Chel",
    "gn:country_code":"AF",
    "gn:dem":972,
    "gn:feature_class":"P",
    "gn:feature_code":"PPL",
    "gn:name":"K\u014dkah Ch\u0113l",
    "gn:population":0,
    "gn:timezone":"Asia/Kabul",
    "iso:country":"AF",
    "name:rus_x_preferred":[
        "Kukachel\u2019"
    ],
    "name:und_x_variant":[
        "Kokochel",
        "Koka\u010d\u0113l",
        "K\u014dkah Ch\u0113l",
        "\u06a9\u0648\u06a9\u0647 \u0686\u06d0\u0644",
        "Kowkah Ch\u0113l"
    ],
    "wof:name":"Kokah Chel",
    "wof:placetype":"locality"
},
  "geometry": {"coordinates":[64.99021999999999,32.28541],"type":"Point"}
}