{
  "type": "Feature",
  "properties": {
    "gn:admin1_code":"37",
    "gn:admin2_code":"3203.0",
    "gn:asciiname":"Qasim Qul Kelay",
    "gn:country_code":"AF",
    "gn:dem":1255,
    "gn:feature_class":"P",
    "gn:feature_code":"PPL",
    "gn:name":"Q\u0101sim Qul K\u00ealay",
    "gn:population":0,
    "gn:timezone":"Asia/Kabul",
    "iso:country":"AF",
    "name:fas_x_preferred":[
        "\u0642\u0631\u064a\u06c0 \u0642\u0627\u0633\u0645 \u0642\u0644"
    ],
    "name:rus_x_preferred":[
        "Kasimkul\u2019kalay"
    ],
    "name:und_x_variant":[
        "Q\u0101sim Gul K\u00ealay",
        "Q\u0101semqul Kalay",
        "Q\u0101sim Qul K\u00ealay",
        "\u0642\u0627\u0633\u0645 \u0642\u0644 \u06a9\u0644\u06cc"
    ],
    "wof:name":"Qasim Qul Kelay",
    "wof:placetype":"locality"
},
  "geometry": {"coordinates":[69.85616,33.26429],"type":"Point"}
}