{
  "type": "Feature",
  "properties": {
    "gn:admin1_code":"08",
    "gn:admin2_code":"611",
    "gn:asciiname":"Sagi Khel",
    "gn:country_code":"AF",
    "gn:dem":2056,
    "gn:feature_class":"P",
    "gn:feature_code":"PPL",
    "gn:name":"S\u0101g\u012b Kh\u0113l",
    "gn:population":0,
    "gn:timezone":"Asia/Kabul",
    "iso:country":"AF",
    "name:fas_x_preferred":[
        "S\u0101g\u012b Kh\u0113l"
    ],
    "name:fas_x_variant":[
        "\u0633\u0627\u06af\u06cc \u062e\u06d0\u0644"
    ],
    "name:und_x_variant":[
        "S\u014dkikh\u0113l",
        "Sh\u0101k\u012b Kheyl",
        "Sakikh\u0113l",
        "Sa\u012bk\u012b Kheyl",
        "S\u0101q\u012b Kheyl-e Aband",
        "S\u0101k\u012b Kheyl",
        "\u0633\u0627\u06af\u06cc \u062e\u06d0\u0644"
    ],
    "wof:name":"Sagi Khel",
    "wof:placetype":"locality"
},
  "geometry": {"coordinates":[68.15099000000001,32.98576],"type":"Point"}
}