{
  "type": "Feature",
  "properties": {
    "gn:admin1_code":"30",
    "gn:admin2_code":"1608.0",
    "gn:asciiname":"Imam Sahib",
    "gn:country_code":"AF",
    "gn:dem":348,
    "gn:feature_class":"P",
    "gn:feature_code":"PPL",
    "gn:name":"Im\u0101m \u015e\u0101\u1e29ib",
    "gn:population":0,
    "gn:timezone":"Asia/Kabul",
    "iso:country":"AF",
    "name:und_x_variant":[
        "Im\u0101m \u015e\u0101\u1e29ib",
        "\u0627\u0645\u0627\u0645 \u0635\u0627\u062d\u0628",
        "Em\u0101m \u015e\u0101\u1e29eb"
    ],
    "wof:name":"Imam Sahib",
    "wof:placetype":"locality"
},
  "geometry": {"coordinates":[66.50662,36.67297],"type":"Point"}
}