{
  "type": "Feature",
  "properties": {
    "gn:admin1_code":"30",
    "gn:admin2_code":"1608.0",
    "gn:asciiname":"Imam Sahib",
    "gn:country_code":"AF",
    "gn:dem":348,
    "gn:feature_class":"P",
    "gn:feature_code":"PPL",
    "gn:name":"Im\u0101m \u015e\u0101\u1e29ib",
    "gn:population":0,
    "gn:timezone":"Asia/Kabul",
    "iso:country":"AF",
    "name:ceb_x_preferred":[
        "Im\u0101m \u015e\u0101\u1e29ib"
    ],
    "name:dan_x_preferred":[
        "Imam Sahib"
    ],
    "name:deu_x_preferred":[
        "Imam Sahib"
    ],
    "name:fas_x_preferred":[
        "\u0627\u0645\u0627\u0645 \u0635\u0627\u062d\u0628"
    ],
    "name:fra_x_preferred":[
        "Emam Saheb"
    ],
    "name:nld_x_preferred":[
        "Imam Saheb"
    ],
    "name:pol_x_preferred":[
        "Emam Saheb"
    ],
    "name:por_x_preferred":[
        "Emam Saheb"
    ],
    "name:ron_x_preferred":[
        "Emam Saheb"
    ],
    "name:swe_x_preferred":[
        "Im\u0101m \u015e\u0101\u1e29ib"
    ],
    "name:tat_x_preferred":[
        "\u0418\u043c\u0430\u043c\u0441\u04d9\u0445\u0438\u0431"
    ],
    "name:und_x_variant":[
        "Em\u0101m \u015e\u0101\u1e29eb"
    ],
    "wof:name":"Imam Sahib",
    "wof:placetype":"locality"
},
  "geometry": {"coordinates":[66.50662,36.67297],"type":"Point"}
}