{
  "type": "Feature",
  "properties": {
    "gn:admin1_code":"40",
    "gn:admin2_code":"306.0",
    "gn:asciiname":"Kharabah",
    "gn:country_code":"AF",
    "gn:dem":2540,
    "gn:feature_class":"P",
    "gn:feature_code":"PPL",
    "gn:name":"Khar\u0101bah",
    "gn:population":0,
    "gn:timezone":"Asia/Kabul",
    "iso:country":"AF",
    "name:und_x_variant":[
        "Kha\u1e5f\u0101ba",
        "Kharaba",
        "Khar\u0101beh",
        "Khar\u0101bah",
        "\u062e\u0631\u0627\u0628\u0647"
    ],
    "wof:name":"Kharabah",
    "wof:placetype":"locality"
},
  "geometry": {"coordinates":[68.52589,34.96915],"type":"Point"}
}