{
  "type": "Feature",
  "properties": {
    "gn:admin1_code":"30",
    "gn:admin2_code":"1603",
    "gn:asciiname":"Zardabadam",
    "gn:country_code":"AF",
    "gn:dem":2106,
    "gn:feature_class":"P",
    "gn:feature_code":"PPL",
    "gn:name":"Zardab\u0101d\u0101m",
    "gn:population":0,
    "gn:timezone":"Asia/Kabul",
    "iso:country":"AF",
    "name:und_x_variant":[
        "Zardab\u0101d\u0101m",
        "\u0632\u0631\u062f\u0628\u0627\u062f\u0627\u0645",
        "Za\u1e5f\u1e0fab\u0101\u1e0f\u0101m"
    ],
    "wof:name":"Zardabadam",
    "wof:placetype":"locality"
},
  "geometry": {"coordinates":[66.70392,35.81902],"type":"Point"}
}