{
  "type": "Feature",
  "properties": {
    "gn:admin1_code":"24",
    "gn:admin2_code":"1406",
    "gn:asciiname":"Lalah Kay",
    "gn:country_code":"AF",
    "gn:dem":974,
    "gn:feature_class":"P",
    "gn:feature_code":"PPL",
    "gn:name":"L\u0101lah Kay",
    "gn:population":0,
    "gn:timezone":"Asia/Kabul",
    "iso:country":"AF",
    "name:fas_x_preferred":[
        "\u0644\u0627\u0644\u0643\u06cc"
    ],
    "name:rus_x_preferred":[
        "\u041b\u0430\u043b\u0430\u043a\u0430\u0439"
    ],
    "name:und_x_variant":[
        "Lalakay",
        "L\u0101lakay",
        "L\u0101lah Kay",
        "\u0644\u0627\u0644\u0647 \u06a9\u06cc"
    ],
    "wof:name":"Lalah Kay",
    "wof:placetype":"locality"
},
  "geometry": {"coordinates":[69.15613,36.54328],"type":"Point"}
}