{
  "type": "Feature",
  "properties": {
    "gn:admin1_code":"9",
    "gn:admin2_code":"2705.0",
    "gn:asciiname":"Pushtah-ye Kharistan",
    "gn:country_code":"AF",
    "gn:dem":2120,
    "gn:feature_class":"P",
    "gn:feature_code":"PPL",
    "gn:name":"Pushtah-ye Kh\u0101rist\u0101n",
    "gn:population":0,
    "gn:timezone":"Asia/Kabul",
    "iso:country":"AF",
    "name:und_x_variant":[
        "Pushtayi-Kharistan",
        "Pu\u0161ta-i-Kh\u0101rest\u0101n",
        "Pushtah-ye Kh\u0101rist\u0101n",
        "\u067e\u0634\u062a\u06c0 \u062e\u0627\u0631\u0633\u062a\u0627\u0646",
        "Poshteh-ye Kh\u0101rest\u0101n"
    ],
    "wof:name":"Pushtah-ye Kharistan",
    "wof:placetype":"locality"
},
  "geometry": {"coordinates":[64.34513000000001,33.50423],"type":"Point"}
}