{
  "type": "Feature",
  "properties": {
    "gn:admin1_code":"07",
    "gn:admin2_code":"1805",
    "gn:asciiname":"Qudughak",
    "gn:country_code":"AF",
    "gn:dem":1862,
    "gn:feature_class":"P",
    "gn:feature_code":"PPL",
    "gn:name":"Qud\u016bghak",
    "gn:population":0,
    "gn:timezone":"Asia/Kabul",
    "iso:country":"AF",
    "name:und_x_variant":[
        "Qu\u1e0f\u016bghak (1)",
        "Qu\u1e0f\u016bghak",
        "Qud\u016bghak",
        "\u0642\u062f\u0648\u063a\u06a9"
    ],
    "wof:name":"Qudughak",
    "wof:placetype":"locality"
},
  "geometry": {"coordinates":[64.74046,35.34091],"type":"Point"}
}