{
  "type": "Feature",
  "properties": {
    "gn:admin1_code":"14",
    "gn:admin2_code":"205.0",
    "gn:asciiname":"Ghani Khel",
    "gn:country_code":"AF",
    "gn:dem":1329,
    "gn:feature_class":"P",
    "gn:feature_code":"PPL",
    "gn:name":"Ghan\u012b Kh\u0113l",
    "gn:population":0,
    "gn:timezone":"Asia/Kabul",
    "iso:country":"AF",
    "name:fas_x_preferred":[
        "\u063a\u0646\u06cc \u062e\u064a\u0644"
    ],
    "name:rus_x_preferred":[
        "Ganikheyl\u2019"
    ],
    "name:und_x_variant":[
        "Ghanikh\u0113l",
        "Ghanikheyl",
        "Ghan\u012b Kh\u0113l",
        "\u063a\u0646\u06cc \u062e\u06d0\u0644"
    ],
    "wof:name":"Ghani Khel",
    "wof:placetype":"locality"
},
  "geometry": {"coordinates":[69.66141999999999,34.84303],"type":"Point"}
}