{
  "type": "Feature",
  "properties": {
    "gn:admin1_code":"10",
    "gn:admin2_code":"2309.0",
    "gn:asciiname":"Sayyidano Kelay",
    "gn:country_code":"AF",
    "gn:dem":729,
    "gn:feature_class":"P",
    "gn:feature_code":"PPL",
    "gn:name":"Sayyid\u0101n\u014d K\u00ealay",
    "gn:population":0,
    "gn:timezone":"Asia/Kabul",
    "iso:country":"AF",
    "name:und_x_variant":[
        "Saye\u1e0f\u0101no Kalay",
        "Seyyed\u0101no Kalay",
        "Sayyid\u0101n\u014d K\u00ealay",
        "\u0633\u06cc\u062f\u0627\u0646\u0648 \u06a9\u0644\u06cc",
        "Seyyed\u0101n\u016b Kalay"
    ],
    "wof:name":"Sayyidano Kelay",
    "wof:placetype":"locality"
},
  "geometry": {"coordinates":[64.24355,31.30371],"type":"Point"}
}