{
  "type": "Feature",
  "properties": {
    "gn:admin1_code":"11",
    "gn:admin2_code":"2014.0",
    "gn:asciiname":"Chashmah-ye Qal'ah-ye Muhammad",
    "gn:country_code":"AF",
    "gn:dem":1069,
    "gn:feature_class":"P",
    "gn:feature_code":"PPL",
    "gn:name":"Chashmah-ye Qal\u2018ah-ye Mu\u1e29ammad",
    "gn:population":0,
    "gn:timezone":"Asia/Kabul",
    "iso:country":"AF",
    "name:fas_x_preferred":[
        "\u0686\u0634\u0645\u06c0 \u0642\u0644\u063a\u0647\u0654 \u0645\u062d\u0645\u062f"
    ],
    "name:und_x_variant":[
        "\u010ca\u0161ma-i-Qal\u2018a-i-Mohammad",
        "Chashmayi-Kalayi-Mukhammed",
        "Cheshmeh-yeh Qal\u0142eh-ye Mo\u0159ammad",
        "Chashmah-ye Qal\u2018ah-ye Mu\u1e29ammad",
        "\u0686\u0634\u0645\u06c0 \u0642\u0644\u0639\u06c0 \u0645\u062d\u0645\u062f"
    ],
    "wof:name":"Chashmah-ye Qal'ah-ye Muhammad",
    "wof:placetype":"locality"
},
  "geometry": {"coordinates":[62.15922,33.31248],"type":"Point"}
}