{
  "type": "Feature",
  "properties": {
    "gn:admin1_code":"01",
    "gn:admin2_code":"1115.0",
    "gn:asciiname":"Paytwan",
    "gn:country_code":"AF",
    "gn:dem":1874,
    "gn:feature_class":"P",
    "gn:feature_code":"PPL",
    "gn:name":"Paytw\u0101n",
    "gn:population":0,
    "gn:timezone":"Asia/Kabul",
    "iso:country":"AF",
    "name:und_x_variant":[
        "Paytw\u0101n",
        "\u067e\u06cc\u062a\u0648\u0627\u0646",
        "P\u0113tw\u0101n"
    ],
    "wof:name":"Paytwan",
    "wof:placetype":"locality"
},
  "geometry": {"coordinates":[70.41261,37.09065],"type":"Point"}
}