{
  "type": "Feature",
  "properties": {
    "gn:admin1_code":"8",
    "gn:admin2_code":"602.0",
    "gn:asciiname":"Bodah",
    "gn:country_code":"AF",
    "gn:dem":2996,
    "gn:feature_class":"P",
    "gn:feature_code":"PPL",
    "gn:name":"B\u014d\u1e0fah",
    "gn:population":0,
    "gn:timezone":"Asia/Kabul",
    "iso:country":"AF",
    "name:fas_x_preferred":[
        "\u0628\u0648\u062f\u0647"
    ],
    "name:rus_x_preferred":[
        "\u0411\u043e\u0434\u0430"
    ],
    "name:und_x_variant":[
        "Boda",
        "B\u014dda",
        "B\u016bdah",
        "B\u014d\u1e0fah",
        "\u0628\u0648\u0689\u0647"
    ],
    "wof:name":"Bodah",
    "wof:placetype":"locality"
},
  "geometry": {"coordinates":[67.99196999999999,33.48325],"type":"Point"}
}