{
  "type": "Feature",
  "properties": {
    "gn:admin1_code":"34",
    "gn:admin2_code":"1008.0",
    "gn:asciiname":"Shege Korunah",
    "gn:country_code":"AF",
    "gn:dem":848,
    "gn:feature_class":"P",
    "gn:feature_code":"PPL",
    "gn:name":"Sh\u00eag\u0113 K\u014dr\u016bnah",
    "gn:population":0,
    "gn:timezone":"Asia/Kabul",
    "iso:country":"AF",
    "name:fas_x_preferred":[
        "\u0634\u06af\u06cc \u0643\u0648\u0631\u0648\u0646\u0647"
    ],
    "name:und_x_variant":[
        "S\u0113g\u0113 K\u014d\u016bnah",
        "Segekoruna",
        "\u0160\u011bg\u0113 Kor\u016bna",
        "Sheg\u0113 Kowr\u016bnah",
        "Sh\u00eag\u0113 K\u014dr\u016bnah",
        "\u0634\u06af\u06d0 \u06a9\u0648\u0631\u0648\u0646\u0647"
    ],
    "wof:name":"Shege Korunah",
    "wof:placetype":"locality"
},
  "geometry": {"coordinates":[71.12742,34.91068],"type":"Point"}
}