{
  "type": "Feature",
  "properties": {
    "gn:admin1_code":"13",
    "gn:admin2_code":"112.0",
    "gn:asciiname":"Anargay",
    "gn:country_code":"AF",
    "gn:dem":1435,
    "gn:feature_class":"P",
    "gn:feature_code":"PPL",
    "gn:name":"An\u0101rgay",
    "gn:population":0,
    "gn:timezone":"Asia/Kabul",
    "iso:country":"AF",
    "name:fas_x_preferred":[
        "\u0627\u0646\u0627\u0631\u06af\u06cc"
    ],
    "name:und_x_variant":[
        "\u0100n\u0101rga\u012b",
        "An\u0101\u1e5fgay",
        "\u0627\u0646\u0627\u0631\u06af\u06cc",
        "An\u0101rgay",
        "\u0627\u0646\u0627\u0631 \u06af\u06cc"
    ],
    "wof:name":"Anargay",
    "wof:placetype":"locality"
},
  "geometry": {"coordinates":[69.74764999999999,34.47345],"type":"Point"}
}