{
  "type": "Feature",
  "properties": {
    "gn:admin1_code":"13",
    "gn:admin2_code":"112",
    "gn:asciiname":"Katah Sang",
    "gn:country_code":"AF",
    "gn:dem":1470,
    "gn:feature_class":"P",
    "gn:feature_code":"PPL",
    "gn:name":"Katah Sang",
    "gn:population":0,
    "gn:timezone":"Asia/Kabul",
    "iso:country":"AF",
    "name:fas_x_preferred":[
        "\u0643\u062a\u0647\u0633\u0646\u06af"
    ],
    "name:und_x_variant":[
        "\u06a9\u062a\u0647 \u0633\u0646\u06af",
        "Katah Sang K\u00ealay",
        "\u06a9\u062a\u0647 \u0633\u0646\u06af \u06a9\u0644\u06cc",
        "Katasang"
    ],
    "wof:name":"Katah Sang",
    "wof:placetype":"locality"
},
  "geometry": {"coordinates":[69.71865,34.5076],"type":"Point"}
}