{
  "type": "Feature",
  "properties": {
    "gn:admin1_code":"18",
    "gn:admin2_code":"817.0",
    "gn:asciiname":"Garay",
    "gn:country_code":"AF",
    "gn:dem":479,
    "gn:feature_class":"P",
    "gn:feature_code":"PPL",
    "gn:name":"Ga\u1e5fay",
    "gn:population":0,
    "gn:timezone":"Asia/Kabul",
    "iso:country":"AF",
    "name:fas_x_preferred":[
        "\u06af\u0631\u06cc"
    ],
    "name:und_x_variant":[
        "Garai",
        "Garae",
        "Ga\u1e5fay",
        "\u06af\u0693\u06cc"
    ],
    "wof:name":"Garay",
    "wof:placetype":"locality"
},
  "geometry": {"coordinates":[70.79518,34.31425],"type":"Point"}
}