{
  "type": "Feature",
  "properties": {
    "gn:admin1_code":"36",
    "gn:admin2_code":"705",
    "gn:asciiname":"Spinah Kala",
    "gn:country_code":"AF",
    "gn:dem":2489,
    "gn:feature_class":"P",
    "gn:feature_code":"PPL",
    "gn:name":"Sp\u012bnah Kal\u0101",
    "gn:population":0,
    "gn:timezone":"Asia/Kabul",
    "iso:country":"AF",
    "name:fas_x_preferred":[
        "\u0633\u067e\u064a\u0646\u0647 \u0643\u0644\u0627"
    ],
    "name:und_x_variant":[
        "Spinakala",
        "Spina Kal\u0101",
        "Sp\u012bnah Kal\u0101",
        "\u0633\u067e\u06cc\u0646\u0647 \u06a9\u0644\u0627"
    ],
    "wof:name":"Spinah Kala",
    "wof:placetype":"locality"
},
  "geometry": {"coordinates":[69.38066999999999,33.7009],"type":"Point"}
}