{
  "type": "Feature",
  "properties": {
    "gn:admin1_code":"35",
    "gn:admin2_code":"905.0",
    "gn:asciiname":"Siqan Watah",
    "gn:country_code":"AF",
    "gn:dem":1294,
    "gn:feature_class":"P",
    "gn:feature_code":"PPL",
    "gn:name":"Siq\u0101n Watah",
    "gn:population":0,
    "gn:timezone":"Asia/Kabul",
    "iso:country":"AF",
    "name:und_x_variant":[
        "Sikanvata",
        "Seq\u0101nwata",
        "Seq\u0101nwatah",
        "Siq\u0101n Watah",
        "\u0633\u0642\u0627\u0646 \u0648\u062a\u0647",
        "S\u012bq\u0101n Watah",
        "\u0633\u06cc\u0642\u0627\u0646 \u0648\u062a\u0647"
    ],
    "wof:name":"Siqan Watah",
    "wof:placetype":"locality"
},
  "geometry": {"coordinates":[70.10710999999999,34.88527],"type":"Point"}
}