{
  "type": "Feature",
  "properties": {
    "gn:admin1_code":"29",
    "gn:admin2_code":"2901.0",
    "gn:asciiname":"Nur Muhammad Kala",
    "gn:country_code":"AF",
    "gn:dem":2129,
    "gn:feature_class":"P",
    "gn:feature_code":"PPL",
    "gn:name":"N\u016br Mu\u1e29ammad Kal\u0101",
    "gn:population":0,
    "gn:timezone":"Asia/Kabul",
    "iso:country":"AF",
    "name:und_x_variant":[
        "N\u016b\u1e5fmo\u1e29amme\u1e0f Kal\u0101",
        "Nurmukhammed Kala",
        "\u0646\u0648\u0631 \u0645\u062d\u0645\u062f \u06a9\u0644\u0627",
        "Nowr Mu\u1e29ammad Kal\u0101",
        "N\u016br Mo\u1e29ammad Kal\u0101",
        "N\u016br Mu\u1e29ammad Kal\u0101"
    ],
    "wof:name":"Nur Muhammad Kala",
    "wof:placetype":"locality"
},
  "geometry": {"coordinates":[68.77824,33.20771],"type":"Point"}
}