{
  "type": "Feature",
  "properties": {
    "gn:admin1_code":"28",
    "gn:admin2_code":"2510",
    "gn:asciiname":"Rahimdad Kelay",
    "gn:country_code":"AF",
    "gn:dem":2629,
    "gn:feature_class":"P",
    "gn:feature_code":"PPL",
    "gn:name":"Ra\u1e29\u012bmd\u0101d K\u00ealay",
    "gn:population":0,
    "gn:timezone":"Asia/Kabul",
    "iso:country":"AF",
    "name:und_x_variant":[
        "Rakhimdadkalay",
        "Ra\u1e29\u012bmd\u0101d K\u00ealay",
        "\u0631\u062d\u06cc\u0645\u062f\u0627\u062f \u06a9\u0644\u06cc",
        "Ra\u1e29\u012bmd\u0101d Kalay"
    ],
    "wof:name":"Rahimdad Kelay",
    "wof:placetype":"locality"
},
  "geometry": {"coordinates":[67.10445,32.85295],"type":"Point"}
}