{
  "type": "Feature",
  "properties": {
    "gn:admin1_code":"01",
    "gn:admin2_code":"1121",
    "gn:asciiname":"Mah-e Now",
    "gn:country_code":"AF",
    "gn:dem":1711,
    "gn:feature_class":"P",
    "gn:feature_code":"PPL",
    "gn:name":"M\u0101h-e Now",
    "gn:population":0,
    "gn:timezone":"Asia/Kabul",
    "iso:country":"AF",
    "name:und_x_variant":[
        "M\u016bn\u012bk",
        "M\u0101h-i-Naw",
        "Munak",
        "M\u0101now",
        "Mano",
        "M\u0101h-e Now",
        "\u0645\u0627\u0647 \u0646\u0648"
    ],
    "wof:name":"Mah-e Now",
    "wof:placetype":"locality"
},
  "geometry": {"coordinates":[70.6932,38.40015],"type":"Point"}
}