{
  "type": "Feature",
  "properties": {
    "gn:admin1_code":"01",
    "gn:admin2_code":"1110.0",
    "gn:asciiname":"Sar-e Deh",
    "gn:country_code":"AF",
    "gn:dem":1292,
    "gn:feature_class":"P",
    "gn:feature_code":"PPL",
    "gn:name":"Sar-e Deh",
    "gn:population":0,
    "gn:timezone":"Asia/Kabul",
    "iso:country":"AF",
    "name:und_x_variant":[
        "Sa\u1e5f-i-Deh",
        "Sar-e Deh",
        "\u0633\u0631 \u062f\u0647"
    ],
    "wof:name":"Sar-e Deh",
    "wof:placetype":"locality"
},
  "geometry": {"coordinates":[70.81667,38.44336],"type":"Point"}
}