{
  "type": "Feature",
  "properties": {
    "gn:admin1_code":"28",
    "gn:admin2_code":"2507",
    "gn:asciiname":"Dudah",
    "gn:country_code":"AF",
    "gn:dem":1494,
    "gn:feature_class":"P",
    "gn:feature_code":"PPL",
    "gn:name":"D\u016bdah",
    "gn:population":0,
    "gn:timezone":"Asia/Kabul",
    "iso:country":"AF",
    "name:und_x_variant":[
        "\u1e0e\u016b\u1e0fa",
        "Duda",
        "D\u016bdah",
        "\u062f\u0648\u062f\u0647"
    ],
    "wof:name":"Dudah",
    "wof:placetype":"locality"
},
  "geometry": {"coordinates":[66.73071999999999,31.80514],"type":"Point"}
}