{
  "type": "Feature",
  "properties": {
    "gn:admin1_code":"23",
    "gn:admin2_code":"2413",
    "gn:asciiname":"Kajakay",
    "gn:country_code":"AF",
    "gn:dem":2047,
    "gn:feature_class":"P",
    "gn:feature_code":"PPL",
    "gn:name":"Kajakay",
    "gn:population":0,
    "gn:timezone":"Asia/Kabul",
    "iso:country":"AF",
    "name:und_x_variant":[
        "Kadzhakay",
        "Kajakay",
        "Kajak\u012b",
        "\u06a9\u062c\u06a9\u06cc"
    ],
    "wof:name":"Kajakay",
    "wof:placetype":"locality"
},
  "geometry": {"coordinates":[67.55752,31.45436],"type":"Point"}
}