{
  "type": "Feature",
  "properties": {
    "gn:admin1_code":"34",
    "gn:admin2_code":"1013.0",
    "gn:asciiname":"Khundah Shal",
    "gn:country_code":"AF",
    "gn:dem":1916,
    "gn:feature_class":"P",
    "gn:feature_code":"PPL",
    "gn:name":"Khundah Sh\u0101l",
    "gn:population":0,
    "gn:timezone":"Asia/Kabul",
    "iso:country":"AF",
    "wof:name":"Khundah Shal",
    "wof:placetype":"locality"
},
  "geometry": {"coordinates":[70.80843,34.73031],"type":"Point"}
}