{
  "type": "Feature",
  "properties": {
    "gn:admin1_code":"9",
    "gn:admin2_code":"2707.0",
    "gn:asciiname":"Dahan-e Nay Daykundi",
    "gn:country_code":"AF",
    "gn:dem":2801,
    "gn:feature_class":"P",
    "gn:feature_code":"PPL",
    "gn:name":"Dahan-e Nay D\u0101ykun\u1e0f\u012b",
    "gn:population":0,
    "gn:timezone":"Asia/Kabul",
    "iso:country":"AF",
    "name:und_x_variant":[
        "\u1e0eahane Nay \u1e0e\u0101ykhundi",
        "Dakhani-Nayday-Kundi",
        "Dahan-e Nay D\u0101ykhonde",
        "Dahan-e Nay D\u0101ykun\u1e0f\u012b",
        "\u062f\u0647\u0646 \u0646\u06cc \u062f\u0627\u06cc\u06a9\u0646\u0689\u06cc",
        "Dahan-e Nay D\u0101ykund\u012b"
    ],
    "wof:name":"Dahan-e Nay Daykundi",
    "wof:placetype":"locality"
},
  "geometry": {"coordinates":[66.13634999999999,34.53507],"type":"Point"}
}