{
  "type": "Feature",
  "properties": {
    "gn:admin1_code":"42",
    "gn:admin2_code":"3306.0",
    "gn:asciiname":"Barkham",
    "gn:country_code":"AF",
    "gn:dem":1873,
    "gn:feature_class":"P",
    "gn:feature_code":"PPL",
    "gn:name":"B\u0101rkham",
    "gn:population":0,
    "gn:timezone":"Asia/Kabul",
    "iso:country":"AF",
    "name:ara_x_preferred":[
        "\u0628\u0631\u0647\u0645"
    ],
    "name:ceb_x_preferred":[
        "Barkham"
    ],
    "name:cym_x_preferred":[
        "Barkham"
    ],
    "name:fas_x_preferred":[
        "\u0628\u0627\u0631\u06a9\u0647\u0627\u0645"
    ],
    "name:ita_x_preferred":[
        "Barkham"
    ],
    "name:nld_x_preferred":[
        "Barkham"
    ],
    "name:pol_x_preferred":[
        "Barkham"
    ],
    "name:swe_x_preferred":[
        "Barkham"
    ],
    "name:und_x_variant":[
        "B\u0101rkham",
        "\u0628\u0627\u0631\u062e\u0645"
    ],
    "wof:name":"Barkham",
    "wof:placetype":"locality"
},
  "geometry": {"coordinates":[69.36728000000001,35.21487],"type":"Point"}
}