{
  "type": "Feature",
  "properties": {
    "gn:admin1_code":"41",
    "gn:admin2_code":"3409.0",
    "gn:asciiname":"Khagru",
    "gn:country_code":"AF",
    "gn:dem":2203,
    "gn:feature_class":"P",
    "gn:feature_code":"PPL",
    "gn:name":"Khagr\u016b",
    "gn:population":0,
    "gn:timezone":"Asia/Kabul",
    "iso:country":"AF",
    "name:und_x_variant":[
        "Khagr\u016b",
        "\u062e\u06af\u0631\u0648",
        "Khag\u1e5fu"
    ],
    "wof:name":"Khagru",
    "wof:placetype":"locality"
},
  "geometry": {"coordinates":[66.26303,33.79361],"type":"Point"}
}