{
  "type": "Feature",
  "properties": {
    "gn:admin1_code":"35",
    "gn:admin2_code":"905.0",
    "gn:asciiname":"Taravu",
    "gn:country_code":"AF",
    "gn:dem":1933,
    "gn:feature_class":"P",
    "gn:feature_code":"PPL",
    "gn:name":"Taravu",
    "gn:population":0,
    "gn:timezone":"Asia/Kabul",
    "iso:country":"AF",
    "name:und_x_variant":[
        "T\u0101r\u0101w\u014d",
        "T\u0101r\u0101wu",
        "T\u0101r\u0101w\u016b",
        "\u062a\u0627\u0631\u0627\u0648\u0648"
    ],
    "wof:name":"Taravu",
    "wof:placetype":"locality"
},
  "geometry": {"coordinates":[69.99637,34.83559],"type":"Point"}
}