{
  "type": "Feature",
  "properties": {
    "gn:admin1_code":"18",
    "gn:admin2_code":"818.0",
    "gn:asciiname":"Qal'ah-ye Wadud",
    "gn:country_code":"AF",
    "gn:dem":526,
    "gn:feature_class":"P",
    "gn:feature_code":"PPL",
    "gn:name":"Qal\u2018ah-ye Wad\u016bd",
    "gn:population":0,
    "gn:timezone":"Asia/Kabul",
    "iso:country":"AF",
    "name:fas_x_preferred":[
        "\u0642\u0644\u0639\u0647\u0654 \u0648\u062f\u0648\u062f"
    ],
    "name:und_x_variant":[
        "Kalavadud",
        "Qal\u2018a Wa\u1e0f\u016b\u1e0f",
        "Qal\u2018ah-ye Wad\u016bd",
        "Qal\u2018eh-ye Wad\u016bd",
        "\u0642\u0644\u0639\u0647 \u0648\u062f\u0648\u062f"
    ],
    "wof:name":"Qal'ah-ye Wadud",
    "wof:placetype":"locality"
},
  "geometry": {"coordinates":[70.6553,34.42665],"type":"Point"}
}