{
  "type": "Feature",
  "properties": {
    "gn:admin1_code":"11",
    "gn:admin2_code":"2012",
    "gn:asciiname":"Deh Gul",
    "gn:country_code":"AF",
    "gn:dem":1609,
    "gn:feature_class":"P",
    "gn:feature_code":"PPL",
    "gn:name":"Deh Gul",
    "gn:population":0,
    "gn:timezone":"Asia/Kabul",
    "iso:country":"AF",
    "name:und_x_variant":[
        "Deh Gu",
        "Deh Gol",
        "\u062f\u0647 \u06af\u0644"
    ],
    "wof:name":"Deh Gul",
    "wof:placetype":"locality"
},
  "geometry": {"coordinates":[63.3663,34.33811],"type":"Point"}
}