{
  "type": "Feature",
  "properties": {
    "gn:admin1_code":"07",
    "gn:admin2_code":"1804",
    "gn:asciiname":"Now Dari Qal'ah",
    "gn:country_code":"AF",
    "gn:dem":1138,
    "gn:feature_class":"P",
    "gn:feature_code":"PPL",
    "gn:name":"Now Dar\u012b Qal\u2018ah",
    "gn:population":0,
    "gn:timezone":"Asia/Kabul",
    "iso:country":"AF",
    "name:und_x_variant":[
        "Naw\u1e0fa\u1e5fi Qal\u2018a",
        "Now Dar\u012b Qal\u2018eh",
        "Now Dar\u012b Qal\u2018ah",
        "\u0646\u0648 \u062f\u0631\u06cc \u0642\u0644\u0639\u0647"
    ],
    "wof:name":"Now Dari Qal'ah",
    "wof:placetype":"locality"
},
  "geometry": {"coordinates":[64.23058,35.70088],"type":"Point"}
}