{
  "type": "Feature",
  "properties": {
    "gn:admin1_code":"35",
    "gn:admin2_code":"901",
    "gn:asciiname":"Sinzalay",
    "gn:country_code":"AF",
    "gn:dem":1277,
    "gn:feature_class":"P",
    "gn:feature_code":"PPL",
    "gn:name":"Sinzalay",
    "gn:population":0,
    "gn:timezone":"Asia/Kabul",
    "iso:country":"AF",
    "name:und_x_variant":[
        "Senzalay",
        "Sinzalay",
        "\u0633\u0646\u0632\u0644\u06cc"
    ],
    "wof:name":"Sinzalay",
    "wof:placetype":"locality"
},
  "geometry": {"coordinates":[69.93077,34.66567],"type":"Point"}
}