{
  "type": "Feature",
  "properties": {
    "gn:admin1_code":"32",
    "gn:admin2_code":"1504",
    "gn:asciiname":"Galahwan Say",
    "gn:country_code":"AF",
    "gn:dem":1723,
    "gn:feature_class":"P",
    "gn:feature_code":"PPL",
    "gn:name":"Galahw\u0101n S\u0101y",
    "gn:population":0,
    "gn:timezone":"Asia/Kabul",
    "iso:country":"AF",
    "name:und_x_variant":[
        "Galawan Sai",
        "Galaw\u0101n S\u0101y",
        "Galahw\u0101n S\u0101y",
        "\u06af\u0644\u0647\u0648\u0627\u0646 \u0633\u0627\u06cc"
    ],
    "wof:name":"Galahwan Say",
    "wof:placetype":"locality"
},
  "geometry": {"coordinates":[67.34952,36.04036],"type":"Point"}
}