{
  "type": "Feature",
  "properties": {
    "gn:admin1_code":"35",
    "gn:admin2_code":"903",
    "gn:asciiname":"Owgowrum",
    "gn:country_code":"AF",
    "gn:dem":1339,
    "gn:feature_class":"P",
    "gn:feature_code":"PPL",
    "gn:name":"Owgowrum",
    "gn:population":0,
    "gn:timezone":"Asia/Kabul",
    "iso:country":"AF",
    "name:und_x_variant":[
        "\u014cg\u014d\u1e5fum",
        "Ogurum",
        "Owgowrum",
        "\u0627\u0648\u06af\u0648\u0693\u0648\u0645"
    ],
    "wof:name":"Owgowrum",
    "wof:placetype":"locality"
},
  "geometry": {"coordinates":[70.45140000000001,34.84927],"type":"Point"}
}