{
  "type": "Feature",
  "properties": {
    "gn:admin1_code":"6",
    "gn:admin2_code":"2110.0",
    "gn:asciiname":"Baj Deh",
    "gn:country_code":"AF",
    "gn:dem":583,
    "gn:feature_class":"P",
    "gn:feature_code":"PPL",
    "gn:name":"B\u0101j Deh",
    "gn:population":0,
    "gn:timezone":"Asia/Kabul",
    "iso:country":"AF",
    "name:fas_x_preferred":[
        "B\u0101j Deh"
    ],
    "name:fas_x_variant":[
        "\u0628\u0627\u062c \u062f\u0647"
    ],
    "wof:name":"Baj Deh",
    "wof:placetype":"locality"
},
  "geometry": {"coordinates":[61.69517,32.13742],"type":"Point"}
}