{
  "type": "Feature",
  "properties": {
    "gn:admin1_code":"34",
    "gn:admin2_code":"1005.0",
    "gn:asciiname":"Shah Masir Kelay",
    "gn:country_code":"AF",
    "gn:dem":1097,
    "gn:feature_class":"P",
    "gn:feature_code":"PPL",
    "gn:name":"Sh\u0101h Masir K\u00ealay",
    "gn:population":0,
    "gn:timezone":"Asia/Kabul",
    "iso:country":"AF",
    "name:fas_x_preferred":[
        "\u0642\u0631\u064a\u06c0 \u0634\u0627\u0647\u0645\u0633\u0631"
    ],
    "name:und_x_variant":[
        "\u0160\u0101hmaser Kalay",
        "Shakhmaserkalay",
        "Sh\u0101h Maser K\u00ealay",
        "Sh\u0101hmaser Kalay",
        "Sh\u0101h Masir K\u00ealay",
        "\u0634\u0627\u0647 \u0645\u0633\u0631 \u06a9\u0644\u06cc"
    ],
    "wof:name":"Shah Masir Kelay",
    "wof:placetype":"locality"
},
  "geometry": {"coordinates":[71.53074000000002,35.21184],"type":"Point"}
}