{
  "type": "Feature",
  "properties": {
    "gn:admin1_code":"28",
    "gn:admin2_code":"2503.0",
    "gn:asciiname":"Nawah",
    "gn:country_code":"AF",
    "gn:dem":2073,
    "gn:feature_class":"P",
    "gn:feature_code":"PPL",
    "gn:name":"N\u0101wah",
    "gn:population":0,
    "gn:timezone":"Asia/Kabul",
    "iso:country":"AF",
    "name:und_x_variant":[
        "N\u0101wa",
        "Nava",
        "N\u0101wah",
        "\u0646\u0627\u0648\u0647"
    ],
    "wof:name":"Nawah",
    "wof:placetype":"locality"
},
  "geometry": {"coordinates":[67.26621,32.64393],"type":"Point"}
}