{
  "type": "Feature",
  "properties": {
    "gn:admin1_code":"27",
    "gn:admin2_code":"406",
    "gn:asciiname":"Karam Qol",
    "gn:country_code":"AF",
    "gn:dem":2629,
    "gn:feature_class":"P",
    "gn:feature_code":"PPL",
    "gn:name":"Karam Q\u014dl",
    "gn:population":0,
    "gn:timezone":"Asia/Kabul",
    "iso:country":"AF",
    "name:rus_x_preferred":[
        "Karamkul\u2019"
    ],
    "name:und_x_variant":[
        "Ka\u1e5famq\u014dl",
        "Karam Q\u014dl",
        "Karamqowl",
        "\u06a9\u0631\u0645 \u0642\u0648\u0644"
    ],
    "wof:name":"Karam Qol",
    "wof:placetype":"locality"
},
  "geometry": {"coordinates":[68.62948,34.24165],"type":"Point"}
}