{
  "type": "Feature",
  "properties": {
    "gn:admin1_code":"23",
    "gn:admin2_code":"2413.0",
    "gn:asciiname":"Wulgay",
    "gn:country_code":"AF",
    "gn:dem":1940,
    "gn:feature_class":"P",
    "gn:feature_code":"PPL",
    "gn:name":"Wulgay",
    "gn:population":0,
    "gn:timezone":"Asia/Kabul",
    "iso:country":"AF",
    "name:rus_x_preferred":[
        "Vul\u2019gay"
    ],
    "name:und_x_variant":[
        "Wulg\u00eay",
        "\u0648\u0644\u06af\u06cd",
        "\u0648\u0644\u06af\u06cc"
    ],
    "wof:name":"Wulgay",
    "wof:placetype":"locality"
},
  "geometry": {"coordinates":[67.23563,31.42902],"type":"Point"}
}