{
  "type": "Feature",
  "properties": {
    "gn:admin1_code":"23",
    "gn:admin2_code":"2408.0",
    "gn:asciiname":"Haji Muhammad Rahim",
    "gn:country_code":"AF",
    "gn:dem":939,
    "gn:feature_class":"P",
    "gn:feature_code":"PPL",
    "gn:name":"\u1e28\u0101j\u012b Mu\u1e29ammad Ra\u1e29\u012bm",
    "gn:population":0,
    "gn:timezone":"Asia/Kabul",
    "iso:country":"AF",
    "name:und_x_variant":[
        "Khadzhi-Mukhammedrakhim",
        "\u1e28\u0101ji Mo\u1e29amma\u1e0f \u1e5ea\u1e29\u012bm",
        "\u1e28\u0101j\u012b Mu\u1e29ammad Ra\u1e29\u012bm",
        "\u062d\u0627\u062c\u06cc \u0645\u062d\u0645\u062f \u0631\u062d\u06cc\u0645",
        "\u1e28\u0101jj\u012b Mo\u1e29ammad Ra\u1e29\u012bm"
    ],
    "wof:name":"Haji Muhammad Rahim",
    "wof:placetype":"locality"
},
  "geometry": {"coordinates":[65.46115999999999,31.52609],"type":"Point"}
}