{
  "type": "Feature",
  "properties": {
    "gn:admin1_code":"41",
    "gn:admin2_code":"3402.0",
    "gn:asciiname":"Sar Qol-e Tabut",
    "gn:country_code":"AF",
    "gn:dem":2242,
    "gn:feature_class":"P",
    "gn:feature_code":"PPL",
    "gn:name":"Sar Q\u014dl-e T\u0101b\u016bt",
    "gn:population":0,
    "gn:timezone":"Asia/Kabul",
    "iso:country":"AF",
    "name:und_x_variant":[
        "Sa\u1e5fq\u014dle Tab\u016bt",
        "Sar Q\u014dl-e T\u0101b\u016bt",
        "\u0633\u0631 \u0642\u0648\u0644 \u062a\u0627\u0628\u0648\u062a",
        "Sar Qowl-e T\u0101b\u016bt"
    ],
    "wof:name":"Sar Qol-e Tabut",
    "wof:placetype":"locality"
},
  "geometry": {"coordinates":[66.62820000000001,33.32969],"type":"Point"}
}