{
  "type": "Feature",
  "properties": {
    "gn:admin1_code":"14",
    "gn:admin2_code":"205",
    "gn:asciiname":"Pakah Chinah",
    "gn:country_code":"AF",
    "gn:dem":1390,
    "gn:feature_class":"P",
    "gn:feature_code":"PPL",
    "gn:name":"P\u0101kah Ch\u012bnah",
    "gn:population":0,
    "gn:timezone":"Asia/Kabul",
    "iso:country":"AF",
    "name:fas_x_preferred":[
        "\u0686\u0634\u0645\u06c0 \u067e\u0627\u0643\u0647"
    ],
    "name:und_x_variant":[
        "P\u0101ka China",
        "Pakachina",
        "P\u0101ka \u010cina",
        "P\u0101kah Ch\u012bnah",
        "\u067e\u0627\u06a9\u0647 \u0686\u06cc\u0646\u0647"
    ],
    "wof:name":"Pakah Chinah",
    "wof:placetype":"locality"
},
  "geometry": {"coordinates":[69.70186,34.78321],"type":"Point"}
}