{
  "type": "Feature",
  "properties": {
    "gn:admin1_code":"27",
    "gn:admin2_code":"404",
    "gn:asciiname":"Markaz-e Behsud",
    "gn:country_code":"AF",
    "gn:dem":3003,
    "gn:feature_class":"P",
    "gn:feature_code":"PPL",
    "gn:name":"Markaz-e Behs\u016bd",
    "gn:population":0,
    "gn:timezone":"Asia/Kabul",
    "iso:country":"AF",
    "wof:name":"Markaz-e Behsud",
    "wof:placetype":"locality"
},
  "geometry": {"coordinates":[67.90000000000001,34.33333],"type":"Point"}
}