{
  "type": "Feature",
  "properties": {
    "gn:admin1_code":"31",
    "gn:admin2_code":"1701",
    "gn:asciiname":"Seh Shanbah",
    "gn:country_code":"AF",
    "gn:dem":428,
    "gn:feature_class":"P",
    "gn:feature_code":"PPL",
    "gn:name":"Seh Shanbah",
    "gn:population":0,
    "gn:timezone":"Asia/Kabul",
    "iso:country":"AF",
    "name:und_x_variant":[
        "Sesbamba",
        "Seh S\u0304anba",
        "Seshamba",
        "Seh Shanbeh",
        "Seh Shanbah",
        "\u0633\u0647 \u0634\u0646\u0628\u0647"
    ],
    "wof:name":"Seh Shanbah",
    "wof:placetype":"locality"
},
  "geometry": {"coordinates":[65.79015,36.4875],"type":"Point"}
}