{
  "type": "Feature",
  "properties": {
    "gn:admin1_code":"09",
    "gn:admin2_code":"2705",
    "gn:asciiname":"Istowan",
    "gn:country_code":"AF",
    "gn:dem":2334,
    "gn:feature_class":"P",
    "gn:feature_code":"PPL",
    "gn:name":"Istow\u0101n",
    "gn:population":0,
    "gn:timezone":"Asia/Kabul",
    "iso:country":"AF",
    "name:und_x_variant":[
        "Istavan",
        "Istow\u0101n",
        "\u0627\u0633\u062a\u0648\u0627\u0646",
        "Estaw\u0101n"
    ],
    "wof:name":"Istowan",
    "wof:placetype":"locality"
},
  "geometry": {"coordinates":[64.37363000000001,33.29741],"type":"Point"}
}