{
  "type": "Feature",
  "properties": {
    "gn:admin1_code":"8",
    "gn:admin2_code":"602.0",
    "gn:asciiname":"Gulbutah",
    "gn:country_code":"AF",
    "gn:dem":2639,
    "gn:feature_class":"P",
    "gn:feature_code":"PPL",
    "gn:name":"Gulbutah",
    "gn:population":0,
    "gn:timezone":"Asia/Kabul",
    "iso:country":"AF",
    "name:rus_x_preferred":[
        "Gul\u2019buta"
    ],
    "name:und_x_variant":[
        "Gulbota",
        "Golbotteh",
        "Gulbutah",
        "\u06af\u0644\u0628\u062a\u0647"
    ],
    "wof:name":"Gulbutah",
    "wof:placetype":"locality"
},
  "geometry": {"coordinates":[68.16011,33.52675],"type":"Point"}
}