{
  "type": "Feature",
  "properties": {
    "gn:admin1_code":"27",
    "gn:admin2_code":"401",
    "gn:asciiname":"Shah Qadam",
    "gn:country_code":"AF",
    "gn:dem":2353,
    "gn:feature_class":"P",
    "gn:feature_code":"PPL",
    "gn:name":"Sh\u0101h Qadam",
    "gn:population":0,
    "gn:timezone":"Asia/Kabul",
    "iso:country":"AF",
    "name:fas_x_preferred":[
        "\u0634\u0627\u0647 \u0642\u062f\u0645"
    ],
    "name:und_x_variant":[
        "\u0160\u0101hqadam",
        "Shakhkadam",
        "Sh\u0101h Qadam",
        "Sh\u0101hqadam",
        "\u0634\u0627\u0647 \u0642\u062f\u0645"
    ],
    "wof:name":"Shah Qadam",
    "wof:placetype":"locality"
},
  "geometry": {"coordinates":[68.88453,34.43192],"type":"Point"}
}