{
  "type": "Feature",
  "properties": {
    "gn:admin1_code":"8",
    "gn:admin2_code":"614.0",
    "gn:asciiname":"Mihman",
    "gn:country_code":"AF",
    "gn:dem":2092,
    "gn:feature_class":"P",
    "gn:feature_code":"PPL",
    "gn:name":"Mihm\u0101n",
    "gn:population":0,
    "gn:timezone":"Asia/Kabul",
    "iso:country":"AF",
    "name:fas_x_preferred":[
        "\u0645\u0647\u0645\u0627\u0646"
    ],
    "name:und_x_variant":[
        "Mikhman",
        "Mehm\u0101n",
        "Mihm\u0101n"
    ],
    "wof:name":"Mihman",
    "wof:placetype":"locality"
},
  "geometry": {"coordinates":[68.44019,33.37147],"type":"Point"}
}