{
  "type": "Feature",
  "properties": {
    "gn:admin1_code":"03",
    "gn:admin2_code":"1308.0",
    "gn:asciiname":"Pashah'i",
    "gn:country_code":"AF",
    "gn:dem":2444,
    "gn:feature_class":"P",
    "gn:feature_code":"PPL",
    "gn:name":"Pashah\u2019\u012b",
    "gn:population":0,
    "gn:timezone":"Asia/Kabul",
    "iso:country":"AF",
    "name:und_x_variant":[
        "Pashah\u2019\u012b",
        "\u067e\u0634\u0647\u0626\u06cc"
    ],
    "wof:name":"Pashah'i",
    "wof:placetype":"locality"
},
  "geometry": {"coordinates":[69.63345,35.86257],"type":"Point"}
}