{
  "type": "Feature",
  "properties": {
    "gn:admin1_code":"32",
    "gn:admin2_code":"1505",
    "gn:asciiname":"Kowlar",
    "gn:country_code":"AF",
    "gn:dem":1908,
    "gn:feature_class":"P",
    "gn:feature_code":"PPL",
    "gn:name":"Kowlar",
    "gn:population":0,
    "gn:timezone":"Asia/Kabul",
    "iso:country":"AF",
    "name:und_x_variant":[
        "Kawla\u1e5f",
        "Kowlar",
        "\u06a9\u0648\u0644\u0631"
    ],
    "wof:name":"Kowlar",
    "wof:placetype":"locality"
},
  "geometry": {"coordinates":[67.84948,35.76874],"type":"Point"}
}