{
  "type": "Feature",
  "properties": {
    "gn:admin1_code":"26",
    "gn:admin2_code":"1203",
    "gn:asciiname":"Panjiri",
    "gn:country_code":"AF",
    "gn:dem":1243,
    "gn:feature_class":"P",
    "gn:feature_code":"PPL",
    "gn:name":"Panj\u012br\u012b",
    "gn:population":0,
    "gn:timezone":"Asia/Kabul",
    "iso:country":"AF",
    "name:fas_x_preferred":[
        "\u067e\u0646\u062c\u064a\u0631\u06cc"
    ],
    "name:rus_x_preferred":[
        "\u041f\u0430\u043d\u0434\u0436\u0438\u0440\u0438"
    ],
    "name:und_x_variant":[
        "Pandzhiri",
        "Panj\u012br\u012b",
        "\u067e\u0646\u062c\u06cc\u0631\u06cc"
    ],
    "wof:name":"Panjiri",
    "wof:placetype":"locality"
},
  "geometry": {"coordinates":[69.21471,36.5086],"type":"Point"}
}