{
  "type": "Feature",
  "properties": {
    "gn:admin1_code":"13",
    "gn:admin2_code":"107.0",
    "gn:asciiname":"Aghil-e Shaykhu",
    "gn:country_code":"AF",
    "gn:dem":2018,
    "gn:feature_class":"P",
    "gn:feature_code":"PPL",
    "gn:name":"\u0100ghil-e Shaykh\u016b",
    "gn:population":0,
    "gn:timezone":"Asia/Kabul",
    "iso:country":"AF",
    "name:fas_x_preferred":[
        "\u0627\u063a\u0644\u0654 \u0634\u064a\u062e"
    ],
    "name:und_x_variant":[
        "\u0100ghale \u0160aykhu",
        "Aghal-e Shaykh",
        "Agali-Sheykhu",
        "\u0100ghil-e Shaykh\u014d",
        "Aghel-e Sheykh",
        "\u0100ghel-e Shaykh\u014d",
        "\u0100ghel-e Shaykh\u016b",
        "\u0622\u063a\u0644 \u0634\u06cc\u062e\u0648",
        "\u0100ghil-e Shaykh\u016b"
    ],
    "wof:name":"Aghil-e Shaykhu",
    "wof:placetype":"locality"
},
  "geometry": {"coordinates":[69.02691999999999,34.67862],"type":"Point"}
}