{
  "type": "Feature",
  "properties": {
    "gn:admin1_code":"07",
    "gn:admin2_code":"1810.0",
    "gn:asciiname":"Qaramqul",
    "gn:country_code":"AF",
    "gn:dem":324,
    "gn:feature_class":"P",
    "gn:feature_code":"PPL",
    "gn:name":"Qaramqul",
    "gn:population":0,
    "gn:timezone":"Asia/Kabul",
    "iso:country":"AF",
    "name:und_x_variant":[
        "Qaramqol (1)",
        "Qaramqul",
        "\u0642\u0631\u0645\u0642\u0644",
        "Qaramq\u016bl (1)"
    ],
    "wof:name":"Qaramqul",
    "wof:placetype":"locality"
},
  "geometry": {"coordinates":[65.08165,36.87669],"type":"Point"}
}