{
  "type": "Feature",
  "properties": {
    "gn:admin1_code":"08",
    "gn:admin2_code":"607",
    "gn:asciiname":"Khushk Qol Kelay",
    "gn:country_code":"AF",
    "gn:dem":2624,
    "gn:feature_class":"P",
    "gn:feature_code":"PPL",
    "gn:name":"Khushk Q\u014dl K\u00ealay",
    "gn:population":0,
    "gn:timezone":"Asia/Kabul",
    "iso:country":"AF",
    "name:rus_x_preferred":[
        "Khushkul\u2019kalay"
    ],
    "name:und_x_variant":[
        "Khu\u0161qol Kalay",
        "Khuskq\u014dl Kalay",
        "Khushk Q\u014dl K\u00ealay",
        "\u062e\u0634\u06a9 \u0642\u0648\u0644 \u06a9\u0644\u06cc",
        "Khvosh Qowl Kalay"
    ],
    "wof:name":"Khushk Qol Kelay",
    "wof:placetype":"locality"
},
  "geometry": {"coordinates":[67.41645,32.98256],"type":"Point"}
}