{
  "type": "Feature",
  "properties": {
    "gn:admin1_code":"01",
    "gn:admin2_code":"1101.0",
    "gn:asciiname":"Parnah Kham",
    "gn:country_code":"AF",
    "gn:dem":1828,
    "gn:feature_class":"P",
    "gn:feature_code":"PPL",
    "gn:name":"Parnah Kham",
    "gn:population":0,
    "gn:timezone":"Asia/Kabul",
    "iso:country":"AF",
    "name:und_x_variant":[
        "Pa\u1e5fna Kham",
        "\u067e\u0631\u0646\u0647 \u062e\u0645",
        "Pa\u1e5fnah Kham",
        "Parnah Kham"
    ],
    "wof:name":"Parnah Kham",
    "wof:placetype":"locality"
},
  "geometry": {"coordinates":[70.63042,37.16538],"type":"Point"}
}