{
  "type": "Feature",
  "properties": {
    "gn:admin1_code":"01",
    "gn:admin2_code":"1128",
    "gn:asciiname":"Luli Khirman",
    "gn:country_code":"AF",
    "gn:dem":2363,
    "gn:feature_class":"P",
    "gn:feature_code":"PPL",
    "gn:name":"L\u016bl\u012b Khirm\u0101n",
    "gn:population":0,
    "gn:timezone":"Asia/Kabul",
    "iso:country":"AF",
    "name:und_x_variant":[
        "L\u016bl\u012b Khirm\u0101n",
        "\u0644\u0648\u0644\u06cc \u062e\u0631\u0645\u0627\u0646",
        "L\u016bli Khe\u1e5fm\u0101n",
        "L\u016bleh Kherm\u0101n"
    ],
    "wof:name":"Luli Khirman",
    "wof:placetype":"locality"
},
  "geometry": {"coordinates":[70.45605999999999,37.49926],"type":"Point"}
}