{
  "type": "Feature",
  "properties": {
    "gn:admin1_code":"28",
    "gn:admin2_code":"2506.0",
    "gn:asciiname":"Samandar",
    "gn:country_code":"AF",
    "gn:dem":1375,
    "gn:feature_class":"P",
    "gn:feature_code":"PPL",
    "gn:name":"Samandar",
    "gn:population":0,
    "gn:timezone":"Asia/Kabul",
    "iso:country":"AF",
    "name:fas_x_preferred":[
        "\u0633\u0645\u0646\u062f\u0631"
    ],
    "wof:name":"Samandar",
    "wof:placetype":"locality"
},
  "geometry": {"coordinates":[66.35970999999999,31.87629],"type":"Point"}
}