{
  "type": "Feature",
  "properties": {
    "gn:admin1_code":"27",
    "gn:admin2_code":"406.0",
    "gn:asciiname":"Tatang",
    "gn:country_code":"AF",
    "gn:dem":2242,
    "gn:feature_class":"P",
    "gn:feature_code":"PPL",
    "gn:name":"\u1e6ea\u1e6fang",
    "gn:population":0,
    "gn:timezone":"Asia/Kabul",
    "iso:country":"AF",
    "name:und_x_variant":[
        "Gatang",
        "\u1e6ea\u1e6fang",
        "Tatang",
        "\u067c\u067c\u0646\u06af"
    ],
    "wof:name":"Tatang",
    "wof:placetype":"locality"
},
  "geometry": {"coordinates":[68.63396,34.16155999999999],"type":"Point"}
}