{
  "type": "Feature",
  "properties": {
    "gn:admin1_code":"23",
    "gn:admin2_code":"2405",
    "gn:asciiname":"Tik",
    "gn:country_code":"AF",
    "gn:dem":1321,
    "gn:feature_class":"P",
    "gn:feature_code":"PPL",
    "gn:name":"T\u012bk",
    "gn:population":0,
    "gn:timezone":"Asia/Kabul",
    "iso:country":"AF",
    "name:fas_x_preferred":[
        "\u062a\u064a\u0643"
    ],
    "name:hat_x_preferred":[
        "Tik"
    ],
    "name:srp_x_preferred":[
        "\u0422\u0438\u043a"
    ],
    "name:tur_x_preferred":[
        "Tik"
    ],
    "name:und_x_variant":[
        "T\u012bk",
        "\u062a\u06cc\u06a9"
    ],
    "wof:name":"Tik",
    "wof:placetype":"locality"
},
  "geometry": {"coordinates":[65.46771,31.89276],"type":"Point"}
}