{
  "type": "Feature",
  "properties": {
    "gn:admin1_code":"05",
    "gn:admin2_code":"2806",
    "gn:asciiname":"Ghundey Sang",
    "gn:country_code":"AF",
    "gn:dem":2770,
    "gn:feature_class":"P",
    "gn:feature_code":"PPL",
    "gn:name":"Ghun\u1e0f\u00eay Sang",
    "gn:population":0,
    "gn:timezone":"Asia/Kabul",
    "iso:country":"AF",
    "name:und_x_variant":[
        "Ghundasang",
        "Gundasang",
        "Gh\u016bn\u1e0f\u00eay Sang",
        "\u063a\u0646\u0689\u06cd \u0633\u0646\u06af",
        "Ghun\u1e0f\u00eay Sang"
    ],
    "wof:name":"Ghundey Sang",
    "wof:placetype":"locality"
},
  "geometry": {"coordinates":[66.54338,34.22903],"type":"Point"}
}