{
  "type": "Feature",
  "properties": {
    "gn:admin1_code":"09",
    "gn:admin2_code":"2705",
    "gn:asciiname":"Kawan-e Khwajah",
    "gn:country_code":"AF",
    "gn:dem":2394,
    "gn:feature_class":"P",
    "gn:feature_code":"PPL",
    "gn:name":"K\u0101w\u0101n-e Khw\u0101jah",
    "gn:population":0,
    "gn:timezone":"Asia/Kabul",
    "iso:country":"AF",
    "name:und_x_variant":[
        "K\u0101w\u0101ne Khw\u0101ja",
        "Kavani-Khodzha",
        "K\u0101w\u0101n-e Khw\u0101jah",
        "\u06a9\u0627\u0648\u0627\u0646 \u062e\u0648\u0627\u062c\u0647",
        "K\u0101w\u0101n-e Khv\u0101jeh"
    ],
    "wof:name":"Kawan-e Khwajah",
    "wof:placetype":"locality"
},
  "geometry": {"coordinates":[64.22399999999999,33.19904],"type":"Point"}
}