{
  "type": "Feature",
  "properties": {
    "gn:admin1_code":"13",
    "gn:admin2_code":"102.0",
    "gn:asciiname":"Pul-e Sangi",
    "gn:country_code":"AF",
    "gn:dem":1776,
    "gn:feature_class":"P",
    "gn:feature_code":"PPLA2",
    "gn:name":"Pul-e Sang\u012b",
    "gn:population":0,
    "gn:timezone":"Asia/Kabul",
    "iso:country":"AF",
    "name:fas_x_preferred":[
        "\u067e\u0644\u0654 \u0633\u0646\u06af\u06cc"
    ],
    "name:und_x_variant":[
        "Pule Sangi",
        "Puli-Sangi",
        "Pol-e Sang\u012b",
        "Pul-e Sang\u012b",
        "\u067e\u0644 \u0633\u0646\u06af\u06cc",
        "Qaryah-ye Sang\u012b",
        "\u0642\u0631\u06cc\u0647 \u0633\u0646\u06af\u06cc"
    ],
    "wof:name":"Pul-e Sangi",
    "wof:placetype":"locality"
},
  "geometry": {"coordinates":[69.25993000000001,34.59972],"type":"Point"}
}