{
  "type": "Feature",
  "properties": {
    "gn:admin1_code":"05",
    "gn:admin2_code":"2806",
    "gn:asciiname":"Mind-e Wulayat",
    "gn:country_code":"AF",
    "gn:dem":3074,
    "gn:feature_class":"P",
    "gn:feature_code":"PPL",
    "gn:name":"Mind-e Wulayat",
    "gn:population":0,
    "gn:timezone":"Asia/Kabul",
    "iso:country":"AF",
    "name:und_x_variant":[
        "Mandi-Vuleat",
        "Mend-e Wol\u0113at",
        "Mind-e Wulayat",
        "\u0645\u0646\u062f \u0648\u0644\u06cc\u062a"
    ],
    "wof:name":"Mind-e Wulayat",
    "wof:placetype":"locality"
},
  "geometry": {"coordinates":[67.01881,34.24341],"type":"Point"}
}