{
  "type": "Feature",
  "properties": {
    "gn:admin1_code":"19",
    "gn:admin2_code":"2202.0",
    "gn:asciiname":"Amir Muhammad Khan",
    "gn:country_code":"AF",
    "gn:dem":483,
    "gn:feature_class":"P",
    "gn:feature_code":"PPL",
    "gn:name":"Amir Muhammad Khan",
    "gn:population":0,
    "gn:timezone":"Asia/Kabul",
    "iso:country":"AF",
    "name:afr_x_preferred":[
        "Am\u012br Mu\u1e29ammad\u00a0Kh\u0101n"
    ],
    "name:und_x_variant":[
        "Am\u012br Mo\u1e96\u1e0f-kh\u0101n",
        "Am\u012br Mu\u1e29ammad\u00a0Kh\u0101n"
    ],
    "wof:name":"Amir Muhammad Khan",
    "wof:placetype":"locality"
},
  "geometry": {"coordinates":[61.85778000000001,31.09944],"type":"Point"}
}