{
  "type": "Feature",
  "properties": {
    "gn:admin1_code":"10",
    "gn:admin2_code":"2309",
    "gn:asciiname":"Sayyidan",
    "gn:country_code":"AF",
    "gn:dem":762,
    "gn:feature_class":"P",
    "gn:feature_code":"PPL",
    "gn:name":"Sayyid\u0101n",
    "gn:population":0,
    "gn:timezone":"Asia/Kabul",
    "iso:country":"AF",
    "name:fas_x_preferred":[
        "\u0633\u064a\u064a\u062f\u0627\u0646"
    ],
    "name:und_x_variant":[
        "Seyidan",
        "Saye\u1e0f\u0101n",
        "Sayyid\u0101n",
        "\u0633\u06cc\u062f\u0627\u0646",
        "Seyyed\u0101n"
    ],
    "wof:name":"Sayyidan",
    "wof:placetype":"locality"
},
  "geometry": {"coordinates":[64.32224000000001,31.50855],"type":"Point"}
}