{
  "type": "Feature",
  "properties": {
    "gn:admin1_code":"28",
    "gn:admin2_code":"2510",
    "gn:asciiname":"Khwajah Atis",
    "gn:country_code":"AF",
    "gn:dem":1786,
    "gn:feature_class":"P",
    "gn:feature_code":"PPL",
    "gn:name":"Khw\u0101jah \u0100t\u012bs",
    "gn:population":0,
    "gn:timezone":"Asia/Kabul",
    "iso:country":"AF",
    "name:und_x_variant":[
        "Khw\u0101ja \u0100t\u012bs",
        "Khodzhatiz",
        "Khw\u0101jah \u0100t\u012bs",
        "\u062e\u0648\u0627\u062c\u0647 \u0622\u062a\u06cc\u0633",
        "Khv\u0101jeh \u0100t\u012bs"
    ],
    "wof:name":"Khwajah Atis",
    "wof:placetype":"locality"
},
  "geometry": {"coordinates":[67.19389,32.74235],"type":"Point"}
}