{
  "type": "Feature",
  "properties": {
    "gn:admin1_code":"23",
    "gn:admin2_code":"2403.0",
    "gn:asciiname":"Nur Muhammad Khan Shor Ab",
    "gn:country_code":"AF",
    "gn:dem":1134,
    "gn:feature_class":"P",
    "gn:feature_code":"PPL",
    "gn:name":"N\u016br Mu\u1e29ammad Kh\u0101n Sh\u014dr \u0100b",
    "gn:population":0,
    "gn:timezone":"Asia/Kabul",
    "iso:country":"AF",
    "name:und_x_variant":[
        "N\u016br Mohammadkh\u0101n \u0160or\u0101b",
        "Nurmukhammedkhan-Sharab",
        "N\u016br Mo\u1e29ammad Kh\u0101n Sh\u014dr\u0101b",
        "N\u016br Mu\u1e29ammad Kh\u0101n Sh\u014dr\u0101b",
        "\u0646\u0648\u0631 \u0645\u062d\u0645\u062f \u062e\u0627\u0646 \u0634\u0648\u0631\u0627\u0628",
        "N\u016br Mo\u1e29ammad Kh\u0101n Sh\u016br\u0101b",
        "N\u016br Mu\u1e29ammad Kh\u0101n Sh\u014dr \u0100b",
        "\u0646\u0648\u0631 \u0645\u062d\u0645\u062f \u062e\u0627\u0646 \u0634\u0648\u0631 \u0622\u0628"
    ],
    "wof:name":"Nur Muhammad Khan Shor Ab",
    "wof:placetype":"locality"
},
  "geometry": {"coordinates":[65.85775,31.87515],"type":"Point"}
}