{
  "type": "Feature",
  "properties": {
    "gn:admin1_code":"09",
    "gn:admin2_code":"2708",
    "gn:asciiname":"Siyah Bayd",
    "gn:country_code":"AF",
    "gn:dem":1837,
    "gn:feature_class":"P",
    "gn:feature_code":"PPL",
    "gn:name":"Siy\u0101h Bayd",
    "gn:population":0,
    "gn:timezone":"Asia/Kabul",
    "iso:country":"AF",
    "name:und_x_variant":[
        "Sy\u0101hb\u0113d",
        "S\u012b\u0101h B\u012bd",
        "S\u012b\u0101h Bayd",
        "\u0633\u06cc\u0627\u0647 \u0628\u06cc\u062f",
        "Siy\u0101h Bayd"
    ],
    "wof:name":"Siyah Bayd",
    "wof:placetype":"locality"
},
  "geometry": {"coordinates":[65.01685000000001,35.15352],"type":"Point"}
}