{
  "type": "Feature",
  "properties": {
    "gn:admin1_code":"23",
    "gn:admin2_code":"2415.0",
    "gn:asciiname":"Burah Ganah",
    "gn:country_code":"AF",
    "gn:dem":1691,
    "gn:feature_class":"P",
    "gn:feature_code":"PPL",
    "gn:name":"Burah G\u0101nah",
    "gn:population":0,
    "gn:timezone":"Asia/Kabul",
    "iso:country":"AF",
    "name:und_x_variant":[
        "Burakhgana",
        "Bo\u1e5fahg\u0101na",
        "Boreh Ganeh",
        "Barana",
        "Burah G\u0101nah",
        "\u0628\u0631\u0647 \u06af\u0627\u0646\u0647",
        "Borah G\u0101nah Kalay"
    ],
    "wof:name":"Burah Ganah",
    "wof:placetype":"locality"
},
  "geometry": {"coordinates":[65.83378,32.35488],"type":"Point"}
}