{
  "type": "Feature",
  "properties": {
    "gn:admin1_code":"27",
    "gn:admin2_code":"408",
    "gn:asciiname":"Shamshayr",
    "gn:country_code":"AF",
    "gn:dem":2421,
    "gn:feature_class":"P",
    "gn:feature_code":"PPL",
    "gn:name":"Shamshayr",
    "gn:population":0,
    "gn:timezone":"Asia/Kabul",
    "iso:country":"AF",
    "name:und_x_variant":[
        "\u0160am\u0161\u0113r",
        "Shamsh\u0113r",
        "Shamsher",
        "Shamshayr",
        "Shamsh\u012br",
        "\u0634\u0645\u0634\u06cc\u0631"
    ],
    "wof:name":"Shamshayr",
    "wof:placetype":"locality"
},
  "geometry": {"coordinates":[68.67440000000001,34.34323],"type":"Point"}
}