{
  "type": "Feature",
  "properties": {
    "gn:admin1_code":"01",
    "gn:admin2_code":"1107",
    "gn:asciiname":"Sikikan",
    "gn:country_code":"AF",
    "gn:dem":2630,
    "gn:feature_class":"P",
    "gn:feature_code":"PPL",
    "gn:name":"Sikik\u0101n",
    "gn:population":0,
    "gn:timezone":"Asia/Kabul",
    "iso:country":"AF",
    "name:und_x_variant":[
        "Sekik\u0101n",
        "\u0633\u06a9\u06a9\u0627\u0646",
        "Sikik\u0101n"
    ],
    "wof:name":"Sikikan",
    "wof:placetype":"locality"
},
  "geometry": {"coordinates":[71.57196,36.72337],"type":"Point"}
}