{
  "type": "Feature",
  "properties": {
    "gn:admin1_code":"23",
    "gn:admin2_code":"2413.0",
    "gn:asciiname":"Bashah",
    "gn:country_code":"AF",
    "gn:dem":2062,
    "gn:feature_class":"P",
    "gn:feature_code":"PPL",
    "gn:name":"B\u0101shah",
    "gn:population":0,
    "gn:timezone":"Asia/Kabul",
    "iso:country":"AF",
    "name:rus_x_preferred":[
        "\u0411\u0430\u0448\u0430"
    ],
    "name:und_x_variant":[
        "B\u0101\u0161a",
        "Basha",
        "B\u0101shah",
        "B\u0101sh\u0101h",
        "\u0628\u0627\u0634\u0647"
    ],
    "wof:name":"Bashah",
    "wof:placetype":"locality"
},
  "geometry": {"coordinates":[67.23889,31.23972],"type":"Point"}
}