{
  "type": "Feature",
  "properties": {
    "gn:admin1_code":"10",
    "gn:admin2_code":"2311.0",
    "gn:asciiname":"'Abdul 'Alim Kelay",
    "gn:country_code":"AF",
    "gn:dem":723,
    "gn:feature_class":"P",
    "gn:feature_code":"PPL",
    "gn:name":"\u2018Abdul \u2018Al\u012bm K\u00ealay",
    "gn:population":0,
    "gn:timezone":"Asia/Kabul",
    "iso:country":"AF",
    "name:und_x_variant":[
        "Abdul\u2018alim Kalay",
        "\u2018Abdul \u2018Al\u012bm K\u00ealay",
        "\u0639\u0628\u062f\u0644 \u0639\u0644\u06cc\u0645 \u06a9\u0644\u06cc",
        "\u2018Abd ol \u2018Al\u012bm Kalay"
    ],
    "wof:name":"'Abdul 'Alim Kelay",
    "wof:placetype":"locality"
},
  "geometry": {"coordinates":[64.2064,31.22968],"type":"Point"}
}