{
  "type": "Feature",
  "properties": {
    "gn:admin1_code":"01",
    "gn:admin2_code":"1121.0",
    "gn:asciiname":"Ghumay",
    "gn:country_code":"AF",
    "gn:dem":1139,
    "gn:feature_class":"P",
    "gn:feature_code":"PPL",
    "gn:name":"Ghumay",
    "gn:population":0,
    "gn:timezone":"Asia/Kabul",
    "iso:country":"AF",
    "name:und_x_variant":[
        "\u063a\u0645\u06cc",
        "Gh\u016bmay",
        "Ghumay"
    ],
    "wof:name":"Ghumay",
    "wof:placetype":"locality"
},
  "geometry": {"coordinates":[70.60852,38.2869],"type":"Point"}
}