{
  "type": "Feature",
  "properties": {
    "gn:admin1_code":"37",
    "gn:admin2_code":"3201",
    "gn:asciiname":"Lakan",
    "gn:country_code":"AF",
    "gn:dem":1041,
    "gn:feature_class":"P",
    "gn:feature_code":"PPL",
    "gn:name":"Lakan",
    "gn:population":0,
    "gn:timezone":"Asia/Kabul",
    "iso:country":"AF",
    "name:fas_x_preferred":[
        "\u0644\u0643\u0646"
    ],
    "name:ilo_x_preferred":[
        "Lakan"
    ],
    "name:und_x_variant":[
        "Laka\u1e49",
        "\u0644\u0643\u0646"
    ],
    "name:zho_x_preferred":[
        "\u62c9\u80af"
    ],
    "wof:name":"Lakan",
    "wof:placetype":"locality"
},
  "geometry": {"coordinates":[70.07833000000001,33.35669],"type":"Point"}
}