{
  "type": "Feature",
  "properties": {
    "gn:admin1_code":"29",
    "gn:admin2_code":"2915",
    "gn:asciiname":"Shah Kala",
    "gn:country_code":"AF",
    "gn:dem":2113,
    "gn:feature_class":"P",
    "gn:feature_code":"PPL",
    "gn:name":"Sh\u0101h Kal\u0101",
    "gn:population":0,
    "gn:timezone":"Asia/Kabul",
    "iso:country":"AF",
    "name:und_x_variant":[
        "\u0160\u0101 Kal\u0101",
        "Shakala",
        "\u0634\u0627\u0647 \u06a9\u0644\u0627",
        "Sh\u0101 Kal\u0101",
        "Sh\u0101h Kal\u0101"
    ],
    "wof:name":"Shah Kala",
    "wof:placetype":"locality"
},
  "geometry": {"coordinates":[68.80514000000001,33.27037],"type":"Point"}
}