{
  "type": "Feature",
  "properties": {
    "gn:admin1_code":"41",
    "gn:admin2_code":"3405",
    "gn:asciiname":"Siyah Joy",
    "gn:country_code":"AF",
    "gn:dem":2119,
    "gn:feature_class":"P",
    "gn:feature_code":"PPL",
    "gn:name":"Siy\u0101h J\u014dy",
    "gn:population":0,
    "gn:timezone":"Asia/Kabul",
    "iso:country":"AF",
    "name:und_x_variant":[
        "Syah J\u014dy",
        "S\u012b\u0101h J\u014dy",
        "\u0633\u06cc\u0627\u0647 \u062c\u0648\u06cc",
        "S\u012b\u0101h J\u016by",
        "Siy\u0101h J\u014dy"
    ],
    "wof:name":"Siyah Joy",
    "wof:placetype":"locality"
},
  "geometry": {"coordinates":[65.72614,33.80765],"type":"Point"}
}