{
  "type": "Feature",
  "properties": {
    "gn:admin1_code":"36",
    "gn:admin2_code":"703.0",
    "gn:asciiname":"'Arab Khel",
    "gn:country_code":"AF",
    "gn:dem":2472,
    "gn:feature_class":"P",
    "gn:feature_code":"PPL",
    "gn:name":"\u2018Arab Kh\u0113l",
    "gn:population":0,
    "gn:timezone":"Asia/Kabul",
    "iso:country":"AF",
    "name:fas_x_preferred":[
        "\u0639\u0631\u0628 \u062e\u064a\u0644"
    ],
    "name:rus_x_preferred":[
        "Arabkheyl\u2019"
    ],
    "name:und_x_variant":[
        "\u2018A\u1e5fabkh\u0113l",
        "\u2018Arab Kheyl",
        "\u2018Arab Kh\u0113l",
        "\u0639\u0631\u0628 \u062e\u06d0\u0644"
    ],
    "wof:name":"'Arab Khel",
    "wof:placetype":"locality"
},
  "geometry": {"coordinates":[69.36190000000001,33.44292],"type":"Point"}
}