{
  "type": "Feature",
  "properties": {
    "gn:admin1_code":"18",
    "gn:admin2_code":"808",
    "gn:asciiname":"Dzholagan",
    "gn:country_code":"AF",
    "gn:dem":846,
    "gn:feature_class":"P",
    "gn:feature_code":"PPL",
    "gn:name":"Dzholagan",
    "gn:population":0,
    "gn:timezone":"Asia/Kabul",
    "iso:country":"AF",
    "name:und_x_variant":[
        "J\u014dl\u0101g\u0101n",
        "Jowl\u0101g\u0101n",
        "\u062c\u0648\u0644\u0627\u06af\u0627\u0646"
    ],
    "wof:name":"Dzholagan",
    "wof:placetype":"locality"
},
  "geometry": {"coordinates":[70.45129,34.23948],"type":"Point"}
}