{
  "type": "Feature",
  "properties": {
    "gn:admin1_code":"11",
    "gn:admin2_code":"2016.0",
    "gn:asciiname":"Araq-Towaylah",
    "gn:country_code":"AF",
    "gn:dem":1598,
    "gn:feature_class":"P",
    "gn:feature_code":"PPL",
    "gn:name":"Araq-\u0162owaylah",
    "gn:population":0,
    "gn:timezone":"Asia/Kabul",
    "iso:country":"AF",
    "name:und_x_variant":[
        "A\u1e5faq-\u1e6eaw\u0113la",
        "Araq-\u0162owaylah",
        "\u0627\u0631\u0642 \u0637\u0648\u06cc\u0644\u0647",
        "Araq-\u0162av\u012blah"
    ],
    "wof:name":"Araq-Towaylah",
    "wof:placetype":"locality"
},
  "geometry": {"coordinates":[62.66721,34.68037],"type":"Point"}
}