{
  "type": "Feature",
  "properties": {
    "gn:admin1_code":"27",
    "gn:admin2_code":"409",
    "gn:asciiname":"Kaj Qal'ah",
    "gn:country_code":"AF",
    "gn:dem":2441,
    "gn:feature_class":"P",
    "gn:feature_code":"PPL",
    "gn:name":"Kaj Qal\u2018ah",
    "gn:population":0,
    "gn:timezone":"Asia/Kabul",
    "iso:country":"AF",
    "name:fas_x_preferred":[
        "\u0643\u062c \u0642\u0644\u0639\u0647"
    ],
    "name:und_x_variant":[
        "Kadzhkala",
        "Kajqal\u2018a",
        "Kaj Qal\u2018ah",
        "Kajqal\u2018eh"
    ],
    "wof:name":"Kaj Qal'ah",
    "wof:placetype":"locality"
},
  "geometry": {"coordinates":[68.33386999999999,33.75838],"type":"Point"}
}