{
  "type": "Feature",
  "properties": {
    "gn:admin1_code":"39",
    "gn:admin2_code":"2602",
    "gn:asciiname":"Khak Shahrak",
    "gn:country_code":"AF",
    "gn:dem":1819,
    "gn:feature_class":"P",
    "gn:feature_code":"PPL",
    "gn:name":"Kh\u0101k Sh\u0101hrak",
    "gn:population":0,
    "gn:timezone":"Asia/Kabul",
    "iso:country":"AF",
    "name:und_x_variant":[
        "Kh\u0101k\u0161ahrak",
        "Kh\u0101k Shahrak",
        "Kh\u0101k Sh\u0101hrak",
        "\u062e\u0627\u06a9 \u0634\u0627\u0647\u0631\u06a9"
    ],
    "wof:name":"Khak Shahrak",
    "wof:placetype":"locality"
},
  "geometry": {"coordinates":[66.31882,33.20041],"type":"Point"}
}