{
  "type": "Feature",
  "properties": {
    "gn:admin1_code":"27",
    "gn:admin2_code":"409.0",
    "gn:asciiname":"'Azim Kala",
    "gn:country_code":"AF",
    "gn:dem":2523,
    "gn:feature_class":"P",
    "gn:feature_code":"PPL",
    "gn:name":"\u2018Az\u0327\u012bm Kal\u0101",
    "gn:population":0,
    "gn:timezone":"Asia/Kabul",
    "iso:country":"AF",
    "name:fas_x_preferred":[
        "\u0642\u0644\u0639\u0647\u0654 \u0639\u0638\u06cc\u0645"
    ],
    "name:und_x_variant":[
        "Azimkala",
        "\u2018Az\u0327\u012bm Kal\u0101",
        "\u0639\u0638\u064a\u0645 \u06a9\u0644\u0627"
    ],
    "wof:name":"'Azim Kala",
    "wof:placetype":"locality"
},
  "geometry": {"coordinates":[68.30696999999999,33.78309],"type":"Point"}
}