{
  "type": "Feature",
  "properties": {
    "gn:admin1_code":"9",
    "gn:admin2_code":"2705.0",
    "gn:asciiname":"Chashmah-ye Safed",
    "gn:country_code":"AF",
    "gn:dem":2391,
    "gn:feature_class":"P",
    "gn:feature_code":"PPL",
    "gn:name":"Chashmah-ye Saf\u0113d",
    "gn:population":0,
    "gn:timezone":"Asia/Kabul",
    "iso:country":"AF",
    "name:und_x_variant":[
        "\u010ca\u0161ma Saf\u0113d",
        "Chashmasafed",
        "Cheshmeh Sef\u012bd",
        "Chashmah-ye Safayd",
        "\u0686\u0634\u0645\u06c0 \u0633\u0641\u06d0\u062f",
        "Cheshmeh-ye Sef\u012bd",
        "Chashmah-ye Saf\u0113d"
    ],
    "wof:name":"Chashmah-ye Safed",
    "wof:placetype":"locality"
},
  "geometry": {"coordinates":[64.36384,33.57717],"type":"Point"}
}