{
  "type": "Feature",
  "properties": {
    "gn:admin1_code":"06",
    "gn:admin2_code":"2104",
    "gn:asciiname":"Ijan",
    "gn:country_code":"AF",
    "gn:dem":2476,
    "gn:feature_class":"P",
    "gn:feature_code":"PPL",
    "gn:name":"\u012ajan",
    "gn:population":0,
    "gn:timezone":"Asia/Kabul",
    "iso:country":"AF",
    "name:und_x_variant":[
        "Idzhan",
        "\u012ajan",
        "\u0627\u062c\u0646",
        "\u012aj\u0101n"
    ],
    "wof:name":"Ijan",
    "wof:placetype":"locality"
},
  "geometry": {"coordinates":[64.12543000000001,32.98451],"type":"Point"}
}