{
  "type": "Feature",
  "properties": {
    "gn:admin1_code":"13",
    "gn:admin2_code":"112.0",
    "gn:asciiname":"Dah Dah",
    "gn:country_code":"AF",
    "gn:dem":990,
    "gn:feature_class":"P",
    "gn:feature_code":"PPL",
    "gn:name":"\u1e0eah \u1e0eah",
    "gn:population":0,
    "gn:timezone":"Asia/Kabul",
    "iso:country":"AF",
    "name:und_x_variant":[
        "\u1e0eah \u1e0eah",
        "\u0689\u0647 \u0689\u0647"
    ],
    "wof:name":"Dah Dah",
    "wof:placetype":"locality"
},
  "geometry": {"coordinates":[69.73371,34.61044],"type":"Point"}
}