{
  "type": "Feature",
  "properties": {
    "gn:admin1_code":"23",
    "gn:admin2_code":"2416.0",
    "gn:asciiname":"Atsakzai-ye Sharqi",
    "gn:country_code":"AF",
    "gn:dem":940,
    "gn:feature_class":"P",
    "gn:feature_code":"PPL",
    "gn:name":"Atsakza\u012b-ye Sharq\u012b",
    "gn:population":0,
    "gn:timezone":"Asia/Kabul",
    "iso:country":"AF",
    "name:fas_x_preferred":[
        "\u0627\u0686\u064a\u0643\u0632\u06cc"
    ],
    "name:und_x_variant":[
        "\u0160arqi",
        "Acekzi",
        "Achikzi",
        "Atsakza\u012b-ye Sharq\u012b",
        "\u0627\u0685\u06a9\u0632\u06cc \u0634\u0631\u0642\u06cc",
        "Atsekz\u012b"
    ],
    "wof:name":"Atsakzai-ye Sharqi",
    "wof:placetype":"locality"
},
  "geometry": {"coordinates":[65.34945,31.55097],"type":"Point"}
}