{
  "type": "Feature",
  "properties": {
    "gn:admin1_code":"41",
    "gn:admin2_code":"3403.0",
    "gn:asciiname":"Godagah",
    "gn:country_code":"AF",
    "gn:dem":2595,
    "gn:feature_class":"P",
    "gn:feature_code":"PPL",
    "gn:name":"G\u014ddag\u0101h",
    "gn:population":0,
    "gn:timezone":"Asia/Kabul",
    "iso:country":"AF",
    "name:und_x_variant":[
        "G\u014d\u1e0fag\u0101h",
        "Godagakh",
        "G\u014ddahg\u0101h",
        "G\u016bdahg\u0101h",
        "G\u014ddag\u0101h",
        "\u06af\u0648\u062f\u06af\u0627\u0647"
    ],
    "wof:name":"Godagah",
    "wof:placetype":"locality"
},
  "geometry": {"coordinates":[66.45780000000001,34.20348],"type":"Point"}
}