{
  "type": "Feature",
  "properties": {
    "gn:admin1_code":"08",
    "gn:admin2_code":"613",
    "gn:asciiname":"Wulikay",
    "gn:country_code":"AF",
    "gn:dem":2086,
    "gn:feature_class":"P",
    "gn:feature_code":"PPL",
    "gn:name":"Wul\u012bkay",
    "gn:population":0,
    "gn:timezone":"Asia/Kabul",
    "iso:country":"AF",
    "name:und_x_variant":[
        "Vulikay",
        "Wal\u012bka\u012b",
        "Wolikay",
        "\u0648\u0644\u0643\u06cc",
        "Wul\u012bkay",
        "\u0648\u0644\u06cc\u06a9\u06cc"
    ],
    "wof:name":"Wulikay",
    "wof:placetype":"locality"
},
  "geometry": {"coordinates":[68.093,33.16087],"type":"Point"}
}