{
  "type": "Feature",
  "properties": {
    "gn:admin1_code":"8",
    "gn:admin2_code":"608.0",
    "gn:asciiname":"Chambar-e Habibullah",
    "gn:country_code":"AF",
    "gn:dem":1989,
    "gn:feature_class":"P",
    "gn:feature_code":"PPL",
    "gn:name":"Chambar-e \u1e28ab\u012bbull\u0101h",
    "gn:population":0,
    "gn:timezone":"Asia/Kabul",
    "iso:country":"AF",
    "name:und_x_variant":[
        "\u010cambare Habibull\u0101h",
        "Chambari-Khabibulla",
        "Chanbar-e \u1e28ab\u012bboll\u0101h",
        "Chambar-e \u1e28ab\u012bbull\u0101h",
        "\u0686\u0645\u0628\u0631\u062d\u0628\u06cc\u0628 \u0627\ufdf2",
        "Chamar-e \u1e28ab\u012bbull\u0101h",
        "\u0686\u0645\u0631\u062d\u0628\u06cc\u0628 \u0627\ufdf2"
    ],
    "wof:name":"Chambar-e Habibullah",
    "wof:placetype":"locality"
},
  "geometry": {"coordinates":[67.82555000000001,32.79236],"type":"Point"}
}