{
  "type": "Feature",
  "properties": {
    "gn:admin1_code":"27",
    "gn:admin2_code":"404.0",
    "gn:asciiname":"Qaryah-ye Dasht",
    "gn:country_code":"AF",
    "gn:dem":2997,
    "gn:feature_class":"P",
    "gn:feature_code":"PPL",
    "gn:name":"Qaryah-ye Dasht",
    "gn:population":0,
    "gn:timezone":"Asia/Kabul",
    "iso:country":"AF",
    "name:und_x_variant":[
        "Dasht",
        "Qarya Da\u0161t",
        "Qarya-i-Da\u0161t",
        "Qa\u1e5fyah-i-\u1e0east",
        "Qaryah-ye Dasht",
        "Qaryeh-ye Dasht",
        "\u0642\u0631\u06cc\u0647 \u062f\u0634\u062a"
    ],
    "wof:name":"Qaryah-ye Dasht",
    "wof:placetype":"locality"
},
  "geometry": {"coordinates":[67.81953,34.51373],"type":"Point"}
}