{
  "type": "Feature",
  "properties": {
    "gn:admin1_code":"40",
    "gn:admin2_code":"302.0",
    "gn:asciiname":"Qal'ah-ye Baqi",
    "gn:country_code":"AF",
    "gn:dem":1728,
    "gn:feature_class":"P",
    "gn:feature_code":"PPL",
    "gn:name":"Qal\u2018ah-ye B\u0101q\u012b",
    "gn:population":0,
    "gn:timezone":"Asia/Kabul",
    "iso:country":"AF",
    "name:fas_x_preferred":[
        "\u0642\u0644\u0639\u0647 \u0628\u0627\u0642\u06cc"
    ],
    "name:und_x_variant":[
        "Kalabaki",
        "Qal\u2018a B\u0101qi",
        "Qal\u2018eh B\u0101q\u012b",
        "Qal\u2018ah-ye B\u0101q\u012b",
        "\u0642\u0644\u0639\u06c0 \u0628\u0627\u0642\u06cc"
    ],
    "wof:name":"Qal'ah-ye Baqi",
    "wof:placetype":"locality"
},
  "geometry": {"coordinates":[69.16587,35.10485],"type":"Point"}
}