{
  "type": "Feature",
  "properties": {
    "gn:admin1_code":"8",
    "gn:admin2_code":"607.0",
    "gn:asciiname":"Chihil Khanah",
    "gn:country_code":"AF",
    "gn:dem":2556,
    "gn:feature_class":"P",
    "gn:feature_code":"PPL",
    "gn:name":"Chihil Kh\u0101nah",
    "gn:population":0,
    "gn:timezone":"Asia/Kabul",
    "iso:country":"AF",
    "name:und_x_variant":[
        "\u010cehelkh\u0101na",
        "Chehel Kh\u0101neh",
        "Chihil Kh\u0101nah",
        "\u0686\u0647\u0644 \u062e\u0627\u0646\u0647"
    ],
    "wof:name":"Chihil Khanah",
    "wof:placetype":"locality"
},
  "geometry": {"coordinates":[67.27757,33.02916],"type":"Point"}
}