{
  "type": "Feature",
  "properties": {
    "gn:admin1_code":"27",
    "gn:admin2_code":"404.0",
    "gn:asciiname":"Gird Olang",
    "gn:country_code":"AF",
    "gn:dem":3038,
    "gn:feature_class":"P",
    "gn:feature_code":"PPL",
    "gn:name":"Gird \u014clang",
    "gn:population":0,
    "gn:timezone":"Asia/Kabul",
    "iso:country":"AF",
    "name:und_x_variant":[
        "Girdaulang",
        "Gerd Owlang",
        "Ge\u1e5f\u1e0f Awlang",
        "Gerd \u0100blang",
        "Gerd \u014clang",
        "Gird \u014clang",
        "\u06af\u0631\u062f \u0627\u0648\u0644\u0646\u06af"
    ],
    "wof:name":"Gird Olang",
    "wof:placetype":"locality"
},
  "geometry": {"coordinates":[67.51524999999999,34.57214],"type":"Point"}
}