{
  "type": "Feature",
  "properties": {
    "gn:admin1_code":"03",
    "gn:admin2_code":"1310",
    "gn:asciiname":"Tangi Murch",
    "gn:country_code":"AF",
    "gn:dem":1187,
    "gn:feature_class":"P",
    "gn:feature_code":"PPL",
    "gn:name":"Tang\u012b Murch",
    "gn:population":0,
    "gn:timezone":"Asia/Kabul",
    "iso:country":"AF",
    "name:und_x_variant":[
        "Tang\u012b Mu\u1e5fc",
        "Tang\u012b Murch",
        "\u062a\u0646\u06af\u06cc \u0645\u0631\u0686"
    ],
    "wof:name":"Tangi Murch",
    "wof:placetype":"locality"
},
  "geometry": {"coordinates":[69.17969000000001,36.28571],"type":"Point"}
}