{
  "type": "Feature",
  "properties": {
    "gn:admin1_code":"30",
    "gn:admin2_code":"1610",
    "gn:asciiname":"Larak",
    "gn:country_code":"AF",
    "gn:dem":1779,
    "gn:feature_class":"P",
    "gn:feature_code":"PPL",
    "gn:name":"Larak",
    "gn:population":0,
    "gn:timezone":"Asia/Kabul",
    "iso:country":"AF",
    "name:und_x_variant":[
        "\u0644\u0631\u06a9",
        "La\u1e5fak"
    ],
    "wof:name":"Larak",
    "wof:placetype":"locality"
},
  "geometry": {"coordinates":[66.8999,35.94035],"type":"Point"}
}