{
  "type": "Feature",
  "properties": {
    "gn:admin1_code":"27",
    "gn:admin2_code":"404",
    "gn:asciiname":"Darah-ye Pay Naw",
    "gn:country_code":"AF",
    "gn:dem":2965,
    "gn:feature_class":"P",
    "gn:feature_code":"PPL",
    "gn:name":"Darah-ye P\u0101y N\u0101w",
    "gn:population":0,
    "gn:timezone":"Asia/Kabul",
    "iso:country":"AF",
    "name:und_x_variant":[
        "Darreh-ye P\u0101y N\u0101v",
        "\u1e0ea\u1e5f\u1e5fahe P\u0101yn\u0101w",
        "\u1e0ea\u1e5f\u1e5fah P\u0101yn\u0101w",
        "Darrapaynav",
        "Darah-ye P\u0101y N\u0101w",
        "Darreh-ye P\u0101yn\u0101w",
        "\u062f\u0631\u06c0 \u067e\u0627\u06cc \u0646\u0627\u0648"
    ],
    "wof:name":"Darah-ye Pay Naw",
    "wof:placetype":"locality"
},
  "geometry": {"coordinates":[67.62011,34.30503],"type":"Point"}
}