{
  "type": "Feature",
  "properties": {
    "gn:admin1_code":"23",
    "gn:admin2_code":"2413.0",
    "gn:asciiname":"Multan",
    "gn:country_code":"AF",
    "gn:dem":2115,
    "gn:feature_class":"P",
    "gn:feature_code":"PPL",
    "gn:name":"Mult\u0101n",
    "gn:population":0,
    "gn:timezone":"Asia/Kabul",
    "iso:country":"AF",
    "name:rus_x_preferred":[
        "\u041c\u0443\u043b\u044c\u0442\u0430\u043d"
    ],
    "name:und_x_variant":[
        "Mult\u0101n",
        "Mul\u2019tan"
    ],
    "wof:name":"Multan",
    "wof:placetype":"locality"
},
  "geometry": {"coordinates":[67.44806,31.22778],"type":"Point"}
}