{
  "type": "Feature",
  "properties": {
    "gn:admin1_code":"11",
    "gn:admin2_code":"2014.0",
    "gn:asciiname":"Dzhinu",
    "gn:country_code":"AF",
    "gn:dem":1083,
    "gn:feature_class":"P",
    "gn:feature_code":"PPL",
    "gn:name":"Dzhinu",
    "gn:population":0,
    "gn:timezone":"Asia/Kabul",
    "iso:country":"AF",
    "name:fas_x_preferred":[
        "\u062c\u0646\u0648"
    ],
    "name:und_x_variant":[
        "Jinu",
        "Jenow",
        "J\u012bn\u016b",
        "\u062c\u06cc\u0646\u0648"
    ],
    "wof:name":"Dzhinu",
    "wof:placetype":"locality"
},
  "geometry": {"coordinates":[62.23879,33.30505],"type":"Point"}
}