{
  "type": "Feature",
  "properties": {
    "gn:admin1_code":"13",
    "gn:admin2_code":"103.0",
    "gn:asciiname":"Qal'ah-ye Rahmdil Khan",
    "gn:country_code":"AF",
    "gn:dem":1684,
    "gn:feature_class":"P",
    "gn:feature_code":"PPL",
    "gn:name":"Qal\u2018ah-ye Ra\u1e29mdil Kh\u0101n",
    "gn:population":0,
    "gn:timezone":"Asia/Kabul",
    "iso:country":"AF",
    "name:fas_x_preferred":[
        "\u0642\u0644\u0639\u06c0 \u0631\u062d\u0645 \u062f\u0644 \u062e\u0627\u0646"
    ],
    "name:rus_x_preferred":[
        "Kalayi-Rakhmdel\u2019khan"
    ],
    "name:und_x_variant":[
        "Qal\u0101-i-\u1e5eahm\u1e0felkh\u0101n",
        "Qal\u2018eh-ye Ra\u1e29mdelkh\u0101n",
        "\u0642\u0644\u0639\u06c0 \u0631\u062d\u0645\u062f\u0644 \u062e\u0627\u0646",
        "Qal\u2018ah-ye Ra\u1e29mdil Kh\u0101n"
    ],
    "wof:name":"Qal'ah-ye Rahmdil Khan",
    "wof:placetype":"locality"
},
  "geometry": {"coordinates":[69.10914,34.75941],"type":"Point"}
}