{
  "type": "Feature",
  "properties": {
    "gn:admin1_code":"18",
    "gn:admin2_code":"810.0",
    "gn:asciiname":"Bandar Khulah",
    "gn:country_code":"AF",
    "gn:dem":1158,
    "gn:feature_class":"P",
    "gn:feature_code":"PPL",
    "gn:name":"Bandar Kh\u016blah",
    "gn:population":0,
    "gn:timezone":"Asia/Kabul",
    "iso:country":"AF",
    "name:fas_x_preferred":[
        "\u062f\u0647\u0627\u0646\u0654 \u0628\u0646\u062f\u0631"
    ],
    "name:und_x_variant":[
        "Bandarkhula",
        "Bandar Kholeh",
        "Bandar Kh\u016blah",
        "\u0628\u0646\u062f\u0631 \u062e\u0648\u0644\u0647"
    ],
    "wof:name":"Bandar Khulah",
    "wof:placetype":"locality"
},
  "geometry": {"coordinates":[70.76446999999997,34.06889],"type":"Point"}
}