{
  "type": "Feature",
  "properties": {
    "gn:admin1_code":"08",
    "gn:admin2_code":"616",
    "gn:asciiname":"Lolah",
    "gn:country_code":"AF",
    "gn:dem":2587,
    "gn:feature_class":"P",
    "gn:feature_code":"PPL",
    "gn:name":"L\u014dlah",
    "gn:population":0,
    "gn:timezone":"Asia/Kabul",
    "iso:country":"AF",
    "name:und_x_variant":[
        "Lola",
        "L\u014dla",
        "L\u014dlah",
        "Lowlah",
        "\u0644\u0648\u0644\u0647"
    ],
    "wof:name":"Lolah",
    "wof:placetype":"locality"
},
  "geometry": {"coordinates":[68.57267,33.67198],"type":"Point"}
}