{
  "type": "Feature",
  "properties": {
    "gn:admin1_code":"37",
    "gn:admin2_code":"3203.0",
    "gn:asciiname":"Metsiyangah",
    "gn:country_code":"AF",
    "gn:dem":1974,
    "gn:feature_class":"P",
    "gn:feature_code":"PPL",
    "gn:name":"M\u00eatsiy\u0101ngah",
    "gn:population":0,
    "gn:timezone":"Asia/Kabul",
    "iso:country":"AF",
    "name:fas_x_preferred":[
        "\u0645\u0686\u064a\u0627\u0646\u06af\u0647"
    ],
    "name:rus_x_preferred":[
        "Mech\u2019yanga"
    ],
    "name:und_x_variant":[
        "M\u011bcy\u0101nga",
        "M\u00eatsy\u0101ngah",
        "Metsy\u0101ngah",
        "M\u00eatsiy\u0101ngah"
    ],
    "wof:name":"Metsiyangah",
    "wof:placetype":"locality"
},
  "geometry": {"coordinates":[69.67489999999999,33.14319],"type":"Point"}
}