{
  "type": "Feature",
  "properties": {
    "gn:admin1_code":"36",
    "gn:admin2_code":"711",
    "gn:asciiname":"Shegah",
    "gn:country_code":"AF",
    "gn:dem":2148,
    "gn:feature_class":"P",
    "gn:feature_code":"PPL",
    "gn:name":"Sh\u00eagah",
    "gn:population":0,
    "gn:timezone":"Asia/Kabul",
    "iso:country":"AF",
    "name:und_x_variant":[
        "\u0160\u011bga",
        "Shega",
        "Shegah",
        "Sh\u00eagah",
        "\u0634\u06af\u0647"
    ],
    "wof:name":"Shegah",
    "wof:placetype":"locality"
},
  "geometry": {"coordinates":[69.69109,33.94130999999999],"type":"Point"}
}