{
  "type": "Feature",
  "properties": {
    "gn:admin1_code":"32",
    "gn:admin2_code":"1503",
    "gn:asciiname":"Maschaytak",
    "gn:country_code":"AF",
    "gn:dem":2375,
    "gn:feature_class":"P",
    "gn:feature_code":"PPL",
    "gn:name":"Maschaytak",
    "gn:population":0,
    "gn:timezone":"Asia/Kabul",
    "iso:country":"AF",
    "name:und_x_variant":[
        "Michtak",
        "Masc\u0113tak",
        "Masch\u0113tak",
        "Maschaytak",
        "\u0645\u0633\u0686\u06cc\u062a\u06a9"
    ],
    "wof:name":"Maschaytak",
    "wof:placetype":"locality"
},
  "geometry": {"coordinates":[67.21316,35.53157],"type":"Point"}
}