{
  "type": "Feature",
  "properties": {
    "gn:admin1_code":"5",
    "gn:admin2_code":"2804.0",
    "gn:asciiname":"Katah Khanah",
    "gn:country_code":"AF",
    "gn:dem":2557,
    "gn:feature_class":"P",
    "gn:feature_code":"PPL",
    "gn:name":"Katah Kh\u0101nah",
    "gn:population":0,
    "gn:timezone":"Asia/Kabul",
    "iso:country":"AF",
    "name:und_x_variant":[
        "Katakhana",
        "Katakh\u0101na",
        "Katah Kh\u0101nah",
        "Katahkh\u0101neh",
        "\u06af\u062a\u0647 \u062e\u0627\u0646\u0647"
    ],
    "wof:name":"Katah Khanah",
    "wof:placetype":"locality"
},
  "geometry": {"coordinates":[66.95475999999999,34.74209],"type":"Point"}
}