{
  "type": "Feature",
  "properties": {
    "gn:admin1_code":"10",
    "gn:admin2_code":"2303",
    "gn:asciiname":"Khak-e Jahannum",
    "gn:country_code":"AF",
    "gn:dem":996,
    "gn:feature_class":"P",
    "gn:feature_code":"PPL",
    "gn:name":"Kh\u0101k-e Jahannum",
    "gn:population":0,
    "gn:timezone":"Asia/Kabul",
    "iso:country":"AF",
    "name:und_x_variant":[
        "Khhke Jhhannum",
        "Kh\u0101ke Jahnnum",
        "Khaki-Dzhakhannum",
        "Kh\u0101k-e Jahannum",
        "\u062e\u0627\u06a9 \u062c\u0647\u0646\u0645",
        "Kh\u0101k-e Jahannam"
    ],
    "wof:name":"Khak-e Jahannum",
    "wof:placetype":"locality"
},
  "geometry": {"coordinates":[65.11570999999999,32.35625],"type":"Point"}
}