{
  "type": "Feature",
  "properties": {
    "gn:admin1_code":"8",
    "gn:admin2_code":"608.0",
    "gn:asciiname":"Manak Khel",
    "gn:country_code":"AF",
    "gn:dem":2007,
    "gn:feature_class":"P",
    "gn:feature_code":"PPL",
    "gn:name":"M\u0101nak Kh\u0113l",
    "gn:population":0,
    "gn:timezone":"Asia/Kabul",
    "iso:country":"AF",
    "name:und_x_variant":[
        "M\u0101nak Kh\u0113l",
        "\u0645\u0627\u0646\u06a9 \u062e\u06d0\u0644",
        "M\u0101nak Kheyl"
    ],
    "wof:name":"Manak Khel",
    "wof:placetype":"locality"
},
  "geometry": {"coordinates":[67.80384000000001,32.83964],"type":"Point"}
}