{
  "type": "Feature",
  "properties": {
    "gn:admin1_code":"23",
    "gn:admin2_code":"2407",
    "gn:asciiname":"Rang Rayzan",
    "gn:country_code":"AF",
    "gn:dem":884,
    "gn:feature_class":"P",
    "gn:feature_code":"PPL",
    "gn:name":"Rang Rayz\u0101n",
    "gn:population":0,
    "gn:timezone":"Asia/Kabul",
    "iso:country":"AF",
    "name:fas_x_preferred":[
        "\u0631\u0646\u06af\u0631\u064a\u0632\u0627\u0646"
    ],
    "name:und_x_variant":[
        "\u1e5eang\u1e5f\u0113z\u0101n",
        "Rangrezan",
        "Rang Rayz\u0101n",
        "\u0631\u0646\u06af \u0631\u06cc\u0632\u0627\u0646",
        "Rangr\u012bz\u0101n"
    ],
    "wof:name":"Rang Rayzan",
    "wof:placetype":"locality"
},
  "geometry": {"coordinates":[65.18075999999999,31.51323],"type":"Point"}
}