{
  "type": "Feature",
  "properties": {
    "gn:admin1_code":"19",
    "gn:admin2_code":"2204.0",
    "gn:asciiname":"Sarfaraz-e Khwashi",
    "gn:country_code":"AF",
    "gn:dem":482,
    "gn:feature_class":"P",
    "gn:feature_code":"PPL",
    "gn:name":"Sarfar\u0101z-e Khw\u0101sh\u012b",
    "gn:population":0,
    "gn:timezone":"Asia/Kabul",
    "iso:country":"AF",
    "name:und_x_variant":[
        "Sa\u1e5ffa\u1e5f\u0101ze Khw\u0101si",
        "Sarfar\u0101z-e Khw\u0101sh\u012b",
        "\u0633\u0631\u0641\u0631\u0627\u0632 \u062e\u0648\u0627\u0634\u06cc",
        "Sarfar\u0101ze Khv\u0101sh\u012b"
    ],
    "wof:name":"Sarfaraz-e Khwashi",
    "wof:placetype":"locality"
},
  "geometry": {"coordinates":[62.06509000000001,31.19541],"type":"Point"}
}