{
  "type": "Feature",
  "properties": {
    "gn:admin1_code":"41",
    "gn:admin2_code":"3409.0",
    "gn:asciiname":"Dewalak",
    "gn:country_code":"AF",
    "gn:dem":1493,
    "gn:feature_class":"P",
    "gn:feature_code":"PPL",
    "gn:name":"D\u0113w\u0101lak",
    "gn:population":0,
    "gn:timezone":"Asia/Kabul",
    "iso:country":"AF",
    "name:und_x_variant":[
        "Dayw\u0101lak",
        "\u062f\u06cc\u0648\u0627\u0644\u06a9",
        "\u1e0eiw\u0101lak",
        "D\u0113w\u0101lak"
    ],
    "wof:name":"Dewalak",
    "wof:placetype":"locality"
},
  "geometry": {"coordinates":[66.52544,33.60355999999999],"type":"Point"}
}