{
  "type": "Feature",
  "properties": {
    "gn:admin1_code":"40",
    "gn:admin2_code":"301.0",
    "gn:asciiname":"Bayan-e Pa'in",
    "gn:country_code":"AF",
    "gn:dem":1501,
    "gn:feature_class":"P",
    "gn:feature_code":"PPL",
    "gn:name":"B\u0101y\u0101n-e P\u0101\u2019\u012bn",
    "gn:population":0,
    "gn:timezone":"Asia/Kabul",
    "iso:country":"AF",
    "name:fas_x_preferred":[
        "\u0628\u0627\u064a\u0627\u0646\u0654 \u067e\u0627\u0626\u064a\u0646"
    ],
    "name:und_x_variant":[
        "Bayani-Pain",
        "B\u0101y\u0101n-e P\u0101\u2019\u012bn",
        "\u0628\u0627\u064a\u0627\u0646\u0654 \u067e\u0627\u0626\u064a\u0646",
        "\u0628\u0627\u06cc\u0627\u0646 \u067e\u0627\u0626\u06cc\u0646"
    ],
    "wof:name":"Bayan-e Pa'in",
    "wof:placetype":"locality"
},
  "geometry": {"coordinates":[69.22193,35.00608],"type":"Point"}
}