{
  "type": "Feature",
  "properties": {
    "gn:admin1_code":"40",
    "gn:admin2_code":"307",
    "gn:asciiname":"Qapzar",
    "gn:country_code":"AF",
    "gn:dem":3167,
    "gn:feature_class":"P",
    "gn:feature_code":"PPL",
    "gn:name":"Q\u0101pz\u0101r",
    "gn:population":0,
    "gn:timezone":"Asia/Kabul",
    "iso:country":"AF",
    "name:und_x_variant":[
        "Kapzar",
        "Q\u0101pz\u0101r",
        "Q\u0101fz\u0101r",
        "\u0642\u0627\u067e\u0632\u0627\u0631"
    ],
    "wof:name":"Qapzar",
    "wof:placetype":"locality"
},
  "geometry": {"coordinates":[68.42563,34.66577],"type":"Point"}
}