{
  "type": "Feature",
  "properties": {
    "gn:admin1_code":"39",
    "gn:admin2_code":"2604",
    "gn:asciiname":"Kakrak",
    "gn:country_code":"AF",
    "gn:dem":1143,
    "gn:feature_class":"P",
    "gn:feature_code":"PPL",
    "gn:name":"Kakrak",
    "gn:population":0,
    "gn:timezone":"Asia/Kabul",
    "iso:country":"AF",
    "name:und_x_variant":[
        "\u06a9\u06a9\u0631\u06a9",
        "Kak\u1e5fak"
    ],
    "wof:name":"Kakrak",
    "wof:placetype":"locality"
},
  "geometry": {"coordinates":[65.67256999999999,32.9708],"type":"Point"}
}