{
  "type": "Feature",
  "properties": {
    "gn:admin1_code":"09",
    "gn:admin2_code":"2706",
    "gn:asciiname":"Rabatak",
    "gn:country_code":"AF",
    "gn:dem":2123,
    "gn:feature_class":"P",
    "gn:feature_code":"PPL",
    "gn:name":"Rab\u0101\u0163ak",
    "gn:population":0,
    "gn:timezone":"Asia/Kabul",
    "iso:country":"AF",
    "name:und_x_variant":[
        "Rab\u0101\u0163ak",
        "\u0631\u0628\u0627\u0637\u06a9"
    ],
    "wof:name":"Rabatak",
    "wof:placetype":"locality"
},
  "geometry": {"coordinates":[65.45189999999999,33.63555],"type":"Point"}
}