{
  "type": "Feature",
  "properties": {
    "gn:admin1_code":"5",
    "gn:admin2_code":"2804.0",
    "gn:asciiname":"Top-e Kilak",
    "gn:country_code":"AF",
    "gn:dem":2490,
    "gn:feature_class":"P",
    "gn:feature_code":"PPL",
    "gn:name":"T\u014dp-e Kilak",
    "gn:population":0,
    "gn:timezone":"Asia/Kabul",
    "iso:country":"AF",
    "name:und_x_variant":[
        "Topi-Kilak",
        "T\u014dpe Kelak",
        "T\u014dp-e Kelak",
        "T\u016bp-e Kelak",
        "T\u014dp-e Kilak",
        "\u062a\u0648\u067e \u06a9\u0644\u06a9"
    ],
    "wof:name":"Top-e Kilak",
    "wof:placetype":"locality"
},
  "geometry": {"coordinates":[66.84595999999999,34.73569000000001],"type":"Point"}
}