{
  "type": "Feature",
  "properties": {
    "gn:admin1_code":"27",
    "gn:admin2_code":"403",
    "gn:asciiname":"Qol-e Madat",
    "gn:country_code":"AF",
    "gn:dem":3102,
    "gn:feature_class":"P",
    "gn:feature_code":"PPL",
    "gn:name":"Q\u014dl-e Madat",
    "gn:population":0,
    "gn:timezone":"Asia/Kabul",
    "iso:country":"AF",
    "name:und_x_variant":[
        "Kuli-Madat",
        "Q\u014dle Ma\u1e0fat",
        "Q\u014dl-e Madat",
        "Qowl-e Madat",
        "\u0642\u0648\u0644 \u0645\u062f\u062a"
    ],
    "wof:name":"Qol-e Madat",
    "wof:placetype":"locality"
},
  "geometry": {"coordinates":[68.08133000000001,34.4741],"type":"Point"}
}