{
  "type": "Feature",
  "properties": {
    "gn:admin1_code":"23",
    "gn:admin2_code":"2412.0",
    "gn:asciiname":"Landi Kelay",
    "gn:country_code":"AF",
    "gn:dem":1422,
    "gn:feature_class":"P",
    "gn:feature_code":"PPL",
    "gn:name":"Lan\u1e0f\u012b K\u00ealay",
    "gn:population":0,
    "gn:timezone":"Asia/Kabul",
    "iso:country":"AF",
    "name:und_x_variant":[
        "Landikalay",
        "Landi Kalay",
        "Lan\u1e0f\u012b K\u00ealay",
        "\u0644\u0646\u0689\u06cc \u06a9\u0644\u06cc"
    ],
    "wof:name":"Landi Kelay",
    "wof:placetype":"locality"
},
  "geometry": {"coordinates":[66.57342,31.31806],"type":"Point"}
}