{
  "type": "Feature",
  "properties": {
    "gn:admin1_code":"26",
    "gn:admin2_code":"1215",
    "gn:asciiname":"Gul Maysh",
    "gn:country_code":"AF",
    "gn:dem":1070,
    "gn:feature_class":"P",
    "gn:feature_code":"PPL",
    "gn:name":"Gul Maysh",
    "gn:population":0,
    "gn:timezone":"Asia/Kabul",
    "iso:country":"AF",
    "name:fas_x_preferred":[
        "\u06af\u0644 \u0645\u064a\u0634"
    ],
    "name:rus_x_preferred":[
        "\u0413\u0443\u043b\u044c\u043c\u0435\u0448"
    ],
    "name:und_x_variant":[
        "Gul M\u0113\u0161",
        "Gul\u2019mesh",
        "Gol Mesh",
        "Gol Mach",
        "Gol M\u012bsh",
        "Gul Maysh",
        "\u06af\u0644 \u0645\u06cc\u0634"
    ],
    "wof:name":"Gul Maysh",
    "wof:placetype":"locality"
},
  "geometry": {"coordinates":[69.50799000000001,36.93845],"type":"Point"}
}