{
  "type": "Feature",
  "properties": {
    "gn:admin1_code":"2",
    "gn:admin2_code":"1907.0",
    "gn:asciiname":"Deh-e Babula'i",
    "gn:cc2":"AF",
    "gn:country_code":"AF",
    "gn:dem":596,
    "gn:feature_class":"P",
    "gn:feature_code":"PPL",
    "gn:name":"Deh-e B\u0101b\u016bl\u0101\u2019\u012b",
    "gn:population":0,
    "gn:timezone":"Asia/Kabul",
    "iso:country":"AF",
    "name:und_x_variant":[
        "\u1e0eeh-i-B\u0101b\u016bl\u0101\u2018i",
        "B\u0101b\u016b\u2019\u012b Z\u012by\u0101rat",
        "B\u0101bulai Zi\u0101rat",
        "Deh-e B\u0101b\u016bl\u0101\u2019\u012b",
        "\u062f\u0647 \u0628\u0627\u0628\u0648\u0644\u0627\u0626\u06cc",
        "B\u0101b\u016bl\u0101\u2019\u012b",
        "\u1e0eeh-i-B\u0101b\u016bl\u0101\u2019i"
    ],
    "wof:name":"Deh-e Babula'i",
    "wof:placetype":"locality"
},
  "geometry": {"coordinates":[62.95096,35.31899],"type":"Point"}
}