{
  "type": "Feature",
  "properties": {
    "gn:admin1_code":"33",
    "gn:admin2_code":"3107",
    "gn:asciiname":"Qishlaq-e Sarwar",
    "gn:country_code":"AF",
    "gn:dem":1326,
    "gn:feature_class":"P",
    "gn:feature_code":"PPL",
    "gn:name":"Qishl\u0101q-e Sarwar",
    "gn:population":0,
    "gn:timezone":"Asia/Kabul",
    "iso:country":"AF",
    "name:und_x_variant":[
        "Qes\u0304l\u0101ge Sa\u1e5fwa\u1e5f",
        "Qes\u0304l\u0101qe Sa\u1e5fwa\u1e5f",
        "Qeshl\u0101q-e Sarvar",
        "Qishl\u0101q-e Sarwar",
        "\u0642\u0634\u0644\u0627\u0642 \u0633\u0631\u0648\u0631"
    ],
    "wof:name":"Qishlaq-e Sarwar",
    "wof:placetype":"locality"
},
  "geometry": {"coordinates":[66.59475999999999,35.90766],"type":"Point"}
}