{
  "type": "Feature",
  "properties": {
    "gn:admin1_code":"03",
    "gn:admin2_code":"1303.0",
    "gn:asciiname":"Daymirak",
    "gn:country_code":"AF",
    "gn:dem":735,
    "gn:feature_class":"P",
    "gn:feature_code":"PPL",
    "gn:name":"Daym\u012brak",
    "gn:population":0,
    "gn:timezone":"Asia/Kabul",
    "iso:country":"AF",
    "name:und_x_variant":[
        "Daymi\u1e5fak",
        "Daym\u012brak",
        "\u062f\u06cc\u0645\u06cc\u0631\u06a9"
    ],
    "wof:name":"Daymirak",
    "wof:placetype":"locality"
},
  "geometry": {"coordinates":[68.52123,35.8973],"type":"Point"}
}