{
  "type": "Feature",
  "properties": {
    "gn:admin1_code":"39",
    "gn:admin2_code":"2604",
    "gn:asciiname":"Gazak",
    "gn:country_code":"AF",
    "gn:dem":1158,
    "gn:feature_class":"P",
    "gn:feature_code":"PPL",
    "gn:name":"Gazak",
    "gn:population":0,
    "gn:timezone":"Asia/Kabul",
    "iso:country":"AF",
    "name:fas_x_preferred":[
        "\u06af\u0632\u0643"
    ],
    "name:rus_x_preferred":[
        "\u0413\u0430\u0437\u0430\u043a"
    ],
    "name:und_x_variant":[
        "\u06af\u0632\u06a9"
    ],
    "wof:name":"Gazak",
    "wof:placetype":"locality"
},
  "geometry": {"coordinates":[65.49604000000001,33.01487],"type":"Point"}
}