{
  "type": "Feature",
  "properties": {
    "gn:admin1_code":"13",
    "gn:admin2_code":"101.0",
    "gn:asciiname":"Qal'ah-ye Pakhchak",
    "gn:country_code":"AF",
    "gn:dem":1835,
    "gn:feature_class":"P",
    "gn:feature_code":"PPL",
    "gn:name":"Qal\u2018ah-ye Pakhchak",
    "gn:population":0,
    "gn:timezone":"Asia/Kabul",
    "iso:country":"AF",
    "name:und_x_variant":[
        "Kalapakhchakh",
        "Qal\u2019eh Pakh\u010dak",
        "Qal\u2018ah Pakhchak",
        "Qal\u2018eh Pakhchak",
        "Qal\u2018ah-ye Pakhchak",
        "\u0642\u0644\u0639\u0647 \u067e\u062e\u0686\u06a9"
    ],
    "wof:name":"Qal'ah-ye Pakhchak",
    "wof:placetype":"locality"
},
  "geometry": {"coordinates":[69.10262,34.48225],"type":"Point"}
}