{
  "type": "Feature",
  "properties": {
    "gn:admin1_code":"28",
    "gn:admin2_code":"2503",
    "gn:asciiname":"Sharah Talah",
    "gn:country_code":"AF",
    "gn:dem":1490,
    "gn:feature_class":"P",
    "gn:feature_code":"PPL",
    "gn:name":"S\u0332h\u0332arah T\u0101lah",
    "gn:population":0,
    "gn:timezone":"Asia/Kabul",
    "iso:country":"AF",
    "name:fas_x_preferred":[
        "\u0634\u0631\u062a\u0627\u0644\u0627"
    ],
    "name:und_x_variant":[
        "Sar T\u0101leh",
        "Sharatala",
        "\u0160arat\u0101l\u0101",
        "S\u0332h\u0332arah T\u0101lah",
        "\u069a\u0631\u0647 \u062a\u0627\u0644\u0647",
        "Sharat\u0101l\u0101"
    ],
    "wof:name":"Sharah Talah",
    "wof:placetype":"locality"
},
  "geometry": {"coordinates":[66.6738,32.36674],"type":"Point"}
}