{
  "type": "Feature",
  "properties": {
    "gn:admin1_code":"10",
    "gn:admin2_code":"2306",
    "gn:asciiname":"Kinjak-e Sufla",
    "gn:country_code":"AF",
    "gn:dem":1286,
    "gn:feature_class":"P",
    "gn:feature_code":"PPL",
    "gn:name":"Kinjak-e Sufl\u00e1",
    "gn:population":0,
    "gn:timezone":"Asia/Kabul",
    "iso:country":"AF",
    "name:und_x_variant":[
        "Kindzhaki-Sufla",
        "Kenjake Sufl\u0101",
        "Kinjak",
        "Kinjak-e Sufl\u00e1",
        "\u06a9\u0646\u062c\u06a9 \u0633\u0641\u0644\u0649",
        "Kenjak-e Sofl\u00e1"
    ],
    "wof:name":"Kinjak-e Sufla",
    "wof:placetype":"locality"
},
  "geometry": {"coordinates":[64.48371999999999,32.47356],"type":"Point"}
}