{
  "type": "Feature",
  "properties": {
    "gn:admin1_code":"33",
    "gn:admin2_code":"3104.0",
    "gn:asciiname":"Bakhsha-ye Khuda'i",
    "gn:country_code":"AF",
    "gn:dem":1795,
    "gn:feature_class":"P",
    "gn:feature_code":"PPL",
    "gn:name":"Bakhsh\u0101-ye Khud\u0101\u2019\u012b",
    "gn:population":0,
    "gn:timezone":"Asia/Kabul",
    "iso:country":"AF",
    "name:und_x_variant":[
        "Bakhs\u0304a-i-Kho\u1e0f\u0101\u2019i",
        "Bakhsh\u0101-ye Khod\u0101\u2019\u012b",
        "Bakhsh\u0101-ye Khud\u0101\u2019\u012b",
        "\u0628\u062e\u0634\u0627\u06cc \u062e\u062f\u0627\u0626\u06cc"
    ],
    "wof:name":"Bakhsha-ye Khuda'i",
    "wof:placetype":"locality"
},
  "geometry": {"coordinates":[66.50479,35.3542],"type":"Point"}
}