{
  "type": "Feature",
  "properties": {
    "gn:admin1_code":"8",
    "gn:admin2_code":"613.0",
    "gn:asciiname":"Kotaray",
    "gn:country_code":"AF",
    "gn:dem":2127,
    "gn:feature_class":"P",
    "gn:feature_code":"PPL",
    "gn:name":"K\u014dtaray",
    "gn:population":0,
    "gn:timezone":"Asia/Kabul",
    "iso:country":"AF",
    "name:fas_x_preferred":[
        "\u0643\u0648\u062a\u0631\u06cc"
    ],
    "name:und_x_variant":[
        "K\u014dta\u1e5fay",
        "Kowtaray",
        "K\u014dtaray",
        "\u06a9\u0648\u062a\u0631\u06cc"
    ],
    "wof:name":"Kotaray",
    "wof:placetype":"locality"
},
  "geometry": {"coordinates":[68.04968000000001,33.16047],"type":"Point"}
}