{
  "type": "Feature",
  "properties": {
    "gn:admin1_code":"23",
    "gn:admin2_code":"2404.0",
    "gn:asciiname":"Babasakhib",
    "gn:country_code":"AF",
    "gn:dem":1014,
    "gn:feature_class":"P",
    "gn:feature_code":"PPLA2",
    "gn:name":"Babasakhib",
    "gn:population":0,
    "gn:timezone":"Asia/Kabul",
    "iso:country":"AF",
    "name:und_x_variant":[
        "B\u0101b\u0101 \u015e\u0101\u1e29ib",
        "\u0628\u0627\u0628\u0627 \u0635\u0627\u062d\u0628",
        "B\u0101b\u0101 \u015e\u0101\u1e29eb"
    ],
    "wof:name":"Babasakhib",
    "wof:placetype":"locality"
},
  "geometry": {"coordinates":[65.66098000000001,31.66144],"type":"Point"}
}