{
  "type": "Feature",
  "properties": {
    "gn:admin1_code":"41",
    "gn:admin2_code":"3401.0",
    "gn:asciiname":"Ghow",
    "gn:country_code":"AF",
    "gn:dem":2152,
    "gn:feature_class":"P",
    "gn:feature_code":"PPL",
    "gn:name":"Ghow",
    "gn:population":0,
    "gn:timezone":"Asia/Kabul",
    "iso:country":"AF",
    "name:und_x_variant":[
        "\u063a\u0648",
        "Ghaw"
    ],
    "wof:name":"Ghow",
    "wof:placetype":"locality"
},
  "geometry": {"coordinates":[66.10259000000001,33.81918],"type":"Point"}
}