{
  "type": "Feature",
  "properties": {
    "gn:admin1_code":"36",
    "gn:admin2_code":"707",
    "gn:asciiname":"Karoto Kelay",
    "gn:country_code":"AF",
    "gn:dem":2202,
    "gn:feature_class":"P",
    "gn:feature_code":"PPL",
    "gn:name":"Kar\u014d\u1e6f\u014d K\u00ealay",
    "gn:population":0,
    "gn:timezone":"Asia/Kabul",
    "iso:country":"AF",
    "name:und_x_variant":[
        "Ka\u1e5f\u014dto Kalay",
        "Karotukalay",
        "Karowto Kalay",
        "Kar\u014d\u1e6f\u014d K\u00ealay",
        "\u06a9\u0631\u0648\u067c\u0648 \u06a9\u0644\u06cc",
        "Kar\u014dt\u014d K\u00ealay",
        "\u06a9\u0631\u0648\u062a\u0648 \u06a9\u0644\u06cc"
    ],
    "wof:name":"Karoto Kelay",
    "wof:placetype":"locality"
},
  "geometry": {"coordinates":[69.86865999999999,33.89371],"type":"Point"}
}