{
  "type": "Feature",
  "properties": {
    "gn:admin1_code":"35",
    "gn:admin2_code":"903.0",
    "gn:asciiname":"Alakhadzhigar",
    "gn:country_code":"AF",
    "gn:dem":882,
    "gn:feature_class":"P",
    "gn:feature_code":"PPL",
    "gn:name":"Alakhadzhigar",
    "gn:population":0,
    "gn:timezone":"Asia/Kabul",
    "iso:country":"AF",
    "name:und_x_variant":[
        "A\u2019l\u0101 \u1e28\u0101jiga\u1e5f",
        "\u0627\u0639\u0644\u0649 \u062d\u0627\u062c\u06cc\u06af\u0631",
        "A\u2018l\u00e1 \u1e28\u0101j\u012bgar",
        "A\u2018l\u0101 \u1e28\u0101jj\u012bgar",
        "A\u2018l\u0101 \u1e28\u0101j\u012bgar",
        "\u0627\u0639\u0644\u0627 \u062d\u0627\u062c\u06cc\u06af\u0631"
    ],
    "wof:name":"Alakhadzhigar",
    "wof:placetype":"locality"
},
  "geometry": {"coordinates":[70.34357,34.79332],"type":"Point"}
}