{
  "type": "Feature",
  "properties": {
    "gn:admin1_code":"18",
    "gn:admin2_code":"807.0",
    "gn:asciiname":"Bandiyan",
    "gn:country_code":"AF",
    "gn:dem":1437,
    "gn:feature_class":"P",
    "gn:feature_code":"PPL",
    "gn:name":"Bandiy\u0101n",
    "gn:population":0,
    "gn:timezone":"Asia/Kabul",
    "iso:country":"AF",
    "name:rus_x_preferred":[
        "Band\u2019yan"
    ],
    "name:und_x_variant":[
        "Ban\u1e0fy\u0101n",
        "Bandiy\u0101n",
        "\u0628\u0646\u062f\u06cc\u0627\u0646"
    ],
    "wof:name":"Bandiyan",
    "wof:placetype":"locality"
},
  "geometry": {"coordinates":[70.24105,34.1607],"type":"Point"}
}