{
  "type": "Feature",
  "properties": {
    "gn:admin1_code":"41",
    "gn:admin2_code":"3407.0",
    "gn:asciiname":"Shor Taq",
    "gn:country_code":"AF",
    "gn:dem":2389,
    "gn:feature_class":"P",
    "gn:feature_code":"PPL",
    "gn:name":"Sh\u014dr \u0162\u0101q",
    "gn:population":0,
    "gn:timezone":"Asia/Kabul",
    "iso:country":"AF",
    "name:und_x_variant":[
        "\u0160ort\u0101q",
        "Sh\u014dr \u0162\u0101q",
        "Shor\u0163\u0101q",
        "\u0634\u0648\u0631 \u0637\u0627\u0642"
    ],
    "wof:name":"Shor Taq",
    "wof:placetype":"locality"
},
  "geometry": {"coordinates":[66.88724000000001,33.8655],"type":"Point"}
}