{
  "type": "Feature",
  "properties": {
    "gn:admin1_code":"11",
    "gn:admin2_code":"2006",
    "gn:asciiname":"Kashkal",
    "gn:country_code":"AF",
    "gn:dem":1212,
    "gn:feature_class":"P",
    "gn:feature_code":"PPL",
    "gn:name":"Kashkal",
    "gn:population":0,
    "gn:timezone":"Asia/Kabul",
    "iso:country":"AF",
    "name:rus_x_preferred":[
        "Kashkal\u2019"
    ],
    "name:und_x_variant":[
        "Ka\u0161kal",
        "Kashkal",
        "\u06a9\u0634\u06a9\u0644"
    ],
    "wof:name":"Kashkal",
    "wof:placetype":"locality"
},
  "geometry": {"coordinates":[62.21076,34.78471],"type":"Point"}
}