{
  "type": "Feature",
  "properties": {
    "gn:admin1_code":"23",
    "gn:admin2_code":"2413.0",
    "gn:asciiname":"Ghizeh Band",
    "gn:country_code":"AF",
    "gn:dem":1921,
    "gn:feature_class":"P",
    "gn:feature_code":"PPL",
    "gn:name":"Ghiz\u00eah Band",
    "gn:population":0,
    "gn:timezone":"Asia/Kabul",
    "iso:country":"AF",
    "name:und_x_variant":[
        "Razvaliny Gizaband",
        "Ghiz\u00eah Band",
        "\u063a\u0632\u0647 \u0628\u0646\u062f",
        "Ghezeh Band"
    ],
    "wof:name":"Ghizeh Band",
    "wof:placetype":"locality"
},
  "geometry": {"coordinates":[67.29000000000001,31.60854],"type":"Point"}
}