{
  "type": "Feature",
  "properties": {
    "gn:admin1_code":"27",
    "gn:admin2_code":"404.0",
    "gn:asciiname":"Jasah",
    "gn:country_code":"AF",
    "gn:dem":3040,
    "gn:feature_class":"P",
    "gn:feature_code":"PPL",
    "gn:name":"Jasah",
    "gn:population":0,
    "gn:timezone":"Asia/Kabul",
    "iso:country":"AF",
    "name:und_x_variant":[
        "\u062c\u0633\u0647"
    ],
    "wof:name":"Jasah",
    "wof:placetype":"locality"
},
  "geometry": {"coordinates":[67.43996,34.34255],"type":"Point"}
}