{
  "type": "Feature",
  "properties": {
    "gn:admin1_code":"10",
    "gn:admin2_code":"2306.0",
    "gn:asciiname":"Amrut",
    "gn:country_code":"AF",
    "gn:dem":1781,
    "gn:feature_class":"P",
    "gn:feature_code":"PPL",
    "gn:name":"Amr\u016bt",
    "gn:population":0,
    "gn:timezone":"Asia/Kabul",
    "iso:country":"AF",
    "name:und_x_variant":[
        "Amr\u016bt",
        "\u0627\u0645\u0631\u0648\u062a"
    ],
    "wof:name":"Amrut",
    "wof:placetype":"locality"
},
  "geometry": {"coordinates":[64.57014000000001,32.85734],"type":"Point"}
}