{
  "type": "Feature",
  "properties": {
    "gn:admin1_code":"10",
    "gn:admin2_code":"2302.0",
    "gn:asciiname":"Shamali Nurzai",
    "gn:country_code":"AF",
    "gn:dem":825,
    "gn:feature_class":"P",
    "gn:feature_code":"PPL",
    "gn:name":"Sham\u0101l\u012b N\u016brza\u012b",
    "gn:population":0,
    "gn:timezone":"Asia/Kabul",
    "iso:country":"AF",
    "name:und_x_variant":[
        "Shamali-Nurzai",
        "\u0160am\u0101li N\u016brza\u2019i",
        "Sham\u0101l\u012b N\u016brza\u012b",
        "\u0634\u0645\u0627\u0644\u06cc \u0646\u0648\u0631\u0632\u06cc",
        "Shom\u0101l\u012b N\u016brza\u2019i"
    ],
    "wof:name":"Shamali Nurzai",
    "wof:placetype":"locality"
},
  "geometry": {"coordinates":[64.59879000000001,31.81932],"type":"Point"}
}