{
  "type": "Feature",
  "properties": {
    "gn:admin1_code":"05",
    "gn:admin2_code":"2806.0",
    "gn:asciiname":"Sewjoy",
    "gn:country_code":"AF",
    "gn:dem":2986,
    "gn:feature_class":"P",
    "gn:feature_code":"PPL",
    "gn:name":"S\u0113wj\u014dy",
    "gn:population":0,
    "gn:timezone":"Asia/Kabul",
    "iso:country":"AF",
    "name:und_x_variant":[
        "S\u0113wj\u014dy",
        "\u0633\u06d0\u0648\u062c\u0648\u06d0"
    ],
    "wof:name":"Sewjoy",
    "wof:placetype":"locality"
},
  "geometry": {"coordinates":[66.96419,34.09979000000001],"type":"Point"}
}