{
  "type": "Feature",
  "properties": {
    "gn:admin1_code":"09",
    "gn:admin2_code":"2707",
    "gn:asciiname":"Manju",
    "gn:country_code":"AF",
    "gn:dem":3016,
    "gn:feature_class":"P",
    "gn:feature_code":"PPL",
    "gn:name":"Manj\u016b",
    "gn:population":0,
    "gn:timezone":"Asia/Kabul",
    "iso:country":"AF",
    "name:und_x_variant":[
        "Mandzhu",
        "Manju",
        "Manj\u016b",
        "\u0645\u0646\u062c\u0648"
    ],
    "wof:name":"Manju",
    "wof:placetype":"locality"
},
  "geometry": {"coordinates":[66.33056999999999,34.5345],"type":"Point"}
}