{
  "type": "Feature",
  "properties": {
    "gn:admin1_code":"09",
    "gn:admin2_code":"2707",
    "gn:asciiname":"Manju",
    "gn:country_code":"AF",
    "gn:dem":3016,
    "gn:feature_class":"P",
    "gn:feature_code":"PPL",
    "gn:name":"Manj\u016b",
    "gn:population":0,
    "gn:timezone":"Asia/Kabul",
    "iso:country":"AF",
    "name:ceb_x_preferred":[
        "Manju"
    ],
    "name:deu_x_preferred":[
        "Manju"
    ],
    "name:fra_x_preferred":[
        "Manju"
    ],
    "name:kor_x_preferred":[
        "\ub9cc\uc8fc"
    ],
    "name:swe_x_preferred":[
        "Manju"
    ],
    "name:tel_x_preferred":[
        "\u0c2e\u0c02\u0c1c\u0c41"
    ],
    "name:und_x_variant":[
        "Mandzhu",
        "Manj\u016b",
        "\u0645\u0646\u062c\u0648"
    ],
    "wof:name":"Manju",
    "wof:placetype":"locality"
},
  "geometry": {"coordinates":[66.33056999999999,34.5345],"type":"Point"}
}