{
  "type": "Feature",
  "properties": {
    "gn:admin1_code":"9",
    "gn:admin2_code":"2707.0",
    "gn:asciiname":"Besarak-e 'Ulya",
    "gn:country_code":"AF",
    "gn:dem":2968,
    "gn:feature_class":"P",
    "gn:feature_code":"PPL",
    "gn:name":"B\u0113sarak-e \u2018Uly\u0101",
    "gn:population":0,
    "gn:timezone":"Asia/Kabul",
    "iso:country":"AF",
    "name:und_x_variant":[
        "B\u0113sa\u1e5fake \u2019Uly\u0101",
        "Besarakhi-Ulia",
        "Baysarak-e \u2018Oly\u0101",
        "B\u012b Sarak-e \u2018Oly\u0101",
        "B\u0113sarak-e \u2018Uly\u0101",
        "\u0628\u06cc \u0633\u0631\u06a9 \u0639\u0644\u06cc\u0627"
    ],
    "wof:name":"Besarak-e 'Ulya",
    "wof:placetype":"locality"
},
  "geometry": {"coordinates":[66.17348,34.44563],"type":"Point"}
}