{
  "type": "Feature",
  "properties": {
    "gn:admin1_code":"17",
    "gn:admin2_code":"506",
    "gn:asciiname":"Maroat",
    "gn:country_code":"AF",
    "gn:dem":2171,
    "gn:feature_class":"P",
    "gn:feature_code":"PPL",
    "gn:name":"Mar\u014dat",
    "gn:population":0,
    "gn:timezone":"Asia/Kabul",
    "iso:country":"AF",
    "name:und_x_variant":[
        "Ma\u1e5f\u014dat",
        "Maroat",
        "Marwat",
        "Ma\u1e5fowat",
        "Mar\u014dat",
        "\u0645\u0631\u0648\u062a",
        "Mar\u014d\u0101t",
        "\u0645\u0631\u0648\u0627\u062a"
    ],
    "wof:name":"Maroat",
    "wof:placetype":"locality"
},
  "geometry": {"coordinates":[69.71994000000001,34.16892],"type":"Point"}
}