{
  "type": "Feature",
  "properties": {
    "gn:admin1_code":"18",
    "gn:admin2_code":"817.0",
    "gn:asciiname":"Grebawah",
    "gn:country_code":"AF",
    "gn:dem":469,
    "gn:feature_class":"P",
    "gn:feature_code":"PPL",
    "gn:name":"G\u1e5f\u00eab\u0101wah",
    "gn:population":0,
    "gn:timezone":"Asia/Kabul",
    "iso:country":"AF",
    "name:fas_x_preferred":[
        "\u06af\u0631\u064a\u0628\u0627\u0648\u0647"
    ],
    "name:und_x_variant":[
        "Gr\u011bb\u0101wa",
        "Grebava",
        "Grebawah",
        "G\u1e5f\u00eab\u0101wah",
        "\u06af\u0693\u0628\u0627\u0648\u0647",
        "G\u1e5fay B\u0101wah",
        "\u06af\u0693\u06cc \u0628\u0627\u0648\u0647"
    ],
    "wof:name":"Grebawah",
    "wof:placetype":"locality"
},
  "geometry": {"coordinates":[70.83761,34.26598],"type":"Point"}
}