{
  "type": "Feature",
  "properties": {
    "gn:admin1_code":"37",
    "gn:admin2_code":"3202",
    "gn:asciiname":"Moghul Khel",
    "gn:country_code":"AF",
    "gn:dem":1360,
    "gn:feature_class":"P",
    "gn:feature_code":"PPL",
    "gn:name":"Moghul Kh\u0113l",
    "gn:population":0,
    "gn:timezone":"Asia/Kabul",
    "iso:country":"AF",
    "name:rus_x_preferred":[
        "Magul\u2019kheyl\u2019"
    ],
    "name:und_x_variant":[
        "Moghulkh\u0113l",
        "Mogh\u016bl Kh\u0113l",
        "Moghol Kheyl",
        "Moghul Kh\u0113l",
        "\u0645\u063a\u0644 \u062e\u06d0\u0644"
    ],
    "wof:name":"Moghul Khel",
    "wof:placetype":"locality"
},
  "geometry": {"coordinates":[70.12129,33.62294],"type":"Point"}
}