{
  "type": "Feature",
  "properties": {
    "gn:admin1_code":"6",
    "gn:admin2_code":"2109.0",
    "gn:asciiname":"Chak Ab",
    "gn:country_code":"AF",
    "gn:dem":487,
    "gn:feature_class":"P",
    "gn:feature_code":"PPL",
    "gn:name":"Chak \u0100b",
    "gn:population":0,
    "gn:timezone":"Asia/Kabul",
    "iso:country":"AF",
    "name:und_x_variant":[
        "Chak \u0100b",
        "\u0686\u06a9 \u0622\u0628",
        "Chak\u0101b"
    ],
    "wof:name":"Chak Ab",
    "wof:placetype":"locality"
},
  "geometry": {"coordinates":[61.13623000000001,31.49577],"type":"Point"}
}