{
  "type": "Feature",
  "properties": {
    "gn:admin1_code":"01",
    "gn:admin2_code":"1123",
    "gn:asciiname":"Du Awi",
    "gn:country_code":"AF",
    "gn:dem":1700,
    "gn:feature_class":"P",
    "gn:feature_code":"PPL",
    "gn:name":"D\u016b \u0100w\u012b",
    "gn:population":0,
    "gn:timezone":"Asia/Kabul",
    "iso:country":"AF",
    "name:und_x_variant":[
        "\u1e0eoawi",
        "Do\u0101b\u012b",
        "D\u016b \u0100w\u012b",
        "\u062f\u0648 \u0622\u0648\u06cc"
    ],
    "wof:name":"Du Awi",
    "wof:placetype":"locality"
},
  "geometry": {"coordinates":[70.36299,36.55916],"type":"Point"}
}