{
  "type": "Feature",
  "properties": {
    "gn:admin1_code":"02",
    "gn:admin2_code":"1903",
    "gn:asciiname":"Jarahi-ye Pasha'i",
    "gn:country_code":"AF",
    "gn:dem":1074,
    "gn:feature_class":"P",
    "gn:feature_code":"PPL",
    "gn:name":"Jarah\u012b-ye Pasha\u2019\u012b",
    "gn:population":0,
    "gn:timezone":"Asia/Kabul",
    "iso:country":"AF",
    "name:und_x_variant":[
        "Dzharakhiyi-Pashai",
        "Jarahi-i-Pasha\u2019i",
        "Jarahi-i-Pa\u0161a\u2019i",
        "Jar\u0101\u1e29\u012b-ye P\u0101sha\u2019\u012b",
        "Jarah\u012b-ye Pasha\u2019\u012b",
        "\u062c\u0631\u0647\u06cc \u067e\u0634\u0626\u06cc"
    ],
    "wof:name":"Jarahi-ye Pasha'i",
    "wof:placetype":"locality"
},
  "geometry": {"coordinates":[63.30812,34.92229],"type":"Point"}
}