{
  "type": "Feature",
  "properties": {
    "gn:admin1_code":"03",
    "gn:admin2_code":"1307.0",
    "gn:asciiname":"Foj",
    "gn:country_code":"AF",
    "gn:dem":1501,
    "gn:feature_class":"P",
    "gn:feature_code":"PPL",
    "gn:name":"F\u014dj",
    "gn:population":0,
    "gn:timezone":"Asia/Kabul",
    "iso:country":"AF",
    "name:und_x_variant":[
        "F\u014dj",
        "Fowj",
        "\u0641\u0648\u062c"
    ],
    "wof:name":"Foj",
    "wof:placetype":"locality"
},
  "geometry": {"coordinates":[69.15631999999999,35.61568],"type":"Point"}
}