{
  "type": "Feature",
  "properties": {
    "gn:admin1_code":"5",
    "gn:admin2_code":"2805.0",
    "gn:asciiname":"Now Bala",
    "gn:country_code":"AF",
    "gn:dem":2943,
    "gn:feature_class":"P",
    "gn:feature_code":"PPL",
    "gn:name":"Now B\u0101l\u0101",
    "gn:population":0,
    "gn:timezone":"Asia/Kabul",
    "iso:country":"AF",
    "name:und_x_variant":[
        "Naubala",
        "N\u0101w B\u0101l\u0101",
        "Naw B\u0101l\u0101",
        "Now B\u0101l\u0101",
        "\u0646\u0648 \u0628\u0627\u0644\u0627"
    ],
    "wof:name":"Now Bala",
    "wof:placetype":"locality"
},
  "geometry": {"coordinates":[66.80978,34.36566],"type":"Point"}
}