{
  "type": "Feature",
  "properties": {
    "gn:admin1_code":"9",
    "gn:admin2_code":"2705.0",
    "gn:asciiname":"Koyan",
    "gn:country_code":"AF",
    "gn:dem":2437,
    "gn:feature_class":"P",
    "gn:feature_code":"PPL",
    "gn:name":"K\u014dy\u0101n",
    "gn:population":0,
    "gn:timezone":"Asia/Kabul",
    "iso:country":"AF",
    "name:und_x_variant":[
        "K\u014dy\u0101n",
        "\u06a9\u0648\u06cc\u0627\u0646",
        "K\u016by\u0101n"
    ],
    "wof:name":"Koyan",
    "wof:placetype":"locality"
},
  "geometry": {"coordinates":[64.63584,33.57925],"type":"Point"}
}