{
  "type": "Feature",
  "properties": {
    "gn:admin1_code":"26",
    "gn:admin2_code":"1208.0",
    "gn:asciiname":"Langar",
    "gn:country_code":"AF",
    "gn:dem":1696,
    "gn:feature_class":"P",
    "gn:feature_code":"PPL",
    "gn:name":"Langar",
    "gn:population":0,
    "gn:timezone":"Asia/Kabul",
    "iso:country":"AF",
    "name:ceb_x_preferred":[
        "Langar"
    ],
    "name:deu_x_preferred":[
        "Langar"
    ],
    "name:swe_x_preferred":[
        "Langar"
    ],
    "name:und_x_variant":[
        "Langar (2)"
    ],
    "name:urd_x_preferred":[
        "\u0644\u0646\u06af\u0631"
    ],
    "name:uzb_x_preferred":[
        "Langar"
    ],
    "wof:name":"Langar",
    "wof:placetype":"locality"
},
  "geometry": {"coordinates":[69.83246,37.00741],"type":"Point"}
}