{
  "type": "Feature",
  "properties": {
    "gn:admin1_code":"33",
    "gn:admin2_code":"3104",
    "gn:asciiname":"Robah Bayan",
    "gn:country_code":"AF",
    "gn:dem":2376,
    "gn:feature_class":"P",
    "gn:feature_code":"PPL",
    "gn:name":"R\u014db\u0101h Bay\u0101n",
    "gn:population":0,
    "gn:timezone":"Asia/Kabul",
    "iso:country":"AF",
    "name:und_x_variant":[
        "\u1e5e\u014dbabay\u0101n",
        "R\u016b B\u0101b\u0101y\u0101n",
        "R\u014db\u0101h Bay\u0101n",
        "\u0631\u0648\u0628\u0627\u0647 \u0628\u06cc\u0627\u0646"
    ],
    "wof:name":"Robah Bayan",
    "wof:placetype":"locality"
},
  "geometry": {"coordinates":[66.31128000000001,35.40891],"type":"Point"}
}