{
  "type": "Feature",
  "properties": {
    "gn:admin1_code":"26",
    "gn:admin2_code":"1203.0",
    "gn:asciiname":"Dahnah",
    "gn:country_code":"AF",
    "gn:dem":1230,
    "gn:feature_class":"P",
    "gn:feature_code":"PPL",
    "gn:name":"Dahnah",
    "gn:population":0,
    "gn:timezone":"Asia/Kabul",
    "iso:country":"AF",
    "name:und_x_variant":[
        "\u1e0eahna",
        "\u1e0eahana",
        "Dahaneh",
        "Dahnah",
        "\u062f\u0647\u0646\u0647"
    ],
    "wof:name":"Dahnah",
    "wof:placetype":"locality"
},
  "geometry": {"coordinates":[69.54203000000001,36.36372],"type":"Point"}
}