{
  "type": "Feature",
  "properties": {
    "gn:admin1_code":"08",
    "gn:admin2_code":"606",
    "gn:asciiname":"Janah",
    "gn:country_code":"AF",
    "gn:dem":2998,
    "gn:feature_class":"P",
    "gn:feature_code":"PPL",
    "gn:name":"J\u0101nah",
    "gn:population":0,
    "gn:timezone":"Asia/Kabul",
    "iso:country":"AF",
    "name:und_x_variant":[
        "J\u0101nah",
        "J\u0101na",
        "\u062c\u0627\u0646\u0647"
    ],
    "wof:name":"Janah",
    "wof:placetype":"locality"
},
  "geometry": {"coordinates":[66.96554999999999,33.08268],"type":"Point"}
}