{
  "type": "Feature",
  "properties": {
    "gn:admin1_code":"8",
    "gn:admin2_code":"611.0",
    "gn:asciiname":"Zya'uddin Kelay",
    "gn:country_code":"AF",
    "gn:dem":2056,
    "gn:feature_class":"P",
    "gn:feature_code":"PPL",
    "gn:name":"\u1e94y\u0101\u2019udd\u012bn K\u00ealay",
    "gn:population":0,
    "gn:timezone":"Asia/Kabul",
    "iso:country":"AF",
    "name:fas_x_preferred":[
        "\u0642\u0631\u064a\u06c0 \u0636\u064a\u0627\u0621 \u0627\u0644\u062f\u064a\u0646"
    ],
    "name:und_x_variant":[
        "\u1e0e\u1e95y\u0101\u2019u\u1e0f\u1e0f\u012bn Kalay",
        "Ziauddin-Kalay",
        "\u1e94iy\u0101 u\u1e0f D\u012bn K\u00ealay",
        "\u1e94\u012b\u0101\u2019 od D\u012bn Kalay",
        "\u1e94y\u0101\u2019udd\u012bn K\u00ealay",
        "\u0636\u06cc\u0623\u0627\u0644\u062f\u06cc\u0646 \u06a9\u0644\u06cc",
        "\u0642\u0631\u064a\u06c0 \u0636\u064a\u0627\u0621 \u0627\u0644\u062f\u064a\u0646"
    ],
    "wof:name":"Zya'uddin Kelay",
    "wof:placetype":"locality"
},
  "geometry": {"coordinates":[68.04082,33.03799],"type":"Point"}
}