{
  "type": "Feature",
  "properties": {
    "gn:admin1_code":"29",
    "gn:admin2_code":"2909.0",
    "gn:asciiname":"Dim Maney",
    "gn:country_code":"AF",
    "gn:dem":1951,
    "gn:feature_class":"P",
    "gn:feature_code":"PPL",
    "gn:name":"Dim M\u0101n\u00eay",
    "gn:population":0,
    "gn:timezone":"Asia/Kabul",
    "iso:country":"AF",
    "name:und_x_variant":[
        "Dimmanay",
        "Dim M\u0101n\u00eay",
        "Dem M\u0101ney"
    ],
    "wof:name":"Dim Maney",
    "wof:placetype":"locality"
},
  "geometry": {"coordinates":[69.29028000000001,32.78917],"type":"Point"}
}