{
  "type": "Feature",
  "properties": {
    "gn:admin1_code":"28",
    "gn:admin2_code":"2506.0",
    "gn:asciiname":"Tughrat",
    "gn:country_code":"AF",
    "gn:dem":1494,
    "gn:feature_class":"P",
    "gn:feature_code":"PPL",
    "gn:name":"\u0162ughr\u0101t",
    "gn:population":0,
    "gn:timezone":"Asia/Kabul",
    "iso:country":"AF",
    "name:und_x_variant":[
        "Tugrat",
        "\u0637\u063a\u0631\u0627\u062a",
        "Tugh\u1e5f\u0101t",
        "\u0162ughr\u0101t"
    ],
    "wof:name":"Tughrat",
    "wof:placetype":"locality"
},
  "geometry": {"coordinates":[66.65635999999999,31.97745],"type":"Point"}
}