{
  "type": "Feature",
  "properties": {
    "gn:admin1_code":"08",
    "gn:admin2_code":"602",
    "gn:asciiname":"Wutah",
    "gn:country_code":"AF",
    "gn:dem":2604,
    "gn:feature_class":"P",
    "gn:feature_code":"PPL",
    "gn:name":"Wutah",
    "gn:population":0,
    "gn:timezone":"Asia/Kabul",
    "iso:country":"AF",
    "name:fas_x_preferred":[
        "\u0648\u062a\u0647"
    ],
    "name:und_x_variant":[
        "Vuta",
        "Wota",
        "Wotah",
        "Wutah"
    ],
    "wof:name":"Wutah",
    "wof:placetype":"locality"
},
  "geometry": {"coordinates":[68.25329000000001,33.6202],"type":"Point"}
}