{
  "type": "Feature",
  "properties": {
    "gn:admin1_code":"8",
    "gn:admin2_code":"602.0",
    "gn:asciiname":"Ati Mir",
    "gn:country_code":"AF",
    "gn:dem":2850,
    "gn:feature_class":"P",
    "gn:feature_code":"PPL",
    "gn:name":"At\u012b M\u012br",
    "gn:population":0,
    "gn:timezone":"Asia/Kabul",
    "iso:country":"AF",
    "name:fas_x_preferred":[
        "\u0627\u062a\u0645\u064a\u0631"
    ],
    "name:und_x_variant":[
        "Atimir",
        "Atim\u012br",
        "At\u012b M\u012br",
        "\u0627\u062a\u06cc \u0645\u06cc\u0631"
    ],
    "wof:name":"Ati Mir",
    "wof:placetype":"locality"
},
  "geometry": {"coordinates":[68.02696,33.56193],"type":"Point"}
}