{
  "type": "Feature",
  "properties": {
    "gn:admin1_code":"40",
    "gn:asciiname":"Pashghur",
    "gn:country_code":"AF",
    "gn:dem":2247,
    "gn:feature_class":"P",
    "gn:feature_code":"PPL",
    "gn:name":"Pashghur",
    "gn:population":0,
    "gn:timezone":"Asia/Kabul",
    "iso:country":"AF",
    "name:rus_x_preferred":[
        "\u041f\u0438\u0448\u0433\u043e\u0440"
    ],
    "name:und_x_variant":[
        "Pe\u0161ghor",
        "Peshgh\u014dr",
        "Pishgor",
        "Pashghur",
        "Peshghowr"
    ],
    "wof:name":"Pashghur",
    "wof:placetype":"locality"
},
  "geometry": {"coordinates":[69.69,35.39],"type":"Point"}
}