{
  "type": "Feature",
  "properties": {
    "gn:admin1_code":"11",
    "gn:admin2_code":"2012.0",
    "gn:asciiname":"Ab Rayzi",
    "gn:country_code":"AF",
    "gn:dem":1931,
    "gn:feature_class":"P",
    "gn:feature_code":"PPL",
    "gn:name":"\u0100b Rayz\u012b",
    "gn:population":0,
    "gn:timezone":"Asia/Kabul",
    "iso:country":"AF",
    "name:und_x_variant":[
        "Awrezi",
        "Abrezi",
        "\u0100b R\u012bz\u012b",
        "\u0100b Rayz\u012b",
        "\u0622\u0628 \u0631\u06cc\u0632\u06cc",
        "\u0100w Rayz\u012b",
        "\u0622\u0648 \u0631\u06cc\u0632\u06cc"
    ],
    "wof:name":"Ab Rayzi",
    "wof:placetype":"locality"
},
  "geometry": {"coordinates":[63.21506,34.26848],"type":"Point"}
}