{
  "type": "Feature",
  "properties": {
    "gn:admin1_code":"06",
    "gn:admin2_code":"2104",
    "gn:asciiname":"Zirah",
    "gn:country_code":"AF",
    "gn:dem":1707,
    "gn:feature_class":"P",
    "gn:feature_code":"PPL",
    "gn:name":"Z\u012brah",
    "gn:population":0,
    "gn:timezone":"Asia/Kabul",
    "iso:country":"AF",
    "name:und_x_variant":[
        "Zi\u1e5fa",
        "Z\u012brah",
        "\u0632\u06cc\u0631\u0647",
        "Z\u012breh"
    ],
    "wof:name":"Zirah",
    "wof:placetype":"locality"
},
  "geometry": {"coordinates":[63.84777,33.03086],"type":"Point"}
}