{
  "type": "Feature",
  "properties": {
    "gn:admin1_code":"18",
    "gn:admin2_code":"804.0",
    "gn:asciiname":"Wech Algad Khulah",
    "gn:country_code":"AF",
    "gn:dem":1803,
    "gn:feature_class":"P",
    "gn:feature_code":"PPL",
    "gn:name":"W\u00each Alga\u1e0f Kh\u016blah",
    "gn:population":0,
    "gn:timezone":"Asia/Kabul",
    "iso:country":"AF",
    "name:fas_x_preferred":[
        "\u062f\u0647\u0627\u0646\u0654\u0654 \u0634\u064a\u0644\u06c0 \u062e\u0634\u0643"
    ],
    "name:rus_x_preferred":[
        "Vechl\u2019gadkhula"
    ],
    "name:und_x_variant":[
        "We\u010d Lgad Khol\u011bh",
        "Wech Lgad Kholeh",
        "W\u00each Alga\u1e0f Kh\u016blah",
        "\u0648\u0686 \u0644\u06af\u0689 \u062e\u0648\u0644\u0647"
    ],
    "wof:name":"Wech Algad Khulah",
    "wof:placetype":"locality"
},
  "geometry": {"coordinates":[69.94261,34.22482],"type":"Point"}
}