{
  "type": "Feature",
  "properties": {
    "gn:admin1_code":"9",
    "gn:admin2_code":"2707.0",
    "gn:asciiname":"Tinah Qarboghi",
    "gn:country_code":"AF",
    "gn:dem":2819,
    "gn:feature_class":"P",
    "gn:feature_code":"PPL",
    "gn:name":"Tinah Qarb\u014dgh\u012b",
    "gn:population":0,
    "gn:timezone":"Asia/Kabul",
    "iso:country":"AF",
    "name:und_x_variant":[
        "Tena-qa\u1e5fb\u014dghi",
        "Tinakarbogi",
        "Tenah Qarah B\u0101gh\u012b",
        "Teneh Garb\u016bgh\u012b",
        "Tinah Qarb\u014dgh\u012b",
        "\u062a\u0646\u0647 \u0642\u0631\u0628\u0648\u063a\u06cc"
    ],
    "wof:name":"Tinah Qarboghi",
    "wof:placetype":"locality"
},
  "geometry": {"coordinates":[66.26581999999999,34.47175],"type":"Point"}
}