{
  "type": "Feature",
  "properties": {
    "gn:admin1_code":"39",
    "gn:admin2_code":"2603",
    "gn:asciiname":"Toshakan",
    "gn:country_code":"AF",
    "gn:dem":2083,
    "gn:feature_class":"P",
    "gn:feature_code":"PPL",
    "gn:name":"T\u014dshak\u0101n",
    "gn:population":0,
    "gn:timezone":"Asia/Kabul",
    "iso:country":"AF",
    "name:fas_x_preferred":[
        "\u062a\u0648\u0634\u0643\u0646"
    ],
    "name:und_x_variant":[
        "To\u0161akan",
        "Toshakan",
        "T\u014dshak\u0101n",
        "\u062a\u0648\u0634\u06a9\u0627\u0646",
        "Towshakan"
    ],
    "wof:name":"Toshakan",
    "wof:placetype":"locality"
},
  "geometry": {"coordinates":[66.65649999999999,32.92197],"type":"Point"}
}