{
  "type": "Feature",
  "properties": {
    "gn:admin1_code":"29",
    "gn:admin2_code":"2901.0",
    "gn:asciiname":"Chakan",
    "gn:country_code":"AF",
    "gn:dem":2138,
    "gn:feature_class":"P",
    "gn:feature_code":"PPL",
    "gn:name":"Chak\u0101n",
    "gn:population":0,
    "gn:timezone":"Asia/Kabul",
    "iso:country":"AF",
    "name:und_x_variant":[
        "\u010cak\u0101n",
        "Chakan",
        "Chak\u0101n",
        "\u0686\u06a9\u0627\u0646"
    ],
    "wof:name":"Chakan",
    "wof:placetype":"locality"
},
  "geometry": {"coordinates":[68.73489000000001,33.17509],"type":"Point"}
}