{
  "type": "Feature",
  "properties": {
    "gn:admin1_code":"33",
    "gn:admin2_code":"3103",
    "gn:asciiname":"Kham-e Safed",
    "gn:country_code":"AF",
    "gn:dem":2514,
    "gn:feature_class":"P",
    "gn:feature_code":"PPL",
    "gn:name":"Kham-e Saf\u0113d",
    "gn:population":0,
    "gn:timezone":"Asia/Kabul",
    "iso:country":"AF",
    "name:und_x_variant":[
        "Khame Saf\u0113\u1e0f",
        "Kham-e Sef\u012bd",
        "Kham-e Safayd",
        "\u062e\u0645 \u0633\u0641\u06d0\u062f",
        "Kham-e Saf\u0113d"
    ],
    "wof:name":"Kham-e Safed",
    "wof:placetype":"locality"
},
  "geometry": {"coordinates":[65.85558,35.32542],"type":"Point"}
}