{
  "type": "Feature",
  "properties": {
    "gn:admin1_code":"29",
    "gn:admin2_code":"2905",
    "gn:asciiname":"Rodakay",
    "gn:country_code":"AF",
    "gn:dem":1820,
    "gn:feature_class":"P",
    "gn:feature_code":"PPL",
    "gn:name":"R\u014ddakay",
    "gn:population":0,
    "gn:timezone":"Asia/Kabul",
    "iso:country":"AF",
    "name:und_x_variant":[
        "\u1e5e\u014d\u1e0fakay",
        "Rodakay",
        "R\u014ddakay",
        "\u0631\u0648\u062f\u06a9\u06cc"
    ],
    "wof:name":"Rodakay",
    "wof:placetype":"locality"
},
  "geometry": {"coordinates":[68.77722,31.73333],"type":"Point"}
}