{
  "type": "Feature",
  "properties": {
    "gn:admin1_code":"11",
    "gn:admin2_code":"2006.0",
    "gn:asciiname":"Dahan-e Shoraw",
    "gn:country_code":"AF",
    "gn:dem":935,
    "gn:feature_class":"P",
    "gn:feature_code":"PPL",
    "gn:name":"Dah\u0101n-e Sh\u014dr\u0101w",
    "gn:population":0,
    "gn:timezone":"Asia/Kabul",
    "iso:country":"AF",
    "name:und_x_variant":[
        "Dahan-e Sh\u016br\u0101b",
        "Dahan-e Sh\u016braw",
        "Dahan-i-\u0160oraw",
        "Dakhani-Shorav",
        "Dah\u0101n-e Sh\u014dr\u0101w",
        "\u062f\u0647\u0627\u0646 \u0634\u0648\u0631\u0627\u0648",
        "Dahan-e Sh\u016brow"
    ],
    "wof:name":"Dahan-e Shoraw",
    "wof:placetype":"locality"
},
  "geometry": {"coordinates":[62.37396999999999,34.94452],"type":"Point"}
}