{
  "type": "Feature",
  "properties": {
    "gn:admin1_code":"9",
    "gn:admin2_code":"2705.0",
    "gn:asciiname":"Dahan-e Mulla A'la",
    "gn:country_code":"AF",
    "gn:dem":2102,
    "gn:feature_class":"P",
    "gn:feature_code":"PPL",
    "gn:name":"Dah\u0101n-e Mull\u0101 A\u2018l\u0101",
    "gn:population":0,
    "gn:timezone":"Asia/Kabul",
    "iso:country":"AF",
    "name:und_x_variant":[
        "\u1e0eahane Mull\u0101 A\u2018l\u0101",
        "Dakhani-Mullaalla",
        "Dah\u0101n-e Mull\u0101 A\u2018l\u0101",
        "\u062f\u0647\u0627\u0646 \u0645\u0644\u0627 \u0627\u0639\u0644\u0627",
        "Dahan-e Moll\u0101 A\u2018l\u0101"
    ],
    "wof:name":"Dahan-e Mulla A'la",
    "wof:placetype":"locality"
},
  "geometry": {"coordinates":[64.33255,33.50247],"type":"Point"}
}