{
  "type": "Feature",
  "properties": {
    "gn:admin1_code":"34",
    "gn:admin2_code":"1010.0",
    "gn:asciiname":"Pitaw Tantil",
    "gn:country_code":"AF",
    "gn:dem":1560,
    "gn:feature_class":"P",
    "gn:feature_code":"PPL",
    "gn:name":"Pit\u0101w Tant\u012bl",
    "gn:population":0,
    "gn:timezone":"Asia/Kabul",
    "iso:country":"AF",
    "wof:name":"Pitaw Tantil",
    "wof:placetype":"locality"
},
  "geometry": {"coordinates":[70.96995,34.95808],"type":"Point"}
}