{
  "type": "Feature",
  "properties": {
    "gn:admin1_code":"06",
    "gn:admin2_code":"2109",
    "gn:asciiname":"Khayrabad",
    "gn:country_code":"AF",
    "gn:dem":491,
    "gn:feature_class":"P",
    "gn:feature_code":"PPL",
    "gn:name":"Khayr\u0101b\u0101d",
    "gn:population":0,
    "gn:timezone":"Asia/Kabul",
    "iso:country":"AF",
    "name:fas_x_preferred":[
        "\u062e\u06cc\u0631\u0622\u0628\u0627\u062f"
    ],
    "name:msa_x_preferred":[
        "Khayrabad"
    ],
    "name:und_x_variant":[
        "Khair\u0101b\u0101d",
        "Khay\u1e5f\u0101b\u0101\u1e0f",
        "Khayr\u0101b\u0101d",
        "\u062e\u06cc\u0631\u0622\u0628\u0627\u062f",
        "Kheyr\u0101b\u0101d"
    ],
    "wof:name":"Khayrabad",
    "wof:placetype":"locality"
},
  "geometry": {"coordinates":[61.51507,31.57116],"type":"Point"}
}