{
  "type": "Feature",
  "properties": {
    "gn:admin1_code":"41",
    "gn:admin2_code":"3403",
    "gn:asciiname":"Sepi Sang",
    "gn:country_code":"AF",
    "gn:dem":2605,
    "gn:feature_class":"P",
    "gn:feature_code":"PPL",
    "gn:name":"S\u00eap\u012b Sang",
    "gn:population":0,
    "gn:timezone":"Asia/Kabul",
    "iso:country":"AF",
    "name:und_x_variant":[
        "Sepisang",
        "S\u011bpisang",
        "Sp\u012b Sang",
        "Sep\u012bsang",
        "S\u00eap\u012b Sang",
        "\u0633\u067e\u06cc \u0633\u0646\u06af"
    ],
    "wof:name":"Sepi Sang",
    "wof:placetype":"locality"
},
  "geometry": {"coordinates":[66.497,34.03734],"type":"Point"}
}