{
  "type": "Feature",
  "properties": {
    "gn:admin1_code":"40",
    "gn:admin2_code":"305.0",
    "gn:asciiname":"Chunar",
    "gn:country_code":"AF",
    "gn:dem":2783,
    "gn:feature_class":"P",
    "gn:feature_code":"PPL",
    "gn:name":"Chun\u0101r",
    "gn:population":0,
    "gn:timezone":"Asia/Kabul",
    "iso:country":"AF",
    "name:und_x_variant":[
        "\u010con\u0101r",
        "Chen\u0101r",
        "Chon\u0101r",
        "Chun\u0101r",
        "\u0686\u0646\u0627\u0631"
    ],
    "wof:name":"Chunar",
    "wof:placetype":"locality"
},
  "geometry": {"coordinates":[68.8334,34.86629],"type":"Point"}
}