{
  "type": "Feature",
  "properties": {
    "gn:admin1_code":"40",
    "gn:admin2_code":"305.0",
    "gn:asciiname":"Chunar",
    "gn:country_code":"AF",
    "gn:dem":2783,
    "gn:feature_class":"P",
    "gn:feature_code":"PPL",
    "gn:name":"Chun\u0101r",
    "gn:population":0,
    "gn:timezone":"Asia/Kabul",
    "iso:country":"AF",
    "name:ara_x_preferred":[
        "\u062a\u0634\u0648\u0646\u0627\u0631"
    ],
    "name:ben_x_preferred":[
        "\u099a\u09c1\u09a8\u09be\u09b0"
    ],
    "name:bih_x_preferred":[
        "\u091a\u0941\u0928\u093e\u0930"
    ],
    "name:bpy_x_preferred":[
        "\u099a\u09c1\u09a8\u09be\u09b0"
    ],
    "name:cat_x_preferred":[
        "Chunar"
    ],
    "name:ceb_x_preferred":[
        "Chun\u0101r"
    ],
    "name:hin_x_preferred":[
        "\u091a\u0941\u0928\u093e\u0930"
    ],
    "name:ita_x_preferred":[
        "Chunar"
    ],
    "name:jpn_x_preferred":[
        "\u30c1\u30e5\u30ca\u30fc\u30eb"
    ],
    "name:mlg_x_preferred":[
        "Chunar"
    ],
    "name:msa_x_preferred":[
        "Chunar"
    ],
    "name:nep_x_preferred":[
        "\u091a\u0941\u0928\u093e\u0930"
    ],
    "name:new_x_preferred":[
        "\u091a\u0941\u0928\u093e\u0930"
    ],
    "name:nld_x_preferred":[
        "Chunar"
    ],
    "name:pol_x_preferred":[
        "Chunar"
    ],
    "name:swe_x_preferred":[
        "Chun\u0101r"
    ],
    "name:und_x_variant":[
        "\u010con\u0101r",
        "Chen\u0101r",
        "Chon\u0101r"
    ],
    "name:urd_x_preferred":[
        "\u0686\u0646\u0627\u0631"
    ],
    "name:vie_x_preferred":[
        "Chunar"
    ],
    "name:zho_x_preferred":[
        "\u4e18\u7eb3\u5c14"
    ],
    "wof:name":"Chunar",
    "wof:placetype":"locality"
},
  "geometry": {"coordinates":[68.8334,34.86629],"type":"Point"}
}