{
  "type": "Feature",
  "properties": {
    "gn:admin1_code":"23",
    "gn:admin2_code":"2413",
    "gn:asciiname":"Wech Obay Kelay",
    "gn:country_code":"AF",
    "gn:dem":2044,
    "gn:feature_class":"P",
    "gn:feature_code":"PPL",
    "gn:name":"W\u00each \u014cbay K\u00ealay",
    "gn:population":0,
    "gn:timezone":"Asia/Kabul",
    "iso:country":"AF",
    "name:und_x_variant":[
        "Vechbaykalay",
        "W\u0113c \u014cbay Kalay",
        "Wech Owbay Kalay",
        "W\u00each \u014cb\u0113 K\u00ealay",
        "W\u00each \u014cbay K\u00ealay",
        "\u0648\u0686 \u0627\u0648\u0628\u06cc \u06a9\u0644\u06cc"
    ],
    "wof:name":"Wech Obay Kelay",
    "wof:placetype":"locality"
},
  "geometry": {"coordinates":[67.58851,31.46609],"type":"Point"}
}