{
  "type": "Feature",
  "properties": {
    "gn:admin1_code":"35",
    "gn:admin2_code":"902",
    "gn:asciiname":"Mindrawur",
    "gn:country_code":"AF",
    "gn:dem":658,
    "gn:feature_class":"P",
    "gn:feature_code":"PPL",
    "gn:name":"Mindrawu\u1e5f",
    "gn:population":0,
    "gn:timezone":"Asia/Kabul",
    "iso:country":"AF",
    "name:und_x_variant":[
        "Mandrawar",
        "Mindravur",
        "Mandr\u0101var",
        "Men\u1e0f\u1e5fawur",
        "Mandrawal",
        "Mendrawol",
        "Mindrawu\u1e5f",
        "\u0645\u0646\u062f\u0631\u0648\u0693"
    ],
    "wof:name":"Mindrawur",
    "wof:placetype":"locality"
},
  "geometry": {"coordinates":[70.21536999999999,34.54848],"type":"Point"}
}