{
  "type": "Feature",
  "properties": {
    "gn:admin1_code":"08",
    "gn:admin2_code":"613",
    "gn:asciiname":"Robah",
    "gn:country_code":"AF",
    "gn:dem":2118,
    "gn:feature_class":"P",
    "gn:feature_code":"PPL",
    "gn:name":"R\u014db\u0101h",
    "gn:population":0,
    "gn:timezone":"Asia/Kabul",
    "iso:country":"AF",
    "name:und_x_variant":[
        "Roba",
        "\u1e5e\u014dbah",
        "R\u014dbah",
        "R\u016bb\u0101h",
        "R\u014db\u0101h",
        "\u0631\u0648\u0628\u0627\u0647"
    ],
    "wof:name":"Robah",
    "wof:placetype":"locality"
},
  "geometry": {"coordinates":[68.03919,33.08539],"type":"Point"}
}