{
  "type": "Feature",
  "properties": {
    "gn:admin1_code":"42",
    "gn:admin2_code":"3302",
    "gn:asciiname":"Sang-e Khan",
    "gn:country_code":"AF",
    "gn:dem":2684,
    "gn:feature_class":"P",
    "gn:feature_code":"PPL",
    "gn:name":"Sang-e Kh\u0101n",
    "gn:population":0,
    "gn:timezone":"Asia/Kabul",
    "iso:country":"AF",
    "name:fas_x_preferred":[
        "\u0633\u0646\u06af\u0654 \u062e\u0627\u0646"
    ],
    "name:rus_x_preferred":[
        "\u0421\u0430\u043d\u0433\u0438-\u0425\u0430\u043d"
    ],
    "name:und_x_variant":[
        "Sanga Khan",
        "Sangi-Khan",
        "Sang-e Kh\u0101n",
        "\u0633\u0646\u06af \u062e\u0627\u0646"
    ],
    "wof:name":"Sang-e Khan",
    "wof:placetype":"locality"
},
  "geometry": {"coordinates":[69.79545999999999,35.24905],"type":"Point"}
}