{
  "type": "Feature",
  "properties": {
    "gn:admin1_code":"08",
    "gn:admin2_code":"610",
    "gn:asciiname":"Sabagay",
    "gn:country_code":"AF",
    "gn:dem":2291,
    "gn:feature_class":"P",
    "gn:feature_code":"PPL",
    "gn:name":"Sab\u0101gay",
    "gn:population":0,
    "gn:timezone":"Asia/Kabul",
    "iso:country":"AF",
    "name:und_x_variant":[
        "Sab\u0101gay",
        "\u0633\u0628\u0627\u06af\u06cc"
    ],
    "wof:name":"Sabagay",
    "wof:placetype":"locality"
},
  "geometry": {"coordinates":[67.94141999999999,32.11928],"type":"Point"}
}