{
  "type": "Feature",
  "properties": {
    "gn:admin1_code":"32",
    "gn:admin2_code":"1503.0",
    "gn:asciiname":"'Ali Miran",
    "gn:country_code":"AF",
    "gn:dem":2222,
    "gn:feature_class":"P",
    "gn:feature_code":"PPL",
    "gn:name":"\u2018Al\u012b M\u012br\u0101n",
    "gn:population":0,
    "gn:timezone":"Asia/Kabul",
    "iso:country":"AF",
    "name:und_x_variant":[
        "\u2018Al\u012b M\u012br\u0101n",
        "\u0639\u0644\u06cc \u0645\u06cc\u0631\u0627\u0646",
        "\u2018Alim\u012b\u1e5f\u0101n"
    ],
    "wof:name":"'Ali Miran",
    "wof:placetype":"locality"
},
  "geometry": {"coordinates":[67.14279000000001,35.79790999999999],"type":"Point"}
}