{
  "type": "Feature",
  "properties": {
    "gn:admin1_code":"09",
    "gn:admin2_code":"2705",
    "gn:asciiname":"Pirak Kushtah",
    "gn:country_code":"AF",
    "gn:dem":2535,
    "gn:feature_class":"P",
    "gn:feature_code":"PPL",
    "gn:name":"P\u012brak K\u016bshtah",
    "gn:population":0,
    "gn:timezone":"Asia/Kabul",
    "iso:country":"AF",
    "name:und_x_variant":[
        "Pirakkushta",
        "Pirakku\u0161ta",
        "P\u012brak K\u016bshtah",
        "\u067e\u06cc\u0631\u06a9 \u06a9\u0648\u0634\u062a\u0647",
        "P\u012brakkoshteh"
    ],
    "wof:name":"Pirak Kushtah",
    "wof:placetype":"locality"
},
  "geometry": {"coordinates":[64.53579000000001,33.67473],"type":"Point"}
}