{
  "type": "Feature",
  "properties": {
    "gn:admin1_code":"09",
    "gn:admin2_code":"2707",
    "gn:asciiname":"Safed Bayd-e 'Ulya",
    "gn:country_code":"AF",
    "gn:dem":2945,
    "gn:feature_class":"P",
    "gn:feature_code":"PPL",
    "gn:name":"Saf\u0113d Bayd-e \u2018Uly\u0101",
    "gn:population":0,
    "gn:timezone":"Asia/Kabul",
    "iso:country":"AF",
    "name:und_x_variant":[
        "Saf\u0113\u1e0fb\u0113\u1e0fe \u2018Uly\u0101",
        "Safedbedi-Ulia",
        "Sef\u012bdb\u012bd-e \u2018Oly\u0101",
        "Safayd Bayd-e \u2018Oly\u0101",
        "Saf\u0113d Bayd-e \u2018Uly\u0101",
        "\u0633\u0641\u064a\u062f \u0628\u064a\u062f \u0639\u0644\u064a\u0627"
    ],
    "wof:name":"Safed Bayd-e 'Ulya",
    "wof:placetype":"locality"
},
  "geometry": {"coordinates":[66.47284999999999,34.31973],"type":"Point"}
}