{
  "type": "Feature",
  "properties": {
    "gn:admin1_code":"41",
    "gn:admin2_code":"3405",
    "gn:asciiname":"Marqul",
    "gn:country_code":"AF",
    "gn:dem":2584,
    "gn:feature_class":"P",
    "gn:feature_code":"PPL",
    "gn:name":"M\u0101rqul",
    "gn:population":0,
    "gn:timezone":"Asia/Kabul",
    "iso:country":"AF",
    "name:und_x_variant":[
        "M\u0101\u1e0fqul",
        "M\u0101rqul",
        "\u0645\u0627\u0631\u0642\u0644"
    ],
    "wof:name":"Marqul",
    "wof:placetype":"locality"
},
  "geometry": {"coordinates":[65.82541999999999,33.82941],"type":"Point"}
}