{
  "type": "Feature",
  "properties": {
    "gn:admin1_code":"18",
    "gn:admin2_code":"822.0",
    "gn:asciiname":"Surubi",
    "gn:country_code":"AF",
    "gn:dem":1267,
    "gn:feature_class":"P",
    "gn:feature_code":"PPL",
    "gn:name":"Sur\u016bb\u012b",
    "gn:population":0,
    "gn:timezone":"Asia/Kabul",
    "iso:country":"AF",
    "name:und_x_variant":[
        "Sor\u016bbi",
        "Sor\u016bb\u012b",
        "Sur\u016bb\u012b",
        "\u0633\u0631\u0648\u0628\u06cc"
    ],
    "wof:name":"Surubi",
    "wof:placetype":"locality"
},
  "geometry": {"coordinates":[70.55364,34.09014000000001],"type":"Point"}
}