{
  "type": "Feature",
  "properties": {
    "gn:admin1_code":"3",
    "gn:admin2_code":"1308.0",
    "gn:asciiname":"Dahanah",
    "gn:country_code":"AF",
    "gn:dem":1776,
    "gn:feature_class":"P",
    "gn:feature_code":"PPL",
    "gn:name":"Dah\u0101nah",
    "gn:population":0,
    "gn:timezone":"Asia/Kabul",
    "iso:country":"AF",
    "name:und_x_variant":[
        "Dahana",
        "Dahaneh",
        "Dah\u0101nah",
        "\u062f\u0647\u0627\u0646\u0647"
    ],
    "wof:name":"Dahanah",
    "wof:placetype":"locality"
},
  "geometry": {"coordinates":[69.50870999999999,35.90172000000001],"type":"Point"}
}