{
  "type": "Feature",
  "properties": {
    "gn:admin1_code":"23",
    "gn:admin2_code":"2407.0",
    "gn:asciiname":"Agha Khelo Kelay",
    "gn:country_code":"AF",
    "gn:dem":841,
    "gn:feature_class":"P",
    "gn:feature_code":"PPL",
    "gn:name":"\u0100gh\u0101 Kh\u0113l\u014d K\u00ealay",
    "gn:population":0,
    "gn:timezone":"Asia/Kabul",
    "iso:country":"AF",
    "name:und_x_variant":[
        "Agakheylu-Kalay",
        "\u0100gh\u0101kh\u0113lo Kalay",
        "\u0100gh\u0101 Kh\u0113l\u014d K\u00ealay",
        "\u0622\u063a\u0627 \u062e\u06d0\u0644\u0648 \u06a9\u0644\u06cc",
        "\u0100gh\u0101kheyl Kalay"
    ],
    "wof:name":"Agha Khelo Kelay",
    "wof:placetype":"locality"
},
  "geometry": {"coordinates":[64.85242,31.57672],"type":"Point"}
}