{
  "type": "Feature",
  "properties": {
    "gn:admin1_code":"31",
    "gn:admin2_code":"1709",
    "gn:asciiname":"Qarah Tappeh",
    "gn:cc2":"AF",
    "gn:country_code":"AF",
    "gn:dem":262,
    "gn:feature_class":"P",
    "gn:feature_code":"PPL",
    "gn:name":"Qarah Tappeh",
    "gn:population":0,
    "gn:timezone":"Asia/Kabul",
    "iso:country":"AF",
    "name:und_x_variant":[
        "Kolodets Kara-tepe-Kelan",
        "Qara Tapa Kal\u0101n",
        "Qara Tepe K\u0101lan",
        "Kolodets Qara-tepe-Kalan",
        "Qara Tepa",
        "Qarah Tappeh"
    ],
    "wof:name":"Qarah Tappeh",
    "wof:placetype":"locality"
},
  "geometry": {"coordinates":[65.64055999999999,37.2475],"type":"Point"}
}