{
  "type": "Feature",
  "properties": {
    "gn:admin1_code":"41",
    "gn:admin2_code":"3403.0",
    "gn:asciiname":"Ushturow",
    "gn:country_code":"AF",
    "gn:dem":2773,
    "gn:feature_class":"P",
    "gn:feature_code":"PPL",
    "gn:name":"Ushturow",
    "gn:population":0,
    "gn:timezone":"Asia/Kabul",
    "iso:country":"AF",
    "name:und_x_variant":[
        "Ustu\u1e5f\u1e5faw",
        "Ushturow",
        "\u0627\u0634\u062a\u0631\u0648",
        "Oshtor\u1e5faw"
    ],
    "wof:name":"Ushturow",
    "wof:placetype":"locality"
},
  "geometry": {"coordinates":[66.13035000000001,33.95666],"type":"Point"}
}