{
  "type": "Feature",
  "properties": {
    "gn:admin1_code":"05",
    "gn:admin2_code":"2806",
    "gn:asciiname":"Qol-e Piri",
    "gn:country_code":"AF",
    "gn:dem":2933,
    "gn:feature_class":"P",
    "gn:feature_code":"PPL",
    "gn:name":"Q\u014dl-e P\u012br\u012b",
    "gn:population":0,
    "gn:timezone":"Asia/Kabul",
    "iso:country":"AF",
    "name:und_x_variant":[
        "Kuli-Piri",
        "Q\u014dle Pi\u1e5fi",
        "Q\u014dl-e P\u012br\u012b",
        "Qowl-e P\u012br\u012b",
        "\u0642\u0648\u0644 \u067e\u06cc\u0631\u06cc"
    ],
    "wof:name":"Qol-e Piri",
    "wof:placetype":"locality"
},
  "geometry": {"coordinates":[66.76585,34.11215],"type":"Point"}
}