{
  "type": "Feature",
  "properties": {
    "gn:admin1_code":"9",
    "gn:admin2_code":"2709.0",
    "gn:asciiname":"Dahan-e Tilak",
    "gn:country_code":"AF",
    "gn:dem":2504,
    "gn:feature_class":"P",
    "gn:feature_code":"PPL",
    "gn:name":"Dahan-e T\u012blak",
    "gn:population":0,
    "gn:timezone":"Asia/Kabul",
    "iso:country":"AF",
    "name:und_x_variant":[
        "Dahan-e T\u012blak",
        "\u062f\u0647\u0646 \u062a\u06cc\u0644\u06a9"
    ],
    "wof:name":"Dahan-e Tilak",
    "wof:placetype":"locality"
},
  "geometry": {"coordinates":[65.82158000000001,34.60268],"type":"Point"}
}