{
  "type": "Feature",
  "properties": {
    "gn:admin1_code":"26",
    "gn:admin2_code":"1209.0",
    "gn:asciiname":"Chashmah-ye Gul",
    "gn:country_code":"AF",
    "gn:dem":1923,
    "gn:feature_class":"P",
    "gn:feature_code":"PPL",
    "gn:name":"Chashmah-ye Gul",
    "gn:population":0,
    "gn:timezone":"Asia/Kabul",
    "iso:country":"AF",
    "name:und_x_variant":[
        "\u010ca\u0161ma-i-Gul",
        "Cheshmeh-ye Gol",
        "Chashmah-ye Gul",
        "\u0686\u0634\u0645\u06c0 \u06af\u0644"
    ],
    "wof:name":"Chashmah-ye Gul",
    "wof:placetype":"locality"
},
  "geometry": {"coordinates":[69.94436999999999,37.46438],"type":"Point"}
}