{
  "type": "Feature",
  "properties": {
    "gn:admin1_code":"18",
    "gn:admin2_code":"806",
    "gn:asciiname":"Dzolozai",
    "gn:country_code":"AF",
    "gn:dem":828,
    "gn:feature_class":"P",
    "gn:feature_code":"PPL",
    "gn:name":"Dz\u014dl\u014dza\u012b",
    "gn:population":0,
    "gn:timezone":"Asia/Kabul",
    "iso:country":"AF",
    "name:fas_x_preferred":[
        "\u062c\u0648\u0644\u0648\u0632\u06cc"
    ],
    "name:und_x_variant":[
        "Dzholozi",
        "J\u014dl\u014dzi",
        "Jowlowzi",
        "Dz\u014dl\u014dza\u012b",
        "\u0681\u0648\u0644\u0648\u0632\u06cc"
    ],
    "wof:name":"Dzolozai",
    "wof:placetype":"locality"
},
  "geometry": {"coordinates":[70.35110999999999,34.3275],"type":"Point"}
}