{
  "type": "Feature",
  "properties": {
    "gn:admin1_code":"8",
    "gn:admin2_code":"607.0",
    "gn:asciiname":"Babul",
    "gn:country_code":"AF",
    "gn:dem":2563,
    "gn:feature_class":"P",
    "gn:feature_code":"PPL",
    "gn:name":"B\u0101bul",
    "gn:population":0,
    "gn:timezone":"Asia/Kabul",
    "iso:country":"AF",
    "name:und_x_variant":[
        "B\u0101bul",
        "\u0628\u0627\u0628\u0644"
    ],
    "wof:name":"Babul",
    "wof:placetype":"locality"
},
  "geometry": {"coordinates":[67.53106,32.99588],"type":"Point"}
}