{
  "type": "Feature",
  "properties": {
    "gn:admin1_code":"35",
    "gn:admin2_code":"905",
    "gn:asciiname":"Qandalah",
    "gn:country_code":"AF",
    "gn:dem":1958,
    "gn:feature_class":"P",
    "gn:feature_code":"PPL",
    "gn:name":"Qandalah",
    "gn:population":0,
    "gn:timezone":"Asia/Kabul",
    "iso:country":"AF",
    "name:und_x_variant":[
        "Kandala",
        "Qan\u1e0fala",
        "Qan\u1e0falah",
        "\u0642\u0646\u062f\u0644\u0647",
        "Qandalah"
    ],
    "wof:name":"Qandalah",
    "wof:placetype":"locality"
},
  "geometry": {"coordinates":[69.9691,34.83277],"type":"Point"}
}