{
  "type": "Feature",
  "properties": {
    "gn:admin1_code":"28",
    "gn:admin2_code":"2503.0",
    "gn:asciiname":"Deh Mazang",
    "gn:country_code":"AF",
    "gn:dem":1573,
    "gn:feature_class":"P",
    "gn:feature_code":"PPL",
    "gn:name":"Deh Mazang",
    "gn:population":0,
    "gn:timezone":"Asia/Kabul",
    "iso:country":"AF",
    "name:und_x_variant":[
        "Dekhmazang",
        "Deh Mazang",
        "\u062f\u0647 \u0645\u0632\u0646\u06af"
    ],
    "wof:name":"Deh Mazang",
    "wof:placetype":"locality"
},
  "geometry": {"coordinates":[66.8481,32.4214],"type":"Point"}
}