{
  "type": "Feature",
  "properties": {
    "gn:admin1_code":"10",
    "gn:admin2_code":"2306",
    "gn:asciiname":"Warlez",
    "gn:country_code":"AF",
    "gn:dem":1820,
    "gn:feature_class":"P",
    "gn:feature_code":"PPL",
    "gn:name":"Warl\u0113z",
    "gn:population":0,
    "gn:timezone":"Asia/Kabul",
    "iso:country":"AF",
    "name:und_x_variant":[
        "Varlez",
        "Warl\u0113z",
        "\u0648\u0631\u0644\u06d0\u0632"
    ],
    "wof:name":"Warlez",
    "wof:placetype":"locality"
},
  "geometry": {"coordinates":[64.5904,32.86049000000001],"type":"Point"}
}