{
  "type": "Feature",
  "properties": {
    "gn:admin1_code":"23",
    "gn:admin2_code":"2408",
    "gn:asciiname":"Haji 'Ata Muhammad Khan",
    "gn:country_code":"AF",
    "gn:dem":918,
    "gn:feature_class":"P",
    "gn:feature_code":"PPL",
    "gn:name":"\u1e28\u0101j\u012b \u2018A\u0163\u0101 Mu\u1e29ammad Kh\u0101n",
    "gn:population":0,
    "gn:timezone":"Asia/Kabul",
    "iso:country":"AF",
    "name:und_x_variant":[
        "H\u0101ji-\u2018at\u0101mo\u1e29\u1e0f-Kh\u0101n",
        "Khadzhiata-Mukhammedkhan",
        "H\u0101ji-\u2018at\u0101mo\u1e29amme\u1e0f-kh\u0101n",
        "\u1e28\u0101j\u012b \u2018A\u0163\u0101 Mu\u1e29ammad Kh\u0101n",
        "\u062d\u0627\u062c\u06cc \u0639\u0637\u0627 \u0645\u062d\u0645\u062f \u062e\u0627\u0646",
        "\u1e28\u0101jj\u012b \u2018A\u0163\u0101mo\u1e29ammad Kh\u0101n"
    ],
    "wof:name":"Haji 'Ata Muhammad Khan",
    "wof:placetype":"locality"
},
  "geometry": {"coordinates":[65.35250000000001,31.48476],"type":"Point"}
}