{
  "type": "Feature",
  "properties": {
    "gn:admin1_code":"8",
    "gn:admin2_code":"618.0",
    "gn:asciiname":"'Omar Wal",
    "gn:country_code":"AF",
    "gn:dem":2378,
    "gn:feature_class":"P",
    "gn:feature_code":"PPL",
    "gn:name":"\u2018Omar W\u0101l",
    "gn:population":0,
    "gn:timezone":"Asia/Kabul",
    "iso:country":"AF",
    "name:fas_x_preferred":[
        "\u0639\u0645\u0631\u0648\u0627\u0644"
    ],
    "name:rus_x_preferred":[
        "Umarval\u2019"
    ],
    "name:und_x_variant":[
        "\u2018Oma\u1e5fw\u0101l",
        "\u2018Omar W\u0101l",
        "\u2018Omarv\u0101l"
    ],
    "wof:name":"'Omar Wal",
    "wof:placetype":"locality"
},
  "geometry": {"coordinates":[68.20965,33.43677],"type":"Point"}
}