{
  "type": "Feature",
  "properties": {
    "gn:admin1_code":"29",
    "gn:admin2_code":"2904.0",
    "gn:asciiname":"Chatrey",
    "gn:country_code":"AF",
    "gn:dem":2250,
    "gn:feature_class":"P",
    "gn:feature_code":"PPL",
    "gn:name":"Chatr\u00eay",
    "gn:population":0,
    "gn:timezone":"Asia/Kabul",
    "iso:country":"AF",
    "name:und_x_variant":[
        "Catr\u0113y",
        "Chatray",
        "\u0686\u062a\u0631\u06cd",
        "Chatr\u0113y",
        "Chatr\u00eay"
    ],
    "wof:name":"Chatrey",
    "wof:placetype":"locality"
},
  "geometry": {"coordinates":[68.27428,32.12674000000001],"type":"Point"}
}