{
  "type": "Feature",
  "properties": {
    "gn:admin1_code":"27",
    "gn:admin2_code":"404.0",
    "gn:asciiname":"Bangarow",
    "gn:country_code":"AF",
    "gn:dem":2979,
    "gn:feature_class":"P",
    "gn:feature_code":"PPL",
    "gn:name":"Bangarow",
    "gn:population":0,
    "gn:timezone":"Asia/Kabul",
    "iso:country":"AF",
    "name:und_x_variant":[
        "Banga\u1e5faw",
        "Bangarau",
        "B\u0101ngah Row",
        "B\u0101ngehraw",
        "Bangarow",
        "\u0628\u0646\u06af\u0631\u0648"
    ],
    "wof:name":"Bangarow",
    "wof:placetype":"locality"
},
  "geometry": {"coordinates":[67.95918,34.30516],"type":"Point"}
}