{
  "type": "Feature",
  "properties": {
    "gn:admin1_code":"28",
    "gn:admin2_code":"2504",
    "gn:asciiname":"Kamal Khan",
    "gn:country_code":"AF",
    "gn:dem":1556,
    "gn:feature_class":"P",
    "gn:feature_code":"PPL",
    "gn:name":"Kam\u0101l Kh\u0101n",
    "gn:population":0,
    "gn:timezone":"Asia/Kabul",
    "iso:country":"AF",
    "name:rus_x_preferred":[
        "Kamal\u2019khan"
    ],
    "name:und_x_variant":[
        "Kam\u0101l Kh\u0101n",
        "\u06a9\u0645\u0627\u0644 \u062e\u0627\u0646"
    ],
    "wof:name":"Kamal Khan",
    "wof:placetype":"locality"
},
  "geometry": {"coordinates":[66.66889,32.41896],"type":"Point"}
}