{
  "type": "Feature",
  "properties": {
    "gn:admin1_code":"03",
    "gn:admin2_code":"1304",
    "gn:asciiname":"Mingak",
    "gn:country_code":"AF",
    "gn:dem":1121,
    "gn:feature_class":"P",
    "gn:feature_code":"PPL",
    "gn:name":"Mingak",
    "gn:population":0,
    "gn:timezone":"Asia/Kabul",
    "iso:country":"AF",
    "name:und_x_variant":[
        "Mengak",
        "Mingak",
        "\u0645\u0646\u06af\u06a9"
    ],
    "wof:name":"Mingak",
    "wof:placetype":"locality"
},
  "geometry": {"coordinates":[68.85834,35.76407000000001],"type":"Point"}
}