{
  "type": "Feature",
  "properties": {
    "gn:admin1_code":"11",
    "gn:admin2_code":"2012.0",
    "gn:asciiname":"Dahan-e Du Ab",
    "gn:country_code":"AF",
    "gn:dem":1192,
    "gn:feature_class":"P",
    "gn:feature_code":"PPL",
    "gn:name":"Dah\u0101n-e D\u016b \u0100b",
    "gn:population":0,
    "gn:timezone":"Asia/Kabul",
    "iso:country":"AF",
    "name:und_x_variant":[
        "\u1e0eahan-i-\u1e0eu\u0101b",
        "Dakhani-Doab",
        "Dahan-e Do\u0101b",
        "Dah\u0101n-e D\u016b \u0100b",
        "\u062f\u0647\u0627\u0646 \u062f\u0648 \u0622\u0628"
    ],
    "wof:name":"Dahan-e Du Ab",
    "wof:placetype":"locality"
},
  "geometry": {"coordinates":[62.96931,34.26031],"type":"Point"}
}