{
  "type": "Feature",
  "properties": {
    "gn:admin1_code":"40",
    "gn:admin2_code":"307.0",
    "gn:asciiname":"Tay-e Howli",
    "gn:country_code":"AF",
    "gn:dem":2885,
    "gn:feature_class":"P",
    "gn:feature_code":"PPL",
    "gn:name":"Tay-e Howl\u012b",
    "gn:population":0,
    "gn:timezone":"Asia/Kabul",
    "iso:country":"AF",
    "name:und_x_variant":[
        "Tayi-Khauli",
        "Tey-e Hawl\u012b",
        "Tay-e Howl\u012b",
        "\u062a\u06cc \u0647\u0648\u0644\u06cc"
    ],
    "wof:name":"Tay-e Howli",
    "wof:placetype":"locality"
},
  "geometry": {"coordinates":[68.38583,34.76492],"type":"Point"}
}