{
  "type": "Feature",
  "properties": {
    "gn:admin1_code":"24",
    "gn:admin2_code":"1401",
    "gn:asciiname":"'Omar Khel",
    "gn:country_code":"AF",
    "gn:dem":377,
    "gn:feature_class":"P",
    "gn:feature_code":"PPL",
    "gn:name":"\u2018Omar Kh\u0113l",
    "gn:population":0,
    "gn:timezone":"Asia/Kabul",
    "iso:country":"AF",
    "name:fas_x_preferred":[
        "\u0639\u0645\u0631 \u062e\u064a\u0644"
    ],
    "name:rus_x_preferred":[
        "\u0423\u043c\u0430\u0440\u0445\u0435\u0439\u043b\u044c"
    ],
    "name:und_x_variant":[
        "\u2018Omar Kh\u0113l",
        "Umarkheyl\u2019",
        "\u2018Omar Kheyl",
        "\u0639\u0645\u0631 \u062e\u06d0\u0644"
    ],
    "wof:name":"'Omar Khel",
    "wof:placetype":"locality"
},
  "geometry": {"coordinates":[68.76172,36.77718],"type":"Point"}
}