{
  "type": "Feature",
  "properties": {
    "gn:admin1_code":"28",
    "gn:admin2_code":"2504",
    "gn:asciiname":"Mariani",
    "gn:country_code":"AF",
    "gn:dem":1532,
    "gn:feature_class":"P",
    "gn:feature_code":"PPL",
    "gn:name":"Mariani",
    "gn:population":0,
    "gn:timezone":"Asia/Kabul",
    "iso:country":"AF",
    "name:cat_x_preferred":[
        "Mariani"
    ],
    "name:deu_x_preferred":[
        "Mariani"
    ],
    "name:fra_x_preferred":[
        "Mariani"
    ],
    "name:ita_x_preferred":[
        "Mariani"
    ],
    "name:msa_x_preferred":[
        "Mariani"
    ],
    "name:nld_x_preferred":[
        "Mariani"
    ],
    "name:rus_x_preferred":[
        "\u041c\u0430\u0440\u0438\u0430\u043d\u0438"
    ],
    "name:spa_x_preferred":[
        "Mariani"
    ],
    "name:ukr_x_preferred":[
        "\u041c\u0430\u0440\u0456\u0430\u043d\u0456"
    ],
    "name:und_x_variant":[
        "Mar\u012b\u0101n\u012b",
        "\u0645\u0631\u06cc\u0627\u0646\u06cc",
        "Ma\u1e5fy\u0101ni"
    ],
    "wof:name":"Mariani",
    "wof:placetype":"locality"
},
  "geometry": {"coordinates":[66.66498,32.40354],"type":"Point"}
}