{
  "type": "Feature",
  "properties": {
    "gn:admin1_code":"37",
    "gn:admin2_code":"3213",
    "gn:asciiname":"Sorwakay",
    "gn:country_code":"AF",
    "gn:dem":1572,
    "gn:feature_class":"P",
    "gn:feature_code":"PPL",
    "gn:name":"S\u014drwakay",
    "gn:population":0,
    "gn:timezone":"Asia/Kabul",
    "iso:country":"AF",
    "name:fas_x_preferred":[
        "\u0633\u0648\u0631\u0648\u06a9\u06cc"
    ],
    "name:und_x_variant":[
        "Sorvakay",
        "S\u014d\u1e5fwakay",
        "S\u014drwakay",
        "Sowrwakay"
    ],
    "wof:name":"Sorwakay",
    "wof:placetype":"locality"
},
  "geometry": {"coordinates":[69.58905,33.26307],"type":"Point"}
}