{
  "type": "Feature",
  "properties": {
    "gn:admin1_code":"6",
    "gn:admin2_code":"2101.0",
    "gn:asciiname":"Qaryah-ye Shah Wali",
    "gn:country_code":"AF",
    "gn:dem":655,
    "gn:feature_class":"P",
    "gn:feature_code":"PPL",
    "gn:name":"Qaryah-ye Sh\u0101h Wal\u012b",
    "gn:population":0,
    "gn:timezone":"Asia/Kabul",
    "iso:country":"AF",
    "name:fas_x_preferred":[
        "\u0642\u0631\u064a\u06c0 \u0634\u0627\u0647 \u0648\u0644\u06cc"
    ],
    "name:und_x_variant":[
        "Qarya-i-\u0160\u0101h Wali",
        "Qaryeh-ye Sh\u0101h Val\u012b",
        "Qaryah-ye Sh\u0101h Wal\u012b",
        "\u0642\u0631\u06cc\u0647 \u0634\u0627\u0647 \u0648\u0644\u06cc",
        "\u0642\u0631\u064a\u06c0 \u0634\u0627\u0647 \u0648\u0644\u06cc"
    ],
    "wof:name":"Qaryah-ye Shah Wali",
    "wof:placetype":"locality"
},
  "geometry": {"coordinates":[62.0014,32.39321],"type":"Point"}
}