{
  "type": "Feature",
  "properties": {
    "gn:admin1_code":"32",
    "gn:admin2_code":"1504",
    "gn:asciiname":"Wutah-ye Zagh",
    "gn:country_code":"AF",
    "gn:dem":1976,
    "gn:feature_class":"P",
    "gn:feature_code":"PPL",
    "gn:name":"Wutah-ye Z\u0101gh",
    "gn:population":0,
    "gn:timezone":"Asia/Kabul",
    "iso:country":"AF",
    "name:und_x_variant":[
        "Wota-i-Z\u0101gh",
        "Wotah-e Z\u0101gh",
        "Wutah-ye Z\u0101gh",
        "\u0648\u062a\u06c0 \u0632\u0627\u063a"
    ],
    "wof:name":"Wutah-ye Zagh",
    "wof:placetype":"locality"
},
  "geometry": {"coordinates":[67.13136,35.87089],"type":"Point"}
}