{
  "type": "Feature",
  "properties": {
    "gn:admin1_code":"37",
    "gn:admin2_code":"3210.0",
    "gn:asciiname":"Alim Gul",
    "gn:country_code":"AF",
    "gn:dem":1172,
    "gn:feature_class":"P",
    "gn:feature_code":"PPL",
    "gn:name":"Al\u012bm Gul",
    "gn:population":0,
    "gn:timezone":"Asia/Kabul",
    "iso:country":"AF",
    "wof:name":"Alim Gul",
    "wof:placetype":"locality"
},
  "geometry": {"coordinates":[70.0175,33.5125],"type":"Point"}
}