{
  "type": "Feature",
  "properties": {
    "gn:admin1_code":"41",
    "gn:admin2_code":"3407.0",
    "gn:asciiname":"Gharak",
    "gn:country_code":"AF",
    "gn:dem":2493,
    "gn:feature_class":"P",
    "gn:feature_code":"PPL",
    "gn:name":"Gharak",
    "gn:population":0,
    "gn:timezone":"Asia/Kabul",
    "iso:country":"AF",
    "name:und_x_variant":[
        "\u063a\u0631\u06a9",
        "Gha\u1e5fak"
    ],
    "wof:name":"Gharak",
    "wof:placetype":"locality"
},
  "geometry": {"coordinates":[67.01378000000001,33.90685],"type":"Point"}
}