{
  "type": "Feature",
  "properties": {
    "gn:admin1_code":"42",
    "gn:admin2_code":"3304",
    "gn:asciiname":"Kuhnah Deh",
    "gn:country_code":"AF",
    "gn:dem":2928,
    "gn:feature_class":"P",
    "gn:feature_code":"PPL",
    "gn:name":"Kuhnah Deh",
    "gn:population":0,
    "gn:timezone":"Asia/Kabul",
    "iso:country":"AF",
    "name:und_x_variant":[
        "Kukhnadekh",
        "Kuhna\u1e0feh",
        "Kohnehdeh",
        "\u06a9\u0647\u0646\u0647 \u062f\u0647",
        "Kuhnah Deh"
    ],
    "wof:name":"Kuhnah Deh",
    "wof:placetype":"locality"
},
  "geometry": {"coordinates":[70.05294000000001,35.59431],"type":"Point"}
}