{
  "type": "Feature",
  "properties": {
    "gn:admin1_code":"30",
    "gn:admin2_code":"1612",
    "gn:asciiname":"Mashi",
    "gn:country_code":"AF",
    "gn:dem":376,
    "gn:feature_class":"P",
    "gn:feature_code":"PPL",
    "gn:name":"Mash\u012b",
    "gn:population":0,
    "gn:timezone":"Asia/Kabul",
    "iso:country":"AF",
    "name:fas_x_preferred":[
        "\u0645\u0634\u06cc"
    ],
    "name:fra_x_preferred":[
        "Mashi"
    ],
    "name:hau_x_preferred":[
        "Mashi"
    ],
    "name:ita_x_preferred":[
        "Mashi"
    ],
    "name:rus_x_preferred":[
        "\u041c\u0430\u0448\u0438"
    ],
    "name:spa_x_preferred":[
        "Mashi"
    ],
    "name:und_x_variant":[
        "Mash\u012b"
    ],
    "wof:name":"Mashi",
    "wof:placetype":"locality"
},
  "geometry": {"coordinates":[66.94819,36.70357],"type":"Point"}
}