{
  "type": "Feature",
  "properties": {
    "gn:admin1_code":"19",
    "gn:admin2_code":"2202",
    "gn:asciiname":"Muhammad Zaynal",
    "gn:country_code":"AF",
    "gn:dem":480,
    "gn:feature_class":"P",
    "gn:feature_code":"PPL",
    "gn:name":"Muhammad Zaynal",
    "gn:population":0,
    "gn:timezone":"Asia/Kabul",
    "iso:country":"AF",
    "name:afr_x_preferred":[
        "Mu\u1e29ammad\u00a0 Zaynal"
    ],
    "name:fas_x_preferred":[
        "Mo\u1e29ammed Zaynal"
    ],
    "name:und_x_variant":[
        "Mo\u1e96\u1e0f-zaynal",
        "Mu\u1e29ammad\u00a0 Zaynal",
        "Mo\u1e29ammad Zeynal",
        "Mo\u1e29ammed Zaynal",
        "\u0645\u062d\u0645\u062f \u0632\u06cc\u0646\u0644"
    ],
    "wof:name":"Muhammad Zaynal",
    "wof:placetype":"locality"
},
  "geometry": {"coordinates":[61.8841,31.15322],"type":"Point"}
}