{
  "type": "Feature",
  "properties": {
    "gn:admin1_code":"41",
    "gn:admin2_code":"3403",
    "gn:asciiname":"Khider Bash",
    "gn:country_code":"AF",
    "gn:dem":2572,
    "gn:feature_class":"P",
    "gn:feature_code":"PPL",
    "gn:name":"Khid\u0113r B\u0101sh",
    "gn:population":0,
    "gn:timezone":"Asia/Kabul",
    "iso:country":"AF",
    "name:und_x_variant":[
        "Khiderbash",
        "Khed\u0113rb\u0101\u0161",
        "Khadayr B\u0101sh",
        "Khed\u0113rb\u0101sh",
        "Khid\u0113r B\u0101sh",
        "\u062e\u062f\u064a\u0631 \u0628\u0627\u0634"
    ],
    "wof:name":"Khider Bash",
    "wof:placetype":"locality"
},
  "geometry": {"coordinates":[66.44122,34.19784],"type":"Point"}
}