{
  "type": "Feature",
  "properties": {
    "gn:admin1_code":"09",
    "gn:admin2_code":"2707",
    "gn:asciiname":"Pakhak-e Balinah",
    "gn:country_code":"AF",
    "gn:dem":2836,
    "gn:feature_class":"P",
    "gn:feature_code":"PPL",
    "gn:name":"Pakhak-e B\u0101l\u012bnah",
    "gn:population":0,
    "gn:timezone":"Asia/Kabul",
    "iso:country":"AF",
    "name:und_x_variant":[
        "Pakhake B\u0101lina",
        "Pakhaki-Balina",
        "P\u0101kh\u0101k-e B\u0101lineh",
        "Pakhak-e B\u0101linah",
        "Pakhak-e B\u0101l\u012bnah",
        "\u067e\u062e\u06a9 \u0628\u0627\u0644\u06cc\u0646\u0647"
    ],
    "wof:name":"Pakhak-e Balinah",
    "wof:placetype":"locality"
},
  "geometry": {"coordinates":[66.17666,34.34438],"type":"Point"}
}