{
  "type": "Feature",
  "properties": {
    "gn:admin1_code":"7",
    "gn:admin2_code":"1805.0",
    "gn:asciiname":"Alunji",
    "gn:country_code":"AF",
    "gn:dem":2418,
    "gn:feature_class":"P",
    "gn:feature_code":"PPL",
    "gn:name":"\u0100lunj\u012b",
    "gn:population":0,
    "gn:timezone":"Asia/Kabul",
    "iso:country":"AF",
    "name:und_x_variant":[
        "\u0100lunj\u012b",
        "\u0622\u0644\u0646\u062c\u06cc",
        "\u0100lunji"
    ],
    "wof:name":"Alunji",
    "wof:placetype":"locality"
},
  "geometry": {"coordinates":[65.35803,35.38515],"type":"Point"}
}