{
  "type": "Feature",
  "properties": {
    "gn:admin1_code":"10",
    "gn:admin2_code":"2303",
    "gn:asciiname":"Kaji",
    "gn:country_code":"AF",
    "gn:dem":979,
    "gn:feature_class":"P",
    "gn:feature_code":"PPL",
    "gn:name":"Kaj\u012b",
    "gn:population":0,
    "gn:timezone":"Asia/Kabul",
    "iso:country":"AF",
    "name:ceb_x_preferred":[
        "Kaji"
    ],
    "name:deu_x_preferred":[
        "Kaji"
    ],
    "name:rus_x_preferred":[
        "\u041a\u0430\u0434\u0437\u0438"
    ],
    "name:swe_x_preferred":[
        "Kaji"
    ],
    "name:und_x_variant":[
        "Kajo",
        "Kadzhi",
        "Kaj\u012b",
        "\u06a9\u062c\u06cc"
    ],
    "wof:name":"Kaji",
    "wof:placetype":"locality"
},
  "geometry": {"coordinates":[65.08208,32.35054],"type":"Point"}
}