{
  "type": "Feature",
  "properties": {
    "gn:admin1_code":"30",
    "gn:admin2_code":"1611",
    "gn:asciiname":"Nur Bay Akah",
    "gn:country_code":"AF",
    "gn:dem":2227,
    "gn:feature_class":"P",
    "gn:feature_code":"PPL",
    "gn:name":"N\u016br B\u0101y Akah",
    "gn:population":0,
    "gn:timezone":"Asia/Kabul",
    "iso:country":"AF",
    "name:und_x_variant":[
        "N\u016br Bai Aka",
        "N\u016br Bai Akah",
        "N\u016br B\u0101y Akah",
        "\u0646\u0648\u0631 \u0628\u0627\u06cc \u0627\u06a9\u0647"
    ],
    "wof:name":"Nur Bay Akah",
    "wof:placetype":"locality"
},
  "geometry": {"coordinates":[67.38706999999999,36.40704],"type":"Point"}
}