{
  "type": "Feature",
  "properties": {
    "gn:admin1_code":"27",
    "gn:admin2_code":"409.0",
    "gn:asciiname":"Kul",
    "gn:country_code":"AF",
    "gn:dem":2457,
    "gn:feature_class":"P",
    "gn:feature_code":"PPL",
    "gn:name":"K\u016bl",
    "gn:population":0,
    "gn:timezone":"Asia/Kabul",
    "iso:country":"AF",
    "name:fas_x_preferred":[
        "\u0643\u0644"
    ],
    "name:und_x_variant":[
        "K\u014dl",
        "Kul",
        "\u0643\u0644",
        "K\u016bl",
        "\u06a9\u0648\u0644"
    ],
    "wof:name":"Kul",
    "wof:placetype":"locality"
},
  "geometry": {"coordinates":[68.32689999999999,33.75841],"type":"Point"}
}