{
  "type": "Feature",
  "properties": {
    "gn:admin1_code":"03",
    "gn:admin2_code":"1304.0",
    "gn:asciiname":"Bilowsang",
    "gn:country_code":"AF",
    "gn:dem":932,
    "gn:feature_class":"P",
    "gn:feature_code":"PPL",
    "gn:name":"Bilowsang",
    "gn:population":0,
    "gn:timezone":"Asia/Kabul",
    "iso:country":"AF",
    "name:und_x_variant":[
        "Bilausang",
        "Belawsang",
        "Bilowsang",
        "\u0628\u0644\u0648\u0633\u0646\u06af"
    ],
    "wof:name":"Bilowsang",
    "wof:placetype":"locality"
},
  "geometry": {"coordinates":[68.77171,35.59632],"type":"Point"}
}