{
  "type": "Feature",
  "properties": {
    "gn:admin1_code":"10",
    "gn:admin2_code":"2306.0",
    "gn:asciiname":"Chak Aw",
    "gn:country_code":"AF",
    "gn:dem":974,
    "gn:feature_class":"P",
    "gn:feature_code":"PPL",
    "gn:name":"Chak \u0100w",
    "gn:population":0,
    "gn:timezone":"Asia/Kabul",
    "iso:country":"AF",
    "name:und_x_variant":[
        "\u010cak\u0101w",
        "Chakav",
        "Chak \u0100w",
        "\u0686\u06a9 \u0622\u0648",
        "Chak\u0101b"
    ],
    "wof:name":"Chak Aw",
    "wof:placetype":"locality"
},
  "geometry": {"coordinates":[64.62579000000001,32.0845],"type":"Point"}
}