{
  "type": "Feature",
  "properties": {
    "gn:admin1_code":"19",
    "gn:admin2_code":"2202.0",
    "gn:asciiname":"Muhammad Yosuf Khangul",
    "gn:country_code":"AF",
    "gn:dem":482,
    "gn:feature_class":"P",
    "gn:feature_code":"PPL",
    "gn:name":"Mu\u1e29ammad Y\u014dsuf Kh\u0101ngul",
    "gn:population":0,
    "gn:timezone":"Asia/Kabul",
    "iso:country":"AF",
    "name:fas_x_preferred":[
        "Mo\u1e29ammad Y\u016bsef Kh\u0101ngol"
    ],
    "name:fas_x_variant":[
        "Mo\u1e29ammad Y\u016bsof Kh\u0101ngol"
    ],
    "name:und_x_variant":[
        "Mo\u1e96\u1e0f Yosuf Kh\u0101ngul",
        "Mu\u1e29ammad Y\u014dsuf Kh\u0101ngul",
        "\u0645\u062d\u0645\u062f \u06cc\u0648\u0633\u0641 \u062e\u0627\u0646\u06af\u0644"
    ],
    "wof:name":"Muhammad Yosuf Khangul",
    "wof:placetype":"locality"
},
  "geometry": {"coordinates":[61.88281,31.11602],"type":"Point"}
}