{
  "type": "Feature",
  "properties": {
    "gn:admin1_code":"19",
    "gn:admin2_code":"2202.0",
    "gn:asciiname":"Kurki",
    "gn:country_code":"AF",
    "gn:dem":478,
    "gn:feature_class":"P",
    "gn:feature_code":"PPL",
    "gn:name":"Kurk\u012b",
    "gn:population":0,
    "gn:timezone":"Asia/Kabul",
    "iso:country":"AF",
    "name:fas_x_preferred":[
        "\u06a9\u0631\u06a9\u06cc"
    ],
    "name:fas_x_variant":[
        "Kark\u012b"
    ],
    "name:und_x_variant":[
        "Kurk\u012b",
        "B\u0101gh-e Sabz"
    ],
    "wof:name":"Kurki",
    "wof:placetype":"locality"
},
  "geometry": {"coordinates":[61.76605,31.32611],"type":"Point"}
}