{
  "type": "Feature",
  "properties": {
    "gn:admin1_code":"34",
    "gn:admin2_code":"1014.0",
    "gn:asciiname":"Dagmene",
    "gn:country_code":"AF",
    "gn:dem":943,
    "gn:feature_class":"P",
    "gn:feature_code":"PPL",
    "gn:name":"Dagmene",
    "gn:population":0,
    "gn:timezone":"Asia/Kabul",
    "iso:country":"AF",
    "name:fas_x_preferred":[
        "\u062f\u0627\u06af \u0645\u06cc\u0646\u06cc"
    ],
    "name:und_x_variant":[
        "D\u0101g M\u0113n\u0113",
        "\u1e0e\u0101g M\u0113n\u0113",
        "\u0689\u0627\u06af \u0645\u06d0\u0646\u06d0"
    ],
    "wof:name":"Dagmene",
    "wof:placetype":"locality"
},
  "geometry": {"coordinates":[70.92815999999998,34.61024],"type":"Point"}
}