{
  "type": "Feature",
  "properties": {
    "gn:admin1_code":"41",
    "gn:admin2_code":"3402",
    "gn:asciiname":"Sang Kushtah",
    "gn:country_code":"AF",
    "gn:dem":2196,
    "gn:feature_class":"P",
    "gn:feature_code":"PPL",
    "gn:name":"Sang Kushtah",
    "gn:population":0,
    "gn:timezone":"Asia/Kabul",
    "iso:country":"AF",
    "name:und_x_variant":[
        "Sangkushta",
        "Sangku\u0161ta",
        "Sang Koshteh",
        "Sang Kushtah",
        "\u0633\u0646\u06af \u06a9\u0634\u062a\u0647"
    ],
    "wof:name":"Sang Kushtah",
    "wof:placetype":"locality"
},
  "geometry": {"coordinates":[66.56763000000001,33.51925],"type":"Point"}
}