{
  "type": "Feature",
  "properties": {
    "gn:admin1_code":"26",
    "gn:admin2_code":"1208.0",
    "gn:asciiname":"Kaltah Darah",
    "gn:country_code":"AF",
    "gn:dem":944,
    "gn:feature_class":"P",
    "gn:feature_code":"PPL",
    "gn:name":"Kaltah Darah",
    "gn:population":0,
    "gn:timezone":"Asia/Kabul",
    "iso:country":"AF",
    "name:und_x_variant":[
        "Kalta Darrah",
        "Kalteh Darreh",
        "Kaltah Darah",
        "\u06a9\u0644\u062a\u0647 \u062f\u0631\u0647"
    ],
    "wof:name":"Kaltah Darah",
    "wof:placetype":"locality"
},
  "geometry": {"coordinates":[69.66658000000001,37.17107],"type":"Point"}
}