{
  "type": "Feature",
  "properties": {
    "gn:admin1_code":"8",
    "gn:admin2_code":"601.0",
    "gn:asciiname":"Qaryah-ye Shams Sahib",
    "gn:country_code":"AF",
    "gn:dem":2202,
    "gn:feature_class":"P",
    "gn:feature_code":"PPL",
    "gn:name":"Qaryah-ye Shams \u015e\u0101\u1e29ib",
    "gn:population":0,
    "gn:timezone":"Asia/Kabul",
    "iso:country":"AF",
    "name:rus_x_preferred":[
        "Kar\u2019yashamssakhib"
    ],
    "name:und_x_variant":[
        "Qarya-i-\u0160ams S\u0101heb",
        "Qarya \u0160ams \u015e\u0101heb",
        "Qaryah-ye Shams \u015e\u0101\u1e29ib",
        "Qaryeh-e Shams \u015e\u0101\u1e29eb",
        "\u0642\u0631\u06cc\u0647 \u0634\u0645\u0633 \u0635\u0627\u062d\u0628"
    ],
    "wof:name":"Qaryah-ye Shams Sahib",
    "wof:placetype":"locality"
},
  "geometry": {"coordinates":[68.41176,33.56997],"type":"Point"}
}