{
  "type": "Feature",
  "properties": {
    "gn:admin1_code":"28",
    "gn:admin2_code":"2509",
    "gn:asciiname":"Portah Kelay",
    "gn:country_code":"AF",
    "gn:dem":2164,
    "gn:feature_class":"P",
    "gn:feature_code":"PPL",
    "gn:name":"P\u014drtah K\u00ealay",
    "gn:population":0,
    "gn:timezone":"Asia/Kabul",
    "iso:country":"AF",
    "name:und_x_variant":[
        "P\u014d\u1e5fta Kalay",
        "P\u014drtah K\u00ealay",
        "\u067e\u0648\u0631\u062a\u0647 \u06a9\u0644\u06cc",
        "Powrtah Kalay"
    ],
    "wof:name":"Portah Kelay",
    "wof:placetype":"locality"
},
  "geometry": {"coordinates":[67.74176999999999,32.04306],"type":"Point"}
}