{
  "type": "Feature",
  "properties": {
    "gn:admin1_code":"08",
    "gn:admin2_code":"614",
    "gn:asciiname":"Gabari 'Ulya",
    "gn:country_code":"AF",
    "gn:dem":2104,
    "gn:feature_class":"P",
    "gn:feature_code":"PPL",
    "gn:name":"Gabar\u012b \u2018Uly\u0101",
    "gn:population":0,
    "gn:timezone":"Asia/Kabul",
    "iso:country":"AF",
    "name:und_x_variant":[
        "Gabari-Ulia",
        "Gaba\u1e5f\u012b \u2018Uly\u0101",
        "Gabar\u012b \u2018Oly\u0101",
        "Gabar\u012b-ye \u2018Oly\u0101",
        "Gabar\u012b \u2018Uly\u0101",
        "\u06af\u0628\u0631\u06cc \u0639\u0644\u064a\u0627"
    ],
    "wof:name":"Gabari 'Ulya",
    "wof:placetype":"locality"
},
  "geometry": {"coordinates":[68.39538,33.41646],"type":"Point"}
}