{
  "type": "Feature",
  "properties": {
    "gn:admin1_code":"8",
    "gn:admin2_code":"618.0",
    "gn:asciiname":"Nasr ud Din",
    "gn:country_code":"AF",
    "gn:dem":2158,
    "gn:feature_class":"P",
    "gn:feature_code":"PPL",
    "gn:name":"Na\u015fr ud D\u012bn",
    "gn:population":0,
    "gn:timezone":"Asia/Kabul",
    "iso:country":"AF",
    "name:fas_x_preferred":[
        "\u0646\u0635\u0631 \u0627\u0644\u062f\u064a\u0646"
    ],
    "name:und_x_variant":[
        "Nasruddin",
        "Na\u015f\u1e5fu\u1e0f\u1e0f\u012bn",
        "Na\u015fr ud D\u012bn",
        "Na\u015frod D\u012bn"
    ],
    "wof:name":"Nasr ud Din",
    "wof:placetype":"locality"
},
  "geometry": {"coordinates":[68.36,33.43939],"type":"Point"}
}