{
  "type": "Feature",
  "properties": {
    "gn:admin1_code":"10",
    "gn:admin2_code":"2303",
    "gn:asciiname":"Zhrande",
    "gn:country_code":"AF",
    "gn:dem":1037,
    "gn:feature_class":"P",
    "gn:feature_code":"PPL",
    "gn:name":"Zhrand\u0113",
    "gn:population":0,
    "gn:timezone":"Asia/Kabul",
    "iso:country":"AF",
    "name:und_x_variant":[
        "Zhrand\u0113",
        "Zhrande",
        "\u0698\u0631\u0646\u062f\u06d0",
        "Z\u1e5fan\u1e0f\u0113"
    ],
    "wof:name":"Zhrande",
    "wof:placetype":"locality"
},
  "geometry": {"coordinates":[65.17103,32.34621],"type":"Point"}
}