{
  "type": "Feature",
  "properties": {
    "gn:admin1_code":"30",
    "gn:admin2_code":"1606",
    "gn:asciiname":"Dewalgai",
    "gn:country_code":"AF",
    "gn:dem":348,
    "gn:feature_class":"P",
    "gn:feature_code":"PPL",
    "gn:name":"D\u0113w\u0101lga\u012b",
    "gn:population":0,
    "gn:timezone":"Asia/Kabul",
    "iso:country":"AF",
    "name:fas_x_preferred":[
        "\u062f\u064a\u0648\u0627\u0631\u06af\u06cc"
    ],
    "name:rus_x_preferred":[
        "\u0414\u0438\u0432\u0430\u043b\u044c\u0433\u0430\u0439"
    ],
    "name:und_x_variant":[
        "D\u012bwalg\u0101i",
        "D\u012bv\u0101lg\u0101\u012b",
        "D\u012bwalq\u0101i",
        "Dival\u2019gay",
        "D\u012bv\u0101rg\u0101\u012b",
        "Dayw\u0101lga\u012b",
        "\u062f\u06cc\u0648\u0627\u0644\u06af\u06cc",
        "D\u0113w\u0101lga\u012b"
    ],
    "wof:name":"Dewalgai",
    "wof:placetype":"locality"
},
  "geometry": {"coordinates":[66.81952,36.73797],"type":"Point"}
}