{
  "type": "Feature",
  "properties": {
    "gn:admin1_code":"37",
    "gn:admin2_code":"3208.0",
    "gn:asciiname":"Badal Kelay",
    "gn:country_code":"AF",
    "gn:dem":1435,
    "gn:feature_class":"P",
    "gn:feature_code":"PPL",
    "gn:name":"Badal K\u00ealay",
    "gn:population":0,
    "gn:timezone":"Asia/Kabul",
    "iso:country":"AF",
    "name:fas_x_preferred":[
        "\u0642\u0631\u064a\u06c0 \u0628\u062f\u0644"
    ],
    "name:und_x_variant":[
        "Badaykalay",
        "Badal K\u00ealay",
        "Ba\u1e0fal Kalay",
        "\u0628\u062f\u0644 \u06a9\u0644\u06cc"
    ],
    "wof:name":"Badal Kelay",
    "wof:placetype":"locality"
},
  "geometry": {"coordinates":[69.80589000000001,33.40783],"type":"Point"}
}