{
  "type": "Feature",
  "properties": {
    "gn:admin1_code":"35",
    "gn:admin2_code":"902",
    "gn:asciiname":"Shahidan",
    "gn:country_code":"AF",
    "gn:dem":713,
    "gn:feature_class":"P",
    "gn:feature_code":"PPL",
    "gn:name":"Shah\u012bd\u0101n",
    "gn:population":0,
    "gn:timezone":"Asia/Kabul",
    "iso:country":"AF",
    "name:und_x_variant":[
        "\u0160ah\u012bd\u0101n",
        "Shakhidan",
        "Shah\u012bd\u0101n",
        "\u0634\u0647\u06cc\u062f\u0627\u0646"
    ],
    "wof:name":"Shahidan",
    "wof:placetype":"locality"
},
  "geometry": {"coordinates":[70.01264,34.51884],"type":"Point"}
}