{
  "type": "Feature",
  "properties": {
    "gn:admin1_code":"18",
    "gn:admin2_code":"816.0",
    "gn:asciiname":"Zhir Gad",
    "gn:country_code":"AF",
    "gn:dem":968,
    "gn:feature_class":"P",
    "gn:feature_code":"PPL",
    "gn:name":"Zhi\u1e5f Ga\u1e0f",
    "gn:population":0,
    "gn:timezone":"Asia/Kabul",
    "iso:country":"AF",
    "name:fas_x_preferred":[
        "\u0698\u0631 \u06af\u062f"
    ],
    "name:und_x_variant":[
        "Zirgad",
        "\u017der Gad",
        "Zher Gad",
        "Zhi\u1e5f Ga\u1e0f",
        "\u0698\u0693 \u06af\u0689"
    ],
    "wof:name":"Zhir Gad",
    "wof:placetype":"locality"
},
  "geometry": {"coordinates":[70.93068000000002,34.48540999999999],"type":"Point"}
}