{
  "type": "Feature",
  "properties": {
    "gn:admin1_code":"7",
    "gn:admin2_code":"1802.0",
    "gn:asciiname":"Aq Machit",
    "gn:country_code":"AF",
    "gn:dem":955,
    "gn:feature_class":"P",
    "gn:feature_code":"PPL",
    "gn:name":"\u0100q Mach\u012b\u1e6f",
    "gn:population":0,
    "gn:timezone":"Asia/Kabul",
    "iso:country":"AF",
    "name:und_x_variant":[
        "\u0100q Mac\u012bt",
        "\u0100q Mach\u012bt",
        "\u0100q Mach\u012b\u1e6f",
        "\u0622\u0642 \u0645\u0686\u06cc\u067c",
        "\u0100q Masjid",
        "\u0622\u0642 \u0645\u0633\u062c\u062f"
    ],
    "wof:name":"Aq Machit",
    "wof:placetype":"locality"
},
  "geometry": {"coordinates":[64.81943000000001,35.88831],"type":"Point"}
}