{
  "type": "Feature",
  "properties": {
    "gn:admin1_code":"27",
    "gn:admin2_code":"402.0",
    "gn:asciiname":"Qol-e Nati",
    "gn:country_code":"AF",
    "gn:dem":2857,
    "gn:feature_class":"P",
    "gn:feature_code":"PPL",
    "gn:name":"Q\u014dl-e N\u0101\u1e6f\u012b",
    "gn:population":0,
    "gn:timezone":"Asia/Kabul",
    "iso:country":"AF",
    "name:und_x_variant":[
        "Kulli-Nati",
        "Qulle N\u0101ti",
        "Q\u014dl-e N\u0101tay",
        "Qolleh-ye N\u0101t\u012b",
        "Q\u014dl-e N\u0101\u1e6f\u012b",
        "\u0642\u0648\u0644 \u0646\u0627\u067c\u0649"
    ],
    "wof:name":"Qol-e Nati",
    "wof:placetype":"locality"
},
  "geometry": {"coordinates":[68.43425000000001,34.4516],"type":"Point"}
}