{
  "type": "Feature",
  "properties": {
    "gn:admin1_code":"10",
    "gn:admin2_code":"2302",
    "gn:asciiname":"Zimriani",
    "gn:country_code":"AF",
    "gn:dem":823,
    "gn:feature_class":"P",
    "gn:feature_code":"PPL",
    "gn:name":"Zimriani",
    "gn:population":0,
    "gn:timezone":"Asia/Kabul",
    "iso:country":"AF",
    "name:und_x_variant":[
        "\u017d\u012bmry\u0101ni",
        "Zh\u012bmry\u0101n\u012b",
        "Zimriani",
        "Z\u0332h\u0332\u012bm\u1e5fiy\u0101n\u012b",
        "\u0696\u06cc\u0645\u0693\u06cc\u0627\u0646\u06cc",
        "Zh\u012bmr\u012b\u0101n\u012b",
        "Z\u0332h\u0332\u012bmr\u012b\u0101n\u012b"
    ],
    "wof:name":"Zimriani",
    "wof:placetype":"locality"
},
  "geometry": {"coordinates":[64.66863000000001,31.68545],"type":"Point"}
}