{
  "type": "Feature",
  "properties": {
    "gn:admin1_code":"09",
    "gn:admin2_code":"2704",
    "gn:asciiname":"Lur Bist",
    "gn:country_code":"AF",
    "gn:dem":1835,
    "gn:feature_class":"P",
    "gn:feature_code":"PPL",
    "gn:name":"L\u016br Bist",
    "gn:population":0,
    "gn:timezone":"Asia/Kabul",
    "iso:country":"AF",
    "name:und_x_variant":[
        "L\u016br Bist",
        "\u0644\u0648\u0631 \u0628\u0633\u062a",
        "L\u016b\u1e5f Best"
    ],
    "wof:name":"Lur Bist",
    "wof:placetype":"locality"
},
  "geometry": {"coordinates":[63.50774000000001,33.55682],"type":"Point"}
}