{
  "type": "Feature",
  "properties": {
    "gn:admin1_code":"23",
    "gn:admin2_code":"2416.0",
    "gn:asciiname":"Taj Muhammad",
    "gn:country_code":"AF",
    "gn:dem":934,
    "gn:feature_class":"P",
    "gn:feature_code":"PPL",
    "gn:name":"T\u0101j Mu\u1e29ammad",
    "gn:population":0,
    "gn:timezone":"Asia/Kabul",
    "iso:country":"AF",
    "name:und_x_variant":[
        "Tadzhmukhammed",
        "T\u0101j Mu\u1e29ammad",
        "\u062a\u0627\u062c \u0645\u062d\u0645\u062f",
        "T\u0101jmo\u1e29ammad"
    ],
    "wof:name":"Taj Muhammad",
    "wof:placetype":"locality"
},
  "geometry": {"coordinates":[65.32665,31.54514],"type":"Point"}
}