{
  "type": "Feature",
  "properties": {
    "gn:admin1_code":"13",
    "gn:admin2_code":"102",
    "gn:asciiname":"Tarakhel Tarnaw",
    "gn:country_code":"AF",
    "gn:dem":1789,
    "gn:feature_class":"P",
    "gn:feature_code":"PPL",
    "gn:name":"Tarakh\u0113l Tarn\u0101w",
    "gn:population":0,
    "gn:timezone":"Asia/Kabul",
    "iso:country":"AF",
    "name:fas_x_preferred":[
        "\u062a\u0631\u0647 \u062e\u06cc\u0644"
    ],
    "name:rus_x_preferred":[
        "Tarakheil\u2019"
    ],
    "name:und_x_variant":[
        "Ta\u1e5fakh\u0113l",
        "Ta\u1e5fakheyl",
        "Tarah Kh\u0113l",
        "\u062a\u0631\u0647 \u062e\u06d0\u0644",
        "Tar N\u0101w",
        "\u062a\u0631 \u0646\u0627\u0648",
        "Tarakh\u0113l Tarn\u0101w",
        "\u062a\u0631\u0647 \u062e\u06d0\u0644 \u062a\u0631\u0646\u0627\u0648"
    ],
    "wof:name":"Tarakhel Tarnaw",
    "wof:placetype":"locality"
},
  "geometry": {"coordinates":[69.25623,34.57989],"type":"Point"}
}