{
  "type": "Feature",
  "properties": {
    "gn:country":"AF",
    "gn:fcode":"PPLA2",
    "gn:pop":10023,
    "iso:country":"AF",
    "name:fas_x_preferred":[
        "An\u0101r Darah"
    ],
    "name:fas_x_variant":[
        "Shaykh \u0100b\u0101d",
        "\u0627\u0646\u0627\u0631 \u062f\u0631\u0647",
        "\u0634\u06cc\u062e \u0622\u0628\u0627\u062f"
    ],
    "name:rus_x_preferred":[
        "\u0410\u043d\u0430\u0440 \u0414\u0430\u0440\u0430"
    ],
    "name:unk_x_variant":[
        "S\u0304aykh \u0100b\u0101\u1e0f"
    ],
    "qs:name":"An\u0101r Darah",
    "qs:photos_9r":0,
    "qs:photos_sr":0,
    "qs:pop_sr":"6",
    "wof:name":"An\u0101r Darah",
    "wof:placetype":"locality",
    "wof:population":10023
},
  "geometry": {"coordinates":[61.65397,32.7587],"type":"Point"}
}