{
  "type": "Feature",
  "properties": {
    "gn:admin1_code":"01",
    "gn:admin2_code":"1101.0",
    "gn:asciiname":"Poshtek",
    "gn:country_code":"AF",
    "gn:dem":1847,
    "gn:feature_class":"P",
    "gn:feature_code":"PPL",
    "gn:name":"P\u014dsht\u0113k",
    "gn:population":0,
    "gn:timezone":"Asia/Kabul",
    "iso:country":"AF",
    "name:und_x_variant":[
        "P\u014dst\u0113k",
        "\u067e\u0648\u0634\u062a\u06d0\u06a9",
        "P\u016bst\u0113k",
        "P\u014dsht\u0113k"
    ],
    "wof:name":"Poshtek",
    "wof:placetype":"locality"
},
  "geometry": {"coordinates":[70.60514000000001,37.21504],"type":"Point"}
}