{
  "type": "Feature",
  "properties": {
    "gn:admin1_code":"17",
    "gn:admin2_code":"507",
    "gn:asciiname":"Jowzi Kala",
    "gn:country_code":"AF",
    "gn:dem":2523,
    "gn:feature_class":"P",
    "gn:feature_code":"PPL",
    "gn:name":"Jowz\u012b Kal\u0101",
    "gn:population":0,
    "gn:timezone":"Asia/Kabul",
    "iso:country":"AF",
    "name:und_x_variant":[
        "Dzhauzkala",
        "Jawzi Kal\u0101",
        "Jowz\u012b Kal\u0101",
        "\u062c\u0648\u0632\u06cc \u06a9\u0644\u0627"
    ],
    "wof:name":"Jowzi Kala",
    "wof:placetype":"locality"
},
  "geometry": {"coordinates":[68.92872,33.66563],"type":"Point"}
}