{
  "type": "Feature",
  "properties": {
    "gn:admin1_code":"07",
    "gn:admin2_code":"1814",
    "gn:asciiname":"Muhammad Tashi",
    "gn:country_code":"AF",
    "gn:dem":292,
    "gn:feature_class":"P",
    "gn:feature_code":"PPL",
    "gn:name":"Mu\u1e29ammad T\u0101sh\u012b",
    "gn:population":0,
    "gn:timezone":"Asia/Kabul",
    "iso:country":"AF",
    "name:und_x_variant":[
        "Muhammad T\u0101shi",
        "Mu\u1e29ammad T\u0101sh\u012b"
    ],
    "wof:name":"Muhammad Tashi",
    "wof:placetype":"locality"
},
  "geometry": {"coordinates":[64.76666999999999,37.08333],"type":"Point"}
}