{
  "type": "Feature",
  "properties": {
    "gn:admin1_code":"02",
    "gn:admin2_code":"1903",
    "gn:asciiname":"Kushak",
    "gn:country_code":"AF",
    "gn:dem":1955,
    "gn:feature_class":"P",
    "gn:feature_code":"PPL",
    "gn:name":"Kushak",
    "gn:population":0,
    "gn:timezone":"Asia/Kabul",
    "iso:country":"AF",
    "wof:name":"Kushak",
    "wof:placetype":"locality"
},
  "geometry": {"coordinates":[63.76667,34.66667],"type":"Point"}
}