{
  "type": "Feature",
  "properties": {
    "gn:admin1_code":"01",
    "gn:admin2_code":"1113",
    "gn:asciiname":"Dashmandi",
    "gn:country_code":"AF",
    "gn:dem":863,
    "gn:feature_class":"P",
    "gn:feature_code":"PPL",
    "gn:name":"D\u0101shmand\u012b",
    "gn:population":0,
    "gn:timezone":"Asia/Kabul",
    "iso:country":"AF",
    "name:und_x_variant":[
        "\u1e0e\u0101s\u0304man\u1e0fi",
        "D\u0101shmand\u012b",
        "\u062f\u0627\u0634\u0645\u0646\u062f\u06cc"
    ],
    "wof:name":"Dashmandi",
    "wof:placetype":"locality"
},
  "geometry": {"coordinates":[70.16628,37.50109000000001],"type":"Point"}
}