{
  "type": "Feature",
  "properties": {
    "gn:admin1_code":"28",
    "gn:admin2_code":"2501",
    "gn:asciiname":"Duri",
    "gn:country_code":"AF",
    "gn:dem":1790,
    "gn:feature_class":"P",
    "gn:feature_code":"PPL",
    "gn:name":"D\u016br\u012b",
    "gn:population":0,
    "gn:timezone":"Asia/Kabul",
    "iso:country":"AF",
    "name:und_x_variant":[
        "D\u016br\u012b",
        "\u062f\u0648\u0631\u06cc"
    ],
    "wof:name":"Duri",
    "wof:placetype":"locality"
},
  "geometry": {"coordinates":[67.20811999999999,32.23242],"type":"Point"}
}