{
  "type": "Feature",
  "properties": {
    "gn:admin1_code":"19",
    "gn:admin2_code":"2204",
    "gn:asciiname":"Sayfuddin",
    "gn:country_code":"AF",
    "gn:dem":485,
    "gn:feature_class":"P",
    "gn:feature_code":"PPL",
    "gn:name":"Sayfudd\u012bn",
    "gn:population":0,
    "gn:timezone":"Asia/Kabul",
    "iso:country":"AF",
    "name:und_x_variant":[
        "Sayfu\u1e0f\u1e0f\u012bn",
        "Sayfudd\u012bn",
        "\u0633\u06cc\u0641 \u0627\u0644\u062f\u06cc\u0646",
        "Seyf od D\u012bn"
    ],
    "wof:name":"Sayfuddin",
    "wof:placetype":"locality"
},
  "geometry": {"coordinates":[62.14538,31.19508],"type":"Point"}
}