{
  "type": "Feature",
  "properties": {
    "gn:admin1_code":"23",
    "gn:admin2_code":"2405",
    "gn:asciiname":"Sunjit",
    "gn:country_code":"AF",
    "gn:dem":1802,
    "gn:feature_class":"P",
    "gn:feature_code":"PPL",
    "gn:name":"Sunjit",
    "gn:population":0,
    "gn:timezone":"Asia/Kabul",
    "iso:country":"AF",
    "name:und_x_variant":[
        "Sundzhit",
        "Sunjit",
        "\u0633\u0646\u062c\u062a",
        "Sunjet"
    ],
    "wof:name":"Sunjit",
    "wof:placetype":"locality"
},
  "geometry": {"coordinates":[65.56863,32.18129],"type":"Point"}
}