{
  "type": "Feature",
  "properties": {
    "gn:admin1_code":"23",
    "gn:admin2_code":"2403",
    "gn:asciiname":"Haji 'Isa Muhammad Kelay",
    "gn:country_code":"AF",
    "gn:dem":1338,
    "gn:feature_class":"P",
    "gn:feature_code":"PPL",
    "gn:name":"\u1e28\u0101j\u012b \u2018\u012as\u00e1 Mu\u1e29ammad K\u00ealay",
    "gn:population":0,
    "gn:timezone":"Asia/Kabul",
    "iso:country":"AF",
    "name:und_x_variant":[
        "\u1e28\u0101ji \u2018Is\u0101 Mo\u1e29amma\u1e0f Kalay",
        "Khadzhi-Isa-Mukhammed-Kalay",
        "\u062d\u0627\u062c\u06cc \u0639\u06cc\u0633\u0649 \u0645\u062d\u0645\u062f \u06a9\u0644\u06cc",
        "\u1e28\u0101jj\u012b \u2018\u012as\u00e1 Mo\u1e29ammad Kalay",
        "\u1e28\u0101j\u012b \u2018\u012as\u00e1 Mu\u1e29ammad K\u00ealay"
    ],
    "wof:name":"Haji 'Isa Muhammad Kelay",
    "wof:placetype":"locality"
},
  "geometry": {"coordinates":[66.23716,31.9315],"type":"Point"}
}