{
  "type": "Feature",
  "properties": {
    "gn:admin1_code":"8",
    "gn:admin2_code":"607.0",
    "gn:asciiname":"Ambulaq",
    "gn:country_code":"AF",
    "gn:dem":2510,
    "gn:feature_class":"P",
    "gn:feature_code":"PPL",
    "gn:name":"\u0100mb\u016bl\u0101q",
    "gn:population":0,
    "gn:timezone":"Asia/Kabul",
    "iso:country":"AF",
    "name:und_x_variant":[
        "\u0100mb\u014dl\u0101q",
        "\u0100mbowl\u0101q",
        "\u0100mb\u016bl\u0101q",
        "\u0622\u0645\u0628\u0648\u0644\u0627\u0642"
    ],
    "wof:name":"Ambulaq",
    "wof:placetype":"locality"
},
  "geometry": {"coordinates":[67.45414,33.05564],"type":"Point"}
}