{
  "type": "Feature",
  "properties": {
    "gn:admin1_code":"28",
    "gn:admin2_code":"2507.0",
    "gn:asciiname":"Chowgay",
    "gn:country_code":"AF",
    "gn:dem":2090,
    "gn:feature_class":"P",
    "gn:feature_code":"PPL",
    "gn:name":"Chowgay",
    "gn:population":0,
    "gn:timezone":"Asia/Kabul",
    "iso:country":"AF",
    "name:und_x_variant":[
        "\u010cawgay",
        "Chaugay",
        "Chowgay",
        "Chawgay",
        "\u0686\u0648\u06af\u06cc"
    ],
    "wof:name":"Chowgay",
    "wof:placetype":"locality"
},
  "geometry": {"coordinates":[67.5201,31.91705],"type":"Point"}
}