{
  "type": "Feature",
  "properties": {
    "gn:admin1_code":"39",
    "gn:admin2_code":"2602.0",
    "gn:asciiname":"Agha Jan",
    "gn:country_code":"AF",
    "gn:dem":1569,
    "gn:feature_class":"P",
    "gn:feature_code":"PPL",
    "gn:name":"\u0100gh\u0101 J\u0101n",
    "gn:population":0,
    "gn:timezone":"Asia/Kabul",
    "iso:country":"AF",
    "name:fas_x_preferred":[
        "\u0622\u063a\u0627\u062c\u0627\u0646"
    ],
    "name:und_x_variant":[
        "Agadzhan",
        "\u0100gh\u0101 J\u0101n",
        "\u0622\u063a\u0627 \u062c\u0627\u0646"
    ],
    "wof:name":"Agha Jan",
    "wof:placetype":"locality"
},
  "geometry": {"coordinates":[66.21633,32.73568],"type":"Point"}
}