{
  "type": "Feature",
  "properties": {
    "gn:admin1_code":"28",
    "gn:admin2_code":"2501",
    "gn:asciiname":"Nahr-e Babru",
    "gn:country_code":"AF",
    "gn:dem":1597,
    "gn:feature_class":"P",
    "gn:feature_code":"PPL",
    "gn:name":"Nahr-e Babr\u016b",
    "gn:population":0,
    "gn:timezone":"Asia/Kabul",
    "iso:country":"AF",
    "name:fas_x_preferred":[
        "\u0646\u0647\u0631\u064b \u0628\u0628\u0631\u0648"
    ],
    "name:und_x_variant":[
        "Nakhri-Babru",
        "Nahr-e Babr\u016b",
        "\u0646\u0647\u0631 \u0628\u0628\u0631\u0648",
        "Nahre Babru"
    ],
    "wof:name":"Nahr-e Babru",
    "wof:placetype":"locality"
},
  "geometry": {"coordinates":[66.96951999999999,32.14325],"type":"Point"}
}