{
  "type": "Feature",
  "properties": {
    "gn:admin1_code":"23",
    "gn:admin2_code":"2411",
    "gn:asciiname":"Kshetah Mil",
    "gn:country_code":"AF",
    "gn:dem":1091,
    "gn:feature_class":"P",
    "gn:feature_code":"PPL",
    "gn:name":"Ks\u0332h\u0332\u00eatah M\u012bl",
    "gn:population":0,
    "gn:timezone":"Asia/Kabul",
    "iso:country":"AF",
    "name:fas_x_preferred":[
        "\u06a9\u0627\u0634\u062a\u0647 \u0645\u064a\u0644"
    ],
    "name:rus_x_preferred":[
        "Kshattamil\u2019"
    ],
    "name:und_x_variant":[
        "Keshatah M\u012bl",
        "Ks\u0304\u00e1ta Mel",
        "K\u0161atta M\u012bl",
        "Kshatah M\u012bl",
        "Ks\u0332h\u0332\u00eatah M\u012bl",
        "\u06a9\u069a\u062a\u0647 \u0645\u06cc\u0644",
        "\u06a9\u0627\u0634\u062a\u0647 \u0645\u064a\u0644",
        "Kshattamil\u2019"
    ],
    "wof:name":"Kshetah Mil",
    "wof:placetype":"locality"
},
  "geometry": {"coordinates":[66.03901999999999,31.09762000000001],"type":"Point"}
}