{
  "type": "Feature",
  "properties": {
    "gn:admin1_code":"23",
    "gn:admin2_code":"2412.0",
    "gn:asciiname":"De Ghani Khan Kelay",
    "gn:country_code":"AF",
    "gn:dem":1197,
    "gn:feature_class":"P",
    "gn:feature_code":"PPL",
    "gn:name":"D\u00ea Ghan\u012b Kh\u0101n K\u00ealay",
    "gn:population":0,
    "gn:timezone":"Asia/Kabul",
    "iso:country":"AF",
    "name:und_x_variant":[
        "Ganikhankalay",
        "D\u00ea Ghan\u012b Kh\u0101n K\u00ealay",
        "\u062f \u063a\u0646\u06cc \u062e\u0627\u0646 \u06a9\u0644\u06cc",
        "De Ghan\u012bkh\u0101n Kalay"
    ],
    "wof:name":"De Ghani Khan Kelay",
    "wof:placetype":"locality"
},
  "geometry": {"coordinates":[66.34416,31.56359],"type":"Point"}
}