{
  "type": "Feature",
  "properties": {
    "gn:admin1_code":"01",
    "gn:admin2_code":"1112.0",
    "gn:asciiname":"Gul-e Khandan",
    "gn:country_code":"AF",
    "gn:dem":2234,
    "gn:feature_class":"P",
    "gn:feature_code":"PPL",
    "gn:name":"Gul-e Khand\u0101n",
    "gn:population":0,
    "gn:timezone":"Asia/Kabul",
    "iso:country":"AF",
    "name:und_x_variant":[
        "Gul-i-Khan\u1e0f\u0101n",
        "\u06af\u0644 \u062e\u0646\u062f\u0627\u0646",
        "Gol-e Khand\u0101n",
        "Gul-e Khand\u0101n"
    ],
    "wof:name":"Gul-e Khandan",
    "wof:placetype":"locality"
},
  "geometry": {"coordinates":[70.51425,37.56651],"type":"Point"}
}