{
  "type": "Feature",
  "properties": {
    "gn:admin1_code":"13",
    "gn:admin2_code":"105.0",
    "gn:asciiname":"Qal'ah-ye Regi",
    "gn:country_code":"AF",
    "gn:dem":1558,
    "gn:feature_class":"P",
    "gn:feature_code":"PPL",
    "gn:name":"Qal\u2018ah-ye R\u0113g\u012b",
    "gn:population":0,
    "gn:timezone":"Asia/Kabul",
    "iso:country":"AF",
    "name:und_x_variant":[
        "Kalayi-Regi",
        "Qal\u0101-i-\u1e5e\u0113gi",
        "Qal\u2018eh-ye R\u0113g\u012b",
        "Qal\u2018eh-ye R\u012bg\u012b",
        "\u0642\u0644\u0639\u06c0 \u0631\u06cc\u06af\u06cc",
        "Qal\u2018ah-ye R\u0113g\u012b",
        "Qal\u2018ah-ye Rayg\u012b"
    ],
    "wof:name":"Qal'ah-ye Regi",
    "wof:placetype":"locality"
},
  "geometry": {"coordinates":[69.1647,34.825],"type":"Point"}
}