{
  "type": "Feature",
  "properties": {
    "gn:admin1_code":"01",
    "gn:admin2_code":"1112.0",
    "gn:asciiname":"Badman",
    "gn:country_code":"AF",
    "gn:dem":1823,
    "gn:feature_class":"P",
    "gn:feature_code":"PPL",
    "gn:name":"B\u0101dm\u0101n",
    "gn:population":0,
    "gn:timezone":"Asia/Kabul",
    "iso:country":"AF",
    "name:und_x_variant":[
        "B\u0101dm\u0101n",
        "\u0628\u0627\u062f\u0645\u0627\u0646",
        "B\u0101\u1e0fm\u0101n"
    ],
    "wof:name":"Badman",
    "wof:placetype":"locality"
},
  "geometry": {"coordinates":[70.43429999999999,37.60785],"type":"Point"}
}