{
  "type": "Feature",
  "properties": {
    "gn:admin1_code":"23",
    "gn:admin2_code":"2402",
    "gn:asciiname":"Najoy",
    "gn:country_code":"AF",
    "gn:dem":1069,
    "gn:feature_class":"P",
    "gn:feature_code":"PPL",
    "gn:name":"Naj\u014dy",
    "gn:population":0,
    "gn:timezone":"Asia/Kabul",
    "iso:country":"AF",
    "name:und_x_variant":[
        "Naj\u014dy",
        "Nadzhoy",
        "\u0646\u062c\u0648\u06cc",
        "Naj\u016by"
    ],
    "wof:name":"Najoy",
    "wof:placetype":"locality"
},
  "geometry": {"coordinates":[65.97476999999999,31.61093],"type":"Point"}
}