{
  "type": "Feature",
  "properties": {
    "gn:admin1_code":"36",
    "gn:admin2_code":"702",
    "gn:asciiname":"Khandaq",
    "gn:country_code":"AF",
    "gn:dem":2131,
    "gn:feature_class":"P",
    "gn:feature_code":"PPL",
    "gn:name":"Khandaq",
    "gn:population":0,
    "gn:timezone":"Asia/Kabul",
    "iso:country":"AF",
    "name:ara_x_preferred":[
        "\u062e\u0646\u062f\u0642"
    ],
    "name:fas_x_preferred":[
        "\u062e\u0646\u062f\u0642"
    ],
    "name:msa_x_preferred":[
        "Khandaq"
    ],
    "name:und_x_variant":[
        "Khandak"
    ],
    "wof:name":"Khandaq",
    "wof:placetype":"locality"
},
  "geometry": {"coordinates":[68.92088000000001,33.42725],"type":"Point"}
}