{
  "type": "Feature",
  "properties": {
    "gn:admin1_code":"33",
    "gn:admin2_code":"3104",
    "gn:asciiname":"Khowalah Siyahgak",
    "gn:country_code":"AF",
    "gn:dem":2025,
    "gn:feature_class":"P",
    "gn:feature_code":"PPL",
    "gn:name":"Khow\u0101lah Siy\u0101hgak",
    "gn:population":0,
    "gn:timezone":"Asia/Kabul",
    "iso:country":"AF",
    "name:und_x_variant":[
        "Khaw\u0101le Sy\u0101hgak",
        "Khav\u0101leh S\u012b\u0101hgak",
        "Khow\u0101lah S\u012b\u0101hgak",
        "\u062e\u0648\u0627\u0644\u0647 \u0633\u06cc\u0627\u0647 \u06af\u06a9",
        "Khow\u0101lah Siy\u0101hgak"
    ],
    "wof:name":"Khowalah Siyahgak",
    "wof:placetype":"locality"
},
  "geometry": {"coordinates":[66.48428,35.51321],"type":"Point"}
}