{
  "type": "Feature",
  "properties": {
    "gn:admin1_code":"34",
    "gn:admin2_code":"1003.0",
    "gn:asciiname":"Hazrat Jan Bandah",
    "gn:country_code":"AF",
    "gn:dem":945,
    "gn:feature_class":"P",
    "gn:feature_code":"PPL",
    "gn:name":"\u1e28a\u1e95rat J\u0101n B\u0101n\u1e0fah",
    "gn:population":0,
    "gn:timezone":"Asia/Kabul",
    "iso:country":"AF",
    "name:fas_x_preferred":[
        "\u062f\u0647\u06a9\u0654 \u062d\u0636\u0631\u062a \u062c\u0627\u0646"
    ],
    "name:und_x_variant":[
        "Khazratdzhanbanda",
        "\u1e28a\u1e0f\u1e95\u1e5fatj\u0101n B\u0101ndeh",
        "\u062d\u0636\u0631\u062a \u062c\u0627\u0646 \u0628\u0627\u0646\u0689\u0647",
        "\u1e28a\u1e95ratj\u0101n B\u0101ndeh",
        "\u1e28a\u1e95rat J\u0101n B\u0101n\u1e0fah"
    ],
    "wof:name":"Hazrat Jan Bandah",
    "wof:placetype":"locality"
},
  "geometry": {"coordinates":[71.35335000000001,35.04182],"type":"Point"}
}