{
  "type": "Feature",
  "properties": {
    "gn:admin1_code":"10",
    "gn:admin2_code":"2305",
    "gn:asciiname":"Gharian",
    "gn:country_code":"AF",
    "gn:dem":1681,
    "gn:feature_class":"P",
    "gn:feature_code":"PPL",
    "gn:name":"Gh\u0101r\u012b\u0101n",
    "gn:population":0,
    "gn:timezone":"Asia/Kabul",
    "iso:country":"AF",
    "name:fas_x_preferred":[
        "\u063a\u0627\u0631\u064a\u0627\u0646"
    ],
    "name:rus_x_preferred":[
        "\u0413\u0430\u0440\u044c\u044f\u043d"
    ],
    "name:und_x_variant":[
        "Gar\u2019yan",
        "Gh\u0101\u1e5fy\u0101n",
        "Gh\u0101r\u012b\u0101n",
        "\u063a\u0627\u0631\u06cc\u0627\u0646"
    ],
    "wof:name":"Gharian",
    "wof:placetype":"locality"
},
  "geometry": {"coordinates":[65.13981,33.19089],"type":"Point"}
}