{
  "type": "Feature",
  "properties": {
    "gn:admin1_code":"28",
    "gn:admin2_code":"2507.0",
    "gn:asciiname":"Gerdian",
    "gn:country_code":"AF",
    "gn:dem":1976,
    "gn:feature_class":"P",
    "gn:feature_code":"PPL",
    "gn:name":"Gerd\u012b\u0101n",
    "gn:population":0,
    "gn:timezone":"Asia/Kabul",
    "iso:country":"AF",
    "name:pus_x_preferred":[
        "\u06af\u0631\u062f\u06cc\u0627\u0646"
    ],
    "name:rus_x_preferred":[
        "Gird\u2019yan"
    ],
    "name:und_x_variant":[
        "Ge\u1e5f\u1e0fy\u0101n",
        "Gird\u012b\u0101n",
        "Gerd\u012b\u0101n"
    ],
    "wof:name":"Gerdian",
    "wof:placetype":"locality"
},
  "geometry": {"coordinates":[67.34095000000001,31.97182],"type":"Point"}
}