{
  "type": "Feature",
  "properties": {
    "gn:admin1_code":"05",
    "gn:admin2_code":"2806.0",
    "gn:asciiname":"Giro Qol",
    "gn:country_code":"AF",
    "gn:dem":2670,
    "gn:feature_class":"P",
    "gn:feature_code":"PPL",
    "gn:name":"G\u012br\u014d Q\u014dl",
    "gn:population":0,
    "gn:timezone":"Asia/Kabul",
    "iso:country":"AF",
    "name:rus_x_preferred":[
        "Girukul\u2019"
    ],
    "name:und_x_variant":[
        "Gi\u1e5f\u016bq\u014dl",
        "G\u012browqowl",
        "G\u012br\u014d Q\u014dl",
        "\u06af\u06cc\u0631\u0648 \u0642\u0648\u0644"
    ],
    "wof:name":"Giro Qol",
    "wof:placetype":"locality"
},
  "geometry": {"coordinates":[67.28336,34.11843],"type":"Point"}
}