{
  "type": "Feature",
  "properties": {
    "gn:admin1_code":"08",
    "gn:admin2_code":"607",
    "gn:asciiname":"Qumagh-e Pa'in",
    "gn:country_code":"AF",
    "gn:dem":2751,
    "gn:feature_class":"P",
    "gn:feature_code":"PPL",
    "gn:name":"Q\u016bm\u0101gh-e P\u0101\u2019\u012bn",
    "gn:population":0,
    "gn:timezone":"Asia/Kabul",
    "iso:country":"AF",
    "name:fas_x_preferred":[
        "\u0642\u0648\u0645\u0627\u063a \u067e\u0627\u0626\u064a\u0646"
    ],
    "name:rus_x_preferred":[
        "\u041a\u0443\u043c\u0430\u0433\u0438-\u041f\u0430\u0439\u043d"
    ],
    "name:und_x_variant":[
        "Kumagi-Payn",
        "Q\u016bm\u0101gh-e P\u0101\u2019\u012bn",
        "\u0642\u0648\u0645\u0627\u063a \u067e\u0627\u0626\u06cc\u0646",
        "\u0642\u0648\u0645\u0627\u063a \u067e\u0627\u0626\u064a\u0646"
    ],
    "wof:name":"Qumagh-e Pa'in",
    "wof:placetype":"locality"
},
  "geometry": {"coordinates":[67.63618000000001,33.05969],"type":"Point"}
}