{
  "type": "Feature",
  "properties": {
    "gn:admin1_code":"9",
    "gn:admin2_code":"2704.0",
    "gn:asciiname":"Tazri",
    "gn:country_code":"AF",
    "gn:dem":2081,
    "gn:feature_class":"P",
    "gn:feature_code":"PPL",
    "gn:name":"\u0162azr\u012b",
    "gn:population":0,
    "gn:timezone":"Asia/Kabul",
    "iso:country":"AF",
    "name:und_x_variant":[
        "\u0162azr\u012b",
        "\u0637\u0632\u0631\u06cc",
        "Tazr\u012b"
    ],
    "wof:name":"Tazri",
    "wof:placetype":"locality"
},
  "geometry": {"coordinates":[64.02452,33.67727],"type":"Point"}
}