{
  "type": "Feature",
  "properties": {
    "gn:admin1_code":"09",
    "gn:admin2_code":"2705",
    "gn:asciiname":"Sayn",
    "gn:country_code":"AF",
    "gn:dem":2309,
    "gn:feature_class":"P",
    "gn:feature_code":"PPL",
    "gn:name":"Sayn",
    "gn:population":0,
    "gn:timezone":"Asia/Kabul",
    "iso:country":"AF",
    "name:bul_x_preferred":[
        "\u0413\u0440\u0430\u0444\u0441\u0442\u0432\u043e \u0417\u0430\u0439\u043d"
    ],
    "name:deu_x_preferred":[
        "Grafschaft Sayn"
    ],
    "name:epo_x_preferred":[
        "Graflando Sayn"
    ],
    "name:ita_x_preferred":[
        "Sayn"
    ],
    "name:jpn_x_preferred":[
        "\u30b6\u30a4\u30f3\u4f2f\u9818"
    ],
    "name:nld_x_preferred":[
        "Graafschap Sayn"
    ],
    "name:und_x_variant":[
        "\u0633\u06cc\u0646"
    ],
    "wof:name":"Sayn",
    "wof:placetype":"locality"
},
  "geometry": {"coordinates":[64.29245999999999,33.34741],"type":"Point"}
}