{
  "type": "Feature",
  "properties": {
    "gn:admin1_code":"09",
    "gn:admin2_code":"2705",
    "gn:asciiname":"Sayn",
    "gn:country_code":"AF",
    "gn:dem":2309,
    "gn:feature_class":"P",
    "gn:feature_code":"PPL",
    "gn:name":"Sayn",
    "gn:population":0,
    "gn:timezone":"Asia/Kabul",
    "iso:country":"AF",
    "name:und_x_variant":[
        "\u0633\u06cc\u0646"
    ],
    "wof:name":"Sayn",
    "wof:placetype":"locality"
},
  "geometry": {"coordinates":[64.29245999999999,33.34741],"type":"Point"}
}