{
  "type": "Feature",
  "properties": {
    "gn:admin1_code":"06",
    "gn:admin2_code":"2108",
    "gn:asciiname":"Qadirabad",
    "gn:country_code":"AF",
    "gn:dem":630,
    "gn:feature_class":"P",
    "gn:feature_code":"PPL",
    "gn:name":"Q\u0101dir\u0101b\u0101d",
    "gn:population":0,
    "gn:timezone":"Asia/Kabul",
    "iso:country":"AF",
    "name:und_x_variant":[
        "Q\u0101\u1e0fe\u1e5f Ab\u0101d",
        "Q\u0101dir\u0101b\u0101d",
        "\u0642\u0627\u062f\u0631 \u0622\u0628\u0627\u062f",
        "Q\u0101der\u0101b\u0101d"
    ],
    "wof:name":"Qadirabad",
    "wof:placetype":"locality"
},
  "geometry": {"coordinates":[61.49278,32.3871],"type":"Point"}
}