{
  "type": "Feature",
  "properties": {
    "gn:admin1_code":"14",
    "gn:admin2_code":"206",
    "gn:asciiname":"Dawud Khel",
    "gn:country_code":"AF",
    "gn:dem":2630,
    "gn:feature_class":"P",
    "gn:feature_code":"PPL",
    "gn:name":"D\u0101w\u016bd Kh\u0113l",
    "gn:population":0,
    "gn:timezone":"Asia/Kabul",
    "iso:country":"AF",
    "name:fas_x_preferred":[
        "\u062f\u0627\u0648\u0648\u062f \u062e\u064a\u0644"
    ],
    "name:rus_x_preferred":[
        "Davudkheyl\u2019"
    ],
    "name:und_x_variant":[
        "D\u0101vodkheyl",
        "\u1e0e\u0101w\u016b\u1e0fkh\u0113l",
        "D\u0101v\u016bdkheyl",
        "D\u0101w\u016bd Kh\u0113l",
        "\u062f\u0627\u0648\u0648\u062f \u062e\u06d0\u0644"
    ],
    "wof:name":"Dawud Khel",
    "wof:placetype":"locality"
},
  "geometry": {"coordinates":[69.86224,34.90052],"type":"Point"}
}