{
  "type": "Feature",
  "properties": {
    "gn:admin1_code":"18",
    "gn:admin2_code":"816.0",
    "gn:asciiname":"Zheray",
    "gn:country_code":"AF",
    "gn:dem":664,
    "gn:feature_class":"P",
    "gn:feature_code":"PPL",
    "gn:name":"Zh\u0113\u1e5fay",
    "gn:population":0,
    "gn:timezone":"Asia/Kabul",
    "iso:country":"AF",
    "name:fas_x_preferred":[
        "\u0698\u064a\u0631\u06cc"
    ],
    "name:und_x_variant":[
        "Zeray",
        "\u017d\u0113ray",
        "Zh\u0113ray",
        "Zh\u0113\u1e5fay",
        "\u0698\u06d0\u0693\u06cc"
    ],
    "wof:name":"Zheray",
    "wof:placetype":"locality"
},
  "geometry": {"coordinates":[70.82916999999998,34.42716],"type":"Point"}
}