{
  "type": "Feature",
  "properties": {
    "gn:admin1_code":"03",
    "gn:admin2_code":"1308.0",
    "gn:asciiname":"Dashtak",
    "gn:country_code":"AF",
    "gn:dem":1788,
    "gn:feature_class":"P",
    "gn:feature_code":"PPL",
    "gn:name":"Dashtak",
    "gn:population":0,
    "gn:timezone":"Asia/Kabul",
    "iso:country":"AF",
    "name:ceb_x_preferred":[
        "Dashtak"
    ],
    "name:swe_x_preferred":[
        "Dashtak"
    ],
    "name:und_x_variant":[
        "\u1e0eastak",
        "Dashtak",
        "\u062f\u0634\u062a\u06a9"
    ],
    "wof:name":"Dashtak",
    "wof:placetype":"locality"
},
  "geometry": {"coordinates":[69.55457,35.92381],"type":"Point"}
}