{
  "type": "Feature",
  "properties": {
    "gn:admin1_code":"11",
    "gn:admin2_code":"2010.0",
    "gn:asciiname":"Jigdah",
    "gn:country_code":"AF",
    "gn:dem":1423,
    "gn:feature_class":"P",
    "gn:feature_code":"PPL",
    "gn:name":"J\u012bgdah",
    "gn:population":0,
    "gn:timezone":"Asia/Kabul",
    "iso:country":"AF",
    "name:und_x_variant":[
        "Jig\u1e0fa",
        "J\u012bgdah",
        "\u062c\u06cc\u06af\u062f\u0647",
        "Jig\u1e0fah"
    ],
    "wof:name":"Jigdah",
    "wof:placetype":"locality"
},
  "geometry": {"coordinates":[61.92283000000001,34.72311],"type":"Point"}
}