{
  "type": "Feature",
  "properties": {
    "gn:admin1_code":"23",
    "gn:admin2_code":"2411",
    "gn:asciiname":"Jowharzai",
    "gn:country_code":"AF",
    "gn:dem":1353,
    "gn:feature_class":"P",
    "gn:feature_code":"PPL",
    "gn:name":"Jowharza\u012b",
    "gn:population":0,
    "gn:timezone":"Asia/Kabul",
    "iso:country":"AF",
    "name:und_x_variant":[
        "Dzhaukharzai",
        "Jawha\u1e5fza\u2019i",
        "Jowharza\u012b",
        "Jawharzay",
        "\u062c\u0648\u0647\u0631\u0632\u06cc"
    ],
    "wof:name":"Jowharzai",
    "wof:placetype":"locality"
},
  "geometry": {"coordinates":[66.51236,31.23815],"type":"Point"}
}