{
  "type": "Feature",
  "properties": {
    "gn:admin1_code":"33",
    "gn:admin2_code":"3105",
    "gn:asciiname":"Panich",
    "gn:country_code":"AF",
    "gn:dem":1092,
    "gn:feature_class":"P",
    "gn:feature_code":"PPL",
    "gn:name":"P\u0101nich",
    "gn:population":0,
    "gn:timezone":"Asia/Kabul",
    "iso:country":"AF",
    "name:und_x_variant":[
        "Apanuch",
        "P\u0101nec",
        "Apanueh",
        "Pakandeh",
        "P\u0101nech",
        "P\u0101nich",
        "\u067e\u0627\u0646\u0686"
    ],
    "wof:name":"Panich",
    "wof:placetype":"locality"
},
  "geometry": {"coordinates":[66.20322,35.92778],"type":"Point"}
}