{
  "type": "Feature",
  "properties": {
    "gn:admin1_code":"8",
    "gn:admin2_code":"609.0",
    "gn:asciiname":"Shimulzi",
    "gn:country_code":"AF",
    "gn:dem":1957,
    "gn:feature_class":"P",
    "gn:feature_code":"PPL",
    "gn:name":"Shimulz\u012b",
    "gn:population":0,
    "gn:timezone":"Asia/Kabul",
    "iso:country":"AF",
    "name:rus_x_preferred":[
        "Shimul\u2019zi"
    ],
    "name:und_x_variant":[
        "\u0160emulzi",
        "Shemolz\u012b",
        "Shimulz\u012b",
        "\u0634\u0645\u0644 \u0632\u06cc"
    ],
    "wof:name":"Shimulzi",
    "wof:placetype":"locality"
},
  "geometry": {"coordinates":[67.78261999999999,32.68724],"type":"Point"}
}