{
  "type": "Feature",
  "properties": {
    "gn:admin1_code":"09",
    "gn:admin2_code":"2705",
    "gn:asciiname":"Zilirgak",
    "gn:country_code":"AF",
    "gn:dem":2200,
    "gn:feature_class":"P",
    "gn:feature_code":"PPL",
    "gn:name":"Zilirgak",
    "gn:population":0,
    "gn:timezone":"Asia/Kabul",
    "iso:country":"AF",
    "name:und_x_variant":[
        "Z\u012bler Gak",
        "Zilirgak",
        "\u0632\u0644\u0631\u06af\u06a9",
        "Zelergak"
    ],
    "wof:name":"Zilirgak",
    "wof:placetype":"locality"
},
  "geometry": {"coordinates":[64.35547,33.23],"type":"Point"}
}