{
  "type": "Feature",
  "properties": {
    "gn:admin1_code":"9",
    "gn:admin2_code":"2702.0",
    "gn:asciiname":"Dahan-e Marghah",
    "gn:country_code":"AF",
    "gn:dem":1734,
    "gn:feature_class":"P",
    "gn:feature_code":"PPL",
    "gn:name":"Dahan-e Marghah",
    "gn:population":0,
    "gn:timezone":"Asia/Kabul",
    "iso:country":"AF",
    "name:und_x_variant":[
        "\u1e0eahane Ma\u1e5fgha",
        "Dahan-e Marghah",
        "Dakhani-Marga",
        "Dahan-e Margheh",
        "\u062f\u0647\u0646 \u0645\u0631\u063a\u0647",
        "Dahanah-ye Morghah",
        "\u062f\u0647\u0646\u06c0 \u0645\u0631\u063a\u0647"
    ],
    "wof:name":"Dahan-e Marghah",
    "wof:placetype":"locality"
},
  "geometry": {"coordinates":[64.27534,34.37217],"type":"Point"}
}