{
  "type": "Feature",
  "properties": {
    "gn:admin1_code":"41",
    "gn:admin2_code":"3409.0",
    "gn:asciiname":"Khinjak",
    "gn:country_code":"AF",
    "gn:dem":1860,
    "gn:feature_class":"P",
    "gn:feature_code":"PPL",
    "gn:name":"Khinjak",
    "gn:population":0,
    "gn:timezone":"Asia/Kabul",
    "iso:country":"AF",
    "name:und_x_variant":[
        "\u062e\u0646\u062c\u06a9",
        "Khenjak"
    ],
    "wof:name":"Khinjak",
    "wof:placetype":"locality"
},
  "geometry": {"coordinates":[66.58189,33.64926],"type":"Point"}
}