{
  "type": "Feature",
  "properties": {
    "gn:admin1_code":"18",
    "gn:admin2_code":"803",
    "gn:asciiname":"Kilokas",
    "gn:country_code":"AF",
    "gn:dem":2062,
    "gn:feature_class":"P",
    "gn:feature_code":"PPL",
    "gn:name":"K\u012bl\u014dkas",
    "gn:population":0,
    "gn:timezone":"Asia/Kabul",
    "iso:country":"AF",
    "name:fas_x_preferred":[
        "\u0643\u0644\u0648\u0643\u0633"
    ],
    "name:und_x_variant":[
        "K\u012bl\u016b Kas",
        "Kilokas",
        "Kil\u014dkas",
        "Kilowkas",
        "\u0643\u0644\u0648\u0643\u0633",
        "K\u012bl\u014dkas",
        "\u06a9\u06cc\u0644\u0648 \u06a9\u0633"
    ],
    "wof:name":"Kilokas",
    "wof:placetype":"locality"
},
  "geometry": {"coordinates":[69.70040999999999,34.26454],"type":"Point"}
}