{
  "type": "Feature",
  "properties": {
    "gn:admin1_code":"10",
    "gn:admin2_code":"2305",
    "gn:asciiname":"Pay Jinjay",
    "gn:country_code":"AF",
    "gn:dem":1574,
    "gn:feature_class":"P",
    "gn:feature_code":"PPL",
    "gn:name":"P\u0101y Jinjay",
    "gn:population":0,
    "gn:timezone":"Asia/Kabul",
    "iso:country":"AF",
    "name:rus_x_preferred":[
        "\u041f\u0430\u0439\u0434\u0436\u0438\u043d\u0434\u0436\u0430\u0439"
    ],
    "name:und_x_variant":[
        "Paydzhindzhay",
        "P\u0101y Jinjay",
        "\u067e\u0627\u06cc \u062c\u0646\u062c\u06cc",
        "P\u0101y Jenjay"
    ],
    "wof:name":"Pay Jinjay",
    "wof:placetype":"locality"
},
  "geometry": {"coordinates":[65.05915,33.04952],"type":"Point"}
}