{
  "type": "Feature",
  "properties": {
    "gn:admin1_code":"28",
    "gn:admin2_code":"2505.0",
    "gn:asciiname":"Muhammad Anwar Kelay",
    "gn:country_code":"AF",
    "gn:dem":1397,
    "gn:feature_class":"P",
    "gn:feature_code":"PPL",
    "gn:name":"Mu\u1e29ammad Anwar K\u00ealay",
    "gn:population":0,
    "gn:timezone":"Asia/Kabul",
    "iso:country":"AF",
    "name:und_x_variant":[
        "Mukhammedanvar Kalay",
        "Mu\u1e29ammad Anwar K\u00ealay",
        "\u0645\u062d\u0645\u062f \u0627\u0646\u0648\u0631 \u06a9\u0644\u06cc",
        "Mo\u1e29ammad Anwar Kalay"
    ],
    "wof:name":"Muhammad Anwar Kelay",
    "wof:placetype":"locality"
},
  "geometry": {"coordinates":[66.49247,32.17649],"type":"Point"}
}