{
  "type": "Feature",
  "properties": {
    "gn:admin1_code":"23",
    "gn:admin2_code":"2412",
    "gn:asciiname":"Malik Khayro Karez",
    "gn:country_code":"AF",
    "gn:dem":1310,
    "gn:feature_class":"P",
    "gn:feature_code":"PPL",
    "gn:name":"Malik Khayr\u014d K\u0101r\u0113z",
    "gn:population":0,
    "gn:timezone":"Asia/Kabul",
    "iso:country":"AF",
    "name:und_x_variant":[
        "Malik-Khayru-Karez",
        "Malek Khay\u1e5fo K\u0101\u1e5f\u0113z",
        "Malik Khayr\u014d K\u0101r\u0113z",
        "\u0645\u0644\u06a9 \u062e\u06cc\u0631\u0648 \u06a9\u0627\u0631\u06d0\u0632",
        "Malek Khayro K\u0101r\u012bz"
    ],
    "wof:name":"Malik Khayro Karez",
    "wof:placetype":"locality"
},
  "geometry": {"coordinates":[66.41956999999999,31.64153],"type":"Point"}
}