{
  "type": "Feature",
  "properties": {
    "gn:admin1_code":"27",
    "gn:admin2_code":"404.0",
    "gn:asciiname":"Mian Deh",
    "gn:country_code":"AF",
    "gn:dem":3055,
    "gn:feature_class":"P",
    "gn:feature_code":"PPL",
    "gn:name":"M\u012b\u0101n Deh",
    "gn:population":0,
    "gn:timezone":"Asia/Kabul",
    "iso:country":"AF",
    "name:fas_x_preferred":[
        "\u0645\u06cc\u0627\u0646 \u062f\u0647"
    ],
    "name:und_x_variant":[
        "My\u0101n\u1e0feh",
        "Miandekh",
        "M\u012b\u0101n Deh"
    ],
    "wof:name":"Mian Deh",
    "wof:placetype":"locality"
},
  "geometry": {"coordinates":[67.79942,34.25205],"type":"Point"}
}