{
  "type": "Feature",
  "properties": {
    "gn:admin1_code":"09",
    "gn:admin2_code":"2707",
    "gn:asciiname":"Surkh Now",
    "gn:country_code":"AF",
    "gn:dem":2639,
    "gn:feature_class":"P",
    "gn:feature_code":"PPL",
    "gn:name":"Surkh Now",
    "gn:population":0,
    "gn:timezone":"Asia/Kabul",
    "iso:country":"AF",
    "name:und_x_variant":[
        "Surkhnau",
        "Sorkh N\u0101v",
        "Su\u1e5fkhnaw",
        "Sorkhn\u0101w",
        "Surkh Now",
        "\u0633\u0631\u062e \u0646\u0648"
    ],
    "wof:name":"Surkh Now",
    "wof:placetype":"locality"
},
  "geometry": {"coordinates":[66.10361999999999,34.59970999999999],"type":"Point"}
}