{
  "type": "Feature",
  "properties": {
    "gn:admin1_code":"06",
    "gn:admin2_code":"2102",
    "gn:asciiname":"Nazargah",
    "gn:country_code":"AF",
    "gn:dem":732,
    "gn:feature_class":"P",
    "gn:feature_code":"PPL",
    "gn:name":"Naz\u0327arg\u0101h",
    "gn:population":0,
    "gn:timezone":"Asia/Kabul",
    "iso:country":"AF",
    "name:fas_x_preferred":[
        "\u0646\u0638\u0631\u06af\u0627\u0647"
    ],
    "name:und_x_variant":[
        "Nazargakh",
        "Naz\u0327arg\u0101h"
    ],
    "wof:name":"Nazargah",
    "wof:placetype":"locality"
},
  "geometry": {"coordinates":[63.04056,32.18287],"type":"Point"}
}