{
  "type": "Feature",
  "properties": {
    "gn:admin1_code":"23",
    "gn:admin2_code":"2403.0",
    "gn:asciiname":"Piro Khan",
    "gn:country_code":"AF",
    "gn:dem":1399,
    "gn:feature_class":"P",
    "gn:feature_code":"PPL",
    "gn:name":"Pir\u014d Kh\u0101n",
    "gn:population":0,
    "gn:timezone":"Asia/Kabul",
    "iso:country":"AF",
    "name:fas_x_preferred":[
        "\u067e\u064a\u0631\u0648 \u062e\u0627\u0646"
    ],
    "name:und_x_variant":[
        "Pirokhan",
        "Pi\u1e5f\u014dkh\u0101n",
        "Pir\u014d Kh\u0101n",
        "\u067e\u0631\u0648 \u062e\u0627\u0646",
        "Pi\u1e5fow Kh\u0101n"
    ],
    "wof:name":"Piro Khan",
    "wof:placetype":"locality"
},
  "geometry": {"coordinates":[65.86988000000001,32.10015],"type":"Point"}
}