{
  "type": "Feature",
  "properties": {
    "gn:admin1_code":"29",
    "gn:admin2_code":"2905.0",
    "gn:asciiname":"Num Rizay",
    "gn:country_code":"AF",
    "gn:dem":2028,
    "gn:feature_class":"P",
    "gn:feature_code":"PPL",
    "gn:name":"N\u016bm R\u012bzay",
    "gn:population":0,
    "gn:timezone":"Asia/Kabul",
    "iso:country":"AF",
    "name:und_x_variant":[
        "Numrizay",
        "N\u016bm R\u012bzay",
        "\u0646\u0648\u0645 \u0631\u064a\u0632\u06cc"
    ],
    "wof:name":"Num Rizay",
    "wof:placetype":"locality"
},
  "geometry": {"coordinates":[68.87917,31.92917000000001],"type":"Point"}
}