{
  "type": "Feature",
  "properties": {
    "gn:admin1_code":"11",
    "gn:admin2_code":"2013",
    "gn:asciiname":"Maymand",
    "gn:country_code":"AF",
    "gn:dem":2177,
    "gn:feature_class":"P",
    "gn:feature_code":"PPL",
    "gn:name":"Maymand",
    "gn:population":0,
    "gn:timezone":"Asia/Kabul",
    "iso:country":"AF",
    "name:und_x_variant":[
        "Mayman\u1e0f",
        "Maymand",
        "\u0645\u06cc\u0645\u0646\u062f",
        "Meymand"
    ],
    "wof:name":"Maymand",
    "wof:placetype":"locality"
},
  "geometry": {"coordinates":[63.16708000000001,33.74271],"type":"Point"}
}