{
  "type": "Feature",
  "properties": {
    "gn:admin1_code":"28",
    "gn:admin2_code":"2503.0",
    "gn:asciiname":"Mulla Qiamuddin Chambar",
    "gn:country_code":"AF",
    "gn:dem":1599,
    "gn:feature_class":"P",
    "gn:feature_code":"PPL",
    "gn:name":"Mull\u0101 Q\u012b\u0101mudd\u012bn Ch\u0101mbar",
    "gn:population":0,
    "gn:timezone":"Asia/Kabul",
    "iso:country":"AF",
    "name:fas_x_preferred":[
        "\u0645\u0644\u0627 \u0642\u064a\u0627\u0645 \u0627\u0644\u062f\u064a\u0646 \u0686\u0645\u0628\u0631"
    ],
    "name:und_x_variant":[
        "Mulla-Kiamuddin-Chambar",
        "Mull\u0101 Qy\u0101mu\u1e0f\u1e0f\u012bn Camba\u1e5f",
        "Mull\u0101 Q\u012b\u0101mudd\u012bn Ch\u0101mbar",
        "\u0645\u0644\u0627 \u0641\u06cc\u0627\u0645 \u0627\u0644\u062f\u06cc\u0646 \u0686\u0627\u0645\u0628\u0631",
        "Moll\u0101 Q\u012b\u0101m od D\u012bn Chambar"
    ],
    "wof:name":"Mulla Qiamuddin Chambar",
    "wof:placetype":"locality"
},
  "geometry": {"coordinates":[66.8917,32.4492],"type":"Point"}
}