{
  "type": "Feature",
  "properties": {
    "gn:admin1_code":"13",
    "gn:admin2_code":"114.0",
    "gn:asciiname":"Qal'ah-ye 'Abdul Ra'uf",
    "gn:country_code":"AF",
    "gn:dem":1827,
    "gn:feature_class":"P",
    "gn:feature_code":"PPL",
    "gn:name":"Qal\u2018ah-ye \u2018Abdul Ra\u2019\u016bf",
    "gn:population":0,
    "gn:timezone":"Asia/Kabul",
    "iso:country":"AF",
    "name:und_x_variant":[
        "Kala-Abdurrauf",
        "Qal\u2018eh-ye Abdurra\u2019\u016bf",
        "Qal\u2018eh Ab\u1e0fu\u1e5f\u1e5fa\u2019\u016bf",
        "Qal\u2018ah-ye \u2018Abdul Ra\u2019\u016bf",
        "Qal\u2018eh-ye \u2018Abd or Ra\u2019\u016bf",
        "Qal\u2018ah-ye \u2018Abd ur Ra\u2019\u016bf",
        "\u0642\u0644\u0639\u0647 \u0639\u0628\u062f\u0644 \u0631\u0639\u0648\u0641",
        "\u0642\u0644\u0639\u0647 \u0639\u0628\u062f\u0644 \u0631\u0624\u0648\u0641"
    ],
    "wof:name":"Qal'ah-ye 'Abdul Ra'uf",
    "wof:placetype":"locality"
},
  "geometry": {"coordinates":[69.21695,34.36676],"type":"Point"}
}