{
  "type": "Feature",
  "properties": {
    "gn:admin1_code":"26",
    "gn:admin2_code":"1208.0",
    "gn:asciiname":"Bolokah",
    "gn:country_code":"AF",
    "gn:dem":577,
    "gn:feature_class":"P",
    "gn:feature_code":"PPL",
    "gn:name":"B\u014dl\u014dkah",
    "gn:population":0,
    "gn:timezone":"Asia/Kabul",
    "iso:country":"AF",
    "name:und_x_variant":[
        "B\u014dl\u014dka",
        "B\u016bl\u016bkah",
        "B\u014dl\u014dkah",
        "\u0628\u0648\u0644\u0648\u06a9\u0647"
    ],
    "wof:name":"Bolokah",
    "wof:placetype":"locality"
},
  "geometry": {"coordinates":[69.58873,37.00763],"type":"Point"}
}