{
  "type": "Feature",
  "properties": {
    "gn:admin1_code":"10",
    "gn:admin2_code":"2304.0",
    "gn:asciiname":"Chinahgay",
    "gn:country_code":"AF",
    "gn:dem":1291,
    "gn:feature_class":"P",
    "gn:feature_code":"PPL",
    "gn:name":"Ch\u012bnahgay",
    "gn:population":0,
    "gn:timezone":"Asia/Kabul",
    "iso:country":"AF",
    "name:und_x_variant":[
        "Chanagay",
        "\u010c\u012bnagay",
        "Ch\u012bnahgay",
        "\u0686\u06cc\u0646\u0647\u06af\u06cc"
    ],
    "wof:name":"Chinahgay",
    "wof:placetype":"locality"
},
  "geometry": {"coordinates":[64.68195,32.67837],"type":"Point"}
}