{
  "type": "Feature",
  "properties": {
    "gn:admin1_code":"11",
    "gn:admin2_code":"2004",
    "gn:asciiname":"Gawash",
    "gn:country_code":"AF",
    "gn:dem":1070,
    "gn:feature_class":"P",
    "gn:feature_code":"PPL",
    "gn:name":"Gawash",
    "gn:population":0,
    "gn:timezone":"Asia/Kabul",
    "iso:country":"AF",
    "name:und_x_variant":[
        "Gawa\u0161",
        "Gawash",
        "Gavash",
        "G\u0101vash",
        "\u06af\u0648\u0634",
        "G\u0101wash",
        "\u06af\u0627\u0648\u0634"
    ],
    "wof:name":"Gawash",
    "wof:placetype":"locality"
},
  "geometry": {"coordinates":[62.65855,34.28658],"type":"Point"}
}