{
  "type": "Feature",
  "properties": {
    "gn:admin1_code":"5",
    "gn:admin2_code":"2806.0",
    "gn:asciiname":"Dilbinak",
    "gn:country_code":"AF",
    "gn:dem":2490,
    "gn:feature_class":"P",
    "gn:feature_code":"PPL",
    "gn:name":"Dilb\u012bnak",
    "gn:population":0,
    "gn:timezone":"Asia/Kabul",
    "iso:country":"AF",
    "name:und_x_variant":[
        "Dilb\u012bnak",
        "\u062f\u0644\u0628\u06cc\u0646\u06a9",
        "Delb\u012bnak"
    ],
    "wof:name":"Dilbinak",
    "wof:placetype":"locality"
},
  "geometry": {"coordinates":[67.01443,33.94336],"type":"Point"}
}