{
  "type": "Feature",
  "properties": {
    "gn:admin1_code":"32",
    "gn:admin2_code":"1501",
    "gn:asciiname":"Royanchah",
    "gn:country_code":"AF",
    "gn:dem":1741,
    "gn:feature_class":"P",
    "gn:feature_code":"PPL",
    "gn:name":"R\u014dy\u0101nchah",
    "gn:population":0,
    "gn:timezone":"Asia/Kabul",
    "iso:country":"AF",
    "name:und_x_variant":[
        "Royancha (2)",
        "Royanchah",
        "R\u014dy\u0101nchah",
        "\u0631\u0648\u06cc\u0627\u0646\u0686\u0647"
    ],
    "wof:name":"Royanchah",
    "wof:placetype":"locality"
},
  "geometry": {"coordinates":[67.82004000000001,36.14235],"type":"Point"}
}