{
  "type": "Feature",
  "properties": {
    "gn:admin1_code":"07",
    "gn:admin2_code":"1803",
    "gn:asciiname":"Surf 'Ali",
    "gn:country_code":"AF",
    "gn:dem":924,
    "gn:feature_class":"P",
    "gn:feature_code":"PPL",
    "gn:name":"Surf \u2018Al\u012b",
    "gn:population":0,
    "gn:timezone":"Asia/Kabul",
    "iso:country":"AF",
    "name:und_x_variant":[
        "Surf \u2018Al\u012b",
        "\u0633\u0631\u0641 \u0639\u0644\u06cc",
        "Su\u1e5ff \u2018Ali"
    ],
    "wof:name":"Surf 'Ali",
    "wof:placetype":"locality"
},
  "geometry": {"coordinates":[64.53261999999999,35.8077],"type":"Point"}
}