{
  "type": "Feature",
  "properties": {
    "gn:admin1_code":"27",
    "gn:admin2_code":"408.0",
    "gn:asciiname":"Qal'ah-ye Muhammad Jan",
    "gn:country_code":"AF",
    "gn:dem":2484,
    "gn:feature_class":"P",
    "gn:feature_code":"PPL",
    "gn:name":"Qal\u2018ah-ye Mu\u1e29ammad J\u0101n",
    "gn:population":0,
    "gn:timezone":"Asia/Kabul",
    "iso:country":"AF",
    "name:und_x_variant":[
        "Qal\u2018a-i-Mo\u1e29amme\u1e0f-j\u0101n",
        "Kalayi-Mukhammeddzhan",
        "Qal\u2018ah-ye Mu\u1e29ammad J\u0101n",
        "Qal\u2018eh-ye Mo\u1e29ammad J\u0101n",
        "\u0642\u0644\u0639\u0647 \u0645\u062d\u0645\u062f \u062c\u0627\u0646"
    ],
    "wof:name":"Qal'ah-ye Muhammad Jan",
    "wof:placetype":"locality"
},
  "geometry": {"coordinates":[68.72496,34.32282],"type":"Point"}
}