{
  "type": "Feature",
  "properties": {
    "gn:admin1_code":"41",
    "gn:admin2_code":"3408.0",
    "gn:asciiname":"Aboli",
    "gn:country_code":"AF",
    "gn:dem":2670,
    "gn:feature_class":"P",
    "gn:feature_code":"PPL",
    "gn:name":"Ab\u014dl\u012b",
    "gn:population":0,
    "gn:timezone":"Asia/Kabul",
    "iso:country":"AF",
    "name:und_x_variant":[
        "Abuli",
        "Ab\u014dl\u012b",
        "Abol\u012b",
        "\u0627\u0628\u0648\u0644\u06cc"
    ],
    "wof:name":"Aboli",
    "wof:placetype":"locality"
},
  "geometry": {"coordinates":[66.07164,34.25954],"type":"Point"}
}