{
  "type": "Feature",
  "properties": {
    "gn:admin1_code":"9",
    "gn:admin2_code":"2707.0",
    "gn:asciiname":"Altatu",
    "gn:country_code":"AF",
    "gn:dem":2841,
    "gn:feature_class":"P",
    "gn:feature_code":"PPL",
    "gn:name":"Altat\u016b",
    "gn:population":0,
    "gn:timezone":"Asia/Kabul",
    "iso:country":"AF",
    "name:ara_x_preferred":[
        "\u0627\u0644\u062a\u0627\u062a\u0648"
    ],
    "name:ceb_x_preferred":[
        "Alt\u0101t\u016b"
    ],
    "name:fas_x_preferred":[
        "\u0627\u0644\u062a\u0627\u062a\u0648"
    ],
    "name:rus_x_preferred":[
        "Al\u2019tatu"
    ],
    "name:swe_x_preferred":[
        "Alt\u0101t\u016b"
    ],
    "name:und_x_variant":[
        "Altat\u016b",
        "\u0627\u0644\u062a\u062a\u0648"
    ],
    "wof:name":"Altatu",
    "wof:placetype":"locality"
},
  "geometry": {"coordinates":[66.06671,34.39550999999999],"type":"Point"}
}