{
  "type": "Feature",
  "properties": {
    "gn:admin1_code":"11",
    "gn:admin2_code":"2005",
    "gn:asciiname":"Hamam",
    "gn:country_code":"AF",
    "gn:dem":2249,
    "gn:feature_class":"P",
    "gn:feature_code":"PPL",
    "gn:name":"\u1e28am\u0101m",
    "gn:population":0,
    "gn:timezone":"Asia/Kabul",
    "iso:country":"AF",
    "name:und_x_variant":[
        "Khamam",
        "Ham\u0101n",
        "\u1e28am\u0101m",
        "\u062d\u0645\u0627\u0645"
    ],
    "wof:name":"Hamam",
    "wof:placetype":"locality"
},
  "geometry": {"coordinates":[63.14456,34.59533],"type":"Point"}
}