{
  "type": "Feature",
  "properties": {
    "gn:admin1_code":"06",
    "gn:admin2_code":"2104",
    "gn:asciiname":"Pirayshti",
    "gn:country_code":"AF",
    "gn:dem":1983,
    "gn:feature_class":"P",
    "gn:feature_code":"PPL",
    "gn:name":"Piraysht\u012b",
    "gn:population":0,
    "gn:timezone":"Asia/Kabul",
    "iso:country":"AF",
    "name:und_x_variant":[
        "Pe\u1e5fays\u0304ti",
        "Piraysht\u012b",
        "\u067e\u0631\u06cc\u0634\u062a\u06cc",
        "Pe\u1e5faysht\u012b"
    ],
    "wof:name":"Pirayshti",
    "wof:placetype":"locality"
},
  "geometry": {"coordinates":[63.86896,33.38752],"type":"Point"}
}