{
  "type": "Feature",
  "properties": {
    "gn:admin1_code":"27",
    "gn:admin2_code":"409",
    "gn:asciiname":"Dilawar Khel",
    "gn:country_code":"AF",
    "gn:dem":2551,
    "gn:feature_class":"P",
    "gn:feature_code":"PPL",
    "gn:name":"Dil\u0101war Kh\u0113l",
    "gn:population":0,
    "gn:timezone":"Asia/Kabul",
    "iso:country":"AF",
    "name:fas_x_preferred":[
        "\u062f\u0644\u0627\u0648\u0631 \u062e\u064a\u0644"
    ],
    "name:rus_x_preferred":[
        "Dilavarkheyl\u2019"
    ],
    "name:und_x_variant":[
        "\u1e0eel\u0101wa\u1e5fkh\u0113l",
        "Del\u0101war Kh\u0113l",
        "Del\u0101var Kheyl",
        "\u062f\u0644\u0627\u0648\u0631 \u062e\u064a\u0644",
        "Dil\u0101war Kh\u0113l",
        "\u062f\u0644\u0627\u0648\u0631 \u062e\u06d0\u0644"
    ],
    "wof:name":"Dilawar Khel",
    "wof:placetype":"locality"
},
  "geometry": {"coordinates":[68.31086999999999,33.72316],"type":"Point"}
}