{
  "type": "Feature",
  "properties": {
    "gn:admin1_code":"05",
    "gn:admin2_code":"2802",
    "gn:asciiname":"Espi Sang",
    "gn:country_code":"AF",
    "gn:dem":2974,
    "gn:feature_class":"P",
    "gn:feature_code":"PPL",
    "gn:name":"Esp\u012b Sang",
    "gn:population":0,
    "gn:timezone":"Asia/Kabul",
    "iso:country":"AF",
    "name:und_x_variant":[
        "Esp\u012b Sang",
        "\u0627\u0633\u067e\u06cc \u0633\u0646\u06af"
    ],
    "wof:name":"Espi Sang",
    "wof:placetype":"locality"
},
  "geometry": {"coordinates":[67.96339,35.02396],"type":"Point"}
}