{
  "type": "Feature",
  "properties": {
    "gn:admin1_code":"41",
    "gn:admin2_code":"3403",
    "gn:asciiname":"Ilaso",
    "gn:country_code":"AF",
    "gn:dem":2902,
    "gn:feature_class":"P",
    "gn:feature_code":"PPL",
    "gn:name":"Ilas\u014d",
    "gn:population":0,
    "gn:timezone":"Asia/Kabul",
    "iso:country":"AF",
    "name:und_x_variant":[
        "Ilas\u014d",
        "\u0627\u0644\u0633\u0648",
        "Elaso"
    ],
    "wof:name":"Ilaso",
    "wof:placetype":"locality"
},
  "geometry": {"coordinates":[66.38516,33.96498],"type":"Point"}
}