{
  "type": "Feature",
  "properties": {
    "gn:admin1_code":"17",
    "gn:admin2_code":"503.0",
    "gn:asciiname":"Baburi",
    "gn:country_code":"AF",
    "gn:dem":1926,
    "gn:feature_class":"P",
    "gn:feature_code":"PPL",
    "gn:name":"B\u0101bur\u012b",
    "gn:population":0,
    "gn:timezone":"Asia/Kabul",
    "iso:country":"AF",
    "name:und_x_variant":[
        "B\u0101bur\u012b",
        "\u0628\u0627\u0628\u0631\u06cc"
    ],
    "wof:name":"Baburi",
    "wof:placetype":"locality"
},
  "geometry": {"coordinates":[68.97389,33.95978],"type":"Point"}
}