{
  "type": "Feature",
  "properties": {
    "gn:admin1_code":"28",
    "gn:admin2_code":"2508.0",
    "gn:asciiname":"Qaryah-ye Wardak Ha",
    "gn:country_code":"AF",
    "gn:dem":1833,
    "gn:feature_class":"P",
    "gn:feature_code":"PPL",
    "gn:name":"Qaryah-ye Wardak H\u0101",
    "gn:population":0,
    "gn:timezone":"Asia/Kabul",
    "iso:country":"AF",
    "name:rus_x_preferred":[
        "Kar\u2019yayi-Vardakkha"
    ],
    "name:und_x_variant":[
        "Qarya-i-Wa\u1e5f\u1e0fak-h\u0101",
        "Qaryah-ye Wardak H\u0101",
        "\u0642\u0631\u06cc\u0647 \u0648\u0631\u062f\u06a9 \u0647\u0627",
        "Qar\u012byeh-e Wardak-h\u0101"
    ],
    "wof:name":"Qaryah-ye Wardak Ha",
    "wof:placetype":"locality"
},
  "geometry": {"coordinates":[67.37289,31.7537],"type":"Point"}
}