{
  "type": "Feature",
  "properties": {
    "gn:admin1_code":"31",
    "gn:admin2_code":"1708",
    "gn:asciiname":"Faizabad",
    "gn:country_code":"AF",
    "gn:dem":312,
    "gn:feature_class":"P",
    "gn:feature_code":"PPLA2",
    "gn:name":"Fa\u012b\u1e95\u0101b\u0101d",
    "gn:population":0,
    "gn:timezone":"Asia/Kabul",
    "iso:country":"AF",
    "name:und_x_variant":[
        "Fay\u1e0f\u1e95\u0101b\u0101\u1e0f",
        "F\u0101zil\u0101b\u0101d",
        "Faiz\u0101b\u0101d",
        "Fey\u1e95\u0101b\u0101d",
        "Fa\u012b\u1e95\u0101b\u0101d",
        "\u0641\u06cc\u0636 \u0622\u0628\u0627\u062f"
    ],
    "wof:name":"Faizabad",
    "wof:placetype":"locality"
},
  "geometry": {"coordinates":[66.45921,36.82091],"type":"Point"}
}