{
  "type": "Feature",
  "properties": {
    "gn:admin1_code":"37",
    "gn:admin2_code":"3213.0",
    "gn:asciiname":"Khalwati",
    "gn:country_code":"AF",
    "gn:dem":1553,
    "gn:feature_class":"P",
    "gn:feature_code":"PPL",
    "gn:name":"Khalw\u0101t\u012b",
    "gn:population":0,
    "gn:timezone":"Asia/Kabul",
    "iso:country":"AF",
    "name:fas_x_preferred":[
        "\u062e\u0644\u0648\u0627\u062a\u06cc"
    ],
    "name:rus_x_preferred":[
        "Khal\u2019vati"
    ],
    "name:und_x_variant":[
        "Khalw\u0101ti",
        "Khalw\u0101t\u012b",
        "Khalvat\u012b"
    ],
    "wof:name":"Khalwati",
    "wof:placetype":"locality"
},
  "geometry": {"coordinates":[69.58275,33.28272],"type":"Point"}
}