{
  "type": "Feature",
  "properties": {
    "gn:admin1_code":"8",
    "gn:admin2_code":"608.0",
    "gn:asciiname":"Karezgay",
    "gn:country_code":"AF",
    "gn:dem":2211,
    "gn:feature_class":"P",
    "gn:feature_code":"PPL",
    "gn:name":"K\u0101r\u0113zgay",
    "gn:population":0,
    "gn:timezone":"Asia/Kabul",
    "iso:country":"AF",
    "name:und_x_variant":[
        "K\u0101\u1e5f\u0113zgay",
        "K\u0101r\u0113zgay",
        "\u06a9\u0627\u0631\u06d0\u0632\u06af\u06cc",
        "K\u0101r\u012bzgay"
    ],
    "wof:name":"Karezgay",
    "wof:placetype":"locality"
},
  "geometry": {"coordinates":[67.76586999999999,32.97445],"type":"Point"}
}