{
  "type": "Feature",
  "properties": {
    "gn:admin1_code":"41",
    "gn:admin2_code":"3408.0",
    "gn:asciiname":"Khar Bayd",
    "gn:country_code":"AF",
    "gn:dem":2727,
    "gn:feature_class":"P",
    "gn:feature_code":"PPL",
    "gn:name":"Khar Bayd",
    "gn:population":0,
    "gn:timezone":"Asia/Kabul",
    "iso:country":"AF",
    "name:und_x_variant":[
        "Kha\u1e5fb\u0113\u1e0f",
        "Kharbed",
        "Khar Bayd",
        "Kharb\u012bd",
        "\u062e\u0631 \u0628\u064a\u062f"
    ],
    "wof:name":"Khar Bayd",
    "wof:placetype":"locality"
},
  "geometry": {"coordinates":[66.01931,34.15819],"type":"Point"}
}