{
  "type": "Feature",
  "properties": {
    "gn:admin1_code":"08",
    "gn:admin2_code":"613",
    "gn:asciiname":"Nalah-ye Khord",
    "gn:country_code":"AF",
    "gn:dem":2597,
    "gn:feature_class":"P",
    "gn:feature_code":"PPL",
    "gn:name":"N\u0101lah-ye Kh\u014drd",
    "gn:population":0,
    "gn:timezone":"Asia/Kabul",
    "iso:country":"AF",
    "name:fas_x_preferred":[
        "\u0646\u0627\u0644\u06c0 \u062e\u0631\u062f"
    ],
    "name:rus_x_preferred":[
        "\u041d\u0430\u043b\u0430\u0439\u0438-\u0425\u0443\u0440\u0434"
    ],
    "name:und_x_variant":[
        "N\u0101la-i-Khu\u1e5f\u1e0f",
        "Nalayi-Khurd",
        "N\u0101lah-e Khord",
        "N\u0101lah-ye Kh\u014drd",
        "\u0646\u0627\u0644\u06c0 \u062e\u0648\u0631\u062f"
    ],
    "wof:name":"Nalah-ye Khord",
    "wof:placetype":"locality"
},
  "geometry": {"coordinates":[67.73025,33.16185],"type":"Point"}
}