{
  "type": "Feature",
  "properties": {
    "gn:admin1_code":"27",
    "gn:admin2_code":"408.0",
    "gn:asciiname":"Qol-e Aka",
    "gn:country_code":"AF",
    "gn:dem":2644,
    "gn:feature_class":"P",
    "gn:feature_code":"PPL",
    "gn:name":"Q\u014dl-e \u0100k\u0101",
    "gn:population":0,
    "gn:timezone":"Asia/Kabul",
    "iso:country":"AF",
    "name:und_x_variant":[
        "Q\u014dle \u0100k\u0101",
        "Kuli-Aka",
        "Q\u014dl-e \u0100k\u0101",
        "Qowl-e \u0100k\u0101",
        "\u0642\u0648\u0644 \u0622\u06a9\u0627"
    ],
    "wof:name":"Qol-e Aka",
    "wof:placetype":"locality"
},
  "geometry": {"coordinates":[68.63365,34.36349000000001],"type":"Point"}
}