{
  "type": "Feature",
  "properties": {
    "gn:admin1_code":"35",
    "gn:admin2_code":"904.0",
    "gn:asciiname":"Chandal",
    "gn:country_code":"AF",
    "gn:dem":1658,
    "gn:feature_class":"P",
    "gn:feature_code":"PPL",
    "gn:name":"Chand\u0101l",
    "gn:population":0,
    "gn:timezone":"Asia/Kabul",
    "iso:country":"AF",
    "name:rus_x_preferred":[
        "Chandal\u2019"
    ],
    "name:und_x_variant":[
        "\u010cand\u0101l",
        "Chand\u0101l",
        "\u0686\u0646\u062f\u0627\u0644"
    ],
    "wof:name":"Chandal",
    "wof:placetype":"locality"
},
  "geometry": {"coordinates":[70.04388,34.96355],"type":"Point"}
}