{
  "type": "Feature",
  "properties": {
    "gn:admin1_code":"41",
    "gn:admin2_code":"3403.0",
    "gn:asciiname":"Awgak",
    "gn:country_code":"AF",
    "gn:dem":2332,
    "gn:feature_class":"P",
    "gn:feature_code":"PPL",
    "gn:name":"Awgak",
    "gn:population":0,
    "gn:timezone":"Asia/Kabul",
    "iso:country":"AF",
    "name:und_x_variant":[
        "\u0627\u0648\u06af\u06a9"
    ],
    "wof:name":"Awgak",
    "wof:placetype":"locality"
},
  "geometry": {"coordinates":[66.22842,33.89237],"type":"Point"}
}