{
  "type": "Feature",
  "properties": {
    "gn:admin1_code":"23",
    "gn:admin2_code":"2411.0",
    "gn:asciiname":"'Alam Khanzi",
    "gn:country_code":"AF",
    "gn:dem":1294,
    "gn:feature_class":"P",
    "gn:feature_code":"PPL",
    "gn:name":"\u2018Alam Kh\u0101nz\u012b",
    "gn:population":0,
    "gn:timezone":"Asia/Kabul",
    "iso:country":"AF",
    "name:und_x_variant":[
        "\u2018Alam Kh\u0101nz\u012b",
        "\u0639\u0644\u0645 \u062e\u0627\u0646\u0632\u06cc",
        "\u2018Alamkh\u0101nzi"
    ],
    "wof:name":"'Alam Khanzi",
    "wof:placetype":"locality"
},
  "geometry": {"coordinates":[66.46146999999999,31.18222],"type":"Point"}
}