{
  "type": "Feature",
  "properties": {
    "gn:admin1_code":"9",
    "gn:admin2_code":"2707.0",
    "gn:asciiname":"Khosh Now",
    "gn:country_code":"AF",
    "gn:dem":2822,
    "gn:feature_class":"P",
    "gn:feature_code":"PPL",
    "gn:name":"Kh\u014dsh Now",
    "gn:population":0,
    "gn:timezone":"Asia/Kabul",
    "iso:country":"AF",
    "name:und_x_variant":[
        "Khushnau",
        "Khu\u0161naw",
        "Khush Now",
        "Khvoshn\u0101w",
        "Kh\u014dsh Now",
        "\u062e\u0648\u0634\u0646\u0648"
    ],
    "wof:name":"Khosh Now",
    "wof:placetype":"locality"
},
  "geometry": {"coordinates":[66.33466,34.50455],"type":"Point"}
}