{
  "type": "Feature",
  "properties": {
    "gn:admin1_code":"18",
    "gn:admin2_code":"805",
    "gn:asciiname":"Kuram",
    "gn:country_code":"AF",
    "gn:dem":1107,
    "gn:feature_class":"P",
    "gn:feature_code":"PPL",
    "gn:name":"Ku\u1e5fam",
    "gn:population":0,
    "gn:timezone":"Asia/Kabul",
    "iso:country":"AF",
    "name:fas_x_preferred":[
        "\u0643\u0631\u0645"
    ],
    "name:und_x_variant":[
        "Koram",
        "Ku\u1e5fam",
        "\u06a9\u0693\u0645",
        "\u06a9\u0631\u0645",
        "Kuram"
    ],
    "wof:name":"Kuram",
    "wof:placetype":"locality"
},
  "geometry": {"coordinates":[70.09910000000001,34.38557],"type":"Point"}
}