{
  "type": "Feature",
  "properties": {
    "gn:admin1_code":"01",
    "gn:admin2_code":"1112",
    "gn:asciiname":"Nowabad",
    "gn:country_code":"AF",
    "gn:dem":2842,
    "gn:feature_class":"P",
    "gn:feature_code":"PPL",
    "gn:name":"Now\u0101b\u0101d",
    "gn:population":0,
    "gn:timezone":"Asia/Kabul",
    "iso:country":"AF",
    "name:und_x_variant":[
        "Naw \u0100b\u0101\u1e0f",
        "Now\u0101b\u0101d",
        "\u0646\u0648 \u0622\u0628\u0627\u062f"
    ],
    "wof:name":"Nowabad",
    "wof:placetype":"locality"
},
  "geometry": {"coordinates":[70.50725,37.68223],"type":"Point"}
}