{
  "type": "Feature",
  "properties": {
    "gn:admin1_code":"03",
    "gn:admin2_code":"1308.0",
    "gn:asciiname":"Damanah",
    "gn:country_code":"AF",
    "gn:dem":1613,
    "gn:feature_class":"P",
    "gn:feature_code":"PPL",
    "gn:name":"D\u0101manah",
    "gn:population":0,
    "gn:timezone":"Asia/Kabul",
    "iso:country":"AF",
    "name:und_x_variant":[
        "D\u0101manah",
        "\u062f\u0627\u0645\u0646\u0647"
    ],
    "wof:name":"Damanah",
    "wof:placetype":"locality"
},
  "geometry": {"coordinates":[69.52056999999999,35.98463],"type":"Point"}
}