{
  "type": "Feature",
  "properties": {
    "gn:admin1_code":"34",
    "gn:admin2_code":"1014.0",
    "gn:asciiname":"Abo Tangah",
    "gn:country_code":"AF",
    "gn:dem":1149,
    "gn:feature_class":"P",
    "gn:feature_code":"PPL",
    "gn:name":"Ab\u014d Tangah",
    "gn:population":0,
    "gn:timezone":"Asia/Kabul",
    "iso:country":"AF",
    "name:und_x_variant":[
        "Abutanga",
        "Abo Tanga",
        "Abo Tangah",
        "Ab\u014d Tangah",
        "\u0627\u0628\u0648 \u062a\u0646\u06af\u0647"
    ],
    "wof:name":"Abo Tangah",
    "wof:placetype":"locality"
},
  "geometry": {"coordinates":[70.89308,34.5689],"type":"Point"}
}