{
  "type": "Feature",
  "properties": {
    "gn:admin1_code":"40",
    "gn:admin2_code":"307.0",
    "gn:asciiname":"Qal'ah-ye 'Ata",
    "gn:country_code":"AF",
    "gn:dem":2425,
    "gn:feature_class":"P",
    "gn:feature_code":"PPL",
    "gn:name":"Qal\u2018ah-ye \u2018A\u0163\u0101",
    "gn:population":0,
    "gn:timezone":"Asia/Kabul",
    "iso:country":"AF",
    "name:und_x_variant":[
        "Kalaata",
        "Qal\u2018a At\u0101",
        "Qal\u2018a-i-At\u0101",
        "Qal\u2018eh-ye \u2018A\u0163\u0101",
        "Qal\u2018ah-ye \u2018A\u0163\u0101",
        "\u0642\u0644\u0639\u0647 \u0639\u0637\u0627"
    ],
    "wof:name":"Qal'ah-ye 'Ata",
    "wof:placetype":"locality"
},
  "geometry": {"coordinates":[68.49061,34.76345999999999],"type":"Point"}
}