{
  "type": "Feature",
  "properties": {
    "gn:admin1_code":"41",
    "gn:admin2_code":"3409.0",
    "gn:asciiname":"Gosh Takht",
    "gn:country_code":"AF",
    "gn:dem":2108,
    "gn:feature_class":"P",
    "gn:feature_code":"PPL",
    "gn:name":"G\u014dsh Takht",
    "gn:population":0,
    "gn:timezone":"Asia/Kabul",
    "iso:country":"AF",
    "name:und_x_variant":[
        "Go\u0161takht",
        "G\u014dsh Takht",
        "G\u016bshtakht",
        "\u06af\u0648\u0634 \u062a\u062e\u062a"
    ],
    "wof:name":"Gosh Takht",
    "wof:placetype":"locality"
},
  "geometry": {"coordinates":[66.71505999999999,33.8046],"type":"Point"}
}