{
  "type": "Feature",
  "properties": {
    "gn:admin1_code":"24",
    "gn:admin2_code":"1404.0",
    "gn:asciiname":"Basoz-e Bala",
    "gn:country_code":"AF",
    "gn:dem":389,
    "gn:feature_class":"P",
    "gn:feature_code":"PPL",
    "gn:name":"B\u0101s\u014dz-e B\u0101l\u0101",
    "gn:population":0,
    "gn:timezone":"Asia/Kabul",
    "iso:country":"AF",
    "name:fas_x_preferred":[
        "\u0628\u0627\u0633\u0648\u0632\u0654 \u0628\u0627\u0644\u0627"
    ],
    "name:rus_x_preferred":[
        "\u0411\u0430\u0441\u043e\u0437\u0438-\u0411\u0430\u043b\u0430"
    ],
    "name:und_x_variant":[
        "B\u0101s\u014dz-i-B\u0101l\u0101",
        "Basozi-Bala",
        "B\u0101s\u016bz-e B\u0101l\u0101",
        "B\u0101s\u014dz-e B\u0101l\u0101",
        "\u0628\u0627\u0633\u0648\u0632 \u0628\u0627\u0644\u0627",
        "B\u0101s\u014dzah-ye B\u0101l\u0101",
        "\u0628\u0627\u0633\u0648\u0632\u06c0 \u0628\u0627\u0644\u0627"
    ],
    "wof:name":"Basoz-e Bala",
    "wof:placetype":"locality"
},
  "geometry": {"coordinates":[68.74594,36.71483],"type":"Point"}
}