{
  "type": "Feature",
  "properties": {
    "gn:admin1_code":"28",
    "gn:admin2_code":"2504.0",
    "gn:asciiname":"Basian",
    "gn:country_code":"AF",
    "gn:dem":2215,
    "gn:feature_class":"P",
    "gn:feature_code":"PPL",
    "gn:name":"B\u0101s\u012ban",
    "gn:population":0,
    "gn:timezone":"Asia/Kabul",
    "iso:country":"AF",
    "name:fas_x_preferred":[
        "\u0628\u0627\u0633\u064a\u0646"
    ],
    "name:und_x_variant":[
        "Basiakh",
        "B\u0101s\u012ban",
        "\u0628\u0627\u0633\u06cc\u0627\u0646"
    ],
    "wof:name":"Basian",
    "wof:placetype":"locality"
},
  "geometry": {"coordinates":[66.77153,32.64003],"type":"Point"}
}