{
  "type": "Feature",
  "properties": {
    "gn:admin1_code":"11",
    "gn:admin2_code":"2013",
    "gn:asciiname":"Dinak",
    "gn:country_code":"AF",
    "gn:dem":2093,
    "gn:feature_class":"P",
    "gn:feature_code":"PPL",
    "gn:name":"D\u012bnak",
    "gn:population":0,
    "gn:timezone":"Asia/Kabul",
    "iso:country":"AF",
    "name:und_x_variant":[
        "D\u012bnak",
        "\u062f\u06cc\u0646\u06a9"
    ],
    "wof:name":"Dinak",
    "wof:placetype":"locality"
},
  "geometry": {"coordinates":[63.08719,33.69642],"type":"Point"}
}