{
  "type": "Feature",
  "properties": {
    "gn:admin1_code":"30",
    "gn:admin2_code":"1606.0",
    "gn:asciiname":"Shah Ab",
    "gn:country_code":"AF",
    "gn:dem":323,
    "gn:feature_class":"P",
    "gn:feature_code":"PPL",
    "gn:name":"Sh\u0101h \u0100b",
    "gn:population":0,
    "gn:timezone":"Asia/Kabul",
    "iso:country":"AF",
    "name:fas_x_preferred":[
        "\u0634\u0627\u0647 \u0622\u0628"
    ],
    "name:rus_x_preferred":[
        "\u0428\u0430\u0445\u0430\u0431"
    ],
    "name:und_x_variant":[
        "Shakhab",
        "Sh\u0101h \u0100b"
    ],
    "wof:name":"Shah Ab",
    "wof:placetype":"locality"
},
  "geometry": {"coordinates":[66.85682,36.88185],"type":"Point"}
}