{
  "type": "Feature",
  "properties": {
    "gn:admin1_code":"02",
    "gn:admin2_code":"1901",
    "gn:asciiname":"Laman",
    "gn:country_code":"AF",
    "gn:dem":1412,
    "gn:feature_class":"P",
    "gn:feature_code":"PPL",
    "gn:name":"L\u0101m\u0101n",
    "gn:population":0,
    "gn:timezone":"Asia/Kabul",
    "iso:country":"AF",
    "name:und_x_variant":[
        "L\u0101m\u0101n",
        "\u0644\u0627\u0645\u0627\u0646"
    ],
    "wof:name":"Laman",
    "wof:placetype":"locality"
},
  "geometry": {"coordinates":[63.10416,34.75230999999999],"type":"Point"}
}