{
  "type": "Feature",
  "properties": {
    "gn:admin1_code":"41",
    "gn:admin2_code":"3408",
    "gn:asciiname":"Pesh-e Pozah",
    "gn:country_code":"AF",
    "gn:dem":2723,
    "gn:feature_class":"P",
    "gn:feature_code":"PPL",
    "gn:name":"P\u0113sh-e P\u014dzah",
    "gn:population":0,
    "gn:timezone":"Asia/Kabul",
    "iso:country":"AF",
    "name:und_x_variant":[
        "Peshi-Puza",
        "P\u0113\u0161e P\u016bza",
        "Paysh-e P\u014dzah",
        "P\u012bsh-e P\u016bzeh",
        "P\u0113sh-e P\u014dzah",
        "\u067e\u064a\u0634 \u067e\u0648\u0632\u0647"
    ],
    "wof:name":"Pesh-e Pozah",
    "wof:placetype":"locality"
},
  "geometry": {"coordinates":[66.27659,34.26742],"type":"Point"}
}