{
  "type": "Feature",
  "properties": {
    "gn:admin1_code":"05",
    "gn:admin2_code":"2806.0",
    "gn:asciiname":"Dahan-e Reg-e Now",
    "gn:country_code":"AF",
    "gn:dem":3067,
    "gn:feature_class":"P",
    "gn:feature_code":"PPL",
    "gn:name":"Dah\u0101n-e R\u0113g-e Now",
    "gn:population":0,
    "gn:timezone":"Asia/Kabul",
    "iso:country":"AF",
    "name:und_x_variant":[
        "\u1e0eahane \u1e5e\u0113ge Naw",
        "Dakhani-Regi-Nau",
        "Dahan-e Rayg-e N\u0101w",
        "Dahan-e R\u012bg-e N\u0101w",
        "Dah\u0101n-e Rayg-e Now",
        "\u062f\u0647\u0627\u0646 \u0631\u06cc\u06af \u0646\u0648",
        "Dah\u0101n-e R\u0113g-e Now"
    ],
    "wof:name":"Dahan-e Reg-e Now",
    "wof:placetype":"locality"
},
  "geometry": {"coordinates":[67.06498000000001,34.26495],"type":"Point"}
}