{
  "type": "Feature",
  "properties": {
    "gn:admin1_code":"03",
    "gn:admin2_code":"1304",
    "gn:asciiname":"Qal'ah-ye Ayshan",
    "gn:country_code":"AF",
    "gn:dem":1295,
    "gn:feature_class":"P",
    "gn:feature_code":"PPL",
    "gn:name":"Qal\u2018ah-ye Aysh\u0101n",
    "gn:population":0,
    "gn:timezone":"Asia/Kabul",
    "iso:country":"AF",
    "name:und_x_variant":[
        "Kalaishan",
        "Qal\u2018a E\u0161\u0101n",
        "Qal\u2018a-i-E\u1e63\u0101n",
        "Qal\u2018eh-ye Esh\u0101n",
        "Qal\u2018ah-ye Aysh\u0101n",
        "\u0642\u0644\u0639\u06c0 \u0627\u06cc\u0634\u0627\u0646"
    ],
    "wof:name":"Qal'ah-ye Ayshan",
    "wof:placetype":"locality"
},
  "geometry": {"coordinates":[68.90531999999999,35.76336],"type":"Point"}
}