{
  "type": "Feature",
  "properties": {
    "gn:admin1_code":"30",
    "gn:admin2_code":"1606.0",
    "gn:asciiname":"Aspaki Now Warid",
    "gn:country_code":"AF",
    "gn:dem":330,
    "gn:feature_class":"P",
    "gn:feature_code":"PPL",
    "gn:name":"Aspak\u012b Now W\u0101rid",
    "gn:population":0,
    "gn:timezone":"Asia/Kabul",
    "iso:country":"AF",
    "name:fas_x_preferred":[
        "\u0627\u0633\u0628\u0643\u06cc \u0646\u0648 \u0648\u0627\u0631\u062f"
    ],
    "name:und_x_variant":[
        "Aspaki Nauwarid",
        "Aspak\u012b Now W\u0101rid"
    ],
    "wof:name":"Aspaki Now Warid",
    "wof:placetype":"locality"
},
  "geometry": {"coordinates":[66.77658000000001,36.82007],"type":"Point"}
}