{
  "type": "Feature",
  "properties": {
    "gn:admin1_code":"37",
    "gn:admin2_code":"3210.0",
    "gn:asciiname":"Shamal Khel",
    "gn:country_code":"AF",
    "gn:dem":1204,
    "gn:feature_class":"P",
    "gn:feature_code":"PPL",
    "gn:name":"Shamal Kh\u0113l",
    "gn:population":0,
    "gn:timezone":"Asia/Kabul",
    "iso:country":"AF",
    "name:rus_x_preferred":[
        "Shomal\u2019khel\u2019-Somankheyl\u2019"
    ],
    "name:und_x_variant":[
        "\u0160omalkh\u0113l",
        "Shomal Kheyl",
        "Shumal Kh\u0113l",
        "Shamal Kh\u0113l",
        "\u0634\u0645\u0644 \u062e\u06d0\u0644"
    ],
    "wof:name":"Shamal Khel",
    "wof:placetype":"locality"
},
  "geometry": {"coordinates":[70.00729,33.53714],"type":"Point"}
}