{
  "type": "Feature",
  "properties": {
    "gn:admin1_code":"19",
    "gn:admin2_code":"2205",
    "gn:asciiname":"Shishabah",
    "gn:country_code":"AF",
    "gn:dem":568,
    "gn:feature_class":"P",
    "gn:feature_code":"PPL",
    "gn:name":"Shish\u0101bah",
    "gn:population":0,
    "gn:timezone":"Asia/Kabul",
    "iso:country":"AF",
    "name:und_x_variant":[
        "S\u0304es\u0304\u0101ba",
        "Shesh\u0101ba",
        "Shesh \u0100beh",
        "Shish\u0101wa",
        "Shish\u0101bah",
        "\u0634\u0634\u0627\u0628\u0647",
        "Shesh \u0100veh"
    ],
    "wof:name":"Shishabah",
    "wof:placetype":"locality"
},
  "geometry": {"coordinates":[62.70035,31.5076],"type":"Point"}
}