{
  "type": "Feature",
  "properties": {
    "gn:admin1_code":"01",
    "gn:admin2_code":"1115.0",
    "gn:asciiname":"Bagh-e Mubarak",
    "gn:country_code":"AF",
    "gn:dem":1293,
    "gn:feature_class":"P",
    "gn:feature_code":"PPL",
    "gn:name":"B\u0101gh-e Mub\u0101rak",
    "gn:population":0,
    "gn:timezone":"Asia/Kabul",
    "iso:country":"AF",
    "name:und_x_variant":[
        "B\u0101gh-i-Mob\u0101\u1e5fak",
        "\u0628\u0627\u063a \u0645\u0628\u0627\u0631\u06a9",
        "B\u0101gh-e Mob\u0101rak",
        "B\u0101gh-e Mub\u0101rak"
    ],
    "wof:name":"Bagh-e Mubarak",
    "wof:placetype":"locality"
},
  "geometry": {"coordinates":[70.67865,37.05256],"type":"Point"}
}