{
  "type": "Feature",
  "properties": {
    "gn:admin1_code":"13",
    "gn:admin2_code":"110.0",
    "gn:asciiname":"Qal'ah-ye Dopah",
    "gn:country_code":"AF",
    "gn:dem":1797,
    "gn:feature_class":"P",
    "gn:feature_code":"PPL",
    "gn:name":"Qal\u2018ah-ye D\u014dpah",
    "gn:population":0,
    "gn:timezone":"Asia/Kabul",
    "iso:country":"AF",
    "name:und_x_variant":[
        "Qal\u2018ah-ye D\u014dpah",
        "\u0642\u0644\u0639\u0647 \u062f\u0648\u067e\u0647"
    ],
    "wof:name":"Qal'ah-ye Dopah",
    "wof:placetype":"locality"
},
  "geometry": {"coordinates":[69.22035,34.45574000000001],"type":"Point"}
}