{
  "type": "Feature",
  "properties": {
    "gn:admin1_code":"7",
    "gn:admin2_code":"1807.0",
    "gn:asciiname":"Abparan",
    "gn:country_code":"AF",
    "gn:dem":1909,
    "gn:feature_class":"P",
    "gn:feature_code":"PPL",
    "gn:name":"\u0100bpar\u0101n",
    "gn:population":0,
    "gn:timezone":"Asia/Kabul",
    "iso:country":"AF",
    "name:und_x_variant":[
        "\u0100bpar\u0101n",
        "\u0622\u0628 \u067e\u0631\u0627\u0646",
        "\u0100bpa\u1e5f\u0101n"
    ],
    "wof:name":"Abparan",
    "wof:placetype":"locality"
},
  "geometry": {"coordinates":[65.06374,35.56448],"type":"Point"}
}