{
  "type": "Feature",
  "properties": {
    "gn:admin1_code":"10",
    "gn:admin2_code":"2302",
    "gn:asciiname":"Mal Gir",
    "gn:country_code":"AF",
    "gn:dem":802,
    "gn:feature_class":"P",
    "gn:feature_code":"PPL",
    "gn:name":"M\u0101l G\u012br",
    "gn:population":0,
    "gn:timezone":"Asia/Kabul",
    "iso:country":"AF",
    "wof:name":"Mal Gir",
    "wof:placetype":"locality"
},
  "geometry": {"coordinates":[64.45,31.73333],"type":"Point"}
}