{
  "type": "Feature",
  "properties": {
    "gn:admin1_code":"05",
    "gn:admin2_code":"2806.0",
    "gn:asciiname":"Shah Nazar",
    "gn:country_code":"AF",
    "gn:dem":3015,
    "gn:feature_class":"P",
    "gn:feature_code":"PPL",
    "gn:name":"Sh\u0101h Naz\u0327ar",
    "gn:population":0,
    "gn:timezone":"Asia/Kabul",
    "iso:country":"AF",
    "name:und_x_variant":[
        "\u0160\u0101hnazar",
        "Shakhnazar",
        "Sh\u0101h Naz\u0327ar",
        "Sh\u0101hnaz\u0327ar",
        "\u0634\u0627\u0647 \u0646\u0638\u0631"
    ],
    "wof:name":"Shah Nazar",
    "wof:placetype":"locality"
},
  "geometry": {"coordinates":[67.22419000000001,34.30063],"type":"Point"}
}