{
  "type": "Feature",
  "properties": {
    "gn:admin1_code":"27",
    "gn:admin2_code":"404",
    "gn:asciiname":"Gungi",
    "gn:country_code":"AF",
    "gn:dem":2975,
    "gn:feature_class":"P",
    "gn:feature_code":"PPL",
    "gn:name":"Gung\u012b",
    "gn:population":0,
    "gn:timezone":"Asia/Kabul",
    "iso:country":"AF",
    "name:und_x_variant":[
        "Gong\u012b",
        "Gungi",
        "Gung\u012b",
        "\u06af\u0646\u06af\u06cc"
    ],
    "wof:name":"Gungi",
    "wof:placetype":"locality"
},
  "geometry": {"coordinates":[67.87441,34.22405999999999],"type":"Point"}
}