{
  "type": "Feature",
  "properties": {
    "gn:admin1_code":"10",
    "gn:admin2_code":"2305",
    "gn:asciiname":"Shin Darah",
    "gn:country_code":"AF",
    "gn:dem":1298,
    "gn:feature_class":"P",
    "gn:feature_code":"PPL",
    "gn:name":"Sh\u012bn Darah",
    "gn:population":0,
    "gn:timezone":"Asia/Kabul",
    "iso:country":"AF",
    "name:und_x_variant":[
        "\u0160\u012bn Darrah",
        "Shindarra",
        "Sh\u012bn Darah",
        "\u0634\u06cc\u0646 \u062f\u0631\u0647",
        "Sh\u012bn Darreh"
    ],
    "wof:name":"Shin Darah",
    "wof:placetype":"locality"
},
  "geometry": {"coordinates":[64.92621,32.59429],"type":"Point"}
}