{
  "type": "Feature",
  "properties": {
    "gn:admin1_code":"05",
    "gn:admin2_code":"2806.0",
    "gn:asciiname":"Kharbayd",
    "gn:country_code":"AF",
    "gn:dem":2959,
    "gn:feature_class":"P",
    "gn:feature_code":"PPL",
    "gn:name":"Kharbayd",
    "gn:population":0,
    "gn:timezone":"Asia/Kabul",
    "iso:country":"AF",
    "name:und_x_variant":[
        "Kha\u1e5fb\u0113\u1e0f",
        "Kharbed",
        "Kharb\u012bd",
        "Kharbayd",
        "\u062e\u0631\u0628\u06cc\u062f"
    ],
    "wof:name":"Kharbayd",
    "wof:placetype":"locality"
},
  "geometry": {"coordinates":[67.17246999999999,34.24119],"type":"Point"}
}