{
  "type": "Feature",
  "properties": {
    "gn:admin1_code":"29",
    "gn:admin2_code":"2914",
    "gn:asciiname":"Srah Kot Kelay",
    "gn:country_code":"AF",
    "gn:dem":2713,
    "gn:feature_class":"P",
    "gn:feature_code":"PPL",
    "gn:name":"Srah K\u014d\u1e6f K\u00ealay",
    "gn:population":0,
    "gn:timezone":"Asia/Kabul",
    "iso:country":"AF",
    "name:fas_x_preferred":[
        "\u0642\u0631\u064a\u06c0 \u0633\u0631\u062e \u0643\u0648\u062a"
    ],
    "name:und_x_variant":[
        "S\u1e5feh K\u014dt Kalay",
        "Srakotkalay",
        "Srah K\u014d\u1e6f K\u00ealay",
        "S\u1e5feh Kowt Kalay",
        "\u0633\u0631\u0647 \u06a9\u0648\u067c \u06a9\u0644\u06cc"
    ],
    "wof:name":"Srah Kot Kelay",
    "wof:placetype":"locality"
},
  "geometry": {"coordinates":[69.13506,33.07052],"type":"Point"}
}