{
  "type": "Feature",
  "properties": {
    "gn:admin1_code":"06",
    "gn:admin2_code":"2104",
    "gn:asciiname":"Kowt",
    "gn:country_code":"AF",
    "gn:dem":1570,
    "gn:feature_class":"P",
    "gn:feature_code":"PPL",
    "gn:name":"Kowt",
    "gn:population":0,
    "gn:timezone":"Asia/Kabul",
    "iso:country":"AF",
    "name:und_x_variant":[
        "K\u014dt",
        "K\u014d\u1e6f",
        "\u06a9\u0648\u067c",
        "Kowt"
    ],
    "wof:name":"Kowt",
    "wof:placetype":"locality"
},
  "geometry": {"coordinates":[63.98115,33.17055],"type":"Point"}
}