{
  "type": "Feature",
  "properties": {
    "gn:admin1_code":"09",
    "gn:admin2_code":"2701",
    "gn:asciiname":"Dasht",
    "gn:country_code":"AF",
    "gn:dem":2407,
    "gn:feature_class":"P",
    "gn:feature_code":"PPL",
    "gn:name":"Dasht",
    "gn:population":0,
    "gn:timezone":"Asia/Kabul",
    "iso:country":"AF",
    "name:ceb_x_preferred":[
        "Dasht"
    ],
    "name:fas_x_preferred":[
        "\u062f\u0634\u062a\u06cc"
    ],
    "name:ita_x_preferred":[
        "Dasht"
    ],
    "name:sco_x_preferred":[
        "Dasht"
    ],
    "name:swe_x_preferred":[
        "Dasht"
    ],
    "name:und_x_variant":[
        "\u1e0eas\u0304t",
        "\u062f\u0634\u062a"
    ],
    "name:vie_x_preferred":[
        "Dasht"
    ],
    "wof:name":"Dasht",
    "wof:placetype":"locality"
},
  "geometry": {"coordinates":[65.33924,34.93457],"type":"Point"}
}