{
  "type": "Feature",
  "properties": {
    "gn:admin1_code":"34",
    "gn:admin2_code":"1002.0",
    "gn:asciiname":"Teper",
    "gn:country_code":"AF",
    "gn:dem":1249,
    "gn:feature_class":"P",
    "gn:feature_code":"PPL",
    "gn:name":"T\u0113p\u00ear",
    "gn:population":0,
    "gn:timezone":"Asia/Kabul",
    "iso:country":"AF",
    "name:fas_x_preferred":[
        "\u062a\u064a\u067e\u0631"
    ],
    "name:und_x_variant":[
        "T\u0113p\u011br",
        "T\u0113p\u00ear",
        "\u062a\u06d0\u067e\u0631"
    ],
    "wof:name":"Teper",
    "wof:placetype":"locality"
},
  "geometry": {"coordinates":[71.23137,34.84945],"type":"Point"}
}