{
  "type": "Feature",
  "properties": {
    "gn:admin1_code":"39",
    "gn:admin2_code":"2602.0",
    "gn:asciiname":"Qalatag",
    "gn:country_code":"AF",
    "gn:dem":2641,
    "gn:feature_class":"P",
    "gn:feature_code":"PPL",
    "gn:name":"Qalatag",
    "gn:population":0,
    "gn:timezone":"Asia/Kabul",
    "iso:country":"AF",
    "name:fas_x_preferred":[
        "\u06a9\u0644\u0639\u062a\u06a9"
    ],
    "name:und_x_variant":[
        "Qal\u2018atak",
        "Qalatag",
        "Kalatak",
        "\u0642\u0644\u062a\u06af",
        "Kal\u2018atak"
    ],
    "wof:name":"Qalatag",
    "wof:placetype":"locality"
},
  "geometry": {"coordinates":[66.51567,32.74718],"type":"Point"}
}