{
  "type": "Feature",
  "properties": {
    "gn:admin1_code":"14",
    "gn:admin2_code":"202.0",
    "gn:asciiname":"Wuluswali Rayzah Kohistan",
    "gn:country_code":"AF",
    "gn:dem":1580,
    "gn:feature_class":"P",
    "gn:feature_code":"PPL",
    "gn:name":"Wulusw\u0101l\u012b Rayzah K\u014dhist\u0101n",
    "gn:population":0,
    "gn:timezone":"Asia/Kabul",
    "iso:country":"AF",
    "name:fas_x_preferred":[
        "\u0648\u0644\u0648\u0633\u0648\u0627\u0644\u06cc \u0631\u064a\u0632\u0647 \u0643\u0648\u0647\u0633\u062a\u0627\u0646"
    ],
    "name:und_x_variant":[
        "Ulusvali-Rezakokhistan",
        "Olusw\u0101l\u012b \u1e5e\u0113zakohest\u0101n",
        "Ol\u016bsw\u0101l\u012b R\u012bzeh K\u016bhest\u0101n",
        "Wolusw\u0101l\u012b Rayzah K\u014dhist\u0101n",
        "\u0648\u0644\u0633\u0648\u0627\u0644\u06cc \u0631\u06cc\u0632\u0647 \u06a9\u0648\u0647\u0633\u062a\u0627\u0646",
        "Wulusw\u0101l\u012b Rayzah K\u014dhist\u0101n"
    ],
    "wof:name":"Wuluswali Rayzah Kohistan",
    "wof:placetype":"locality"
},
  "geometry": {"coordinates":[69.29947,35.12574],"type":"Point"}
}