{
  "type": "Feature",
  "properties": {
    "gn:admin1_code":"27",
    "gn:admin2_code":"404",
    "gn:asciiname":"Sar-e Raqol",
    "gn:country_code":"AF",
    "gn:dem":3058,
    "gn:feature_class":"P",
    "gn:feature_code":"PPL",
    "gn:name":"Sar-e R\u0101q\u014dl",
    "gn:population":0,
    "gn:timezone":"Asia/Kabul",
    "iso:country":"AF",
    "name:und_x_variant":[
        "R\u0101q\u016bl",
        "Sari-Rakul\u2019",
        "R\u0101h Kol",
        "Sa\u1e5fe \u1e5e\u0101q\u014dl",
        "Sar-e R\u0101q\u014dl",
        "Sar-e R\u0101qowl",
        "\u0633\u0631 \u0631\u0627\u0642\u0648\u0644"
    ],
    "wof:name":"Sar-e Raqol",
    "wof:placetype":"locality"
},
  "geometry": {"coordinates":[67.85198000000001,34.337],"type":"Point"}
}