{
  "type": "Feature",
  "properties": {
    "gn:admin1_code":"07",
    "gn:admin2_code":"1806",
    "gn:asciiname":"Khwajah 'Arab",
    "gn:country_code":"AF",
    "gn:dem":1624,
    "gn:feature_class":"P",
    "gn:feature_code":"PPL",
    "gn:name":"Khw\u0101jah \u2018Arab",
    "gn:population":0,
    "gn:timezone":"Asia/Kabul",
    "iso:country":"AF",
    "name:und_x_variant":[
        "Khw\u0101ja Arabi",
        "Khw\u0101ja Arab",
        "Khv\u0101jeh \u2018Arab",
        "Khw\u0101jah \u2018Arab",
        "\u062e\u0648\u0627\u062c\u0647 \u0639\u0631\u0628"
    ],
    "wof:name":"Khwajah 'Arab",
    "wof:placetype":"locality"
},
  "geometry": {"coordinates":[65.52679000000001,35.96061],"type":"Point"}
}