{
  "type": "Feature",
  "properties": {
    "gn:admin1_code":"09",
    "gn:admin2_code":"2701",
    "gn:asciiname":"Inishwak",
    "gn:country_code":"AF",
    "gn:dem":2558,
    "gn:feature_class":"P",
    "gn:feature_code":"PPL",
    "gn:name":"Inishwak",
    "gn:population":0,
    "gn:timezone":"Asia/Kabul",
    "iso:country":"AF",
    "name:und_x_variant":[
        "Enes\u0304wak",
        "Inishwak",
        "\u0627\u0646\u0634\u0648\u06a9",
        "Eneshwak"
    ],
    "wof:name":"Inishwak",
    "wof:placetype":"locality"
},
  "geometry": {"coordinates":[64.92893000000001,34.68901],"type":"Point"}
}