{
  "type": "Feature",
  "properties": {
    "gn:admin1_code":"08",
    "gn:admin2_code":"608",
    "gn:asciiname":"Jaras Kala",
    "gn:country_code":"AF",
    "gn:dem":2206,
    "gn:feature_class":"P",
    "gn:feature_code":"PPL",
    "gn:name":"Jaras Kal\u0101",
    "gn:population":0,
    "gn:timezone":"Asia/Kabul",
    "iso:country":"AF",
    "name:fas_x_preferred":[
        "\u062c\u0631\u0633 \u0643\u0644\u0627"
    ],
    "name:rus_x_preferred":[
        "\u0414\u0436\u0430\u0440\u0430\u0441\u043a\u0430\u043b\u0430"
    ],
    "name:und_x_variant":[
        "Dzharaskala",
        "Jaras Kal\u0101",
        "\u062c\u0631\u0633 \u06a9\u0644\u0627"
    ],
    "wof:name":"Jaras Kala",
    "wof:placetype":"locality"
},
  "geometry": {"coordinates":[67.78614,33.0271],"type":"Point"}
}