{
  "type": "Feature",
  "properties": {
    "gn:admin1_code":"01",
    "gn:admin2_code":"1120.0",
    "gn:asciiname":"Karniw",
    "gn:country_code":"AF",
    "gn:dem":2515,
    "gn:feature_class":"P",
    "gn:feature_code":"PPL",
    "gn:name":"Karniw",
    "gn:population":0,
    "gn:timezone":"Asia/Kabul",
    "iso:country":"AF",
    "name:und_x_variant":[
        "\u06a9\u0631\u0646\u0648",
        "Ka\u1e5fniw",
        "Karniw"
    ],
    "wof:name":"Karniw",
    "wof:placetype":"locality"
},
  "geometry": {"coordinates":[70.58255,37.9783],"type":"Point"}
}