{
  "type": "Feature",
  "properties": {
    "gn:admin1_code":"10",
    "gn:admin2_code":"2302.0",
    "gn:asciiname":"Tajdar-e Wali",
    "gn:country_code":"AF",
    "gn:dem":835,
    "gn:feature_class":"P",
    "gn:feature_code":"PPL",
    "gn:name":"T\u0101jd\u0101r-e Wal\u012b",
    "gn:population":0,
    "gn:timezone":"Asia/Kabul",
    "iso:country":"AF",
    "name:und_x_variant":[
        "Gadzhari-Vali",
        "T\u0101j\u1e0f\u0101\u1e5fe Wali",
        "T\u0101jd\u0101r-e Wal\u012b",
        "\u062a\u0627\u062c\u062f\u0627\u0631 \u0648\u0644\u06cc",
        "T\u0101jd\u0101r-e Val\u012b"
    ],
    "wof:name":"Tajdar-e Wali",
    "wof:placetype":"locality"
},
  "geometry": {"coordinates":[64.57687,31.79758],"type":"Point"}
}