{
  "type": "Feature",
  "properties": {
    "gn:admin1_code":"26",
    "gn:admin2_code":"1215",
    "gn:asciiname":"Kukiya",
    "gn:country_code":"AF",
    "gn:dem":882,
    "gn:feature_class":"P",
    "gn:feature_code":"PPL",
    "gn:name":"Kukiya",
    "gn:population":0,
    "gn:timezone":"Asia/Kabul",
    "iso:country":"AF",
    "name:azb_x_preferred":[
        "\u06a9\u0648\u06a9\u06cc\u0627"
    ],
    "name:aze_x_preferred":[
        "Kukiya"
    ],
    "name:ceb_x_preferred":[
        "K\u016bk\u012by\u0101"
    ],
    "name:fas_x_preferred":[
        "\u0642\u0648\u0642\u064a\u0627"
    ],
    "name:fas_x_variant":[
        "\u06a9\u0648\u06a9\u06cc\u0627"
    ],
    "name:msa_x_preferred":[
        "Kukiya"
    ],
    "name:pol_x_preferred":[
        "Kukija"
    ],
    "name:rus_x_preferred":[
        "\u041a\u0443\u043a\u0438\u044f"
    ],
    "name:swe_x_preferred":[
        "K\u016bk\u012by\u0101"
    ],
    "name:ukr_x_preferred":[
        "\u041a\u0443\u043a\u0456\u044f"
    ],
    "name:und_x_variant":[
        "Q\u016bqy\u0101",
        "Qowqy\u0101",
        "Q\u016bq\u012b\u0101",
        "\u0642\u0648\u0642\u06cc\u0627"
    ],
    "wof:name":"Kukiya",
    "wof:placetype":"locality"
},
  "geometry": {"coordinates":[69.47518000000001,36.92753],"type":"Point"}
}