{
  "type": "Feature",
  "properties": {
    "gn:admin1_code":"38",
    "gn:admin2_code":"3008.0",
    "gn:asciiname":"Daring",
    "gn:country_code":"AF",
    "gn:dem":989,
    "gn:feature_class":"P",
    "gn:feature_code":"PPL",
    "gn:name":"Daring",
    "gn:population":0,
    "gn:timezone":"Asia/Kabul",
    "iso:country":"AF",
    "name:und_x_variant":[
        "Darang",
        "Dareng",
        "Daring",
        "\u062f\u0631\u0646\u06af"
    ],
    "wof:name":"Daring",
    "wof:placetype":"locality"
},
  "geometry": {"coordinates":[70.38212,34.90948],"type":"Point"}
}