{
  "type": "Feature",
  "properties": {
    "gn:admin1_code":"13",
    "gn:admin2_code":"102.0",
    "gn:asciiname":"Qal'ah-ye Haji Pirwar",
    "gn:country_code":"AF",
    "gn:dem":1777,
    "gn:feature_class":"P",
    "gn:feature_code":"PPL",
    "gn:name":"Qal\u2018ah-ye \u1e28\u0101ji P\u012brwar",
    "gn:population":0,
    "gn:timezone":"Asia/Kabul",
    "iso:country":"AF",
    "name:und_x_variant":[
        "Qal\u2018ah-ye \u1e28\u0101ji P\u012brwar",
        "\u0642\u0644\u0639\u0647 \u062d\u0627\u062c\u06cc \u067e\u064a\u0631\u0648\u0631"
    ],
    "wof:name":"Qal'ah-ye Haji Pirwar",
    "wof:placetype":"locality"
},
  "geometry": {"coordinates":[69.2409,34.60487],"type":"Point"}
}