{
  "type": "Feature",
  "properties": {
    "gn:admin1_code":"5",
    "gn:admin2_code":"2805.0",
    "gn:asciiname":"Tarkhay Ginah",
    "gn:country_code":"AF",
    "gn:dem":2746,
    "gn:feature_class":"P",
    "gn:feature_code":"PPL",
    "gn:name":"Tarkhay G\u012bnah",
    "gn:population":0,
    "gn:timezone":"Asia/Kabul",
    "iso:country":"AF",
    "name:und_x_variant":[
        "Ta\u1e5fkhaygina",
        "Tarkhaygina",
        "Ta\u1e5fkhaygana",
        "T\u0101\u1e5fkhaygena",
        "Tarkhayg\u012bnah",
        "Tarkhayg\u012bneh",
        "Tarkhay G\u012bnah",
        "\u062a\u0631\u062e\u06cc \u06af\u06cc\u0646\u0647",
        "Tarkhay Ganah",
        "\u062a\u0631\u062e\u06cc \u06af\u0646\u0647"
    ],
    "wof:name":"Tarkhay Ginah",
    "wof:placetype":"locality"
},
  "geometry": {"coordinates":[66.97725,34.33701],"type":"Point"}
}