{
  "type": "Feature",
  "properties": {
    "gn:admin1_code":"30",
    "gn:admin2_code":"1607.0",
    "gn:asciiname":"Qowrachi",
    "gn:country_code":"AF",
    "gn:dem":326,
    "gn:feature_class":"P",
    "gn:feature_code":"PPL",
    "gn:name":"Qowrach\u012b",
    "gn:population":0,
    "gn:timezone":"Asia/Kabul",
    "iso:country":"AF",
    "name:fas_x_preferred":[
        "\u0642\u0648\u0631\u0686\u06cc"
    ],
    "name:rus_x_preferred":[
        "\u041a\u0430\u0443\u0440\u0430\u0447\u0438"
    ],
    "name:und_x_variant":[
        "Kaurachi",
        "Qowrach\u012b"
    ],
    "wof:name":"Qowrachi",
    "wof:placetype":"locality"
},
  "geometry": {"coordinates":[66.68141999999999,36.81398],"type":"Point"}
}