{
  "type": "Feature",
  "properties": {
    "gn:admin1_code":"41",
    "gn:admin2_code":"3403",
    "gn:asciiname":"Qol-e Khayri",
    "gn:country_code":"AF",
    "gn:dem":2453,
    "gn:feature_class":"P",
    "gn:feature_code":"PPL",
    "gn:name":"Q\u014dl-e Khayr\u012b",
    "gn:population":0,
    "gn:timezone":"Asia/Kabul",
    "iso:country":"AF",
    "name:und_x_variant":[
        "Qulle Khay\u1e5fi",
        "Q\u014dl-e Khayr\u012b",
        "\u0642\u0648\u0644 \u062e\u06cc\u0631\u06cc",
        "Qolle Kheyr\u012b"
    ],
    "wof:name":"Qol-e Khayri",
    "wof:placetype":"locality"
},
  "geometry": {"coordinates":[66.17121,33.93449],"type":"Point"}
}