{
  "type": "Feature",
  "properties": {
    "gn:admin1_code":"11",
    "gn:admin2_code":"2012.0",
    "gn:asciiname":"Dahan-e Tangi Azow",
    "gn:country_code":"AF",
    "gn:dem":1289,
    "gn:feature_class":"P",
    "gn:feature_code":"PPL",
    "gn:name":"Dah\u0101n-e Tang\u012b Azow",
    "gn:population":0,
    "gn:timezone":"Asia/Kabul",
    "iso:country":"AF",
    "name:und_x_variant":[
        "Saf\u0113dkha\u1e5fa",
        "\u1e0eahan-e Tangi Azaw",
        "Dah\u0101n-e Tang\u012b Azow",
        "\u062f\u0647\u0627\u0646 \u062a\u0646\u06af\u06cc \u0627\u0632\u0648",
        "Dah\u0101nah-ye Tang\u012b Azow",
        "Safayd Kharah",
        "\u062f\u0647\u0627\u0646\u06c0 \u062a\u0646\u06af\u06cc \u0627\u0632\u0648",
        "\u0633\u0641\u06cc\u062f \u062e\u0631\u0647"
    ],
    "wof:name":"Dahan-e Tangi Azow",
    "wof:placetype":"locality"
},
  "geometry": {"coordinates":[63.09419000000001,34.17723],"type":"Point"}
}