{
  "type": "Feature",
  "properties": {
    "gn:admin1_code":"27",
    "gn:admin2_code":"401.0",
    "gn:asciiname":"Akhundzadah Kala",
    "gn:country_code":"AF",
    "gn:dem":2150,
    "gn:feature_class":"P",
    "gn:feature_code":"PPL",
    "gn:name":"\u0100kh\u016bndz\u0101dah Kal\u0101",
    "gn:population":0,
    "gn:timezone":"Asia/Kabul",
    "iso:country":"AF",
    "name:und_x_variant":[
        "Akhundzada-Kala",
        "Akhun\u1e0fz\u0101\u1e0fah Kal\u0101",
        "\u0100kh\u016bndz\u0101dah Kal\u0101",
        "\u0100khvondz\u0101deh Kal\u0101",
        "\u0622\u062e\u0648\u0646\u062f\u0632\u0627\u062f\u0647 \u06a9\u0644\u0627"
    ],
    "wof:name":"Akhundzadah Kala",
    "wof:placetype":"locality"
},
  "geometry": {"coordinates":[68.83346,34.34834],"type":"Point"}
}