{
  "type": "Feature",
  "properties": {
    "gn:admin1_code":"27",
    "gn:admin2_code":"403.0",
    "gn:asciiname":"Qal'ah-ye Muhammad Khan",
    "gn:country_code":"AF",
    "gn:dem":3463,
    "gn:feature_class":"P",
    "gn:feature_code":"PPL",
    "gn:name":"Qal\u2018ah-ye Mu\u1e29ammad Kh\u0101n",
    "gn:population":0,
    "gn:timezone":"Asia/Kabul",
    "iso:country":"AF",
    "name:und_x_variant":[
        "Kala-Mukhammedkhan",
        "Qal\u2018a-i-Mo\u1e29amma\u1e0f-kh\u0101n",
        "Qal\u2018a Mo\u1e29amme\u1e0f-kh\u0101n",
        "Qal\u2018eh-ye Mo\u1e29ammad Kh\u0101n",
        "Qal\u2018ah-ye Mu\u1e29ammad Kh\u0101n",
        "\u0642\u0644\u0639\u0647 \u0645\u062d\u0645\u062f \u062e\u0627\u0646"
    ],
    "wof:name":"Qal'ah-ye Muhammad Khan",
    "wof:placetype":"locality"
},
  "geometry": {"coordinates":[68.17562,34.60567],"type":"Point"}
}