{
  "type": "Feature",
  "properties": {
    "gn:admin1_code":"08",
    "gn:admin2_code":"604",
    "gn:asciiname":"Obe Karam",
    "gn:country_code":"AF",
    "gn:dem":2748,
    "gn:feature_class":"P",
    "gn:feature_code":"PPL",
    "gn:name":"\u014cb\u0113 Karam",
    "gn:population":0,
    "gn:timezone":"Asia/Kabul",
    "iso:country":"AF",
    "name:und_x_variant":[
        "Obekaram",
        "\u014cb\u0113 Ka\u1e5fam",
        "Owbeh Karam",
        "\u014cb\u00eah Karam",
        "\u014cb\u0113 Karam",
        "\u0627\u0648\u0628\u06d0 \u06a9\u0631\u0645"
    ],
    "wof:name":"Obe Karam",
    "wof:placetype":"locality"
},
  "geometry": {"coordinates":[68.04324,34.06916],"type":"Point"}
}