{
  "type": "Feature",
  "properties": {
    "gn:admin1_code":"41",
    "gn:admin2_code":"3403.0",
    "gn:asciiname":"Takhtah Poshak",
    "gn:country_code":"AF",
    "gn:dem":2302,
    "gn:feature_class":"P",
    "gn:feature_code":"PPL",
    "gn:name":"Takhtah P\u014dshak",
    "gn:population":0,
    "gn:timezone":"Asia/Kabul",
    "iso:country":"AF",
    "name:und_x_variant":[
        "Takhtapo\u0161ak",
        "Takhtaposhak",
        "Takhtah Pushak",
        "Takhtehpushak",
        "Takhtah P\u014dshak",
        "\u062a\u062e\u062a\u0647 \u067e\u0648\u0634\u06a9"
    ],
    "wof:name":"Takhtah Poshak",
    "wof:placetype":"locality"
},
  "geometry": {"coordinates":[66.46056999999999,34.05069],"type":"Point"}
}