{
  "type": "Feature",
  "properties": {
    "gn:admin1_code":"34",
    "gn:admin2_code":"1003.0",
    "gn:asciiname":"Teshah",
    "gn:country_code":"AF",
    "gn:dem":1359,
    "gn:feature_class":"P",
    "gn:feature_code":"PPL",
    "gn:name":"T\u0113shah",
    "gn:population":0,
    "gn:timezone":"Asia/Kabul",
    "iso:country":"AF",
    "name:fas_x_preferred":[
        "\u062a\u064a\u0634\u0647"
    ],
    "name:und_x_variant":[
        "T\u0113\u0161a",
        "Tesha",
        "\u062a\u06d0\u0634\u0647",
        "T\u012bsheh",
        "T\u0113shah"
    ],
    "wof:name":"Teshah",
    "wof:placetype":"locality"
},
  "geometry": {"coordinates":[71.40373000000002,35.06641],"type":"Point"}
}