{
  "type": "Feature",
  "properties": {
    "gn:admin1_code":"42",
    "gn:admin2_code":"3301",
    "gn:asciiname":"Parakh",
    "gn:country_code":"AF",
    "gn:dem":1882,
    "gn:feature_class":"P",
    "gn:feature_code":"PPL",
    "gn:name":"P\u0101r\u0101kh",
    "gn:population":0,
    "gn:timezone":"Asia/Kabul",
    "iso:country":"AF",
    "name:und_x_variant":[
        "P\u0101r\u0101kh",
        "\u067e\u0627\u0631\u0627\u062e"
    ],
    "wof:name":"Parakh",
    "wof:placetype":"locality"
},
  "geometry": {"coordinates":[69.48493000000001,35.28504],"type":"Point"}
}