{
  "type": "Feature",
  "properties": {
    "gn:admin1_code":"8",
    "gn:admin2_code":"606.0",
    "gn:asciiname":"Dahan-e Qurqand",
    "gn:country_code":"AF",
    "gn:dem":3084,
    "gn:feature_class":"P",
    "gn:feature_code":"PPL",
    "gn:name":"Dah\u0101n-e Qurqand",
    "gn:population":0,
    "gn:timezone":"Asia/Kabul",
    "iso:country":"AF",
    "name:fas_x_preferred":[
        "\u062f\u0647\u0646\u0654 \u0642\u0631\u0642\u0646\u062f"
    ],
    "name:rus_x_preferred":[
        "\u0414\u0430\u0445\u0430\u043d\u0438-\u041a\u0443\u0440\u043a\u0430\u043d\u0434"
    ],
    "name:und_x_variant":[
        "Dakhani-Kurkand",
        "Dahan-e Qurqand",
        "Dah\u0101n-e Qurqand",
        "\u062f\u0647\u0627\u0646 \u0642\u0631\u0642\u0646\u062f"
    ],
    "wof:name":"Dahan-e Qurqand",
    "wof:placetype":"locality"
},
  "geometry": {"coordinates":[67.54637,33.52285999999999],"type":"Point"}
}