{
  "type": "Feature",
  "properties": {
    "gn:admin1_code":"27",
    "gn:admin2_code":"402.0",
    "gn:asciiname":"Qol-e Khudadad",
    "gn:country_code":"AF",
    "gn:dem":2674,
    "gn:feature_class":"P",
    "gn:feature_code":"PPL",
    "gn:name":"Q\u014dl-e Khud\u0101d\u0101d",
    "gn:population":0,
    "gn:timezone":"Asia/Kabul",
    "iso:country":"AF",
    "name:und_x_variant":[
        "Kulli-Khudadad",
        "Qulle Kho\u1e0f\u0101\u1e0f\u0101\u1e0f",
        "Q\u014dl-e Khud\u0101d\u0101d",
        "Qolleh-ye Khod\u0101d\u0101d",
        "\u0642\u0648\u0644 \u062e\u062f\u0627\u062f\u0627\u062f"
    ],
    "wof:name":"Qol-e Khudadad",
    "wof:placetype":"locality"
},
  "geometry": {"coordinates":[68.48758000000001,34.42862],"type":"Point"}
}