{
  "type": "Feature",
  "properties": {
    "gn:admin1_code":"03",
    "gn:admin2_code":"1308",
    "gn:asciiname":"Imuk",
    "gn:country_code":"AF",
    "gn:dem":2129,
    "gn:feature_class":"P",
    "gn:feature_code":"PPL",
    "gn:name":"Imuk",
    "gn:population":0,
    "gn:timezone":"Asia/Kabul",
    "iso:country":"AF",
    "name:und_x_variant":[
        "\u0627\u0645\u06a9",
        "Emuk"
    ],
    "wof:name":"Imuk",
    "wof:placetype":"locality"
},
  "geometry": {"coordinates":[69.77129000000001,36.0288],"type":"Point"}
}