{
  "type": "Feature",
  "properties": {
    "gn:admin1_code":"08",
    "gn:admin2_code":"617",
    "gn:asciiname":"Malah",
    "gn:country_code":"AF",
    "gn:dem":2640,
    "gn:feature_class":"P",
    "gn:feature_code":"PPL",
    "gn:name":"Malah",
    "gn:population":0,
    "gn:timezone":"Asia/Kabul",
    "iso:country":"AF",
    "name:fas_x_preferred":[
        "\u0645\u0644\u0647"
    ],
    "name:und_x_variant":[
        "Mala"
    ],
    "wof:name":"Malah",
    "wof:placetype":"locality"
},
  "geometry": {"coordinates":[68.17574,33.699],"type":"Point"}
}