{
  "type": "Feature",
  "properties": {
    "gn:admin1_code":"09",
    "gn:admin2_code":"2707",
    "gn:asciiname":"Khuk Kushtah",
    "gn:country_code":"AF",
    "gn:dem":2817,
    "gn:feature_class":"P",
    "gn:feature_code":"PPL",
    "gn:name":"Kh\u016bk Kushtah",
    "gn:population":0,
    "gn:timezone":"Asia/Kabul",
    "iso:country":"AF",
    "name:und_x_variant":[
        "Khukkushta",
        "Kh\u016bkku\u0161ta",
        "Kh\u016bk Koshteh",
        "Kh\u016bk Kushtah",
        "\u062e\u0648\u06a9 \u06a9\u0634\u062a\u0647"
    ],
    "wof:name":"Khuk Kushtah",
    "wof:placetype":"locality"
},
  "geometry": {"coordinates":[66.16458,34.41699000000001],"type":"Point"}
}