{
  "type": "Feature",
  "properties": {
    "gn:admin1_code":"33",
    "gn:admin2_code":"3104",
    "gn:asciiname":"Nawor-e Gali",
    "gn:country_code":"AF",
    "gn:dem":2758,
    "gn:feature_class":"P",
    "gn:feature_code":"PPL",
    "gn:name":"Nawor-e Gal\u012b",
    "gn:population":0,
    "gn:timezone":"Asia/Kabul",
    "iso:country":"AF",
    "name:und_x_variant":[
        "Nawu\u1e5fe Gali",
        "Nawor-e Gal\u012b"
    ],
    "wof:name":"Nawor-e Gali",
    "wof:placetype":"locality"
},
  "geometry": {"coordinates":[66.74221999999999,35.46528],"type":"Point"}
}