{
  "type": "Feature",
  "properties": {
    "gn:admin1_code":"26",
    "gn:admin2_code":"1205",
    "gn:asciiname":"Jangal-e Mukhnoy",
    "gn:country_code":"AF",
    "gn:dem":1985,
    "gn:feature_class":"P",
    "gn:feature_code":"PPL",
    "gn:name":"Jangal-e Mukhn\u014dy",
    "gn:population":0,
    "gn:timezone":"Asia/Kabul",
    "iso:country":"AF",
    "name:und_x_variant":[
        "Jangal-e Mukhn\u014dy",
        "Jangal-e Mukhn\u016by",
        "\u062c\u0646\u06af\u0644 \u0645\u062e\u0646\u0648\u06cc"
    ],
    "wof:name":"Jangal-e Mukhnoy",
    "wof:placetype":"locality"
},
  "geometry": {"coordinates":[70.13691,36.18685],"type":"Point"}
}