{
  "type": "Feature",
  "properties": {
    "gn:admin1_code":"42",
    "gn:admin2_code":"3302",
    "gn:asciiname":"Gulab Khel",
    "gn:country_code":"AF",
    "gn:dem":2467,
    "gn:feature_class":"P",
    "gn:feature_code":"PPL",
    "gn:name":"Gul\u0101b Kh\u0113l",
    "gn:population":0,
    "gn:timezone":"Asia/Kabul",
    "iso:country":"AF",
    "name:fas_x_preferred":[
        "\u06af\u0644\u0627\u0628 \u062e\u064a\u0644"
    ],
    "name:rus_x_preferred":[
        "\u0413\u0443\u043b\u0430\u0431\u0445\u0435\u0439\u043b\u044c"
    ],
    "name:und_x_variant":[
        "Gol\u0101bkh\u0113l",
        "Gulabkheyl\u2019",
        "Gol\u0101bkheyl",
        "Gul\u0101b Kh\u0113l",
        "\u06af\u0644\u0627\u0628 \u062e\u06d0\u0644"
    ],
    "wof:name":"Gulab Khel",
    "wof:placetype":"locality"
},
  "geometry": {"coordinates":[69.73318,35.2518],"type":"Point"}
}