{
  "type": "Feature",
  "properties": {
    "gn:admin1_code":"01",
    "gn:admin2_code":"1119.0",
    "gn:asciiname":"Deh-e Mughul",
    "gn:country_code":"AF",
    "gn:dem":2654,
    "gn:feature_class":"P",
    "gn:feature_code":"PPL",
    "gn:name":"Deh-e Mughul",
    "gn:population":0,
    "gn:timezone":"Asia/Kabul",
    "iso:country":"AF",
    "name:und_x_variant":[
        "Deh-i-Mughu",
        "\u062f\u0647 \u0645\u063a\u0644",
        "Deh-e Mughu",
        "Deh-e Moghul",
        "Deh-e Mughul"
    ],
    "wof:name":"Deh-e Mughul",
    "wof:placetype":"locality"
},
  "geometry": {"coordinates":[70.72136,37.37792],"type":"Point"}
}