{
  "type": "Feature",
  "properties": {
    "gn:admin1_code":"34",
    "gn:admin2_code":"1010.0",
    "gn:asciiname":"Ashat",
    "gn:country_code":"AF",
    "gn:dem":1689,
    "gn:feature_class":"P",
    "gn:feature_code":"PPL",
    "gn:name":"Ash\u0101t",
    "gn:population":0,
    "gn:timezone":"Asia/Kabul",
    "iso:country":"AF",
    "name:und_x_variant":[
        "A\u0161\u0101t",
        "Ash\u0101t",
        "\u0627\u0634\u0627\u062a"
    ],
    "wof:name":"Ashat",
    "wof:placetype":"locality"
},
  "geometry": {"coordinates":[70.88486999999998,34.8794],"type":"Point"}
}