{
  "type": "Feature",
  "properties": {
    "gn:admin1_code":"9",
    "gn:admin2_code":"2710.0",
    "gn:asciiname":"Birinji",
    "gn:country_code":"AF",
    "gn:dem":2684,
    "gn:feature_class":"P",
    "gn:feature_code":"PPL",
    "gn:name":"Birinj\u012b",
    "gn:population":0,
    "gn:timezone":"Asia/Kabul",
    "iso:country":"AF",
    "name:und_x_variant":[
        "Birindzhi",
        "Berenj\u012b",
        "Birinj\u012b",
        "\u0628\u0631\u0646\u062c\u06cc"
    ],
    "wof:name":"Birinji",
    "wof:placetype":"locality"
},
  "geometry": {"coordinates":[64.86366,34.19392],"type":"Point"}
}