{
  "type": "Feature",
  "properties": {
    "gn:admin1_code":"6",
    "gn:admin2_code":"2105.0",
    "gn:asciiname":"Alakozai",
    "gn:country_code":"AF",
    "gn:dem":749,
    "gn:feature_class":"P",
    "gn:feature_code":"PPL",
    "gn:name":"Alak\u014dza\u012b",
    "gn:population":0,
    "gn:timezone":"Asia/Kabul",
    "iso:country":"AF",
    "name:pus_x_preferred":[
        "\u0627\u0644\u06a9\u0648\u0632\u064a"
    ],
    "name:und_x_variant":[
        "Alak\u014dzay",
        "Alakowzay",
        "Alak\u014dza\u012b",
        "\u0627\u0644\u06a9\u0648\u0632\u06cc"
    ],
    "wof:name":"Alakozai",
    "wof:placetype":"locality"
},
  "geometry": {"coordinates":[62.47089,32.62938],"type":"Point"}
}