{
  "type": "Feature",
  "properties": {
    "gn:admin1_code":"10",
    "gn:admin2_code":"2308.0",
    "gn:asciiname":"Panj Famili",
    "gn:country_code":"AF",
    "gn:dem":770,
    "gn:feature_class":"P",
    "gn:feature_code":"PPL",
    "gn:name":"Panj F\u0101m\u012bl\u012b",
    "gn:population":0,
    "gn:timezone":"Asia/Kabul",
    "iso:country":"AF",
    "name:fas_x_preferred":[
        "\u067e\u0646\u062c \u0641\u0627\u0645\u064a\u0644\u06cc"
    ],
    "name:und_x_variant":[
        "Pandzhfamili",
        "Panj Tam\u012bl\u012b",
        "Panj F\u0101m\u012bl\u012b",
        "\u067e\u0646\u062c \u0641\u0627\u0645\u06cc\u0644\u06cc"
    ],
    "wof:name":"Panj Famili",
    "wof:placetype":"locality"
},
  "geometry": {"coordinates":[64.11724,31.50782],"type":"Point"}
}