{
  "type": "Feature",
  "properties": {
    "gn:admin1_code":"5",
    "gn:admin2_code":"2806.0",
    "gn:asciiname":"Kajnow",
    "gn:country_code":"AF",
    "gn:dem":2943,
    "gn:feature_class":"P",
    "gn:feature_code":"PPL",
    "gn:name":"Kajnow",
    "gn:population":0,
    "gn:timezone":"Asia/Kabul",
    "iso:country":"AF",
    "name:und_x_variant":[
        "Kadzhnau",
        "Kajn\u0101w",
        "Kajnow",
        "\u06a9\u062c\u0646\u0648"
    ],
    "wof:name":"Kajnow",
    "wof:placetype":"locality"
},
  "geometry": {"coordinates":[66.67668,34.19179],"type":"Point"}
}