{
  "type": "Feature",
  "properties": {
    "gn:admin1_code":"10",
    "gn:admin2_code":"2305.0",
    "gn:asciiname":"Gham-e Chowdi",
    "gn:country_code":"AF",
    "gn:dem":1671,
    "gn:feature_class":"P",
    "gn:feature_code":"PPL",
    "gn:name":"Gham-e Chowd\u012b",
    "gn:population":0,
    "gn:timezone":"Asia/Kabul",
    "iso:country":"AF",
    "name:und_x_variant":[
        "Gami-Chaudi",
        "Ghame \u010cawdi",
        "Gham-e Chowd\u012b",
        "\u063a\u0645 \u0686\u0648\u062f\u06cc",
        "Ghameh Chaw\u1e0fi"
    ],
    "wof:name":"Gham-e Chowdi",
    "wof:placetype":"locality"
},
  "geometry": {"coordinates":[65.01464,32.96321],"type":"Point"}
}