{
  "type": "Feature",
  "properties": {
    "gn:admin1_code":"08",
    "gn:admin2_code":"604",
    "gn:asciiname":"Saqi",
    "gn:country_code":"AF",
    "gn:dem":3205,
    "gn:feature_class":"P",
    "gn:feature_code":"PPL",
    "gn:name":"S\u0101q\u012b",
    "gn:population":0,
    "gn:timezone":"Asia/Kabul",
    "iso:country":"AF",
    "name:und_x_variant":[
        "S\u0101q\u012b",
        "\u0633\u0627\u0642\u06cc"
    ],
    "wof:name":"Saqi",
    "wof:placetype":"locality"
},
  "geometry": {"coordinates":[67.96789,33.66556],"type":"Point"}
}