{
  "type": "Feature",
  "properties": {
    "gn:admin1_code":"34",
    "gn:admin2_code":"1006.0",
    "gn:asciiname":"Tangay",
    "gn:country_code":"AF",
    "gn:dem":1031,
    "gn:feature_class":"P",
    "gn:feature_code":"PPL",
    "gn:name":"Tangay",
    "gn:population":0,
    "gn:timezone":"Asia/Kabul",
    "iso:country":"AF",
    "name:fas_x_preferred":[
        "\u062a\u0646\u06af\u06cc"
    ],
    "name:und_x_variant":[
        "Tanga\u012b"
    ],
    "wof:name":"Tangay",
    "wof:placetype":"locality"
},
  "geometry": {"coordinates":[71.37945999999999,35.13965],"type":"Point"}
}