{
  "type": "Feature",
  "properties": {
    "gn:admin1_code":"9",
    "gn:admin2_code":"2704.0",
    "gn:asciiname":"Dahan-e Masjid",
    "gn:country_code":"AF",
    "gn:dem":2390,
    "gn:feature_class":"P",
    "gn:feature_code":"PPL",
    "gn:name":"Dah\u0101n-e Masjid",
    "gn:population":0,
    "gn:timezone":"Asia/Kabul",
    "iso:country":"AF",
    "name:und_x_variant":[
        "Dah\u0101n-e Masjid",
        "\u062f\u0647\u0627\u0646 \u0645\u0633\u062c\u062f",
        "Dahan-e Masjed"
    ],
    "wof:name":"Dahan-e Masjid",
    "wof:placetype":"locality"
},
  "geometry": {"coordinates":[63.97016,33.85533],"type":"Point"}
}