{
  "type": "Feature",
  "properties": {
    "gn:admin1_code":"23",
    "gn:admin2_code":"2408.0",
    "gn:asciiname":"Muhammad Akram",
    "gn:country_code":"AF",
    "gn:dem":941,
    "gn:feature_class":"P",
    "gn:feature_code":"PPL",
    "gn:name":"Mu\u1e29ammad Akram",
    "gn:population":0,
    "gn:timezone":"Asia/Kabul",
    "iso:country":"AF",
    "name:pnb_x_preferred":[
        "\u0645\u062d\u0645\u062f \u0627\u06a9\u0631\u0645"
    ],
    "name:rus_x_preferred":[
        "\u0410\u043a\u0440\u0430\u043c"
    ],
    "name:und_x_variant":[
        "Mukhammedakram",
        "Mu\u1e29ammad Akram",
        "\u0645\u062d\u0645\u062f \u0627\u06a9\u0631\u0645",
        "Mo\u1e29ammad Akram"
    ],
    "name:urd_x_preferred":[
        "\u0645\u062d\u0645\u062f \u0627\u06a9\u0631\u0645"
    ],
    "wof:name":"Muhammad Akram",
    "wof:placetype":"locality"
},
  "geometry": {"coordinates":[65.46552,31.53396],"type":"Point"}
}