{
  "type": "Feature",
  "properties": {
    "gn:admin1_code":"08",
    "gn:admin2_code":"613",
    "gn:asciiname":"Qishlaqak",
    "gn:country_code":"AF",
    "gn:dem":2635,
    "gn:feature_class":"P",
    "gn:feature_code":"PPL",
    "gn:name":"Qishl\u0101qak",
    "gn:population":0,
    "gn:timezone":"Asia/Kabul",
    "iso:country":"AF",
    "name:fas_x_preferred":[
        "\u0642\u0634\u0644\u0627\u0642\u0643"
    ],
    "name:und_x_variant":[
        "Kyshlagak",
        "Qe\u0161l\u0101ghak",
        "Qeshl\u0101qak",
        "Qeshl\u0101ghak",
        "Qishl\u0101qak",
        "\u0642\u0634\u0644\u0627\u0642\u06a9"
    ],
    "wof:name":"Qishlaqak",
    "wof:placetype":"locality"
},
  "geometry": {"coordinates":[68.04715,33.37341],"type":"Point"}
}