{
  "type": "Feature",
  "properties": {
    "gn:admin1_code":"13",
    "gn:admin2_code":"107.0",
    "gn:asciiname":"Qal'ah-ye Sadr-e A'zam",
    "gn:country_code":"AF",
    "gn:dem":1880,
    "gn:feature_class":"P",
    "gn:feature_code":"PPL",
    "gn:name":"Qal\u2018ah-ye \u015eadr-e A\u2018z\u0327am",
    "gn:population":0,
    "gn:timezone":"Asia/Kabul",
    "iso:country":"AF",
    "name:und_x_variant":[
        "Kalasadri-Azam",
        "Qal\u2018a \u015ea\u1e0f\u1e5fe A\u2018\u1e95am",
        "Qal\u2018ah-ye \u015eadr-e A\u2018z\u0327am",
        "Qal\u2018eh-ye \u015eadr-e A\u2018z\u0327am",
        "Qal\u2018ah-ye \u015eadr-i\u0101\u2018z\u0327am",
        "\u0642\u0644\u0639\u06c0 \u0635\u062f\u0631 \u0627\u0639\u0638\u0645"
    ],
    "wof:name":"Qal'ah-ye Sadr-e A'zam",
    "wof:placetype":"locality"
},
  "geometry": {"coordinates":[69.06511999999999,34.65319],"type":"Point"}
}