{
  "type": "Feature",
  "properties": {
    "gn:admin1_code":"23",
    "gn:admin2_code":"2408.0",
    "gn:asciiname":"Badwan",
    "gn:country_code":"AF",
    "gn:dem":953,
    "gn:feature_class":"P",
    "gn:feature_code":"PPL",
    "gn:name":"Badw\u0101n",
    "gn:population":0,
    "gn:timezone":"Asia/Kabul",
    "iso:country":"AF",
    "name:und_x_variant":[
        "Ba\u1e0fw\u0101n",
        "Badvan",
        "Badv\u0101n",
        "Badw\u0101n",
        "\u0628\u062f\u0648\u0627\u0646"
    ],
    "wof:name":"Badwan",
    "wof:placetype":"locality"
},
  "geometry": {"coordinates":[65.48373000000001,31.57198],"type":"Point"}
}