{
  "type": "Feature",
  "properties": {
    "gn:admin1_code":"07",
    "gn:admin2_code":"1802.0",
    "gn:asciiname":"Karez-e Qal'ah",
    "gn:country_code":"AF",
    "gn:dem":759,
    "gn:feature_class":"P",
    "gn:feature_code":"PPL",
    "gn:name":"K\u0101r\u0113z-e Qal\u2018ah",
    "gn:population":0,
    "gn:timezone":"Asia/Kabul",
    "iso:country":"AF",
    "name:und_x_variant":[
        "Karez-i-qala",
        "K\u0101r\u0113z-e Qal\u2018ah",
        "\u06a9\u0627\u0631\u06d0\u0632 \u0642\u0644\u0639\u0647",
        "Kar\u012bz-e Qaleh"
    ],
    "wof:name":"Karez-e Qal'ah",
    "wof:placetype":"locality"
},
  "geometry": {"coordinates":[64.72829,35.98651],"type":"Point"}
}