{
  "type": "Feature",
  "properties": {
    "gn:admin1_code":"01",
    "gn:admin2_code":"1102",
    "gn:asciiname":"Namazgah",
    "gn:country_code":"AF",
    "gn:dem":1069,
    "gn:feature_class":"P",
    "gn:feature_code":"PPL",
    "gn:name":"Nam\u0101zg\u0101h",
    "gn:population":0,
    "gn:timezone":"Asia/Kabul",
    "iso:country":"AF",
    "name:rus_x_preferred":[
        "\u041d\u0430\u043c\u0430\u0437\u0433\u0430\u0445"
    ],
    "name:tur_x_preferred":[
        "Namazgah"
    ],
    "name:und_x_variant":[
        "Nam\u0101zga",
        "Nam\u0101zg\u0101h",
        "\u0646\u0645\u0627\u0632\u06af\u0627\u0647"
    ],
    "wof:name":"Namazgah",
    "wof:placetype":"locality"
},
  "geometry": {"coordinates":[70.13973,36.76843],"type":"Point"}
}