{
  "type": "Feature",
  "properties": {
    "gn:admin1_code":"18",
    "gn:admin2_code":"805.0",
    "gn:asciiname":"Qayyum Khel",
    "gn:country_code":"AF",
    "gn:dem":1138,
    "gn:feature_class":"P",
    "gn:feature_code":"PPL",
    "gn:name":"Qayy\u016bm Kh\u0113l",
    "gn:population":0,
    "gn:timezone":"Asia/Kabul",
    "iso:country":"AF",
    "name:fas_x_preferred":[
        "\u0642\u064a\u0648\u0645 \u062e\u064a\u0644"
    ],
    "name:rus_x_preferred":[
        "Kayumkheyl\u2019"
    ],
    "name:und_x_variant":[
        "Qay\u016bm Kh\u0113l",
        "Qay\u016bmkheyl",
        "Qayy\u016bm Kh\u0113l",
        "\u0642\u06cc\u0648\u0645 \u062e\u06d0\u0644"
    ],
    "wof:name":"Qayyum Khel",
    "wof:placetype":"locality"
},
  "geometry": {"coordinates":[70.10736,34.2916],"type":"Point"}
}