{
  "type": "Feature",
  "properties": {
    "gn:admin1_code":"34",
    "gn:admin2_code":"1008.0",
    "gn:asciiname":"Mullayano Kelay",
    "gn:country_code":"AF",
    "gn:dem":929,
    "gn:feature_class":"P",
    "gn:feature_code":"PPL",
    "gn:name":"Mull\u0101y\u0101n\u014d K\u00ealay",
    "gn:population":0,
    "gn:timezone":"Asia/Kabul",
    "iso:country":"AF",
    "name:fas_x_preferred":[
        "\u0642\u0631\u064a\u06c0 \u0645\u0644\u0627 \u064a\u0627\u0646\u0648"
    ],
    "name:und_x_variant":[
        "Molayanokalay",
        "Mol\u0101y\u0101nokalay",
        "Mull\u0101y\u0101n\u014d K\u00ealay",
        "\u0645\u0644\u0627\u06cc\u0627\u0646\u0648 \u06a9\u0644\u06cc"
    ],
    "wof:name":"Mullayano Kelay",
    "wof:placetype":"locality"
},
  "geometry": {"coordinates":[71.09624000000002,34.93462],"type":"Point"}
}