{
  "type": "Feature",
  "properties": {
    "gn:admin1_code":"5",
    "gn:admin2_code":"2804.0",
    "gn:asciiname":"Baydak",
    "gn:country_code":"AF",
    "gn:dem":2080,
    "gn:feature_class":"P",
    "gn:feature_code":"PPL",
    "gn:name":"Baydak",
    "gn:population":0,
    "gn:timezone":"Asia/Kabul",
    "iso:country":"AF",
    "name:und_x_variant":[
        "B\u0113\u1e0fak",
        "B\u012bdak",
        "Baydak",
        "\u0628\u06cc\u062f\u06a9"
    ],
    "wof:name":"Baydak",
    "wof:placetype":"locality"
},
  "geometry": {"coordinates":[66.38974,35.11587],"type":"Point"}
}