{
  "type": "Feature",
  "properties": {
    "gn:admin1_code":"36",
    "gn:admin2_code":"702",
    "gn:asciiname":"Marzak",
    "gn:country_code":"AF",
    "gn:dem":2575,
    "gn:feature_class":"P",
    "gn:feature_code":"PPL",
    "gn:name":"M\u0101rzak",
    "gn:population":0,
    "gn:timezone":"Asia/Kabul",
    "iso:country":"AF",
    "name:fas_x_preferred":[
        "\u0645\u0627\u0631\u0632\u0643"
    ],
    "name:fas_x_variant":[
        "\u0645\u0631\u0632\u06a9"
    ],
    "name:und_x_variant":[
        "M\u0101rz\u00eak",
        "M\u0101rzak",
        "\u0645\u0627\u0631\u0632\u06a9"
    ],
    "wof:name":"Marzak",
    "wof:placetype":"locality"
},
  "geometry": {"coordinates":[69.19365000000001,33.35002],"type":"Point"}
}