{
  "type": "Feature",
  "properties": {
    "gn:admin1_code":"27",
    "gn:admin2_code":"409",
    "gn:asciiname":"Deh-e Mirdad Kunjghatu",
    "gn:country_code":"AF",
    "gn:dem":2697,
    "gn:feature_class":"P",
    "gn:feature_code":"PPL",
    "gn:name":"Deh-e M\u012brd\u0101d K\u016bnjghat\u016b",
    "gn:population":0,
    "gn:timezone":"Asia/Kabul",
    "iso:country":"AF",
    "name:fas_x_preferred":[
        "\u062f\u0647\u0654 \u0645\u064a\u0631\u062f\u0627\u062f \u06a9\u0646\u062c\u063a\u062a\u0648"
    ],
    "name:und_x_variant":[
        "Dekhi-Mirdadkundzhgatu",
        "Deh-e M\u012brd\u0101d K\u016bnj Ghat\u016b",
        "Deh-e M\u012brd\u0101d Kunjghatu",
        "Deh-e M\u012brd\u0101d K\u016bnjghat\u016b",
        "\u062f\u0647 \u0645\u06cc\u0631\u062f\u0627\u062f \u06a9\u0648\u0646\u062c\u063a\u062a\u0648"
    ],
    "wof:name":"Deh-e Mirdad Kunjghatu",
    "wof:placetype":"locality"
},
  "geometry": {"coordinates":[68.38814000000001,33.99615],"type":"Point"}
}