{
  "type": "Feature",
  "properties": {
    "gn:admin1_code":"28",
    "gn:admin2_code":"2505.0",
    "gn:asciiname":"Khwajah Guk",
    "gn:country_code":"AF",
    "gn:dem":1508,
    "gn:feature_class":"P",
    "gn:feature_code":"PPL",
    "gn:name":"Khw\u0101jah G\u016bk",
    "gn:population":0,
    "gn:timezone":"Asia/Kabul",
    "iso:country":"AF",
    "name:und_x_variant":[
        "Khodzhaguk",
        "Khw\u0101ja G\u016bk",
        "Khw\u0101jah G\u016bk",
        "\u062e\u0648\u0627\u062c\u0647 \u06af\u0648\u06a9",
        "Khv\u0101jeh G\u016bk"
    ],
    "wof:name":"Khwajah Guk",
    "wof:placetype":"locality"
},
  "geometry": {"coordinates":[66.40241,32.22459],"type":"Point"}
}