{
  "type": "Feature",
  "properties": {
    "gn:admin1_code":"24",
    "gn:admin2_code":"1406",
    "gn:asciiname":"Shor Aw",
    "gn:country_code":"AF",
    "gn:dem":645,
    "gn:feature_class":"P",
    "gn:feature_code":"PPL",
    "gn:name":"Sh\u014dr \u0100w",
    "gn:population":0,
    "gn:timezone":"Asia/Kabul",
    "iso:country":"AF",
    "name:fas_x_preferred":[
        "\u0634\u0648\u0631\u0627\u0628"
    ],
    "name:rus_x_preferred":[
        "\u0428\u043e\u0440\u0430\u0432"
    ],
    "name:und_x_variant":[
        "Shorav",
        "\u0160or\u0101w",
        "Sh\u016br\u0101b",
        "Sh\u014dr \u0100w",
        "\u0634\u0648\u0631 \u0622\u0648"
    ],
    "wof:name":"Shor Aw",
    "wof:placetype":"locality"
},
  "geometry": {"coordinates":[69.04562,36.54888],"type":"Point"}
}