{
  "type": "Feature",
  "properties": {
    "gn:admin1_code":"13",
    "gn:admin2_code":"105",
    "gn:asciiname":"Sabz Sang",
    "gn:country_code":"AF",
    "gn:dem":1585,
    "gn:feature_class":"P",
    "gn:feature_code":"PPL",
    "gn:name":"Sabz Sang",
    "gn:population":0,
    "gn:timezone":"Asia/Kabul",
    "iso:country":"AF",
    "name:und_x_variant":[
        "Sauzsang",
        "Sawzsang",
        "Sabz Sang",
        "\u0633\u0628\u0632 \u0633\u0646\u06af"
    ],
    "wof:name":"Sabz Sang",
    "wof:placetype":"locality"
},
  "geometry": {"coordinates":[69.14461999999999,34.8173],"type":"Point"}
}