{
  "type": "Feature",
  "properties": {
    "gn:admin1_code":"06",
    "gn:admin2_code":"2108",
    "gn:asciiname":"Kalatah-ye Haji Rasul",
    "gn:country_code":"AF",
    "gn:dem":602,
    "gn:feature_class":"P",
    "gn:feature_code":"PPL",
    "gn:name":"Kal\u0101tah-ye \u1e28\u0101j\u012b Ras\u016bl",
    "gn:population":0,
    "gn:timezone":"Asia/Kabul",
    "iso:country":"AF",
    "name:und_x_variant":[
        "Kal\u0101ta-i- H\u0101ji \u1e5eas\u016bl",
        "Kal\u0101teh-ye \u1e28\u0101jj\u012b Ras\u016bl",
        "Kal\u0101tah-ye \u1e28\u0101j\u012b Ras\u016bl",
        "\u06a9\u0644\u0627\u062a\u0647 \u062d\u0627\u062c\u06cc \u0631\u0633\u0648\u0644"
    ],
    "wof:name":"Kalatah-ye Haji Rasul",
    "wof:placetype":"locality"
},
  "geometry": {"coordinates":[61.3802,32.31414],"type":"Point"}
}