{
  "type": "Feature",
  "properties": {
    "gn:admin1_code":"01",
    "gn:admin2_code":"1113.0",
    "gn:asciiname":"Rabat-e Hamdin",
    "gn:country_code":"AF",
    "gn:dem":2009,
    "gn:feature_class":"P",
    "gn:feature_code":"PPL",
    "gn:name":"Rab\u0101\u0163-e Hamd\u012bn",
    "gn:population":0,
    "gn:timezone":"Asia/Kabul",
    "iso:country":"AF",
    "name:und_x_variant":[
        "Rab\u0101t-i-Ham\u1e0f\u012bn",
        "Rob\u0101\u0163-e Hamd\u012bn",
        "Rab\u0101\u0163-e Hamd\u012bn",
        "\u0631\u0628\u0627\u0637 \u0647\u0645\u062f\u06cc\u0646"
    ],
    "wof:name":"Rabat-e Hamdin",
    "wof:placetype":"locality"
},
  "geometry": {"coordinates":[70.04579,37.39669],"type":"Point"}
}