{
  "type": "Feature",
  "properties": {
    "gn:admin1_code":"11",
    "gn:admin2_code":"2010",
    "gn:asciiname":"Ghowgha",
    "gn:country_code":"AF",
    "gn:dem":863,
    "gn:feature_class":"P",
    "gn:feature_code":"PPL",
    "gn:name":"Ghowgh\u0101",
    "gn:population":0,
    "gn:timezone":"Asia/Kabul",
    "iso:country":"AF",
    "name:und_x_variant":[
        "Ghawgh\u0101",
        "Ghowgh\u0101",
        "\u063a\u0648\u063a\u0627"
    ],
    "wof:name":"Ghowgha",
    "wof:placetype":"locality"
},
  "geometry": {"coordinates":[61.91919,34.35817],"type":"Point"}
}