{
  "type": "Feature",
  "properties": {
    "gn:admin1_code":"39",
    "gn:admin2_code":"2601.0",
    "gn:asciiname":"Chinah Ab",
    "gn:country_code":"AF",
    "gn:dem":1361,
    "gn:feature_class":"P",
    "gn:feature_code":"PPL",
    "gn:name":"Ch\u012bnah \u0100b",
    "gn:population":0,
    "gn:timezone":"Asia/Kabul",
    "iso:country":"AF",
    "name:und_x_variant":[
        "Chinaab",
        "\u010cina \u0100b",
        "Ch\u012bnah \u0100b",
        "\u0686\u06cc\u0646\u0647 \u0622\u0628",
        "Chinah \u0100b"
    ],
    "wof:name":"Chinah Ab",
    "wof:placetype":"locality"
},
  "geometry": {"coordinates":[65.93445,32.65055],"type":"Point"}
}