{
  "type": "Feature",
  "properties": {
    "gn:admin1_code":"5",
    "gn:admin2_code":"2806.0",
    "gn:asciiname":"Awparan",
    "gn:country_code":"AF",
    "gn:dem":2821,
    "gn:feature_class":"P",
    "gn:feature_code":"PPL",
    "gn:name":"\u0100wpar\u0101n",
    "gn:population":0,
    "gn:timezone":"Asia/Kabul",
    "iso:country":"AF",
    "name:und_x_variant":[
        "Awpa\u1e5f\u0101n",
        "Avparan",
        "\u0100wpar\u0101n",
        "\u0100bpar\u0101n",
        "\u0622\u0648\u067e\u0631\u0627\u0646"
    ],
    "wof:name":"Awparan",
    "wof:placetype":"locality"
},
  "geometry": {"coordinates":[66.87399000000001,34.19311],"type":"Point"}
}