{
  "type": "Feature",
  "properties": {
    "gn:admin1_code":"36",
    "gn:admin2_code":"707.0",
    "gn:asciiname":"Landay",
    "gn:country_code":"AF",
    "gn:dem":1619,
    "gn:feature_class":"P",
    "gn:feature_code":"PPL",
    "gn:name":"Lan\u1e0fay",
    "gn:population":0,
    "gn:timezone":"Asia/Kabul",
    "iso:country":"AF",
    "name:slv_x_preferred":[
        "Landaj"
    ],
    "name:und_x_variant":[
        "Landai",
        "Lan\u1e0fay",
        "\u0644\u0646\u0689\u06cc",
        "Landay"
    ],
    "wof:name":"Landay",
    "wof:placetype":"locality"
},
  "geometry": {"coordinates":[69.90371,33.81832],"type":"Point"}
}