{
  "type": "Feature",
  "properties": {
    "gn:admin1_code":"10",
    "gn:admin2_code":"2303",
    "gn:asciiname":"Dayhak",
    "gn:country_code":"AF",
    "gn:dem":1192,
    "gn:feature_class":"P",
    "gn:feature_code":"PPL",
    "gn:name":"Dayhak",
    "gn:population":0,
    "gn:timezone":"Asia/Kabul",
    "iso:country":"AF",
    "name:und_x_variant":[
        "Di Yak",
        "Dekhak",
        "Dayhak",
        "\u062f\u06cc\u0647\u06a9",
        "D\u0113hak"
    ],
    "wof:name":"Dayhak",
    "wof:placetype":"locality"
},
  "geometry": {"coordinates":[65.05325999999999,32.51495999999999],"type":"Point"}
}