{
  "type": "Feature",
  "properties": {
    "gn:admin1_code":"27",
    "gn:admin2_code":"405",
    "gn:asciiname":"Jowr Sang",
    "gn:country_code":"AF",
    "gn:dem":2945,
    "gn:feature_class":"P",
    "gn:feature_code":"PPL",
    "gn:name":"Jowr Sang",
    "gn:population":0,
    "gn:timezone":"Asia/Kabul",
    "iso:country":"AF",
    "name:und_x_variant":[
        "Dzhaursang",
        "Jowr Sang",
        "Jawrsang",
        "\u062c\u0648\u0631 \u0633\u0646\u06af"
    ],
    "wof:name":"Jowr Sang",
    "wof:placetype":"locality"
},
  "geometry": {"coordinates":[68.285,34.36917],"type":"Point"}
}