{
  "type": "Feature",
  "properties": {
    "gn:admin1_code":"09",
    "gn:admin2_code":"2701",
    "gn:asciiname":"Sadiq 'Ali",
    "gn:country_code":"AF",
    "gn:dem":2390,
    "gn:feature_class":"P",
    "gn:feature_code":"PPL",
    "gn:name":"\u015ead\u012bq \u2018Al\u012b",
    "gn:population":0,
    "gn:timezone":"Asia/Kabul",
    "iso:country":"AF",
    "name:und_x_variant":[
        "\u015ead\u012bq \u2018Al\u012b",
        "\u0635\u062f\u06cc\u0642 \u0639\u0644\u06cc",
        "\u015eedq\u2018ali"
    ],
    "wof:name":"Sadiq 'Ali",
    "wof:placetype":"locality"
},
  "geometry": {"coordinates":[65.03187,34.40153],"type":"Point"}
}