{
  "type": "Feature",
  "properties": {
    "gn:admin1_code":"02",
    "gn:admin2_code":"1904",
    "gn:asciiname":"Sar-e Langar",
    "gn:country_code":"AF",
    "gn:dem":2070,
    "gn:feature_class":"P",
    "gn:feature_code":"PPL",
    "gn:name":"Sar-e Langar",
    "gn:population":0,
    "gn:timezone":"Asia/Kabul",
    "iso:country":"AF",
    "name:und_x_variant":[
        "\u0633\u0631 \u0644\u0646\u06af\u0631"
    ],
    "wof:name":"Sar-e Langar",
    "wof:placetype":"locality"
},
  "geometry": {"coordinates":[64.59189000000001,35.0943],"type":"Point"}
}