{
  "type": "Feature",
  "properties": {
    "gn:admin1_code":"23",
    "gn:admin2_code":"2412",
    "gn:asciiname":"Dirishah",
    "gn:country_code":"AF",
    "gn:dem":1526,
    "gn:feature_class":"P",
    "gn:feature_code":"PPL",
    "gn:name":"Dirishah",
    "gn:population":0,
    "gn:timezone":"Asia/Kabul",
    "iso:country":"AF",
    "name:und_x_variant":[
        "Dirisha",
        "Deresha",
        "Dere\u0161a",
        "Dirishah",
        "\u062f\u0631\u0634\u0647",
        "Dereshah"
    ],
    "wof:name":"Dirishah",
    "wof:placetype":"locality"
},
  "geometry": {"coordinates":[66.85969,31.62354],"type":"Point"}
}