{
  "type": "Feature",
  "properties": {
    "gn:admin1_code":"41",
    "gn:admin2_code":"3407.0",
    "gn:asciiname":"Shah Bayd",
    "gn:country_code":"AF",
    "gn:dem":2423,
    "gn:feature_class":"P",
    "gn:feature_code":"PPL",
    "gn:name":"Sh\u0101h Bayd",
    "gn:population":0,
    "gn:timezone":"Asia/Kabul",
    "iso:country":"AF",
    "name:und_x_variant":[
        "S\u0101hb\u0113\u1e0f",
        "Sh\u0101hb\u012bd",
        "Sh\u0101h Bayd",
        "\u0634\u0627\u0647 \u0628\u06cc\u062f"
    ],
    "wof:name":"Shah Bayd",
    "wof:placetype":"locality"
},
  "geometry": {"coordinates":[67.0033,33.8776],"type":"Point"}
}