{
  "type": "Feature",
  "properties": {
    "gn:admin1_code":"6",
    "gn:admin2_code":"2105.0",
    "gn:asciiname":"Khwajah Khizir",
    "gn:country_code":"AF",
    "gn:dem":759,
    "gn:feature_class":"P",
    "gn:feature_code":"PPL",
    "gn:name":"Khw\u0101jah Khi\u1e95ir",
    "gn:population":0,
    "gn:timezone":"Asia/Kabul",
    "iso:country":"AF",
    "name:und_x_variant":[
        "Khodzha-Khizir",
        "Khw\u0101ja Khe\u1e0f\u1e95e\u1e5f",
        "Khv\u0101jeh Khe\u1e95er",
        "Khw\u0101jah Khi\u1e95ir",
        "\u062e\u0648\u0627\u062c\u0647 \u062e\u0636\u0631"
    ],
    "wof:name":"Khwajah Khizir",
    "wof:placetype":"locality"
},
  "geometry": {"coordinates":[62.50705,32.6245],"type":"Point"}
}