{
  "type": "Feature",
  "properties": {
    "gn:admin1_code":"23",
    "gn:admin2_code":"2403.0",
    "gn:asciiname":"Daragay",
    "gn:country_code":"AF",
    "gn:dem":1295,
    "gn:feature_class":"P",
    "gn:feature_code":"PPL",
    "gn:name":"Daragay",
    "gn:population":0,
    "gn:timezone":"Asia/Kabul",
    "iso:country":"AF",
    "name:und_x_variant":[
        "\u062f\u0631\u06af\u06cc",
        "Daragay"
    ],
    "wof:name":"Daragay",
    "wof:placetype":"locality"
},
  "geometry": {"coordinates":[66.18300000000001,31.9188],"type":"Point"}
}