{
  "type": "Feature",
  "properties": {
    "gn:admin1_code":"28",
    "gn:admin2_code":"2506.0",
    "gn:asciiname":"Zare Khune",
    "gn:country_code":"AF",
    "gn:dem":1362,
    "gn:feature_class":"P",
    "gn:feature_code":"PPL",
    "gn:name":"Za\u1e5f\u0113 Kh\u016bn\u0113",
    "gn:population":0,
    "gn:timezone":"Asia/Kabul",
    "iso:country":"AF",
    "name:und_x_variant":[
        "Zar\u0113 Kh\u016bn\u0113",
        "Zari-Khuna",
        "\u0632\u0693\u06d0 \u062e\u0648\u0646\u06d0",
        "Zar\u012b Kh\u016bn\u012b",
        "Za\u1e5f\u0113 Kh\u016bn\u0113"
    ],
    "wof:name":"Zare Khune",
    "wof:placetype":"locality"
},
  "geometry": {"coordinates":[66.39933000000001,31.87809],"type":"Point"}
}