{
  "type": "Feature",
  "properties": {
    "gn:admin1_code":"40",
    "gn:admin2_code":"303",
    "gn:asciiname":"Mianahgi",
    "gn:country_code":"AF",
    "gn:dem":2746,
    "gn:feature_class":"P",
    "gn:feature_code":"PPL",
    "gn:name":"M\u012b\u0101nahg\u012b",
    "gn:population":0,
    "gn:timezone":"Asia/Kabul",
    "iso:country":"AF",
    "name:fas_x_preferred":[
        "\u0645\u06cc\u0627\u0646\u06af\u06cc"
    ],
    "name:und_x_variant":[
        "My\u0101nagi",
        "Mianagi",
        "M\u012b\u0101nag\u012b",
        "M\u012b\u0101nahg\u012b",
        "\u0645\u06cc\u0627\u0646\u0647 \u06af\u06cc"
    ],
    "wof:name":"Mianahgi",
    "wof:placetype":"locality"
},
  "geometry": {"coordinates":[69.0921,35.29152],"type":"Point"}
}