{
  "type": "Feature",
  "properties": {
    "gn:admin1_code":"27",
    "gn:admin2_code":"404.0",
    "gn:asciiname":"Arg",
    "gn:country_code":"AF",
    "gn:dem":2797,
    "gn:feature_class":"P",
    "gn:feature_code":"PPL",
    "gn:name":"Arg",
    "gn:population":0,
    "gn:timezone":"Asia/Kabul",
    "iso:country":"AF",
    "name:und_x_variant":[
        "\u0627\u0631\u06af"
    ],
    "wof:name":"Arg",
    "wof:placetype":"locality"
},
  "geometry": {"coordinates":[67.40541,34.4819],"type":"Point"}
}