{
  "type": "Feature",
  "properties": {
    "gn:admin1_code":"09",
    "gn:admin2_code":"2710",
    "gn:asciiname":"Garmabak",
    "gn:country_code":"AF",
    "gn:dem":2703,
    "gn:feature_class":"P",
    "gn:feature_code":"PPL",
    "gn:name":"Garm\u0101bak",
    "gn:population":0,
    "gn:timezone":"Asia/Kabul",
    "iso:country":"AF",
    "name:ara_x_preferred":[
        "\u063a\u0631\u0645\u0627\u0628\u0643"
    ],
    "name:fas_x_preferred":[
        "\u06af\u0631\u0645\u0627\u0628\u06a9"
    ],
    "name:und_x_variant":[
        "Garm\u0101bak",
        "\u06af\u0631\u0645\u0627\u0628\u06a9"
    ],
    "wof:name":"Garmabak",
    "wof:placetype":"locality"
},
  "geometry": {"coordinates":[64.83530999999999,34.01571],"type":"Point"}
}