{
  "type": "Feature",
  "properties": {
    "gn:admin1_code":"27",
    "gn:admin2_code":"406",
    "gn:asciiname":"Manjar Khel",
    "gn:country_code":"AF",
    "gn:dem":2626,
    "gn:feature_class":"P",
    "gn:feature_code":"PPL",
    "gn:name":"M\u0101njar Kh\u0113l",
    "gn:population":0,
    "gn:timezone":"Asia/Kabul",
    "iso:country":"AF",
    "name:rus_x_preferred":[
        "Mandzharkheyl\u2019"
    ],
    "name:und_x_variant":[
        "M\u0101nja\u1e5fkh\u0113l",
        "M\u0101njarkheyl",
        "M\u0101njar Kh\u0113l",
        "\u0645\u0627\u0646\u062c\u0631 \u062e\u06d0\u0644"
    ],
    "wof:name":"Manjar Khel",
    "wof:placetype":"locality"
},
  "geometry": {"coordinates":[68.35429000000001,34.02882],"type":"Point"}
}