{
  "type": "Feature",
  "properties": {
    "gn:admin1_code":"40",
    "gn:admin2_code":"308.0",
    "gn:asciiname":"Qal'ah-ye Now",
    "gn:country_code":"AF",
    "gn:dem":1501,
    "gn:feature_class":"P",
    "gn:feature_code":"PPL",
    "gn:name":"Qal\u2018ah-ye Now",
    "gn:population":0,
    "gn:timezone":"Asia/Kabul",
    "iso:country":"AF",
    "name:und_x_variant":[
        "Kala-Nau",
        "Qal\u2019eh-ye Naw",
        "Qal\u2018a Naw",
        "Qal\u2018eh-ye Now",
        "\u0642\u0644\u0639\u06c0 \u0646\u0648",
        "Qal\u2018ah-ye Now"
    ],
    "wof:name":"Qal'ah-ye Now",
    "wof:placetype":"locality"
},
  "geometry": {"coordinates":[69.21003,34.96582],"type":"Point"}
}