{
  "type": "Feature",
  "properties": {
    "gn:admin1_code":"09",
    "gn:admin2_code":"2703.0",
    "gn:asciiname":"Pilband",
    "gn:country_code":"AF",
    "gn:dem":2270,
    "gn:feature_class":"P",
    "gn:feature_code":"PPL",
    "gn:name":"Pilband",
    "gn:population":0,
    "gn:timezone":"Asia/Kabul",
    "iso:country":"AF",
    "name:und_x_variant":[
        "Pelband",
        "\u067e\u0644\u0628\u0646\u062f"
    ],
    "wof:name":"Pilband",
    "wof:placetype":"locality"
},
  "geometry": {"coordinates":[63.86059,34.19605],"type":"Point"}
}