{
  "type": "Feature",
  "properties": {
    "gn:admin1_code":"27",
    "gn:admin2_code":"406",
    "gn:asciiname":"Karam 'Ali",
    "gn:country_code":"AF",
    "gn:dem":2328,
    "gn:feature_class":"P",
    "gn:feature_code":"PPL",
    "gn:name":"Karam \u2018Al\u012b",
    "gn:population":0,
    "gn:timezone":"Asia/Kabul",
    "iso:country":"AF",
    "name:und_x_variant":[
        "Karamalay",
        "Ka\u1e5fam\u2018alay",
        "Karam \u2018Al\u012b",
        "Karam\u2018al\u012b",
        "\u06a9\u0631\u0645 \u0639\u0644\u06cc"
    ],
    "wof:name":"Karam 'Ali",
    "wof:placetype":"locality"
},
  "geometry": {"coordinates":[68.50785999999999,34.20052],"type":"Point"}
}