{
  "type": "Feature",
  "properties": {
    "gn:admin1_code":"28",
    "gn:admin2_code":"2505",
    "gn:asciiname":"Garnalah",
    "gn:country_code":"AF",
    "gn:dem":1411,
    "gn:feature_class":"P",
    "gn:feature_code":"PPL",
    "gn:name":"Garn\u0101lah",
    "gn:population":0,
    "gn:timezone":"Asia/Kabul",
    "iso:country":"AF",
    "name:und_x_variant":[
        "Garnala",
        "Ga\u1e5fn\u0101la",
        "Garn\u0101lah",
        "\u06af\u0631\u0646\u0627\u0644\u0647"
    ],
    "wof:name":"Garnalah",
    "wof:placetype":"locality"
},
  "geometry": {"coordinates":[66.59484999999999,32.2765],"type":"Point"}
}