{
  "type": "Feature",
  "properties": {
    "gn:admin1_code":"2",
    "gn:admin2_code":"1901.0",
    "gn:asciiname":"Kharistan",
    "gn:country_code":"AF",
    "gn:dem":990,
    "gn:feature_class":"P",
    "gn:feature_code":"PPL",
    "gn:name":"Kh\u0101rist\u0101n",
    "gn:population":0,
    "gn:timezone":"Asia/Kabul",
    "iso:country":"AF",
    "name:und_x_variant":[
        "Kh\u0101\u1e5fist\u0101n",
        "Kh\u0101rist\u0101n",
        "\u062e\u0627\u0631\u0633\u062a\u0627\u0646",
        "Kh\u0101rest\u0101n"
    ],
    "wof:name":"Kharistan",
    "wof:placetype":"locality"
},
  "geometry": {"coordinates":[63.21213,34.9512],"type":"Point"}
}