{
  "type": "Feature",
  "properties": {
    "gn:admin1_code":"41",
    "gn:admin2_code":"3408",
    "gn:asciiname":"Yar Minah",
    "gn:country_code":"AF",
    "gn:dem":2686,
    "gn:feature_class":"P",
    "gn:feature_code":"PPL",
    "gn:name":"Y\u0101r M\u012bnah",
    "gn:population":0,
    "gn:timezone":"Asia/Kabul",
    "iso:country":"AF",
    "name:und_x_variant":[
        "Y\u0101\u1e5fm\u012bna",
        "Yarmina",
        "Y\u0101r M\u012bnah",
        "\u06cc\u0627\u0631 \u0645\u06cc\u0646\u0647"
    ],
    "wof:name":"Yar Minah",
    "wof:placetype":"locality"
},
  "geometry": {"coordinates":[65.88663000000001,34.21252],"type":"Point"}
}