{
  "type": "Feature",
  "properties": {
    "gn:admin1_code":"27",
    "gn:admin2_code":"409",
    "gn:asciiname":"Khalifah Baba Khel",
    "gn:country_code":"AF",
    "gn:dem":2460,
    "gn:feature_class":"P",
    "gn:feature_code":"PPL",
    "gn:name":"Khal\u012bfah B\u0101b\u0101 Kh\u0113l",
    "gn:population":0,
    "gn:timezone":"Asia/Kabul",
    "iso:country":"AF",
    "name:fas_x_preferred":[
        "\u062e\u0644\u064a\u0641\u0647 \u0628\u0627\u0628\u0627 \u062e\u064a\u0644"
    ],
    "name:rus_x_preferred":[
        "Khalifa-Babakheyl\u2019"
    ],
    "name:und_x_variant":[
        "Khal\u012bfa",
        "Khal\u012bfeh",
        "Khalifa B\u0101b\u0101kh\u0113l",
        "Khal\u012bfah B\u0101b\u0101 Kh\u0113l",
        "Khal\u012bfeh B\u0101b\u0101 Kheyl",
        "\u062e\u0644\u064a\u0641\u0647 \u0628\u0627\u0628\u0627 \u062e\u06d0\u0644"
    ],
    "wof:name":"Khalifah Baba Khel",
    "wof:placetype":"locality"
},
  "geometry": {"coordinates":[68.36496,33.79567],"type":"Point"}
}