{
  "type": "Feature",
  "properties": {
    "gn:admin1_code":"8",
    "gn:admin2_code":"609.0",
    "gn:asciiname":"Shamardan",
    "gn:country_code":"AF",
    "gn:dem":1942,
    "gn:feature_class":"P",
    "gn:feature_code":"PPL",
    "gn:name":"Sh\u0101mard\u0101n",
    "gn:population":0,
    "gn:timezone":"Asia/Kabul",
    "iso:country":"AF",
    "name:und_x_variant":[
        "\u0160\u0101mard\u0101n",
        "Sh\u0101mard\u0101n",
        "\u0634\u0627\u0645\u0631\u062f\u0627\u0646"
    ],
    "wof:name":"Shamardan",
    "wof:placetype":"locality"
},
  "geometry": {"coordinates":[67.70477,32.68066],"type":"Point"}
}