{
  "type": "Feature",
  "properties": {
    "gn:admin1_code":"05",
    "gn:admin2_code":"2805",
    "gn:asciiname":"Shiwnah Deh",
    "gn:country_code":"AF",
    "gn:dem":2899,
    "gn:feature_class":"P",
    "gn:feature_code":"PPL",
    "gn:name":"Shiwnah Deh",
    "gn:population":0,
    "gn:timezone":"Asia/Kabul",
    "iso:country":"AF",
    "name:und_x_variant":[
        "\u0160ewnadeh",
        "Shevnadeh",
        "Shivnadekh",
        "Shaywnah Deh",
        "Shownehdeh",
        "Shiwnah Deh",
        "\u0634\u0648\u0646\u0647 \u062f\u0647"
    ],
    "wof:name":"Shiwnah Deh",
    "wof:placetype":"locality"
},
  "geometry": {"coordinates":[67.02665999999999,34.32417],"type":"Point"}
}