{
  "type": "Feature",
  "properties": {
    "gn:admin1_code":"40",
    "gn:admin2_code":"309",
    "gn:asciiname":"Iskam Darah",
    "gn:country_code":"AF",
    "gn:dem":1808,
    "gn:feature_class":"P",
    "gn:feature_code":"PPL",
    "gn:name":"Isk\u0101m Darah",
    "gn:population":0,
    "gn:timezone":"Asia/Kabul",
    "iso:country":"AF",
    "name:fas_x_preferred":[
        "\u062f\u0631\u06c0 \u0627\u0633\u0643\u0627\u0645"
    ],
    "name:fas_x_variant":[
        "\u0627\u0633\u0643\u0627\u0645 \u062f\u0631\u0647"
    ],
    "name:und_x_variant":[
        "Iskamdara",
        "Esk\u0101m\u1e0fa\u1e5fa",
        "Esk\u0101mdarreh",
        "\u0627\u0633\u06a9\u0627\u0645 \u062f\u0631\u0647",
        "Isk\u0101m Darah"
    ],
    "wof:name":"Iskam Darah",
    "wof:placetype":"locality"
},
  "geometry": {"coordinates":[69.52014,34.8283],"type":"Point"}
}