{
  "type": "Feature",
  "properties": {
    "gn:admin1_code":"11",
    "gn:admin2_code":"2007",
    "gn:asciiname":"Deh-e Nakhak",
    "gn:country_code":"AF",
    "gn:dem":1262,
    "gn:feature_class":"P",
    "gn:feature_code":"PPL",
    "gn:name":"Deh-e Nakhak",
    "gn:population":0,
    "gn:timezone":"Asia/Kabul",
    "iso:country":"AF",
    "name:und_x_variant":[
        "\u1e0eeh-i-Nakhak",
        "Deh-e Nakhak",
        "\u062f\u0647 \u0646\u062e\u06a9"
    ],
    "wof:name":"Deh-e Nakhak",
    "wof:placetype":"locality"
},
  "geometry": {"coordinates":[61.893,34.77432],"type":"Point"}
}