{
  "type": "Feature",
  "properties": {
    "gn:admin1_code":"11",
    "gn:admin2_code":"2015",
    "gn:asciiname":"Tagab-Suni",
    "gn:country_code":"AF",
    "gn:dem":1611,
    "gn:feature_class":"P",
    "gn:feature_code":"PPL",
    "gn:name":"Tag\u0101b-Sun\u012b",
    "gn:population":0,
    "gn:timezone":"Asia/Kabul",
    "iso:country":"AF",
    "name:und_x_variant":[
        "Tag\u0101b-Sun\u012b",
        "\u062a\u06af\u0627\u0628 \u0633\u0646\u06cc",
        "Tag\u0101b-soni"
    ],
    "wof:name":"Tagab-Suni",
    "wof:placetype":"locality"
},
  "geometry": {"coordinates":[63.63098000000001,34.36613],"type":"Point"}
}