{
  "type": "Feature",
  "properties": {
    "gn:admin1_code":"36",
    "gn:admin2_code":"702",
    "gn:asciiname":"Salih Khel",
    "gn:country_code":"AF",
    "gn:dem":2147,
    "gn:feature_class":"P",
    "gn:feature_code":"PPL",
    "gn:name":"\u015e\u0101li\u1e29 Kh\u0113l",
    "gn:population":0,
    "gn:timezone":"Asia/Kabul",
    "iso:country":"AF",
    "name:fas_x_preferred":[
        "\u0635\u0627\u0644\u062d \u062e\u064a\u0644"
    ],
    "name:rus_x_preferred":[
        "Salekhkheyl\u2019"
    ],
    "name:und_x_variant":[
        "\u015e\u0101le\u1e29 Kheyl",
        "\u015e\u0101li\u1e29 Kh\u0113l",
        "\u0635\u0627\u0644\u062d \u062e\u06d0\u0644",
        "\u015e\u0101le\u1e29 Kh\u0113l"
    ],
    "wof:name":"Salih Khel",
    "wof:placetype":"locality"
},
  "geometry": {"coordinates":[68.99538000000001,33.38099],"type":"Point"}
}