{
  "type": "Feature",
  "properties": {
    "gn:admin1_code":"11",
    "gn:admin2_code":"2015",
    "gn:asciiname":"Tangi Nabat",
    "gn:country_code":"AF",
    "gn:dem":2145,
    "gn:feature_class":"P",
    "gn:feature_code":"PPL",
    "gn:name":"Tang\u012b Nab\u0101t",
    "gn:population":0,
    "gn:timezone":"Asia/Kabul",
    "iso:country":"AF",
    "name:und_x_variant":[
        "Tangi-Nabat",
        "Tang\u012b Nab\u0101t",
        "\u062a\u0646\u06af\u06cc \u0646\u0628\u0627\u062a"
    ],
    "wof:name":"Tangi Nabat",
    "wof:placetype":"locality"
},
  "geometry": {"coordinates":[64.08277,34.29047],"type":"Point"}
}