{
  "type": "Feature",
  "properties": {
    "gn:admin1_code":"39",
    "gn:admin2_code":"2604",
    "gn:asciiname":"Serkay",
    "gn:country_code":"AF",
    "gn:dem":1649,
    "gn:feature_class":"P",
    "gn:feature_code":"PPL",
    "gn:name":"S\u00earkay",
    "gn:population":0,
    "gn:timezone":"Asia/Kabul",
    "iso:country":"AF",
    "name:fas_x_preferred":[
        "\u0633\u0631\u0643\u06cc"
    ],
    "name:rus_x_preferred":[
        "\u0421\u0435\u0440\u043a\u0430\u0439"
    ],
    "name:und_x_variant":[
        "S\u00earkay",
        "\u0633\u0631\u06a9\u06cc",
        "Sarkay"
    ],
    "wof:name":"Serkay",
    "wof:placetype":"locality"
},
  "geometry": {"coordinates":[65.38108000000001,33.0425],"type":"Point"}
}