{
  "type": "Feature",
  "properties": {
    "gn:admin1_code":"01",
    "gn:admin2_code":"1128",
    "gn:asciiname":"Shalmand",
    "gn:country_code":"AF",
    "gn:dem":751,
    "gn:feature_class":"P",
    "gn:feature_code":"PPL",
    "gn:name":"Shalm\u0101nd",
    "gn:population":0,
    "gn:timezone":"Asia/Kabul",
    "iso:country":"AF",
    "name:und_x_variant":[
        "S\u0304alm\u0101n\u1e0f",
        "Shalm\u0101nd",
        "\u0634\u0644\u0645\u0627\u0646\u062f"
    ],
    "wof:name":"Shalmand",
    "wof:placetype":"locality"
},
  "geometry": {"coordinates":[70.21706999999999,37.57205],"type":"Point"}
}