{
  "type": "Feature",
  "properties": {
    "gn:admin1_code":"41",
    "gn:admin2_code":"3408",
    "gn:asciiname":"Saylbitu",
    "gn:country_code":"AF",
    "gn:dem":2482,
    "gn:feature_class":"P",
    "gn:feature_code":"PPL",
    "gn:name":"Saylb\u012bt\u016b",
    "gn:population":0,
    "gn:timezone":"Asia/Kabul",
    "iso:country":"AF",
    "name:rus_x_preferred":[
        "Sayl\u2019bitu"
    ],
    "name:und_x_variant":[
        "Saylb\u012bt\u016b",
        "\u0633\u06cc\u0644\u0628\u06cc\u062a\u0648",
        "Saylb\u012btu"
    ],
    "wof:name":"Saylbitu",
    "wof:placetype":"locality"
},
  "geometry": {"coordinates":[65.80962,34.2043],"type":"Point"}
}