{
  "type": "Feature",
  "properties": {
    "gn:admin1_code":"08",
    "gn:admin2_code":"607",
    "gn:asciiname":"Tormay",
    "gn:country_code":"AF",
    "gn:dem":2988,
    "gn:feature_class":"P",
    "gn:feature_code":"PPL",
    "gn:name":"T\u014drmay",
    "gn:population":0,
    "gn:timezone":"Asia/Kabul",
    "iso:country":"AF",
    "name:rus_x_preferred":[
        "\u0422\u043e\u0440\u043c\u0430\u0439"
    ],
    "name:und_x_variant":[
        "T\u014d\u1e5fmay",
        "T\u016brmay",
        "T\u014drmay",
        "\u062a\u0648\u0631\u0645\u06cc",
        "Tormay"
    ],
    "wof:name":"Tormay",
    "wof:placetype":"locality"
},
  "geometry": {"coordinates":[67.60675999999999,33.28961],"type":"Point"}
}