{
  "type": "Feature",
  "properties": {
    "gn:admin1_code":"27",
    "gn:admin2_code":"403.0",
    "gn:asciiname":"Baldarghangak",
    "gn:country_code":"AF",
    "gn:dem":3311,
    "gn:feature_class":"P",
    "gn:feature_code":"PPL",
    "gn:name":"Baldarghangak",
    "gn:population":0,
    "gn:timezone":"Asia/Kabul",
    "iso:country":"AF",
    "name:rus_x_preferred":[
        "Bal\u2019dargangak"
    ],
    "name:und_x_variant":[
        "B\u0101ld\u0101rghangak",
        "Baldarghangak",
        "\u0628\u0644\u062f\u0631\u063a\u0646\u06af\u06a9"
    ],
    "wof:name":"Baldarghangak",
    "wof:placetype":"locality"
},
  "geometry": {"coordinates":[67.99361,34.5316],"type":"Point"}
}