{
  "type": "Feature",
  "properties": {
    "gn:admin1_code":"39",
    "gn:admin2_code":"2603",
    "gn:asciiname":"Jangarigh",
    "gn:country_code":"AF",
    "gn:dem":2707,
    "gn:feature_class":"P",
    "gn:feature_code":"PPL",
    "gn:name":"Jangarigh",
    "gn:population":0,
    "gn:timezone":"Asia/Kabul",
    "iso:country":"AF",
    "name:und_x_variant":[
        "\u062c\u0646\u06af\u0631\u063a",
        "Janga\u1e5fegh"
    ],
    "wof:name":"Jangarigh",
    "wof:placetype":"locality"
},
  "geometry": {"coordinates":[66.86358,33.05897],"type":"Point"}
}