{
  "type": "Feature",
  "properties": {
    "gn:admin1_code":"28",
    "gn:admin2_code":"2501",
    "gn:asciiname":"Majnun Kelay",
    "gn:country_code":"AF",
    "gn:dem":1741,
    "gn:feature_class":"P",
    "gn:feature_code":"PPL",
    "gn:name":"Majn\u016bn K\u00ealay",
    "gn:population":0,
    "gn:timezone":"Asia/Kabul",
    "iso:country":"AF",
    "name:fas_x_preferred":[
        "\u0642\u0631\u064a\u06c0 \u0645\u062c\u0644\u0648\u0646"
    ],
    "name:und_x_variant":[
        "Madzhlunkalay",
        "Majl\u016bn K\u00ealay",
        "\u0645\u062c\u0644\u0648\u0646 \u06a9\u0644\u06cc",
        "Majl\u016bn Kalay",
        "Majn\u016bn K\u00ealay",
        "\u0645\u062c\u0646\u0648\u0646 \u06a9\u0644\u06cc"
    ],
    "wof:name":"Majnun Kelay",
    "wof:placetype":"locality"
},
  "geometry": {"coordinates":[67.24269,32.32799],"type":"Point"}
}