{
  "type": "Feature",
  "properties": {
    "gn:admin1_code":"03",
    "gn:admin2_code":"1303",
    "gn:asciiname":"Shini Masjid",
    "gn:country_code":"AF",
    "gn:dem":1606,
    "gn:feature_class":"P",
    "gn:feature_code":"PPL",
    "gn:name":"Sh\u012bn\u012b Masjid",
    "gn:population":0,
    "gn:timezone":"Asia/Kabul",
    "iso:country":"AF",
    "name:und_x_variant":[
        "Sinimasje\u1e0f",
        "Sh\u012bn\u012bmasjed",
        "Sh\u012bn\u012b Masjid",
        "\u0634\u0646\u06cc \u0645\u0633\u062c\u062f"
    ],
    "wof:name":"Shini Masjid",
    "wof:placetype":"locality"
},
  "geometry": {"coordinates":[68.48699999999999,35.70664],"type":"Point"}
}