{
  "type": "Feature",
  "properties": {
    "gn:admin1_code":"26",
    "gn:admin2_code":"1205",
    "gn:asciiname":"Sayl-e Posidah",
    "gn:country_code":"AF",
    "gn:dem":2503,
    "gn:feature_class":"P",
    "gn:feature_code":"PPL",
    "gn:name":"Sayl-e P\u014dsidah",
    "gn:population":0,
    "gn:timezone":"Asia/Kabul",
    "iso:country":"AF",
    "name:und_x_variant":[
        "Sayl-e P\u014dsidah",
        "\u0633\u06cc\u0644 \u067e\u0648\u0633\u062f\u0647",
        "S\u0113le P\u014dsida"
    ],
    "wof:name":"Sayl-e Posidah",
    "wof:placetype":"locality"
},
  "geometry": {"coordinates":[70.27330000000001,36.13166],"type":"Point"}
}