{
  "type": "Feature",
  "properties": {
    "gn:admin1_code":"7",
    "gn:admin2_code":"1804.0",
    "gn:asciiname":"Gandab-e Pa'in",
    "gn:country_code":"AF",
    "gn:dem":1008,
    "gn:feature_class":"P",
    "gn:feature_code":"PPL",
    "gn:name":"Gand\u0101b-e P\u0101\u2019\u012bn",
    "gn:population":0,
    "gn:timezone":"Asia/Kabul",
    "iso:country":"AF",
    "name:und_x_variant":[
        "Gan\u1e0f\u0101b-i-P\u0101\u2019\u012bn",
        "Gand\u0101b-e P\u0101\u2019\u012bn",
        "\u06af\u0646\u062f\u0627\u0628 \u067e\u0627\u0626\u06cc\u0646"
    ],
    "wof:name":"Gandab-e Pa'in",
    "wof:placetype":"locality"
},
  "geometry": {"coordinates":[64.07696999999999,35.7037],"type":"Point"}
}