{
  "type": "Feature",
  "properties": {
    "gn:admin1_code":"17",
    "gn:admin2_code":"504",
    "gn:asciiname":"Torah Tizhah",
    "gn:country_code":"AF",
    "gn:dem":2758,
    "gn:feature_class":"P",
    "gn:feature_code":"PPL",
    "gn:name":"T\u014drah T\u012bz\u0332h\u0332ah",
    "gn:population":0,
    "gn:timezone":"Asia/Kabul",
    "iso:country":"AF",
    "name:fas_x_preferred":[
        "\u062a\u0648\u0631\u0647 \u062a\u06cc\u0698\u0647"
    ],
    "name:und_x_variant":[
        "Toratiza",
        "Tora Ti\u017e\u0101",
        "T\u014drah Tiz\u0332h\u0332ah",
        "Towrah Tiz\u0332h\u0332ah",
        "T\u014drah T\u012bz\u0332h\u0332ah",
        "\u062a\u0648\u0631\u0647 \u062a\u06cc\u0696\u0647"
    ],
    "wof:name":"Torah Tizhah",
    "wof:placetype":"locality"
},
  "geometry": {"coordinates":[69.36360999999999,33.98415],"type":"Point"}
}