{
  "type": "Feature",
  "properties": {
    "gn:admin1_code":"09",
    "gn:admin2_code":"2701.0",
    "gn:asciiname":"Raza Kushtah",
    "gn:country_code":"AF",
    "gn:dem":2500,
    "gn:feature_class":"P",
    "gn:feature_code":"PPL",
    "gn:name":"Ra\u1e95\u0101 Kushtah",
    "gn:population":0,
    "gn:timezone":"Asia/Kabul",
    "iso:country":"AF",
    "name:und_x_variant":[
        "\u1e5ea\u1e0f\u1e95\u0101kusta",
        "Re\u1e95\u0101koshteh",
        "Ra\u1e95\u0101 Kushtah",
        "\u0631\u0636\u0627 \u06a9\u0634\u062a\u0647"
    ],
    "wof:name":"Raza Kushtah",
    "wof:placetype":"locality"
},
  "geometry": {"coordinates":[64.92345,34.51742],"type":"Point"}
}