{
  "type": "Feature",
  "properties": {
    "gn:admin1_code":"11",
    "gn:admin2_code":"2003.0",
    "gn:asciiname":"Chashmah Khani",
    "gn:country_code":"AF",
    "gn:dem":1323,
    "gn:feature_class":"P",
    "gn:feature_code":"PPL",
    "gn:name":"Chashmah Kh\u0101n\u012b",
    "gn:population":0,
    "gn:timezone":"Asia/Kabul",
    "iso:country":"AF",
    "name:fas_x_preferred":[
        "\u0686\u0634\u0645\u06c0 \u062e\u0627\u0646\u06cc"
    ],
    "name:und_x_variant":[
        "\u010ca\u0161ma Kh\u0101ni",
        "Chashmeh Kh\u0101n\u012b",
        "Chashmakhani",
        "Cheshmeh Kh\u0101n\u012b",
        "Chashmah Kh\u0101n\u012b",
        "\u0686\u0634\u0645\u0647 \u062e\u0627\u0646\u06cc",
        "\u0686\u0634\u0645\u06c0 \u062e\u0627\u0646\u06cc"
    ],
    "wof:name":"Chashmah Khani",
    "wof:placetype":"locality"
},
  "geometry": {"coordinates":[62.18212,34.03028],"type":"Point"}
}