{
  "type": "Feature",
  "properties": {
    "gn:admin1_code":"28",
    "gn:admin2_code":"2506",
    "gn:asciiname":"Tawaray",
    "gn:country_code":"AF",
    "gn:dem":1437,
    "gn:feature_class":"P",
    "gn:feature_code":"PPL",
    "gn:name":"Tawaray",
    "gn:population":0,
    "gn:timezone":"Asia/Kabul",
    "iso:country":"AF",
    "name:und_x_variant":[
        "Tavaray",
        "\u062a\u0648\u0631\u06cc",
        "Tawa\u1e5fay",
        "Tawaray"
    ],
    "wof:name":"Tawaray",
    "wof:placetype":"locality"
},
  "geometry": {"coordinates":[66.64771999999999,31.91722],"type":"Point"}
}