{
  "type": "Feature",
  "properties": {
    "gn:admin1_code":"26",
    "gn:admin2_code":"1201.0",
    "gn:asciiname":"Bolak Urtah Baz",
    "gn:country_code":"AF",
    "gn:dem":828,
    "gn:feature_class":"P",
    "gn:feature_code":"PPL",
    "gn:name":"B\u014dlak Urtah Baz",
    "gn:population":0,
    "gn:timezone":"Asia/Kabul",
    "iso:country":"AF",
    "name:fas_x_preferred":[
        "\u0628\u0644\u0627\u063a \u0627\u0631\u062a\u0647 \u0628\u0627\u0632"
    ],
    "name:rus_x_preferred":[
        "\u0411\u0443\u043b\u0430\u043a\u0443\u0440\u0442\u0430\u0431\u0430\u0437"
    ],
    "name:und_x_variant":[
        "Bulakurtabaz",
        "B\u016blak Ortah Baz",
        "B\u014dlak U\u1e5fta Baz",
        "Bol\u0101gh Ortah B\u0101z",
        "B\u014dlak Urtah Baz",
        "\u0628\u0648\u0644\u06a9 \u0627\u0631\u062a\u0647 \u0628\u0632"
    ],
    "wof:name":"Bolak Urtah Baz",
    "wof:placetype":"locality"
},
  "geometry": {"coordinates":[69.56416999999999,36.73356],"type":"Point"}
}