{
  "type": "Feature",
  "properties": {
    "gn:admin1_code":"07",
    "gn:admin2_code":"1809",
    "gn:asciiname":"Pash Shui",
    "gn:country_code":"AF",
    "gn:dem":407,
    "gn:feature_class":"P",
    "gn:feature_code":"PPL",
    "gn:name":"Pash Shu\u012b",
    "gn:population":0,
    "gn:timezone":"Asia/Kabul",
    "iso:country":"AF",
    "name:und_x_variant":[
        "Pash Shu\u012b",
        "\u067e\u0634 \u0634\u06cc",
        "Pash Shoi"
    ],
    "wof:name":"Pash Shui",
    "wof:placetype":"locality"
},
  "geometry": {"coordinates":[64.86874,36.43209],"type":"Point"}
}