{
  "type": "Feature",
  "properties": {
    "gn:admin1_code":"27",
    "gn:admin2_code":"405.0",
    "gn:asciiname":"Qol-e Mughul",
    "gn:country_code":"AF",
    "gn:dem":3236,
    "gn:feature_class":"P",
    "gn:feature_code":"PPL",
    "gn:name":"Q\u014dl-e Mughul",
    "gn:population":0,
    "gn:timezone":"Asia/Kabul",
    "iso:country":"AF",
    "name:rus_x_preferred":[
        "Kulli-Mugul\u2019"
    ],
    "name:und_x_variant":[
        "Qulle Moghul",
        "Qolleh-ye Moghol",
        "Q\u014dl-e Mughul",
        "\u0642\u0648\u0644 \u0645\u063a\u0644"
    ],
    "wof:name":"Qol-e Mughul",
    "wof:placetype":"locality"
},
  "geometry": {"coordinates":[68.2884,34.43078],"type":"Point"}
}