{
  "type": "Feature",
  "properties": {
    "gn:admin1_code":"11",
    "gn:admin2_code":"2001",
    "gn:asciiname":"Moghul Bachah",
    "gn:country_code":"AF",
    "gn:dem":881,
    "gn:feature_class":"P",
    "gn:feature_code":"PPL",
    "gn:name":"Moghul Bachah",
    "gn:population":0,
    "gn:timezone":"Asia/Kabul",
    "iso:country":"AF",
    "name:rus_x_preferred":[
        "Mugul\u2019bacha"
    ],
    "name:und_x_variant":[
        "Mughal Bachcha",
        "Mughul Ba\u010da",
        "Moghol Bachcheh",
        "Moghul Bachah",
        "\u0645\u063a\u0644 \u0628\u0686\u0647"
    ],
    "wof:name":"Moghul Bachah",
    "wof:placetype":"locality"
},
  "geometry": {"coordinates":[62.00954,34.38905],"type":"Point"}
}