{
  "type": "Feature",
  "properties": {
    "gn:admin1_code":"40",
    "gn:admin2_code":"307.0",
    "gn:asciiname":"Darah-ye Katah Sang",
    "gn:country_code":"AF",
    "gn:dem":3081,
    "gn:feature_class":"P",
    "gn:feature_code":"PPL",
    "gn:name":"Darah-ye Ka\u1e6fah Sang",
    "gn:population":0,
    "gn:timezone":"Asia/Kabul",
    "iso:country":"AF",
    "name:und_x_variant":[
        "Durayi-Katasang",
        "Darrah-ye Katasang",
        "Darrah-ye Ka\u1e6fah Sang",
        "\u1e0ea\u1e5fa-i-Katasang",
        "Darreh-ye Ka\u1e6fah Sang",
        "Darah-ye Katah Sang",
        "Darah-ye Ka\u1e6fah Sang",
        "\u062f\u0631\u0647 \u06a9\u067c\u0647 \u0633\u0646\u06af"
    ],
    "wof:name":"Darah-ye Katah Sang",
    "wof:placetype":"locality"
},
  "geometry": {"coordinates":[68.58565,34.70405],"type":"Point"}
}