{
  "type": "Feature",
  "properties": {
    "gn:admin1_code":"24",
    "gn:admin2_code":"1402.0",
    "gn:asciiname":"'Omar Khel",
    "gn:country_code":"AF",
    "gn:dem":360,
    "gn:feature_class":"P",
    "gn:feature_code":"PPL",
    "gn:name":"\u2018Omar Kh\u0113l",
    "gn:population":0,
    "gn:timezone":"Asia/Kabul",
    "iso:country":"AF",
    "name:rus_x_preferred":[
        "Umarkheyl\u2019"
    ],
    "name:und_x_variant":[
        "Oma\u1e5f Kh\u0113l",
        "\u2018Omar Kheyl",
        "\u0639\u0645\u0631 \u062e\u06d0\u0644",
        "\u2018Omar Kh\u0113l"
    ],
    "wof:name":"'Omar Khel",
    "wof:placetype":"locality"
},
  "geometry": {"coordinates":[68.89513000000001,37.16168],"type":"Point"}
}