{
  "type": "Feature",
  "properties": {
    "gn:admin1_code":"08",
    "gn:admin2_code":"603",
    "gn:asciiname":"'Alaqahdari-ye Khwajah 'Umri",
    "gn:country_code":"AF",
    "gn:dem":2302,
    "gn:feature_class":"P",
    "gn:feature_code":"PPL",
    "gn:name":"\u2018Al\u0101qahd\u0101r\u012b-ye Khw\u0101jah \u2018Umr\u012b",
    "gn:population":0,
    "gn:timezone":"Asia/Kabul",
    "iso:country":"AF",
    "name:fas_x_preferred":[
        "\u0639\u0644\u0627\u0642\u062d\u062f\u0627\u0631\u0626 \u062e\u0648\u0627\u062c\u0647 \u0639\u0645\u0631\u06cc"
    ],
    "name:und_x_variant":[
        "Khw\u0101jah \u2018Omar\u012b",
        "Alakadari-Khodzha-Umri",
        "Khv\u0101jeh \u2018Omr\u012b",
        "Al\u0101qehd\u0101r\u012b Khv\u0101jeh \u2018Omr\u012b",
        "Khw\u0101ja Um\u1e5fi",
        "\u2018Al\u0101qa\u1e0f\u0101r\u012b Khw\u0101ja \u2018Um\u1e5fi",
        "Qala Khw\u0101ja Mori",
        "Qal\u2018eh-ye Khv\u0101jeh",
        "\u2018Al\u0101qahd\u0101r\u012b-ye Khw\u0101jah \u2018Omr\u012b",
        "\u2018Al\u0101qehd\u0101r\u012b-ye Khv\u0101jeh \u2018Omr\u012b",
        "\u2018Al\u0101qahd\u0101r\u012b-ye Khw\u0101jah \u2018Umr\u012b",
        "\u0639\u0644\u0627\u0642\u062d\u062f\u0627\u0631\u06cc \u062e\u0648\u0627\u062c\u0647 \u0639\u0645\u0631\u06cc"
    ],
    "wof:name":"'Alaqahdari-ye Khwajah 'Umri",
    "wof:placetype":"locality"
},
  "geometry": {"coordinates":[68.4025,33.69192],"type":"Point"}
}