{
  "type": "Feature",
  "properties": {
    "gn:admin1_code":"30",
    "gn:admin2_code":"1613",
    "gn:asciiname":"Joy Jadid",
    "gn:country_code":"AF",
    "gn:dem":301,
    "gn:feature_class":"P",
    "gn:feature_code":"PPL",
    "gn:name":"J\u014dy Jad\u012bd",
    "gn:population":0,
    "gn:timezone":"Asia/Kabul",
    "iso:country":"AF",
    "name:und_x_variant":[
        "Dzhuyi-Dzhadid",
        "Joi Jad\u012bd",
        "Joi Jad\u012br",
        "J\u016by-ye Jad\u012bd",
        "J\u014dy Jad\u012bd",
        "\u062c\u0648\u06cc \u062c\u062f\u064a\u062f"
    ],
    "wof:name":"Joy Jadid",
    "wof:placetype":"locality"
},
  "geometry": {"coordinates":[67.58694,37.19889000000001],"type":"Point"}
}