{
  "type": "Feature",
  "properties": {
    "gn:admin1_code":"02",
    "gn:admin2_code":"1904.0",
    "gn:asciiname":"Quydyak",
    "gn:country_code":"AF",
    "gn:dem":2615,
    "gn:feature_class":"P",
    "gn:feature_code":"PPL",
    "gn:name":"Q\u016by\u1e0fyak",
    "gn:population":0,
    "gn:timezone":"Asia/Kabul",
    "iso:country":"AF",
    "wof:name":"Quydyak",
    "wof:placetype":"locality"
},
  "geometry": {"coordinates":[64.96611,34.975],"type":"Point"}
}