{
  "type": "Feature",
  "properties": {
    "gn:admin1_code":"05",
    "gn:admin2_code":"2801",
    "gn:asciiname":"Qal'ah-ye Gaday",
    "gn:country_code":"AF",
    "gn:dem":3213,
    "gn:feature_class":"P",
    "gn:feature_code":"PPL",
    "gn:name":"Qal\u2018ah-ye Gad\u0101y",
    "gn:population":0,
    "gn:timezone":"Asia/Kabul",
    "iso:country":"AF",
    "name:fas_x_preferred":[
        "\u0642\u0644\u0639\u0647\u0654 \u06af\u062f\u0627\u06cc"
    ],
    "name:rus_x_preferred":[
        "\u041a\u0430\u043b\u0430\u0439\u0438-\u0413\u0430\u0434\u0430\u0439"
    ],
    "name:und_x_variant":[
        "Kalayi-Gaday",
        "Qal\u2018a-i-Ga\u1e0f\u0101y",
        "Qal\u2018ah-ye Gad\u0101y",
        "Qal\u2018eh-ye Gad\u0101y",
        "\u0642\u0644\u0639\u0647 \u06af\u062f\u0627\u06cc"
    ],
    "wof:name":"Qal'ah-ye Gaday",
    "wof:placetype":"locality"
},
  "geometry": {"coordinates":[67.40731,34.78988],"type":"Point"}
}