{
  "type": "Feature",
  "properties": {
    "gn:admin1_code":"5",
    "gn:admin2_code":"2806.0",
    "gn:asciiname":"Warghah",
    "gn:country_code":"AF",
    "gn:dem":2698,
    "gn:feature_class":"P",
    "gn:feature_code":"PPL",
    "gn:name":"Warghah",
    "gn:population":0,
    "gn:timezone":"Asia/Kabul",
    "iso:country":"AF",
    "name:und_x_variant":[
        "Wa\u1e5fgha",
        "Wa\u1e5fghah",
        "Warghah",
        "\u0648\u0631\u063a\u0647"
    ],
    "wof:name":"Warghah",
    "wof:placetype":"locality"
},
  "geometry": {"coordinates":[67.07812,33.99164],"type":"Point"}
}