{
  "type": "Feature",
  "properties": {
    "gn:admin1_code":"05",
    "gn:admin2_code":"2806",
    "gn:asciiname":"Miyanah Deh",
    "gn:country_code":"AF",
    "gn:dem":2796,
    "gn:feature_class":"P",
    "gn:feature_code":"PPL",
    "gn:name":"Miy\u0101nah Deh",
    "gn:population":0,
    "gn:timezone":"Asia/Kabul",
    "iso:country":"AF",
    "name:und_x_variant":[
        "My\u0101na\u1e0feh",
        "Mianadekh",
        "M\u012b\u0101nah Deh",
        "Miy\u0101nah Deh",
        "\u0645\u06cc\u0627\u0646\u0647 \u062f\u0647"
    ],
    "wof:name":"Miyanah Deh",
    "wof:placetype":"locality"
},
  "geometry": {"coordinates":[66.63488000000001,34.19848],"type":"Point"}
}