{
  "type": "Feature",
  "properties": {
    "gn:admin1_code":"32",
    "gn:admin2_code":"1503",
    "gn:asciiname":"Sherah",
    "gn:country_code":"AF",
    "gn:dem":2756,
    "gn:feature_class":"P",
    "gn:feature_code":"PPL",
    "gn:name":"Sh\u0113rah",
    "gn:population":0,
    "gn:timezone":"Asia/Kabul",
    "iso:country":"AF",
    "name:und_x_variant":[
        "S\u0304\u0113\u1e5fa",
        "Sh\u012breh",
        "Shayrah",
        "\u0634\u06cc\u0631\u0647",
        "Sh\u0113rah"
    ],
    "wof:name":"Sherah",
    "wof:placetype":"locality"
},
  "geometry": {"coordinates":[67.35736999999999,35.53572],"type":"Point"}
}