{
  "type": "Feature",
  "properties": {
    "gn:admin1_code":"42",
    "gn:admin2_code":"3301.0",
    "gn:asciiname":"Nisharow",
    "gn:country_code":"AF",
    "gn:dem":2364,
    "gn:feature_class":"P",
    "gn:feature_code":"PPL",
    "gn:name":"Nisharow",
    "gn:population":0,
    "gn:timezone":"Asia/Kabul",
    "iso:country":"AF",
    "name:und_x_variant":[
        "Nisharau",
        "Ne\u0161araw",
        "Nesharaw",
        "Nisharow",
        "\u0646\u0634\u0631\u0648"
    ],
    "wof:name":"Nisharow",
    "wof:placetype":"locality"
},
  "geometry": {"coordinates":[69.49070999999999,35.34863],"type":"Point"}
}