{
  "type": "Feature",
  "properties": {
    "gn:admin1_code":"13",
    "gn:admin2_code":"102.0",
    "gn:asciiname":"Barah Aw Darah",
    "gn:country_code":"AF",
    "gn:dem":2027,
    "gn:feature_class":"P",
    "gn:feature_code":"PPL",
    "gn:name":"Barah Aw Darah",
    "gn:population":0,
    "gn:timezone":"Asia/Kabul",
    "iso:country":"AF",
    "name:fas_x_preferred":[
        "\u0628\u0631\u0647 \u0627\u0648 \u062f\u0631\u0647"
    ],
    "name:und_x_variant":[
        "Bara-Avdara",
        "Ba\u1e5fa Aw\u1e0fa\u1e5fa",
        "Bareh Awdarreh",
        "Barah Awdarah",
        "\u0628\u0631\u0647 \u0627\u0648 \u062f\u0631\u0647",
        "Barah Aw Darah"
    ],
    "wof:name":"Barah Aw Darah",
    "wof:placetype":"locality"
},
  "geometry": {"coordinates":[69.35485,34.7166],"type":"Point"}
}