{
  "type": "Feature",
  "properties": {
    "gn:admin1_code":"27",
    "gn:admin2_code":"402.0",
    "gn:asciiname":"Sher Khan",
    "gn:country_code":"AF",
    "gn:dem":2377,
    "gn:feature_class":"P",
    "gn:feature_code":"PPL",
    "gn:name":"Sh\u0113r Kh\u0101n",
    "gn:population":0,
    "gn:timezone":"Asia/Kabul",
    "iso:country":"AF",
    "name:fra_x_preferred":[
        "Sher Khan"
    ],
    "name:nld_x_preferred":[
        "Shere Khan"
    ],
    "name:und_x_variant":[
        "Sherkhan",
        "\u0160\u0113rkh\u0101n",
        "Sh\u0113rkh\u0101n",
        "Shayr Kh\u0101n",
        "Sh\u012brkh\u0101n",
        "Sh\u0113r Kh\u0101n",
        "\u0634\u06d0\u0631 \u062e\u0627\u0646"
    ],
    "wof:name":"Sher Khan",
    "wof:placetype":"locality"
},
  "geometry": {"coordinates":[68.68014000000001,34.46864],"type":"Point"}
}