{
  "type": "Feature",
  "properties": {
    "gn:admin1_code":"13",
    "gn:admin2_code":"101.0",
    "gn:asciiname":"Qal'ah-ye Khalifah Muhammad 'Ali",
    "gn:country_code":"AF",
    "gn:dem":1857,
    "gn:feature_class":"P",
    "gn:feature_code":"PPL",
    "gn:name":"Qal\u2018ah-ye Khal\u012bfah Mu\u1e29amma\u1e0f \u2018Al\u012b",
    "gn:population":0,
    "gn:timezone":"Asia/Kabul",
    "iso:country":"AF",
    "name:und_x_variant":[
        "Qal\u2018ah-ye Khal\u012bfah Mu\u1e29amma\u1e0f \u2018Al\u012b",
        "\u0642\u0644\u0639\u0647 \u062e\u0644\u06cc\u0641\u0647 \u0645\u062d\u0645\u062f \u0639\u0644\u06cc"
    ],
    "wof:name":"Qal'ah-ye Khalifah Muhammad 'Ali",
    "wof:placetype":"locality"
},
  "geometry": {"coordinates":[69.18037,34.4963],"type":"Point"}
}