{
  "type": "Feature",
  "properties": {
    "gn:admin1_code":"28",
    "gn:admin2_code":"2509",
    "gn:asciiname":"Wulah",
    "gn:country_code":"AF",
    "gn:dem":2180,
    "gn:feature_class":"P",
    "gn:feature_code":"PPL",
    "gn:name":"Wulah",
    "gn:population":0,
    "gn:timezone":"Asia/Kabul",
    "iso:country":"AF",
    "name:und_x_variant":[
        "Vula",
        "Wola",
        "Walah",
        "Wolah",
        "Wulah",
        "\u0648\u0644\u0647"
    ],
    "wof:name":"Wulah",
    "wof:placetype":"locality"
},
  "geometry": {"coordinates":[67.95158000000001,31.91635],"type":"Point"}
}