{
  "type": "Feature",
  "properties": {
    "gn:admin1_code":"41",
    "gn:admin2_code":"3408.0",
    "gn:asciiname":"Shor Pa'inah",
    "gn:country_code":"AF",
    "gn:dem":2783,
    "gn:feature_class":"P",
    "gn:feature_code":"PPL",
    "gn:name":"Sh\u014dr P\u0101\u2019\u012bnah",
    "gn:population":0,
    "gn:timezone":"Asia/Kabul",
    "iso:country":"AF",
    "name:und_x_variant":[
        "\u0160or-p\u0101\u2019ina",
        "Shor-Paina",
        "Sh\u014dr P\u0101\u2019\u012bnah",
        "Sh\u016br Pa\u2019ineh",
        "\u0634\u0648\u0631 \u067e\u0627\u0626\u06cc\u0646\u0647"
    ],
    "wof:name":"Shor Pa'inah",
    "wof:placetype":"locality"
},
  "geometry": {"coordinates":[66.01746999999999,34.30417],"type":"Point"}
}