{
  "type": "Feature",
  "properties": {
    "gn:admin1_code":"39",
    "gn:admin2_code":"2601",
    "gn:asciiname":"Surkhmurgar",
    "gn:country_code":"AF",
    "gn:dem":1429,
    "gn:feature_class":"P",
    "gn:feature_code":"PPL",
    "gn:name":"Surkhmurgar",
    "gn:population":0,
    "gn:timezone":"Asia/Kabul",
    "iso:country":"AF",
    "name:und_x_variant":[
        "Su\u1e5fkh Murg\u0101b",
        "Surkhmurgar",
        "Su\u1e5fkh-mu\u1e5fgh\u0101b",
        "Sorkh Morgh\u0101b"
    ],
    "wof:name":"Surkhmurgar",
    "wof:placetype":"locality"
},
  "geometry": {"coordinates":[65.92,32.72],"type":"Point"}
}