{
  "type": "Feature",
  "properties": {
    "gn:admin1_code":"11",
    "gn:admin2_code":"2010",
    "gn:asciiname":"Pozah-ye Kaftar Khan",
    "gn:country_code":"AF",
    "gn:dem":892,
    "gn:feature_class":"P",
    "gn:feature_code":"PPL",
    "gn:name":"P\u014dzah-ye Kaftar Kh\u0101n",
    "gn:population":0,
    "gn:timezone":"Asia/Kabul",
    "iso:country":"AF",
    "name:und_x_variant":[
        "P\u016bza-i-Kafta\u1e5f Kh\u0101n",
        "P\u016bzehye Kaftar Kh\u0101n",
        "P\u014dzah-ye Kaftar Kh\u0101n",
        "\u067e\u0648\u0632\u06c0 \u06a9\u0641\u062a\u0631 \u062e\u0627\u0646"
    ],
    "wof:name":"Pozah-ye Kaftar Khan",
    "wof:placetype":"locality"
},
  "geometry": {"coordinates":[61.97278000000001,34.29942],"type":"Point"}
}