{
  "type": "Feature",
  "properties": {
    "gn:admin1_code":"28",
    "gn:admin2_code":"2511.0",
    "gn:asciiname":"Tsiliray",
    "gn:country_code":"AF",
    "gn:dem":2282,
    "gn:feature_class":"P",
    "gn:feature_code":"PPL",
    "gn:name":"Tsiliray",
    "gn:population":0,
    "gn:timezone":"Asia/Kabul",
    "iso:country":"AF",
    "name:und_x_variant":[
        "Chiliray",
        "Cele\u1e5fay",
        "Tsiliray",
        "\u0685\u0644\u0631\u06cc",
        "Tseleray"
    ],
    "wof:name":"Tsiliray",
    "wof:placetype":"locality"
},
  "geometry": {"coordinates":[67.56846,32.42472],"type":"Point"}
}