{
  "type": "Feature",
  "properties": {
    "gn:admin1_code":"05",
    "gn:admin2_code":"2806",
    "gn:asciiname":"Gumbatak",
    "gn:country_code":"AF",
    "gn:dem":2699,
    "gn:feature_class":"P",
    "gn:feature_code":"PPL",
    "gn:name":"Gumbatak",
    "gn:population":0,
    "gn:timezone":"Asia/Kabul",
    "iso:country":"AF",
    "name:und_x_variant":[
        "Gonbadak",
        "\u06af\u0645\u0628\u062a\u06a9"
    ],
    "wof:name":"Gumbatak",
    "wof:placetype":"locality"
},
  "geometry": {"coordinates":[67.35894999999999,34.19197],"type":"Point"}
}