{
  "type": "Feature",
  "properties": {
    "gn:admin1_code":"05",
    "gn:admin2_code":"2805",
    "gn:asciiname":"Surkh Naw",
    "gn:country_code":"AF",
    "gn:dem":3198,
    "gn:feature_class":"P",
    "gn:feature_code":"PPL",
    "gn:name":"Surkh N\u0101w",
    "gn:population":0,
    "gn:timezone":"Asia/Kabul",
    "iso:country":"AF",
    "name:und_x_variant":[
        "Surkhnau",
        "Sorkh N\u0101v",
        "Su\u1e5fkhnaw",
        "Surkh N\u0101w",
        "Sorkhn\u0101w",
        "\u0633\u0631\u062e \u0646\u0627\u0648"
    ],
    "wof:name":"Surkh Naw",
    "wof:placetype":"locality"
},
  "geometry": {"coordinates":[66.8498,34.51618],"type":"Point"}
}