{
  "type": "Feature",
  "properties": {
    "gn:admin1_code":"10",
    "gn:admin2_code":"2306",
    "gn:asciiname":"Qaryah-ye Zarwaji",
    "gn:country_code":"AF",
    "gn:dem":1721,
    "gn:feature_class":"P",
    "gn:feature_code":"PPL",
    "gn:name":"Qaryah-ye Zarwaj\u012b",
    "gn:population":0,
    "gn:timezone":"Asia/Kabul",
    "iso:country":"AF",
    "name:und_x_variant":[
        "Zarvadzhi",
        "Qa\u1e5fya-i-Za\u1e5fwaji",
        "Qaryah-ye Zarwaj\u012b",
        "\u0642\u0631\u06cc\u0647 \u0632\u0631\u0648\u062c\u06cc",
        "Qaryeh-ye Zarwaj\u012b"
    ],
    "wof:name":"Qaryah-ye Zarwaji",
    "wof:placetype":"locality"
},
  "geometry": {"coordinates":[64.20804,32.4847],"type":"Point"}
}