{
  "type": "Feature",
  "properties": {
    "gn:admin1_code":"41",
    "gn:admin2_code":"3406",
    "gn:asciiname":"Wushay",
    "gn:country_code":"AF",
    "gn:dem":1850,
    "gn:feature_class":"P",
    "gn:feature_code":"PPL",
    "gn:name":"Wushay",
    "gn:population":0,
    "gn:timezone":"Asia/Kabul",
    "iso:country":"AF",
    "name:und_x_variant":[
        "Wos\u0304ay",
        "Wushay",
        "\u0648\u0634\u06cc",
        "Woshay"
    ],
    "wof:name":"Wushay",
    "wof:placetype":"locality"
},
  "geometry": {"coordinates":[65.76054000000001,33.48924],"type":"Point"}
}