{
  "type": "Feature",
  "properties": {
    "gn:admin1_code":"27",
    "gn:admin2_code":"407",
    "gn:asciiname":"Zamuch",
    "gn:country_code":"AF",
    "gn:dem":2016,
    "gn:feature_class":"P",
    "gn:feature_code":"PPL",
    "gn:name":"Zam\u016bch",
    "gn:population":0,
    "gn:timezone":"Asia/Kabul",
    "iso:country":"AF",
    "name:und_x_variant":[
        "Zam\u016bch",
        "Zamuch",
        "Zam\u016b\u010d",
        "Zamowch",
        "\u0632\u0645\u0648\u0686"
    ],
    "wof:name":"Zamuch",
    "wof:placetype":"locality"
},
  "geometry": {"coordinates":[68.78986999999999,34.00715],"type":"Point"}
}