{
  "type": "Feature",
  "properties": {
    "gn:admin1_code":"36",
    "gn:admin2_code":"708.0",
    "gn:asciiname":"Makkam",
    "gn:country_code":"AF",
    "gn:dem":1745,
    "gn:feature_class":"P",
    "gn:feature_code":"PPL",
    "gn:name":"Makkam",
    "gn:population":0,
    "gn:timezone":"Asia/Kabul",
    "iso:country":"AF",
    "wof:name":"Makkam",
    "wof:placetype":"locality"
},
  "geometry": {"coordinates":[69.79939,33.76246],"type":"Point"}
}