{
  "type": "Feature",
  "properties": {
    "gn:admin1_code":"3",
    "gn:admin2_code":"1304.0",
    "gn:asciiname":"Shalizar",
    "gn:country_code":"AF",
    "gn:dem":970,
    "gn:feature_class":"P",
    "gn:feature_code":"PPL",
    "gn:name":"Sh\u0101liz\u0101r",
    "gn:population":0,
    "gn:timezone":"Asia/Kabul",
    "iso:country":"AF",
    "name:und_x_variant":[
        "S\u0101liz\u0101",
        "Sh\u0101l\u012bz\u0101r",
        "Sh\u0101liz\u0101r",
        "\u0634\u0627\u0644\u0632\u0627\u0631"
    ],
    "wof:name":"Shalizar",
    "wof:placetype":"locality"
},
  "geometry": {"coordinates":[68.48427,35.58809],"type":"Point"}
}