{
  "type": "Feature",
  "properties": {
    "gn:admin1_code":"36",
    "gn:admin2_code":"702.0",
    "gn:asciiname":"Kundalah",
    "gn:country_code":"AF",
    "gn:dem":2176,
    "gn:feature_class":"P",
    "gn:feature_code":"PPL",
    "gn:name":"Kund\u0101lah",
    "gn:population":0,
    "gn:timezone":"Asia/Kabul",
    "iso:country":"AF",
    "name:fas_x_preferred":[
        "\u0643\u0648\u0646\u062f\u0644\u0647"
    ],
    "name:und_x_variant":[
        "Kundala",
        "Kun\u1e0f\u0101la",
        "Kond\u0101lah",
        "Kund\u0101lah",
        "\u06a9\u0646\u062f\u0627\u0644\u0647",
        "Gund\u0101lah",
        "\u06af\u0646\u062f\u0627\u0644\u0647"
    ],
    "wof:name":"Kundalah",
    "wof:placetype":"locality"
},
  "geometry": {"coordinates":[69.09111999999999,33.46025],"type":"Point"}
}