{
  "type": "Feature",
  "properties": {
    "gn:admin1_code":"26",
    "gn:admin2_code":"1201.0",
    "gn:asciiname":"Shah Mardan Beg",
    "gn:country_code":"AF",
    "gn:dem":786,
    "gn:feature_class":"P",
    "gn:feature_code":"PPL",
    "gn:name":"Sh\u0101h Mard\u0101n B\u0113g",
    "gn:population":0,
    "gn:timezone":"Asia/Kabul",
    "iso:country":"AF",
    "name:fas_x_preferred":[
        "\u0634\u0627\u0647 \u0645\u0631\u062f\u0627\u0646 \u0628\u064a\u06af"
    ],
    "name:rus_x_preferred":[
        "\u0428\u0430\u0445-\u041c\u0430\u0440\u0434\u0430\u043d\u043e\u0435\u0433"
    ],
    "name:und_x_variant":[
        "Shakh-Mardanoyeg",
        "\u0160\u0101h Mard\u0101n B\u0113g",
        "Sh\u0101h Mard\u0101n Beyg",
        "Sh\u0101h Mard\u0101n B\u0113g",
        "\u0634\u0627\u0647 \u0645\u0631\u062f\u0627\u0646 \u0628\u06d0\u06af"
    ],
    "wof:name":"Shah Mardan Beg",
    "wof:placetype":"locality"
},
  "geometry": {"coordinates":[69.49965999999999,36.74191],"type":"Point"}
}