{
  "type": "Feature",
  "properties": {
    "gn:admin1_code":"05",
    "gn:admin2_code":"2806",
    "gn:asciiname":"Gaw Khanahgak",
    "gn:country_code":"AF",
    "gn:dem":3126,
    "gn:feature_class":"P",
    "gn:feature_code":"PPL",
    "gn:name":"G\u0101w Kh\u0101nahgak",
    "gn:population":0,
    "gn:timezone":"Asia/Kabul",
    "iso:country":"AF",
    "name:und_x_variant":[
        "G\u0101wkh\u0101nagak",
        "Gavkhanagak",
        "G\u0101vkh\u0101nagak",
        "G\u0101vkh\u0101nehgak",
        "G\u0101w Kh\u0101nahgak",
        "\u06af\u0627\u0648 \u062e\u0627\u0646\u0647 \u06af\u06a9"
    ],
    "wof:name":"Gaw Khanahgak",
    "wof:placetype":"locality"
},
  "geometry": {"coordinates":[67.40470999999999,34.30515],"type":"Point"}
}