{
  "type": "Feature",
  "properties": {
    "gn:admin1_code":"06",
    "gn:admin2_code":"2104",
    "gn:asciiname":"Sirzar",
    "gn:country_code":"AF",
    "gn:dem":1162,
    "gn:feature_class":"P",
    "gn:feature_code":"PPL",
    "gn:name":"S\u012brz\u0101r",
    "gn:population":0,
    "gn:timezone":"Asia/Kabul",
    "iso:country":"AF",
    "name:ceb_x_preferred":[
        "Sirzar"
    ],
    "name:swe_x_preferred":[
        "Sirzar"
    ],
    "name:und_x_variant":[
        "S\u012brz\u0101r",
        "\u0633\u06cc\u0631\u0632\u0627\u0631"
    ],
    "wof:name":"Sirzar",
    "wof:placetype":"locality"
},
  "geometry": {"coordinates":[63.4769,33.13693],"type":"Point"}
}