{
  "type": "Feature",
  "properties": {
    "gn:admin1_code":"29",
    "gn:admin2_code":"2915",
    "gn:asciiname":"Karmah",
    "gn:country_code":"AF",
    "gn:dem":2118,
    "gn:feature_class":"P",
    "gn:feature_code":"PPL",
    "gn:name":"Karmah",
    "gn:population":0,
    "gn:timezone":"Asia/Kabul",
    "iso:country":"AF",
    "name:und_x_variant":[
        "Ka\u1e5fma",
        "Karma",
        "Karmah",
        "\u06a9\u0631\u0645\u0647"
    ],
    "wof:name":"Karmah",
    "wof:placetype":"locality"
},
  "geometry": {"coordinates":[68.88434000000001,33.33916],"type":"Point"}
}