{
  "type": "Feature",
  "properties": {
    "gn:admin1_code":"9",
    "gn:admin2_code":"2706.0",
    "gn:asciiname":"Chashmah-ye Surkhak",
    "gn:country_code":"AF",
    "gn:dem":2688,
    "gn:feature_class":"P",
    "gn:feature_code":"PPL",
    "gn:name":"Chashmah-ye Surkhak",
    "gn:population":0,
    "gn:timezone":"Asia/Kabul",
    "iso:country":"AF",
    "name:und_x_variant":[
        "\u010ca\u0161ma-i-Surkhak",
        "Chashmayi-Surkhak",
        "Chashmah-ye Surkhak",
        "\u0686\u0634\u0645\u06c0 \u0633\u0631\u062e\u06a9",
        "Cheshmeh-ye Sorkhak"
    ],
    "wof:name":"Chashmah-ye Surkhak",
    "wof:placetype":"locality"
},
  "geometry": {"coordinates":[64.79961999999999,33.5249],"type":"Point"}
}