{
  "type": "Feature",
  "properties": {
    "gn:admin1_code":"29",
    "gn:admin2_code":"2905.0",
    "gn:asciiname":"Mullayano Kelay",
    "gn:country_code":"AF",
    "gn:dem":2032,
    "gn:feature_class":"P",
    "gn:feature_code":"PPL",
    "gn:name":"Mull\u0101y\u0101n\u014d K\u00ealay",
    "gn:population":0,
    "gn:timezone":"Asia/Kabul",
    "iso:country":"AF",
    "name:fas_x_preferred":[
        "\u0642\u0631\u064a\u06c0 \u0645\u0644\u0627\u064a\u0627\u0646"
    ],
    "name:und_x_variant":[
        "Mullayanu-Kalay",
        "Mull\u0101y\u0101no Kalay",
        "\u0645\u0644\u0627\u06cc\u0627\u0646\u0648 \u06a9\u0644\u06cc",
        "Moll\u0101y\u0101no Kalay",
        "Mull\u0101y\u0101n\u014d K\u00ealay"
    ],
    "wof:name":"Mullayano Kelay",
    "wof:placetype":"locality"
},
  "geometry": {"coordinates":[68.87503000000001,32.05332],"type":"Point"}
}