{
  "type": "Feature",
  "properties": {
    "gn:admin1_code":"32",
    "gn:admin2_code":"1505",
    "gn:asciiname":"Mangak",
    "gn:country_code":"AF",
    "gn:dem":2370,
    "gn:feature_class":"P",
    "gn:feature_code":"PPL",
    "gn:name":"Mangak",
    "gn:population":0,
    "gn:timezone":"Asia/Kabul",
    "iso:country":"AF",
    "name:und_x_variant":[
        "\u0645\u0646\u06af\u06a9"
    ],
    "wof:name":"Mangak",
    "wof:placetype":"locality"
},
  "geometry": {"coordinates":[67.89623,35.54597000000001],"type":"Point"}
}