{
  "type": "Feature",
  "properties": {
    "gn:admin1_code":"8",
    "gn:admin2_code":"608.0",
    "gn:asciiname":"Singasi",
    "gn:country_code":"AF",
    "gn:dem":2149,
    "gn:feature_class":"P",
    "gn:feature_code":"PPL",
    "gn:name":"Sing\u0101s\u012b",
    "gn:population":0,
    "gn:timezone":"Asia/Kabul",
    "iso:country":"AF",
    "name:und_x_variant":[
        "Sing\u0101s\u012b",
        "\u0633\u0646\u06af\u0627\u0633\u06cc",
        "Seng\u0101si"
    ],
    "wof:name":"Singasi",
    "wof:placetype":"locality"
},
  "geometry": {"coordinates":[67.79949000000001,32.99027],"type":"Point"}
}