{
  "type": "Feature",
  "properties": {
    "gn:admin1_code":"34",
    "gn:admin2_code":"1002.0",
    "gn:asciiname":"Parkot Kandare",
    "gn:country_code":"AF",
    "gn:dem":808,
    "gn:feature_class":"P",
    "gn:feature_code":"PPL",
    "gn:name":"P\u0101rk\u014d\u1e6f Kandar\u0113",
    "gn:population":0,
    "gn:timezone":"Asia/Kabul",
    "iso:country":"AF",
    "name:fas_x_preferred":[
        "\u067e\u0627\u0631 \u0643\u0648\u062a \u0643\u0646\u062f\u0631\u0627"
    ],
    "name:und_x_variant":[
        "Parkotkandare",
        "P\u0101\u1e5fk\u014dt Kanda\u1e5f\u0113",
        "P\u0101\u1e5fk\u014dt Kanda\u1e5f\u0101",
        "P\u0101rk\u014d\u1e6f Kandar\u0113",
        "\u067e\u0627\u0631\u06a9\u0648\u067c \u06a9\u0646\u062f\u0631\u06d0"
    ],
    "wof:name":"Parkot Kandare",
    "wof:placetype":"locality"
},
  "geometry": {"coordinates":[71.13856,34.83638],"type":"Point"}
}