{
  "type": "Feature",
  "properties": {
    "gn:admin1_code":"34",
    "gn:admin2_code":"1005.0",
    "gn:asciiname":"Apingal",
    "gn:country_code":"AF",
    "gn:dem":1755,
    "gn:feature_class":"P",
    "gn:feature_code":"PPL",
    "gn:name":"Apingal",
    "gn:population":0,
    "gn:timezone":"Asia/Kabul",
    "iso:country":"AF",
    "name:fas_x_preferred":[
        "\u0627\u067e\u0646\u06af\u0644"
    ],
    "name:rus_x_preferred":[
        "Apingal\u2019"
    ],
    "name:und_x_variant":[
        "Apengal",
        "Apingal"
    ],
    "wof:name":"Apingal",
    "wof:placetype":"locality"
},
  "geometry": {"coordinates":[71.46153000000002,35.28182],"type":"Point"}
}