{
  "type": "Feature",
  "properties": {
    "gn:admin1_code":"10",
    "gn:admin2_code":"2309.0",
    "gn:asciiname":"Sher Jan Kelay",
    "gn:country_code":"AF",
    "gn:dem":732,
    "gn:feature_class":"P",
    "gn:feature_code":"PPL",
    "gn:name":"Sh\u0113r J\u0101n K\u00ealay",
    "gn:population":0,
    "gn:timezone":"Asia/Kabul",
    "iso:country":"AF",
    "name:und_x_variant":[
        "S\u0113\u1e5fj\u0101n Kalay",
        "S\u012brj\u0101n Kalay",
        "Shayr J\u0101n K\u00ealay",
        "\u0634\u06cc\u0631 \u062c\u0627\u0646 \u06a9\u0644\u06cc",
        "Sh\u012brj\u0101n Kalay",
        "Sh\u0113r J\u0101n K\u00ealay"
    ],
    "wof:name":"Sher Jan Kelay",
    "wof:placetype":"locality"
},
  "geometry": {"coordinates":[64.26021999999999,31.29526],"type":"Point"}
}