{
  "type": "Feature",
  "properties": {
    "gn:admin1_code":"35",
    "gn:admin2_code":"905",
    "gn:asciiname":"Shamakat",
    "gn:country_code":"AF",
    "gn:dem":1271,
    "gn:feature_class":"P",
    "gn:feature_code":"PPL",
    "gn:name":"Shamaka\u1e6f",
    "gn:population":0,
    "gn:timezone":"Asia/Kabul",
    "iso:country":"AF",
    "name:und_x_variant":[
        "\u0160amakat",
        "Shamaka\u1e6f",
        "\u0634\u0645\u06a9\u067c",
        "Shamakat"
    ],
    "wof:name":"Shamakat",
    "wof:placetype":"locality"
},
  "geometry": {"coordinates":[70.02880999999999,34.73163],"type":"Point"}
}