{
  "type": "Feature",
  "properties": {
    "gn:admin1_code":"03",
    "gn:admin2_code":"1313",
    "gn:asciiname":"Fatmal",
    "gn:country_code":"AF",
    "gn:dem":1595,
    "gn:feature_class":"P",
    "gn:feature_code":"PPL",
    "gn:name":"F\u0101\u0163m\u0101l",
    "gn:population":0,
    "gn:timezone":"Asia/Kabul",
    "iso:country":"AF",
    "name:und_x_variant":[
        "F\u0101\u0163m\u0101l",
        "\u0641\u0627\u0637\u0645\u0627\u0644",
        "F\u0101tm\u0101l"
    ],
    "wof:name":"Fatmal",
    "wof:placetype":"locality"
},
  "geometry": {"coordinates":[69.5772,36.12927],"type":"Point"}
}