{
  "type": "Feature",
  "properties": {
    "gn:admin1_code":"10",
    "gn:admin2_code":"2304",
    "gn:asciiname":"Ghulbah",
    "gn:country_code":"AF",
    "gn:dem":1274,
    "gn:feature_class":"P",
    "gn:feature_code":"PPL",
    "gn:name":"Ghulbah",
    "gn:population":0,
    "gn:timezone":"Asia/Kabul",
    "iso:country":"AF",
    "name:rus_x_preferred":[
        "Gul\u2019ba"
    ],
    "name:und_x_variant":[
        "Ghulba",
        "Ghulbah",
        "\u063a\u0644\u0628\u0647"
    ],
    "wof:name":"Ghulbah",
    "wof:placetype":"locality"
},
  "geometry": {"coordinates":[64.69444,32.6742],"type":"Point"}
}