{
  "type": "Feature",
  "properties": {
    "gn:admin1_code":"09",
    "gn:admin2_code":"2701",
    "gn:asciiname":"Sanaman",
    "gn:country_code":"AF",
    "gn:dem":2651,
    "gn:feature_class":"P",
    "gn:feature_code":"PPL",
    "gn:name":"\u015eanam\u0101n",
    "gn:population":0,
    "gn:timezone":"Asia/Kabul",
    "iso:country":"AF",
    "name:und_x_variant":[
        "\u015eanam\u0101n",
        "\u0635\u0646\u0645\u0627\u0646",
        "Sanam\u0101n"
    ],
    "wof:name":"Sanaman",
    "wof:placetype":"locality"
},
  "geometry": {"coordinates":[64.81649,34.71268],"type":"Point"}
}