{
  "type": "Feature",
  "properties": {
    "gn:admin1_code":"01",
    "gn:admin2_code":"1120.0",
    "gn:asciiname":"Pur Zarg",
    "gn:country_code":"AF",
    "gn:dem":2245,
    "gn:feature_class":"P",
    "gn:feature_code":"PPL",
    "gn:name":"Pur Zarg",
    "gn:population":0,
    "gn:timezone":"Asia/Kabul",
    "iso:country":"AF",
    "name:und_x_variant":[
        "\u067e\u0631 \u0632\u0631\u06af",
        "Pu\u1e5f Za\u1e5fg",
        "Pur Zarg"
    ],
    "wof:name":"Pur Zarg",
    "wof:placetype":"locality"
},
  "geometry": {"coordinates":[70.60574,37.96957],"type":"Point"}
}