{
  "type": "Feature",
  "properties": {
    "gn:admin1_code":"11",
    "gn:admin2_code":"2014",
    "gn:asciiname":"Karez-e Bibi",
    "gn:country_code":"AF",
    "gn:dem":1107,
    "gn:feature_class":"P",
    "gn:feature_code":"PPL",
    "gn:name":"K\u0101r\u0113z-e B\u012bb\u012b",
    "gn:population":0,
    "gn:timezone":"Asia/Kabul",
    "iso:country":"AF",
    "name:und_x_variant":[
        "K\u0101\u1e5f\u0113ze Bibi",
        "Karezi-Bibi",
        "K\u0101r\u0113z-e B\u012bb\u012b",
        "\u06a9\u0627\u0631\u06d0\u0632 \u0628\u06cc\u0628\u06cc",
        "K\u0101r\u012bz-e B\u012bb\u012b"
    ],
    "wof:name":"Karez-e Bibi",
    "wof:placetype":"locality"
},
  "geometry": {"coordinates":[62.22346,33.35085],"type":"Point"}
}