{
  "type": "Feature",
  "properties": {
    "gn:admin1_code":"18",
    "gn:admin2_code":"821",
    "gn:asciiname":"Samar Khel",
    "gn:country_code":"AF",
    "gn:dem":530,
    "gn:feature_class":"P",
    "gn:feature_code":"PPL",
    "gn:name":"Samar Kh\u0113l",
    "gn:population":0,
    "gn:timezone":"Asia/Kabul",
    "iso:country":"AF",
    "name:rus_x_preferred":[
        "Shamarkheyl\u2019"
    ],
    "name:und_x_variant":[
        "S\u0304ama\u1e5fkh\u0113l",
        "Samar Kh\u0113l",
        "S\u0304amar Kheyl",
        "\u062b\u0645\u0631 \u062e\u06cc\u0644",
        "\u062b\u0645\u0631 \u062e\u06d0\u0644"
    ],
    "wof:name":"Samar Khel",
    "wof:placetype":"locality"
},
  "geometry": {"coordinates":[70.57993,34.37508],"type":"Point"}
}