{
  "type": "Feature",
  "properties": {
    "gn:admin1_code":"27",
    "gn:admin2_code":"405.0",
    "gn:asciiname":"Kotah-ye Nazar 'Ali",
    "gn:country_code":"AF",
    "gn:dem":2944,
    "gn:feature_class":"P",
    "gn:feature_code":"PPL",
    "gn:name":"K\u014d\u1e6fah-ye Naz\u0327ar \u2018Al\u012b",
    "gn:population":0,
    "gn:timezone":"Asia/Kabul",
    "iso:country":"AF",
    "name:und_x_variant":[
        "Kotayi-Nazarali",
        "K\u014dta-i-Na\u1e95a\u1e5f\u2018ali",
        "K\u014d\u1e6fah-ye Naz\u0327ar \u2018Al\u012b",
        "Kowteh-ye Naz\u0327ar\u2018al\u012b",
        "\u06a9\u0648\u067c\u0647 \u0646\u0638\u0631 \u0639\u0644\u06cc"
    ],
    "wof:name":"Kotah-ye Nazar 'Ali",
    "wof:placetype":"locality"
},
  "geometry": {"coordinates":[68.31583000000001,34.36889],"type":"Point"}
}