{
  "type": "Feature",
  "properties": {
    "gn:admin1_code":"07",
    "gn:admin2_code":"1803",
    "gn:asciiname":"Qilishli",
    "gn:country_code":"AF",
    "gn:dem":944,
    "gn:feature_class":"P",
    "gn:feature_code":"PPL",
    "gn:name":"Qilishl\u012b",
    "gn:population":0,
    "gn:timezone":"Asia/Kabul",
    "iso:country":"AF",
    "name:und_x_variant":[
        "Qeles\u0304li",
        "Qeleshl\u012b",
        "Qilishl\u012b",
        "\u0642\u0644\u0634\u0644\u06cc"
    ],
    "wof:name":"Qilishli",
    "wof:placetype":"locality"
},
  "geometry": {"coordinates":[64.52048000000001,35.798],"type":"Point"}
}