{
  "type": "Feature",
  "properties": {
    "gn:admin1_code":"39",
    "gn:admin2_code":"2603",
    "gn:asciiname":"Kaji Jowz",
    "gn:country_code":"AF",
    "gn:dem":2070,
    "gn:feature_class":"P",
    "gn:feature_code":"PPL",
    "gn:name":"Kaj\u012b Jowz",
    "gn:population":0,
    "gn:timezone":"Asia/Kabul",
    "iso:country":"AF",
    "name:fas_x_preferred":[
        "\u0643\u062c\u06cc \u062c\u0648\u0632"
    ],
    "name:und_x_variant":[
        "Kadzhidzhauz",
        "Kaj\u012b Jowz",
        "\u06a9\u062c\u06cc \u062c\u0648\u0632",
        "Kaj\u012b Jawz"
    ],
    "wof:name":"Kaji Jowz",
    "wof:placetype":"locality"
},
  "geometry": {"coordinates":[66.68578000000001,32.98758],"type":"Point"}
}