{
  "type": "Feature",
  "properties": {
    "gn:admin1_code":"8",
    "gn:admin2_code":"605.0",
    "gn:asciiname":"Gunbad",
    "gn:country_code":"AF",
    "gn:dem":3129,
    "gn:feature_class":"P",
    "gn:feature_code":"PPL",
    "gn:name":"Gunbad",
    "gn:population":0,
    "gn:timezone":"Asia/Kabul",
    "iso:country":"AF",
    "name:und_x_variant":[
        "Gumba\u1e0f",
        "Gonbad",
        "Gunbad",
        "\u06af\u0646\u0628\u062f"
    ],
    "wof:name":"Gunbad",
    "wof:placetype":"locality"
},
  "geometry": {"coordinates":[66.89856999999999,33.57722],"type":"Point"}
}