{
  "type": "Feature",
  "properties": {
    "gn:admin1_code":"23",
    "gn:admin2_code":"2405.0",
    "gn:asciiname":"Allahdad Khune",
    "gn:country_code":"AF",
    "gn:dem":1449,
    "gn:feature_class":"P",
    "gn:feature_code":"PPL",
    "gn:name":"All\u0101hd\u0101d Kh\u016bn\u0113",
    "gn:population":0,
    "gn:timezone":"Asia/Kabul",
    "iso:country":"AF",
    "name:fas_x_preferred":[
        "\u0627\u0644\u0627\u0647\u062f\u0627\u062f \u062e\u0648\u0646\u06cc"
    ],
    "name:und_x_variant":[
        "All\u0101h\u1e0f\u0101\u1e0f Kh\u016bn\u0113",
        "Allakhdadkhune",
        "All\u0101hd\u0101d Kh\u016bn\u0113",
        "\u0627\u0644\u0644\u0640\u0647 \u062f\u0627\u062f \u062e\u0648\u0646\u06d0",
        "All\u0101hd\u0101d Kh\u016bn\u012b"
    ],
    "wof:name":"Allahdad Khune",
    "wof:placetype":"locality"
},
  "geometry": {"coordinates":[65.65382,31.99749000000001],"type":"Point"}
}