{
  "type": "Feature",
  "properties": {
    "gn:admin1_code":"23",
    "gn:admin2_code":"2403",
    "gn:asciiname":"Spin Kechah",
    "gn:country_code":"AF",
    "gn:dem":1275,
    "gn:feature_class":"P",
    "gn:feature_code":"PPL",
    "gn:name":"Sp\u012bn K\u0113chah",
    "gn:population":0,
    "gn:timezone":"Asia/Kabul",
    "iso:country":"AF",
    "name:und_x_variant":[
        "Sp\u012bn K\u0113\u010da",
        "Spinkecha",
        "Sp\u012bn K\u0113chah",
        "\u0633\u067e\u06cc\u0646 \u06a9\u06d0\u0686\u0647"
    ],
    "wof:name":"Spin Kechah",
    "wof:placetype":"locality"
},
  "geometry": {"coordinates":[66.20631999999999,32.10443],"type":"Point"}
}