{
  "type": "Feature",
  "properties": {
    "gn:admin1_code":"18",
    "gn:admin2_code":"810.0",
    "gn:asciiname":"Shah Now",
    "gn:country_code":"AF",
    "gn:dem":2076,
    "gn:feature_class":"P",
    "gn:feature_code":"PPL",
    "gn:name":"Sh\u0101h Now",
    "gn:population":0,
    "gn:timezone":"Asia/Kabul",
    "iso:country":"AF",
    "name:fas_x_preferred":[
        "\u0634\u0627\u0647\u0646\u0648"
    ],
    "name:und_x_variant":[
        "\u0160\u0101hnaw",
        "Shakhnau",
        "Sh\u0101h N\u0101w",
        "Sh\u0101hnaw",
        "Sh\u0101h Now",
        "\u0634\u0627\u0647 \u0646\u0648"
    ],
    "wof:name":"Shah Now",
    "wof:placetype":"locality"
},
  "geometry": {"coordinates":[70.63245000000001,33.99632],"type":"Point"}
}