{
  "type": "Feature",
  "properties": {
    "gn:admin1_code":"03",
    "gn:admin2_code":"1308",
    "gn:asciiname":"Deh-e Talib",
    "gn:country_code":"AF",
    "gn:dem":1757,
    "gn:feature_class":"P",
    "gn:feature_code":"PPL",
    "gn:name":"Deh-e \u0162\u0101lib",
    "gn:population":0,
    "gn:timezone":"Asia/Kabul",
    "iso:country":"AF",
    "name:und_x_variant":[
        "Deh \u0162al\u012bb",
        "Deh Tal\u0113b",
        "Deh-e \u0162\u0101leb",
        "Deh-e \u0162\u0101lib",
        "\u062f\u0647 \u0637\u0627\u0644\u0628"
    ],
    "wof:name":"Deh-e Talib",
    "wof:placetype":"locality"
},
  "geometry": {"coordinates":[69.54621999999999,35.93143],"type":"Point"}
}