{
  "type": "Feature",
  "properties": {
    "gn:admin1_code":"39",
    "gn:admin2_code":"2601.0",
    "gn:asciiname":"Safar Karez",
    "gn:country_code":"AF",
    "gn:dem":1322,
    "gn:feature_class":"P",
    "gn:feature_code":"PPL",
    "gn:name":"Safar K\u0101r\u0113z",
    "gn:population":0,
    "gn:timezone":"Asia/Kabul",
    "iso:country":"AF",
    "name:fas_x_preferred":[
        "\u0633\u0641\u0631 \u0643\u0627\u0631\u064a\u0632"
    ],
    "name:und_x_variant":[
        "Safa\u1e5f K\u0101\u1e5f\u0113z",
        "Safarkarez",
        "Safar K\u0101r\u0113z",
        "\u0633\u0641\u0631 \u06a9\u0627\u0631\u06d0\u0632",
        "Safar K\u0101r\u012bz"
    ],
    "wof:name":"Safar Karez",
    "wof:placetype":"locality"
},
  "geometry": {"coordinates":[65.85564000000001,32.64149],"type":"Point"}
}