{
  "type": "Feature",
  "properties": {
    "gn:admin1_code":"08",
    "gn:admin2_code":"604.0",
    "gn:asciiname":"Tughni",
    "gn:country_code":"AF",
    "gn:dem":2861,
    "gn:feature_class":"P",
    "gn:feature_code":"PPL",
    "gn:name":"T\u016bghn\u012b",
    "gn:population":0,
    "gn:timezone":"Asia/Kabul",
    "iso:country":"AF",
    "name:und_x_variant":[
        "Tugni",
        "T\u016bghn\u012b",
        "\u062a\u0648\u063a\u0646\u06cc"
    ],
    "wof:name":"Tughni",
    "wof:placetype":"locality"
},
  "geometry": {"coordinates":[67.46240999999999,34.03193],"type":"Point"}
}