{
  "type": "Feature",
  "properties": {
    "gn:admin1_code":"03",
    "gn:admin2_code":"1314.0",
    "gn:asciiname":"Yakhchi Khord",
    "gn:country_code":"AF",
    "gn:dem":1747,
    "gn:feature_class":"P",
    "gn:feature_code":"PPL",
    "gn:name":"Yakhch\u012b Kh\u014drd",
    "gn:population":0,
    "gn:timezone":"Asia/Kabul",
    "iso:country":"AF",
    "name:und_x_variant":[
        "Yakhch\u012b Kh\u014drd",
        "\u06cc\u062e\u0686\u06cc \u062e\u0648\u0631\u062f"
    ],
    "wof:name":"Yakhchi Khord",
    "wof:placetype":"locality"
},
  "geometry": {"coordinates":[69.51839,36.21984000000001],"type":"Point"}
}