{
  "type": "Feature",
  "properties": {
    "gn:admin1_code":"8",
    "gn:admin2_code":"604.0",
    "gn:asciiname":"Altan",
    "gn:country_code":"AF",
    "gn:dem":3188,
    "gn:feature_class":"P",
    "gn:feature_code":"PPL",
    "gn:name":"\u0100lt\u0101n",
    "gn:population":0,
    "gn:timezone":"Asia/Kabul",
    "iso:country":"AF",
    "name:deu_x_preferred":[
        "Altan"
    ],
    "name:rus_x_preferred":[
        "Al\u2019tan"
    ],
    "name:und_x_variant":[
        "\u0100lt\u0101n",
        "\u0622\u0644\u062a\u0627\u0646"
    ],
    "wof:name":"Altan",
    "wof:placetype":"locality"
},
  "geometry": {"coordinates":[67.73609999999999,34.0769],"type":"Point"}
}