{
  "type": "Feature",
  "properties": {
    "gn:admin1_code":"01",
    "gn:admin2_code":"1112",
    "gn:asciiname":"Du Darah",
    "gn:country_code":"AF",
    "gn:dem":2214,
    "gn:feature_class":"P",
    "gn:feature_code":"PPL",
    "gn:name":"D\u016b Darah",
    "gn:population":0,
    "gn:timezone":"Asia/Kabul",
    "iso:country":"AF",
    "name:und_x_variant":[
        "Du \u1e0ea\u1e5f\u1e5fah",
        "\u062f\u0648 \u062f\u0631\u0647",
        "Do Darreh",
        "D\u014d Darah",
        "D\u016b Darah"
    ],
    "wof:name":"Du Darah",
    "wof:placetype":"locality"
},
  "geometry": {"coordinates":[70.50263000000002,37.56443],"type":"Point"}
}