{
  "type": "Feature",
  "properties": {
    "gn:admin1_code":"8",
    "gn:admin2_code":"606.0",
    "gn:asciiname":"Qal'ah-ye Sayyid Majnun",
    "gn:country_code":"AF",
    "gn:dem":3075,
    "gn:feature_class":"P",
    "gn:feature_code":"PPL",
    "gn:name":"Qal\u2018ah-ye Sayyid Majn\u016bn",
    "gn:population":0,
    "gn:timezone":"Asia/Kabul",
    "iso:country":"AF",
    "name:und_x_variant":[
        "K\u014dcekpa\u1e5fi\u1e0fa",
        "Qal\u2018a-i-Say\u1e0fmajn\u016bn",
        "Qal\u2018eh-ye Seyyed Majn\u016bn",
        "Qal\u2018ah-ye Sayyid Majn\u016bn",
        "\u0642\u0644\u0639\u06c0 \u0633\u06cc\u062f \u0645\u062c\u0646\u0648\u0646",
        "K\u014dchik Paridah",
        "\u06a9\u0648\u0686\u06a9 \u067e\u0631\u062f\u0647"
    ],
    "wof:name":"Qal'ah-ye Sayyid Majnun",
    "wof:placetype":"locality"
},
  "geometry": {"coordinates":[67.10824000000001,33.33482],"type":"Point"}
}