{
  "type": "Feature",
  "properties": {
    "gn:admin1_code":"26",
    "gn:admin2_code":"1201",
    "gn:asciiname":"Qarah Bay",
    "gn:country_code":"AF",
    "gn:dem":834,
    "gn:feature_class":"P",
    "gn:feature_code":"PPL",
    "gn:name":"Qarah B\u0101y",
    "gn:population":0,
    "gn:timezone":"Asia/Kabul",
    "iso:country":"AF",
    "name:rus_x_preferred":[
        "\u041a\u0430\u0440\u0430\u0431\u0430\u0439"
    ],
    "name:und_x_variant":[
        "Qa\u1e5fa B\u0101y",
        "Karabay",
        "Qareh B\u0101y",
        "Qarah B\u0101y",
        "\u0642\u0631\u0647 \u0628\u0627\u06cc"
    ],
    "wof:name":"Qarah Bay",
    "wof:placetype":"locality"
},
  "geometry": {"coordinates":[69.56278,36.74655],"type":"Point"}
}