{
  "type": "Feature",
  "properties": {
    "gn:admin1_code":"41",
    "gn:admin2_code":"3407.0",
    "gn:asciiname":"Ghowch Now",
    "gn:country_code":"AF",
    "gn:dem":2331,
    "gn:feature_class":"P",
    "gn:feature_code":"PPL",
    "gn:name":"Ghowch Now",
    "gn:population":0,
    "gn:timezone":"Asia/Kabul",
    "iso:country":"AF",
    "name:und_x_variant":[
        "Ghaw\u010dnaw",
        "Ghowch Now",
        "Ghawch Now",
        "\u063a\u0648\u0686 \u0646\u0648"
    ],
    "wof:name":"Ghowch Now",
    "wof:placetype":"locality"
},
  "geometry": {"coordinates":[66.62687,33.84931],"type":"Point"}
}