{
  "type": "Feature",
  "properties": {
    "gn:admin1_code":"26",
    "gn:admin2_code":"1208",
    "gn:asciiname":"Qal'ah-ye Girdab",
    "gn:country_code":"AF",
    "gn:dem":613,
    "gn:feature_class":"P",
    "gn:feature_code":"PPL",
    "gn:name":"Qal\u2018ah-ye Gird\u0101b",
    "gn:population":0,
    "gn:timezone":"Asia/Kabul",
    "iso:country":"AF",
    "name:und_x_variant":[
        "Qal\u2018a-i-Gerd\u0101b",
        "Kala-Sirdab",
        "Qala Gird\u0101b",
        "Kala Girdab",
        "Qal\u2018a Ge\u1e5fd\u0101b",
        "Qal\u2018eh-ye Gerd \u0100b",
        "Qal\u2018ah-ye Gird\u0101b",
        "\u0642\u0644\u0639\u06c0 \u06af\u0631\u062f\u0627\u0628"
    ],
    "wof:name":"Qal'ah-ye Girdab",
    "wof:placetype":"locality"
},
  "geometry": {"coordinates":[69.70531,36.93406],"type":"Point"}
}