{
  "type": "Feature",
  "properties": {
    "gn:admin1_code":"23",
    "gn:admin2_code":"2410.0",
    "gn:asciiname":"Baramzi",
    "gn:country_code":"AF",
    "gn:dem":997,
    "gn:feature_class":"P",
    "gn:feature_code":"PPL",
    "gn:name":"B\u0101r\u0101mz\u012b",
    "gn:population":0,
    "gn:timezone":"Asia/Kabul",
    "iso:country":"AF",
    "name:und_x_variant":[
        "B\u0101r\u0101mza\u012b",
        "B\u0101\u1e5f\u0101mzi",
        "B\u0101r\u0101mz\u012b",
        "\u0628\u0627\u0631\u0627\u0645\u0632\u06cc"
    ],
    "wof:name":"Baramzi",
    "wof:placetype":"locality"
},
  "geometry": {"coordinates":[66.09061,30.08805],"type":"Point"}
}