{
  "type": "Feature",
  "properties": {
    "gn:admin1_code":"27",
    "gn:admin2_code":"407",
    "gn:asciiname":"Sher Khel",
    "gn:country_code":"AF",
    "gn:dem":2451,
    "gn:feature_class":"P",
    "gn:feature_code":"PPL",
    "gn:name":"Sh\u0113r Kh\u0113l",
    "gn:population":0,
    "gn:timezone":"Asia/Kabul",
    "iso:country":"AF",
    "name:rus_x_preferred":[
        "Sherkheyl\u2019"
    ],
    "name:und_x_variant":[
        "\u0160\u0113rkh\u0113l",
        "Sh\u0113r Kh\u0113l",
        "Sh\u012br Kheyl",
        "\u0634\u06d0\u0631 \u062e\u06d0\u0644"
    ],
    "wof:name":"Sher Khel",
    "wof:placetype":"locality"
},
  "geometry": {"coordinates":[68.57207,33.76903],"type":"Point"}
}