{
  "type": "Feature",
  "properties": {
    "gn:admin1_code":"05",
    "gn:admin2_code":"2806",
    "gn:asciiname":"Patahgak",
    "gn:country_code":"AF",
    "gn:dem":2916,
    "gn:feature_class":"P",
    "gn:feature_code":"PPL",
    "gn:name":"Patahgak",
    "gn:population":0,
    "gn:timezone":"Asia/Kabul",
    "iso:country":"AF",
    "name:und_x_variant":[
        "Padagak",
        "Patagak",
        "Patahgak",
        "\u067e\u062a\u0647\u06af\u06a9"
    ],
    "wof:name":"Patahgak",
    "wof:placetype":"locality"
},
  "geometry": {"coordinates":[66.96344999999999,34.15463],"type":"Point"}
}