{
  "type": "Feature",
  "properties": {
    "gn:admin1_code":"23",
    "gn:admin2_code":"2401",
    "gn:asciiname":"Jabar Kelay",
    "gn:country_code":"AF",
    "gn:dem":990,
    "gn:feature_class":"P",
    "gn:feature_code":"PPL",
    "gn:name":"Jab\u0101r K\u00ealay",
    "gn:population":0,
    "gn:timezone":"Asia/Kabul",
    "iso:country":"AF",
    "name:fas_x_preferred":[
        "\u0642\u0631\u064a\u06c0 \u062c\u0628\u0627\u0631"
    ],
    "name:und_x_variant":[
        "Jab\u0101r",
        "Jabr",
        "Jab\u0101r Kalay",
        "Jab\u0101r K\u00ealay",
        "\u062c\u0628\u0627\u0631 \u06a9\u0644\u06cc"
    ],
    "wof:name":"Jabar Kelay",
    "wof:placetype":"locality"
},
  "geometry": {"coordinates":[65.76038,31.50471],"type":"Point"}
}