{
  "type": "Feature",
  "properties": {
    "gn:admin1_code":"3",
    "gn:admin2_code":"1310.0",
    "gn:asciiname":"Badam Pistah",
    "gn:country_code":"AF",
    "gn:dem":975,
    "gn:feature_class":"P",
    "gn:feature_code":"PPL",
    "gn:name":"B\u0101d\u0101m Pistah",
    "gn:population":0,
    "gn:timezone":"Asia/Kabul",
    "iso:country":"AF",
    "name:rus_x_preferred":[
        "\u0411\u0430\u0434\u0430\u043c\u043f\u0438\u0441\u0442\u0430"
    ],
    "name:und_x_variant":[
        "Badampista",
        "B\u0101\u1e0f\u0101m Pesta",
        "B\u0101d\u0101m Pesteh",
        "B\u0101d\u0101m Pistah",
        "\u0628\u0627\u062f\u0627\u0645 \u067e\u0633\u062a\u0647"
    ],
    "wof:name":"Badam Pistah",
    "wof:placetype":"locality"
},
  "geometry": {"coordinates":[68.9833,36.39835],"type":"Point"}
}