{
  "type": "Feature",
  "properties": {
    "gn:admin1_code":"34",
    "gn:admin2_code":"1011.0",
    "gn:asciiname":"Qala Wunah",
    "gn:country_code":"AF",
    "gn:dem":882,
    "gn:feature_class":"P",
    "gn:feature_code":"PPL",
    "gn:name":"Qal\u0101 Wunah",
    "gn:population":0,
    "gn:timezone":"Asia/Kabul",
    "iso:country":"AF",
    "name:fas_x_preferred":[
        "\u0642\u0644\u0639\u0647 \u0648\u0646\u0647"
    ],
    "name:und_x_variant":[
        "Kalavuna",
        "Qal\u0101 Wona",
        "Qal\u2018ah Wonah",
        "Qal\u2018eh Wonah",
        "Qal\u0101 Wunah",
        "\u0642\u0644\u0627 \u0648\u0646\u0647"
    ],
    "wof:name":"Qala Wunah",
    "wof:placetype":"locality"
},
  "geometry": {"coordinates":[71.00099,34.76402],"type":"Point"}
}