{
  "type": "Feature",
  "properties": {
    "gn:admin1_code":"07",
    "gn:admin2_code":"1809",
    "gn:asciiname":"Ralwartli",
    "gn:country_code":"AF",
    "gn:dem":392,
    "gn:feature_class":"P",
    "gn:feature_code":"PPL",
    "gn:name":"Ralwartl\u012b",
    "gn:population":0,
    "gn:timezone":"Asia/Kabul",
    "iso:country":"AF",
    "name:und_x_variant":[
        "Ralwartl\u012b",
        "\u0631\u0644\u0648\u0631\u062a\u0644\u06cc"
    ],
    "wof:name":"Ralwartli",
    "wof:placetype":"locality"
},
  "geometry": {"coordinates":[64.91318000000001,36.50796],"type":"Point"}
}