{
  "type": "Feature",
  "properties": {
    "gn:admin1_code":"35",
    "gn:admin2_code":"902.0",
    "gn:asciiname":"Kalkalabad",
    "gn:country_code":"AF",
    "gn:dem":631,
    "gn:feature_class":"P",
    "gn:feature_code":"PPL",
    "gn:name":"Kalkal\u0101b\u0101d",
    "gn:population":0,
    "gn:timezone":"Asia/Kabul",
    "iso:country":"AF",
    "name:rus_x_preferred":[
        "Kal\u2019kalabad"
    ],
    "name:und_x_variant":[
        "Kalkal\u0101b\u0101d",
        "\u06a9\u0644 \u06a9\u0644 \u0622\u0628\u0627\u062f"
    ],
    "wof:name":"Kalkalabad",
    "wof:placetype":"locality"
},
  "geometry": {"coordinates":[70.26745,34.53685],"type":"Point"}
}