{
  "type": "Feature",
  "properties": {
    "gn:admin1_code":"7",
    "gn:admin2_code":"1807.0",
    "gn:asciiname":"Bashfirish",
    "gn:country_code":"AF",
    "gn:dem":1653,
    "gn:feature_class":"P",
    "gn:feature_code":"PPL",
    "gn:name":"B\u0101shfir\u012bsh",
    "gn:population":0,
    "gn:timezone":"Asia/Kabul",
    "iso:country":"AF",
    "name:und_x_variant":[
        "B\u0101s\u0304fe\u1e5f\u012bs\u0304",
        "B\u0101shfer\u012bsh",
        "B\u0101shfir\u012bsh",
        "\u0628\u0627\u0634 \u0641\u0631\u06cc\u0634"
    ],
    "wof:name":"Bashfirish",
    "wof:placetype":"locality"
},
  "geometry": {"coordinates":[65.0825,35.64102000000001],"type":"Point"}
}