{
  "type": "Feature",
  "properties": {
    "gn:admin1_code":"19",
    "gn:admin2_code":"2201",
    "gn:asciiname":"Mulla Nur Muhammad",
    "gn:country_code":"AF",
    "gn:dem":492,
    "gn:feature_class":"P",
    "gn:feature_code":"PPL",
    "gn:name":"Mull\u0101 N\u016br Mu\u1e29ammad",
    "gn:population":0,
    "gn:timezone":"Asia/Kabul",
    "iso:country":"AF",
    "name:fas_x_preferred":[
        "\u0645\u0644\u0627 \u0646\u0648\u0631 \u0645\u062d\u062f"
    ],
    "name:und_x_variant":[
        "Mull\u0101 N\u016b\u1e5fmoh\u1e0f",
        "Mull\u0101 N\u016br Mu\u1e29ammad",
        "\u0645\u0644\u0627 \u0646\u0648\u0631 \u0645\u062d\u0645\u062f",
        "Moll\u0101 N\u016br Mo\u1e29d"
    ],
    "wof:name":"Mulla Nur Muhammad",
    "wof:placetype":"locality"
},
  "geometry": {"coordinates":[61.8225,30.87694],"type":"Point"}
}