{
  "type": "Feature",
  "properties": {
    "gn:admin1_code":"34",
    "gn:admin2_code":"1005.0",
    "gn:asciiname":"Bunjalalah",
    "gn:country_code":"AF",
    "gn:dem":1525,
    "gn:feature_class":"P",
    "gn:feature_code":"PPL",
    "gn:name":"B\u016bnjal\u0101lah",
    "gn:population":0,
    "gn:timezone":"Asia/Kabul",
    "iso:country":"AF",
    "name:fas_x_preferred":[
        "\u0628\u0648\u0646\u062c\u0644\u0627\u0644\u0647"
    ],
    "name:und_x_variant":[
        "B\u016bnjal\u0101la",
        "Bundzhalala",
        "B\u016bnjal\u0101leh",
        "B\u016bnjal\u0101lah"
    ],
    "wof:name":"Bunjalalah",
    "wof:placetype":"locality"
},
  "geometry": {"coordinates":[71.49947,35.15595],"type":"Point"}
}