{
  "type": "Feature",
  "properties": {
    "gn:admin1_code":"30",
    "gn:admin2_code":"1606",
    "gn:asciiname":"Khwajah Khaliq Munjai",
    "gn:country_code":"AF",
    "gn:dem":343,
    "gn:feature_class":"P",
    "gn:feature_code":"PPL",
    "gn:name":"Khw\u0101jah Kh\u0101liq Munja\u012b",
    "gn:population":0,
    "gn:timezone":"Asia/Kabul",
    "iso:country":"AF",
    "name:fas_x_preferred":[
        "\u062e\u0648\u0627\u062c\u0647 \u062e\u0627\u0644\u0642 \u0645\u0646\u062c\u06cc"
    ],
    "name:rus_x_preferred":[
        "\u0425\u043e\u0434\u0436\u0430-\u0425\u0430\u043b\u0438\u043a\u043c\u0443\u043d\u0434\u0436\u0430\u0439"
    ],
    "name:und_x_variant":[
        "Khw\u0101ja Kh\u0101liq Munjai",
        "Khodzha-Khalikmundzhay",
        "Khw\u0101jah Kh\u0101l\u012bq Munja\u012b",
        "Khv\u0101jeh Kh\u0101leq Monjay",
        "Khw\u0101jah Kh\u0101liq Munja\u012b"
    ],
    "wof:name":"Khwajah Khaliq Munjai",
    "wof:placetype":"locality"
},
  "geometry": {"coordinates":[66.91334000000001,36.76704],"type":"Point"}
}