{
  "type": "Feature",
  "properties": {
    "gn:admin1_code":"09",
    "gn:admin2_code":"2701.0",
    "gn:asciiname":"Jar Matu",
    "gn:country_code":"AF",
    "gn:dem":2313,
    "gn:feature_class":"P",
    "gn:feature_code":"PPL",
    "gn:name":"Jar Mat\u016b",
    "gn:population":0,
    "gn:timezone":"Asia/Kabul",
    "iso:country":"AF",
    "name:und_x_variant":[
        "Jar Mat\u016b",
        "\u062c\u0631 \u0645\u062a\u0648",
        "Ju\u1e5fmatu"
    ],
    "wof:name":"Jar Matu",
    "wof:placetype":"locality"
},
  "geometry": {"coordinates":[65.005,34.53531],"type":"Point"}
}