{
  "type": "Feature",
  "properties": {
    "gn:admin1_code":"17",
    "gn:admin2_code":"505",
    "gn:asciiname":"Gomaran",
    "gn:country_code":"AF",
    "gn:dem":1840,
    "gn:feature_class":"P",
    "gn:feature_code":"PPL",
    "gn:name":"G\u014dmar\u0101n",
    "gn:population":0,
    "gn:timezone":"Asia/Kabul",
    "iso:country":"AF",
    "name:und_x_variant":[
        "G\u014dma\u1e5f\u0101n",
        "Gomaran",
        "Gomar\u0101n",
        "Gowmaran",
        "Sh\u0113r\u0101zah",
        "G\u014dmar\u0101n",
        "\u06af\u0648\u0645\u0631\u0627\u0646"
    ],
    "wof:name":"Gomaran",
    "wof:placetype":"locality"
},
  "geometry": {"coordinates":[69.15164,34.28777],"type":"Point"}
}