{
  "type": "Feature",
  "properties": {
    "gn:admin1_code":"01",
    "gn:admin2_code":"1117.0",
    "gn:asciiname":"Uzgad",
    "gn:country_code":"AF",
    "gn:dem":1648,
    "gn:feature_class":"P",
    "gn:feature_code":"PPL",
    "gn:name":"\u016azgad",
    "gn:population":0,
    "gn:timezone":"Asia/Kabul",
    "iso:country":"AF",
    "name:und_x_variant":[
        "\u016azgad",
        "\u0627\u0648\u0632\u06af\u062f"
    ],
    "wof:name":"Uzgad",
    "wof:placetype":"locality"
},
  "geometry": {"coordinates":[71.05094,38.39588],"type":"Point"}
}