{
  "type": "Feature",
  "properties": {
    "gn:admin1_code":"01",
    "gn:admin2_code":"1128",
    "gn:asciiname":"Ragh",
    "gn:country_code":"AF",
    "gn:dem":1511,
    "gn:feature_class":"P",
    "gn:feature_code":"PPL",
    "gn:name":"R\u0101gh",
    "gn:population":0,
    "gn:timezone":"Asia/Kabul",
    "iso:country":"AF",
    "name:fas_x_preferred":[
        "\u0631\u064e\u0627\u063a"
    ],
    "name:und_x_variant":[
        "R\u0101gh",
        "\u0631\u0627\u063a"
    ],
    "wof:name":"Ragh",
    "wof:placetype":"locality"
},
  "geometry": {"coordinates":[70.44655999999998,37.53984000000001],"type":"Point"}
}