{
  "type": "Feature",
  "properties": {
    "gn:admin1_code":"8",
    "gn:admin2_code":"604.0",
    "gn:asciiname":"Chowni",
    "gn:country_code":"AF",
    "gn:dem":3206,
    "gn:feature_class":"P",
    "gn:feature_code":"PPL",
    "gn:name":"Chown\u012b",
    "gn:population":0,
    "gn:timezone":"Asia/Kabul",
    "iso:country":"AF",
    "name:und_x_variant":[
        "\u010cawni",
        "Chawn\u012b",
        "Chown\u012b",
        "\u0686\u0648\u0646\u06cc"
    ],
    "wof:name":"Chowni",
    "wof:placetype":"locality"
},
  "geometry": {"coordinates":[67.96081,33.66624],"type":"Point"}
}