{
  "type": "Feature",
  "properties": {
    "gn:admin1_code":"42",
    "gn:admin2_code":"3306.0",
    "gn:asciiname":"Malikan",
    "gn:country_code":"AF",
    "gn:dem":1739,
    "gn:feature_class":"P",
    "gn:feature_code":"PPL",
    "gn:name":"Malik\u0101n",
    "gn:population":0,
    "gn:timezone":"Asia/Kabul",
    "iso:country":"AF",
    "name:fas_x_preferred":[
        "\u0645\u0644\u0643\u0627\u0646"
    ],
    "name:und_x_variant":[
        "Malek\u0101n",
        "Malik\u0101n",
        "\u0645\u0644\u06a9\u0627\u0646"
    ],
    "wof:name":"Malikan",
    "wof:placetype":"locality"
},
  "geometry": {"coordinates":[69.36514,35.2308],"type":"Point"}
}