{
  "type": "Feature",
  "properties": {
    "gn:admin1_code":"19",
    "gn:admin2_code":"2201",
    "gn:asciiname":"Yosuf",
    "gn:country_code":"AF",
    "gn:dem":486,
    "gn:feature_class":"P",
    "gn:feature_code":"PPL",
    "gn:name":"Y\u014dsuf",
    "gn:population":0,
    "gn:timezone":"Asia/Kabul",
    "iso:country":"AF",
    "name:und_x_variant":[
        "Y\u016bsof",
        "Y\u014dsuf",
        "Y\u016bsef",
        "\u06cc\u0648\u0633\u0641"
    ],
    "wof:name":"Yosuf",
    "wof:placetype":"locality"
},
  "geometry": {"coordinates":[61.90464,30.98365],"type":"Point"}
}