{
  "type": "Feature",
  "properties": {
    "gn:admin1_code":"05",
    "gn:admin2_code":"2807",
    "gn:asciiname":"Khudaydad Khel",
    "gn:country_code":"AF",
    "gn:dem":2030,
    "gn:feature_class":"P",
    "gn:feature_code":"PPLA2",
    "gn:name":"Khud\u0101yd\u0101d Kh\u0113l",
    "gn:population":0,
    "gn:timezone":"Asia/Kabul",
    "iso:country":"AF",
    "name:und_x_variant":[
        "Kho\u1e0f\u0101y\u1e0f\u0101\u1e0fkh\u0113l",
        "Khod\u0101yd\u0101d Kh\u0113l",
        "Khod\u0101yd\u0101d Kheyl",
        "Khud\u0101yd\u0101d Kh\u0113l",
        "\u062e\u062f\u0627\u06cc\u062f\u0627\u062f \u062e\u06d0\u0644",
        "Khud\u0101 D\u0101d Kh\u0113l",
        "\u062e\u062f\u0627 \u062f\u0627\u062f \u062e\u06d0\u0644"
    ],
    "wof:name":"Khudaydad Khel",
    "wof:placetype":"locality"
},
  "geometry": {"coordinates":[67.68758000000001,35.17835],"type":"Point"}
}