{
  "type": "Feature",
  "properties": {
    "gn:admin1_code":"26",
    "gn:admin2_code":"1208.0",
    "gn:asciiname":"Hazarah Qishlaq",
    "gn:country_code":"AF",
    "gn:dem":1034,
    "gn:feature_class":"P",
    "gn:feature_code":"PPL",
    "gn:name":"Haz\u0101rah Qishl\u0101q",
    "gn:population":0,
    "gn:timezone":"Asia/Kabul",
    "iso:country":"AF",
    "name:und_x_variant":[
        "Haz\u0101\u1e5fa Qesl\u0101q",
        "Hez\u0101reh Qeshl\u0101q",
        "Haz\u0101rah Qishl\u0101q",
        "\u0647\u0632\u0627\u0631\u0647 \u0642\u0634\u0644\u0627\u0642"
    ],
    "wof:name":"Hazarah Qishlaq",
    "wof:placetype":"locality"
},
  "geometry": {"coordinates":[69.63831,37.10891],"type":"Point"}
}