{
  "type": "Feature",
  "properties": {
    "gn:admin1_code":"27",
    "gn:admin2_code":"407.0",
    "gn:asciiname":"Nasir Khel",
    "gn:country_code":"AF",
    "gn:dem":2307,
    "gn:feature_class":"P",
    "gn:feature_code":"PPL",
    "gn:name":"Na\u015f\u012br Kh\u0113l",
    "gn:population":0,
    "gn:timezone":"Asia/Kabul",
    "iso:country":"AF",
    "name:rus_x_preferred":[
        "Nasirkheyl\u2019"
    ],
    "name:und_x_variant":[
        "Na\u015f\u012b\u1e5fkh\u0113l",
        "Na\u015f\u012br Kh\u0113l",
        "Na\u015f\u012br Kheyl",
        "\u0646\u0635\u064a\u0631 \u062e\u06d0\u0644"
    ],
    "wof:name":"Nasir Khel",
    "wof:placetype":"locality"
},
  "geometry": {"coordinates":[68.64168000000001,33.99332],"type":"Point"}
}