{
  "type": "Feature",
  "properties": {
    "gn:admin1_code":"9",
    "gn:admin2_code":"2707.0",
    "gn:asciiname":"Kushk",
    "gn:country_code":"AF",
    "gn:dem":2910,
    "gn:feature_class":"P",
    "gn:feature_code":"PPL",
    "gn:name":"Kushk",
    "gn:population":0,
    "gn:timezone":"Asia/Kabul",
    "iso:country":"AF",
    "name:und_x_variant":[
        "Ku\u0161k",
        "K\u016bshk",
        "Kushk",
        "\u06a9\u0634\u06a9"
    ],
    "wof:name":"Kushk",
    "wof:placetype":"locality"
},
  "geometry": {"coordinates":[66.28848000000001,34.57836],"type":"Point"}
}