{
  "type": "Feature",
  "properties": {
    "gn:admin1_code":"9",
    "gn:admin2_code":"2709.0",
    "gn:asciiname":"Dahan-e Jar-e Jawak",
    "gn:country_code":"AF",
    "gn:dem":2599,
    "gn:feature_class":"P",
    "gn:feature_code":"PPL",
    "gn:name":"Dahan-e Jar-e Jawak",
    "gn:population":0,
    "gn:timezone":"Asia/Kabul",
    "iso:country":"AF",
    "name:und_x_variant":[
        "\u1e0eahane",
        "Dahan-e Jar-e Jawak",
        "\u062f\u0647\u0646 \u062c\u0631 \u062c\u0648\u06a9"
    ],
    "wof:name":"Dahan-e Jar-e Jawak",
    "wof:placetype":"locality"
},
  "geometry": {"coordinates":[65.93256,34.63398],"type":"Point"}
}