{
  "type": "Feature",
  "properties": {
    "gn:admin1_code":"36",
    "gn:admin2_code":"702",
    "gn:asciiname":"Dowlat Khan",
    "gn:country_code":"AF",
    "gn:dem":2271,
    "gn:feature_class":"P",
    "gn:feature_code":"PPL",
    "gn:name":"Dowlat Kh\u0101n",
    "gn:population":0,
    "gn:timezone":"Asia/Kabul",
    "iso:country":"AF",
    "name:und_x_variant":[
        "Kala Daulat Kh\u0101n",
        "Qal\u2018eh-ye Dowlat Kh\u0101n",
        "\u1e0eawlatkh\u0101n",
        "Qala Daulat Kh\u0101n",
        "Daulatkhan",
        "Dowlat Kh\u0101n",
        "\u062f\u0648\u0644\u062a \u062e\u0627\u0646"
    ],
    "wof:name":"Dowlat Khan",
    "wof:placetype":"locality"
},
  "geometry": {"coordinates":[68.80365999999999,33.51003],"type":"Point"}
}