{
  "type": "Feature",
  "properties": {
    "gn:admin1_code":"28",
    "gn:admin2_code":"2507",
    "gn:asciiname":"Wuchakay",
    "gn:country_code":"AF",
    "gn:dem":1947,
    "gn:feature_class":"P",
    "gn:feature_code":"PPL",
    "gn:name":"Wuchakay",
    "gn:population":0,
    "gn:timezone":"Asia/Kabul",
    "iso:country":"AF",
    "name:und_x_variant":[
        "Vuchakay",
        "Wo\u010dakay",
        "Wuchakay",
        "\u0648\u0686\u06a9\u06cc",
        "Wochakay"
    ],
    "wof:name":"Wuchakay",
    "wof:placetype":"locality"
},
  "geometry": {"coordinates":[67.27413,31.94373],"type":"Point"}
}