{
  "type": "Feature",
  "properties": {
    "gn:admin1_code":"06",
    "gn:admin2_code":"2108",
    "gn:asciiname":"Hasanabad",
    "gn:country_code":"AF",
    "gn:dem":618,
    "gn:feature_class":"P",
    "gn:feature_code":"PPL",
    "gn:name":"\u1e28asan\u0101b\u0101d",
    "gn:population":0,
    "gn:timezone":"Asia/Kabul",
    "iso:country":"AF",
    "name:und_x_variant":[
        "H\u0331as\u1e0f\u0101n Ab\u0101\u1e0f",
        "\u1e28asan\u0101b\u0101d",
        "\u062d\u0633\u0646 \u0622\u0628\u0627\u062f"
    ],
    "wof:name":"Hasanabad",
    "wof:placetype":"locality"
},
  "geometry": {"coordinates":[61.43355,32.36551],"type":"Point"}
}