{
  "type": "Feature",
  "properties": {
    "gn:admin1_code":"05",
    "gn:admin2_code":"2806.0",
    "gn:asciiname":"Ghar",
    "gn:country_code":"AF",
    "gn:dem":2936,
    "gn:feature_class":"P",
    "gn:feature_code":"PPL",
    "gn:name":"Gh\u0101r",
    "gn:population":0,
    "gn:timezone":"Asia/Kabul",
    "iso:country":"AF",
    "wof:name":"Ghar",
    "wof:placetype":"locality"
},
  "geometry": {"coordinates":[67.31638000000001,34.32168],"type":"Point"}
}