{
  "type": "Feature",
  "properties": {
    "gn:admin1_code":"35",
    "gn:admin2_code":"905.0",
    "gn:asciiname":"Dumah Yo",
    "gn:country_code":"AF",
    "gn:dem":1261,
    "gn:feature_class":"P",
    "gn:feature_code":"PPL",
    "gn:name":"Dumah Y\u014d",
    "gn:population":0,
    "gn:timezone":"Asia/Kabul",
    "iso:country":"AF",
    "name:und_x_variant":[
        "Dumayo",
        "Domayo",
        "Dumah Y\u014d",
        "\u062f\u0645\u0647 \u06cc\u0648",
        "D\u014dmah Y\u014d",
        "\u062f\u0648\u0645\u0647 \u06cc\u0648"
    ],
    "wof:name":"Dumah Yo",
    "wof:placetype":"locality"
},
  "geometry": {"coordinates":[70.04286,34.79369000000001],"type":"Point"}
}