{
  "type": "Feature",
  "properties": {
    "gn:admin1_code":"30",
    "gn:admin2_code":"1611",
    "gn:asciiname":"Sar-e Shor",
    "gn:country_code":"AF",
    "gn:dem":2013,
    "gn:feature_class":"P",
    "gn:feature_code":"PPL",
    "gn:name":"Sar-e Sh\u014dr",
    "gn:population":0,
    "gn:timezone":"Asia/Kabul",
    "iso:country":"AF",
    "name:und_x_variant":[
        "Sar-i-Shor",
        "Sar-e Sh\u016br",
        "Sar-e Sh\u014dr",
        "\u0633\u0631 \u0634\u0648\u0631"
    ],
    "wof:name":"Sar-e Shor",
    "wof:placetype":"locality"
},
  "geometry": {"coordinates":[67.19879,36.41261],"type":"Point"}
}