{
  "type": "Feature",
  "properties": {
    "gn:admin1_code":"5",
    "gn:admin2_code":"2805.0",
    "gn:asciiname":"Dahan-e Gudar",
    "gn:country_code":"AF",
    "gn:dem":2773,
    "gn:feature_class":"P",
    "gn:feature_code":"PPL",
    "gn:name":"Dahan-e Gudar",
    "gn:population":0,
    "gn:timezone":"Asia/Kabul",
    "iso:country":"AF",
    "name:und_x_variant":[
        "Dakhani-Gudar",
        "Dahan-e G\u014ddar",
        "Dahan-e God\u0101r",
        "Dahan-e Gudar",
        "\u062f\u0647\u0646 \u06af\u062f\u0631"
    ],
    "wof:name":"Dahan-e Gudar",
    "wof:placetype":"locality"
},
  "geometry": {"coordinates":[66.76626999999999,34.36743],"type":"Point"}
}