{
  "type": "Feature",
  "properties": {
    "gn:admin1_code":"03",
    "gn:admin2_code":"1310",
    "gn:asciiname":"Pahlavan Tash",
    "gn:country_code":"AF",
    "gn:dem":1062,
    "gn:feature_class":"P",
    "gn:feature_code":"PPL",
    "gn:name":"Pahlav\u0101n T\u0101sh",
    "gn:population":0,
    "gn:timezone":"Asia/Kabul",
    "iso:country":"AF",
    "name:fas_x_preferred":[
        "\u067e\u0647\u0644\u0648\u0627\u0646 \u062a\u0627\u0634"
    ],
    "name:und_x_variant":[
        "Pahlaw\u0101n T\u0101sh",
        "Pahlav\u0101n T\u0101sh"
    ],
    "wof:name":"Pahlavan Tash",
    "wof:placetype":"locality"
},
  "geometry": {"coordinates":[68.98333000000001,36.35],"type":"Point"}
}