{
  "type": "Feature",
  "properties": {
    "gn:admin1_code":"28",
    "gn:admin2_code":"2509.0",
    "gn:asciiname":"Ambargai",
    "gn:country_code":"AF",
    "gn:dem":2193,
    "gn:feature_class":"P",
    "gn:feature_code":"PPL",
    "gn:name":"Amb\u0101rga\u012b",
    "gn:population":0,
    "gn:timezone":"Asia/Kabul",
    "iso:country":"AF",
    "name:und_x_variant":[
        "Amb\u0101rga\u012b",
        "Amb\u0101rgay",
        "\u0627\u0645\u0628\u0627\u0631\u06af\u06cc"
    ],
    "wof:name":"Ambargai",
    "wof:placetype":"locality"
},
  "geometry": {"coordinates":[67.80773000000001,31.8201],"type":"Point"}
}