{
  "type": "Feature",
  "properties": {
    "gn:admin1_code":"05",
    "gn:admin2_code":"2804.0",
    "gn:asciiname":"Naudzhu",
    "gn:country_code":"AF",
    "gn:dem":3125,
    "gn:feature_class":"P",
    "gn:feature_code":"PPL",
    "gn:name":"Naudzhu",
    "gn:population":0,
    "gn:timezone":"Asia/Kabul",
    "iso:country":"AF",
    "name:fas_x_preferred":[
        "\u062c\u0648\u0626 \u0646\u0648"
    ],
    "name:rus_x_preferred":[
        "\u041d\u0430\u0443\u0434\u0436\u0443"
    ],
    "wof:name":"Naudzhu",
    "wof:placetype":"locality"
},
  "geometry": {"coordinates":[67.2025,34.73889],"type":"Point"}
}