{
  "type": "Feature",
  "properties": {
    "gn:admin1_code":"11",
    "gn:admin2_code":"2003",
    "gn:asciiname":"Padah-ye Kaj",
    "gn:country_code":"AF",
    "gn:dem":1245,
    "gn:feature_class":"P",
    "gn:feature_code":"PPL",
    "gn:name":"Padah-ye Kaj",
    "gn:population":0,
    "gn:timezone":"Asia/Kabul",
    "iso:country":"AF",
    "name:fas_x_preferred":[
        "\u067e\u062f\u06c0 \u0643\u062c"
    ],
    "name:und_x_variant":[
        "Pa\u1e0fa-i-Kaj",
        "Padayi-Kadzh",
        "Padeh-ye Kaj",
        "Padah-ye Kaj",
        "\u067e\u062f\u06c0 \u06a9\u062c"
    ],
    "wof:name":"Padah-ye Kaj",
    "wof:placetype":"locality"
},
  "geometry": {"coordinates":[62.36816999999999,34.10684000000001],"type":"Point"}
}