{
  "type": "Feature",
  "properties": {
    "gn:admin1_code":"09",
    "gn:admin2_code":"2702",
    "gn:asciiname":"Kolakia",
    "gn:country_code":"AF",
    "gn:dem":2391,
    "gn:feature_class":"P",
    "gn:feature_code":"PPL",
    "gn:name":"K\u014dlak\u012b\u0101",
    "gn:population":0,
    "gn:timezone":"Asia/Kabul",
    "iso:country":"AF",
    "name:rus_x_preferred":[
        "Kolak\u2019ya"
    ],
    "name:und_x_variant":[
        "K\u014dlak\u012b\u0101",
        "\u06a9\u0648\u0644\u06a9\u06cc\u0627",
        "Kolaky\u0101"
    ],
    "wof:name":"Kolakia",
    "wof:placetype":"locality"
},
  "geometry": {"coordinates":[64.22843,34.20405],"type":"Point"}
}