{
  "type": "Feature",
  "properties": {
    "gn:admin1_code":"27",
    "gn:admin2_code":"404",
    "gn:asciiname":"Mian Qol",
    "gn:country_code":"AF",
    "gn:dem":3096,
    "gn:feature_class":"P",
    "gn:feature_code":"PPL",
    "gn:name":"M\u012b\u0101n Q\u014dl",
    "gn:population":0,
    "gn:timezone":"Asia/Kabul",
    "iso:country":"AF",
    "name:rus_x_preferred":[
        "Miankul\u2019"
    ],
    "name:und_x_variant":[
        "My\u0101nq\u014dl",
        "M\u012b\u0101nqowl",
        "M\u012b\u0101n Q\u014dl",
        "\u0645\u06cc\u0627\u0646 \u0642\u0648\u0644"
    ],
    "wof:name":"Mian Qol",
    "wof:placetype":"locality"
},
  "geometry": {"coordinates":[67.82395,34.22731],"type":"Point"}
}