{
  "type": "Feature",
  "properties": {
    "gn:admin1_code":"5",
    "gn:admin2_code":"2801.0",
    "gn:asciiname":"Band-e Bala",
    "gn:country_code":"AF",
    "gn:dem":3019,
    "gn:feature_class":"P",
    "gn:feature_code":"PPL",
    "gn:name":"Band-e B\u0101l\u0101",
    "gn:population":0,
    "gn:timezone":"Asia/Kabul",
    "iso:country":"AF",
    "name:und_x_variant":[
        "Bandi-Bala",
        "Band-e B\u0101l\u0101",
        "\u0628\u0646\u062f \u0628\u0627\u0644\u0627"
    ],
    "wof:name":"Band-e Bala",
    "wof:placetype":"locality"
},
  "geometry": {"coordinates":[67.70696,34.73428],"type":"Point"}
}