{
  "type": "Feature",
  "properties": {
    "gn:admin1_code":"8",
    "gn:admin2_code":"605.0",
    "gn:asciiname":"Azragi",
    "gn:country_code":"AF",
    "gn:dem":2614,
    "gn:feature_class":"P",
    "gn:feature_code":"PPL",
    "gn:name":"Azrag\u012b",
    "gn:population":0,
    "gn:timezone":"Asia/Kabul",
    "iso:country":"AF",
    "name:und_x_variant":[
        "Azrag\u012b",
        "\u0627\u0632\u0631\u06af\u06cc",
        "Az\u1e5fag\u012b"
    ],
    "wof:name":"Azragi",
    "wof:placetype":"locality"
},
  "geometry": {"coordinates":[67.21871999999999,33.53344],"type":"Point"}
}