{
  "type": "Feature",
  "properties": {
    "gn:admin1_code":"13",
    "gn:admin2_code":"107.0",
    "gn:asciiname":"Qal'ah-ye Qala Biki",
    "gn:country_code":"AF",
    "gn:dem":1899,
    "gn:feature_class":"P",
    "gn:feature_code":"PPL",
    "gn:name":"Qal\u2018ah-ye Qal\u0101 B\u012bk\u012b",
    "gn:population":0,
    "gn:timezone":"Asia/Kabul",
    "iso:country":"AF",
    "name:und_x_variant":[
        "Qal\u2018ah-ye Qal\u0101 B\u012bk\u012b",
        "\u0642\u0644\u0639\u0647 \u0642\u0644\u0627 \u0628\u064a\u06a9\u06cc"
    ],
    "wof:name":"Qal'ah-ye Qala Biki",
    "wof:placetype":"locality"
},
  "geometry": {"coordinates":[69.07423,34.60993],"type":"Point"}
}