{
  "type": "Feature",
  "properties": {
    "gn:admin1_code":"23",
    "gn:admin2_code":"2415.0",
    "gn:asciiname":"Tatar",
    "gn:country_code":"AF",
    "gn:dem":1604,
    "gn:feature_class":"P",
    "gn:feature_code":"PPL",
    "gn:name":"T\u0101tar",
    "gn:population":0,
    "gn:timezone":"Asia/Kabul",
    "iso:country":"AF",
    "name:und_x_variant":[
        "T\u0101tar",
        "\u062a\u0627\u062a\u0631"
    ],
    "wof:name":"Tatar",
    "wof:placetype":"locality"
},
  "geometry": {"coordinates":[65.61369000000001,32.33669],"type":"Point"}
}