{
  "type": "Feature",
  "properties": {
    "gn:admin1_code":"2",
    "gn:admin2_code":"1904.0",
    "gn:asciiname":"Qishlaq-e Badgah",
    "gn:country_code":"AF",
    "gn:dem":2260,
    "gn:feature_class":"P",
    "gn:feature_code":"PPL",
    "gn:name":"Qishl\u0101q-e B\u0101dg\u0101h",
    "gn:population":0,
    "gn:timezone":"Asia/Kabul",
    "iso:country":"AF",
    "name:und_x_variant":[
        "Y\u0101d Qol",
        "Qos\u0304 B\u0101\u1e0fg\u0101h",
        "B\u0101\u1e0fgh\u014dl",
        "Qeshl\u0101q B\u0101dg\u0101h",
        "B\u0101d Ghowl",
        "Qes\u0304laq B\u0101\u1e0fg\u0101h",
        "B\u0101\u1e0fga",
        "B\u0101d Qol",
        "B\u0101dg\u0101h",
        "Qishl\u0101q-e B\u0101dg\u0101h",
        "\u0642\u0634\u0644\u0627\u0642 \u0628\u0627\u062f \u06af\u0627\u0647"
    ],
    "wof:name":"Qishlaq-e Badgah",
    "wof:placetype":"locality"
},
  "geometry": {"coordinates":[64.96926999999999,35.00338],"type":"Point"}
}