{
  "type": "Feature",
  "properties": {
    "gn:admin1_code":"31",
    "gn:admin2_code":"1703",
    "gn:asciiname":"Qarahghu",
    "gn:country_code":"AF",
    "gn:dem":1592,
    "gn:feature_class":"P",
    "gn:feature_code":"PPL",
    "gn:name":"Qarahgh\u016b",
    "gn:population":0,
    "gn:timezone":"Asia/Kabul",
    "iso:country":"AF",
    "name:und_x_variant":[
        "Qarahgh\u016b",
        "\u0642\u0631\u0647 \u063a\u0648",
        "Qaraghu"
    ],
    "wof:name":"Qarahghu",
    "wof:placetype":"locality"
},
  "geometry": {"coordinates":[65.50729,36.01305],"type":"Point"}
}