{
  "type": "Feature",
  "properties": {
    "gn:admin1_code":"30",
    "gn:admin2_code":"1611",
    "gn:asciiname":"Mulla Nazar 'Ali",
    "gn:country_code":"AF",
    "gn:dem":1538,
    "gn:feature_class":"P",
    "gn:feature_code":"PPL",
    "gn:name":"Mull\u0101 Naz\u0327ar \u2018Al\u012b",
    "gn:population":0,
    "gn:timezone":"Asia/Kabul",
    "iso:country":"AF",
    "name:und_x_variant":[
        "Mulla Nazar Ali",
        "Moll\u0101 Naz\u0327ar \u2018Al\u012b",
        "Mull\u0101 Naz\u0327ar \u2018Al\u012b",
        "\u0645\u0644\u0627 \u0646\u0638\u0631 \u0639\u0644\u06cc"
    ],
    "wof:name":"Mulla Nazar 'Ali",
    "wof:placetype":"locality"
},
  "geometry": {"coordinates":[67.38636,36.18282],"type":"Point"}
}