{
  "type": "Feature",
  "properties": {
    "gn:admin1_code":"39",
    "gn:admin2_code":"2604",
    "gn:asciiname":"Khakrezak",
    "gn:country_code":"AF",
    "gn:dem":1202,
    "gn:feature_class":"P",
    "gn:feature_code":"PPL",
    "gn:name":"Kh\u0101kr\u0113zak",
    "gn:population":0,
    "gn:timezone":"Asia/Kabul",
    "iso:country":"AF",
    "name:und_x_variant":[
        "Kh\u0101k\u1e5f\u0113zak",
        "Kh\u0101krayzak",
        "\u062e\u0627\u06a9\u0631\u06cc\u0632\u06a9",
        "Kh\u0101kr\u012bzak",
        "Kh\u0101kr\u0113zak"
    ],
    "wof:name":"Khakrezak",
    "wof:placetype":"locality"
},
  "geometry": {"coordinates":[65.56371999999999,33.12712],"type":"Point"}
}