{
  "type": "Feature",
  "properties": {
    "gn:admin1_code":"40",
    "gn:admin2_code":"308.0",
    "gn:asciiname":"Deh-e Hazarah",
    "gn:country_code":"AF",
    "gn:dem":1505,
    "gn:feature_class":"P",
    "gn:feature_code":"PPL",
    "gn:name":"Deh-e \u1e28az\u0101rah",
    "gn:population":0,
    "gn:timezone":"Asia/Kabul",
    "iso:country":"AF",
    "name:fas_x_preferred":[
        "\u062f\u0647\u0654 \u0647\u0631\u0632\u0627\u0631\u0647"
    ],
    "name:und_x_variant":[
        "Deh-e Harz\u0101ra",
        "\u1e0eehe \u1e28az\u0101\u1e5fa",
        "Dekhi-Khazara",
        "Deh-e Haz\u0101rah",
        "Deh-e Harz\u0101reh",
        "Deh-e \u1e28az\u0101rah",
        "\u062f\u0647 \u062d\u0632\u0627\u0631\u0647"
    ],
    "wof:name":"Deh-e Hazarah",
    "wof:placetype":"locality"
},
  "geometry": {"coordinates":[69.20028000000001,34.95037],"type":"Point"}
}