{
  "type": "Feature",
  "properties": {
    "gn:admin1_code":"10",
    "gn:admin2_code":"2305",
    "gn:asciiname":"Towlay",
    "gn:country_code":"AF",
    "gn:dem":1786,
    "gn:feature_class":"P",
    "gn:feature_code":"PPL",
    "gn:name":"Towlay",
    "gn:population":0,
    "gn:timezone":"Asia/Kabul",
    "iso:country":"AF",
    "name:und_x_variant":[
        "Taulay",
        "Towlay",
        "\u062a\u0648\u0644\u06cc",
        "Tawlay"
    ],
    "wof:name":"Towlay",
    "wof:placetype":"locality"
},
  "geometry": {"coordinates":[65.02327,32.94983],"type":"Point"}
}