{
  "type": "Feature",
  "properties": {
    "gn:admin1_code":"08",
    "gn:admin2_code":"607",
    "gn:asciiname":"Sang Joy",
    "gn:country_code":"AF",
    "gn:dem":2592,
    "gn:feature_class":"P",
    "gn:feature_code":"PPL",
    "gn:name":"Sang J\u014dy",
    "gn:population":0,
    "gn:timezone":"Asia/Kabul",
    "iso:country":"AF",
    "name:rus_x_preferred":[
        "\u0421\u0430\u043d\u0433\u0434\u0436\u043e\u0439"
    ],
    "name:und_x_variant":[
        "Sang J\u014dy",
        "Sangdzhoy",
        "Sangj\u016by",
        "\u0633\u0646\u06af \u062c\u0648\u06cc"
    ],
    "wof:name":"Sang Joy",
    "wof:placetype":"locality"
},
  "geometry": {"coordinates":[67.62012,33.14665],"type":"Point"}
}