{
  "type": "Feature",
  "properties": {
    "gn:admin1_code":"27",
    "gn:admin2_code":"402.0",
    "gn:asciiname":"Lakar",
    "gn:country_code":"AF",
    "gn:dem":2495,
    "gn:feature_class":"P",
    "gn:feature_code":"PPL",
    "gn:name":"Lak\u0101r",
    "gn:population":0,
    "gn:timezone":"Asia/Kabul",
    "iso:country":"AF",
    "name:und_x_variant":[
        "Lak\u0101r",
        "\u0644\u06a9\u0627\u0631"
    ],
    "wof:name":"Lakar",
    "wof:placetype":"locality"
},
  "geometry": {"coordinates":[68.63186,34.50394],"type":"Point"}
}