{
  "type": "Feature",
  "properties": {
    "gn:admin1_code":"31",
    "gn:admin2_code":"1701.0",
    "gn:asciiname":"Afghan Tapah",
    "gn:country_code":"AF",
    "gn:dem":401,
    "gn:feature_class":"P",
    "gn:feature_code":"PPL",
    "gn:name":"Afgh\u0101n Tapah",
    "gn:population":0,
    "gn:timezone":"Asia/Kabul",
    "iso:country":"AF",
    "name:und_x_variant":[
        "Afgh\u0101n Tapah",
        "\u0627\u0641\u063a\u0627\u0646 \u062a\u067e\u0647"
    ],
    "wof:name":"Afghan Tapah",
    "wof:placetype":"locality"
},
  "geometry": {"coordinates":[65.79824000000001,36.5451],"type":"Point"}
}