{
  "type": "Feature",
  "properties": {
    "gn:admin1_code":"41",
    "gn:admin2_code":"3407.0",
    "gn:asciiname":"Ishtu",
    "gn:country_code":"AF",
    "gn:dem":2619,
    "gn:feature_class":"P",
    "gn:feature_code":"PPL",
    "gn:name":"Isht\u016b",
    "gn:population":0,
    "gn:timezone":"Asia/Kabul",
    "iso:country":"AF",
    "name:und_x_variant":[
        "E\u0161tu (2)",
        "Eshtu (2)",
        "Isht\u016b",
        "\u0627\u0634\u062a\u0648"
    ],
    "wof:name":"Ishtu",
    "wof:placetype":"locality"
},
  "geometry": {"coordinates":[66.99325,33.67841],"type":"Point"}
}