{
  "type": "Feature",
  "properties": {
    "gn:admin1_code":"10",
    "gn:admin2_code":"2305",
    "gn:asciiname":"Kshetah-Bum",
    "gn:country_code":"AF",
    "gn:dem":1831,
    "gn:feature_class":"P",
    "gn:feature_code":"PPL",
    "gn:name":"Ks\u0332h\u0332\u00eatah-B\u016bm",
    "gn:population":0,
    "gn:timezone":"Asia/Kabul",
    "iso:country":"AF",
    "name:fas_x_preferred":[
        "\u0628\u0648\u0645 \u067e\u0627\u0626\u06cc\u0646"
    ],
    "name:rus_x_preferred":[
        "\u041a\u0448\u0430\u0442\u0442\u0430\u0431\u0443\u043c"
    ],
    "name:und_x_variant":[
        "K\u0161atta-b\u016bm",
        "Kshattabum",
        "Ks\u0332h\u0332atah B\u016bm",
        "Ks\u0332h\u0332\u00eatah-B\u016bm",
        "\u06a9\u069a\u062a\u0647 \u0628\u0648\u0645",
        "Ks\u0332h\u0332attah-B\u016bm"
    ],
    "wof:name":"Kshetah-Bum",
    "wof:placetype":"locality"
},
  "geometry": {"coordinates":[65.03389,33.14992],"type":"Point"}
}