{
  "type": "Feature",
  "properties": {
    "gn:admin1_code":"08",
    "gn:admin2_code":"618",
    "gn:asciiname":"Sulaiman Khel",
    "gn:country_code":"AF",
    "gn:dem":2212,
    "gn:feature_class":"P",
    "gn:feature_code":"PPL",
    "gn:name":"Sula\u012bm\u0101n Kh\u0113l",
    "gn:population":0,
    "gn:timezone":"Asia/Kabul",
    "iso:country":"AF",
    "name:fas_x_preferred":[
        "\u0633\u0644\u064a\u0645\u0627\u0646 \u062e\u064a\u0644"
    ],
    "name:rus_x_preferred":[
        "Suleymankheyl\u2019"
    ],
    "name:und_x_variant":[
        "Sol\u0113m\u0101nkh\u0113l",
        "Sula\u012bm\u0101n Kh\u0113l",
        "Soleym\u0101n Kheyl",
        "\u0633\u0644\u064a\u0645\u0627\u0646 \u062e\u06d0\u0644"
    ],
    "wof:name":"Sulaiman Khel",
    "wof:placetype":"locality"
},
  "geometry": {"coordinates":[68.30526,33.39806],"type":"Point"}
}