{
  "type": "Feature",
  "properties": {
    "gn:admin1_code":"29",
    "gn:admin2_code":"2909",
    "gn:asciiname":"'Abbas Khel",
    "gn:country_code":"AF",
    "gn:dem":2024,
    "gn:feature_class":"P",
    "gn:feature_code":"PPL",
    "gn:name":"\u2018Abb\u0101s Kh\u0113l",
    "gn:population":0,
    "gn:timezone":"Asia/Kabul",
    "iso:country":"AF",
    "name:und_x_variant":[
        "Khreabaskheyl\u2019",
        "Kh\u1e5f\u0113 \u2018Ab\u0101skh\u0113l",
        "\u2018Abb\u0101s Kh\u0113l",
        "\u2018Abb\u0101skheyl"
    ],
    "wof:name":"'Abbas Khel",
    "wof:placetype":"locality"
},
  "geometry": {"coordinates":[69.26056,32.83139],"type":"Point"}
}