{
  "type": "Feature",
  "properties": {
    "gn:admin1_code":"32",
    "gn:admin2_code":"1504",
    "gn:asciiname":"Deh-Kalan",
    "gn:country_code":"AF",
    "gn:dem":1490,
    "gn:feature_class":"P",
    "gn:feature_code":"PPL",
    "gn:name":"Deh-Kal\u0101n",
    "gn:population":0,
    "gn:timezone":"Asia/Kabul",
    "iso:country":"AF",
    "name:und_x_variant":[
        "Deh-Kal\u0101n",
        "\u062f\u0647 \u06a9\u0644\u0627\u0646",
        "\u1e0eeh-kal\u0101n"
    ],
    "wof:name":"Deh-Kalan",
    "wof:placetype":"locality"
},
  "geometry": {"coordinates":[67.36798,35.90855999999999],"type":"Point"}
}