{
  "type": "Feature",
  "properties": {
    "gn:admin1_code":"06",
    "gn:admin2_code":"2108",
    "gn:asciiname":"Karez-e Bakhshabad",
    "gn:country_code":"AF",
    "gn:dem":628,
    "gn:feature_class":"P",
    "gn:feature_code":"PPL",
    "gn:name":"K\u0101r\u0113z-e Bakhsh\u0101b\u0101d",
    "gn:population":0,
    "gn:timezone":"Asia/Kabul",
    "iso:country":"AF",
    "name:und_x_variant":[
        "K\u0101r\u0113z-e Bakh\u0161\u0101b\u0101d",
        "K\u0101r\u012bz-e Bakhsh\u0101b\u0101d",
        "K\u0101r\u0113z-e Bakhsh\u0101b\u0101d",
        "\u06a9\u0627\u0631\u06d0\u0632 \u0628\u062e\u0634 \u0622\u0628\u0627\u062f"
    ],
    "wof:name":"Karez-e Bakhshabad",
    "wof:placetype":"locality"
},
  "geometry": {"coordinates":[61.77548,32.31925],"type":"Point"}
}