{
  "type": "Feature",
  "properties": {
    "gn:admin1_code":"09",
    "gn:admin2_code":"2703",
    "gn:asciiname":"Sarghol",
    "gn:country_code":"AF",
    "gn:dem":2304,
    "gn:feature_class":"P",
    "gn:feature_code":"PPL",
    "gn:name":"Sargh\u014dl",
    "gn:population":0,
    "gn:timezone":"Asia/Kabul",
    "iso:country":"AF",
    "name:und_x_variant":[
        "Sar Qol",
        "Sa\u1e5f-gh\u014dl",
        "Sargh\u014dl",
        "\u0633\u0631\u063a\u0648\u0644",
        "Sar Gh\u016bl"
    ],
    "wof:name":"Sarghol",
    "wof:placetype":"locality"
},
  "geometry": {"coordinates":[63.76886999999999,34.091],"type":"Point"}
}