{
  "type": "Feature",
  "properties": {
    "gn:admin1_code":"09",
    "gn:admin2_code":"2703",
    "gn:asciiname":"Qar-e Day",
    "gn:country_code":"AF",
    "gn:dem":1869,
    "gn:feature_class":"P",
    "gn:feature_code":"PPL",
    "gn:name":"Q\u0101r-e D\u0101y",
    "gn:population":0,
    "gn:timezone":"Asia/Kabul",
    "iso:country":"AF",
    "name:und_x_variant":[
        "Q\u0101r-e D\u0101y",
        "\u0642\u0627\u0631\u062f\u0627\u06cc"
    ],
    "wof:name":"Qar-e Day",
    "wof:placetype":"locality"
},
  "geometry": {"coordinates":[63.55786,34.17998],"type":"Point"}
}