{
  "type": "Feature",
  "properties": {
    "gn:admin1_code":"01",
    "gn:admin2_code":"1119.0",
    "gn:asciiname":"Zarmich-e Bala",
    "gn:country_code":"AF",
    "gn:dem":2590,
    "gn:feature_class":"P",
    "gn:feature_code":"PPL",
    "gn:name":"Zarm\u012bch-e B\u0101l\u0101",
    "gn:population":0,
    "gn:timezone":"Asia/Kabul",
    "iso:country":"AF",
    "name:und_x_variant":[
        "Za\u1e5fm\u012bc-i-B\u0101l\u0101",
        "Zarm\u012bch-e B\u0101l\u0101",
        "\u0632\u0631\u0645\u06cc\u0686 \u0628\u0627\u0644\u0627"
    ],
    "wof:name":"Zarmich-e Bala",
    "wof:placetype":"locality"
},
  "geometry": {"coordinates":[70.59536999999997,37.45329],"type":"Point"}
}