{
  "type": "Feature",
  "properties": {
    "gn:admin1_code":"29",
    "gn:admin2_code":"2909.0",
    "gn:asciiname":"Sowdal Malkshay Kot",
    "gn:country_code":"AF",
    "gn:dem":2121,
    "gn:feature_class":"P",
    "gn:feature_code":"PPL",
    "gn:name":"Sowdal Malkshay K\u014d\u1e6f",
    "gn:population":0,
    "gn:timezone":"Asia/Kabul",
    "iso:country":"AF",
    "name:rus_x_preferred":[
        "Saudal\u2019mal\u2019kshay-Kot"
    ],
    "name:und_x_variant":[
        "Sawdal Malk\u0161ay Kot",
        "Saudal\u2019mal\u2019kshay-Kot",
        "Sawdal Malkshay Kow\u1e6f",
        "Sowdal Malkshay K\u014d\u1e6f",
        "\u0633\u0648\u062f\u0644 \u0645\u0644\u06a9\u0634\u06cc \u06a9\u0648\u067c"
    ],
    "wof:name":"Sowdal Malkshay Kot",
    "wof:placetype":"locality"
},
  "geometry": {"coordinates":[69.22705000000001,32.61258],"type":"Point"}
}