{
  "type": "Feature",
  "properties": {
    "gn:admin1_code":"17",
    "gn:admin2_code":"503.0",
    "gn:asciiname":"Bavu",
    "gn:country_code":"AF",
    "gn:dem":1968,
    "gn:feature_class":"P",
    "gn:feature_code":"PPL",
    "gn:name":"Bavu",
    "gn:population":0,
    "gn:timezone":"Asia/Kabul",
    "iso:country":"AF",
    "name:und_x_variant":[
        "B\u0101w\u016b",
        "B\u0101wu",
        "\u0628\u0627\u0648\u0648"
    ],
    "wof:name":"Bavu",
    "wof:placetype":"locality"
},
  "geometry": {"coordinates":[68.87257,33.95261],"type":"Point"}
}