{
  "type": "Feature",
  "properties": {
    "gn:admin1_code":"19",
    "gn:admin2_code":"2202.0",
    "gn:asciiname":"Haji Amir",
    "gn:country_code":"AF",
    "gn:dem":482,
    "gn:feature_class":"P",
    "gn:feature_code":"PPL",
    "gn:name":"\u1e28\u0101j\u012b Am\u012br",
    "gn:population":0,
    "gn:timezone":"Asia/Kabul",
    "iso:country":"AF",
    "name:und_x_variant":[
        "H\u0331\u0101ji Am\u012br",
        "\u1e28\u0101j\u012b Am\u012br",
        "\u1e28\u0101jj\u012b Am\u012br"
    ],
    "wof:name":"Haji Amir",
    "wof:placetype":"locality"
},
  "geometry": {"coordinates":[61.82583,31.14278],"type":"Point"}
}