{
  "type": "Feature",
  "properties": {
    "gn:admin1_code":"27",
    "gn:admin2_code":"403.0",
    "gn:asciiname":"Qol-e Daday",
    "gn:country_code":"AF",
    "gn:dem":3247,
    "gn:feature_class":"P",
    "gn:feature_code":"PPL",
    "gn:name":"Q\u014dl-e D\u0101day",
    "gn:population":0,
    "gn:timezone":"Asia/Kabul",
    "iso:country":"AF",
    "name:und_x_variant":[
        "Kulle-Daday",
        "Qulle \u1e0e\u0101\u1e0fay",
        "Qoll-e D\u0101day",
        "Q\u014dl-e D\u0101d\u012b",
        "Q\u014dl-e D\u0101day",
        "\u0642\u0648\u0644 \u062f\u0627\u062f\u06cc"
    ],
    "wof:name":"Qol-e Daday",
    "wof:placetype":"locality"
},
  "geometry": {"coordinates":[68.12899999999999,34.60399],"type":"Point"}
}