{
  "type": "Feature",
  "properties": {
    "gn:admin1_code":"10",
    "gn:admin2_code":"2301.0",
    "gn:asciiname":"Dewghan",
    "gn:country_code":"AF",
    "gn:dem":787,
    "gn:feature_class":"P",
    "gn:feature_code":"PPL",
    "gn:name":"D\u0113wgh\u0101n",
    "gn:population":0,
    "gn:timezone":"Asia/Kabul",
    "iso:country":"AF",
    "name:fas_x_preferred":[
        "\u062f\u064a\u0648\u063a\u0627\u0646"
    ],
    "name:und_x_variant":[
        "Devgan",
        "D\u0113wgh\u0101n",
        "\u062f\u06d0\u0648\u063a\u0627\u0646"
    ],
    "wof:name":"Dewghan",
    "wof:placetype":"locality"
},
  "geometry": {"coordinates":[64.49468,31.62423],"type":"Point"}
}