{
  "type": "Feature",
  "properties": {
    "gn:admin1_code":"23",
    "gn:admin2_code":"2401.0",
    "gn:asciiname":"Deh-e Now",
    "gn:country_code":"AF",
    "gn:dem":954,
    "gn:feature_class":"P",
    "gn:feature_code":"PPL",
    "gn:name":"Deh-e Now",
    "gn:population":0,
    "gn:timezone":"Asia/Kabul",
    "iso:country":"AF",
    "name:und_x_variant":[
        "Dekhi-Nau",
        "\u1e0eehe Naw",
        "Deh-e Now",
        "\u062f\u0647 \u0646\u0648"
    ],
    "wof:name":"Deh-e Now",
    "wof:placetype":"locality"
},
  "geometry": {"coordinates":[65.60242,31.42273],"type":"Point"}
}