{
  "type": "Feature",
  "properties": {
    "gn:admin1_code":"30",
    "gn:admin2_code":"1610",
    "gn:asciiname":"Khal-e Mirzan",
    "gn:country_code":"AF",
    "gn:dem":1894,
    "gn:feature_class":"P",
    "gn:feature_code":"PPL",
    "gn:name":"Kh\u0101l-e M\u012brz\u0101n",
    "gn:population":0,
    "gn:timezone":"Asia/Kabul",
    "iso:country":"AF",
    "name:und_x_variant":[
        "Kh\u0101l-e M\u012brz\u0101n",
        "\u062e\u0627\u0644 \u0645\u06cc\u0631\u0632\u0627\u0646"
    ],
    "wof:name":"Khal-e Mirzan",
    "wof:placetype":"locality"
},
  "geometry": {"coordinates":[67.10989000000001,35.92987],"type":"Point"}
}