{
  "type": "Feature",
  "properties": {
    "gn:admin1_code":"08",
    "gn:admin2_code":"602",
    "gn:asciiname":"Qal'ah-ye Ikhtiar",
    "gn:country_code":"AF",
    "gn:dem":2998,
    "gn:feature_class":"P",
    "gn:feature_code":"PPL",
    "gn:name":"Qal\u2018ah-ye Ikht\u012b\u0101r",
    "gn:population":0,
    "gn:timezone":"Asia/Kabul",
    "iso:country":"AF",
    "name:fas_x_preferred":[
        "\u0642\u0644\u0639\u0647\u0654 \u0627\u062e\u062a\u064a\u0627\u0631"
    ],
    "name:rus_x_preferred":[
        "\u041a\u0430\u043b\u0430\u0438\u0445\u0442\u0438\u0430\u0440"
    ],
    "name:und_x_variant":[
        "Kalaikhtiar",
        "Qal\u2018a-i-Ekhty\u0101\u1e5f",
        "Qal\u2018eh-ye Ekht\u012b\u0101r",
        "Qal\u2018ah-ye Ikht\u012b\u0101r",
        "\u0642\u0644\u0639\u06c0 \u0627\u062e\u062a\u06cc\u0627\u0631"
    ],
    "wof:name":"Qal'ah-ye Ikhtiar",
    "wof:placetype":"locality"
},
  "geometry": {"coordinates":[67.99122,33.48717],"type":"Point"}
}