{
  "type": "Feature",
  "properties": {
    "gn:admin1_code":"26",
    "gn:admin2_code":"1201.0",
    "gn:asciiname":"Moghul",
    "gn:country_code":"AF",
    "gn:dem":856,
    "gn:feature_class":"P",
    "gn:feature_code":"PPL",
    "gn:name":"Moghul",
    "gn:population":0,
    "gn:timezone":"Asia/Kabul",
    "iso:country":"AF",
    "name:rus_x_preferred":[
        "\u041c\u0443\u0433\u0443\u043b\u044c"
    ],
    "name:und_x_variant":[
        "Mugul\u2019",
        "Mughul",
        "Moghol",
        "Moghul",
        "\u0645\u063a\u0644"
    ],
    "wof:name":"Moghul",
    "wof:placetype":"locality"
},
  "geometry": {"coordinates":[69.58981999999999,36.72219000000001],"type":"Point"}
}