{
  "type": "Feature",
  "properties": {
    "gn:admin1_code":"23",
    "gn:admin2_code":"2401.0",
    "gn:asciiname":"Nasiran",
    "gn:country_code":"AF",
    "gn:dem":1000,
    "gn:feature_class":"P",
    "gn:feature_code":"PPL",
    "gn:name":"Nasiran",
    "gn:population":0,
    "gn:timezone":"Asia/Kabul",
    "iso:country":"AF",
    "name:und_x_variant":[
        "N\u0101\u015fir\u0101n",
        "\u0646\u0627\u0635\u0631\u0627\u0646",
        "N\u0101\u015fer\u0101n"
    ],
    "wof:name":"Nasiran",
    "wof:placetype":"locality"
},
  "geometry": {"coordinates":[65.75934000000001,31.59505],"type":"Point"}
}