{
  "type": "Feature",
  "properties": {
    "gn:admin1_code":"36",
    "gn:admin2_code":"705.0",
    "gn:asciiname":"Srah Kala",
    "gn:country_code":"AF",
    "gn:dem":2420,
    "gn:feature_class":"P",
    "gn:feature_code":"PPL",
    "gn:name":"Srah Kal\u0101",
    "gn:population":0,
    "gn:timezone":"Asia/Kabul",
    "iso:country":"AF",
    "name:fas_x_preferred":[
        "\u0633\u0631\u0647 \u0643\u0644\u0627"
    ],
    "name:und_x_variant":[
        "Srakala",
        "S\u1e5fa Kal\u0101",
        "Srah Kal\u0101",
        "\u0633\u0631\u0647 \u06a9\u0644\u0627"
    ],
    "wof:name":"Srah Kala",
    "wof:placetype":"locality"
},
  "geometry": {"coordinates":[69.33423000000001,33.67394],"type":"Point"}
}