{
  "type": "Feature",
  "properties": {
    "gn:admin1_code":"23",
    "gn:admin2_code":"2408.0",
    "gn:asciiname":"Haji Qudus",
    "gn:country_code":"AF",
    "gn:dem":931,
    "gn:feature_class":"P",
    "gn:feature_code":"PPL",
    "gn:name":"\u1e28\u0101j\u012b Qud\u016bs",
    "gn:population":0,
    "gn:timezone":"Asia/Kabul",
    "iso:country":"AF",
    "name:und_x_variant":[
        "Khadzhikuddus",
        "\u1e28\u0101jiqu\u1e0f\u1e0f\u016bs",
        "\u1e28\u0101j\u012b Qud\u016bs",
        "\u062d\u0627\u062c\u06cc \u0642\u062f\u0648\u0633",
        "\u1e28\u0101jj\u012bqodd\u016bs"
    ],
    "wof:name":"Haji Qudus",
    "wof:placetype":"locality"
},
  "geometry": {"coordinates":[65.44184,31.50245],"type":"Point"}
}