{
  "type": "Feature",
  "properties": {
    "gn:admin1_code":"11",
    "gn:admin2_code":"2006",
    "gn:asciiname":"Khwajah Qasim",
    "gn:country_code":"AF",
    "gn:dem":1270,
    "gn:feature_class":"P",
    "gn:feature_code":"PPL",
    "gn:name":"Khw\u0101jah Q\u0101sim",
    "gn:population":0,
    "gn:timezone":"Asia/Kabul",
    "iso:country":"AF",
    "name:und_x_variant":[
        "Khodzha-Kasim",
        "Khw\u0101ja Q\u0101sem",
        "Khw\u0101ja Q\u0101sim",
        "Khw\u0101ja Q\u0101sin",
        "Khwaja Kasim",
        "Khv\u0101jeh Q\u0101sem",
        "Khw\u0101jah Q\u0101sim",
        "\u062e\u0648\u0627\u062c\u0647 \u0642\u0627\u0633\u0645"
    ],
    "wof:name":"Khwajah Qasim",
    "wof:placetype":"locality"
},
  "geometry": {"coordinates":[62.0837,34.81034],"type":"Point"}
}