{
  "type": "Feature",
  "properties": {
    "gn:admin1_code":"23",
    "gn:admin2_code":"2406.0",
    "gn:asciiname":"Pir Qadam",
    "gn:country_code":"AF",
    "gn:dem":1210,
    "gn:feature_class":"P",
    "gn:feature_code":"PPL",
    "gn:name":"P\u012br Qadam",
    "gn:population":0,
    "gn:timezone":"Asia/Kabul",
    "iso:country":"AF",
    "name:und_x_variant":[
        "Pirkadam",
        "P\u012br Qadam",
        "\u067e\u06cc\u0631 \u0642\u062f\u0645"
    ],
    "wof:name":"Pir Qadam",
    "wof:placetype":"locality"
},
  "geometry": {"coordinates":[65.17412,32.07813],"type":"Point"}
}