{
  "type": "Feature",
  "properties": {
    "gn:admin1_code":"30",
    "gn:admin2_code":"1602.0",
    "gn:asciiname":"Baba Yadgar",
    "gn:country_code":"AF",
    "gn:dem":362,
    "gn:feature_class":"P",
    "gn:feature_code":"PPL",
    "gn:name":"B\u0101b\u0101 Y\u0101dg\u0101r",
    "gn:population":0,
    "gn:timezone":"Asia/Kabul",
    "iso:country":"AF",
    "name:fas_x_preferred":[
        "\u0628\u0627\u0628\u0627 \u064a\u0627\u062f\u06af\u0627\u0631"
    ],
    "name:rus_x_preferred":[
        "\u0411\u0430\u0431\u0430\u044f\u0434\u0433\u0430\u0440"
    ],
    "name:und_x_variant":[
        "B\u0101b\u0101 Y\u0101deg\u0101r",
        "Babayadgar",
        "B\u0101b\u0101 Y\u0101dg\u0101r",
        "\u0628\u0627\u0628\u0627 \u06cc\u0627\u062f\u06af\u0627\u0631",
        "Qaryah-ye B\u0101bah Y\u0101dg\u0101r",
        "\u0642\u0631\u06cc\u0647 \u0628\u0627\u0628\u0647 \u06cc\u0627\u062f\u06af\u0627\u0631"
    ],
    "wof:name":"Baba Yadgar",
    "wof:placetype":"locality"
},
  "geometry": {"coordinates":[67.08700999999999,36.7063],"type":"Point"}
}