{
  "type": "Feature",
  "properties": {
    "gn:admin1_code":"34",
    "gn:admin2_code":"1009.0",
    "gn:asciiname":"Draykhet",
    "gn:country_code":"AF",
    "gn:dem":1433,
    "gn:feature_class":"P",
    "gn:feature_code":"PPL",
    "gn:name":"Draykh\u00ea\u1e6f",
    "gn:population":0,
    "gn:timezone":"Asia/Kabul",
    "iso:country":"AF",
    "name:fas_x_preferred":[
        "\u062f\u0631\u06cc\u062e\u062a"
    ],
    "name:rus_x_preferred":[
        "Drekheyl\u2019"
    ],
    "name:und_x_variant":[
        "\u1e0e\u1e5f\u0113khet",
        "Draykh\u00ea\u1e6f",
        "\u062f\u0631\u06cc\u062e\u067c"
    ],
    "wof:name":"Draykhet",
    "wof:placetype":"locality"
},
  "geometry": {"coordinates":[70.77128,34.9275],"type":"Point"}
}