{
  "type": "Feature",
  "properties": {
    "gn:admin1_code":"05",
    "gn:admin2_code":"2806",
    "gn:asciiname":"Gardon-Arg",
    "gn:country_code":"AF",
    "gn:dem":2695,
    "gn:feature_class":"P",
    "gn:feature_code":"PPL",
    "gn:name":"Gard\u014dn-Arg",
    "gn:population":0,
    "gn:timezone":"Asia/Kabul",
    "iso:country":"AF",
    "name:und_x_variant":[
        "Gardonarg",
        "Ga\u1e5f\u1e0f\u014dn-a\u1e5fg",
        "Gard\u016bn Arg",
        "Gard\u014dn-Arg",
        "\u06af\u0631\u062f\u0648\u0646 \u0627\u0631\u06af"
    ],
    "wof:name":"Gardon-Arg",
    "wof:placetype":"locality"
},
  "geometry": {"coordinates":[67.03901,34.17394],"type":"Point"}
}