{
  "type": "Feature",
  "properties": {
    "gn:admin1_code":"29",
    "gn:admin2_code":"2916",
    "gn:asciiname":"Muhammad Amin",
    "gn:country_code":"AF",
    "gn:dem":2038,
    "gn:feature_class":"P",
    "gn:feature_code":"PPL",
    "gn:name":"Mu\u1e29ammad Am\u012bn",
    "gn:population":0,
    "gn:timezone":"Asia/Kabul",
    "iso:country":"AF",
    "name:und_x_variant":[
        "Mukhammedamin",
        "\u0645\u062d\u0645\u062f \u0627\u0645\u06cc\u0646",
        "Mo\u1e29ammad Am\u012bn",
        "Mu\u1e29ammad Am\u012bn"
    ],
    "wof:name":"Muhammad Amin",
    "wof:placetype":"locality"
},
  "geometry": {"coordinates":[68.37219,32.69648],"type":"Point"}
}