{
  "type": "Feature",
  "properties": {
    "gn:admin1_code":"06",
    "gn:admin2_code":"2105",
    "gn:asciiname":"Dizak",
    "gn:country_code":"AF",
    "gn:dem":767,
    "gn:feature_class":"P",
    "gn:feature_code":"PPL",
    "gn:name":"D\u012bzak",
    "gn:population":0,
    "gn:timezone":"Asia/Kabul",
    "iso:country":"AF",
    "name:und_x_variant":[
        "Dehzak",
        "Dizak",
        "D\u012bzak",
        "\u062f\u06cc\u0632\u06a9"
    ],
    "wof:name":"Dizak",
    "wof:placetype":"locality"
},
  "geometry": {"coordinates":[62.52381,32.61214],"type":"Point"}
}