{
  "type": "Feature",
  "properties": {
    "gn:admin1_code":"06",
    "gn:admin2_code":"2105",
    "gn:asciiname":"Dizak",
    "gn:country_code":"AF",
    "gn:dem":767,
    "gn:feature_class":"P",
    "gn:feature_code":"PPL",
    "gn:name":"D\u012bzak",
    "gn:population":0,
    "gn:timezone":"Asia/Kabul",
    "iso:country":"AF",
    "name:aze_x_preferred":[
        "Dizaq mahal\u0131"
    ],
    "name:nld_x_preferred":[
        "Dizak"
    ],
    "name:rus_x_preferred":[
        "\u0414\u0438\u0437\u0430\u043a\u0441\u043a\u0438\u0439 \u043c\u0430\u0433\u0430\u043b"
    ],
    "name:ukr_x_preferred":[
        "\u0414\u0456\u0437\u0430\u043a"
    ],
    "name:und_x_variant":[
        "Dehzak",
        "D\u012bzak",
        "\u062f\u06cc\u0632\u06a9"
    ],
    "wof:name":"Dizak",
    "wof:placetype":"locality"
},
  "geometry": {"coordinates":[62.52381,32.61214],"type":"Point"}
}