{
  "type": "Feature",
  "properties": {
    "gn:admin1_code":"08",
    "gn:admin2_code":"613",
    "gn:asciiname":"Katah Deh",
    "gn:country_code":"AF",
    "gn:dem":2577,
    "gn:feature_class":"P",
    "gn:feature_code":"PPL",
    "gn:name":"Katah Deh",
    "gn:population":0,
    "gn:timezone":"Asia/Kabul",
    "iso:country":"AF",
    "name:fas_x_preferred":[
        "\u0643\u062a\u0647 \u062f\u0647"
    ],
    "name:rus_x_preferred":[
        "\u041a\u0430\u0442\u0430\u0434\u0435\u0445"
    ],
    "name:und_x_variant":[
        "Katadekh",
        "Kata\u1e0feh",
        "Katah Deh",
        "\u06a9\u062a\u0647 \u062f\u0647"
    ],
    "wof:name":"Katah Deh",
    "wof:placetype":"locality"
},
  "geometry": {"coordinates":[67.96464,33.32649],"type":"Point"}
}