{
  "type": "Feature",
  "properties": {
    "gn:admin1_code":"41",
    "gn:admin2_code":"3403.0",
    "gn:asciiname":"Qol-e Sherak",
    "gn:country_code":"AF",
    "gn:dem":2728,
    "gn:feature_class":"P",
    "gn:feature_code":"PPL",
    "gn:name":"Q\u014dl-e Sh\u0113rak",
    "gn:population":0,
    "gn:timezone":"Asia/Kabul",
    "iso:country":"AF",
    "name:und_x_variant":[
        "Qule \u0160\u0113r\u0101k",
        "Q\u014dl-e Shayrak",
        "\u0642\u0648\u0644 \u0634\u06cc\u0631\u06a9",
        "Qol-e \u1e62\u012brak",
        "Q\u014dl-e Sh\u0113rak"
    ],
    "wof:name":"Qol-e Sherak",
    "wof:placetype":"locality"
},
  "geometry": {"coordinates":[66.36941,33.96631],"type":"Point"}
}