{
  "type": "Feature",
  "properties": {
    "gn:admin1_code":"18",
    "gn:admin2_code":"802.0",
    "gn:asciiname":"Mirzaiyan",
    "gn:country_code":"AF",
    "gn:dem":604,
    "gn:feature_class":"P",
    "gn:feature_code":"PPL",
    "gn:name":"M\u012brz\u0101iy\u0101n",
    "gn:population":0,
    "gn:timezone":"Asia/Kabul",
    "iso:country":"AF",
    "name:fas_x_preferred":[
        "\u0645\u0631\u0632\u0627\u064a\u0627\u0646"
    ],
    "name:und_x_variant":[
        "Mirzayan",
        "Merz\u0101y\u0101n",
        "M\u012brz\u0101iy\u0101n",
        "\u0645\u06cc\u0631\u0632\u0627\u06cc\u0627\u0646"
    ],
    "wof:name":"Mirzaiyan",
    "wof:placetype":"locality"
},
  "geometry": {"coordinates":[70.36669000000001,34.43980999999999],"type":"Point"}
}