{
  "type": "Feature",
  "properties": {
    "gn:admin1_code":"10",
    "gn:admin2_code":"2306",
    "gn:asciiname":"Qaryah-ye Chiwin",
    "gn:country_code":"AF",
    "gn:dem":1543,
    "gn:feature_class":"P",
    "gn:feature_code":"PPL",
    "gn:name":"Qaryah-ye Chiw\u012bn",
    "gn:population":0,
    "gn:timezone":"Asia/Kabul",
    "iso:country":"AF",
    "name:rus_x_preferred":[
        "Kar\u2019yayi-Chivin"
    ],
    "name:und_x_variant":[
        "Qarya-i-\u010cew\u012bn",
        "Qaryeh-e Chew\u012bn",
        "Qaryah-ye Chiw\u012bn",
        "\u0642\u0631\u06cc\u0647 \u0686\u0648\u06cc\u0646",
        "Qaryeh-ye Chew\u012bn"
    ],
    "wof:name":"Qaryah-ye Chiwin",
    "wof:placetype":"locality"
},
  "geometry": {"coordinates":[64.57013000000001,32.7945],"type":"Point"}
}