{
  "type": "Feature",
  "properties": {
    "gn:admin1_code":"26",
    "gn:admin2_code":"1201",
    "gn:asciiname":"Kalak Say",
    "gn:country_code":"AF",
    "gn:dem":1388,
    "gn:feature_class":"P",
    "gn:feature_code":"PPL",
    "gn:name":"Kalak S\u0101y",
    "gn:population":0,
    "gn:timezone":"Asia/Kabul",
    "iso:country":"AF",
    "name:rus_x_preferred":[
        "\u041a\u0430\u043b\u0430\u043a\u0441\u0430\u0439"
    ],
    "name:und_x_variant":[
        "Kalaksay",
        "Kalak S\u0101y",
        "\u06a9\u0644\u06a9 \u0633\u0627\u06cc"
    ],
    "wof:name":"Kalak Say",
    "wof:placetype":"locality"
},
  "geometry": {"coordinates":[69.49706999999999,36.61256],"type":"Point"}
}