{
  "type": "Feature",
  "properties": {
    "gn:admin1_code":"32",
    "gn:admin2_code":"1504",
    "gn:asciiname":"Tukan Awar",
    "gn:country_code":"AF",
    "gn:dem":1729,
    "gn:feature_class":"P",
    "gn:feature_code":"PPL",
    "gn:name":"Tukan \u0100war",
    "gn:population":0,
    "gn:timezone":"Asia/Kabul",
    "iso:country":"AF",
    "name:und_x_variant":[
        "Tokan Aawar (1)",
        "Tokan \u0100var",
        "Tukan \u0100war",
        "\u062a\u06a9\u0646 \u0622\u0648\u0631"
    ],
    "wof:name":"Tukan Awar",
    "wof:placetype":"locality"
},
  "geometry": {"coordinates":[67.45696,36.12708],"type":"Point"}
}