{
  "type": "Feature",
  "properties": {
    "gn:admin1_code":"8",
    "gn:admin2_code":"606.0",
    "gn:asciiname":"Awlaya",
    "gn:country_code":"AF",
    "gn:dem":3041,
    "gn:feature_class":"P",
    "gn:feature_code":"PPL",
    "gn:name":"Awlay\u0101",
    "gn:population":0,
    "gn:timezone":"Asia/Kabul",
    "iso:country":"AF",
    "name:und_x_variant":[
        "Awlay\u0101",
        "Owl\u012b\u0101",
        "\u0627\u0648\u0644\u06cc\u0627"
    ],
    "wof:name":"Awlaya",
    "wof:placetype":"locality"
},
  "geometry": {"coordinates":[67.12223,33.33468],"type":"Point"}
}