{
  "type": "Feature",
  "properties": {
    "gn:admin1_code":"11",
    "gn:admin2_code":"2006",
    "gn:asciiname":"Qal'ah-ye Nowak",
    "gn:country_code":"AF",
    "gn:dem":991,
    "gn:feature_class":"P",
    "gn:feature_code":"PPL",
    "gn:name":"Qal\u2018ah-ye Nowak",
    "gn:population":0,
    "gn:timezone":"Asia/Kabul",
    "iso:country":"AF",
    "name:und_x_variant":[
        "Nauk",
        "Baldi",
        "Kalayi-Novak",
        "Qal\u2018a-i-Nowak",
        "Naok",
        "Nowak-e B\u0101l\u0101 Deh",
        "Qal\u2018eh-ye Nowak",
        "Qal\u2018ah-ye Nowak",
        "\u0642\u0644\u0639\u06c0 \u0646\u0648\u06a9"
    ],
    "wof:name":"Qal'ah-ye Nowak",
    "wof:placetype":"locality"
},
  "geometry": {"coordinates":[62.45045,34.90902],"type":"Point"}
}