{
  "type": "Feature",
  "properties": {
    "gn:admin1_code":"07",
    "gn:admin2_code":"1808",
    "gn:asciiname":"Sharq-e Qishlaq",
    "gn:country_code":"AF",
    "gn:dem":967,
    "gn:feature_class":"P",
    "gn:feature_code":"PPL",
    "gn:name":"Sharq-e Qishl\u0101q",
    "gn:population":0,
    "gn:timezone":"Asia/Kabul",
    "iso:country":"AF",
    "name:und_x_variant":[
        "Sharq-i-Qishl\u0101q",
        "Sharq-e Qeshl\u0101q",
        "Sharq-e Qishl\u0101q",
        "\u0634\u0631\u0642 \u0642\u0634\u0644\u0627\u0642"
    ],
    "wof:name":"Sharq-e Qishlaq",
    "wof:placetype":"locality"
},
  "geometry": {"coordinates":[65.09146,36.17199],"type":"Point"}
}