{
  "type": "Feature",
  "properties": {
    "gn:admin1_code":"28",
    "gn:admin2_code":"2509",
    "gn:asciiname":"Kuchney Spinah",
    "gn:country_code":"AF",
    "gn:dem":2255,
    "gn:feature_class":"P",
    "gn:feature_code":"PPL",
    "gn:name":"Kuchn\u00eay Sp\u012bnah",
    "gn:population":0,
    "gn:timezone":"Asia/Kabul",
    "iso:country":"AF",
    "name:und_x_variant":[
        "Kucn\u0113y Sp\u012bna",
        "Kuchney Sp\u012bnah",
        "Kuchnay-Spina",
        "K\u016bchn\u00eay Sp\u012bnah",
        "Kuchnay Sp\u012bnah",
        "Kuchn\u00eay Sp\u012bnah",
        "\u06a9\u0686\u0646\u06cd \u0633\u067e\u064a\u0646\u0647"
    ],
    "wof:name":"Kuchney Spinah",
    "wof:placetype":"locality"
},
  "geometry": {"coordinates":[67.81026999999999,31.93192],"type":"Point"}
}