{
  "type": "Feature",
  "properties": {
    "gn:admin1_code":"11",
    "gn:admin2_code":"2013",
    "gn:asciiname":"Nagharah Khanah",
    "gn:country_code":"AF",
    "gn:dem":2169,
    "gn:feature_class":"P",
    "gn:feature_code":"PPL",
    "gn:name":"Nagh\u0101rah Kh\u0101nah",
    "gn:population":0,
    "gn:timezone":"Asia/Kabul",
    "iso:country":"AF",
    "name:und_x_variant":[
        "Neg\u0101r Kh\u0101neh",
        "Nagh\u0101\u1e5fakh\u0101na",
        "Nag\u0101r Kh\u0101neh",
        "Nagarakhana",
        "Nagh\u0101reh Kh\u0101neh",
        "Nag\u0101r Kh\u0101na",
        "Nagh\u0101rah Kh\u0101nah",
        "\u0646\u063a\u0627\u0631\u0647 \u062e\u0627\u0646\u0647",
        "Naq\u0101reh Kh\u0101neh",
        "Nagh\u0101rakh\u0101nah"
    ],
    "wof:name":"Nagharah Khanah",
    "wof:placetype":"locality"
},
  "geometry": {"coordinates":[63.17111,33.90687],"type":"Point"}
}