{
  "type": "Feature",
  "properties": {
    "gn:admin1_code":"08",
    "gn:admin2_code":"614",
    "gn:asciiname":"Kuz Khado Khel",
    "gn:country_code":"AF",
    "gn:dem":2073,
    "gn:feature_class":"P",
    "gn:feature_code":"PPL",
    "gn:name":"K\u016bz Khad\u014d Kh\u0113l",
    "gn:population":0,
    "gn:timezone":"Asia/Kabul",
    "iso:country":"AF",
    "name:fas_x_preferred":[
        "\u0643\u0648\u0632 \u062e\u062f\u0648 \u062e\u064a\u0644"
    ],
    "name:rus_x_preferred":[
        "Kuz-Khadokheyl\u2019"
    ],
    "name:und_x_variant":[
        "K\u016bz Kha\u1e0f\u014dkh\u0113l",
        "K\u016bz Khad\u014d Kh\u0113l",
        "K\u016bz Khadow Kheyl",
        "\u0643\u0648\u0632 \u062e\u062f\u0648 \u062e\u06d0\u0644"
    ],
    "wof:name":"Kuz Khado Khel",
    "wof:placetype":"locality"
},
  "geometry": {"coordinates":[68.35866,33.33149],"type":"Point"}
}