{
  "type": "Feature",
  "properties": {
    "gn:admin1_code":"03",
    "gn:admin2_code":"1303",
    "gn:asciiname":"Deh-e Toran",
    "gn:country_code":"AF",
    "gn:dem":1670,
    "gn:feature_class":"P",
    "gn:feature_code":"PPL",
    "gn:name":"Deh-e T\u014dr\u0101n",
    "gn:population":0,
    "gn:timezone":"Asia/Kabul",
    "iso:country":"AF",
    "name:und_x_variant":[
        "Deh-e T\u014dran",
        "Deh-e Towran",
        "Deh-e T\u014dr\u0101n",
        "\u062f\u0647 \u062a\u0648\u0631\u0627\u0646"
    ],
    "wof:name":"Deh-e Toran",
    "wof:placetype":"locality"
},
  "geometry": {"coordinates":[68.35285,35.86915],"type":"Point"}
}