{
  "type": "Feature",
  "properties": {
    "gn:admin1_code":"33",
    "gn:admin2_code":"3103",
    "gn:asciiname":"Sar-e Tulah",
    "gn:country_code":"AF",
    "gn:dem":2314,
    "gn:feature_class":"P",
    "gn:feature_code":"PPL",
    "gn:name":"Sar-e \u0162\u016blah",
    "gn:population":0,
    "gn:timezone":"Asia/Kabul",
    "iso:country":"AF",
    "name:und_x_variant":[
        "Sa\u1e5fe \u1e6e\u016bla",
        "Sa\u1e5f-e \u1e6e\u016blah",
        "Sar-e \u0162\u016blah",
        "\u0633\u0631 \u0637\u0648\u0644\u0647"
    ],
    "wof:name":"Sar-e Tulah",
    "wof:placetype":"locality"
},
  "geometry": {"coordinates":[66.22413,35.04652],"type":"Point"}
}