{
  "type": "Feature",
  "properties": {
    "gn:admin1_code":"5",
    "gn:admin2_code":"2806.0",
    "gn:asciiname":"Bum",
    "gn:country_code":"AF",
    "gn:dem":3045,
    "gn:feature_class":"P",
    "gn:feature_code":"PPL",
    "gn:name":"B\u016bm",
    "gn:population":0,
    "gn:timezone":"Asia/Kabul",
    "iso:country":"AF",
    "name:ceb_x_preferred":[
        "Bum"
    ],
    "name:dan_x_preferred":[
        "Bums"
    ],
    "name:deu_x_preferred":[
        "Bum"
    ],
    "name:kat_x_preferred":[
        "\u10d1\u10e3\u10db\u10d8"
    ],
    "name:swe_x_preferred":[
        "Bum"
    ],
    "name:und_x_variant":[
        "B\u016bm",
        "\u0628\u0648\u0645"
    ],
    "wof:name":"Bum",
    "wof:placetype":"locality"
},
  "geometry": {"coordinates":[67.32212,34.30302],"type":"Point"}
}