{
  "type": "Feature",
  "properties": {
    "gn:admin1_code":"08",
    "gn:admin2_code":"604",
    "gn:asciiname":"Siyah Reg",
    "gn:country_code":"AF",
    "gn:dem":2685,
    "gn:feature_class":"P",
    "gn:feature_code":"PPL",
    "gn:name":"Siy\u0101h R\u0113g",
    "gn:population":0,
    "gn:timezone":"Asia/Kabul",
    "iso:country":"AF",
    "name:und_x_variant":[
        "Sy\u0101h\u1e5f\u0113g",
        "Siakhreg",
        "Si\u0101h Reg",
        "S\u012b\u0101hr\u012bg",
        "S\u012b\u0101h Rayg",
        "Siy\u0101h R\u0113g",
        "\u0633\u06cc\u0627\u0647 \u0631\u06d0\u06af"
    ],
    "wof:name":"Siyah Reg",
    "wof:placetype":"locality"
},
  "geometry": {"coordinates":[68.11019,34.08592],"type":"Point"}
}