{
  "type": "Feature",
  "properties": {
    "gn:admin1_code":"35",
    "gn:admin2_code":"902",
    "gn:asciiname":"Loy Dergi",
    "gn:country_code":"AF",
    "gn:dem":1454,
    "gn:feature_class":"P",
    "gn:feature_code":"PPL",
    "gn:name":"L\u014dy D\u00earg\u012b",
    "gn:population":0,
    "gn:timezone":"Asia/Kabul",
    "iso:country":"AF",
    "name:fas_x_preferred":[
        "\u062f\u0631\u06af\u0626 \u0643\u0644\u0627\u0646"
    ],
    "name:und_x_variant":[
        "L\u014dy \u1e0ee\u1e5fgi",
        "Loy-Dergi",
        "\u0644\u0648\u06cc \u062f\u0631\u06af\u06cc",
        "L\u016by \u1e0e\u0113\u1e5fgi",
        "L\u014dy D\u00earg\u012b"
    ],
    "wof:name":"Loy Dergi",
    "wof:placetype":"locality"
},
  "geometry": {"coordinates":[69.87915,34.45696],"type":"Point"}
}