{
  "type": "Feature",
  "properties": {
    "gn:admin1_code":"23",
    "gn:admin2_code":"2403",
    "gn:asciiname":"Payindah Khune",
    "gn:country_code":"AF",
    "gn:dem":1903,
    "gn:feature_class":"P",
    "gn:feature_code":"PPL",
    "gn:name":"P\u0101yindah Kh\u016bn\u0113",
    "gn:population":0,
    "gn:timezone":"Asia/Kabul",
    "iso:country":"AF",
    "name:und_x_variant":[
        "Payindakhune",
        "P\u0101yen\u1e0fah Kh\u016bn\u0113",
        "P\u0101yendah Kh\u016bn\u0113",
        "\u067e\u0627\u06cc\u0646\u062f\u0647 \u062e\u0648\u0646\u06d0",
        "P\u0101yandeh Kh\u016bneh",
        "P\u0101yindah Kh\u016bn\u0113"
    ],
    "wof:name":"Payindah Khune",
    "wof:placetype":"locality"
},
  "geometry": {"coordinates":[66.06922,32.47229],"type":"Point"}
}