{
  "type": "Feature",
  "properties": {
    "gn:admin1_code":"13",
    "gn:admin2_code":"101.0",
    "gn:asciiname":"Qaryah-ye Chonaghar",
    "gn:country_code":"AF",
    "gn:dem":1974,
    "gn:feature_class":"P",
    "gn:feature_code":"PPL",
    "gn:name":"Qaryah-ye Ch\u014dnaghar",
    "gn:population":0,
    "gn:timezone":"Asia/Kabul",
    "iso:country":"AF",
    "name:und_x_variant":[
        "Qaryah-ye Ch\u014dnaghar",
        "\u0642\u0631\u06cc\u0647 \u0686\u0648\u0646\u063a\u0631"
    ],
    "wof:name":"Qaryah-ye Chonaghar",
    "wof:placetype":"locality"
},
  "geometry": {"coordinates":[69.00573,34.49089],"type":"Point"}
}