{
  "type": "Feature",
  "properties": {
    "gn:admin1_code":"13",
    "gn:admin2_code":"109.0",
    "gn:asciiname":"Qal'ah-ye Nishan",
    "gn:country_code":"AF",
    "gn:dem":1874,
    "gn:feature_class":"P",
    "gn:feature_code":"PPL",
    "gn:name":"Qal\u2018ah-ye Nish\u0101n",
    "gn:population":0,
    "gn:timezone":"Asia/Kabul",
    "iso:country":"AF",
    "name:und_x_variant":[
        "Kalanishan",
        "Qal\u2019eh Ne\u0161\u0101n",
        "Qal\u2018ah-ye Nesh\u0101n",
        "Qal\u2018eh-ye Nesh\u0101n",
        "Qal\u2018ah-ye Nish\u0101n",
        "\u0642\u0644\u0639\u0647 \u0646\u0634\u0627\u0646"
    ],
    "wof:name":"Qal'ah-ye Nishan",
    "wof:placetype":"locality"
},
  "geometry": {"coordinates":[69.11631,34.32282],"type":"Point"}
}