{
  "type": "Feature",
  "properties": {
    "gn:admin1_code":"41",
    "gn:admin2_code":"3403",
    "gn:asciiname":"Karas",
    "gn:country_code":"AF",
    "gn:dem":2699,
    "gn:feature_class":"P",
    "gn:feature_code":"PPL",
    "gn:name":"Karas",
    "gn:population":0,
    "gn:timezone":"Asia/Kabul",
    "iso:country":"AF",
    "name:und_x_variant":[
        "\u06a9\u0631\u0633",
        "Ka\u1e5fas"
    ],
    "wof:name":"Karas",
    "wof:placetype":"locality"
},
  "geometry": {"coordinates":[66.07638,33.9333],"type":"Point"}
}