{
  "type": "Feature",
  "properties": {
    "gn:admin1_code":"41",
    "gn:admin2_code":"3403",
    "gn:asciiname":"Karas",
    "gn:country_code":"AF",
    "gn:dem":2699,
    "gn:feature_class":"P",
    "gn:feature_code":"PPL",
    "gn:name":"Karas",
    "gn:population":0,
    "gn:timezone":"Asia/Kabul",
    "iso:country":"AF",
    "name:bul_x_preferred":[
        "\u041a\u0430\u0440\u0430\u0441"
    ],
    "name:ceb_x_preferred":[
        "Karas"
    ],
    "name:ces_x_preferred":[
        "Karas"
    ],
    "name:deu_x_preferred":[
        "Karas"
    ],
    "name:fra_x_preferred":[
        "Karas"
    ],
    "name:ind_x_preferred":[
        "Karas"
    ],
    "name:kor_x_preferred":[
        "\uce74\ub77c\uc2a4"
    ],
    "name:lit_x_preferred":[
        "Karas"
    ],
    "name:msa_x_preferred":[
        "Karas"
    ],
    "name:nld_x_preferred":[
        "Karas"
    ],
    "name:pol_x_preferred":[
        "Karas"
    ],
    "name:por_x_preferred":[
        "Karas"
    ],
    "name:rus_x_preferred":[
        "\u041a\u0430\u0440\u0430\u0441"
    ],
    "name:spa_x_preferred":[
        "Karas"
    ],
    "name:swe_x_preferred":[
        "Karas"
    ],
    "name:ukr_x_preferred":[
        "\u041a\u0430\u0440\u0430\u0441"
    ],
    "name:und_x_variant":[
        "\u06a9\u0631\u0633",
        "Ka\u1e5fas"
    ],
    "wof:name":"Karas",
    "wof:placetype":"locality"
},
  "geometry": {"coordinates":[66.07638,33.9333],"type":"Point"}
}