{
  "type": "Feature",
  "properties": {
    "gn:admin1_code":"35",
    "gn:admin2_code":"901.0",
    "gn:asciiname":"Manjo",
    "gn:country_code":"AF",
    "gn:dem":782,
    "gn:feature_class":"P",
    "gn:feature_code":"PPL",
    "gn:name":"Manj\u014d",
    "gn:population":0,
    "gn:timezone":"Asia/Kabul",
    "iso:country":"AF",
    "name:ceb_x_preferred":[
        "Manjo"
    ],
    "name:deu_x_preferred":[
        "Manjo"
    ],
    "name:fra_x_preferred":[
        "Manjo"
    ],
    "name:ita_x_preferred":[
        "Manjo"
    ],
    "name:msa_x_preferred":[
        "Manjo"
    ],
    "name:pol_x_preferred":[
        "Manjo"
    ],
    "name:por_x_preferred":[
        "Manjo"
    ],
    "name:spa_x_preferred":[
        "Manjo"
    ],
    "name:swe_x_preferred":[
        "Manjo"
    ],
    "name:und_x_variant":[
        "Mandzhu",
        "Manjo",
        "Manj\u014d",
        "\u0645\u0627\u0646\u062c\u0648",
        "M\u0101n\u014d",
        "\u0645\u0627\u0646\u0648"
    ],
    "wof:name":"Manjo",
    "wof:placetype":"locality"
},
  "geometry": {"coordinates":[70.24873000000001,34.70749],"type":"Point"}
}