{
  "type": "Feature",
  "properties": {
    "gn:admin1_code":"32",
    "gn:admin2_code":"1502",
    "gn:asciiname":"Kol-e Ishan",
    "gn:country_code":"AF",
    "gn:dem":743,
    "gn:feature_class":"P",
    "gn:feature_code":"PPL",
    "gn:name":"K\u014dl-e Ish\u0101n",
    "gn:population":0,
    "gn:timezone":"Asia/Kabul",
    "iso:country":"AF",
    "name:und_x_variant":[
        "Kol-i-Eshan",
        "Kol-e Eshan",
        "K\u014dl-e Ish\u0101n",
        "\u06a9\u0648\u0644 \u0627\u0634\u0627\u0646"
    ],
    "wof:name":"Kol-e Ishan",
    "wof:placetype":"locality"
},
  "geometry": {"coordinates":[67.898,36.51011],"type":"Point"}
}