{
  "type": "Feature",
  "properties": {
    "gn:admin1_code":"8",
    "gn:admin2_code":"604.0",
    "gn:asciiname":"Bilgaw",
    "gn:country_code":"AF",
    "gn:dem":3319,
    "gn:feature_class":"P",
    "gn:feature_code":"PPL",
    "gn:name":"B\u012blg\u0101w",
    "gn:population":0,
    "gn:timezone":"Asia/Kabul",
    "iso:country":"AF",
    "name:rus_x_preferred":[
        "Bil\u2019gav"
    ],
    "name:und_x_variant":[
        "B\u012blg\u0101w",
        "B\u012blg\u0101v",
        "\u0628\u06cc\u0644\u06af\u0627\u0648"
    ],
    "wof:name":"Bilgaw",
    "wof:placetype":"locality"
},
  "geometry": {"coordinates":[67.67869,34.09805],"type":"Point"}
}