{
  "type": "Feature",
  "properties": {
    "gn:admin1_code":"08",
    "gn:admin2_code":"608",
    "gn:asciiname":"Hilal Khel",
    "gn:country_code":"AF",
    "gn:dem":2194,
    "gn:feature_class":"P",
    "gn:feature_code":"PPL",
    "gn:name":"\u1e28il\u0101l Kh\u0113l",
    "gn:population":0,
    "gn:timezone":"Asia/Kabul",
    "iso:country":"AF",
    "name:fas_x_preferred":[
        "\u062d\u0644\u0627\u0644 \u062e\u064a\u0644"
    ],
    "name:rus_x_preferred":[
        "\u0425\u0438\u043b\u0430\u043b\u044c\u0445\u0435\u0439\u043b\u044c"
    ],
    "name:und_x_variant":[
        "Khilal\u2019kheyl\u2019",
        "Hel\u0101lkh\u0113l",
        "\u1e28al\u0101lkheyl",
        "\u1e28il\u0101l Kh\u0113l",
        "\u062d\u0644\u0627\u0644 \u062e\u06d0\u0644"
    ],
    "wof:name":"Hilal Khel",
    "wof:placetype":"locality"
},
  "geometry": {"coordinates":[67.79254,33.02135],"type":"Point"}
}