{
  "type": "Feature",
  "properties": {
    "gn:admin1_code":"33",
    "gn:admin2_code":"3106",
    "gn:asciiname":"Qal'ah-ye Khatun",
    "gn:country_code":"AF",
    "gn:dem":2055,
    "gn:feature_class":"P",
    "gn:feature_code":"PPL",
    "gn:name":"Qal\u2018ah-ye Kh\u0101t\u016bn",
    "gn:population":0,
    "gn:timezone":"Asia/Kabul",
    "iso:country":"AF",
    "name:und_x_variant":[
        "Qal\u2018\u0101-i-Kh\u0101t\u016bn",
        "Qal\u2018eh-ye Kh\u0101t\u016bn",
        "Qal\u2018ah-ye Kh\u0101t\u016bn",
        "\u0642\u0644\u0639\u06c0 \u062e\u0627\u062a\u0648\u0646"
    ],
    "wof:name":"Qal'ah-ye Khatun",
    "wof:placetype":"locality"
},
  "geometry": {"coordinates":[65.83150000000001,35.99005],"type":"Point"}
}