{
  "type": "Feature",
  "properties": {
    "gn:admin1_code":"9",
    "gn:admin2_code":"2706.0",
    "gn:asciiname":"Awak",
    "gn:country_code":"AF",
    "gn:dem":2664,
    "gn:feature_class":"P",
    "gn:feature_code":"PPL",
    "gn:name":"\u0100wak",
    "gn:population":0,
    "gn:timezone":"Asia/Kabul",
    "iso:country":"AF",
    "name:und_x_variant":[
        "Avak",
        "\u0100wak",
        "\u0622\u0648\u06a9",
        "\u0100bak"
    ],
    "wof:name":"Awak",
    "wof:placetype":"locality"
},
  "geometry": {"coordinates":[64.91079999999999,33.70946],"type":"Point"}
}