{
  "type": "Feature",
  "properties": {
    "gn:admin1_code":"33",
    "gn:admin2_code":"3101.0",
    "gn:asciiname":"Chaman-e 'Ali Jan",
    "gn:country_code":"AF",
    "gn:dem":545,
    "gn:feature_class":"P",
    "gn:feature_code":"PPL",
    "gn:name":"Chaman-e \u2018Al\u012b J\u0101n",
    "gn:population":0,
    "gn:timezone":"Asia/Kabul",
    "iso:country":"AF",
    "name:und_x_variant":[
        "Chaman-i-Ali J\u0101n",
        "Chaman-e \u2018Al\u012b J\u0101n",
        "\u0686\u0645\u0646 \u0639\u0644\u06cc \u062c\u0627\u0646"
    ],
    "wof:name":"Chaman-e 'Ali Jan",
    "wof:placetype":"locality"
},
  "geometry": {"coordinates":[65.93285,36.31201],"type":"Point"}
}