{
  "type": "Feature",
  "properties": {
    "gn:admin1_code":"05",
    "gn:admin2_code":"2803",
    "gn:asciiname":"Dehqan Qal'ah",
    "gn:country_code":"AF",
    "gn:dem":1966,
    "gn:feature_class":"P",
    "gn:feature_code":"PPL",
    "gn:name":"Dehq\u0101n Qal\u2018ah",
    "gn:population":0,
    "gn:timezone":"Asia/Kabul",
    "iso:country":"AF",
    "name:und_x_variant":[
        "\u1e0eehq\u0101nqal\u2018a",
        "\u1e0eehq\u0101ngal\u2018a",
        "Dehq\u0101n Qal\u2018ah",
        "\u062f\u0647\u0642\u0627\u0646 \u0642\u0644\u0639\u0647"
    ],
    "wof:name":"Dehqan Qal'ah",
    "wof:placetype":"locality"
},
  "geometry": {"coordinates":[67.48393,35.3676],"type":"Point"}
}