{
  "type": "Feature",
  "properties": {
    "gn:admin1_code":"02",
    "gn:admin2_code":"1904",
    "gn:asciiname":"Tahtayghah",
    "gn:country_code":"AF",
    "gn:dem":1989,
    "gn:feature_class":"P",
    "gn:feature_code":"PPL",
    "gn:name":"Tahtayghah",
    "gn:population":0,
    "gn:timezone":"Asia/Kabul",
    "iso:country":"AF",
    "name:und_x_variant":[
        "Taht\u0113gha",
        "Tahtayghah",
        "\u062a\u0647\u062a\u06cc\u063a\u0647",
        "Taht\u0113ghah"
    ],
    "wof:name":"Tahtayghah",
    "wof:placetype":"locality"
},
  "geometry": {"coordinates":[64.21469999999999,34.93731],"type":"Point"}
}