{
  "type": "Feature",
  "properties": {
    "gn:admin1_code":"08",
    "gn:admin2_code":"607",
    "gn:asciiname":"Luman",
    "gn:country_code":"AF",
    "gn:dem":2627,
    "gn:feature_class":"P",
    "gn:feature_code":"PPL",
    "gn:name":"Luman",
    "gn:population":0,
    "gn:timezone":"Asia/Kabul",
    "iso:country":"AF",
    "name:deu_x_preferred":[
        "Luman"
    ],
    "name:rus_x_preferred":[
        "\u041b\u0443\u043c\u0430\u043d"
    ],
    "name:und_x_variant":[
        "L\u016bm\u0101n"
    ],
    "wof:name":"Luman",
    "wof:placetype":"locality"
},
  "geometry": {"coordinates":[67.63,33.12],"type":"Point"}
}