{
  "type": "Feature",
  "properties": {
    "gn:admin1_code":"28",
    "gn:admin2_code":"2509.0",
    "gn:asciiname":"Qal'ah-ye Burj-e Sangi",
    "gn:country_code":"AF",
    "gn:dem":2059,
    "gn:feature_class":"P",
    "gn:feature_code":"PPL",
    "gn:name":"Qal\u2018ah-ye Burj-e Sang\u012b",
    "gn:population":0,
    "gn:timezone":"Asia/Kabul",
    "iso:country":"AF",
    "name:und_x_variant":[
        "Kalayi-Burdzhi-Sangi",
        "Qala-i-Bu\u1e5fje Sangi",
        "Qal\u2018eh-ye Borj-e Sang\u012b",
        "Qal\u2018ah-ye Burj-e Sang\u012b"
    ],
    "wof:name":"Qal'ah-ye Burj-e Sangi",
    "wof:placetype":"locality"
},
  "geometry": {"coordinates":[67.61843,31.55896],"type":"Point"}
}