{
  "type": "Feature",
  "properties": {
    "gn:admin1_code":"35",
    "gn:admin2_code":"901.0",
    "gn:asciiname":"Garahwu",
    "gn:country_code":"AF",
    "gn:dem":696,
    "gn:feature_class":"P",
    "gn:feature_code":"PPL",
    "gn:name":"Ga\u1e5fahw\u016b",
    "gn:population":0,
    "gn:timezone":"Asia/Kabul",
    "iso:country":"AF",
    "name:und_x_variant":[
        "Garavu",
        "Garawu",
        "Ga\u1e5fahw\u016b",
        "\u06af\u0693\u0647\u0648\u0648",
        "Ka\u1e5fahow",
        "\u06a9\u0693\u0647 \u0648"
    ],
    "wof:name":"Garahwu",
    "wof:placetype":"locality"
},
  "geometry": {"coordinates":[70.22181999999999,34.60605],"type":"Point"}
}