{
  "type": "Feature",
  "properties": {
    "gn:admin1_code":"28",
    "gn:admin2_code":"2511",
    "gn:asciiname":"Mapan",
    "gn:country_code":"AF",
    "gn:dem":2042,
    "gn:feature_class":"P",
    "gn:feature_code":"PPL",
    "gn:name":"M\u0101p\u0101n",
    "gn:population":0,
    "gn:timezone":"Asia/Kabul",
    "iso:country":"AF",
    "name:und_x_variant":[
        "M\u0101p\u0101n",
        "\u0645\u0627\u067e\u0627\u0646"
    ],
    "wof:name":"Mapan",
    "wof:placetype":"locality"
},
  "geometry": {"coordinates":[67.60876,32.17181],"type":"Point"}
}