{
  "type": "Feature",
  "properties": {
    "gn:admin1_code":"29",
    "gn:admin2_code":"2909.0",
    "gn:asciiname":"Mir Khuday Kelay",
    "gn:country_code":"AF",
    "gn:dem":1908,
    "gn:feature_class":"P",
    "gn:feature_code":"PPL",
    "gn:name":"M\u012br Khud\u0101y K\u00ealay",
    "gn:population":0,
    "gn:timezone":"Asia/Kabul",
    "iso:country":"AF",
    "name:und_x_variant":[
        "Mir-Khuday-Kalay",
        "M\u012br Khod\u0101y Kalay",
        "M\u012br Khud\u0101\u012b K\u00ealay",
        "M\u012br Khud\u0101y K\u00ealay"
    ],
    "wof:name":"Mir Khuday Kelay",
    "wof:placetype":"locality"
},
  "geometry": {"coordinates":[69.28771999999999,32.80499],"type":"Point"}
}