{
  "type": "Feature",
  "properties": {
    "gn:admin1_code":"28",
    "gn:admin2_code":"2510",
    "gn:asciiname":"Tukmi",
    "gn:country_code":"AF",
    "gn:dem":2399,
    "gn:feature_class":"P",
    "gn:feature_code":"PPL",
    "gn:name":"Tukm\u012b",
    "gn:population":0,
    "gn:timezone":"Asia/Kabul",
    "iso:country":"AF",
    "name:und_x_variant":[
        "Tukm\u012b",
        "\u062a\u06a9\u0645\u06cc",
        "Tukmi"
    ],
    "wof:name":"Tukmi",
    "wof:placetype":"locality"
},
  "geometry": {"coordinates":[67.19275,32.92942],"type":"Point"}
}