{
  "type": "Feature",
  "properties": {
    "gn:admin1_code":"17",
    "gn:admin2_code":"505.0",
    "gn:asciiname":"Ghazni Khel",
    "gn:country_code":"AF",
    "gn:dem":1850,
    "gn:feature_class":"P",
    "gn:feature_code":"PPL",
    "gn:name":"Ghazn\u012b Kh\u0113l",
    "gn:population":0,
    "gn:timezone":"Asia/Kabul",
    "iso:country":"AF",
    "name:rus_x_preferred":[
        "Gaznikheyl\u2019"
    ],
    "name:und_x_variant":[
        "Ghazn\u012b Kh\u0113l",
        "Ghaznikh\u0113l",
        "\u063a\u0632\u0646\u06cc \u062e\u06d0\u0644"
    ],
    "wof:name":"Ghazni Khel",
    "wof:placetype":"locality"
},
  "geometry": {"coordinates":[69.13518000000001,34.24423],"type":"Point"}
}