{
  "type": "Feature",
  "properties": {
    "gn:admin1_code":"41",
    "gn:admin2_code":"3407",
    "gn:asciiname":"Israk",
    "gn:country_code":"AF",
    "gn:dem":2794,
    "gn:feature_class":"P",
    "gn:feature_code":"PPL",
    "gn:name":"Israk",
    "gn:population":0,
    "gn:timezone":"Asia/Kabul",
    "iso:country":"AF",
    "name:und_x_variant":[
        "\u0627\u0633\u0631\u06a9",
        "Es\u1e5fak"
    ],
    "wof:name":"Israk",
    "wof:placetype":"locality"
},
  "geometry": {"coordinates":[67.27975000000001,33.86962],"type":"Point"}
}