{
  "type": "Feature",
  "properties": {
    "gn:admin1_code":"13",
    "gn:admin2_code":"112.0",
    "gn:asciiname":"'Alimad Khel",
    "gn:country_code":"AF",
    "gn:dem":1796,
    "gn:feature_class":"P",
    "gn:feature_code":"PPL",
    "gn:name":"\u2018Al\u012bmad Kh\u0113l",
    "gn:population":0,
    "gn:timezone":"Asia/Kabul",
    "iso:country":"AF",
    "name:fas_x_preferred":[
        "\u0639\u0644\u06cc \u0645\u062f \u062e\u064a\u0644"
    ],
    "name:rus_x_preferred":[
        "Razvaliny Alimadkheyl\u2019"
    ],
    "name:und_x_variant":[
        "\u2018Alima\u1e0fkh\u0113l",
        "\u0639\u0644\u06cc\u0645\u062f \u062e\u06d0\u0644",
        "\u2018Al\u012bmadkheyl",
        "\u2018Al\u012b Mad Kh\u0113l",
        "\u2018Al\u012bmad Kh\u0113l"
    ],
    "wof:name":"'Alimad Khel",
    "wof:placetype":"locality"
},
  "geometry": {"coordinates":[69.83056999999999,34.42755],"type":"Point"}
}