{
  "type": "Feature",
  "properties": {
    "gn:admin1_code":"27",
    "gn:admin2_code":"403",
    "gn:asciiname":"Zar Kharid",
    "gn:country_code":"AF",
    "gn:dem":2971,
    "gn:feature_class":"P",
    "gn:feature_code":"PPL",
    "gn:name":"Zar Khar\u012bd",
    "gn:population":0,
    "gn:timezone":"Asia/Kabul",
    "iso:country":"AF",
    "name:und_x_variant":[
        "Zarkharid",
        "Zarkhar\u012bd",
        "Zar Khar\u012bd",
        "\u0632\u0631 \u062e\u0631\u06cc\u062f"
    ],
    "wof:name":"Zar Kharid",
    "wof:placetype":"locality"
},
  "geometry": {"coordinates":[68.23834000000001,34.50999],"type":"Point"}
}