{
  "type": "Feature",
  "properties": {
    "gn:admin1_code":"02",
    "gn:admin2_code":"1903",
    "gn:asciiname":"Khanah-ye Haji Khalifah",
    "gn:country_code":"AF",
    "gn:dem":1857,
    "gn:feature_class":"P",
    "gn:feature_code":"PPL",
    "gn:name":"Kh\u0101nah-ye \u1e28\u0101j\u012b Khal\u012bfah",
    "gn:population":0,
    "gn:timezone":"Asia/Kabul",
    "iso:country":"AF",
    "name:und_x_variant":[
        "Kh\u0101na-i-\u1e28\u0101ji Khalifa",
        "Khanayi-Khadzhi-Khalifa",
        "Kh\u0101nah-ye \u1e28\u0101j\u012b Khal\u012bfah",
        "\u062e\u0627\u0646\u06c0 \u062d\u0627\u062c\u06cc \u062e\u0644\u06cc\u0641\u0647",
        "Kh\u0101neh-ye \u1e28\u0101jj\u012b Khal\u012bfeh"
    ],
    "wof:name":"Khanah-ye Haji Khalifah",
    "wof:placetype":"locality"
},
  "geometry": {"coordinates":[63.59753000000001,34.64459],"type":"Point"}
}