{
  "type": "Feature",
  "properties": {
    "gn:admin1_code":"01",
    "gn:admin2_code":"1126",
    "gn:asciiname":"Wulk-e Pa'in",
    "gn:country_code":"AF",
    "gn:dem":2344,
    "gn:feature_class":"P",
    "gn:feature_code":"PPL",
    "gn:name":"Wulk-e P\u0101\u2019\u012bn",
    "gn:population":0,
    "gn:timezone":"Asia/Kabul",
    "iso:country":"AF",
    "name:und_x_variant":[
        "Wolk-i-P\u0101\u2019\u012bn",
        "Wolk-e P\u0101\u2019\u012bn",
        "Wulk-e P\u0101\u2019\u012bn",
        "\u0648\u0644\u06a9 \u067e\u0627\u0626\u06cc\u0646"
    ],
    "wof:name":"Wulk-e Pa'in",
    "wof:placetype":"locality"
},
  "geometry": {"coordinates":[70.39305,37.36223],"type":"Point"}
}