{
  "type": "Feature",
  "properties": {
    "gn:admin1_code":"06",
    "gn:admin2_code":"2106",
    "gn:asciiname":"Khushk Abah",
    "gn:country_code":"AF",
    "gn:dem":699,
    "gn:feature_class":"P",
    "gn:feature_code":"PPL",
    "gn:name":"Khushk \u0100bah",
    "gn:population":0,
    "gn:timezone":"Asia/Kabul",
    "iso:country":"AF",
    "name:und_x_variant":[
        "\u0100ba",
        "Khosk \u0100beh",
        "Khu\u0161k\u0101ba",
        "Khu\u0161k \u0100wa",
        "Khoshk \u0100beh",
        "Khushk \u0100bah",
        "\u062e\u0634\u06a9 \u0622\u0628\u0647",
        "Khushk \u0100wah",
        "\u062e\u0634\u06a9 \u0622\u0648\u0647",
        "Khushkaba"
    ],
    "wof:name":"Khushk Abah",
    "wof:placetype":"locality"
},
  "geometry": {"coordinates":[62.16116,32.66949],"type":"Point"}
}