{
  "type": "Feature",
  "properties": {
    "gn:admin1_code":"9",
    "gn:admin2_code":"2707.0",
    "gn:asciiname":"Zaryaftah",
    "gn:country_code":"AF",
    "gn:dem":3016,
    "gn:feature_class":"P",
    "gn:feature_code":"PPL",
    "gn:name":"Zary\u0101ftah",
    "gn:population":0,
    "gn:timezone":"Asia/Kabul",
    "iso:country":"AF",
    "name:und_x_variant":[
        "Zariafta",
        "Za\u1e5fy\u0101fta",
        "Zary\u0101ftah",
        "Zary\u0101fteh",
        "\u0632\u0631\u06cc\u0627\u0641\u062a\u0647"
    ],
    "wof:name":"Zaryaftah",
    "wof:placetype":"locality"
},
  "geometry": {"coordinates":[66.63342,34.62175],"type":"Point"}
}