{
  "type": "Feature",
  "properties": {
    "gn:admin1_code":"37",
    "gn:admin2_code":"3202.0",
    "gn:asciiname":"Dani",
    "gn:country_code":"AF",
    "gn:dem":1387,
    "gn:feature_class":"P",
    "gn:feature_code":"PPL",
    "gn:name":"Dani",
    "gn:population":0,
    "gn:timezone":"Asia/Kabul",
    "iso:country":"AF",
    "name:bos_x_preferred":[
        "Dani"
    ],
    "name:bul_x_preferred":[
        "\u0414\u0430\u043d\u0438"
    ],
    "name:ceb_x_preferred":[
        "Dani"
    ],
    "name:deu_x_preferred":[
        "Dani"
    ],
    "name:fra_x_preferred":[
        "Dani"
    ],
    "name:hrv_x_preferred":[
        "Dani"
    ],
    "name:hun_x_preferred":[
        "Dani"
    ],
    "name:ind_x_preferred":[
        "Dani"
    ],
    "name:ita_x_preferred":[
        "Dani"
    ],
    "name:jpn_x_preferred":[
        "\u30c0\u30cb"
    ],
    "name:nld_x_preferred":[
        "Dani"
    ],
    "name:rus_x_preferred":[
        "\u0414\u0430\u043d\u0438"
    ],
    "name:slk_x_preferred":[
        "Dani"
    ],
    "name:slv_x_preferred":[
        "Dani"
    ],
    "name:srp_x_preferred":[
        "Dani"
    ],
    "name:swe_x_preferred":[
        "Dani"
    ],
    "name:zho_x_preferred":[
        "Dani"
    ],
    "wof:name":"Dani",
    "wof:placetype":"locality"
},
  "geometry": {"coordinates":[70.0575,33.58917],"type":"Point"}
}