{
  "type": "Feature",
  "properties": {
    "gn:admin1_code":"13",
    "gn:admin2_code":"110",
    "gn:asciiname":"Qal'ah-ye Wazir",
    "gn:country_code":"AF",
    "gn:dem":1796,
    "gn:feature_class":"P",
    "gn:feature_code":"PPL",
    "gn:name":"Qal\u2018ah-ye Waz\u012br",
    "gn:population":0,
    "gn:timezone":"Asia/Kabul",
    "iso:country":"AF",
    "name:und_x_variant":[
        "Kalavazir",
        "Qal\u2018eh-ye Waz\u012br",
        "Qal\u2018a-i-Waz\u012b\u1e5f",
        "Qal\u2018eh Waz\u012b\u1e5f",
        "Qal\u2018ah-ye Waz\u012br",
        "Qal\u2018eh-ye Vaz\u012br",
        "\u0642\u0644\u0639\u0647 \u0648\u0632\u06cc\u0631"
    ],
    "wof:name":"Qal'ah-ye Wazir",
    "wof:placetype":"locality"
},
  "geometry": {"coordinates":[69.21507,34.47458],"type":"Point"}
}