{
  "type": "Feature",
  "properties": {
    "gn:admin1_code":"08",
    "gn:admin2_code":"609",
    "gn:asciiname":"Qaryah-ye Khanan",
    "gn:country_code":"AF",
    "gn:dem":1966,
    "gn:feature_class":"P",
    "gn:feature_code":"PPL",
    "gn:name":"Qaryah-ye Kh\u0101n\u0101n",
    "gn:population":0,
    "gn:timezone":"Asia/Kabul",
    "iso:country":"AF",
    "name:rus_x_preferred":[
        "Kar\u2019yayi-Khanan"
    ],
    "name:und_x_variant":[
        "Qa\u1e5fya-i-Kh\u0101n\u0101n",
        "Qaryah-ye Kh\u0101n\u0101n",
        "\u0642\u0631\u06cc\u06c0 \u062e\u0627\u0646\u0627\u0646",
        "Qaryeh-ye Kh\u0101n\u0101n"
    ],
    "wof:name":"Qaryah-ye Khanan",
    "wof:placetype":"locality"
},
  "geometry": {"coordinates":[67.73402,32.75758],"type":"Point"}
}