{
  "type": "Feature",
  "properties": {
    "gn:admin1_code":"11",
    "gn:admin2_code":"2014.0",
    "gn:asciiname":"Deh-e Chashmah",
    "gn:country_code":"AF",
    "gn:dem":1056,
    "gn:feature_class":"P",
    "gn:feature_code":"PPL",
    "gn:name":"Deh-e Chashmah",
    "gn:population":0,
    "gn:timezone":"Asia/Kabul",
    "iso:country":"AF",
    "name:fas_x_preferred":[
        "\u0642\u0631\u064a\u06c0 \u0686\u0634\u0645\u0647"
    ],
    "name:und_x_variant":[
        "Dehe \u010ca\u0161ma",
        "Deh-e Chashmeh",
        "Dekhi-Chashma",
        "Deh-e Cheshmeh",
        "Deh-e Chashmah",
        "\u062f\u0647 \u0686\u0634\u0645\u0647",
        "\u0642\u0631\u064a\u06c0 \u0686\u0634\u0645\u0647"
    ],
    "wof:name":"Deh-e Chashmah",
    "wof:placetype":"locality"
},
  "geometry": {"coordinates":[62.22264000000001,33.27728],"type":"Point"}
}