{
  "type": "Feature",
  "properties": {
    "gn:admin1_code":"13",
    "gn:admin2_code":"110.0",
    "gn:asciiname":"Qal'ah-ye Ghulam 'Omar Khan",
    "gn:country_code":"AF",
    "gn:dem":1792,
    "gn:feature_class":"P",
    "gn:feature_code":"PPL",
    "gn:name":"Qal\u2018ah-ye Ghul\u0101m \u2018Omar Kh\u0101n",
    "gn:population":0,
    "gn:timezone":"Asia/Kabul",
    "iso:country":"AF",
    "name:und_x_variant":[
        "Qal\u2018ah-ye Ghul\u0101m \u2018Omar Kh\u0101n",
        "\u0642\u0644\u0639\u0647 \u063a\u0644\u0627\u0645 \u0639\u0645\u0631 \u062e\u0627\u0646",
        "Qal\u2019a Pakh\u010dak",
        "Kalarakhchak",
        "Qal\u2018eh-ye Pakhchak",
        "Qal\u2018ah-ye Pakhchak",
        "Qal\u2018ah-ye Yakhchak",
        "\u0642\u0644\u0639\u06c0 \u067e\u062e\u0686\u06a9"
    ],
    "wof:name":"Qal'ah-ye Ghulam 'Omar Khan",
    "wof:placetype":"locality"
},
  "geometry": {"coordinates":[69.2597,34.468],"type":"Point"}
}