{
  "type": "Feature",
  "properties": {
    "gn:admin1_code":"09",
    "gn:admin2_code":"2703",
    "gn:asciiname":"Tahow",
    "gn:country_code":"AF",
    "gn:dem":2437,
    "gn:feature_class":"P",
    "gn:feature_code":"PPL",
    "gn:name":"Tahow",
    "gn:population":0,
    "gn:timezone":"Asia/Kabul",
    "iso:country":"AF",
    "name:und_x_variant":[
        "\u062a\u0647\u0648",
        "Tahaw"
    ],
    "wof:name":"Tahow",
    "wof:placetype":"locality"
},
  "geometry": {"coordinates":[63.76217,33.92355999999999],"type":"Point"}
}