{
  "type": "Feature",
  "properties": {
    "gn:admin1_code":"02",
    "gn:admin2_code":"1907",
    "gn:asciiname":"Mulla Tuti-ye Fayroz-e Zai",
    "gn:country_code":"AF",
    "gn:dem":923,
    "gn:feature_class":"P",
    "gn:feature_code":"PPL",
    "gn:name":"Mull\u0101 \u0162\u016b\u0163\u012b-ye Fayr\u014dz-e Za\u012b",
    "gn:population":0,
    "gn:timezone":"Asia/Kabul",
    "iso:country":"AF",
    "name:und_x_variant":[
        "Mull\u0101 \u1e6e\u016b\u1e6fi F\u0113\u1e5f\u014dz Z\u0101\u2019i",
        "Moll\u0101 \u0162\u016b\u0163\u012b Fir\u016bzz\u0101y",
        "Moll\u0101 \u0162\u016b\u0163\u012b F\u012br\u016bzah\u2019\u012b",
        "Mull\u0101 \u0162\u016b\u0163\u012b-ye Fayr\u014dz-e Za\u012b",
        "\u0645\u0644\u0627 \u0637\u0648\u0637\u06cc \u0641\u06cc\u0631\u0648\u0632 \u0632\u06cc"
    ],
    "wof:name":"Mulla Tuti-ye Fayroz-e Zai",
    "wof:placetype":"locality"
},
  "geometry": {"coordinates":[63.29084,35.05965],"type":"Point"}
}