{
  "type": "Feature",
  "properties": {
    "gn:admin1_code":"33",
    "gn:admin2_code":"3105.0",
    "gn:asciiname":"Owdan",
    "gn:country_code":"AF",
    "gn:dem":899,
    "gn:feature_class":"P",
    "gn:feature_code":"PPL",
    "gn:name":"Owd\u0101n",
    "gn:population":0,
    "gn:timezone":"Asia/Kabul",
    "iso:country":"AF",
    "name:und_x_variant":[
        "Owd\u0101n",
        "\u0627\u0648\u062f\u0627\u0646",
        "\u0100bd\u0101n (3)"
    ],
    "wof:name":"Owdan",
    "wof:placetype":"locality"
},
  "geometry": {"coordinates":[66.12163000000001,36.04126],"type":"Point"}
}