{
  "type": "Feature",
  "properties": {
    "gn:admin1_code":"09",
    "gn:admin2_code":"2706",
    "gn:asciiname":"Khowal",
    "gn:country_code":"AF",
    "gn:dem":2445,
    "gn:feature_class":"P",
    "gn:feature_code":"PPL",
    "gn:name":"Khow\u0101l",
    "gn:population":0,
    "gn:timezone":"Asia/Kabul",
    "iso:country":"AF",
    "name:rus_x_preferred":[
        "Khaval\u2019"
    ],
    "name:und_x_variant":[
        "Khav\u0101l",
        "Khow\u0101l",
        "\u062e\u0648\u0627\u0644",
        "Khaw\u0101l"
    ],
    "wof:name":"Khowal",
    "wof:placetype":"locality"
},
  "geometry": {"coordinates":[64.82455,33.68569],"type":"Point"}
}