{
  "type": "Feature",
  "properties": {
    "gn:admin1_code":"40",
    "gn:admin2_code":"304.0",
    "gn:asciiname":"Tay Qal'ah",
    "gn:country_code":"AF",
    "gn:dem":1784,
    "gn:feature_class":"P",
    "gn:feature_code":"PPL",
    "gn:name":"Tay Qal\u2018ah",
    "gn:population":0,
    "gn:timezone":"Asia/Kabul",
    "iso:country":"AF",
    "name:fas_x_preferred":[
        "\u062a\u064a\u0642\u0644\u0627"
    ],
    "name:und_x_variant":[
        "Taykala",
        "Tayqal\u0101",
        "Tay Qal\u2018ah",
        "\u062a\u06cc \u0642\u0644\u0639\u0647"
    ],
    "wof:name":"Tay Qal'ah",
    "wof:placetype":"locality"
},
  "geometry": {"coordinates":[69.00606999999999,35.03352],"type":"Point"}
}