{
  "type": "Feature",
  "properties": {
    "gn:admin1_code":"7",
    "gn:admin2_code":"1804.0",
    "gn:asciiname":"Pa'in Guzar",
    "gn:country_code":"AF",
    "gn:dem":925,
    "gn:feature_class":"P",
    "gn:feature_code":"PPL",
    "gn:name":"P\u0101\u2019\u012bn Guz\u0304ar",
    "gn:population":0,
    "gn:timezone":"Asia/Kabul",
    "iso:country":"AF",
    "name:und_x_variant":[
        "P\u0101\u2019\u012bn Guz\u0304\u0101\u1e5f",
        "P\u0101\u2019\u012bn Goz\u0304\u0101r",
        "P\u0101\u2019\u012bn Guz\u0304ar",
        "\u067e\u0627\u0626\u06cc\u0646 \u06af\u0630\u0631"
    ],
    "wof:name":"Pa'in Guzar",
    "wof:placetype":"locality"
},
  "geometry": {"coordinates":[64.07133,35.7341],"type":"Point"}
}