{
  "type": "Feature",
  "properties": {
    "gn:admin1_code":"19",
    "gn:admin2_code":"2202",
    "gn:asciiname":"Kharot",
    "gn:country_code":"AF",
    "gn:dem":479,
    "gn:feature_class":"P",
    "gn:feature_code":"PPL",
    "gn:name":"Khar\u014dt",
    "gn:population":0,
    "gn:timezone":"Asia/Kabul",
    "iso:country":"AF",
    "name:fas_x_preferred":[
        "Kharow\u1e6f"
    ],
    "name:fas_x_variant":[
        "\u062e\u0631\u0648\u062a"
    ],
    "name:und_x_variant":[
        "Kha\u1e5f\u014dt",
        "Khar\u014dt",
        "Kharowt"
    ],
    "wof:name":"Kharot",
    "wof:placetype":"locality"
},
  "geometry": {"coordinates":[61.77969,31.20251],"type":"Point"}
}