{
  "type": "Feature",
  "properties": {
    "gn:admin1_code":"08",
    "gn:admin2_code":"604.0",
    "gn:asciiname":"Girdbayd-e Qalandar",
    "gn:country_code":"AF",
    "gn:dem":2893,
    "gn:feature_class":"P",
    "gn:feature_code":"PPL",
    "gn:name":"Girdbayd-e Qalandar",
    "gn:population":0,
    "gn:timezone":"Asia/Kabul",
    "iso:country":"AF",
    "name:und_x_variant":[
        "Girdbedi-Kalandar",
        "Ge\u1e5f\u1e0fb\u0113\u1e0fe Qalan\u1e0fa\u1e5f",
        "Gerdb\u012bd-e Qalandar",
        "Girdbayd-e Qalandar",
        "\u06af\u0631\u062f\u0628\u06cc\u062f \u0642\u0644\u0646\u062f\u0631"
    ],
    "wof:name":"Girdbayd-e Qalandar",
    "wof:placetype":"locality"
},
  "geometry": {"coordinates":[67.37334,34.02155],"type":"Point"}
}