{
  "type": "Feature",
  "properties": {
    "gn:admin1_code":"41",
    "gn:admin2_code":"3405",
    "gn:asciiname":"Dayktor",
    "gn:country_code":"AF",
    "gn:dem":2014,
    "gn:feature_class":"P",
    "gn:feature_code":"PPL",
    "gn:name":"Daykt\u014dr",
    "gn:population":0,
    "gn:timezone":"Asia/Kabul",
    "iso:country":"AF",
    "name:und_x_variant":[
        "\u1e0e\u0113kt\u014d\u1e5f",
        "Daykt\u014dr",
        "\u062f\u06cc\u06a9\u062a\u0648\u0631",
        "D\u0113ktowr"
    ],
    "wof:name":"Dayktor",
    "wof:placetype":"locality"
},
  "geometry": {"coordinates":[65.68735,33.78343],"type":"Point"}
}