{
  "type": "Feature",
  "properties": {
    "gn:admin1_code":"13",
    "gn:admin2_code":"115.0",
    "gn:asciiname":"Deh-e Mir Afghan",
    "gn:country_code":"AF",
    "gn:dem":1920,
    "gn:feature_class":"P",
    "gn:feature_code":"PPL",
    "gn:name":"Deh-e M\u012br Afgh\u0101n",
    "gn:population":0,
    "gn:timezone":"Asia/Kabul",
    "iso:country":"AF",
    "name:fas_x_preferred":[
        "\u062f\u0647\u0654 \u0645\u064a\u0631\u0641\u063a\u0627\u0646"
    ],
    "name:und_x_variant":[
        "Dekhi-Mirafgan",
        "Deh-e M\u012br Afgh\u0101n",
        "\u062f\u0647 \u0645\u06cc\u0631 \u0627\u0641\u063a\u0627\u0646"
    ],
    "wof:name":"Deh-e Mir Afghan",
    "wof:placetype":"locality"
},
  "geometry": {"coordinates":[69.06310000000001,34.80072],"type":"Point"}
}