{
  "type": "Feature",
  "properties": {
    "gn:admin1_code":"10",
    "gn:admin2_code":"2304.0",
    "gn:asciiname":"Seh Ab",
    "gn:country_code":"AF",
    "gn:dem":930,
    "gn:feature_class":"P",
    "gn:feature_code":"PPL",
    "gn:name":"Seh \u0100b",
    "gn:population":0,
    "gn:timezone":"Asia/Kabul",
    "iso:country":"AF",
    "name:und_x_variant":[
        "Sikhab",
        "Seh \u0100b",
        "\u0633\u0647 \u0622\u0628"
    ],
    "wof:name":"Seh Ab",
    "wof:placetype":"locality"
},
  "geometry": {"coordinates":[64.78366,32.14493],"type":"Point"}
}