{
  "type": "Feature",
  "properties": {
    "gn:admin1_code":"06",
    "gn:admin2_code":"2104",
    "gn:asciiname":"Poz Barij",
    "gn:country_code":"AF",
    "gn:dem":1466,
    "gn:feature_class":"P",
    "gn:feature_code":"PPL",
    "gn:name":"P\u014dz Bar\u012bj",
    "gn:population":0,
    "gn:timezone":"Asia/Kabul",
    "iso:country":"AF",
    "name:und_x_variant":[
        "P\u014dz Ba\u1e5f\u012bj",
        "Pozbaridzh",
        "P\u016bz Bar\u012bj",
        "P\u014dz Bar\u012bj",
        "\u067e\u0648\u0632 \u0628\u0631\u06cc\u062c"
    ],
    "wof:name":"Poz Barij",
    "wof:placetype":"locality"
},
  "geometry": {"coordinates":[63.12923000000001,33.19368],"type":"Point"}
}