{
  "type": "Feature",
  "properties": {
    "gn:admin1_code":"02",
    "gn:admin2_code":"1903",
    "gn:asciiname":"Kotal-e Jowza",
    "gn:country_code":"AF",
    "gn:dem":1566,
    "gn:feature_class":"P",
    "gn:feature_code":"PPL",
    "gn:name":"K\u014dtal-e Jowz\u0101",
    "gn:population":0,
    "gn:timezone":"Asia/Kabul",
    "iso:country":"AF",
    "name:und_x_variant":[
        "K\u014dtal-e Jawz\u0101",
        "Kotali-Dzhauza",
        "K\u014dtal-e Jowz\u0101",
        "\u06a9\u0648\u062a\u0644 \u062c\u0648\u0632\u0627",
        "Kowtal-e Jawz\u0101"
    ],
    "wof:name":"Kotal-e Jowza",
    "wof:placetype":"locality"
},
  "geometry": {"coordinates":[63.55037,34.73004],"type":"Point"}
}