{
  "type": "Feature",
  "properties": {
    "gn:admin1_code":"23",
    "gn:admin2_code":"2412.0",
    "gn:asciiname":"Saliktu Kelay",
    "gn:country_code":"AF",
    "gn:dem":1345,
    "gn:feature_class":"P",
    "gn:feature_code":"PPL",
    "gn:name":"Salikt\u016b K\u00ealay",
    "gn:population":0,
    "gn:timezone":"Asia/Kabul",
    "iso:country":"AF",
    "name:und_x_variant":[
        "Saliktukalay",
        "Sal\u00eakt\u014d K\u00ealay",
        "Salektu Kalay",
        "Salikt\u016b K\u00ealay",
        "\u0633\u0644\u06a9\u062a\u0648 \u06a9\u0644\u06cc"
    ],
    "wof:name":"Saliktu Kelay",
    "wof:placetype":"locality"
},
  "geometry": {"coordinates":[66.54579,31.43801],"type":"Point"}
}