{
  "type": "Feature",
  "properties": {
    "gn:admin1_code":"08",
    "gn:admin2_code":"610",
    "gn:asciiname":"Sayyid Khel",
    "gn:country_code":"AF",
    "gn:dem":2000,
    "gn:feature_class":"P",
    "gn:feature_code":"PPL",
    "gn:name":"Sayyid Kh\u0113l",
    "gn:population":0,
    "gn:timezone":"Asia/Kabul",
    "iso:country":"AF",
    "name:rus_x_preferred":[
        "Seyidkheyl\u2019"
    ],
    "name:und_x_variant":[
        "Saye\u1e0fkh\u0113l",
        "Sayyid Kh\u0113l",
        "\u0633\u06cc\u062f \u062e\u06d0\u0644",
        "\u015eeyyed Kheyl"
    ],
    "wof:name":"Sayyid Khel",
    "wof:placetype":"locality"
},
  "geometry": {"coordinates":[67.72939000000001,32.26562],"type":"Point"}
}