{
  "type": "Feature",
  "properties": {
    "gn:admin1_code":"11",
    "gn:asciiname":"Karez-e Aghah",
    "gn:country_code":"AF",
    "gn:dem":933,
    "gn:feature_class":"P",
    "gn:feature_code":"PPL",
    "gn:name":"K\u0101r\u0113z-e \u0100ghah",
    "gn:population":0,
    "gn:timezone":"Asia/Kabul",
    "iso:country":"AF",
    "name:und_x_variant":[
        "K\u0101r\u0113ze \u0100gha",
        "K\u0101r\u012bz-e \u0100gh\u0101",
        "K\u0101r\u0113z-e \u0100ghah",
        "\u06a9\u0627\u0631\u06d0\u0632 \u0622\u063a\u0647"
    ],
    "wof:name":"Karez-e Aghah",
    "wof:placetype":"locality"
},
  "geometry": {"coordinates":[61.91651,32.91695],"type":"Point"}
}