{
  "type": "Feature",
  "properties": {
    "gn:admin1_code":"40",
    "gn:admin2_code":"304",
    "gn:asciiname":"Yakah Khinjak",
    "gn:country_code":"AF",
    "gn:dem":1916,
    "gn:feature_class":"P",
    "gn:feature_code":"PPL",
    "gn:name":"Yakah Khinjak",
    "gn:population":0,
    "gn:timezone":"Asia/Kabul",
    "iso:country":"AF",
    "name:fas_x_preferred":[
        "\u064a\u0643\u0647 \u062e\u0646\u062c\u0643"
    ],
    "name:und_x_variant":[
        "Yakakhindzhak",
        "Yakakhenjak",
        "Yakah Khinjak",
        "\u06cc\u06a9\u0647 \u062e\u0646\u062c\u06a9"
    ],
    "wof:name":"Yakah Khinjak",
    "wof:placetype":"locality"
},
  "geometry": {"coordinates":[69.03664000000001,35.07057],"type":"Point"}
}