{
  "type": "Feature",
  "properties": {
    "gn:admin1_code":"34",
    "gn:admin2_code":"1007",
    "gn:asciiname":"Mirzagi",
    "gn:country_code":"AF",
    "gn:dem":1168,
    "gn:feature_class":"P",
    "gn:feature_code":"PPL",
    "gn:name":"Mirzagi",
    "gn:population":0,
    "gn:timezone":"Asia/Kabul",
    "iso:country":"AF",
    "name:fas_x_preferred":[
        "\u0645\u064a\u0631\u0632\u06af\u06cc"
    ],
    "name:und_x_variant":[
        "M\u012b\u1e5fzagi",
        "M\u012brz\u0101g\u012b",
        "\u0645\u06cc\u0631\u0632\u0627\u06af\u06cc"
    ],
    "wof:name":"Mirzagi",
    "wof:placetype":"locality"
},
  "geometry": {"coordinates":[71.19104,34.95753],"type":"Point"}
}