{
  "type": "Feature",
  "properties": {
    "gn:admin1_code":"35",
    "gn:admin2_code":"905",
    "gn:asciiname":"Parmawan",
    "gn:country_code":"AF",
    "gn:dem":1542,
    "gn:feature_class":"P",
    "gn:feature_code":"PPL",
    "gn:name":"Parm\u0101w\u0101n",
    "gn:population":0,
    "gn:timezone":"Asia/Kabul",
    "iso:country":"AF",
    "name:und_x_variant":[
        "Parmavan",
        "Pa\u1e5fm\u0101w\u0101n",
        "Parm\u0101w\u0101n",
        "\u067e\u0631\u0645\u0627\u0648\u0627\u0646"
    ],
    "wof:name":"Parmawan",
    "wof:placetype":"locality"
},
  "geometry": {"coordinates":[70.15054000000001,34.90436],"type":"Point"}
}