{
  "type": "Feature",
  "properties": {
    "gn:admin1_code":"8",
    "gn:admin2_code":"604.0",
    "gn:asciiname":"Panqash",
    "gn:country_code":"AF",
    "gn:dem":3338,
    "gn:feature_class":"P",
    "gn:feature_code":"PPL",
    "gn:name":"Panq\u0101sh",
    "gn:population":0,
    "gn:timezone":"Asia/Kabul",
    "iso:country":"AF",
    "name:und_x_variant":[
        "Pankash",
        "Panq\u0101\u0161",
        "Panq\u0101sh",
        "\u067e\u0646\u0642\u0627\u0634"
    ],
    "wof:name":"Panqash",
    "wof:placetype":"locality"
},
  "geometry": {"coordinates":[67.76488000000001,34.15522],"type":"Point"}
}