{
  "type": "Feature",
  "properties": {
    "gn:admin1_code":"39",
    "gn:admin2_code":"2602",
    "gn:asciiname":"Nowab Khan",
    "gn:country_code":"AF",
    "gn:dem":1733,
    "gn:feature_class":"P",
    "gn:feature_code":"PPL",
    "gn:name":"Now\u0101b Kh\u0101n",
    "gn:population":0,
    "gn:timezone":"Asia/Kabul",
    "iso:country":"AF",
    "name:und_x_variant":[
        "Naw\u0101bkh\u0101n",
        "Gu\u1e5fjiza\u2019i",
        "Navabkhan",
        "Now\u0101b Kh\u0101n",
        "\u0646\u0648\u0627\u0628 \u062e\u0627\u0646",
        "Navv\u0101bkh\u0101n",
        "Gurj\u012bza\u012b",
        "\u06af\u0631\u062c\u06cc\u0632\u06cc"
    ],
    "wof:name":"Nowab Khan",
    "wof:placetype":"locality"
},
  "geometry": {"coordinates":[66.09124,32.88179],"type":"Point"}
}