{
  "type": "Feature",
  "properties": {
    "gn:admin1_code":"29",
    "gn:admin2_code":"2909.0",
    "gn:asciiname":"Musa Kalim Kala",
    "gn:country_code":"AF",
    "gn:dem":2078,
    "gn:feature_class":"P",
    "gn:feature_code":"PPL",
    "gn:name":"M\u016bs\u00e1 Kal\u012bm Kal\u0101",
    "gn:population":0,
    "gn:timezone":"Asia/Kabul",
    "iso:country":"AF",
    "name:fas_x_preferred":[
        "\u0645\u0648\u0633\u0649 \u0643\u0644\u064a\u0645 \u0643\u0644\u0627"
    ],
    "name:und_x_variant":[
        "Muoakalim-Kala",
        "M\u016bs\u00e1 Kal\u012bm Kal\u0101",
        "M\u016bs\u00e1kal\u012bm Kal\u0101",
        "\u0645\u0648\u0633\u0649 \u0643\u0644\u064a\u0645 \u0643\u0644\u0627"
    ],
    "wof:name":"Musa Kalim Kala",
    "wof:placetype":"locality"
},
  "geometry": {"coordinates":[69.19509000000001,32.49726],"type":"Point"}
}