{
  "type": "Feature",
  "properties": {
    "gn:admin1_code":"17",
    "gn:admin2_code":"506",
    "gn:asciiname":"Muhammad Khel",
    "gn:country_code":"AF",
    "gn:dem":2302,
    "gn:feature_class":"P",
    "gn:feature_code":"PPL",
    "gn:name":"Mu\u1e29ammad Kh\u0113l",
    "gn:population":0,
    "gn:timezone":"Asia/Kabul",
    "iso:country":"AF",
    "name:fas_x_preferred":[
        "\u0645\u062d\u0645\u062f \u062e\u064a\u0644"
    ],
    "name:rus_x_preferred":[
        "Mukhammedkheyl\u2019"
    ],
    "name:und_x_variant":[
        "Mo\u1e29amme\u1e0f-kh\u0113l",
        "M\u014dh\u1e0f-Kh\u0113l",
        "Mu\u1e29ammad Kh\u0113l",
        "Mo\u1e29ammad Kheyl",
        "Mu\u1e29ammad-Kh\u0113l",
        "\u0645\u062d\u0645\u062f \u062e\u06d0\u0644"
    ],
    "name:urd_x_preferred":[
        "\u0645\u062d\u0645\u062f \u062e\u06cc\u0644"
    ],
    "wof:name":"Muhammad Khel",
    "wof:placetype":"locality"
},
  "geometry": {"coordinates":[69.72145999999999,34.14794000000001],"type":"Point"}
}