{
  "type": "Feature",
  "properties": {
    "gn:admin1_code":"35",
    "gn:admin2_code":"902.0",
    "gn:asciiname":"Darwar",
    "gn:country_code":"AF",
    "gn:dem":618,
    "gn:feature_class":"P",
    "gn:feature_code":"PPL",
    "gn:name":"Darwa\u1e5f",
    "gn:population":0,
    "gn:timezone":"Asia/Kabul",
    "iso:country":"AF",
    "name:und_x_variant":[
        "Darvar",
        "Darwar",
        "Darwa\u1e5f",
        "\u062f\u0631\u0648\u0693"
    ],
    "wof:name":"Darwar",
    "wof:placetype":"locality"
},
  "geometry": {"coordinates":[70.26286,34.50346],"type":"Point"}
}