{
  "type": "Feature",
  "properties": {
    "gn:admin1_code":"01",
    "gn:admin2_code":"1120.0",
    "gn:asciiname":"Wajud",
    "gn:country_code":"AF",
    "gn:dem":2456,
    "gn:feature_class":"P",
    "gn:feature_code":"PPL",
    "gn:name":"W\u0101j\u016bd",
    "gn:population":0,
    "gn:timezone":"Asia/Kabul",
    "iso:country":"AF",
    "name:und_x_variant":[
        "\u0648\u0627\u062c\u0648\u062f",
        "W\u0101j\u016b\u1e0f",
        "W\u0101j\u016bd"
    ],
    "wof:name":"Wajud",
    "wof:placetype":"locality"
},
  "geometry": {"coordinates":[70.60899000000001,37.97588],"type":"Point"}
}