{
  "type": "Feature",
  "properties": {
    "gn:admin1_code":"18",
    "gn:admin2_code":"816",
    "gn:asciiname":"Khuga Khel",
    "gn:country_code":"AF",
    "gn:dem":957,
    "gn:feature_class":"P",
    "gn:feature_code":"PPL",
    "gn:name":"Kh\u016bg\u0101 Kh\u0113l",
    "gn:population":0,
    "gn:timezone":"Asia/Kabul",
    "iso:country":"AF",
    "name:fas_x_preferred":[
        "\u062e\u0648\u06af\u0627 \u062e\u064a\u0644"
    ],
    "name:rus_x_preferred":[
        "Kugakheyl\u2019"
    ],
    "name:und_x_variant":[
        "Kh\u016bg\u0101kh\u014dl",
        "Kh\u016bg\u0101 Kh\u0113l",
        "Kh\u016bg\u0101 Kheyl",
        "\u062e\u0648\u06af\u0627 \u062e\u064a\u0644",
        "\u062e\u0648\u06af\u0627 \u062e\u06d0\u0644"
    ],
    "wof:name":"Khuga Khel",
    "wof:placetype":"locality"
},
  "geometry": {"coordinates":[70.91421,34.49167],"type":"Point"}
}