{
  "type": "Feature",
  "properties": {
    "gn:admin1_code":"23",
    "gn:admin2_code":"2416",
    "gn:asciiname":"Sutian",
    "gn:country_code":"AF",
    "gn:dem":931,
    "gn:feature_class":"P",
    "gn:feature_code":"PPL",
    "gn:name":"Sutian",
    "gn:population":0,
    "gn:timezone":"Asia/Kabul",
    "iso:country":"AF",
    "name:und_x_variant":[
        "\u015e\u016bf\u012b\u0101n",
        "\u0635\u0648\u0641\u06cc\u0627\u0646"
    ],
    "wof:name":"Sutian",
    "wof:placetype":"locality"
},
  "geometry": {"coordinates":[65.33599,31.53461],"type":"Point"}
}