{
  "type": "Feature",
  "properties": {
    "gn:admin1_code":"08",
    "gn:admin2_code":"617",
    "gn:asciiname":"Qal'ah-ye Na'ib Jan 'Ali",
    "gn:country_code":"AF",
    "gn:dem":2685,
    "gn:feature_class":"P",
    "gn:feature_code":"PPL",
    "gn:name":"Qal\u2018ah-ye N\u0101\u2019ib J\u0101n \u2018Al\u012b",
    "gn:population":0,
    "gn:timezone":"Asia/Kabul",
    "iso:country":"AF",
    "name:fas_x_preferred":[
        "\u0642\u0644\u0639\u0647\u0654 \u0646\u0627\u0626\u0628 \u062c\u0627\u0646 \u0639\u0644\u06cc"
    ],
    "name:und_x_variant":[
        "Qal\u2018a N\u0101\u2019eb Jan\u2018ali",
        "Kalanaib-Dzhanali",
        "Qal\u2018a-i-N\u0101\u2019eb Jan\u2018ali",
        "Qal\u2018eh-ye N\u0101\u2019eb Jan\u2018al\u012b",
        "Qal\u2018ah-ye N\u0101\u2019ib J\u0101n \u2018Al\u012b",
        "\u0642\u0644\u0639\u06c0 \u0646\u0627 \u0626\u0628 \u062c\u0627\u0646\u0639\u0644\u06cc"
    ],
    "wof:name":"Qal'ah-ye Na'ib Jan 'Ali",
    "wof:placetype":"locality"
},
  "geometry": {"coordinates":[68.11284999999999,33.6555],"type":"Point"}
}