{
  "type": "Feature",
  "properties": {
    "gn:admin1_code":"29",
    "gn:admin2_code":"2903",
    "gn:asciiname":"Kutgay",
    "gn:country_code":"AF",
    "gn:dem":2035,
    "gn:feature_class":"P",
    "gn:feature_code":"PPL",
    "gn:name":"K\u016btgay",
    "gn:population":0,
    "gn:timezone":"Asia/Kabul",
    "iso:country":"AF",
    "name:und_x_variant":[
        "\u06a9\u0648\u062a\u06af\u06cc",
        "Kowtgay",
        "K\u016btgay"
    ],
    "wof:name":"Kutgay",
    "wof:placetype":"locality"
},
  "geometry": {"coordinates":[68.35115999999999,32.65855999999999],"type":"Point"}
}