{
  "type": "Feature",
  "properties": {
    "gn:admin1_code":"35",
    "gn:admin2_code":"903",
    "gn:asciiname":"Shingari",
    "gn:country_code":"AF",
    "gn:dem":831,
    "gn:feature_class":"P",
    "gn:feature_code":"PPL",
    "gn:name":"Shing\u0101r\u012b",
    "gn:population":0,
    "gn:timezone":"Asia/Kabul",
    "iso:country":"AF",
    "name:und_x_variant":[
        "\u0160ing\u0101ri",
        "Shingari",
        "\u0634\u0646\u06af\u0627\u0631\u06cc",
        "Sh\u012bng\u0101r\u012b",
        "Shing\u0101r\u012b"
    ],
    "wof:name":"Shingari",
    "wof:placetype":"locality"
},
  "geometry": {"coordinates":[70.29859,34.74014],"type":"Point"}
}