{
  "type": "Feature",
  "properties": {
    "gn:admin1_code":"23",
    "gn:admin2_code":"2413.0",
    "gn:asciiname":"Jamrod",
    "gn:country_code":"AF",
    "gn:dem":1712,
    "gn:feature_class":"P",
    "gn:feature_code":"PPL",
    "gn:name":"Jamr\u014dd",
    "gn:population":0,
    "gn:timezone":"Asia/Kabul",
    "iso:country":"AF",
    "name:pus_x_preferred":[
        "\u062c\u0645\u0631\u0648\u062f"
    ],
    "name:und_x_variant":[
        "Dzhamrud",
        "Jam\u1e5f\u014d\u1e0f",
        "Jamr\u014dd",
        "\u062c\u0645\u0631\u0648\u062f",
        "Jamr\u016bd"
    ],
    "wof:name":"Jamrod",
    "wof:placetype":"locality"
},
  "geometry": {"coordinates":[67.2163,31.62527],"type":"Point"}
}