{
  "type": "Feature",
  "properties": {
    "gn:admin1_code":"29",
    "gn:admin2_code":"2901.0",
    "gn:asciiname":"Mulkaki",
    "gn:country_code":"AF",
    "gn:dem":2149,
    "gn:feature_class":"P",
    "gn:feature_code":"PPL",
    "gn:name":"Mulkak\u012b",
    "gn:population":0,
    "gn:timezone":"Asia/Kabul",
    "iso:country":"AF",
    "name:rus_x_preferred":[
        "Mul\u2019kaki"
    ],
    "name:und_x_variant":[
        "\u0645\u0644\u06a9\u06a9\u06cc",
        "Molkak\u012b",
        "Mulkak\u012b"
    ],
    "wof:name":"Mulkaki",
    "wof:placetype":"locality"
},
  "geometry": {"coordinates":[68.78527,33.14745],"type":"Point"}
}