{
  "type": "Feature",
  "properties": {
    "gn:admin1_code":"41",
    "gn:admin2_code":"3405.0",
    "gn:asciiname":"Kayti",
    "gn:country_code":"AF",
    "gn:dem":2390,
    "gn:feature_class":"P",
    "gn:feature_code":"PPL",
    "gn:name":"Kayt\u012b",
    "gn:population":0,
    "gn:timezone":"Asia/Kabul",
    "iso:country":"AF",
    "name:und_x_variant":[
        "Kayt\u012b",
        "\u06a9\u06cc\u062a\u06cc",
        "K\u0113ti"
    ],
    "wof:name":"Kayti",
    "wof:placetype":"locality"
},
  "geometry": {"coordinates":[65.75315999999999,33.85163],"type":"Point"}
}