{
  "type": "Feature",
  "properties": {
    "gn:admin1_code":"30",
    "gn:admin2_code":"1609",
    "gn:asciiname":"Qurbaqah Khanah",
    "gn:country_code":"AF",
    "gn:dem":574,
    "gn:feature_class":"P",
    "gn:feature_code":"PPL",
    "gn:name":"Q\u016brbaqah Kh\u0101nah",
    "gn:population":0,
    "gn:timezone":"Asia/Kabul",
    "iso:country":"AF",
    "name:und_x_variant":[
        "Qurbaqqa Kh\u0101na",
        "Q\u016brb\u0101gheh Kh\u0101neh",
        "Q\u016brbaqah Kh\u0101nah",
        "\u0642\u0648\u0631\u0628\u0642\u0647 \u062e\u0627\u0646\u0647"
    ],
    "wof:name":"Qurbaqah Khanah",
    "wof:placetype":"locality"
},
  "geometry": {"coordinates":[66.88113,36.39058],"type":"Point"}
}