{
  "type": "Feature",
  "properties": {
    "gn:admin1_code":"41",
    "gn:admin2_code":"3407.0",
    "gn:asciiname":"Sar-e Sang",
    "gn:country_code":"AF",
    "gn:dem":2101,
    "gn:feature_class":"P",
    "gn:feature_code":"PPL",
    "gn:name":"Sar-e Sang",
    "gn:population":0,
    "gn:timezone":"Asia/Kabul",
    "iso:country":"AF",
    "name:und_x_variant":[
        "\u0633\u0631 \u0633\u0646\u06af"
    ],
    "wof:name":"Sar-e Sang",
    "wof:placetype":"locality"
},
  "geometry": {"coordinates":[67.22620000000001,33.92652],"type":"Point"}
}