{
  "type": "Feature",
  "properties": {
    "gn:admin1_code":"27",
    "gn:admin2_code":"408",
    "gn:asciiname":"Khushkak Darah",
    "gn:country_code":"AF",
    "gn:dem":2113,
    "gn:feature_class":"P",
    "gn:feature_code":"PPL",
    "gn:name":"Khushkak Darah",
    "gn:population":0,
    "gn:timezone":"Asia/Kabul",
    "iso:country":"AF",
    "name:und_x_variant":[
        "Khu\u0161kak-dara",
        "Khushkak-dara",
        "Khushkakdara",
        "Khoshkak Darrah",
        "Khushkak Darah",
        "Khoshkak Darreh",
        "\u062e\u0634\u06a9\u06a9 \u062f\u0631\u0647"
    ],
    "wof:name":"Khushkak Darah",
    "wof:placetype":"locality"
},
  "geometry": {"coordinates":[68.88653000000001,34.32747],"type":"Point"}
}