{
  "type": "Feature",
  "properties": {
    "gn:admin1_code":"24",
    "gn:admin2_code":"1407.0",
    "gn:asciiname":"Baysh Qutan",
    "gn:country_code":"AF",
    "gn:dem":437,
    "gn:feature_class":"P",
    "gn:feature_code":"PPL",
    "gn:name":"Baysh Q\u016btan",
    "gn:population":0,
    "gn:timezone":"Asia/Kabul",
    "iso:country":"AF",
    "name:rus_x_preferred":[
        "\u0411\u0435\u0448\u043a\u0443\u0442\u0430\u043d"
    ],
    "name:und_x_variant":[
        "B\u0113\u0161 Q\u016btan",
        "Beshkutan",
        "B\u012bsh Q\u016btan",
        "Baysh Q\u016btan",
        "\u0628\u06cc\u0634 \u0642\u0648\u062a\u0646"
    ],
    "wof:name":"Baysh Qutan",
    "wof:placetype":"locality"
},
  "geometry": {"coordinates":[69.10732,36.9932],"type":"Point"}
}