{
  "type": "Feature",
  "properties": {
    "gn:admin1_code":"8",
    "gn:admin2_code":"601.0",
    "gn:asciiname":"Shahr-e Kuhnah wa Bala Hisar",
    "gn:country_code":"AF",
    "gn:dem":2187,
    "gn:feature_class":"P",
    "gn:feature_code":"PPL",
    "gn:name":"Shahr-e Kuhnah wa B\u0101l\u0101 \u1e28i\u015f\u0101r",
    "gn:population":0,
    "gn:timezone":"Asia/Kabul",
    "iso:country":"AF",
    "name:fas_x_preferred":[
        "\u0634\u0647\u0631\u0654 \u0643\u0647\u0646\u0647 \u0648 \u0628\u0627\u0644\u0627 \u062d\u0633\u0627\u0631"
    ],
    "name:und_x_variant":[
        "\u0160\u0101hre Kuhna wa B\u0101l\u0101he\u015f\u0101r",
        "Shakhri-Kukhna-Va-Balakhisar",
        "Shahr-e Kuhnah wa B\u0101l\u0101 \u1e28i\u015f\u0101r",
        "Shahr-e Kohneh va B\u0101l\u0101\u1e29es\u0101r",
        "\u0634\u0647\u0631 \u06a9\u0647\u0646\u0647 \u0648 \u0628\u0627\u0644\u0627 \u062d\u0635\u0627\u0631"
    ],
    "wof:name":"Shahr-e Kuhnah wa Bala Hisar",
    "wof:placetype":"locality"
},
  "geometry": {"coordinates":[68.43214999999999,33.55932],"type":"Point"}
}