{
  "type": "Feature",
  "properties": {
    "gn:admin1_code":"11",
    "gn:admin2_code":"2005",
    "gn:asciiname":"Mir Salman",
    "gn:country_code":"AF",
    "gn:dem":1239,
    "gn:feature_class":"P",
    "gn:feature_code":"PPL",
    "gn:name":"M\u012br Salm\u0101n",
    "gn:population":0,
    "gn:timezone":"Asia/Kabul",
    "iso:country":"AF",
    "name:und_x_variant":[
        "Mir-Suleyman",
        "M\u012br Salm\u0101n",
        "\u0645\u06cc\u0631 \u0633\u0644\u0645\u0627\u0646",
        "M\u012b\u1e5f Salm\u0101n"
    ],
    "wof:name":"Mir Salman",
    "wof:placetype":"locality"
},
  "geometry": {"coordinates":[62.43819000000001,34.48063],"type":"Point"}
}