{
  "type": "Feature",
  "properties": {
    "gn:admin1_code":"03",
    "gn:admin2_code":"1304",
    "gn:asciiname":"Qal'ah-ye Kayan",
    "gn:country_code":"AF",
    "gn:dem":1739,
    "gn:feature_class":"P",
    "gn:feature_code":"PPL",
    "gn:name":"Qal\u2018ah-ye Kay\u0101n",
    "gn:population":0,
    "gn:timezone":"Asia/Kabul",
    "iso:country":"AF",
    "name:und_x_variant":[
        "Qal\u2018a-i-Kay\u0101n",
        "Kai\u0101n",
        "Qal\u2018eh-ye Kay\u0101n",
        "Qala Kay\u0101n",
        "Kay\u0101n",
        "Qal\u2018ah-ye Kay\u0101n",
        "\u0642\u0644\u0639\u06c0 \u06a9\u06cc\u0627\u0646"
    ],
    "wof:name":"Qal'ah-ye Kayan",
    "wof:placetype":"locality"
},
  "geometry": {"coordinates":[68.42729,35.63468],"type":"Point"}
}