{
  "type": "Feature",
  "properties": {
    "gn:admin1_code":"01",
    "gn:admin2_code":"1107.0",
    "gn:asciiname":"Aytch",
    "gn:country_code":"AF",
    "gn:dem":2273,
    "gn:feature_class":"P",
    "gn:feature_code":"PPL",
    "gn:name":"Aytch",
    "gn:population":0,
    "gn:timezone":"Asia/Kabul",
    "iso:country":"AF",
    "name:und_x_variant":[
        "\u0112tch",
        "\u0627\u06d0\u062a\u0686",
        "Aytch"
    ],
    "wof:name":"Aytch",
    "wof:placetype":"locality"
},
  "geometry": {"coordinates":[71.46384,37.22181],"type":"Point"}
}