{
  "type": "Feature",
  "properties": {
    "gn:admin1_code":"41",
    "gn:admin2_code":"3405.0",
    "gn:asciiname":"Asmurdah",
    "gn:country_code":"AF",
    "gn:dem":2574,
    "gn:feature_class":"P",
    "gn:feature_code":"PPL",
    "gn:name":"\u0100smurdah",
    "gn:population":0,
    "gn:timezone":"Asia/Kabul",
    "iso:country":"AF",
    "name:und_x_variant":[
        "\u0100smu\u1e5f\u1e0fa",
        "\u0100smurdah",
        "\u0622\u0633\u0645\u0631\u062f\u0647",
        "\u0100smordeh"
    ],
    "wof:name":"Asmurdah",
    "wof:placetype":"locality"
},
  "geometry": {"coordinates":[65.87153000000001,33.79618],"type":"Point"}
}