{
  "type": "Feature",
  "properties": {
    "gn:admin1_code":"5",
    "gn:admin2_code":"2802.0",
    "gn:asciiname":"Mirazar",
    "gn:country_code":"AF",
    "gn:dem":3148,
    "gn:feature_class":"P",
    "gn:feature_code":"PPL",
    "gn:name":"M\u012braz\u0101r",
    "gn:population":0,
    "gn:timezone":"Asia/Kabul",
    "iso:country":"AF",
    "name:und_x_variant":[
        "M\u012b\u1e5faz\u0101\u1e5f",
        "Mirazar",
        "M\u012brahz\u0101r",
        "M\u012brehz\u0101r",
        "M\u012braz\u0101r",
        "\u0645\u06cc\u0631\u0632\u0627\u0631"
    ],
    "wof:name":"Mirazar",
    "wof:placetype":"locality"
},
  "geometry": {"coordinates":[67.98669,34.67989],"type":"Point"}
}