{
  "type": "Feature",
  "properties": {
    "gn:admin1_code":"30",
    "gn:admin2_code":"1603.0",
    "gn:asciiname":"Darah",
    "gn:country_code":"AF",
    "gn:dem":2042,
    "gn:feature_class":"P",
    "gn:feature_code":"PPL",
    "gn:name":"\u1e0e\u0101rah",
    "gn:population":0,
    "gn:timezone":"Asia/Kabul",
    "iso:country":"AF",
    "name:und_x_variant":[
        "D\u0101\u1e5fa",
        "D\u0101\u1e5fah",
        "\u1e0e\u0101rah",
        "\u0689\u0627\u0631\u0647"
    ],
    "wof:name":"Darah",
    "wof:placetype":"locality"
},
  "geometry": {"coordinates":[66.67193,35.72017],"type":"Point"}
}