{
  "type": "Feature",
  "properties": {
    "gn:admin1_code":"17",
    "gn:admin2_code":"504.0",
    "gn:asciiname":"Bala Deh",
    "gn:country_code":"AF",
    "gn:dem":2202,
    "gn:feature_class":"P",
    "gn:feature_code":"PPL",
    "gn:name":"B\u0101l\u0101 Deh",
    "gn:population":0,
    "gn:timezone":"Asia/Kabul",
    "iso:country":"AF",
    "name:und_x_variant":[
        "B\u0101l\u0101\u1e0feh",
        "Baladekh",
        "B\u0101l\u0101 Deh",
        "\u0628\u0627\u0644\u0627 \u062f\u0647"
    ],
    "wof:name":"Bala Deh",
    "wof:placetype":"locality"
},
  "geometry": {"coordinates":[69.20599,34.00391],"type":"Point"}
}