{
  "type": "Feature",
  "properties": {
    "gn:admin1_code":"08",
    "gn:admin2_code":"602",
    "gn:asciiname":"Deh-e Shashi",
    "gn:country_code":"AF",
    "gn:dem":2681,
    "gn:feature_class":"P",
    "gn:feature_code":"PPL",
    "gn:name":"Deh-e Sh\u0101sh\u012b",
    "gn:population":0,
    "gn:timezone":"Asia/Kabul",
    "iso:country":"AF",
    "name:fas_x_preferred":[
        "\u062f\u0647\u0654 \u0634\u0627\u0634\u06cc"
    ],
    "name:und_x_variant":[
        "Dehe \u0160\u0101\u0161i",
        "Dekhi-Shashi",
        "Deh-e Sh\u0101sh\u012b",
        "\u062f\u0647 \u0634\u0627\u0634\u06cc"
    ],
    "wof:name":"Deh-e Shashi",
    "wof:placetype":"locality"
},
  "geometry": {"coordinates":[68.1348,33.54615],"type":"Point"}
}