{
  "type": "Feature",
  "properties": {
    "gn:admin1_code":"8",
    "gn:admin2_code":"606.0",
    "gn:asciiname":"Giro",
    "gn:country_code":"AF",
    "gn:dem":2705,
    "gn:feature_class":"P",
    "gn:feature_code":"PPL",
    "gn:name":"G\u012br\u014d",
    "gn:population":0,
    "gn:timezone":"Asia/Kabul",
    "iso:country":"AF",
    "name:bul_x_preferred":[
        "\u0414\u0436\u0438\u0440\u043e"
    ],
    "name:cat_x_preferred":[
        "Gir bancari"
    ],
    "name:ces_x_preferred":[
        "\u017diro"
    ],
    "name:deu_x_preferred":[
        "\u00dcberweisung"
    ],
    "name:fin_x_preferred":[
        "Tilisiirto"
    ],
    "name:ind_x_preferred":[
        "Giro"
    ],
    "name:jpn_x_preferred":[
        "\u90f5\u4fbf\u632f\u66ff"
    ],
    "name:nld_x_preferred":[
        "Overschrijving"
    ],
    "name:nno_x_preferred":[
        "Giro"
    ],
    "name:nor_x_preferred":[
        "Giro"
    ],
    "name:rus_x_preferred":[
        "\u0420\u0430\u0441\u0447\u0451\u0442\u043d\u044b\u0439 \u0441\u0447\u0451\u0442"
    ],
    "name:spa_x_preferred":[
        "Giro bancario"
    ],
    "name:srp_x_preferred":[
        "\u0414\u0438\u0440\u0435\u043a\u0442\u043d\u0438 \u0434\u0435\u043f\u043e\u0437\u0438\u0442"
    ],
    "name:swe_x_preferred":[
        "Giro"
    ],
    "name:ukr_x_preferred":[
        "\u041f\u043b\u0430\u0442\u0456\u0436\u043d\u0435 \u0434\u043e\u0440\u0443\u0447\u0435\u043d\u043d\u044f"
    ],
    "name:und_x_variant":[
        "G\u012br\u014d",
        "\u06af\u06cc\u0631\u0648",
        "Gi\u1e5fu"
    ],
    "wof:name":"Giro",
    "wof:placetype":"locality"
},
  "geometry": {"coordinates":[67.34433,33.34336],"type":"Point"}
}