{
  "type": "Feature",
  "properties": {
    "gn:admin1_code":"18",
    "gn:admin2_code":"805.0",
    "gn:asciiname":"'Araban",
    "gn:country_code":"AF",
    "gn:dem":1151,
    "gn:feature_class":"P",
    "gn:feature_code":"PPL",
    "gn:name":"\u2018Arab\u0101n",
    "gn:population":0,
    "gn:timezone":"Asia/Kabul",
    "iso:country":"AF",
    "name:und_x_variant":[
        "Araban",
        "\u2018Arab\u0101n",
        "\u0639\u0631\u0628\u0627\u0646"
    ],
    "wof:name":"'Araban",
    "wof:placetype":"locality"
},
  "geometry": {"coordinates":[70.09085,34.29086],"type":"Point"}
}