{
  "type": "Feature",
  "properties": {
    "gn:admin1_code":"09",
    "gn:admin2_code":"2709",
    "gn:asciiname":"Garayamdad",
    "gn:country_code":"AF",
    "gn:dem":2566,
    "gn:feature_class":"P",
    "gn:feature_code":"PPL",
    "gn:name":"Garayamd\u0101d",
    "gn:population":0,
    "gn:timezone":"Asia/Kabul",
    "iso:country":"AF",
    "name:und_x_variant":[
        "Garayamd\u0101d",
        "\u06af\u0631\u06cc\u0645\u062f\u0627\u062f",
        "Garah-ye Madad",
        "\u06af\u0631\u0647 \u0645\u062f\u062f"
    ],
    "wof:name":"Garayamdad",
    "wof:placetype":"locality"
},
  "geometry": {"coordinates":[65.66905,34.44387],"type":"Point"}
}