{
  "type": "Feature",
  "properties": {
    "gn:admin1_code":"37",
    "gn:admin2_code":"3206.0",
    "gn:asciiname":"'Ali Wat",
    "gn:country_code":"AF",
    "gn:dem":1256,
    "gn:feature_class":"P",
    "gn:feature_code":"PPL",
    "gn:name":"\u2018Al\u012b W\u0101t",
    "gn:population":0,
    "gn:timezone":"Asia/Kabul",
    "iso:country":"AF",
    "name:fas_x_preferred":[
        "\u0639\u0644\u06cc \u0648\u0627\u062a"
    ],
    "name:und_x_variant":[
        "Alivat",
        "\u2018Al\u012b Wat",
        "Al\u012bw\u0101t",
        "\u2018Al\u012b W\u0101t"
    ],
    "wof:name":"'Ali Wat",
    "wof:placetype":"locality"
},
  "geometry": {"coordinates":[69.82091,33.31683],"type":"Point"}
}