{
  "type": "Feature",
  "properties": {
    "gn:admin1_code":"29",
    "gn:admin2_code":"2908.0",
    "gn:asciiname":"Gharayzai",
    "gn:country_code":"AF",
    "gn:dem":2528,
    "gn:feature_class":"P",
    "gn:feature_code":"PPL",
    "gn:name":"Ghar\u0101yza\u012b",
    "gn:population":0,
    "gn:timezone":"Asia/Kabul",
    "iso:country":"AF",
    "wof:name":"Gharayzai",
    "wof:placetype":"locality"
},
  "geometry": {"coordinates":[69.0947,32.74048],"type":"Point"}
}