{
  "type": "Feature",
  "properties": {
    "gn:admin1_code":"39",
    "gn:admin2_code":"2602.0",
    "gn:asciiname":"Gosha",
    "gn:country_code":"AF",
    "gn:dem":1603,
    "gn:feature_class":"P",
    "gn:feature_code":"PPL",
    "gn:name":"Gosha",
    "gn:population":0,
    "gn:timezone":"Asia/Kabul",
    "iso:country":"AF",
    "name:fas_x_preferred":[
        "\u06af\u0648\u062e\u0647"
    ],
    "name:und_x_variant":[
        "Go\u0161a",
        "G\u014ds\u0332h\u0332ah",
        "\u06af\u0648\u069a\u0647",
        "G\u016bs\u0332h\u0332ah"
    ],
    "wof:name":"Gosha",
    "wof:placetype":"locality"
},
  "geometry": {"coordinates":[66.13542,32.73138],"type":"Point"}
}