{
  "type": "Feature",
  "properties": {
    "gn:admin1_code":"34",
    "gn:admin2_code":"1014.0",
    "gn:asciiname":"Kolawul",
    "gn:country_code":"AF",
    "gn:dem":926,
    "gn:feature_class":"P",
    "gn:feature_code":"PPL",
    "gn:name":"K\u014dl\u0101wul",
    "gn:population":0,
    "gn:timezone":"Asia/Kabul",
    "iso:country":"AF",
    "name:rus_x_preferred":[
        "Kulavul\u2019"
    ],
    "name:und_x_variant":[
        "K\u014dl\u0101wul",
        "Kowl\u0101wul",
        "\u06a9\u0648\u0644\u0627\u0648\u0644"
    ],
    "wof:name":"Kolawul",
    "wof:placetype":"locality"
},
  "geometry": {"coordinates":[70.87408000000001,34.59222],"type":"Point"}
}