{
  "type": "Feature",
  "properties": {
    "gn:admin1_code":"28",
    "gn:admin2_code":"2502",
    "gn:asciiname":"Kuchnay Khakah",
    "gn:country_code":"AF",
    "gn:dem":1892,
    "gn:feature_class":"P",
    "gn:feature_code":"PPL",
    "gn:name":"Kuchnay Kh\u0101kah",
    "gn:population":0,
    "gn:timezone":"Asia/Kabul",
    "iso:country":"AF",
    "name:fas_x_preferred":[
        "\u0643\u0686\u0646\u06cc \u062e\u0627\u0643\u0647"
    ],
    "name:und_x_variant":[
        "Kuchnay-Khaka",
        "Ku\u010dnay Kh\u0101ka",
        "Kochnay Kh\u0101keh",
        "Kuchnay Kh\u0101kah",
        "\u06a9\u0686\u0646\u06cc \u062e\u0627\u06a9\u0647",
        "\u0643\u0686\u0646\u06cc \u062e\u0627\u0643\u0647"
    ],
    "wof:name":"Kuchnay Khakah",
    "wof:placetype":"locality"
},
  "geometry": {"coordinates":[67.38249999999999,32.36472],"type":"Point"}
}