{
  "type": "Feature",
  "properties": {
    "gn:admin1_code":"05",
    "gn:admin2_code":"2806",
    "gn:asciiname":"Takht",
    "gn:country_code":"AF",
    "gn:dem":3033,
    "gn:feature_class":"P",
    "gn:feature_code":"PPL",
    "gn:name":"Takht",
    "gn:population":0,
    "gn:timezone":"Asia/Kabul",
    "iso:country":"AF",
    "name:und_x_variant":[
        "\u062a\u062e\u062a"
    ],
    "wof:name":"Takht",
    "wof:placetype":"locality"
},
  "geometry": {"coordinates":[66.92775999999999,34.08081],"type":"Point"}
}