{
  "type": "Feature",
  "properties": {
    "gn:admin1_code":"27",
    "gn:admin2_code":"407",
    "gn:asciiname":"Top",
    "gn:country_code":"AF",
    "gn:dem":2225,
    "gn:feature_class":"P",
    "gn:feature_code":"PPL",
    "gn:name":"T\u014dp",
    "gn:population":0,
    "gn:timezone":"Asia/Kabul",
    "iso:country":"AF",
    "name:und_x_variant":[
        "K\u016bt-e Khv\u0101jeh Dasht-e T\u016bp",
        "Topkalay",
        "Khv\u0101jeh T\u016bp",
        "Towp",
        "Khw\u0101jah T\u016bp",
        "T\u014dp",
        "T\u016bp",
        "\u062a\u0648\u067e"
    ],
    "wof:name":"Top",
    "wof:placetype":"locality"
},
  "geometry": {"coordinates":[68.79003,34.16198],"type":"Point"}
}