{
  "type": "Feature",
  "properties": {
    "gn:admin1_code":"10",
    "gn:admin2_code":"2311",
    "gn:asciiname":"Muhammad Anwar Khan Kelay",
    "gn:country_code":"AF",
    "gn:dem":663,
    "gn:feature_class":"P",
    "gn:feature_code":"PPL",
    "gn:name":"Mu\u1e29ammad Anwar Kh\u0101n K\u00ealay",
    "gn:population":0,
    "gn:timezone":"Asia/Kabul",
    "iso:country":"AF",
    "name:und_x_variant":[
        "Mohamma\u1e0f Anwa\u1e5f Kh\u0101n Kalay",
        "Mu\u1e29ammad Anwar Kh\u0101n K\u00ealay",
        "\u0645\u062d\u0645\u062f \u0627\u0646\u0648\u0631 \u062e\u0627\u0646 \u06a9\u0644\u06cc",
        "Mo\u1e29ammad Anvar Kh\u0101n Kalay"
    ],
    "wof:name":"Muhammad Anwar Khan Kelay",
    "wof:placetype":"locality"
},
  "geometry": {"coordinates":[64.07093,30.68772],"type":"Point"}
}