{
  "type": "Feature",
  "properties": {
    "gn:admin1_code":"38",
    "gn:admin2_code":"3001.0",
    "gn:asciiname":"Ishtiwi",
    "gn:country_code":"AF",
    "gn:dem":2841,
    "gn:feature_class":"P",
    "gn:feature_code":"PPL",
    "gn:name":"Ishtiw\u012b",
    "gn:population":0,
    "gn:timezone":"Asia/Kabul",
    "iso:country":"AF",
    "name:und_x_variant":[
        "Esht\u0101v\u012b",
        "As\u0304tiway",
        "Shtevgrom",
        "Ishtivi",
        "Eyshtow\u012b",
        "Shatevgr\u0101m",
        "Shtevgrom Ishtawi",
        "E\u0161tiwi",
        "Esht\u012bv\u012b",
        "\u0627\u0634\u062a\u0648\u06cc",
        "Asht\u012bway",
        "Ishtiw\u012b"
    ],
    "wof:name":"Ishtiwi",
    "wof:placetype":"locality"
},
  "geometry": {"coordinates":[70.938,35.45630999999999],"type":"Point"}
}