{
  "type": "Feature",
  "properties": {
    "gn:admin1_code":"40",
    "gn:admin2_code":"305",
    "gn:asciiname":"Pa'in Deh",
    "gn:country_code":"AF",
    "gn:dem":1937,
    "gn:feature_class":"P",
    "gn:feature_code":"PPL",
    "gn:name":"P\u0101\u2019\u012bn Deh",
    "gn:population":0,
    "gn:timezone":"Asia/Kabul",
    "iso:country":"AF",
    "name:und_x_variant":[
        "Paindekh",
        "P\u0101\u2019\u012bndeh",
        "P\u0101\u2019\u012bn Deh",
        "\u067e\u0627\u0626\u06cc\u0646 \u062f\u0647"
    ],
    "wof:name":"Pa'in Deh",
    "wof:placetype":"locality"
},
  "geometry": {"coordinates":[68.87682,34.98385],"type":"Point"}
}