{
  "type": "Feature",
  "properties": {
    "gn:country":"AF",
    "gn:fcode":"HLL",
    "gn:pop":1450,
    "iso:country":"AF",
    "name:fas_x_preferred":[
        "\u0643\u0648\u0647\u0654\u0654 \u0627\u0645\u0628\u0631\u06af\u06cc"
    ],
    "name:unk_x_variant":[
        "Gora Ambargaygar"
    ],
    "qs:name":"Ambargay Ghar",
    "qs:photos_9r":0,
    "qs:photos_sr":0,
    "qs:pop_sr":"3",
    "wof:name":"Ambargay Ghar",
    "wof:placetype":"locality",
    "wof:population":1450
},
  "geometry": {"coordinates":[65.89095,31.99053],"type":"Point"}
}