{
  "type": "Feature",
  "properties": {
    "gn:admin1_code":"11",
    "gn:admin2_code":"2011",
    "gn:asciiname":"Sipalghand",
    "gn:country_code":"AF",
    "gn:dem":1788,
    "gn:feature_class":"P",
    "gn:feature_code":"PPL",
    "gn:name":"Sipalghand",
    "gn:population":0,
    "gn:timezone":"Asia/Kabul",
    "iso:country":"AF",
    "name:und_x_variant":[
        "\u0633\u067e\u0644\u063a\u0646\u062f",
        "Sepalghan\u1e0f"
    ],
    "wof:name":"Sipalghand",
    "wof:placetype":"locality"
},
  "geometry": {"coordinates":[62.78154,33.57181],"type":"Point"}
}