{
  "type": "Feature",
  "properties": {
    "gn:admin1_code":"34",
    "gn:admin2_code":"1015",
    "gn:asciiname":"Nawah",
    "gn:country_code":"AF",
    "gn:dem":1255,
    "gn:feature_class":"P",
    "gn:feature_code":"PPL",
    "gn:name":"N\u0101wah",
    "gn:population":0,
    "gn:timezone":"Asia/Kabul",
    "iso:country":"AF",
    "name:fas_x_preferred":[
        "\u0646\u0627\u0648\u0647"
    ],
    "name:und_x_variant":[
        "N\u0101wa",
        "Nava",
        "N\u0101wah",
        "N\u0101veh"
    ],
    "wof:name":"Nawah",
    "wof:placetype":"locality"
},
  "geometry": {"coordinates":[71.15446,34.74406],"type":"Point"}
}