{
  "type": "Feature",
  "properties": {
    "gn:admin1_code":"14",
    "gn:admin2_code":"203.0",
    "gn:asciiname":"Chap Darah",
    "gn:country_code":"AF",
    "gn:dem":2168,
    "gn:feature_class":"P",
    "gn:feature_code":"PPL",
    "gn:name":"Chap Darah",
    "gn:population":0,
    "gn:timezone":"Asia/Kabul",
    "iso:country":"AF",
    "name:und_x_variant":[
        "\u010capdara",
        "Chapdarreh",
        "Chap Darah",
        "\u0686\u067e \u062f\u0631\u0647",
        "Chapdara"
    ],
    "wof:name":"Chap Darah",
    "wof:placetype":"locality"
},
  "geometry": {"coordinates":[69.45905,35.13071],"type":"Point"}
}