{
  "type": "Feature",
  "properties": {
    "gn:admin1_code":"5",
    "gn:admin2_code":"2805.0",
    "gn:asciiname":"Now Baltarqan",
    "gn:country_code":"AF",
    "gn:dem":3197,
    "gn:feature_class":"P",
    "gn:feature_code":"PPL",
    "gn:name":"Now Baltarq\u0101n",
    "gn:population":0,
    "gn:timezone":"Asia/Kabul",
    "iso:country":"AF",
    "name:rus_x_preferred":[
        "Naubal\u2019tarkan"
    ],
    "name:und_x_variant":[
        "Now Baldargh\u0101n",
        "Nawbaltarq\u0101n",
        "Now Baltarq\u0101n",
        "\u0646\u0648 \u0628\u0644\u062a\u0631\u0642\u0627\u0646"
    ],
    "wof:name":"Now Baltarqan",
    "wof:placetype":"locality"
},
  "geometry": {"coordinates":[66.74902,34.44637],"type":"Point"}
}