{
  "type": "Feature",
  "properties": {
    "gn:admin1_code":"29",
    "gn:admin2_code":"2918",
    "gn:asciiname":"Mindzo Kala",
    "gn:country_code":"AF",
    "gn:dem":2141,
    "gn:feature_class":"P",
    "gn:feature_code":"PPL",
    "gn:name":"Mindz\u014d Kal\u0101",
    "gn:population":0,
    "gn:timezone":"Asia/Kabul",
    "iso:country":"AF",
    "name:und_x_variant":[
        "Mindzhukala",
        "\u0645\u0646\u0681\u0648 \u06a9\u0644\u0627",
        "Menjo Kal\u0101",
        "Mindz\u014d Kal\u0101"
    ],
    "wof:name":"Mindzo Kala",
    "wof:placetype":"locality"
},
  "geometry": {"coordinates":[68.63200000000001,32.97305],"type":"Point"}
}