{
  "type": "Feature",
  "properties": {
    "gn:admin1_code":"09",
    "gn:admin2_code":"2701",
    "gn:asciiname":"Qafak-e Bala",
    "gn:country_code":"AF",
    "gn:dem":2633,
    "gn:feature_class":"P",
    "gn:feature_code":"PPL",
    "gn:name":"Qafak-e B\u0101l\u0101",
    "gn:population":0,
    "gn:timezone":"Asia/Kabul",
    "iso:country":"AF",
    "name:und_x_variant":[
        "Kafaki-Bala",
        "Qafak-e B\u0101l\u0101",
        "\u0642\u0641\u06a9 \u0628\u0627\u0644\u0627",
        "Q\u0101fak-e B\u0101l\u0101"
    ],
    "wof:name":"Qafak-e Bala",
    "wof:placetype":"locality"
},
  "geometry": {"coordinates":[65.63013000000001,34.17158],"type":"Point"}
}