{
  "type": "Feature",
  "properties": {
    "gn:admin1_code":"10",
    "gn:admin2_code":"2305",
    "gn:asciiname":"Pay Sang",
    "gn:country_code":"AF",
    "gn:dem":1396,
    "gn:feature_class":"P",
    "gn:feature_code":"PPL",
    "gn:name":"P\u0101y Sang",
    "gn:population":0,
    "gn:timezone":"Asia/Kabul",
    "iso:country":"AF",
    "name:und_x_variant":[
        "P\u0101y Sang",
        "\u067e\u0627\u06cc \u0633\u0646\u06af",
        "Paysang"
    ],
    "wof:name":"Pay Sang",
    "wof:placetype":"locality"
},
  "geometry": {"coordinates":[64.93485,32.99835],"type":"Point"}
}