{
  "type": "Feature",
  "properties": {
    "gn:admin1_code":"28",
    "gn:admin2_code":"2502.0",
    "gn:asciiname":"'Ashiqi Kelay",
    "gn:country_code":"AF",
    "gn:dem":1838,
    "gn:feature_class":"P",
    "gn:feature_code":"PPL",
    "gn:name":"\u2018\u0100shiq\u012b K\u00ealay",
    "gn:population":0,
    "gn:timezone":"Asia/Kabul",
    "iso:country":"AF",
    "name:fas_x_preferred":[
        "\u0642\u0631\u064a\u06c0 \u0639\u0627\u0634\u0642\u06cc"
    ],
    "name:und_x_variant":[
        "Ashikikalay",
        "\u0100\u0161eqi Kalay",
        "\u2018\u0100shiq\u012b K\u00ealay",
        "\u0639\u0627\u0634\u0642\u06cc \u06a9\u0644\u06cc",
        "\u2018\u0100sheq\u012b Kalay"
    ],
    "wof:name":"'Ashiqi Kelay",
    "wof:placetype":"locality"
},
  "geometry": {"coordinates":[67.30206,32.44203],"type":"Point"}
}