{
  "type": "Feature",
  "properties": {
    "gn:admin1_code":"08",
    "gn:admin2_code":"613",
    "gn:asciiname":"Kuhnah Deh",
    "gn:country_code":"AF",
    "gn:dem":2234,
    "gn:feature_class":"P",
    "gn:feature_code":"PPL",
    "gn:name":"Kuhnah Deh",
    "gn:population":0,
    "gn:timezone":"Asia/Kabul",
    "iso:country":"AF",
    "name:fas_x_preferred":[
        "\u0643\u0647\u0646\u0647 \u062f\u0647"
    ],
    "name:und_x_variant":[
        "Kuhna \u1e0eeh",
        "Kukhna-Dekh",
        "Kuhnah Deh",
        "Kohneh Deh"
    ],
    "wof:name":"Kuhnah Deh",
    "wof:placetype":"locality"
},
  "geometry": {"coordinates":[68.04321999999999,33.27737],"type":"Point"}
}