{
  "type": "Feature",
  "properties": {
    "gn:admin1_code":"13",
    "gn:admin2_code":"110.0",
    "gn:asciiname":"Qal'ah-ye Sher 'Alam",
    "gn:country_code":"AF",
    "gn:dem":1793,
    "gn:feature_class":"P",
    "gn:feature_code":"PPL",
    "gn:name":"Qal\u2018ah-ye Sh\u0113r \u2018Alam",
    "gn:population":0,
    "gn:timezone":"Asia/Kabul",
    "iso:country":"AF",
    "name:und_x_variant":[
        "Qal\u2018ah-ye Sh\u0113r \u2018Alam",
        "\u0642\u0644\u0639\u0647 \u0634\u06cc\u0631 \u0639\u0644\u0645",
        "Qal\u2018ah-ye Shayr \u2018Alam"
    ],
    "wof:name":"Qal'ah-ye Sher 'Alam",
    "wof:placetype":"locality"
},
  "geometry": {"coordinates":[69.24953000000001,34.48847],"type":"Point"}
}