{
  "type": "Feature",
  "properties": {
    "gn:admin1_code":"05",
    "gn:admin2_code":"2805",
    "gn:asciiname":"Kalan Deh",
    "gn:country_code":"AF",
    "gn:dem":2895,
    "gn:feature_class":"P",
    "gn:feature_code":"PPL",
    "gn:name":"Kal\u0101n Deh",
    "gn:population":0,
    "gn:timezone":"Asia/Kabul",
    "iso:country":"AF",
    "name:und_x_variant":[
        "Kalandekh",
        "Kal\u0101ndeh",
        "Kal\u0101n Deh",
        "\u06a9\u0644\u0627\u0646 \u062f\u0647"
    ],
    "wof:name":"Kalan Deh",
    "wof:placetype":"locality"
},
  "geometry": {"coordinates":[67.1016,34.36562],"type":"Point"}
}