{
  "type": "Feature",
  "properties": {
    "gn:admin1_code":"02",
    "gn:admin2_code":"1904",
    "gn:asciiname":"Yakamrowak",
    "gn:country_code":"AF",
    "gn:dem":2031,
    "gn:feature_class":"P",
    "gn:feature_code":"PPL",
    "gn:name":"Yakamrowak",
    "gn:population":0,
    "gn:timezone":"Asia/Kabul",
    "iso:country":"AF",
    "name:und_x_variant":[
        "\u064a\u06a9\u0645\u0631\u0648\u06a9",
        "Yakamrowak",
        "Yakam\u1e5fowak"
    ],
    "wof:name":"Yakamrowak",
    "wof:placetype":"locality"
},
  "geometry": {"coordinates":[64.16459999999999,35.15147],"type":"Point"}
}