{
  "type": "Feature",
  "properties": {
    "gn:admin1_code":"31",
    "gn:admin2_code":"1701",
    "gn:asciiname":"Kowdee",
    "gn:country_code":"AF",
    "gn:dem":413,
    "gn:feature_class":"P",
    "gn:feature_code":"PPL",
    "gn:name":"Kowdee",
    "gn:population":0,
    "gn:timezone":"Asia/Kabul",
    "iso:country":"AF",
    "name:und_x_variant":[
        "K\u014dd\u012b",
        "\u06a9\u0648\u062f\u06cc"
    ],
    "wof:name":"Kowdee",
    "wof:placetype":"locality"
},
  "geometry": {"coordinates":[65.8087,36.51912],"type":"Point"}
}