{
  "type": "Feature",
  "properties": {
    "gn:admin1_code":"41",
    "gn:admin2_code":"3408",
    "gn:asciiname":"Ayl-e Ghulam",
    "gn:country_code":"AF",
    "gn:dem":2575,
    "gn:feature_class":"P",
    "gn:feature_code":"PPL",
    "gn:name":"Ayl-e Ghul\u0101m",
    "gn:population":0,
    "gn:timezone":"Asia/Kabul",
    "iso:country":"AF",
    "name:und_x_variant":[
        "\u0112le Ghol\u0101m",
        "Eli-Gulyam",
        "\u0112l-e Ghul\u0101m",
        "\u0112l\u012b Ghol\u0101m",
        "Ayl-e Ghul\u0101m",
        "\u0627\u064a\u0644 \u063a\u0644\u0627\u0645"
    ],
    "wof:name":"Ayl-e Ghulam",
    "wof:placetype":"locality"
},
  "geometry": {"coordinates":[66.25794,34.24175],"type":"Point"}
}