{
  "type": "Feature",
  "properties": {
    "gn:admin1_code":"7",
    "gn:admin2_code":"1802.0",
    "gn:asciiname":"Pashah Khan",
    "gn:country_code":"AF",
    "gn:dem":1050,
    "gn:feature_class":"P",
    "gn:feature_code":"PPL",
    "gn:name":"Pashah Kh\u0101n",
    "gn:population":0,
    "gn:timezone":"Asia/Kabul",
    "iso:country":"AF",
    "name:und_x_variant":[
        "Pasa Kh\u0101n",
        "P\u0101sh\u0101 Kh\u0101n",
        "Pashah Kh\u0101n",
        "\u067e\u0634\u0647 \u062e\u0627\u0646"
    ],
    "wof:name":"Pashah Khan",
    "wof:placetype":"locality"
},
  "geometry": {"coordinates":[64.77969,35.85102],"type":"Point"}
}