{
  "type": "Feature",
  "properties": {
    "gn:admin1_code":"6",
    "gn:admin2_code":"2107.0",
    "gn:asciiname":"Dalghah",
    "gn:country_code":"AF",
    "gn:dem":806,
    "gn:feature_class":"P",
    "gn:feature_code":"PPL",
    "gn:name":"D\u0101lghah",
    "gn:population":0,
    "gn:timezone":"Asia/Kabul",
    "iso:country":"AF",
    "name:fas_x_preferred":[
        "D\u0101lghah"
    ],
    "name:fas_x_variant":[
        "\u062f\u0627\u0644\u063a\u0647"
    ],
    "name:und_x_variant":[
        "\u1e0e\u0101lgha",
        "D\u0101lghah",
        "\u062f\u0627\u0644\u063a\u0647"
    ],
    "wof:name":"Dalghah",
    "wof:placetype":"locality"
},
  "geometry": {"coordinates":[61.60666,32.80563],"type":"Point"}
}