{
  "type": "Feature",
  "properties": {
    "gn:admin1_code":"10",
    "gn:admin2_code":"2312.0",
    "gn:asciiname":"Qina'at Surat",
    "gn:country_code":"AF",
    "gn:dem":983,
    "gn:feature_class":"P",
    "gn:feature_code":"PPL",
    "gn:name":"Qin\u0101\u2018at \u015e\u016brat",
    "gn:population":0,
    "gn:timezone":"Asia/Kabul",
    "iso:country":"AF",
    "name:und_x_variant":[
        "Kinaatsurat",
        "Qen\u0101\u2018at \u015e\u016b\u1e5fat",
        "Qin\u0101\u2018at \u015e\u016brat",
        "\u0642\u0646\u0627\u0639\u062a \u0635\u0648\u0631\u062a",
        "Qan\u0101\u2018at \u015e\u016brat"
    ],
    "wof:name":"Qina'at Surat",
    "wof:placetype":"locality"
},
  "geometry": {"coordinates":[65.02785,32.183],"type":"Point"}
}