{
  "type": "Feature",
  "properties": {
    "gn:admin1_code":"23",
    "gn:admin2_code":"2412",
    "gn:asciiname":"Terghak",
    "gn:country_code":"AF",
    "gn:dem":1369,
    "gn:feature_class":"P",
    "gn:feature_code":"PPL",
    "gn:name":"T\u00earghak",
    "gn:population":0,
    "gn:timezone":"Asia/Kabul",
    "iso:country":"AF",
    "name:und_x_variant":[
        "Tirgak",
        "T\u00earghak",
        "\u062a\u0631\u063a\u06a9",
        "T\u0113\u1e5fghak"
    ],
    "wof:name":"Terghak",
    "wof:placetype":"locality"
},
  "geometry": {"coordinates":[66.44511999999999,31.33142],"type":"Point"}
}