{
  "type": "Feature",
  "properties": {
    "gn:admin1_code":"27",
    "gn:admin2_code":"407",
    "gn:asciiname":"Yami Khel",
    "gn:country_code":"AF",
    "gn:dem":2464,
    "gn:feature_class":"P",
    "gn:feature_code":"PPL",
    "gn:name":"Y\u0101m\u012b Kh\u0113l",
    "gn:population":0,
    "gn:timezone":"Asia/Kabul",
    "iso:country":"AF",
    "name:rus_x_preferred":[
        "Yamikheyl\u2019"
    ],
    "name:und_x_variant":[
        "Y\u0101mikh\u0113l",
        "Y\u0101m\u012b Kh\u0113l",
        "Y\u0101m\u012b Kheyl",
        "\u064a\u0627\u0645\u06cc \u062e\u06d0\u0644"
    ],
    "wof:name":"Yami Khel",
    "wof:placetype":"locality"
},
  "geometry": {"coordinates":[68.60784,33.97150999999999],"type":"Point"}
}