{
  "type": "Feature",
  "properties": {
    "gn:admin1_code":"8",
    "gn:admin2_code":"610.0",
    "gn:asciiname":"Salih Gul",
    "gn:country_code":"AF",
    "gn:dem":2041,
    "gn:feature_class":"P",
    "gn:feature_code":"PPL",
    "gn:name":"\u015e\u0101li\u1e29 Gul",
    "gn:population":0,
    "gn:timezone":"Asia/Kabul",
    "iso:country":"AF",
    "name:rus_x_preferred":[
        "Salekhgul\u2019"
    ],
    "name:und_x_variant":[
        "S\u0101le\u1e96gul",
        "\u015e\u0101li\u1e29 Gul",
        "\u0635\u0627\u0644\u062d \u06af\u0644",
        "\u015e\u0101le\u1e29gol"
    ],
    "wof:name":"Salih Gul",
    "wof:placetype":"locality"
},
  "geometry": {"coordinates":[67.91429000000001,32.30811],"type":"Point"}
}