{
  "type": "Feature",
  "properties": {
    "gn:admin1_code":"23",
    "gn:admin2_code":"2413.0",
    "gn:asciiname":"Zharah Ghbargah",
    "gn:country_code":"AF",
    "gn:dem":2156,
    "gn:feature_class":"P",
    "gn:feature_code":"PPL",
    "gn:name":"Zha\u1e5fah Ghbargah",
    "gn:population":0,
    "gn:timezone":"Asia/Kabul",
    "iso:country":"AF",
    "name:und_x_variant":[
        "Zara Ghba\u1e5fga",
        "Zharagbarga",
        "Zha\u1e5fah Ghbargah",
        "Zharah Ghba\u1e5fgah",
        "\u0698\u0693\u0647 \u063a\u0628\u0631\u06af\u0647"
    ],
    "wof:name":"Zharah Ghbargah",
    "wof:placetype":"locality"
},
  "geometry": {"coordinates":[67.36605,31.2884],"type":"Point"}
}