{
  "type": "Feature",
  "properties": {
    "gn:admin1_code":"23",
    "gn:admin2_code":"2413.0",
    "gn:asciiname":"Angizay",
    "gn:country_code":"AF",
    "gn:dem":1890,
    "gn:feature_class":"P",
    "gn:feature_code":"PPL",
    "gn:name":"Ang\u012bzay",
    "gn:population":0,
    "gn:timezone":"Asia/Kabul",
    "iso:country":"AF",
    "name:und_x_variant":[
        "Angizi",
        "Ang\u012bza\u012b",
        "Ang\u012bzay",
        "\u0627\u0646\u06af\u06cc\u0632\u06cc",
        "Angizay",
        "\u0627\u0646\u06af\u0632\u06cc"
    ],
    "wof:name":"Angizay",
    "wof:placetype":"locality"
},
  "geometry": {"coordinates":[67.2363,31.37817],"type":"Point"}
}