{
  "type": "Feature",
  "properties": {
    "gn:admin1_code":"5",
    "gn:admin2_code":"2804.0",
    "gn:asciiname":"Bedak",
    "gn:country_code":"AF",
    "gn:dem":3404,
    "gn:feature_class":"P",
    "gn:feature_code":"PPL",
    "gn:name":"Bedak",
    "gn:population":0,
    "gn:timezone":"Asia/Kabul",
    "iso:country":"AF",
    "name:rus_x_preferred":[
        "\u0411\u0435\u0434\u0430\u043a"
    ],
    "name:und_x_variant":[
        "B\u0113\u1e0fak",
        "B\u012bdak"
    ],
    "wof:name":"Bedak",
    "wof:placetype":"locality"
},
  "geometry": {"coordinates":[67.20999999999999,34.64],"type":"Point"}
}