{
  "type": "Feature",
  "properties": {
    "gn:admin1_code":"39",
    "gn:admin2_code":"2603",
    "gn:asciiname":"Qaryah-ye Gird",
    "gn:country_code":"AF",
    "gn:dem":3267,
    "gn:feature_class":"P",
    "gn:feature_code":"PPL",
    "gn:name":"Qaryah-ye Gird",
    "gn:population":0,
    "gn:timezone":"Asia/Kabul",
    "iso:country":"AF",
    "name:fas_x_preferred":[
        "\u0642\u0631\u064a\u06c0 \u06af\u0631\u062f"
    ],
    "name:rus_x_preferred":[
        "Kar\u2019yayi-Gird"
    ],
    "name:und_x_variant":[
        "Qa\u1e5fya-i-Ge\u1e5f\u1e0f",
        "Qaryah-ye Gird",
        "\u0642\u0631\u06cc\u0647 \u06af\u0631\u062f",
        "Qaryeh-ye Gerd"
    ],
    "wof:name":"Qaryah-ye Gird",
    "wof:placetype":"locality"
},
  "geometry": {"coordinates":[66.84347,32.86275],"type":"Point"}
}