{
  "type": "Feature",
  "properties": {
    "gn:admin1_code":"40",
    "gn:admin2_code":"307",
    "gn:asciiname":"Faqirak",
    "gn:country_code":"AF",
    "gn:dem":2871,
    "gn:feature_class":"P",
    "gn:feature_code":"PPL",
    "gn:name":"Faq\u012brak",
    "gn:population":0,
    "gn:timezone":"Asia/Kabul",
    "iso:country":"AF",
    "name:und_x_variant":[
        "Fakirak",
        "Faq\u012brak",
        "\u0641\u0642\u064a\u0631\u06a9"
    ],
    "wof:name":"Faqirak",
    "wof:placetype":"locality"
},
  "geometry": {"coordinates":[68.41490999999999,34.76325],"type":"Point"}
}