{
  "type": "Feature",
  "properties": {
    "gn:admin1_code":"08",
    "gn:admin2_code":"607.0",
    "gn:asciiname":"Siyah Butah",
    "gn:country_code":"AF",
    "gn:dem":2429,
    "gn:feature_class":"P",
    "gn:feature_code":"PPL",
    "gn:name":"Siy\u0101h Butah",
    "gn:population":0,
    "gn:timezone":"Asia/Kabul",
    "iso:country":"AF",
    "name:und_x_variant":[
        "S\u012b\u0101h Butah",
        "\u0633\u06cc\u0627\u0647 \u0628\u062a\u0647",
        "Siy\u0101h Butah"
    ],
    "wof:name":"Siyah Butah",
    "wof:placetype":"locality"
},
  "geometry": {"coordinates":[67.42954,33.12296],"type":"Point"}
}