{
  "type": "Feature",
  "properties": {
    "gn:admin1_code":"29",
    "gn:admin2_code":"2916",
    "gn:asciiname":"Nasu Khel",
    "gn:country_code":"AF",
    "gn:dem":2039,
    "gn:feature_class":"P",
    "gn:feature_code":"PPL",
    "gn:name":"Nas\u016b Kh\u0113l",
    "gn:population":0,
    "gn:timezone":"Asia/Kabul",
    "iso:country":"AF",
    "name:und_x_variant":[
        "Nas\u016b Kheyl",
        "\u0646\u0633\u0648 \u062e\u06d0\u0644",
        "Nasow Kheyl",
        "Nas\u016b Kh\u0113l"
    ],
    "wof:name":"Nasu Khel",
    "wof:placetype":"locality"
},
  "geometry": {"coordinates":[68.36475,32.65959],"type":"Point"}
}