{
  "type": "Feature",
  "properties": {
    "gn:admin1_code":"26",
    "gn:admin2_code":"1204.0",
    "gn:asciiname":"Mandakan",
    "gn:country_code":"AF",
    "gn:dem":1767,
    "gn:feature_class":"P",
    "gn:feature_code":"PPL",
    "gn:name":"M\u0101ndak\u0101n",
    "gn:population":0,
    "gn:timezone":"Asia/Kabul",
    "iso:country":"AF",
    "name:ceb_x_preferred":[
        "Mandeg\u0101n"
    ],
    "name:fas_x_preferred":[
        "\u0645\u0646\u062f\u06a9\u0627\u0646"
    ],
    "name:swe_x_preferred":[
        "Mandeg\u0101n"
    ],
    "name:und_x_variant":[
        "M\u0101ndak\u0101n",
        "\u0645\u0627\u0646\u062f\u06a9\u0627\u0646"
    ],
    "wof:name":"Mandakan",
    "wof:placetype":"locality"
},
  "geometry": {"coordinates":[69.60451999999999,36.42755],"type":"Point"}
}