{
  "type": "Feature",
  "properties": {
    "gn:admin1_code":"02",
    "gn:admin2_code":"1903",
    "gn:asciiname":"Piwar",
    "gn:country_code":"AF",
    "gn:dem":966,
    "gn:feature_class":"P",
    "gn:feature_code":"PPL",
    "gn:name":"P\u012bw\u0101r",
    "gn:population":0,
    "gn:timezone":"Asia/Kabul",
    "iso:country":"AF",
    "name:und_x_variant":[
        "P\u012bw\u0101r",
        "\u067e\u06cc\u0648\u0627\u0631",
        "P\u012bw\u0101\u1e5f"
    ],
    "wof:name":"Piwar",
    "wof:placetype":"locality"
},
  "geometry": {"coordinates":[63.51163,35.04166],"type":"Point"}
}