{
  "type": "Feature",
  "properties": {
    "gn:admin1_code":"14",
    "gn:admin2_code":"206.0",
    "gn:asciiname":"Tangi Khel",
    "gn:country_code":"AF",
    "gn:dem":2038,
    "gn:feature_class":"P",
    "gn:feature_code":"PPL",
    "gn:name":"Tang\u012b Kh\u0113l",
    "gn:population":0,
    "gn:timezone":"Asia/Kabul",
    "iso:country":"AF",
    "name:fas_x_preferred":[
        "\u062a\u0646\u06af\u06cc \u062e\u064a\u0644"
    ],
    "name:rus_x_preferred":[
        "Tangikheyl\u2019"
    ],
    "name:und_x_variant":[
        "Kotalay",
        "K\u016btalay",
        "K\u014dtalay",
        "Tangikh\u0113l",
        "Tang\u012bkheyl",
        "Tang\u012b Kh\u0113l",
        "\u062a\u0646\u06af\u06cc \u062e\u06d0\u0644",
        "\u06a9\u0648\u062a\u0644\u06cc"
    ],
    "wof:name":"Tangi Khel",
    "wof:placetype":"locality"
},
  "geometry": {"coordinates":[69.75929000000001,34.94208],"type":"Point"}
}