{
  "type": "Feature",
  "properties": {
    "gn:admin1_code":"09",
    "gn:admin2_code":"2702",
    "gn:asciiname":"Izhda Khan",
    "gn:country_code":"AF",
    "gn:dem":2478,
    "gn:feature_class":"P",
    "gn:feature_code":"PPL",
    "gn:name":"Izhd\u0101 Kh\u0101n",
    "gn:population":0,
    "gn:timezone":"Asia/Kabul",
    "iso:country":"AF",
    "name:und_x_variant":[
        "Izdakhan",
        "E\u017ed\u0101kh\u0101n",
        "Izhd\u0101 Kh\u0101n",
        "\u0627\u0698\u062f\u0627 \u062e\u0627\u0646",
        "Ezhd\u0101kh\u0101n"
    ],
    "wof:name":"Izhda Khan",
    "wof:placetype":"locality"
},
  "geometry": {"coordinates":[64.43932,33.84018],"type":"Point"}
}