{
  "type": "Feature",
  "properties": {
    "gn:admin1_code":"09",
    "gn:admin2_code":"2710",
    "gn:asciiname":"Puy",
    "gn:country_code":"AF",
    "gn:dem":2277,
    "gn:feature_class":"P",
    "gn:feature_code":"PPL",
    "gn:name":"P\u016by",
    "gn:population":0,
    "gn:timezone":"Asia/Kabul",
    "iso:country":"AF",
    "name:bre_x_preferred":[
        "Puy"
    ],
    "name:deu_x_preferred":[
        "Puy"
    ],
    "name:fra_x_preferred":[
        "Puy"
    ],
    "name:msa_x_preferred":[
        "Puy"
    ],
    "name:spa_x_preferred":[
        "Puy"
    ],
    "name:und_x_variant":[
        "P\u016by",
        "\u067e\u0648\u06cc"
    ],
    "wof:name":"Puy",
    "wof:placetype":"locality"
},
  "geometry": {"coordinates":[64.73506999999999,34.40225],"type":"Point"}
}