{
  "type": "Feature",
  "properties": {
    "gn:admin1_code":"33",
    "gn:admin2_code":"3101.0",
    "gn:asciiname":"Alazgar",
    "gn:country_code":"AF",
    "gn:dem":796,
    "gn:feature_class":"P",
    "gn:feature_code":"PPL",
    "gn:name":"Alazgar",
    "gn:population":0,
    "gn:timezone":"Asia/Kabul",
    "iso:country":"AF",
    "wof:name":"Alazgar",
    "wof:placetype":"locality"
},
  "geometry": {"coordinates":[66.14416999999999,36.29694],"type":"Point"}
}