{
  "type": "Feature",
  "properties": {
    "gn:admin1_code":"18",
    "gn:admin2_code":"818.0",
    "gn:asciiname":"Belah",
    "gn:country_code":"AF",
    "gn:dem":523,
    "gn:feature_class":"P",
    "gn:feature_code":"PPL",
    "gn:name":"B\u0113lah",
    "gn:population":0,
    "gn:timezone":"Asia/Kabul",
    "iso:country":"AF",
    "name:fas_x_preferred":[
        "\u0628\u064a\u0644\u0647"
    ],
    "name:und_x_variant":[
        "Bela",
        "B\u0113la",
        "B\u0113lah",
        "\u0628\u06d0\u0644\u0647"
    ],
    "wof:name":"Belah",
    "wof:placetype":"locality"
},
  "geometry": {"coordinates":[70.59088,34.38907],"type":"Point"}
}