{
  "type": "Feature",
  "properties": {
    "gn:admin1_code":"41",
    "gn:admin2_code":"3406",
    "gn:asciiname":"Shahlizar",
    "gn:country_code":"AF",
    "gn:dem":1868,
    "gn:feature_class":"P",
    "gn:feature_code":"PPL",
    "gn:name":"Sh\u0101hliz\u0101r",
    "gn:population":0,
    "gn:timezone":"Asia/Kabul",
    "iso:country":"AF",
    "name:und_x_variant":[
        "S\u0304\u0101liz\u0101\u1e5f",
        "Sh\u0101hliz\u0101r",
        "\u0634\u0627\u0647\u0644\u0632\u0627\u0631",
        "Sh\u0101l\u012bz\u0101r"
    ],
    "wof:name":"Shahlizar",
    "wof:placetype":"locality"
},
  "geometry": {"coordinates":[65.75205,33.64054],"type":"Point"}
}