{
  "type": "Feature",
  "properties": {
    "gn:admin1_code":"08",
    "gn:admin2_code":"601",
    "gn:asciiname":"Postinduz",
    "gn:country_code":"AF",
    "gn:dem":2272,
    "gn:feature_class":"P",
    "gn:feature_code":"PPL",
    "gn:name":"P\u014dst\u012bnd\u016bz",
    "gn:population":0,
    "gn:timezone":"Asia/Kabul",
    "iso:country":"AF",
    "name:fas_x_preferred":[
        "\u067e\u0648\u0633\u062a\u064a\u0646\u062f\u0648\u0632"
    ],
    "name:und_x_variant":[
        "P\u014dst\u012bn\u1e0f\u014dz",
        "Postindoz",
        "P\u014dst\u012bnd\u016bz",
        "P\u016bst\u012bnd\u016bz"
    ],
    "wof:name":"Postinduz",
    "wof:placetype":"locality"
},
  "geometry": {"coordinates":[68.38266,33.59237],"type":"Point"}
}