{
  "type": "Feature",
  "properties": {
    "gn:admin1_code":"06",
    "gn:admin2_code":"2110",
    "gn:asciiname":"Farib",
    "gn:country_code":"AF",
    "gn:dem":561,
    "gn:feature_class":"P",
    "gn:feature_code":"PPL",
    "gn:name":"Far\u012bb",
    "gn:population":0,
    "gn:timezone":"Asia/Kabul",
    "iso:country":"AF",
    "name:und_x_variant":[
        "Far\u012bb",
        "\u0641\u0631\u06cc\u0628"
    ],
    "wof:name":"Farib",
    "wof:placetype":"locality"
},
  "geometry": {"coordinates":[61.48764,32.13154],"type":"Point"}
}