{
  "type": "Feature",
  "properties": {
    "gn:admin1_code":"10",
    "gn:admin2_code":"2302",
    "gn:asciiname":"Yaklang",
    "gn:country_code":"AF",
    "gn:dem":813,
    "gn:feature_class":"P",
    "gn:feature_code":"PPL",
    "gn:name":"Yaklang",
    "gn:population":0,
    "gn:timezone":"Asia/Kabul",
    "iso:country":"AF",
    "name:und_x_variant":[
        "\u06cc\u06a9\u0644\u0646\u06af",
        "Yaklang"
    ],
    "wof:name":"Yaklang",
    "wof:placetype":"locality"
},
  "geometry": {"coordinates":[64.59033000000001,31.67344000000001],"type":"Point"}
}