{
  "type": "Feature",
  "properties": {
    "gn:admin1_code":"23",
    "gn:admin2_code":"2407.0",
    "gn:asciiname":"Tulak",
    "gn:country_code":"AF",
    "gn:dem":1114,
    "gn:feature_class":"P",
    "gn:feature_code":"PPL",
    "gn:name":"T\u016blak",
    "gn:population":0,
    "gn:timezone":"Asia/Kabul",
    "iso:country":"AF",
    "name:und_x_variant":[
        "Tolak",
        "Tulak",
        "T\u014dlak",
        "T\u016blak",
        "\u062a\u0648\u0644\u06a9"
    ],
    "wof:name":"Tulak",
    "wof:placetype":"locality"
},
  "geometry": {"coordinates":[65.05504999999999,31.79953],"type":"Point"}
}