{
  "type": "Feature",
  "properties": {
    "gn:admin1_code":"11",
    "gn:admin2_code":"2007.0",
    "gn:asciiname":"Hakimabad",
    "gn:country_code":"AF",
    "gn:dem":654,
    "gn:feature_class":"P",
    "gn:feature_code":"PPL",
    "gn:name":"\u1e28\u0101kim\u0101b\u0101d",
    "gn:population":0,
    "gn:timezone":"Asia/Kabul",
    "iso:country":"AF",
    "name:und_x_variant":[
        "H\u0101kem \u0100b\u0101d",
        "\u1e28\u0101kem \u0100b\u0101d",
        "\u1e28\u0101kim\u0101b\u0101d",
        "\u062d\u0627\u06a9\u0645 \u0622\u0628\u0627\u062f"
    ],
    "wof:name":"Hakimabad",
    "wof:placetype":"locality"
},
  "geometry": {"coordinates":[61.93601999999999,35.261],"type":"Point"}
}