{
  "type": "Feature",
  "properties": {
    "gn:admin1_code":"23",
    "gn:admin2_code":"2407",
    "gn:asciiname":"Padah",
    "gn:country_code":"AF",
    "gn:dem":948,
    "gn:feature_class":"P",
    "gn:feature_code":"PPL",
    "gn:name":"Pa\u1e0fah",
    "gn:population":0,
    "gn:timezone":"Asia/Kabul",
    "iso:country":"AF",
    "name:und_x_variant":[
        "Pa\u1e0fah",
        "\u067e\u0689\u0647",
        "Padeh",
        "Pada"
    ],
    "wof:name":"Padah",
    "wof:placetype":"locality"
},
  "geometry": {"coordinates":[64.8578,31.8655],"type":"Point"}
}