{
  "type": "Feature",
  "properties": {
    "gn:admin1_code":"36",
    "gn:admin2_code":"705",
    "gn:asciiname":"Mowroz Khel",
    "gn:country_code":"AF",
    "gn:dem":2399,
    "gn:feature_class":"P",
    "gn:feature_code":"PPL",
    "gn:name":"Mowr\u014dz Kh\u0113l",
    "gn:population":0,
    "gn:timezone":"Asia/Kabul",
    "iso:country":"AF",
    "name:fas_x_preferred":[
        "\u0645\u0648\u0631\u0648\u0632 \u062e\u064a\u0644"
    ],
    "name:rus_x_preferred":[
        "Maurozkheyl\u2019"
    ],
    "name:und_x_variant":[
        "Mowroz Kheyl",
        "Maw\u1e5f\u014dzkh\u0113l",
        "Mawr\u016bz Kheyl",
        "Mowr\u014dz Kh\u0113l",
        "\u0645\u0648\u0631\u0648\u0632 \u062e\u06d0\u0644"
    ],
    "wof:name":"Mowroz Khel",
    "wof:placetype":"locality"
},
  "geometry": {"coordinates":[69.31933000000001,33.64883],"type":"Point"}
}