{
  "type": "Feature",
  "properties": {
    "gn:admin1_code":"39",
    "gn:admin2_code":"2601.0",
    "gn:asciiname":"Jalezai",
    "gn:country_code":"AF",
    "gn:dem":1283,
    "gn:feature_class":"P",
    "gn:feature_code":"PPL",
    "gn:name":"Jal\u0113za\u012b",
    "gn:population":0,
    "gn:timezone":"Asia/Kabul",
    "iso:country":"AF",
    "name:fas_x_preferred":[
        "\u062c\u0644\u06cc\u0632\u06cc"
    ],
    "name:und_x_variant":[
        "Dzhalezay",
        "Jal\u0113za\u012b",
        "\u062c\u0644\u06d0\u0632\u06cc",
        "Jal\u0113zay"
    ],
    "wof:name":"Jalezai",
    "wof:placetype":"locality"
},
  "geometry": {"coordinates":[65.77406999999999,32.55519],"type":"Point"}
}