{
  "type": "Feature",
  "properties": {
    "gn:admin1_code":"10",
    "gn:admin2_code":"2303.0",
    "gn:asciiname":"Zirkhar",
    "gn:country_code":"AF",
    "gn:dem":1051,
    "gn:feature_class":"P",
    "gn:feature_code":"PPL",
    "gn:name":"Z\u012brkh\u0101r",
    "gn:population":0,
    "gn:timezone":"Asia/Kabul",
    "iso:country":"AF",
    "name:und_x_variant":[
        "Z\u012brkh\u0101r",
        "\u0632\u06cc\u0631\u062e\u0627\u0631",
        "Z\u012b\u1e5fkh\u0101\u1e5f"
    ],
    "wof:name":"Zirkhar",
    "wof:placetype":"locality"
},
  "geometry": {"coordinates":[65.20155,32.39941],"type":"Point"}
}