{
  "type": "Feature",
  "properties": {
    "gn:admin1_code":"9",
    "gn:admin2_code":"2706.0",
    "gn:asciiname":"Borj",
    "gn:country_code":"AF",
    "gn:dem":2048,
    "gn:feature_class":"P",
    "gn:feature_code":"PPL",
    "gn:name":"Borj",
    "gn:population":0,
    "gn:timezone":"Asia/Kabul",
    "iso:country":"AF",
    "name:ceb_x_preferred":[
        "Borj"
    ],
    "name:fra_x_preferred":[
        "Borj"
    ],
    "name:rus_x_preferred":[
        "\u0411\u0443\u0440\u0434\u0436"
    ],
    "name:swe_x_preferred":[
        "Borj"
    ],
    "name:und_x_variant":[
        "Burdzh",
        "Bu\u1e5fj",
        "Borj"
    ],
    "wof:name":"Borj",
    "wof:placetype":"locality"
},
  "geometry": {"coordinates":[65.20999999999999,33.46],"type":"Point"}
}