{
  "type": "Feature",
  "properties": {
    "gn:admin1_code":"41",
    "gn:admin2_code":"3402.0",
    "gn:asciiname":"Tagabdar",
    "gn:country_code":"AF",
    "gn:dem":1369,
    "gn:feature_class":"P",
    "gn:feature_code":"PPL",
    "gn:name":"Tag\u0101bd\u0101r",
    "gn:population":0,
    "gn:timezone":"Asia/Kabul",
    "iso:country":"AF",
    "name:und_x_variant":[
        "Tag\u0101bd\u0101r",
        "\u062a\u06af\u0627\u0628\u062f\u0627\u0631",
        "Tag\u0101b\u1e0f\u0101\u1e5f"
    ],
    "wof:name":"Tagabdar",
    "wof:placetype":"locality"
},
  "geometry": {"coordinates":[66.02923,33.27596],"type":"Point"}
}