{
  "type": "Feature",
  "properties": {
    "gn:admin1_code":"27",
    "gn:admin2_code":"405.0",
    "gn:asciiname":"Baghalak",
    "gn:country_code":"AF",
    "gn:dem":2984,
    "gn:feature_class":"P",
    "gn:feature_code":"PPL",
    "gn:name":"Baghalak",
    "gn:population":0,
    "gn:timezone":"Asia/Kabul",
    "iso:country":"AF",
    "name:und_x_variant":[
        "Bagalak",
        "Baghalak",
        "\u0628\u063a\u0644\u06a9"
    ],
    "wof:name":"Baghalak",
    "wof:placetype":"locality"
},
  "geometry": {"coordinates":[68.35013000000001,34.34758],"type":"Point"}
}