{
  "type": "Feature",
  "properties": {
    "gn:admin1_code":"23",
    "gn:admin2_code":"2412",
    "gn:asciiname":"Utmanzai",
    "gn:country_code":"AF",
    "gn:dem":1251,
    "gn:feature_class":"P",
    "gn:feature_code":"PPL",
    "gn:name":"Utm\u0101nza\u012b",
    "gn:population":0,
    "gn:timezone":"Asia/Kabul",
    "iso:country":"AF",
    "name:ceb_x_preferred":[
        "Utmanzai"
    ],
    "name:und_x_variant":[
        "Utmanzay",
        "Utm\u0101nza\u012b",
        "\u0627\u062a\u0645\u0627\u0646\u0632\u06cc",
        "Utm\u0101nzay"
    ],
    "wof:name":"Utmanzai",
    "wof:placetype":"locality"
},
  "geometry": {"coordinates":[66.46429999999999,31.57254],"type":"Point"}
}