{
  "type": "Feature",
  "properties": {
    "gn:admin1_code":"37",
    "gn:admin2_code":"3211.0",
    "gn:asciiname":"'Omar Khan Kelay",
    "gn:country_code":"AF",
    "gn:dem":1244,
    "gn:feature_class":"P",
    "gn:feature_code":"PPL",
    "gn:name":"\u2018Omar Kh\u0101n K\u00ealay",
    "gn:population":0,
    "gn:timezone":"Asia/Kabul",
    "iso:country":"AF",
    "name:fas_x_preferred":[
        "\u0642\u0631\u064a\u06c0 \u0639\u0645\u0631 \u062e\u0627\u0646"
    ],
    "name:fas_x_variant":[
        "\u0639\u0645\u0631 \u062e\u0627\u0646 \u0643\u0644\u06cc"
    ],
    "name:und_x_variant":[
        "Umarkhankalay",
        "\u2018Omar Kh\u0101n K\u00ealay",
        "\u2018Omar Kh\u0101n Kalay"
    ],
    "wof:name":"'Omar Khan Kelay",
    "wof:placetype":"locality"
},
  "geometry": {"coordinates":[69.89596999999999,33.25206],"type":"Point"}
}