{
  "type": "Feature",
  "properties": {
    "gn:admin1_code":"36",
    "gn:admin2_code":"701",
    "gn:asciiname":"Shaykh Kala",
    "gn:country_code":"AF",
    "gn:dem":2447,
    "gn:feature_class":"P",
    "gn:feature_code":"PPL",
    "gn:name":"Shaykh Kal\u0101",
    "gn:population":0,
    "gn:timezone":"Asia/Kabul",
    "iso:country":"AF",
    "name:fas_x_preferred":[
        "\u0634\u064a\u062e \u0643\u0644\u0627"
    ],
    "name:und_x_variant":[
        "\u0160\u0113kh Kal\u0101",
        "Sheykhkala",
        "Sheykh Kal\u0101",
        "Shaykh Kal\u0101",
        "\u0634\u06cc\u062e \u06a9\u0644\u0627"
    ],
    "wof:name":"Shaykh Kala",
    "wof:placetype":"locality"
},
  "geometry": {"coordinates":[69.24829,33.53328],"type":"Point"}
}