{
  "type": "Feature",
  "properties": {
    "gn:admin1_code":"34",
    "gn:admin2_code":"1008",
    "gn:asciiname":"Zawardiwuz",
    "gn:country_code":"AF",
    "gn:dem":2152,
    "gn:feature_class":"P",
    "gn:feature_code":"PPL",
    "gn:name":"Zawa\u1e5f\u1e0fiwuz",
    "gn:population":0,
    "gn:timezone":"Asia/Kabul",
    "iso:country":"AF",
    "name:fas_x_preferred":[
        "\u0632\u0648\u0631\u062f\u0648\u0632"
    ],
    "name:und_x_variant":[
        "Zavardivuz",
        "\u0632\u0648\u0693\u0689\u0648\u0632",
        "Zawardiwuz",
        "Zawa\u1e5f\u1e0fiwuz"
    ],
    "wof:name":"Zawardiwuz",
    "wof:placetype":"locality"
},
  "geometry": {"coordinates":[71.08469000000002,35.01735],"type":"Point"}
}