{
  "type": "Feature",
  "properties": {
    "gn:admin1_code":"40",
    "gn:admin2_code":"305",
    "gn:asciiname":"Qal'ahchah",
    "gn:country_code":"AF",
    "gn:dem":1914,
    "gn:feature_class":"P",
    "gn:feature_code":"PPL",
    "gn:name":"Qal\u2018ahchah",
    "gn:population":0,
    "gn:timezone":"Asia/Kabul",
    "iso:country":"AF",
    "name:und_x_variant":[
        "Kalacha",
        "Qal\u2018acheh",
        "Qal\u2019a\u010da",
        "Qal\u2018ehcheh",
        "Qal\u2018ahchah",
        "\u0642\u0644\u0639\u0647 \u0686\u0647"
    ],
    "wof:name":"Qal'ahchah",
    "wof:placetype":"locality"
},
  "geometry": {"coordinates":[68.76833000000001,35.00518],"type":"Point"}
}